Workbook
Name Select_Bank: DashBoard!#REF!

Sheet Company Profile
A1: Company Profile
A2: Logo | B2: #VALUE! | C2: #VALUE! | D2: #VALUE! | E2: #VALUE! | F2: #VALUE! | G2: #VALUE! | H2: #VALUE!
A3: Company Name | B3: HDFC Bank | C3: ICICI Bank | D3: Axis Bank | E3: SBI | F3: Bajaj Finance | G3: Bajaj Housing Finance | H3: Muthoot Finance
A4: Company name as per Exchange | B4: #VALUE! | C4: #VALUE! | D4: #VALUE! | E4: #VALUE! | F4: #VALUE! | G4: #VALUE! | H4: #VALUE!
A5: Industry | B5: {=_FV(B4,"Industry")} -> Banking Services | C5: {=_FV(C4,"Industry")} -> Banking Services | D5: {=_FV(D4,"Industry")} -> Banking Services | E5: {=_FV(E4,"Industry")} -> Banking Services | F5: {=_FV(F4,"Industry")} -> Banking Services | G5: {=_FV(G4,"Industry")} -> Banking Services | H5: {=_FV(H4,"Industry")} -> Banking Services
A6: Current Market Price | B6: {=_FV(B4,"Price")} -> 982.3 | C6: {=_FV(C4,"Price")} -> 1343 | D6: {=_FV(D4,"Price")} -> 1222.8 | E6: {=_FV(E4,"Price")} -> 925 | F6: {=_FV(F4,"Price")} -> 1066.6 | G6: {=_FV(G4,"Price")} -> 109.5 | H6: {=_FV(H4,"Price")} -> 3230
A7: Beta | B7: {=_FV(B4,"Beta")} -> 0.8793 | C7: {=_FV(C4,"Beta")} -> 0.9991 | D7: {=_FV(D4,"Beta")} -> 1.0905 | E7: {=_FV(E4,"Beta")} -> 1.2655 | F7: {=_FV(F4,"Beta")} -> 1.1683 | G7: {=_FV(G4,"Beta")} -> 1.422 | H7: {=_FV(H4,"Beta")} -> 0.9721
A8: P/E (Current) | B8: {=_FV(B4,"P/E",TRUE)} -> 20.83 | C8: {=_FV(C4,"P/E",TRUE)} -> 17.58 | D8: {=_FV(D4,"P/E",TRUE)} -> 14.64 | E8: {=_FV(E4,"P/E",TRUE)} -> 10.38 | F8: {=_FV(F4,"P/E",TRUE)} -> 48.19 | G8: {=_FV(G4,"P/E",TRUE)} -> 38.63 | H8: {=_FV(H4,"P/E",TRUE)} -> 20.67
A9: INR/USD | B9: #VALUE! | C9: #VALUE! | D9: #VALUE! | E9: #VALUE! | F9: #VALUE! | G9: #VALUE! | H9: #VALUE!
A10: Conversion | B10: {=_FV(B9,"Price")} -> 0.01128 | C10: {=_FV(C9,"Price")} -> 0.01128 | D10: {=_FV(D9,"Price")} -> 0.01128 | E10: {=_FV(E9,"Price")} -> 0.01128 | F10: {=_FV(F9,"Price")} -> 0.01128 | G10: {=_FV(G9,"Price")} -> 0.01128 | H10: {=_FV(H9,"Price")} -> 0.01128
A11: Market Cap | B11: {=_FV(B4,"Market cap",TRUE)} -> 15104490000000 | C11: {=_FV(C4,"Market cap",TRUE)} -> 9592768000000 | D11: {=_FV(D4,"Market cap",TRUE)} -> 3794774000000 | E11: {=_FV(E4,"Market cap",TRUE)} -> 8517552000000 | F11: {=_FV(F4,"Market cap",TRUE)} -> 6629063000000 | G11: {=_FV(G4,"Market cap",TRUE)} -> 911982700000 | H11: {=_FV(H4,"Market cap",TRUE)} -> 1296743000000
B12: =B11/10000000 -> 1510449 | C12: =C11/10000000 -> 959276.8 | D12: =D11/10000000 -> 379477.4 | E12: =E11/10000000 -> 851755.2 | F12: =F11/10000000 -> 662906.3 | G12: =G11/10000000 -> 91198.27 | H12: =H11/10000000 -> 129674.3
A13: Shares Outstanding | B13: {=_FV(B4,"Shares outstanding",TRUE)} -> 15376650000 | C13: {=_FV(C4,"Shares outstanding",TRUE)} -> 7142791000 | D13: {=_FV(D4,"Shares outstanding",TRUE)} -> 3103348000 | E13: {=_FV(E4,"Shares outstanding",TRUE)} -> 9230617000 | F13: {=_FV(F4,"Shares outstanding",TRUE)} -> 6215135000 | G13: {=_FV(G4,"Shares outstanding",TRUE)} -> 8328608000 | H13: {=_FV(H4,"Shares outstanding",TRUE)} -> 401468500
A14: In Crores | B14: =B13/10000000 -> 1537.665 | C14: =C13/10000000 -> 714.2791 | D14: =D13/10000000 -> 310.3348 | E14: =E13/10000000 -> 923.0617 | F14: =F13/10000000 -> 621.5135 | G14: =G13/10000000 -> 832.8608 | H14: =H13/10000000 -> 40.14685
A15: Change (%) | B15: {=_FV(B4,"Change (%)",TRUE)} -> -0.002387 | C15: {=_FV(C4,"Change (%)",TRUE)} -> 0.017116 | D15: {=_FV(D4,"Change (%)",TRUE)} -> -0.00464 | E15: {=_FV(E4,"Change (%)",TRUE)} -> 0.042959 | F15: {=_FV(F4,"Change (%)",TRUE)} -> 0.023707 | G15: {=_FV(G4,"Change (%)",TRUE)} -> 0.001097 | H15: {=_FV(H4,"Change (%)",TRUE)} -> 0.014511
A16: Change (Rs) | B16: {=_FV(B4,"Change")} -> -2.35 | C16: {=_FV(C4,"Change")} -> 22.6 | D16: {=_FV(D4,"Change")} -> -5.7 | E16: {=_FV(E4,"Change")} -> 38.1 | F16: {=_FV(F4,"Change")} -> 24.7 | G16: {=_FV(G4,"Change")} -> 0.12 | H16: {=_FV(H4,"Change")} -> 46.2
A18: Mcap ($) | B18: =B11*B10 -> 170378647200 | C18: =C11*C10 -> 108206423040 | D18: =D11*D10 -> 42805050720 | E18: =E11*E10 -> 96077986560 | F18: =F11*F10 -> 74775830640 | G18: =G11*G10 -> 10287164856 | H18: =H11*H10 -> 14627261040
A19: In Millions | B19: =B18/1000000 -> 170378.65 | C19: =C18/1000000 -> 108206.42 | D19: =D18/1000000 -> 42805.051 | E19: =E18/1000000 -> 96077.987 | F19: =F18/1000000 -> 74775.831 | G19: =G18/1000000 -> 10287.165 | H19: =H18/1000000 -> 14627.261

Sheet Balance Sheet-Banks
A1: Balance Sheet
A2: Particulars | B2: #VALUE! | G2: #VALUE! | L2: #VALUE! | Q2: #VALUE!
B3: 2020 | C3: 2021 | D3: 2022 | E3: 2023 | F3: 2024 | G3: 2020 | H3: 2021 | I3: 2022 | J3: 2023 | K3: 2024 | L3: 2020 | M3: 2021 | N3: 2022 | O3: 2023 | P3: 2024 | Q3: 2020 | R3: 2021 | S3: 2022 | T3: 2023 | U3: 2024
A4: Shareholder's Equity
A5: Equity Share Capital | B5: 564.33 | C5: =612.75 -> 612.75 | D5: 613.95 | E5: 615.37 | F5: 617.31 | G5: 548.32 | H5: 551.27 | I5: 554.55 | J5: 557.97 | K5: 759.69 | L5: 1294.76 | M5: 1383.41 | N5: 1389.96 | O5: 1396.77 | P5: 1404.67 | Q5: 892.46 | R5: 892.46 | S5: 892.46 | T5: 892.46 | U5: 892.46
A6: Reserves and Surplus | B6: 85776.09 | C6: 102980.95 | D6: 117495.94 | E6: 128740.25 | F6: 155511.72 | G6: 175810.37 | H6: 209258.91 | I6: 246771.62 | J6: 288879.53 | K6: 452982.84 | L6: 121661.8 | M6: 146122.67 | N6: 168855.59 | O6: 212340.12 | P6: 253333.83 | Q6: 250167.66 | R6: 274669.09 | S6: 304695.58 | T6: 358038.85 | U6: 414046.71
A7: Minority Interest | B7: 113.55 | C7: 173.75 | D7: 261.35 | E7: 393.39 | F7: 499.44 | G7: 576.64 | H7: 632.76 | I7: 720.41 | J7: 860.26 | K7: 13383.4 | L7: 6794.76 | M7: 0 | N7: 0 | O7: 6686.75 | P7: 13888.41 | Q7: 7943.82 | R7: 9625.91 | S7: 11207.42 | T7: 12836.61 | U7: 15617.96
A8: Employees Stock options outstanding | B8: 0 | C8: 0 | D8: 150.77 | E8: 426.09 | F8: 894.49 | G8: 0 | H8: 0 | I8: 0 | J8: 0 | K8: 2652.72 | L8: 3.48 | M8: 3.1 | N8: 266.41 | O8: 760.88 | P8: 1405.31 | Q8: 0 | R8: 0 | S8: 0 | T8: 0 | U8: 0
A9: Total Equity | B9: =B5+B6+B7 -> 86453.97 | C9: =C5+C6+C7 -> 103767.45 | D9: =D5+D6+D7+D8 -> 118522.01 | E9: =E5+E6+E7+E8 -> 130175.1 | F9: =F5+F6+F7+F8 -> 157522.96 | G9: =G5+G6+G7+G8 -> 176935.33 | H9: =H5+H6+H7+H8 -> 210442.94 | I9: =I5+I6+I7+I8 -> 248046.58 | J9: =J5+J6+J7+J8 -> 290297.76 | K9: =K5+K6+K7+K8 -> 469778.65 | ... U9: =U5+U6+U7+U8 -> 430557.13
A10: Liabilities
A11: Deposits of branches in India | B11: 635203.77 | C11: 695234.99 | D11: 818308.24 | E11: 931486.13 | F11: 1052137.3 | G11: 1141364.1 | H11: 1327832.4 | I11: 1547880.7 | J11: 1865420.2 | K11: 2354694.8 | L11: 762401.07 | M11: 924888.06 | N11: 1054760.9 | O11: 1163807.9 | P11: 1395478.5 | Q11: 3122567.4 | R11: 3567926.8 | S11: 3917357.6 | T11: 4248617.5 | U11: 4718596.7
A12: Deposits of branches outside India | B12: 6953.43 | C12: 3067.64 | D12: 2605.92 | E12: 14338.59 | F12: 14965.08 | G12: 4843.05 | H12: 5888.44 | I12: 10122.3 | J12: 17243 | K12: 22192.53 | L12: 38383.38 | M12: 7634.09 | N12: 9810.71 | O12: 47024.22 | P12: 48101.42 | Q12: 151593.2 | R12: 147404.39 | S12: 170053.01 | T12: 219918.02 | U12: 247940.75
A13: Total Deposits | B13: =B11+B12 -> 642157.2 | C13: =C11+C12 -> 698302.63 | D13: =D11+D12 -> 820914.16 | E13: =E11+E12 -> 945824.72 | F13: =F11+F12 -> 1067102.4 | G13: =G11+G12 -> 1146207.1 | H13: =H11+H12 -> 1333720.9 | I13: =I11+I12 -> 1558003 | ... U13: =U11+U12 -> 4966537.5
A14: Borrowings in India
A15: RBI | B15: 11619 | C15: 18102 | D15: 18102 | E15: 7769 | F15: 0 | G15: 1726 | H15: 9020 | I15: 9020 | J15: 9020 | K15: 4556 | L15: 11832.85 | M15: 100 | N15: 0 | O15: 1889.92 | P15: 2618.69 | Q15: 34981.75 | R15: 24956 | S15: 24956 | T15: 26467.44 | U15: 98806.56
A16: Other Banks | B16: 2358.29 | C16: 3284.48 | D16: 8518.11 | E16: 13696.28 | F16: 15891.26 | G16: 13804.08 | H16: 11504.26 | I16: 9975.09 | J16: 17538.29 | K16: 138414.6 | L16: 7719.61 | M16: 69.99 | N16: 0 | O16: 7191.11 | P16: 10471.4 | Q16: 10041.13 | R16: 10678.34 | S16: 12601.43 | T16: 12929.14 | U16: 18549.19
A17: Other institutions & agencies | B17: 84526.52 | C17: 90548.85 | D17: 118770.87 | E17: 147235.52 | F17: 176230.7 | G17: 74982.43 | H17: 69351.56 | I17: 88651.96 | J17: 95782.45 | K17: 148410.04 | L17: 58397.15 | M17: 21606.9 | N17: 18716.87 | O17: 60894.23 | P17: 66184.05 | Q17: 11419.94 | R17: 159271.91 | S17: 152877.62 | T17: 98387.56 | U17: 74966.15
A18: Upper and lower capital debts | B18: 0 | C18: 0 | D18: 0 | E18: 0 | F18: 0 | G18: 21875.5 | H18: 21127 | I18: 17627 | J18: 28550 | K18: 30583.32 | L18: 22342.49 | M18: =10120+7125.8998 -> 17245.9 | N18: =6695+7155.6981 -> 13850.698 | O18: =5140+5320.66 -> 10460.66 | P18: 4859.41 | Q18: 56464.75 | R18: 67465.6 | S18: 73239.6 | T18: 90522.6 | U18: 96310.4
A19: Bonds and debentures | B19: 0 | C19: 0 | D19: 0 | E19: 0 | F19: 0 | G19: 39242.41 | H19: 38975.21 | I19: 43986.21 | J19: 46619.58 | K19: 299626.91 | L19: 28115.02 | M19: 19786.78 | N19: 39149.5 | O19: =50678.2+9802.28+3662.44 -> 64142.92 | P19: =52530.38+17296.08+3810.6 -> 73637.06 | Q19: 2927.08 | R19: 2382.91 | S19: 164.61 | T19: 23073 | U19: 42703
A20: Borrowings outside India | B20: 56676.34 | C20: 40313.39 | D20: 54387.18 | E20: 37512.77 | F20: 36077.59 | G20: 35203.89 | H20: 27718.7 | I20: 57706.24 | J20: 59038.34 | K20: 109024.59 | L20: 85444.62 | M20: 32890.66 | N20: 35514.28 | O20: 44482.93 | P20: 49657.37 | Q20: 217066 | R20: 169041.42 | S20: 185320.49 | T20: 269772.2 | U20: 308274.2
A21: Total Borrowings | B21: =B20+B15+B16+B17 -> 155180.15 | C21: =C20+C15+C16+C17 -> 152248.72 | D21: =D20+D15+D16+D17 -> 199778.16 | E21: =E20+E15+E16+E17 -> 206213.57 | F21: =F20+F15+F16+F17 -> 228199.55 | G21: =G20+G15+G16+G17+G18+G19 -> 186834.31 | H21: =H20+H15+H16+H17+H18+H19 -> 177696.73 | I21: =I20+I15+I16+I17+I18+I19 -> 226966.5 | J21: =J20+J15+J16+J17+J18+J19 -> 256548.66 | K21: =K20+K15+K16+K17+K18+K19 -> 730615.46 | L21: =L20+L15+L16+L17+L18+L19 -> 213851.74 | M21: =M20+M15+M16+M17+M18+M19 -> 91700.23 | N21: =N20+N15+N16+N17+N18+N19 -> 107231.35 | ... U21: =U20+U15+U16+U17+U18+U19 -> 639609.5
A22: Bills Payable | B22: 3689.78 | C22: 7032.65 | D22: 8499.36 | E22: 9543.81 | F22: 6713.89 | G22: 7583.72 | H22: 12424.19 | I22: 13093.74 | J22: 11790.76 | K22: 13932.56 | L22: 5714.22 | M22: 12387.06 | N22: 12949.57 | O22: 13603.7 | P22: 12819.31 | Q22: 26889.76 | R22: 17728.51 | S22: 33485.82 | T22: 27408.121 | U22: 15700.292
A23: Inter office adjustments (net) | B23: 0 | C23: 0 | D23: 0 | E23: 0 | F23: 0 | G23: 0 | H23: 0 | I23: 0 | J23: 0 | K23: 0 | L23: 743.95 | M23: 326.26 | N23: 441.81 | O23: 322.8 | P23: 42.09 | Q23: =85.41+10.35 -> 95.76 | R23: =49.69+1.23 -> 50.92 | S23: =37.86+2344.61 -> 2382.47 | T23: =235.5+4346.6 -> 4582.1 | U23: =491.12+1126.5956 -> 1617.7156
A24: Interest accrued | B24: 3412.28 | C24: 3898.24 | D24: 4662.33 | E24: 4097.95 | F24: 3658.22 | G24: 8582.55 | H24: 8123.58 | I24: 8241.11 | J24: 11393.84 | K24: 23853.43 | L24: 3071.04 | M24: 2138.91 | N24: 2463.28 | O24: 3339.01 | P24: 3898.55 | Q24: 15477.09 | R24: 15309.15 | S24: 17990.61 | T24: 27495.02 | U24: 32861.615
A25: Proposed Dividend | B25: 0 | C25: 0 | D25: 0 | E25: 0 | F25: 0 | G25: 0 | H25: 0 | I25: 0 | J25: 0 | K25: 0 | L25: 0 | M25: 0 | N25: 0 | O25: 0 | P25: 0 | Q25: 0 | R25: 0 | S25: 0 | T25: 0 | U25: 0
A26: Sundry Creditors | B26: 0 | C26: 0 | D26: 0 | E26: 0 | F26: 0 | G26: 0 | H26: 0 | I26: 0 | J26: 0 | K26: 0 | L26: 35049.34 | M26: 12184.83 | N26: 14473.12 | O26: 24283.06 | P26: 63912.06 | Q26: 0 | R26: 0 | S26: 0 | T26: 0 | U26: 0
A27: Other Liabilities | B27: 4635.31 | C27: 7113.04 | D27: 7346.31 | E27: 7988.94 | F27: 5113.43 | G27: 4651.76 | H27: 5525.85 | I27: 6791.27 | J27: 7252.06 | K27: 11005.15 | L27: 6623.58 | M27: 3634.28 | N27: 4094.28 | O27: =4994.67+18376.47 -> 23371.14 | P27: =6160.2+17651.91 -> 23812.11 | Q27: =6.6 -> 6.6 | R27: 3.7 | S27: 5.68 | T27: 3.8018 | U27: 23.2084
A28: Liabilities on policies in force | B28: 0 | C28: 0 | D28: 0 | E28: 0 | F28: 0 | G28: 0 | H28: 0 | I28: 0 | J28: 0 | K28: 0 | L28: 0 | M28: 0 | N28: 0 | O28: 238867.36 | P28: 281318.33 | Q28: 159661.49 | R28: 219027.87 | S28: 264548.27 | T28: 308442.72 | U28: 392280.43
A29: Provisions | B29: 32343.05 | C29: 28641.81 | D29: 35806.18 | E29: 40573.87 | F29: 49928.08 | G29: 50035.59 | H29: 51572.43 | I29: 61792.07 | J29: 70486.11 | K29: 126040.93 | L29: 36212.75 | M29: 28099.01 | N29: 34560.7 | O29: 33624.89 | P29: 57220.35 | Q29: =12444.21+116852.16 -> 129296.37 | R29: =16005.37+143178.05 -> 159183.42 | S29: =20592.09+168512.69 -> 189104.78 | T29: =26332.69+198698.4492 -> 225031.14 | U29: =24851.7215+229739.6833 -> 254591.4
A30: Total Liabilities | B30: =B22+B23+B24+B25+B27+B29+B13+B9+B21 -> 927871.74 | C30: =C22+C23+C24+C25+C27+C29+C13+C9+C21 -> 1001004.5 | D30: =D22+D23+D24+D25+D27+D29+D13+D9+D21 -> 1195528.5 | E30: =E22+E23+E24+E25+E27+E29+E13+E9+E21 -> 1344418 | F30: =F22+F23+F24+F25+F27+F29+F13+F9+F21 -> 1518238.5 | G30: =G22+G23+G24+G25+G27+G29+G13+G9+G21 -> 1580830.4 | H30: =H22+H23+H24+H25+H27+H29+H13+H9+H21 -> 1799506.6 | I30: =I22+I23+I24+I25+I27+I29+I13+I9+I21 -> 2122934.3 | ... K30: =K22+K23+K24+K25+K27+K29+K13+K9+K21 -> 3752113.5 | L30: =L22+L23+L24+L25+L27+L29+L13+L9+L21+L26 -> 1231805.9 | M30: =M22+M23+M24+M25+M27+M29+M13+M9+M21+M26 -> 1230501.9 | N30: =N22+N23+N24+N25+N27+N29+N13+N9+N21+N26 -> 1411297.7 | O30: =O22+O23+O24+O25+O27+O29+O13+O9+O21+O26+O28 -> 1958490.4 | P30: =P22+P23+P24+P25+P27+P29+P13+P9+P21+P26+P28 -> 2364062.9 | Q30: =Q22+Q23+Q24+Q25+Q27+Q29+Q13+Q9+Q21+Q26+Q28 -> 4197492.3 | R30: =R22+R23+R24+R25+R27+R29+R13+R9+R21+R26+R28 -> 4845618.4 | S30: =S22+S23+S24+S25+S27+S29+S13+S9+S21+S26+S28 -> 5360883.4 | T30: =T22+T23+T24+T25+T27+T29+T13+T9+T21 -> 5645975.5 | U30: =U22+U23+U24+U25+U27+U29+U13+U9+U21 -> 6341498.3
A31: ASSETS
A32: Cash and Cash Equivalents | B32: 7987.92 | C32: 12673.16 | D32: 9840.1 | E32: 9665.88 | F32: 9634.81 | G32: 9213.58 | H32: 10722.18 | I32: 11239.51 | J32: 13271.35 | K32: 13060.08 | L32: 9969.82 | M32: 7030.96 | N32: 7120.83 | O32: 8681.29 | P32: 8955.84 | Q32: 20334.94 | R32: 23691.32 | S32: 21967.22 | T32: 21628.41 | U32: 18589.64
A33: Balance in Current Accounts | B33: 20971.34 | C33: 23435.41 | D33: 36993.41 | E33: 43003.88 | F33: 48193.68 | G33: 37797.42 | H33: 59442.17 | I33: 81777.2 | J33: 94391.93 | K33: 131892.59 | L33: 25342.11 | M33: 39000.22 | N33: 52999.98 | O33: 48025.64 | P33: 62503.17 | Q33: 146633.51 | R33: 189807.29 | S33: 236119.2 | T33: 225692.63 | U33: 206747.68
A34: Balance in other accounts | B34: 56000 | C34: 15700 | D34: 47201 | E34: 13448 | F34: 28249 | G34: 25200 | H34: 27206 | I34: 37014 | J34: 9526 | K34: 33766 | L34: 0 | M34: 0 | N34: 0 | O34: 11942 | P34: 18484 | Q34: 0 | R34: 0 | S34: 0 | T34: 0 | U34: 19
A35: Total Balances | B35: =B33+B34+B32 -> 84959.26 | C35: =C33+C34+C32 -> 51808.57 | D35: =D33+D34+D32 -> 94034.51 | E35: =E33+E34+E32 -> 66117.76 | F35: =F33+F34+F32 -> 86077.49 | G35: =G33+G34+G32 -> 72211 | H35: =H33+H34+H32 -> 97370.35 | I35: =I33+I34+I32 -> 130030.71 | ... U35: =U33+U34+U32 -> 225356.32
A36: Balance with Banks in India
A37: In current Accounts | B37: 64.55 | C37: 286.85 | D37: 1240.04 | E37: 1517.1 | F37: 721.23 | G37: 415.54 | H37: 989.78 | I37: 627.61 | J37: 933.34 | K37: 1036.55 | L37: 364.19 | M37: 52.64 | N37: 32.41 | O37: 310.32 | P37: 355.37 | Q37: 638.49 | R37: 1067.9 | S37: 1064.57 | T37: 1262.19 | U37: 2510.86
A38: In other deposit accounts | B38: 2890.3 | C38: 1142.08 | D38: 886.98 | E38: 4061.4 | F38: 2931.78 | G38: 1247.68 | H38: 1617.09 | I38: 2730.83 | J38: 4100.75 | K38: 5247.91 | L38: 3335.0096 | M38: 1.52 | N38: 532.14 | O38: 10728.76 | P38: 12580.21 | Q38: 1429.61 | R38: 3160.05 | S38: 3727.11 | T38: 4395.41 | U38: 5211.2181
A39: Money at call and short notice
A40: With banks | B40: 0 | C40: 0 | D40: 0 | E40: 200 | F40: 100 | G40: 0 | H40: 0 | I40: 0 | J40: 0 | K40: 200 | L40: 59421.28 | M40: 35219 | N40: 49402 | O40: 821.7 | P40: 417.02 | Q40: 44747.71 | R40: 47369.93 | S40: 60938.22 | T40: 7770.44 | U40: 2550
A41: With other institutions | B41: 0 | C41: 0 | D41: 998.48 | E41: 11260.03 | F41: 6149.77 | G41: 0 | H41: 0 | I41: 491.33 | J41: 45527.54 | K41: 3819.32 | L41: 8192.52 | M41: 14.56 | N41: 0 | O41: 5965.23 | P41: 18019.18 | Q41: 8.69 | R41: 0 | S41: 0 | T41: 0 | U41: 26988.486
A42: Total Balances with Banks | B42: =B37+B38+B40+B41 -> 2954.85 | C42: =C37+C38+C40+C41 -> 1428.93 | D42: =D37+D38+D40+D41 -> 3125.5 | E42: =E37+E38+E40+E41 -> 17038.53 | F42: =F37+F38+F40+F41 -> 9902.78 | G42: =G37+G38+G40+G41 -> 1663.22 | H42: =H37+H38+H40+H41 -> 2606.87 | I42: =I37+I38+I40+I41 -> 3849.77 | ... U42: =U37+U38+U40+U41 -> 37260.564
A43: Balance with Banks outside India
A44: In current Accounts | B44: 4503 | C44: 3407.13 | D44: 2722.53 | E44: 4930.27 | F44: 4182.88 | G44: 4762.86 | H44: 11034.48 | I44: 7362.22 | J44: 13552.76 | K44: 10324.23 | L44: 13909.06 | M44: 26315.93 | N44: 30260.78 | O44: 31063.57 | P44: 21888.52 | Q44: 30104.93 | R44: 64287.31 | S44: 62547.03 | T44: 44397.865 | U44: 45740.696
A45: In other deposit accounts | B45: 72.51 | C45: 452.06 | D45: 5518.38 | E45: 10083.06 | F45: 9321.34 | G45: 1017.69 | H45: 390.96 | I45: 2020.43 | J45: 3890.26 | K45: 11933.99 | L45: 2542.06 | M45: 19899.03 | N45: 17963.08 | O45: 2678.2 | P45: 8015.16 | Q45: 1672.52 | R45: 8587.68 | S45: 3579.7 | T45: 1816.8 | U45: 2279.8271
A46: Money at call and short notice | B46: 5310.11 | C46: 6327.67 | D46: 6942.59 | E46: 10538.31 | F46: 7008.69 | G46: 8285.31 | H46: 9869.85 | I46: 12122.6 | J46: 11953.88 | K46: 17553.84 | L46: 4776.84 | M46: 5594.35 | N46: 9511.11 | O46: 16239.73 | P46: 11550.38 | Q46: 8744.83 | R46: 9735.53 | S46: 8962.04 | T46: 11348.143 | U46: 15934.872
A47: Total Balances with Banks | B47: =B44+B45+B46 -> 9885.62 | C47: =C44+C45+C46 -> 10186.86 | D47: =D44+D45+D46 -> 15183.5 | E47: =E44+E45+E46 -> 25551.64 | F47: =F44+F45+F46 -> 20512.91 | G47: =G44+G45+G46 -> 14065.86 | H47: =H44+H45+H46 -> 21295.29 | I47: =I44+I45+I46 -> 21505.25 | ... U47: =U44+U45+U46 -> 63955.395
A48: Total Balances | B48: =B42+B47 -> 12840.47 | C48: =C42+C47 -> 11615.79 | D48: =D42+D47 -> 18309 | E48: =E42+E47 -> 42590.17 | F48: =F42+F47 -> 30415.69 | G48: =G42+G47 -> 15729.08 | H48: =H42+H47 -> 23902.16 | I48: =I42+I47 -> 25355.02 | ... U48: =U42+U47 -> 101215.96
A49: Investments in India
A50: Government Securities | B50: 121918.07 | C50: 180702.84 | D50: 219508.11 | E50: 219706.84 | F50: 238963.72 | G50: 323039.9 | H50: 352015.86 | I50: 367723.1 | J50: 438861.82 | K50: 654866.87 | L50: 242682.44 | M50: 213620.79 | N50: 256387.73 | O50: 396062.32 | P50: 505592.83 | Q50: 872769.55 | R50: 1139960.4 | S50: 1261071.1 | T50: 1357221.4 | U50: 1515043.9
A51: Other approved securities | B51: 0 | C51: 0 | D51: 0 | E51: 0 | F51: 0 | G51: 0 | H51: 0 | I51: 0 | J51: 0 | K51: 0 | L51: 0 | M51: 0 | N51: 0 | O51: 0 | P51: 0 | Q51: 19106.17 | R51: 27743.27 | S51: 35365.93 | T51: 34762.19 | U51: 37831.75
A52: Shares | B52: 1155.28 | C52: 1394.97 | D52: 1194.08 | E52: 1193.12 | F52: 1317.01 | G52: 418.24 | H52: 449.43 | I52: 513.89 | J52: 522.53 | K52: 5116.1 | L52: 14098.03 | M52: 2822.01 | N52: 2413.59 | O52: 12722.51 | P52: 21975.13 | Q52: 42165.97 | R52: 68972.62 | S52: 90652.83 | T52: 105133.88 | U52: 149287.03
A53: Debentures and Bonds | B53: 20643.91 | C53: 34870.39 | D53: 44737.83 | E53: 54797.65 | F53: 74702.09 | G53: 25801.19 | H53: 58674.72 | I53: 59628.36 | J53: 54125.99 | K53: 20395.38 | L53: 39087.2 | M53: 27001.81 | N53: 22580.34 | O53: 52653.98 | P53: 96762.77 | Q53: 145276.27 | R53: 253967.01 | S53: 269609.83 | T53: 285134.41 | U53: 258588.02
A54: Investments in Joint ventures | B54: 0 | C54: 0 | D54: 797.89 | E54: 863.74 | F54: 932.45 | G54: 0 | H54: 0 | I54: 0 | J54: 0 | K54: =293986.13+200 -> 294186.13 | L54: 97084.97 | M54: 6073.88 | N54: 6626.41 | O54: =144058.05+6414.07 -> 150472.12 | P54: =164842.4+1510.23 -> 166352.63 | Q54: 12365.01 | R54: 13209.01 | S54: 14603.34 | T54: 16013.18 | U54: 17498.56
A55: Others | B55: 6449 | C55: 4387.57 | D55: 2435.57 | E55: 2827.25 | F55: 6769.42 | G55: 37852.82 | H55: 25314.96 | I55: 18776.09 | J55: 16570.37 | K55: 29044.34 | L55: 36386.5 | M55: 11182.25 | N55: 7192.25 | O55: 12845.76 | P55: 22267.21 | Q55: 85958.98 | R55: 40219.16 | S55: 47875.58 | T55: 49582.88 | U55: 60206.81
A56: Total Investments in India | B56: =SUM(B50:B55) -> 150166.26 | C56: =SUM(C50:C55) -> 221355.77 | D56: =SUM(D50:D55) -> 268673.48 | E56: =SUM(E50:E55) -> 279388.6 | F56: =SUM(F50:F55) -> 322684.69 | G56: =SUM(G50:G55) -> 387112.15 | H56: =SUM(H50:H55) -> 436454.97 | I56: =SUM(I50:I55) -> 446641.44 | ... U56: =SUM(U50:U55) -> 2038456
A57: Investments outside India
A58: Government Securities | B58: 4281.94 | C58: 3487.21 | D58: 5669.76 | E58: 8487.64 | F58: 9421.86 | G58: 840.93 | H58: 593.6 | I58: 227.58 | J58: 79.72 | K58: 248.04 | L58: 7681.58 | M58: 15162.23 | N58: 10734.08 | O58: 8997.24 | P58: 7948.9 | Q58: 20791.8 | R58: 21697.01 | S58: 24165.67 | T58: 34915.98 | U58: 39158.826
A59: Subsidiaries and/or Joint ventures abroad | B59: 0 | C59: 0 | D59: 0 | E59: 0 | F59: 0 | G59: 0 | H59: 0 | I59: 0 | J59: 0 | K59: 175.76 | L59: 0 | M59: 3682.68 | N59: 1969.89 | O59: 0 | P59: 0 | Q59: 147.64 | R59: 145.62 | S59: 158.8 | T59: 176.0239 | U59: 177.0173
A60: Equity shares and Bonds | B60: 833.41 | C60: 492.79 | D60: 264.89 | E60: 218.59 | F60: 247.19 | G60: =3.5+1338.33 -> 1341.83 | H60: =3.5+1771.01 -> 1774.51 | I60: =2.64+2392.2 -> 2394.84 | J60: =2.64+1418.64 -> 1421.28 | K60: =21.53+1627.48 -> 1649.01 | L60: 6451.8795 | M60: 1740.86 | N60: 2336.67 | O60: 5798 | P60: 6262.99 | Q60: 29702.84 | R60: 29186.12 | S60: 32986.75 | T60: 30167.881 | U60: 32756.325
A61: Total Investments outside India | B61: =B58+B59+B60 -> 5115.35 | C61: =C58+C59+C60 -> 3980 | D61: =D58+D59+D60 -> 5934.65 | E61: =E58+E59+E60 -> 8706.23 | F61: =F58+F59+F60 -> 9669.05 | G61: =G58+G59+G60 -> 2182.76 | H61: =H58+H59+H60 -> 2368.11 | I61: =I58+I59+I60 -> 2622.42 | ... U61: =U58+U59+U60 -> 72092.169
A62: Total Investments | B62: =B56+B61 -> 155281.61 | C62: =C56+C61 -> 225335.77 | D62: =D56+D61 -> 274608.13 | E62: =E56+E61 -> 288094.83 | F62: =F56+F61 -> 332353.74 | G62: =G56+G61 -> 389294.91 | H62: =H56+H61 -> 438823.08 | I62: =I56+I61 -> 449263.86 | ... U62: =U56+U61 -> 2110548.2
A63: Advances in India
A64: Priority sector | B64: 143859.33 | C64: 184171.37 | D64: 254162.74 | E64: 306850.92 | F64: 369070.11 | G64: 258281.76 | H64: 258611.15 | I64: 390181.51 | J64: 534388.32 | K64: 780715.25 | L64: 190900.99 | M64: 203179.74 | N64: 249168.08 | O64: 280781.25 | P64: 373906.05 | Q64: 526675.87 | R64: 564570.86 | S64: 658546.88 | T64: 697644.44 | U64: 804184.21
A65: Public sector | B65: 13427.08 | C65: 32680.92 | D65: 22195.7 | E65: 17719.94 | F65: 17132.94 | G65: 62335.37 | H65: 119908.27 | I65: 135693.81 | J65: 135907.74 | K65: 140554.7 | L65: 15954.14 | M65: 45189.75 | N65: 48378.24 | O65: 51615.24 | P65: 51080.11 | Q65: 287505.82 | R65: 257246.24 | S65: 167199.41 | T65: 258922.88 | U65: 252633.74
A66: Banks | B66: 2180.9 | C66: 3131 | D66: 2446.93 | E66: 1112.52 | F66: 15646.12 | G66: 6855.04 | H66: 8538.38 | I66: 6886.3 | J66: 6403.88 | K66: 2567.12 | L66: 446.83 | M66: 26.47 | N66: 43.23 | O66: 769.81 | P66: 1635.98 | Q66: 975.1 | R66: 4833.33 | S66: 1536.43 | T66: 512.5014 | U66: 592.1356
A67: Others | B67: 374713.7 | C67: 369341.94 | D67: 397983.15 | E67: 509024.03 | F67: 568840.19 | G67: 687787.31 | H67: 766615.85 | I67: 845365.56 | J67: 943500.41 | K67: 1603405.2 | L67: 398377.26 | M67: 447742.76 | N67: 520146.07 | O67: 676949.95 | P67: 759851.86 | Q67: 1171958.8 | R67: 1285608.5 | S67: 1519580.5 | T67: 1777189.2 | U67: 2143154.3
A68: Total advances in India | B68: =B64+B66+B65+B67 -> 534181.01 | C68: =C64+C66+C65+C67 -> 589325.23 | D68: =D64+D66+D65+D67 -> 676788.52 | E68: =E64+E66+E65+E67 -> 834707.41 | F68: =F64+F66+F65+F67 -> 970689.36 | G68: =G64+G66+G65+G67 -> 1015259.5 | H68: =H64+H66+H65+H67 -> 1153673.6 | I68: =I64+I66+I65+I67 -> 1378127.2 | ... U68: =U64+U66+U65+U67 -> 3200564.4
A69: Advances outside India
A70: Due from banks | B70: 2582.83 | C70: 1748.29 | D70: 560.86 | E70: 205.42 | F70: 241.87 | G70: 3325.09 | H70: 5527.65 | I70: 4909.88 | J70: 2296.29 | K70: 2756.16 | L70: 756.7 | M70: 277.37 | N70: 0 | O70: 807.64 | P70: 1442.2 | Q70: 80561.91 | R70: 80143.34 | S70: 119514.35 | T70: 152095.52 | U70: 181073.38
A71: Bills purchased and discounted | B71: 2828.86 | C71: 9907.95 | D71: 23888.56 | E71: 6954.73 | F71: 6295.36 | G71: 5.1 | H71: 6.349 | I71: 254.83 | J71: 604.09 | K71: 714.86 | L71: 16922.91 | M71: 7835.19 | N71: 17317.83 | O71: 15255.39 | P71: 11632.52 | Q71: 31106.22 | R71: 35004.71 | S71: 35345.8 | T71: 42531.129 | U71: 42424.381
A72: Syndicated loans | B72: 3167.19 | C72: 588.13 | D72: 236.56 | E72: 150.63 | F72: 0 | G72: 1253.11 | H72: 834.79 | I72: 541.89 | J72: 1988.24 | K72: 1180.49 | L72: 57219.7 | M72: 16826.64 | N72: 8579.3 | O72: 24526.78 | P72: 25793.9 | Q72: 186697.53 | R72: 184413.38 | S72: 196311.75 | T72: 223887.33 | U72: 230369.09
A73: Others | B73: 40198.91 | C73: 24180.3 | D73: 23651 | E73: 26369.35 | F73: 22106.89 | G73: 23828.05 | H73: 25241.05 | I73: 37108.5 | J73: 36860.32 | K73: 33997.62 | L73: 25667.558 | M73: 12651.12 | N73: 15387.65 | O73: 33160.2 | P73: 35433.55 | Q73: 88829.9 | R73: 88778.64 | S73: 96040.85 | T73: 115119.15 | U73: 129841.45
A74: Total advances outside India | B74: =B70+B71+B72+B73 -> 48777.79 | C74: =C70+C71+C72+C73 -> 36424.67 | D74: =D70+D71+D72+D73 -> 48336.98 | E74: =E70+E71+E72+E73 -> 33680.13 | F74: =F70+F71+F72+F73 -> 28644.12 | G74: =G70+G71+G72+G73 -> 28411.35 | H74: =H70+H71+H72+H73 -> 31609.839 | I74: =I70+I71+I72+I73 -> 42815.1 | ... U74: =U70+U71+U72+U73 -> 583708.3
A75: Total advances | B75: =B68+B74 -> 582958.8 | C75: =C68+C74 -> 625749.9 | D75: =D68+D74 -> 725125.5 | E75: =E68+E74 -> 868387.54 | F75: =F68+F74 -> 999333.48 | G75: =G68+G74 -> 1043670.8 | H75: =H68+H74 -> 1185283.5 | I75: =I68+I74 -> 1420942.3 | ... U75: =U68+U74 -> 3784272.7
A76: Fixed Assets | B76: 4394.33 | C76: 4329.69 | D76: 4679.12 | E76: 4852.58 | F76: 5837.56 | G76: 4626.85 | H76: 5099.56 | I76: 6283.28 | J76: 8282.56 | K76: 12603.76 | L76: 10408.65 | M76: 8877.58 | N76: 9373.81 | O76: 10969 | P76: 13240.27 | Q76: 40078.16 | R76: 40166.78 | S76: 39510.03 | T76: 44407.38 | U76: 44708.177
A77: Other Assets | B77: 87437.22 | C77: 81975.58 | D77: 78483.01 | E77: 74085.84 | F77: 63931.33 | G77: 55287.64 | H77: 49027.92 | I77: 90910.36 | J77: 151322.28 | K77: 217182.95 | L77: 89311.91 | M77: 73411.21 | N77: 64840.12 | O77: 87545.38 | P77: 97640.97 | Q77: 300503.45 | R77: 362045.46 | S77: 351902.47 | T77: 410689.04 | U77: 467677.42
A78: Goodwill on consolidation | B78: 0 | C78: 289.24 | D78: 289.24 | E78: 289.24 | F78: 289.24 | G78: 0 | H78: 0 | I78: 0 | J78: 0 | K78: 0 | L78: 0 | M78: 0 | N78: 0 | O78: 101.33 | P78: 2474.16 | Q78: 0 | R78: 0 | S78: 0 | T78: 0 | U78: 0
A79: Total Assets | B79: =B35+B62+B75+B76+B77+B48+B78 -> 927871.69 | C79: =C35+C62+C75+C76+C77+C48+C78 -> 1001104.5 | D79: =D35+D62+D75+D76+D77+D48+D78 -> 1195528.5 | E79: =E35+E62+E75+E76+E77+E48+E78 -> 1344418 | F79: =F35+F62+F75+F76+F77+F48+F78 -> 1518238.5 | G79: =G35+G62+G75+G76+G77+G48+G78 -> 1580820.3 | H79: =H35+H62+H75+H76+H77+H48+H78 -> 1799506.6 | I79: =I35+I62+I75+I76+I77+I48+I78 -> 2122785.5 | ... U79: =U35+U62+U75+U76+U77+U48+U78 -> 6733778.7
A81: Particulars | B81: 2020 | C81: 2021 | D81: 2022 | E81: 2023 | F81: 2024 | G81: 2020 | H81: 2021 | I81: 2022 | J81: 2023 | K81: 2024 | L81: 2020 | M81: 2021 | N81: 2022 | O81: 2023 | P81: 2024 | Q81: 2020 | R81: 2021 | S81: 2022 | T81: 2023 | U81: 2024
A82: Demand Deposits | B82: =3888.7703+85861.9416 -> 89750.712 | C82: =5145.45+107692.01 -> 112837.46 | D82: =4792.62+121903.9 -> 126696.52 | E82: =4760.03+143543.86 -> 148303.89 | F82: =4675.28+151659.07 -> 156334.35 | G82: 173159.01 | H82: 211076.24 | I82: 238205.22 | J82: 272917.63 | K82: 307776.67 | L82: =6480.2599+98508.2977 -> 104988.56 | M82: =11479.2811+124690.846 -> 136170.13 | N82: =7970.041+150509.6359 -> 158479.68 | O82: =4997.8962+160834.9299 -> 165832.83 | P82: =4761.3641+194057.139 -> 198818.5 | Q82: =4750.6724+224677.6339 -> 229428.31 | R82: =5469.1961+283808.8605 -> 289278.06 | S82: =6328.021+273403.3796 -> 279731.4 | T82: =3160.4031+302572.9464 -> 305733.35 | U82: =5745.873+303531.705 -> 309277.58
A83: Savings Account deposits | B83: 173592.6 | C83: 204472.56 | D83: 242449.27 | E83: 297415.99 | F83: 302132.58 | G83: 310376.94 | H83: 403492.47 | I83: 511737.21 | J83: 562491.14 | K83: 598743.72 | L83: 254064.97 | M83: 295453.3 | N83: 359956.9 | O83: 384829.86 | P83: 406088.72 | Q83: 1216783 | R83: 1397501.4 | S83: 1539980.6 | T83: 1600786.1 | U83: 1673652.2
A84: Risk weighted assets | B84: 610527 | C84: 635863 | D84: 721356 | E84: 851335 | F84: 1039313 | G84: 994715.74 | H84: 1131143.9 | I84: 1353510.9 | J84: 1586635 | K84: 2468028.1 | M84: 883591 | N84: 785400 | Q84: 2188803.9 | R84: 2353096 | S84: 2608923 | T84: 2941677.9 | U84: 3423514.9
A85: Tier 1 Capital | B85: 88449 | C85: 104748 | D85: 117875 | E85: 124048 | F85: 147633 | G85: 171414.44 | H85: 198587.36 | I85: 241806.75 | J85: 271823.91 | K85: 414281.32 | M85: =0.1806*M84 -> 159576.53 | N85: =0.1835*N84 -> 144120.9 | R85: 0.11 | S85: 0.1144 | T85: 0.1142 | U85: 0.1193
A86: Tier 2 Capital | B86: 18556 | C86: 16829 | D86: 15858 | E86: 26116 | F86: 25231 | G86: 12843.41 | H86: 13958.94 | I86: 13927.75 | J86: 33740.94 | K86: 49721.5 | M86: =0.0106*M84 -> 9366.0646 | N86: =0.0081*N84 -> 6361.74 | R86: 0.0206 | S86: 0.023 | T86: 0.0241 | U86: 0.0235
A87: Common Equity tier 1 | B87: =B84*B88 -> 88465.362 | C87: =C84*C88 -> 97922.902 | D87: =D84*D88 -> 109934.65 | E87: =E84*E88 -> 119357.17 | F87: =F84*F88 -> 142801.61 | G87: =G84*G88 -> 163431.8 | H87: =H84*H88 -> 190597.74 | I87: =I84*I88 -> 225630.26 | ... K87: =K84*K88 -> 402288.57
A88: CET Ratio | B88: 0.1449 | C88: 0.154 | D88: 0.1524 | E88: 0.1402 | F88: 0.1374 | G88: 0.1643 | H88: 0.1685 | I88: 0.1667 | J88: 0.164 | K88: 0.163 | M88: 0.168 | N88: 0.176 | Q88: 0.1002 | R88: 0.1038 | S88: 0.1144 | T88: 0.1142 | U88: 0.1036
Q89: =Q84*Q88 -> 219318.15 | R89: =R84*R88 -> 244251.37 | S89: =S84*S88 -> 298460.79 | T89: =T84*T88 -> 335939.62 | U89: =U84*U88 -> 354676.14

Sheet Balance Sheet-NBFCs
A2: Particulars | B2: #VALUE! | G2: #VALUE! | L2: #VALUE!
B3: 2020 | C3: 2021 | D3: 2022 | E3: 2023 | F3: 2024 | G3: 2020 | H3: 2021 | I3: 2022 | J3: 2023 | K3: 2024 | L3: 2020 | M3: 2021 | N3: 2022 | O3: 2023 | P3: 2024
A4: Equity
A5: Equity share capital | B5: 4883.33 | C5: 4883.33 | D5: 4883.33 | E5: 6712.16 | F5: 6712.16 | G5: 119.99 | H5: 120.32 | I5: 120.66 | J5: 120.89 | K5: 123.6 | L5: 4010.37 | M5: 4011.96 | N5: 4013.45 | O5: 4014.48 | P5: 4014.62
A6: Other Equity | B6: 701.8 | C6: 1148.89 | D6: 1858.03 | E6: 3791.03 | F6: 5521.34 | G6: 32207.64 | H6: 36798.09 | I6: 43592.03 | J6: 54251.09 | K6: 76571.75 | L6: 114281.73 | M6: 151738.29 | N6: 183843.79 | O6: 212643.04 | P6: 247057.45
A7: Non-controlling interest | L7: 1721.42 | M7: 1845.75 | N7: 3521.72 | O7: 4870.52 | P7: 6468.33
A9: Total Equity | B9: =B5+B6+B7+B8 -> 5585.13 | C9: =C5+C6+C7+C8 -> 6032.22 | D9: =D5+D6+D7+D8 -> 6741.36 | E9: =E5+E6+E7+E8 -> 10503.19 | F9: =F5+F6+F7+F8 -> 12233.5 | G9: =G5+G6+G7+G8 -> 32327.63 | H9: =H5+H6+H7+H8 -> 36918.41 | I9: =I5+I6+I7+I8 -> 43712.69 | ... P9: =P5+P6+P7+P8 -> 257540.4
A10: Liabilities
A11: Payables | B11: =0.24+30.35+17.83 -> 48.42 | C11: =20.9+21.28 -> 42.18 | D11: =0.18+36.23+38.17 -> 74.58 | E11: =73.04+45.93 -> 118.97 | F11: =0.83+57.61+82.75 -> 141.19 | G11: =0.54+761.43+197.84 -> 959.81 | H11: =213.82+884.01+0.27 -> 1098.1 | I11: =0.24+1169.08+341.78 -> 1511.1 | J11: =1.86+1450.26+0.65+638.67 -> 2091.44 | K11: =0.73+2063.31+764.58 -> 2828.62 | L11: 2220.28 | M11: =2111.53+2.31 -> 2113.84 | N11: =1570.2+3.46 -> 1573.66 | O11: =7.2+871.23+1119.71 -> 1998.14 | P11: =7.68+1381.23+1280.77 -> 2669.68
A12: Debt securities | B12: 7823.59 | C12: 11332.08 | D12: 16489.15 | E12: 19914.92 | F12: 26645.33 | G12: 49537.36 | H12: 54502.14 | I12: 76223.07 | J12: 86845.24 | K12: 117999.54 | L12: 102826.55 | M12: 146669.9 | N12: 131740.35 | O12: 146045.79 | P12: 174762.2
A13: Borrowings | B13: 17776.85 | C13: 20268.52 | D13: 24493.17 | E13: 33654.7 | F13: 42299.73 | G13: 54700.17 | H13: 47429.36 | I13: 54363.56 | J13: 81549.4 | K13: 111617.47 | L13: 300115.44 | M13: 351009.78 | N13: 408553.24 | O13: 405974.58 | P13: 500519.53
A14: Deposits | B14: 0 | C14: 0 | D14: 510 | E14: 175.77 | F14: 184.26 | G14: 21427.1 | H14: 25803.43 | I14: 30799.52 | J14: 44665.56 | K14: 60150.92 | L14: 2560.06 | M14: 2579.53 | N14: 2235.26 | O14: 3314.76 | P14: 4018.26
A15: Other financial liabilities | B15: 73.59 | C15: 151.14 | D15: 174.42 | E15: 211.62 | F15: 234.14 | G15: =4141.75+745.05 -> 4886.8 | H15: =945.12+3898.61+137.87 -> 4981.6 | I15: =1110.43+3845.77+140.02 -> 5096.22 | J15: =3630.29+1309.29+4.01 -> 4943.59 | K15: =3577.9+1844.39+2.12 -> 5424.41 | L15: =11884.77+167.72+3849.85 -> 15902.34 | M15: =13598.4+3706.89+177.57+3305.19 -> 20788.05 | N15: =2997.33+159.8+13323.48+4797.97 -> 21278.58 | O15: =2546.55+155.57+12638.76+1921.73 -> 17262.61 | P15: =138.86+3309.73+125.91+16014.9 -> 19589.4
A16: Current tax liabilities (net) | B16: 7.07 | C16: 7.39 | D16: 20.06 | E16: 16.17 | F16: 25.93 | G16: 59.17 | H16: 180.17 | I16: 100.06 | J16: 139.21 | K16: 108.64 | L16: 808.33 | M16: 1302.75 | N16: 1418.15 | O16: 811.92 | P16: 551.68
A17: Provisions | B17: 2.28 | C17: 2.29 | D17: 4.05 | E17: 15.63 | F17: 35.64 | G17: 81.24 | H17: 137.69 | I17: 166.9 | J17: 268.08 | K17: 421.89 | L17: 3712.33 | M17: 3695.29 | N17: 3679.83 | O17: 3618.92 | P17: 3733.27
A18: Deferred tax liabilities (net) | B18: 11.43 | C18: 0 | D18: 0 | E18: 28.27 | F18: 0 | G18: 0 | H18: 0 | I18: 0 | J18: 0 | K18: 0 | L18: 151.03 | M18: 142.21 | N18: 166.36 | O18: 152.86 | P18: 167.62
A19: Other non financial liabilities | B19: 44.06 | C19: 0 | D19: 0 | E19: 14.9 | F19: 27.37 | G19: 412.09 | H19: 419.5 | I19: 532.24 | J19: 351.81 | K19: 494.78 | L19: 507.04 | M19: 517 | N19: 1140.36 | O19: 781.58 | P19: 1142.16
A20: Total Liabilities | B20: =SUM(B11:B19) -> 25787.29 | C20: =SUM(C11:C19) -> 31803.6 | D20: =SUM(D11:D19) -> 41765.43 | E20: =SUM(E11:E19) -> 54150.95 | F20: =SUM(F11:F19) -> 69593.59 | G20: =SUM(G11:G19) -> 132063.74 | H20: =SUM(H11:H19) -> 134551.99 | I20: =SUM(I11:I19) -> 168792.67 | ... P20: =SUM(P11:P19) -> 707153.8
A21: Total Equity and liabilities | B21: =B9+B20 -> 31372.42 | C21: =C9+C20 -> 37835.82 | D21: =D9+D20 -> 48506.79 | E21: =E9+E20 -> 64654.14 | F21: =F9+F20 -> 81827.09 | G21: =G9+G20 -> 164391.37 | H21: =H9+H20 -> 171470.4 | I21: =I9+I20 -> 212505.36 | ... P21: =P9+P20 -> 964694.2
A22: ASSETS
A23: Cash and Cash equivalents | B23: 658.72 | C23: 461.78 | D23: 407.03 | E23: 93.88 | F23: 63.86 | G23: 1344.52 | H23: 1849.33 | I23: 3407.17 | J23: 1550.75 | K23: 4034.51 | L23: 58347.65 | M23: 77775.2 | N23: 100358.14 | O23: 77701.83 | P23: 60373.45
A24: Bank Balances other than cash | B24: 0 | C24: 255 | D24: 0.14 | E24: 14.99 | F24: 0.15 | G24: 38.2 | H24: 314.99 | I24: 273.13 | J24: 2753.77 | K24: 6589.5 | L24: 2958.88 | M24: 2434.87 | N24: 2791.47 | O24: 2654.76 | P24: 2346.57
A25: Derivative Financial Instruments | B25: 0 | C25: 0 | D25: 0 | E25: 1.37 | F25: 11.66 | G25: 171.76 | H25: 0 | I25: 121.9 | J25: 148.88 | K25: 27.84 | L25: 3448.94 | M25: 153.64 | N25: 605.01 | O25: 0 | P25: 0
A26: Receivables | B26: 118.4 | C26: 310.66 | D26: 237.33 | E26: =1.59+0.36 -> 1.95 | F26: 13.36 | G26: 952.49 | H26: 1096.86 | I26: 1265.89 | J26: 1299.72 | K26: 1733.49 | L26: 89.82 | M26: 98.02 | N26: 70.09 | O26: 98.95 | P26: 178.36
A27: Loans | B27: 27975.41 | C27: 33418.9 | D27: 46482.07 | E27: 62113.89 | F27: 79300.75 | G27: 141376.05 | H27: 146686.87 | I27: 191423.25 | J27: 242268.93 | K27: 326293.32 | L27: 470677.41 | M27: 588085.17 | N27: 645276.41 | O27: 705543.84 | P27: 881871.71
A28: Investments | B28: 2508.02 | C28: 3266.06 | D28: 1248.27 | E28: 2000.91 | F28: 1938.57 | G28: 17543.9 | H28: 18396.91 | I28: 12245.54 | J28: 22751.84 | K28: 30880.65 | L28: =6302.16+156.48 -> 6458.64 | M28: =8085.05+139.45 -> 8224.5 | N28: =5233.06+93.41 -> 5326.47 | O28: 5457.12 | P28: 7124.72
A29: Other Financial assets | B29: 8.44 | C29: 33.99 | D29: 18.48 | E29: 301.94 | F29: 284.07 | G29: 470.39 | H29: 536.98 | I29: 721.49 | J29: 817.28 | K29: 1431.88 | L29: 2448.75 | M29: 4383.41 | N29: 2807.28 | O29: 3453 | P29: 4136.12
A30: Current tax assets (net) | B30: 11.1 | C30: 4.46 | D30: 9.08 | E30: 3.97 | F30: 31.09 | G30: 216.72 | H30: 159.77 | I30: 168.3 | J30: 181.43 | K30: 290.92 | L30: 94.25 | M30: 93.96 | N30: 110.21 | O30: 474.57 | P30: 724.86
A31: Deferred tax assets (net) | B31: 0 | C31: 15.26 | D31: 15.58 | E31: 0 | F31: 50.94 | G31: 850.13 | H31: 945.9 | I31: 951.11 | J31: 937.09 | K31: 1017.43 | L31: 171.04 | M31: 592.75 | N31: 1089.74 | O31: 640.98 | P31: 975.78
A32: Property, Plant and Equipments | B32: 77.8 | C32: 63.32 | D32: 78.09 | E32: 84.92 | F32: 87.5 | G32: 1097.26 | H32: 1041.69 | I32: 1282.58 | J32: 1676.57 | K32: 2358.32 | L32: 2426.87 | M32: 2575.11 | N32: 2816.92 | O32: 3272.37 | P32: 4255.24
A33: Intangible assets | B33: 7.98 | C33: =14.57 -> 14.57 | D33: =1.46+19.11 -> 20.57 | E33: =0.31+28.07 -> 28.38 | F33: =0.87+35.36 -> 36.23 | G33: 220.46 | H33: =43.99+270.74 -> 314.73 | I33: =20.87+430.45 -> 451.32 | J33: =65.24+627.78 -> 693.02 | K33: =18.11+888.31 -> 906.42 | L33: =167.56+85.37 -> 252.93 | M33: =170.01+86.31+0.55 -> 256.87 | N33: =147.8+58.74+0.49 -> 207.03 | O33: =82.02+142.23+58.85+0.44 -> 283.54 | P33: =91.07+111.11+58.35+3.65 -> 264.18
A34: Capital work in progress | B34: 0 | C34: 0 | D34: 0 | E34: 0 | F34: 0 | G34: 0 | H34: 7.07 | I34: 13.27 | J34: 14.6 | K34: 25.35 | L34: 287.36 | M34: 384.77 | N34: 523.44 | O34: 674.27 | P34: 883.16
A35: Goodwill | B35: 0 | C35: 0 | D35: 0 | E35: 0 | F35: 0 | G35: 0 | H35: 3.27 | I35: 3.27 | J35: 3.27 | K35: 3.27 | L35: 299.96 | M35: 299.96 | N35: 299.96 | O35: 299.96 | P35: 299.96
A36: Other non financial assets | B36: 6.55 | C36: 13.4 | D36: 10.44 | E36: 7.94 | F36: 8.91 | G36: =3.27+106.22 -> 109.49 | H36: 116.03 | I36: 177.14 | J36: 129.16 | K36: 148.72 | L36: 854.42 | M36: 1056.12 | N36: 882.57 | O36: 934.01 | P36: 1260.09
A37: Total Assets | B37: =SUM(B23:B36) -> 31372.42 | C37: =SUM(C23:C36) -> 37857.4 | D37: =SUM(D23:D36) -> 48527.08 | E37: =SUM(E23:E36) -> 64654.14 | F37: =SUM(F23:F36) -> 81827.09 | G37: =SUM(G23:G36) -> 164391.37 | H37: =SUM(H23:H36) -> 171470.4 | I37: =SUM(I23:I36) -> 212505.36 | ... P37: =SUM(P23:P36) -> 964694.2
A39: Particulars | B39: 2020 | C39: 2021 | D39: 2022 | E39: 2023 | F39: 2024 | G39: 2020 | H39: 2021 | I39: 2022 | J39: 2023 | K39: 2024 | L39: 2020 | M39: 2021 | N39: 2022 | O39: 2023 | P39: 2024
A40: Demand Deposits | B40: 0
A41: Savings Account deposits | B41: 0
A42: Risk weighted assets | B42: 22450.99 | C42: 28119.67 | D42: 34126.15 | E42: 45901.75 | F42: 57351.83 | G42: 134916.74 | H42: 130767.5 | I42: 155832.47 | J42: 198890.13 | K42: 315149.85 | L42: 465414.95 | M42: 577179.12 | N42: 628762.36 | O42: 673758.71 | P42: 815900.47
A43: Tier 1 Capital | B43: 5495.58 | C43: 5820.36 | D43: 6469.01 | E43: 10184.74 | F43: 11857.24 | G43: 28697.72 | H43: 32838.5 | I43: 38570.88 | J43: 46152.01 | K43: 67796.11
A44: Tier 2 Capital | B44: 151.25 | C44: 178.68 | D44: 259.95 | E44: 359.66 | F44: 348.45 | G44: 5043.43 | H44: 4179.83 | I44: 3850.54 | J44: 3513.81 | K44: 3166.61
A45: Common Equity tier 1 | L45: 113095.18 | M45: 151879.74 | N45: 182960.89 | O45: 208943.81 | P45: 241570.84
A46: CET Ratio | F46: 0.09 | G46: 0.196 | H46: 0.236 | I46: 0.238 | J46: 0.232 | K46: 0.227 | L46: =L45/L42 -> 0.2429986 | M46: =M45/M42 -> 0.26314143 | N46: =N45/N42 -> 0.29098575 | O46: =O45/O42 -> 0.31011667 | P46: =P45/P42 -> 0.29607881

Sheet Income Statement-Banks
A1: INCOME STATEMENT
A2: Particulars | B2: #VALUE! | G2: #VALUE! | L2: #VALUE! | Q2: #VALUE!
B3: 2020 | C3: 2021 | D3: 2022 | E3: 2023 | F3: 2024 | G3: 2020 | H3: 2021 | I3: 2022 | J3: 2023 | K3: 2024 | L3: 2020 | M3: 2021 | N3: 2022 | O3: 2023 | P3: 2024 | Q3: 2020 | R3: 2021 | S3: 2022 | T3: 2023 | U3: 2024
A4: INCOME
A5: Interest earned | B5: 63715.68 | C5: 64397.36 | D5: 68846.06 | E5: 87448.37 | F5: 112759.05 | G5: 122189.29 | H5: 128552.39 | I5: 135936.41 | J5: 170754.05 | K5: 283649.02 | L5: 84835.773 | M5: 79118.271 | N5: 86374.545 | O5: 121066.81 | P5: 159515.93 | Q5: 269851.65 | R5: 278115.48 | S5: 289972.69 | T5: 350844.58 | U5: 439188.51 | V5: =U5-U9 -> 179452.46
A6: Other income | B6: 16341.99 | C6: 13576.92 | D6: 17268.13 | E6: 18348.93 | F6: 25230.31 | G6: 24878.975 | H6: 27332.88 | I6: 31758.99 | J6: 33912.05 | K6: 124345.75 | L6: 64950.33 | M6: 18968.527 | N6: 18517.53 | O6: 65111.991 | P6: 76521.802 | Q6: 98158.99 | R6: 107222.41 | S6: 117000.4 | T6: 122533.56 | U6: 155386.39
A7: Total Income | B7: =B5+B6 -> 80057.67 | C7: =C5+C6 -> 77974.28 | D7: =D5+D6 -> 86114.19 | E7: =E5+E6 -> 105797.3 | F7: =F5+F6 -> 137989.36 | G7: =G5+G6 -> 147068.27 | H7: =H5+H6 -> 155885.27 | I7: =I5+I6 -> 167695.4 | ... U7: =U5+U6 -> 594574.9
A8: EXPENDITURE
A9: Interest expended | B9: 37995.94 | C9: 34627.38 | D9: 34922.66 | E9: 43389.15 | F9: 61390.74 | G9: 62137.422 | H9: 59247.58 | I9: 58584.33 | J9: 77779.94 | K9: 154138.55 | L9: 44665.522 | M9: 40128.837 | N9: 38908.451 | O9: 50543.388 | P9: 74108.163 | Q9: 161123.8 | R9: 156010.17 | S9: 156194.34 | T9: 189980.82 | U9: 259736.05
A10: Operating expenses | B10: 18065.758 | C10: 19174.88 | D10: 24824.23 | E10: 40869.62 | F10: 37242.55 | G10: 33036.056 | H10: 35001.257 | I10: 40312.43 | J10: 51533.69 | K10: 152269.34 | L10: 71517.899 | M10: 21560.834 | N10: 26733.316 | O10: 82439.023 | P10: 97782.792 | Q10: 131781.56 | R10: 150429.6 | S10: 174363.43 | T10: 189814.49 | U10: 235893.84
A11: Provisions and contingencies | B11: 22117.22 | C11: 16919.63 | D11: 12202.95 | E11: 10685.87 | F11: 12932.53 | G11: 24598.524 | H11: 29779.669 | I11: 30647.74 | J11: 29203.77 | K11: 36140.38 | L11: 22377.214 | M11: 20204.443 | N11: 15910.818 | O11: 18733.363 | P11: 19140.028 | Q11: 56928.459 | R11: 54618.409 | S11: 40059.148 | T11: 37024.409 | U11: 30806.757
A12: Total Expenses | B12: =B9+B10+B11 -> 78178.919 | C12: =C9+C10+C11 -> 70721.89 | D12: =D9+D10+D11 -> 71949.84 | E12: =E9+E10+E11 -> 94944.64 | F12: =F9+F10+F11 -> 111565.82 | G12: =G9+G10+G11 -> 119772 | H12: =H9+H10+H11 -> 124028.51 | I12: =I9+I10+I11 -> 129544.5 | ... U12: =U9+U10+U11 -> 526436.64
A13: Net Profit for the year | B13: =B7-B12 -> 1878.7514 | C13: =C7-C12 -> 7252.39 | D13: =D7-D12 -> 14164.35 | E13: =E7-E12 -> 10852.66 | F13: =F7-F12 -> 26423.54 | G13: =G7-G12 -> 27296.265 | H13: =H7-H12 -> 31856.768 | I13: =I7-I12 -> 38150.9 | ... U13: =U7-U12 -> 68138.261
A14: Minority Interest | B14: -25.6409 | C14: -56.89 | D14: =-87.6+42.54 -> -45.06 | E14: =-100.06+65.85 -> -34.21 | F14: =-106.05+68.71 -> -37.34 | G14: -42.3147 | H14: =-23.559 -> -23.559 | I14: -98.15 | J14: -151.59 | K14: -1384.46 | L14: -1659.1602 | M14: 0 | N14: 0 | O14: =-1424.6738+998.2876 -> -426.3862 | P14: =-1824.1392+1073.768 -> -750.3712 | Q14: =-1372.1667+2963.1404 -> 1590.9737 | R14: =-1482.3573-391.9045 -> -1874.2618 | S14: =-1809.3049+827.0133 -> -982.2916 | T14: =1191.4521-2101.7092 -> -910.2571 | U14: =1405.1543-2458.7491 -> -1053.5948
A15: Consolidated Net Profit | B15: =B13+B14 -> 1853.1105 | C15: =C13+C14 -> 7195.5 | D15: =D13+D14 -> 14119.29 | E15: =E13+E14 -> 10818.45 | F15: =F13+F14 -> 26386.2 | G15: =G13+G14 -> 27253.951 | H15: =H13+H14 -> 31833.209 | I15: =I13+I14 -> 38052.75 | ... U15: =U13+U14 -> 67084.666
A16: Balance in P&L b/d from Previous year | B16: 25117.523 | C16: 27125.82 | D16: 31466.92 | E16: 40604.49 | F16: 47769.25 | G16: 52849.607 | H16: 61817.688 | I16: 78594.2 | J16: 99062.77 | K16: =120369.35+3570.1 -> 123939.45 | L16: 22020.109 | M16: 21327.468 | N16: 31009.066 | O16: 50898.851 | P16: 65638.677 | Q16: -8328.3999 | R16: -1361.7425 | S16: 8096.5412 | T16: 20394.351 | U16: 41923.303
A17: Amount available for appropriation | B17: =B15+B16 -> 26970.633 | C17: =C15+C16 -> 34321.32 | D17: =D15+D16 -> 45586.21 | E17: =E15+E16 -> 51422.94 | F17: =F15+F16 -> 74155.45 | G17: =G15+G16 -> 80103.558 | H17: =H15+H16 -> 93650.897 | I17: =I15+I16 -> 116646.95 | ... U17: =U15+U16 -> 109007.97
A18: Appropriations:
A19: Tranfer to statutory reserve | B19: 406.8 | C19: 1647.13 | D19: 3256.37 | E19: 2394.92 | F19: 6215.36 | G19: 6771.7167 | H19: 7879.6978 | I19: 9444.38 | J19: 11445.96 | K19: 15684.72 | L19: 1982.8 | M19: 4048.2 | N19: 5834.9 | O19: 7974.2 | P19: 10222.1 | Q19: 4538.1761 | R19: 6287.8379 | S19: 9769.0269 | T19: 15370.4 | U19: 18716.883
A20: Transfer to reserve fund | B20: 38.65 | C20: 0 | D20: 609.19 | E20: 841 | F20: 968.13 | G20: 90.2672 | H20: 0 | I20: 0 | J20: 500 | K20: 3000 | L20: 0.367 | M20: 1090 | N20: 1500 | O20: 0 | P20: 0 | Q20: 8254.9135 | R20: 0 | S20: 0
A21: Transfer to Investment reserve | B21: 0 | C21: 0 | D21: 148.5 | E21: -148.5 | F21: 242.29 | G21: 4893.3585 | H21: 0 | I21: 233.13 | J21: -294.79 | K21: 529.42 | L21: 0 | M21: 0 | N21: 0 | O21: 0 | P21: 0 | Q21: 0 | R21: 0 | S21: 0
A22: Transfer to capital reserve | B22: 340.5245 | C22: 848.24 | D22: 441.04 | E22: 67.84 | F22: 139.55 | G22: 1646.9504 | H22: 0 | I22: 666.47 | J22: 4.62 | K22: 4166.41 | L22: 395.44 | M22: 130.23 | N22: 1574.2037 | O22: 87.82 | P22: 33.25 | Q22: 0 | R22: 1465.1242 | S22: 538.1524 | T22: 232.8084 | U22: 326.2104
A23: Transfer to general reserve | B23: 3.4138 | C23: 18.49 | D23: 2.32 | E23: 2.46 | F23: 2.47 | G23: 2625.7315 | H23: 3111.6525 | I23: 3696.14 | J23: 4410.87 | K23: 6081.23 | L23: 796.63 | M23: 1500 | N23: 0 | O23: 2625.4 | P23: 3135.3 | Q23: 0 | R23: -307.4807 | S23: 1783.6804 | T23: 3854.2653 | U23: 6456.9182
A24: Transfer to Investment fluctuation reserve | B24: 328 | C24: 326 | D24: 455 | E24: 73 | F24: 879 | G24: 1123.846 | H24: 2219.6842 | I24: 0 | J24: 82 | K24: 378 | L24: 669 | M24: -249.5799 | N24: 382.8798 | O24: 104.381 | P24: 992.79 | Q24: 0 | R24: 1928.1963 | S24: 4647.8702 | T24: 4575.4343 | U24: -749.0805
A25: Transfer to/from reserve fund | B25: 0.8502 | C25: 42.23 | D25: 69.3 | E25: 115.83 | F25: 119.5 | G25: 0 | H25: 61.6645 | I25: -48.34 | J25: -62.65 | K25: -288.28 | L25: 68.6312 | M25: -7.7638 | N25: 0 | O25: 5025.568 | P25: 87.234 | Q25: 0 | R25: 0 | S25: 0 | T25: 0 | U25: 0
A26: Dividend paid | B26: 331.8569 | C26: 0 | D26: 0 | E26: 307.14 | F26: 307.98 | G26: 1134 | H26: 1712 | I26: 3592.4 | J26: 8604.52 | K26: 8404.42 | L26: 645.3078 | M26: 0 | N26: 1385.2335 | O26: 3479.4463 | P26: 5598.5964 | Q26: 8.0552 | R26: 3559.8446 | S26: 6336.4742 | T26: 10084.811 | U26: 12226.718
A27: Balance in P&L c/d | B27: 25520.538 | C27: 31439.23 | D27: 40604.49 | E27: 47769.25 | F27: 65281.17 | G27: 61817.688 | H27: 78594.198 | I27: 99062.77 | J27: 120369.35 | K27: 150045.57 | L27: 26799.996 | M27: 31009.066 | N27: 43671.339 | O27: 65638.677 | P27: 89825.78 | Q27: -1361.7425 | R27: 8096.5412 | S27: 20394.351 | T27: 41923.303 | U27: 72019.179
A28: Corporate dividend tax paid | L28: 228.2446 | M28: 0 | N28: 0 | O28: 0 | P28: 0 | Q28: 0 | R28: 3.6516 | S28: 0.8664 | T28: 1.5013 | U28: 11.1401
A29: Total of Appropriations | B29: =SUM(B19:B27) -> 26970.633 | C29: =SUM(C19:C27) -> 34321.32 | D29: =SUM(D19:D27) -> 45586.21 | E29: =SUM(E19:E27) -> 51422.94 | F29: =SUM(F19:F27) -> 74155.45 | G29: =SUM(G19:G27) -> 80103.558 | H29: =SUM(H19:H27) -> 93578.897 | I29: =SUM(I19:I27) -> 116646.95 | ... K29: =SUM(K19:K27) -> 188001.49 | L29: =SUM(L19:L28) -> 31586.416 | M29: =SUM(M19:M28) -> 37520.152 | N29: =SUM(N19:N28) -> 54348.556 | O29: =SUM(O19:O28) -> 84935.492 | P29: =SUM(P19:P28) -> 109895.05 | Q29: =SUM(Q19:Q28) -> 11439.402 | R29: =SUM(R19:R28) -> 21033.715 | S29: =SUM(S19:S28) -> 43470.421 | ... U29: =SUM(U19:U28) -> 109007.97
A30: Earnings Per equity share
A31: Basic | B31: 6.83 | C31: 24.19 | D31: 46.04 | E31: 35.2 | F31: 85.62 | G31: 49.84 | H31: 57.88 | I31: 68.77 | J31: 82.64 | K31: 90.42 | L31: 14.81 | M31: 24.01 | N31: 33.66 | O31: 48.86 | P31: 63.19 | Q31: 22.15 | R31: 25.11 | S31: 39.64 | T31: 62.35 | U31: 75.17
A32: Market prices | B32: 495.05 | C32: 706.3 | D32: =760 -> 760 | E32: =864 -> 864 | F32: =1052.35 -> 1052.35 | G32: 1128 | H32: 1499.4 | I32: 1476.4 | J32: 1607.55 | K32: =1458 -> 1458 | L32: 394.15 | M32: 587.7 | N32: 726.4 | O32: 877.6 | P32: 1097 | Q32: 213.1 | R32: 367.7 | S32: 491 | T32: 524.75 | U32: 759.05
B33: =B5-B9 -> 25719.74 | C33: =C5-C9 -> 29769.98 | D33: =D5-D9 -> 33923.4 | E33: =E5-E9 -> 44059.22 | F33: =F5-F9 -> 51368.31 | G33: =G5-G9 -> 60051.87 | H33: =H5-H9 -> 69304.813 | I33: =I5-I9 -> 77352.08 | ... U33: =U5-U9 -> 179452.46
A34: P/E | B34: =B32/'Income Statement-Banks'!B31 -> 72.481698 | C34: =C32/'Income Statement-Banks'!C31 -> 29.198016 | D34: =D32/'Income Statement-Banks'!D31 -> 16.507385 | E34: =E32/'Income Statement-Banks'!E31 -> 24.545455 | F34: =F32/'Income Statement-Banks'!F31 -> 12.290937 | G34: =G32/'Income Statement-Banks'!G31 -> 22.632424 | H34: =H32/'Income Statement-Banks'!H31 -> 25.905321 | I34: =I32/'Income Statement-Banks'!I31 -> 21.468664 | ... U34: =U32/'Income Statement-Banks'!U31 -> 10.097778
A35: P/B | B35: =B32/('Balance Sheet-Banks'!B9/'Company Profile'!$D$14) -> 1.7770294 | C35: =C32/('Balance Sheet-Banks'!C9/'Company Profile'!$D$14) -> 2.1123143 | D35: =D32/('Balance Sheet-Banks'!D9/'Company Profile'!$D$14) -> 1.9899633 | E35: =E32/('Balance Sheet-Banks'!E9/'Company Profile'!$D$14) -> 2.0597585 | F35: =F32/('Balance Sheet-Banks'!F9/'Company Profile'!$D$14) -> 2.0732268 | G35: =G32/('Balance Sheet-Banks'!G9/'Company Profile'!$D$14) -> 1.9784497 | H35: =H32/('Balance Sheet-Banks'!H9/'Company Profile'!$D$14) -> 2.2111267 | I35: =I32/('Balance Sheet-Banks'!I9/'Company Profile'!$D$14) -> 1.8471462 | ... U35: =U32/('Balance Sheet-Banks'!U9/'Company Profile'!$D$14) -> 0.54710424
A36: Market Cap | B36: =B32*'Company Profile'!$D$14 -> 153631.24 | C36: =C32*'Company Profile'!$D$14 -> 219189.47 | D36: =D32*'Company Profile'!$D$14 -> 235854.45 | E36: =E32*'Company Profile'!$D$14 -> 268129.27 | F36: =F32*'Company Profile'!$D$14 -> 326580.83 | G36: =G32*'Company Profile'!$B$14 -> 1734486.1 | H36: =H32*'Company Profile'!$B$14 -> 2305574.9 | I36: =I32*'Company Profile'!$B$14 -> 2270208.6 | J36: =J32*'Company Profile'!$B$14 -> 2471873.4 | K36: =K32*'Company Profile'!$B$14 -> 2241915.6 | L36: =L32*'Company Profile'!$C$14 -> 281533.11 | M36: =M32*'Company Profile'!$C$14 -> 419781.83 | N36: =N32*'Company Profile'!$C$14 -> 518852.34 | O36: =O32*'Company Profile'!$C$14 -> 626851.34 | P36: =P32*'Company Profile'!$C$14 -> 783564.17 | Q36: =Q32*'Company Profile'!$E$14 -> 196704.45 | R36: =R32*'Company Profile'!$E$14 -> 339409.79 | S36: =S32*'Company Profile'!$E$14 -> 453223.29 | T36: =T32*'Company Profile'!$E$14 -> 484376.63 | U36: =U32*'Company Profile'!$E$14 -> 700649.98

Sheet Income Statement-NBFCs
A1: INCOME STATEMENT
A2: Particulars | B2: #VALUE! | G2: #VALUE! | L2: #VALUE!
B3: 2020 | C3: 2021 | D3: 2022 | E3: 2023 | F3: 2024 | G3: 2020 | H3: 2021 | I3: 2022 | J3: 2023 | K3: 2024 | L3: 2020 | M3: 2021 | N3: 2022 | O3: 2023 | P3: 2024
A4: INCOME
A5: Revenue from Operations
A6: Interest Income | B6: 2303.08 | C6: 2877.43 | D6: 3481.75 | E6: 5269.24 | F6: 7202.36 | G6: 22970.39 | H6: 23303.38 | I6: 27269.76 | J6: 35548.57 | K6: 48306.6 | L6: 94177.36 | M6: 112102.79 | N6: 119251.52 | O6: 115555.35 | P6: 145457.01
A7: Fees and commission income | B7: 100.08 | C7: 74.62 | D7: 81.85 | E7: 86.22 | F7: 138.23 | G7: 2590.95 | H7: 2452.39 | I7: 3066.69 | J7: 4355.63 | K7: 5267.17 | L7: 9.19 | M7: 0.13 | N7: 0.09 | O7: 9.41 | P7: 48.1
A8: Net gain on fair value changes | B8: 73.71 | C8: 59.85 | D8: 58.97 | E8: 112.04 | F8: 133.2 | G8: 537.49 | H8: 591.22 | I8: 327.74 | J8: 334.32 | K8: 308.29 | L8: 739.79 | M8: 1648.37 | N8: 488.74 | O8: 524.14 | P8: 640.06
A9: Sale of services | B9: 169.15 | C9: 142.15 | D9: 142.02 | E9: 50.29 | F9: 52.48 | G9: 124.27 | H9: 157.53 | I9: 74.96 | J9: 38.18 | K9: 49.97 | L9: 191.14 | M9: 120.33 | N9: 139.69 | O9: 90.7 | P9: 88.87
A10: Income on assigned. Derecongnised loans | B10: 0 | C10: 0 | D10: 0 | E10: 134.8 | F10: 53.08 | G10: 0 | H10: 0 | I10: 0 | J10: 23.17 | K10: 13.33 | L10: 779.3 | M10: 487.93 | N10: 847.74 | O10: 1403.12 | P10: 1723.34
A11: Other operating income | B11: 0 | C11: 0.65 | D11: 2.07 | E11: 12.14 | F11: 37.96 | G11: 150.7 | H11: 163.58 | I11: 893.27 | J11: 1110.29 | K11: 1024.13 | L11: 943.02 | M11: 986.08 | N11: 1121.31 | O11: 1393.91 | P11: 2659.19
A12: Total revenue from operations | B12: =SUM(B6:B11) -> 2646.02 | C12: =SUM(C5:C11) -> 3154.7 | D12: =SUM(D5:D11) -> 3766.66 | E12: =SUM(E5:E11) -> 5664.73 | F12: =SUM(F5:F11) -> 7617.31 | G12: =SUM(G5:G11) -> 26373.8 | H12: =SUM(H5:H11) -> 26668.1 | I12: =SUM(I5:I11) -> 31632.42 | J12: =SUM(J5:J11) -> 41410.16 | ... P12: =SUM(P5:P11) -> 150616.57
A13: Other Income | B13: 0.21 | C13: 0.58 | D13: 0.47 | E13: 0.71 | F13: 0.4 | G13: 11.83 | H13: 14.95 | I13: 7.99 | J13: 8.1 | K13: 13.02 | L13: 232.87 | M13: 356.33 | N13: 525.54 | O13: 773.42 | P13: 1010.85
A14: Total income | B14: =B12+B13 -> 2646.23 | C14: =C12+C13 -> 3155.28 | D14: =D12+D13 -> 3767.13 | E14: =E12+E13 -> 5665.44 | F14: =F12+F13 -> 7617.71 | G14: =G12+G13 -> 26385.63 | H14: =H12+H13 -> 26683.05 | I14: =I12+I13 -> 31640.41 | ... P14: =P12+P13 -> 151627.42
A16: EXPENSES
A17: Finance costs | B17: 1616.03 | C17: 1965.87 | D17: 2155.31 | E17: 3211.32 | F17: 4692.61 | G17: 9473.21 | H17: 9414 | I17: 9748.24 | J17: 12559.89 | K17: 18724.69 | L17: 31728.4 | M17: 40999.29 | N17: 42558.52 | O17: 42091.78 | P17: 54300.78
A18: Fees and commission expense | B18: 1.3 | C18: 1.33 | D18: 4.68 | E18: 14.03 | F18: 11.71 | G18: 1056.37 | H18: 1246.48 | I18: 1745.55 | J18: 1891.47 | K18: 1931.5 | L18: 0 | M18: 32.48 | N18: 35.19
A19: Impairment on financial instruments | B19: 124.33 | C19: 247.21 | D19: 181.07 | E19: 123.5 | F19: 60.88 | G19: 3929.48 | H19: 5968.58 | I19: 4803.4 | J19: 3189.65 | K19: 4630.7 | L19: 1870.8 | M19: 2552.15 | N19: 3835.21 | O19: 2432.22 | P19: 5538.21
A20: Employee benefit expense | B20: 248.51 | C20: 245.76 | D20: 348.8 | E20: 435.14 | F20: 465.63 | G20: 2549.08 | H20: 2498.67 | I20: 3589.66 | J20: 5100.19 | K20: 6396.01 | L20: 12084.9 | M20: 11892.72 | N20: 12394.8 | O20: 14882.68 | P20: 18282.06
A21: Depreciation and ammortization expense | B21: 23.14 | C21: 21.77 | D21: 25.76 | E21: 33.4 | F21: 39.6 | G21: 294.63 | H21: 325.27 | I21: 384.57 | J21: 485.38 | K21: 683.32 | L21: 592.42 | M21: 673.6 | N21: 700.03 | O21: 781.61 | P21: 921.06
A22: Other expenses | B22: 65.47 | C22: 60.16 | D22: 91.65 | E22: 147.99 | F22: 185.96 | G22: 1760.74 | H22: 1237.79 | I22: 1865.21 | J22: 2665.49 | K22: 3314.36 | L22: 8192.24 | M22: 8236.92 | N22: 8749 | O22: 10333.96 | P22: 12620.27
A23: Total expenses | B23: =SUM(B17:B22) -> 2078.78 | C23: =SUM(C17:C22) -> 2542.1 | D23: =SUM(D17:D22) -> 2807.27 | E23: =SUM(E17:E22) -> 3965.38 | F23: =SUM(F17:F22) -> 5456.39 | G23: =SUM(G17:G22) -> 19063.51 | H23: =SUM(H17:H22) -> 20690.79 | I23: =SUM(I17:I22) -> 22136.63 | ... P23: =SUM(P17:P22) -> 91662.38
A24: Share of profit/loss from associates | B24: 0 | C24: 0 | D24: 0 | E24: 0 | F24: 0 | G24: 0 | H24: 0 | I24: 0 | J24: 1.67 | K24: 7.64 | L24: 0 | M24: 0 | N24: 0 | O24: 0 | P24: 0
A25: Profit before tax and exceptional items | B25: =B14-B23+B24 -> 567.45 | C25: =C14-C23+C24 -> 613.18 | D25: =D14-D23+D24 -> 959.86 | E25: =E14-E23+E24 -> 1700.06 | F25: =F14-F23+F24 -> 2161.32 | G25: =G14-G23+G24 -> 7322.12 | H25: =H14-H23+H24 -> 5992.26 | I25: =I14-I23+I24 -> 9503.78 | ... P25: =P14-P23+P24 -> 59965.04
A26: Exceptional items | B26: 0 | G26: 0 | H26: 0 | I26: 0 | J26: 0 | K26: 0 | L26: 0 | M26: 0 | N26: 0 | O26: 0 | P26: 0
A27: Tax expense
A28: Current tax | B28: 126.1 | C28: 187 | D28: 250.4 | E28: 399.8 | F28: 509 | G28: 2205.25 | H28: 1660.26 | I28: 2497.45 | J28: 3998.18 | K28: 4957.72 | L28: 10779.28 | M28: 13359.62 | N28: 14110.96 | O28: 12341.19 | P28: 15807.24
A29: Deferred tax | B29: 20.02 | C29: -27.01 | D29: -0.16 | E29: 42.46 | F29: -78.9 | G29: -146.88 | H29: -87.82 | I29: -21.9 | J29: 21.99 | K29: -99.32 | L29: 137.32 | M29: -225.02 | N29: -315.12 | O29: 294.47 | P29: -512.3
A30: Tax relating to prior years | L30: 0.5 | M30: -8.5 | N30: -7.2 | O30: -105.52 | P30: -5.84
A31: Total tax expense | B31: =B28+B29 -> 146.12 | C31: =C28+C29 -> 159.99 | D31: =D28+D29 -> 250.24 | E31: =E28+E29 -> 442.26 | F31: =F28+F29 -> 430.1 | G31: =G28+G29 -> 2058.37 | H31: =H28+H29 -> 1572.44 | I31: =I28+I29 -> 2475.55 | ... K31: =K28+K29 -> 4858.4 | L31: =L28+L29+L30 -> 10917.1 | M31: =M28+M29+M30 -> 13126.1 | N31: =N28+N29+N30 -> 13788.64 | O31: =O28+O29+O30 -> 12530.14 | P31: =P28+P29+P30 -> 15289.1
A33: Profit after tax | B33: =B25-B31 -> 421.33 | C33: =C25-C31 -> 453.19 | D33: =D25-D31 -> 709.62 | E33: =E25-E31 -> 1257.8 | F33: =F25-F31 -> 1731.22 | G33: =G25+G26-G31 -> 5263.75 | H33: =H25+H26-H31 -> 4419.82 | I33: =I25+I26-I31 -> 7028.23 | J33: =J25+J26-J31 -> 11507.69 | K33: =K25+K26-K31 -> 14451.17 | L33: =L25+L26-L31 -> 31686.81 | M33: =M25+M26-M31 -> 38188.7 | N33: =N25+N26-N31 -> 40313.24 | ... P33: =P25+P26-P31 -> 44675.94
A34: Earnings Per Share
A35: Basic | B35: 1.12 | C35: 0.93 | D35: 1.45 | E35: 1.88 | F35: 2.58 | G35: 89.77 | H35: 73.58 | I35: 116.64 | J35: 190.53 | K35: 236.89 | L35: 78.3 | M35: 94.84 | N35: 100.1 | O35: 89.99 | P35: 107.72
A36: Market price | B36: 0 | C36: 0 | D36: 0 | E36: 0 | F36: 150 | G36: 364.39 | H36: 461.36 | I36: 724.05 | J36: 628.01 | K36: 689.32 | L36: 0 | M36: 0 | N36: 0 | O36: 275.3 | P36: 200.5
A38: Operating expenses | B38: =B18+B20+B21+B22+B19 -> 462.75 | C38: =C18+C20+C21+C22+C19 -> 576.23 | D38: =D18+D20+D21+D22+D19 -> 651.96 | E38: =E18+E20+E21+E22+E19 -> 754.06 | F38: =F18+F20+F21+F22+F19 -> 763.78 | G38: =G18+G20+G21+G22+G19 -> 9590.3 | H38: =H18+H20+H21+H22+H19 -> 11276.79 | I38: =I18+I20+I21+I22+I19 -> 12388.39 | ... P38: =P18+P20+P21+P22+P19 -> 37361.6
A39: Operating Income | B39: =B7+B8+B9+B10+B11+B13 -> 343.15 | C39: =C7+C8+C9+C10+C11+C13 -> 277.85 | D39: =D7+D8+D9+D10+D11+D13 -> 285.38 | E39: =E7+E8+E9+E10+E11+E13 -> 396.2 | F39: =F7+F8+F9+F10+F11+F13 -> 415.35 | G39: =G7+G8+G9+G10+G11+G13 -> 3415.24 | H39: =H7+H8+H9+H10+H11+H13 -> 3379.67 | I39: =I7+I8+I9+I10+I11+I13 -> 4370.65 | ... P39: =P7+P8+P9+P10+P11+P13 -> 6170.41
A40: P/E | B40: =B36/B35 -> 0 | C40: =C36/C35 -> 0 | D40: =D36/D35 -> 0 | E40: =E36/E35 -> 0 | F40: =F36/F35 -> 58.139535 | G40: =G36/G35 -> 4.0591512 | H40: =H36/H35 -> 6.2701821 | I40: =I36/I35 -> 6.2075617 | ... P40: =P36/P35 -> 1.8613071
A41: P/B | B41: =B36/('Balance Sheet-NBFCs'!B9/'Company Profile'!$G$14) -> 0 | C41: =C36/('Balance Sheet-NBFCs'!C9/'Company Profile'!$G$14) -> 0 | D41: =D36/('Balance Sheet-NBFCs'!D9/'Company Profile'!$G$14) -> 0 | E41: =E36/('Balance Sheet-NBFCs'!E9/'Company Profile'!$G$14) -> 0 | F41: =F36/('Balance Sheet-NBFCs'!F9/'Company Profile'!$G$14) -> 10.212051 | G41: =G36/('Balance Sheet-NBFCs'!G9/'Company Profile'!$F$14) -> 7.0055647 | H41: =H36/('Balance Sheet-NBFCs'!H9/'Company Profile'!$F$14) -> 7.7668965 | I41: =I36/('Balance Sheet-NBFCs'!I9/'Company Profile'!$F$14) -> 10.29465 | J41: =J36/('Balance Sheet-NBFCs'!J9/'Company Profile'!$F$14) -> 7.1786367 | K41: =K36/('Balance Sheet-NBFCs'!K9/'Company Profile'!$F$14) -> 5.586019 | L41: =L36/('Balance Sheet-NBFCs'!L9/'Company Profile'!$H$14) -> 0 | M41: =M36/('Balance Sheet-NBFCs'!M9/'Company Profile'!$H$14) -> 0 | N41: =N36/('Balance Sheet-NBFCs'!N9/'Company Profile'!$H$14) -> 0 | O41: =O36/('Balance Sheet-NBFCs'!O9/'Company Profile'!$H$14) -> 0.049891778 | P41: =P36/('Balance Sheet-NBFCs'!P9/'Company Profile'!$H$14) -> 0.031255071
A42: Market cap | B42: =B36*'Company Profile'!$G$14 -> 0 | C42: =C36*'Company Profile'!$G$14 -> 0 | D42: =D36*'Company Profile'!$G$14 -> 0 | E42: =E36*'Company Profile'!$G$14 -> 0 | F42: =F36*'Company Profile'!$G$14 -> 124929.12 | G42: =G36*'Company Profile'!$F$14 -> 226473.3 | H42: =H36*'Company Profile'!$F$14 -> 286741.47 | I42: =I36*'Company Profile'!$F$14 -> 450006.85 | J42: =J36*'Company Profile'!$F$14 -> 390316.69 | K42: =K36*'Company Profile'!$F$14 -> 428421.69 | L42: =L36*'Company Profile'!$H$14 -> 0 | M42: =M36*'Company Profile'!$H$14 -> 0 | N42: =N36*'Company Profile'!$H$14 -> 0 | O42: =O36*'Company Profile'!$H$14 -> 11052.428 | P42: =P36*'Company Profile'!$H$14 -> 8049.4434

Sheet Cash Flow Statement-Banks
A1: CASH FLOW STATEMENT
A2: Particulars | B2: #VALUE! | G2: #VALUE! | L2: #VALUE! | Q2: #VALUE!
B3: 2020 | C3: 2021 | D3: 2022 | E3: 2023 | F3: 2024 | G3: 2020 | H3: 2021 | I3: 2022 | J3: 2023 | K3: 2024 | L3: 2020 | M3: 2021 | N3: 2022 | O3: 2023 | P3: 2024 | Q3: 2020 | R3: 2021 | S3: 2022 | T3: 2023 | U3: 2024
A4: Cash flow from Operating activities
A5: Net profit before taxes | B5: 5254.4043 | C5: 9693.19 | D5: 18841.86 | E5: 18521.12 | F5: 35071.95 | G5: 38152.537 | H5: 42772.584 | I5: 50775.24 | J5: 61346.8 | K5: 75184.14 | L5: 16929.447 | M5: 20182.718 | N5: 30608.885 | O5: 45830.078 | P5: 59683.996 | Q5: 31907.559 | R5: 30921.708 | S5: 48756.343 | T5: 74488.304 | U5: 90186.447
A6: Adjustments for:
A7: Depreciation on fixed assets | B7: 806.0735 | C7: 979.39 | D7: 1048.99 | E7: 13145.65 | F7: 1388.46 | G7: 1276.7714 | H7: 1385.0062 | I7: 1680.73 | J7: 2345.47 | K7: 3092.08 | L7: 1369.6381 | M7: 1201.3384 | N7: 1316.2116 | O7: 1635.1038 | P7: 1995.8856 | Q7: 3661.5585 | R7: 3711.0636 | S7: 3691.27 | T7: 3695.5986 | U7: 3849.1245
A8: Depreciation on investments | B8: 135.9912 | C8: 1329.08 | D8: -264.48 | E8: 595.57 | F8: -431.32 | G8: 702.1095 | H8: 1485.3243 | I8: -1546.4 | J8: 545.82 | K8: -6957.14 | L8: 2180.9159 | M8: -2214.3504 | N8: 1908.9256 | O8: 2705.3455 | P8: 1617.2037 | Q8: 626.5221 | R8: 5.1548 | S8: 445.7369 | T8: 0 | U8: 0
A9: Ammortisation of premium on held to maturity | B9: 354.6142 | C9: 592.12 | D9: 823.78 | E9: 889.11 | F9: 894.18 | G9: 501.4137 | H9: 765.4693 | I9: 821.32 | J9: 851.2 | K9: 966.09 | L9: 0 | M9: 0 | N9: 0 | O9: 0 | P9: 0 | Q9: 0 | R9: 0 | S9: 0 | T9: 0 | U9: 0
A10: Provision for Non performing assets | B10: 12835.295 | C10: 12344.85 | D10: 7580.8 | E10: 6225.9 | F10: 6533.43 | G10: 11065.713 | H10: 13927.011 | I10: 13286.95 | J10: 13561.19 | K10: 12540.05 | L10: 8962.7398 | M10: 10749.126 | N10: 6164.0412 | O10: -365.3501 | P10: 963.5716 | Q10: 43848.89 | R10: =29732.6529+2820.9883 -> 32553.641 | S10: =15845.8997+3471.788 -> 19317.688 | T10: =10826.8816+1483.8759 -> 12310.757 | U10: =12241.867-604.1107 -> 11637.756
A11: Provision on standard assets | B11: 1534.1633 | C11: 3322.61 | D11: 2224.17 | E11: -421.94 | F11: 424.15 | G11: 3057.4317 | H11: 5283.0711 | I11: 5418.21 | J11: 292.89 | K11: 1578.23 | L11: 3443.9929 | M11: 278.8318 | N11: 449.2475 | O11: 489.8941 | P11: 1165.8491 | Q11: -291.3652 | R11: 3601.3226 | S11: 4581.8142 | T11: 5641.5051 | U11: -1264.4725
A12: Profit/Loss on sale of land, buildings and other assets | B12: 5.0818 | C12: 8.77 | D12: 6.11 | E12: 7.69 | F12: 4.42 | G12: 8.1865 | H12: 0.2859 | I12: 3.25 | J12: -8.05 | K12: -75.36 | L12: -0.145 | M12: 2.7974 | N12: -4.04 | O12: -54.2579 | P12: -14.4093 | Q12: 28.3375 | R12: 28.3364 | S12: 16.4047 | T12: 29.0316 | U12: 25.2054
A13: Profit/Loss on revaluation of investments | T13: 4922.6098 | U13: -4892.7872
A14: Income from subsidiaries, joint ventures and entities | B14: 12.1721 | C14: 0 | D14: 0 | E14: 0 | F14: 0 | G14: 0 | H14: 0 | I14: 0 | J14: 0 | K14: 0 | L14: 0 | M14: -1233.995 | N14: -1828.7906 | O14: 0 | P14: 0 | Q14: -5573.6296 | R14: =-1577.8431+254.4131 -> -1323.43 | S14: =-9.7432 -> -9.7432 | T14: 0 | U14: 0
A15: Provision for restructured assets/ strategic debt restructuring | B15: -15.498 | C15: 0 | D15: 0 | E15: 0 | F15: 0 | G15: 0 | H15: 0 | I15: 0 | J15: 0 | K15: -7341.42 | L15: 0 | M15: 0 | N15: 0 | O15: 0 | P15: 0 | Q15: 4908.0907 | R15: 5900.3121 | S15: 5587.8874 | T15: 6543.7306 | U15: 9661.5237
A16: Provision on unhedged foreign currency exposure | B16: -10.68 | C16: 0 | D16: 0 | E16: 0 | G16: 0 | H16: 0 | I16: 0 | J16: 0 | K16: 0 | L16: 0 | M16: 0 | N16: 0 | O16: 0 | P16: 0
A17: Provision for other contingencies | B17: 4224.4858 | C17: 0 | D17: 0 | F17: 0 | G17: 0 | H17: 0 | I17: 0 | J17: 0 | K17: 10900 | L17: 793.6906 | M17: 5344.2673 | N17: 1651.0217 | O17: 5423.6861 | P17: 878.0202 | Q17: 604.6549 | R17: 9947.1949 | S17: 2777.1833 | T17: 232.0148 | U17: -2668.3083
A18: Employee stock exchange expense | B18: 0 | C18: 0 | D18: 150.77 | E18: 286.02 | F18: 519.57 | G18: 0 | H18: 0 | I18: 341.24 | J18: 787.06 | K18: 1731.73 | L18: 11.413 | M18: 0 | N18: 264.219 | O18: 518.0508 | P18: 702.9081 | Q18: =-2963.1404-14.6677 -> -2977.8081 | R18: =391.9045-3.195 -> 388.7095 | S18: =-827.0133-3.195 -> -830.2083 | T18: =-1191.4521-2.6625 -> -1194.1146 | U18: =-1405.1543-5.5719 -> -1410.7262
A19: Adjustments for:
A20: Increase/Decrease in investments | B20: 24432.47 | C20: -19644 | D20: -24189.72 | E20: 4622.29 | F20: -38129.02 | G20: -101070.1 | H20: -50156.636 | I20: -10849.22 | J20: -64182.03 | K20: -88411.63 | L20: -31531.315 | M20: 24066.691 | N20: 4431.1642 | O20: -15828.629 | P20: 16735.535 | Q20: -100670.42 | R20: -368800.15 | S20: -183899.64 | T20: -141597.38 | U20: -190457.11
A21: Increase/decrease in advances | B21: -86703.113 | C21: -63518.12 | D21: -106571.94 | E21: -149553.15 | F21: -137622.1 | G21: -185500.36 | H21: -155681.07 | I21: -248946.13 | J21: -254569.45 | K21: -309210.7 | L21: -69243.415 | M21: -99494.736 | N21: -131475.82 | O21: -163893.16 | P21: -178264.48 | Q21: -191306.4 | R21: -156020.46 | S21: -309322.91 | T21: -484653.01 | U21: -528612.41
A22: increase/decrease in deposits | B22: 91411.273 | C22: 65466.21 | D22: 122611.53 | E22: 125161.2 | F22: 121277.69 | G22: 223704.46 | H22: 187513.74 | I22: 224282.15 | J22: 324660.22 | K22: 336964.81 | L22: 119467.52 | M22: 161553.17 | N22: 132049.45 | O22: 119466.36 | P22: 232993.01 | Q22: 333619.56 | R22: 441170.62 | S22: 372079.36 | T22: 381124.91 | U22: 498001.98
A23: Increase/decrease in other assets | B23: -26522.351 | C23: 4801.71 | D23: 2920.04 | E23: 2968.61 | F23: 9145.17 | G23: -7249.7457 | H23: 8307.684 | I23: -40044.7 | J23: -58909.79 | K23: -31197.26 | L23: 2456.0834 | M23: 1077.3799 | N23: 5072.7916 | O23: -16597.135 | P23: 1881.8794 | Q23: -21857.443 | R23: -66249.946 | S23: 5255.8279 | T23: -60531.723 | U23: -46236.906
A24: Increase/Decrease in borrowings other than capital instruments | Q24: -89342.809 | R24: 90438.852 | S24: 11807.876 | T24: 54584.073 | U24: 112581.11
A25: Increase/decrease in other liabilities & provisions | B25: 5698.2825 | C25: -715.93 | D25: 7401.45 | E25: 6313.23 | F25: 2599.86 | G25: 9359.8719 | H25: -104.56 | I25: 7655.94 | J25: 10459.86 | K25: 6420.4 | L25: 27116.069 | M25: 5082.0785 | N25: 8133.4402 | O25: 27774.253 | P25: 30289.317 | Q25: 31602.728 | R25: 67465.501 | S25: 86464.266 | T25: 75713.74 | U25: 102500.28
A26: Direct taxes paid | B26: -3037.0292 | C26: -2027 | D26: -4446.06 | E26: -6686.52 | F26: -7231.11 | G26: -10877.375 | H26: -13021.453 | I26: -14838.16 | J26: -16367.49 | K26: -22842.84 | L26: -2391.8931 | M26: -2501.9557 | N26: -3693.8225 | O26: -10875.426 | P26: -13343.605 | Q26: -14859.491 | R26: -3819.4934 | S26: -9024.303 | T26: -17323.722 | U26: -31268.268
A27: Increase in policy holder's funds | K27: 35728.16 | L27: 0 | M27: 0 | N27: 0 | O27: 0 | P27: 0 | Q27: 0 | R27: 0 | S27: 0 | T27: 0 | U27: 0
A28: Net cash flow from operating activities | B28: =SUM(B5,B7:B17,B20:B26) -> 30415.636 | C28: =SUM(C5,C7:C17,C20:C26) -> 12632.88 | D28: =SUM(D5,D7:D18,D20:D26) -> 28137.3 | E28: =SUM(E5,E7:E18,E20:E26) -> 22074.78 | F28: =SUM(F5,F7:F18,F20:F26) -> -5554.67 | G28: =SUM(G5,G7:G18,G20:G26) -> -16869.092 | H28: =SUM(H5,H7:H18,H20:H26) -> 42476.456 | I28: =SUM(I5,I7:I18,I20:I26) -> -11959.58 | J28: =SUM(J5,J7:J18,J20:J26) -> 20813.7 | K28: =SUM(K5,K7:K18,K20:K27) -> 19069.34 | L28: =SUM(L5,L7:L18,L20:L26) -> 79564.747 | M28: =SUM(M5,M7:M18,M20:M26) -> 124093.36 | N28: =SUM(N5,N7:N18,N20:N26) -> 55046.925 | O28: =SUM(O5,O7:O18,O20:O26) -> -3771.1921 | P28: =SUM(P5,P7:P18,P20:P26) -> 157284.68 | Q28: =SUM(Q5,Q7:Q18,Q20:Q26) -> 23928.532 | R28: =SUM(R5,R7:R18,R20:R26) -> 89918.93 | S28: =SUM(S5,S7:S18,S20:S26) -> 57694.846 | ... U28: =SUM(U5,U7:U18,U20:U26) -> 21632.431
A30: Cash flow from Investing activities
A31: Purchase of fixed assets | B31: -1104.2694 | C31: -938.44 | D31: -1408.97 | E31: -1389.42 | F31: -2385.41 | G31: -1635.8706 | H31: -1696.146 | I31: -2236.24 | J31: -3466.57 | K31: -4286.72 | L31: -1873.4522 | M31: -1430.1487 | N31: -1610.9856 | O31: -2467.6808 | P31: -3678.5464 | Q31: -3065.0113 | R31: =-3909.825+81.8047 -> -3828.0203 | S31: =-3305.2601+254.3431 -> -3050.917 | T31: -4043.6315 | U31: -4175.1262
A32: Increase/decrease in held to maturity investments | B32: -8581.9362 | C32: -53269.93 | D32: -25830.38 | E32: -19714.15 | F32: -6381.97 | G32: 0 | H32: 0 | I32: 0 | J32: 0 | K32: 0 | L32: -40460.513 | M32: -57037.844 | N32: -38089.5 | O32: -65825.059 | P32: -142322.44 | Q32: -6031.0606 | R32: 0 | S32: 0 | T32: 0 | U32: 0
A33: Proceeds from sale of fixed assets | B33: 27.3426 | C33: 13.55 | D33: 7.25 | E33: 11.73 | F33: 9.07 | G33: 18.9462 | H33: 15.2809 | I33: 19.91 | J33: 42.68 | K33: 99.82 | L33: 25.5374 | M33: 5.6622 | N33: 20.8665 | O33: 287.4176 | P33: 69.8893 | Q33: 0 | R33: 0 | S33: 0 | T33: 0 | U33: 0
A34: Purchase consideration for acquisition | B34: 0 | C34: 0 | D34: 0 | E34: -11602.54 | F34: -329.85 | G34: 0 | H34: 0 | I34: 0 | J34: 0 | L34: 0 | M34: 0 | N34: 0 | O34: 0 | P34: 0 | Q34: 184.0819 | R34: -3176.9416 | S34: -582.764 | T34: 0 | U34: -82.161
A35: Dividend from associates | Q35: 0 | R35: 3.195 | S35: 3.195 | T35: 2.6625 | U35: 5.5719
A36: Income from subsidiaries, joint ventures and entities | L36: 0 | M36: 1233.995 | N36: 1828.7906 | O36: 0 | P36: 0 | Q36: 14.6677 | R36: =1577.8431-254.4131 -> 1323.43 | S36: 9.7432 | T36: 0 | U36: 0
A37: Proceeds from sale of investment in subsidiaries | K37: 9500.67 | L37: 0 | M37: 3736.9338 | N37: 2815.38 | O37: 0 | P37: 0 | Q37: 5573.6296 | R37: 1942.1097 | S37: 2.2296 | T37: 0 | U37: 0
A38: Net cash generated from/to investing activities | B38: =SUM(B31:B34) -> -9658.863 | C38: =SUM(C31:C34) -> -54194.82 | D38: =SUM(D31:D34) -> -27232.1 | E38: =SUM(E31:E34) -> -32694.38 | F38: =SUM(F31:F34) -> -9088.16 | G38: =SUM(G31:G34) -> -1616.9244 | H38: =SUM(H31:H34) -> -1680.8651 | I38: =SUM(I31:I34) -> -2216.33 | J38: =SUM(J31:J34) -> -3423.89 | K38: =SUM(K31:K37) -> 5313.77 | L38: =SUM(L31:L37) -> -42308.428 | M38: =SUM(M31:M37) -> -53491.402 | N38: =SUM(N31:N37) -> -35035.448 | O38: =SUM(O31:O37) -> -68005.322 | P38: =SUM(P31:P37) -> -145931.09 | Q38: =SUM(Q31:Q37) -> -3323.6927 | R38: =SUM(R31:R37) -> -3736.2272 | ... U38: =SUM(U31:U37) -> -4251.7153
A40: Cash flow from Financing activities
A41: Proceeds/repayment from issue of subordinated debt, perpetual debt & upper tier II instruments | B41: -2000 | C41: 0 | D41: -2377.45 | E41: =12382.65-6000 -> 6382.65 | F41: 0 | G41: 743.5 | H41: =356.5-1105 -> -748.5 | I41: =8312.75-3650 -> 4662.75 | J41: =23000-12077 -> 10923 | K41: =2350-230 -> 2120 | L41: 0 | M41: 0 | N41: 0 | O41: 0 | P41: 0 | Q41: =8495.818-4908.0907 -> 3587.7273 | R41: =27431-16897.664-5069.1088 -> 5464.2272 | S41: =14074-10518.3-5411.0089 -> -1855.3089 | T41: =19533.0925-2125-6324.6256 -> 11083.467 | U41: =20164.6479-14288.2-8589.2532 -> -2712.8053
A42: Increase/decrease in borrowings (net) | B42: -4069.6631 | C42: -2931.44 | D42: 49906.9 | E42: 52.76 | F42: 21985.98 | G42: 28358.044 | H42: -8389.0744 | I42: 44308.08 | J42: 18007.29 | K42: -7342.84 | L42: =36611.4451-52000.6249+18718.421 -> 3329.2412 | M42: =15208.9846-37729.0832-48875.2518 -> -71395.35 | N42: =25260.1665-23314.4678+13509.5945 -> 15455.293 | O42: =41736.1966-26891.7978+12483.696 -> 27328.095 | P42: =39196.8191-39146.8771+18142.3005 -> 18192.243 | Q42: 0 | R42: 0 | S42: 0
A43: Proceeds from issue of share capital | B43: 50.0066 | C43: 48.41 | D43: 1.2 | E43: 1.42 | F43: 1.94 | G43: 1848.6821 | H43: 1760.0995 | I43: 2609.76 | J43: 3415.83 | K43: 5249.73 | L43: 549.3213 | M43: 15460.032 | N43: 797.9764 | O43: 942.0691 | P43: 1170.8675 | Q43: 0 | R43: 0 | S43: 0
A44: Proceeds from share premium | B44: 15187.706 | C44: 10102.17 | D44: 275.83 | E44: 378.81 | F44: 555.26 | G44: 0 | H44: 0 | I44: 0 | J44: 0 | K44: 3192.81 | L44: 0 | M44: 0 | N44: 0 | O44: 0 | P44: 0 | Q44: 0 | R44: 0 | S44: 0 | T44: 0.0064 | U44: 0
A45: Payment of dividend | B45: -331.8569 | C45: 0 | D45: 0 | E45: -307.14 | F45: -307.98 | G45: -6630.5761 | H45: 0 | I45: -3592.4 | J45: -8604.52 | K45: -8404.42 | L45: -886.3792 | M45: 0 | N45: -1385.2335 | O45: -3479.4463 | P45: -5598.5964 | Q45: -65.04 | R45: -3.6516 | S45: =-3569.8446-0.8664 -> -3570.711 | T45: =-6336.7216-1.2283 -> -6337.9499 | U45: =-10084.8115-12.4081 -> -10097.22
A46: Increase in minority interest | B46: 28.941 | C46: 60.19 | D46: 87.6 | E46: 132.04 | F46: 106.05 | G46: 74.8466 | H46: 56.1234 | I46: 135.83 | J46: 198.96 | K46: 1201.66 | L46: 0 | M46: 0 | N46: 0 | O46: 0 | P46: 0 | Q46: 1906.8307 | R46: 1682.0946 | S46: 1581.5062 | T46: 1640.8585 | U46: 2913.7449
A47: Net cash generated from/to financing activities | B47: =SUM(B41:B46) -> 8865.134 | C47: =SUM(C41:C46) -> 7279.33 | D47: =SUM(D41:D46) -> 47894.08 | E47: =SUM(E41:E46) -> 6640.54 | F47: =SUM(F41:F46) -> 22341.25 | G47: =SUM(G41:G46) -> 24394.497 | H47: =SUM(H41:H46) -> -7321.3515 | I47: =SUM(I41:I46) -> 48124.02 | ... U47: =SUM(U41:U46) -> -9896.28
A49: Effect of exchange fluctuation translation reserve | B49: 173.5596 | C49: -92.81 | D49: 119.87 | E49: 343.48 | F49: 86.83 | G49: 213.9891 | H49: -141.8252 | I49: 165.1 | J49: 431.71 | K49: 104.94 | L49: 213.5244 | M49: -594.1251 | N49: -185.3998 | O49: 316.3063 | P49: 423.4435 | Q49: 2768.6427 | R49: 66.399 | S49: 966.2665 | T49: 3075.0546 | U49: 775.9581
A50: Net increase in cash and cash equivalents | B50: =B28+B38+B47+B49 -> 29795.466 | C50: =C28+C38+C47+C49 -> -34375.42 | D50: =D28+D38+D47+D49 -> 48919.15 | E50: =E28+E38+E47+E49 -> -3635.58 | F50: =F28+F38+F47+F49 -> 7785.25 | G50: =G28+G38+G47+G49 -> 6122.4694 | H50: =H28+H38+H47+H49 -> 33332.414 | I50: =I28+I38+I47+I49 -> 34113.21 | ... U50: =U28+U38+U47+U49 -> 8260.3938
A51: Cash and cash equivalents acquired on amalgamation | K51: 11181.71 | L51: 0 | M51: 0 | N51: 0 | O51: 0 | P51: 0 | Q51: 0
A52: Cash and cash equivalents at the beginning of the year | B52: 68004.308 | C52: =B53 -> 97799.774 | D52: =C53 -> 63424.354 | E52: =D53 -> 112343.5 | F52: =E53 -> 108707.92 | G52: 81817.642 | H52: =G53 -> 87940.112 | I52: =H53 -> 121272.53 | J52: =I53 -> 155385.74 | K52: =J53 -> 197147.82 | L52: 87390.895 | M52: 119155.74 | N52: 133128.25 | O52: 183125.98 | P52: =O53 -> 136456.49 | Q52: 225512.26 | R52: =Q53 -> 254315.26 | S52: =R53 -> 347707.04 | T52: =S53 -> 398905.12 | U52: =T53 -> 318311.91
A53: Cash and cash equivalents at the end of the year | B53: =B50+B52 -> 97799.774 | C53: =C50+C52 -> 63424.354 | D53: =D50+D52 -> 112343.5 | E53: =E50+E52 -> 108707.92 | F53: =F50+F52 -> 116493.17 | G53: =G50+G52 -> 87940.112 | H53: =H50+H52 -> 121272.53 | I53: =I50+I52 -> 155385.74 | J53: =J50+J52 -> 197147.82 | K53: =K50+K52+K51 -> 228834.52 | L53: =L50+L52+L51 -> 127852.92 | M53: =M50+M52+M51 -> 133228.25 | N53: =N50+N52+N51 -> 167822.36 | O53: =O50+O52+O51 -> 136456.49 | P53: =P50+P52+P51 -> 161998.04 | Q53: =Q50+Q52+Q51 -> 254315.26 | R53: =R50+R52+R51 -> 347707.04 | ... U53: =U50+U52+U51 -> 326572.3

Sheet Cash Flow Statement-NBFCs
A1: CASH FLOW STATEMENT
A2: Particulars | B2: #VALUE! | G2: #VALUE! | L2: #VALUE!
B3: 2020 | C3: 2021 | D3: 2022 | E3: 2023 | F3: 2024 | G3: 2020 | H3: 2021 | I3: 2022 | J3: 2023 | K3: 2024 | L3: 2020 | M3: 2021 | N3: 2022 | O3: 2023 | P3: 2024
A4: CASH FLOW FROM OPERATING ACTIVITIES
A5: Profit before tax | B5: 567.45 | C5: 613.18 | D5: 959.86 | E5: 1700.06 | F5: 2161.32 | G5: 7322.12 | H5: 5992.26 | I5: 9503.78 | J5: 15527.86 | K5: 19309.57 | L5: 42603.91 | M5: 51314.8 | N5: 54101.87 | O5: 49227.8 | P5: 59965.04
A6: Adjustments for:
A7: Interest income | B7: -2303.08 | C7: -2877.43 | D7: -3481.75 | E7: -5269.24 | F7: -7202.36 | G7: -22970.39 | H7: -23303.38 | I7: -27269.76 | J7: -35548.57 | K7: -48306.6 | L7: -474.33 | M7: -1154.55 | N7: -1799.91 | O7: -2665.79 | P7: -3369.08
A8: Depreciation and ammortization | B8: 23.14 | C8: 21.77 | D8: 25.76 | E8: 33.4 | F8: 39.6 | G8: 294.63 | H8: 325.27 | I8: 384.57 | J8: 485.38 | K8: 683.32 | L8: 592.42 | M8: 673.6 | N8: 700.03 | O8: 781.61 | P8: 921.06
A9: Impairment on financial instruments | B9: 124.33 | C9: 247.21 | D9: 181.07 | E9: 123.5 | F9: 60.88 | G9: 3929.48 | H9: 5968.58 | I9: 4803.4 | J9: 3189.65 | K9: 4630.7 | L9: 1870.8 | M9: 2552.15 | N9: 3835.21 | O9: 2420.07 | P9: 5538.21
A10: Finance costs | B10: 1616.03 | C10: 1965.87 | D10: 2155.31 | E10: 3211.32 | F10: 4692.61 | G10: 9473.21 | H10: 9414 | I10: 9748.24 | J10: 12559.89 | K10: 18724.69 | L10: 31728.4 | M10: 40999.29 | N10: 42558.52 | O10: 42091.78 | P10: 54300.78
A11: Dividend income | B11: 0 | C11: 0 | D11: 0 | E11: 0 | F11: 0 | G11: -0.64 | H11: 0 | I11: 0 | J11: -1.67 | K11: -7.64 | L11: -9.19 | M11: -0.13 | N11: -0.09 | O11: -9.41 | P11: -48.1
A12: Profit/loss on disposal of PPE (Fixed assets) | B12: 0.49 | C12: 0.44 | D12: 0.48 | E12: 0.7 | F12: 0.77 | G12: 2.29 | H12: 6.85 | I12: 24.84 | J12: 13.33 | K12: 12.54 | L12: -0.11 | M12: -7.19 | N12: -7.9 | O12: -2.39 | P12: -6.39
A13: Service fees for management of assigned portfolio of loans | B13: -129.81 | C13: -103.74 | D13: -112.53 | E13: -22.49 | F13: -37.11 | G13: -124.27 | H13: -157.53 | I13: -74.96 | J13: -38.18 | K13: -49.97 | L13: 0 | M13: 0 | N13: 0 | O13: 0 | P13: 0
A14: Share based payments to employees | B14: 7.05 | C14: 13.36 | D14: 19.23 | E14: 0 | F14: 0 | G14: 100.76 | H14: 124.75 | I14: 161.03 | J14: 224.41 | K14: 268.23 | L14: 31.03 | M14: 14.04 | N14: -1.98 | O14: 0 | P14: 0
A15: Provision for gratuity | L15: 176.21 | M15: 159.52 | N15: 172.74 | O15: 145.71 | P15: 161.02
A16: Provision for compensated absences | L16: 137.78 | M16: 17.52 | N16: -32.34 | O16: 31.16 | P16: -13.55
A17: Provision for refund of interest | L17: 0 | M17: 19 | N17: 4.55 | O17: 0 | P17: 0
A18: Profit/Loss on sale of mutual funds | L18: -707.46 | M18: -1618.18 | N18: -492.84 | O18: -716.5 | P18: -1022.58
A19: Unrealised gain on investments | L19: -31.03 | M19: -29.39 | N19: 4.1 | O19: 192.36 | P19: 388.78
A20: Provision for unspent expenditure on CSR | L20: 0 | M20: 120.49 | N20: 66.83 | O20: 0 | P20: 0
A21: Provision no longer required written back | B21: 0 | C21: 0 | D21: -0.05 | E21: 0 | F21: 0 | G21: 0 | H21: 0 | I21: 0 | J21: 0 | K21: 0 | L21: 0 | M21: 0 | N21: 0 | O21: 0 | P21: 0
A22: Gain/loss on sale of investment in subsidiary | B22: 0 | C22: 0 | D22: 0 | E22: 0 | F22: 0 | G22: 0 | H22: 0 | I22: 0 | J22: 0 | K22: 0 | L22: 0 | M22: 0 | N22: 0 | O22: 0 | P22: 0
A23: Income on derecognised (assigned) loans | B23: 0 | C23: 0 | D23: 0 | E23: -134.8 | F23: -53.08 | G23: 0 | H23: 0 | I23: 0 | J23: -23.17 | K23: -13.33 | L23: 0 | M23: 0 | N23: 0 | O23: 0 | P23: 0
A24: Net gain/loss on fair value changes | B24: -73.71 | C24: -59.85 | D24: -58.97 | E24: -112.04 | F24: -133.2 | G24: -537.49 | H24: -591.22 | I24: -327.74 | J24: -334.32 | K24: -308.29 | L24: 0 | M24: 0 | N24: 0 | O24: 0 | P24: 0
A26: Cash inflow from interest on loans | B26: 2286.61 | C26: 2840.61 | D26: 3476.05 | E26: 5040.5 | F26: 6886.57 | G26: 22903.15 | H26: 21342.24 | I26: 27605.27 | J26: 35032.84 | K26: 45853.53 | L26: 0 | M26: 0 | N26: 0 | O26: 0 | P26: 0
A27: Cash inflow form receivables on assignment of loans | B27: 0 | C27: 0 | D27: 0 | E27: 104.64 | F27: 102.72 | G27: 0 | H27: 0 | I27: 0 | J27: 0 | K27: 0 | L27: 0 | M27: 0 | N27: 0 | O27: 0 | P27: 0
A28: Cash inflow from service cost | B28: 16.53 | C28: 38.52 | D28: 57.13 | E28: 0 | F28: 0 | G28: 61.7 | H28: 73.65 | I28: 86.25 | J28: 106.59 | K28: 89.61 | L28: 0 | M28: 0 | N28: 0 | O28: 0 | P28: 0
A29: Cash outflow towards finance cost | B29: -1244.72 | C29: -1669.72 | D29: -2502.59 | E29: -3103.62 | F29: -4456.77 | G29: -8366.49 | H29: -9025.49 | I29: -8961.18 | J29: -13107.38 | K29: -17044.04 | L29: 0 | M29: 0 | N29: 0 | O29: 0 | P29: 0
A30: Cash generated from/used operations before working capital changes | B30: =SUM(B5,B7:B29) -> 890.31 | C30: =SUM(C5,C7:C29) -> 1030.22 | D30: =SUM(D5,D7:D29) -> 719 | E30: =SUM(E5,E7:E29) -> 1571.93 | F30: =SUM(F5,F7:F29) -> 2061.95 | G30: =SUM(G5,G7:G29) -> 12088.06 | H30: =SUM(H5,H7:H29) -> 10169.98 | I30: =SUM(I5,I7:I29) -> 15683.74 | ... P30: =SUM(P5,P7:P29) -> 116815.19
A32: Working capital changes
A33: Increase/decrease in bank balances other than cash | B33: 0 | C33: 0 | D33: 0 | E33: -14.85 | F33: 14.84 | G33: 0 | H33: 0 | J33: -2413.16 | K33: -3589.13 | L33: -980.66 | M33: 523.91 | N33: -356.63 | O33: 136.22 | P33: 307.81
A34: Increase/decrease in trade receivables | B34: -1.81 | C34: -1.97 | D34: 3.73 | E34: 0.27 | F34: -11.81 | G34: -118.55 | H34: 45.95 | I34: -320.93 | J34: -93.43 | K34: -457.54 | L34: 126.93 | M34: -8.2 | N34: 27.93 | O34: -28.86 | P34: -79.41
A35: Increase/decrease in other receivables | B35: 0 | C35: 0 | D35: 0 | E35: -0.35 | F35: 0.36 | G35: 0 | H35: 0 | I35: 0 | J35: 0 | K35: 0 | L35: 0 | M35: 0 | N35: 0 | O35: 0 | P35: 0
A36: Increase in loans | B36: -10763.52 | C36: -5698.5 | D36: -13256.65 | E36: -15584.98 | F36: -17047.27 | G36: -32880.54 | H36: -9573.87 | I36: -50246.38 | J36: -54412.09 | K36: -88187.48 | L36: -83860.48 | M36: -120849.04 | N36: -61195.18 | O36: -59869.49 | P36: -179256.51
A37: Decrease in other financial assets | B37: -0.05 | C37: -275.64 | D37: 265.4 | E37: 3.96 | F37: 4.01 | G37: -116.97 | H37: -337.54 | I37: -175.97 | J37: 87.83 | K37: -306.33 | L37: -651.89 | M37: -1134.17 | N37: 775.58 | O37: -723.3 | P37: -681.02
A38: Increase/decrease in other non financial assets | B38: -3.25 | C38: -8.59 | D38: 3.32 | E38: 1.55 | F38: -1 | G38: -49.84 | H38: -11.13 | I38: -23.48 | J38: 47.17 | K38: -33.6 | L38: -169.73 | M38: -160.87 | N38: 91.13 | O38: 28.64 | P38: -136.05
A39: Increase/decrease in derivative financial instruments (net) | J39: 8.75 | K39: -24.86 | L39: 0 | M39: 0 | N39: 0 | O39: 0 | P39: 0
A40: Increase in trade payables | B40: 14.53 | C40: -9.69 | D40: 15.56 | E40: 9.52 | F40: 11.68 | G40: 198.19 | H40: 122.31 | I40: 286.12 | J40: 292.93 | K40: 611.91 | L40: 556.23 | M40: -145.56 | N40: -540.19 | O40: 116.42 | P40: 510.48
A41: Increase in other payables | B41: -11.27 | C41: 3.45 | D41: 16.89 | E41: 34.87 | F41: 9.71 | G41: -49.9 | H41: 15.98 | I41: 127.95 | J41: 285.69 | K41: 125.26 | L41: 0 | M41: 0 | N41: 0 | O41: 457.11 | P41: 161.06
A42: Increase in other financial liabilities | B42: -257.5 | C42: 80.79 | D42: 14.95 | E42: 33.16 | F42: 25.23 | G42: -1313.27 | H42: 206.36 | I42: 89.52 | J42: 75.3 | K42: 125.33 | L42: -97.06 | M42: -148.43 | N42: 113.95 | O42: 1563.16 | P42: 378.94
A43: Increase in provisions | B43: -4.72 | C43: 1.28 | D43: 1.12 | E43: 17.12 | F43: 18.08 | G43: -24.17 | H43: 25 | I43: 22.7 | J43: 75.83 | K43: 89.81 | L43: -262.28 | M43: -248.32 | N43: -888.3 | O43: -3011.4 | P43: -1995.56
A44: Increase/decrease in other non financial liabilities | B44: 23.26 | C44: -17.08 | D44: -2.27 | E44: -5.39 | F44: 12.47 | G44: 76.16 | H44: 12 | I44: 114.21 | J44: -181.09 | K44: 142.16 | L44: 87.94 | M44: 51.1 | N44: 627.55 | O44: -465.63 | P44: 355.76
B45: =SUM(B30,B33:B44) -> -10114.02 | C45: =SUM(C30,C33:C44) -> -4895.73 | D45: =SUM(D30,D33:D44) -> -12218.95 | E45: =SUM(E30,E33:E44) -> -13933.19 | F45: =SUM(F30,F33:F44) -> -14901.75 | G45: =SUM(G30,G33:G44) -> -22190.83 | H45: =SUM(H30,H33:H44) -> 675.04 | I45: =SUM(I30,I33:I44) -> -34442.52 | ... P45: =SUM(P30,P33:P44) -> -63619.31
A46: Finance cost paid | L46: -29758.83 | M46: -36211.41 | N46: -39706.33 | O46: -44521.97 | P46: -57593.09
A47: Income tax paid | B47: -128.13 | C47: -180.04 | D47: -242.35 | E47: -398.58 | F47: -526.36 | G47: -2235.35 | H47: -1482.31 | I47: -2586.1 | J47: -3972.18 | K47: -5097.99 | L47: -10660.38 | M47: -12872.87 | N47: -14022.79 | O47: -13217.97 | P47: -16327.78
A48: Net cash generated from/used in operating activities | B48: =B45+B47 -> -10242.15 | C48: =C45+C47 -> -5075.77 | D48: =D45+D47 -> -12461.3 | E48: =E45+E47 -> -14331.77 | F48: =F45+F47 -> -15428.11 | G48: =G45+G47 -> -24426.18 | H48: =H45+H47 -> -807.27 | I48: =I45+I47 -> -37028.62 | ... K48: =K45+K47 -> -72760.14 | L48: =L45+L47+L46 -> -49751.78 | M48: =M45+M47+M46 -> -78142.89 | N48: =N45+N47+N46 -> -15964.49 | O48: =O45+O47+O46 -> -28040.67 | P48: =P45+P47+P46 -> -137540.18
A50: CASH FLOW FROM INVESTING ACTIVITIES
A51: Purchase of property, plant and equipment (fixed assets) | B51: -24.7 | C51: -6.6 | D51: -18.41 | E51: -20.37 | F51: -25.62 | G51: -396.76 | H51: -138.73 | I51: -375.55 | J51: -485.88 | K51: -603.62 | L51: -931.18 | M51: -914.8 | N51: -970.59 | O51: -1411.43 | P51: -2224.24
A52: Sale of PPE (Fixed assets) | B52: 1.12 | C52: 1.51 | D52: 1.63 | E52: 3.87 | F52: 3.3 | G52: 7.21 | H52: 11.39 | I52: 19.14 | J52: 19.81 | K52: 38.89 | L52: 4.44 | M52: 17.08 | N52: 24.11 | O52: 13.99 | P52: 19.08
A53: Purchase of intangible assets and intangibles assets under development | B53: -2.92 | C53: -8.43 | D53: -10.71 | E53: -13.43 | F53: -17.38 | G53: -110.38 | H53: -170.76 | I53: -258.62 | J53: -392.44 | K53: -434.16 | L53: 0 | M53: 0 | N53: 0 | O53: 0 | P53: 0
A54: Increase/decrease in investment property | L54: -2.28 | M54: 8.65 | N54: 4.4 | O54: 8.74 | P54: -0.38
A55: Increase/decrease in investment in mutual funds (net) | L55: -3288.54 | M55: 5343.78 | N55: -8.9 | O55: 1624.4 | P55: 1022.58
A56: Investments in quoted equity shares | L56: -249.39 | M56: 0 | N56: 0 | O56: 0 | P56: -338.35
A57: Investments in unquoted equity shares | L57: -241.78 | M57: 0 | N57: 0 | O57: 0 | P57: 0
A58: Acquisition of shares in subsidiaries | L58: 0 | M58: 0 | N58: 0 | O58: 0 | P58: 0
A59: Purchase of investments measured under FVTPL | B59: -55545.26 | C59: -314.45 | D59: 1698.08 | E59: -43035.86 | F59: -36567.55 | G59: -442958.18 | H59: -234606.53 | I59: -223245.35 | J59: -296988.97 | K59: -111040.08 | L59: 0 | M59: 0 | N59: 0 | O59: 0 | P59: 0
A60: Sale of investments measured under FVTPL | B60: 54866.91 | C60: 0 | D60: 0 | E60: 42408.09 | F60: 37300.89 | G60: 436102.25 | H60: 236150.89 | I60: 235384.89 | J60: 292353.31 | K60: 113012.92 | L60: 0 | M60: 0 | N60: 0 | O60: 0 | P60: 0
A61: Purchase of investments measured under ammortized cost | C61: -3475 | D61: -4900 | E61: 0 | F61: -6139.67 | G61: 0 | H61: -3975 | I61: -14366.94 | J61: -148.72 | K61: -6429.43 | L61: 323.18 | M61: -5159.07 | N61: 3410.95 | O61: -1160.39 | P61: -374.06
A62: Sale of investments measured under ammortized cost | B62: 0 | C62: 2975 | D62: 5400 | E62: 0 | F62: 6139.67 | G62: 33.39 | H62: 2995.32 | I62: 10279.41 | J62: 5107.14 | K62: 6201.62 | L62: 0 | M62: 0 | N62: 0 | O62: 0 | P62: 0
A63: Purchase of equity investments designated under FVOCI | B63: 0 | C63: 0 | D63: 0 | E63: 0 | F63: 0 | G63: -150 | H63: 0 | I63: -283.16 | J63: 0 | K63: -514.96 | L63: 0 | M63: 0 | N63: 0 | O63: 0 | P63: 0
A64: Increase/decrease in investments in secuirty reciepts (net) | L64: 0 | M64: 0 | N64: 0 | O64: 0 | P64: -1144.77
A65: Proceeds from sale of investments under FVOCI | B65: 0 | C65: 0 | D65: 0 | E65: 0 | F65: 0 | G65: 826.09 | H65: 2082.54 | I65: 2083.84 | J65: 10900.36 | K65: 15231.8 | L65: 0 | M65: 0 | N65: 0 | O65: 0 | P65: 0
A66: Dividend received | B66: 0 | C66: 0 | D66: 0 | E66: 0 | F66: 0 | G66: 0.64 | H66: 0 | I66: 0 | L66: 9.19 | M66: 0.13 | N66: 0.09 | O66: 9.41 | P66: 48.1
A67: Purchase of investments measured under FVOCI | B67: 0 | C67: 0 | D67: 0 | E67: 0 | F67: -514.96 | G67: -2246.45 | H67: -3004.37 | I67: -3291.4 | J67: -21272.49 | K67: -23310.68 | L67: 0 | M67: 0 | N67: 0 | O67: 0 | P67: 0
A68: Investment in associates | J68: -92.74 | K68: -267.47 | L68: 0 | M68: 0 | N68: 0 | O68: 0 | P68: 0
A69: Interest received on investments | B69: 12.02 | C69: 30.93 | D69: 26.73 | E69: 46.26 | F69: 94.63 | G69: 135.31 | H69: 226.7 | I69: 400.58 | J69: 606.71 | K69: 943.99 | L69: 460.74 | M69: 1100.04 | N69: 1756.33 | O69: 2724.95 | P69: 3445.63
A70: Net cash generated from/used in investing activities | B70: =SUM(B51:B69) -> -692.83 | C70: =SUM(C51:C69) -> -797.04 | D70: =SUM(D51:D69) -> 2197.32 | E70: =SUM(E51:E69) -> -611.44 | F70: =SUM(F51:F69) -> 273.31 | G70: =SUM(G51:G69) -> -8756.88 | H70: =SUM(H51:H69) -> -428.55 | I70: =SUM(I51:I69) -> 6346.84 | ... P70: =SUM(P51:P69) -> 453.59
A72: CASH FLOW FROM FINANCING ACTIVITIES
A73: Issue of equity share capital (including securities premium) | B73: 1500 | C73: 0 | D73: 0 | E73: 2499.88 | F73: 0 | G73: 8568.04 | H73: 103.21 | I73: 172.9 | J73: 158.12 | K73: 9067.17 | L73: 18.76 | M73: 7.92 | N73: 7.47 | O73: 5.15 | P73: 0.64
A74: Proceeds from issue of subsidiary shares to non controlling interest | L74: 0 | M74: 0 | N74: 2276.29 | O74: 1050 | P74: -530
A75: Issue of share warrants | G75: 0 | H75: 0 | I75: 0 | J75: 0 | K75: 297.21 | L75: 0 | M75: 0 | N75: 0 | O75: 0 | P75: 0
A76: Payment to holding on account of recharge liability | B76: 0 | C76: -20.41 | D76: -19.23 | E76: 0 | F76: 0 | G76: 0 | H76: 0 | I76: 0 | J76: 0 | K76: 0 | L76: 0 | M76: 0 | N76: 0 | O76: 0 | P76: 0
A77: Dividend paid | G77: -943.28 | H77: -2.74 | I77: -602.63 | J77: -1206.86 | K77: -1814.58 | L77: -13055.28 | M77: -6.75 | N77: -8027.3 | O77: -8032.06 | P77: -8844.39
A78: Increase/decrease in subordinated liabilities | L78: -1347.69 | M78: -297.6 | N78: -732.83 | O78: -459.47 | P78: 783.6
A79: Dividend distribution tax | G79: -195.2 | H79: 0 | I79: 0 | J79: 0 | K79: 0 | L79: 0 | M79: 0 | N79: 0 | O79: 0 | P79: 0
A80: Share issue expense | G80: -45.06 | H80: 0 | I80: 0 | J80: -0.12 | K80: -34.55 | L80: 0 | M80: 0 | N80: 0 | O80: 0 | P80: 0
A81: Proceeds from long term borrowings | C81: 7302.31 | D81: 15597.4 | E81: 26657.22 | F81: 23987.12 | G81: 0 | H81: -2338.69 | I81: 41178.35 | J81: 66860.38 | K81: 72666.31 | L81: 0 | M81: 0 | N81: 0 | O81: 0 | P81: 0
A82: Repayments towards long term borrowings | C82: -3026.88 | D82: -6923.39 | E82: -10737.42 | F82: -11817.87 | G82: 0 | H82: -3255.6 | I82: -17889.57 | J82: -36473.64 | K82: -34375.91 | L82: 0 | M82: 0 | N82: 0 | O82: 0 | P82: 0
A83: Debt securities issued (net) | B83: -178.78 | C83: 0 | D83: 0 | E83: 0 | F83: 0 | G83: 1972.98 | H83: 0 | I83: 0 | J83: 0 | K83: 0 | L83: 20541.65 | M83: 43962.63 | N83: -14991.44 | O83: 14225.96 | P83: 28746.08
A84: Borrowings othe than debt securities issued (net) | B84: 10174.58 | C84: 0 | D84: 0 | E84: 0 | F84: 0 | G84: 16906.34 | H84: 0 | I84: 0 | J84: 0 | K84: 0 | L84: 85817.99 | M84: 53374.48 | N84: 55565.48 | O84: -3896.22 | P84: 99173.53
A85: Short term borrowings (net) | B85: 0 | C85: 1428.58 | D85: 1054.99 | E85: -3435.11 | F85: 2961.33 | G85: 0 | H85: 3148.54 | I85: 4702.39 | J85: 7923.66 | K85: 22023.5 | L85: 0 | M85: 0 | N85: 0 | O85: 0 | P85: 0
A86: Deposits (other than public deposits) (net) | B86: 0 | C86: 0 | D86: 510 | E86: -340.68 | F86: 8.05 | G86: 7987.86 | H86: 4172.75 | I86: 4784.07 | J86: 13556.92 | K86: 14759.93 | L86: -12.48 | M86: 157.58 | N86: 432.27 | O86: 1143.57 | P86: 335.71
A87: Payment of lease liability | B87: -9.08 | C87: -7.73 | D87: -10.54 | E87: -13.83 | F87: -13.85 | G87: -71.12 | H87: -86.84 | I87: -105.89 | J87: -143.45 | K87: -174 | L87: 0 | M87: -74.04 | N87: -75.05 | O87: -86.74 | P87: -89.23
A88: Net cash generated from/used financial activities | B88: =SUM(B73:B87) -> 11486.72 | C88: =SUM(C73:C87) -> 5675.87 | D88: =SUM(D73:D87) -> 10209.23 | E88: =SUM(E73:E87) -> 14630.06 | F88: =SUM(F73:F87) -> 15124.78 | G88: =SUM(G73:G87) -> 34180.56 | H88: =SUM(H73:H87) -> 1740.63 | I88: =SUM(I73:I87) -> 32239.62 | ... P88: =SUM(P73:P87) -> 119575.94
A90: Net increase/decrease in cash and cash equivalents | B90: =B48+B70+B88 -> 551.74 | C90: =C48+C70+C88 -> -196.94 | D90: =D48+D70+D88 -> -54.75 | E90: =E48+E70+E88 -> -313.15 | F90: =F48+F70+F88 -> -30.02 | G90: =G48+G70+G88 -> 997.5 | H90: =H48+H70+H88 -> 504.81 | I90: =I48+I70+I88 -> 1557.84 | ... P90: =P48+P70+P88 -> -17510.65
A91: Net foreign exchange difference | L91: -4.52 | M91: -29.46 | N91: -111.38 | O91: -10.3 | P91: 23.13
A92: Cash and cash equivalents acquired on acquisition of subsidiary | L92: 0 | M92: 0 | N92: 0 | O92: 0 | P92: 0
A93: Cash and cash equivalents at the beginning of the year | B93: 106.98 | C93: =B94 -> 658.72 | D93: =C94 -> 461.78 | E93: =D94 -> 407.03 | F93: =E94 -> 93.88 | G93: 347.02 | H93: =G94 -> 1344.52 | I93: =H94 -> 1849.33 | J93: =I94 -> 3407.17 | K93: =J94 -> 1576.48 | L93: 20056.62 | M93: =L94 -> 58347.65 | N93: =M94 -> 77695.33 | O93: =N94 -> 100290.74 | P93: =O94 -> 77999.63
A94: Cash and cash equivalents at the end of the year | B94: =B90+B93 -> 658.72 | C94: =C90+C93 -> 461.78 | D94: =D90+D93 -> 407.03 | E94: =E90+E93 -> 93.88 | F94: =F90+F93 -> 63.86 | G94: =G90+G93 -> 1344.52 | H94: =H90+H93 -> 1849.33 | I94: =I90+I93 -> 3407.17 | ... K94: =K90+K93 -> 4060.24 | L94: =L90+L93+L91+L92 -> 58347.65 | M94: =M90+M93+M91+M92 -> 77695.33 | N94: =N90+N93+N91+N92 -> 100290.74 | O94: =O90+O93+O91+O92 -> 77999.63 | P94: =P90+P93+P91+P92 -> 60512.11

Sheet Financial Ratios-Banks
A1: FINANCIAL RATIOS
A2: Particulars | B2: #VALUE! | H2: #VALUE! | N2: #VALUE! | T2: #VALUE!
B3: 2020 | C3: 2021 | D3: 2022 | E3: 2023 | F3: 2024 | G3: Average | H3: 2020 | I3: 2021 | J3: 2022 | K3: 2023 | L3: 2024 | M3: Average | N3: 2020 | O3: 2021 | P3: 2022 | Q3: 2023 | R3: 2024 | S3: Average | T3: 2020 | U3: 2021 | V3: 2022 | W3: 2023 | X3: 2024 | Y3: Average
A4: Profitability Ratios
A5: Net Interest Margin | B5: =('Income Statement-Banks'!B5-'Income Statement-Banks'!B9)/('Balance Sheet-Banks'!B62+'Balance Sheet-Banks'!B75) -> 0.034839247 | C5: =('Income Statement-Banks'!C5-'Income Statement-Banks'!C9)/('Balance Sheet-Banks'!C62+'Balance Sheet-Banks'!C75) -> 0.034978829 | D5: =('Income Statement-Banks'!D5-'Income Statement-Banks'!D9)/('Balance Sheet-Banks'!D62+'Balance Sheet-Banks'!D75) -> 0.033932439 | E5: =('Income Statement-Banks'!E5-'Income Statement-Banks'!E9)/('Balance Sheet-Banks'!E62+'Balance Sheet-Banks'!E75) -> 0.038097615 | F5: =('Income Statement-Banks'!F5-'Income Statement-Banks'!F9)/('Balance Sheet-Banks'!F62+'Balance Sheet-Banks'!F75) -> 0.038573855 | G5: =AVERAGE(B5:F5) -> 0.036084397 | H5: =('Income Statement-Banks'!G5-'Income Statement-Banks'!G9)/('Balance Sheet-Banks'!G62+'Balance Sheet-Banks'!G75) -> 0.041907401 | I5: =('Income Statement-Banks'!H5-'Income Statement-Banks'!H9)/('Balance Sheet-Banks'!H62+'Balance Sheet-Banks'!H75) -> 0.042672577 | J5: =('Income Statement-Banks'!I5-'Income Statement-Banks'!I9)/('Balance Sheet-Banks'!I62+'Balance Sheet-Banks'!I75) -> 0.041360189 | K5: =('Income Statement-Banks'!J5-'Income Statement-Banks'!J9)/('Balance Sheet-Banks'!J62+'Balance Sheet-Banks'!J75) -> 0.042775608 | L5: =('Income Statement-Banks'!K5-'Income Statement-Banks'!K9)/('Balance Sheet-Banks'!K62+'Balance Sheet-Banks'!K75) -> 0.036261465 | M5: =AVERAGE(H5:L5) -> 0.040995448 | N5: =('Income Statement-Banks'!L5-'Income Statement-Banks'!L9)/('Balance Sheet-Banks'!L62+'Balance Sheet-Banks'!L75) -> 0.0349392 | O5: =('Income Statement-Banks'!M5-'Income Statement-Banks'!M9)/('Balance Sheet-Banks'!M62+'Balance Sheet-Banks'!M75) -> 0.038412647 | P5: =('Income Statement-Banks'!N5-'Income Statement-Banks'!N9)/('Balance Sheet-Banks'!N62+'Balance Sheet-Banks'!N75) -> 0.04059494 | Q5: =('Income Statement-Banks'!O5-'Income Statement-Banks'!O9)/('Balance Sheet-Banks'!O62+'Balance Sheet-Banks'!O75) -> 0.040920667 | R5: =('Income Statement-Banks'!P5-'Income Statement-Banks'!P9)/('Balance Sheet-Banks'!P62+'Balance Sheet-Banks'!P75) -> 0.040905303 | S5: =AVERAGE(N5:R5) -> 0.039154551 | T5: =('Income Statement-Banks'!Q5-'Income Statement-Banks'!Q9)/('Balance Sheet-Banks'!Q62+'Balance Sheet-Banks'!Q75) -> 0.030180423 | U5: =('Income Statement-Banks'!R5-'Income Statement-Banks'!R9)/('Balance Sheet-Banks'!R62+'Balance Sheet-Banks'!R75) -> 0.029813056 | V5: =('Income Statement-Banks'!S5-'Income Statement-Banks'!S9)/('Balance Sheet-Banks'!S62+'Balance Sheet-Banks'!S75) -> 0.029269536 | W5: =('Income Statement-Banks'!T5-'Income Statement-Banks'!T9)/('Balance Sheet-Banks'!T62+'Balance Sheet-Banks'!T75) -> 0.031048727 | X5: =('Income Statement-Banks'!U5-'Income Statement-Banks'!U9)/('Balance Sheet-Banks'!U62+'Balance Sheet-Banks'!U75) -> 0.030442395 | Y5: =AVERAGE(T5:X5) -> 0.030150827
A6: Return on Assets | B6: ='Income Statement-Banks'!D13/'Balance Sheet-Banks'!D79 -> 0.011847773 | C6: ='Income Statement-Banks'!E13/'Balance Sheet-Banks'!E79 -> 0.0080723855 | D6: ='Income Statement-Banks'!F13/'Balance Sheet-Banks'!F79 -> 0.017404077 | E6: ='Income Statement-Banks'!G13/'Balance Sheet-Banks'!G79 -> 0.017267152 | F6: ='Income Statement-Banks'!H13/'Balance Sheet-Banks'!H79 -> 0.017703058 | G6: =AVERAGE(B6:F6) -> 0.014458889 | H6: ='Income Statement-Banks'!I13/'Balance Sheet-Banks'!I79 -> 0.017972094 | I6: ='Income Statement-Banks'!J13/'Balance Sheet-Banks'!J79 -> 0.018238548 | J6: ='Income Statement-Banks'!K13/'Balance Sheet-Banks'!K79 -> 0.016239044 | K6: ='Income Statement-Banks'!L13/'Balance Sheet-Banks'!L79 -> 0.00815039 | L6: ='Income Statement-Banks'!M13/'Balance Sheet-Banks'!M79 -> 0.013160156 | M6: =AVERAGE(H6:L6) -> 0.014752046 | N6: ='Income Statement-Banks'!N13/'Balance Sheet-Banks'!N79 -> 0.016537611 | O6: ='Income Statement-Banks'!O13/'Balance Sheet-Banks'!O79 -> 0.017596731 | P6: ='Income Statement-Banks'!P13/'Balance Sheet-Banks'!P79 -> 0.01903788 | Q6: ='Income Statement-Banks'!Q13/'Balance Sheet-Banks'!Q79 -> 0.0043304005 | R6: ='Income Statement-Banks'!R13/'Balance Sheet-Banks'!R79 -> 0.0050106544 | S6: =AVERAGE(N6:R6) -> 0.012502655 | T6: ='Income Statement-Banks'!S13/'Balance Sheet-Banks'!S79 -> 0.0067817501 | U6: ='Income Statement-Banks'!T13/'Balance Sheet-Banks'!T79 -> 0.0094985652 | V6: ='Income Statement-Banks'!U13/'Balance Sheet-Banks'!U79 -> 0.010118874 | W6: ='Income Statement-Banks'!T13/'Balance Sheet-Banks'!T79 -> 0.0094985652 | X6: ='Income Statement-Banks'!U13/'Balance Sheet-Banks'!U79 -> 0.010118874 | Y6: =AVERAGE(T6:X6) -> 0.0092033258
A7: Return on Equity | B7: ='Income Statement-Banks'!B13/'Balance Sheet-Banks'!B9 -> 0.021731233 | C7: ='Income Statement-Banks'!C13/'Balance Sheet-Banks'!C9 -> 0.069890799 | D7: ='Income Statement-Banks'!D13/'Balance Sheet-Banks'!D9 -> 0.11950818 | E7: ='Income Statement-Banks'!E13/'Balance Sheet-Banks'!E9 -> 0.083369707 | F7: ='Income Statement-Banks'!F13/'Balance Sheet-Banks'!F9 -> 0.16774405 | G7: =AVERAGE(B7:F7) -> 0.092448795 | H7: ='Income Statement-Banks'!G13/'Balance Sheet-Banks'!G9 -> 0.15427255 | I7: ='Income Statement-Banks'!H13/'Balance Sheet-Banks'!H9 -> 0.1513796 | J7: ='Income Statement-Banks'!I13/'Balance Sheet-Banks'!I9 -> 0.15380539 | K7: ='Income Statement-Banks'!J13/'Balance Sheet-Banks'!J9 -> 0.15897022 | L7: ='Income Statement-Banks'!K13/'Balance Sheet-Banks'!K9 -> 0.13931348 | M7: =AVERAGE(H7:L7) -> 0.15154825 | N7: ='Income Statement-Banks'!L13/'Balance Sheet-Banks'!L9 -> 0.086512931 | O7: ='Income Statement-Banks'!M13/'Balance Sheet-Banks'!M9 -> 0.10977408 | P7: ='Income Statement-Banks'!N13/'Balance Sheet-Banks'!N9 -> 0.13687891 | Q7: ='Income Statement-Banks'!O13/'Balance Sheet-Banks'!O9 -> 0.15581121 | R7: ='Income Statement-Banks'!P13/'Balance Sheet-Banks'!P9 -> 0.16667176 | S7: =AVERAGE(N7:R7) -> 0.13112978 | T7: ='Income Statement-Banks'!Q13/'Balance Sheet-Banks'!Q9 -> 0.070179713 | U7: ='Income Statement-Banks'!R13/'Balance Sheet-Banks'!R9 -> 0.085135999 | V7: ='Income Statement-Banks'!S13/'Balance Sheet-Banks'!S9 -> 0.11476229 | W7: ='Income Statement-Banks'!T13/'Balance Sheet-Banks'!T9 -> 0.1521337 | X7: ='Income Statement-Banks'!U13/'Balance Sheet-Banks'!U9 -> 0.15825603 | Y7: =AVERAGE(T7:X7) -> 0.11609355
A8: Cost to Income ratio | B8: =('Income Statement-Banks'!B10/'Income Statement-Banks'!B7) -> 0.22565931 | C8: =('Income Statement-Banks'!C10/'Income Statement-Banks'!C7) -> 0.24591288 | D8: =('Income Statement-Banks'!D10/'Income Statement-Banks'!D7) -> 0.28827107 | E8: =('Income Statement-Banks'!E10/'Income Statement-Banks'!E7) -> 0.38630116 | F8: =('Income Statement-Banks'!F10/'Income Statement-Banks'!F7) -> 0.26989436 | G8: =AVERAGE(B8:F8) -> 0.28320776 | H8: =('Income Statement-Banks'!G10/'Income Statement-Banks'!G7) -> 0.22463075 | I8: =('Income Statement-Banks'!H10/'Income Statement-Banks'!H7) -> 0.22453216 | J8: =('Income Statement-Banks'!I10/'Income Statement-Banks'!I7) -> 0.24039079 | K8: =('Income Statement-Banks'!J10/'Income Statement-Banks'!J7) -> 0.25179397 | L8: =('Income Statement-Banks'!K10/'Income Statement-Banks'!K7) -> 0.37321395 | M8: =AVERAGE(H8:L8) -> 0.26291232 | N8: =('Income Statement-Banks'!L10/'Income Statement-Banks'!L7) -> 0.47746685 | O8: =('Income Statement-Banks'!M10/'Income Statement-Banks'!M7) -> 0.21981382 | P8: =('Income Statement-Banks'!N10/'Income Statement-Banks'!N7) -> 0.25486497 | Q8: =('Income Statement-Banks'!O10/'Income Statement-Banks'!O7) -> 0.4427949 | R8: =('Income Statement-Banks'!P10/'Income Statement-Banks'!P7) -> 0.41426764 | S8: =AVERAGE(N8:R8) -> 0.36184164 | T8: =('Income Statement-Banks'!Q10/'Income Statement-Banks'!Q7) -> 0.35809171 | U8: =('Income Statement-Banks'!R10/'Income Statement-Banks'!R7) -> 0.39038361 | V8: =('Income Statement-Banks'!S10/'Income Statement-Banks'!S7) -> 0.42843969 | W8: =('Income Statement-Banks'!T10/'Income Statement-Banks'!T7) -> 0.40097856 | X8: =('Income Statement-Banks'!U10/'Income Statement-Banks'!U7) -> 0.39674369 | Y8: =AVERAGE(T8:X8) -> 0.39492745
A9: Operating profit margin | B9: =('Income Statement-Banks'!B7-'Income Statement-Banks'!B10)/'Income Statement-Banks'!B7 -> 0.77434069 | C9: =('Income Statement-Banks'!C7-'Income Statement-Banks'!C10)/'Income Statement-Banks'!C7 -> 0.75408712 | D9: =('Income Statement-Banks'!D7-'Income Statement-Banks'!D10)/'Income Statement-Banks'!D7 -> 0.71172893 | E9: =('Income Statement-Banks'!E7-'Income Statement-Banks'!E10)/'Income Statement-Banks'!E7 -> 0.61369884 | F9: =('Income Statement-Banks'!F7-'Income Statement-Banks'!F10)/'Income Statement-Banks'!F7 -> 0.73010564 | G9: =AVERAGE(B9:F9) -> 0.71679224 | H9: =('Income Statement-Banks'!G7-'Income Statement-Banks'!G10)/'Income Statement-Banks'!G7 -> 0.77536925 | I9: =('Income Statement-Banks'!H7-'Income Statement-Banks'!H10)/'Income Statement-Banks'!H7 -> 0.77546784 | J9: =('Income Statement-Banks'!I7-'Income Statement-Banks'!I10)/'Income Statement-Banks'!I7 -> 0.75960921 | K9: =('Income Statement-Banks'!J7-'Income Statement-Banks'!J10)/'Income Statement-Banks'!J7 -> 0.74820603 | L9: =('Income Statement-Banks'!K7-'Income Statement-Banks'!K10)/'Income Statement-Banks'!K7 -> 0.62678605 | M9: =AVERAGE(H9:L9) -> 0.73708768 | N9: =('Income Statement-Banks'!L7-'Income Statement-Banks'!L10)/'Income Statement-Banks'!L7 -> 0.52253315 | O9: =('Income Statement-Banks'!M7-'Income Statement-Banks'!M10)/'Income Statement-Banks'!M7 -> 0.78018618 | P9: =('Income Statement-Banks'!N7-'Income Statement-Banks'!N10)/'Income Statement-Banks'!N7 -> 0.74513503 | Q9: =('Income Statement-Banks'!O7-'Income Statement-Banks'!O10)/'Income Statement-Banks'!O7 -> 0.5572051 | R9: =('Income Statement-Banks'!P7-'Income Statement-Banks'!P10)/'Income Statement-Banks'!P7 -> 0.58573236 | S9: =AVERAGE(N9:R9) -> 0.63815836 | T9: =('Income Statement-Banks'!Q7-'Income Statement-Banks'!Q10)/'Income Statement-Banks'!Q7 -> 0.64190829 | U9: =('Income Statement-Banks'!R7-'Income Statement-Banks'!R10)/'Income Statement-Banks'!R7 -> 0.60961639 | V9: =('Income Statement-Banks'!S7-'Income Statement-Banks'!S10)/'Income Statement-Banks'!S7 -> 0.57156031 | W9: =('Income Statement-Banks'!T7-'Income Statement-Banks'!T10)/'Income Statement-Banks'!T7 -> 0.59902144 | X9: =('Income Statement-Banks'!U7-'Income Statement-Banks'!U10)/'Income Statement-Banks'!U7 -> 0.60325631 | Y9: =AVERAGE(T9:X9) -> 0.60507255
A10: Net Profit Margin | B10: ='Income Statement-Banks'!B13/'Income Statement-Banks'!B7 -> 0.023467475 | C10: ='Income Statement-Banks'!C13/'Income Statement-Banks'!C7 -> 0.093010028 | D10: ='Income Statement-Banks'!D13/'Income Statement-Banks'!D7 -> 0.16448334 | E10: ='Income Statement-Banks'!E13/'Income Statement-Banks'!E7 -> 0.10257974 | F10: ='Income Statement-Banks'!F13/'Income Statement-Banks'!F7 -> 0.19148969 | G10: =AVERAGE(B10:F10) -> 0.11500606 | H10: ='Income Statement-Banks'!G13/'Income Statement-Banks'!G7 -> 0.18560269 | I10: ='Income Statement-Banks'!H13/'Income Statement-Banks'!H7 -> 0.20436034 | J10: ='Income Statement-Banks'!I13/'Income Statement-Banks'!I7 -> 0.22750117 | K10: ='Income Statement-Banks'!J13/'Income Statement-Banks'!J7 -> 0.22548287 | L10: ='Income Statement-Banks'!K13/'Income Statement-Banks'!K7 -> 0.16041014 | M10: =AVERAGE(H10:L10) -> 0.20067144 | N10: ='Income Statement-Banks'!L13/'Income Statement-Banks'!L7 -> 0.074943321 | O10: ='Income Statement-Banks'!M13/'Income Statement-Banks'!M7 -> 0.16508525 | P10: ='Income Statement-Banks'!N13/'Income Statement-Banks'!N7 -> 0.22250957 | Q10: ='Income Statement-Banks'!O13/'Income Statement-Banks'!O7 -> 0.18510715 | R10: ='Income Statement-Banks'!P13/'Income Statement-Banks'!P7 -> 0.19067606 | S10: =AVERAGE(N10:R10) -> 0.16766427 | T10: ='Income Statement-Banks'!Q13/'Income Statement-Banks'!Q7 -> 0.049392111 | U10: ='Income Statement-Banks'!R13/'Income Statement-Banks'!R7 -> 0.063008907 | V10: ='Income Statement-Banks'!S13/'Income Statement-Banks'!S7 -> 0.089333109 | W10: ='Income Statement-Banks'!T13/'Income Statement-Banks'!T7 -> 0.11947833 | X10: ='Income Statement-Banks'!U13/'Income Statement-Banks'!U7 -> 0.11459996 | Y10: =AVERAGE(T10:X10) -> 0.087162484
A11: Asset Quality Ratios
A12: Gross NPA ratio | B12: 0.0486 | C12: 0.037 | D12: 0.0282 | E12: 0.0202 | F12: 0.0143 | G12: =AVERAGE(B12:F12) -> 0.02966 | H12: 0.0126 | I12: 0.0132 | J12: 0.0124 | K12: 0.0112 | L12: 0.0117 | M12: =AVERAGE(H12:L12) -> 0.01222 | N12: 0.0496 | O12: 0.036 | P12: 0.0281 | Q12: 0.0216 | R12: 0.0167 | S12: =AVERAGE(N12:R12) -> 0.0304 | T12: 0.0498 | U12: 0.0397 | V12: 0.0278 | W12: 0.0224 | X12: 0.0182 | Y12: =AVERAGE(T12:X12) -> 0.03158
A13: Net NPA Ratio | B13: 0.0156 | C13: 0.0105 | D13: 0.0073 | E13: 0.0039 | F13: 0.0031 | G13: =AVERAGE(B13:F13) -> 0.00808 | H13: 0.004 | I13: 0.0032 | J13: 0.0027 | K13: 0.0033 | L13: 0.0043 | M13: =AVERAGE(H13:L13) -> 0.0035 | N13: 0.0114 | O13: 0.0076 | P13: 0.0048 | Q13: 0.0042 | R13: 0.0039 | S13: =AVERAGE(N13:R13) -> 0.00638 | T13: 0.015 | U13: 0.0102 | V13: 0.0067 | W13: 0.0057 | X13: 0.0047 | Y13: =AVERAGE(T13:X13) -> 0.00846
A14: Provision Coverage ratio | B14: ='Cash Flow Statement-Banks'!B10/'Financial Ratios-Banks'!B34 -> 0.45303498 | C14: ='Cash Flow Statement-Banks'!C10/'Financial Ratios-Banks'!C34 -> 0.53319161 | D14: ='Cash Flow Statement-Banks'!D10/'Financial Ratios-Banks'!D34 -> 0.37072575 | E14: ='Cash Flow Statement-Banks'!E10/'Financial Ratios-Banks'!E34 -> 0.35492549 | F14: ='Cash Flow Statement-Banks'!F10/'Financial Ratios-Banks'!F34 -> 0.45718794 | G14: =AVERAGE(B14:F14) -> 0.43381315 | H14: ='Cash Flow Statement-Banks'!G10/'Financial Ratios-Banks'!H34 -> 0.84148292 | I14: ='Cash Flow Statement-Banks'!H10/'Financial Ratios-Banks'!I34 -> 0.89014704 | J14: ='Cash Flow Statement-Banks'!I10/'Financial Ratios-Banks'!J34 -> 0.75409694 | K14: ='Cash Flow Statement-Banks'!J10/'Financial Ratios-Banks'!K34 -> 0.72855444 | L14: ='Cash Flow Statement-Banks'!K10/'Financial Ratios-Banks'!L34 -> 0.41771025 | M14: =AVERAGE(H14:L14) -> 0.72639832 | N14: ='Cash Flow Statement-Banks'!L10/'Financial Ratios-Banks'!N34 -> 0.25586039 | O14: ='Cash Flow Statement-Banks'!M10/'Financial Ratios-Banks'!O34 -> 0.40694427 | P14: ='Cash Flow Statement-Banks'!N10/'Financial Ratios-Banks'!P34 -> 0.25536169 | Q14: ='Cash Flow Statement-Banks'!O10/'Financial Ratios-Banks'!Q34 -> -0.015605575 | R14: ='Cash Flow Statement-Banks'!P10/'Financial Ratios-Banks'!R34 -> 0.045764585 | S14: =AVERAGE(N14:R14) -> 0.18966507 | T14: ='Cash Flow Statement-Banks'!Q10/'Financial Ratios-Banks'!T34 -> 0.37084432 | U14: ='Cash Flow Statement-Banks'!R10/'Financial Ratios-Banks'!U34 -> 0.32791782 | V14: ='Cash Flow Statement-Banks'!S10/'Financial Ratios-Banks'!V34 -> 0.24869791 | W14: ='Cash Flow Statement-Banks'!T10/'Financial Ratios-Banks'!W34 -> 0.16817743 | X14: ='Cash Flow Statement-Banks'!U10/'Financial Ratios-Banks'!X34 -> 0.16897227 | Y14: =AVERAGE(T14:X14) -> 0.25692195
A15: Capital Adequacy ratios
A16: Capital Adequacy ratio (CAR) | B16: =('Balance Sheet-Banks'!B85+'Balance Sheet-Banks'!B86)/'Balance Sheet-Banks'!B84 -> 0.17526661 | C16: =('Balance Sheet-Banks'!C85+'Balance Sheet-Banks'!C86)/'Balance Sheet-Banks'!C84 -> 0.19119999 | D16: =('Balance Sheet-Banks'!D85+'Balance Sheet-Banks'!D86)/'Balance Sheet-Banks'!D84 -> 0.18539112 | E16: =('Balance Sheet-Banks'!E85+'Balance Sheet-Banks'!E86)/'Balance Sheet-Banks'!E84 -> 0.1763865 | F16: =('Balance Sheet-Banks'!F85+'Balance Sheet-Banks'!F86)/'Balance Sheet-Banks'!F84 -> 0.16632526 | G16: =AVERAGE(B16:F16) -> 0.1789139 | H16: =('Balance Sheet-Banks'!G85+'Balance Sheet-Banks'!G86)/'Balance Sheet-Banks'!G84 -> 0.18523669 | I16: =('Balance Sheet-Banks'!H85+'Balance Sheet-Banks'!H86)/'Balance Sheet-Banks'!H84 -> 0.18790386 | J16: =('Balance Sheet-Banks'!I85+'Balance Sheet-Banks'!I86)/'Balance Sheet-Banks'!I84 -> 0.1889416 | K16: =('Balance Sheet-Banks'!J85+'Balance Sheet-Banks'!J86)/'Balance Sheet-Banks'!J84 -> 0.19258674 | L16: =('Balance Sheet-Banks'!K85+'Balance Sheet-Banks'!K86)/'Balance Sheet-Banks'!K84 -> 0.18800549 | M16: =AVERAGE(H16:L16) -> 0.18853487 | N16: 0 | O16: =('Balance Sheet-Banks'!M85+'Balance Sheet-Banks'!M86)/'Balance Sheet-Banks'!M84 -> 0.1912 | P16: =('Balance Sheet-Banks'!N85+'Balance Sheet-Banks'!N86)/'Balance Sheet-Banks'!N84 -> 0.1916 | Q16: 0 | R16: 0 | S16: =AVERAGE(O16:P16) -> 0.1914 | T16: =('Balance Sheet-Banks'!Q85+'Balance Sheet-Banks'!Q86)/'Balance Sheet-Banks'!Q84 -> 0 | U16: 0 | V16: 0 | W16: 0 | X16: 0 | Y16: =AVERAGE(T16:X16) -> 0
A17: Tier 1 capital ratio | B17: ='Balance Sheet-Banks'!B85/'Balance Sheet-Banks'!B84 -> 0.1448732 | C17: ='Balance Sheet-Banks'!C85/'Balance Sheet-Banks'!C84 -> 0.1647336 | D17: ='Balance Sheet-Banks'!D85/'Balance Sheet-Banks'!D84 -> 0.16340753 | E17: ='Balance Sheet-Banks'!E85/'Balance Sheet-Banks'!E84 -> 0.14570997 | F17: ='Balance Sheet-Banks'!F85/'Balance Sheet-Banks'!F84 -> 0.14204864 | G17: =AVERAGE(B17:F17) -> 0.15215459 | H17: ='Balance Sheet-Banks'!G85/'Balance Sheet-Banks'!G84 -> 0.17232505 | I17: ='Balance Sheet-Banks'!H85/'Balance Sheet-Banks'!H84 -> 0.17556331 | J17: ='Balance Sheet-Banks'!I85/'Balance Sheet-Banks'!I84 -> 0.1786515 | K17: ='Balance Sheet-Banks'!J85/'Balance Sheet-Banks'!J84 -> 0.17132101 | L17: ='Balance Sheet-Banks'!K85/'Balance Sheet-Banks'!K84 -> 0.16785924 | M17: =AVERAGE(H17:L17) -> 0.17314402 | N17: 0 | O17: ='Balance Sheet-Banks'!M85/'Balance Sheet-Banks'!M84 -> 0.1806 | P17: ='Balance Sheet-Banks'!N85/'Balance Sheet-Banks'!N84 -> 0.1835 | Q17: 0 | R17: 0 | S17: =AVERAGE(O17:P17) -> 0.18205 | T17: ='Balance Sheet-Banks'!Q85/'Balance Sheet-Banks'!Q84 -> 0 | U17: 0 | V17: 0 | W17: 0 | X17: 0 | Y17: =AVERAGE(T17:X17) -> 0
A18: CET 1 Ratio | B18: ='Balance Sheet-Banks'!B88 -> 0.1449 | C18: ='Balance Sheet-Banks'!C88 -> 0.154 | D18: ='Balance Sheet-Banks'!D88 -> 0.1524 | E18: ='Balance Sheet-Banks'!E88 -> 0.1402 | F18: ='Balance Sheet-Banks'!F88 -> 0.1374 | G18: =AVERAGE(B18:F18) -> 0.14578 | H18: ='Balance Sheet-Banks'!G88 -> 0.1643 | I18: ='Balance Sheet-Banks'!H88 -> 0.1685 | J18: ='Balance Sheet-Banks'!I88 -> 0.1667 | K18: ='Balance Sheet-Banks'!J88 -> 0.164 | L18: ='Balance Sheet-Banks'!K88 -> 0.163 | M18: =AVERAGE(H18:L18) -> 0.1653 | N18: ='Balance Sheet-Banks'!L88 -> 0 | O18: ='Balance Sheet-Banks'!M88 -> 0.168 | P18: ='Balance Sheet-Banks'!N88 -> 0.176 | Q18: ='Balance Sheet-Banks'!O88 -> 0 | R18: ='Balance Sheet-Banks'!P88 -> 0 | S18: =AVERAGE(O18:P18) -> 0.172 | T18: ='Balance Sheet-Banks'!Q88 -> 0.1002 | U18: ='Balance Sheet-Banks'!R88 -> 0.1038 | V18: ='Balance Sheet-Banks'!S88 -> 0.1144 | W18: ='Balance Sheet-Banks'!T88 -> 0.1142 | X18: ='Balance Sheet-Banks'!U88 -> 0.1036 | Y18: =AVERAGE(T18:X18) -> 0.10724
A19: Liquidity & Funding ratios
A20: Credit to Deposit ratio | B20: ='Balance Sheet-Banks'!B75/'Balance Sheet-Banks'!B13 -> 0.90781323 | C20: ='Balance Sheet-Banks'!C75/'Balance Sheet-Banks'!C13 -> 0.89610131 | D20: ='Balance Sheet-Banks'!D75/'Balance Sheet-Banks'!D13 -> 0.88331465 | E20: ='Balance Sheet-Banks'!E75/'Balance Sheet-Banks'!E13 -> 0.91812735 | F20: ='Balance Sheet-Banks'!F75/'Balance Sheet-Banks'!F13 -> 0.93649258 | G20: =AVERAGE(B20:F20) -> 0.90836982 | H20: ='Balance Sheet-Banks'!G75/'Balance Sheet-Banks'!G13 -> 0.91054296 | I20: ='Balance Sheet-Banks'!H75/'Balance Sheet-Banks'!H13 -> 0.88870431 | J20: ='Balance Sheet-Banks'!I75/'Balance Sheet-Banks'!I13 -> 0.91202793 | K20: ='Balance Sheet-Banks'!J75/'Balance Sheet-Banks'!J13 -> 0.88276504 | L20: ='Balance Sheet-Banks'!K75/'Balance Sheet-Banks'!K13 -> 1.0795175 | M20: =AVERAGE(H20:L20) -> 0.93471155 | N20: ='Balance Sheet-Banks'!L75/'Balance Sheet-Banks'!L13 -> 0.88194281 | O20: ='Balance Sheet-Banks'!M75/'Balance Sheet-Banks'!M13 -> 0.7868221 | P20: ='Balance Sheet-Banks'!N75/'Balance Sheet-Banks'!N13 -> 0.8069165 | Q20: ='Balance Sheet-Banks'!O75/'Balance Sheet-Banks'!O13 -> 0.89514163 | R20: ='Balance Sheet-Banks'!P75/'Balance Sheet-Banks'!P13 -> 0.87336775 | S20: =AVERAGE(N20:R20) -> 0.84883816 | T20: ='Balance Sheet-Banks'!Q75/'Balance Sheet-Banks'!Q13 -> 0.72516637 | U20: ='Balance Sheet-Banks'!R75/'Balance Sheet-Banks'!R13 -> 0.67304873 | V20: ='Balance Sheet-Banks'!S75/'Balance Sheet-Banks'!S13 -> 0.68358094 | W20: ='Balance Sheet-Banks'!T75/'Balance Sheet-Banks'!T13 -> 0.7313139 | X20: ='Balance Sheet-Banks'!U75/'Balance Sheet-Banks'!U13 -> 0.76195391 | Y20: =AVERAGE(T20:X20) -> 0.71501277
A21: CASA Ratio | B21: =('Balance Sheet-Banks'!B82+'Balance Sheet-Banks'!B83)/'Balance Sheet-Banks'!B13 -> 0.41009166 | C21: =('Balance Sheet-Banks'!C82+'Balance Sheet-Banks'!C83)/'Balance Sheet-Banks'!C13 -> 0.45440187 | D21: =('Balance Sheet-Banks'!D82+'Balance Sheet-Banks'!D83)/'Balance Sheet-Banks'!D13 -> 0.44967648 | E21: =('Balance Sheet-Banks'!E82+'Balance Sheet-Banks'!E83)/'Balance Sheet-Banks'!E13 -> 0.47124998 | F21: =('Balance Sheet-Banks'!F82+'Balance Sheet-Banks'!F83)/'Balance Sheet-Banks'!F13 -> 0.42963724 | G21: =AVERAGE(B21:F21) -> 0.44301145 | H21: =('Balance Sheet-Banks'!G82+'Balance Sheet-Banks'!G83)/'Balance Sheet-Banks'!G13 -> 0.42185739 | I21: =('Balance Sheet-Banks'!H82+'Balance Sheet-Banks'!H83)/'Balance Sheet-Banks'!H13 -> 0.46079261 | J21: =('Balance Sheet-Banks'!I82+'Balance Sheet-Banks'!I83)/'Balance Sheet-Banks'!I13 -> 0.48134851 | K21: =('Balance Sheet-Banks'!J82+'Balance Sheet-Banks'!J83)/'Balance Sheet-Banks'!J13 -> 0.44373776 | L21: =('Balance Sheet-Banks'!K82+'Balance Sheet-Banks'!K83)/'Balance Sheet-Banks'!K13 -> 0.38138973 | M21: =AVERAGE(H21:L21) -> 0.4378252 | N21: =('Balance Sheet-Banks'!L82+'Balance Sheet-Banks'!L83)/'Balance Sheet-Banks'!L13 -> 0.44837725 | O21: =('Balance Sheet-Banks'!M82+'Balance Sheet-Banks'!M83)/'Balance Sheet-Banks'!M13 -> 0.46285595 | P21: =('Balance Sheet-Banks'!N82+'Balance Sheet-Banks'!N83)/'Balance Sheet-Banks'!N13 -> 0.48699079 | Q21: =('Balance Sheet-Banks'!O82+'Balance Sheet-Banks'!O83)/'Balance Sheet-Banks'!O13 -> 0.45478036 | R21: =('Balance Sheet-Banks'!P82+'Balance Sheet-Banks'!P83)/'Balance Sheet-Banks'!P13 -> 0.41903272 | S21: =AVERAGE(N21:R21) -> 0.45440742 | T21: =('Balance Sheet-Banks'!Q82+'Balance Sheet-Banks'!Q83)/'Balance Sheet-Banks'!Q13 -> 0.44170445 | U21: =('Balance Sheet-Banks'!R82+'Balance Sheet-Banks'!R83)/'Balance Sheet-Banks'!R13 -> 0.45400515 | V21: =('Balance Sheet-Banks'!S82+'Balance Sheet-Banks'!S83)/'Balance Sheet-Banks'!S13 -> 0.44519921 | W21: =('Balance Sheet-Banks'!T82+'Balance Sheet-Banks'!T83)/'Balance Sheet-Banks'!T13 -> 0.4266542 | X21: =('Balance Sheet-Banks'!U82+'Balance Sheet-Banks'!U83)/'Balance Sheet-Banks'!U13 -> 0.399258 | Y21: =AVERAGE(T21:X21) -> 0.4333642
A22: Liquidity Coverage ratio | B22: =B38/B39 -> 0.80885697 | C22: =C38/C39 -> 0.8584246 | D22: =D38/D39 -> 0.88754931 | E22: =E38/E39 -> 0.90209232 | F22: =F38/F39 -> 0.82070528 | G22: =AVERAGE(B22:F22) -> 0.85552569 | H22: =H38/H39 -> 0.86833868 | I22: =I38/I39 -> 0.98446504 | J22: =J38/J39 -> 0.81863656 | K22: =K38/K39 -> 0.82849322 | L22: =L38/L39 -> 0.80022705 | M22: =AVERAGE(H22:L22) -> 0.86003211 | N22: 0 | O22: =O38/O39 -> 1.1269147 | P22: =P38/P39 -> 1.106577 | Q22: 0 | R22: 0 | S22: =AVERAGE(N22:R22) -> 0.44669834 | T22: 0 | U22: 0 | V22: 0 | W22: 0 | X22: 0 | Y22: =AVERAGE(T22:X22) -> 0
A23: Efficiency Ratios
A24: Operating expense ratio | B24: ='Income Statement-Banks'!B10/'Income Statement-Banks'!B7 -> 0.22565931 | C24: ='Income Statement-Banks'!C10/'Income Statement-Banks'!C7 -> 0.24591288 | D24: ='Income Statement-Banks'!D10/'Income Statement-Banks'!D7 -> 0.28827107 | E24: ='Income Statement-Banks'!E10/'Income Statement-Banks'!E7 -> 0.38630116 | F24: ='Income Statement-Banks'!F10/'Income Statement-Banks'!F7 -> 0.26989436 | G24: =AVERAGE(B24:F24) -> 0.28320776 | H24: ='Income Statement-Banks'!G10/'Income Statement-Banks'!G7 -> 0.22463075 | I24: ='Income Statement-Banks'!H10/'Income Statement-Banks'!H7 -> 0.22453216 | J24: ='Income Statement-Banks'!I10/'Income Statement-Banks'!I7 -> 0.24039079 | K24: ='Income Statement-Banks'!J10/'Income Statement-Banks'!J7 -> 0.25179397 | L24: ='Income Statement-Banks'!K10/'Income Statement-Banks'!K7 -> 0.37321395 | M24: =AVERAGE(H24:L24) -> 0.26291232 | N24: ='Income Statement-Banks'!L10/'Income Statement-Banks'!L7 -> 0.47746685 | O24: ='Income Statement-Banks'!M10/'Income Statement-Banks'!M7 -> 0.21981382 | P24: ='Income Statement-Banks'!N10/'Income Statement-Banks'!N7 -> 0.25486497 | Q24: ='Income Statement-Banks'!O10/'Income Statement-Banks'!O7 -> 0.4427949 | R24: ='Income Statement-Banks'!P10/'Income Statement-Banks'!P7 -> 0.41426764 | S24: =AVERAGE(N24:R24) -> 0.36184164 | T24: ='Income Statement-Banks'!Q10/'Income Statement-Banks'!Q7 -> 0.35809171 | U24: ='Income Statement-Banks'!R10/'Income Statement-Banks'!R7 -> 0.39038361 | V24: ='Income Statement-Banks'!S10/'Income Statement-Banks'!S7 -> 0.42843969 | W24: ='Income Statement-Banks'!T10/'Income Statement-Banks'!T7 -> 0.40097856 | X24: ='Income Statement-Banks'!U10/'Income Statement-Banks'!U7 -> 0.39674369 | Y24: =AVERAGE(T24:X24) -> 0.39492745
A25: Non-interest income ratio | B25: ='Income Statement-Banks'!B6/'Income Statement-Banks'!B7 -> 0.20412772 | C25: ='Income Statement-Banks'!C6/'Income Statement-Banks'!C7 -> 0.17412049 | D25: ='Income Statement-Banks'!D6/'Income Statement-Banks'!D7 -> 0.20052595 | E25: ='Income Statement-Banks'!E6/'Income Statement-Banks'!E7 -> 0.17343477 | F25: ='Income Statement-Banks'!F6/'Income Statement-Banks'!F7 -> 0.18284243 | G25: =AVERAGE(B25:F25) -> 0.18701027 | H25: ='Income Statement-Banks'!G6/'Income Statement-Banks'!G7 -> 0.16916617 | I25: ='Income Statement-Banks'!H6/'Income Statement-Banks'!H7 -> 0.17533972 | J25: ='Income Statement-Banks'!I6/'Income Statement-Banks'!I7 -> 0.18938498 | K25: ='Income Statement-Banks'!J6/'Income Statement-Banks'!J7 -> 0.16569451 | L25: ='Income Statement-Banks'!K6/'Income Statement-Banks'!K7 -> 0.3047729 | M25: =AVERAGE(H25:L25) -> 0.20087166 | N25: ='Income Statement-Banks'!L6/'Income Statement-Banks'!L7 -> 0.43362053 | O25: ='Income Statement-Banks'!M6/'Income Statement-Banks'!M7 -> 0.19338512 | P25: ='Income Statement-Banks'!N6/'Income Statement-Banks'!N7 -> 0.17653888 | Q25: ='Income Statement-Banks'!O6/'Income Statement-Banks'!O7 -> 0.34972828 | R25: ='Income Statement-Banks'!P6/'Income Statement-Banks'!P7 -> 0.3241931 | S25: =AVERAGE(N25:R25) -> 0.29549318 | T25: ='Income Statement-Banks'!Q6/'Income Statement-Banks'!Q7 -> 0.26672867 | U25: ='Income Statement-Banks'!R6/'Income Statement-Banks'!R7 -> 0.27825557 | V25: ='Income Statement-Banks'!S6/'Income Statement-Banks'!S7 -> 0.28748929 | W25: ='Income Statement-Banks'!T6/'Income Statement-Banks'!T7 -> 0.25884922 | X25: ='Income Statement-Banks'!U6/'Income Statement-Banks'!U7 -> 0.26134031 | Y25: =AVERAGE(T25:X25) -> 0.27053261
A26: Cash Flow Ratios
A27: Operating cash flow/Net Profit | B27: ='Cash Flow Statement-Banks'!B28/'Income Statement-Banks'!B13 -> 16.189282 | C27: ='Cash Flow Statement-Banks'!C28/'Income Statement-Banks'!C13 -> 1.741892 | D27: ='Cash Flow Statement-Banks'!D28/'Income Statement-Banks'!D13 -> 1.9864872 | E27: ='Cash Flow Statement-Banks'!E28/'Income Statement-Banks'!E13 -> 2.0340433 | F27: ='Cash Flow Statement-Banks'!F28/'Income Statement-Banks'!F13 -> -0.21021672 | G27: =AVERAGE(B27:F27) -> 4.3482975 | H27: ='Cash Flow Statement-Banks'!G28/'Income Statement-Banks'!G13 -> -0.618 | I27: ='Cash Flow Statement-Banks'!H28/'Income Statement-Banks'!H13 -> 1.3333574 | J27: ='Cash Flow Statement-Banks'!I28/'Income Statement-Banks'!I13 -> -0.31348094 | K27: ='Cash Flow Statement-Banks'!J28/'Income Statement-Banks'!J13 -> 0.45101379 | L27: ='Cash Flow Statement-Banks'!K28/'Income Statement-Banks'!K13 -> 0.29137295 | M27: =AVERAGE(H27:L27) -> 0.22885263 | N27: ='Cash Flow Statement-Banks'!L28/'Income Statement-Banks'!L13 -> 7.0878779 | O27: ='Cash Flow Statement-Banks'!M28/'Income Statement-Banks'!M13 -> 7.6635446 | P27: ='Cash Flow Statement-Banks'!N28/'Income Statement-Banks'!N13 -> 2.3585316 | Q27: ='Cash Flow Statement-Banks'!O28/'Income Statement-Banks'!O13 -> -0.10942719 | R27: ='Cash Flow Statement-Banks'!P28/'Income Statement-Banks'!P13 -> 3.4946913 | S27: =AVERAGE(N27:R27) -> 4.0990436 | T27: ='Cash Flow Statement-Banks'!Q28/'Income Statement-Banks'!Q13 -> 1.316431 | U27: ='Cash Flow Statement-Banks'!R28/'Income Statement-Banks'!R13 -> 3.7034584 | V27: ='Cash Flow Statement-Banks'!S28/'Income Statement-Banks'!S13 -> 1.5869341 | W27: ='Cash Flow Statement-Banks'!T28/'Income Statement-Banks'!T13 -> -1.5207933 | X27: ='Cash Flow Statement-Banks'!U28/'Income Statement-Banks'!U13 -> 0.31747847 | Y27: =AVERAGE(T27:X27) -> 1.0807017
A28: Cash flow coverage ratio | B28: ='Cash Flow Statement-Banks'!B28/('Income Statement-Banks'!B9+'Financial Ratios-Banks'!B40) -> 0.47392162 | C28: ='Cash Flow Statement-Banks'!C28/('Income Statement-Banks'!C9+'Financial Ratios-Banks'!C40) -> 0.20125521 | D28: ='Cash Flow Statement-Banks'!D28/('Income Statement-Banks'!D9+'Financial Ratios-Banks'!D40) -> 0.33471555 | E28: ='Cash Flow Statement-Banks'!E28/('Income Statement-Banks'!E9+'Financial Ratios-Banks'!E40) -> 0.29994693 | F28: ='Cash Flow Statement-Banks'!F28/('Income Statement-Banks'!F9+'Financial Ratios-Banks'!F40) -> -0.052628781 | G28: =AVERAGE(B28:F28) -> 0.2514421 | H28: ='Cash Flow Statement-Banks'!G28/('Income Statement-Banks'!G9+'Financial Ratios-Banks'!H40) -> -0.24352033 | I28: ='Cash Flow Statement-Banks'!H28/('Income Statement-Banks'!H9+'Financial Ratios-Banks'!I40) -> 0.61160826 | J28: ='Cash Flow Statement-Banks'!I28/('Income Statement-Banks'!I9+'Financial Ratios-Banks'!J40) -> -0.14006262 | K28: ='Cash Flow Statement-Banks'!J28/('Income Statement-Banks'!J9+'Financial Ratios-Banks'!K40) -> 0.21189558 | L28: ='Cash Flow Statement-Banks'!K28/('Income Statement-Banks'!K9+'Financial Ratios-Banks'!L40) -> 0.093787455 | M28: =AVERAGE(H28:L28) -> 0.10674167 | N28: ='Cash Flow Statement-Banks'!L28/('Income Statement-Banks'!L9+'Financial Ratios-Banks'!N40) -> 0.82308801 | O28: ='Cash Flow Statement-Banks'!M28/('Income Statement-Banks'!M9+'Financial Ratios-Banks'!O40) -> 0.97917031 | P28: ='Cash Flow Statement-Banks'!N28/('Income Statement-Banks'!N9+'Financial Ratios-Banks'!P40) -> 0.88467283 | Q28: ='Cash Flow Statement-Banks'!O28/('Income Statement-Banks'!O9+'Financial Ratios-Banks'!Q40) -> -0.048701273 | R28: ='Cash Flow Statement-Banks'!P28/('Income Statement-Banks'!P9+'Financial Ratios-Banks'!R40) -> 1.3887654 | S28: =AVERAGE(N28:R28) -> 0.80539905 | T28: ='Cash Flow Statement-Banks'!Q28/('Income Statement-Banks'!Q9+'Financial Ratios-Banks'!T40) -> 0.095535816 | U28: ='Cash Flow Statement-Banks'!R28/('Income Statement-Banks'!R9+'Financial Ratios-Banks'!U40) -> 0.52003966 | V28: ='Cash Flow Statement-Banks'!S28/('Income Statement-Banks'!S9+'Financial Ratios-Banks'!V40) -> 0.34607361 | W28: ='Cash Flow Statement-Banks'!T28/('Income Statement-Banks'!T9+'Financial Ratios-Banks'!W40) -> -0.44774115 | X28: ='Cash Flow Statement-Banks'!U28/('Income Statement-Banks'!U9+'Financial Ratios-Banks'!X40) -> 0.078943492 | Y28: =AVERAGE(T28:X28) -> 0.11857029
A29: Loan Growth rate | B29: 0.15 | C29: =('Balance Sheet-Banks'!C75-'Balance Sheet-Banks'!B75)/'Balance Sheet-Banks'!B75 -> 0.073403301 | D29: =('Balance Sheet-Banks'!D75-'Balance Sheet-Banks'!C75)/'Balance Sheet-Banks'!C75 -> 0.15881041 | E29: =('Balance Sheet-Banks'!E75-'Balance Sheet-Banks'!D75)/'Balance Sheet-Banks'!D75 -> 0.19756861 | F29: =('Balance Sheet-Banks'!F75-'Balance Sheet-Banks'!E75)/'Balance Sheet-Banks'!E75 -> 0.15079205 | G29: =AVERAGE(B29:F29) -> 0.14611488 | H29: 0.212 | I29: =('Balance Sheet-Banks'!H75-'Balance Sheet-Banks'!G75)/'Balance Sheet-Banks'!G75 -> 0.13568709 | J29: =('Balance Sheet-Banks'!I75-'Balance Sheet-Banks'!H75)/'Balance Sheet-Banks'!H75 -> 0.19882061 | K29: =('Balance Sheet-Banks'!J75-'Balance Sheet-Banks'!I75)/'Balance Sheet-Banks'!I75 -> 0.1696107 | L29: =('Balance Sheet-Banks'!K75-'Balance Sheet-Banks'!J75)/'Balance Sheet-Banks'!J75 -> 0.54390475 | M29: =AVERAGE(H29:L29) -> 0.25200463 | N29: 0.1 | O29: =('Balance Sheet-Banks'!M75-'Balance Sheet-Banks'!L75)/'Balance Sheet-Banks'!L75 -> 0.038914133 | P29: =('Balance Sheet-Banks'!N75-'Balance Sheet-Banks'!M75)/'Balance Sheet-Banks'!M75 -> 0.17075971 | Q29: =('Balance Sheet-Banks'!O75-'Balance Sheet-Banks'!N75)/'Balance Sheet-Banks'!N75 -> 0.26174682 | R29: =('Balance Sheet-Banks'!P75-'Balance Sheet-Banks'!O75)/'Balance Sheet-Banks'!O75 -> 0.16322116 | S29: =AVERAGE(N29:R29) -> 0.14692837 | T29: 0.0638 | U29: =('Balance Sheet-Banks'!R75-'Balance Sheet-Banks'!Q75)/'Balance Sheet-Banks'!Q75 -> 0.053189245 | V29: =('Balance Sheet-Banks'!S75-'Balance Sheet-Banks'!R75)/'Balance Sheet-Banks'!R75 -> 0.11736268 | W29: =('Balance Sheet-Banks'!T75-'Balance Sheet-Banks'!S75)/'Balance Sheet-Banks'!S75 -> 0.16958241 | X29: =('Balance Sheet-Banks'!U75-'Balance Sheet-Banks'!T75)/'Balance Sheet-Banks'!T75 -> 0.15801285 | Y29: =AVERAGE(T29:X29) -> 0.11238944
A30: Deposit Growth rate | B30: ~ | C30: =('Balance Sheet-Banks'!C13-'Balance Sheet-Banks'!B13)/'Balance Sheet-Banks'!B13 -> 0.087432532 | D30: =('Balance Sheet-Banks'!D13-'Balance Sheet-Banks'!C13)/'Balance Sheet-Banks'!C13 -> 0.17558509 | E30: =('Balance Sheet-Banks'!E13-'Balance Sheet-Banks'!D13)/'Balance Sheet-Banks'!D13 -> 0.15216032 | F30: =('Balance Sheet-Banks'!F13-'Balance Sheet-Banks'!E13)/'Balance Sheet-Banks'!E13 -> 0.12822427 | G30: =AVERAGE(B30:F30) -> 0.13585055 | H30: ~ | I30: =('Balance Sheet-Banks'!H13-'Balance Sheet-Banks'!G13)/'Balance Sheet-Banks'!G13 -> 0.16359499 | J30: =('Balance Sheet-Banks'!I13-'Balance Sheet-Banks'!H13)/'Balance Sheet-Banks'!H13 -> 0.16816274 | K30: =('Balance Sheet-Banks'!J13-'Balance Sheet-Banks'!I13)/'Balance Sheet-Banks'!I13 -> 0.20838228 | L30: =('Balance Sheet-Banks'!K13-'Balance Sheet-Banks'!J13)/'Balance Sheet-Banks'!J13 -> 0.26251324 | M30: =AVERAGE(H30:L30) -> 0.20066331 | N30: ~ | O30: =('Balance Sheet-Banks'!M13-'Balance Sheet-Banks'!L13)/'Balance Sheet-Banks'!L13 -> 0.16451081 | P30: =('Balance Sheet-Banks'!N13-'Balance Sheet-Banks'!M13)/'Balance Sheet-Banks'!M13 -> 0.14160464 | Q30: =('Balance Sheet-Banks'!O13-'Balance Sheet-Banks'!N13)/'Balance Sheet-Banks'!N13 -> 0.13738909 | R30: =('Balance Sheet-Banks'!P13-'Balance Sheet-Banks'!O13)/'Balance Sheet-Banks'!O13 -> 0.19222136 | S30: =AVERAGE(N30:R30) -> 0.15893148 | T30: ~ | U30: =('Balance Sheet-Banks'!R13-'Balance Sheet-Banks'!Q13)/'Balance Sheet-Banks'!Q13 -> 0.13474312 | V30: =('Balance Sheet-Banks'!S13-'Balance Sheet-Banks'!R13)/'Balance Sheet-Banks'!R13 -> 0.10014702 | W30: =('Balance Sheet-Banks'!T13-'Balance Sheet-Banks'!S13)/'Balance Sheet-Banks'!S13 -> 0.093243603 | X30: =('Balance Sheet-Banks'!U13-'Balance Sheet-Banks'!T13)/'Balance Sheet-Banks'!T13 -> 0.11144635 | Y30: =AVERAGE(T30:X30) -> 0.10989503
A33: Particulars | B33: 2020 | C33: 2021 | D33: 2022 | E33: 2023 | F33: 2024 | H33: 2020 | I33: 2021 | J33: 2022 | K33: 2023 | L33: 2024 | N33: 2020 | O33: 2021 | P33: 2022 | Q33: 2023 | R33: 2024 | T33: 2020 | U33: 2021 | V33: 2022 | W33: 2023 | X33: 2024
A34: Gross NPA | B34: =B12*B37 -> 28331.798 | C34: =C12*C37 -> 23152.746 | D34: =D12*D37 -> 20448.539 | E34: =E12*E37 -> 17541.428 | F34: =F12*F37 -> 14290.469 | H34: =H12*H37 -> 13150.252 | I34: =I12*I37 -> 15645.742 | J34: =J12*J37 -> 17619.684 | K34: =K12*K37 -> 18613.832 | L34: =L12*L37 -> 30020.929 | N34: =N12*N37 -> 35029.806 | O34: =O12*O37 -> 26414.245 | P34: =P12*P37 -> 24138.473 | Q34: =Q12*Q37 -> 23411.511 | R34: =R12*R37 -> 21054.962 | T34: =T12*T37 -> 118240.7 | U34: =U12*U37 -> 99273.779 | V34: =V12*V37 -> 77675.312 | W34: =W12*W37 -> 73201.008 | X34: =X12*X37 -> 68873.763
A35: Net NPA | B35: =B13*B37 -> 9094.1573 | C35: =C13*C37 -> 6570.374 | D35: =D13*D37 -> 5293.4162 | E35: =E13*E37 -> 3386.7114 | F35: =F13*F37 -> 3097.9338 | H35: =H13*H37 -> 4174.6833 | I35: =I13*I37 -> 3792.9072 | J35: =J13*J37 -> 3836.5442 | K35: =K13*K37 -> 5484.4327 | L35: =L13*L37 -> 11033.333 | N35: =N13*N37 -> 8051.2054 | O35: =O13*O37 -> 5576.3407 | P35: =P13*P37 -> 4123.2979 | Q35: =Q13*Q37 -> 4552.2383 | R35: =R13*R37 -> 4917.0271 | T35: =T13*T37 -> 35614.667 | U35: =U13*U37 -> 25506.109 | V35: =V13*V37 -> 18720.309 | W35: =W13*W37 -> 18627.042 | X35: =X13*X37 -> 17786.082
A36: CASA | B36: ='Balance Sheet-Banks'!B82+'Balance Sheet-Banks'!B83 -> 263343.32 | C36: ='Balance Sheet-Banks'!C82+'Balance Sheet-Banks'!C83 -> 317310.02 | D36: ='Balance Sheet-Banks'!D82+'Balance Sheet-Banks'!D83 -> 369145.79 | E36: ='Balance Sheet-Banks'!E82+'Balance Sheet-Banks'!E83 -> 445719.88 | F36: ='Balance Sheet-Banks'!F82+'Balance Sheet-Banks'!F83 -> 458466.93 | H36: ='Balance Sheet-Banks'!G82+'Balance Sheet-Banks'!G83 -> 483535.95 | I36: ='Balance Sheet-Banks'!H82+'Balance Sheet-Banks'!H83 -> 614568.72 | J36: ='Balance Sheet-Banks'!I82+'Balance Sheet-Banks'!I83 -> 749942.43 | K36: ='Balance Sheet-Banks'!J82+'Balance Sheet-Banks'!J83 -> 835408.77 | L36: ='Balance Sheet-Banks'!K82+'Balance Sheet-Banks'!K83 -> 906520.39 | N36: ='Balance Sheet-Banks'!L82+'Balance Sheet-Banks'!L83 -> 359053.53 | O36: ='Balance Sheet-Banks'!M82+'Balance Sheet-Banks'!M83 -> 431623.43 | P36: ='Balance Sheet-Banks'!N82+'Balance Sheet-Banks'!N83 -> 518436.57 | Q36: ='Balance Sheet-Banks'!O82+'Balance Sheet-Banks'!O83 -> 550662.68 | R36: ='Balance Sheet-Banks'!P82+'Balance Sheet-Banks'!P83 -> 604907.22 | T36: ='Balance Sheet-Banks'!Q82+'Balance Sheet-Banks'!Q83 -> 1446211.3 | U36: ='Balance Sheet-Banks'!R82+'Balance Sheet-Banks'!R83 -> 1686779.5 | V36: ='Balance Sheet-Banks'!S82+'Balance Sheet-Banks'!S83 -> 1819712 | W36: ='Balance Sheet-Banks'!T82+'Balance Sheet-Banks'!T83 -> 1906519.4 | X36: ='Balance Sheet-Banks'!U82+'Balance Sheet-Banks'!U83 -> 1982929.8
A37: Advances | B37: ='Balance Sheet-Banks'!B75 -> 582958.8 | C37: ='Balance Sheet-Banks'!C75 -> 625749.9 | D37: ='Balance Sheet-Banks'!D75 -> 725125.5 | E37: ='Balance Sheet-Banks'!E75 -> 868387.54 | F37: ='Balance Sheet-Banks'!F75 -> 999333.48 | H37: ='Balance Sheet-Banks'!G75 -> 1043670.8 | I37: ='Balance Sheet-Banks'!H75 -> 1185283.5 | J37: ='Balance Sheet-Banks'!I75 -> 1420942.3 | K37: ='Balance Sheet-Banks'!J75 -> 1661949.3 | L37: ='Balance Sheet-Banks'!K75 -> 2565891.4 | N37: ='Balance Sheet-Banks'!L75 -> 706246.09 | O37: ='Balance Sheet-Banks'!M75 -> 733729.04 | P37: ='Balance Sheet-Banks'!N75 -> 859020.4 | Q37: ='Balance Sheet-Banks'!O75 -> 1083866.3 | R37: ='Balance Sheet-Banks'!P75 -> 1260776.2 | T37: ='Balance Sheet-Banks'!Q75 -> 2374311.2 | U37: ='Balance Sheet-Banks'!R75 -> 2500599 | V37: ='Balance Sheet-Banks'!S75 -> 2794076 | W37: ='Balance Sheet-Banks'!T75 -> 3267902.1 | X37: ='Balance Sheet-Banks'!U75 -> 3784272.7
A38: Average Total High quality liquid assets (HQLAs) | B38: 153367.16 | C38: 197825.03 | D38: 247519.05 | E38: 247980.92 | F38: 257647.25 | H38: 281400.84 | I38: 387444.92 | J38: 385997.51 | K38: 442566.92 | L38: 558424.94 | O38: 276744.36 | P38: 319727.33
A39: Average Total Net cash outflows | B39: 189609.74 | C39: 230451.26 | D39: 278879.21 | E39: 274895.28 | F39: 313933.95 | H39: 324068.07 | I39: 393558.84 | J39: 471512.67 | K39: 534182.91 | L39: 697833.12 | O39: 245577.02 | P39: 288933.65
A40: Repayment of Borrowings | B40: 26182.68 | C40: 28143.07 | D40: 49140.66 | E40: 30206.47 | F40: 44153.6 | H40: 7134.38 | I40: 10202.85 | J40: 26803.05 | K40: 20446.27 | L40: 49186.51 | N40: 52000.625 | O40: =37729.08+48875.2518 -> 86604.332 | P40: 23314.468 | Q40: 26891.798 | R40: 39146.877 | T40: 89342.809 | U40: 16897.664 | V40: 10518.3 | W40: 2125 | X40: 14288.2
A42: Total Assets/Equity | B42: ='Balance Sheet-Banks'!B79/'Balance Sheet-Banks'!B9 -> 10.732552 | C42: ='Balance Sheet-Banks'!C79/'Balance Sheet-Banks'!C9 -> 9.6475777 | D42: ='Balance Sheet-Banks'!D79/'Balance Sheet-Banks'!D9 -> 10.086975 | E42: ='Balance Sheet-Banks'!E79/'Balance Sheet-Banks'!E9 -> 10.327766 | F42: ='Balance Sheet-Banks'!F79/'Balance Sheet-Banks'!F9 -> 9.6382047 | H42: ='Balance Sheet-Banks'!G79/'Balance Sheet-Banks'!G9 -> 8.9344525 | I42: ='Balance Sheet-Banks'!H79/'Balance Sheet-Banks'!H9 -> 8.5510427 | J42: ='Balance Sheet-Banks'!I79/'Balance Sheet-Banks'!I9 -> 8.5580116 | K42: ='Balance Sheet-Banks'!J79/'Balance Sheet-Banks'!J9 -> 8.7161666 | L42: ='Balance Sheet-Banks'!K79/'Balance Sheet-Banks'!K9 -> 8.5789217 | N42: ='Balance Sheet-Banks'!L79/'Balance Sheet-Banks'!L9 -> 10.614576 | O42: ='Balance Sheet-Banks'!M79/'Balance Sheet-Banks'!M9 -> 8.3413964 | P42: ='Balance Sheet-Banks'!N79/'Balance Sheet-Banks'!N9 -> 8.2768248 | Q42: ='Balance Sheet-Banks'!O79/'Balance Sheet-Banks'!O9 -> 8.8545543 | R42: ='Balance Sheet-Banks'!P79/'Balance Sheet-Banks'!P9 -> 8.7547437 | T42: ='Balance Sheet-Banks'!Q79/'Balance Sheet-Banks'!Q9 -> 16.206287 | U42: ='Balance Sheet-Banks'!R79/'Balance Sheet-Banks'!R9 -> 16.990994 | V42: ='Balance Sheet-Banks'!S79/'Balance Sheet-Banks'!S9 -> 16.922223 | W42: ='Balance Sheet-Banks'!T79/'Balance Sheet-Banks'!T9 -> 16.016493 | X42: ='Balance Sheet-Banks'!U79/'Balance Sheet-Banks'!U9 -> 15.639687
A43: Deposits/NII | B43: ='Balance Sheet-Banks'!B13/('Income Statement-Banks'!B5-'Income Statement-Banks'!B9) -> 24.967484 | C43: ='Balance Sheet-Banks'!C13/('Income Statement-Banks'!C5-'Income Statement-Banks'!C9) -> 23.456604 | D43: ='Balance Sheet-Banks'!D13/('Income Statement-Banks'!D5-'Income Statement-Banks'!D9) -> 24.199053 | E43: ='Balance Sheet-Banks'!E13/('Income Statement-Banks'!E5-'Income Statement-Banks'!E9) -> 21.467124 | F43: ='Balance Sheet-Banks'!F13/('Income Statement-Banks'!F5-'Income Statement-Banks'!F9) -> 20.773555 | H43: ='Balance Sheet-Banks'!G13/('Income Statement-Banks'!G5-'Income Statement-Banks'!G9) -> 19.086952 | I43: ='Balance Sheet-Banks'!H13/('Income Statement-Banks'!H5-'Income Statement-Banks'!H9) -> 19.244275 | J43: ='Balance Sheet-Banks'!I13/('Income Statement-Banks'!I5-'Income Statement-Banks'!I9) -> 20.141708 | K43: ='Balance Sheet-Banks'!J13/('Income Statement-Banks'!J5-'Income Statement-Banks'!J9) -> 20.249328 | L43: ='Balance Sheet-Banks'!K13/('Income Statement-Banks'!K5-'Income Statement-Banks'!K9) -> 18.352858 | N43: ='Balance Sheet-Banks'!L13/('Income Statement-Banks'!L5-'Income Statement-Banks'!L9) -> 19.934764 | O43: ='Balance Sheet-Banks'!M13/('Income Statement-Banks'!M5-'Income Statement-Banks'!M9) -> 23.917304 | P43: ='Balance Sheet-Banks'!N13/('Income Statement-Banks'!N5-'Income Statement-Banks'!N9) -> 22.428043 | Q43: ='Balance Sheet-Banks'!O13/('Income Statement-Banks'!O5-'Income Statement-Banks'!O9) -> 17.16922 | R43: ='Balance Sheet-Banks'!P13/('Income Statement-Banks'!P5-'Income Statement-Banks'!P9) -> 16.90221 | T43: ='Balance Sheet-Banks'!Q13/('Income Statement-Banks'!Q5-'Income Statement-Banks'!Q9) -> 30.113357 | U43: ='Balance Sheet-Banks'!R13/('Income Statement-Banks'!R5-'Income Statement-Banks'!R9) -> 30.42727 | V43: ='Balance Sheet-Banks'!S13/('Income Statement-Banks'!S5-'Income Statement-Banks'!S9) -> 30.553605 | W43: ='Balance Sheet-Banks'!T13/('Income Statement-Banks'!T5-'Income Statement-Banks'!T9) -> 27.778385 | X43: ='Balance Sheet-Banks'!U13/('Income Statement-Banks'!U5-'Income Statement-Banks'!U9) -> 27.676062
A44: RWA/Equity | B44: ='Balance Sheet-Banks'!B84/'Balance Sheet-Banks'!B9 -> 7.0618735 | C44: ='Balance Sheet-Banks'!C84/'Balance Sheet-Banks'!C9 -> 6.1277694 | D44: ='Balance Sheet-Banks'!D84/'Balance Sheet-Banks'!D9 -> 6.086262 | E44: ='Balance Sheet-Banks'!E84/'Balance Sheet-Banks'!E9 -> 6.539922 | F44: ='Balance Sheet-Banks'!F84/'Balance Sheet-Banks'!F9 -> 6.5978509 | H44: ='Balance Sheet-Banks'!G84/'Balance Sheet-Banks'!G9 -> 5.621917 | I44: ='Balance Sheet-Banks'!H84/'Balance Sheet-Banks'!H9 -> 5.3750621 | J44: ='Balance Sheet-Banks'!I84/'Balance Sheet-Banks'!I9 -> 5.4566802 | K44: ='Balance Sheet-Banks'!J84/'Balance Sheet-Banks'!J9 -> 5.4655432 | L44: ='Balance Sheet-Banks'!K84/'Balance Sheet-Banks'!K9 -> 5.2535978 | N44: ='Balance Sheet-Banks'!L84/'Balance Sheet-Banks'!L9 -> 0 | O44: ='Balance Sheet-Banks'!M84/'Balance Sheet-Banks'!M9 -> 5.9900747 | P44: ='Balance Sheet-Banks'!N84/'Balance Sheet-Banks'!N9 -> 4.6061285 | Q44: ='Balance Sheet-Banks'!O84/'Balance Sheet-Banks'!O9 -> 0 | R44: ='Balance Sheet-Banks'!P84/'Balance Sheet-Banks'!P9 -> 0 | T44: ='Balance Sheet-Banks'!Q84/'Balance Sheet-Banks'!Q9 -> 8.4508516 | U44: ='Balance Sheet-Banks'!R84/'Balance Sheet-Banks'!R9 -> 8.2510501 | V44: ='Balance Sheet-Banks'!S84/'Balance Sheet-Banks'!S9 -> 8.2353547 | W44: ='Balance Sheet-Banks'!T84/'Balance Sheet-Banks'!T9 -> 7.9126729 | X44: ='Balance Sheet-Banks'!U84/'Balance Sheet-Banks'!U9 -> 7.9513603
A45: Cost of deposits | B45: ='Income Statement-Banks'!B9/'Balance Sheet-Banks'!B13 -> 0.059169219 | C45: ='Income Statement-Banks'!C9/'Balance Sheet-Banks'!C13 -> 0.049587927 | D45: ='Income Statement-Banks'!D9/'Balance Sheet-Banks'!D13 -> 0.042541184 | E45: ='Income Statement-Banks'!E9/'Balance Sheet-Banks'!E13 -> 0.045874409 | F45: ='Income Statement-Banks'!F9/'Balance Sheet-Banks'!F13 -> 0.057530318 | H45: ='Income Statement-Banks'!G9/'Balance Sheet-Banks'!G13 -> 0.054211338 | I45: ='Income Statement-Banks'!H9/'Balance Sheet-Banks'!H13 -> 0.044422773 | J45: ='Income Statement-Banks'!I9/'Balance Sheet-Banks'!I13 -> 0.037602193 | K45: ='Income Statement-Banks'!J9/'Balance Sheet-Banks'!J13 -> 0.041313782 | L45: ='Income Statement-Banks'!K9/'Balance Sheet-Banks'!K13 -> 0.06484891 | N45: ='Income Statement-Banks'!L9/'Balance Sheet-Banks'!L13 -> 0.05577721 | O45: ='Income Statement-Banks'!M9/'Balance Sheet-Banks'!M13 -> 0.043032584 | P45: ='Income Statement-Banks'!N9/'Balance Sheet-Banks'!N13 -> 0.036548458 | Q45: ='Income Statement-Banks'!O9/'Balance Sheet-Banks'!O13 -> 0.041742688 | R45: ='Income Statement-Banks'!P9/'Balance Sheet-Banks'!P13 -> 0.051336376 | T45: ='Income Statement-Banks'!Q9/'Balance Sheet-Banks'!Q13 -> 0.049210719 | U45: ='Income Statement-Banks'!R9/'Balance Sheet-Banks'!R13 -> 0.041990917 | V45: ='Income Statement-Banks'!S9/'Balance Sheet-Banks'!S13 -> 0.038213519 | W45: ='Income Statement-Banks'!T9/'Balance Sheet-Banks'!T13 -> 0.042515231 | X45: ='Income Statement-Banks'!U9/'Balance Sheet-Banks'!U13 -> 0.052297209

Sheet Financial Ratios-NBFCs
B1: FINANCIAL RATIOS
A2: Particulars | B2: #VALUE! | G2: #VALUE! | L2: #VALUE!
B3: 2020 | C3: 2021 | D3: 2022 | E3: 2023 | F3: 2024 | G3: 2020 | H3: 2021 | I3: 2022 | J3: 2023 | K3: 2024 | L3: 2020 | M3: 2021 | N3: 2022 | O3: 2023 | P3: 2024
A4: Profitability Ratios
A5: Net Interest Margin | B5: =('Income Statement-NBFCs'!B6-'Income Statement-NBFCs'!B17)/('Balance Sheet-NBFCs'!B27+'Balance Sheet-NBFCs'!B28) -> 0.022538474 | C5: =('Income Statement-NBFCs'!C6-'Income Statement-NBFCs'!C17)/('Balance Sheet-NBFCs'!C27+'Balance Sheet-NBFCs'!C28) -> 0.02484833 | D5: =('Income Statement-NBFCs'!D6-'Income Statement-NBFCs'!D17)/('Balance Sheet-NBFCs'!D27+'Balance Sheet-NBFCs'!D28) -> 0.02779029 | E5: =('Income Statement-NBFCs'!E6-'Income Statement-NBFCs'!E17)/('Balance Sheet-NBFCs'!E27+'Balance Sheet-NBFCs'!E28) -> 0.032097425 | F5: =('Income Statement-NBFCs'!F6-'Income Statement-NBFCs'!F17)/('Balance Sheet-NBFCs'!F27+'Balance Sheet-NBFCs'!F28) -> 0.030893292 | G5: =('Income Statement-NBFCs'!G6-'Income Statement-NBFCs'!G17)/('Balance Sheet-NBFCs'!G27+'Balance Sheet-NBFCs'!G28) -> 0.084930684 | H5: =('Income Statement-NBFCs'!H6-'Income Statement-NBFCs'!H17)/('Balance Sheet-NBFCs'!H27+'Balance Sheet-NBFCs'!H28) -> 0.08413534 | I5: =('Income Statement-NBFCs'!I6-'Income Statement-NBFCs'!I17)/('Balance Sheet-NBFCs'!I27+'Balance Sheet-NBFCs'!I28) -> 0.08602948 | ... P5: =('Income Statement-NBFCs'!P6-'Income Statement-NBFCs'!P17)/('Balance Sheet-NBFCs'!P27+'Balance Sheet-NBFCs'!P28) -> 0.10253835
A6: Return on Assets | B6: ='Income Statement-NBFCs'!B33/'Balance Sheet-NBFCs'!B37 -> 0.013429949 | C6: ='Income Statement-NBFCs'!C33/'Balance Sheet-NBFCs'!C37 -> 0.011970975 | D6: ='Income Statement-NBFCs'!D33/'Balance Sheet-NBFCs'!D37 -> 0.014623175 | E6: ='Income Statement-NBFCs'!E33/'Balance Sheet-NBFCs'!E37 -> 0.019454284 | F6: ='Income Statement-NBFCs'!F33/'Balance Sheet-NBFCs'!F37 -> 0.021157052 | G6: ='Income Statement-NBFCs'!G33/'Balance Sheet-NBFCs'!G37 -> 0.032019625 | H6: ='Income Statement-NBFCs'!H33/'Balance Sheet-NBFCs'!H37 -> 0.025775994 | I6: ='Income Statement-NBFCs'!I33/'Balance Sheet-NBFCs'!I37 -> 0.033073189 | ... P6: ='Income Statement-NBFCs'!P33/'Balance Sheet-NBFCs'!P37 -> 0.046310986
A7: Return on Equity | B7: ='Income Statement-NBFCs'!B33/'Balance Sheet-NBFCs'!B9 -> 0.075437814 | C7: ='Income Statement-NBFCs'!C33/'Balance Sheet-NBFCs'!C9 -> 0.075128228 | D7: ='Income Statement-NBFCs'!D33/'Balance Sheet-NBFCs'!D9 -> 0.10526363 | E7: ='Income Statement-NBFCs'!E33/'Balance Sheet-NBFCs'!E9 -> 0.11975409 | F7: ='Income Statement-NBFCs'!F33/'Balance Sheet-NBFCs'!F9 -> 0.14151469 | G7: ='Income Statement-NBFCs'!G33/'Balance Sheet-NBFCs'!G9 -> 0.16282511 | H7: ='Income Statement-NBFCs'!H33/'Balance Sheet-NBFCs'!H9 -> 0.11971859 | I7: ='Income Statement-NBFCs'!I33/'Balance Sheet-NBFCs'!I9 -> 0.16078237 | ... P7: ='Income Statement-NBFCs'!P33/'Balance Sheet-NBFCs'!P9 -> 0.17347158
A8: Cost to Income ratio | B8: =('Income Statement-NBFCs'!B17+'Income Statement-NBFCs'!B18+'Income Statement-NBFCs'!B19+'Income Statement-NBFCs'!B20+'Income Statement-NBFCs'!B21+'Income Statement-NBFCs'!B22)/'Income Statement-NBFCs'!B12 -> 0.7856252 | C8: =('Income Statement-NBFCs'!C17+'Income Statement-NBFCs'!C18+'Income Statement-NBFCs'!C19+'Income Statement-NBFCs'!C20+'Income Statement-NBFCs'!C21+'Income Statement-NBFCs'!C22)/'Income Statement-NBFCs'!C12 -> 0.80581355 | D8: =('Income Statement-NBFCs'!D17+'Income Statement-NBFCs'!D18+'Income Statement-NBFCs'!D19+'Income Statement-NBFCs'!D20+'Income Statement-NBFCs'!D21+'Income Statement-NBFCs'!D22)/'Income Statement-NBFCs'!D12 -> 0.74529424 | E8: =('Income Statement-NBFCs'!E17+'Income Statement-NBFCs'!E18+'Income Statement-NBFCs'!E19+'Income Statement-NBFCs'!E20+'Income Statement-NBFCs'!E21+'Income Statement-NBFCs'!E22)/'Income Statement-NBFCs'!E12 -> 0.70001218 | F8: =('Income Statement-NBFCs'!F17+'Income Statement-NBFCs'!F18+'Income Statement-NBFCs'!F19+'Income Statement-NBFCs'!F20+'Income Statement-NBFCs'!F21+'Income Statement-NBFCs'!F22)/'Income Statement-NBFCs'!F12 -> 0.71631455 | G8: =('Income Statement-NBFCs'!G17+'Income Statement-NBFCs'!G18+'Income Statement-NBFCs'!G19+'Income Statement-NBFCs'!G20+'Income Statement-NBFCs'!G21+'Income Statement-NBFCs'!G22)/'Income Statement-NBFCs'!G12 -> 0.72282 | H8: =('Income Statement-NBFCs'!H17+'Income Statement-NBFCs'!H18+'Income Statement-NBFCs'!H19+'Income Statement-NBFCs'!H20+'Income Statement-NBFCs'!H21+'Income Statement-NBFCs'!H22)/'Income Statement-NBFCs'!H12 -> 0.77586292 | I8: =('Income Statement-NBFCs'!I17+'Income Statement-NBFCs'!I18+'Income Statement-NBFCs'!I19+'Income Statement-NBFCs'!I20+'Income Statement-NBFCs'!I21+'Income Statement-NBFCs'!I22)/'Income Statement-NBFCs'!I12 -> 0.6998083 | ... P8: =('Income Statement-NBFCs'!P17+'Income Statement-NBFCs'!P18+'Income Statement-NBFCs'!P19+'Income Statement-NBFCs'!P20+'Income Statement-NBFCs'!P21+'Income Statement-NBFCs'!P22)/'Income Statement-NBFCs'!P12 -> 0.60858098
A9: Operating profit margin | B9: ='Income Statement-NBFCs'!B25/'Income Statement-NBFCs'!B12 -> 0.21445416 | C9: ='Income Statement-NBFCs'!C25/'Income Statement-NBFCs'!C12 -> 0.1943703 | D9: ='Income Statement-NBFCs'!D25/'Income Statement-NBFCs'!D12 -> 0.25483054 | E9: ='Income Statement-NBFCs'!E25/'Income Statement-NBFCs'!E12 -> 0.30011316 | F9: ='Income Statement-NBFCs'!F25/'Income Statement-NBFCs'!F12 -> 0.28373796 | G9: ='Income Statement-NBFCs'!G25/'Income Statement-NBFCs'!G12 -> 0.27762856 | H9: ='Income Statement-NBFCs'!H25/'Income Statement-NBFCs'!H12 -> 0.22469767 | I9: ='Income Statement-NBFCs'!I25/'Income Statement-NBFCs'!I12 -> 0.30044429 | ... P9: ='Income Statement-NBFCs'!P25/'Income Statement-NBFCs'!P12 -> 0.39813043
A10: Net Profit margin | B10: ='Income Statement-NBFCs'!B33/'Income Statement-NBFCs'!B14 -> 0.15921896 | C10: ='Income Statement-NBFCs'!C33/'Income Statement-NBFCs'!C14 -> 0.14362909 | D10: ='Income Statement-NBFCs'!D33/'Income Statement-NBFCs'!D14 -> 0.18837152 | E10: ='Income Statement-NBFCs'!E33/'Income Statement-NBFCs'!E14 -> 0.22201277 | F10: ='Income Statement-NBFCs'!F33/'Income Statement-NBFCs'!F14 -> 0.22726252 | G10: ='Income Statement-NBFCs'!G33/'Income Statement-NBFCs'!G14 -> 0.19949306 | H10: ='Income Statement-NBFCs'!H33/'Income Statement-NBFCs'!H14 -> 0.16564148 | I10: ='Income Statement-NBFCs'!I33/'Income Statement-NBFCs'!I14 -> 0.22212828 | ... P10: ='Income Statement-NBFCs'!P33/'Income Statement-NBFCs'!P14 -> 0.29464288
A11: Asset Quality Ratios
A12: Gross NPA ratio | B12: 0.0008 | C12: 0.0035 | D12: 0.0031 | E12: 0.0023 | F12: 0.003 | G12: 0.0161 | H12: 0.0179 | I12: 0.016 | J12: 0.0094 | K12: 0.0085 | L12: 0.022 | M12: 0.009 | N12: 0 | O12: 0 | P12: 0.016
A13: Net NPA Ratio | B13: 0.0005 | C13: 0.0018 | D13: 0.0014 | E13: 0.0008 | F13: 0.001 | G13: 0.0065 | H13: 0.0075 | I13: 0.0068 | J13: 0.0034 | K13: 0.0037 | L13: 0.0196 | M13: 0.0078 | N13: 0.0271 | O13: 0.0345 | P13: 0.0293
A14: Provision Coverage ratio | B14: =B39/B34 -> 0.27434808 | C14: =C39/C34 -> 0.30940576 | D14: =D39/D34 -> 0.23783017 | E14: =E39/E34 -> 0.055088147 | F14: =F39/F34 -> 0.21059069 | G14: =G39/G34 -> 0.15061368 | H14: =H39/H34 -> 0.050828448 | I14: =I39/I34 -> 0.061862261 | ... M14: =M39/M34 -> 0.15671011 | N14: 0 | O14: 0 | P14: =P39/P34 -> 0.12051852
A15: Capital Adequacy ratios
A16: Capital Adequacy ratio (CAR) | B16: =('Balance Sheet-NBFCs'!B43+'Balance Sheet-NBFCs'!B44)/'Balance Sheet-NBFCs'!B42 -> 0.25151808 | C16: =('Balance Sheet-NBFCs'!C43+'Balance Sheet-NBFCs'!C44)/'Balance Sheet-NBFCs'!C42 -> 0.21333963 | D16: =('Balance Sheet-NBFCs'!D43+'Balance Sheet-NBFCs'!D44)/'Balance Sheet-NBFCs'!D42 -> 0.197179 | E16: =('Balance Sheet-NBFCs'!E43+'Balance Sheet-NBFCs'!E44)/'Balance Sheet-NBFCs'!E42 -> 0.22971673 | F16: =('Balance Sheet-NBFCs'!F43+'Balance Sheet-NBFCs'!F44)/'Balance Sheet-NBFCs'!F42 -> 0.21282128 | G16: =('Balance Sheet-NBFCs'!G43+'Balance Sheet-NBFCs'!G44)/'Balance Sheet-NBFCs'!G42 -> 0.25008868 | H16: =('Balance Sheet-NBFCs'!H43+'Balance Sheet-NBFCs'!H44)/'Balance Sheet-NBFCs'!H42 -> 0.28308509 | I16: =('Balance Sheet-NBFCs'!I43+'Balance Sheet-NBFCs'!I44)/'Balance Sheet-NBFCs'!I42 -> 0.27222452 | ... P16: =('Balance Sheet-NBFCs'!P43+'Balance Sheet-NBFCs'!P44)/'Balance Sheet-NBFCs'!P42 -> 0
A17: Tier 1 capital ratio | B17: ='Balance Sheet-NBFCs'!B43/'Balance Sheet-NBFCs'!B42 -> 0.24478119 | C17: ='Balance Sheet-NBFCs'!C43/'Balance Sheet-NBFCs'!C42 -> 0.20698536 | D17: ='Balance Sheet-NBFCs'!D43/'Balance Sheet-NBFCs'!D42 -> 0.18956167 | E17: ='Balance Sheet-NBFCs'!E43/'Balance Sheet-NBFCs'!E42 -> 0.2218813 | F17: ='Balance Sheet-NBFCs'!F43/'Balance Sheet-NBFCs'!F42 -> 0.20674563 | G17: ='Balance Sheet-NBFCs'!G43/'Balance Sheet-NBFCs'!G42 -> 0.21270689 | H17: ='Balance Sheet-NBFCs'!H43/'Balance Sheet-NBFCs'!H42 -> 0.25112126 | I17: ='Balance Sheet-NBFCs'!I43/'Balance Sheet-NBFCs'!I42 -> 0.24751504 | ... P17: ='Balance Sheet-NBFCs'!P43/'Balance Sheet-NBFCs'!P42 -> 0
A18: CET 1 Ratio | B18: ='Balance Sheet-NBFCs'!B46 -> 0 | C18: ='Balance Sheet-NBFCs'!C46 -> 0 | D18: ='Balance Sheet-NBFCs'!D46 -> 0 | E18: ='Balance Sheet-NBFCs'!E46 -> 0 | F18: ='Balance Sheet-NBFCs'!F46 -> 0.09 | G18: ='Balance Sheet-NBFCs'!G46 -> 0.196 | H18: ='Balance Sheet-NBFCs'!H46 -> 0.236 | I18: ='Balance Sheet-NBFCs'!I46 -> 0.238 | ... K18: ='Balance Sheet-NBFCs'!K46 -> 0.227 | L18: ='Balance Sheet-NBFCs'!L45/'Balance Sheet-NBFCs'!L42 -> 0.2429986 | M18: ='Balance Sheet-NBFCs'!M45/'Balance Sheet-NBFCs'!M42 -> 0.26314143 | N18: ='Balance Sheet-NBFCs'!N45/'Balance Sheet-NBFCs'!N42 -> 0.29098575 | O18: ='Balance Sheet-NBFCs'!O45/'Balance Sheet-NBFCs'!O42 -> 0.31011667 | P18: ='Balance Sheet-NBFCs'!P45/'Balance Sheet-NBFCs'!P42 -> 0.29607881
A19: Liquidity & funding ratios
A20: Debt to AUM ratio | B20: ='Balance Sheet-NBFCs'!B13/'Balance Sheet-NBFCs'!B27 -> 0.63544556 | C20: ='Balance Sheet-NBFCs'!C13/'Balance Sheet-NBFCs'!C27 -> 0.60649872 | D20: ='Balance Sheet-NBFCs'!D13/'Balance Sheet-NBFCs'!D27 -> 0.52693802 | E20: ='Balance Sheet-NBFCs'!E13/'Balance Sheet-NBFCs'!E27 -> 0.54182245 | F20: ='Balance Sheet-NBFCs'!F13/'Balance Sheet-NBFCs'!F27 -> 0.53340895 | G20: ='Balance Sheet-NBFCs'!G13/'Balance Sheet-NBFCs'!G27 -> 0.38691256 | H20: ='Balance Sheet-NBFCs'!H13/'Balance Sheet-NBFCs'!H27 -> 0.32333746 | I20: ='Balance Sheet-NBFCs'!I13/'Balance Sheet-NBFCs'!I27 -> 0.28399664 | ... P20: ='Balance Sheet-NBFCs'!P13/'Balance Sheet-NBFCs'!P27 -> 0.56756501
A21: Debt to Equity Ratio | B21: ='Balance Sheet-NBFCs'!B13/'Balance Sheet-NBFCs'!B9 -> 3.1828892 | C21: ='Balance Sheet-NBFCs'!C13/'Balance Sheet-NBFCs'!C9 -> 3.3600432 | D21: ='Balance Sheet-NBFCs'!D13/'Balance Sheet-NBFCs'!D9 -> 3.6332684 | E21: ='Balance Sheet-NBFCs'!E13/'Balance Sheet-NBFCs'!E9 -> 3.204236 | F21: ='Balance Sheet-NBFCs'!F13/'Balance Sheet-NBFCs'!F9 -> 3.4576965 | G21: ='Balance Sheet-NBFCs'!G13/'Balance Sheet-NBFCs'!G9 -> 1.6920563 | H21: ='Balance Sheet-NBFCs'!H13/'Balance Sheet-NBFCs'!H9 -> 1.2847075 | I21: ='Balance Sheet-NBFCs'!I13/'Balance Sheet-NBFCs'!I9 -> 1.2436562 | ... P21: ='Balance Sheet-NBFCs'!P13/'Balance Sheet-NBFCs'!P9 -> 1.9434602
A22: Liquidity Coverage ratio | B22: 0 | C22: 0 | D22: =D38/D40 -> 1.0835388 | E22: =E38/E40 -> 0.32288723 | F22: =F38/F40 -> 0.35654287 | G22: 0 | H22: =H38/H40 -> 0.25773819 | I22: =I38/I40 -> 0.33453994 | J22: =J38/J40 -> 0.60797661 | K22: =K38/K40 -> 0.65003216 | L22: =L38/L40 -> 1.3037628 | M22: =M38/M40 -> 0.94309973 | N22: =N38/N40 -> 0.81816653 | O22: =O38/O40 -> 0.97542976 | P22: =P38/P40 -> 0.56487288
A23: Efficiency Ratios
A24: Operating expense ratio | B24: =('Income Statement-NBFCs'!B18+'Income Statement-NBFCs'!B20+'Income Statement-NBFCs'!B22)/'Balance Sheet-NBFCs'!B37 -> 0.010049591 | C24: =('Income Statement-NBFCs'!C18+'Income Statement-NBFCs'!C20+'Income Statement-NBFCs'!C22)/'Balance Sheet-NBFCs'!C37 -> 0.0081159826 | D24: =('Income Statement-NBFCs'!D18+'Income Statement-NBFCs'!D20+'Income Statement-NBFCs'!D22)/'Balance Sheet-NBFCs'!D37 -> 0.0091728165 | E24: =('Income Statement-NBFCs'!E18+'Income Statement-NBFCs'!E20+'Income Statement-NBFCs'!E22)/'Balance Sheet-NBFCs'!E37 -> 0.0092362222 | F24: =('Income Statement-NBFCs'!F18+'Income Statement-NBFCs'!F20+'Income Statement-NBFCs'!F22)/'Balance Sheet-NBFCs'!F37 -> 0.0081061174 | G24: =('Income Statement-NBFCs'!G18+'Income Statement-NBFCs'!G20+'Income Statement-NBFCs'!G22)/'Balance Sheet-NBFCs'!G37 -> 0.032642772 | H24: =('Income Statement-NBFCs'!H18+'Income Statement-NBFCs'!H20+'Income Statement-NBFCs'!H22)/'Balance Sheet-NBFCs'!H37 -> 0.029060059 | I24: =('Income Statement-NBFCs'!I18+'Income Statement-NBFCs'!I20+'Income Statement-NBFCs'!I22)/'Balance Sheet-NBFCs'!I37 -> 0.033883475 | ... P24: =('Income Statement-NBFCs'!P18+'Income Statement-NBFCs'!P20+'Income Statement-NBFCs'!P22)/'Balance Sheet-NBFCs'!P37 -> 0.032033291
A25: Non-interest income ratio | B25: =('Income Statement-NBFCs'!B14-'Income Statement-NBFCs'!B6)/'Income Statement-NBFCs'!B14 -> 0.12967505 | C25: =('Income Statement-NBFCs'!C14-'Income Statement-NBFCs'!C6)/'Income Statement-NBFCs'!C14 -> 0.088058746 | D25: =('Income Statement-NBFCs'!D14-'Income Statement-NBFCs'!D6)/'Income Statement-NBFCs'!D14 -> 0.075755283 | E25: =('Income Statement-NBFCs'!E14-'Income Statement-NBFCs'!E6)/'Income Statement-NBFCs'!E14 -> 0.069932785 | F25: =('Income Statement-NBFCs'!F14-'Income Statement-NBFCs'!F6)/'Income Statement-NBFCs'!F14 -> 0.05452426 | G25: =('Income Statement-NBFCs'!G14-'Income Statement-NBFCs'!G6)/'Income Statement-NBFCs'!G14 -> 0.12943561 | H25: =('Income Statement-NBFCs'!H14-'Income Statement-NBFCs'!H6)/'Income Statement-NBFCs'!H14 -> 0.12665981 | I25: =('Income Statement-NBFCs'!I14-'Income Statement-NBFCs'!I6)/'Income Statement-NBFCs'!I14 -> 0.13813506 | ... P25: =('Income Statement-NBFCs'!P14-'Income Statement-NBFCs'!P6)/'Income Statement-NBFCs'!P14 -> 0.040694552
A26: Cash flow ratios
A27: Operating cash flow/Net Profit | B27: ='Cash Flow Statement-NBFCs'!B48/'Income Statement-NBFCs'!B33 -> -24.309093 | C27: ='Cash Flow Statement-NBFCs'!C48/'Income Statement-NBFCs'!C33 -> -11.200093 | D27: ='Cash Flow Statement-NBFCs'!D48/'Income Statement-NBFCs'!D33 -> -17.560525 | E27: ='Cash Flow Statement-NBFCs'!E48/'Income Statement-NBFCs'!E33 -> -11.394315 | F27: ='Cash Flow Statement-NBFCs'!F48/'Income Statement-NBFCs'!F33 -> -8.9116981 | G27: ='Cash Flow Statement-NBFCs'!G48/'Income Statement-NBFCs'!G33 -> -4.6404521 | H27: ='Cash Flow Statement-NBFCs'!H48/'Income Statement-NBFCs'!H33 -> -0.18264771 | I27: ='Cash Flow Statement-NBFCs'!I48/'Income Statement-NBFCs'!I33 -> -5.2685555 | ... P27: ='Cash Flow Statement-NBFCs'!P48/'Income Statement-NBFCs'!P33 -> -3.0786186
A28: Cash flow coverage ratio | B28: ='Cash Flow Statement-NBFCs'!B48/('Income Statement-NBFCs'!B17+'Financial Ratios-NBFCs'!B41) -> -3.0626058 | C28: ='Cash Flow Statement-NBFCs'!C48/('Income Statement-NBFCs'!C17+'Financial Ratios-NBFCs'!C41) -> -1.0166281 | D28: ='Cash Flow Statement-NBFCs'!D48/('Income Statement-NBFCs'!D17+'Financial Ratios-NBFCs'!D41) -> -1.3725864 | E28: ='Cash Flow Statement-NBFCs'!E48/('Income Statement-NBFCs'!E17+'Financial Ratios-NBFCs'!E41) -> -1.0274598 | F28: ='Cash Flow Statement-NBFCs'!F48/('Income Statement-NBFCs'!F17+'Financial Ratios-NBFCs'!F41) -> -0.93444346 | G28: ='Cash Flow Statement-NBFCs'!G48/('Income Statement-NBFCs'!G17+'Financial Ratios-NBFCs'!G41) -> -1.0817617 | H28: ='Cash Flow Statement-NBFCs'!H48/('Income Statement-NBFCs'!H17+'Financial Ratios-NBFCs'!H41) -> -0.063717087 | I28: ='Cash Flow Statement-NBFCs'!I48/('Income Statement-NBFCs'!I17+'Financial Ratios-NBFCs'!I41) -> -1.3397813 | ... P28: ='Cash Flow Statement-NBFCs'!P48/('Income Statement-NBFCs'!P17+'Financial Ratios-NBFCs'!P41) -> -2.0136156
A29: Loan Growth rate | B29: 0.26 | C29: =('Balance Sheet-NBFCs'!C27-'Balance Sheet-NBFCs'!B27)/'Balance Sheet-NBFCs'!B27 -> 0.19458124 | D29: =('Balance Sheet-NBFCs'!D27-'Balance Sheet-NBFCs'!C27)/'Balance Sheet-NBFCs'!C27 -> 0.39089168 | E29: =('Balance Sheet-NBFCs'!E27-'Balance Sheet-NBFCs'!D27)/'Balance Sheet-NBFCs'!D27 -> 0.33629785 | F29: =('Balance Sheet-NBFCs'!F27-'Balance Sheet-NBFCs'!E27)/'Balance Sheet-NBFCs'!E27 -> 0.27669914 | G29: 0.26 | H29: =('Balance Sheet-NBFCs'!H27-'Balance Sheet-NBFCs'!G27)/'Balance Sheet-NBFCs'!G27 -> 0.037565203 | I29: =('Balance Sheet-NBFCs'!I27-'Balance Sheet-NBFCs'!H27)/'Balance Sheet-NBFCs'!H27 -> 0.30497876 | J29: =('Balance Sheet-NBFCs'!J27-'Balance Sheet-NBFCs'!I27)/'Balance Sheet-NBFCs'!I27 -> 0.26561915 | K29: =('Balance Sheet-NBFCs'!K27-'Balance Sheet-NBFCs'!J27)/'Balance Sheet-NBFCs'!J27 -> 0.34682281 | L29: 0.22 | M29: =('Balance Sheet-NBFCs'!M27-'Balance Sheet-NBFCs'!L27)/'Balance Sheet-NBFCs'!L27 -> 0.24944422 | N29: =('Balance Sheet-NBFCs'!N27-'Balance Sheet-NBFCs'!M27)/'Balance Sheet-NBFCs'!M27 -> 0.097249927 | O29: =('Balance Sheet-NBFCs'!O27-'Balance Sheet-NBFCs'!N27)/'Balance Sheet-NBFCs'!N27 -> 0.093397851 | P29: =('Balance Sheet-NBFCs'!P27-'Balance Sheet-NBFCs'!O27)/'Balance Sheet-NBFCs'!O27 -> 0.24991767
A30: Borrowings Growth rate | B30: -0.2219 | C30: =('Balance Sheet-NBFCs'!C13-'Balance Sheet-NBFCs'!B13)/'Balance Sheet-NBFCs'!B13 -> 0.14016375 | D30: =('Balance Sheet-NBFCs'!D13-'Balance Sheet-NBFCs'!C13)/'Balance Sheet-NBFCs'!C13 -> 0.20843406 | E30: =('Balance Sheet-NBFCs'!E13-'Balance Sheet-NBFCs'!D13)/'Balance Sheet-NBFCs'!D13 -> 0.37404427 | F30: =('Balance Sheet-NBFCs'!F13-'Balance Sheet-NBFCs'!E13)/'Balance Sheet-NBFCs'!E13 -> 0.25687437 | G30: 0 | H30: =('Balance Sheet-NBFCs'!H13-'Balance Sheet-NBFCs'!G13)/'Balance Sheet-NBFCs'!G13 -> -0.13292116 | I30: =('Balance Sheet-NBFCs'!I13-'Balance Sheet-NBFCs'!H13)/'Balance Sheet-NBFCs'!H13 -> 0.14620058 | J30: =('Balance Sheet-NBFCs'!J13-'Balance Sheet-NBFCs'!I13)/'Balance Sheet-NBFCs'!I13 -> 0.50007468 | K30: =('Balance Sheet-NBFCs'!K13-'Balance Sheet-NBFCs'!J13)/'Balance Sheet-NBFCs'!J13 -> 0.36870989 | L30: 0 | M30: =('Balance Sheet-NBFCs'!M13-'Balance Sheet-NBFCs'!L13)/'Balance Sheet-NBFCs'!L13 -> 0.16958254 | N30: =('Balance Sheet-NBFCs'!N13-'Balance Sheet-NBFCs'!M13)/'Balance Sheet-NBFCs'!M13 -> 0.16393691 | O30: =('Balance Sheet-NBFCs'!O13-'Balance Sheet-NBFCs'!N13)/'Balance Sheet-NBFCs'!N13 -> -0.0063116866 | P30: =('Balance Sheet-NBFCs'!P13-'Balance Sheet-NBFCs'!O13)/'Balance Sheet-NBFCs'!O13 -> 0.23288392
A33: Particulars | B33: 2020 | C33: 2021 | D33: 2022 | E33: 2023 | F33: 2024 | G33: 2020 | H33: 2021 | I33: 2022 | J33: 2023 | K33: 2024 | L33: 2020 | M33: 2021 | N33: 2022 | O33: 2023 | P33: 2024
A34: Gross NPA | B34: =B12*B37 -> 22.380328 | C34: =C12*C37 -> 116.96615 | D34: =D12*D37 -> 144.09442 | E34: =E12*E37 -> 142.86195 | F34: =F12*F37 -> 237.90225 | G34: =G12*G37 -> 2276.1544 | H34: =H12*H37 -> 2625.695 | I34: =I12*I37 -> 3062.772 | ... P34: =P12*P37 -> 14109.947
A35: Net NPA | B35: =B13*B37 -> 13.987705 | C35: =C13*C37 -> 60.15402 | D35: =D13*D37 -> 65.074898 | E35: =E13*E37 -> 49.691112 | F35: =F13*F37 -> 79.30075 | G35: =G13*G37 -> 918.94432 | H35: =H13*H37 -> 1100.1515 | I35: =I13*I37 -> 1301.6781 | ... P35: =P13*P37 -> 25838.841
A36: CASA
A37: Advances | B37: ='Balance Sheet-NBFCs'!B27 -> 27975.41 | C37: ='Balance Sheet-NBFCs'!C27 -> 33418.9 | D37: ='Balance Sheet-NBFCs'!D27 -> 46482.07 | E37: ='Balance Sheet-NBFCs'!E27 -> 62113.89 | F37: ='Balance Sheet-NBFCs'!F27 -> 79300.75 | G37: ='Balance Sheet-NBFCs'!G27 -> 141376.05 | H37: ='Balance Sheet-NBFCs'!H27 -> 146686.87 | I37: ='Balance Sheet-NBFCs'!I27 -> 191423.25 | ... P37: ='Balance Sheet-NBFCs'!P27 -> 881871.71
A38: Average Total High quality liquid assets (HQLAs) | D38: 896.65 | E38: 1519.63 | F38: 2015.79 | H38: 4304.3 | I38: 5212.43 | J38: 9733.59 | K38: 11975.77 | L38: 79643.05 | M38: 62139.87 | N38: 53466.07 | O38: 39191.89 | P38: 36424.37
A39: Provision towards NPA | B39: 6.14 | C39: 36.19 | D39: 34.27 | E39: 7.87 | F39: 50.1 | G39: 342.82 | H39: 133.46 | I39: 189.47 | J39: -350.29 | K39: 79.42 | L39: 287.96 | M39: 829.43 | N39: 979.1 | O39: 426 | P39: 1700.51
A40: Average Total Net cash outflows | D40: 827.52 | E40: 4706.38 | F40: 5653.71 | H40: 16700.28 | I40: 15580.89 | J40: 16009.81 | K40: 18423.35 | L40: 61087.07 | M40: 65888.97 | N40: 65348.64 | O40: 40179.1 | P40: 64482.42
A41: Repayment of Borrowings | B41: 1728.23 | C41: =-'Cash Flow Statement-NBFCs'!C82 -> 3026.88 | D41: =-'Cash Flow Statement-NBFCs'!D82 -> 6923.39 | E41: =-'Cash Flow Statement-NBFCs'!E82 -> 10737.42 | F41: =-'Cash Flow Statement-NBFCs'!F82 -> 11817.87 | G41: 13106.79 | H41: =-'Cash Flow Statement-NBFCs'!H82 -> 3255.6 | I41: =-'Cash Flow Statement-NBFCs'!I82 -> 17889.57 | J41: =-'Cash Flow Statement-NBFCs'!J82 -> 36473.64 | K41: =-'Cash Flow Statement-NBFCs'!K82 -> 34375.91 | L41: 4552.68 | M41: 8360.711 | N41: 8736.69 | O41: 14052.376 | P41: 14004.304
A42: Market Price | B42: 0 | C42: 0 | D42: 0 | E42: 0 | F42: 154.06
A43: Market Cap | B43: 0 | C43: 0 | D43: 0 | E43: 0 | F43: =F42*'Company Profile'!G14 -> 128310.53
A44: P/B | B44: =B43/'Balance Sheet-NBFCs'!B9 -> 0 | C44: =C43/'Balance Sheet-NBFCs'!C9 -> 0 | D44: =D43/'Balance Sheet-NBFCs'!D9 -> 0 | E44: =E43/'Balance Sheet-NBFCs'!E9 -> 0 | F44: =F43/'Balance Sheet-NBFCs'!F9 -> 10.488457 | G44: =G43/'Balance Sheet-NBFCs'!G9 -> 0 | H44: =H43/'Balance Sheet-NBFCs'!H9 -> 0 | I44: =I43/'Balance Sheet-NBFCs'!I9 -> 0 | ... P44: =P43/'Balance Sheet-NBFCs'!P9 -> 0

Sheet Dupont Analysis
A2: Company | B2: Metric | C2: 2020 | D2: 2021 | E2: 2022 | F2: 2023 | G2: 2024 | H2: CAGR | J2: Company | K2: Metric | L2: 2020 | M2: 2021 | N2: 2022 | O2: 2023 | P2: 2024 | Q2: CAGR
A3: Axis Bank | B3: Net Income | C3: ='Income Statement-Banks'!B15 -> 1853.1105 | D3: ='Income Statement-Banks'!C15 -> 7195.5 | E3: ='Income Statement-Banks'!D15 -> 14119.29 | F3: ='Income Statement-Banks'!E15 -> 10818.45 | G3: ='Income Statement-Banks'!F15 -> 26386.2 | H3: =(G3/C3)^(1/5)-1 -> 0.70096394 | J3: BHFL | K3: Net Income | L3: ='Income Statement-NBFCs'!B33 -> 421.33 | M3: ='Income Statement-NBFCs'!C33 -> 453.19 | N3: ='Income Statement-NBFCs'!D33 -> 709.62 | O3: ='Income Statement-NBFCs'!E33 -> 1257.8 | P3: ='Income Statement-NBFCs'!F33 -> 1731.22 | Q3: =(Table4[[#This Row],[2024]]/Table4[[#This Row],[2020]])^(1/5)-1 -> 0.32661827
A4: Axis Bank | B4: Revenue | C4: ='Income Statement-Banks'!B7 -> 80057.67 | D4: ='Income Statement-Banks'!C7 -> 77974.28 | E4: ='Income Statement-Banks'!D7 -> 86114.19 | F4: ='Income Statement-Banks'!E7 -> 105797.3 | G4: ='Income Statement-Banks'!F7 -> 137989.36 | H4: =(G4/C4)^(1/5)-1 -> 0.11503508 | J4: BHFL | K4: Revenue | L4: ='Income Statement-NBFCs'!B12 -> 2646.02 | M4: ='Income Statement-NBFCs'!C12 -> 3154.7 | N4: ='Income Statement-NBFCs'!D12 -> 3766.66 | O4: ='Income Statement-NBFCs'!E12 -> 5664.73 | P4: ='Income Statement-NBFCs'!F12 -> 7617.31 | Q4: =(Table4[[#This Row],[2024]]/Table4[[#This Row],[2020]])^(1/5)-1 -> 0.23549702
A5: Axis Bank | B5: Average total assets | C5: ='Balance Sheet-Banks'!B79 -> 927871.69 | D5: =AVERAGE('Balance Sheet-Banks'!B79:C79) -> 964488.11 | E5: =AVERAGE('Balance Sheet-Banks'!C79:D79) -> 1098316.5 | F5: =AVERAGE('Balance Sheet-Banks'!D79:E79) -> 1269973.2 | G5: =AVERAGE('Balance Sheet-Banks'!E79:F79) -> 1431328.2 | H5: =(G5/C5)^(1/5)-1 -> 0.090561755 | J5: BHFL | K5: Average total assets | L5: ='Balance Sheet-NBFCs'!B37 -> 31372.42 | M5: =AVERAGE('Balance Sheet-NBFCs'!B37:C37) -> 34614.91 | N5: =AVERAGE('Balance Sheet-NBFCs'!C37:D37) -> 43192.24 | O5: =AVERAGE('Balance Sheet-NBFCs'!D37:E37) -> 56590.61 | P5: =AVERAGE('Balance Sheet-NBFCs'!E37:F37) -> 73240.615 | Q5: =(Table4[[#This Row],[2024]]/Table4[[#This Row],[2020]])^(1/5)-1 -> 0.1847884
A6: Axis Bank | B6: Average Shareholder's Equity | C6: ='Balance Sheet-Banks'!B9 -> 86453.97 | D6: =AVERAGE('Balance Sheet-Banks'!B9:C9) -> 95110.71 | E6: =AVERAGE('Balance Sheet-Banks'!C9:D9) -> 111144.73 | F6: =AVERAGE('Balance Sheet-Banks'!D9:E9) -> 124348.55 | G6: =AVERAGE('Balance Sheet-Banks'!E9:F9) -> 143849.03 | H6: =(G6/C6)^(1/5)-1 -> 0.10719572 | J6: BHFL | K6: Average Shareholder's Equity | L6: ='Balance Sheet-NBFCs'!B9 -> 5585.13 | M6: =AVERAGE('Balance Sheet-NBFCs'!B9:C9) -> 5808.675 | N6: =AVERAGE('Balance Sheet-NBFCs'!C9:D9) -> 6386.79 | O6: =AVERAGE('Balance Sheet-NBFCs'!D9:E9) -> 8622.275 | P6: =AVERAGE('Balance Sheet-NBFCs'!E9:F9) -> 11368.345 | Q6: =(Table4[[#This Row],[2024]]/Table4[[#This Row],[2020]])^(1/5)-1 -> 0.15274379
A7: Axis Bank | B7: Net Profit Margin | C7: =C3/C4 -> 0.023147195 | D7: =D3/D4 -> 0.092280429 | E7: =E3/E4 -> 0.16396009 | F7: =F3/F4 -> 0.10225639 | G7: =G3/G4 -> 0.19121909 | H7: =AVERAGE(C7:G7) -> 0.11457264 | J7: BHFL | K7: Net Profit Margin | L7: =L3/L4 -> 0.1592316 | M7: =M3/M4 -> 0.1436555 | N7: =N3/N4 -> 0.18839502 | O7: =O3/O4 -> 0.22204059 | P7: =P3/P4 -> 0.22727446 | Q7: =AVERAGE(Table4[[#This Row],[2020]:[2024]]) -> 0.18811943
A8: Axis Bank | B8: Asset Turnover | C8: =C4/C5 -> 0.086280971 | D8: =D4/D5 -> 0.080845247 | E8: =E4/E5 -> 0.078405622 | F8: =F4/F5 -> 0.083306716 | G8: =G4/G5 -> 0.096406509 | H8: =AVERAGE(C8:G8) -> 0.085049013 | J8: BHFL | K8: Asset Turnover | L8: =L4/L5 -> 0.084342234 | M8: =M4/M5 -> 0.091137027 | N8: =N4/N5 -> 0.087206869 | O8: =O4/O5 -> 0.10010018 | P8: =P4/P5 -> 0.10400391 | Q8: =AVERAGE(Table4[[#This Row],[2020]:[2024]]) -> 0.093358042
A9: Axis Bank | B9: Equity multiplier | C9: =C5/C6 -> 10.732552 | D9: =D5/D6 -> 10.140689 | E9: =E5/E6 -> 9.8818588 | F9: =F5/F6 -> 10.213012 | G9: =G5/G6 -> 9.9502113 | H9: =AVERAGE(C9:G9) -> 10.183664 | J9: BHFL | K9: Equity multiplier | L9: =L5/L6 -> 5.6171334 | M9: =M5/M6 -> 5.9591749 | N9: =N5/N6 -> 6.7627462 | O9: =O5/O6 -> 6.5633038 | P9: =P5/P6 -> 6.4425046 | Q9: =AVERAGE(Table4[[#This Row],[2020]:[2024]]) -> 6.2689726
A10: Axis Bank | B10: Return on Equity | C10: =C7*C8*C9 -> 0.021434649 | D10: =D7*D8*D9 -> 0.075653941 | E10: =E7*E8*E9 -> 0.12703517 | F10: =F7*F8*F9 -> 0.087001011 | G10: =G7*G8*G9 -> 0.18342981 | H10: =AVERAGE(C10:G10) -> 0.098910916 | J10: BHFL | K10: Return on Equity | L10: =L7*L8*L9 -> 0.075437814 | M10: =M7*M8*M9 -> 0.078019514 | N10: =N7*N8*N9 -> 0.11110746 | O10: =O7*O8*O9 -> 0.14587797 | P10: =P7*P8*P9 -> 0.15228426 | Q10: =AVERAGE(Table4[[#This Row],[2020]:[2024]]) -> 0.1125454
A11: HDFC Bank | B11: Net Income | C11: ='Income Statement-Banks'!G15 -> 27253.951 | D11: ='Income Statement-Banks'!H15 -> 31833.209 | E11: ='Income Statement-Banks'!I15 -> 38052.75 | F11: ='Income Statement-Banks'!J15 -> 45997.11 | G11: ='Income Statement-Banks'!K15 -> 64062.04 | H11: =(Table3[[#This Row],[2024]]/Table3[[#This Row],[2020]])^(1/5)-1 -> 0.18640853 | J11: BFS | K11: Net Income | L11: ='Income Statement-NBFCs'!G33 -> 5263.75 | M11: ='Income Statement-NBFCs'!H33 -> 4419.82 | N11: ='Income Statement-NBFCs'!I33 -> 7028.23 | O11: ='Income Statement-NBFCs'!J33 -> 11507.69 | P11: ='Income Statement-NBFCs'!K33 -> 14451.17 | Q11: =(Table4[[#This Row],[2024]]/Table4[[#This Row],[2020]])^(1/5)-1 -> 0.22383129
A12: HDFC Bank | B12: Revenue | C12: ='Income Statement-Banks'!G7 -> 147068.27 | D12: ='Income Statement-Banks'!H7 -> 155885.27 | E12: ='Income Statement-Banks'!I7 -> 167695.4 | F12: ='Income Statement-Banks'!J7 -> 204666.1 | G12: ='Income Statement-Banks'!K7 -> 407994.77 | H12: =(Table3[[#This Row],[2024]]/Table3[[#This Row],[2020]])^(1/5)-1 -> 0.22638583 | J12: BFS | K12: Revenue | L12: ='Income Statement-NBFCs'!G14 -> 26385.63 | M12: ='Income Statement-NBFCs'!H12 -> 26668.1 | N12: ='Income Statement-NBFCs'!I12 -> 31632.42 | O12: ='Income Statement-NBFCs'!J12 -> 41410.16 | P12: ='Income Statement-NBFCs'!K12 -> 54969.49 | Q12: =(Table4[[#This Row],[2024]]/Table4[[#This Row],[2020]])^(1/5)-1 -> 0.15811276
A13: HDFC Bank | B13: Average total assets | C13: ='Balance Sheet-Banks'!G79 -> 1580820.3 | D13: =AVERAGE('Balance Sheet-Banks'!G79:H79) -> 1690163.4 | E13: =AVERAGE('Balance Sheet-Banks'!H79:I79) -> 1961146 | F13: =AVERAGE('Balance Sheet-Banks'!I79:J79) -> 2326534.6 | G13: =AVERAGE('Balance Sheet-Banks'!J79:K79) -> 3280239 | H13: =(Table3[[#This Row],[2024]]/Table3[[#This Row],[2020]])^(1/5)-1 -> 0.15718979 | J13: BFS | K13: Average total assets | L13: ='Balance Sheet-NBFCs'!G37 -> 164391.37 | M13: =AVERAGE('Balance Sheet-NBFCs'!G37:H37) -> 167930.89 | N13: =AVERAGE('Balance Sheet-NBFCs'!H37:I37) -> 191987.88 | O13: =AVERAGE('Balance Sheet-NBFCs'!I37:J37) -> 243865.84 | P13: =AVERAGE('Balance Sheet-NBFCs'!J37:K37) -> 325483.97 | Q13: =(Table4[[#This Row],[2024]]/Table4[[#This Row],[2020]])^(1/5)-1 -> 0.146384
A14: HDFC Bank | B14: Average Shareholder's Equity | C14: ='Balance Sheet-Banks'!G9 -> 176935.33 | D14: =AVERAGE('Balance Sheet-Banks'!G9:H9) -> 193689.14 | E14: =AVERAGE('Balance Sheet-Banks'!H9:I9) -> 229244.76 | F14: =AVERAGE('Balance Sheet-Banks'!I9:J9) -> 269172.17 | G14: =AVERAGE('Balance Sheet-Banks'!J9:K9) -> 380038.21 | H14: =(Table3[[#This Row],[2024]]/Table3[[#This Row],[2020]])^(1/5)-1 -> 0.16520554 | J14: BFS | K14: Average Shareholder's Equity | L14: ='Balance Sheet-NBFCs'!G9 -> 32327.63 | M14: =AVERAGE('Balance Sheet-NBFCs'!G9:H9) -> 34623.02 | N14: =AVERAGE('Balance Sheet-NBFCs'!H9:I9) -> 40315.55 | O14: =AVERAGE('Balance Sheet-NBFCs'!I9:J9) -> 49042.335 | P14: =AVERAGE('Balance Sheet-NBFCs'!J9:K9) -> 65533.665 | Q14: =(Table4[[#This Row],[2024]]/Table4[[#This Row],[2020]])^(1/5)-1 -> 0.15180277
A15: HDFC Bank | B15: Net Profit Margin | C15: =C11/C12 -> 0.18531496 | D15: =D11/D12 -> 0.20420921 | E15: =E11/E12 -> 0.22691588 | F15: =F11/F12 -> 0.2247422 | G15: =G11/G12 -> 0.15701682 | H15: =AVERAGE(C15:G15) -> 0.19963982 | J15: BFS | K15: Net Profit Margin | L15: =L11/L12 -> 0.19949306 | M15: =M11/M12 -> 0.16573434 | N15: =N11/N12 -> 0.22218439 | O15: =O11/O12 -> 0.27789533 | P15: =P11/P12 -> 0.26289438 | Q15: =AVERAGE(Table4[[#This Row],[2020]:[2024]]) -> 0.2256403
A16: HDFC Bank | B16: Asset Turnover | C16: =C12/C13 -> 0.09303288 | D16: =D12/D13 -> 0.092230888 | E16: =E12/E13 -> 0.08550888 | F16: =F12/F13 -> 0.087970367 | G16: =G12/G13 -> 0.12437959 | H16: =AVERAGE(C16:G16) -> 0.09662452 | J16: BFS | K16: Asset Turnover | L16: =L12/L13 -> 0.16050496 | M16: =M12/M13 -> 0.15880402 | N16: =N12/N13 -> 0.16476259 | O16: =O12/O13 -> 0.16980714 | P16: =P12/P13 -> 0.1688854 | Q16: =AVERAGE(Table4[[#This Row],[2020]:[2024]]) -> 0.16455282
A17: HDFC Bank | B17: Equity multiplier | C17: =C13/C14 -> 8.9344525 | D17: =D13/D14 -> 8.7261654 | E17: =E13/E14 -> 8.5548129 | F17: =F13/F14 -> 8.6432954 | G17: =G13/G14 -> 8.63134 | H17: =AVERAGE(C17:G17) -> 8.6980133 | J17: BFS | K17: Equity multiplier | L17: =L13/L14 -> 5.0851662 | M17: =M13/M14 -> 4.8502668 | N17: =N13/N14 -> 4.7621297 | O17: =O13/O14 -> 4.9725576 | P17: =P13/P14 -> 4.9666681 | Q17: =AVERAGE(Table4[[#This Row],[2020]:[2024]]) -> 4.9273577
A18: HDFC Bank | B18: Return on Equity | C18: =C15*C16*C17 -> 0.1540334 | D18: =D15*D16*D17 -> 0.16435206 | E18: =E15*E16*E17 -> 0.1659918 | F18: =F15*F16*F17 -> 0.1708836 | G18: =G15*G16*G17 -> 0.16856737 | H18: =AVERAGE(C18:G18) -> 0.16476565 | J18: BFS | K18: Return on Equity | L18: =L15*L16*L17 -> 0.16282511 | M18: =M15*M16*M17 -> 0.12765553 | N18: =N15*N16*N17 -> 0.1743305 | O18: =O15*O16*O17 -> 0.23464809 | P18: =P15*P16*P17 -> 0.22051521 | Q18: =AVERAGE(Table4[[#This Row],[2020]:[2024]]) -> 0.18399489
A19: ICICI Bank | B19: Net Income | C19: ='Income Statement-Banks'!L15 -> 9566.3078 | D19: ='Income Statement-Banks'!M15 -> 16192.684 | E19: ='Income Statement-Banks'!N15 -> 23339.491 | F19: ='Income Statement-Banks'!O15 -> 34036.641 | G19: ='Income Statement-Banks'!P15 -> 44256.373 | H19: =(Table3[[#This Row],[2024]]/Table3[[#This Row],[2020]])^(1/5)-1 -> 0.35845825 | J19: MFL | K19: Net Income | L19: ='Income Statement-NBFCs'!L33 -> 31686.81 | M19: ='Income Statement-NBFCs'!M33 -> 38188.7 | N19: ='Income Statement-NBFCs'!N33 -> 40313.24 | O19: ='Income Statement-NBFCs'!O33 -> 36697.66 | P19: ='Income Statement-NBFCs'!P33 -> 44675.94 | Q19: =(Table4[[#This Row],[2024]]/Table4[[#This Row],[2020]])^(1/5)-1 -> 0.071122238
A20: ICICI Bank | B20: Revenue | C20: ='Income Statement-Banks'!L7 -> 149786.1 | D20: ='Income Statement-Banks'!M7 -> 98086.798 | E20: ='Income Statement-Banks'!N7 -> 104892.08 | F20: ='Income Statement-Banks'!O7 -> 186178.8 | G20: ='Income Statement-Banks'!P7 -> 236037.73 | H20: =(Table3[[#This Row],[2024]]/Table3[[#This Row],[2020]])^(1/5)-1 -> 0.09522155 | J20: MFL | K20: Revenue | L20: ='Income Statement-NBFCs'!L12 -> 96839.8 | M20: ='Income Statement-NBFCs'!M12 -> 115345.63 | N20: ='Income Statement-NBFCs'!N12 -> 121849.09 | O20: ='Income Statement-NBFCs'!O12 -> 118976.63 | P20: ='Income Statement-NBFCs'!P12 -> 150616.57 | Q20: =(Table4[[#This Row],[2024]]/Table4[[#This Row],[2020]])^(1/5)-1 -> 0.092354932
A21: ICICI Bank | B21: Average total assets | C21: ='Balance Sheet-Banks'!L79 -> 1377292.1 | D21: =AVERAGE('Balance Sheet-Banks'!L79:M79) -> 1303862.3 | E21: =AVERAGE('Balance Sheet-Banks'!M79:N79) -> 1320865.1 | F21: =AVERAGE('Balance Sheet-Banks'!N79:O79) -> 1684894 | G21: =AVERAGE('Balance Sheet-Banks'!O79:P79) -> 2161276.6 | H21: =(Table3[[#This Row],[2024]]/Table3[[#This Row],[2020]])^(1/5)-1 -> 0.094301154 | J21: MFL | K21: Average total assets | L21: ='Balance Sheet-NBFCs'!L37 -> 548816.92 | M21: =AVERAGE('Balance Sheet-NBFCs'!L37:M37) -> 617615.64 | N21: =AVERAGE('Balance Sheet-NBFCs'!M37:N37) -> 724789.54 | O21: =AVERAGE('Balance Sheet-NBFCs'!N37:O37) -> 782326.97 | P21: =AVERAGE('Balance Sheet-NBFCs'!O21:P21) -> 883091.7 | Q21: =(Table4[[#This Row],[2024]]/Table4[[#This Row],[2020]])^(1/5)-1 -> 0.09980493
A22: ICICI Bank | B22: Average Shareholder's Equity | C22: ='Balance Sheet-Banks'!L9 -> 129754.8 | D22: =AVERAGE('Balance Sheet-Banks'!L9:M9) -> 138631.99 | E22: =AVERAGE('Balance Sheet-Banks'!M9:N9) -> 159010.57 | F22: =AVERAGE('Balance Sheet-Banks'!N9:O9) -> 195848.24 | G22: =AVERAGE('Balance Sheet-Banks'!O9:P9) -> 245608.37 | H22: =(Table3[[#This Row],[2024]]/Table3[[#This Row],[2020]])^(1/5)-1 -> 0.13611932 | J22: MFL | K22: Average Shareholder's Equity | L22: ='Balance Sheet-NBFCs'!L9 -> 120013.52 | M22: =AVERAGE('Balance Sheet-NBFCs'!L9:M9) -> 138804.76 | N22: =AVERAGE('Balance Sheet-NBFCs'!M9:N9) -> 174487.48 | O22: =AVERAGE('Balance Sheet-NBFCs'!N9:O9) -> 206453.5 | P22: =AVERAGE('Balance Sheet-NBFCs'!O9:P9) -> 239534.22 | Q22: =(Table4[[#This Row],[2024]]/Table4[[#This Row],[2020]])^(1/5)-1 -> 0.14822627
A23: ICICI Bank | B23: Net Profit Margin | C23: =C19/C20 -> 0.063866458 | D23: =D19/D20 -> 0.16508525 | E23: =E19/E20 -> 0.22250957 | F23: =F19/F20 -> 0.18281695 | G23: =G19/G20 -> 0.18749703 | H23: =AVERAGE(C23:G23) -> 0.16435505 | J23: MFL | K23: Net Profit Margin | L23: =L19/L20 -> 0.32720854 | M23: =M19/M20 -> 0.3310806 | N23: =N19/N20 -> 0.33084564 | O23: =O19/O20 -> 0.30844427 | P23: =P19/P20 -> 0.29662035 | Q23: =AVERAGE(Table4[[#This Row],[2020]:[2024]]) -> 0.31883988
A24: ICICI Bank | B24: Asset Turnover | C24: =C20/C21 -> 0.10875405 | D24: =D20/D21 -> 0.075227879 | E24: =E20/E21 -> 0.079411649 | F24: =F20/F21 -> 0.11049882 | G24: =G20/G21 -> 0.10921218 | H24: =AVERAGE(C24:G24) -> 0.096620917 | J24: MFL | K24: Asset Turnover | L24: =L20/L21 -> 0.17645192 | M24: =M20/M21 -> 0.18675957 | N24: =N20/N21 -> 0.16811651 | O24: =O20/O21 -> 0.15208044 | P24: =P20/P21 -> 0.17055598 | Q24: =AVERAGE(Table4[[#This Row],[2020]:[2024]]) -> 0.17079288
A25: ICICI Bank | B25: Equity multiplier | C25: =C21/C22 -> 10.614576 | D25: =D21/D22 -> 9.4052054 | E25: =E21/E22 -> 8.3067754 | F25: =F21/F22 -> 8.6030591 | G25: =G21/G22 -> 8.7996863 | H25: =AVERAGE(C25:G25) -> 9.1458604 | J25: MFL | K25: Equity multiplier | L25: =L21/L22 -> 4.5729591 | M25: =M21/M22 -> 4.4495278 | N25: =N21/N22 -> 4.1538198 | O25: =O21/O22 -> 3.7893616 | P25: =P21/P22 -> 3.6867037 | Q25: =AVERAGE(Table4[[#This Row],[2020]:[2024]]) -> 4.1304744
A26: ICICI Bank | B26: Return on Equity | C26: =C23*C24*C25 -> 0.073726042 | D26: =D23*D24*D25 -> 0.11680337 | E26: =E23*E24*E25 -> 0.14677949 | F26: =F23*F24*F25 -> 0.17379089 | G26: =G23*G24*G25 -> 0.18019082 | H26: =AVERAGE(C26:G26) -> 0.13825812 | J26: MFL | K26: Return on Equity | L26: =L23*L24*L25 -> 0.264027 | M26: =M23*M24*M25 -> 0.27512529 | N26: =N23*N24*N25 -> 0.23103801 | O26: =O23*O24*O25 -> 0.17775267 | P26: =P23*P24*P25 -> 0.18651172 | Q26: =AVERAGE(Table4[[#This Row],[2020]:[2024]]) -> 0.22689094
A27: SBI | B27: Net Income | C27: ='Income Statement-Banks'!Q15 -> 19767.796 | D27: ='Income Statement-Banks'!R15 -> 22405.458 | E27: ='Income Statement-Banks'!S15 -> 35373.88 | F27: ='Income Statement-Banks'!T15 -> 55648.173 | G27: ='Income Statement-Banks'!U15 -> 67084.666 | H27: =(Table3[[#This Row],[2024]]/Table3[[#This Row],[2020]])^(1/5)-1 -> 0.27682978
A28: SBI | B28: Revenue | C28: ='Income Statement-Banks'!Q7 -> 368010.64 | D28: ='Income Statement-Banks'!R7 -> 385337.89 | E28: ='Income Statement-Banks'!S7 -> 406973.09 | F28: ='Income Statement-Banks'!T7 -> 473378.14 | G28: ='Income Statement-Banks'!U7 -> 594574.9 | H28: =(Table3[[#This Row],[2024]]/Table3[[#This Row],[2020]])^(1/5)-1 -> 0.10070069
A29: SBI | B29: Average total assets | C29: ='Balance Sheet-Banks'!Q79 -> 4197492.2 | D29: =AVERAGE('Balance Sheet-Banks'!Q79:R79) -> 4521555.3 | E29: =AVERAGE('Balance Sheet-Banks'!R79:S79) -> 5103250.9 | F29: =AVERAGE('Balance Sheet-Banks'!S79:T79) -> 5657650.8 | G29: =AVERAGE('Balance Sheet-Banks'!T79:U79) -> 6344098.5 | H29: =(Table3[[#This Row],[2024]]/Table3[[#This Row],[2020]])^(1/5)-1 -> 0.08611548
A30: SBI | B30: Average Shareholder's Equity | C30: ='Balance Sheet-Banks'!Q9 -> 259003.94 | D30: =AVERAGE('Balance Sheet-Banks'!Q9:R9) -> 272095.7 | E30: =AVERAGE('Balance Sheet-Banks'!R9:S9) -> 300991.46 | F30: =AVERAGE('Balance Sheet-Banks'!S9:T9) -> 344281.69 | G30: =AVERAGE('Balance Sheet-Banks'!T9:U9) -> 401162.53 | H30: =(Table3[[#This Row],[2024]]/Table3[[#This Row],[2020]])^(1/5)-1 -> 0.091447366
A31: SBI | B31: Net Profit Margin | C31: =C27/C28 -> 0.053715284 | D31: =D27/D28 -> 0.058144964 | E31: =E27/E28 -> 0.086919457 | F31: =F27/F28 -> 0.11755543 | G31: =G27/G28 -> 0.11282795 | H31: =AVERAGE(C31:G31) -> 0.085832617
A32: SBI | B32: Asset Turnover | C32: =C28/C29 -> 0.08767393 | D32: =D28/D29 -> 0.085222421 | E32: =E28/E29 -> 0.079747811 | F32: =F28/F29 -> 0.083670441 | G32: =G28/G29 -> 0.093720945 | H32: =AVERAGE(C32:G32) -> 0.08600711
A33: SBI | B33: Equity multiplier | C33: =C29/C30 -> 16.206287 | D33: =D29/D30 -> 16.617519 | E33: =E29/E30 -> 16.954803 | F33: =F29/F30 -> 16.433203 | G33: =G29/G30 -> 15.814285 | H33: =AVERAGE(C33:G33) -> 16.405219
A34: SBI | B34: Return on Equity | C34: =C31*C32*C33 -> 0.076322376 | D34: =D31*D32*D33 -> 0.082344034 | E34: =E31*E32*E33 -> 0.11752453 | F34: =F31*F32*F33 -> 0.16163559 | G34: =G31*G32*G33 -> 0.16722566 | H34: =AVERAGE(C34:G34) -> 0.12101044
H37: =AVERAGE(H10,H18,H26,H34) -> 0.13073628

Sheet Input & Assumptions-Banks
A1: Key Assumptions & Inputs
A2: Particulars | B2: #VALUE! | C2: #VALUE! | D2: #VALUE! | E2: #VALUE! | F2: #VALUE! | G2: #VALUE! | H2: #VALUE!
A4: Risk Free rate | B4: 0.0635 | C4: 0.0635 | D4: 0.0635 | E4: 0.0635 | F4: 0.0635 | G4: 0.0635 | H4: 0.0635
A5: Equity risk premium | B5: 0.0675 | C5: 0.0675 | D5: 0.0675 | E5: 0.0675 | F5: 0.0675 | G5: 0.0675 | H5: 0.0675
A6: Beta | B6: ='Company Profile'!D7 -> 1.0905 | C6: ='Company Profile'!B7 -> 0.8793 | D6: ='Company Profile'!C7 -> 0.9991 | E6: ='Company Profile'!E7 -> 1.2655 | F6: ='Company Profile'!G7 -> 1.422 | G6: ='Company Profile'!F7 -> 1.1683 | H6: ='Company Profile'!H7 -> 0.9721
A7: Cost of Equity | B7: =B4*(B5+B6) -> 0.073533 | C7: =C4*(C5+C6) -> 0.0601218 | D7: =D4*(D5+D6) -> 0.0677291 | E7: =E4*(E5+E6) -> 0.0846455 | F7: =F4*(F5+F6) -> 0.09458325 | G7: =G4*(G5+G6) -> 0.0784733 | H7: =H4*(H5+H6) -> 0.0660146
A8: Cost of Debt | B8: =(AVERAGE('Income Statement-Banks'!B9:F9)/(AVERAGE('Balance Sheet-Banks'!B21:F21)+AVERAGE('Balance Sheet-Banks'!B13:F13))) -> 0.041502959 | C8: =(AVERAGE('Income Statement-Banks'!G9:K9)/(AVERAGE('Balance Sheet-Banks'!G13:K13)+AVERAGE('Balance Sheet-Banks'!G21:K21))) -> 0.041705331 | D8: =(AVERAGE('Income Statement-Banks'!L9:P9)/(AVERAGE('Balance Sheet-Banks'!L13:P13)+AVERAGE('Balance Sheet-Banks'!L21:P21))) -> 0.039663315 | E8: =(AVERAGE('Income Statement-Banks'!Q9:U9)/(AVERAGE('Balance Sheet-Banks'!Q13:U13)+AVERAGE('Balance Sheet-Banks'!Q21:U21))) -> 0.040327737 | F8: =(AVERAGE('Income Statement-NBFCs'!B17:F17)/(AVERAGE('Balance Sheet-NBFCs'!B13:F13)+AVERAGE('Balance Sheet-NBFCs'!B14:F14))) -> 0.097882078 | G8: =(AVERAGE('Income Statement-NBFCs'!G17:K17)/(AVERAGE('Balance Sheet-NBFCs'!G13:J13)+AVERAGE('Balance Sheet-NBFCs'!G14:K14))) -> 0.12472955 | H8: =(AVERAGE('Income Statement-NBFCs'!L17:P17)/(AVERAGE('Balance Sheet-NBFCs'!L13:P13)+AVERAGE('Balance Sheet-NBFCs'!L14:P14))) -> 0.10686095
A9: Tax rate | B9: 0.2517 | C9: 0.2517 | D9: 0.2517 | E9: 0.2517 | F9: 0.2517 | G9: 0.2517 | H9: 0.2517
A10: Target CET 1/CRAR Ratio | B10: =AVERAGE('Balance Sheet-Banks'!B88:F88) -> 0.14578 | C10: =AVERAGE('Balance Sheet-Banks'!G88:K88) -> 0.1653 | D10: =AVERAGE('Balance Sheet-Banks'!L88:P88) -> 0.172 | E10: =AVERAGE('Balance Sheet-Banks'!Q88:U88) -> 0.10724 | F10: =AVERAGE('Financial Ratios-NBFCs'!B17:F17) -> 0.21399103 | G10: =AVERAGE('Financial Ratios-NBFCs'!G17:K17) -> 0.23170287 | H10: =AVERAGE('Financial Ratios-NBFCs'!L18:P18) -> 0.28066425
A11: Long-term growth rate | B11: 0.02 | C11: 0.02 | D11: 0.02 | E11: 0.02 | F11: 0.03 | G11: 0.02 | H11: 0.02
A12: Dividend Payout ratio | B12: =(AVERAGE('Income Statement-Banks'!B26:F26)/(AVERAGE('Income Statement-Banks'!B13:F13))) -> 0.015633985 | C12: =(AVERAGE('Income Statement-Banks'!G26:K26)/(AVERAGE('Income Statement-Banks'!G13:K13))) -> 0.1122424 | D12: =(AVERAGE('Income Statement-Banks'!L26:P26)/(AVERAGE('Income Statement-Banks'!L13:P13))) -> 0.085301425 | E12: =(AVERAGE('Income Statement-Banks'!Q26:U26)/(AVERAGE('Income Statement-Banks'!Q13:U13))) -> 0.15830179 | F12: 0 | G12: =(-AVERAGE('Cash Flow Statement-NBFCs'!G77:K77)/(AVERAGE('Income Statement-NBFCs'!G33:K33))) -> 0.10710146 | H12: =(-AVERAGE('Cash Flow Statement-NBFCs'!L77:P77)/(AVERAGE('Income Statement-NBFCs'!L33:P33))) -> 0.1981902

Sheet Financial Projections
A1: FINANCIAL PROJECTIONS
A2: Particulars | B2: #VALUE! | K2: #VALUE! | T2: #VALUE! | AC2: #VALUE! | AL2: #VALUE! | AU2: #VALUE! | BD2: #VALUE!
B3: 2024 | C3: Average | D3: 2025 | E3: 2026 | F3: 2027 | G3: 2028 | H3: 2029 | I3: 2030 | K3: 2024 | L3: Average | M3: 2025 | N3: 2026 | O3: 2027 | P3: 2028 | Q3: 2029 | R3: 2030 | T3: 2024 | U3: Average | V3: 2025 | W3: 2026 | X3: 2027 | Y3: 2028 | Z3: 2029 | AA3: 2030 | AC3: 2024 | AD3: Average | AE3: 2025 | AF3: 2026 | AG3: 2027 | AH3: 2028 | AI3: 2029 | AJ3: 2030 | AL3: 2024 | AM3: Average | AN3: 2025 | AO3: 2026 | AP3: 2027 | AQ3: 2028 | AR3: 2029 | AS3: 2030 | AU3: 2024 | AV3: Average | AW3: 2025 | AX3: 2026 | AY3: 2027 | AZ3: 2028 | BA3: 2029 | BB3: 2030 | BD3: 2024 | BE3: Average | BF3: 2025 | BG3: 2026 | BH3: 2027 | BI3: 2028 | BJ3: 2029 | BK3: 2030
A4: Income Statement Projections | K4: Income Statement Projections
A5: Total Advances/Loans (AUM) | B5: ='Balance Sheet-Banks'!F75 -> 999333.48 | C5: =('Balance Sheet-Banks'!F75/'Balance Sheet-Banks'!B75)^(1/5)-1 -> 0.11381873 | D5: =B5*(1+$C$5)^1 -> 1113076.3 | E5: =D5*(1+C5) -> 1239765.3 | F5: =E5*(1+C5) -> 1380873.8 | G5: =F5*(1+C5) -> 1538043.1 | H5: =G5*(1+C5) -> 1713101.2 | I5: =H5*(1+C5) -> 1908084.2 | K5: ='Balance Sheet-Banks'!K75 -> 2565891.4 | L5: =('Balance Sheet-Banks'!K75/'Balance Sheet-Banks'!G75)^(1/5)-1 -> 0.19711244 | M5: =K5*(1+$L$5) -> 3071660.5 | N5: =M5*(1+$L$5) -> 3677123 | O5: =N5*(1+$L$5) -> 4401929.7 | P5: =O5*(1+$L$5) -> 5269604.9 | Q5: =P5*(1+$L$5) -> 6308309.6 | R5: =Q5*(1+$L$5) -> 7551755.9 | T5: ='Balance Sheet-Banks'!P75 -> 1260776.2 | U5: =('Balance Sheet-Banks'!P75/'Balance Sheet-Banks'!L75)^(1/5)-1 -> 0.12288786 | V5: =T5*(1+U5) -> 1415710.3 | W5: =V5*(1+U5) -> 1589683.9 | X5: =W5*(1+U5) -> 1785036.7 | Y5: =X5*(1+U5) -> 2004396.1 | Z5: =Y5*(1+U5) -> 2250712 | AA5: =Z5*(1+U5) -> 2527297.2 | AC5: ='Balance Sheet-Banks'!U75 -> 3784272.7 | AD5: =RATE(5,0,'Balance Sheet-Banks'!Q75,-'Balance Sheet-Banks'!U75,0) -> 0.09771338 | AE5: =AC5*(1+AD5) -> 4154046.7 | AF5: =AE5*(1+AD5) -> 4559952.7 | AG5: =AF5*(1+AD5) -> 5005521.1 | AH5: =AG5*(1+AD5) -> 5494627.5 | AI5: =AH5*(1+AD5) -> 6031526.1 | AJ5: =AI5*(1+AD5) -> 6620886.9 | AL5: ='Balance Sheet-NBFCs'!F27 -> 79300.75 | AM5: =('Balance Sheet-NBFCs'!F27/'Balance Sheet-NBFCs'!B27)^(1/5)-1 -> 0.23168646 | AN5: =AL5*(1+AM5) -> 97673.66 | AO5: =AN5*(1+AM5) -> 120303.32 | AP5: =AO5*(1+AM5) -> 148175.98 | AQ5: =AP5*(1+AM5) -> 182506.34 | AR5: =AQ5*(1+AM5) -> 224790.59 | AS5: =AR5*(1+AM5) -> 276871.53 | AU5: ='Balance Sheet-NBFCs'!K27 -> 326293.32 | AV5: =('Balance Sheet-NBFCs'!K27/'Balance Sheet-NBFCs'!G27)^(1/5)-1 -> 0.18207891 | AW5: =AU5*(1+AV5) -> 385704.45 | AX5: =AW5*(1+AV5) -> 455933.1 | AY5: =AX5*(1+AV5) -> 538948.9 | AZ5: =AY5*(1+AV5) -> 637080.12 | BA5: =AZ5*(1+AV5) -> 753078.97 | BB5: =BA5*(1+AV5) -> 890198.77 | BD5: ='Balance Sheet-NBFCs'!P27 -> 881871.71 | BE5: =('Balance Sheet-NBFCs'!P27/'Balance Sheet-NBFCs'!L27)^(1/5)-1 -> 0.13379989 | BF5: =BD5*(1+BE5) -> 999866.05 | BG5: =BF5*(1+BE5) -> 1133648 | BH5: =BG5*(1+BE5) -> 1285330 | BI5: =BH5*(1+BE5) -> 1457307 | BJ5: =BI5*(1+BE5) -> 1652294.5 | BK5: =BJ5*(1+BE5) -> 1873371.4
A6: Net Interest Income | B6: ='Income Statement-Banks'!F5-'Income Statement-Banks'!F9 -> 51368.31 | C6: =('Income Statement-Banks'!F33/'Income Statement-Banks'!B33)^(1/5)-1 -> 0.14838032 | D6: =B6*(1+C6) -> 58990.356 | E6: =D6*(1+$C$6) -> 67743.364 | F6: =E6*(1+$C$6) -> 77795.146 | G6: =F6*(1+$C$6) -> 89338.415 | H6: =G6*(1+$C$6) -> 102594.48 | I6: =H6*(1+$C$6) -> 117817.48 | K6: ='Income Statement-Banks'!K5-'Income Statement-Banks'!K9 -> 129510.47 | L6: =('Income Statement-Banks'!K33/'Income Statement-Banks'!G33)^(1/5)-1 -> 0.16615336 | M6: =K6*(1+L6) -> 151029.07 | N6: =M6*(1+$L$6) -> 176123.06 | O6: =N6*(1+$L$6) -> 205386.5 | P6: =O6*(1+$L$6) -> 239512.15 | Q6: =P6*(1+$L$6) -> 279307.9 | R6: =Q6*(1+$L$6) -> 325715.85 | T6: ='Income Statement-Banks'!P5-'Income Statement-Banks'!P9 -> 85407.762 | U6: =('Income Statement-Banks'!P33/'Income Statement-Banks'!L33)^(1/5)-1 -> 0.16283625 | V6: =T6*(1+U6) -> 99315.242 | W6: =V6*(1+$U$6) -> 115487.36 | X6: =W6*(1+$U$6) -> 134292.89 | Y6: =X6*(1+$U$6) -> 156160.64 | Z6: =Y6*(1+$U$6) -> 181589.25 | AA6: =Z6*(1+$U$6) -> 211158.57 | AC6: ='Income Statement-Banks'!U5-'Income Statement-Banks'!U9 -> 179452.46 | AD6: =('Income Statement-Banks'!U33/'Income Statement-Banks'!Q33)^(1/5)-1 -> 0.10540576 | AE6: =AC6*(1+AD6) -> 198367.79 | AF6: =AE6*(1+$AD$6) -> 219276.9 | AG6: =AF6*(1+$AD$6) -> 242389.94 | AH6: =AG6*(1+$AD$6) -> 267939.24 | AI6: =AH6*(1+$AD$6) -> 296181.58 | AJ6: =AI6*(1+$AD$6) -> 327400.83 | AL6: ='Income Statement-NBFCs'!F6-'Income Statement-NBFCs'!F17 -> 2509.75 | AM6: =AVERAGE('Financial Ratios-NBFCs'!B5:F5) -> 0.027633562 | AN6: =AN5*$AM$6 -> 2699.0712 | AO6: =AO5*$AM$6 -> 3324.4094 | AP6: =AP5*$AM$6 -> 4094.6301 | AQ6: =AQ5*$AM$6 -> 5043.3004 | AR6: =AR5*$AM$6 -> 6211.7648 | AS6: =AS5*$AM$6 -> 7650.9466 | AU6: ='Income Statement-NBFCs'!K6-'Income Statement-NBFCs'!K17 -> 29581.91 | AV6: =AVERAGE('Financial Ratios-NBFCs'!G5:K5) -> 0.084932115 | AW6: =AW5*$AV$6 -> 32758.695 | AX6: =AX5*$AV$6 -> 38723.362 | AY6: =AY5*$AV$6 -> 45774.069 | AZ6: =AZ5*$AV$6 -> 54108.562 | BA6: =BA5*$AV$6 -> 63960.59 | BB6: =BB5*$AV$6 -> 75606.464 | BD6: ='Income Statement-NBFCs'!P6-'Income Statement-NBFCs'!P17 -> 91156.23 | BE6: =AVERAGE('Financial Ratios-NBFCs'!L5:P5) -> 0.11477291 | BF6: =BF5*$BE$6 -> 114757.53 | BG6: =BG5*$BE$6 -> 130112.08 | BH6: =BH5*$BE$6 -> 147521.06 | BI6: =BI5*$BE$6 -> 167259.36 | BJ6: =BJ5*$BE$6 -> 189638.65 | BK6: =BK5*$BE$6 -> 215012.28
A7: Other Income | B7: ='Income Statement-Banks'!F6 -> 25230.31 | C7: =('Income Statement-Banks'!F6/'Income Statement-Banks'!B6)^(1/5)-1 -> 0.090745749 | D7: =B7*(1+C7) -> 27519.853 | E7: =D7*(1+C7) -> 30017.163 | F7: =E7*(1+C7) -> 32741.093 | G7: =F7*(1+C7) -> 35712.208 | H7: =G7*(1+C7) -> 38952.939 | I7: =H7*(1+C7) -> 42487.753 | K7: ='Income Statement-Banks'!K6 -> 124345.75 | L7: =(K7/'Income Statement-Banks'!G6)^(1/5)-1 -> 0.37962067 | M7: =K7*(1+L7) -> 171549.97 | N7: =M7*(1+L7) -> 236673.88 | O7: =N7*(1+L7) -> 326520.18 | P7: =O7*(1+L7) -> 450473.99 | Q7: =P7*(1+L7) -> 621483.23 | R7: =Q7*(1+L7) -> 857411.11 | T7: ='Income Statement-Banks'!P6 -> 76521.802 | U7: =('Income Statement-Banks'!P6/'Income Statement-Banks'!L6)^(1/5)-1 -> 0.033334109 | V7: =T7*(1+U7) -> 79072.588 | W7: =V7*(1+U7) -> 81708.402 | X7: =W7*(1+U7) -> 84432.079 | Y7: =X7*(1+U7) -> 87246.547 | Z7: =Y7*(1+U7) -> 90154.833 | AA7: =Z7*(1+U7) -> 93160.064 | AC7: ='Income Statement-Banks'!U6 -> 155386.39 | AD7: =('Income Statement-Banks'!U6/'Income Statement-Banks'!Q6)^(1/5)-1 -> 0.09621712 | AE7: =AC7*(1+AD7) -> 170337.22 | AF7: =AE7*(1+AD7) -> 186726.58 | AG7: =AF7*(1+AD7) -> 204692.87 | AH7: =AG7*(1+AD7) -> 224387.83 | AI7: =AH7*(1+AD7) -> 245977.78 | AJ7: =AI7*(1+AD7) -> 269645.06 | AL7: ='Income Statement-NBFCs'!F39 -> 415.35 | AM7: =('Income Statement-NBFCs'!F39/'Income Statement-NBFCs'!B39)^(1/5)-1 -> 0.038929414 | AN7: =AL7*(1+AM7) -> 431.51933 | AO7: =AN7*(1+AM7) -> 448.31813 | AP7: =AO7*(1+AM7) -> 465.77089 | AQ7: =AP7*(1+AM7) -> 483.90308 | AR7: =AQ7*(1+AM7) -> 502.74114 | AS7: =AR7*(1+AM7) -> 522.31256 | AU7: ='Income Statement-NBFCs'!K39 -> 6675.91 | AV7: =('Income Statement-NBFCs'!K39/'Income Statement-NBFCs'!G39)^(1/5)-1 -> 0.14345176 | AW7: =AU7*(1+AV7) -> 7633.5811 | AX7: =AW7*(1+AV7) -> 8728.6317 | AY7: =AX7*(1+AV7) -> 9980.7694 | AZ7: =AY7*(1+AV7) -> 11412.528 | BA7: =AZ7*(1+AV7) -> 13049.676 | BB7: =BA7*(1+AV7) -> 14921.675 | BD7: ='Income Statement-NBFCs'!P39 -> 6170.41 | BE7: =('Income Statement-NBFCs'!P39/'Income Statement-NBFCs'!L39)^(1/5)-1 -> 0.16338589 | BF7: =BD7*(1+BE7) -> 7178.5679 | BG7: =BF7*(1+BE7) -> 8351.4446 | BH7: =BG7*(1+BE7) -> 9715.9527 | BI7: =BH7*(1+BE7) -> 11303.402 | BJ7: =BI7*(1+BE7) -> 13150.219 | BK7: =BJ7*(1+BE7) -> 15298.779
A8: Total Income | B8: =B6+B7 -> 76598.62 | D8: =D6+D7 -> 86510.21 | E8: =E6+E7 -> 97760.527 | F8: =F6+F7 -> 110536.24 | G8: =G6+G7 -> 125050.62 | H8: =H6+H7 -> 141547.42 | I8: =I6+I7 -> 160305.23 | K8: =K6+K7 -> 253856.22 | M8: =M6+M7 -> 322579.04 | N8: =N6+N7 -> 412796.94 | O8: =O6+O7 -> 531906.68 | P8: =P6+P7 -> 689986.14 | Q8: =Q6+Q7 -> 900791.13 | R8: =R6+R7 -> 1183127 | T8: =T6+T7 -> 161929.56 | V8: =V6+V7 -> 178387.83 | W8: =W6+W7 -> 197195.77 | X8: =X6+X7 -> 218724.97 | Y8: =Y6+Y7 -> 243407.19 | Z8: =Z6+Z7 -> 271744.09 | AA8: =AA6+AA7 -> 304318.63 | AC8: =AC6+AC7 -> 334838.86 | AE8: =AE6+AE7 -> 368705.01 | AF8: =AF6+AF7 -> 406003.48 | AG8: =AG6+AG7 -> 447082.82 | AH8: =AH6+AH7 -> 492327.07 | AI8: =AI6+AI7 -> 542159.37 | AJ8: =AJ6+AJ7 -> 597045.88 | AL8: =AL6+AL7 -> 2925.1 | AN8: =AN6+AN7 -> 3130.5905 | AO8: =AO6+AO7 -> 3772.7275 | AP8: =AP6+AP7 -> 4560.4009 | AQ8: =AQ6+AQ7 -> 5527.2035 | AR8: =AR6+AR7 -> 6714.5059 | AS8: =AS6+AS7 -> 8173.2592 | AU8: =AU6+AU7 -> 36257.82 | AW8: =AW6+AW7 -> 40392.276 | AX8: =AX6+AX7 -> 47451.994 | AY8: =AY6+AY7 -> 55754.839 | AZ8: =AZ6+AZ7 -> 65521.09 | BA8: =BA6+BA7 -> 77010.265 | BB8: =BB6+BB7 -> 90528.139 | BD8: =BD6+BD7 -> 97326.64 | BF8: =BF6+BF7 -> 121936.1 | BG8: =BG6+BG7 -> 138463.52 | BH8: =BH6+BH7 -> 157237.01 | BI8: =BI6+BI7 -> 178562.77 | BJ8: =BJ6+BJ7 -> 202788.87 | BK8: =BK6+BK7 -> 230311.06
A9: Operating Expenses | B9: ='Income Statement-Banks'!F10 -> 37242.55 | C9: =('Income Statement-Banks'!F10/'Income Statement-Banks'!B10)^(1/5)-1 -> 0.15567746 | D9: =B9*(1+C9) -> 43040.375 | E9: =D9*(1+C9) -> 49740.792 | F9: =E9*(1+C9) -> 57484.312 | G9: =F9*(1+C9) -> 66433.323 | H9: =G9*(1+C9) -> 76775.494 | I9: =H9*(1+C9) -> 88727.707 | K9: ='Income Statement-Banks'!K10 -> 152269.34 | L9: =('Income Statement-Banks'!K10/'Income Statement-Banks'!G10)^(1/5)-1 -> 0.35745317 | M9: =K9*(1+L9) -> 206698.5 | N9: =M9*(1+L9) -> 280583.53 | O9: =N9*(1+L9) -> 380879 | P9: =O9*(1+L9) -> 517025.41 | Q9: =P9*(1+L9) -> 701837.78 | R9: =Q9*(1+L9) -> 952711.92 | T9: ='Income Statement-Banks'!P10 -> 97782.792 | U9: =('Income Statement-Banks'!P10/'Income Statement-Banks'!L10)^(1/5)-1 -> 0.064558514 | V9: =T9*(1+U9) -> 104095.5 | W9: =V9*(1+U9) -> 110815.75 | X9: =W9*(1+U9) -> 117969.86 | Y9: =X9*(1+U9) -> 125585.81 | Z9: =Y9*(1+U9) -> 133693.45 | AA9: =Z9*(1+U9) -> 142324.5 | AC9: ='Income Statement-Banks'!U10 -> 235893.84 | AD9: =('Income Statement-Banks'!U10/'Income Statement-Banks'!Q10)^(1/5)-1 -> 0.12349823 | AE9: =AC9*(1+AD9) -> 265026.31 | AF9: =AC9*(1+AD9)^2 -> 297756.59 | AG9: =AF9*(1+AD9) -> 334529 | AH9: =AC9*(1+AD9)^4 -> 375842.74 | AI9: =AH9*(1+AD9) -> 422258.65 | AJ9: =AI9*(1+AD9) -> 474406.84 | AL9: ='Income Statement-NBFCs'!F38+'Income Statement-NBFCs'!F19 -> 824.66 | AM9: =AVERAGE('Income Statement-NBFCs'!B38:F38)/AVERAGE('Income Statement-NBFCs'!B14:F14) -> 0.14041701 | AN9: =AN8*$AM$9 -> 439.58815 | AO9: =AO8*$AM$9 -> 529.75512 | AP9: =AP8*$AM$9 -> 640.35786 | AQ9: =AQ8*$AM$9 -> 776.11338 | AR9: =AR8*$AM$9 -> 942.83084 | AS9: =AS8*$AM$9 -> 1147.6646 | AU9: ='Income Statement-NBFCs'!K38 -> 16955.89 | AV9: =AVERAGE('Income Statement-NBFCs'!G38:K38)/AVERAGE('Income Statement-NBFCs'!G14:K14) -> 0.35085638 | AW9: =AW8*$AV$9 -> 14171.888 | AX9: =AX8*$AV$9 -> 16648.835 | AY9: =AY8*$AV$9 -> 19561.941 | AZ9: =AZ8*$AV$9 -> 22988.493 | BA9: =BA8*$AV$9 -> 27019.543 | BB9: =BB8*$AV$9 -> 31762.375 | BD9: ='Income Statement-NBFCs'!L38 -> 22740.36 | BE9: =AVERAGE('Income Statement-NBFCs'!L38:P38)/AVERAGE('Income Statement-NBFCs'!L14:P14) -> 0.22692245 | BF9: =BF8*$BE$9 -> 27670.039 | BG9: =BG8*$BE$9 -> 31420.482 | BH9: =BH8*$BE$9 -> 35680.608 | BI9: =BI8*$BE$9 -> 40519.9 | BJ9: =BJ8*$BE$9 -> 46017.346 | BK9: =BK8*$BE$9 -> 52262.749
A10: Pre-Provision Operating Profit | B10: =B8-B9 -> 39356.07 | D10: =D8-D9 -> 43469.834 | E10: =E8-E9 -> 48019.735 | F10: =F8-F9 -> 53051.927 | G10: =G8-G9 -> 58617.3 | H10: =H8-H9 -> 64771.922 | I10: =I8-I9 -> 71577.523 | K10: =K8-K9 -> 101586.88 | M10: =M8-M9 -> 115880.54 | N10: =N8-N9 -> 132213.41 | O10: =O8-O9 -> 151027.67 | P10: =P8-P9 -> 172960.73 | Q10: =Q8-Q9 -> 198953.35 | R10: =R8-R9 -> 230415.04 | T10: =T8-T9 -> 64146.772 | V10: =V8-V9 -> 74292.326 | W10: =W8-W9 -> 86380.01 | X10: =X8-X9 -> 100755.12 | Y10: =Y8-Y9 -> 117821.38 | Z10: =Z8-Z9 -> 138050.64 | AA10: =AA8-AA9 -> 161994.13 | AC10: =AC8-AC9 -> 98945.018 | AE10: =AE8-AE9 -> 103678.7 | AF10: =AF8-AF9 -> 108246.89 | AG10: =AG8-AG9 -> 112553.82 | AH10: =AH8-AH9 -> 116484.34 | AI10: =AI8-AI9 -> 119900.72 | AJ10: =AJ8-AJ9 -> 122639.04 | AL10: =AL8-AL9 -> 2100.44 | AN10: =AN8-AN9 -> 2691.0023 | AO10: =AO8-AO9 -> 3242.9724 | AP10: =AP8-AP9 -> 3920.0431 | AQ10: =AQ8-AQ9 -> 4751.0901 | AR10: =AR8-AR9 -> 5771.6751 | AS10: =AS8-AS9 -> 7025.5945 | AU10: =AU8-AU9 -> 19301.93 | AW10: =AW8-AW9 -> 26220.388 | AX10: =AX8-AX9 -> 30803.159 | AY10: =AY8-AY9 -> 36192.898 | AZ10: =AZ8-AZ9 -> 42532.598 | BA10: =BA8-BA9 -> 49990.722 | BB10: =BB8-BB9 -> 58765.764 | BD10: =BD8-BD9 -> 74586.28 | BF10: =BF8-BF9 -> 94266.063 | BG10: =BG8-BG9 -> 107043.04 | BH10: =BH8-BH9 -> 121556.41 | BI10: =BI8-BI9 -> 138042.87 | BJ10: =BJ8-BJ9 -> 156771.52 | BK10: =BK8-BK9 -> 178048.31
A11: Provisions | B11: =(B16-'Financial Ratios-Banks'!E34)*'Financial Projections'!C16 -> -96.42346 | C11: ='Financial Ratios-Banks'!G14 -> 0.43381315 | D11: =(D16-B16)*C11 -> 8122.4466 | E11: =(E16-D16)*C11 -> 1630.0936 | F11: =(F16-E16)*C11 -> 1815.6287 | G11: =(G16-F16)*C11 -> 2022.2813 | H11: =(H16-G16)*C11 -> 2252.4548 | I11: =(I16-H16)*C11 -> 2508.8263 | K11: =(K16-'Financial Ratios-Banks'!K34)*L11 -> 8286.0963 | L11: ='Financial Ratios-Banks'!M14 -> 0.72639832 | M11: =(M16-K16)*L11 -> 5458.7107 | N11: =(N16-M16)*L11 -> 5374.4409 | O11: =(O16-N16)*L11 -> 6433.8101 | P11: =(P16-O16)*L11 -> 7701.9942 | Q11: =(Q16-P16)*L11 -> 9220.1531 | R11: =(R16-Q16)*L11 -> 11037.56 | T11: ='Cash Flow Statement-Banks'!P10 -> 963.5716 | U11: ='Financial Ratios-Banks'!S14 -> 0.18966507 | V11: =(V16-T16)*U11 -> 4169.3371 | W11: =(W16-V16)*U11 -> 1003.1002 | X11: =(X16-W16)*U11 -> 1126.369 | Y11: =(Y16-X16)*U11 -> 1264.7861 | Z11: =(Z16-Y16)*U11 -> 1420.213 | AA11: =(AA16-Z16)*U11 -> 1594.7399 | AC11: ='Income Statement-Banks'!U11 -> 30806.757 | AD11: ='Financial Ratios-Banks'!Y14 -> 0.25692195 | AE11: =(AE16-AC16)*'Financial Ratios-Banks'!Y14 -> 16009.072 | AF11: =(AF16-AE16)*AD11 -> 3293.3565 | AG11: =(AG16-AF16)*AD11 -> 3615.1615 | AH11: =(AH16-AG16)*AD11 -> 3968.4112 | AI11: =(AI16-AH16)*AD11 -> 4356.1781 | AJ11: =(AJ16-AI16)*AD11 -> 4781.835 | AL11: =AL5*AM11*AM16 -> 43.800146 | AM11: =AVERAGE('Financial Ratios-NBFCs'!B14:F14) -> 0.21745257 | AN11: =AN5*$AM$11*$AM$16 -> 53.948046 | AO11: =AO5*$AM$11*$AM$16 -> 66.447078 | AP11: =AP5*$AM$11*$AM$16 -> 81.841967 | AQ11: =AQ5*$AM$11*$AM$16 -> 100.80364 | AR11: =AR5*$AM$11*$AM$16 -> 124.15848 | AS11: =AS5*$AM$11*$AM$16 -> 152.92432 | AU11: =AU5*AV11*AV16 -> 122.40682 | AV11: =AVERAGE('Financial Ratios-NBFCs'!G14:K14) -> 0.027624706 | AW11: =AW5*$AV$11*$AV$16 -> 144.69452 | AX11: =AX5*$AV$11*$AV$16 -> 171.04034 | AY11: =AY5*$AV$11*$AV$16 -> 202.18318 | AZ11: =AZ5*$AV$11*$AV$16 -> 238.99647 | BA11: =BA5*$AV$11*$AV$16 -> 282.51269 | BB11: =BB5*$AV$11*$AV$16 -> 333.95229 | BD11: =BD5*BE11*BE16 -> 505.7277 | BE11: =AVERAGE('Financial Ratios-NBFCs'!L14:P14) -> 0.061007535 | BF11: =BF5*$BE$11*$BE$16 -> 573.39401 | BG11: =BG5*$BE$11*$BE$16 -> 650.11407 | BH11: =BH5*$BE$11*$BE$16 -> 737.09926 | BI11: =BI5*$BE$11*$BE$16 -> 835.72306 | BJ11: =BJ5*$BE$11*$BE$16 -> 947.54272 | BK11: =BK5*$BE$11*$BE$16 -> 1074.3238
A12: Profit Before Tax (PBT) | B12: =B10-B11 -> 39452.493 | D12: =D10-D11 -> 35347.388 | E12: =E10-E11 -> 46389.642 | F12: =F10-F11 -> 51236.299 | G12: =G10-G11 -> 56595.018 | H12: =H10-H11 -> 62519.468 | I12: =I10-I11 -> 69068.697 | K12: =K10-K11 -> 93300.784 | M12: =M10-M11 -> 110421.83 | N12: =N10-N11 -> 126838.97 | O12: =O10-O11 -> 144593.86 | P12: =P10-P11 -> 165258.74 | Q12: =Q10-Q11 -> 189733.2 | R12: =R10-R11 -> 219377.48 | T12: =T10-T11 -> 63183.201 | V12: =V10-V11 -> 70122.989 | W12: =W10-W11 -> 85376.91 | X12: =X10-X11 -> 99628.746 | Y12: =Y10-Y11 -> 116556.59 | Z12: =Z10-Z11 -> 136630.43 | AA12: =AA10-AA11 -> 160399.39 | AC12: =AC10-AC11 -> 68138.261 | AE12: =AE10-AE11 -> 87669.63 | AF12: =AF10-AF11 -> 104953.53 | AG12: =AG10-AG11 -> 108938.66 | AH12: =AH10-AH11 -> 112515.93 | AI12: =AI10-AI11 -> 115544.54 | AJ12: =AJ10-AJ11 -> 117857.21 | AL12: =AL10-AL11 -> 2056.6399 | AN12: =AN10-AN11 -> 2637.0543 | AO12: =AO10-AO11 -> 3176.5253 | AP12: =AP10-AP11 -> 3838.2011 | AQ12: =AQ10-AQ11 -> 4650.2864 | AR12: =AR10-AR11 -> 5647.5166 | AS12: =AS10-AS11 -> 6872.6702 | AU12: =AU10-AU11 -> 19179.523 | AW12: =AW10-AW11 -> 26075.694 | AX12: =AX10-AX11 -> 30632.119 | AY12: =AY10-AY11 -> 35990.715 | AZ12: =AZ10-AZ11 -> 42293.601 | BA12: =BA10-BA11 -> 49708.21 | BB12: =BB10-BB11 -> 58431.811 | BD12: =BD10-BD11 -> 74080.552 | BF12: =BF10-BF11 -> 93692.669 | BG12: =BG10-BG11 -> 106392.93 | BH12: =BH10-BH11 -> 120819.31 | BI12: =BI10-BI11 -> 137207.14 | BJ12: =BJ10-BJ11 -> 155823.98 | BK12: =BK10-BK11 -> 176973.99
