Workbook

Sheet Company Profile
A1: COMPANY PROFILE
A3: Logo | B3: #VALUE! | C3: #VALUE! | D3: #VALUE! | E3: #VALUE! | F3: #VALUE! | G3: #VALUE!
A4: Name | B4: #VALUE! | C4: #VALUE! | D4: #VALUE! | E4: #VALUE! | F4: #VALUE! | G4: #VALUE!
A5: Official Name | B5: {=_FV(B4,"Official name",TRUE)} -> COAL INDIA LTD | C5: {=_FV(C4,"Official name",TRUE)} -> HINDUSTAN ZINC LIMITED | D5: {=_FV(D4,"Official name",TRUE)} -> JSW Steel Limited | E5: {=_FV(E4,"Official name",TRUE)} -> TATA STEEL LIMITED | F5: {=_FV(F4,"Official name",TRUE)} -> STEEL AUTHORITY OF INDIA LIMITED | G5: {=_FV(G4,"Official name",TRUE)} -> NMDC LIMITED
A6: Industry | B6: {=_FV(B4,"Industry")} -> Coal | C6: {=_FV(C4,"Industry")} -> Metals & Mining | D6: {=_FV(D4,"Industry")} -> Metals & Mining | E6: {=_FV(E4,"Industry")} -> Metals & Mining | F6: {=_FV(F4,"Industry")} -> Metals & Mining | G6: {=_FV(G4,"Industry")} -> Metals & Mining
A7: Share Price | B7: {=_FV(B4,"Price")} -> 381.3 | C7: {=_FV(C4,"Price")} -> 484.65 | D7: {=_FV(D4,"Price")} -> 1179.3 | E7: {=_FV(E4,"Price")} -> 181.48 | F7: {=_FV(F4,"Price")} -> 144.34 | G7: {=_FV(G4,"Price")} -> 75.08
A8: Change (%) | B8: {=_FV(B4,"Change (%)",TRUE)} -> 0.013691 | C8: {=_FV(C4,"Change (%)",TRUE)} -> 0.021283 | D8: {=_FV(D4,"Change (%)",TRUE)} -> 0.006486 | E8: {=_FV(E4,"Change (%)",TRUE)} -> 0.0006065 | F8: {=_FV(F4,"Change (%)",TRUE)} -> 0.023688 | G8: {=_FV(G4,"Change (%)",TRUE)} -> 0.011315
A9: Shares Outstanding | B9: {=_FV(B4,"Shares outstanding",TRUE)} -> 6162729000 | C9: {=_FV(C4,"Shares outstanding",TRUE)} -> 4225319000 | D9: {=_FV(D4,"Shares outstanding",TRUE)} -> 2442547000 | E9: {=_FV(E4,"Shares outstanding",TRUE)} -> 12485450000 | F9: {=_FV(F4,"Shares outstanding",TRUE)} -> 4130525000 | G9: {=_FV(G4,"Shares outstanding",TRUE)} -> 8791817000
A10: In Crores | B10: =B9/10000000 -> 616.2729 | C10: =C9/10000000 -> 422.5319 | D10: =D9/10000000 -> 244.2547 | E10: =E9/10000000 -> 1248.545 | F10: =F9/10000000 -> 413.0525 | G10: =G9/10000000 -> 879.1817
A11: Market Cap | B11: {=_FV(B4,"Market cap",TRUE)} -> 2317186000000 | C11: {=_FV(C4,"Market cap",TRUE)} -> 2004914000000 | D11: {=_FV(D4,"Market cap",TRUE)} -> 2861933000000 | E11: {=_FV(E4,"Market cap",TRUE)} -> 2264138000000 | F11: {=_FV(F4,"Market cap",TRUE)} -> 582404100000 | G11: {=_FV(G4,"Market cap",TRUE)} -> 652704600000
A12: In crores | B12: =B11/10000000 -> 231718.6 | C12: =C11/10000000 -> 200491.4 | D12: =D11/10000000 -> 286193.3 | E12: =E11/10000000 -> 226413.8 | F12: =F11/10000000 -> 58240.41 | G12: =G11/10000000 -> 65270.46
A13: Beta | B13: {=_FV(B4,"Beta")} -> 1.0568 | C13: {=_FV(C4,"Beta")} -> 0.4783 | D13: {=_FV(D4,"Beta")} -> 0.8371 | E13: {=_FV(E4,"Beta")} -> 1.2322 | F13: {=_FV(F4,"Beta")} -> 1.7377 | G13: {=_FV(G4,"Beta")} -> 1.0063
A14: Year of Corporation | B14: {=_FV(B4,"Year incorporated",TRUE)} -> 1973 | C14: {=_FV(C4,"Year incorporated",TRUE)} -> 1966 | D14: {=_FV(D4,"Year incorporated",TRUE)} -> 1994 | E14: {=_FV(E4,"Year incorporated",TRUE)} -> 1907 | F14: {=_FV(F4,"Year incorporated",TRUE)} -> 1973 | G14: {=_FV(G4,"Year incorporated",TRUE)} -> 1958

Sheet Balance Sheet
A1: BALANCE SHEET
A3: #VALUE! | I3: #VALUE! | Q3: #VALUE! | Y3: #VALUE! | AG3: #VALUE! | AO3: #VALUE!
A4: Particulars | B4: 2020 | C4: 2021 | D4: 2022 | E4: 2023 | F4: 2024 | G4: 2025 | I4: Particulars | J4: 2020 | K4: 2021 | L4: 2022 | M4: 2023 | N4: 2024 | O4: 2025 | Q4: Particulars | R4: 2020 | S4: 2021 | T4: 2022 | U4: 2023 | V4: 2024 | W4: 2025 | Y4: Particulars | Z4: 2020 | AA4: 2021 | AB4: 2022 | AC4: 2023 | AD4: 2024 | AE4: 2025 | AG4: Particulars | AH4: 2020 | AI4: 2021 | AJ4: 2022 | AK4: 2023 | AL4: 2024 | AM4: 2025 | AO4: Particulars | AP4: 2020 | AQ4: 2021 | AR4: 2022 | AS4: 2023 | AT4: 2024 | AU4: 2025
A5: Non current assets | I5: Non current assets | Q5: Non Current assets | Y5: Non current assets | AG5: Non current assets | AO5: Non current assets
A6: PPE | B6: 32302.35 | C6: 37753.65 | D6: 42697.79 | E6: 44447.97 | F6: 67900.41 | G6: 76639.85 | I6: PPE | J6: 16217 | K6: 16447 | L6: 17165 | M6: 17530 | N6: 17971 | O6: 18485 | Q6: PPE | R6: 57625 | S6: 58857 | T6: 92952 | U6: 97699 | V6: 105123 | W6: 116814 | Y6: PPE | Z6: 119503 | AA6: 119003.5 | AB6: 116166.46 | AC6: 118696.74 | AD6: 123538.14 | AE6: 125215.17 | AG6: PPE | AH6: 65384.47 | AI6: 64133.48 | AJ6: 68382.92 | AK6: 67110.71 | AL6: 65415.07 | AM6: 65061.37 | AO6: PPE | AP6: 3253.87 | AQ6: 3313.92 | AR6: 3024.61 | AS6: 2381.31 | AT6: 2477.88 | AU6: 2634.35
A7: Capital work in progress | B7: 8271.09 | C7: 10403.66 | D7: 12713.73 | E7: 15262.62 | F7: 14738.66 | G7: 15888.64 | I7: Capital work in progress | J7: 2489 | K7: 1922 | L7: 2075 | M7: 2237 | N7: 1696 | O7: 2606 | Q7: Capital work in progress | R7: 26857 | S7: 32433 | T7: 16756 | U7: 21921 | V7: 29216 | W7: 20478 | Y7: Capital work in progress | Z7: 18862.06 | AA7: 18128.74 | AB7: 21227.62 | AC7: 30307.9 | AD7: 33370.19 | AE7: 40601.88 | AG7: Capital work in progress | AH7: 8753.33 | AI7: 8880.63 | AJ7: 4709.95 | AK7: 4891.36 | AL7: 6140.57 | AM7: 7206.21 | AO7: Right of use assets | AP7: 7.08 | AQ7: 7.02 | AR7: 8.27 | AS7: 7.44 | AT7: 42.61 | AU7: 1542.95
A8: Exploration and Evaluation assets | B8: 4443.12 | C8: 4605.81 | D8: 3873.55 | E8: 4924.85 | F8: 5049.58 | G8: 3645.3 | I8: Intangible assets | J8: 252 | K8: 361 | L8: 231 | M8: 92 | N8: 109 | O8: 65 | Q8: Investment property | R8: 224 | S8: 259 | T8: 180 | U8: 86 | V8: 140 | W8: 163 | Y8: Right of use assets | Z8: 8549.78 | AA8: 9450.95 | AB8: 8337.7 | AC8: 9222.52 | AD8: 7585.89 | AE8: 8087.95 | AG8: Right of use assets | AH8: 2205.08 | AI8: 2054.21 | AJ8: 3834.1 | AK8: 4910.28 | AL8: 5521.19 | AM8: 6838.6 | AO8: Capital work in progress | AP8: 15500.22 | AQ8: 17106.51 | AR8: 1328.31 | AS8: 1991.55 | AT8: 3230.51 | AU8: 4737.48
A9: Intangible assets | B9: 38.14 | C9: 45.76 | D9: 105.62 | E9: 2588.11 | F9: 2718.21 | G9: 2579.89 | I9: Loans | J9: 13 | K9: 12 | L9: 0 | M9: 257 | N9: 71 | O9: 58 | Q9: Right of use assets | R9: 3471 | S9: 3816 | T9: 4715 | U9: 4699 | V9: 4477 | W9: 4837 | Y9: Goodwill on consolidation | Z9: 4054.53 | AA9: 4344.69 | AB9: 4311.2 | AC9: 5601.65 | AD9: 5745.3 | AE9: 5958.53 | AG9: Investment property | AH9: 1.12 | AI9: 1.09 | AJ9: 1.06 | AK9: 1.03 | AL9: 0.99 | AM9: 0.96 | AO9: Goodwill | AP9: 93.89 | AQ9: 93.89 | AR9: 93.89 | AS9: 93.89 | AT9: 93.89 | AU9: 93.89
A10: Intangible assets under development | B10: 57.16 | C10: 86.17 | D10: 183.41 | E10: 2359.35 | F10: 4221.64 | G10: 6496.27 | I10: Others | J10: 40 | K10: 43 | L10: 2 | M10: 0 | N10: 578 | O10: 823 | Q10: Goodwill | R10: 415 | S10: 336 | T10: 119 | U10: 128 | V10: 639 | W10: 643 | Y10: Other intangible assets | Z10: 2442.37 | AA10: 2976.04 | AB10: 4472.47 | AC10: 13100.55 | AD10: 11945.05 | AE10: 11652.41 | AG10: Intangible assets | AH10: 1443.61 | AI10: 1429.38 | AJ10: 1459.41 | AK10: 1521.04 | AL10: 1488.86 | AM10: 1425.71 | AO10: Other intangible assets | AP10: 454.66 | AQ10: 518.57 | AR10: 535.72 | AS10: 715.93 | AT10: 762.24 | AU10: 767.27
A11: Investments | B11: 1873.17 | C11: 2317.64 | D11: 2426.97 | E11: 3085.4 | F11: 3859.31 | G11: 4416.07 | I11: Deferred tax assets | J11: 1822 | K11: 1058 | L11: 56 | M11: 112 | N11: 131 | O11: 96 | Q11: Other intangible assets | R11: 350 | S11: 1649 | T11: 1914 | U11: 1840 | V11: 2082 | W11: 2009 | Y11: Intangible assets under development | Z11: 634.77 | AA11: 878.66 | AB11: 817.93 | AC11: 905.12 | AD11: 985.34 | AE11: 1020.47 | AG11: Investments accounted for using the equity method | AH11: 3107.27 | AI11: 3297.56 | AJ11: 3587.35 | AK11: 3967.5 | AL11: 4278.55 | AM11: 4603.25 | AO11: Intangible assets under development | AP11: 29.64 | AQ11: 51.42 | AR11: 5 | AS11: 6.49 | AT11: 4.14 | AU11: 0
A12: Loans | B12: 638.59 | C12: 136.27 | D12: 355.47 | E12: 372.21 | F12: 358.71 | G12: 389.86 | I12: Other non current assets | J12: 480 | K12: 431 | L12: 275 | M12: 290 | N12: 145 | O12: 140 | Q12: Intangible assets under development | R12: 334 | S12: 133 | T12: 149 | U12: 245 | V12: 460 | W12: 529 | Y12: Equity accounted investments | Z12: 2168.54 | AA12: 2475.66 | AB12: =1210+2961.65 -> 4171.65 | AC12: 3233.33 | AD12: 2947.15 | AE12: 2970.86 | AG12: Inventories | AH12: 0 | AI12: 4236.26 | AJ12: 4598.45 | AK12: 4635.29 | AL12: 4625.29 | AM12: 4591.88 | AO12: Investments | AP12: 910.1 | AQ12: 874.9 | AR12: 894.95 | AS12: 934.68 | AT12: 951.17 | AU12: 974.53
A13: Other financial assets | B13: 12293.05 | C13: 13020.45 | D13: 14498.79 | E13: 16300.29 | F13: 18010.69 | G13: 19668.15 | I13: Income tax assets | J13: 849 | K13: 885 | L13: 884 | M13: 145 | N13: 569 | O13: 591 | Q13: Investments in joint ventures | R13: 283 | S13: 2969 | T13: 367 | U13: 700 | V13: 1709 | W13: 3689 | Y13: Investments | Z13: 684.77 | AA13: 987.38 | AB13: 1653.78 | AC13: 1546.92 | AD13: 2579.19 | AE13: 2780.6 | AG13: Investments | AH13: 133.12 | AI13: 144.7 | AJ13: 169.57 | AK13: 217.75 | AL13: 310.47 | AM13: 372.33 | AO13: Loans | AP13: 224.38 | AQ13: 259.17 | AR13: =40.77+589.75 -> 630.52 | AS13: =62.62+2646.17 -> 2708.79 | AT13: 81.74 | AU13: 126.72
A14: Deferred tax assets | B14: 3618.01 | C14: 4059.43 | D14: 4128.42 | E14: 4177 | F14: 3141.29 | G14: 2694.71 | I14: Total non current assets | J14: =SUM(J6:J13) -> 22162 | K14: =SUM(K6:K13) -> 21159 | L14: =SUM(L6:L13) -> 20688 | M14: =SUM(M6:M13) -> 20663 | N14: =SUM(N6:N13) -> 21270 | O14: =SUM(O6:O13) -> 22864 | Q14: Investments | R14: 974 | S14: 5604 | T14: 4565 | U14: 4101 | V14: 5534 | W14: 5709 | Y14: Loans | Z14: 488.71 | AA14: 336.57 | AB14: 72.44 | AC14: 64.74 | AD14: 73.14 | AE14: 114.66 | AG14: Trade receivables | AH14: 0.92 | AI14: 0.9 | AJ14: 0 | AK14: 0 | AL14: 0 | AM14: 0 | AO14: Deferred tax assets | AP14: 397.07 | AQ14: 408.28 | AR14: 568.94 | AS14: 297.5 | AT14: 265.89 | AU14: 296.25
A15: Other non current assets | B15: 3105.25 | C15: 4625.99 | D15: 6407.94 | E15: 9606.15 | F15: =71.14+13719.26 -> 13790.4 | G15: 31586.21 | I15: Current assets | Q15: Loans | R15: 772 | S15: 1022 | T15: 125 | U15: 130 | V15: 120 | W15: 70 | Y15: Derivative assets | Z15: 279.64 | AA15: 162.66 | AB15: 318.15 | AC15: 403.4 | AD15: 265.86 | AE15: 0.05 | AG15: Loans | AH15: 665.28 | AI15: 756.99 | AJ15: 559.61 | AK15: 655.26 | AL15: 877.37 | AM15: 950.93 | AO15: Other non current assets | AP15: 3502.9 | AQ15: 3695.91 | AR15: 2103.89 | AS15: 3302.92 | AT15: =2609.89+3860.79 -> 6470.68 | AU15: =2269.38+4187.38 -> 6456.76
A16: Total non current assets | B16: =SUM(B6:B15) -> 66639.93 | C16: =SUM(C6:C15) -> 77054.83 | D16: =SUM(D6:D15) -> 87391.69 | E16: =SUM(E6:E15) -> 103123.95 | F16: =SUM(F6:F15) -> 133788.9 | G16: =SUM(G6:G15) -> 164004.95 | I16: Inventories | J16: 1835 | K16: 1425 | L16: 1953 | M16: 1862 | N16: 1926 | O16: 1889 | Q16: Derivative assets | R16: 0 | S16: 110 | T16: 24 | U16: 18 | V16: 88 | W16: 116 | Y16: Other financial assets | Z16: 588.93 | AA16: 214.93 | AB16: 442.64 | AC16: 510.88 | AD16: 1608.32 | AE16: 1662.34 | AG16: Other financial assets | AH16: 448.58 | AI16: 336.25 | AJ16: 237.57 | AK16: 370.73 | AL16: 444.96 | AM16: 623.13 | AO16: Total non current assets | AP16: =SUM(AP6:AP15) -> 24373.81 | AQ16: =SUM(AQ6:AQ15) -> 26329.59 | AR16: =SUM(AR6:AR15) -> 9194.1 | AS16: =SUM(AS6:AS15) -> 12440.5 | AT16: =SUM(AT6:AT15) -> 14380.75 | AU16: =SUM(AU6:AU15) -> 17630.2
A17: Current Assets | I17: Investments | J17: 20329 | K17: 12957 | L17: 15052 | M17: 9850 | N17: 9874 | O17: 9149 | Q17: Other financial assets | R17: 696 | S17: 2154 | T17: 4084 | U17: 4799 | V17: 6135 | W17: 6899 | Y17: Retirement benefit assets | Z17: 27278.45 | AA17: 20019.47 | AB17: 20397.96 | AC17: 6990.83 | AD17: 23.26 | AE17: 12.67 | AG17: Deferred tax assets | AH17: 2022.17 | AI17: 0 | AJ17: 0 | AK17: 0 | AL17: 0 | AM17: 0 | AO17: Current assets
A18: Inventories | B18: 6617.98 | C18: 8947.47 | D18: 7075.68 | E18: 8154.68 | F18: 10177.23 | G18: 12613.7 | I18: Trade receivables | J18: 379 | K18: 406 | L18: 716 | M18: 380 | N18: 155 | O18: 117 | Q18: Current tax assets | R18: 385 | S18: 275 | T18: 528 | U18: =631+539 -> 1170 | V18: 1338 | W18: =829+297 -> 1126 | Y18: Non current tax assets | Z18: 1725.67 | AA18: 1845.34 | AB18: 3785.01 | AC18: 4369.03 | AD18: 4754.11 | AE18: 3824.52 | AG18: Current tax assets | AH18: 153.31 | AI18: 217.56 | AJ18: 296.34 | AK18: 595.49 | AL18: 374.78 | AM18: 452.14 | AO18: Inventories | AP18: 723.51 | AQ18: 921.72 | AR18: 2125.21 | AS18: 2660.58 | AT18: 2766.95 | AU18: 2637.72
A19: Investments | B19: 99.7 | C19: 3632.59 | D19: 6493.63 | E19: 4054.01 | F19: 3251.1 | G19: 3175.26 | I19: Cash and cash equivalents | J19: 1878 | K19: 313 | L19: 1592 | M19: 59 | N19: 53 | O19: 96 | Q19: Other non current assets | R19: 2956 | S19: 2848 | T19: 4633 | U19: 5392 | V19: 6603 | W19: 6924 | Y19: Deferred tax assets | Z19: 1270.33 | AA19: 1578.02 | AB19: 3023.93 | AC19: 2625.96 | AD19: 4111.08 | AE19: 3936.22 | AG19: Other non current assets | AH19: 1483.92 | AI19: 1572.65 | AJ19: 3433.13 | AK19: 3610.03 | AL19: 3092.79 | AM19: 2355.95 | AO19: Trade receivables | AP19: 2223.71 | AQ19: 2139.89 | AR19: 2954.3 | AS19: 2656.02 | AT19: 3508.93 | AU19: 7744.61
A20: Trade receivables | B20: 14408.22 | C20: 19623.12 | D20: 11367.68 | E20: 13060.48 | F20: 13255.75 | G20: 12727.72 | I20: Bank balances | J20: 40 | K20: 9063 | L20: 4171 | M20: 1353 | N20: 122 | O20: 81 | Q20: Total non current assets | R20: =SUM(R6:R19) -> 95342 | S20: =SUM(S6:S19) -> 112465 | T20: =SUM(T6:T19) -> 131111 | U20: =SUM(U6:U19) -> 142928 | V20: =SUM(V6:V19) -> 163664 | W20: =SUM(W6:W19) -> 170006 | Y20: Other assets | Z20: 3154.2 | AA20: 2872.7 | AB20: 3690.05 | AC20: 3776.63 | AD20: 3343.23 | AE20: 3164.93 | AG20: Total non current assets | AH20: =SUM(AH6:AH19) -> 85802.18 | AI20: =SUM(AI6:AI19) -> 87061.66 | AJ20: =SUM(AJ6:AJ19) -> 91269.46 | AK20: =SUM(AK6:AK19) -> 92486.47 | AL20: =SUM(AL6:AL19) -> 92570.89 | AM20: =SUM(AM6:AM19) -> 94482.46 | AO20: Cash and cash equivalents | AP20: 105.57 | AQ20: 464.1 | AR20: 120.6 | AS20: 93 | AT20: 109.39 | AU20: 84.82
A21: Cash and cash equivalents | B21: 2791.1 | C21: 5234.54 | D21: 7063.48 | E21: 5665.38 | F21: 6008.71 | G21: 11160.68 | I21: Loans | J21: 2 | K21: 2 | L21: 2 | M21: 3 | N21: 1 | O21: 1 | Q21: Current Assets | Y21: Total non current assets | Z21: =SUM(Z6:Z20) -> 191685.75 | AA21: =SUM(AA6:AA20) -> 185275.31 | AB21: =SUM(AB6:AB20) -> 192888.99 | AC21: =SUM(AC6:AC20) -> 201356.2 | AD21: =SUM(AD6:AD20) -> 202875.25 | AE21: =SUM(AE6:AE20) -> 211003.26 | AG21: Current assets | AO21: Bank balances | AP21: 2331.89 | AQ21: 5397.72 | AR21: 7856.87 | AS21: 7004.75 | AT21: 12254.26 | AU21: 10003.73
A22: Bank Balances | B22: 25657.86 | C22: 12075.76 | D22: 22901.75 | E22: 34256.48 | F22: 24226.46 | G22: 23054.63 | I22: Others | J22: 21 | K22: 53 | L22: 33 | M22: 89 | N22: 59 | O22: 42 | Q22: Inventories | R22: 13773 | S22: 14249 | T22: 33787 | U22: 33135 | V22: 37815 | W22: 34956 | Y22: Current assets | AG22: Inventories | AH22: 23836.27 | AI22: 15334.17 | AJ22: 19568.28 | AK22: 27764.9 | AL22: 32721.45 | AM22: 29151.45 | AO22: Other financial assets | AP22: 365.4 | AQ22: 292.61 | AR22: 583.86 | AS22: 490.79 | AT22: =40.29+295.51 -> 335.8 | AU22: =53.91+292.19 -> 346.1
A23: Loans | B23: 502.65 | C23: 501.28 | D23: 0.32 | E23: 20.79 | F23: 21.59 | G23: 18.9 | I23: Other current assets | J23: 329 | K23: 349 | L23: 463 | M23: 336 | N23: 435 | O23: 251 | Q23: Investments | R23: 2 | S23: 8 | T23: 8 | U23: 5 | V23: 3 | W23: 5819 | Y23: Inventories | Z23: 31068.72 | AA23: 33276.38 | AB23: 48824.39 | AC23: 54415.33 | AD23: 49157.51 | AE23: 44589.94 | AG23: Investments | AH23: 0 | AI23: 0 | AJ23: 0 | AK23: 0 | AL23: 15.11 | AM23: 3.9 | AO23: Current tax assets | AP23: 429.24 | AQ23: 257.05 | AR23: 899.86 | AS23: 1121.82 | AT23: 830.69 | AU23: 682.37
A24: Other financial assets | B24: 2779.28 | C24: 2344.77 | D24: 2620.91 | E24: 2716.96 | F24: 2698.51 | G24: 2475.77 | I24: Total current assets | J24: =SUM(J16:J23) -> 24813 | K24: =SUM(K16:K23) -> 24568 | L24: =SUM(L16:L23) -> 23982 | M24: =SUM(M16:M23) -> 13932 | N24: =SUM(N16:N23) -> 12625 | O24: =SUM(O16:O23) -> 11626 | Q24: Trade receivables | R24: 4505 | S24: 4486 | T24: 7457 | U24: 7134 | V24: 7548 | W24: 8415 | Y24: Investments | Z24: 3431.87 | AA24: 7218.89 | AB24: 8524.42 | AC24: 3630.06 | AD24: 731.23 | AE24: 442.65 | AG24: Trade receivables | AH24: 8844.73 | AI24: 7153.7 | AJ24: 4770.85 | AK24: 5389.97 | AL24: 8355.37 | AM24: 7609.94 | AO24: Other current assets | AP24: 740.64 | AQ24: 1126.48 | AR24: 1176.73 | AS24: 1779.59 | AT24: =1468.39+4.89 -> 1473.28 | AU24: =1872.79+3.6 -> 1876.39
A25: Current tax assets | B25: 8950.27 | C25: 9398.38 | D25: 8423.19 | E25: 8719 | F25: 9064.13 | G25: 9822.62 | I25: Total Assets | J25: =J14+J24 -> 46975 | K25: =K14+K24 -> 45727 | L25: =L14+L24 -> 44670 | M25: =M14+M24 -> 34595 | N25: =N14+N24 -> 33895 | O25: =O14+O24 -> 34490 | Q25: Cash and cash equivalents | R25: 3966 | S25: 11943 | T25: 8808 | U25: 15424 | V25: 8030 | W25: 11655 | Y25: Trade receivables | Z25: 7884.91 | AA25: 9539.84 | AB25: 12246.43 | AC25: 8257.24 | AD25: 6263.53 | AE25: 5260.06 | AG25: Cash and cash equivalents | AH25: 190.54 | AI25: 518.28 | AJ25: 131.54 | AK25: 57.09 | AL25: 69.38 | AM25: 291.58 | AO25: Assets held for sale | AP25: 0.66 | AQ25: 0.63 | AR25: 0.81 | AS25: 0.66 | AT25: 0.98 | AU25: 0.94
A26: Other current assets | B26: 21880.49 | C26: 22966.95 | D26: 26899.35 | E26: 31434.93 | F26: 35179.88 | G26: 21144.14 | I26: EQUITY AND LIABILITIES | Q26: Bank balances | R26: 8037 | S26: 870 | T26: 8575 | U26: 5290 | V26: 4318 | W26: 1630 | Y26: Cash and cash equivalents | Z26: 7541.96 | AA26: 5532.08 | AB26: 15604.68 | AC26: 12129.9 | AD26: 7080.84 | AE26: 9604.96 | AG26: Bank balances | AH26: 254.48 | AI26: 278.07 | AJ26: 654.52 | AK26: 493.55 | AL26: 603.57 | AM26: 675.3 | AO26: Total current assets | AP26: =SUM(AP18:AP25) -> 6920.62 | AQ26: =SUM(AQ18:AQ25) -> 10600.2 | AR26: =SUM(AR18:AR25) -> 15718.24 | AS26: =SUM(AS18:AS25) -> 15807.21 | AT26: =SUM(AT18:AT25) -> 21280.28 | AU26: =SUM(AU18:AU25) -> 23376.68
A27: Total current assets | B27: =SUM(B18:B26) -> 83687.55 | C27: =SUM(C18:C26) -> 84724.86 | D27: =SUM(D18:D26) -> 92845.99 | E27: =SUM(E18:E26) -> 108082.71 | F27: =SUM(F18:F26) -> 103883.36 | G27: =SUM(G18:G26) -> 96193.42 | I27: Equity | Q27: Loans | R27: 742 | S27: 622 | T27: 759 | U27: 717 | V27: 4 | W27: 2 | Y27: Bank balances | Z27: 512.76 | AA27: 250.1 | AB27: 294.25 | AC27: 1227.36 | AD27: 1596.88 | AE27: 2042.02 | AG27: Loans | AH27: 49.67 | AI27: 50.47 | AJ27: 43.1 | AK27: 35.29 | AL27: 28.31 | AM27: 22.6 | AO27: Total assets | AP27: =AP16+AP26 -> 31294.43 | AQ27: =AQ16+AQ26 -> 36929.79 | AR27: =AR16+AR26 -> 24912.34 | AS27: =AS16+AS26 -> 28247.71 | AT27: =AT16+AT26 -> 35661.03 | AU27: =AU16+AU26 -> 41006.88
A28: Total Assets | B28: =B16+B27 -> 150327.48 | C28: =C16+C27 -> 161779.69 | D28: =D16+D27 -> 180237.68 | E28: =E16+E27 -> 211206.66 | F28: =F16+F27 -> 237672.26 | G28: =G16+G27 -> 260198.37 | I28: Equity share capital | J28: 845 | K28: 845 | L28: 845 | M28: 845 | N28: 845 | O28: 845 | Q28: Derivative assets | R28: 294 | S28: 102 | T28: 426 | U28: 460 | V28: 173 | W28: 284 | Y28: Loans | Z28: 215.68 | AA28: 64.72 | AB28: 5.84 | AC28: 1.84 | AD28: 1.6 | AE28: 4.98 | AG28: Other financial assets | AH28: 2189.25 | AI28: 2478.32 | AJ28: 1338.45 | AK28: 1262.61 | AL28: 1369.07 | AM28: 1221.76 | AO28: EQUITY AND LIABILITIES
A29: EQUITY AND LIABILITIES | I29: Other equity | J29: 39465 | K29: 31468 | L29: 33436 | M29: 12087 | N29: 14350 | O29: 12481 | Q29: Other financial assets | R29: 2858 | S29: 1467 | T29: 1289 | U29: 1701 | V29: 1752 | W29: 1247 | Y29: Derivative assets | Z29: 1486.06 | AA29: 498.79 | AB29: 1172.74 | AC29: 561.46 | AD29: 201.33 | AE29: 370.5 | AG29: Other current assets | AH29: 5733.32 | AI29: 6354.19 | AJ29: 2318.92 | AK29: 2961.93 | AL29: 433.11 | AM29: 0 | AO29: Equity
A30: Equity | I30: Total Equity | J30: =J28+J29 -> 40310 | K30: =K28+K29 -> 32313 | L30: =L28+L29 -> 34281 | M30: =M28+M29 -> 12932 | N30: =N28+N29 -> 15195 | O30: =O28+O29 -> 13326 | Q30: Current tax assets | R30: 6 | S30: 6 | T30: 7 | U30: 3 | V30: 5 | W30: 15 | Y30: Other financial assets | Z30: 446.42 | AA30: 1420.97 | AB30: 2011.62 | AC30: 1435.51 | AD30: 1172.58 | AE30: 1456.14 | AG30: Assets classified for sale | AH30: 27.2 | AI30: 17.01 | AJ30: 14 | AK30: 29.28 | AL30: 4542.32 | AM30: 2911.95 | AO30: Equity share capital | AP30: 306.19 | AQ30: 293.07 | AR30: 293.07 | AS30: 293.07 | AT30: 293.07 | AU30: 879.18
A31: Equity share capital | B31: 6162.73 | C31: 6162.73 | D31: 6162.73 | E31: 6162.73 | F31: 6162.73 | G31: 6162.73 | I31: Non current liabilities | Q31: Other current assets | R31: 2286 | S31: 2091 | T31: 4250 | U31: 4277 | V31: 4885 | W31: 6684 | Y31: Retirement benefit assets | Z31: 0 | AA31: 0.42 | AB31: 1.25 | AC31: 0 | AD31: 0 | AE31: 2.33 | AG31: Total current assets | AH31: =SUM(AH22:AH30) -> 41125.46 | AI31: =SUM(AI22:AI30) -> 32184.21 | AJ31: =SUM(AJ22:AJ30) -> 28839.66 | AK31: =SUM(AK22:AK30) -> 37994.62 | AL31: =SUM(AL22:AL30) -> 48137.69 | AM31: =SUM(AM22:AM30) -> 41888.48 | AO31: Other equity | AP31: 27366.88 | AQ31: 29590.98 | AR31: 17725.18 | AS31: 22327.76 | AT31: 25362.83 | AU31: 28816.59
A32: Other equity | B32: 25994.19 | C32: 30354.63 | D32: 36980.31 | E32: 51082.16 | F32: 76567.05 | G32: 92942.19 | I32: Borrowings | J32: 0 | K32: 4312 | L32: 2111 | M32: 1500 | N32: 4246 | O32: 5990 | Q32: Assets classified as held for sale | R32: 9 | S32: 8 | T32: 8 | U32: 4 | V32: 1 | W32: 29 | Y32: Current tax assets | Z32: 143.2 | AA32: 156.74 | AB32: 61.63 | AC32: 117.69 | AD32: 79.68 | AE32: 79.52 | AG32: Total assets | AH32: =AH20+AH31 -> 126927.64 | AI32: =AI20+AI31 -> 119245.87 | AJ32: =AJ20+AJ31 -> 120109.12 | AK32: =AK20+AK31 -> 130481.09 | AL32: =AL20+AL31 -> 140708.58 | AM32: =AM20+AM31 -> 136370.94 | AO32: Non controlling interest | AP32: 8.05 | AQ32: 13.54 | AR32: 13.45 | AS32: 14.23 | AT32: 17.01 | AU32: 11.41
A33: Non controlling interest | B33: 394.08 | C33: 441.08 | D33: 673.79 | E33: 770.68 | F33: 852.12 | G33: 845.77 | I33: Lease Liabilities | J33: 0 | K33: 0 | L33: 6 | M33: 19 | N33: 178 | O33: 178 | Q33: Total current assets | R33: =SUM(R22:R32) -> 36478 | S33: =SUM(S22:S32) -> 35852 | T33: =SUM(T22:T32) -> 65374 | U33: =SUM(U22:U32) -> 68150 | V33: =SUM(V22:V32) -> 64534 | W33: =SUM(W22:W32) -> 70736 | Y33: Other assets | Z33: 3177.69 | AA33: 2153.44 | AB33: 3508.82 | AC33: 4829.75 | AD33: 4218.41 | AE33: 4538.44 | AG33: EQUITY AND LIABILITES | AO33: Total equity | AP33: =SUM(AP30:AP32) -> 27681.12 | AQ33: =SUM(AQ30:AQ32) -> 29897.59 | AR33: =SUM(AR30:AR32) -> 18031.7 | AS33: =SUM(AS30:AS32) -> 22635.06 | AT33: =SUM(AT30:AT32) -> 25672.91 | AU33: =SUM(AU30:AU32) -> 29707.18
A34: Total Equity | B34: =SUM(B31:B33) -> 32551 | C34: =SUM(C31:C33) -> 36958.44 | D34: =SUM(D31:D33) -> 43816.83 | E34: =SUM(E31:E33) -> 58015.57 | F34: =SUM(F31:F33) -> 83581.9 | G34: =SUM(G31:G33) -> 99950.69 | I34: Other financial liabilities | J34: 22 | K34: 8 | L34: 1024 | M34: 1060 | N34: =925 -> 925 | O34: =342+963 -> 1305 | Q34: Total assets | R34: =R20+R33 -> 131820 | S34: =S20+S33 -> 148317 | T34: =T20+T33 -> 196485 | U34: =U20+U33 -> 211078 | V34: =V20+V33 -> 228198 | W34: =W20+W33 -> 240742 | Y34: Total current assets | Z34: =SUM(Z23:Z33) -> 55909.27 | AA34: =SUM(AA23:AA33) -> 60112.37 | AB34: =SUM(AB23:AB33) -> 92256.07 | AC34: =SUM(AC23:AC33) -> 86606.14 | AD34: =SUM(AD23:AD33) -> 70503.59 | AE34: =SUM(AE23:AE33) -> 68391.54 | AG34: Equity | AO34: Non current liabilities
A35: Non current liabilities | I35: Other non current liabilities | J35: 1068 | K35: 1036 | L35: 212 | M35: 189 | N35: 199 | O35: 200 | Q35: EQUITY AND LIABILITIES | Y35: Assets held for sale | Z35: 2823.45 | AA35: 99.53 | AB35: 300.54 | AC35: 59.4 | AD35: 44.66 | AE35: 0 | AG35: Equity share capital | AH35: 4130.53 | AI35: 4130.53 | AJ35: 4130.53 | AK35: 4130.53 | AL35: 4130.53 | AM35: 4130.53 | AO35: Borrowings | AP35: 0 | AQ35: 546.43 | AR35: 0 | AS35: 0 | AT35: 0 | AU35: 0
A36: Borrowings | B36: 1993.38 | C36: 2688.1 | D36: 3301.78 | E36: 4106.25 | F36: 5617.2 | G36: 7385.75 | I36: Provisions | J36: 162 | K36: 182 | L36: 942 | M36: 2314 | N36: 2311 | O36: 2292 | Q36: Equity | Y36: Total assets | Z36: =Z21+Z34+Z35 -> 250418.47 | AA36: =AA21+AA34+AA35 -> 245487.21 | AB36: =AB21+AB34+AB35 -> 285445.6 | AC36: =AC21+AC34+AC35 -> 288021.74 | AD36: =AD21+AD34+AD35 -> 273423.5 | AE36: =AE21+AE34+AE35 -> 279394.8 | AG36: Other equity | AH36: 37379.7 | AI36: 41275.69 | AJ36: 50081.15 | AK36: 50616.14 | AL36: 52970.69 | AM36: 54775.08 | AO36: Lease liabilities | AP36: 0 | AQ36: 0 | AR36: 5.85 | AS36: 5.02 | AT36: 1.76 | AU36: 1.97
A37: Lease liabilities | B37: 0 | C37: 0 | D37: 159.66 | E37: 157 | F37: 156.29 | G37: 146.46 | I37: Total non current liabilities | J37: =SUM(J32:J36) -> 1252 | K37: =SUM(K32:K36) -> 5538 | L37: =SUM(L32:L36) -> 4295 | M37: =SUM(M32:M36) -> 5082 | N37: =SUM(N32:N36) -> 7859 | O37: =SUM(O32:O36) -> 9965 | Q37: Equity share capital | R37: 301 | S37: 302 | T37: 301 | U37: 301 | V37: 305 | W37: 305 | Y37: EQUITY AND LIABILITES | AG37: Non controlling interest | AH37: 0.01 | AI37: 0.01 | AJ37: 0.01 | AK37: 0.01 | AL37: 0.01 | AM37: -0.01 | AO37: Other financial liabilities | AP37: 5.83 | AQ37: 4.7 | AR37: 150.28 | AS37: 150.28 | AT37: 150.28 | AU37: 150.28
A38: Other financial liabilities | B38: 802.51 | C38: 942.3 | D38: 2477.84 | E38: 3207.57 | F38: 3469.26 | G38: 3427.31 | I38: Current Liabilities | Q38: Other equity | R38: 36298 | S38: 46462 | T38: 66996 | U38: 65394 | V38: 77364 | W38: 79191 | Y38: Equity | AG38: Total equity | AH38: =SUM(AH35:AH37) -> 41510.24 | AI38: =SUM(AI35:AI37) -> 45406.23 | AJ38: =SUM(AJ35:AJ37) -> 54211.69 | AK38: =SUM(AK35:AK37) -> 54746.68 | AL38: =SUM(AL35:AL37) -> 57101.23 | AM38: =SUM(AM35:AM37) -> 58905.6 | AO38: Provisions | AP38: 827.96 | AQ38: 945.41 | AR38: 1092.46 | AS38: 1255.99 | AT38: 1431.26 | AU38: 1479.09
A39: Provisions | B39: 60223.45 | C39: 63178.61 | D39: 65944 | E39: 68827.95 | F39: 74311.01 | G39: 74531.52 | I39: Borrowings | J39: 611 | K39: 2161 | L39: 712 | M39: 10341 | N39: 4210 | O39: 4661 | Q39: Non controlling interests | R39: -575 | S39: -619 | T39: 1238 | U39: 1344 | V39: 2107 | W39: 2170 | Y39: Equity share capital | Z39: 1144.95 | AA39: 1197.61 | AB39: 1221.21 | AC39: 1221.24 | AD39: 1247.44 | AE39: 1247.44 | AG39: Non current liabilities | AO39: Total non current liabilities | AP39: =SUM(AP35:AP38) -> 833.79 | AQ39: =SUM(AQ35:AQ38) -> 1496.54 | AR39: =SUM(AR35:AR38) -> 1248.59 | AS39: =SUM(AS35:AS38) -> 1411.29 | AT39: =SUM(AT35:AT38) -> 1583.3 | AU39: =SUM(AU35:AU38) -> 1631.34
A40: Deferred tax liabilities | B40: 307.04 | C40: 722.07 | D40: 801.35 | E40: 1330.68 | F40: 1822.16 | G40: 1831.9 | I40: Lease Liabilities | J40: 0 | K40: 0 | L40: 15 | M40: 21 | N40: 88 | O40: 138 | Q40: Total equity | R40: =SUM(R37:R39) -> 36024 | S40: =SUM(S37:S39) -> 46145 | T40: =SUM(T37:T39) -> 68535 | U40: =SUM(U37:U39) -> 67039 | V40: =SUM(V37:V39) -> 79776 | W40: =SUM(W37:W39) -> 81666 | Y40: Hybrid perpetual securities | Z40: 2275 | AA40: 775 | AB40: 0 | AC40: 0 | AD40: 0 | AE40: 0 | AG40: Borrowings | AH40: 34560.03 | AI40: 19726.03 | AJ40: 8135.81 | AK40: 6112.58 | AL40: 9568.21 | AM40: 10100.95 | AO40: Current liabilities
A41: Other non current liabilities | B41: 5381.81 | C41: 5647.3 | D41: 6527.71 | E41: 6826.99 | F41: 7441.9 | G41: 8183.09 | I41: Operational buyers credit | J41: 76 | K41: 0 | L41: 280 | M41: 307 | N41: 399 | O41: 569 | Q41: Non current liabilities | Y41: Other equity | Z41: 70156.35 | AA41: 72266.16 | AB41: 113221.83 | AC41: 101860.86 | AD41: 90788.32 | AE41: 89922.19 | AG41: Total outstanding dues of micro and small enterprises | AH41: 0 | AI41: 0 | AJ41: 0 | AK41: 0 | AL41: 0 | AM41: 0 | AO41: Borrowings | AP41: 565.57 | AQ41: 1448.04 | AR41: 1792.5 | AS41: 415.98 | AT41: 3356.54 | AU41: 3770.45
A42: Total non current liabilities | B42: =SUM(B36:B41) -> 68708.19 | C42: =SUM(C36:C41) -> 73178.38 | D42: =SUM(D36:D41) -> 79212.34 | E42: =SUM(E36:E41) -> 84456.44 | F42: =SUM(F36:F41) -> 92817.82 | G42: =SUM(G36:G41) -> 95506.03 | I42: Total outstanding dues of micro, small and medium enterprises | J42: 36 | K42: 38 | L42: 2038 | M42: 2088 | N42: 2106 | O42: 2204 | Q42: Borrowings | R42: 44673 | S42: 49731 | T42: 57929 | U42: 61966 | V42: 67354 | W42: 81983 | Y42: Non controlling interest | Z42: 2586.6 | AA42: 3269.68 | AB42: 2655.42 | AC42: 2093.11 | AD42: 396.98 | AE42: 183.15 | AG42: Total outstanding dues of creditors other than above | AH42: 10.7 | AI42: 4.1 | AJ42: 3.34 | AK42: 3.31 | AL42: 6.07 | AM42: 5.93 | AO42: Total outstanding dues of small and micro enterprises | AP42: 15.25 | AQ42: 12.66 | AR42: 26.59 | AS42: 25.23 | AT42: 28.29 | AU42: 34.94
A43: Current Liabilities | I43: Total outstanding dues to creditors other than above | J43: 1376 | K43: 1507 | L43: 0 | M43: 0 | N43: 0 | O43: 0 | Q43: Lease Liabilities | R43: 1744 | S43: 1939 | T43: 1582 | U43: 1594 | V43: 2060 | W43: 2399 | Y43: Total equity | Z43: =SUM(Z39:Z42) -> 76162.9 | AA43: =SUM(AA39:AA42) -> 77508.45 | AB43: =SUM(AB39:AB42) -> 117098.46 | AC43: =SUM(AC39:AC42) -> 105175.21 | AD43: =SUM(AD39:AD42) -> 92432.74 | AE43: =SUM(AE39:AE42) -> 91352.78 | AG43: Total trade payables | AH43: =AH41+AH42 -> 10.7 | AI43: =AI41+AI42 -> 4.1 | AJ43: =AJ41+AJ42 -> 3.34 | AK43: =AK41+AK42 -> 3.31 | AL43: =AL41+AL42 -> 6.07 | AM43: =AM41+AM42 -> 5.93 | AO43: Total outstanding dues of creditors other than above | AP43: 210.65 | AQ43: 348.12 | AR43: 638.17 | AS43: 400.68 | AT43: 384.26 | AU43: 286.52
A44: Borrowings | B44: 4432.61 | C44: 3187.2 | D44: 7.98 | E44: 8.48 | F44: 671.82 | G44: 1522.65 | I44: Total trade payables | J44: =J42+J43 -> 1412 | K44: =K42+K43 -> 1545 | L44: =L42+L43 -> 2038 | M44: =M42+M43 -> 2088 | N44: =N42+N43 -> 2106 | O44: =O42+O43 -> 2204 | Q44: Derivative liabilities | R44: 130 | S44: 57 | T44: 7 | U44: 15 | V44: 10 | W44: 0 | Y44: Non current liabilities | AG44: Lease Liabilities | AH44: 0 | AI44: 0 | AJ44: 3606.44 | AK44: 4737.13 | AL44: 5235.25 | AM44: 6553.42 | AO44: Total trade payables | AP44: =AP42+AP43 -> 225.9 | AQ44: =AQ42+AQ43 -> 360.78 | AR44: =AR42+AR43 -> 664.76 | AS44: =AS42+AS43 -> 425.91 | AT44: =AT42+AT43 -> 412.55 | AU44: =AU42+AU43 -> 321.46
A45: Total outstanding dues of micro and small enterprises | B45: 10.39 | C45: 27.47 | D45: 42.54 | E45: 53.9 | F45: 157.38 | G45: 164.77 | I45: Other financial liabilities | J45: 1487 | K45: 1971 | L45: 1901 | M45: 2419 | N45: 1414 | O45: 1717 | Q45: Other financial liabilities | R45: 464 | S45: 588 | T45: 699 | U45: 1131 | V45: 1774 | W45: 3124 | Y45: Borrowings | Z45: 94104.97 | AA45: 72408.79 | AB45: 44764.07 | AC45: 51446.33 | AD45: 51576.73 | AE45: 68551.81 | AG45: Other financial liabilities | AH45: 1368.51 | AI45: 1304.08 | AJ45: 1424.79 | AK45: 1429 | AL45: 1449.99 | AM45: 1472.57 | AO45: Lease liabilities | AP45: 0 | AQ45: 0 | AR45: 1.59 | AS45: 1.66 | AT45: 0.48 | AU45: 503.4
A46: Total outstanding dues other than above | B46: 7240.57 | C46: 7610.16 | D46: 8560.99 | E46: 8495.28 | F46: 8228.27 | G46: 10040.86 | I46: Other current liabilities | J46: 1694 | K46: 1947 | L46: 860 | M46: 1687 | N46: 2126 | O46: 1579 | Q46: Provisions | R46: 348 | S46: 852 | T46: 1481 | U46: 1395 | V46: 1451 | W46: 1399 | Y46: Derivative liabilities | Z46: 127.92 | AA46: 71.41 | AB46: 10.35 | AC46: 0 | AD46: 0.11 | AE46: 206.38 | AG46: Provisions | AH46: 4115.81 | AI46: 4533.75 | AJ46: 5342.89 | AK46: 5616.63 | AL46: 5737.42 | AM46: 6106.43 | AO46: Other financial liabilities | AP46: 1220.02 | AQ46: 1776.04 | AR46: 521.78 | AS46: 896.93 | AT46: 1119.28 | AU46: 1663.89
A47: Total trade payables | B47: =B45+B46 -> 7250.96 | C47: =C45+C46 -> 7637.63 | D47: =D45+D46 -> 8603.53 | E47: =E45+E46 -> 8549.18 | F47: =F45+F46 -> 8385.65 | G47: =G45+G46 -> 10205.63 | I47: Provisions | J47: 70 | K47: 70 | L47: 32 | M47: 26 | N47: 21 | O47: 19 | Q47: Deferred tax liabilities | R47: 1677 | S47: 3509 | T47: 7621 | U47: 7936 | V47: 9659 | W47: 9510 | Y47: Lease liabilities | Z47: 0 | AA47: 0 | AB47: 5696.46 | AC47: 5811.08 | AD47: 4538.7 | AE47: 4832.71 | AG47: Deferred tax liabilities | AH47: 0 | AI47: 1334.08 | AJ47: 5358.42 | AK47: 5821.27 | AL47: 6285.5 | AM47: 6542.82 | AO47: Other current liabilities | AP47: 545.25 | AQ47: 1852.24 | AR47: 2636.3 | AS47: 2337.02 | AT47: =3027.12+233.56 -> 3260.68 | AU47: =2773.83+251.58 -> 3025.41
A48: Lease liabilities | B48: 0 | C48: 0 | D48: 44.22 | E48: 59.69 | F48: 77.72 | G48: 90.87 | I48: Current tax liabilities | J48: 63 | K48: 182 | L48: 256 | M48: 564 | N48: 477 | O48: 312 | Q48: Other non current liabilities | R48: 3072 | S48: 2197 | T48: 1080 | U48: 39 | V48: 49 | W48: 35 | Y48: Other financial liabilities | Z48: 387.67 | AA48: 522.7 | AB48: 989.57 | AC48: 1871.51 | AD48: 1491.83 | AE48: 1294.17 | AG48: Other non current liabilities | AH48: 397.51 | AI48: 439.97 | AJ48: 2682.82 | AK48: 2682.21 | AL48: 1860.49 | AM48: 493.13 | AO48: Provisions | AP48: 222.78 | AQ48: 98.56 | AR48: 15.12 | AS48: 123.86 | AT48: 255.29 | AU48: 383.75
A49: Other financial liabilities | B49: 8446.8 | C49: 9925.3 | D49: 11431.07 | E49: 12815.19 | F49: 16148.19 | G49: 17202.86 | I49: Total current liabilities | J49: =SUM(J39:J41,J44:J48) -> 5413 | K49: =SUM(K39:K41,K44:K48) -> 7876 | L49: =SUM(L39:L41,L44:L48) -> 6094 | M49: =SUM(M39:M41,M44:M48) -> 17453 | N49: =SUM(N39:N41,N44:N48) -> 10841 | O49: =SUM(O39:O41,O44:O48) -> 11199 | Q49: Total non current liabilities | R49: =SUM(R42:R48) -> 52108 | S49: =SUM(S42:S48) -> 58873 | T49: =SUM(T42:T48) -> 70399 | U49: =SUM(U42:U48) -> 74076 | V49: =SUM(V42:V48) -> 82357 | W49: =SUM(W42:W48) -> 98450 | Y49: Provisions | Z49: 4235.07 | AA49: 4691.92 | AB49: 4825.98 | AC49: 4775.84 | AD49: 5424.03 | AE49: 5806.5 | AG49: Total non current liabilities | AH49: =SUM(AH40,AH43:AH48) -> 40452.56 | AI49: =SUM(AI40,AI43:AI48) -> 27342.01 | AJ49: =SUM(AJ40,AJ43:AJ48) -> 26554.51 | AK49: =SUM(AK40,AK43:AK48) -> 26402.13 | AL49: =SUM(AL40,AL43:AL48) -> 30142.93 | AM49: =SUM(AM40,AM43:AM48) -> 31275.25 | AO49: Total current liabilities | AP49: =SUM(AP41,AP44:AP48) -> 2779.52 | AQ49: =SUM(AQ41,AQ44:AQ48) -> 5535.66 | AR49: =SUM(AR41,AR44:AR48) -> 5632.05 | AS49: =SUM(AS41,AS44:AS48) -> 4201.36 | AT49: =SUM(AT41,AT44:AT48) -> 8404.82 | AU49: =SUM(AU41,AU44:AU48) -> 9668.36
A50: Other current liabilities | B50: 22156.48 | C50: 24426.84 | D50: 30897.32 | E50: =32313.94+24.78 -> 32338.72 | F50: 29110.25 | G50: 29494.17 | I50: Total equity and liabilities | J50: =J30+J37+J49 -> 46975 | K50: =K30+K37+K49 -> 45727 | L50: =L30+L37+L49 -> 44670 | M50: =M30+M37+M49 -> 35467 | N50: =N30+N37+N49 -> 33895 | O50: =O30+O37+O49 -> 34490 | Q50: Current liabilities | Y50: Retirement benefit obligations | Z50: 3598.18 | AA50: 3499.79 | AB50: 3413.71 | AC50: 2931.37 | AD50: 3219.48 | AE50: 3272.01 | AG50: Current Liabilities | AO50: Total equity and liabilities | AP50: =AP33+AP39+AP49 -> 31294.43 | AQ50: =AQ33+AQ39+AQ49 -> 36929.79 | AR50: =AR33+AR39+AR49 -> 24912.34 | AS50: =AS33+AS39+AS49 -> 28247.71 | AT50: =AT33+AT39+AT49 -> 35661.03 | AU50: =AU33+AU39+AU49 -> 41006.88
A51: Provisions | B51: 6781.44 | C51: 6465.9 | D51: 6224.39 | E51: 14963.38 | F51: =6680.58+198.33 -> 6878.91 | G51: =6222.35+3.12 -> 6225.47 | I51: Working capital | J51: =J24-J49 -> 19400 | K51: =K24-K49 -> 16692 | L51: =L24-L49 -> 17888 | M51: =M24-M49 -> -3521 | N51: =N24-N49 -> 1784 | O51: =O24-O49 -> 427 | Q51: Borrowings | R51: 8325 | S51: 1999 | T51: 12046 | U51: 16876 | V51: 18221 | W51: 13974 | Y51: Deferred income | Z51: 151.3 | AA51: 144.26 | AB51: 137.16 | AC51: 132.36 | AD51: 433.65 | AE51: 764.91 | AG51: Borrowings | AH51: 16640.78 | AI51: 15850.24 | AJ51: 5249.84 | AK51: 19549.2 | AL51: 21032.76 | AM51: 19710.17 | AO51: Working capital | AP51: =AP26-AP49 -> 4141.1 | AQ51: =AQ26-AQ49 -> 5064.54 | AR51: =AR26-AR49 -> 10086.19 | AS51: =AS26-AS49 -> 11605.85 | AT51: =AT26-AT49 -> 12875.46 | AU51: =AU26-AU49 -> 13708.32
A52: Total current liabilities | B52: =SUM(B44,B47:B51) -> 49068.29 | C52: =SUM(C44,C47:C51) -> 51642.87 | D52: =SUM(D44,D47:D51) -> 57208.51 | E52: =SUM(E44,E47:E51) -> 68734.64 | F52: =SUM(F44,F47:F51) -> 61272.54 | G52: =SUM(G44,G47:G51) -> 64741.65 | Q52: Total outstanding dues of small and micro enterprises | R52: 142 | S52: 230 | T52: 497 | U52: 436 | V52: 1100 | W52: 1316 | Y52: Deferred tax liabilities | Z52: 9261.38 | AA52: 9241.42 | AB52: 12325.78 | AC52: 14115.64 | AD52: 12992.34 | AE52: 14430.15 | AG52: Total outstanding dues of micro and small enterprises | AH52: 47.99 | AI52: 103.57 | AJ52: 140.65 | AK52: 448.62 | AL52: 498.06 | AM52: 637.65
A53: Total Equity and Liabilities | B53: =B34+B42+B52 -> 150327.48 | C53: =C34+C42+C52 -> 161779.69 | D53: =D34+D42+D52 -> 180237.68 | E53: =E34+E42+E52 -> 211206.65 | F53: =F34+F42+F52 -> 237672.26 | G53: =G34+G42+G52 -> 260198.37 | I53: Working capital Forecast | J53: 2026 | K53: 2027 | L53: 2028 | M53: 2029 | N53: 2030 | Q53: Total outstanding dues other than above | R53: 17776 | S53: 15013 | T53: 30392 | U53: 37767 | V53: 14611 | W53: 10702 | Y53: Other liabilities | Z53: 729.15 | AA53: 6531.34 | AB53: 5596.06 | AC53: 4467.27 | AD53: 2910.41 | AE53: 2789.83 | AG53: Total outstanding dues of creditors other than above | AH53: 6274.38 | AI53: 6911.43 | AJ53: 16535.71 | AK53: 13893.08 | AL53: 14834.33 | AM53: 9866.34 | AO53: Working capital Forecast | AP53: 2026 | AQ53: 2027 | AR53: 2028 | AS53: 2029 | AT53: 2030
A54: Working Capital | B54: =B27-B52 -> 34619.26 | C54: =C27-C52 -> 33081.99 | D54: =D27-D52 -> 35637.48 | E54: =E27-E52 -> 39348.07 | F54: =F27-F52 -> 42610.82 | G54: =G27-G52 -> 31451.77 | I54: Value | J54: =DCF!M5*DCF!$L$11 -> 1303.0284 | K54: =DCF!N5*DCF!$L$11 -> 1425.0396 | L54: =DCF!O5*DCF!$L$11 -> 1558.4755 | M54: =DCF!P5*DCF!$L$11 -> 1704.4059 | N54: =DCF!Q5*DCF!$L$11 -> 1864.0007 | Q54: Total trade payables | R54: =R52+R53 -> 17918 | S54: =S52+S53 -> 15243 | T54: =T52+T53 -> 30889 | U54: =U52+U53 -> 38203 | V54: =V52+V53 -> 15711 | W54: =W52+W53 -> 12018 | Y54: Total non current liabilities | Z54: =SUM(Z45:Z53) -> 112595.64 | AA54: =SUM(AA45:AA53) -> 97111.63 | AB54: =SUM(AB45:AB53) -> 77759.14 | AC54: =SUM(AC45:AC53) -> 85551.4 | AD54: =SUM(AD45:AD53) -> 82587.28 | AE54: =SUM(AE45:AE53) -> 101948.47 | AG54: Total trade payables | AH54: =AH52+AH53 -> 6322.37 | AI54: =AI52+AI53 -> 7015 | AJ54: =AJ52+AJ53 -> 16676.36 | AK54: =AK52+AK53 -> 14341.7 | AL54: =AL52+AL53 -> 15332.39 | AM54: =AM52+AM53 -> 10503.99 | AO54: Value | AP54: =DCF!AW5*DCF!$AV$11 -> 13668.285 | AQ54: =DCF!AX5*DCF!$AV$11 -> 15452.317 | AR54: =DCF!AY5*DCF!$AV$11 -> 17469.206 | AS54: =DCF!AZ5*DCF!$AV$11 -> 19749.347 | AT54: =DCF!BA5*DCF!$AV$11 -> 22327.1
Q55: Derivative liabilities | R55: 251 | S55: 110 | T55: 115 | U55: 405 | V55: 329 | W55: 227 | Y55: Current liabilities | AG55: Lease Liabilities | AH55: 0 | AI55: 0 | AJ55: 292.08 | AK55: 374.52 | AL55: 486.43 | AM55: 569.4
A56: Working capital Forecast | B56: 2026 | C56: 2027 | D56: 2028 | E56: 2029 | F56: 2030 | Q56: Lease Liabilities | R56: 306 | S56: 405 | T56: 680 | U56: 417 | V56: 349 | W56: 396 | Y56: Borrowings | Z56: 19184.48 | AA56: 9492.11 | AB56: 24064.61 | AC56: 26571.37 | AD56: 29997.19 | AE56: 20412 | AG56: Other financial liabilities | AH56: 13740.89 | AI56: 14023.78 | AJ56: 11875.42 | AK56: 10150.2 | AL56: 10543.57 | AM56: 9671.15
A57: Value | B57: =DCF!D5*DCF!$C$11 -> 46569.308 | C57: =DCF!E5*DCF!$C$11 -> 49773.743 | D57: =DCF!F5*DCF!$C$11 -> 53198.675 | E57: =DCF!G5*DCF!$C$11 -> 56859.276 | F57: =DCF!H5*DCF!$C$11 -> 60771.764 | Q57: Other financial liabilities | R57: 14143 | S57: 21347 | T57: 8415 | U57: 7976 | V57: 8446 | W57: 7388 | Y57: Total outstanding dues of micro and small enterprises | Z57: 198.86 | AA57: 484.66 | AB57: 897.5 | AC57: 1170.33 | AD57: 1203.7 | AE57: 1510.71 | AG57: Other current liabilities | AH57: 5724.06 | AI57: 7555.15 | AJ57: 4076.89 | AK57: 3533.85 | AL57: 4565.97 | AM57: 4196.35
Q58: Provisions | R58: 161 | S58: 274 | T58: 256 | U58: 280 | V58: 439 | W58: 285 | Y58: Total outstanding dues of creditors other than above | Z58: 21181.99 | AA58: 25482.83 | AB58: 35867.37 | AC58: 36662.21 | AD58: 29023.94 | AE58: 27803.67 | AG58: Provisions | AH58: 2357.24 | AI58: 2041.4 | AJ58: 1171.67 | AK58: 1381.68 | AL58: 1294.11 | AM58: 1391.05
Q59: Other current liabilities | R59: 2455 | S59: 3365 | T59: 4759 | U59: 4457 | V59: =4564+17654 -> 22218 | W59: =5606+20534 -> 26140 | Y59: Total trade payables | Z59: =Z57+Z58 -> 21380.85 | AA59: =AA57+AA58 -> 25967.49 | AB59: =AB57+AB58 -> 36764.87 | AC59: =AC57+AC58 -> 37832.54 | AD59: =AD57+AD58 -> 30227.64 | AE59: =AE57+AE58 -> 29314.38 | AG59: Current tax liabilities | AH59: 179.5 | AI59: 12.06 | AJ59: 0.66 | AK59: 3.13 | AL59: 209.19 | AM59: 147.98
Q60: Current tax liabilities | R60: 129 | S60: 556 | T60: 391 | U60: 1349 | V60: 352 | W60: 198 | Y60: Lease liabilities | Z60: 0 | AA60: 0 | AB60: 1036.21 | AC60: 1064.27 | AD60: 969.5 | AE60: 1004.53 | AG60: Total current liabilities | AH60: =SUM(AH51,AH54:AH59) -> 44964.84 | AI60: =SUM(AI51,AI54:AI59) -> 46497.63 | AJ60: =SUM(AJ51,AJ54:AJ59) -> 39342.92 | AK60: =SUM(AK51,AK54:AK59) -> 49334.28 | AL60: =SUM(AL51,AL54:AL59) -> 53464.42 | AM60: =SUM(AM51,AM54:AM59) -> 46190.09
Q61: Total current liabilities | R61: =SUM(R51,R54:R60) -> 43688 | S61: =SUM(S51,S54:S60) -> 43299 | T61: =SUM(T51,T54:T60) -> 57551 | U61: =SUM(U51,U54:U60) -> 69963 | V61: =SUM(V51,V54:V60) -> 66065 | W61: =SUM(W51,W54:W60) -> 60626 | Y61: Derivative liabilities | Z61: 729.22 | AA61: 510.01 | AB61: 196.91 | AC61: 1630.53 | AD61: 214.38 | AE61: 391.18 | AG61: Total equity and liabilities | AH61: =AH38+AH49+AH60 -> 126927.64 | AI61: =AI38+AI49+AI60 -> 119245.87 | AJ61: =AJ38+AJ49+AJ60 -> 120109.12 | AK61: =AK38+AK49+AK60 -> 130483.09 | AL61: =AL38+AL49+AL60 -> 140708.58 | AM61: =AM38+AM49+AM60 -> 136370.94
Q62: Total equity and liabilities | R62: =R40+R49+R61 -> 131820 | S62: =S40+S49+S61 -> 148317 | T62: =T40+T49+T61 -> 196485 | U62: =U40+U49+U61 -> 211078 | V62: =V40+V49+V61 -> 228198 | W62: =W40+W49+W61 -> 240742 | Y62: Other financial liabilities | Z62: 9518.53 | AA62: 14403.11 | AB62: 8381.41 | AC62: 9590.21 | AD62: 15652.68 | AE62: 15820.51 | AG62: Working Capital | AH62: =AH31-AH60 -> -3839.38 | AI62: =AI31-AI60 -> -14313.42 | AJ62: =AJ31-AJ60 -> -10503.26 | AK62: =AK31-AK60 -> -11339.66 | AL62: =AL31-AL60 -> -5326.73 | AM62: =AM31-AM60 -> -4301.61
Q63: Working capital | R63: =R33-R61 -> -7210 | S63: =S33-S61 -> -7447 | T63: =T33-T61 -> 7823 | U63: =U33-U61 -> -1813 | V63: =V33-V61 -> -1531 | W63: =W33-W61 -> 10110 | Y63: Provisions | Z63: 1663.67 | AA63: 4725.32 | AB63: 2768.49 | AC63: 3882.73 | AD63: 3779.08 | AE63: 3888.29
Y64: Retirement benefit obligations | Z64: 141.26 | AA64: 166.84 | AB64: 158.22 | AC64: 162.47 | AD64: 146.72 | AE64: 154.62 | AG64: Working capital Forecast | AH64: 2026 | AI64: 2027 | AJ64: 2028 | AK64: 2029 | AL64: 2030
Q65: Working capital Forecast | R65: 2026 | S65: 2027 | T65: 2028 | U65: 2029 | V65: 2030 | Y65: Deferred income | Z65: 34.55 | AA65: 63.98 | AB65: 130.45 | AC65: 91.93 | AD65: 63.71 | AE65: 30.71 | AG65: Value | AH65: =DCF!AN5*DCF!$AM$11 -> -5157.0562 | AI65: =DCF!AO5*DCF!$AM$11 -> -5606.9778 | AJ65: =DCF!AP5*DCF!$AM$11 -> -6096.1524 | AK65: =DCF!AQ5*DCF!$AM$11 -> -6628.0044 | AL65: =DCF!AR5*DCF!$AM$11 -> -7206.2574
Q66: Value | R66: =DCF!V5*DCF!$U$11 -> 2570.167 | S66: =DCF!W5*DCF!$U$11 -> 2951.7802 | T66: =DCF!X5*DCF!$U$11 -> 3390.0544 | U66: =DCF!Y5*DCF!$U$11 -> 3893.4028 | V66: =DCF!Z5*DCF!$U$11 -> 4471.4872 | Y66: Current tax liabilities | Z66: 609.58 | AA66: 4424.44 | AB66: 1382.7 | AC66: 1923.98 | AD66: 2166.85 | AE66: 1775.52
Y67: Other liabilities | Z67: 7050.44 | AA67: 11113.83 | AB67: 15513.02 | AC67: 14545.1 | AD67: 15185.73 | AE67: 13301.81
Y68: Total current liabilities | Z68: =SUM(Z56,Z59:Z67) -> 60312.58 | AA68: =SUM(AA56,AA59:AA67) -> 70867.13 | AB68: =SUM(AB56,AB59:AB67) -> 90396.89 | AC68: =SUM(AC56,AC59:AC67) -> 97295.13 | AD68: =SUM(AD56,AD59:AD67) -> 98403.48 | AE68: =SUM(AE56,AE59:AE67) -> 86093.55
Y69: Liabilities held for sale | Z69: 1348.33 | AA69: 0 | AB69: 191.11 | AC69: 0 | AD69: 0 | AE69: 0
Y70: Total equity and liabilities | Z70: =Z43+Z54+Z68+Z69 -> 250419.45 | AA70: =AA43+AA54+AA68+AA69 -> 245487.21 | AB70: =AB43+AB54+AB68+AB69 -> 285445.6 | AC70: =AC43+AC54+AC68+AC69 -> 288021.74 | AD70: =AD43+AD54+AD68+AD69 -> 273423.5 | AE70: =AE43+AE54+AE68+AE69 -> 279394.8
Y71: Working capital | Z71: =Z34-Z68 -> -4403.31 | AA71: =AA34-AA68 -> -10754.76 | AB71: =AB34-AB68 -> 1859.18 | AC71: =AC34-AC68 -> -10688.99 | AD71: =AD34-AD68 -> -27899.89 | AE71: =AE34-AE68 -> -17702.01
Y73: Working capital Forecast | Z73: 2026 | AA73: 2027 | AB73: 2028 | AC73: 2029 | AD73: 2030
Y74: Value | Z74: =DCF!AE5*DCF!$AD$11 -> -18972.501 | AA74: =DCF!AF5*DCF!$AD$11 -> -20206.549 | AB74: =DCF!AG5*DCF!$AD$11 -> -21520.865 | AC74: =DCF!AH5*DCF!$AD$11 -> -22920.669 | AD74: =DCF!AI5*DCF!$AD$11 -> -24411.522

Sheet Income Statement
A1: INCOME STATEMENT
B3: #VALUE! | J3: #VALUE! | R3: #VALUE! | Z3: #VALUE! | AH3: #VALUE! | AP3: #VALUE!
A4: Particulars | B4: 2020 | C4: 2021 | D4: 2022 | E4: 2023 | F4: 2024 | G4: 2025 | I4: Particulars | J4: 2020 | K4: 2021 | L4: 2022 | M4: 2023 | N4: 2024 | O4: 2025 | Q4: Particulars | R4: 2020 | S4: 2021 | T4: 2022 | U4: 2023 | V4: 2024 | W4: 2025 | Y4: Particulars | Z4: 2020 | AA4: 2021 | AB4: 2022 | AC4: 2023 | AD4: 2024 | AE4: 2025 | AG4: Particulars | AH4: 2020 | AI4: 2021 | AJ4: 2022 | AK4: 2023 | AL4: 2024 | AM4: 2025 | AO4: Particulars | AP4: 2020 | AQ4: 2021 | AR4: 2022 | AS4: 2023 | AT4: 2024 | AU4: 2025
A5: INCOME | I5: INCOME | Q5: INCOME | Y5: INCOME | AG5: INCOME | AO5: INCOME
A6: Revenue from Operations | B6: 89373.34 | C6: 82710.32 | D6: 100562.57 | E6: 127627.47 | F6: 130325.65 | G6: 126956.76 | I6: Revenue from operations | J6: 18332 | K6: 22071 | L6: 28790 | M6: 33272 | N6: 28082 | O6: 33041 | Q6: Revenue from operations | R6: 72610 | S6: 79839 | T6: 146371 | U6: 165960 | V6: 175006 | W6: 168824 | Y6: Revenue from operations | Z6: 148971 | AA6: 156294.18 | AB6: 243959.17 | AC6: 243352.69 | AD6: 229170.78 | AE6: 218542.51 | AG6: Revenue from operations | AH6: 61664.16 | AI6: 69113.61 | AJ6: 103476.84 | AK6: 104447.72 | AL6: 105378.33 | AM6: 102479.06 | AO6: Revenue from operations | AP6: 11699.22 | AQ6: 15370.06 | AR6: 25964.79 | AS6: 17666.88 | AT6: 21307.85 | AU6: 23905.52
A7: Other operating income | B7: 6707 | C7: 7315.69 | D7: 9152.85 | E7: 10624.44 | F7: 14436.77 | G7: 16412.16 | I7: Other operating income | J7: 229 | K7: 558 | L7: 650 | M7: 826 | N7: 850 | O7: 1042 | Q7: Fees for assignment of contract | R7: 250 | S7: 0 | T7: 0 | U7: 0 | V7: 0 | W7: 0 | Y7: Other income | Z7: 1821.99 | AA7: 895.6 | AB7: 784.89 | AC7: 1037.48 | AD7: 1808.85 | AE7: 1540.53 | AG7: Other income | AH7: 905.79 | AI7: 860.67 | AJ7: 858.55 | AK7: 950.36 | AL7: 1066.96 | AM7: 875.03 | AO7: Other income | AP7: 514.36 | AQ7: 351.6 | AR7: 718.52 | AS7: 768.22 | AT7: 1370.68 | AU7: 1593.32
A8: Other income | B8: 6444.96 | C8: 3792.38 | D8: 3881.41 | E8: 6550.66 | F8: 7969.08 | G8: 9470.06 | I8: Other income | J8: 1934 | K8: 1819 | L8: 1216 | M8: 1379 | N8: 1074 | O8: 983 | Q8: Government grant income | R8: 466 | S8: 0 | T8: 0 | U8: 0 | V8: 0 | W8: 0 | Y8: Total income | Z8: =SUM(Z6:Z7) -> 150792.99 | AA8: =SUM(AA6:AA7) -> 157189.78 | AB8: =SUM(AB6:AB7) -> 244744.06 | AC8: =SUM(AC6:AC7) -> 244390.17 | AD8: =SUM(AD6:AD7) -> 230979.63 | AE8: =SUM(AE6:AE7) -> 220083.04 | AG8: Total income | AH8: =SUM(AH6:AH7) -> 62569.95 | AI8: =SUM(AI6:AI7) -> 69974.28 | AJ8: =SUM(AJ6:AJ7) -> 104335.39 | AK8: =SUM(AK6:AK7) -> 105398.08 | AL8: =SUM(AL6:AL7) -> 106445.29 | AM8: =SUM(AM6:AM7) -> 103354.09 | AO8: Total income | AP8: =SUM(AP6:AP7) -> 12213.58 | AQ8: =SUM(AQ6:AQ7) -> 15721.66 | AR8: =SUM(AR6:AR7) -> 26683.31 | AS8: =SUM(AS6:AS7) -> 18435.1 | AT8: =SUM(AT6:AT7) -> 22678.53 | AU8: =SUM(AU6:AU7) -> 25498.84
A9: Total income | B9: =SUM(B6:B8) -> 102525.3 | C9: =SUM(C6:C8) -> 93818.39 | D9: =SUM(D6:D8) -> 113596.83 | E9: =SUM(E6:E8) -> 144802.57 | F9: =SUM(F6:F8) -> 152731.5 | G9: =SUM(G6:G8) -> 152838.98 | I9: Total income | J9: =SUM(J6:J8) -> 20495 | K9: =SUM(K6:K8) -> 24448 | L9: =SUM(L6:L8) -> 30656 | M9: =SUM(M6:M8) -> 35477 | N9: =SUM(N6:N8) -> 30006 | O9: =SUM(O6:O8) -> 35066 | Q9: Total revenue from operations | R9: =SUM(R6:R8) -> 73326 | S9: =SUM(S6:S8) -> 79839 | T9: =SUM(T6:T8) -> 146371 | U9: =SUM(U6:U8) -> 165960 | V9: =SUM(V6:V8) -> 175006 | W9: =SUM(W6:W8) -> 168824 | Y9: EXPENSES | AG9: EXPENSES | AO9: EXPENSES
A10: EXPENSES | I10: EXPENSES | Q10: Other income | R10: 546 | S10: 592 | T10: 1531 | U10: 1030 | V10: 1004 | W10: 694 | Y10: Cost of materials consumed | Z10: 53592.83 | AA10: 46187.96 | AB10: 75763.7 | AC10: 101483.08 | AD10: 82533.6 | AE10: 77079.62 | AG10: Cost of materials consumed | AH10: 29371.73 | AI10: 23213.59 | AJ10: 42890.12 | AK10: 62179.91 | AL10: 57709.26 | AM10: 49051.46 | AO10: Cosumption of raw materials | AP10: 36.48 | AQ10: 42.01 | AR10: 106.95 | AS10: 70.59 | AT10: 20.97 | AU10: 12.42
A11: Cost of materials consumed | B11: 7065.46 | C11: 7585.35 | D11: 9443.51 | E11: 13557 | F11: 11580.04 | G11: 11246.95 | I11: Change in inventories of finished goods | J11: -291 | K11: 239 | L11: -278 | M11: -143 | N11: -157 | O11: -64 | Q11: Total income | R11: =R9+R10 -> 73872 | S11: =S9+S10 -> 80431 | T11: =T9+T10 -> 147902 | U11: =U9+U10 -> 166990 | V11: =V9+V10 -> 176010 | W11: =W9+W10 -> 169518 | Y11: Purchase of stock in trade | Z11: 10504.2 | AA11: 9235.42 | AB11: 15312.91 | AC11: 15114.11 | AD11: 14972.79 | AE11: 18017.68 | AG11: Purchase of stock in trade | AH11: 0 | AI11: 0 | AJ11: 0 | AK11: 0 | AL11: 0 | AM11: 1856.98 | AO11: Consumption of stores and spares | AP11: 243.15 | AQ11: 257.41 | AR11: 396.53 | AS11: 556.34 | AT11: 652.72 | AU11: 720.84
A12: Purchase of stock in trade | B12: 60.8 | C12: 282.34 | D12: 103.56 | E12: 469.74 | F12: 0 | G12: 0 | I12: Employee benefit expenses | J12: 689 | K12: 760 | L12: 718 | M12: 845 | N12: 828 | O12: 886 | Q12: EXPENSES | Y12: Changes in inventories of finished goods | Z12: -490.05 | AA12: 1516.77 | AB12: -7597.87 | AC12: -3358.89 | AD12: 4409.35 | AE12: -96.65 | AG12: Changes in inventories of finished goods | AH12: -5577.63 | AI12: 4276.64 | AJ12: -279.54 | AK12: -5154.71 | AL12: -3354.77 | AM12: 88.75 | AO12: Purchase of stock in trade | AP12: 0 | AQ12: 0 | AR12: 0 | AS12: 0 | AT12: 0 | AU12: 197.09
A13: Changes in inventories of finished goods | B13: -1042.5 | C13: -2351.26 | D13: 2308.49 | E13: -678.12 | F13: -1521.5 | G13: -2303.35 | I13: Depreciation/Amortisation | J13: 2279 | K13: 2531 | L13: 2917 | M13: 3264 | N13: 3468 | O13: 3640 | Q13: Cost of materials consumed | R13: 38865 | S13: 32623 | T13: 62337 | U13: 94456 | V13: 93590 | W13: 88324 | Y13: Employee benefit expense | Z13: 19152.23 | AA13: 19908.81 | AB13: 23264.1 | AC13: 22419.32 | AD13: 24509.58 | AE13: 24888.99 | AG13: Employee benefit expenses | AH13: 8797.32 | AI13: 10461.05 | AJ13: 12861.99 | AK13: 12071.53 | AL13: 11765.72 | AM13: 11674.95 | AO13: Changes in inventories of finished goods, WIP | AP13: -53.83 | AQ13: -161.81 | AR13: -1159.39 | AS13: -496.6 | AT13: -93.36 | AU13: 99.31
A14: Employee benefit expense | B14: 39404.18 | C14: 38697.72 | D14: 40473.21 | E14: 49409.16 | F14: 48782.58 | G14: 46249.13 | I14: Power and fuel | J14: 1704 | K14: 1732 | L14: 2452 | M14: 3711 | N14: 2843 | O14: 2702 | Q14: Purchase of stock in trade | R14: 135 | S14: 233 | T14: 534 | U14: 1514 | V14: 1164 | W14: 845 | Y14: Finance costs | Z14: 7580.72 | AA14: 7606.71 | AB14: 5462.2 | AC14: 6298.7 | AD14: 7507.57 | AE14: 7340.95 | AG14: Finance costs | AH14: 3486.76 | AI14: 2817.15 | AJ14: 1697.89 | AK14: 2037.47 | AL14: 2473.86 | AM14: 2793.17 | AO14: Employee benefit expenses | AP14: 1049.36 | AQ14: 1085.24 | AR14: 1337.07 | AS14: 1530.57 | AT14: 1625.54 | AU14: 1795.04
A15: Power expense | B15: 2467.22 | C15: 2538.19 | D15: 2638.46 | E15: 2759.89 | F15: 0 | G15: 0 | I15: Minority royalty | J15: 2353 | K15: 2759 | L15: 3667 | M15: 4068 | N15: 3517 | O15: 4103 | Q15: Changes in inventories of SIT, WIP | R15: -270 | S15: -348 | T15: -3601 | U15: -2636 | V15: -3087 | W15: 829 | Y15: Depreciation/Amortisation | Z15: 8707.67 | AA15: 9233.64 | AB15: 9100.87 | AC15: 9335.2 | AD15: 9882.16 | AE15: 10421.33 | AG15: Depreciation/Amortisation | AH15: 3755.73 | AI15: 4102.78 | AJ15: 4275.02 | AK15: 4963.54 | AL15: 5278.37 | AM15: 5650.68 | AO15: Power and electricity | AP15: 114.73 | AQ15: 110.82 | AR15: 122.54 | AS15: 144.1 | AT15: 168.1 | AU15: 163.13
A16: CSR Expense | B16: 587.84 | C16: 449.31 | D16: 548.98 | E16: 586.5 | F16: 0 | G16: 0 | I16: Finance costs | J16: 112 | K16: 386 | L16: 290 | M16: 333 | N16: 955 | O16: 1095 | Q16: Mining premium and royalties | R16: 651 | S16: 6972 | T16: 13894 | U16: 7457 | V16: 10011 | W16: 9144 | Y16: Other expenses | Z16: 50702.93 | AA16: 50706.65 | AB16: 76616.28 | AC16: 80518.87 | AD16: 82354.89 | AE16: 74699.99 | AG16: Other expenses | AH16: 18857.02 | AI16: 18423.59 | AJ16: 26662.75 | AK16: 27311.56 | AL16: 28108.81 | AM16: 29160.71 | AO16: Repairs and maintenance | AP16: 156.95 | AQ16: 136.02 | AR16: 192.23 | AS16: 210.01 | AT16: 246.34 | AU16: 254.8
A17: Repairs | B17: 1410.93 | C17: 1418.8 | D17: 1632.33 | E17: 1772.28 | F17: 0 | G17: 0 | I17: Other expenses | J17: 5259 | K17: 5467 | L17: 6656 | M17: 8111 | N17: 8245 | O17: 9068 | Q17: Employee benefit expenses | R17: 2839 | S17: 2506 | T17: 3493 | U17: 3915 | V17: 4591 | W17: 4798 | Y17: Less: Expenditure | Z17: -2318 | AA17: -1765.69 | AB17: -2889.9 | AC17: -5123.96 | AD17: -1915.33 | AE17: -1345.57 | AG17: Total expenses | AH17: =SUM(AH10:AH16) -> 58690.93 | AI17: =SUM(AI10:AI16) -> 63294.8 | AJ17: =SUM(AJ10:AJ16) -> 88108.23 | AK17: =SUM(AK10:AK16) -> 103409.3 | AL17: =SUM(AL10:AL16) -> 101981.25 | AM17: =SUM(AM10:AM16) -> 100276.7 | AO17: Royalty & other levies | AP17: 2096.29 | AQ17: 2969.38 | AR17: 9986.76 | AS17: 7725.04 | AT17: 9214.13 | AU17: 9709.17
A18: Contractual expense | B18: 13911.55 | C18: 16023.08 | D18: 18875.16 | E18: 23289.21 | F18: 27439.88 | G18: 31811.5 | I18: Total expenses | J18: =SUM(J11:J17) -> 12105 | K18: =SUM(K11:K17) -> 13874 | L18: =SUM(L11:L17) -> 16422 | M18: =SUM(M11:M17) -> 20189 | N18: =SUM(N11:N17) -> 19699 | O18: =SUM(O11:O17) -> 21430 | Q18: Finance costs | R18: 4265 | S18: 3957 | T18: 4968 | U18: 6902 | V18: 8105 | W18: 8412 | Y18: Total expenses | Z18: =SUM(Z10:Z17) -> 147432.53 | AA18: =SUM(AA10:AA17) -> 142630.27 | AB18: =SUM(AB10:AB17) -> 195032.29 | AC18: =SUM(AC10:AC17) -> 226686.43 | AD18: =SUM(AD10:AD17) -> 224254.61 | AE18: =SUM(AE10:AE17) -> 211006.34 | AG18: Profit before exceptional items, share of profits | AH18: =AH8-AH17 -> 3879.02 | AI18: =AI8-AI17 -> 6679.48 | AJ18: =AJ8-AJ17 -> 16227.16 | AK18: =AK8-AK17 -> 1988.78 | AL18: =AL8-AL17 -> 4464.04 | AM18: =AM8-AM17 -> 3077.39 | AO18: Selling expenses | AP18: 702.43 | AQ18: 695.27 | AR18: 227.74 | AS18: 263 | AT18: 338.47 | AU18: 538.94
A19: Finance costs | B19: 502.92 | C19: 644.69 | D19: 541.49 | E19: 684.31 | F19: 819.37 | G19: 883.65 | I19: Exceptional items | J19: 0 | K19: 0 | L19: -134 | M19: 0 | N19: 0 | O19: -83 | Q19: Depreciation/Amortisation | R19: 4246 | S19: 4679 | T19: 6001 | U19: 7474 | V19: 8172 | W19: 9309 | Y19: Share of profit/loss | Z19: 187.97 | AA19: 327.34 | AB19: 649.16 | AC19: 418.12 | AD19: -57.98 | AE19: 190.81 | AG19: Share of profit | AH19: 194.32 | AI19: 467.74 | AJ19: 418.12 | AK19: 645.67 | AL19: 438.61 | AM19: 486.78 | AO19: Finance costs | AP19: 9.88 | AQ19: 16.81 | AR19: 39.06 | AS19: 75.23 | AT19: 78.24 | AU19: 177.68
A20: Depreciation/Amortisation/Impairment | B20: 3450.83 | C20: 3708.92 | D20: 4428.67 | E20: 4675.27 | F20: 6735.42 | G20: 9145.49 | I20: Profit before tax | J20: =J9-J18+J19 -> 8390 | K20: =K9-K18+K19 -> 10574 | L20: =L9-L18+L19 -> 14100 | M20: =M9-M18+M19 -> 15288 | N20: =N9-N18+N19 -> 10307 | O20: =O9-O18+O19 -> 13553 | Q20: Other expenses | R20: 19233 | S20: 17712 | T20: 30707 | U20: 42707 | V20: 40501 | W20: 41980 | Y20: Profit/Loss before exceptional items and tax | Z20: =Z8-Z18+Z19 -> 3548.43 | AA20: =AA8-AA18+AA19 -> 14886.85 | AB20: =AB8-AB18+AB19 -> 50360.93 | AC20: =AC8-AC18+AC19 -> 18121.86 | AD20: =AD8-AD18+AD19 -> 6667.04 | AE20: =AE8-AE18+AE19 -> 9267.51 | AG20: Profit before exceptional items and tax | AH20: =AH18+AH19 -> 4073.34 | AI20: =AI18+AI19 -> 7147.22 | AJ20: =AJ18+AJ19 -> 16645.28 | AK20: =AK18+AK19 -> 2634.45 | AL20: =AL18+AL19 -> 4902.65 | AM20: =AM18+AM19 -> 3564.17 | AO20: Depreciation/Amortisation | AP20: 294.93 | AQ20: 228.54 | AR20: 287.74 | AS20: 336.18 | AT20: 350.66 | AU20: 420.42
A21: Provisions | B21: 457.04 | C21: 1036.32 | D21: 172.77 | E21: 374.93 | F21: 0 | G21: 0 | I21: Current tax | J21: 1428 | K21: 1827 | L21: 2445 | M21: 3431 | N21: 2549 | O21: 3226 | Q21: Total expenses | R21: =SUM(R13:R20) -> 69964 | S21: =SUM(S13:S20) -> 68334 | T21: =SUM(T13:T20) -> 118333 | U21: =SUM(U13:U20) -> 161789 | V21: =SUM(V13:V20) -> 163047 | W21: =SUM(W13:W20) -> 163641 | Y21: Exceptional items: | AG21: Exceptional items | AH21: 771.76 | AI21: -58.43 | AJ21: -353.41 | AK21: 257.99 | AL21: -840.84 | AM21: -312.64 | AO21: Other expenses | AP21: 1351.74 | AQ21: 1446.45 | AR21: 2129.89 | AS21: 1611.3 | AT21: 1841.91 | AU21: 2266.11
A22: Write off | B22: 29.37 | C22: 5.81 | D22: 11.56 | E22: 192.6 | F22: 0 | G22: 0 | I22: Deferred tax charge | J22: 157 | K22: 767 | L22: 2026 | M22: 1346 | N22: -1 | O22: -26 | Q22: Profit before share of profit/loss from joint ventures | R22: =R11-R21 -> 3908 | S22: =S11-S21 -> 12097 | T22: =T11-T21 -> 29569 | U22: =U11-U21 -> 5201 | V22: =V11-V21 -> 12963 | W22: =W11-W21 -> 5877 | Y22: Profit on sale of subsidiaries | Z22: 202.99 | AA22: 15.81 | AB22: 724.84 | AC22: 66.86 | AD22: 4.68 | AE22: -7.05 | AG22: Profit before tax | AH22: =AH20-AH21 -> 3301.58 | AI22: =AI20-AI21 -> 7205.65 | AJ22: =AJ20+AJ21 -> 16291.87 | AK22: =AK20+AK21 -> 2892.44 | AL22: =AL20+AL21 -> 4061.81 | AM22: =AM20+AM21 -> 3251.53 | AO22: Total expenses | AP22: =SUM(AP10:AP21) -> 6002.11 | AQ22: =SUM(AQ10:AQ21) -> 6826.14 | AR22: =SUM(AR10:AR21) -> 13667.12 | AS22: =SUM(AS10:AS21) -> 12025.76 | AT22: =SUM(AT10:AT21) -> 14443.72 | AU22: =SUM(AU10:AU21) -> 16354.95
A23: Stripping activity adjustment | B23: 5541.87 | C23: 1450.37 | D23: 3760.86 | E23: 3809.11 | F23: -3699.73 | G23: -4105.52 | I23: Total tax expenses | J23: =J21+J22 -> 1585 | K23: =K21+K22 -> 2594 | L23: =L21+L22 -> 4471 | M23: =M21+M22 -> 4777 | N23: =N21+N22 -> 2548 | O23: =O21+O22 -> 3200 | Q23: Share of profit/loss | R23: -90 | S23: 1 | T23: 917 | U23: -137 | V23: -172 | W23: -311 | Y23: Provision for impairement of investments | Z23: -40.95 | AA23: 70.23 | AB23: 30.83 | AC23: 0 | AD23: 51.77 | AE23: 61.89 | AG23: Current tax | AH23: 229.79 | AI23: 16.35 | AJ23: 7.25 | AK23: 125.47 | AL23: 612.79 | AM23: 821.32 | AO23: Profit before exceptional items and tax | AP23: =AP8-AP22 -> 6211.47 | AQ23: =AQ8-AQ22 -> 8895.52 | AR23: =AR8-AR22 -> 13016.19 | AS23: =AS8-AS22 -> 6409.34 | AT23: =AT8-AT22 -> 8234.81 | AU23: =AU8-AU22 -> 9143.89
A24: Other expenses | B24: 4605.3 | C24: 4316.54 | D24: 5032.91 | E24: 5891.74 | F24: 14209.66 | G24: 13407.2 | I24: Profit for the year | J24: =J20-J23 -> 6805 | K24: =K20-K23 -> 7980 | L24: =L20-L23 -> 9629 | M24: =M20-M23 -> 10511 | N24: =N20-N23 -> 7759 | O24: =O20-O23 -> 10353 | Q24: Profit before exceptional items and tax | R24: =R22+R23 -> 3818 | S24: =S22+S23 -> 12098 | T24: =T22+T23 -> 30486 | U24: =U22+U23 -> 5064 | V24: =V22+V23 -> 12791 | W24: =W22+W23 -> 5566 | Y24: Provision for impairment of non current assets | Z24: -4372.44 | AA24: -723.41 | AB24: -99.74 | AC24: 83.68 | AD24: 19.98 | AE24: 0 | AG24: Deferred tax | AH24: 951.08 | AI24: 3041.17 | AJ24: 4041.15 | AK24: 590.44 | AL24: 382.35 | AM24: 58.41 | AO24: Exceptional items | AP24: 96.44 | AQ24: 0 | AR24: 0 | AS24: 1237.27 | AT24: -282.15 | AU24: 0
A25: Total expenses | B25: =SUM(B11:B24) -> 78452.81 | C25: =SUM(C11:C24) -> 75806.18 | D25: =SUM(D11:D24) -> 89971.96 | E25: =SUM(E11:E24) -> 106793.62 | F25: =SUM(F11:F24) -> 104345.72 | G25: =SUM(G11:G24) -> 106335.05 | Q25: Exceptional items | R25: 805 | S25: 83 | T25: 741 | U25: -591 | V25: -589 | W25: 489 | Y25: Provision for demands and claims | Z25: -196.41 | AA25: 0 | AB25: -252.68 | AC25: 25.37 | AD25: -3515.99 | AE25: -119.18 | AG25: Total tax expense | AH25: =SUM(AH23:AH24) -> 1180.87 | AI25: =SUM(AI23:AI24) -> 3057.52 | AJ25: =SUM(AJ23:AJ24) -> 4048.4 | AK25: =SUM(AK23:AK24) -> 715.91 | AL25: =SUM(AL23:AL24) -> 995.14 | AM25: =SUM(AM23:AM24) -> 879.73 | AO25: Profit before tax | AP25: =AP23-AP24 -> 6115.03 | AQ25: =AQ23-AQ24 -> 8895.52 | AR25: =AR23-AR24 -> 13016.19 | AS25: =AS23+AS24 -> 7646.61 | AT25: =AT23+AT24 -> 7952.66 | AU25: =AU23+AU24 -> 9143.89
A26: Profit before share of joint venture | B26: =B9-B25 -> 24072.49 | C26: =C9-C25 -> 18012.21 | D26: =D9-D25 -> 23624.87 | E26: =E9-E25 -> 38008.95 | F26: =F9-F25 -> 48385.78 | G26: =G9-G25 -> 46503.93 | Q26: Profit before tax | R26: =R24-R25 -> 3013 | S26: =S24-S25 -> 12015 | T26: =T24-T25 -> 29745 | U26: =U24-U25 -> 5655 | V26: =V24-V25 -> 13380 | W26: =W24-W25 -> 5077 | Y26: Employee seperation compensation | Z26: -107.37 | AA26: -443.55 | AB26: -330.81 | AC26: -91.94 | AD26: -129.86 | AE26: -691.65 | AG26: Profit for the year | AH26: =AH22-AH25 -> 2120.71 | AI26: =AI22-AI25 -> 4148.13 | AJ26: =AJ22-AJ25 -> 12243.47 | AK26: =AK22-AK25 -> 2176.53 | AL26: =AL22-AL25 -> 3066.67 | AM26: =AM22-AM25 -> 2371.8 | AO26: Current tax | AP26: 1555.59 | AQ26: 2316.46 | AR26: 3444.39 | AS26: 1664.65 | AT26: 2117.62 | AU26: 2410.81
A27: Share of Joint venture | B27: -1.17 | C27: -2.97 | D27: -8.59 | E27: -8.14 | F27: 426.83 | G27: 462.26 | Q27: Current tax | R27: 943 | S27: 2467 | T27: 4974 | U27: 1499 | V27: 2643 | W27: 1986 | Y27: Restructuring and other provisions | Z27: -165.4 | AA27: 87.5 | AB27: -256.24 | AC27: -1.7 | AD27: -4262.75 | AE27: 57.7 | AO27: Earlier years | AP27: 771.47 | AQ27: 343.2 | AR27: 260.53 | AS27: 172.13 | AT27: 231.18 | AU27: 223.69
A28: Profit before tax | B28: =B26+B27 -> 24071.32 | C28: =C26+C27 -> 18009.24 | D28: =D26+D27 -> 23616.28 | E28: =E26+E27 -> 38000.81 | F28: =F26+F27 -> 48812.61 | G28: =G26+G27 -> 46966.19 | Q28: Deferred tax | R28: -1849 | S28: 1675 | T28: 3833 | U28: 17 | V28: 733 | W28: -182 | Y28: Gain/loss on non current investments | Z28: -250 | AA28: -49.74 | AB28: 49.74 | AC28: 30.99 | AD28: 18.09 | AE28: =16.76-173.11 -> -156.35 | AO28: Deferred tax | AP28: 185.66 | AQ28: -11.21 | AR28: -129.83 | AS28: 271.43 | AT28: 31.62 | AU28: -30.36
A29: Tax expense | Q29: Tax impact of earlier years | R29: 0 | S29: 0 | T29: 0 | U29: 0 | V29: 1031 | W29: -218 | Y29: Total exceptional items | Z29: =SUM(Z22:Z28) -> -4929.58 | AA29: =SUM(AA22:AA28) -> -1043.16 | AB29: =SUM(AB22:AB28) -> -134.06 | AC29: =SUM(AC22:AC28) -> 113.26 | AD29: =SUM(AD22:AD28) -> -7814.08 | AE29: =SUM(AE22:AE28) -> -854.64 | AO29: Total tax expenses | AP29: =SUM(AP26:AP28) -> 2512.72 | AQ29: =SUM(AQ26:AQ28) -> 2648.45 | AR29: =SUM(AR26:AR28) -> 3575.09 | AS29: =SUM(AS26:AS28) -> 2108.21 | AT29: =SUM(AT26:AT28) -> 2380.42 | AU29: =SUM(AU26:AU28) -> 2604.14
A30: Current tax | B30: 6272.4 | C30: 5379.53 | D30: 6257.12 | E30: 9389.75 | F30: 11576.35 | G30: 11148.08 | Q30: Total tax expense | R30: =SUM(R27:R28) -> -906 | S30: =SUM(S27:S28) -> 4142 | T30: =SUM(T27:T28) -> 8807 | U30: =SUM(U27:U28) -> 1516 | V30: =SUM(V27:V29) -> 4407 | W30: =SUM(W27:W29) -> 1586 | Y30: Profit/loss before tax | Z30: =Z20+Z29 -> -1381.15 | AA30: =AA20+AA29 -> 13843.69 | AB30: =AB20+AB29 -> 50226.87 | AC30: =AC20+AC29 -> 18235.12 | AD30: =AD20+AD29 -> -1147.04 | AE30: =AE20+AE29 -> 8412.87 | AO30: Profit/loss for the year from continuing operations | AP30: =AP25-AP29 -> 3602.31 | AQ30: =AQ25-AQ29 -> 6247.07 | AR30: =AR25-AR29 -> 9441.1 | AS30: =AS25-AS29 -> 5538.4 | AT30: =AT25-AT29 -> 5572.24 | AU30: =AU25-AU29 -> 6539.75
A31: Deferred tax | B31: 1098.58 | C31: -72.46 | D31: -19.26 | E31: 486.12 | F31: -132.87 | G31: 516.01 | Q31: Profit for the year | R31: =R26-R30 -> 3919 | S31: =S26-S30 -> 7873 | T31: =T26-T30 -> 20938 | U31: =U26-U30 -> 4139 | V31: =V26-V30 -> 8973 | W31: =W26-W30 -> 3491 | Y31: Current tax | Z31: 2113.63 | AA31: 4288.27 | AB31: 7049.88 | AC31: 5361.33 | AD31: 5368.91 | AE31: 3563.77 | AO31: Profit/loss from discontinued operations | AP31: -1.05 | AQ31: 0.53 | AR31: -0.91 | AS31: -0.91 | AT31: -1.32 | AU31: -1.24
A32: Total tax expense | B32: =SUM(B30:B31) -> 7370.98 | C32: =SUM(C30:C31) -> 5307.07 | D32: =SUM(D30:D31) -> 6237.86 | E32: =SUM(E30:E31) -> 9875.87 | F32: =SUM(F30:F31) -> 11443.48 | G32: =SUM(G30:G31) -> 11664.09 | Y32: Deferred tax | Z32: -4666.53 | AA32: 1365.63 | AB32: 1427.67 | AC32: 4798.44 | AD32: -1527.57 | AE32: 1683.11 | AO32: Tax expense of discontinued operations | AP32: -0.26 | AQ32: 0.13 | AR32: -0.23 | AS32: -0.23 | AT32: -0.33 | AU32: -0.31
A33: Profit for the year from continuing operations | B33: =B28-B32 -> 16700.34 | C33: =C28-C32 -> 12702.17 | D33: =D28-D32 -> 17378.42 | E33: =E28-E32 -> 28124.94 | F33: =F28-F32 -> 37369.13 | G33: =G28-G32 -> 35302.1 | Y33: Current tax for earlier years | Z33: 0 | AA33: 0 | AB33: 0 | AC33: 0 | AD33: -78.77 | AE33: -7.79 | AO33: Profit/loss from discontinued operations (after tax) | AP33: =AP31-AP32 -> -0.79 | AQ33: =AQ31-AQ32 -> 0.4 | AR33: =AR31-AR32 -> -0.68 | AS33: =AS31-AS32 -> -0.68 | AT33: =AT31-AT32 -> -0.99 | AU33: =AU31-AU32 -> -0.93
A34: Profit/loss from discontinued operations | B34: 0 | C34: 0 | D34: 0 | E34: 0 | F34: 0 | G34: 0 | Y34: Total tax expense | Z34: =SUM(Z31:Z33) -> -2552.9 | AA34: =SUM(AA31:AA33) -> 5653.9 | AB34: =SUM(AB31:AB33) -> 8477.55 | AC34: =SUM(AC31:AC33) -> 10159.77 | AD34: =SUM(AD31:AD33) -> 3762.57 | AE34: =SUM(AE31:AE33) -> 5239.09 | AO34: Profit/Loss for the year | AP34: =AP30+AP33 -> 3601.52 | AQ34: =AQ30+AQ33 -> 6247.47 | AR34: =AR30+AR33 -> 9440.42 | AS34: =AS30+AS33 -> 5537.72 | AT34: =AT30+AT33 -> 5571.25 | AU34: =AU30+AU33 -> 6538.82
A35: Tax expense of discontinued operations | B35: 0 | C35: 0 | D35: 0 | E35: 0 | F35: 0 | G35: 0 | Y35: Profit/Loss for the year | Z35: =Z30-Z34 -> 1171.75 | AA35: =AA30-AA34 -> 8189.79 | AB35: =AB30-AB34 -> 41749.32 | AC35: =AC30-AC34 -> 8075.35 | AD35: =AD30-AD34 -> -4909.61 | AE35: =AE30-AE34 -> 3173.78
A36: Profit/loss from discontinued operations (after tax) | B36: =SUM(B34:B35) -> 0 | C36: =SUM(C34:C35) -> 0 | D36: =SUM(D34:D35) -> 0 | E36: =SUM(E34:E35) -> 0 | F36: =SUM(F34:F35) -> 0 | G36: =SUM(G34:G35) -> 0
A37: Profit/Loss for the year | B37: =B33+B36 -> 16700.34 | C37: =C33+C36 -> 12702.17 | D37: =D33+D36 -> 17378.42 | E37: =E33+E36 -> 28124.94 | F37: =F33+F36 -> 37369.13 | G37: =G33+G36 -> 35302.1

Sheet Cash Flow Statement
A1: CASH FLOW STATEMENT
B3: #VALUE! | J3: #VALUE! | R3: #VALUE! | Z3: #VALUE! | AH3: #VALUE! | AP3: #VALUE!
A4: Particulars | B4: 2020 | C4: 2021 | D4: 2022 | E4: 2023 | F4: 2024 | G4: 2025 | I4: Particulars | J4: 2020 | K4: 2021 | L4: 2022 | M4: 2023 | N4: 2024 | O4: 2025 | Q4: Particulars | R4: 2020 | S4: 2021 | T4: 2022 | U4: 2023 | V4: 2024 | W4: 2025 | Y4: Particulars | Z4: 2020 | AA4: 2021 | AB4: 2022 | AC4: 2023 | AD4: 2024 | AE4: 2025 | AG4: Particulars | AH4: 2020 | AI4: 2021 | AJ4: 2022 | AK4: 2023 | AL4: 2024 | AM4: 2025 | AO4: Particulars | AP4: 2020 | AQ4: 2021 | AR4: 2022 | AS4: 2023 | AT4: 2024 | AU4: 2025
A5: Net cash flow from/used in Operating Activities | B5: 4977.24 | C5: 10559.85 | D5: 41106.77 | E5: 35686.21 | F5: 18103.1 | G5: 29199.66 | I5: Net cash flow from/used in Operating Activities | J5: 6621 | K5: 10567 | L5: 12691 | M5: 15129 | N5: 13346 | O5: 14160 | Q5: Net cash flow from/used in Operating Activities | R5: 12785 | S5: 18789 | T5: 26270 | U5: 23323 | V5: 12078 | W5: 20899 | Y5: Net cash flow from/used in Operating Activities | Z5: 20168.72 | AA5: 44326.68 | AB5: 44380.99 | AC5: 21683.08 | AD5: 20300.67 | AE5: 23511.81 | AG5: Net cash flow from/used in Operating Activities | AH5: -617.67 | AI5: 23430.37 | AJ5: 30986.65 | AK5: -5290.15 | AL5: 2910.88 | AM5: 9914.3 | AO5: Net cash flow from/used in Operating Activities | AP5: 2125.97 | AQ5: 7266.11 | AR5: 6941.8 | AS5: 2465.61 | AT5: 7393.94 | AU5: 1894.28
A6: Net cash flow from/used in Investing activities | B6: 1032.84 | C6: 338.87 | D6: -25714.51 | E6: -23422.99 | F6: -4485.8 | G6: -10076.36 | I6: CapEx | J6: -3637 | K6: -2481 | L6: -2998 | M6: -3561 | N6: -3866 | O6: -4006 | Q6: CapEx | R6: -12810 | S6: -9258 | T6: -10091 | U6: -14784 | V6: -15801 | W6: -12694 | Y6: CapEx | Z6: -10398 | AA6: -6978.59 | AB6: -10522.2 | AC6: -14142.49 | AD6: -18206.6 | AE6: -15670.52 | AG6: CapEx | AH6: -4754.36 | AI6: -3672.7 | AJ6: -3665.49 | AK6: -3921.64 | AL6: -4710.69 | AM6: -6221.15 | AO6: CapEx | AP6: -2403.49 | AQ6: -1622.11 | AR6: -1198.34 | AS6: -1401.28 | AT6: -1847.09 | AU6: -3230.34
A7: CapEX | B7: -5213.86 | C7: -10852.51 | D7: -11679.27 | E7: -14209.48 | F7: -16379.95 | G7: -12803.58 | I7: Net cash flow from/used in Investing activities | J7: -2648 | K7: -2435 | L7: 846 | M7: 6562 | N7: -3406 | O7: -2706 | Q7: Net cash flow from/used in Investing activities | R7: -19586 | S7: -8119 | T7: -15987 | U7: -10711 | V7: -14638 | W7: -16997 | Y7: Net cash flow from/used in Investing activities | Z7: -14530.35 | AA7: -9322.88 | AB7: -10881.23 | AC7: -18679.84 | AD7: -14251.44 | AE7: -14172.73 | AG7: Net cash flow from/used in Investing activities | AH7: -4260.52 | AI7: -3412.69 | AJ7: -3975.78 | AK7: -3370.98 | AL7: -4260.54 | AM7: -5268.5 | AO7: Net cash flow from/used in Investing activities | AP7: -312.76 | AQ7: -4316.28 | AR7: -3213.89 | AS7: 43.29 | AT7: -6075.57 | AU7: 305.7
A8: Net cash flow from/used in Financing activities | B8: -4790.87 | C8: -8455.4 | D8: -13441.24 | E8: -13661.14 | F8: -13899.27 | G8: -13308.5 | I8: Net cash flow from/used in Financing activities | J8: -2098 | K8: -9697 | L8: -12258 | M8: -23224 | N8: -9946 | O8: -11411 | Q8: Net cash flow from/used in Financing activities | R8: 5189 | S8: -3110 | T8: -14657 | U8: -5977 | V8: -5005 | W8: -262 | Y8: Net cash flow from/used in Financing activities | Z8: -1694.62 | AA8: -37089.67 | AB8: -23401.09 | AC8: -6980.69 | AD8: -11096.99 | AE8: -7002.44 | AG8: Net cash flow from/used in Financing activities | AH8: 5003.15 | AI8: -19689.94 | AJ8: -27397.61 | AK8: 8586.68 | AL8: 1361.95 | AM8: -4423.6 | AO8: Net cash flow from/used in Financing activities | AP8: -1753.31 | AQ8: -2591.3 | AR8: -4066.85 | AS8: -2536.5 | AT8: -1301.98 | AU8: -2224.55
A9: Net change in cash and cash equivalents | B9: =SUM(B5:B6,B8) -> 1219.21 | C9: =SUM(C5:C6,C8) -> 2443.32 | D9: =SUM(D5:D6,D8) -> 1951.02 | E9: =SUM(E5:E6,E8) -> -1397.92 | F9: =SUM(F5:F6,F8) -> -281.97 | G9: =SUM(G5:G6,G8) -> 5814.8 | I9: Net change in cash and cash equivalents | J9: =SUM(J5,J7:J8) -> 1875 | K9: =SUM(K5,K7:K8) -> -1565 | L9: =SUM(L5,L7:L8) -> 1279 | M9: =SUM(M5,M7:M8) -> -1533 | N9: =SUM(N5,N7:N8) -> -6 | O9: =SUM(O5,O7:O8) -> 43 | Q9: Net change in cash and cash equivalents | R9: =SUM(R5,R7:R8) -> -1612 | S9: =SUM(S5,S7:S8) -> 7560 | T9: =SUM(T5,T7:T8) -> -4374 | U9: =SUM(U5,U7:U8) -> 6635 | V9: =SUM(V5,V7:V8) -> -7565 | W9: =SUM(W5,W7:W8) -> 3640 | Y9: Net change in cash and cash equivalents | Z9: =SUM(Z5,Z7:Z8) -> 3943.75 | AA9: =SUM(AA5,AA7:AA8) -> -2085.87 | AB9: =SUM(AB5,AB7:AB8) -> 10098.67 | AC9: =SUM(AC5,AC7:AC8) -> -3977.45 | AD9: =SUM(AD5,AD7:AD8) -> -5047.76 | AE9: =SUM(AE5,AE7:AE8) -> 2336.64 | AG9: Net change in cash and cash equivalents | AH9: =SUM(AH5,AH7:AH8) -> 124.96 | AI9: =SUM(AI5,AI7:AI8) -> 327.74 | AJ9: =SUM(AJ5,AJ7:AJ8) -> -386.74 | AK9: =SUM(AK5,AK7:AK8) -> -74.45 | AL9: =SUM(AL5,AL7:AL8) -> 12.29 | AM9: =SUM(AM5,AM7:AM8) -> 222.2 | AO9: Net change in cash and cash equivalents | AP9: =SUM(AP5,AP7:AP8) -> 59.9 | AQ9: =SUM(AQ5,AQ7:AQ8) -> 358.53 | AR9: =SUM(AR5,AR7:AR8) -> -338.94 | AS9: =SUM(AS5,AS7:AS8) -> -27.6 | AT9: =SUM(AT5,AT7:AT8) -> 16.39 | AU9: =SUM(AU5,AU7:AU8) -> -24.57

Sheet Financial Ratios
A1: FINANCIAL RATIOS
B3: #VALUE! | J3: #VALUE! | S3: #VALUE! | AA3: #VALUE! | AI3: #VALUE! | AQ3: #VALUE!
A4: Particulars | B4: 2020 | C4: 2021 | D4: 2022 | E4: 2023 | F4: 2024 | G4: 2025 | I4: Particulars | J4: 2020 | K4: 2021 | L4: 2022 | M4: 2023 | N4: 2024 | O4: 2025 | Q4: Particulars | R4: 2020 | S4: 2021 | T4: 2022 | U4: 2023 | V4: 2024 | W4: 2025 | Y4: Particulars | Z4: 2020 | AA4: 2021 | AB4: 2022 | AC4: 2023 | AD4: 2024 | AE4: 2025 | AG4: Particulars | AH4: 2020 | AI4: 2021 | AJ4: 2022 | AK4: 2023 | AL4: 2024 | AM4: 2025 | AO4: Particulars | AP4: 2020 | AQ4: 2021 | AR4: 2022 | AS4: 2023 | AT4: 2024 | AU4: 2025
A5: Liquidity | I5: Liquidity | Q5: Liquidity | Y5: Liquidity | AG5: Liquidity | AO5: Liquidity
A6: Current Ratio | B6: ='Balance Sheet'!B27/'Balance Sheet'!B52 -> 1.7055322 | C6: ='Balance Sheet'!C27/'Balance Sheet'!C52 -> 1.6405916 | D6: ='Balance Sheet'!D27/'Balance Sheet'!D52 -> 1.6229402 | E6: ='Balance Sheet'!E27/'Balance Sheet'!E52 -> 1.5724635 | F6: ='Balance Sheet'!F27/'Balance Sheet'!F52 -> 1.6954309 | G6: ='Balance Sheet'!G27/'Balance Sheet'!G52 -> 1.4858043 | I6: Current Ratio | J6: ='Balance Sheet'!J24/'Balance Sheet'!J49 -> 4.5839645 | K6: ='Balance Sheet'!K24/'Balance Sheet'!K49 -> 3.1193499 | L6: ='Balance Sheet'!L24/'Balance Sheet'!L49 -> 3.9353462 | M6: ='Balance Sheet'!M24/'Balance Sheet'!M49 -> 0.79825818 | N6: ='Balance Sheet'!N24/'Balance Sheet'!N49 -> 1.1645605 | O6: ='Balance Sheet'!O24/'Balance Sheet'!O49 -> 1.0381284 | Q6: Current Ratio | R6: ='Balance Sheet'!R33/'Balance Sheet'!R61 -> 0.83496612 | S6: ='Balance Sheet'!S33/'Balance Sheet'!S61 -> 0.82800988 | T6: ='Balance Sheet'!T33/'Balance Sheet'!T61 -> 1.1359316 | U6: ='Balance Sheet'!U33/'Balance Sheet'!U61 -> 0.9740863 | V6: ='Balance Sheet'!V33/'Balance Sheet'!V61 -> 0.97682585 | W6: ='Balance Sheet'!W33/'Balance Sheet'!W61 -> 1.1667601 | Y6: Current Ratio | Z6: ='Balance Sheet'!Z34/'Balance Sheet'!Z68 -> 0.92699185 | AA6: ='Balance Sheet'!AA34/'Balance Sheet'!AA68 -> 0.8482405 | AB6: ='Balance Sheet'!AB34/'Balance Sheet'!AB68 -> 1.0205669 | AC6: ='Balance Sheet'!AC34/'Balance Sheet'!AC68 -> 0.89013849 | AD6: ='Balance Sheet'!AD34/'Balance Sheet'!AD68 -> 0.71647456 | AE6: ='Balance Sheet'!AE34/'Balance Sheet'!AE68 -> 0.79438634 | AG6: Current Ratio | AH6: ='Balance Sheet'!AH31/'Balance Sheet'!AH60 -> 0.91461373 | AI6: ='Balance Sheet'!AI31/'Balance Sheet'!AI60 -> 0.69216883 | AJ6: ='Balance Sheet'!AJ31/'Balance Sheet'!AJ60 -> 0.73303303 | AK6: ='Balance Sheet'!AK31/'Balance Sheet'!AK60 -> 0.77014644 | AL6: ='Balance Sheet'!AL31/'Balance Sheet'!AL60 -> 0.90036869 | AM6: ='Balance Sheet'!AM31/'Balance Sheet'!AM60 -> 0.90687158 | AO6: Current Ratio | AP6: ='Balance Sheet'!AP26/'Balance Sheet'!AP49 -> 2.4898616 | AQ6: ='Balance Sheet'!AQ26/'Balance Sheet'!AQ49 -> 1.9148936 | AR6: ='Balance Sheet'!AR26/'Balance Sheet'!AR49 -> 2.7908559 | AS6: ='Balance Sheet'!AS26/'Balance Sheet'!AS49 -> 3.7624031 | AT6: ='Balance Sheet'!AT26/'Balance Sheet'!AT49 -> 2.5319138 | AU6: ='Balance Sheet'!AU26/'Balance Sheet'!AU49 -> 2.4178537
A7: Quick Ratio | B7: =('Balance Sheet'!B27-'Balance Sheet'!B18)/'Balance Sheet'!B52 -> 1.5706594 | C7: =('Balance Sheet'!C27-'Balance Sheet'!C18)/'Balance Sheet'!C52 -> 1.467335 | D7: =('Balance Sheet'!D27-'Balance Sheet'!D18)/'Balance Sheet'!D52 -> 1.4992579 | E7: =('Balance Sheet'!E27-'Balance Sheet'!E18)/'Balance Sheet'!E52 -> 1.4538234 | F7: =('Balance Sheet'!F27-'Balance Sheet'!F18)/'Balance Sheet'!F52 -> 1.5293332 | G7: =('Balance Sheet'!G27-'Balance Sheet'!G18)/'Balance Sheet'!G52 -> 1.290973 | I7: Quick Ratio | J7: =('Balance Sheet'!J24-'Balance Sheet'!J16)/'Balance Sheet'!J49 -> 4.2449658 | K7: =('Balance Sheet'!K24-'Balance Sheet'!K16)/'Balance Sheet'!K49 -> 2.9384205 | L7: =('Balance Sheet'!L24-'Balance Sheet'!L16)/'Balance Sheet'!L49 -> 3.6148671 | M7: =('Balance Sheet'!M24-'Balance Sheet'!M16)/'Balance Sheet'!M49 -> 0.69157165 | N7: =('Balance Sheet'!N24-'Balance Sheet'!N16)/'Balance Sheet'!N49 -> 0.98690158 | O7: =('Balance Sheet'!O24-'Balance Sheet'!O16)/'Balance Sheet'!O49 -> 0.86945263 | Q7: Quick Ratio | R7: =('Balance Sheet'!R33-'Balance Sheet'!R22)/'Balance Sheet'!R61 -> 0.51970793 | S7: =('Balance Sheet'!S33-'Balance Sheet'!S22)/'Balance Sheet'!S61 -> 0.49892607 | T7: =('Balance Sheet'!T33-'Balance Sheet'!T22)/'Balance Sheet'!T61 -> 0.54885232 | U7: =('Balance Sheet'!U33-'Balance Sheet'!U22)/'Balance Sheet'!U61 -> 0.50047882 | V7: =('Balance Sheet'!V33-'Balance Sheet'!V22)/'Balance Sheet'!V61 -> 0.40443503 | W7: =('Balance Sheet'!W33-'Balance Sheet'!W22)/'Balance Sheet'!W61 -> 0.59017583 | Y7: Quick Ratio | Z7: =('Balance Sheet'!Z34-'Balance Sheet'!Z23)/'Balance Sheet'!Z68 -> 0.4118635 | AA7: =('Balance Sheet'!AA34-'Balance Sheet'!AA23)/'Balance Sheet'!AA68 -> 0.37868036 | AB7: =('Balance Sheet'!AB34-'Balance Sheet'!AB23)/'Balance Sheet'!AB68 -> 0.48045547 | AC7: =('Balance Sheet'!AC34-'Balance Sheet'!AC23)/'Balance Sheet'!AC68 -> 0.33085736 | AD7: =('Balance Sheet'!AD34-'Balance Sheet'!AD23)/'Balance Sheet'!AD68 -> 0.21692404 | AE7: =('Balance Sheet'!AE34-'Balance Sheet'!AE23)/'Balance Sheet'!AE68 -> 0.27646206 | AG7: Quick Ratio | AH7: =('Balance Sheet'!AH31-'Balance Sheet'!AH22)/'Balance Sheet'!AH60 -> 0.38450465 | AI7: =('Balance Sheet'!AI31-'Balance Sheet'!AI22)/'Balance Sheet'!AI60 -> 0.36238492 | AJ7: =('Balance Sheet'!AJ31-'Balance Sheet'!AJ22)/'Balance Sheet'!AJ60 -> 0.23565561 | AK7: =('Balance Sheet'!AK31-'Balance Sheet'!AK22)/'Balance Sheet'!AK60 -> 0.20735521 | AL7: =('Balance Sheet'!AL31-'Balance Sheet'!AL22)/'Balance Sheet'!AL60 -> 0.28834578 | AM7: =('Balance Sheet'!AM31-'Balance Sheet'!AM22)/'Balance Sheet'!AM60 -> 0.27575244 | AO7: Quick Ratio | AP7: =('Balance Sheet'!AP26-'Balance Sheet'!AP18)/'Balance Sheet'!AP49 -> 2.2295612 | AQ7: =('Balance Sheet'!AQ26-'Balance Sheet'!AQ18)/'Balance Sheet'!AQ49 -> 1.7483877 | AR7: =('Balance Sheet'!AR26-'Balance Sheet'!AR18)/'Balance Sheet'!AR49 -> 2.4135137 | AS7: =('Balance Sheet'!AS26-'Balance Sheet'!AS18)/'Balance Sheet'!AS49 -> 3.1291368 | AT7: =('Balance Sheet'!AT26-'Balance Sheet'!AT18)/'Balance Sheet'!AT49 -> 2.2027039 | AU7: =('Balance Sheet'!AU26-'Balance Sheet'!AU18)/'Balance Sheet'!AU49 -> 2.1450339
A8: Leverage/Solvency | I8: Leverage/Solvency | Q8: Leverage/Solvency | Y8: Leverage/Solvency | AG8: Leverage/Solvency | AO8: Leverage/Solvency
A9: Debt to Equity | B9: =('Balance Sheet'!B36+'Balance Sheet'!B44)/'Balance Sheet'!B34 -> 0.19741298 | C9: =('Balance Sheet'!C36+'Balance Sheet'!C44)/'Balance Sheet'!C34 -> 0.15897045 | D9: =('Balance Sheet'!D36+'Balance Sheet'!D44)/'Balance Sheet'!D34 -> 0.075536272 | E9: =('Balance Sheet'!E36+'Balance Sheet'!E44)/'Balance Sheet'!E34 -> 0.070924581 | F9: =('Balance Sheet'!F36+'Balance Sheet'!F44)/'Balance Sheet'!F34 -> 0.075243803 | G9: =('Balance Sheet'!G36+'Balance Sheet'!G44)/'Balance Sheet'!G34 -> 0.089127949 | I9: Debt to Equity | J9: =('Balance Sheet'!J32+'Balance Sheet'!J39)/'Balance Sheet'!J30 -> 0.015157529 | K9: =('Balance Sheet'!K32+'Balance Sheet'!K39)/'Balance Sheet'!K30 -> 0.20032185 | L9: =('Balance Sheet'!L32+'Balance Sheet'!L39)/'Balance Sheet'!L30 -> 0.082348823 | M9: =('Balance Sheet'!M32+'Balance Sheet'!M39)/'Balance Sheet'!M30 -> 0.91563563 | N9: =('Balance Sheet'!N32+'Balance Sheet'!N39)/'Balance Sheet'!N30 -> 0.55649885 | O9: =('Balance Sheet'!O32+'Balance Sheet'!O39)/'Balance Sheet'!O30 -> 0.7992646 | Q9: Debt to Equity | R9: =('Balance Sheet'!R42+'Balance Sheet'!R51)/'Balance Sheet'!R40 -> 1.4711859 | S9: =('Balance Sheet'!S42+'Balance Sheet'!S51)/'Balance Sheet'!S40 -> 1.1210315 | T9: =('Balance Sheet'!T42+'Balance Sheet'!T51)/'Balance Sheet'!T40 -> 1.0210112 | U9: =('Balance Sheet'!U42+'Balance Sheet'!U51)/'Balance Sheet'!U40 -> 1.1760617 | V9: =('Balance Sheet'!V42+'Balance Sheet'!V51)/'Balance Sheet'!V40 -> 1.072691 | W9: =('Balance Sheet'!W42+'Balance Sheet'!W51)/'Balance Sheet'!W40 -> 1.1749933 | Y9: Debt to Equity | Z9: =('Balance Sheet'!Z45+'Balance Sheet'!Z56)/'Balance Sheet'!Z43 -> 1.4874624 | AA9: =('Balance Sheet'!AA45+'Balance Sheet'!AA56)/'Balance Sheet'!AA43 -> 1.0566706 | AB9: =('Balance Sheet'!AB45+'Balance Sheet'!AB56)/'Balance Sheet'!AB43 -> 0.58778467 | AC9: =('Balance Sheet'!AC45+'Balance Sheet'!AC56)/'Balance Sheet'!AC43 -> 0.74178792 | AD9: =('Balance Sheet'!AD45+'Balance Sheet'!AD56)/'Balance Sheet'!AD43 -> 0.88252193 | AE9: =('Balance Sheet'!AE45+'Balance Sheet'!AE56)/'Balance Sheet'!AE43 -> 0.97384896 | AG9: Debt to Equity | AH9: =('Balance Sheet'!AH40+'Balance Sheet'!AH51)/'Balance Sheet'!AH38 -> 1.2334501 | AI9: =('Balance Sheet'!AI40+'Balance Sheet'!AI51)/'Balance Sheet'!AI38 -> 0.78351076 | AJ9: =('Balance Sheet'!AJ40+'Balance Sheet'!AJ51)/'Balance Sheet'!AJ38 -> 0.24691446 | AK9: =('Balance Sheet'!AK40+'Balance Sheet'!AK51)/'Balance Sheet'!AK38 -> 0.46873673 | AL9: =('Balance Sheet'!AL40+'Balance Sheet'!AL51)/'Balance Sheet'!AL38 -> 0.53590737 | AM9: =('Balance Sheet'!AM40+'Balance Sheet'!AM51)/'Balance Sheet'!AM38 -> 0.50608295 | AO9: Debt to Equity | AP9: =('Balance Sheet'!AP35+'Balance Sheet'!AP41)/'Balance Sheet'!AP33 -> 0.020431615 | AQ9: =('Balance Sheet'!AQ35+'Balance Sheet'!AQ41)/'Balance Sheet'!AQ33 -> 0.066710059 | AR9: =('Balance Sheet'!AR35+'Balance Sheet'!AR41)/'Balance Sheet'!AR33 -> 0.099408264 | AS9: =('Balance Sheet'!AS35+'Balance Sheet'!AS41)/'Balance Sheet'!AS33 -> 0.018377685 | AT9: =('Balance Sheet'!AT35+'Balance Sheet'!AT41)/'Balance Sheet'!AT33 -> 0.13074248 | AU9: =('Balance Sheet'!AU35+'Balance Sheet'!AU41)/'Balance Sheet'!AU33 -> 0.1269205
A10: Interest Coverage | B10: =('Income Statement'!B26+'Income Statement'!B19)/'Income Statement'!B19 -> 48.865446 | C10: =('Income Statement'!C26+'Income Statement'!C19)/'Income Statement'!C19 -> 28.939335 | D10: =('Income Statement'!D26+'Income Statement'!D19)/'Income Statement'!D19 -> 44.629375 | E10: =('Income Statement'!E26+'Income Statement'!E19)/'Income Statement'!E19 -> 56.543467 | F10: =('Income Statement'!F26+'Income Statement'!F19)/'Income Statement'!F19 -> 60.052418 | G10: =('Income Statement'!G26+'Income Statement'!G19)/'Income Statement'!G19 -> 53.627092 | I10: Interest Coverage | J10: =('Income Statement'!J20+'Income Statement'!J16+'Income Statement'!J13)/'Income Statement'!J16 -> 96.258929 | K10: =('Income Statement'!K20+'Income Statement'!K16+'Income Statement'!K13)/'Income Statement'!K16 -> 34.950777 | L10: =('Income Statement'!L20+'Income Statement'!L16+'Income Statement'!L13)/'Income Statement'!L16 -> 59.67931 | M10: =('Income Statement'!M20+'Income Statement'!M16+'Income Statement'!M13)/'Income Statement'!M16 -> 56.711712 | N10: =('Income Statement'!N20+'Income Statement'!N16+'Income Statement'!N13)/'Income Statement'!N16 -> 15.424084 | O10: =('Income Statement'!O20+'Income Statement'!O16+'Income Statement'!O13)/'Income Statement'!O16 -> 16.70137 | Q10: Interest Coverage | R10: =('Income Statement'!R22+'Income Statement'!R18)/'Income Statement'!R18 -> 1.9162954 | S10: =('Income Statement'!S22+'Income Statement'!S18)/'Income Statement'!S18 -> 4.057114 | T10: =('Income Statement'!T22+'Income Statement'!T18)/'Income Statement'!T18 -> 6.9518921 | U10: =('Income Statement'!U22+'Income Statement'!U18)/'Income Statement'!U18 -> 1.7535497 | V10: =('Income Statement'!V22+'Income Statement'!V18)/'Income Statement'!V18 -> 2.5993831 | W10: =('Income Statement'!W22+'Income Statement'!W18)/'Income Statement'!W18 -> 1.6986448 | Y10: Interest Coverage | Z10: =('Income Statement'!Z20+'Income Statement'!Z14)/'Income Statement'!Z14 -> 1.4680861 | AA10: =('Income Statement'!AA20+'Income Statement'!AA14)/'Income Statement'!AA14 -> 2.9570682 | AB10: =('Income Statement'!AB20+'Income Statement'!AB14)/'Income Statement'!AB14 -> 10.219899 | AC10: =('Income Statement'!AC20+'Income Statement'!AC14)/'Income Statement'!AC14 -> 3.8770794 | AD10: =('Income Statement'!AD20+'Income Statement'!AD14)/'Income Statement'!AD14 -> 1.8880423 | AE10: =('Income Statement'!AE20+'Income Statement'!AE14)/'Income Statement'!AE14 -> 2.2624401 | AG10: Interest Coverage | AH10: =('Income Statement'!AH18+'Income Statement'!AH14)/'Income Statement'!AH14 -> 2.1124999 | AI10: =('Income Statement'!AI18+'Income Statement'!AI14)/'Income Statement'!AI14 -> 3.3710062 | AJ10: =('Income Statement'!AJ18+'Income Statement'!AJ14)/'Income Statement'!AJ14 -> 10.55725 | AK10: =('Income Statement'!AK18+'Income Statement'!AK14)/'Income Statement'!AK14 -> 1.9761027 | AL10: =('Income Statement'!AL18+'Income Statement'!AL14)/'Income Statement'!AL14 -> 2.8044837 | AM10: =('Income Statement'!AM18+'Income Statement'!AM14)/'Income Statement'!AM14 -> 2.1017554 | AO10: Interest Coverage | AP10: =('Income Statement'!AP23+'Income Statement'!AP19)/'Income Statement'!AP19 -> 629.6913 | AQ10: =('Income Statement'!AQ23+'Income Statement'!AQ19)/'Income Statement'!AQ19 -> 530.18025 | AR10: =('Income Statement'!AR23+'Income Statement'!AR19)/'Income Statement'!AR19 -> 334.23579 | AS10: =('Income Statement'!AS23+'Income Statement'!AS19)/'Income Statement'!AS19 -> 86.196597 | AT10: =('Income Statement'!AT23+'Income Statement'!AT19)/'Income Statement'!AT19 -> 106.25064 | AU10: =('Income Statement'!AU23+'Income Statement'!AU19)/'Income Statement'!AU19 -> 52.462686
A11: Debt to Assets | B11: =('Balance Sheet'!B36+'Balance Sheet'!B44)/'Balance Sheet'!B28 -> 0.042746609 | C11: =('Balance Sheet'!C36+'Balance Sheet'!C44)/'Balance Sheet'!C28 -> 0.036316672 | D11: =('Balance Sheet'!D36+'Balance Sheet'!D44)/'Balance Sheet'!D28 -> 0.018363308 | E11: =('Balance Sheet'!E36+'Balance Sheet'!E44)/'Balance Sheet'!E28 -> 0.019482009 | F11: =('Balance Sheet'!F36+'Balance Sheet'!F44)/'Balance Sheet'!F28 -> 0.026460892 | G11: =('Balance Sheet'!G36+'Balance Sheet'!G44)/'Balance Sheet'!G28 -> 0.034236955 | I11: Debt to Assets | J11: =('Balance Sheet'!J32+'Balance Sheet'!J39)/'Balance Sheet'!J25 -> 0.013006919 | K11: =('Balance Sheet'!K32+'Balance Sheet'!K39)/'Balance Sheet'!K25 -> 0.1415575 | L11: =('Balance Sheet'!L32+'Balance Sheet'!L39)/'Balance Sheet'!L25 -> 0.063196776 | M11: =('Balance Sheet'!M32+'Balance Sheet'!M39)/'Balance Sheet'!M25 -> 0.3422749 | N11: =('Balance Sheet'!N32+'Balance Sheet'!N39)/'Balance Sheet'!N25 -> 0.24947632 | O11: =('Balance Sheet'!O32+'Balance Sheet'!O39)/'Balance Sheet'!O25 -> 0.30881415 | Q11: Debt to Assets | R11: =('Balance Sheet'!R42+'Balance Sheet'!R51)/'Balance Sheet'!R34 -> 0.40204825 | S11: =('Balance Sheet'!S42+'Balance Sheet'!S51)/'Balance Sheet'!S34 -> 0.34877998 | T11: =('Balance Sheet'!T42+'Balance Sheet'!T51)/'Balance Sheet'!T34 -> 0.35613406 | U11: =('Balance Sheet'!U42+'Balance Sheet'!U51)/'Balance Sheet'!U34 -> 0.37352069 | V11: =('Balance Sheet'!V42+'Balance Sheet'!V51)/'Balance Sheet'!V34 -> 0.37500329 | W11: =('Balance Sheet'!W42+'Balance Sheet'!W51)/'Balance Sheet'!W34 -> 0.39858853 | Y11: Debt to Assets | Z11: =('Balance Sheet'!Z45+'Balance Sheet'!Z56)/'Balance Sheet'!Z36 -> 0.45240054 | AA11: =('Balance Sheet'!AA45+'Balance Sheet'!AA56)/'Balance Sheet'!AA36 -> 0.33362594 | AB11: =('Balance Sheet'!AB45+'Balance Sheet'!AB56)/'Balance Sheet'!AB36 -> 0.24112714 | AC11: =('Balance Sheet'!AC45+'Balance Sheet'!AC56)/'Balance Sheet'!AC36 -> 0.27087434 | AD11: =('Balance Sheet'!AD45+'Balance Sheet'!AD56)/'Balance Sheet'!AD36 -> 0.29834275 | AE11: =('Balance Sheet'!AE45+'Balance Sheet'!AE56)/'Balance Sheet'!AE36 -> 0.31841613 | AG11: Debt to Assets | AH11: =('Balance Sheet'!AH40+'Balance Sheet'!AH51)/'Balance Sheet'!AH32 -> 0.40338582 | AI11: =('Balance Sheet'!AI40+'Balance Sheet'!AI51)/'Balance Sheet'!AI32 -> 0.29834383 | AJ11: =('Balance Sheet'!AJ40+'Balance Sheet'!AJ51)/'Balance Sheet'!AJ32 -> 0.11144574 | AK11: =('Balance Sheet'!AK40+'Balance Sheet'!AK51)/'Balance Sheet'!AK32 -> 0.19667049 | AL11: =('Balance Sheet'!AL40+'Balance Sheet'!AL51)/'Balance Sheet'!AL32 -> 0.21747764 | AM11: =('Balance Sheet'!AM40+'Balance Sheet'!AM51)/'Balance Sheet'!AM32 -> 0.21860317 | AO11: Debt to Assets | AP11: =('Balance Sheet'!AP35+'Balance Sheet'!AP41)/'Balance Sheet'!AP27 -> 0.018072545 | AQ11: =('Balance Sheet'!AQ35+'Balance Sheet'!AQ41)/'Balance Sheet'!AQ27 -> 0.054007077 | AR11: =('Balance Sheet'!AR35+'Balance Sheet'!AR41)/'Balance Sheet'!AR27 -> 0.071952294 | AS11: =('Balance Sheet'!AS35+'Balance Sheet'!AS41)/'Balance Sheet'!AS27 -> 0.014726149 | AT11: =('Balance Sheet'!AT35+'Balance Sheet'!AT41)/'Balance Sheet'!AT27 -> 0.094123473 | AU11: =('Balance Sheet'!AU35+'Balance Sheet'!AU41)/'Balance Sheet'!AU27 -> 0.091946766
A12: Profitability | I12: Profitability | Q12: Profitability | Y12: Profitability | AG12: Profitability | AO12: Profitability
A13: Gross Profit margin | B13: =('Income Statement'!B9-('Income Statement'!B11+'Income Statement'!B12+Table8[[#This Row],[2020]]+'Income Statement'!B15))/'Income Statement'!B9 -> 0.91659639 | C13: =('Income Statement'!C9-('Income Statement'!C11+'Income Statement'!C12+Table8[[#This Row],[2021]]+'Income Statement'!C15))/'Income Statement'!C9 -> 0.91414668 | D13: =('Income Statement'!D9-('Income Statement'!D11+'Income Statement'!D12+Table8[[#This Row],[2022]]+'Income Statement'!D15))/'Income Statement'!D9 -> 0.87240824 | E13: =('Income Statement'!E9-('Income Statement'!E11+'Income Statement'!E12+Table8[[#This Row],[2023]]+'Income Statement'!E15))/'Income Statement'!E9 -> 0.88875536 | F13: =('Income Statement'!F9-('Income Statement'!F11+'Income Statement'!F12+Table8[[#This Row],[2024]]+'Income Statement'!F15))/'Income Statement'!F9 -> 0.93414233 | G13: =('Income Statement'!G9-('Income Statement'!G11+'Income Statement'!G12+Table8[[#This Row],[2025]]+'Income Statement'!G15))/'Income Statement'!G9 -> 0.94148351 | I13: Gross Profit margin | J13: =('Income Statement'!J9-('Income Statement'!J11+'Income Statement'!J14))/'Income Statement'!J9 -> 0.93105636 | K13: =('Income Statement'!K9-('Income Statement'!K11+'Income Statement'!K14))/'Income Statement'!K9 -> 0.91937991 | L13: =('Income Statement'!L9-('Income Statement'!L11+'Income Statement'!L14))/'Income Statement'!L9 -> 0.92908403 | M13: =('Income Statement'!M9-('Income Statement'!M11+'Income Statement'!M14))/'Income Statement'!M9 -> 0.8994278 | N13: =('Income Statement'!N9-('Income Statement'!N11+'Income Statement'!N14))/'Income Statement'!N9 -> 0.91048457 | O13: =('Income Statement'!O9-('Income Statement'!O11+'Income Statement'!O14))/'Income Statement'!O9 -> 0.92477043 | Q13: Gross Profit margin | R13: =('Income Statement'!R11-(Table10[[#This Row],[2020]]+'Income Statement'!R14+'Income Statement'!R15))/'Income Statement'!R11 -> 0.47571475 | S13: =('Income Statement'!S11-(Table10[[#This Row],[2021]]+'Income Statement'!S14+'Income Statement'!S15))/'Income Statement'!S11 -> 0.59582748 | T13: =('Income Statement'!T11-(Table10[[#This Row],[2022]]+'Income Statement'!T14+'Income Statement'!T15))/'Income Statement'!T11 -> 0.59926167 | U13: =('Income Statement'!U11-(Table10[[#This Row],[2023]]+'Income Statement'!U14+'Income Statement'!U15))/'Income Statement'!U11 -> 0.4410803 | V13: =('Income Statement'!V11-(Table10[[#This Row],[2024]]+'Income Statement'!V14+'Income Statement'!V15))/'Income Statement'!V11 -> 0.47919436 | W13: =('Income Statement'!W11-(Table10[[#This Row],[2025]]+'Income Statement'!W14+'Income Statement'!W15))/'Income Statement'!W11 -> 0.46909473 | Y13: Gross Profit margin | Z13: =('Income Statement'!Z8-('Income Statement'!Z10+'Income Statement'!Z11+'Income Statement'!Z12))/'Income Statement'!Z8 -> 0.57818344 | AA13: =('Income Statement'!AA8-('Income Statement'!AA10+'Income Statement'!AA11+'Income Statement'!AA12))/'Income Statement'!AA8 -> 0.63776176 | AB13: =('Income Statement'!AB8-('Income Statement'!AB10+'Income Statement'!AB11+'Income Statement'!AB12))/'Income Statement'!AB8 -> 0.65891413 | AC13: =('Income Statement'!AC8-('Income Statement'!AC10+'Income Statement'!AC11+'Income Statement'!AC12))/'Income Statement'!AC8 -> 0.53664953 | AD13: =('Income Statement'!AD8-('Income Statement'!AD10+'Income Statement'!AD11+'Income Statement'!AD12))/'Income Statement'!AD8 -> 0.55876741 | AE13: =('Income Statement'!AE8-('Income Statement'!AE10+'Income Statement'!AE11+'Income Statement'!AE12))/'Income Statement'!AE8 -> 0.56834179 | AG13: Gross Profit margin | AH13: =('Income Statement'!AH8-('Income Statement'!AH10+'Income Statement'!AH11+'Income Statement'!AH12))/'Income Statement'!AH8 -> 0.61972001 | AI13: =('Income Statement'!AI8-('Income Statement'!AI10+'Income Statement'!AI11+'Income Statement'!AI12))/'Income Statement'!AI8 -> 0.60713808 | AJ13: =('Income Statement'!AJ8-('Income Statement'!AJ10+'Income Statement'!AJ11+'Income Statement'!AJ12))/'Income Statement'!AJ8 -> 0.59159994 | AK13: =('Income Statement'!AK8-('Income Statement'!AK10+'Income Statement'!AK11+'Income Statement'!AK12))/'Income Statement'!AK8 -> 0.45895409 | AL13: =('Income Statement'!AL8-('Income Statement'!AL10+'Income Statement'!AL11+'Income Statement'!AL12))/'Income Statement'!AL8 -> 0.48936689 | AM13: =('Income Statement'!AM8-('Income Statement'!AM10+'Income Statement'!AM11+'Income Statement'!AM12))/'Income Statement'!AM8 -> 0.50657792 | AO13: Gross Profit margin | AP13: =('Income Statement'!AP8-('Income Statement'!AP10+'Income Statement'!AP11+'Income Statement'!AP12+Table13[[#This Row],[2020]]+'Income Statement'!AP15+'Income Statement'!AP16))/'Income Statement'!AP8 -> 0.95926829 | AQ13: =('Income Statement'!AQ8-('Income Statement'!AQ10+'Income Statement'!AQ11+'Income Statement'!AQ12+Table13[[#This Row],[2021]]+'Income Statement'!AQ15+'Income Statement'!AQ16))/'Income Statement'!AQ8 -> 0.97554648 | AR13: =('Income Statement'!AR8-('Income Statement'!AR10+'Income Statement'!AR11+'Income Statement'!AR12+Table13[[#This Row],[2022]]+'Income Statement'!AR15+'Income Statement'!AR16))/'Income Statement'!AR8 -> 1.0127848 | AS13: =('Income Statement'!AS8-('Income Statement'!AS10+'Income Statement'!AS11+'Income Statement'!AS12+Table13[[#This Row],[2023]]+'Income Statement'!AS15+'Income Statement'!AS16))/'Income Statement'!AS8 -> 0.97372187 | AT13: =('Income Statement'!AT8-('Income Statement'!AT10+'Income Statement'!AT11+'Income Statement'!AT12+Table13[[#This Row],[2024]]+'Income Statement'!AT15+'Income Statement'!AT16))/'Income Statement'!AT8 -> 0.95613605 | AU13: =('Income Statement'!AU8-('Income Statement'!AU10+'Income Statement'!AU11+'Income Statement'!AU12+Table13[[#This Row],[2025]]+'Income Statement'!AU15+'Income Statement'!AU16))/'Income Statement'!AU8 -> 0.94322918
A14: Operating Profit margin | B14: =('Income Statement'!B26+'Income Statement'!B19)/'Income Statement'!B9 -> 0.23970093 | C14: =('Income Statement'!C26+'Income Statement'!C19)/'Income Statement'!C9 -> 0.19886186 | D14: =('Income Statement'!D26+'Income Statement'!D19)/'Income Statement'!D9 -> 0.21273798 | E14: =('Income Statement'!E26+'Income Statement'!E19)/'Income Statement'!E9 -> 0.2672139 | F14: =('Income Statement'!F26+'Income Statement'!F19)/'Income Statement'!F9 -> 0.32216766 | G14: =('Income Statement'!G26+'Income Statement'!G19)/'Income Statement'!G9 -> 0.31004905 | I14: Operating Profit margin | J14: =('Income Statement'!J20+'Income Statement'!J16)/'Income Statement'!J9 -> 0.41483289 | K14: =('Income Statement'!K20+'Income Statement'!K16)/'Income Statement'!K9 -> 0.44829843 | L14: =('Income Statement'!L20+'Income Statement'!L16)/'Income Statement'!L9 -> 0.4694024 | M14: =('Income Statement'!M20+'Income Statement'!M16)/'Income Statement'!M9 -> 0.44031344 | N14: =('Income Statement'!N20+'Income Statement'!N16)/'Income Statement'!N9 -> 0.37532494 | O14: =('Income Statement'!O20+'Income Statement'!O16)/'Income Statement'!O9 -> 0.41772657 | Q14: Operating Profit margin | R14: =('Income Statement'!R22+'Income Statement'!R18)/'Income Statement'!R11 -> 0.11063732 | S14: =('Income Statement'!S22+'Income Statement'!S18)/'Income Statement'!S11 -> 0.19959966 | T14: =('Income Statement'!T22+'Income Statement'!T18)/'Income Statement'!T11 -> 0.23351273 | U14: =('Income Statement'!U22+'Income Statement'!U18)/'Income Statement'!U11 -> 0.072477394 | V14: =('Income Statement'!V22+'Income Statement'!V18)/'Income Statement'!V11 -> 0.11969774 | W14: =('Income Statement'!W22+'Income Statement'!W18)/'Income Statement'!W11 -> 0.084291934 | Y14: Operating Profit margin | Z14: =('Income Statement'!Z20+Table11[[#This Row],[2020]])/'Income Statement'!Z8 -> 0.07380416 | AA14: =('Income Statement'!AA20+Table11[[#This Row],[2021]])/'Income Statement'!AA8 -> 0.14309811 | AB14: =('Income Statement'!AB20+Table11[[#This Row],[2022]])/'Income Statement'!AB8 -> 0.22808778 | AC14: =('Income Statement'!AC20+Table11[[#This Row],[2023]])/'Income Statement'!AC8 -> 0.099924477 | AD14: =('Income Statement'!AD20+Table11[[#This Row],[2024]])/'Income Statement'!AD8 -> 0.06136736 | AE14: =('Income Statement'!AE20+Table11[[#This Row],[2025]])/'Income Statement'!AE8 -> 0.075464516 | AG14: Operating Profit margin | AH14: =('Income Statement'!AH18+Table12[[#This Row],[2020]])/'Income Statement'!AH8 -> 0.11772073 | AI14: =('Income Statement'!AI18+Table12[[#This Row],[2021]])/'Income Statement'!AI8 -> 0.13571601 | AJ14: =('Income Statement'!AJ18+Table12[[#This Row],[2022]])/'Income Statement'!AJ8 -> 0.1718022 | AK14: =('Income Statement'!AK18+Table12[[#This Row],[2023]])/'Income Statement'!AK8 -> 0.038200411 | AL14: =('Income Statement'!AL18+Table12[[#This Row],[2024]])/'Income Statement'!AL8 -> 0.065178084 | AM14: =('Income Statement'!AM18+Table12[[#This Row],[2025]])/'Income Statement'!AM8 -> 0.056800461 | AO14: Operating Profit margin | AP14: =('Income Statement'!AP23+'Income Statement'!AP19)/'Income Statement'!AP8 -> 0.50937972 | AQ14: =('Income Statement'!AQ23+'Income Statement'!AQ19)/'Income Statement'!AQ8 -> 0.56688225 | AR14: =('Income Statement'!AR23+'Income Statement'!AR19)/'Income Statement'!AR8 -> 0.48926651 | AS14: =('Income Statement'!AS23+'Income Statement'!AS19)/'Income Statement'!AS8 -> 0.35175128 | AT14: =('Income Statement'!AT23+'Income Statement'!AT19)/'Income Statement'!AT8 -> 0.36656035 | AU14: =('Income Statement'!AU23+'Income Statement'!AU19)/'Income Statement'!AU8 -> 0.36556839
A15: Net Profit margin | B15: ='Income Statement'!B37/'Income Statement'!B9 -> 0.16288994 | C15: ='Income Statement'!C37/'Income Statement'!C9 -> 0.13539105 | D15: ='Income Statement'!D37/'Income Statement'!D9 -> 0.15298332 | E15: ='Income Statement'!E37/'Income Statement'!E9 -> 0.19422956 | F15: ='Income Statement'!F37/'Income Statement'!F9 -> 0.24467206 | G15: ='Income Statement'!G37/'Income Statement'!G9 -> 0.23097576 | I15: Net Profit margin | J15: ='Income Statement'!J24/'Income Statement'!J9 -> 0.3320322 | K15: ='Income Statement'!K24/'Income Statement'!K9 -> 0.32640707 | L15: ='Income Statement'!L24/'Income Statement'!L9 -> 0.31409838 | M15: ='Income Statement'!M24/'Income Statement'!M9 -> 0.29627646 | N15: ='Income Statement'!N24/'Income Statement'!N9 -> 0.25858162 | O15: ='Income Statement'!O24/'Income Statement'!O9 -> 0.29524326 | Q15: Net Profit margin | R15: ='Income Statement'!R31/'Income Statement'!R11 -> 0.053051224 | S15: ='Income Statement'!S31/'Income Statement'!S11 -> 0.097885144 | T15: ='Income Statement'!T31/'Income Statement'!T11 -> 0.14156671 | U15: ='Income Statement'!U31/'Income Statement'!U11 -> 0.024785915 | V15: ='Income Statement'!V31/'Income Statement'!V11 -> 0.050980058 | W15: ='Income Statement'!W31/'Income Statement'!W11 -> 0.020593683 | Y15: Net Profit margin | Z15: ='Income Statement'!Z35/'Income Statement'!Z8 -> 0.0077705867 | AA15: ='Income Statement'!AA35/'Income Statement'!AA8 -> 0.052101288 | AB15: ='Income Statement'!AB35/'Income Statement'!AB8 -> 0.17058359 | AC15: ='Income Statement'!AC35/'Income Statement'!AC8 -> 0.033042859 | AD15: ='Income Statement'!AD35/'Income Statement'!AD8 -> -0.021255597 | AE15: ='Income Statement'!AE35/'Income Statement'!AE8 -> 0.01442083 | AG15: Net Profit margin | AH15: ='Income Statement'!AH26/'Income Statement'!AH8 -> 0.033893426 | AI15: ='Income Statement'!AI26/'Income Statement'!AI8 -> 0.059280781 | AJ15: ='Income Statement'!AJ26/'Income Statement'!AJ8 -> 0.11734724 | AK15: ='Income Statement'!AK26/'Income Statement'!AK8 -> 0.020650566 | AL15: ='Income Statement'!AL26/'Income Statement'!AL8 -> 0.028809823 | AM15: ='Income Statement'!AM26/'Income Statement'!AM8 -> 0.022948294 | AO15: Net Profit margin | AP15: ='Income Statement'!AP34/'Income Statement'!AP8 -> 0.29487832 | AQ15: ='Income Statement'!AQ34/'Income Statement'!AQ8 -> 0.39737979 | AR15: ='Income Statement'!AR34/'Income Statement'!AR8 -> 0.35379494 | AS15: ='Income Statement'!AS34/'Income Statement'!AS8 -> 0.30039002 | AT15: ='Income Statement'!AT34/'Income Statement'!AT8 -> 0.24566187 | AU15: ='Income Statement'!AU34/'Income Statement'!AU8 -> 0.25643598
A16: Return on assets | B16: ='Income Statement'!B37/'Balance Sheet'!B28 -> 0.11109306 | C16: ='Income Statement'!C37/'Balance Sheet'!C28 -> 0.078515233 | D16: ='Income Statement'!D37/'Balance Sheet'!D28 -> 0.096419461 | E16: ='Income Statement'!E37/'Balance Sheet'!E28 -> 0.13316313 | F16: ='Income Statement'!F37/'Balance Sheet'!F28 -> 0.15722967 | G16: ='Income Statement'!G37/'Balance Sheet'!G28 -> 0.13567379 | I16: Return on assets | J16: ='Income Statement'!J24/'Balance Sheet'!J25 -> 0.14486429 | K16: ='Income Statement'!K24/'Balance Sheet'!K25 -> 0.17451396 | L16: ='Income Statement'!L24/'Balance Sheet'!L25 -> 0.21555854 | M16: ='Income Statement'!M24/'Balance Sheet'!M25 -> 0.30383003 | N16: ='Income Statement'!N24/'Balance Sheet'!N25 -> 0.22891282 | O16: ='Income Statement'!O24/'Balance Sheet'!O25 -> 0.30017396 | Q16: Return on assets | R16: ='Income Statement'!R31/'Balance Sheet'!R34 -> 0.029729935 | S16: ='Income Statement'!S31/'Balance Sheet'!S34 -> 0.05308225 | T16: ='Income Statement'!T31/'Balance Sheet'!T34 -> 0.10656284 | U16: ='Income Statement'!U31/'Balance Sheet'!U34 -> 0.019608865 | V16: ='Income Statement'!V31/'Balance Sheet'!V34 -> 0.039321116 | W16: ='Income Statement'!W31/'Balance Sheet'!W34 -> 0.014501001 | Y16: Return on assets | Z16: ='Income Statement'!Z35/'Balance Sheet'!Z36 -> 0.0046791676 | AA16: ='Income Statement'!AA35/'Balance Sheet'!AA36 -> 0.033361371 | AB16: ='Income Statement'!AB35/'Balance Sheet'!AB36 -> 0.14626016 | AC16: ='Income Statement'!AC35/'Balance Sheet'!AC36 -> 0.028037293 | AD16: ='Income Statement'!AD35/'Balance Sheet'!AD36 -> -0.017956064 | AE16: ='Income Statement'!AE35/'Balance Sheet'!AE36 -> 0.011359481 | AG16: Return on assets | AH16: ='Income Statement'!AH26/'Balance Sheet'!AH32 -> 0.016708024 | AI16: ='Income Statement'!AI26/'Balance Sheet'!AI32 -> 0.034786362 | AJ16: ='Income Statement'!AJ26/'Balance Sheet'!AJ32 -> 0.10193622 | AK16: ='Income Statement'!AK26/'Balance Sheet'!AK32 -> 0.016680808 | AL16: ='Income Statement'!AL26/'Balance Sheet'!AL32 -> 0.021794478 | AM16: ='Income Statement'!AM26/'Balance Sheet'!AM32 -> 0.017392268 | AO16: Return on assets | AP16: ='Income Statement'!AP34/'Balance Sheet'!AP27 -> 0.11508502 | AQ16: ='Income Statement'!AQ34/'Balance Sheet'!AQ27 -> 0.16917155 | AR16: ='Income Statement'!AR34/'Balance Sheet'!AR27 -> 0.37894553 | AS16: ='Income Statement'!AS34/'Balance Sheet'!AS27 -> 0.19604138 | AT16: ='Income Statement'!AT34/'Balance Sheet'!AT27 -> 0.15622796 | AU16: ='Income Statement'!AU34/'Balance Sheet'!AU27 -> 0.15945666
A17: Return on Equity | B17: ='Income Statement'!B37/'Balance Sheet'!B34 -> 0.51305152 | C17: ='Income Statement'!C37/'Balance Sheet'!C34 -> 0.34368794 | D17: ='Income Statement'!D37/'Balance Sheet'!D34 -> 0.39661518 | E17: ='Income Statement'!E37/'Balance Sheet'!E34 -> 0.48478262 | F17: ='Income Statement'!F37/'Balance Sheet'!F34 -> 0.44709596 | G17: ='Income Statement'!G37/'Balance Sheet'!G34 -> 0.35319516 | I17: Return on Equity | J17: ='Income Statement'!J24/'Balance Sheet'!J30 -> 0.16881667 | K17: ='Income Statement'!K24/'Balance Sheet'!K30 -> 0.24695943 | L17: ='Income Statement'!L24/'Balance Sheet'!L30 -> 0.28088445 | M17: ='Income Statement'!M24/'Balance Sheet'!M30 -> 0.81278998 | N17: ='Income Statement'!N24/'Balance Sheet'!N30 -> 0.5106285 | O17: ='Income Statement'!O24/'Balance Sheet'!O30 -> 0.7769023 | Q17: Return on Equity | R17: ='Income Statement'!R31/'Balance Sheet'!R40 -> 0.10878859 | S17: ='Income Statement'!S31/'Balance Sheet'!S40 -> 0.17061437 | T17: ='Income Statement'!T31/'Balance Sheet'!T40 -> 0.30550813 | U17: ='Income Statement'!U31/'Balance Sheet'!U40 -> 0.061740181 | V17: ='Income Statement'!V31/'Balance Sheet'!V40 -> 0.11247744 | W17: ='Income Statement'!W31/'Balance Sheet'!W40 -> 0.042747288 | Y17: Return on Equity | Z17: ='Income Statement'!Z35/'Balance Sheet'!Z43 -> 0.015384787 | AA17: ='Income Statement'!AA35/'Balance Sheet'!AA43 -> 0.10566319 | AB17: ='Income Statement'!AB35/'Balance Sheet'!AB43 -> 0.35653176 | AC17: ='Income Statement'!AC35/'Balance Sheet'!AC43 -> 0.076779975 | AD17: ='Income Statement'!AD35/'Balance Sheet'!AD43 -> -0.053115487 | AE17: ='Income Statement'!AE35/'Balance Sheet'!AE43 -> 0.034742019 | AG17: Return on Equity | AH17: ='Income Statement'!AH26/'Balance Sheet'!AH38 -> 0.05108884 | AI17: ='Income Statement'!AI26/'Balance Sheet'!AI38 -> 0.091355966 | AJ17: ='Income Statement'!AJ26/'Balance Sheet'!AJ38 -> 0.22584557 | AK17: ='Income Statement'!AK26/'Balance Sheet'!AK38 -> 0.039756383 | AL17: ='Income Statement'!AL26/'Balance Sheet'!AL38 -> 0.053705848 | AM17: ='Income Statement'!AM26/'Balance Sheet'!AM38 -> 0.040264423 | AO17: Return on Equity | AP17: ='Income Statement'!AP34/'Balance Sheet'!AP33 -> 0.13010745 | AQ17: ='Income Statement'!AQ34/'Balance Sheet'!AQ33 -> 0.20896233 | AR17: ='Income Statement'!AR34/'Balance Sheet'!AR33 -> 0.52354576 | AS17: ='Income Statement'!AS34/'Balance Sheet'!AS33 -> 0.24465232 | AT17: ='Income Statement'!AT34/'Balance Sheet'!AT33 -> 0.2170089 | AU17: ='Income Statement'!AU34/'Balance Sheet'!AU33 -> 0.22010908
A18: Efficiency | I18: Efficiency | Q18: Efficiency | Y18: Efficiency | AG18: Efficiency | AO18: Efficiency
A19: Inventory turnover | B19: =('Income Statement'!B11+'Income Statement'!B12+'Income Statement'!B13)/'Balance Sheet'!B18 -> 0.91927748 | C19: =('Income Statement'!C11+'Income Statement'!C12+'Income Statement'!C13)/AVERAGE('Balance Sheet'!B18:C18) -> 0.70880444 | D19: =('Income Statement'!D11+'Income Statement'!D12+'Income Statement'!D13)/AVERAGE('Balance Sheet'!C18:D18) -> 1.4798039 | E19: =('Income Statement'!E11+'Income Statement'!E12+'Income Statement'!E13)/AVERAGE('Balance Sheet'!D18:E18) -> 1.7528962 | F19: =('Income Statement'!F11+'Income Statement'!F12+'Income Statement'!F13)/AVERAGE('Balance Sheet'!E18:F18) -> 1.0973805 | G19: =('Income Statement'!G11+'Income Statement'!G12+'Income Statement'!G13)/AVERAGE('Balance Sheet'!F18:G18) -> 0.78483853 | I19: Inventory turnover | J19: =('Income Statement'!J11+'Income Statement'!J14)/'Balance Sheet'!J16 -> 0.77002725 | K19: =('Income Statement'!K11+'Income Statement'!K14)/AVERAGE('Balance Sheet'!J16:K16) -> 1.2092025 | L19: =('Income Statement'!L11+'Income Statement'!L14)/AVERAGE('Balance Sheet'!K16:L16) -> 1.2871522 | M19: =('Income Statement'!M11+'Income Statement'!M14)/AVERAGE('Balance Sheet'!L16:M16) -> 1.8705111 | N19: =('Income Statement'!N11+'Income Statement'!N14)/AVERAGE('Balance Sheet'!M16:N16) -> 1.4181626 | O19: =('Income Statement'!O11+'Income Statement'!O14)/AVERAGE('Balance Sheet'!N16:O16) -> 1.382962 | Q19: Inventory turnover | R19: =('Income Statement'!R13+'Income Statement'!R14+'Income Statement'!R15)/'Balance Sheet'!R22 -> 2.8120235 | S19: =('Income Statement'!S13+'Income Statement'!S14+'Income Statement'!S15)/AVERAGE('Balance Sheet'!R22:S22) -> 2.320177 | T19: =('Income Statement'!T13+'Income Statement'!T14+'Income Statement'!T15)/AVERAGE('Balance Sheet'!S22:T22) -> 2.4677325 | U19: =('Income Statement'!U13+'Income Statement'!U14+'Income Statement'!U15)/AVERAGE('Balance Sheet'!T22:U22) -> 2.7893368 | V19: =('Income Statement'!V13+'Income Statement'!V14+'Income Statement'!V15)/AVERAGE('Balance Sheet'!U22:V22) -> 2.5839887 | W19: =('Income Statement'!W13+'Income Statement'!W14+'Income Statement'!W15)/AVERAGE('Balance Sheet'!V22:W22) -> 2.4734578 | Y19: Inventory turnover | Z19: =('Income Statement'!Z10+'Income Statement'!Z11+'Income Statement'!Z12)/'Balance Sheet'!Z23 -> 2.0472997 | AA19: =('Income Statement'!AA10+'Income Statement'!AA11+'Income Statement'!AA12)/AVERAGE('Balance Sheet'!Z23:AA23) -> 1.7698364 | AB19: =('Income Statement'!AB10+'Income Statement'!AB11+'Income Statement'!AB12)/AVERAGE('Balance Sheet'!AA23:AB23) -> 2.0335678 | AC19: =('Income Statement'!AC10+'Income Statement'!AC11+'Income Statement'!AC12)/AVERAGE('Balance Sheet'!AB23:AC23) -> 2.1936964 | AD19: =('Income Statement'!AD10+'Income Statement'!AD11+'Income Statement'!AD12)/AVERAGE('Balance Sheet'!AC23:AD23) -> 1.9680013 | AE19: =('Income Statement'!AE10+'Income Statement'!AE11+'Income Statement'!AE12)/AVERAGE('Balance Sheet'!AD23:AE23) -> 2.0267357 | AG19: Inventory turnover | AH19: =('Income Statement'!AH10+'Income Statement'!AH11+'Income Statement'!AH12)/'Balance Sheet'!AH22 -> 0.99823085 | AI19: =('Income Statement'!AI10+'Income Statement'!AI11+'Income Statement'!AI12)/AVERAGE('Balance Sheet'!AH22:AI22) -> 1.4036212 | AJ19: =('Income Statement'!AJ10+'Income Statement'!AJ11+'Income Statement'!AJ12)/AVERAGE('Balance Sheet'!AI22:AJ22) -> 2.4416956 | AK19: =('Income Statement'!AK10+'Income Statement'!AK11+'Income Statement'!AK12)/AVERAGE('Balance Sheet'!AJ22:AK22) -> 2.4095233 | AL19: =('Income Statement'!AL10+'Income Statement'!AL11+'Income Statement'!AL12)/AVERAGE('Balance Sheet'!AK22:AL22) -> 1.7972481 | AM19: =('Income Statement'!AM10+'Income Statement'!AM11+'Income Statement'!AM12)/AVERAGE('Balance Sheet'!AL22:AM22) -> 1.64845 | AO19: Inventory turnover | AP19: =('Income Statement'!AP10+'Income Statement'!AP11+'Income Statement'!AP12+'Income Statement'!AP13)/'Balance Sheet'!AP18 -> 0.31208967 | AQ19: =('Income Statement'!AQ10+'Income Statement'!AQ11+'Income Statement'!AQ12+'Income Statement'!AQ13)/AVERAGE('Balance Sheet'!AP18:AQ18) -> 0.1672836 | AR19: =('Income Statement'!AR10+'Income Statement'!AR11+'Income Statement'!AR12+'Income Statement'!AR13)/AVERAGE('Balance Sheet'!AQ18:AR18) -> -0.43053828 | AS19: =('Income Statement'!AS10+'Income Statement'!AS11+'Income Statement'!AS12+'Income Statement'!AS13)/AVERAGE('Balance Sheet'!AR18:AS18) -> 0.054465407 | AT19: =('Income Statement'!AT10+'Income Statement'!AT11+'Income Statement'!AT12+'Income Statement'!AT13)/AVERAGE('Balance Sheet'!AS18:AT18) -> 0.21384681 | AU19: =('Income Statement'!AU10+'Income Statement'!AU11+'Income Statement'!AU12+'Income Statement'!AU13)/AVERAGE('Balance Sheet'!AT18:AU18) -> 0.38102604
A20: Debtors turnover | B20: ='Income Statement'!B9/Table2[[#This Row],[2020]] -> 7.1157506 | C20: ='Income Statement'!C9/AVERAGE(Table2[[#This Row],[2020]:[2021]]) -> 5.5136465 | D20: ='Income Statement'!D9/AVERAGE(Table2[[#This Row],[2020]:[2021]]) -> 6.6760128 | E20: ='Income Statement'!E9/AVERAGE(Table2[[#This Row],[2020]:[2021]]) -> 8.5099541 | F20: ='Income Statement'!F9/AVERAGE(Table2[[#This Row],[2020]:[2021]]) -> 8.9759322 | G20: ='Income Statement'!G9/AVERAGE(Table2[[#This Row],[2020]:[2021]]) -> 8.9822487 | I20: Debtors turnover | J20: ='Income Statement'!J9/'Balance Sheet'!J18 -> 54.076517 | K20: ='Income Statement'!K9/AVERAGE('Balance Sheet'!J18:K18) -> 62.287898 | L20: ='Income Statement'!L9/AVERAGE('Balance Sheet'!K18:L18) -> 54.645276 | M20: ='Income Statement'!M9/AVERAGE('Balance Sheet'!L18:M18) -> 64.739051 | N20: ='Income Statement'!N9/AVERAGE('Balance Sheet'!M18:N18) -> 112.17196 | O20: ='Income Statement'!O9/AVERAGE('Balance Sheet'!N18:O18) -> 257.83824 | Q20: Debtors turnover | R20: ='Income Statement'!R11/'Balance Sheet'!R24 -> 16.39778 | S20: ='Income Statement'!S11/AVERAGE('Balance Sheet'!R24:S24) -> 17.891447 | T20: ='Income Statement'!T11/AVERAGE('Balance Sheet'!S24:T24) -> 24.767981 | U20: ='Income Statement'!U11/AVERAGE('Balance Sheet'!T24:U24) -> 22.889452 | V20: ='Income Statement'!V11/AVERAGE('Balance Sheet'!U24:V24) -> 23.976298 | W20: ='Income Statement'!W11/AVERAGE('Balance Sheet'!V24:W24) -> 21.238865 | Y20: Debtors turnover | Z20: ='Income Statement'!Z8/'Balance Sheet'!Z25 -> 19.12425 | AA20: ='Income Statement'!AA8/AVERAGE('Balance Sheet'!Z25:AA25) -> 18.042127 | AB20: ='Income Statement'!AB8/AVERAGE('Balance Sheet'!AA25:AB25) -> 22.467734 | AC20: ='Income Statement'!AC8/AVERAGE('Balance Sheet'!AB25:AC25) -> 23.838676 | AD20: ='Income Statement'!AD8/AVERAGE('Balance Sheet'!AC25:AD25) -> 31.813689 | AE20: ='Income Statement'!AE8/AVERAGE('Balance Sheet'!AD25:AE25) -> 38.196958 | AG20: Debtors turnover | AH20: ='Income Statement'!AH8/'Balance Sheet'!AH24 -> 7.0742634 | AI20: ='Income Statement'!AI8/AVERAGE('Balance Sheet'!AH24:AI24) -> 8.7476434 | AJ20: ='Income Statement'!AJ8/AVERAGE('Balance Sheet'!AI24:AJ24) -> 17.499258 | AK20: ='Income Statement'!AK8/AVERAGE('Balance Sheet'!AJ24:AK24) -> 20.745979 | AL20: ='Income Statement'!AL8/AVERAGE('Balance Sheet'!AK24:AL24) -> 15.4882 | AM20: ='Income Statement'!AM8/AVERAGE('Balance Sheet'!AL24:AM24) -> 12.947333 | AO20: Debtors turnover | AP20: ='Income Statement'!AP8/'Balance Sheet'!AP19 -> 5.4924338 | AQ20: ='Income Statement'!AQ8/AVERAGE('Balance Sheet'!AP18:AQ18) -> 19.111808 | AR20: ='Income Statement'!AR8/AVERAGE('Balance Sheet'!AQ18:AR18) -> 17.514882 | AS20: ='Income Statement'!AS8/AVERAGE('Balance Sheet'!AR18:AS18) -> 7.704099 | AT20: ='Income Statement'!AT8/AVERAGE('Balance Sheet'!AS18:AT18) -> 8.3568511 | AU20: ='Income Statement'!AU8/AVERAGE('Balance Sheet'!AT18:AU18) -> 9.4358545
A21: Assets Turnover | B21: ='Income Statement'!B9/'Balance Sheet'!B28 -> 0.68201303 | C21: ='Income Statement'!C9/'Balance Sheet'!C28 -> 0.57991451 | D21: ='Income Statement'!D9/'Balance Sheet'!D28 -> 0.63026128 | E21: ='Income Statement'!E9/'Balance Sheet'!E28 -> 0.68559661 | F21: ='Income Statement'!F9/'Balance Sheet'!F28 -> 0.64261391 | G21: ='Income Statement'!G9/'Balance Sheet'!G28 -> 0.58739407 | I21: Assets Turnover | J21: ='Income Statement'!J9/'Balance Sheet'!J25 -> 0.4362959 | K21: ='Income Statement'!K9/'Balance Sheet'!K25 -> 0.5346513 | L21: ='Income Statement'!L9/'Balance Sheet'!L25 -> 0.68627714 | M21: ='Income Statement'!M9/'Balance Sheet'!M25 -> 1.025495 | N21: ='Income Statement'!N9/'Balance Sheet'!N25 -> 0.88526331 | O21: ='Income Statement'!O9/'Balance Sheet'!O25 -> 1.0167005 | Q21: Assets Turnover | R21: ='Income Statement'!R11/'Balance Sheet'!R34 -> 0.56040055 | S21: ='Income Statement'!S11/AVERAGE('Balance Sheet'!R34:S34) -> 0.57422618 | T21: ='Income Statement'!T11/AVERAGE('Balance Sheet'!S34:T34) -> 0.85789526 | U21: ='Income Statement'!U11/AVERAGE('Balance Sheet'!T34:U34) -> 0.81945613 | V21: ='Income Statement'!V11/AVERAGE('Balance Sheet'!U34:V34) -> 0.80136406 | W21: ='Income Statement'!W11/AVERAGE('Balance Sheet'!V34:W34) -> 0.72298375 | Y21: Assets Turnover | Z21: ='Income Statement'!Z8/'Balance Sheet'!Z36 -> 0.60216401 | AA21: ='Income Statement'!AA8/'Balance Sheet'!AA36 -> 0.6403176 | AB21: ='Income Statement'!AB8/'Balance Sheet'!AB36 -> 0.85741052 | AC21: ='Income Statement'!AC8/'Balance Sheet'!AC36 -> 0.84851293 | AD21: ='Income Statement'!AD8/'Balance Sheet'!AD36 -> 0.84476876 | AE21: ='Income Statement'!AE8/'Balance Sheet'!AE36 -> 0.78771344 | AG21: Assets Turnover | AH21: ='Income Statement'!AH8/'Balance Sheet'!AH32 -> 0.49295764 | AI21: ='Income Statement'!AI8/AVERAGE('Balance Sheet'!AH32:AI32) -> 0.56849561 | AJ21: ='Income Statement'!AJ8/AVERAGE('Balance Sheet'!AI32:AJ32) -> 0.87180459 | AK21: ='Income Statement'!AK8/AVERAGE('Balance Sheet'!AJ32:AK32) -> 0.8411987 | AL21: ='Income Statement'!AL8/AVERAGE('Balance Sheet'!AK32:AL32) -> 0.78502467 | AM21: ='Income Statement'!AM8/AVERAGE('Balance Sheet'!AL32:AM32) -> 0.74602475 | AO21: Assets Turnover | AP21: ='Income Statement'!AP8/'Balance Sheet'!AP27 -> 0.39027968 | AQ21: ='Income Statement'!AQ8/AVERAGE('Balance Sheet'!AP27:AQ27) -> 0.46088207 | AR21: ='Income Statement'!AR8/AVERAGE('Balance Sheet'!AQ27:AR27) -> 0.86294925 | AS21: ='Income Statement'!AS8/AVERAGE('Balance Sheet'!AR27:AS27) -> 0.6935697 | AT21: ='Income Statement'!AT8/AVERAGE('Balance Sheet'!AS27:AT27) -> 0.70971607 | AU21: ='Income Statement'!AU8/AVERAGE('Balance Sheet'!AT27:AU27) -> 0.66517634
A22: Fixed Asset Turnover | B22: ='Income Statement'!B9/('Balance Sheet'!B6+'Balance Sheet'!B9+'Balance Sheet'!B8+'Balance Sheet'!B11) -> 2.6521945 | C22: ='Income Statement'!C9/('Balance Sheet'!C6+'Balance Sheet'!C9+'Balance Sheet'!C8+'Balance Sheet'!C11) -> 2.0977726 | D22: ='Income Statement'!D9/('Balance Sheet'!D6+'Balance Sheet'!D9+'Balance Sheet'!D8+'Balance Sheet'!D11) -> 2.3133959 | E22: ='Income Statement'!E9/('Balance Sheet'!E6+'Balance Sheet'!E9+'Balance Sheet'!E8+'Balance Sheet'!E11) -> 2.6305581 | F22: ='Income Statement'!F9/('Balance Sheet'!F6+'Balance Sheet'!F9+'Balance Sheet'!F8+'Balance Sheet'!F11) -> 1.9204864 | G22: ='Income Statement'!G9/('Balance Sheet'!G6+'Balance Sheet'!G9+'Balance Sheet'!G8+'Balance Sheet'!G11) -> 1.7511118 | I22: Fixed Asset Turnover | J22: ='Income Statement'!J9/('Balance Sheet'!J6+'Balance Sheet'!J8) -> 1.2444593 | K22: ='Income Statement'!K9/('Balance Sheet'!K6+'Balance Sheet'!K8) -> 1.4545455 | L22: ='Income Statement'!L9/('Balance Sheet'!L6+'Balance Sheet'!L8) -> 1.7622442 | M22: ='Income Statement'!M9/('Balance Sheet'!M6+'Balance Sheet'!M8) -> 2.0132221 | N22: ='Income Statement'!N9/('Balance Sheet'!N6+'Balance Sheet'!N8) -> 1.6596239 | O22: ='Income Statement'!O9/('Balance Sheet'!O6+'Balance Sheet'!O8) -> 1.8903504 | Q22: Fixed Asset Turnover | R22: ='Income Statement'!R11/('Balance Sheet'!R6+'Balance Sheet'!R8+'Balance Sheet'!R11) -> 1.2693002 | S22: ='Income Statement'!S11/('Balance Sheet'!S6+'Balance Sheet'!S8+'Balance Sheet'!S11) -> 1.3236403 | T22: ='Income Statement'!T11/('Balance Sheet'!T6+'Balance Sheet'!T8+'Balance Sheet'!T11) -> 1.5561097 | U22: ='Income Statement'!U11/('Balance Sheet'!U6+'Balance Sheet'!U8+'Balance Sheet'!U11) -> 1.6761857 | V22: ='Income Statement'!V11/('Balance Sheet'!V6+'Balance Sheet'!V8+'Balance Sheet'!V11) -> 1.6396665 | W22: ='Income Statement'!W11/('Balance Sheet'!W6+'Balance Sheet'!W8+'Balance Sheet'!W11) -> 1.4246886 | Y22: Fixed Asset Turnover | Z22: ='Income Statement'!Z8/('Balance Sheet'!Z6+'Balance Sheet'!Z10+'Balance Sheet'!Z11+'Balance Sheet'!Z8+'Balance Sheet'!Z7+'Balance Sheet'!Z13) -> 1.0007715 | AA22: ='Income Statement'!AA8/('Balance Sheet'!AA6+'Balance Sheet'!AA10+'Balance Sheet'!AA11+'Balance Sheet'!AA8+'Balance Sheet'!AA7+'Balance Sheet'!AA13) -> 1.0380683 | AB22: ='Income Statement'!AB8/('Balance Sheet'!AB6+'Balance Sheet'!AB10+'Balance Sheet'!AB11+'Balance Sheet'!AB8+'Balance Sheet'!AB7+'Balance Sheet'!AB13) -> 1.6030294 | AC22: ='Income Statement'!AC8/('Balance Sheet'!AC6+'Balance Sheet'!AC10+'Balance Sheet'!AC11+'Balance Sheet'!AC8+'Balance Sheet'!AC7+'Balance Sheet'!AC13) -> 1.4063213 | AD22: ='Income Statement'!AD8/('Balance Sheet'!AD6+'Balance Sheet'!AD10+'Balance Sheet'!AD11+'Balance Sheet'!AD8+'Balance Sheet'!AD7+'Balance Sheet'!AD13) -> 1.2831931 | AE22: ='Income Statement'!AE8/('Balance Sheet'!AE6+'Balance Sheet'!AE10+'Balance Sheet'!AE11+'Balance Sheet'!AE8+'Balance Sheet'!AE7+'Balance Sheet'!AE13) -> 1.1622561 | AG22: Fixed Asset Turnover | AH22: ='Income Statement'!AH8/('Balance Sheet'!AH6+'Balance Sheet'!AH7+'Balance Sheet'!AH8+'Balance Sheet'!AH10+'Balance Sheet'!AH9+'Balance Sheet'!AH11+'Balance Sheet'!AH13) -> 0.77220158 | AI22: ='Income Statement'!AI8/('Balance Sheet'!AI6+'Balance Sheet'!AI7+'Balance Sheet'!AI8+'Balance Sheet'!AI10+'Balance Sheet'!AI9+'Balance Sheet'!AI11+'Balance Sheet'!AI13) -> 0.8753235 | AJ22: ='Income Statement'!AJ8/('Balance Sheet'!AJ6+'Balance Sheet'!AJ7+'Balance Sheet'!AJ8+'Balance Sheet'!AJ10+'Balance Sheet'!AJ9+'Balance Sheet'!AJ11+'Balance Sheet'!AJ13) -> 1.2701467 | AK22: ='Income Statement'!AK8/('Balance Sheet'!AK6+'Balance Sheet'!AK7+'Balance Sheet'!AK8+'Balance Sheet'!AK10+'Balance Sheet'!AK9+'Balance Sheet'!AK11+'Balance Sheet'!AK13) -> 1.275702 | AL22: ='Income Statement'!AL8/('Balance Sheet'!AL6+'Balance Sheet'!AL7+'Balance Sheet'!AL8+'Balance Sheet'!AL10+'Balance Sheet'!AL9+'Balance Sheet'!AL11+'Balance Sheet'!AL13) -> 1.2800721 | AM22: ='Income Statement'!AM8/('Balance Sheet'!AM6+'Balance Sheet'!AM7+'Balance Sheet'!AM8+'Balance Sheet'!AM10+'Balance Sheet'!AM9+'Balance Sheet'!AM11+'Balance Sheet'!AM13) -> 1.2087006 | AO22: Fixed Asset Turnover | AP22: ='Income Statement'!AP8/('Balance Sheet'!AP6+'Balance Sheet'!AP7+'Balance Sheet'!AP8+'Balance Sheet'!AP10+'Balance Sheet'!AP11+'Balance Sheet'!AP12) -> 0.6059655 | AQ22: ='Income Statement'!AQ8/('Balance Sheet'!AQ6+'Balance Sheet'!AQ7+'Balance Sheet'!AQ8+'Balance Sheet'!AQ10+'Balance Sheet'!AQ11+'Balance Sheet'!AQ12) -> 0.71879186 | AR22: ='Income Statement'!AR8/('Balance Sheet'!AR6+'Balance Sheet'!AR7+'Balance Sheet'!AR8+'Balance Sheet'!AR10+'Balance Sheet'!AR11+'Balance Sheet'!AR12) -> 4.6030627 | AS22: ='Income Statement'!AS8/('Balance Sheet'!AS6+'Balance Sheet'!AS7+'Balance Sheet'!AS8+'Balance Sheet'!AS10+'Balance Sheet'!AS11+'Balance Sheet'!AS12) -> 3.0534833 | AT22: ='Income Statement'!AT8/('Balance Sheet'!AT6+'Balance Sheet'!AT7+'Balance Sheet'!AT8+'Balance Sheet'!AT10+'Balance Sheet'!AT11+'Balance Sheet'!AT12) -> 3.0365372 | AU22: ='Income Statement'!AU8/('Balance Sheet'!AU6+'Balance Sheet'!AU7+'Balance Sheet'!AU8+'Balance Sheet'!AU10+'Balance Sheet'!AU11+'Balance Sheet'!AU12) -> 2.3927789
A23: Valuation | I23: Valuation | Q23: Valuation | Y23: Valuation | AG23: Valuation | AO23: Valuation
A24: EPS | B24: ='Income Statement'!B37/'Company Profile'!$B$10 -> 27.098936 | C24: ='Income Statement'!C37/'Company Profile'!$B$10 -> 20.611275 | D24: ='Income Statement'!D37/'Company Profile'!$B$10 -> 28.199228 | E24: ='Income Statement'!E37/'Company Profile'!$B$10 -> 45.637152 | F24: ='Income Statement'!F37/'Company Profile'!$B$10 -> 60.637309 | G24: ='Income Statement'!G37/'Company Profile'!$B$10 -> 57.283226 | I24: EPS | J24: =Table9[[#This Row],[2020]]/'Company Profile'!$C$10 -> 16.105293 | K24: =Table9[[#This Row],[2021]]/'Company Profile'!$C$10 -> 18.886148 | L24: =Table9[[#This Row],[2022]]/'Company Profile'!$C$10 -> 22.788812 | M24: =Table9[[#This Row],[2023]]/'Company Profile'!$C$10 -> 24.876228 | N24: =Table9[[#This Row],[2024]]/'Company Profile'!$C$10 -> 18.363111 | O24: =Table9[[#This Row],[2025]]/'Company Profile'!$C$10 -> 24.502292 | Q24: EPS | R24: ='Income Statement'!R31/'Company Profile'!$D$10 -> 16.044727 | S24: ='Income Statement'!S31/'Company Profile'!$D$10 -> 32.232747 | T24: ='Income Statement'!T31/'Company Profile'!$D$10 -> 85.721994 | U24: ='Income Statement'!U31/'Company Profile'!$D$10 -> 16.945426 | V24: ='Income Statement'!V31/'Company Profile'!$D$10 -> 36.736243 | W24: ='Income Statement'!W31/'Company Profile'!$D$10 -> 14.292458 | Y24: EPS | Z24: ='Income Statement'!Z35/'Company Profile'!$E$10 -> 0.93849241 | AA24: ='Income Statement'!AA35/'Company Profile'!$E$10 -> 6.5594672 | AB24: ='Income Statement'!AB35/'Company Profile'!$E$10 -> 33.438378 | AC24: ='Income Statement'!AC35/'Company Profile'!$E$10 -> 6.4678085 | AD24: ='Income Statement'!AD35/'Company Profile'!$E$10 -> -3.9322652 | AE24: ='Income Statement'!AE35/'Company Profile'!$E$10 -> 2.5419829 | AG24: EPS | AH24: ='Income Statement'!AH26/'Company Profile'!$F$10 -> 5.1342384 | AI24: ='Income Statement'!AI26/'Company Profile'!$F$10 -> 10.042622 | AJ24: ='Income Statement'!AJ26/'Company Profile'!$F$10 -> 29.641438 | AK24: ='Income Statement'!AK26/'Company Profile'!$F$10 -> 5.2693786 | AL24: ='Income Statement'!AL26/'Company Profile'!$F$10 -> 7.4244073 | AM24: ='Income Statement'!AM26/'Company Profile'!$F$10 -> 5.7421272 | AO24: EPS | AP24: ='Income Statement'!AP34/'Company Profile'!$G$10 -> 4.0964456 | AQ24: ='Income Statement'!AQ34/'Company Profile'!$G$10 -> 7.1060055 | AR24: ='Income Statement'!AR34/'Company Profile'!$G$10 -> 10.737735 | AS24: ='Income Statement'!AS34/'Company Profile'!$G$10 -> 6.2987207 | AT24: ='Income Statement'!AT34/'Company Profile'!$G$10 -> 6.3368585 | AU24: ='Income Statement'!AU34/'Company Profile'!$G$10 -> 7.4373932
A25: P/E | B25: =B28/'Financial Ratios'!B24 -> 5.0832254 | C25: =C28/'Financial Ratios'!C24 -> 6.282969 | D25: =D28/'Financial Ratios'!D24 -> 6.899125 | E25: =E28/'Financial Ratios'!E24 -> 4.9411497 | F25: =F28/'Financial Ratios'!F24 -> 7.3708746 | G25: =G28/'Financial Ratios'!G24 -> 6.6563988 | I25: P/E | J25: =J28/J24 -> 10.030864 | K25: =K28/K24 -> 16.353255 | L25: =L28/L24 -> 14.070501 | M25: =M28/M24 -> 12.851627 | N25: =N28/N24 -> 23.522703 | O25: =O28/O24 -> 19.779782 | Q25: P/E | R25: =R28/R24 -> 8.7692361 | S25: =S28/S24 -> 19.266121 | T25: =T28/T24 -> 8.8262062 | U25: =U28/U24 -> 40.606828 | V25: =V28/V24 -> 23.5857 | W25: =W28/W24 -> 82.51205 | Y25: P/E | Z25: =Z28/Z24 -> 30.357198 | AA25: =AA28/AA24 -> 13.158081 | AB25: =AB28/AB24 -> 3.9388872 | AC25: =AC28/AC24 -> 16.156941 | AD25: =AD28/AD24 -> -41.579088 | AE25: =AE28/AE24 -> 71.393085 | AG25: P/E | AH25: =AH28/AH24 -> 5.132212 | AI25: =AI28/AI24 -> 9.3949571 | AJ25: =AJ28/AJ24 -> 3.4461891 | AK25: =AK28/AK24 -> 15.69445 | AL25: =AL28/AL24 -> 19.691808 | AM25: =AM28/AM24 -> 25.137026 | AO25: P/E | AP25: =AP28/AP24 -> 6.4494937 | AQ25: =AQ28/AQ24 -> 6.4945066 | AR25: =AR28/AR24 -> 5.4154811 | AS25: =AS28/AS24 -> 5.8742087 | AT25: =AT28/AT24 -> 11.461515 | AU25: =AU28/AU24 -> 10.094935
A26: EV/EBITDA | B26: =(B29+('Balance Sheet'!B36+'Balance Sheet'!B44-'Balance Sheet'!B21))/(Table8[[#This Row],[2020]]+'Income Statement'!B19+'Income Statement'!B20) -> 3.1586999 | C26: =(C29+('Balance Sheet'!C36+'Balance Sheet'!C44-'Balance Sheet'!C21))/(Table8[[#This Row],[2021]]+'Income Statement'!C19+'Income Statement'!C20) -> 3.5969216 | D26: =(D29+('Balance Sheet'!D36+'Balance Sheet'!D44-'Balance Sheet'!D21))/(Table8[[#This Row],[2022]]+'Income Statement'!D19+'Income Statement'!D20) -> 4.0616209 | E26: =(E29+('Balance Sheet'!E36+'Balance Sheet'!E44-'Balance Sheet'!E21))/(Table8[[#This Row],[2023]]+'Income Statement'!E19+'Income Statement'!E20) -> 3.1686315 | F26: =(F29+('Balance Sheet'!F36+'Balance Sheet'!F44-'Balance Sheet'!F21))/(Table8[[#This Row],[2024]]+'Income Statement'!F19+'Income Statement'!F20) -> 4.9288644 | G26: =(G29+('Balance Sheet'!G36+'Balance Sheet'!G44-'Balance Sheet'!G21))/(Table8[[#This Row],[2025]]+'Income Statement'!G19+'Income Statement'!G20) -> 4.1167511 | I26: EV/EBITDA | J26: =(J29+('Balance Sheet'!J32+'Balance Sheet'!J39-'Balance Sheet'!J19))/('Income Statement'!J20+'Income Statement'!J16+'Income Statement'!J13) -> 6.2139902 | K26: =(K29+('Balance Sheet'!K32+'Balance Sheet'!K39-'Balance Sheet'!K19))/('Income Statement'!K20+'Income Statement'!K16+'Income Statement'!K13) -> 10.12964 | L26: =(L29+('Balance Sheet'!L32+'Balance Sheet'!L39-'Balance Sheet'!L19))/('Income Statement'!L20+'Income Statement'!L16+'Income Statement'!L13) -> 7.8994542 | M26: =(M29+('Balance Sheet'!M32+'Balance Sheet'!M39-'Balance Sheet'!M19))/('Income Statement'!M20+'Income Statement'!M16+'Income Statement'!M13) -> 7.7768307 | N26: =(N29+('Balance Sheet'!N32+'Balance Sheet'!N39-'Balance Sheet'!N19))/('Income Statement'!N20+'Income Statement'!N16+'Income Statement'!N13) -> 12.961008 | O26: =(O29+('Balance Sheet'!O32+'Balance Sheet'!O39-'Balance Sheet'!O19))/('Income Statement'!O20+'Income Statement'!O16+'Income Statement'!O13) -> 11.774666 | Q26: EV/EBITDA | R26: =(R29+('Balance Sheet'!R42+'Balance Sheet'!R51-'Balance Sheet'!R25))/('Income Statement'!R22+'Income Statement'!R18+'Income Statement'!R19) -> 6.7154067 | S26: =(S29+('Balance Sheet'!S42+'Balance Sheet'!S51-'Balance Sheet'!S25))/('Income Statement'!S22+'Income Statement'!S18+'Income Statement'!S19) -> 9.2349958 | T26: =(T29+('Balance Sheet'!T42+'Balance Sheet'!T51-'Balance Sheet'!T25))/('Income Statement'!T22+'Income Statement'!T18+'Income Statement'!T19) -> 6.0676429 | U26: =(U29+('Balance Sheet'!U42+'Balance Sheet'!U51-'Balance Sheet'!U25))/('Income Statement'!U22+'Income Statement'!U18+'Income Statement'!U19) -> 11.824573 | V26: =(V29+('Balance Sheet'!V42+'Balance Sheet'!V51-'Balance Sheet'!V25))/('Income Statement'!V22+'Income Statement'!V18+'Income Statement'!V19) -> 9.8898593 | W26: =(W29+('Balance Sheet'!W42+'Balance Sheet'!W51-'Balance Sheet'!W25))/('Income Statement'!W22+'Income Statement'!W18+'Income Statement'!W19) -> 15.778946 | Y26: EV/EBITDA | Z26: =(Z29+('Balance Sheet'!Z45+'Balance Sheet'!Z56-Table5[[#This Row],[2020]]))/('Income Statement'!Z20+'Income Statement'!Z14+'Income Statement'!Z15) -> 7.124052 | AA26: =(AA29+('Balance Sheet'!AA45+'Balance Sheet'!AA56-Table5[[#This Row],[2021]]))/('Income Statement'!AA20+'Income Statement'!AA14+'Income Statement'!AA15) -> 5.8035609 | AB26: =(AB29+('Balance Sheet'!AB45+'Balance Sheet'!AB56-Table5[[#This Row],[2022]]))/('Income Statement'!AB20+'Income Statement'!AB14+'Income Statement'!AB15) -> 3.3526872 | AC26: =(AC29+('Balance Sheet'!AC45+'Balance Sheet'!AC56-Table5[[#This Row],[2023]]))/('Income Statement'!AC20+'Income Statement'!AC14+'Income Statement'!AC15) -> 5.8171036 | AD26: =(AD29+('Balance Sheet'!AD45+'Balance Sheet'!AD56-Table5[[#This Row],[2024]]))/('Income Statement'!AD20+'Income Statement'!AD14+'Income Statement'!AD15) -> 11.582194 | AE26: =(AE29+('Balance Sheet'!AE45+'Balance Sheet'!AE56-Table5[[#This Row],[2025]]))/('Income Statement'!AE20+'Income Statement'!AE14+'Income Statement'!AE15) -> 11.3188 | AG26: EV/EBITDA | AH26: =(AH29+('Balance Sheet'!AH40+'Balance Sheet'!AH51-'Balance Sheet'!AH25))/('Income Statement'!AH18+'Income Statement'!AH14+'Income Statement'!AH15) -> 5.5652698 | AI26: =(AI29+('Balance Sheet'!AI40+'Balance Sheet'!AI51-'Balance Sheet'!AI25))/('Income Statement'!AI18+'Income Statement'!AI14+'Income Statement'!AI15) -> 5.4435813 | AJ26: =(AJ29+('Balance Sheet'!AJ40+'Balance Sheet'!AJ51-'Balance Sheet'!AJ25))/('Income Statement'!AJ18+'Income Statement'!AJ14+'Income Statement'!AJ15) -> 2.4976238 | AK26: =(AK29+('Balance Sheet'!AK40+'Balance Sheet'!AK51-'Balance Sheet'!AK25))/('Income Statement'!AK18+'Income Statement'!AK14+'Income Statement'!AK15) -> 6.6480009 | AL26: =(AL29+('Balance Sheet'!AL40+'Balance Sheet'!AL51-'Balance Sheet'!AL25))/('Income Statement'!AL18+'Income Statement'!AL14+'Income Statement'!AL15) -> 7.4425226 | AM26: =(AM29+('Balance Sheet'!AM40+'Balance Sheet'!AM51-'Balance Sheet'!AM25))/('Income Statement'!AM18+'Income Statement'!AM14+'Income Statement'!AM15) -> 7.7369743 | AO26: EV/EBITDA | AP26: =(AP29+'Balance Sheet'!AP35+'Balance Sheet'!AP41-'Balance Sheet'!AP20)/('Income Statement'!AP23+'Income Statement'!AP19+'Income Statement'!AP20) -> 3.6351999 | AQ26: =(AQ29+'Balance Sheet'!AQ35+'Balance Sheet'!AQ41-'Balance Sheet'!AQ20)/('Income Statement'!AQ23+'Income Statement'!AQ19+'Income Statement'!AQ20) -> 4.6061923 | AR26: =(AR29+'Balance Sheet'!AR35+'Balance Sheet'!AR41-'Balance Sheet'!AR20)/('Income Statement'!AR23+'Income Statement'!AR19+'Income Statement'!AR20) -> 3.9568579 | AS26: =(AS29+'Balance Sheet'!AS35+'Balance Sheet'!AS41-'Balance Sheet'!AS20)/('Income Statement'!AS23+'Income Statement'!AS19+'Income Statement'!AS20) -> 4.8165822 | AT26: =(AT29+'Balance Sheet'!AT35+'Balance Sheet'!AT41-'Balance Sheet'!AT20)/('Income Statement'!AT23+'Income Statement'!AT19+'Income Statement'!AT20) -> 7.7451942 | AU26: =(AU29+'Balance Sheet'!AU35+'Balance Sheet'!AU41-'Balance Sheet'!AU20)/('Income Statement'!AU23+'Income Statement'!AU19+'Income Statement'!AU20) -> 7.1540406
A27: P/S | B27: =B28/('Income Statement'!B9/'Company Profile'!$B$10) -> 0.82800628 | C27: =C28/('Income Statement'!C9/'Company Profile'!$B$10) -> 0.85065775 | D27: =D28/('Income Statement'!D9/'Company Profile'!$B$10) -> 1.055451 | E27: =E28/('Income Statement'!E9/'Company Profile'!$B$10) -> 0.95971735 | F27: =F28/('Income Statement'!F9/'Company Profile'!$B$10) -> 1.803447 | G27: =G28/('Income Statement'!G9/'Company Profile'!$B$10) -> 1.5374668 | I27: P/S | J27: =J28/('Income Statement'!J9/'Company Profile'!$C$10) -> 3.3305698 | K27: =K28/('Income Statement'!K9/'Company Profile'!$C$10) -> 5.3378181 | L27: =L28/('Income Statement'!L9/'Company Profile'!$C$10) -> 4.4195216 | M27: =M28/('Income Statement'!M9/'Company Profile'!$C$10) -> 3.8076345 | N27: =N28/('Income Statement'!N9/'Company Profile'!$C$10) -> 6.0825386 | O27: =O28/('Income Statement'!O9/'Company Profile'!$C$10) -> 5.8398473 | Q27: P/S | R27: =R28/('Income Statement'!R11/'Company Profile'!$D$10) -> 0.46521871 | S27: =S28/('Income Statement'!S11/'Company Profile'!$D$10) -> 1.885867 | T27: =T28/('Income Statement'!T11/'Company Profile'!$D$10) -> 1.249497 | U27: =U28/('Income Statement'!U11/'Company Profile'!$D$10) -> 1.0064774 | V27: =V28/('Income Statement'!V11/'Company Profile'!$D$10) -> 1.2024003 | W27: =W28/('Income Statement'!W11/'Company Profile'!$D$10) -> 1.699227 | Y27: P/S | Z27: =Z28/('Income Statement'!Z8/'Company Profile'!$E$10) -> 0.23589324 | AA27: =AA28/('Income Statement'!AA8/'Company Profile'!$E$10) -> 0.68555296 | AB27: =AB28/('Income Statement'!AB8/'Company Profile'!$E$10) -> 0.67190951 | AC27: =AC28/('Income Statement'!AC8/'Company Profile'!$E$10) -> 0.53387152 | AD27: =AD28/('Income Statement'!AD8/'Company Profile'!$E$10) -> 0.88378836 | AE27: =AE28/('Income Statement'!AE8/'Company Profile'!$E$10) -> 1.0295475 | AG27: P/S | AH27: =AH28/('Income Statement'!AH8/'Company Profile'!$F$10) -> 0.17394825 | AI27: =AI28/('Income Statement'!AI8/'Company Profile'!$F$10) -> 0.5569404 | AJ27: =AJ28/('Income Statement'!AJ8/'Company Profile'!$F$10) -> 0.40440078 | AK27: =AK28/('Income Statement'!AK8/'Company Profile'!$F$10) -> 0.32409928 | AL27: =AL28/('Income Statement'!AL8/'Company Profile'!$F$10) -> 0.5673175 | AM27: =AM28/('Income Statement'!AM8/'Company Profile'!$F$10) -> 0.57685185 | AO27: P/S | AP27: =AP28/('Income Statement'!AP8/'Company Profile'!$G$10) -> 1.9018159 | AQ27: =AQ28/('Income Statement'!AQ8/'Company Profile'!$G$10) -> 2.5807857 | AR27: =AR28/('Income Statement'!AR8/'Company Profile'!$G$10) -> 1.9159698 | AS27: =AS28/('Income Statement'!AS8/'Company Profile'!$G$10) -> 1.7645536 | AT27: =AT28/('Income Statement'!AT8/'Company Profile'!$G$10) -> 2.8156572 | AU27: =AU28/('Income Statement'!AU8/'Company Profile'!$G$10) -> 2.5887045
A28: Market Price | B28: 137.75 | C28: 129.5 | D28: 194.55 | E28: 225.5 | F28: 446.95 | G28: ='Company Profile'!B7 -> 381.3 | I28: Market Price | J28: 161.55 | K28: 308.85 | L28: 320.65 | M28: 319.7 | N28: 431.95 | O28: ='Company Profile'!C7 -> 484.65 | Q28: Market price | R28: 140.7 | S28: 621 | T28: 756.6 | U28: 688.1 | V28: 866.45 | W28: ='Company Profile'!D7 -> 1179.3 | Y28: Market price | Z28: 28.49 | AA28: 86.31 | AB28: 131.71 | AC28: 104.5 | AD28: 163.5 | AE28: ='Company Profile'!E7 -> 181.48 | AG28: Market price | AH28: 26.35 | AI28: 94.35 | AJ28: 102.15 | AK28: 82.7 | AL28: 146.2 | AM28: ='Company Profile'!F7 -> 144.34 | AO28: Market price | AP28: 26.42 | AQ28: 46.15 | AR28: 58.15 | AS28: 37 | AT28: 72.63 | AU28: ='Company Profile'!G7 -> 75.08
A29: Market Cap | B29: =B28*'Company Profile'!$B$10 -> 84891.592 | C29: =C28*'Company Profile'!$B$10 -> 79807.341 | D29: =D28*'Company Profile'!$B$10 -> 119895.89 | E29: =E28*'Company Profile'!$B$10 -> 138969.54 | F29: =F28*'Company Profile'!$B$10 -> 275443.17 | G29: =G28*'Company Profile'!$B$10 -> 234984.86 | I29: Market cap | J29: =J28*'Company Profile'!$C$10 -> 68260.028 | K29: =K28*'Company Profile'!$C$10 -> 130498.98 | L29: =L28*'Company Profile'!$C$10 -> 135484.85 | M29: =M28*'Company Profile'!$C$10 -> 135083.45 | N29: =N28*'Company Profile'!$C$10 -> 182512.65 | O29: =O28*'Company Profile'!$C$10 -> 204780.09 | Q29: Market cap | R29: =R28*'Company Profile'!$D$10 -> 34366.636 | S29: =S28*'Company Profile'!$D$10 -> 151682.17 | T29: =T28*'Company Profile'!$D$10 -> 184803.11 | U29: =U28*'Company Profile'!$D$10 -> 168071.66 | V29: =V28*'Company Profile'!$D$10 -> 211634.48 | W29: =W28*'Company Profile'!$D$10 -> 288049.57 | Y29: Market cap | Z29: =Z28*'Company Profile'!$E$10 -> 35571.047 | AA29: =AA28*'Company Profile'!$E$10 -> 107761.92 | AB29: =AB28*'Company Profile'!$E$10 -> 164445.86 | AC29: =AC28*'Company Profile'!$E$10 -> 130472.95 | AD29: =AD28*'Company Profile'!$E$10 -> 204137.11 | AE29: =AE28*'Company Profile'!$E$10 -> 226585.95 | AG29: Market cap | AH29: =AH28*'Company Profile'!$F$10 -> 10883.933 | AI29: =AI28*'Company Profile'!$F$10 -> 38971.503 | AJ29: =AJ28*'Company Profile'!$F$10 -> 42193.313 | AK29: =AK28*'Company Profile'!$F$10 -> 34159.442 | AL29: =AL28*'Company Profile'!$F$10 -> 60388.275 | AM29: =AM28*'Company Profile'!$F$10 -> 59619.998 | AO29: Market cap | AP29: =AP28*'Company Profile'!$G$10 -> 23227.981 | AQ29: =AQ28*'Company Profile'!$G$10 -> 40574.235 | AR29: =AR28*'Company Profile'!$G$10 -> 51124.416 | AS29: =AS28*'Company Profile'!$G$10 -> 32529.723 | AT29: =AT28*'Company Profile'!$G$10 -> 63854.967 | AU29: =AU28*'Company Profile'!$G$10 -> 66008.962
A30: P/B | B30: =B28/('Balance Sheet'!B34/'Company Profile'!$B$10) -> 2.6079565 | C30: =C28/('Balance Sheet'!C34/'Company Profile'!$B$10) -> 2.1593807 | D30: =D28/('Balance Sheet'!D34/'Company Profile'!$B$10) -> 2.7362977 | E30: =E28/('Balance Sheet'!E34/'Company Profile'!$B$10) -> 2.3953835 | F30: =F28/('Balance Sheet'!F34/'Company Profile'!$B$10) -> 3.2954883 | G30: =G28/('Balance Sheet'!G34/'Company Profile'!$B$10) -> 2.3510078 | I30: P/B | J30: =J28/(Table3[[#This Row],[2020]]/'Company Profile'!$C$10) -> 1.693377 | K30: =K28/(Table3[[#This Row],[2021]]/'Company Profile'!$C$10) -> 4.0385906 | L30: =L28/(Table3[[#This Row],[2022]]/'Company Profile'!$C$10) -> 3.952185 | M30: =M28/(Table3[[#This Row],[2023]]/'Company Profile'!$C$10) -> 10.445673 | N30: =N28/(Table3[[#This Row],[2024]]/'Company Profile'!$C$10) -> 12.011363 | O30: =O28/(Table3[[#This Row],[2025]]/'Company Profile'!$C$10) -> 15.366958 | Q30: P/B | R30: =R28/('Balance Sheet'!R40/'Company Profile'!$D$10) -> 0.95399279 | S30: =S28/('Balance Sheet'!S40/'Company Profile'!$D$10) -> 3.287077 | T30: =T28/('Balance Sheet'!T40/'Company Profile'!$D$10) -> 2.6964778 | U30: =U28/('Balance Sheet'!U40/'Company Profile'!$D$10) -> 2.5070729 | V30: =V28/('Balance Sheet'!V40/'Company Profile'!$D$10) -> 2.6528591 | W30: =W28/('Balance Sheet'!W40/'Company Profile'!$D$10) -> 3.5271664 | Y30: P/B | Z30: =Z28/('Balance Sheet'!Z43/'Company Profile'!$E$10) -> 0.46703903 | AA30: =AA28/('Balance Sheet'!AA43/'Company Profile'!$E$10) -> 1.3903248 | AB30: =AB28/('Balance Sheet'!AB43/'Company Profile'!$E$10) -> 1.4043384 | AC30: =AC28/('Balance Sheet'!AC43/'Company Profile'!$E$10) -> 1.2405295 | AD30: =AD28/('Balance Sheet'!AD43/'Company Profile'!$E$10) -> 2.2084935 | AE30: =AE28/('Balance Sheet'!AE43/'Company Profile'!$E$10) -> 2.4803399 | AG30: P/B | AH30: =AH28/('Balance Sheet'!AH38/'Company Profile'!$F$10) -> 0.26219876 | AI30: =AI28/('Balance Sheet'!AI38/'Company Profile'!$F$10) -> 0.85828538 | AJ30: =AJ28/('Balance Sheet'!AJ38/'Company Profile'!$F$10) -> 0.77830654 | AK30: =AK28/('Balance Sheet'!AK38/'Company Profile'!$F$10) -> 0.62395458 | AL30: =AL28/('Balance Sheet'!AL38/'Company Profile'!$F$10) -> 1.0575652 | AM30: =AM28/('Balance Sheet'!AM38/'Company Profile'!$F$10) -> 1.0121278 | AO30: P/B | AP30: =AP28/('Balance Sheet'!AP33/'Company Profile'!$G$10) -> 0.83912719 | AQ30: =AQ28/('Balance Sheet'!AQ33/'Company Profile'!$G$10) -> 1.3571072 | AR30: =AR28/('Balance Sheet'!AR33/'Company Profile'!$G$10) -> 2.8352521 | AS30: =AS28/('Balance Sheet'!AS33/'Company Profile'!$G$10) -> 1.4371388 | AT30: =AT28/('Balance Sheet'!AT33/'Company Profile'!$G$10) -> 2.4872508 | AU30: =AU28/('Balance Sheet'!AU33/'Company Profile'!$G$10) -> 2.2219868

Sheet WACC
A1: WACC and Key Assumptions
A3: Parameters | B3: Coal India | C3: Hindustan Zinc | D3: JSW Steel | E3: TATA Steel | F3: SAIL | G3: NMDC
A4: Risk free rate | B4: 0.0633 | C4: 0.0633 | D4: 0.0633 | E4: 0.0633 | F4: 0.0633 | G4: 0.0633
A5: Beta | B5: ='Company Profile'!B13 -> 1.0568 | C5: ='Company Profile'!C13 -> 0.4783 | D5: ='Company Profile'!D13 -> 0.8371 | E5: ='Company Profile'!E13 -> 1.2322 | F5: ='Company Profile'!F13 -> 1.7377 | G5: ='Company Profile'!G13 -> 1.0063
A6: Market risk premium | B6: 0.075 | C6: 0.075 | D6: 0.075 | E6: 0.075 | F6: 0.075 | G6: 0.075
A7: Cost of Equity | B7: =B4+B5*(B6) -> 0.14256 | C7: =C4+C5*(C6) -> 0.0991725 | D7: =D4+D5*(D6) -> 0.1260825 | E7: =E4+E5*(E6) -> 0.155715 | F7: =F4+F5*(F6) -> 0.1936275 | G7: =G4+G5*(G6) -> 0.1387725
A8: Interest cost | B8: ='Income Statement'!G19 -> 883.65 | C8: ='Income Statement'!O16 -> 1095 | D8: ='Income Statement'!W18 -> 8412 | E8: ='Income Statement'!AE14 -> 7340.95 | F8: ='Income Statement'!AM14 -> 2793.17 | G8: ='Income Statement'!AU19 -> 177.68
A9: Total debt | B9: ='Balance Sheet'!G36+'Balance Sheet'!G44 -> 8908.4 | C9: ='Balance Sheet'!O39+'Balance Sheet'!O32 -> 10651 | D9: ='Balance Sheet'!W42+'Balance Sheet'!W51 -> 95957 | E9: ='Balance Sheet'!AE45+'Balance Sheet'!AE56 -> 88963.81 | F9: ='Balance Sheet'!AM51+'Balance Sheet'!AM40 -> 29811.12 | G9: ='Balance Sheet'!AU35+'Balance Sheet'!AU41 -> 3770.45
A10: Cost of Debt (Pre-tax) | B10: =B8/B9 -> 0.099192897 | C10: =C8/C9 -> 0.10280725 | D10: =D8/D9 -> 0.087664266 | E10: =E8/E9 -> 0.082516138 | F10: =F8/F9 -> 0.093695574 | G10: =G8/G9 -> 0.047124349
A11: Tax expense | B11: ='Income Statement'!G32/'Income Statement'!G28 -> 0.24835078 | C11: ='Income Statement'!O23/'Income Statement'!O20 -> 0.23611009 | D11: ='Income Statement'!W30/'Income Statement'!W26 -> 0.31238921 | E11: ='Income Statement'!AE34/'Income Statement'!AE30 -> 0.62274705 | F11: ='Income Statement'!AM25/'Income Statement'!AM22 -> 0.27055878 | G11: ='Income Statement'!AU29/'Income Statement'!AU25 -> 0.28479564
A12: Cost of debt (After tax) | B12: =B10*(1-B11) -> 0.074558263 | C12: =C10*(1-C11) -> 0.07853342 | D12: =D10*(1-D11) -> 0.060278896 | E12: =E10*(1-E11) -> 0.031129456 | F12: =F10*(1-F11) -> 0.068345414 | G12: =G10*(1-G11) -> 0.03370354
A13: Total Debt | B13: =B9 -> 8908.4 | C13: =C9 -> 10651 | D13: =D9 -> 95957 | E13: =E9 -> 88963.81 | F13: =F9 -> 29811.12 | G13: =G9 -> 3770.45
A14: Market value of Equity | B14: ='Company Profile'!B12 -> 231718.6 | C14: ='Company Profile'!C12 -> 200491.4 | D14: ='Company Profile'!D12 -> 286193.3 | E14: ='Company Profile'!E12 -> 226413.8 | F14: ='Company Profile'!F12 -> 58240.41 | G14: ='Company Profile'!G12 -> 65270.46
A15: Total Capital | B15: =B13+B14 -> 240627 | C15: =C13+C14 -> 211142.4 | D15: =D13+D14 -> 382150.3 | E15: =E13+E14 -> 315377.61 | F15: =F13+F14 -> 88051.53 | G15: =G13+G14 -> 69040.91
A16: Weight of equity | B16: =B14/B15 -> 0.96297839 | C16: =C14/C15 -> 0.94955537 | D16: =D14/D15 -> 0.74890246 | E16: =E14/E15 -> 0.71791336 | F16: =F14/F15 -> 0.66143553 | G16: =G14/G15 -> 0.94538818
A17: Weight of debt | B17: =B13/B15 -> 0.037021614 | C17: =C13/C15 -> 0.050444629 | D17: =D13/D15 -> 0.25109754 | E17: =E13/E15 -> 0.28208664 | F17: =F13/F15 -> 0.33856447 | G17: =G13/G15 -> 0.054611824
A18: WACC | B18: =(B7*B16)+(B12*B17) -> 0.14004247 | C18: =(C7*C16)+(C12*C17) -> 0.098131369 | D18: =(D7*D16)+(D12*D17) -> 0.10955938 | E18: =(E7*E16)+(E12*E17) -> 0.12057108 | F18: =(F7*F16)+(F12*F17) -> 0.15121144 | G18: =(G7*G16)+(G12*G17) -> 0.13303449
A19: Terminal Growth | B19: 0.035 | C19: 0.035 | D19: 0.035 | E19: 0.035 | F19: 0.035 | G19: 0.035
A20: Cash and Cash equivalents | B20: ='Balance Sheet'!G21 -> 11160.68 | C20: ='Balance Sheet'!O19 -> 96 | D20: ='Balance Sheet'!W25 -> 11655 | E20: ='Balance Sheet'!AE26 -> 9604.96 | F20: ='Balance Sheet'!AM25 -> 291.58 | G20: =Table7[[#This Row],[2025]] -> 84.82
A21: Net Debt | B21: =B13-B20 -> -2252.28 | C21: =C13-C20 -> 10555 | D21: =D13-D20 -> 84302 | E21: =E13-E20 -> 79358.85 | F21: =F13-F20 -> 29519.54 | G21: =G13-G20 -> 3685.63

Sheet DCF
A1: Discounted Cash Flow
A3: COAL INDIA | H3: #VALUE! | J3: HINDUSTAN ZINC | Q3: #VALUE! | S3: JSW STEEL | Z3: #VALUE! | AB3: TATA STEEL | AI3: #VALUE! | AK3: SAIL | AR3: #VALUE! | AT3: NMDC | BA3: #VALUE!
A4: Parameters | B4: 2025 | C4: Growth/Ratio | D4: 2026 | E4: 2027 | F4: 2028 | G4: 2029 | H4: 2030 | J4: Parameters | K4: 2025 | L4: Growth/Ratio | M4: 2026 | N4: 2027 | O4: 2028 | P4: 2029 | Q4: 2030 | S4: Parameters | T4: 2025 | U4: Growth/Ratio | V4: 2026 | W4: 2027 | X4: 2028 | Y4: 2029 | Z4: 2030 | AB4: Parameters | AC4: 2025 | AD4: Growth/Ratio | AE4: 2026 | AF4: 2027 | AG4: 2028 | AH4: 2029 | AI4: 2030 | AK4: Parameters | AL4: 2025 | AM4: Growth/Ratio | AN4: 2026 | AO4: 2027 | AP4: 2028 | AQ4: 2029 | AR4: 2030 | AT4: Parameters | AU4: 2025 | AV4: Growth/Ratio | AW4: 2026 | AX4: 2027 | AY4: 2028 | AZ4: 2029 | BA4: 2030
A5: Revenue | B5: ='Income Statement'!G9 -> 152838.98 | C5: =('Income Statement'!G9/'Income Statement'!B9)^(1/6)-1 -> 0.068810013 | D5: =Table22[[#This Row],[2025]]*(1+C5) -> 163355.83 | E5: =Table22[[#This Row],[2026]]*(1+$C$5) -> 174596.35 | F5: =Table22[[#This Row],[2027]]*(1+$C$5) -> 186610.33 | G5: =Table22[[#This Row],[2028]]*(1+$C$5) -> 199450.98 | H5: =Table22[[#This Row],[2029]]*(1+$C$5) -> 213175.21 | J5: Revenue | K5: ='Income Statement'!O9 -> 35066 | L5: =('Income Statement'!O9/'Income Statement'!J9)^(1/6)-1 -> 0.093636638 | M5: =Table2231[[#This Row],[2025]]*(1+L5) -> 38349.462 | N5: =Table2231[[#This Row],[2026]]*(1+$L$5) -> 41940.377 | O5: =Table2231[[#This Row],[2027]]*(1+$L$5) -> 45867.533 | P5: =Table2231[[#This Row],[2028]]*(1+$L$5) -> 50162.414 | Q5: =Table2231[[#This Row],[2029]]*(1+$L$5) -> 54859.454 | S5: Revenue | T5: ='Income Statement'!W11 -> 169518 | U5: =('Income Statement'!W11/'Income Statement'!R11)^(1/6)-1 -> 0.14847795 | V5: =Table2233[[#This Row],[2025]]*(1+U5) -> 194687.68 | W5: =Table2233[[#This Row],[2026]]*(1+$U$5) -> 223594.51 | X5: =Table2233[[#This Row],[2027]]*(1+$U$5) -> 256793.37 | Y5: =Table2233[[#This Row],[2028]]*(1+$U$5) -> 294921.52 | Z5: =Table2233[[#This Row],[2029]]*(1+$U$5) -> 338710.86 | AB5: Revenue | AC5: ='Income Statement'!AE8 -> 220083.04 | AD5: =('Income Statement'!AE8/'Income Statement'!Z8)^(1/6)-1 -> 0.06504405 | AE5: =Table2235[[#This Row],[2025]]*(1+AD5) -> 234398.13 | AF5: =Table2235[[#This Row],[2026]]*(1+$AD$5) -> 249644.34 | AG5: =Table2235[[#This Row],[2027]]*(1+$AD$5) -> 265882.22 | AH5: =Table2235[[#This Row],[2028]]*(1+$AD$5) -> 283176.27 | AI5: =Table2235[[#This Row],[2029]]*(1+$AD$5) -> 301595.2 | AK5: Revenue | AL5: ='Income Statement'!AM8 -> 103354.09 | AM5: =('Income Statement'!AM8/'Income Statement'!AH8)^(1/6)-1 -> 0.087243892 | AN5: =Table2237[[#This Row],[2025]]*(1+$AM$5) -> 112371.1 | AO5: =Table2237[[#This Row],[2026]]*(1+$AM$5) -> 122174.8 | AP5: =Table2237[[#This Row],[2027]]*(1+$AM$5) -> 132833.8 | AQ5: =Table2237[[#This Row],[2028]]*(1+$AM$5) -> 144422.74 | AR5: =Table2237[[#This Row],[2029]]*(1+$AM$5) -> 157022.74 | AT5: Revenue | AU5: ='Income Statement'!AU8 -> 25498.84 | AV5: =('Income Statement'!AU8/'Income Statement'!AP8)^(1/6)-1 -> 0.13052345 | AW5: =Table2239[[#This Row],[2025]]*(1+AV5) -> 28827.036 | AX5: =Table2239[[#This Row],[2026]]*(1+$AV$5) -> 32589.641 | AY5: =Table2239[[#This Row],[2027]]*(1+$AV$5) -> 36843.353 | AZ5: =Table2239[[#This Row],[2028]]*(1+$AV$5) -> 41652.274 | BA5: =Table2239[[#This Row],[2029]]*(1+$AV$5) -> 47088.873
A6: EBITDA | B6: ='Income Statement'!G26+'Income Statement'!G19+'Income Statement'!G20 -> 56533.07 | C6: =(AVERAGE('Income Statement'!B26:G26)+AVERAGE('Income Statement'!B19:G19)+AVERAGE('Income Statement'!B20:G20))/AVERAGE('Income Statement'!B9:G9) -> 0.30885844 | D6: =D5*$C$6 -> 50453.827 | E6: =E5*$C$6 -> 53925.555 | F6: =F5*$C$6 -> 57636.173 | G6: =G5*$C$6 -> 61602.119 | H6: =H5*$C$6 -> 65840.962 | J6: EBITDA | K6: ='Income Statement'!O20+'Income Statement'!O16+'Income Statement'!O13 -> 18288 | L6: =(AVERAGE('Income Statement'!J20:O20)+AVERAGE('Income Statement'!J16:O16)+AVERAGE('Income Statement'!J13:O13))/AVERAGE('Income Statement'!J9:O9) -> 0.53070146 | M6: =M5*$L$6 -> 20352.115 | N6: =N5*$L$6 -> 22257.819 | O6: =O5*$L$6 -> 24341.966 | P6: =P5*$L$6 -> 26621.266 | Q6: =Q5*$L$6 -> 29113.992 | S6: EBITDA | T6: ='Income Statement'!W22+'Income Statement'!W18+'Income Statement'!W19 -> 23598 | U6: =(AVERAGE('Income Statement'!R22:W22)+AVERAGE('Income Statement'!R18:W18)+AVERAGE('Income Statement'!R19:W19))/AVERAGE('Income Statement'!R11:W11) -> 0.17933089 | V6: =V5*$U$6 -> 34913.516 | W6: =W5*$U$6 -> 40097.403 | X6: =X5*$U$6 -> 46050.983 | Y6: =Y5*$U$6 -> 52888.538 | Z6: =Z5*$U$6 -> 60741.32 | AB6: EBITDA | AC6: ='Income Statement'!AE20+'Income Statement'!AE14+'Income Statement'!AE15 -> 27029.79 | AD6: =(AVERAGE('Income Statement'!AD20:AE20)+AVERAGE('Income Statement'!AD14:AE14)+AVERAGE('Income Statement'!AD15:AE15))/AVERAGE('Income Statement'!AD8:AE8) -> 0.11325823 | AE6: =AE5*$AD$6 -> 26547.518 | AF6: =AF5*$AD$6 -> 28274.276 | AG6: =AG5*$AD$6 -> 30113.349 | AH6: =AH5*$AD$6 -> 32072.043 | AI6: =AI5*$AD$6 -> 34158.139 | AK6: EBITDA | AL6: ='Income Statement'!AM18+'Income Statement'!AM14+'Income Statement'!AM15 -> 11521.24 | AM6: =(AVERAGE('Income Statement'!AK18:AM18)+AVERAGE('Income Statement'!AK14:AM14)+AVERAGE('Income Statement'!AK15:AM15))/AVERAGE('Income Statement'!AK8:AM8) -> 0.1038311 | AN6: =AN5*$AM$6 -> 11667.616 | AO6: =AO5*$AM$6 -> 12685.544 | AP6: =AP5*$AM$6 -> 13792.28 | AQ6: =AQ5*$AM$6 -> 14995.572 | AR6: =AR5*$AM$6 -> 16303.844 | AT6: EBITDA | AU6: ='Income Statement'!AU23+'Income Statement'!AU19+'Income Statement'!AU20 -> 9741.99 | AV6: =(AVERAGE('Income Statement'!AP23:AU23)+AVERAGE('Income Statement'!AP19:AU19)+AVERAGE('Income Statement'!AP20:AU20))/AVERAGE('Income Statement'!AP8:AU8) -> 0.44729963 | AW6: =AW5*$AV$6 -> 12894.323 | AX6: =AX5*$AV$6 -> 14577.334 | AY6: =AY5*$AV$6 -> 16480.018 | AZ6: =AZ5*$AV$6 -> 18631.047 | BA6: =BA5*$AV$6 -> 21062.835
A7: Tax Expense | B7: ='Income Statement'!G32 -> 11664.09 | C7: =WACC!B11 -> 0.24835078 | D7: =D6*$C$7 -> 12530.247 | E7: =E6*$C$7 -> 13392.454 | F7: =F6*$C$7 -> 14313.989 | G7: =G6*$C$7 -> 15298.934 | H7: =H6*$C$7 -> 16351.654 | J7: Tax Expense | K7: ='Income Statement'!O23 -> 3200 | L7: =WACC!C11 -> 0.23611009 | M7: =M6*$L$7 -> 4805.3397 | N7: =N6*$L$7 -> 5255.2956 | O7: =O6*$L$7 -> 5747.3838 | P7: =P6*$L$7 -> 6285.5495 | Q7: =Q6*$L$7 -> 6874.1072 | S7: Tax Expense | T7: ='Income Statement'!W30 -> 1586 | U7: =WACC!D11 -> 0.31238921 | V7: =V6*$U$7 -> 10906.605 | W7: =W6*$U$7 -> 12525.996 | X7: =X6*$U$7 -> 14385.83 | Y7: =Y6*$U$7 -> 16521.808 | Z7: =Z6*$U$7 -> 18974.933 | AB7: Tax Expense | AC7: ='Income Statement'!AE34 -> 5239.09 | AD7: =AVERAGE('Income Statement'!Z34:AE34)/AVERAGE('Income Statement'!Z30:AE30) -> 0.34856395 | AE7: =AE6*$AD$7 -> 9253.5076 | AF7: =AF6*$AD$7 -> 9855.3932 | AG7: =AG6*$AD$7 -> 10496.428 | AH7: =AH6*$AD$7 -> 11179.158 | AI7: =AI6*$AD$7 -> 11906.296 | AK7: Tax Expense | AL7: =AL6*AM7 -> 3117.1727 | AM7: =WACC!F11 -> 0.27055878 | AN7: =AN6*$AM$7 -> 3156.7759 | AO7: =AO6*$AM$7 -> 3432.1853 | AP7: =AP6*$AM$7 -> 3731.6225 | AQ7: =AQ6*$AM$7 -> 4057.1838 | AR7: =AR6*$AM$7 -> 4411.1483 | AT7: Tax Expense | AU7: =AU6*Table2239[[#This Row],[Growth/Ratio]] -> 2774.4763 | AV7: =WACC!G11 -> 0.28479564 | AW7: =AW6*$AV$7 -> 3672.2469 | AX7: =AX6*$AV$7 -> 4151.5612 | AY7: =AY6*$AV$7 -> 4693.4373 | AZ7: =AZ6*$AV$7 -> 5306.0409 | BA7: =BA6*$AV$7 -> 5998.6036
A8: NOPAT | B8: =B6-B7 -> 44868.98 | D8: =D6-D7 -> 37923.579 | E8: =E6-E7 -> 40533.101 | F8: =F6-F7 -> 43322.185 | G8: =G6-G7 -> 46303.185 | H8: =H6-H7 -> 49489.308 | J8: NOPAT | K8: =K6-K7 -> 15088 | M8: =M6-M7 -> 15546.776 | N8: =N6-N7 -> 17002.524 | O8: =O6-O7 -> 18594.583 | P8: =P6-P7 -> 20335.717 | Q8: =Q6-Q7 -> 22239.885 | S8: NOPAT | T8: =T6-T7 -> 22012 | V8: =V6-V7 -> 24006.91 | W8: =W6-W7 -> 27571.407 | X8: =X6-X7 -> 31665.153 | Y8: =Y6-Y7 -> 36366.73 | Z8: =Z6-Z7 -> 41766.387 | AB8: NOPAT | AC8: =AC6-AC7 -> 21790.7 | AE8: =AE6-AE7 -> 17294.01 | AF8: =AF6-AF7 -> 18418.883 | AG8: =AG6-AG7 -> 19616.921 | AH8: =AH6-AH7 -> 20892.885 | AI8: =AI6-AI7 -> 22251.843 | AK8: NOPAT | AL8: =AL6-AL7 -> 8404.0673 | AN8: =AN6-AN7 -> 8510.8397 | AO8: =AO6-AO7 -> 9253.3585 | AP8: =AP6-AP7 -> 10060.658 | AQ8: =AQ6-AQ7 -> 10938.388 | AR8: =AR6-AR7 -> 11892.696 | AT8: NOPAT | AU8: =AU6-AU7 -> 6967.5137 | AW8: =AW6-AW7 -> 9222.0758 | AX8: =AX6-AX7 -> 10425.773 | AY8: =AY6-AY7 -> 11786.581 | AZ8: =AZ6-AZ7 -> 13325.006 | BA8: =BA6-BA7 -> 15064.232
A9: Depreciation | B9: ='Income Statement'!G20 -> 9145.49 | C9: =AVERAGE('Income Statement'!C20:G20)/AVERAGE(Table8[[#This Row],[2021]:[2025]]) -> 0.04362159 | D9: =D5*$C$9 -> 7125.8411 | E9: =E5*$C$9 -> 7616.1703 | F9: =F5*$C$9 -> 8140.2391 | G9: =G5*$C$9 -> 8700.369 | H9: =H5*$C$9 -> 9299.0415 | J9: Depreciation | K9: ='Income Statement'!O13 -> 3640 | L9: =AVERAGE('Income Statement'!J13:O13)/AVERAGE(Table9[[#This Row],[2020]:[2025]]) -> 0.10274882 | M9: =M5*$L$9 -> 3940.3622 | N9: =N5*$L$9 -> 4309.3245 | O9: =O5*$L$9 -> 4712.8351 | P9: =P5*$L$9 -> 5154.1291 | Q9: =Q5*$L$9 -> 5636.7445 | S9: Depreciation | T9: ='Income Statement'!W19 -> 9309 | U9: =AVERAGE('Income Statement'!R19:W19)/AVERAGE('Income Statement'!R11:W11) -> 0.048950379 | V9: =V5*$U$9 -> 9530.036 | W9: =W5*$U$9 -> 10945.036 | X9: =X5*$U$9 -> 12570.133 | Y9: =Y5*$U$9 -> 14436.52 | Z9: =Z5*$U$9 -> 16580.025 | AB9: Depreciation | AC9: ='Income Statement'!AE15 -> 10421.33 | AD9: =AVERAGE('Income Statement'!Z15:AE15)/AVERAGE('Income Statement'!Z8:AE8) -> 0.045410826 | AE9: =AE5*$AD$9 -> 10644.213 | AF9: =AF5*$AD$9 -> 11336.556 | AG9: =AG5*$AD$9 -> 12073.931 | AH9: =AH5*$AD$9 -> 12859.268 | AI9: =AI5*$AD$9 -> 13695.687 | AK9: Depreciation | AL9: ='Income Statement'!AM15 -> 5650.68 | AM9: =AVERAGE('Income Statement'!AH15:AM15)/AVERAGE('Income Statement'!AH8:AM8) -> 0.050764868 | AN9: =AN5*$AM$9 -> 5704.5042 | AO9: =AO5*$AM$9 -> 6202.1873 | AP9: =AP5*$AM$9 -> 6743.2903 | AQ9: =AQ5*$AM$9 -> 7331.6012 | AR9: =AR5*$AM$9 -> 7971.2386 | AT9: Depreciation | AU9: ='Income Statement'!AU20 -> 420.42 | AV9: =AVERAGE('Income Statement'!AP20:AU20)/AVERAGE('Income Statement'!AP8:AU8) -> 0.01582491 | AW9: =AW5*$AV$9 -> 456.18526 | AX9: =AX5*$AV$9 -> 515.72813 | AY9: =AY5*$AV$9 -> 583.04275 | AZ9: =AZ5*$AV$9 -> 659.1435 | BA9: =BA5*$AV$9 -> 745.17718
A10: CapEx | B10: =-'Cash Flow Statement'!G7 -> 12803.58 | C10: =ABS(AVERAGE('Cash Flow Statement'!B7:G7))/AVERAGE('Income Statement'!B9:G9) -> 0.093564883 | D10: =D5*$C$10 -> 15284.369 | E10: =E5*$C$10 -> 16336.087 | F10: =F5*$C$10 -> 17460.173 | G10: =G5*$C$10 -> 18661.608 | H10: =H5*$C$10 -> 19945.713 | J10: CapEx | K10: =-'Cash Flow Statement'!O6 -> 4006 | L10: =ABS(AVERAGE('Cash Flow Statement'!J6:O6))/AVERAGE('Income Statement'!J9:O9) -> 0.11665758 | M10: =M5*$L$10 -> 4473.7556 | N10: =N5*$L$10 -> 4892.663 | O10: =O5*$L$10 -> 5350.7955 | P10: =P5*$L$10 -> 5851.8261 | Q10: =Q5*$L$10 -> 6399.7714 | S10: CapEx | T10: =-'Cash Flow Statement'!W6 -> 12694 | U10: =ABS(AVERAGE('Cash Flow Statement'!R6:W6))/AVERAGE('Income Statement'!R11:W11) -> 0.092593434 | V10: =V5*$U$10 -> 18026.801 | W10: =W5*$U$10 -> 20703.384 | X10: =X5*$U$10 -> 23777.38 | Y10: =Y5*$U$10 -> 27307.796 | Z10: =Z5*$U$10 -> 31362.402 | AB10: CapEx | AC10: =-'Cash Flow Statement'!AE6 -> 15670.52 | AD10: =ABS(AVERAGE('Cash Flow Statement'!Z6:AE6))/AVERAGE('Income Statement'!Z8:AE8) -> 0.060823295 | AE10: =AE5*$AD$10 -> 14256.867 | AF10: =AF5*$AD$10 -> 15184.191 | AG10: =AG5*$AD$10 -> 16171.832 | AH10: =AH5*$AD$10 -> 17223.714 | AI10: =AI5*$AD$10 -> 18344.014 | AK10: CapEx | AL10: =-'Cash Flow Statement'!AM6 -> 6221.15 | AM10: =ABS(AVERAGE('Cash Flow Statement'!AH6:AM6))/AVERAGE('Income Statement'!AH8:AM8) -> 0.048808456 | AN10: =AN5*$AM$10 -> 5484.6601 | AO10: =AO5*$AM$10 -> 5963.1632 | AP10: =AP5*$AM$10 -> 6483.4127 | AQ10: =AQ5*$AM$10 -> 7049.0509 | AR10: =AR5*$AM$10 -> 7664.0375 | AT10: CapEx | AU10: =-'Cash Flow Statement'!AU6 -> 3230.34 | AV10: =ABS(AVERAGE('Cash Flow Statement'!AP6:AU6))/AVERAGE('Income Statement'!AP8:AU8) -> 0.096531812 | AW10: =AW5*$AV$10 -> 2782.7261 | AX10: =AX5*$AV$10 -> 3145.9371 | AY10: =AY5*$AV$10 -> 3556.5556 | AZ10: =AZ5*$AV$10 -> 4020.7695 | BA10: =BA5*$AV$10 -> 4545.5742
A11: Δ in working capital | B11: ='Balance Sheet'!G54-'Balance Sheet'!F54 -> -11159.05 | C11: =AVERAGE('Balance Sheet'!B54:G54)/AVERAGE('Income Statement'!B9:G9) -> 0.28507894 | D11: {=Table44[2026]-'Balance Sheet'!G54} -> 15117.538 | E11: {=Table44[2027]-Table44[2026]} -> 3204.4347 | F11: {=Table44[2028]-Table44[2027]} -> 3424.9319 | G11: {=Table44[2029]-Table44[2028]} -> 3660.6015 | H11: {=Table44[2030]-Table44[2029]} -> 3912.4875 | J11: Δ in working capital | K11: ='Balance Sheet'!O51-'Balance Sheet'!N51 -> -1357 | L11: =AVERAGE('Balance Sheet'!N51:O51)/AVERAGE('Income Statement'!N9:O9) -> 0.033977748 | M11: {=Table4446[2026]-'Balance Sheet'!O51} -> 876.02836 | N11: {=Table4446[2027]-Table4446[2026]} -> 122.01119 | O11: {=Table4446[2028]-Table4446[2027]} -> 133.43591 | P11: {=Table4446[2029]-Table4446[2028]} -> 145.9304 | Q11: {=Table4446[2030]-Table4446[2029]} -> 159.59483 | S11: Δ in working capital | T11: ='Balance Sheet'!W63-'Balance Sheet'!V63 -> 11641 | U11: =AVERAGE('Balance Sheet'!U63:W63)/AVERAGE(Table10[[#This Row],[2023]:[2025]]) -> 0.013201488 | V11: {=Table444647[2026]-'Balance Sheet'!W63} -> -7539.833 | W11: {=Table444647[2027]-Table444647[2026]} -> 381.61313 | X11: {=Table444647[2028]-Table444647[2027]} -> 438.27426 | Y11: {=Table444647[2029]-Table444647[2028]} -> 503.34832 | Z11: {=Table444647[2030]-Table444647[2029]} -> 578.08445 | AB11: Δ in working capital | AC11: ='Balance Sheet'!AE71-'Balance Sheet'!AD71 -> 10197.88 | AD11: =AVERAGE('Balance Sheet'!AC71:AE71)/AVERAGE('Income Statement'!AC8:AE8) -> -0.080941348 | AE11: {=Table44464748[2026]-'Balance Sheet'!AE71} -> -1270.4907 | AF11: {=Table44464748[2027]-Table44464748[2026]} -> -1234.0483 | AG11: {=Table44464748[2028]-Table44464748[2027]} -> -1314.3158 | AH11: {=Table44464748[2029]-Table44464748[2028]} -> -1399.8042 | AI11: {=Table44464748[2030]-Table44464748[2029]} -> -1490.8531 | AK11: Δ in working capital | AL11: ='Balance Sheet'!AM62-'Balance Sheet'!AL62 -> 1025.12 | AM11: =AVERAGE('Balance Sheet'!AL62:AM62)/AVERAGE('Income Statement'!AL8:AM8) -> -0.045893081 | AN11: {=Table4446474849[2026]-'Balance Sheet'!AM62} -> -855.44617 | AO11: {=Table4446474849[2027]-Table4446474849[2026]} -> -449.92165 | AP11: {=Table4446474849[2028]-Table4446474849[2027]} -> -489.17457 | AQ11: {=Table4446474849[2029]-Table4446474849[2028]} -> -531.85206 | AR11: {=Table4446474849[2030]-Table4446474849[2029]} -> -578.25291 | AT11: Δ in working capital | AU11: ='Balance Sheet'!AU51-'Balance Sheet'!AT51 -> 832.86 | AV11: =AVERAGE('Balance Sheet'!AP51:AU51)/AVERAGE('Income Statement'!AP8:AU8) -> 0.47414812 | AW11: {=Table444647484950[2026]-'Balance Sheet'!AU51} -> -40.034903 | AX11: {=Table444647484950[2027]-Table444647484950[2026]} -> 1784.0317 | AY11: {=Table444647484950[2028]-Table444647484950[2027]} -> 2016.8896 | AZ11: {=Table444647484950[2029]-Table444647484950[2028]} -> 2280.141 | BA11: {=Table444647484950[2030]-Table444647484950[2029]} -> 2577.7529
A12: FCFF | B12: =B8+B9-B10-B11 -> 52369.94 | D12: =D8+D9-D10-D11 -> 14647.513 | E12: =E8+E9-E10-E11 -> 28608.75 | F12: =F8+F9-F10-F11 -> 30577.319 | G12: =G8+G9-G10-G11 -> 32681.344 | H12: =H8+H9-H10-H11 -> 34930.148 | J12: FCFF | K12: =K8+K9-K10-K11 -> 16079 | M12: =M8+M9-M10-M11 -> 14137.354 | N12: =N8+N9-N10-N11 -> 16297.174 | O12: =O8+O9-O10-O11 -> 17823.186 | P12: =P8+P9-P10-P11 -> 19492.09 | Q12: =Q8+Q9-Q10-Q11 -> 21317.263 | S12: FCFF | T12: =T8+T9-T10-T11 -> 6986 | V12: =V8+V9-V10-V11 -> 23049.978 | W12: =W8+W9-W10-W11 -> 17431.446 | X12: =X8+X9-X10-X11 -> 20019.632 | Y12: =Y8+Y9-Y10-Y11 -> 22992.106 | Z12: =Z8+Z9-Z10-Z11 -> 26405.926 | AB12: FCFF | AC12: =AC8+AC9-AC10-AC11 -> 6343.63 | AE12: =AE8+AE9-AE10-AE11 -> 14951.847 | AF12: =AF8+AF9-AF10-AF11 -> 15805.295 | AG12: =AG8+AG9-AG10-AG11 -> 16833.336 | AH12: =AH8+AH9-AH10-AH11 -> 17928.244 | AI12: =AI8+AI9-AI10-AI11 -> 19094.37 | AK12: FCFF | AL12: =AL8+AL9-AL10-AL11 -> 6808.4773 | AN12: =AN8+AN9-AN10-AN11 -> 9586.13 | AO12: =AO8+AO9-AO10-AO11 -> 9942.3043 | AP12: =AP8+AP9-AP10-AP11 -> 10809.71 | AQ12: =AQ8+AQ9-AQ10-AQ11 -> 11752.791 | AR12: =AR8+AR9-AR10-AR11 -> 12778.15 | AT12: FCFF | AU12: =AU8+AU9-AU10-AU11 -> 3324.7337 | AW12: =AW8+AW9-AW10-AW11 -> 6935.5699 | AX12: =AX8+AX9-AX10-AX11 -> 6011.5323 | AY12: =AY8+AY9-AY10-AY11 -> 6796.1782 | AZ12: =AZ8+AZ9-AZ10-AZ11 -> 7683.2388 | BA12: =BA8+BA9-BA10-BA11 -> 8686.0816
A14: Parameters | B14: Value | J14: Parameters | K14: Value | S14: Parameters | T14: Value | AB14: Parameters | AC14: Value | AK14: Parameters | AL14: Value | AT14: Parameters | AU14: Value
A15: Terminal Value | B15: =(H12*(1+WACC!B19))/(WACC!B18-WACC!B19) -> 344172.26 | J15: Terminal Value | K15: =(Q12*(1+WACC!C19))/(WACC!C18-WACC!C19) -> 349483.43 | S15: Terminal Value | T15: =(Z12*(1+WACC!D19))/(WACC!D18-WACC!D19) -> 366555.29 | AB15: Terminal Value | AC15: =(AI12*(1+WACC!E19))/(WACC!E18-WACC!E19) -> 230950.37 | AK15: Terminal Value | AL15: =(AR12*(1+WACC!F19))/(WACC!F18-WACC!F19) -> 113804.51 | AT15: Terminal Value | AU15: =(BA12*(1+WACC!G19))/(WACC!G18-WACC!G19) -> 91703.382
A16: PV of Terminal Value | B16: =B15/(1+WACC!B18)^5 -> 178719 | J16: PV of Terminal Value | K16: =K15/(1+WACC!C18)^5 -> 218854.31 | S16: PV of Terminal Value | T16: =T15/(1+WACC!D18)^5 -> 217964.99 | AB16: PV of Terminal Value | AC16: =AC15/(1+WACC!E18)^5 -> 130713.85 | AK16: PV of Terminal Value | AL16: =AL15/(1+WACC!F18)^5 -> 56283.875 | AT16: PV of Terminal Value | AU16: =AU15/(1+WACC!G18)^5 -> 49109.973
A17: PV of FCFF | B17: =NPV(WACC!B18,DCF!D12:H12) -> 92981.936 | J17: PV of FCFF | K17: =NPV(WACC!C18,DCF!M12:Q12) -> 66601.479 | S17: PV of FCFF | T17: =NPV(WACC!D18,DCF!V12:Z12) -> 80460.069 | AB17: PV of FCFF | AC17: =NPV(WACC!E18,DCF!AE12:AI12) -> 60071.024 | AK17: PV of FCFF | AL17: =NPV(WACC!F18,DCF!AN12:AR12) -> 35925.233 | AT17: PV of FCFF | AU17: =NPV(WACC!G18,DCF!AW12:BA12) -> 24789.971
A18: Enterprise value | B18: =B16+B17 -> 271700.94 | J18: Enterprise value | K18: =K16+K17 -> 285455.79 | S18: Enterprise value | T18: =T16+T17 -> 298425.06 | AB18: Enterprise value | AC18: =AC16+AC17 -> 190784.87 | AK18: Enterprise value | AL18: =AL16+AL17 -> 92209.108 | AT18: Enterprise value | AU18: =AU16+AU17 -> 73899.944
A19: Net Debt | B19: =WACC!B21 -> -2252.28 | J19: Net Debt | K19: =WACC!C21 -> 10555 | S19: Net Debt | T19: =WACC!D21 -> 84302 | AB19: Net Debt | AC19: =WACC!E21 -> 79358.85 | AK19: Net Debt | AL19: =WACC!F21 -> 29519.54 | AT19: Net Debt | AU19: =WACC!G21 -> 3685.63
A20: Equity Value | B20: =B18-B19 -> 273953.22 | J20: Equity Value | K20: =K18-K19 -> 274900.79 | S20: Equity Value | T20: =T18-T19 -> 214123.06 | AB20: Equity Value | AC20: =AC18-AC19 -> 111426.02 | AK20: Equity Value | AL20: =AL18-AL19 -> 62689.568 | AT20: Equity Value | AU20: =AU18-AU19 -> 70214.314
A21: Outstanding shares | B21: ='Company Profile'!B10 -> 616.2729 | J21: Outstanding shares | K21: ='Company Profile'!C10 -> 422.5319 | S21: Outstanding shares | T21: ='Company Profile'!D10 -> 244.2547 | AB21: Outstanding shares | AC21: ='Company Profile'!E10 -> 1248.545 | AK21: Outstanding shares | AL21: ='Company Profile'!F10 -> 413.0525 | AT21: Outstanding shares | AU21: ='Company Profile'!G10 -> 879.1817
A22: Intrinsic Value/share | B22: =B20/B21 -> 444.53231 | J22: Intrinsic Value/share | K22: =K20/K21 -> 650.60363 | S22: Intrinsic Value/share | T22: =T20/T21 -> 876.63845 | AB22: Intrinsic Value/share | AC22: =AC20/AC21 -> 89.244698 | AK22: Intrinsic Value/share | AL22: =AL20/AL21 -> 151.77143 | AT22: Intrinsic Value/share | AU22: =AU20/AU21 -> 79.863257
A23: Current market price | B23: ='Company Profile'!B7 -> 381.3 | J23: Current market price | K23: ='Company Profile'!C7 -> 484.65 | S23: Current market price | T23: ='Company Profile'!D7 -> 1179.3 | AB23: Current market price | AC23: ='Company Profile'!E7 -> 181.48 | AK23: Current market price | AL23: ='Company Profile'!F7 -> 144.34 | AT23: Current market price | AU23: ='Company Profile'!G7 -> 75.08
A24: #VALUE! | B24: =(B22-B23)/B23 -> 0.16583349 | J24: #VALUE! | K24: =(K22-K23)/K23 -> 0.34241954 | S24: #VALUE! | T24: =(T22-T23)/T23 -> -0.25664509 | AB24: #VALUE! | AC24: =(AC22-AC23)/AC23 -> -0.50823949 | AK24: #VALUE! | AL24: =(AL22-AL23)/AL23 -> 0.051485583 | AT24: #VALUE! | AU24: =(AU22-AU23)/AU23 -> 0.063708798

Sheet Relative Valuation
A1: RELATIVE VALUATION
A3: Company | B3: EV/EBITDA | C3: P/E | D3: P/B | E3: P/S | G3: Metrics | H3: JSW Steel | I3: TATA Steel
A4: JSW Steel | B4: ='Financial Ratios'!W26 -> 15.778946 | C4: ='Financial Ratios'!W25 -> 82.51205 | D4: ='Company Profile'!D7/('Balance Sheet'!W40/'Company Profile'!D10) -> 3.5271664 | E4: ='Financial Ratios'!W27 -> 1.699227 | G4: EV/EBITDA | H4: =B15*B20 -> 355662.11 | I4: =B15*B21 -> 407385.04
A5: Tata Steel | B5: ='Financial Ratios'!AE26 -> 11.3188 | C5: ='Financial Ratios'!AE25 -> 71.393085 | D5: ='Company Profile'!E7/('Balance Sheet'!AE43/'Company Profile'!E10) -> 2.4803399 | E5: ='Financial Ratios'!AE27 -> 1.0295475 | G5: P/E | H5: =C15*C20 -> 125941.66 | I5: =C15*C21 -> 114497.6
A6: Jindal Steel | B6: 12.1 | C6: 37.3 | D6: 2.24 | E6: 2.1 | G6: P/B | H6: =D20*D15 -> 428016.12 | I6: =D21*D15 -> 478785.08
A7: Lloyds Metals and Energy | B7: 34.7 | C7: 46.8 | D7: 12.8 | E7: 10.1 | G7: P/S | H7: =E20*E15 -> 1131060 | I7: =E21*E15 -> 1468440.7
A8: NMDC | B8: ='Financial Ratios'!AU26 -> 7.1540406 | C8: ='Financial Ratios'!AU25 -> 10.094935 | D8: ='Company Profile'!G7/('Balance Sheet'!AU33/'Company Profile'!G10) -> 2.2219868 | E8: ='Financial Ratios'!AU27 -> 2.5887045 | G8: Market Cap | H8: ='Company Profile'!D12 -> 286193.3 | I8: ='Company Profile'!E12 -> 226413.8
A9: Jindal Stainless | B9: 13.5 | C9: 24.4 | D9: 3.8 | E9: 1.6 | G9: Average | H9: =AVERAGE(H4:H7) -> 510169.98 | I9: =AVERAGE(I4:I7) -> 617277.1
A10: SAIL | B10: ='Financial Ratios'!AM26 -> 7.7369743 | C10: ='Financial Ratios'!AM25 -> 25.137026 | D10: ='Company Profile'!F7/('Balance Sheet'!AM38/'Company Profile'!F10) -> 1.0121278 | E10: ='Financial Ratios'!AM27 -> 0.57685185
A11: KIOCL | B11: 0 | C11: 0 | D11: 13.5 | E11: 48 | G11: Metrics | H11: JSW Steel | I11: TATA Steel
A12: Shyam Metalics and Energy | B12: 13.3 | C12: 28.1 | D12: 2.27 | E12: 1.7 | G12: EV/EBITDA | H12: =H4/DCF!$T$21 -> 1456.1116 | I12: =I4/DCF!$AC$21 -> 326.28783
A13: Welspun Corp | B13: 13.1 | C13: 12.1 | D13: 3.1 | E13: 1.7 | G13: P/E | H13: =H5/DCF!$T$21 -> 515.61613 | I13: =I5/DCF!$AC$21 -> 91.704827
A14: APL Apollo Tubes | B14: 37.1 | C14: 59 | D14: 10.7 | E14: 2.3 | G14: P/B | H14: =H6/DCF!$T$21 -> 1752.3352 | I14: =I6/DCF!$AC$21 -> 383.47443
A15: Average | B15: =AVERAGE(B4:B14) -> 15.071706 | C15: =AVERAGE(C4:C14) -> 36.0761 | D15: =AVERAGE(D4:D14) -> 5.2410564 | E15: =AVERAGE(E4:E14) -> 6.6722119 | G15: P/S | H15: =H7/DCF!$T$21 -> 4630.6581 | I15: =I7/DCF!$AC$21 -> 1176.1215
G16: Market Price | H16: ='Company Profile'!D7 -> 1179.3 | I16: ='Company Profile'!E7 -> 181.48
G17: Average | H17: =AVERAGE(H12:H15) -> 2088.6803 | I17: =AVERAGE(I12:I15) -> 494.39716
A19: Particulars | B19: EBITDA | C19: Net Income | D19: Book Value | E19: Revenue | G19: Metrics | H19: JSW Steel | I19: TATA Steel
A20: JSW Steel | B20: =DCF!T6 -> 23598 | C20: ='Income Statement'!W31 -> 3491 | D20: ='Balance Sheet'!W40 -> 81666 | E20: ='Income Statement'!W11 -> 169518 | G20: EV/EBITDA | H20: =(H12-$H$16)/$H$16 -> 0.23472537 | I20: =(I12-$I$16)/$I$16 -> 0.7979272
A21: TATA Steel | B21: =DCF!AC6 -> 27029.79 | C21: ='Income Statement'!AE35 -> 3173.78 | D21: ='Balance Sheet'!AE43 -> 91352.78 | E21: ='Income Statement'!AE8 -> 220083.04 | G21: P/E | H21: =(H13-$H$16)/$H$16 -> -0.56277781 | I21: =(I13-$I$16)/$I$16 -> -0.49468356
G22: P/B | H22: =(H14-$H$16)/$H$16 -> 0.48591133 | I22: =(I14-$I$16)/$I$16 -> 1.1130396
G23: P/S | H23: =(H15-$H$16)/$H$16 -> 2.9266159 | I23: =(I15-$I$16)/$I$16 -> 5.4807227
G24: Average | H24: =(H17-H16)/H16 -> 0.7711187 | I24: =(I17-I16)/I16 -> 1.7242515

Sheet Calc
A1: Revenue CAGR | B1: CIL | C1: =(DCF!H5/DCF!D5)^(1/5)-1 -> 0.054679272 | I1: Company | J1: Change in EBIT (Historical) | K1: Change in CE | L1: Incremental ROCE (Historical) | M1: Change in EBIT (Forecast) | N1: Capex | O1: Depreciation | P1: Effective Capital | Q1: Raw ROCE (Forecast) | R1: Adjusted ROCE (Forecast)
A2: Revenue CAGR | B2: HZ | C2: =(DCF!Q5/DCF!M5)^(1/5)-1 -> 0.074232879 | I2: =B1 -> CIL | J2: =(('Income Statement'!G26+'Income Statement'!G19)-('Income Statement'!B26+'Income Statement'!B19)) -> 22812.17 | K2: =(('Balance Sheet'!G28-'Balance Sheet'!G52)-('Balance Sheet'!B28-'Balance Sheet'!B52)) -> 94197.53 | L2: =J2/K2 -> 0.24217376 | M2: =DCF!H6-DCF!D6 -> 15387.135 | N2: =AVERAGE(DCF!D10:H10) -> 17537.59 | O2: =AVERAGE(DCF!D9:H9) -> 8176.3322 | P2: =IF(N2-O2<=0,N2,MAX(N2-O2,0.1*N2)) -> 9361.258 | Q2: =M2/P2 -> 1.6437038 | R2: =MIN(MAX(Q2,0.08),0.2) -> 0.2
A3: Revenue CAGR | B3: JSW | C3: =(DCF!Z5/DCF!V5)^(1/5)-1 -> 0.11711563 | I3: =B2 -> HZ | J3: =(('Income Statement'!O20+'Income Statement'!O16)-('Income Statement'!J20+'Income Statement'!J16)) -> 6146 | K3: =(('Balance Sheet'!O25-'Balance Sheet'!O49)-('Balance Sheet'!J25-'Balance Sheet'!J49)) -> -18271 | L3: =J3/K3 -> -0.33638006 | M3: =DCF!Q6-DCF!M6 -> 8761.8768 | N3: =AVERAGE(DCF!M10:Q10) -> 5393.7623 | O3: =AVERAGE(DCF!M9:Q9) -> 4750.6791 | P3: =IF(N3-O3<=0,N3,MAX(N3-O3,0.1*N3)) -> 643.08325 | Q3: =M3/P3 -> 13.624794 | R3: =MIN(MAX(Q3,0.08),0.2) -> 0.2
A4: Revenue CAGR | B4: TATA | C4: =(DCF!AI5/DCF!AE5)^(1/5)-1 -> 0.051705285 | I4: =B3 -> JSW | J4: =(('Income Statement'!W22+'Income Statement'!W18)-('Income Statement'!R22+'Income Statement'!R18)) -> 6116 | K4: =(('Balance Sheet'!W34-'Balance Sheet'!W61)-('Balance Sheet'!R34-'Balance Sheet'!R61)) -> 91984 | L4: =J4/K4 -> 0.066489824 | M4: =DCF!Z6-DCF!V6 -> 25827.804 | N4: =AVERAGE(DCF!V10:Z10) -> 24235.552 | O4: =AVERAGE(DCF!V9:Z9) -> 12812.35 | P4: =IF(N4-O4<=0,N4,MAX(N4-O4,0.1*N4)) -> 11423.202 | Q4: =M4/P4 -> 2.2609951 | R4: =MIN(MAX(Q4,0.08),0.2) -> 0.2
A5: Revenue CAGR | B5: SAIL | C5: =(Table2237[[#This Row],[2030]]/Table2237[[#This Row],[2026]])^(1/5)-1 -> 0.069206478 | I5: =B4 -> TATA | J5: =(('Income Statement'!AE20+'Income Statement'!AE14)-('Income Statement'!Z20+'Income Statement'!Z14)) -> 5479.31 | K5: =(('Balance Sheet'!AE36-'Balance Sheet'!AE68)-('Balance Sheet'!Z36-'Balance Sheet'!Z68)) -> 3195.36 | L5: =J5/K5 -> 1.7147708 | M5: =DCF!AI6-DCF!AE6 -> 7610.6213 | N5: =AVERAGE(DCF!AE10:AI10) -> 16236.124 | O5: =AVERAGE(DCF!AE9:AI9) -> 12121.931 | P5: =IF(N5-O5<=0,N5,MAX(N5-O5,0.1*N5)) -> 4114.1925 | Q5: =M5/P5 -> 1.8498457 | R5: =MIN(MAX(Q5,0.08),0.2) -> 0.2
A6: Revenue CAGR | B6: NMDC | C6: =(DCF!BA5/DCF!AW5)^(1/5)-1 -> 0.10312229 | E6: GDP g | F6: 2020 | G6: =AVERAGE(-5.8%,9.7%) -> 0.0195 | I6: =B5 -> SAIL | J6: =(('Income Statement'!AM18+'Income Statement'!AM14)-('Income Statement'!AH18+'Income Statement'!AH14)) -> -1495.22 | K6: =(('Balance Sheet'!AM32-'Balance Sheet'!AM60)-('Balance Sheet'!AH32-'Balance Sheet'!AH60)) -> 8218.05 | L6: =J6/K6 -> -0.18194341 | M6: =Table2237[[#This Row],[2030]]-Table2237[[#This Row],[2026]] -> 4636.2287 | N6: =AVERAGE(DCF!AN10:AR10) -> 6528.8649 | O6: =AVERAGE(DCF!AN9:AR9) -> 6790.5643 | P6: =IF(N6-O6<=0,N6,MAX(N6-O6,0.1*N6)) -> 6528.8649 | Q6: =M6/P6 -> 0.71011252 | R6: =MIN(MAX(Q6,0.08),0.2) -> 0.2
A7: Revenue CAGR | B7: Average | C7: =AVERAGE(C1:C6) -> 0.078343639 | E7: GDP g | F7: 2025 | G7: 0.078 | I7: NMDC | J7: =(('Income Statement'!AU23+'Income Statement'!AU19)-('Income Statement'!AP23+'Income Statement'!AP19)) -> 3100.22 | K7: =(('Balance Sheet'!AU27-'Balance Sheet'!AU49)-('Balance Sheet'!AP27-'Balance Sheet'!AP49)) -> 2823.61 | L7: =J7/K7 -> 1.0979632 | M7: =DCF!BA6-DCF!AW6 -> 8168.5125 | N7: =AVERAGE(DCF!AW10:BA10) -> 3610.3125 | O7: =AVERAGE(DCF!AW9:BA9) -> 591.85536 | P7: =IF(N7-O7<=0,N7,MAX(N7-O7,0.1*N7)) -> 3018.4571 | Q7: =M7/P7 -> 2.706188 | R7: =MIN(MAX(Q7,0.08),0.2) -> 0.2
A8: Capex Intensity | B8: CIL | C8: =AVERAGE(DCF!D10:H10)/AVERAGE(DCF!D5:H5) -> 0.093564883 | E8: GDP g | F8: Change | G8: =G7-G6 -> 0.0585 | I8: Average | L8: =AVERAGE(L2:L7) -> 0.43384569 | Q8: =AVERAGE(Q2:Q7) -> 3.7992732 | R8: =AVERAGE(R2:R7) -> 0.2
A9: Capex Intensity | B9: HZ | C9: =AVERAGE(DCF!M10:Q10)/AVERAGE(DCF!M5:Q5) -> 0.11665758 | E9: GDP g | F9: Sensitivity | G9: =C21/G8 -> 11.876289
A10: Capex Intensity | B10: JSW | C10: =AVERAGE(Table2233[[#This Row],[2026]:[2030]])/AVERAGE(DCF!V5:Z5) -> 0.092593434
A11: Capex Intensity | B11: TATA | C11: =AVERAGE(DCF!AE10:AI10)/AVERAGE(DCF!AE5:AI5) -> 0.060823295
A12: Capex Intensity | B12: SAIL | C12: =AVERAGE(DCF!AN10:AR10)/AVERAGE(DCF!AN5:AR5) -> 0.048808456
A13: Capex Intensity | B13: NMDC | C13: =AVERAGE(DCF!AW10:BA10)/AVERAGE(DCF!AW5:BA5) -> 0.096531812
A14: Capex Intensity | B14: Average | C14: =AVERAGE(C8:C13) -> 0.08482991
A15: Earnings growth | B15: CIL | C15: =('Income Statement'!G37-'Income Statement'!B37)/'Income Statement'!B37 -> 1.1138552
A16: Earnings growth | B16: HZ | C16: =('Income Statement'!O24-'Income Statement'!J24)/'Income Statement'!J24 -> 0.52138134
A17: Earnings growth | B17: JSW | C17: =('Income Statement'!W31-'Income Statement'!R31)/'Income Statement'!R31 -> -0.10921153
A18: Earnings growth | B18: TATA | C18: =('Income Statement'!AE35-'Income Statement'!Z35)/'Income Statement'!Z35 -> 1.7085812
A19: Earnings growth | B19: SAIL | C19: =('Income Statement'!AM26-'Income Statement'!AH26)/'Income Statement'!AH26 -> 0.11839903
A20: Earnings growth | B20: NMDC | C20: =('Income Statement'!AU34-'Income Statement'!AP34)/'Income Statement'!AP34 -> 0.81557231
A21: Earnings growth | B21: Average | C21: =AVERAGE(C15:C20) -> 0.69476292
A22: Capex CAGR | B22: =B15 -> CIL | C22: =(DCF!H10/DCF!D10)^(1/5)-1 -> 0.054679272
A23: Capex CAGR | B23: =B16 -> HZ | C23: =(DCF!Q10/DCF!M10)^(1/5)-1 -> 0.074232879
A24: Capex CAGR | B24: =B17 -> JSW | C24: =(DCF!Z10/DCF!V10)^(1/5)-1 -> 0.11711563
A25: Capex CAGR | B25: =B18 -> TATA | C25: =(DCF!AI10/DCF!AE10)^(1/5)-1 -> 0.051705285
A26: Capex CAGR | B26: =B19 -> SAIL | C26: =(DCF!AR10/DCF!AN10)^(1/5)-1 -> 0.069206478
A27: Capex CAGR | B27: =B20 -> NMDC | C27: =(DCF!BA10/DCF!AW10)^(1/5)-1 -> 0.10312229
A28: Capex CAGR | B28: =B21 -> Average | C28: =AVERAGE(C22:C27) -> 0.078343639
A29: Earnings CAGR | B29: =B22 -> CIL | C29: =(DCF!H8/DCF!D8)^(1/5)-1 -> 0.054679272
A30: Earnings CAGR | B30: =B23 -> HZ | C30: =(DCF!Q8/DCF!M8)^(1/5)-1 -> 0.074232879
A31: Earnings CAGR | B31: =B24 -> JSW | C31: =(DCF!Z8/DCF!V8)^(1/5)-1 -> 0.11711563
A32: Earnings CAGR | B32: =B25 -> TATA | C32: =(DCF!AI8/DCF!AE8)^(1/5)-1 -> 0.051705285
A33: Earnings CAGR | B33: =B26 -> SAIL | C33: =(DCF!AR8/DCF!AN8)^(1/5)-1 -> 0.069206478
A34: Earnings CAGR | B34: =B27 -> NMDC | C34: =(DCF!BA8/DCF!AW8)^(1/5)-1 -> 0.10312229
A35: Earnings CAGR | B35: =B28 -> Average | C35: =AVERAGE(C29:C34) -> 0.078343639
