Workbook

Sheet Company Profile
A1: Particulars | B1: #VALUE! | C1: #VALUE! | D1: #VALUE! | E1: #VALUE! | F1: #VALUE! | G1: #VALUE!
A2: Company | B2: #VALUE! | C2: #VALUE! | D2: #VALUE! | E2: #VALUE! | F2: #VALUE! | G2: #VALUE!
A3: Official Name | B3: {=_FV(B2,"Official name",TRUE)} -> AVENUE SUPERMARTS LIMITED | C3: {=_FV(C2,"Official name",TRUE)} -> ITC LIMITED | D3: {=_FV(D2,"Official name",TRUE)} -> TRENT LIMITED | E3: {=_FV(E2,"Official name",TRUE)} -> VARUN BEVERAGES LIMITED | F3: {=_FV(F2,"Official name",TRUE)} -> TITAN COMPANY LIMITED | G3: {=_FV(G2,"Official name",TRUE)} -> HINDUSTAN UNILEVER LIMITED
A4: Ticker Symbol | B4: {=_FV(B2,"Ticker symbol",TRUE)} -> DMART | C4: {=_FV(C2,"Ticker symbol",TRUE)} -> ITC | D4: {=_FV(D2,"Ticker symbol",TRUE)} -> TRENT | E4: {=_FV(E2,"Ticker symbol",TRUE)} -> VBL | F4: {=_FV(F2,"Ticker symbol",TRUE)} -> TITAN | G4: {=_FV(G2,"Ticker symbol",TRUE)} -> HINDUNILVR
A5: Industry | B5: {=_FV(B2,"Industry")} -> Food & Drug Retailing | C5: {=_FV(C2,"Industry")} -> Food & Tobacco | D5: {=_FV(D2,"Industry")} -> Diversified Retail | E5: {=_FV(E2,"Industry")} -> Beverages | F5: {=_FV(F2,"Industry")} -> Textiles & Apparel | G5: {=_FV(G2,"Industry")} -> Personal & Household Products & Services
A6: Year of Corporation | B6: {=_FV(B2,"Year incorporated",TRUE)} -> 2000 | C6: {=_FV(C2,"Year incorporated",TRUE)} -> 1910 | D6: {=_FV(D2,"Year incorporated",TRUE)} -> 1952 | E6: {=_FV(E2,"Year incorporated",TRUE)} -> 1995 | F6: {=_FV(F2,"Year incorporated",TRUE)} -> 1984 | G6: {=_FV(G2,"Year incorporated",TRUE)} -> 1933
A7: Employees count | B7: {=_FV(B2,"Employees")} -> 16959 | C7: {=_FV(C2,"Employees")} -> 22041 | D7: {=_FV(D2,"Employees")} -> 27887 | E7: {=_FV(E2,"Employees")} -> 11041 | F7: {=_FV(F2,"Employees")} -> 9191 | G7: {=_FV(G2,"Employees")} -> 18802
A8: Shares outstanding | B8: {=_FV(B2,"Shares outstanding",TRUE)} -> 650733100 | C8: {=_FV(C2,"Shares outstanding",TRUE)} -> 12527840000 | D8: {=_FV(D2,"Shares outstanding",TRUE)} -> 355487500 | E8: {=_FV(E2,"Shares outstanding",TRUE)} -> 3381989000 | F8: {=_FV(F2,"Shares outstanding",TRUE)} -> 887045300 | G8: {=_FV(G2,"Shares outstanding",TRUE)} -> 2349591000
B9: =B8/10000000 -> 65.07331 | C9: =C8/10000000 -> 1252.784 | D9: =D8/10000000 -> 35.54875 | E9: =E8/10000000 -> 338.1989 | F9: =F8/10000000 -> 88.70453 | G9: =G8/10000000 -> 234.9591
A10: Share Price | B10: {=_FV(B2,"Price")} -> 4019 | C10: {=_FV(C2,"Price")} -> 405.55 | D10: {=_FV(D2,"Price")} -> 4283.7 | E10: {=_FV(E2,"Price")} -> 463.25 | F10: {=_FV(F2,"Price")} -> 3803 | G10: {=_FV(G2,"Price")} -> 2408.8
A11: Market Cap | B11: {=_FV(B2,"Market cap",TRUE)} -> 2610090000000 | C11: {=_FV(C2,"Market cap",TRUE)} -> 5061873000000 | D11: {=_FV(D2,"Market cap",TRUE)} -> 1644947000000 | E11: {=_FV(E2,"Market cap",TRUE)} -> 1590211000000 | F11: {=_FV(F2,"Market cap",TRUE)} -> 3343540000000 | G11: {=_FV(G2,"Market cap",TRUE)} -> 5671914000000
B12: =B11/10000000 -> 261009 | C12: =C11/10000000 -> 506187.3 | D12: =D11/10000000 -> 164494.7 | E12: =E11/10000000 -> 159021.1 | F12: =F11/10000000 -> 334354 | G12: =G11/10000000 -> 567191.4
A13: Change (%) | B13: {=_FV(B2,"Change (%)",TRUE)} -> 0.001995 | C13: {=_FV(C2,"Change (%)",TRUE)} -> 0.003712 | D13: {=_FV(D2,"Change (%)",TRUE)} -> -0.074255 | E13: {=_FV(E2,"Change (%)",TRUE)} -> -0.014781 | F13: {=_FV(F2,"Change (%)",TRUE)} -> 0.008941 | G13: {=_FV(G2,"Change (%)",TRUE)} -> -0.002154
A14: Beta | B14: {=_FV(B2,"Beta")} -> 1.4373 | C14: {=_FV(C2,"Beta")} -> 0.7767 | D14: {=_FV(D2,"Beta")} -> 1.4651 | E14: {=_FV(E2,"Beta")} -> 0.9261 | F14: {=_FV(F2,"Beta")} -> 1.3028 | G14: {=_FV(G2,"Beta")} -> 0.8014

Sheet Balance Sheet
G1: #VALUE! | N1: #VALUE! | V1: #VALUE! | AD1: #VALUE! | AL1: #VALUE! | AS1: #VALUE!
A2: Particulars | B2: 2020 | C2: 2021 | D2: 2022 | E2: 2023 | F2: 2024 | G2: 2025 | I2: Particulars | J2: 2020 | K2: 2021 | L2: 2022 | M2: 2023 | N2: 2024 | P2: Particulars | Q2: 2020 | R2: 2021 | S2: 2022 | T2: 2023 | U2: 2024 | V2: 2025 | X2: Particulars | Y2: 2020 | Z2: 2021 | AA2: 2022 | AB2: 2023 | AC2: 2024 | AD2: 2025 | AF2: Particulars | AG2: 2020 | AH2: 2021 | AI2: 2022 | AJ2: 2023 | AK2: 2024 | AL2: 2025 | AN2: Particulars | AO2: 2020 | AP2: 2021 | AQ2: 2022 | AR2: 2023 | AS2: 2024
A3: Assets | I3: Assets | P3: Assets | X3: Assets | AF3: Assets | AN3: Assets
A4: Non-current Assets | I4: Non-current assets | P4: Non-current Assets | X4: Non-current Assets | AF4: Non-current Assets | AN4: Non-current Assets
A5: Property, plant and equipment | B5: 5107.36 | C5: 5938.5 | D5: 7770.46 | E5: 9725.61 | F5: 11759.19 | G5: 14349.83 | I5: Property, plant and equipment | J5: 4192 | K5: 4960 | L5: 6116 | M5: 6169 | N5: 8031 | P5: Property, plant and equipment | Q5: 19632.92 | R5: 19153.94 | S5: 20207.43 | T5: 21117.06 | U5: 23082.33 | V5: 17428.89 | X5: Property, plant and equipment | Y5: 1285 | Z5: 1216 | AA5: 1218 | AB5: 1343 | AC5: 1737 | AD5: 1854 | AF5: Property, plant and equipment | AG5: 654.64 | AH5: 640.45 | AI5: 724.94 | AJ5: 871.18 | AK5: 1146.32 | AL5: 2068.24 | AN5: Property, plant and equipment | AO5: 5827.188 | AP5: 5155.172 | AQ5: 5441.578 | AR5: 6803.132 | AS5: 10622.551
A6: Capital work in progress | B6: 364.4 | C6: 1019.59 | D6: 1129.34 | E6: 829.16 | F6: 935.22 | G6: 1099.35 | I6: Capital work in progress | J6: 406 | K6: 597 | L6: 745 | M6: 1313 | N6: 1025 | P6: Capital work in progress | Q6: 3251.61 | R6: 4004.45 | S6: 3198.45 | T6: 2984.71 | U6: 2851.14 | V6: 1087.6 | X6: Capital work in progress | Y6: 11 | Z6: 19 | AA6: 69 | AB6: 133 | AC6: 88 | AD6: 93 | AF6: Capital work in progress | AG6: 23.32 | AH6: 107.98 | AI6: 104.72 | AJ6: 101.72 | AK6: 223.78 | AL6: 179.5 | AN6: Capital work in progress | AO6: 66.815 | AP6: 496.608 | AQ6: 606.632 | AR6: 1922.222 | AS6: 1162.343
A7: Right of use assets | B7: 717.33 | C7: 960.24 | D7: 1388.65 | E7: 1504.88 | F7: 1539.1 | G7: 1741.73 | I7: Goodwill | J7: 36 | K7: 36 | L7: 17316 | M7: 17316 | N7: 17466 | P7: Investment property | Q7: 385.36 | R7: 376.56 | S7: 364.2 | T7: 352.26 | U7: 340.93 | V7: 322.4 | X7: Right of use assets | Y7: 935 | Z7: 917 | AA7: 973 | AB7: 1285 | AC7: 1543 | AD7: 1774 | AF7: Investment property | AG7: 28.76 | AH7: 28.11 | AI7: 27.84 | AJ7: 27.13 | AK7: 26.91 | AL7: 26.86 | AN7: Right of use assets | AO7: 0 | AP7: 572.799 | AQ7: 915.501 | AR7: 1034.707 | AS7: 1363.122
A8: Investment Properties | B8: 16.53 | C8: 9.57 | D8: 9.03 | E8: 8.54 | F8: 8.09 | G8: 7.65 | I8: Other intangible assets | J8: 406 | K8: 402 | L8: 27930 | M8: 27907 | N8: 28247 | P8: Goodwill | Q8: 202.53 | R8: 779.73 | S8: 779.73 | T8: 779.73 | U8: 779.73 | V8: 896.93 | X8: Investment property | Y8: 24 | Z8: 24 | AA8: 1 | AB8: 1 | AC8: 1 | AD8: 1 | AF8: Goodwill on consolidation | AG8: 27.19 | AH8: 27.19 | AI8: 27.19 | AJ8: 27.19 | AK8: 27.19 | AL8: 27.19 | AN8: Goodwill | AO8: 24.23 | AP8: 24.23 | AQ8: 24.23 | AR8: 24.23 | AS8: 300.937
A9: Goodwill | B9: 78.27 | C9: 78.27 | D9: 78.27 | E9: 78.27 | F9: 78.27 | G9: 78.27 | I9: Goodwill on consideration | J9: 81 | K9: 81 | L9: 81 | M9: 81 | N9: 65 | P9: Other tangible assets | Q9: 525.37 | R9: 2011.06 | S9: 2013.1 | T9: 2727.32 | U9: 2678.11 | V9: 2724.74 | X9: Goodwill | Y9: 123 | Z9: 123 | AA9: 123 | AB9: 123 | AC9: 123 | AD9: 123 | AF9: Other intangible assets | AG9: 42.27 | AH9: 39.58 | AI9: 42.53 | AJ9: 51.21 | AK9: 47.37 | AL9: 46.09 | AN9: Other intangible assets | AO9: 557.201 | AP9: 558.574 | AQ9: 550.91 | AR9: 547.1 | AS9: 1115.126
A10: Intangible assets | B10: 28.54 | C10: 22.22 | D10: 13.61 | E10: 23.18 | F10: 30.35 | G10: 28.98 | I10: Financial assets | P10: Intangible assets under development | Q10: 4.85 | R10: 6.84 | S10: 27.09 | T10: 18.59 | U10: 9.64 | V10: 3.31 | X10: Other intangible assets | Y10: 266 | Z10: 243 | AA10: 229 | AB10: 246 | AC10: 305 | AD10: 310 | AF10: Right of use assets | AG10: 1985.57 | AH10: 2318.49 | AI10: 3864.21 | AJ10: 3550.24 | AK10: 1202.13 | AL10: 1726.75 | AN10: Intangible assets under development | AO10: 0 | AP10: 0 | AQ10: 0 | AR10: 0 | AS10: 4.369
A11: Financial Assets | I11: Investments | J11: 2 | K11: 2 | L11: 2 | M11: 2 | N11: 2 | P11: Right of use assets | Q11: 967.16 | R11: 977.19 | S11: 867.13 | T11: 874.88 | U11: 939.12 | V11: 581.89 | X11: Intangible assets under development | Y11: 7 | Z11: 13 | AA11: 16 | AB11: 11 | AC11: 9 | AD11: 12 | AF11: Investments | AG11: 735.91 | AH11: 816.63 | AI11: 757.39 | AJ11: 564.13 | AK11: 696.26 | AL11: 845.56 | AN11: Investment in associate | AO11: 0 | AP11: 0 | AQ11: 0.004 | AR11: 17.932 | AS11: 53.447
A12: Other non-current financial assets | B12: 3122.67 | C12: 1109.28 | D12: 1262.7 | E12: 108.55 | F12: 0.01 | G12: 2.01 | I12: Loans | J12: 215 | K12: 238 | L12: 111 | M12: 115 | N12: 102 | P12: Investment accounted for using the equity method | Q12: 266.16 | R12: 262.55 | S12: 269.24 | T12: 337.59 | U12: 549.73 | V12: 4711.78 | X12: Investments | Y12: 44 | Z12: 19 | AA12: 279 | AB12: 351 | AC12: 679 | AD12: 651 | AF12: Loan considered good-unsecured | AG12: 2.34 | AH12: 2.35 | AI12: 2.13 | AJ12: 1.86 | AK12: 1.66 | AL12: 1.35 | AN12: Investments | AO12: 0.001 | AP12: 0.001 | AQ12: 0.001 | AR12: 3.151 | AS12: 6.055
A13: Investments | D13: 0.01 | E13: 0.01 | F13: 234.76 | G13: 168.12 | I13: Other financial assets | J13: 11 | K13: 3 | L13: 757 | M13: 729 | N13: 760 | P13: Financial Assets | X13: Loans receivables | Y13: 154 | Z13: 158 | AA13: 42 | AB13: 54 | AC13: 72 | AD13: 62 | AF13: Others | AG13: 76.07 | AH13: 72.28 | AI13: 94.75 | AJ13: 136.71 | AK13: 447.7 | AL13: 616.75 | AN13: Loans | AO13: 41.789 | AP13: 0 | AQ13: 0 | AR13: 0 | AS13: 21.887
A14: Income tax assets (net) | B14: 8.25 | C14: 1.63 | D14: 2.28 | E14: 17.5 | F14: 17.56 | G14: 18.19 | I14: Non-current tax assets (net) | J14: 835 | K14: 1083 | L14: 17 | M14: 11 | N14: 10 | P14: Investments | Q14: 10448.46 | R14: 9761.99 | S14: 12307.49 | T14: 11844.57 | U14: 17619.87 | V14: 13720.54 | X14: Other financial assets | Y14: 199 | Z14: 211 | AA14: 382 | AB14: 595 | AC14: 788 | AD14: 868 | AF14: Deferred tax assets (net) | AG14: 110.4 | AH14: 114.52 | AI14: 126.35 | AJ14: 156.05 | AK14: 54.43 | AL14: 43.47 | AN14: Others | AO14: 0.121 | AP14: 42.06 | AQ14: 48.68 | AR14: 62.267 | AS14: 98.726
A15: Deferred tax assets (net) | B15: 0.29 | C15: 0.92 | D15: 1.66 | E15: 1.77 | F15: 4.72 | G15: 7.51 | I15: Deferred tax assets (net) | J15: 373 | K15: 284 | L15: 1246 | M15: 1158 | N15: 1175 | P15: Loans | Q15: 5.27 | R15: 4.07 | S15: 6.61 | T15: 5.48 | U15: 4.05 | V15: 7.6 | X15: Deferred tax assets (net) | Y15: 159 | Z15: 105 | AA15: 187 | AB15: 158 | AC15: 187 | AD15: 170 | AF15: Other non-current assets | AG15: 116.75 | AH15: 152.8 | AI15: 170.51 | AJ15: 216.33 | AK15: 178.15 | AL15: 164.43 | AN15: Deferred tax assets (net) | AO15: 11.018 | AP15: 2.41 | AQ15: 0 | AR15: 0 | AS15: 19.631
A16: Other non-current assets | B16: 285.14 | C16: 454.62 | D16: 373.78 | E16: 360.73 | F16: 367.9 | G16: 426.45 | I16: Other non-current assets | J16: 158 | K16: 146 | L16: 219 | M16: 194 | N16: 292 | P16: Others | Q16: 615.65 | R16: 101.87 | S16: 1589.58 | T16: 3739.75 | U16: 408.99 | V16: 1557.57 | X16: Income tax assets (net) | Y16: 144 | Z16: 121 | AA16: 137 | AB16: 151 | AC16: 213 | AD16: 104 | AF16: Total non-current assets | AG16: =SUM(AG5:AG15) -> 3803.22 | AH16: =SUM(AH5:AH15) -> 4320.38 | AI16: =SUM(AI5:AI15) -> 5942.56 | AJ16: =SUM(AJ5:AJ15) -> 5703.75 | AK16: =SUM(AK5:AK15) -> 4051.9 | AL16: =SUM(AL5:AL15) -> 5746.19 | AN16: Other non current assets | AO16: 130.344 | AP16: 183.923 | AQ16: 626.677 | AR16: 536.812 | AS16: 511.742
A17: Total non-current Assets | B17: =SUM(B5:B10,B12:B16) -> 9728.78 | C17: =SUM(C5:C10,C12:C16) -> 9594.84 | D17: =SUM(D5:D10,D12:D16) -> 12029.79 | E17: =SUM(E5:E10,E12:E16) -> 12658.2 | F17: =SUM(F5:F10,F12:F16) -> 14975.17 | G17: =SUM(G5:G10,G12:G16) -> 17928.09 | I17: Total non-current assets | J17: =SUM(J5:J16) -> 6715 | K17: =SUM(K5:K16) -> 7832 | L17: =SUM(L5:L16) -> 54540 | M17: =SUM(M5:M16) -> 54995 | N17: =SUM(N5:N16) -> 57175 | P17: Deferred tax assets (net) | Q17: 56.29 | R17: 58.54 | S17: 63.53 | T17: 52.02 | U17: 72.19 | V17: 87.98 | X17: Other non-current assets | Y17: 78 | Z17: 86 | AA17: 84 | AB17: 165 | AC17: 197 | AD17: 191 | AF17: Current Assets | AN17: Total non-current assets | AO17: =SUM(AO5:AO16) -> 6658.707 | AP17: =SUM(AP5:AP16) -> 7035.777 | AQ17: =SUM(AQ5:AQ16) -> 8214.213 | AR17: =SUM(AR5:AR16) -> 10951.553 | AS17: =SUM(AS5:AS16) -> 15279.936
A18: Current Assets | I18: Current Assets | P18: Income tax assets (net) | Q18: 38.42 | R18: 33.04 | S18: 42.3 | T18: 66.16 | U18: 44.93 | V18: 50.24 | X18: Total non-current assets | Y18: =SUM(Y5:Y17) -> 3429 | Z18: =SUM(Z5:Z17) -> 3255 | AA18: =SUM(AA5:AA17) -> 3740 | AB18: =SUM(AB5:AB17) -> 4616 | AC18: =SUM(AC5:AC17) -> 5942 | AD18: =SUM(AD5:AD17) -> 6213 | AF18: Inventories | AG18: 607.81 | AH18: 428.39 | AI18: 867.78 | AJ18: 1361.16 | AK18: 1582.73 | AL18: 2045.05 | AN18: Current Assets
A19: Inventories | B19: 1947.4 | C19: 2248.28 | D19: 2742.66 | E19: 3243.48 | F19: 3927.31 | G19: 5044.37 | I19: Inventories | J19: 2574 | K19: 2767 | L19: 3579 | M19: 4096 | N19: 4022 | P19: Other non-current assets | Q19: 1461.24 | R19: 1295.48 | S19: 1291.22 | T19: 1311.95 | U19: 1379.86 | V19: 1015.93 | X19: Current Assets | AF19: Investments | AG19: 778.87 | AH19: 670.66 | AI19: 526.33 | AJ19: 545.74 | AK19: 719.77 | AL19: 634.69 | AN19: Inventories | AO19: 928.804 | AP19: 1448.087 | AQ19: 1993.885 | AR19: 2150.533 | AS19: 2791.234
A20: Financial Assets | I20: Investments | J20: 2714 | K20: 1253 | L20: 2707 | M20: 3519 | N20: 4558 | P20: Total non-current assets | Q20: =SUM(Q5:Q19) -> 37861.29 | R20: =SUM(R5:R19) -> 38827.31 | S20: =SUM(S5:S19) -> 43027.1 | T20: =SUM(T5:T19) -> 46212.07 | U20: =SUM(U5:U19) -> 50760.62 | V20: =SUM(V5:V19) -> 44197.4 | X20: Inventories | Y20: 8103 | Z20: 8408 | AA20: 13609 | AB20: 16584 | AC20: 19051 | AD20: 28184 | AF20: Trade receivables considered good-unsecured | AG20: 17.12 | AH20: 20.77 | AI20: 18.26 | AJ20: 34.39 | AK20: 81.74 | AL20: 62.95 | AN20: Trade receivables | AO20: 241.797 | AP20: 221.249 | AQ20: 299.338 | AR20: 359.385 | AS20: 845.842
A21: Investments | B21: 14.68 | C21: 2.95 | D21: 5.93 | E21: 202.19 | F21: 106.66 | G21: 1.25 | I21: Loans | J21: 4 | K21: 0 | L21: 34 | M21: 35 | N21: 38 | P21: Current Assets | X21: Investments | Y21: 114 | Z21: 2805 | AA21: 15 | AB21: 2164 | AC21: 1666 | AD21: 1337 | AF21: Credit impaired | AG21: 0 | AH21: 0 | AI21: 0 | AJ21: 0 | AK21: 0 | AL21: 0 | AN21: Cash and cash equivalents | AO21: 104.558 | AP21: 150.75 | AQ21: 154.332 | AR21: 242.212 | AS21: 2266.283
A22: Trade receivables | B22: 19.55 | C22: 43.58 | D22: 66.89 | E22: 62.16 | F22: 166.37 | G22: 153.79 | I22: Trade receivables | J22: 1816 | K22: 1149 | L22: 1758 | M22: 2236 | N22: 2997 | P22: Inventories | Q22: 8879.33 | R22: 10397.16 | S22: 10864.15 | T22: 11771.16 | U22: 14152.88 | V22: 15637.56 | X22: Trade receivables | Y22: 312 | Z22: 366 | AA22: 565 | AB22: 674 | AC22: 1018 | AD22: 1068 | AF22: Cash and cash equivalents | AG22: 56 | AH22: 75.63 | AI22: 82.39 | AJ22: 83.23 | AK22: 294.55 | AL22: 338.47 | AN22: Bank balances | AO22: 85.492 | AP22: 185.872 | AQ22: 130.935 | AR22: 217.65 | AS22: 183.771
A23: Cash and cash equivalents | B23: 105.87 | C23: 191.5 | D23: 95.12 | E23: 207.15 | F23: 337.12 | G23: 355.48 | I23: Cash and cash equivalents | J23: 621 | K23: 3216 | L23: 1842 | M23: 1147 | N23: 825 | P23: Biological assets other than bearer plants | Q23: 86.2 | R23: 110.06 | S23: 109.44 | T23: 142.97 | U23: 150 | V23: 198.58 | X23: Cash and cash equivalents | Y23: 75 | Z23: 181 | AA23: 219 | AB23: 232 | AC23: 409 | AD23: 407 | AF23: Bank balances | AG23: 5.41 | AH23: 5.84 | AI23: 3.58 | AJ23: 3.07 | AK23: 3.01 | AL23: 1.37 | AN23: Loans | AO23: 10.016 | AP23: 0 | AQ23: 0 | AR23: 0 | AS23: 0
A24: Bank balances other cash & cash equiv. | B24: 2.01 | C24: 1254.08 | D24: 203.46 | E24: 1201.18 | F24: 301.06 | G24: 2.72 | I24: Bank balances other than cash and cash equivalents | J24: 3136 | K24: 1897 | L24: 2629 | M24: 2699 | N24: 6734 | P24: Financial Assets | X24: Balances other than above | Y24: 306 | Z24: 379 | AA24: 1354 | AB24: 1111 | AC24: 1117 | AD24: 1177 | AF24: Loans receivables considered good- Secured | AG24: 25 | AH24: 25 | AI24: 25 | AJ24: 15 | AK24: 15 | AL24: 15 | AN24: Others | AO24: 167.004 | AP24: 245.555 | AQ24: 397.706 | AR24: 738.823 | AS24: 835.616
A25: Other current financial assets | B25: 109.06 | C25: 167.91 | D25: 127.46 | E25: 316.77 | F25: 1128.49 | G25: 528.36 | I25: Other financial assets | J25: 605 | K25: 1420 | L25: 1154 | M25: 1089 | N25: 1425 | P25: Investments | Q25: 17948.33 | R25: 14846.33 | S25: 12264.28 | T25: 17232.86 | U25: 12944.42 | V25: 16287.5 | X25: Loans receivables | Y25: 56 | Z25: 109 | AA25: 423 | AB25: 135 | AC25: 281 | AD25: 44 | AF25: Unsecured | AG25: 60.98 | AH25: 1.04 | AI25: 1.44 | AJ25: 2.04 | AK25: 2.08 | AL25: 2.97 | AN25: Current tax assets (net) | AO25: 10.219 | AP25: 1.108 | AQ25: 0 | AR25: 0.311 | AS25: 4.872
A26: Other current assets | B26: 149.1 | C26: 152.83 | D26: 201.33 | E26: 215.46 | F26: 235.02 | G26: 306.23 | I26: Other current assets | J26: 440 | K26: 601 | L26: 497 | M26: 688 | N26: 713 | P26: Trade receivables | Q26: 2562.48 | R26: 2501.7 | S26: 2461.9 | T26: 2956.17 | U26: 4025.82 | V26: 4719.67 | X26: Others financial assets | Y26: 459 | Z26: 197 | AA26: 291 | AB26: 201 | AC26: 327 | AD26: 260 | AF26: Credit impaired | AG26: 0 | AH26: 0 | AI26: 0 | AJ26: 0 | AK26: 0 | AL26: 0 | AN26: Other current assets | AO26: 251.786 | AP26: 293.492 | AQ26: 427.834 | AR26: 526.716 | AS26: 936.356
A27: Total current assets | B27: =SUM(B19:B26) -> 2347.67 | C27: =SUM(C19:C26) -> 4061.13 | D27: =SUM(D19:D26) -> 3442.85 | E27: =SUM(E19:E26) -> 5448.39 | F27: =SUM(F19:F26) -> 6202.03 | G27: =SUM(G19:G26) -> 6392.2 | I27: Assets held for sale | J27: 4 | K27: 18 | L27: 17 | M27: 13 | N27: 12 | P27: Cash and cash equivalents | Q27: 650.35 | R27: 290.42 | S27: 271.37 | T27: 463.35 | U27: 625.89 | V27: 620 | X27: Other current assets | Y27: 696 | Z27: 752 | AA27: 978 | AB27: 1288 | AC27: 1721 | AD27: 1957 | AF27: Others | AG27: 39.09 | AH27: 55.5 | AI27: 98.19 | AJ27: 119.24 | AK27: 140.22 | AL27: 158.84 | AN27: Total current assets | AO27: =SUM(AO19:AO26) -> 1799.676 | AP27: =SUM(AP19:AP26) -> 2546.113 | AQ27: =SUM(AQ19:AQ26) -> 3404.03 | AR27: =SUM(AR19:AR26) -> 4235.63 | AS27: =SUM(AS19:AS26) -> 7863.974
A28: Total Assets | B28: =B17+B27 -> 12076.45 | C28: =C17+C27 -> 13655.97 | D28: =D17+D27 -> 15472.64 | E28: =E17+E27 -> 18106.59 | F28: =F17+F27 -> 21177.2 | G28: =G17+G27 -> 24320.29 | I28: Total current assets | J28: =SUM(J19:J27) -> 11914 | K28: =SUM(K19:K27) -> 12321 | L28: =SUM(L19:L27) -> 14217 | M28: =SUM(M19:M27) -> 15522 | N28: =SUM(N19:N27) -> 21324 | P28: Other bank balances | Q28: 6626.99 | R28: 4368.6 | S28: 4383.05 | T28: 4416.84 | U28: 6591.79 | V28: 3392.36 | X28: Assets held for sale | Y28: 0 | Z28: 0 | AA28: 0 | AB28: 18 | AC28: 18 | AD28: 0 | AF28: Current tax assets (net) | AG28: 23.45 | AH28: 4.52 | AI28: 1.89 | AJ28: 17.21 | AK28: 4 | AL28: 2.36 | AN28: Total assets | AO28: =AO17+AO27 -> 8458.383 | AP28: =AP17+AP27 -> 9581.89 | AQ28: =AQ17+AQ27 -> 11618.243 | AR28: =AR17+AR27 -> 15187.183 | AS28: =AS17+AS27 -> 23143.91
A29: Equity and Liabilities | I29: Total assets | J29: =J17+J28 -> 18629 | K29: =K17+K28 -> 20153 | L29: =L17+L28 -> 68757 | M29: =M17+M28 -> 70517 | N29: =N17+N28 -> 78499 | P29: Loans | Q29: 6.33 | R29: 3.47 | S29: 6.77 | T29: 7.12 | U29: 9.81 | V29: 9.51 | X29: Total current assets | Y29: =SUM(Y20:Y28) -> 10121 | Z29: =SUM(Z20:Z28) -> 13197 | AA29: =SUM(AA20:AA28) -> 17454 | AB29: =SUM(AB20:AB28) -> 22407 | AC29: =SUM(AC20:AC28) -> 25608 | AD29: =SUM(AD20:AD28) -> 34434 | AF29: Other current assets | AG29: 83.28 | AH29: 106.03 | AI29: 152.2 | AJ29: 188.01 | AK29: 253.63 | AL29: 402.61 | AN29: Equity and Liabilities
A30: Equity | I30: Equity and Liabilities | P30: Others | Q30: 1818.54 | R30: 1379.02 | S30: 2565.41 | T30: 1118.67 | U30: 1181.74 | V30: 1656.25 | X30: Total assets | Y30: =Y18+Y29 -> 13550 | Z30: =Z18+Z29 -> 16452 | AA30: =AA18+AA29 -> 21194 | AB30: =AB18+AB29 -> 27023 | AC30: =AC18+AC29 -> 31550 | AD30: =AD18+AD29 -> 40647 | AF30: Assets held under sale | AG30: 6.45 | AH30: 9.97 | AI30: 6.4 | AJ30: 8.69 | AK30: 13.12 | AL30: 9.14 | AN30: Equity
A31: Equity Share capital | B31: 647.77 | C31: 647.77 | D31: 647.77 | E31: 648.26 | F31: 650.73 | G31: 650.73 | I31: Equity | P31: Other current assets | Q31: 926.8 | R31: 1095.23 | S31: 1306.08 | T31: 1561.75 | U31: 1383.19 | V31: 1371.85 | X31: Equity and Liabilities | AF31: Total current assets | AG31: =SUM(AG18:AG30) -> 1703.46 | AH31: =SUM(AH18:AH30) -> 1403.35 | AI31: =SUM(AI18:AI30) -> 1783.46 | AJ31: =SUM(AJ18:AJ30) -> 2377.78 | AK31: =SUM(AK18:AK30) -> 3109.85 | AL31: =SUM(AL18:AL30) -> 3673.45 | AN31: Equity share capital | AO31: 288.689 | AP31: 433.033 | AQ31: 649.55 | AR31: 649.607 | AS31: 676.302
A32: Other equity | B32: 10431.97 | C32: 11535.94 | D32: 13029.87 | E32: 15430.44 | F32: 18047.09 | G32: 20777.02 | I32: Equity share capital | J32: 216 | K32: 216 | L32: 235 | M32: 235 | N32: 235 | P32: Total current assets | Q32: =SUM(Q22:Q31) -> 39505.35 | R32: =SUM(R22:R31) -> 34991.99 | S32: =SUM(S22:S31) -> 34232.45 | T32: =SUM(T22:T31) -> 39670.89 | U32: =SUM(U22:U31) -> 41065.54 | V32: =SUM(V22:V31) -> 43893.28 | X32: Equity | AF32: Total assets | AG32: =AG16+AG31 -> 5506.68 | AH32: =AH16+AH31 -> 5723.73 | AI32: =AI16+AI31 -> 7726.02 | AJ32: =AJ16+AJ31 -> 8081.53 | AK32: =AK16+AK31 -> 7161.75 | AL32: =AL16+AL31 -> 9419.64 | AN32: Other equity | AO32: 3235.12 | AP32: 3646.875 | AQ32: 4452.83 | AR32: 6286.891 | AS32: 15933.527
A33: Equity attributable to equity holders of the parent | B33: =SUM(B31:B32) -> 11079.74 | C33: =SUM(C31:C32) -> 12183.71 | D33: =SUM(D31:D32) -> 13677.64 | E33: =SUM(E31:E32) -> 16078.7 | F33: =SUM(F31:F32) -> 18697.82 | G33: =SUM(G31:G32) -> 21427.75 | I33: Other equity | J33: 7651 | K33: 8013 | L33: 47439 | M33: 48826 | N33: 50983 | P33: Total assets | Q33: =Q20+Q32 -> 77366.64 | R33: =R20+R32 -> 73819.3 | S33: =S20+S32 -> 77259.55 | T33: =T20+T32 -> 85882.96 | U33: =U20+U32 -> 91826.16 | V33: =V20+V32 -> 88090.68 | X33: Equity share capital | Y33: 89 | Z33: 89 | AA33: 89 | AB33: 89 | AC33: 89 | AD33: 89 | AF33: Equity and Liabilities | AN33: Attributable to the owners | AO33: =AO31+AO32 -> 3523.809 | AP33: =AP31+AP32 -> 4079.908 | AQ33: =AQ31+AQ32 -> 5102.38 | AR33: =AR31+AR32 -> 6936.498 | AS33: =AS31+AS32 -> 16609.829
A34: Non-controlling interest | B34: 0.46 | C34: 0.4 | D34: 0.25 | E34: 0.08 | F34: -0.48 | G34: -1.05 | I34: Non-controlling interest | J34: 18 | K34: 17 | L34: 20 | M34: 26 | N34: 205 | P34: Equity and Liabilities | X34: Other equity | Y34: 6580 | Z34: 7408 | AA34: 9214 | AB34: 11762 | AC34: 9304 | AD34: 11535 | AF34: Equity | AN34: Non controlling interest | AO34: 64.788 | AP34: 116.789 | AQ34: 113.107 | AR34: 148.155 | AS34: 129.807
A35: Total equity | B35: =SUM(B33,B34) -> 11080.2 | C35: =SUM(C33,C34) -> 12184.11 | D35: =SUM(D33,D34) -> 13677.89 | E35: =SUM(E33,E34) -> 16078.78 | F35: =SUM(F33,F34) -> 18697.34 | G35: =SUM(G33,G34) -> 21426.7 | I35: Total equity | J35: =SUM(J32:J34) -> 7885 | K35: =SUM(K32:K34) -> 8246 | L35: =SUM(L32:L34) -> 47694 | M35: =SUM(M32:M34) -> 49087 | N35: =SUM(N32:N34) -> 51423 | P35: Equity | X35: Attributable to the owners | Y35: =Y33+Y34 -> 6669 | Z35: =Z33+Z34 -> 7497 | AA35: =AA33+AA34 -> 9303 | AB35: =AB33+AB34 -> 11851 | AC35: =AC33+AC34 -> 9393 | AD35: =AD33+AD34 -> 11624 | AF35: Equity share capital | AG35: 35.55 | AH35: 35.55 | AI35: 35.55 | AJ35: 35.55 | AK35: 35.55 | AL35: 35.55 | AN35: Total equity | AO35: =AO33+AO34 -> 3588.597 | AP35: =AP33+AP34 -> 4196.697 | AQ35: =AQ33+AQ34 -> 5215.487 | AR35: =AR33+AR34 -> 7084.653 | AS35: =AS33+AS34 -> 16739.636
A36: Liabilities | I36: Liabilities | P36: Equity Share capital | Q36: 1229.22 | R36: 1230.88 | S36: 1232.33 | T36: 1242.8 | U36: 1248.47 | V36: 1251.41 | X36: Non controlling interest | Y36: 4 | Z36: 5 | AA36: 30 | AB36: 53 | AC36: 0 | AD36: 0 | AF36: Other equity | AG36: 2352.22 | AH36: 2277.48 | AI36: 2328.45 | AJ36: 2559.94 | AK36: 4032.19 | AL36: 5426.19 | AN36: Liabilities
A37: Non-current liabilities | I37: Non-current liabilities | P37: Other equity | Q37: 64044.04 | R37: 59116.46 | S37: 61223.24 | T37: 67912.46 | U37: 73258.53 | V37: 68778.64 | X37: Total equity | Y37: =Y35+Y36 -> 6673 | Z37: =Z35+Z36 -> 7502 | AA37: =AA35+AA36 -> 9333 | AB37: =AB35+AB36 -> 11904 | AC37: =AC35+AC36 -> 9393 | AD37: =AD35+AD36 -> 11624 | AF37: Attributable to the owners | AG37: =AG35+AG36 -> 2387.77 | AH37: =AH35+AH36 -> 2313.03 | AI37: =AI35+AI36 -> 2364 | AJ37: =AJ35+AJ36 -> 2595.49 | AK37: =AK35+AK36 -> 4067.74 | AL37: =AL35+AL36 -> 5461.74 | AN37: Non-current liabilities
A38: Financial Liabilities | I38: Lease liabilities | J38: 0 | K38: 0 | L38: 731 | M38: 741 | N38: 1106 | P38: Attributale to the owners of the parent | Q38: =Q36+Q37 -> 65273.26 | R38: =R36+R37 -> 60347.34 | S38: =S36+S37 -> 62455.57 | T38: =T36+T37 -> 69155.26 | U38: =U36+U37 -> 74507 | V38: =V36+V37 -> 70030.05 | X38: Liabilities | AF38: Non controlling interest | AG38: 79.59 | AH38: 44.49 | AI38: 45.94 | AJ38: 67.48 | AK38: 34.85 | AL38: 121.62 | AN38: Borrowings | AO38: 1979.622 | AP38: 1813.327 | AQ38: 1727.022 | AR38: 3188.938 | AS38: 840.689
A39: Borrowings | B39: 0 | C39: 0 | D39: 0 | E39: 0 | F39: 0 | G39: 0 | I39: Other financial liabilities | J39: 394 | K39: 939 | L39: 296 | M39: 357 | N39: 718 | P39: Non-controlling interest | Q39: 377.47 | R39: 346.81 | S39: 366.3 | T39: 383.53 | U39: 382.97 | V39: 367.89 | X39: Non-current liabilities | AF39: Total equity | AG39: =AG37+AG38 -> 2467.36 | AH39: =AH37+AH38 -> 2357.52 | AI39: =AI37+AI38 -> 2409.94 | AJ39: =AJ37+AJ38 -> 2662.97 | AK39: =AK37+AK38 -> 4102.59 | AL39: =AL37+AL38 -> 5583.36 | AN39: Other financial liabilities | AO39: 24.439 | AP39: 31.263 | AQ39: 165.425 | AR39: 197.885 | AS39: 357.086
A40: Lease Liability | B40: 221.11 | C40: 312.01 | D40: 507.15 | E40: 476.66 | F40: 399.24 | G40: 555.79 | I40: Provisions | J40: 1082 | K40: 1227 | L40: 1578 | M40: 1580 | N40: 1576 | P40: Total equity | Q40: =Q38+Q39 -> 65650.73 | R40: =R38+R39 -> 60694.15 | S40: =S38+S39 -> 62821.87 | T40: =T38+T39 -> 69538.79 | U40: =U38+U39 -> 74889.97 | V40: =V38+V39 -> 70397.94 | X40: Borrowings | Y40: 17 | Z40: 9 | AA40: 2 | AB40: 0 | AC40: 3302 | AD40: 595 | AF40: Liabilities | AN40: Provisions | AO40: 203.906 | AP40: 208.543 | AQ40: 204.113 | AR40: 212.644 | AS40: 189.434
A41: Other non-current financial liabilities | B41: 0.47 | C41: 0.44 | D41: 0.41 | E41: 0.47 | F41: 0.37 | G41: 0.49 | I41: Deferred tax liabilities | J41: 0 | K41: 0 | L41: 5988 | M41: 6141 | N41: 6557 | P41: Liabilities | X41: Lease liabilities | Y41: 1056 | Z41: 1059 | AA41: 1138 | AB41: 1607 | AC41: 2032 | AD41: 2318 | AF41: Non-current liabilities | AN41: Deferred tax liabilities (net) | AO41: 225.943 | AP41: 311.141 | AQ41: 336.848 | AR41: 343.011 | AS41: 487.909
A42: Provisions | B42: 1.48 | C42: 2.45 | D42: 4.87 | E42: 6.41 | F42: 9.18 | G42: 12.67 | I42: Non-current tax liabilities (net) | J42: 601 | K42: 424 | L42: 1367 | M42: 1331 | N42: 4243 | P42: Non-current liabilities | X42: Other financial liabilities | Y42: 4 | Z42: 3 | AA42: 4 | AB42: 4 | AC42: 8 | AD42: 6 | AF42: Borrowings | AG42: 299.74 | AH42: 0 | AI42: 497.38 | AJ42: 497.95 | AK42: 498.56 | AL42: 499.2 | AN42: Other non-current liabilities | AO42: 0.734 | AP42: 0.673 | AQ42: 0.594 | AR42: 6.84 | AS42: 4.731
A43: Deferred tax liabilities (net) | B43: 47.39 | C43: 51.19 | D43: 64.03 | E43: 76.96 | F43: 91.93 | G43: 112.48 | I43: Total non-current liabilities | J43: =SUM(J38:J42) -> 2077 | K43: =SUM(K38:K42) -> 2590 | L43: =SUM(L38:L42) -> 9960 | M43: =SUM(M38:M42) -> 10150 | N43: =SUM(N38:N42) -> 14200 | P43: Borrowings | Q43: 5.9 | R43: 5.58 | S43: 4.85 | T43: 3.49 | U43: 1.76 | V43: 0 | X43: Provisions | Y43: 166 | Z43: 156 | AA43: 198 | AB43: 240 | AC43: 274 | AD43: 299 | AF43: Lease liabilities | AG43: 2227.2 | AH43: 2592.13 | AI43: 4126.01 | AJ43: 3750.22 | AK43: 845.2 | AL43: 1101.8 | AN43: Total non-current liabilities | AO43: =SUM(AO38:AO42) -> 2434.644 | AP43: =SUM(AP38:AP42) -> 2364.947 | AQ43: =SUM(AQ38:AQ42) -> 2434.002 | AR43: =SUM(AR38:AR42) -> 3949.318 | AS43: =SUM(AS38:AS42) -> 1879.849
A44: Total non-current liabilities | B44: =SUM(B39:B43) -> 270.45 | C44: =SUM(C39:C43) -> 366.09 | D44: =SUM(D39:D43) -> 576.46 | E44: =SUM(E39:E43) -> 560.5 | F44: =SUM(F39:F43) -> 500.72 | G44: =SUM(G39:G43) -> 681.43 | I44: Current liabilities | P44: Lease liabilities | Q44: 204 | R44: 206.96 | S44: 193.67 | T44: 213.37 | U44: 230.61 | V44: 137.21 | X44: Deferred tax liability (net) | Y44: 6 | Z44: 8 | AA44: 6 | AB44: 3 | AC44: 3 | AD44: 2 | AF44: Other financial liabilities | AG44: 18.21 | AH44: 13.98 | AI44: 8.48 | AJ44: 8.06 | AK44: 5.3 | AL44: 46.47 | AN44: Current Liabilities
A45: Current Liabilities | I45: Borrowings | J45: 99 | K45: 0 | L45: 0 | M45: 0 | N45: 13 | P45: Other financial liabilities | Q45: 127.87 | R45: 283.5 | S45: 144.5 | T45: 416.87 | U45: 433.96 | V45: 301.34 | X45: Other non-current liabilities | Y45: 0 | Z45: 1 | AA45: 1 | AB45: 1 | AC45: 9 | AD45: 10 | AF45: Provisions | AG45: 6.9 | AH45: 8.66 | AI45: 21.26 | AJ45: 58.9 | AK45: 160.04 | AL45: 165.78 | AN45: Borrowings | AO45: 713.858 | AP45: 1528.568 | AQ45: 1967.79 | AR45: 2005.449 | AS45: 1523.576
A46: Financial Liabilities | I46: Lease liabilities | J46: 0 | K46: 0 | L46: 278 | M46: 302 | N46: 365 | P46: Provisions | Q46: 175.37 | R46: 187.5 | S46: 221.05 | T46: 259.21 | U46: 288.3 | V46: 303.11 | X46: Total non-current liabilities | Y46: =SUM(Y40:Y45) -> 1249 | Z46: =SUM(Z40:Z45) -> 1236 | AA46: =SUM(AA40:AA45) -> 1349 | AB46: =SUM(AB40:AB45) -> 1855 | AC46: =SUM(AC40:AC45) -> 5628 | AD46: =SUM(AD40:AD45) -> 3230 | AF46: Deferred tax liability (net) | AG46: 0 | AH46: 0 | AI46: 0 | AJ46: 0 | AK46: 0 | AL46: 0 | AN46: Lease liabilities | AO46: 0 | AP46: 0 | AQ46: 0 | AR46: 39.038 | AS46: 104.903
A47: Borrowings | B47: 3.73 | C47: 0 | D47: 0 | E47: 0 | F47: 0 | G47: 0 | I47: TP total outstanding dues of micro and small enterprises | J47: 0 | K47: 0 | L47: 67 | M47: 60 | N47: 250 | P47: Deferred tax liabilities (net) | Q47: 1627.2 | R47: 1736.39 | S47: 1673.47 | T47: 1629 | U47: 2141.44 | V47: 2582.46 | X47: Current Liabilities | AF47: Other non-current liabilities | AG47: 0 | AH47: 0 | AI47: 9.5 | AJ47: 9.45 | AK47: 8.59 | AL47: 12.34 | AN47: TP outstanding dues of micro and small ent | AO47: 9.37 | AP47: 34.285 | AQ47: 65.911 | AR47: 76.743 | AS47: 64.575
A48: Lease Liability | B48: 74.35 | C48: 80.7 | D48: 139.79 | E48: 166.32 | F48: 192.92 | G48: 263.83 | I48: TP total outstanding dues of creditors other than above | J48: 7206 | K48: 7535 | L48: 8735 | M48: 9008 | N48: 10236 | P48: Other non-current liabilities | Q48: 16.2 | R48: 15.54 | S48: 36.43 | T48: 82.84 | U48: 149.72 | V48: 34.51 | X48: Financial Liabilities | AF48: Total non-current liabilities | AG48: =SUM(AG42:AG47) -> 2552.05 | AH48: =SUM(AH42:AH47) -> 2614.77 | AI48: =SUM(AI42:AI47) -> 4662.63 | AJ48: =SUM(AJ42:AJ47) -> 4324.58 | AK48: =SUM(AK42:AK47) -> 1517.69 | AL48: =SUM(AL42:AL47) -> 1825.59 | AN48: TP outstanding dues other than above | AO48: 502.015 | AP48: 677.468 | AQ48: 758.35 | AR48: 681.505 | AS48: 1495.852
A49: Trade payables due to micro and small enterprises | B49: 17.47 | C49: 21.95 | D49: 32.39 | E49: 76.29 | F49: 230.6 | G49: 289.53 | I49: Other financial liabilities | J49: 492 | K49: 932 | L49: 928 | M49: 899 | N49: 865 | P49: Total non-current liabilities | Q49: =SUM(Q43:Q48) -> 2156.54 | R49: =SUM(R43:R48) -> 2435.47 | S49: =SUM(S43:S48) -> 2273.97 | T49: =SUM(T43:T48) -> 2604.78 | U49: =SUM(U43:U48) -> 3245.79 | V49: =SUM(V43:V48) -> 3358.63 | X49: Borrowings | Y49: 706 | Z49: 156 | AA49: 516 | AB49: 2195 | AC49: 4536 | AD49: 9691 | AF49: Current Liabilities | AN49: Other financial liabilities | AO49: 854.351 | AP49: 392.966 | AQ49: 559.39 | AR49: 763.839 | AS49: 704.341
A50: TP other than micro and small enterprises | B50: 415.98 | C50: 556.18 | D50: 556.81 | E50: 677.5 | F50: 754.21 | G50: 781.28 | I50: Other current liabilities | J50: 347 | K50: 428 | L50: 588 | M50: 665 | N50: 807 | P50: Current Liabilities | X50: Gold on loan | Y50: 1585 | Z50: 4210 | AA50: 5398 | AB50: 5299 | AC50: 5341 | AD50: 7810 | AF50: Financial Liabilities | AN50: Other current liabilities | AO50: 318.292 | AP50: 309.676 | AQ50: 488.977 | AR50: 465.093 | AS50: 491.655
A51: Other current financial liabilities | B51: 177.94 | C51: 269.78 | D51: 282.92 | E51: 289.46 | F51: 389.85 | G51: 448.64 | I51: Provisions | J51: 523 | K51: 422 | L51: 507 | M51: 346 | N51: 340 | P51: Financial Liabilities | X51: Lease liabilities | Y51: 187 | Z51: 197 | AA51: 221 | AB51: 266 | AC51: 317 | AD51: 363 | AF51: Lease Liabilities | AG51: 0 | AH51: 0 | AI51: 101.97 | AJ51: 215.97 | AK51: 409.23 | AL51: 636.19 | AN51: Provisions | AO51: 33.172 | AP51: 49.74 | AQ51: 29.191 | AR51: 82.543 | AS51: 73.9
A52: Current tax liabilities | B52: 0.45 | C52: 112.66 | D52: 58.37 | E52: 121.18 | F52: 95.74 | G52: 138.62 | I52: Total current liabilities | J52: =SUM(J45:J51) -> 8667 | K52: =SUM(K45:K51) -> 9317 | L52: =SUM(L45:L51) -> 11103 | M52: =SUM(M45:M51) -> 11280 | N52: =SUM(N45:N51) -> 12876 | P52: Borrowings | Q52: 1.42 | R52: 3.88 | S52: 0.74 | T52: 35.32 | U52: 9.52 | V52: 91.26 | X52: TP outstandings dues of micro and small ent | Y52: 68 | Z52: 167 | AA52: 242 | AB52: 181 | AC52: 207 | AD52: 217 | AF52: TP outstanding dues of micro and small ent | AG52: 18.87 | AH52: 9.59 | AI52: 7.14 | AJ52: 35.88 | AK52: 34.21 | AL52: 31.25 | AN52: Current tax liabilities (net) | AO52: 3.892 | AP52: 13.941 | AQ52: 75.568 | AR52: 39.002 | AS52: 65.623
A53: Other current liabilities | B53: 20.7 | C53: 40.73 | D53: 36.44 | E53: 50.87 | F53: 61.04 | G53: 49.14 | I53: Total equity and liabilities | J53: =SUM(J35,J43,J52) -> 18629 | K53: =SUM(K35,K43,K52) -> 20153 | L53: =SUM(L35,L43,L52) -> 68757 | M53: =SUM(M35,M43,M52) -> 70517 | N53: =SUM(N35,N43,N52) -> 78499 | P53: TP outstanding dues of micro enterprises and small ent | Q53: 37.93 | R53: 61.15 | S53: 101.42 | T53: 137.88 | U53: 207.23 | V53: 180.64 | X53: Outstanding dues creditors other than above | Y53: 528 | Z53: 622 | AA53: 1052 | AB53: 1033 | AC53: 1203 | AD53: 1746 | AF53: TP outstanding dues of creditors other than above | AG53: 278.78 | AH53: 264.98 | AI53: 370.89 | AJ53: 629.34 | AK53: 739.7 | AL53: 896.94 | AN53: Total current liabilities | AO53: =SUM(AO45:AO52) -> 2434.95 | AP53: =SUM(AP45:AP52) -> 3006.644 | AQ53: =SUM(AQ45:AQ52) -> 3945.177 | AR53: =SUM(AR45:AR52) -> 4153.212 | AS53: =SUM(AS45:AS52) -> 4524.425
A54: Provisions | B54: 15.18 | C54: 23.77 | D54: 111.57 | E54: 85.39 | F54: 254.78 | G54: 241.12 | P54: Total outstanding dues of creditors other than above | Q54: 3591.9 | R54: 4257.58 | S54: 4315.84 | T54: 4521.11 | U54: 4590.6 | V54: 4626.66 | X54: Other financial liabilities | Y54: 219 | Z54: 239 | AA54: 440 | AB54: 568 | AC54: 670 | AD54: 1330 | AF54: Other financial liabilities | AG54: 139.04 | AH54: 421.48 | AI54: 85.93 | AJ54: 79.49 | AK54: 159.62 | AL54: 242.91 | AN54: Total liabilities | AO54: =AO43+AO53 -> 4869.594 | AP54: =AP43+AP53 -> 5371.591 | AQ54: =AQ43+AQ53 -> 6379.179 | AR54: =AR43+AR53 -> 8102.53 | AS54: =AS43+AS53 -> 6404.274
A55: Total current liabilities | B55: =SUM(B47:B54) -> 725.8 | C55: =SUM(C47:C54) -> 1105.77 | D55: =SUM(D47:D54) -> 1218.29 | E55: =SUM(E47:E54) -> 1467.01 | F55: =SUM(F47:F54) -> 1979.14 | G55: =SUM(G47:G54) -> 2212.16 | P55: Lease liabilities | Q55: 63.87 | R55: 54.06 | S55: 50.18 | T55: 53.86 | U55: 61.54 | V55: 56.07 | X55: Other current liabilities | Y55: 2206 | Z55: 2013 | AA55: 2523 | AB55: 3517 | AC55: 4092 | AD55: 4441 | AF55: Other current liabilities | AG55: 41.28 | AH55: 46.17 | AI55: 71.9 | AJ55: 118.44 | AK55: 150.05 | AL55: 172.6 | AN55: Total equity and liabilities | AO55: =AO35+AO54 -> 8458.191 | AP55: =AP35+AP54 -> 9568.288 | AQ55: =AQ35+AQ54 -> 11594.666 | AR55: =AR35+AR54 -> 15187.183 | AS55: =AS35+AS54 -> 23143.91
A56: Total equity and Liabilities | B56: =B35+B44+B55 -> 12076.45 | C56: =C35+C44+C55 -> 13655.97 | D56: =D35+D44+D55 -> 15472.64 | E56: =E35+E44+E55 -> 18106.29 | F56: =F35+F44+F55 -> 21177.2 | G56: =G35+G44+G55 -> 24320.29 | P56: Other financial liabilities | Q56: 1394.88 | R56: 1491.85 | S56: 1812.85 | T56: 2407.71 | U56: 2179 | V56: 1921.5 | X56: Provisions | Y56: 120 | Z56: 30 | AA56: 38 | AB56: 132 | AC56: 100 | AD56: 155 | AF56: Provisions | AG56: 7.23 | AH56: 6.45 | AI56: 9.59 | AJ56: 12.42 | AK56: 18.71 | AL56: 27.08
P57: Other current liabilities | Q57: 4072.72 | R57: 4294.4 | S57: 5116.03 | T57: 5571.35 | U57: 5594.72 | V57: 6148.27 | X57: Current tax liabilities (net) | Y57: 9 | Z57: 80 | AA57: 82 | AB57: 73 | AC57: 63 | AD57: 40 | AF57: Current tax liabilities (net) | AG57: 2.07 | AH57: 2.77 | AI57: 6.03 | AJ57: 2.44 | AK57: 29.95 | AL57: 3.72
A58: Trade Payables | B58: =B49+B50 -> 433.45 | C58: =C49+C50 -> 578.13 | D58: =D49+D50 -> 589.2 | E58: =E49+E50 -> 753.79 | F58: =F49+F50 -> 984.81 | G58: =G49+G50 -> 1070.81 | P58: Provisions | Q58: 148.18 | R58: 194.01 | S58: 79.56 | T58: 100.56 | U58: 106.91 | V58: 80.06 | X58: Total current liabilities | Y58: =SUM(Y49:Y57) -> 5628 | Z58: =SUM(Z49:Z57) -> 7714 | AA58: =SUM(AA49:AA57) -> 10512 | AB58: =SUM(AB49:AB57) -> 13264 | AC58: =SUM(AC49:AC57) -> 16529 | AD58: =SUM(AD49:AD57) -> 25793 | AF58: Total current liabilities | AG58: =SUM(AG51:AG57) -> 487.27 | AH58: =SUM(AH51:AH57) -> 751.44 | AI58: =SUM(AI51:AI57) -> 653.45 | AJ58: =SUM(AJ51:AJ57) -> 1093.98 | AK58: =SUM(AK51:AK57) -> 1541.47 | AL58: =SUM(AL51:AL57) -> 2010.69
A59: Other non-current assets | B59: =B6+B7+B8+B12+B14+B16 -> 4514.32 | C59: =C6+C7+C8+C12+C14+C16 -> 3554.93 | D59: =D6+D7+D8+D12+D14+D16 -> 4165.78 | E59: =E6+E7+E8+E12+E14+E16 -> 2829.36 | F59: =F6+F7+F8+F12+F14+F16 -> 2867.88 | G59: =G6+G7+G8+G12+G14+G16 -> 3295.38 | P59: Current tax liabilities (net) | Q59: 248.87 | R59: 332.75 | S59: 687.09 | T59: 911.62 | U59: 940.88 | V59: 1229.65 | X59: Total equity and liabilities | Y59: =Y37+Y46+Y58 -> 13550 | Z59: =Z37+Z46+Z58 -> 16452 | AA59: =AA37+AA46+AA58 -> 21194 | AB59: =AB37+AB46+AB58 -> 27023 | AC59: =AC37+AC46+AC58 -> 31550 | AD59: =AD37+AD46+AD58 -> 40647 | AF59: Total liabilities | AG59: =AG48+AG58 -> 3039.32 | AH59: =AH48+AH58 -> 3366.21 | AI59: =AI48+AI58 -> 5316.08 | AJ59: =AJ48+AJ58 -> 5418.56 | AK59: =AK48+AK58 -> 3059.16 | AL59: =AL48+AL58 -> 3836.28
C60: =(C59-B59)/B59 -> -0.21252149 | D60: =(D59-C59)/C59 -> 0.17183179 | E60: =(E59-D59)/D59 -> -0.32080907 | F60: =(F59-E59)/E59 -> 0.013614386 | G60: =(G59-F59)/F59 -> 0.14906481 | P60: Total current liabilities | Q60: =SUM(Q52:Q59) -> 9559.77 | R60: =SUM(R52:R59) -> 10689.68 | S60: =SUM(S52:S59) -> 12163.71 | T60: =SUM(T52:T59) -> 13739.41 | U60: =SUM(U52:U59) -> 13690.4 | V60: =SUM(V52:V59) -> 14334.11 | AF60: Total equity and liabilities | AG60: =AG39+AG59 -> 5506.68 | AH60: =AH39+AH59 -> 5723.73 | AI60: =AI39+AI59 -> 7726.02 | AJ60: =AJ39+AJ59 -> 8081.53 | AK60: =AK39+AK59 -> 7161.75 | AL60: =AL39+AL59 -> 9419.64
C61: =AVERAGE(C60:G60) -> -0.039763912 | P61: Total equity and liabilities | Q61: =Q40+Q49+Q60 -> 77367.04 | R61: =R40+R49+R60 -> 73819.3 | S61: =S40+S49+S60 -> 77259.55 | T61: =T40+T49+T60 -> 85882.98 | U61: =U40+U49+U60 -> 91826.16 | V61: =V40+V49+V60 -> 88090.68
A62: Other current assets | B62: =B24+B25+B26+B21 -> 274.85 | C62: =C24+C25+C26+C21 -> 1577.77 | D62: =D24+D25+D26+D21 -> 538.18 | E62: =E24+E25+E26+E21 -> 1935.6 | F62: =F24+F25+F26+F21 -> 1771.23 | G62: =G24+G25+G26+G21 -> 838.56
A63: Revenue | B63: ='Income Statement'!B4 -> 24870.2 | C63: ='Income Statement'!C4 -> 24143.06 | D63: ='Income Statement'!D4 -> 30976.27 | E63: ='Income Statement'!E4 -> 42839.56 | F63: ='Income Statement'!F4 -> 50788.83 | G63: ='Income Statement'!G4 -> 59358.05
A64: Ratio | B64: =B62/B63 -> 0.011051379 | C64: =C62/C63 -> 0.065350871 | D64: =D62/D63 -> 0.017373945 | E64: =E62/E63 -> 0.045182537 | F64: =F62/F63 -> 0.034874401 | G64: =G62/G63 -> 0.014127149
A65: Average | B65: =AVERAGE(B64:G64) -> 0.031326713

Sheet Common Size Balance Sheet
A1: Common Size Balance Sheet | F1: #VALUE! | I1: Common Size Balance Sheet | M1: #VALUE! | P1: Common Size Balance Sheet | U1: #VALUE! | X1: Common Size Balance Sheet | AC1: #VALUE! | AF1: Common Size Balance Sheet | AK1: #VALUE! | AN1: Common Size Balance Sheet | AR1: #VALUE!
A2: Particulars | B2: 2020 | C2: 2021 | D2: 2022 | E2: 2023 | F2: 2024 | G2: 2025 | I2: Particulars | J2: 2020 | K2: 2021 | L2: 2022 | M2: 2023 | N2: 2024 | P2: Particulars | Q2: 2020 | R2: 2021 | S2: 2022 | T2: 2023 | U2: 2024 | V2: 2025 | X2: Particulars | Y2: 2020 | Z2: 2021 | AA2: 2022 | AB2: 2023 | AC2: 2024 | AD2: 2025 | AF2: Particulars | AG2: 2020 | AH2: 2021 | AI2: 2022 | AJ2: 2023 | AK2: 2024 | AL2: 2025 | AN2: Particulars | AO2: 2020 | AP2: 2021 | AQ2: 2022 | AR2: 2023 | AS2: 2024
A3: Assets | I3: Assets | P3: Assets | X3: Assets | AF3: Assets | AN3: Assets
A4: Property, plant and Equipment | B4: ='Balance Sheet'!B5/'Balance Sheet'!B28 -> 0.42291899 | C4: ='Balance Sheet'!C5/'Balance Sheet'!C28 -> 0.43486475 | D4: ='Balance Sheet'!D5/'Balance Sheet'!D28 -> 0.50220648 | E4: ='Balance Sheet'!E5/'Balance Sheet'!E28 -> 0.53713096 | F4: ='Balance Sheet'!F5/'Balance Sheet'!F28 -> 0.55527596 | G4: ='Balance Sheet'!G5/'Balance Sheet'!G28 -> 0.59003532 | I4: Property, plant and Equipment | J4: ='Balance Sheet'!J5/'Balance Sheet'!J29 -> 0.2250255 | K4: ='Balance Sheet'!K5/'Balance Sheet'!K29 -> 0.2461172 | L4: ='Balance Sheet'!L5/'Balance Sheet'!L29 -> 0.088950943 | M4: ='Balance Sheet'!M5/'Balance Sheet'!M29 -> 0.087482451 | N4: ='Balance Sheet'!N5/'Balance Sheet'!N29 -> 0.10230704 | P4: Property, plant and Equipment | Q4: ='Balance Sheet'!Q5/'Balance Sheet'!Q33 -> 0.25376467 | R4: ='Balance Sheet'!R5/'Balance Sheet'!R33 -> 0.25947063 | S4: ='Balance Sheet'!S5/'Balance Sheet'!S33 -> 0.26155252 | T4: ='Balance Sheet'!T5/'Balance Sheet'!T33 -> 0.24588184 | U4: ='Balance Sheet'!U5/'Balance Sheet'!U33 -> 0.25136987 | V4: ='Balance Sheet'!V5/'Balance Sheet'!V33 -> 0.19785169 | X4: Property, plant and Equipment | Y4: ='Balance Sheet'!Y5/'Balance Sheet'!Y30 -> 0.094833948 | Z4: ='Balance Sheet'!Z5/'Balance Sheet'!Z30 -> 0.073911986 | AA4: ='Balance Sheet'!AA5/'Balance Sheet'!AA30 -> 0.057469095 | AB4: ='Balance Sheet'!AB5/'Balance Sheet'!AB30 -> 0.049698405 | AC4: ='Balance Sheet'!AC5/'Balance Sheet'!AC30 -> 0.055055468 | AD4: ='Balance Sheet'!AD5/'Balance Sheet'!AD30 -> 0.045612222 | AF4: Property, plant and Equipment | AG4: ='Balance Sheet'!AG5/'Balance Sheet'!AG32 -> 0.11888107 | AH4: ='Balance Sheet'!AH5/'Balance Sheet'!AH32 -> 0.11189382 | AI4: ='Balance Sheet'!AI5/'Balance Sheet'!AI32 -> 0.093830976 | AJ4: ='Balance Sheet'!AJ5/'Balance Sheet'!AJ32 -> 0.10779889 | AK4: ='Balance Sheet'!AK5/'Balance Sheet'!AK32 -> 0.16006144 | AL4: ='Balance Sheet'!AL5/'Balance Sheet'!AL32 -> 0.21956678 | AN4: Property, plant and Equipment | AO4: ='Balance Sheet'!AO5/'Balance Sheet'!AO28 -> 0.68892459 | AP4: ='Balance Sheet'!AP5/'Balance Sheet'!AP28 -> 0.53801202 | AQ4: ='Balance Sheet'!AQ5/'Balance Sheet'!AQ28 -> 0.46836497 | AR4: ='Balance Sheet'!AR5/'Balance Sheet'!AR28 -> 0.4479522 | AS4: ='Balance Sheet'!AS5/'Balance Sheet'!AS28 -> 0.45897824
A5: Rights of use assets | B5: ='Balance Sheet'!B7/'Balance Sheet'!B28 -> 0.059399078 | C5: ='Balance Sheet'!C7/'Balance Sheet'!C28 -> 0.070316499 | D5: ='Balance Sheet'!D7/'Balance Sheet'!D28 -> 0.089748744 | E5: ='Balance Sheet'!E7/'Balance Sheet'!E28 -> 0.083112281 | F5: ='Balance Sheet'!F7/'Balance Sheet'!F28 -> 0.072677219 | G5: ='Balance Sheet'!G7/'Balance Sheet'!G28 -> 0.071616334 | I5: Rights of use assets | J5: 0 | K5: 1 | L5: 2 | M5: 3 | N5: 4 | P5: Rights of use assets | Q5: ='Balance Sheet'!Q11/'Balance Sheet'!Q33 -> 0.012500995 | R5: ='Balance Sheet'!R11/'Balance Sheet'!R33 -> 0.013237595 | S5: ='Balance Sheet'!S11/'Balance Sheet'!S33 -> 0.011223596 | T5: ='Balance Sheet'!T11/'Balance Sheet'!T33 -> 0.010186887 | U5: ='Balance Sheet'!U11/'Balance Sheet'!U33 -> 0.010227151 | V5: ='Balance Sheet'!V11/'Balance Sheet'!V33 -> 0.0066055796 | X5: Rights of use assets | Y5: ='Balance Sheet'!Y7/'Balance Sheet'!Y30 -> 0.06900369 | Z5: ='Balance Sheet'!Z7/'Balance Sheet'!Z30 -> 0.055737904 | AA5: ='Balance Sheet'!AA7/'Balance Sheet'!AA30 -> 0.04590922 | AB5: ='Balance Sheet'!AB7/'Balance Sheet'!AB30 -> 0.047552085 | AC5: ='Balance Sheet'!AC7/'Balance Sheet'!AC30 -> 0.048906498 | AD5: ='Balance Sheet'!AD7/'Balance Sheet'!AD30 -> 0.043644057 | AF5: Rights of use assets | AG5: ='Balance Sheet'!AG10/'Balance Sheet'!AG32 -> 0.36057479 | AH5: ='Balance Sheet'!AH10/'Balance Sheet'!AH32 -> 0.40506628 | AI5: ='Balance Sheet'!AI10/'Balance Sheet'!AI32 -> 0.50015532 | AJ5: ='Balance Sheet'!AJ10/'Balance Sheet'!AJ32 -> 0.43930295 | AK5: ='Balance Sheet'!AK10/'Balance Sheet'!AK32 -> 0.16785423 | AL5: ='Balance Sheet'!AL10/'Balance Sheet'!AL32 -> 0.1833138 | AN5: Rights of use assets | AO5: ='Balance Sheet'!AO7/'Balance Sheet'!AO28 -> 0 | AP5: ='Balance Sheet'!AP7/'Balance Sheet'!AP28 -> 0.059779334 | AQ5: ='Balance Sheet'!AQ7/'Balance Sheet'!AQ28 -> 0.078798576 | AR5: ='Balance Sheet'!AR7/'Balance Sheet'!AR28 -> 0.068130278 | AS5: ='Balance Sheet'!AS7/'Balance Sheet'!AS28 -> 0.058897654
A6: Intangible assets | B6: ='Balance Sheet'!B10/'Balance Sheet'!B28 -> 0.0023632773 | C6: ='Balance Sheet'!C10/'Balance Sheet'!C28 -> 0.0016271272 | D6: ='Balance Sheet'!D10/'Balance Sheet'!D28 -> 0.00087961718 | E6: ='Balance Sheet'!E10/'Balance Sheet'!E28 -> 0.0012801969 | F6: ='Balance Sheet'!F10/'Balance Sheet'!F28 -> 0.0014331451 | G6: ='Balance Sheet'!G10/'Balance Sheet'!G28 -> 0.0011915976 | I6: Intangible assets | J6: ='Balance Sheet'!J8/'Balance Sheet'!J29 -> 0.021793977 | K6: ='Balance Sheet'!K8/'Balance Sheet'!K29 -> 0.019947402 | L6: ='Balance Sheet'!L8/'Balance Sheet'!L29 -> 0.40621319 | M6: ='Balance Sheet'!M8/'Balance Sheet'!M29 -> 0.39574854 | N6: ='Balance Sheet'!N8/'Balance Sheet'!N29 -> 0.35983898 | P6: Intangible assets | Q6: =('Balance Sheet'!Q9+'Balance Sheet'!Q10)/'Balance Sheet'!Q33 -> 0.0068533414 | R6: =('Balance Sheet'!R9+'Balance Sheet'!R10)/'Balance Sheet'!R33 -> 0.02733567 | S6: =('Balance Sheet'!S9+'Balance Sheet'!S10)/'Balance Sheet'!S33 -> 0.026406962 | T6: =('Balance Sheet'!T9+'Balance Sheet'!T10)/'Balance Sheet'!T33 -> 0.031972699 | U6: =('Balance Sheet'!U9+'Balance Sheet'!U10)/'Balance Sheet'!U33 -> 0.029269981 | V6: =('Balance Sheet'!V9+'Balance Sheet'!V10)/'Balance Sheet'!V33 -> 0.030968656 | X6: Intangible assets | Y6: =('Balance Sheet'!Y10+'Balance Sheet'!Y11)/'Balance Sheet'!Y30 -> 0.020147601 | Z6: =('Balance Sheet'!Z10+'Balance Sheet'!Z11)/'Balance Sheet'!Z30 -> 0.015560418 | AA6: =('Balance Sheet'!AA10+'Balance Sheet'!AA11)/'Balance Sheet'!AA30 -> 0.011559875 | AB6: =('Balance Sheet'!AB10+'Balance Sheet'!AB11)/'Balance Sheet'!AB30 -> 0.0095104171 | AC6: =('Balance Sheet'!AC10+'Balance Sheet'!AC11)/'Balance Sheet'!AC30 -> 0.0099524564 | AD6: =('Balance Sheet'!AD10+'Balance Sheet'!AD11)/'Balance Sheet'!AD30 -> 0.0079218639 | AF6: Intangible assets | AG6: =('Balance Sheet'!AG9)/'Balance Sheet'!AG32 -> 0.0076761315 | AH6: =('Balance Sheet'!AH9)/'Balance Sheet'!AH32 -> 0.0069150711 | AI6: =('Balance Sheet'!AI9)/'Balance Sheet'!AI32 -> 0.0055047748 | AJ6: =('Balance Sheet'!AJ9)/'Balance Sheet'!AJ32 -> 0.0063366714 | AK6: =('Balance Sheet'!AK9)/'Balance Sheet'!AK32 -> 0.0066143052 | AL6: =('Balance Sheet'!AL9)/'Balance Sheet'!AL32 -> 0.0048929683 | AN6: Intangible assets | AO6: ='Balance Sheet'!AO9/'Balance Sheet'!AO28 -> 0.065875593 | AP6: ='Balance Sheet'!AP9/'Balance Sheet'!AP28 -> 0.058294762 | AQ6: ='Balance Sheet'!AQ9/'Balance Sheet'!AQ28 -> 0.047417669 | AR6: ='Balance Sheet'!AR9/'Balance Sheet'!AR28 -> 0.036023797 | AS6: ='Balance Sheet'!AS9/'Balance Sheet'!AS28 -> 0.048182265
A7: Non-current investments | B7: ='Balance Sheet'!B13/'Balance Sheet'!B28 -> 0 | C7: ='Balance Sheet'!C13/'Balance Sheet'!C28 -> 0 | D7: ='Balance Sheet'!D13/'Balance Sheet'!D28 -> 6.4630212e-07 | E7: ='Balance Sheet'!E13/'Balance Sheet'!E28 -> 5.5228511e-07 | F7: ='Balance Sheet'!F13/'Balance Sheet'!F28 -> 0.011085507 | G7: ='Balance Sheet'!G13/'Balance Sheet'!G28 -> 0.0069127465 | I7: Non-current investments | J7: ='Balance Sheet'!J11/'Balance Sheet'!J29 -> 0.00010735949 | K7: ='Balance Sheet'!K11/'Balance Sheet'!K29 -> 9.9240808e-05 | L7: ='Balance Sheet'!L11/'Balance Sheet'!L29 -> 2.9087947e-05 | M7: ='Balance Sheet'!M11/'Balance Sheet'!M29 -> 2.8361955e-05 | N7: ='Balance Sheet'!N11/'Balance Sheet'!N29 -> 2.5478032e-05 | P7: Non-current investments | Q7: ='Balance Sheet'!Q14/'Balance Sheet'!Q33 -> 0.13505123 | R7: ='Balance Sheet'!R14/'Balance Sheet'!R33 -> 0.1322417 | S7: ='Balance Sheet'!S14/'Balance Sheet'!S33 -> 0.15930057 | T7: ='Balance Sheet'!T14/'Balance Sheet'!T33 -> 0.13791525 | U7: ='Balance Sheet'!U14/'Balance Sheet'!U33 -> 0.1918829 | V7: ='Balance Sheet'!V14/'Balance Sheet'!V33 -> 0.15575473 | X7: Non-current investments | Y7: ='Balance Sheet'!Y12/'Balance Sheet'!Y30 -> 0.0032472325 | Z7: ='Balance Sheet'!Z12/'Balance Sheet'!Z30 -> 0.0011548748 | AA7: ='Balance Sheet'!AA12/'Balance Sheet'!AA30 -> 0.013164103 | AB7: ='Balance Sheet'!AB12/'Balance Sheet'!AB30 -> 0.012988935 | AC7: ='Balance Sheet'!AC12/'Balance Sheet'!AC30 -> 0.021521395 | AD7: ='Balance Sheet'!AD12/'Balance Sheet'!AD30 -> 0.016015942 | AF7: Non-current investments | AG7: ='Balance Sheet'!AG11/'Balance Sheet'!AG32 -> 0.13363951 | AH7: ='Balance Sheet'!AH11/'Balance Sheet'!AH32 -> 0.14267444 | AI7: ='Balance Sheet'!AI11/'Balance Sheet'!AI32 -> 0.098031069 | AJ7: ='Balance Sheet'!AJ11/'Balance Sheet'!AJ32 -> 0.069804851 | AK7: ='Balance Sheet'!AK11/'Balance Sheet'!AK32 -> 0.097219255 | AL7: ='Balance Sheet'!AL11/'Balance Sheet'!AL32 -> 0.089765639 | AN7: Non-current investments | AO7: ='Balance Sheet'!AO12/'Balance Sheet'!AO28 -> 1.1822591e-07 | AP7: ='Balance Sheet'!AP12/'Balance Sheet'!AP28 -> 1.0436354e-07 | AQ7: ='Balance Sheet'!AQ12/'Balance Sheet'!AQ28 -> 8.6071534e-08 | AR7: ='Balance Sheet'!AR12/'Balance Sheet'!AR28 -> 0.00020747758 | AS7: ='Balance Sheet'!AS12/'Balance Sheet'!AS28 -> 0.0002616239
A8: Total non-current investments | B8: ='Balance Sheet'!B17/'Balance Sheet'!B28 -> 0.80559933 | C8: ='Balance Sheet'!C17/'Balance Sheet'!C28 -> 0.70261139 | D8: ='Balance Sheet'!D17/'Balance Sheet'!D28 -> 0.77748788 | E8: ='Balance Sheet'!E17/'Balance Sheet'!E28 -> 0.69909353 | F8: ='Balance Sheet'!F17/'Balance Sheet'!F28 -> 0.70713645 | G8: ='Balance Sheet'!G17/'Balance Sheet'!G28 -> 0.73716596 | I8: Total non-current assets | J8: ='Balance Sheet'!J17/'Balance Sheet'!J29 -> 0.3604595 | K8: ='Balance Sheet'!K17/'Balance Sheet'!K29 -> 0.388627 | L8: ='Balance Sheet'!L17/'Balance Sheet'!L29 -> 0.79322833 | M8: ='Balance Sheet'!M17/'Balance Sheet'!M29 -> 0.77988287 | N8: ='Balance Sheet'!N17/'Balance Sheet'!N29 -> 0.72835323 | P8: Total non-current assets | Q8: ='Balance Sheet'!Q20/'Balance Sheet'!Q33 -> 0.48937488 | R8: ='Balance Sheet'!R20/'Balance Sheet'!R33 -> 0.52597776 | S8: ='Balance Sheet'!S20/'Balance Sheet'!S33 -> 0.55691626 | T8: ='Balance Sheet'!T20/'Balance Sheet'!T33 -> 0.53808194 | U8: ='Balance Sheet'!U20/'Balance Sheet'!U33 -> 0.5527904 | V8: ='Balance Sheet'!V20/'Balance Sheet'!V33 -> 0.50172618 | X8: Total non-current assets | Y8: ='Balance Sheet'!Y18/'Balance Sheet'!Y30 -> 0.25306273 | Z8: ='Balance Sheet'!Z18/'Balance Sheet'!Z30 -> 0.19784829 | AA8: ='Balance Sheet'!AA18/'Balance Sheet'!AA30 -> 0.17646504 | AB8: ='Balance Sheet'!AB18/'Balance Sheet'!AB30 -> 0.17081745 | AC8: ='Balance Sheet'!AC18/'Balance Sheet'!AC30 -> 0.18833597 | AD8: ='Balance Sheet'!AD18/'Balance Sheet'!AD30 -> 0.15285261 | AF8: Total non-current assets | AG8: ='Balance Sheet'!AG16/'Balance Sheet'!AG32 -> 0.69065571 | AH8: ='Balance Sheet'!AH16/'Balance Sheet'!AH32 -> 0.75481897 | AI8: ='Balance Sheet'!AI16/'Balance Sheet'!AI32 -> 0.76916187 | AJ8: ='Balance Sheet'!AJ16/'Balance Sheet'!AJ32 -> 0.70577601 | AK8: ='Balance Sheet'!AK16/'Balance Sheet'!AK32 -> 0.56576954 | AL8: ='Balance Sheet'!AL16/'Balance Sheet'!AL32 -> 0.61002225 | AN8: Total non-current assets | AO8: ='Balance Sheet'!AO17/'Balance Sheet'!AO28 -> 0.78723167 | AP8: ='Balance Sheet'!AP17/'Balance Sheet'!AP28 -> 0.73427862 | AQ8: ='Balance Sheet'!AQ17/'Balance Sheet'!AQ28 -> 0.70700992 | AR8: ='Balance Sheet'!AR17/'Balance Sheet'!AR28 -> 0.72110496 | AS8: ='Balance Sheet'!AS17/'Balance Sheet'!AS28 -> 0.66021411
A9: Inventories | B9: ='Balance Sheet'!B19/'Balance Sheet'!B28 -> 0.161256 | C9: ='Balance Sheet'!C19/'Balance Sheet'!C28 -> 0.16463715 | D9: ='Balance Sheet'!D19/'Balance Sheet'!D28 -> 0.1772587 | E9: ='Balance Sheet'!E19/'Balance Sheet'!E28 -> 0.17913257 | F9: ='Balance Sheet'!F19/'Balance Sheet'!F28 -> 0.18544992 | G9: ='Balance Sheet'!G19/'Balance Sheet'!G28 -> 0.20741406 | I9: Inventories | J9: ='Balance Sheet'!J19/'Balance Sheet'!J29 -> 0.13817167 | K9: ='Balance Sheet'!K19/'Balance Sheet'!K29 -> 0.13729966 | L9: ='Balance Sheet'!L19/'Balance Sheet'!L29 -> 0.052052882 | M9: ='Balance Sheet'!M19/'Balance Sheet'!M29 -> 0.058085284 | N9: ='Balance Sheet'!N19/'Balance Sheet'!N29 -> 0.051236321 | P9: Inventories | Q9: ='Balance Sheet'!Q22/'Balance Sheet'!Q33 -> 0.11476949 | R9: ='Balance Sheet'!R22/'Balance Sheet'!R33 -> 0.14084609 | S9: ='Balance Sheet'!S22/'Balance Sheet'!S33 -> 0.14061886 | T9: ='Balance Sheet'!T22/'Balance Sheet'!T33 -> 0.13706048 | U9: ='Balance Sheet'!U22/'Balance Sheet'!U33 -> 0.15412688 | V9: ='Balance Sheet'!V22/'Balance Sheet'!V33 -> 0.17751662 | X9: Inventories | Y9: ='Balance Sheet'!Y20/'Balance Sheet'!Y30 -> 0.59800738 | Z9: ='Balance Sheet'!Z20/'Balance Sheet'!Z30 -> 0.51106248 | AA9: ='Balance Sheet'!AA20/'Balance Sheet'!AA30 -> 0.64211569 | AB9: ='Balance Sheet'!AB20/'Balance Sheet'!AB30 -> 0.61369944 | AC9: ='Balance Sheet'!AC20/'Balance Sheet'!AC30 -> 0.60383518 | AD9: ='Balance Sheet'!AD20/'Balance Sheet'!AD30 -> 0.69338451 | AF9: Inventories | AG9: ='Balance Sheet'!AG18/'Balance Sheet'!AG32 -> 0.11037685 | AH9: ='Balance Sheet'!AH18/'Balance Sheet'!AH32 -> 0.074844551 | AI9: ='Balance Sheet'!AI18/'Balance Sheet'!AI32 -> 0.11231915 | AJ9: ='Balance Sheet'!AJ18/'Balance Sheet'!AJ32 -> 0.1684285 | AK9: ='Balance Sheet'!AK18/'Balance Sheet'!AK32 -> 0.22099766 | AL9: ='Balance Sheet'!AL18/'Balance Sheet'!AL32 -> 0.2171049 | AN9: Inventories | AO9: ='Balance Sheet'!AO19/'Balance Sheet'!AO28 -> 0.1098087 | AP9: ='Balance Sheet'!AP19/'Balance Sheet'!AP28 -> 0.15112749 | AQ9: ='Balance Sheet'!AQ19/'Balance Sheet'!AQ28 -> 0.17161674 | AR9: ='Balance Sheet'!AR19/'Balance Sheet'!AR28 -> 0.14160184 | AS9: ='Balance Sheet'!AS19/'Balance Sheet'!AS28 -> 0.12060339
A10: Trade receivables | B10: ='Balance Sheet'!B22/'Balance Sheet'!B28 -> 0.0016188532 | C10: ='Balance Sheet'!C22/'Balance Sheet'!C28 -> 0.0031912782 | D10: ='Balance Sheet'!D22/'Balance Sheet'!D28 -> 0.0043231149 | E10: ='Balance Sheet'!E22/'Balance Sheet'!E28 -> 0.0034330042 | F10: ='Balance Sheet'!F22/'Balance Sheet'!F28 -> 0.0078560905 | G10: ='Balance Sheet'!G22/'Balance Sheet'!G28 -> 0.0063235266 | I10: Trade receivables | J10: ='Balance Sheet'!J22/'Balance Sheet'!J29 -> 0.09748242 | K10: ='Balance Sheet'!K22/'Balance Sheet'!K29 -> 0.057013844 | L10: ='Balance Sheet'!L22/'Balance Sheet'!L29 -> 0.025568306 | M10: ='Balance Sheet'!M22/'Balance Sheet'!M29 -> 0.031708666 | N10: ='Balance Sheet'!N22/'Balance Sheet'!N29 -> 0.03817883 | P10: Trade receivables | Q10: =('Balance Sheet'!Q26)/'Balance Sheet'!Q33 -> 0.033121252 | R10: =('Balance Sheet'!R26)/'Balance Sheet'!R33 -> 0.033889511 | S10: =('Balance Sheet'!S26)/'Balance Sheet'!S33 -> 0.031865316 | T10: =('Balance Sheet'!T26)/'Balance Sheet'!T33 -> 0.034420914 | U10: =('Balance Sheet'!U26)/'Balance Sheet'!U33 -> 0.043841755 | V10: =('Balance Sheet'!V26)/'Balance Sheet'!V33 -> 0.053577405 | X10: Trade receivables | Y10: ='Balance Sheet'!Y22/'Balance Sheet'!Y30 -> 0.02302583 | Z10: ='Balance Sheet'!Z22/'Balance Sheet'!Z30 -> 0.022246535 | AA10: ='Balance Sheet'!AA22/'Balance Sheet'!AA30 -> 0.026658488 | AB10: ='Balance Sheet'!AB22/'Balance Sheet'!AB30 -> 0.024941716 | AC10: ='Balance Sheet'!AC22/'Balance Sheet'!AC30 -> 0.032266244 | AD10: ='Balance Sheet'!AD22/'Balance Sheet'!AD30 -> 0.026275002 | AF10: Trade receivables | AG10: ='Balance Sheet'!AG20/'Balance Sheet'!AG32 -> 0.0031089513 | AH10: ='Balance Sheet'!AH20/'Balance Sheet'!AH32 -> 0.0036287526 | AI10: ='Balance Sheet'!AI20/'Balance Sheet'!AI32 -> 0.002363442 | AJ10: ='Balance Sheet'!AJ20/'Balance Sheet'!AJ32 -> 0.0042553823 | AK10: ='Balance Sheet'!AK20/'Balance Sheet'!AK32 -> 0.011413412 | AL10: ='Balance Sheet'!AL20/'Balance Sheet'!AL32 -> 0.0066828456 | AN10: Trade receivables | AO10: ='Balance Sheet'!AO20/'Balance Sheet'!AO28 -> 0.02858667 | AP10: ='Balance Sheet'!AP20/'Balance Sheet'!AP28 -> 0.02309033 | AQ10: ='Balance Sheet'!AQ20/'Balance Sheet'!AQ28 -> 0.025764481 | AR10: ='Balance Sheet'!AR20/'Balance Sheet'!AR28 -> 0.023663704 | AS10: ='Balance Sheet'!AS20/'Balance Sheet'!AS28 -> 0.036547066
A11: Cash and bank balances | B11: =('Balance Sheet'!B23+'Balance Sheet'!B24)/'Balance Sheet'!B28 -> 0.0089330888 | C11: =('Balance Sheet'!C23+'Balance Sheet'!C24)/'Balance Sheet'!C28 -> 0.105857 | D11: =('Balance Sheet'!D23+'Balance Sheet'!D24)/'Balance Sheet'!D28 -> 0.019297289 | E11: =('Balance Sheet'!E23+'Balance Sheet'!E24)/'Balance Sheet'!E28 -> 0.077779969 | F11: =('Balance Sheet'!F23+'Balance Sheet'!F24)/'Balance Sheet'!F28 -> 0.03013524 | G11: =('Balance Sheet'!G23+'Balance Sheet'!G24)/'Balance Sheet'!G28 -> 0.014728443 | I11: Cash and bank balances | J11: =('Balance Sheet'!J23+'Balance Sheet'!J24)/'Balance Sheet'!J29 -> 0.20167481 | K11: =('Balance Sheet'!K23+'Balance Sheet'!K24)/'Balance Sheet'!K29 -> 0.25370913 | L11: =('Balance Sheet'!L23+'Balance Sheet'!L24)/'Balance Sheet'!L29 -> 0.065026106 | M11: =('Balance Sheet'!M23+'Balance Sheet'!M24)/'Balance Sheet'!M29 -> 0.05454004 | N11: =('Balance Sheet'!N23+'Balance Sheet'!N24)/'Balance Sheet'!N29 -> 0.09629422 | P11: Cash and bank balances | Q11: =('Balance Sheet'!Q27+'Balance Sheet'!Q28)/'Balance Sheet'!Q33 -> 0.094063023 | R11: =('Balance Sheet'!R27+'Balance Sheet'!R28)/'Balance Sheet'!R33 -> 0.063113847 | S11: =('Balance Sheet'!S27+'Balance Sheet'!S28)/'Balance Sheet'!S33 -> 0.060243944 | T11: =('Balance Sheet'!T27+'Balance Sheet'!T28)/'Balance Sheet'!T33 -> 0.056823728 | U11: =('Balance Sheet'!U27+'Balance Sheet'!U28)/'Balance Sheet'!U33 -> 0.078601566 | V11: =('Balance Sheet'!V27+'Balance Sheet'!V28)/'Balance Sheet'!V33 -> 0.045548065 | X11: Cash and bank balances | Y11: =('Balance Sheet'!Y23+'Balance Sheet'!Y24)/'Balance Sheet'!Y30 -> 0.028118081 | Z11: =('Balance Sheet'!Z23+'Balance Sheet'!Z24)/'Balance Sheet'!Z30 -> 0.034038415 | AA11: =('Balance Sheet'!AA23+'Balance Sheet'!AA24)/'Balance Sheet'!AA30 -> 0.074219119 | AB11: =('Balance Sheet'!AB23+'Balance Sheet'!AB24)/'Balance Sheet'!AB30 -> 0.049698405 | AC11: =('Balance Sheet'!AC23+'Balance Sheet'!AC24)/'Balance Sheet'!AC30 -> 0.04836767 | AD11: =('Balance Sheet'!AD23+'Balance Sheet'!AD24)/'Balance Sheet'!AD30 -> 0.038969666 | AF11: Cash and bank balances | AG11: =('Balance Sheet'!AG22+'Balance Sheet'!AG23)/'Balance Sheet'!AG32 -> 0.01115191 | AH11: =('Balance Sheet'!AH22+'Balance Sheet'!AH23)/'Balance Sheet'!AH32 -> 0.014233725 | AI11: =('Balance Sheet'!AI22+'Balance Sheet'!AI23)/'Balance Sheet'!AI32 -> 0.011127333 | AJ11: =('Balance Sheet'!AJ22+'Balance Sheet'!AJ23)/'Balance Sheet'!AJ32 -> 0.010678671 | AK11: =('Balance Sheet'!AK22+'Balance Sheet'!AK23)/'Balance Sheet'!AK32 -> 0.041548504 | AL11: =('Balance Sheet'!AL22+'Balance Sheet'!AL23)/'Balance Sheet'!AL32 -> 0.036077812 | AN11: Cash and bank balances | AO11: =('Balance Sheet'!AO21+'Balance Sheet'!AO22)/'Balance Sheet'!AO28 -> 0.022468834 | AP11: =('Balance Sheet'!AP21+'Balance Sheet'!AP22)/'Balance Sheet'!AP28 -> 0.035131065 | AQ11: =('Balance Sheet'!AQ21+'Balance Sheet'!AQ22)/'Balance Sheet'!AQ28 -> 0.024553368 | AR11: =('Balance Sheet'!AR21+'Balance Sheet'!AR22)/'Balance Sheet'!AR28 -> 0.030279611 | AS11: =('Balance Sheet'!AS21+'Balance Sheet'!AS22)/'Balance Sheet'!AS28 -> 0.10586171
A12: Other current assets | B12: ='Balance Sheet'!B26/'Balance Sheet'!B28 -> 0.012346344 | C12: ='Balance Sheet'!C26/'Balance Sheet'!C28 -> 0.011191442 | D12: ='Balance Sheet'!D26/'Balance Sheet'!D28 -> 0.013012001 | E12: ='Balance Sheet'!E26/'Balance Sheet'!E28 -> 0.011899535 | F12: ='Balance Sheet'!F26/'Balance Sheet'!F28 -> 0.011097784 | G12: ='Balance Sheet'!G26/'Balance Sheet'!G28 -> 0.012591544 | I12: Other current assets | J12: ='Balance Sheet'!J26/'Balance Sheet'!J29 -> 0.023619089 | K12: ='Balance Sheet'!K26/'Balance Sheet'!K29 -> 0.029821863 | L12: ='Balance Sheet'!L26/'Balance Sheet'!L29 -> 0.0072283549 | M12: ='Balance Sheet'!M26/'Balance Sheet'!M29 -> 0.0097565126 | N12: ='Balance Sheet'!N26/'Balance Sheet'!N29 -> 0.0090829183 | P12: Other current assets | Q12: ='Balance Sheet'!Q31/'Balance Sheet'!Q33 -> 0.011979323 | R12: ='Balance Sheet'!R31/'Balance Sheet'!R33 -> 0.014836635 | S12: ='Balance Sheet'!S31/'Balance Sheet'!S33 -> 0.016905095 | T12: ='Balance Sheet'!T31/'Balance Sheet'!T33 -> 0.018184632 | U12: ='Balance Sheet'!U31/'Balance Sheet'!U33 -> 0.015063137 | V12: ='Balance Sheet'!V31/'Balance Sheet'!V33 -> 0.015573157 | X12: Other current assets | Y12: ='Balance Sheet'!Y27/'Balance Sheet'!Y30 -> 0.051365314 | Z12: ='Balance Sheet'!Z27/'Balance Sheet'!Z30 -> 0.045708728 | AA12: ='Balance Sheet'!AA27/'Balance Sheet'!AA30 -> 0.046145135 | AB12: ='Balance Sheet'!AB27/'Balance Sheet'!AB30 -> 0.047663102 | AC12: ='Balance Sheet'!AC27/'Balance Sheet'!AC30 -> 0.054548336 | AD12: ='Balance Sheet'!AD27/'Balance Sheet'!AD30 -> 0.048146235 | AF12: Other current assets | AG12: ='Balance Sheet'!AG29/'Balance Sheet'!AG32 -> 0.01512345 | AH12: ='Balance Sheet'!AH29/'Balance Sheet'!AH32 -> 0.018524633 | AI12: ='Balance Sheet'!AI29/'Balance Sheet'!AI32 -> 0.019699664 | AJ12: ='Balance Sheet'!AJ29/'Balance Sheet'!AJ32 -> 0.023264159 | AK12: ='Balance Sheet'!AK29/'Balance Sheet'!AK32 -> 0.035414529 | AL12: ='Balance Sheet'!AL29/'Balance Sheet'!AL32 -> 0.042741549 | AN12: Other current assets | AO12: ='Balance Sheet'!AO26/'Balance Sheet'!AO28 -> 0.029767628 | AP12: ='Balance Sheet'!AP26/'Balance Sheet'!AP28 -> 0.030629865 | AQ12: ='Balance Sheet'!AQ26/'Balance Sheet'!AQ28 -> 0.036824329 | AR12: ='Balance Sheet'!AR26/'Balance Sheet'!AR28 -> 0.034681613 | AS12: ='Balance Sheet'!AS26/'Balance Sheet'!AS28 -> 0.040457987
A13: Total current assets | B13: ='Balance Sheet'!B27/'Balance Sheet'!B28 -> 0.19440067 | C13: ='Balance Sheet'!C27/'Balance Sheet'!C28 -> 0.29738861 | D13: ='Balance Sheet'!D27/'Balance Sheet'!D28 -> 0.22251212 | E13: ='Balance Sheet'!E27/'Balance Sheet'!E28 -> 0.30090647 | F13: ='Balance Sheet'!F27/'Balance Sheet'!F28 -> 0.29286355 | G13: ='Balance Sheet'!G27/'Balance Sheet'!G28 -> 0.26283404 | I13: Total current assets | J13: ='Balance Sheet'!J28/'Balance Sheet'!J29 -> 0.6395405 | K13: ='Balance Sheet'!K28/'Balance Sheet'!K29 -> 0.611373 | L13: ='Balance Sheet'!L28/'Balance Sheet'!L29 -> 0.20677167 | M13: ='Balance Sheet'!M28/'Balance Sheet'!M29 -> 0.22011713 | N13: ='Balance Sheet'!N28/'Balance Sheet'!N29 -> 0.27164677 | P13: Total current assets | Q13: ='Balance Sheet'!Q32/'Balance Sheet'!Q33 -> 0.51062512 | R13: ='Balance Sheet'!R32/'Balance Sheet'!R33 -> 0.47402224 | S13: ='Balance Sheet'!S32/'Balance Sheet'!S33 -> 0.44308374 | T13: ='Balance Sheet'!T32/'Balance Sheet'!T33 -> 0.46191806 | U13: ='Balance Sheet'!U32/'Balance Sheet'!U33 -> 0.4472096 | V13: ='Balance Sheet'!V32/'Balance Sheet'!V33 -> 0.49827382 | X13: Total current assets | Y13: ='Balance Sheet'!Y29/'Balance Sheet'!Y30 -> 0.74693727 | Z13: ='Balance Sheet'!Z29/'Balance Sheet'!Z30 -> 0.80215171 | AA13: ='Balance Sheet'!AA29/'Balance Sheet'!AA30 -> 0.82353496 | AB13: ='Balance Sheet'!AB29/'Balance Sheet'!AB30 -> 0.82918255 | AC13: ='Balance Sheet'!AC29/'Balance Sheet'!AC30 -> 0.81166403 | AD13: ='Balance Sheet'!AD29/'Balance Sheet'!AD30 -> 0.84714739 | AF13: Total current assets | AG13: ='Balance Sheet'!AG31/'Balance Sheet'!AG32 -> 0.30934429 | AH13: ='Balance Sheet'!AH31/'Balance Sheet'!AH32 -> 0.24518103 | AI13: ='Balance Sheet'!AI31/'Balance Sheet'!AI32 -> 0.23083813 | AJ13: ='Balance Sheet'!AJ31/'Balance Sheet'!AJ32 -> 0.29422399 | AK13: ='Balance Sheet'!AK31/'Balance Sheet'!AK32 -> 0.43423046 | AL13: ='Balance Sheet'!AL31/'Balance Sheet'!AL32 -> 0.38997775 | AN13: Total current assets | AO13: ='Balance Sheet'!AO27/'Balance Sheet'!AO28 -> 0.21276833 | AP13: ='Balance Sheet'!AP27/'Balance Sheet'!AP28 -> 0.26572138 | AQ13: ='Balance Sheet'!AQ27/'Balance Sheet'!AQ28 -> 0.29299008 | AR13: ='Balance Sheet'!AR27/'Balance Sheet'!AR28 -> 0.27889504 | AS13: ='Balance Sheet'!AS27/'Balance Sheet'!AS28 -> 0.33978589
A14: Total assets | B14: =B8+B13 -> 1 | C14: =C8+C13 -> 1 | D14: =D8+D13 -> 1 | E14: =E8+E13 -> 1 | F14: =F8+F13 -> 1 | G14: =G8+G13 -> 1 | I14: Total assets | J14: =J8+J13 -> 1 | K14: =K8+K13 -> 1 | L14: =L8+L13 -> 1 | M14: =M8+M13 -> 1 | N14: =N8+N13 -> 1 | P14: Total assets | Q14: =Q8+Q13 -> 1 | R14: =R8+R13 -> 1 | S14: =S8+S13 -> 1 | T14: =T8+T13 -> 1 | U14: =U8+U13 -> 1 | V14: =V8+V13 -> 1 | X14: Total assets | Y14: =Y8+Y13 -> 1 | Z14: =Z8+Z13 -> 1 | AA14: =AA8+AA13 -> 1 | AB14: =AB8+AB13 -> 1 | AC14: =AC8+AC13 -> 1 | AD14: =AD8+AD13 -> 1 | AF14: Total assets | AG14: =AG8+AG13 -> 1 | AH14: =AH8+AH13 -> 1 | AI14: =AI8+AI13 -> 1 | AJ14: =AJ8+AJ13 -> 1 | AK14: =AK8+AK13 -> 1 | AL14: =AL8+AL13 -> 1 | AN14: Total assets | AO14: =AO8+AO13 -> 1 | AP14: =AP8+AP13 -> 1 | AQ14: =AQ8+AQ13 -> 1 | AR14: =AR8+AR13 -> 1 | AS14: =AS8+AS13 -> 1
A15: Equity & Liabilities | I15: Equity & Liabilities | P15: Equity & Liabilities | X15: Equity & Liabilities | AF15: Equity & Liabilities | AN15: Equity & Liabilities
A16: Equity share capital | B16: ='Balance Sheet'!B31/'Balance Sheet'!B56 -> 0.053639108 | C16: ='Balance Sheet'!C31/'Balance Sheet'!C56 -> 0.047434931 | D16: ='Balance Sheet'!D31/'Balance Sheet'!D56 -> 0.041865512 | E16: ='Balance Sheet'!E31/'Balance Sheet'!E56 -> 0.035803028 | F16: ='Balance Sheet'!F31/'Balance Sheet'!F56 -> 0.030727858 | G16: ='Balance Sheet'!G31/'Balance Sheet'!G56 -> 0.026756671 | I16: Equity share capital | J16: ='Balance Sheet'!J32/'Balance Sheet'!J53 -> 0.011594825 | K16: ='Balance Sheet'!K32/'Balance Sheet'!K53 -> 0.010718007 | L16: ='Balance Sheet'!L32/'Balance Sheet'!L53 -> 0.0034178338 | M16: ='Balance Sheet'!M32/'Balance Sheet'!M53 -> 0.0033325297 | N16: ='Balance Sheet'!N32/'Balance Sheet'!N53 -> 0.0029936687 | P16: Equity share capital | Q16: ='Balance Sheet'!Q36/'Balance Sheet'!Q61 -> 0.015888161 | R16: ='Balance Sheet'!R36/'Balance Sheet'!R61 -> 0.01667423 | S16: ='Balance Sheet'!S36/'Balance Sheet'!S61 -> 0.01595052 | T16: ='Balance Sheet'!T36/'Balance Sheet'!T61 -> 0.014470853 | U16: ='Balance Sheet'!U36/'Balance Sheet'!U61 -> 0.013596017 | V16: ='Balance Sheet'!V36/'Balance Sheet'!V61 -> 0.01420593 | X16: Equity share capital | Y16: ='Balance Sheet'!Y33/'Balance Sheet'!Y59 -> 0.0065682657 | Z16: ='Balance Sheet'!Z33/'Balance Sheet'!Z59 -> 0.0054096766 | AA16: ='Balance Sheet'!AA33/'Balance Sheet'!AA59 -> 0.0041993017 | AB16: ='Balance Sheet'!AB33/'Balance Sheet'!AB59 -> 0.0032934907 | AC16: ='Balance Sheet'!AC33/'Balance Sheet'!AC59 -> 0.0028209192 | AD16: ='Balance Sheet'!AD33/'Balance Sheet'!AD59 -> 0.0021895835 | AF16: Equity share capital | AG16: ='Balance Sheet'!AG35/'Balance Sheet'!AG60 -> 0.0064557955 | AH16: ='Balance Sheet'!AH35/'Balance Sheet'!AH60 -> 0.0062109848 | AI16: ='Balance Sheet'!AI35/'Balance Sheet'!AI60 -> 0.0046013342 | AJ16: ='Balance Sheet'!AJ35/'Balance Sheet'!AJ60 -> 0.0043989195 | AK16: ='Balance Sheet'!AK35/'Balance Sheet'!AK60 -> 0.0049638706 | AL16: ='Balance Sheet'!AL35/'Balance Sheet'!AL60 -> 0.0037740296 | AN16: Equity share capital | AO16: ='Balance Sheet'!AO31/'Balance Sheet'!AO55 -> 0.034131294 | AP16: ='Balance Sheet'!AP31/'Balance Sheet'!AP55 -> 0.045257103 | AQ16: ='Balance Sheet'!AQ31/'Balance Sheet'!AQ55 -> 0.05602145 | AR16: ='Balance Sheet'!AR31/'Balance Sheet'!AR55 -> 0.04277337 | AS16: ='Balance Sheet'!AS31/'Balance Sheet'!AS55 -> 0.029221597
A17: Other equity | B17: ='Balance Sheet'!B32/'Balance Sheet'!B56 -> 0.86382753 | C17: ='Balance Sheet'!C32/'Balance Sheet'!C56 -> 0.84475435 | D17: ='Balance Sheet'!D32/'Balance Sheet'!D56 -> 0.84212326 | E17: ='Balance Sheet'!E32/'Balance Sheet'!E56 -> 0.85221434 | F17: ='Balance Sheet'!F32/'Balance Sheet'!F56 -> 0.85219434 | G17: ='Balance Sheet'!G32/'Balance Sheet'!G56 -> 0.85430807 | I17: Other equity | J17: =('Balance Sheet'!J33+'Balance Sheet'!J34)/'Balance Sheet'!J53 -> 0.41166998 | K17: =('Balance Sheet'!K33+'Balance Sheet'!K34)/'Balance Sheet'!K53 -> 0.39845184 | L17: =('Balance Sheet'!L33+'Balance Sheet'!L34)/'Balance Sheet'!L53 -> 0.69024245 | M17: =('Balance Sheet'!M33+'Balance Sheet'!M34)/'Balance Sheet'!M53 -> 0.69276912 | N17: =('Balance Sheet'!N33+'Balance Sheet'!N34)/'Balance Sheet'!N53 -> 0.65208474 | P17: Other equity | Q17: ='Balance Sheet'!Q37/'Balance Sheet'!Q61 -> 0.82779489 | R17: ='Balance Sheet'!R37/'Balance Sheet'!R61 -> 0.80082661 | S17: ='Balance Sheet'!S37/'Balance Sheet'!S61 -> 0.79243589 | T17: ='Balance Sheet'!T37/'Balance Sheet'!T61 -> 0.79075575 | U17: ='Balance Sheet'!U37/'Balance Sheet'!U61 -> 0.79779586 | V17: ='Balance Sheet'!V37/'Balance Sheet'!V61 -> 0.78077091 | X17: Other equity | Y17: ='Balance Sheet'!Y34/'Balance Sheet'!Y59 -> 0.48560886 | Z17: ='Balance Sheet'!Z34/'Balance Sheet'!Z59 -> 0.4502796 | AA17: ='Balance Sheet'!AA34/'Balance Sheet'!AA59 -> 0.43474568 | AB17: ='Balance Sheet'!AB34/'Balance Sheet'!AB59 -> 0.43525885 | AC17: ='Balance Sheet'!AC34/'Balance Sheet'!AC59 -> 0.29489699 | AD17: ='Balance Sheet'!AD34/'Balance Sheet'!AD59 -> 0.28378478 | AF17: Other equity | AG17: ='Balance Sheet'!AG36/'Balance Sheet'!AG60 -> 0.42715756 | AH17: ='Balance Sheet'!AH36/'Balance Sheet'!AH60 -> 0.39790137 | AI17: ='Balance Sheet'!AI36/'Balance Sheet'!AI60 -> 0.30137768 | AJ17: ='Balance Sheet'!AJ36/'Balance Sheet'!AJ60 -> 0.31676428 | AK17: ='Balance Sheet'!AK36/'Balance Sheet'!AK60 -> 0.56301742 | AL17: ='Balance Sheet'!AL36/'Balance Sheet'!AL60 -> 0.57605068 | AN17: Other equity | AO17: ='Balance Sheet'!AO32/'Balance Sheet'!AO55 -> 0.38248368 | AP17: ='Balance Sheet'!AP32/'Balance Sheet'!AP55 -> 0.38114185 | AQ17: ='Balance Sheet'!AQ32/'Balance Sheet'!AQ55 -> 0.38404125 | AR17: ='Balance Sheet'!AR32/'Balance Sheet'!AR55 -> 0.41396031 | AS17: ='Balance Sheet'!AS32/'Balance Sheet'!AS55 -> 0.68845441
A18: Total equity | B18: ='Balance Sheet'!B35/'Balance Sheet'!B56 -> 0.91750473 | C18: ='Balance Sheet'!C35/'Balance Sheet'!C56 -> 0.89221857 | D18: ='Balance Sheet'!D35/'Balance Sheet'!D56 -> 0.88400493 | E18: ='Balance Sheet'!E35/'Balance Sheet'!E56 -> 0.88802179 | F18: ='Balance Sheet'!F35/'Balance Sheet'!F56 -> 0.88289953 | G18: ='Balance Sheet'!G35/'Balance Sheet'!G56 -> 0.88102157 | I18: Total equity | J18: ='Balance Sheet'!J35/'Balance Sheet'!J53 -> 0.4232648 | K18: ='Balance Sheet'!K35/'Balance Sheet'!K53 -> 0.40916985 | L18: ='Balance Sheet'!L35/'Balance Sheet'!L53 -> 0.69366028 | M18: ='Balance Sheet'!M35/'Balance Sheet'!M53 -> 0.69610165 | N18: ='Balance Sheet'!N35/'Balance Sheet'!N53 -> 0.65507841 | P18: Total equity | Q18: ='Balance Sheet'!Q40/'Balance Sheet'!Q61 -> 0.848562 | R18: ='Balance Sheet'!R40/'Balance Sheet'!R61 -> 0.82219894 | S18: ='Balance Sheet'!S40/'Balance Sheet'!S61 -> 0.81312757 | T18: ='Balance Sheet'!T40/'Balance Sheet'!T61 -> 0.80969233 | U18: ='Balance Sheet'!U40/'Balance Sheet'!U61 -> 0.81556247 | V18: ='Balance Sheet'!V40/'Balance Sheet'!V61 -> 0.7991531 | X18: Total equity | Y18: ='Balance Sheet'!Y37/'Balance Sheet'!Y59 -> 0.49247232 | Z18: ='Balance Sheet'!Z37/'Balance Sheet'!Z59 -> 0.45599319 | AA18: ='Balance Sheet'!AA37/'Balance Sheet'!AA59 -> 0.44036048 | AB18: ='Balance Sheet'!AB37/'Balance Sheet'!AB59 -> 0.44051364 | AC18: ='Balance Sheet'!AC37/'Balance Sheet'!AC59 -> 0.29771791 | AD18: ='Balance Sheet'!AD37/'Balance Sheet'!AD59 -> 0.28597436 | AF18: Total equity | AG18: ='Balance Sheet'!AG39/'Balance Sheet'!AG60 -> 0.44806671 | AH18: ='Balance Sheet'!AH39/'Balance Sheet'!AH60 -> 0.41188526 | AI18: ='Balance Sheet'!AI39/'Balance Sheet'!AI60 -> 0.31192516 | AJ18: ='Balance Sheet'!AJ39/'Balance Sheet'!AJ60 -> 0.3295131 | AK18: ='Balance Sheet'!AK39/'Balance Sheet'!AK60 -> 0.57284742 | AL18: ='Balance Sheet'!AL39/'Balance Sheet'!AL60 -> 0.59273603 | AN18: Total equity | AO18: ='Balance Sheet'!AO35/'Balance Sheet'!AO55 -> 0.42427477 | AP18: ='Balance Sheet'!AP35/'Balance Sheet'!AP55 -> 0.4386048 | AQ18: ='Balance Sheet'!AQ35/'Balance Sheet'!AQ55 -> 0.44981779 | AR18: ='Balance Sheet'!AR35/'Balance Sheet'!AR55 -> 0.46648895 | AS18: ='Balance Sheet'!AS35/'Balance Sheet'!AS55 -> 0.7232847
A19: Long term borrowings | B19: ='Balance Sheet'!B39/'Balance Sheet'!B56 -> 0 | C19: ='Balance Sheet'!C39/'Balance Sheet'!C56 -> 0 | D19: ='Balance Sheet'!D39/'Balance Sheet'!D56 -> 0 | E19: ='Balance Sheet'!E39/'Balance Sheet'!E56 -> 0 | F19: ='Balance Sheet'!F39/'Balance Sheet'!F56 -> 0 | G19: ='Balance Sheet'!G39/'Balance Sheet'!G56 -> 0 | I19: Long term borrowings | J19: 0 | K19: 1 | L19: 2 | M19: 3 | N19: 4 | P19: Long term borrowings | Q19: ='Balance Sheet'!Q43/'Balance Sheet'!Q61 -> 7.6259865e-05 | R19: ='Balance Sheet'!R43/'Balance Sheet'!R61 -> 7.5589988e-05 | S19: ='Balance Sheet'!S43/'Balance Sheet'!S61 -> 6.2775411e-05 | T19: ='Balance Sheet'!T43/'Balance Sheet'!T61 -> 4.063669e-05 | U19: ='Balance Sheet'!U43/'Balance Sheet'!U61 -> 1.9166651e-05 | V19: ='Balance Sheet'!V43/'Balance Sheet'!V61 -> 0 | X19: Long term borrowings | Y19: ='Balance Sheet'!Y40/'Balance Sheet'!Y59 -> 0.0012546125 | Z19: ='Balance Sheet'!Z40/'Balance Sheet'!Z59 -> 0.00054704595 | AA19: ='Balance Sheet'!AA40/'Balance Sheet'!AA59 -> 9.436633e-05 | AB19: ='Balance Sheet'!AB40/'Balance Sheet'!AB59 -> 0 | AC19: ='Balance Sheet'!AC40/'Balance Sheet'!AC59 -> 0.10465927 | AD19: ='Balance Sheet'!AD40/'Balance Sheet'!AD59 -> 0.014638227 | AF19: Long term borrowings | AG19: ='Balance Sheet'!AG42/'Balance Sheet'!AG60 -> 0.054432072 | AH19: ='Balance Sheet'!AH42/'Balance Sheet'!AH60 -> 0 | AI19: ='Balance Sheet'!AI42/'Balance Sheet'!AI60 -> 0.06437726 | AJ19: ='Balance Sheet'!AJ42/'Balance Sheet'!AJ60 -> 0.061615808 | AK19: ='Balance Sheet'!AK42/'Balance Sheet'!AK60 -> 0.06961427 | AL19: ='Balance Sheet'!AL42/'Balance Sheet'!AL60 -> 0.052995656 | AN19: Long term borrowings | AO19: ='Balance Sheet'!AO38/'Balance Sheet'!AO55 -> 0.23404792 | AP19: ='Balance Sheet'!AP38/'Balance Sheet'!AP55 -> 0.18951426 | AQ19: ='Balance Sheet'!AQ38/'Balance Sheet'!AQ55 -> 0.1489497 | AR19: ='Balance Sheet'!AR38/'Balance Sheet'!AR55 -> 0.20997561 | AS19: ='Balance Sheet'!AS38/'Balance Sheet'!AS55 -> 0.036324415
A20: Lease liabilities | B20: ='Balance Sheet'!B40/'Balance Sheet'!B56 -> 0.018309189 | C20: ='Balance Sheet'!C40/'Balance Sheet'!C56 -> 0.022847883 | D20: ='Balance Sheet'!D40/'Balance Sheet'!D56 -> 0.032777212 | E20: ='Balance Sheet'!E40/'Balance Sheet'!E56 -> 0.026325658 | F20: ='Balance Sheet'!F40/'Balance Sheet'!F56 -> 0.018852351 | G20: ='Balance Sheet'!G40/'Balance Sheet'!G56 -> 0.022852935 | I20: Lease liabilities | J20: ='Balance Sheet'!J38/'Balance Sheet'!J53 -> 0 | K20: ='Balance Sheet'!K38/'Balance Sheet'!K53 -> 0 | L20: ='Balance Sheet'!L38/'Balance Sheet'!L53 -> 0.010631645 | M20: ='Balance Sheet'!M38/'Balance Sheet'!M53 -> 0.010508104 | N20: ='Balance Sheet'!N38/'Balance Sheet'!N53 -> 0.014089351 | P20: Lease liabilities | Q20: ='Balance Sheet'!Q44/'Balance Sheet'!Q61 -> 0.0026367818 | R20: ='Balance Sheet'!R44/'Balance Sheet'!R61 -> 0.0028036029 | S20: ='Balance Sheet'!S44/'Balance Sheet'!S61 -> 0.0025067451 | T20: ='Balance Sheet'!T44/'Balance Sheet'!T61 -> 0.0024844271 | U20: ='Balance Sheet'!U44/'Balance Sheet'!U61 -> 0.0025113758 | V20: ='Balance Sheet'!V44/'Balance Sheet'!V61 -> 0.0015575995 | X20: Lease liabilities | Y20: ='Balance Sheet'!Y41/'Balance Sheet'!Y59 -> 0.077933579 | Z20: ='Balance Sheet'!Z41/'Balance Sheet'!Z59 -> 0.064369074 | AA20: ='Balance Sheet'!AA41/'Balance Sheet'!AA59 -> 0.053694442 | AB20: ='Balance Sheet'!AB41/'Balance Sheet'!AB59 -> 0.059467861 | AC20: ='Balance Sheet'!AC41/'Balance Sheet'!AC59 -> 0.064405705 | AD20: ='Balance Sheet'!AD41/'Balance Sheet'!AD59 -> 0.057027579 | AF20: Lease liabilities | AG20: ='Balance Sheet'!AG43/'Balance Sheet'!AG60 -> 0.40445423 | AH20: ='Balance Sheet'!AH43/'Balance Sheet'!AH60 -> 0.45287426 | AI20: ='Balance Sheet'!AI43/'Balance Sheet'!AI60 -> 0.53404081 | AJ20: ='Balance Sheet'!AJ43/'Balance Sheet'!AJ60 -> 0.46404827 | AK20: ='Balance Sheet'!AK43/'Balance Sheet'!AK60 -> 0.11801585 | AL20: ='Balance Sheet'!AL43/'Balance Sheet'!AL60 -> 0.11696838 | AN20: Lease liabilities | AO20: 0 | AP20: 1 | AQ20: 2 | AR20: 3 | AS20: 4
A21: Other non-current liabilities | B21: ='Balance Sheet'!B41/'Balance Sheet'!B56 -> 3.8918722e-05 | C21: ='Balance Sheet'!C41/'Balance Sheet'!C56 -> 3.222034e-05 | D21: ='Balance Sheet'!D41/'Balance Sheet'!D56 -> 2.6498387e-05 | E21: ='Balance Sheet'!E41/'Balance Sheet'!E56 -> 2.595783e-05 | F21: ='Balance Sheet'!F41/'Balance Sheet'!F56 -> 1.747162e-05 | G21: ='Balance Sheet'!G41/'Balance Sheet'!G56 -> 2.0147786e-05 | I21: Other non-current liabilities | J21: ='Balance Sheet'!J39/'Balance Sheet'!J53 -> 0.02114982 | K21: ='Balance Sheet'!K39/'Balance Sheet'!K53 -> 0.046593559 | L21: ='Balance Sheet'!L39/'Balance Sheet'!L53 -> 0.0043050162 | M21: ='Balance Sheet'!M39/'Balance Sheet'!M53 -> 0.005062609 | N21: ='Balance Sheet'!N39/'Balance Sheet'!N53 -> 0.0091466133 | P21: Other non-current liabilities | Q21: ='Balance Sheet'!Q48/'Balance Sheet'!Q61 -> 0.00020939149 | R21: ='Balance Sheet'!R48/'Balance Sheet'!R61 -> 0.00021051405 | S21: ='Balance Sheet'!S48/'Balance Sheet'!S61 -> 0.00047152747 | T21: ='Balance Sheet'!T48/'Balance Sheet'!T61 -> 0.0009645683 | U21: ='Balance Sheet'!U48/'Balance Sheet'!U61 -> 0.0016304722 | V21: ='Balance Sheet'!V48/'Balance Sheet'!V61 -> 0.0003917554 | X21: Other non-current liabilities | Y21: ='Balance Sheet'!Y45/'Balance Sheet'!Y59 -> 0 | Z21: ='Balance Sheet'!Z45/'Balance Sheet'!Z59 -> 6.0782884e-05 | AA21: ='Balance Sheet'!AA45/'Balance Sheet'!AA59 -> 4.7183165e-05 | AB21: ='Balance Sheet'!AB45/'Balance Sheet'!AB59 -> 3.7005514e-05 | AC21: ='Balance Sheet'!AC45/'Balance Sheet'!AC59 -> 0.00028526149 | AD21: ='Balance Sheet'!AD45/'Balance Sheet'!AD59 -> 0.00024602062 | AF21: Other non-current liabilities | AG21: ='Balance Sheet'!AG47/'Balance Sheet'!AG60 -> 0 | AH21: ='Balance Sheet'!AH47/'Balance Sheet'!AH60 -> 0 | AI21: ='Balance Sheet'!AI47/'Balance Sheet'!AI60 -> 0.0012296111 | AJ21: ='Balance Sheet'!AJ47/'Balance Sheet'!AJ60 -> 0.001169333 | AK21: ='Balance Sheet'!AK47/'Balance Sheet'!AK60 -> 0.0011994275 | AL21: ='Balance Sheet'!AL47/'Balance Sheet'!AL60 -> 0.0013100288 | AN21: Other non-current liabilities | AO21: ='Balance Sheet'!AO42/'Balance Sheet'!AO55 -> 8.6779785e-05 | AP21: ='Balance Sheet'!AP42/'Balance Sheet'!AP55 -> 7.0336512e-05 | AQ21: ='Balance Sheet'!AQ42/'Balance Sheet'!AQ55 -> 5.1230454e-05 | AR21: ='Balance Sheet'!AR42/'Balance Sheet'!AR55 -> 0.00045037977 | AS21: ='Balance Sheet'!AS42/'Balance Sheet'!AS55 -> 0.00020441663
A22: Total non-current liabilities | B22: ='Balance Sheet'!B44/'Balance Sheet'!B56 -> 0.022394826 | C22: ='Balance Sheet'!C44/'Balance Sheet'!C56 -> 0.026808055 | D22: ='Balance Sheet'!D44/'Balance Sheet'!D56 -> 0.037256732 | E22: ='Balance Sheet'!E44/'Balance Sheet'!E56 -> 0.030956093 | F22: ='Balance Sheet'!F44/'Balance Sheet'!F56 -> 0.023644297 | G22: ='Balance Sheet'!G44/'Balance Sheet'!G56 -> 0.028018992 | I22: Total non-current liabilities | J22: ='Balance Sheet'!J43/'Balance Sheet'!J53 -> 0.11149283 | K22: ='Balance Sheet'!K43/'Balance Sheet'!K53 -> 0.12851685 | L22: ='Balance Sheet'!L43/'Balance Sheet'!L53 -> 0.14485798 | M22: ='Balance Sheet'!M43/'Balance Sheet'!M53 -> 0.14393692 | N22: ='Balance Sheet'!N43/'Balance Sheet'!N53 -> 0.18089402 | P22: Total non-current liabilities | Q22: ='Balance Sheet'!Q49/'Balance Sheet'!Q61 -> 0.027874144 | R22: ='Balance Sheet'!R49/'Balance Sheet'!R61 -> 0.03299232 | S22: ='Balance Sheet'!S49/'Balance Sheet'!S61 -> 0.029432866 | T22: ='Balance Sheet'!T49/'Balance Sheet'!T61 -> 0.030329409 | U22: ='Balance Sheet'!U49/'Balance Sheet'!U61 -> 0.035347117 | V22: ='Balance Sheet'!V49/'Balance Sheet'!V61 -> 0.038126962 | X22: Total non-current liabilities | Y22: ='Balance Sheet'!Y45/'Balance Sheet'!Y59 -> 0 | Z22: ='Balance Sheet'!Z45/'Balance Sheet'!Z59 -> 6.0782884e-05 | AA22: ='Balance Sheet'!AA45/'Balance Sheet'!AA59 -> 4.7183165e-05 | AB22: ='Balance Sheet'!AB45/'Balance Sheet'!AB59 -> 3.7005514e-05 | AC22: ='Balance Sheet'!AC45/'Balance Sheet'!AC59 -> 0.00028526149 | AD22: ='Balance Sheet'!AD45/'Balance Sheet'!AD59 -> 0.00024602062 | AF22: Total non-current liabilities | AG22: ='Balance Sheet'!AG48/'Balance Sheet'!AG60 -> 0.46344621 | AH22: ='Balance Sheet'!AH48/'Balance Sheet'!AH60 -> 0.45682972 | AI22: ='Balance Sheet'!AI48/'Balance Sheet'!AI60 -> 0.60349701 | AJ22: ='Balance Sheet'!AJ48/'Balance Sheet'!AJ60 -> 0.53511897 | AK22: ='Balance Sheet'!AK48/'Balance Sheet'!AK60 -> 0.21191608 | AL22: ='Balance Sheet'!AL48/'Balance Sheet'!AL60 -> 0.19380677 | AN22: Total non-current liabilities | AO22: ='Balance Sheet'!AO43/'Balance Sheet'!AO55 -> 0.28784453 | AP22: ='Balance Sheet'!AP43/'Balance Sheet'!AP55 -> 0.24716511 | AQ22: ='Balance Sheet'!AQ43/'Balance Sheet'!AQ55 -> 0.20992429 | AR22: ='Balance Sheet'!AR43/'Balance Sheet'!AR55 -> 0.26004283 | AS22: ='Balance Sheet'!AS43/'Balance Sheet'!AS55 -> 0.081224348
A23: Short term borrowings | B23: ='Balance Sheet'!B47/'Balance Sheet'!B56 -> 0.0003088656 | C23: ='Balance Sheet'!C47/'Balance Sheet'!C56 -> 0 | D23: ='Balance Sheet'!D47/'Balance Sheet'!D56 -> 0 | E23: ='Balance Sheet'!E47/'Balance Sheet'!E56 -> 0 | F23: ='Balance Sheet'!F47/'Balance Sheet'!F56 -> 0 | G23: ='Balance Sheet'!G47/'Balance Sheet'!G56 -> 0 | I23: Short term borrowings | J23: ='Balance Sheet'!J45/'Balance Sheet'!J53 -> 0.0053142949 | K23: ='Balance Sheet'!K45/'Balance Sheet'!K53 -> 0 | L23: ='Balance Sheet'!L45/'Balance Sheet'!L53 -> 0 | M23: ='Balance Sheet'!M45/'Balance Sheet'!M53 -> 0 | N23: ='Balance Sheet'!N45/'Balance Sheet'!N53 -> 0.00016560721 | P23: Short term borrowings | Q23: ='Balance Sheet'!Q52/'Balance Sheet'!Q61 -> 1.8354069e-05 | R23: ='Balance Sheet'!R52/'Balance Sheet'!R61 -> 5.256078e-05 | S23: ='Balance Sheet'!S52/'Balance Sheet'!S61 -> 9.5781039e-06 | T23: ='Balance Sheet'!T52/'Balance Sheet'!T61 -> 0.00041125727 | U23: ='Balance Sheet'!U52/'Balance Sheet'!U61 -> 0.00010367416 | V23: ='Balance Sheet'!V52/'Balance Sheet'!V61 -> 0.0010359779 | X23: Short term borrowings | Y23: ='Balance Sheet'!Y49/'Balance Sheet'!Y59 -> 0.052103321 | Z23: ='Balance Sheet'!Z49/'Balance Sheet'!Z59 -> 0.0094821298 | AA23: ='Balance Sheet'!AA49/'Balance Sheet'!AA59 -> 0.024346513 | AB23: ='Balance Sheet'!AB49/'Balance Sheet'!AB59 -> 0.081227103 | AC23: ='Balance Sheet'!AC49/'Balance Sheet'!AC59 -> 0.14377179 | AD23: ='Balance Sheet'!AD49/'Balance Sheet'!AD59 -> 0.23841858 | AF23: Short term borrowings | AG23: =0 -> 0 | AH23: =0 -> 0 | AI23: =0 -> 0 | AJ23: =0 -> 0 | AK23: =0 -> 0 | AL23: =0 -> 0 | AN23: Short term borrowings | AO23: ='Balance Sheet'!AO45/'Balance Sheet'!AO55 -> 0.084398425 | AP23: ='Balance Sheet'!AP45/'Balance Sheet'!AP55 -> 0.15975355 | AQ23: ='Balance Sheet'!AQ45/'Balance Sheet'!AQ55 -> 0.16971511 | AR23: ='Balance Sheet'!AR45/'Balance Sheet'!AR55 -> 0.13204878 | AS23: ='Balance Sheet'!AS45/'Balance Sheet'!AS55 -> 0.065830536
A24: Trade Payables | B24: =('Balance Sheet'!B49+'Balance Sheet'!B50)/'Balance Sheet'!B56 -> 0.03589217 | C24: =('Balance Sheet'!C49+'Balance Sheet'!C50)/'Balance Sheet'!C56 -> 0.04233533 | D24: =('Balance Sheet'!D49+'Balance Sheet'!D50)/'Balance Sheet'!D56 -> 0.038080121 | E24: =('Balance Sheet'!E49+'Balance Sheet'!E50)/'Balance Sheet'!E56 -> 0.041631389 | F24: =('Balance Sheet'!F49+'Balance Sheet'!F50)/'Balance Sheet'!F56 -> 0.046503315 | G24: =('Balance Sheet'!G49+'Balance Sheet'!G50)/'Balance Sheet'!G56 -> 0.044029491 | I24: Trade Payables | J24: =('Balance Sheet'!J47+'Balance Sheet'!J48)/'Balance Sheet'!J53 -> 0.38681625 | K24: =('Balance Sheet'!K47+'Balance Sheet'!K48)/'Balance Sheet'!K53 -> 0.37388974 | L24: =('Balance Sheet'!L47+'Balance Sheet'!L48)/'Balance Sheet'!L53 -> 0.12801606 | M24: =('Balance Sheet'!M47+'Balance Sheet'!M48)/'Balance Sheet'!M53 -> 0.12859311 | N24: =('Balance Sheet'!N47+'Balance Sheet'!N48)/'Balance Sheet'!N53 -> 0.13358132 | P24: Trade Payables | Q24: =('Balance Sheet'!Q53+'Balance Sheet'!Q54)/'Balance Sheet'!Q61 -> 0.046917008 | R24: =('Balance Sheet'!R53+'Balance Sheet'!R54)/'Balance Sheet'!R61 -> 0.058504077 | S24: =('Balance Sheet'!S53+'Balance Sheet'!S54)/'Balance Sheet'!S61 -> 0.057174291 | T24: =('Balance Sheet'!T53+'Balance Sheet'!T54)/'Balance Sheet'!T61 -> 0.054248118 | U24: =('Balance Sheet'!U53+'Balance Sheet'!U54)/'Balance Sheet'!U61 -> 0.052249054 | V24: =('Balance Sheet'!V53+'Balance Sheet'!V54)/'Balance Sheet'!V61 -> 0.054572175 | X24: Trade Payables | Y24: =('Balance Sheet'!Y52+'Balance Sheet'!Y53)/'Balance Sheet'!Y59 -> 0.04398524 | Z24: =('Balance Sheet'!Z52+'Balance Sheet'!Z53)/'Balance Sheet'!Z59 -> 0.047957695 | AA24: =('Balance Sheet'!AA52+'Balance Sheet'!AA53)/'Balance Sheet'!AA59 -> 0.061055016 | AB24: =('Balance Sheet'!AB52+'Balance Sheet'!AB53)/'Balance Sheet'!AB59 -> 0.044924694 | AC24: =('Balance Sheet'!AC52+'Balance Sheet'!AC53)/'Balance Sheet'!AC59 -> 0.044690967 | AD24: =('Balance Sheet'!AD52+'Balance Sheet'!AD53)/'Balance Sheet'!AD59 -> 0.048293847 | AF24: Trade Payables | AG24: =('Balance Sheet'!AG52+'Balance Sheet'!AG53)/'Balance Sheet'!AG60 -> 0.054052533 | AH24: =('Balance Sheet'!AH52+'Balance Sheet'!AH53)/'Balance Sheet'!AH60 -> 0.047970467 | AI24: =('Balance Sheet'!AI52+'Balance Sheet'!AI53)/'Balance Sheet'!AI60 -> 0.048929462 | AJ24: =('Balance Sheet'!AJ52+'Balance Sheet'!AJ53)/'Balance Sheet'!AJ60 -> 0.082313621 | AK24: =('Balance Sheet'!AK52+'Balance Sheet'!AK53)/'Balance Sheet'!AK60 -> 0.10806158 | AL24: =('Balance Sheet'!AL52+'Balance Sheet'!AL53)/'Balance Sheet'!AL60 -> 0.098537736 | AN24: Trade Payables | AO24: =('Balance Sheet'!AO47+'Balance Sheet'!AO48)/'Balance Sheet'!AO55 -> 0.060460328 | AP24: =('Balance Sheet'!AP47+'Balance Sheet'!AP48)/'Balance Sheet'!AP55 -> 0.074386661 | AQ24: =('Balance Sheet'!AQ47+'Balance Sheet'!AQ48)/'Balance Sheet'!AQ55 -> 0.071089672 | AR24: =('Balance Sheet'!AR47+'Balance Sheet'!AR48)/'Balance Sheet'!AR55 -> 0.049926836 | AS24: =('Balance Sheet'!AS47+'Balance Sheet'!AS48)/'Balance Sheet'!AS55 -> 0.067422791
A25: Other current liabilities | B25: ='Balance Sheet'!B53/'Balance Sheet'!B56 -> 0.0017140799 | C25: ='Balance Sheet'!C53/'Balance Sheet'!C56 -> 0.0029825783 | D25: ='Balance Sheet'!D53/'Balance Sheet'!D56 -> 0.0023551249 | E25: ='Balance Sheet'!E53/'Balance Sheet'!E56 -> 0.0028095209 | F25: ='Balance Sheet'!F53/'Balance Sheet'!F56 -> 0.0028823452 | G25: ='Balance Sheet'!G53/'Balance Sheet'!G56 -> 0.0020205351 | I25: Other current liabilities | J25: ='Balance Sheet'!J50/'Balance Sheet'!J53 -> 0.018626872 | K25: ='Balance Sheet'!K50/'Balance Sheet'!K53 -> 0.021237533 | L25: ='Balance Sheet'!L50/'Balance Sheet'!L53 -> 0.0085518565 | M25: ='Balance Sheet'!M50/'Balance Sheet'!M53 -> 0.0094303501 | N25: ='Balance Sheet'!N50/'Balance Sheet'!N53 -> 0.010280386 | P25: Other current liabilities | Q25: ='Balance Sheet'!Q57/'Balance Sheet'!Q61 -> 0.052641538 | R25: ='Balance Sheet'!R57/'Balance Sheet'!R61 -> 0.058174488 | S25: ='Balance Sheet'!S57/'Balance Sheet'!S61 -> 0.066218739 | T25: ='Balance Sheet'!T57/'Balance Sheet'!T61 -> 0.06487141 | U25: ='Balance Sheet'!U57/'Balance Sheet'!U61 -> 0.0609273 | V25: ='Balance Sheet'!V57/'Balance Sheet'!V61 -> 0.069794784 | X25: Other current liabilities | Y25: ='Balance Sheet'!Y55/'Balance Sheet'!Y59 -> 0.16280443 | Z25: ='Balance Sheet'!Z55/'Balance Sheet'!Z59 -> 0.12235594 | AA25: ='Balance Sheet'!AA55/'Balance Sheet'!AA59 -> 0.11904313 | AB25: ='Balance Sheet'!AB55/'Balance Sheet'!AB59 -> 0.13014839 | AC25: ='Balance Sheet'!AC55/'Balance Sheet'!AC59 -> 0.12969889 | AD25: ='Balance Sheet'!AD55/'Balance Sheet'!AD59 -> 0.10925776 | AF25: Other current liabilities | AG25: ='Balance Sheet'!AG55/'Balance Sheet'!AG60 -> 0.0074963499 | AH25: ='Balance Sheet'!AH55/'Balance Sheet'!AH60 -> 0.0080664182 | AI25: ='Balance Sheet'!AI55/'Balance Sheet'!AI60 -> 0.0093062146 | AJ25: ='Balance Sheet'!AJ55/'Balance Sheet'!AJ60 -> 0.014655641 | AK25: ='Balance Sheet'!AK55/'Balance Sheet'!AK60 -> 0.020951583 | AL25: ='Balance Sheet'!AL55/'Balance Sheet'!AL60 -> 0.018323418 | AN25: Other current liabilities | AO25: ='Balance Sheet'!AO50/'Balance Sheet'!AO55 -> 0.037631215 | AP25: ='Balance Sheet'!AP50/'Balance Sheet'!AP55 -> 0.032364828 | AQ25: ='Balance Sheet'!AQ50/'Balance Sheet'!AQ55 -> 0.042172582 | AR25: ='Balance Sheet'!AR50/'Balance Sheet'!AR55 -> 0.030624047 | AS25: ='Balance Sheet'!AS50/'Balance Sheet'!AS55 -> 0.021243385
A26: Total current liabilities | B26: ='Balance Sheet'!B55/'Balance Sheet'!B56 -> 0.060100443 | C26: ='Balance Sheet'!C55/'Balance Sheet'!C56 -> 0.080973376 | D26: ='Balance Sheet'!D55/'Balance Sheet'!D56 -> 0.078738341 | E26: ='Balance Sheet'!E55/'Balance Sheet'!E56 -> 0.08102212 | F26: ='Balance Sheet'!F55/'Balance Sheet'!F56 -> 0.09345617 | G26: ='Balance Sheet'!G55/'Balance Sheet'!G56 -> 0.090959442 | I26: Total current liabilities | J26: ='Balance Sheet'!J52/'Balance Sheet'!J53 -> 0.46524236 | K26: ='Balance Sheet'!K52/'Balance Sheet'!K53 -> 0.4623133 | L26: ='Balance Sheet'!L52/'Balance Sheet'!L53 -> 0.16148174 | M26: ='Balance Sheet'!M52/'Balance Sheet'!M53 -> 0.15996143 | N26: ='Balance Sheet'!N52/'Balance Sheet'!N53 -> 0.16402757 | P26: Total current liabilities | Q26: ='Balance Sheet'!Q60/'Balance Sheet'!Q61 -> 0.12356386 | R26: ='Balance Sheet'!R60/'Balance Sheet'!R61 -> 0.14480874 | S26: ='Balance Sheet'!S60/'Balance Sheet'!S61 -> 0.15743957 | T26: ='Balance Sheet'!T60/'Balance Sheet'!T61 -> 0.15997826 | U26: ='Balance Sheet'!U60/'Balance Sheet'!U61 -> 0.14909041 | V26: ='Balance Sheet'!V60/'Balance Sheet'!V61 -> 0.16271994 | X26: Total current liabilities | Y26: ='Balance Sheet'!Y58/'Balance Sheet'!Y59 -> 0.41535055 | Z26: ='Balance Sheet'!Z58/'Balance Sheet'!Z59 -> 0.46887916 | AA26: ='Balance Sheet'!AA58/'Balance Sheet'!AA59 -> 0.49598943 | AB26: ='Balance Sheet'!AB58/'Balance Sheet'!AB59 -> 0.49084114 | AC26: ='Balance Sheet'!AC58/'Balance Sheet'!AC59 -> 0.52389857 | AD26: ='Balance Sheet'!AD58/'Balance Sheet'!AD59 -> 0.63456098 | AF26: Total current liabilities | AG26: ='Balance Sheet'!AG58/'Balance Sheet'!AG60 -> 0.088487074 | AH26: ='Balance Sheet'!AH58/'Balance Sheet'!AH60 -> 0.13128502 | AI26: ='Balance Sheet'!AI58/'Balance Sheet'!AI60 -> 0.084577829 | AJ26: ='Balance Sheet'!AJ58/'Balance Sheet'!AJ60 -> 0.13536793 | AK26: ='Balance Sheet'!AK58/'Balance Sheet'!AK60 -> 0.2152365 | AL26: ='Balance Sheet'!AL58/'Balance Sheet'!AL60 -> 0.2134572 | AN26: Total current liabilities | AO26: ='Balance Sheet'!AO53/'Balance Sheet'!AO55 -> 0.28788071 | AP26: ='Balance Sheet'!AP53/'Balance Sheet'!AP55 -> 0.31423009 | AQ26: ='Balance Sheet'!AQ53/'Balance Sheet'!AQ55 -> 0.34025793 | AR26: ='Balance Sheet'!AR53/'Balance Sheet'!AR55 -> 0.27346823 | AS26: ='Balance Sheet'!AS53/'Balance Sheet'!AS55 -> 0.19549095
A27: Total liabilities | B27: =('Balance Sheet'!B44+'Balance Sheet'!B55)/'Balance Sheet'!B56 -> 0.08249527 | C27: =('Balance Sheet'!C44+'Balance Sheet'!C55)/'Balance Sheet'!C56 -> 0.10778143 | D27: =('Balance Sheet'!D44+'Balance Sheet'!D55)/'Balance Sheet'!D56 -> 0.11599507 | E27: =('Balance Sheet'!E44+'Balance Sheet'!E55)/'Balance Sheet'!E56 -> 0.11197821 | F27: =('Balance Sheet'!F44+'Balance Sheet'!F55)/'Balance Sheet'!F56 -> 0.11710047 | G27: =('Balance Sheet'!G44+'Balance Sheet'!G55)/'Balance Sheet'!G56 -> 0.11897843 | I27: Total liabilities | J27: =('Balance Sheet'!J43+'Balance Sheet'!J52)/'Balance Sheet'!J53 -> 0.5767352 | K27: =('Balance Sheet'!K43+'Balance Sheet'!K52)/'Balance Sheet'!K53 -> 0.59083015 | L27: =('Balance Sheet'!L43+'Balance Sheet'!L52)/'Balance Sheet'!L53 -> 0.30633972 | M27: =('Balance Sheet'!M43+'Balance Sheet'!M52)/'Balance Sheet'!M53 -> 0.30389835 | N27: =('Balance Sheet'!N43+'Balance Sheet'!N52)/'Balance Sheet'!N53 -> 0.34492159 | P27: Total liabilities | Q27: =('Balance Sheet'!Q49+'Balance Sheet'!Q60)/'Balance Sheet'!Q61 -> 0.151438 | R27: =('Balance Sheet'!R49+'Balance Sheet'!R60)/'Balance Sheet'!R61 -> 0.17780106 | S27: =('Balance Sheet'!S49+'Balance Sheet'!S60)/'Balance Sheet'!S61 -> 0.18687243 | T27: =('Balance Sheet'!T49+'Balance Sheet'!T60)/'Balance Sheet'!T61 -> 0.19030767 | U27: =('Balance Sheet'!U49+'Balance Sheet'!U60)/'Balance Sheet'!U61 -> 0.18443753 | V27: =('Balance Sheet'!V49+'Balance Sheet'!V60)/'Balance Sheet'!V61 -> 0.2008469 | X27: Total liabilities | Y27: =('Balance Sheet'!Y46+'Balance Sheet'!Y58)/'Balance Sheet'!Y59 -> 0.50752768 | Z27: =('Balance Sheet'!Z46+'Balance Sheet'!Z58)/'Balance Sheet'!Z59 -> 0.54400681 | AA27: =('Balance Sheet'!AA46+'Balance Sheet'!AA58)/'Balance Sheet'!AA59 -> 0.55963952 | AB27: =('Balance Sheet'!AB46+'Balance Sheet'!AB58)/'Balance Sheet'!AB59 -> 0.55948636 | AC27: =('Balance Sheet'!AC46+'Balance Sheet'!AC58)/'Balance Sheet'!AC59 -> 0.70228209 | AD27: =('Balance Sheet'!AD46+'Balance Sheet'!AD58)/'Balance Sheet'!AD59 -> 0.71402564 | AF27: Total liabilities | AG27: ='Balance Sheet'!AG59/'Balance Sheet'!AG60 -> 0.55193329 | AH27: ='Balance Sheet'!AH59/'Balance Sheet'!AH60 -> 0.58811474 | AI27: ='Balance Sheet'!AI59/'Balance Sheet'!AI60 -> 0.68807484 | AJ27: ='Balance Sheet'!AJ59/'Balance Sheet'!AJ60 -> 0.6704869 | AK27: ='Balance Sheet'!AK59/'Balance Sheet'!AK60 -> 0.42715258 | AL27: ='Balance Sheet'!AL59/'Balance Sheet'!AL60 -> 0.40726397 | AN27: Total liabilities | AO27: ='Balance Sheet'!AO54/'Balance Sheet'!AO55 -> 0.57572523 | AP27: ='Balance Sheet'!AP54/'Balance Sheet'!AP55 -> 0.5613952 | AQ27: ='Balance Sheet'!AQ54/'Balance Sheet'!AQ55 -> 0.55018221 | AR27: ='Balance Sheet'!AR54/'Balance Sheet'!AR55 -> 0.53351105 | AS27: ='Balance Sheet'!AS54/'Balance Sheet'!AS55 -> 0.2767153
A28: Total Equity & Liabilities | B28: =B18+B22+B26 -> 1 | C28: =C18+C22+C26 -> 1 | D28: =D18+D22+D26 -> 1 | E28: =E18+E22+E26 -> 1 | F28: =F18+F22+F26 -> 1 | G28: =G18+G22+G26 -> 1 | I28: Total Equity & Liabilities | J28: =J18+J22+J26 -> 1 | K28: =K18+K22+K26 -> 1 | L28: =L18+L22+L26 -> 1 | M28: =M18+M22+M26 -> 1 | N28: =N18+N22+N26 -> 1 | P28: Total Equity & Liabilities | Q28: =Q18+Q27 -> 1 | R28: =R18+R27 -> 1 | S28: =S18+S27 -> 1 | T28: =T18+T27 -> 1 | U28: =U18+U27 -> 1 | V28: =V18+V27 -> 1 | X28: Total Equity & Liabilities | Y28: =Y18+Y27 -> 1 | Z28: =Z18+Z27 -> 1 | AA28: =AA18+AA27 -> 1 | AB28: =AB18+AB27 -> 1 | AC28: =AC18+AC27 -> 1 | AD28: =AD18+AD27 -> 1 | AF28: Total Equity & Liabilities | AG28: =AG18+AG27 -> 1 | AH28: =AH18+AH27 -> 1 | AI28: =AI18+AI27 -> 1 | AJ28: =AJ18+AJ27 -> 1 | AK28: =AK18+AK27 -> 1 | AL28: =AL18+AL27 -> 1 | AN28: Total Equity & Liabilities | AO28: =AO18+AO27 -> 1 | AP28: =AP18+AP27 -> 1 | AQ28: =AQ18+AQ27 -> 1 | AR28: =AR18+AR27 -> 1 | AS28: =AS18+AS27 -> 1

Sheet Income Statement
A1: Income Statement | G1: #VALUE! | I1: Income Statement | N1: #VALUE! | P1: Income Statement | V1: #VALUE! | X1: Income Statement | AD1: #VALUE! | AF1: Income Statement | AL1: #VALUE! | AN1: Income Statement | AS1: #VALUE!
A2: Particulars | B2: 2020 | C2: 2021 | D2: 2022 | E2: 2023 | F2: 2024 | G2: 2025 | I2: Particulars | J2: 2020 | K2: 2021 | L2: 2022 | M2: 2023 | N2: 2024 | P2: Particulars | Q2: 2020 | R2: 2021 | S2: 2022 | T2: 2023 | U2: 2024 | V2: 2025 | X2: Particulars | Y2: 2020 | Z2: 2021 | AA2: 2022 | AB2: 2023 | AC2: 2024 | AD2: 2025 | AF2: Particulars | AG2: 2020 | AH2: 2021 | AI2: 2022 | AJ2: 2023 | AK2: 2024 | AL2: 2025 | AN2: Particulars | AO2: 2020 | AP2: 2021 | AQ2: 2022 | AR2: 2023 | AS2: 2024
A3: Income | I3: Income | P3: Income | X3: Income | AF3: Income | AN3: Income
A4: Revenue from operations | B4: 24870.2 | C4: 24143.06 | D4: 30976.27 | E4: 42839.56 | F4: 50788.83 | G4: 59358.05 | I4: Revenue from operations | J4: 39783 | K4: 47028 | L4: 52446 | M4: 60580 | N4: 61896 | P4: Revenue from operations | Q4: 51393.47 | R4: 53155.12 | S4: 65204.96 | T4: 76518.21 | U4: 73891.43 | V4: 81612.78 | X4: Revenue from operations | Y4: 21052 | Z4: 21644 | AA4: 28799 | AB4: 40575 | AC4: 51084 | AD4: 60456 | AF4: Revenue from operations | AG4: 3485.98 | AH4: 2592.96 | AI4: 4498.02 | AJ4: 8242.02 | AK4: 12375.11 | AL4: 17134.61 | AN4: Revenue from operations | AO4: 6555.79 | AP4: 8958.291 | AQ4: 13390.558 | AR4: 16321.063 | AS4: 20481.328
A5: Other income | B5: 59.99 | C5: 196.21 | D5: 117.49 | E5: 129.34 | F5: 146.45 | G5: 124.31 | I5: Other income | J5: 632 | K5: 410 | L5: 258 | M5: 512 | N5: 811 | P5: Other income | Q5: 2597.89 | R5: 2632.56 | S5: 1836.35 | T5: 1980.49 | U5: 2693.22 | V5: 2529.69 | X5: Other income | Y5: 153 | Z5: 186 | AA5: 234 | AB5: 308 | AC5: 533 | AD5: 486 | AF5: Other income | AG5: 149.42 | AH5: 201.6 | AI5: 175.21 | AJ5: 260.92 | AK5: 289.27 | AL5: 218.56 | AN5: Other income | AO5: 36.97 | AP5: 67.925 | AQ5: 38.849 | AR5: 79.359 | AS5: 121.268
A6: Total income | B6: =B4+B5 -> 24930.19 | C6: =C4+C5 -> 24339.27 | D6: =D4+D5 -> 31093.76 | E6: =E4+E5 -> 42968.9 | F6: =F4+F5 -> 50935.28 | G6: =G4+G5 -> 59482.36 | I6: Total income | J6: =SUM(J4:J5) -> 40415 | K6: =SUM(K4:K5) -> 47438 | L6: =SUM(L4:L5) -> 52704 | M6: =SUM(M4:M5) -> 61092 | N6: =SUM(N4:N5) -> 62707 | P6: Total income | Q6: =SUM(Q4:Q5) -> 53991.36 | R6: =SUM(R4:R5) -> 55787.68 | S6: =SUM(S4:S5) -> 67041.31 | T6: =SUM(T4:T5) -> 78498.7 | U6: =SUM(U4:U5) -> 76584.65 | V6: =SUM(V4:V5) -> 84142.47 | X6: Total income | Y6: =SUM(Y4:Y5) -> 21205 | Z6: =SUM(Z4:Z5) -> 21830 | AA6: =SUM(AA4:AA5) -> 29033 | AB6: =SUM(AB4:AB5) -> 40883 | AC6: =SUM(AC4:AC5) -> 51617 | AD6: =SUM(AD4:AD5) -> 60942 | AF6: Total income | AG6: =SUM(AG4:AG5) -> 3635.4 | AH6: =SUM(AH4:AH5) -> 2794.56 | AI6: =SUM(AI4:AI5) -> 4673.23 | AJ6: =SUM(AJ4:AJ5) -> 8502.94 | AK6: =SUM(AK4:AK5) -> 12664.38 | AL6: =SUM(AL4:AL5) -> 17353.17 | AN6: Total income | AO6: =SUM(AO4:AO5) -> 6592.76 | AP6: =SUM(AP4:AP5) -> 9026.216 | AQ6: =SUM(AQ4:AQ5) -> 13429.407 | AR6: =SUM(AR4:AR5) -> 16400.422 | AS6: =SUM(AS4:AS5) -> 20602.596
A7: Expenses | I7: Expenses | P7: Expenses | X7: Expenses | AF7: Expenses | AN7: Expenses
A8: Purchase of stock-in-trade | B8: 21441.68 | C8: 20855.56 | D8: 26891.77 | E8: 36884.77 | F8: 43958.31 | G8: 51668.76 | I8: Cost of materials consumed | J8: 11976 | K8: 15432 | L8: 16446 | M8: 20212 | N8: 19257 | P8: Cost of materials consumed | Q8: 13810.7 | R8: 13939.84 | S8: 16399.94 | T8: 20275.99 | U8: 21288.44 | V8: 23757.33 | X8: Cost of materials and components consumed | Y8: 13042 | Z8: 13713 | AA8: 22108 | AB8: 26891 | AC8: 36104 | AD8: 47708 | AF8: Purchase of stock-in-trade | AG8: 1951.64 | AH8: 1371.64 | AI8: 2920.38 | AJ8: 5211.05 | AK8: 7123.6 | AL8: 10143.39 | AN8: Cost of material consumed | AO8: 2688.509 | AP8: 3968.913 | AQ8: 6417.092 | AR8: 7026.461 | AS8: 8293.743
A9: Changes in inventories of stock in trade | B9: -338.75 | C9: -300.88 | D9: -494.38 | E9: -500.82 | F9: -683.77 | G9: -1117.06 | I9: Purchases of stock-in-trade | J9: 6391 | K9: 7121 | L9: 9311 | M9: 11579 | N9: 10514 | P9: Purchases of stock-in-trade | Q9: 4237.9 | R9: 6836.87 | S9: 10671.13 | T9: 9088.37 | U9: 6060.13 | V9: 8947.04 | X9: Purchase of stock-in-trade | Y9: 2991 | Z9: 2579 | AA9: 4328 | AB9: 5698 | AC9: 5999 | AD9: 7563 | AF9: Changes in inventories of stock-in-trade | AG9: -69.89 | AH9: 162.36 | AI9: -438.84 | AJ9: -491.31 | AK9: -164.71 | AL9: -454.25 | AN9: Excise duty | AO9: 105.649 | AP9: 135.061 | AQ9: 217.416 | AR9: 278.482 | AS9: 473.678
A10: Employee benefit expenses | B10: 456.1 | C10: 536.57 | D10: 616.21 | E10: 746.97 | F10: 906.12 | G10: 1165.9 | I10: Changes in inventories of finished goods and WIP | J10: -108 | K10: -405 | L10: -22 | M10: -75 | N10: -11 | P10: Changes in inventories of finished goods, SIT and WIP | Q10: -703.13 | R10: -645.27 | S10: -686 | T10: -358.59 | U10: -367.77 | V10: -725.65 | X10: Changes in inventories of finished goods, SIT, WIP | Y10: -878 | Z10: 122 | AA10: -4795 | AB10: -2234 | AC10: -2671 | AD10: -7815 | AF10: Employee benefits expense | AG10: 358.52 | AH10: 301.86 | AI10: 398.95 | AJ10: 655.23 | AK10: 1036.64 | AL10: 1308.45 | AN10: Purchase of stock-in-trade | AO10: 92.587 | AP10: 165.469 | AQ10: 188.571 | AR10: 462.696 | AS10: 685.921
A11: Finance costs | B11: 69.12 | C11: 41.65 | D11: 53.79 | E11: 67.41 | F11: 58.13 | G11: 69.45 | I11: Employee benefit expenses | J11: 1820 | K11: 2358 | L11: 2545 | M11: 2854 | N11: 3009 | P11: Excise duty | Q11: 1989.42 | R11: 3882.34 | S11: 4536.87 | T11: 5581.36 | U11: 5959.49 | V11: 6289.44 | X11: Employee benefit expense | Y11: 1199 | Z11: 1065 | AA11: 1349 | AB11: 1647 | AC11: 1864 | AD11: 2156 | AF11: Finance cost | AG11: 245.8 | AH11: 248.65 | AI11: 304.74 | AJ11: 369.22 | AK11: 319.1 | AL11: 138.59 | AN11: Changes in inventories of finished goods, SIT and WIP | AO11: -17.159 | AP11: -99.722 | AQ11: -344.507 | AR11: -84.269 | AS11: -74.94
A12: Depreciation and amortisation | B12: 374.41 | C12: 414.16 | D12: 498.08 | E12: 638.87 | F12: 730.76 | G12: 869.52 | I12: Finance costs | J12: 118 | K12: 117 | L12: 106 | M12: 114 | N12: 334 | P12: Employee benefits expense | Q12: 4295.79 | R12: 4463.33 | S12: 4890.55 | T12: 5736.22 | U12: 5548.53 | V12: 6169.78 | X12: Finance costs | Y12: 166 | Z12: 203 | AA12: 218 | AB12: 300 | AC12: 619 | AD12: 953 | AF12: Depreciation and amortisation | AG12: 247.24 | AH12: 257.3 | AI12: 310.82 | AJ12: 493.69 | AK12: 671.11 | AL12: 895.18 | AN12: Employee benefit expense | AO12: 889.736 | AP12: 1007.699 | AQ12: 1216.642 | AR12: 1446.587 | AS12: 1885.026
A13: Other expenses | B13: 1182.86 | C13: 1308.76 | D13: 1464.17 | E13: 2071.61 | F13: 2504.4 | G13: 3153.12 | I13: Depreciation and amortisation expense | J13: 1002 | K13: 1074 | L13: 1091 | M13: 1137 | N13: 1216 | P13: Finance costs | Q13: 54.68 | R13: 44.58 | S13: 39.36 | T13: 43.2 | U13: 39.11 | V13: 45.06 | X13: Depreciation and amortisation expense | Y13: 348 | Z13: 375 | AA13: 399 | AB13: 441 | AC13: 584 | AD13: 693 | AF13: Other expenses | AG13: 706.67 | AH13: 585.2 | AI13: 1043.66 | AJ13: 1793.4 | AK13: 2457.45 | AL13: 3378.57 | AN13: Finance costs | AO13: 281.104 | AP13: 184.7 | AQ13: 186.122 | AR13: 268.099 | AS13: 450.386
A14: Total expenses | B14: =SUM(B8:B13) -> 23185.42 | C14: =SUM(C8:C13) -> 22855.82 | D14: =SUM(D8:D13) -> 29029.64 | E14: =SUM(E8:E13) -> 39908.81 | F14: =SUM(F8:F13) -> 47473.95 | G14: =SUM(G8:G13) -> 55809.69 | I14: Other expenses | J14: 9843 | K14: 10896 | L14: 11309 | M14: 11862 | N14: 14464 | P14: Depreciation and amortisation expense | Q14: 1644.91 | R14: 1645.59 | S14: 1732.41 | T14: 1809.01 | U14: 1518.05 | V14: 1646.32 | X14: Other expenses | Y14: 2231 | Z14: 2441 | AA14: 2468 | AB14: 3694 | AC14: 4496 | AD14: 5150 | AF14: Total expenses | AG14: =SUM(AG8:AG13) -> 3439.98 | AH14: =SUM(AH8:AH13) -> 2927.01 | AI14: =SUM(AI8:AI13) -> 4539.71 | AJ14: =SUM(AJ8:AJ13) -> 8031.28 | AK14: =SUM(AK8:AK13) -> 11443.19 | AL14: =SUM(AL8:AL13) -> 15409.93 | AN14: Depreciation and amortisation expense | AO14: 528.702 | AP14: 531.262 | AQ14: 617.189 | AR14: 680.906 | AS14: 947.386
A15: Profit before tax | B15: =B6-B14 -> 1744.77 | C15: =C6-C14 -> 1483.45 | D15: =D6-D14 -> 2064.12 | E15: =E6-E14 -> 3060.09 | F15: =F6-F14 -> 3461.33 | G15: =G6-G14 -> 3672.67 | I15: Total expenses | J15: =SUM(J8:J14) -> 31042 | K15: =SUM(K8:K14) -> 36593 | L15: =SUM(L8:L14) -> 40786 | M15: =SUM(M8:M14) -> 47683 | N15: =SUM(N8:N14) -> 48783 | P15: Other expenses | Q15: 8502.63 | R15: 7675.31 | S15: 8734.06 | T15: 10529.93 | U15: 10152.82 | V15: 11196.63 | X15: Total expenses | Y15: =SUM(Y8:Y14) -> 19099 | Z15: =SUM(Z8:Z14) -> 20498 | AA15: =SUM(AA8:AA14) -> 26075 | AB15: =SUM(AB8:AB14) -> 36437 | AC15: =SUM(AC8:AC14) -> 46995 | AD15: =SUM(AD8:AD14) -> 56408 | AF15: Profit/Loss before exceptional items and tax | AG15: =AG6-AG14 -> 195.42 | AH15: =AH6-AH14 -> -132.45 | AI15: =AI6-AI14 -> 133.52 | AJ15: =AJ6-AJ14 -> 471.66 | AK15: =AK6-AK14 -> 1221.19 | AL15: =AL6-AL14 -> 1943.24 | AN15: Other expenses | AO15: 1594.601 | AP15: 2126.226 | AQ15: 2907.239 | AR15: 3581.621 | AS15: 4506.829
A16: Tax expense | I16: Profit before exceptional items and tax | J16: =J6-J15 -> 9373 | K16: =K6-K15 -> 10845 | L16: =L6-L15 -> 11918 | M16: =M6-M15 -> 13409 | N16: =N6-N15 -> 13924 | P16: Total expenses | Q16: =SUM(Q8:Q15) -> 33832.9 | R16: =SUM(R8:R15) -> 37842.59 | S16: =SUM(S8:S15) -> 46318.32 | T16: =SUM(T8:T15) -> 52705.49 | U16: =SUM(U8:U15) -> 50198.8 | V16: =SUM(V8:V15) -> 57325.95 | X16: Profit before share of profit/loss of an associate and JV | Y16: =Y6-Y15 -> 2106 | Z16: =Z6-Z15 -> 1332 | AA16: =AA6-AA15 -> 2958 | AB16: =AB6-AB15 -> 4446 | AC16: =AC6-AC15 -> 4622 | AD16: =AD6-AD15 -> 4534 | AF16: Exceptional items | AG16: 0 | AH16: -1.01 | AI16: -27.44 | AJ16: -3 | AK16: 576 | AL16: 0 | AN16: Total expenses | AO16: =SUM(AO8:AO15) -> 6163.729 | AP16: =SUM(AP8:AP15) -> 8019.608 | AQ16: =SUM(AQ8:AQ15) -> 11405.764 | AR16: =SUM(AR8:AR15) -> 13660.583 | AS16: =SUM(AS8:AS15) -> 17168.029
A17: Current tax | B17: 459.74 | C17: 394.69 | D17: 546.33 | E17: 807.7 | F17: 913.09 | G17: 983.47 | I17: Exceptional items | J17: -200 | K17: -239 | L17: -44 | M17: =-1-64 -> -65 | N17: =-4+6 -> 2 | P17: Share of profit/loss of associates and joint venture | Q17: 8.22 | R17: -6.92 | S17: 17.48 | T17: 49.04 | U17: 14.43 | V17: 110.42 | X17: Share of profit/loss of: | AF17: Profit/Loss before tax after exceptional items and tax | AG17: =AG15-AG16 -> 195.42 | AH17: =AH15+AH16 -> -133.46 | AI17: =AI15+AI16 -> 106.08 | AJ17: =AJ15+AJ16 -> 468.66 | AK17: =AK15+AK16 -> 1797.19 | AL17: =AL15+AL16 -> 1943.24 | AN17: Profit before share of profit in associate, exceptional items and tax | AO17: =AO6-AO16 -> 429.031 | AP17: =AP6-AP16 -> 1006.608 | AQ17: =AQ6-AQ16 -> 2023.643 | AR17: =AR6-AR16 -> 2739.839 | AS17: =AS6-AS16 -> 3434.567
A18: Deferred tax | B18: -15.97 | C18: 3.17 | D18: 12.1 | E18: 12.82 | F18: 12.02 | G18: 17.76 | I18: Profit before tax from continuing operations | J18: =J16+J17 -> 9173 | K18: =K16+K17 -> 10606 | L18: =L16+L17 -> 11874 | M18: =M16+M17 -> 13344 | N18: =N16+N17 -> 13926 | P18: Profit before exceptional items and tax | Q18: =Q6-Q16+Q17 -> 20166.68 | R18: =R6-R16+R17 -> 17938.17 | S18: =S6-S16+S17 -> 20740.47 | T18: =T6-T16+T17 -> 25842.25 | U18: =U6-U16+U17 -> 26400.28 | V18: =V6-V16+V17 -> 26926.94 | X18: Associate | Y18: 1 | Z18: 0 | AA18: 0 | AB18: 1 | AC18: 1 | AD18: 1 | AF18: Share in profit and loss of associates | AG18: -30.43 | AH18: -71.36 | AI18: 5.14 | AJ18: 83.47 | AK18: 123.57 | AL18: 86.5 | AN18: Share of profit in associate | AO18: 0 | AP18: 0 | AQ18: -0.006 | AR18: -0.479 | AS18: -1.479
A19: Adjustment of tax related to earlier yrs | B19: 0.02 | C19: -13.84 | D19: 13.29 | E19: -138.77 | F19: 0.61 | G19: -36.01 | I19: Tax expenses | P19: Exceptional items | Q19: -132.11 | R19: 0 | S19: 0 | T19: 72.87 | U19: 0 | V19: 0 | X19: Joint venture | Y19: -5 | Z19: -5 | AA19: 0 | AB19: 0 | AC19: 0 | AD19: 0 | AF19: Profit/Loss before tax | AG19: =AG17+AG18 -> 164.99 | AH19: =AH17+AH18 -> -204.82 | AI19: =AI17+AI18 -> 111.22 | AJ19: =AJ17+AJ18 -> 552.13 | AK19: =AK17+AK18 -> 1920.76 | AL19: =AL17+AL18 -> 2029.74 | AN19: Profit before tax exceptional items and tax | AO19: =AO17+AO18 -> 429.031 | AP19: =AP17+AP18 -> 1006.608 | AQ19: =AQ17+AQ18 -> 2023.637 | AR19: =AR17+AR18 -> 2739.36 | AS19: =AS17+AS18 -> 3433.088
A20: Total Tax expenses | B20: =SUM(B17:B19) -> 443.79 | C20: =SUM(C17:C19) -> 384.02 | D20: =SUM(D17:D19) -> 571.72 | E20: =SUM(E17:E19) -> 681.75 | F20: =SUM(F17:F19) -> 925.72 | G20: =SUM(G17:G19) -> 965.22 | I20: Current tax | J20: -2243 | K20: -2520 | L20: -2840 | M20: -3001 | N20: -3521 | P20: Profit before tax | Q20: =Q18+Q19 -> 20034.57 | R20: =R18+R19 -> 17938.17 | S20: =S18+S19 -> 20740.47 | T20: =T18+T19 -> 25915.12 | U20: =U18+U19 -> 26400.28 | V20: =V18+V19 -> 26926.94 | X20: Profit before exceptional items and tax | Y20: =Y16+Y18+Y19 -> 2102 | Z20: =Z16+Z18+Z19 -> 1327 | AA20: =AA16+AA18+AA19 -> 2958 | AB20: =AB16+AB18+AB19 -> 4447 | AC20: =AC16+AC18+AC19 -> 4623 | AD20: =AD16+AD18+AD19 -> 4535 | AF20: Tax expense | AN20: Exceptional items | AO20: 66.529 | AP20: 0 | AQ20: 0 | AR20: 0 | AS20: 0
A21: Net profit after tax | B21: =B15-B20 -> 1300.98 | C21: =C15-C20 -> 1099.43 | D21: =D15-D20 -> 1492.4 | E21: =E15-E20 -> 2378.34 | F21: =F15-F20 -> 2535.61 | G21: =G15-G20 -> 2707.45 | I21: Deferred tax credit/charge | J21: -166 | K21: -86 | L21: -147 | M21: -200 | N21: -123 | P21: Tax expense | X21: Exceptional items | Y21: 0 | Z21: 0 | AA21: 54 | AB21: 0 | AC21: 0 | AD21: 0 | AF21: Current tax | AG21: 64.5 | AH21: 0.89 | AI21: 89.14 | AJ21: 170.44 | AK21: 343.28 | AL21: 487.71 | AN21: Profit before tax | AO21: =AO19-AO20 -> 362.502 | AP21: =AP19-AP20 -> 1006.608 | AQ21: =AQ19-AQ20 -> 2023.637 | AR21: =AR19-AR20 -> 2739.36 | AS21: =AS19-AS20 -> 3433.088
I22: Total tax expense | J22: =SUM(J20:J21) -> -2409 | K22: =SUM(K20:K21) -> -2606 | L22: =SUM(L20:L21) -> -2987 | M22: =SUM(M20:M21) -> -3201 | N22: =SUM(N20:N21) -> -3644 | P22: Current tax | Q22: 4846.15 | R22: 4463.74 | S22: 5306.58 | T22: 6450.9 | U22: 6017.21 | V22: 6509.61 | X22: Profit before tax | Y22: =Y20-Y21 -> 2102 | Z22: =Z20-Z21 -> 1327 | AA22: =AA20-AA21 -> 2904 | AB22: =AB20-AB21 -> 4447 | AC22: =AC20-AC21 -> 4623 | AD22: =AD20-AD21 -> 4535 | AF22: Deferred tax | AG22: -2.62 | AH22: -15.97 | AI22: -12.43 | AJ22: -11.83 | AK22: 100 | AL22: 7.65 | AN22: Tax expense
A23: COGS | B23: =B8+B9 -> 21102.93 | C23: =C8+C9 -> 20554.68 | D23: =D8+D9 -> 26397.39 | E23: =E8+E9 -> 36383.95 | F23: =F8+F9 -> 43274.54 | G23: =G8+G9 -> 50551.7 | I23: Profit after tax from continuing operations | J23: =J18+J22 -> 6764 | K23: =K18+K22 -> 8000 | L23: =L18+L22 -> 8887 | M23: =M18+M22 -> 10143 | N23: =N18+N22 -> 10282 | P23: Deferred tax | Q23: -404.36 | R23: 91.55 | S23: -69.24 | T23: -12.5 | U23: 192.25 | V23: 380.86 | X23: Tax expense | AF23: Short/Excess provision for tax | AG23: -2.87 | AH23: -8.61 | AI23: -0.09 | AJ23: -0.17 | AK23: 0.09 | AL23: -0.03 | AN23: Current tax | AO23: 42.385 | AP23: 134.198 | AQ23: 425.866 | AR23: 629.081 | AS23: 750.205
A24: Earnings growth | B24: =(B21-936)/936 -> 0.3899359 | C24: =(C21-B21)/B21 -> -0.15492167 | D24: =(D21-C21)/C21 -> 0.35743067 | E24: =(E21-D21)/D21 -> 0.59363441 | F24: =(F21-E21)/E21 -> 0.066125953 | G24: =(G21-F21)/F21 -> 0.067770675 | I24: Profit/Loss from discontinued operations before tax | J24: -6 | K24: -1 | L24: 3 | M24: 0 | N24: 0 | P24: Total tax expense | Q24: =SUM(Q22:Q23) -> 4441.79 | R24: =SUM(R22:R23) -> 4555.29 | S24: =SUM(S22:S23) -> 5237.34 | T24: =SUM(T22:T23) -> 6438.4 | U24: =SUM(U22:U23) -> 6209.46 | V24: =SUM(V22:V23) -> 6890.47 | X24: Current tax | Y24: 570 | Z24: 360 | AA24: 786 | AB24: 1150 | AC24: 1101 | AD24: 1183 | AF24: Total tax expense | AG24: =SUM(AG21:AG23) -> 59.01 | AH24: =SUM(AH21:AH23) -> -23.69 | AI24: =SUM(AI21:AI23) -> 76.62 | AJ24: =SUM(AJ21:AJ23) -> 158.44 | AK24: =SUM(AK21:AK23) -> 443.37 | AL24: =SUM(AL21:AL23) -> 495.33 | AN24: Adjustment of tax relating to earlier periods | AO24: 15.369 | AP24: 35.006 | AQ24: 22.691 | AR24: 2.055 | AS24: 0.528
A25: Trade payables | B25: ='Balance Sheet'!B49+'Balance Sheet'!B50 -> 433.45 | C25: ='Balance Sheet'!C49+'Balance Sheet'!C50 -> 578.13 | D25: ='Balance Sheet'!D49+'Balance Sheet'!D50 -> 589.2 | E25: ='Balance Sheet'!E49+'Balance Sheet'!E50 -> 753.79 | F25: ='Balance Sheet'!F49+'Balance Sheet'!F50 -> 984.81 | G25: ='Balance Sheet'!G49+'Balance Sheet'!G50 -> 1070.81 | I25: Tax expenses of discontinued operations | J25: -2 | K25: 0 | L25: 2 | M25: 0 | N25: 0 | P25: Profit for the year from continuing operations | Q25: =Q20-Q24 -> 15592.78 | R25: =R20-R24 -> 13382.88 | S25: =S20-S24 -> 15503.13 | T25: =T20-T24 -> 19476.72 | U25: =U20-U24 -> 20190.82 | V25: =V20-V24 -> 20036.47 | X25: Deferred tax | Y25: 39 | Z25: -7 | AA25: -80 | AB25: 26 | AC25: 26 | AD25: 15 | AF25: Profit/Loss for the year | AG25: =AG19-AG24 -> 105.98 | AH25: =AH19-AH24 -> -181.13 | AI25: =AI19-AI24 -> 34.6 | AJ25: =AJ19-AJ24 -> 393.69 | AK25: =AK19-AK24 -> 1477.39 | AL25: =AL19-AL24 -> 1534.41 | AN25: Deferred tax credit/expense | AO25: -52.52 | AP25: 91.352 | AQ25: 24.966 | AR25: 6.411 | AS25: 48.071
A26: TP:COGS | B26: =B25/B23 -> 0.020539802 | C26: =C25/C23 -> 0.028126441 | D26: =D25/D23 -> 0.022320388 | E26: =E25/E23 -> 0.020717652 | F26: =F25/F23 -> 0.022757261 | G26: =G25/G23 -> 0.021182473 | I26: Profit/Loss from discontinued operations after tax | J26: =J24+J25 -> -8 | K26: =K24+K25 -> -1 | L26: =L24+L25 -> 5 | M26: =M24+M25 -> 0 | N26: =N24+N25 -> 0 | P26: Profit before exceptional items and tax from dis cont opt | Q26: 0 | R26: 0 | S26: 0 | T26: 0 | U26: 747.17 | V26: 525.84 | X26: Tax expense of earlier year | Y26: 0 | Z26: 0 | AA26: 0 | AB26: -3 | AC26: 0 | AD26: 0 | AN26: Total tax expense | AO26: =SUM(AO23:AO25) -> 5.234 | AP26: =SUM(AP23:AP25) -> 260.556 | AQ26: =SUM(AQ23:AQ25) -> 473.523 | AR26: =SUM(AR23:AR25) -> 637.547 | AS26: =SUM(AS23:AS25) -> 798.804
B27: =AVERAGE(B26:G26) -> 0.022607336 | I27: Profit for the year | J27: =SUM(J23+J26) -> 6756 | K27: =SUM(K23+K26) -> 7999 | L27: =SUM(L23+L26) -> 8892 | M27: =SUM(M23+M26) -> 10143 | N27: =SUM(N23+N26) -> 10282 | P27: Exceptional items of discontinued operations | Q27: 0 | R27: 0 | S27: 0 | T27: 0 | U27: -7.57 | V27: 15128.81 | X27: Total tax | Y27: =SUM(Y24:Y26) -> 609 | Z27: =SUM(Z24:Z26) -> 353 | AA27: =SUM(AA24:AA26) -> 706 | AB27: =SUM(AB24:AB26) -> 1173 | AC27: =SUM(AC24:AC26) -> 1127 | AD27: =SUM(AD24:AD26) -> 1198 | AN27: Profit/Loss for the year | AO27: =AO21-AO26 -> 357.268 | AP27: =AP21-AP26 -> 746.052 | AQ27: =AQ21-AQ26 -> 1550.114 | AR27: =AR21-AR26 -> 2101.813 | AS27: =AS21-AS26 -> 2634.284
P28: Tax expense of discontinued operations | Q28: 0 | R28: 0 | S28: 0 | T28: 0 | U28: 179.06 | V28: 638.64 | X28: Profit for the year | Y28: =Y22-Y27 -> 1493 | Z28: =Z22-Z27 -> 974 | AA28: =AA22-AA27 -> 2198 | AB28: =AB22-AB27 -> 3274 | AC28: =AC22-AC27 -> 3496 | AD28: =AD22-AD27 -> 3337
P29: Profit for the year from discontinuing operations | Q29: =Q26+Q27-Q28 -> 0 | R29: =R26+R27-R28 -> 0 | S29: =S26+S27-S28 -> 0 | T29: =T26+T27-T28 -> 0 | U29: =U26+U27-U28 -> 560.54 | V29: =V26+V27-V28 -> 15016.01
P30: Profit for the year | Q30: =Q25+Q29 -> 15592.78 | R30: =R25+R29 -> 13382.88 | S30: =S25+S29 -> 15503.13 | T30: =T25+T29 -> 19476.72 | U30: =U25+U29 -> 20751.36 | V30: =V25+V29 -> 35052.48

Sheet Common Size Income Statement
A1: Common Size Income Statement | F1: #VALUE! | I1: Common Size Income Statement | M1: #VALUE! | P1: Common Size Income Statement | U1: #VALUE! | X1: Common Size Income Statement | AC1: #VALUE! | AF1: Common Size Income Statement | AK1: #VALUE! | AN1: Common Size Income Statement | AR1: #VALUE!
A2: Particulars | B2: 2020 | C2: 2021 | D2: 2022 | E2: 2023 | F2: 2024 | G2: 2025 | I2: Particulars | J2: 2020 | K2: 2021 | L2: 2022 | M2: 2023 | N2: 2024 | P2: Particulars | Q2: 2020 | R2: 2021 | S2: 2022 | T2: 2023 | U2: 2024 | V2: 2025 | X2: Particulars | Y2: 2020 | Z2: 2021 | AA2: 2022 | AB2: 2023 | AC2: 2024 | AD2: 2025 | AF2: Particulars | AG2: 2020 | AH2: 2021 | AI2: 2022 | AJ2: 2023 | AK2: 2024 | AL2: 2025 | AN2: Particulars | AO2: 2020 | AP2: 2021 | AQ2: 2022 | AR2: 2023 | AS2: 2024
A3: Revenue (Net Sales) | B3: 1 | C3: 1 | D3: 1 | E3: 1 | F3: 1 | G3: 1 | I3: =A3 -> Revenue (Net Sales) | J3: 1 | K3: 1 | L3: 1 | M3: 1 | N3: 1 | P3: =I3 -> Revenue (Net Sales) | Q3: 1 | R3: 1 | S3: 1 | T3: 1 | U3: 1 | V3: 1 | X3: =P3 -> Revenue (Net Sales) | Y3: 1 | Z3: 1 | AA3: 1 | AB3: 1 | AC3: 1 | AD3: 1 | AF3: Revenue (Net Sales) | AG3: 1 | AH3: 1 | AI3: 1 | AJ3: 1 | AK3: 1 | AL3: 1 | AN3: Revenue (Net Sales) | AO3: 1 | AP3: 1 | AQ3: 1 | AR3: 1 | AS3: 1
A4: Cost of Goods sold | B4: =('Income Statement'!B8+'Income Statement'!B9)/Dmart_IS[[#This Row],[2020]] -> 0.84852273 | C4: =('Income Statement'!C8+'Income Statement'!C9)/Dmart_IS[[#This Row],[2021]] -> 0.85137012 | D4: =('Income Statement'!D8+'Income Statement'!D9)/Dmart_IS[[#This Row],[2022]] -> 0.85218104 | E4: =('Income Statement'!E8+'Income Statement'!E9)/Dmart_IS[[#This Row],[2023]] -> 0.84930728 | F4: =('Income Statement'!F8+'Income Statement'!F9)/Dmart_IS[[#This Row],[2024]] -> 0.85204837 | G4: =('Income Statement'!G8+'Income Statement'!G9)/Dmart_IS[[#This Row],[2025]] -> 0.85164017 | I4: =A4 -> Cost of Goods sold | J4: =('Income Statement'!J8+'Income Statement'!J9+'Income Statement'!J10)/HUL_IS[[#This Row],[2020]] -> 0.45896488 | K4: =('Income Statement'!K8+'Income Statement'!K9+'Income Statement'!K10)/HUL_IS[[#This Row],[2021]] -> 0.47095347 | L4: =('Income Statement'!L8+'Income Statement'!L9+'Income Statement'!L10)/HUL_IS[[#This Row],[2022]] -> 0.49069519 | M4: =('Income Statement'!M8+'Income Statement'!M9+'Income Statement'!M10)/HUL_IS[[#This Row],[2023]] -> 0.52353912 | N4: =('Income Statement'!N8+'Income Statement'!N9+'Income Statement'!N10)/HUL_IS[[#This Row],[2024]] -> 0.48080651 | P4: =I4 -> Cost of Goods sold | Q4: =('Income Statement'!Q8+'Income Statement'!Q9+'Income Statement'!Q10)/ITC_IS[[#This Row],[2020]] -> 0.33750338 | R4: =('Income Statement'!R8+'Income Statement'!R9+'Income Statement'!R10)/ITC_IS[[#This Row],[2021]] -> 0.37873003 | S4: =('Income Statement'!S8+'Income Statement'!S9+'Income Statement'!S10)/ITC_IS[[#This Row],[2022]] -> 0.4046482 | T4: =('Income Statement'!T8+'Income Statement'!T9+'Income Statement'!T10)/ITC_IS[[#This Row],[2023]] -> 0.37907016 | U4: =('Income Statement'!U8+'Income Statement'!U9+'Income Statement'!U10)/ITC_IS[[#This Row],[2024]] -> 0.36514113 | V4: =('Income Statement'!V8+'Income Statement'!V9+'Income Statement'!V10)/ITC_IS[[#This Row],[2025]] -> 0.39183471 | X4: =P4 -> Cost of Goods sold | Y4: =('Income Statement'!Y8+'Income Statement'!Y9+'Income Statement'!Y10)/Titan_IS[[#This Row],[2020]] -> 0.7198841 | Z4: =('Income Statement'!Z8+'Income Statement'!Z9+'Income Statement'!Z10)/Titan_IS[[#This Row],[2021]] -> 0.75836259 | AA4: =('Income Statement'!AA8+'Income Statement'!AA9+'Income Statement'!AA10)/Titan_IS[[#This Row],[2022]] -> 0.7514497 | AB4: =('Income Statement'!AB8+'Income Statement'!AB9+'Income Statement'!AB10)/Titan_IS[[#This Row],[2023]] -> 0.74812076 | AC4: =('Income Statement'!AC8+'Income Statement'!AC9+'Income Statement'!AC10)/Titan_IS[[#This Row],[2024]] -> 0.7719051 | AD4: =('Income Statement'!AD8+'Income Statement'!AD9+'Income Statement'!AD10)/Titan_IS[[#This Row],[2025]] -> 0.78496758 | AF4: Cost of Goods sold | AG4: =('Income Statement'!AG8+'Income Statement'!AG9)/Trent_IS[[#This Row],[2020]] -> 0.53980516 | AH4: =('Income Statement'!AH8+'Income Statement'!AH9)/Trent_IS[[#This Row],[2021]] -> 0.59160188 | AI4: =('Income Statement'!AI8+'Income Statement'!AI9)/Trent_IS[[#This Row],[2022]] -> 0.55169608 | AJ4: =('Income Statement'!AJ8+'Income Statement'!AJ9)/Trent_IS[[#This Row],[2023]] -> 0.5726436 | AK4: =('Income Statement'!AK8+'Income Statement'!AK9)/Trent_IS[[#This Row],[2024]] -> 0.56232955 | AL4: =('Income Statement'!AL8+'Income Statement'!AL9)/Trent_IS[[#This Row],[2025]] -> 0.56547187 | AN4: Cost of Goods sold | AO4: =('Income Statement'!AO8+'Income Statement'!AO10+'Income Statement'!AO11)/VBL_IS[[#This Row],[2020]] -> 0.42160243 | AP4: =('Income Statement'!AP8+'Income Statement'!AP10+'Income Statement'!AP11)/VBL_IS[[#This Row],[2021]] -> 0.45038278 | AQ4: =('Income Statement'!AQ8+'Income Statement'!AQ10+'Income Statement'!AQ11)/VBL_IS[[#This Row],[2022]] -> 0.46757992 | AR4: =('Income Statement'!AR8+'Income Statement'!AR10+'Income Statement'!AR11)/VBL_IS[[#This Row],[2023]] -> 0.45370133 | AS4: =('Income Statement'!AS8+'Income Statement'!AS10+'Income Statement'!AS11)/VBL_IS[[#This Row],[2024]] -> 0.43477278
A5: Gross Profit | B5: =B3-B4 -> 0.15147727 | C5: =C3-C4 -> 0.14862988 | D5: =D3-D4 -> 0.14781896 | E5: =E3-E4 -> 0.15069272 | F5: =F3-F4 -> 0.14795163 | G5: =G3-G4 -> 0.14835983 | I5: =A5 -> Gross Profit | J5: =J3-J4 -> 0.54103512 | K5: =K3-K4 -> 0.52904653 | L5: =L3-L4 -> 0.50930481 | M5: =M3-M4 -> 0.47646088 | N5: =N3-N4 -> 0.51919349 | P5: =I5 -> Gross Profit | Q5: =Q3-Q4 -> 0.66249662 | R5: =R3-R4 -> 0.62126997 | S5: =S3-S4 -> 0.5953518 | T5: =T3-T4 -> 0.62092984 | U5: =U3-U4 -> 0.63485887 | V5: =V3-V4 -> 0.60816529 | X5: =P5 -> Gross Profit | Y5: =Y3-Y4 -> 0.2801159 | Z5: =Z3-Z4 -> 0.24163741 | AA5: =AA3-AA4 -> 0.2485503 | AB5: =AB3-AB4 -> 0.25187924 | AC5: =AC3-AC4 -> 0.2280949 | AD5: =AD3-AD4 -> 0.21503242 | AF5: Gross Profit | AG5: =AG3-AG4 -> 0.46019484 | AH5: =AH3-AH4 -> 0.40839812 | AI5: =AI3-AI4 -> 0.44830392 | AJ5: =AJ3-AJ4 -> 0.4273564 | AK5: =AK3-AK4 -> 0.43767045 | AL5: =AL3-AL4 -> 0.43452813 | AN5: Gross Profit | AO5: =AO3-AO4 -> 0.57839757 | AP5: =AP3-AP4 -> 0.54961722 | AQ5: =AQ3-AQ4 -> 0.53242008 | AR5: =AR3-AR4 -> 0.54629867 | AS5: =AS3-AS4 -> 0.56522722
A6: Employee benefit expense | B6: ='Income Statement'!B10/'Income Statement'!B4 -> 0.018339217 | C6: ='Income Statement'!C10/'Income Statement'!C4 -> 0.022224606 | D6: ='Income Statement'!D10/'Income Statement'!D4 -> 0.01989297 | E6: ='Income Statement'!E10/'Income Statement'!E4 -> 0.017436454 | F6: ='Income Statement'!F10/'Income Statement'!F4 -> 0.017840931 | G6: ='Income Statement'!G10/'Income Statement'!G4 -> 0.019641818 | I6: =A6 -> Employee benefit expense | J6: ='Income Statement'!J11/'Income Statement'!J4 -> 0.045748184 | K6: ='Income Statement'!K11/'Income Statement'!K4 -> 0.050140342 | L6: ='Income Statement'!L11/'Income Statement'!L4 -> 0.048526103 | M6: ='Income Statement'!M11/'Income Statement'!M4 -> 0.047111258 | N6: ='Income Statement'!N11/'Income Statement'!N4 -> 0.048613804 | P6: =I6 -> Employee benefit expense | Q6: ='Income Statement'!Q12/'Income Statement'!Q4 -> 0.0835863 | R6: ='Income Statement'!R12/'Income Statement'!R4 -> 0.083968017 | S6: ='Income Statement'!S12/'Income Statement'!S4 -> 0.07500273 | T6: ='Income Statement'!T12/'Income Statement'!T4 -> 0.074965423 | U6: ='Income Statement'!U12/'Income Statement'!U4 -> 0.075090305 | V6: ='Income Statement'!V12/'Income Statement'!V4 -> 0.075598209 | X6: =P6 -> Employee benefit expense | Y6: ='Income Statement'!Y11/'Income Statement'!Y4 -> 0.056954209 | Z6: ='Income Statement'!Z11/'Income Statement'!Z4 -> 0.049205322 | AA6: ='Income Statement'!AA11/'Income Statement'!AA4 -> 0.046841904 | AB6: ='Income Statement'!AB11/'Income Statement'!AB4 -> 0.040591497 | AC6: ='Income Statement'!AC11/'Income Statement'!AC4 -> 0.03648892 | AD6: ='Income Statement'!AD11/'Income Statement'!AD4 -> 0.0356623 | AF6: Employee benefit expense | AG6: ='Income Statement'!AG10/'Income Statement'!AG4 -> 0.10284626 | AH6: ='Income Statement'!AH10/'Income Statement'!AH4 -> 0.11641522 | AI6: ='Income Statement'!AI10/'Income Statement'!AI4 -> 0.088694581 | AJ6: ='Income Statement'!AJ10/'Income Statement'!AJ4 -> 0.079498715 | AK6: ='Income Statement'!AK10/'Income Statement'!AK4 -> 0.083768144 | AL6: ='Income Statement'!AL10/'Income Statement'!AL4 -> 0.076362987 | AN6: Employee benefit expense | AO6: ='Income Statement'!AO12/'Income Statement'!AO4 -> 0.13571759 | AP6: ='Income Statement'!AP12/'Income Statement'!AP4 -> 0.11248786 | AQ6: ='Income Statement'!AQ12/'Income Statement'!AQ4 -> 0.0908582 | AR6: ='Income Statement'!AR12/'Income Statement'!AR4 -> 0.088633136 | AS6: ='Income Statement'!AS12/'Income Statement'!AS4 -> 0.092036317
A7: Other expenses (Office, administrative & operating) | B7: ='Income Statement'!B13/'Income Statement'!B4 -> 0.047561338 | C7: ='Income Statement'!C13/'Income Statement'!C4 -> 0.054208539 | D7: ='Income Statement'!D13/'Income Statement'!D4 -> 0.047267473 | E7: ='Income Statement'!E13/'Income Statement'!E4 -> 0.048357406 | F7: ='Income Statement'!F13/'Income Statement'!F4 -> 0.049310055 | G7: ='Income Statement'!G13/'Income Statement'!G4 -> 0.053120343 | I7: =A7 -> Other expenses (Office, administrative & operating) | J7: ='Income Statement'!J14/'Income Statement'!J4 -> 0.24741724 | K7: ='Income Statement'!K14/'Income Statement'!K4 -> 0.23169176 | L7: ='Income Statement'!L14/'Income Statement'!L4 -> 0.21563132 | M7: ='Income Statement'!M14/'Income Statement'!M4 -> 0.1958072 | N7: ='Income Statement'!N14/'Income Statement'!N4 -> 0.23368231 | P7: =I7 -> Other expenses (Office, administrative & operating) | Q7: =('Income Statement'!Q15+'Income Statement'!Q11)/'Income Statement'!Q4 -> 0.20415142 | R7: =('Income Statement'!R15+'Income Statement'!R11)/'Income Statement'!R4 -> 0.21743249 | S7: =('Income Statement'!S15+'Income Statement'!S11)/'Income Statement'!S4 -> 0.20352639 | T7: =('Income Statement'!T15+'Income Statement'!T11)/'Income Statement'!T4 -> 0.21055498 | U7: =('Income Statement'!U15+'Income Statement'!U11)/'Income Statement'!U4 -> 0.21805384 | V7: =('Income Statement'!V15+'Income Statement'!V11)/'Income Statement'!V4 -> 0.21425652 | X7: =P7 -> Other expenses (Office, administrative & operating) | Y7: ='Income Statement'!Y14/'Income Statement'!Y4 -> 0.10597568 | Z7: ='Income Statement'!Z14/'Income Statement'!Z4 -> 0.11277952 | AA7: ='Income Statement'!AA14/'Income Statement'!AA4 -> 0.08569742 | AB7: ='Income Statement'!AB14/'Income Statement'!AB4 -> 0.091041282 | AC7: ='Income Statement'!AC14/'Income Statement'!AC4 -> 0.088011902 | AD7: ='Income Statement'!AD14/'Income Statement'!AD4 -> 0.08518592 | AF7: Other expenses (Office, administrative & operating) | AG7: ='Income Statement'!AG13/'Income Statement'!AG4 -> 0.20271774 | AH7: ='Income Statement'!AH13/'Income Statement'!AH4 -> 0.22568802 | AI7: ='Income Statement'!AI13/'Income Statement'!AI4 -> 0.23202654 | AJ7: ='Income Statement'!AJ13/'Income Statement'!AJ4 -> 0.21759229 | AK7: ='Income Statement'!AK13/'Income Statement'!AK4 -> 0.19858005 | AL7: ='Income Statement'!AL13/'Income Statement'!AL4 -> 0.19717811 | AN7: Other expenses (Office, administrative & operating) | AO7: =('Income Statement'!AO15+'Income Statement'!AO9)/'Income Statement'!AO4 -> 0.25935089 | AP7: =('Income Statement'!AP15+'Income Statement'!AP9)/'Income Statement'!AP4 -> 0.25242393 | AQ7: =('Income Statement'!AQ15+'Income Statement'!AQ9)/'Income Statement'!AQ4 -> 0.23334763 | AR7: =('Income Statement'!AR15+'Income Statement'!AR9)/'Income Statement'!AR4 -> 0.23651051 | AS7: =('Income Statement'!AS15+'Income Statement'!AS9)/'Income Statement'!AS4 -> 0.24317305
A8: EBITDA (Operating Profit) | B8: =('Income Statement'!B15+'Income Statement'!B10+'Income Statement'!B13)/'Income Statement'!B4 -> 0.1360556 | C8: =('Income Statement'!C15+'Income Statement'!C10+'Income Statement'!C13)/'Income Statement'!C4 -> 0.1378773 | D8: =('Income Statement'!D15+'Income Statement'!D10+'Income Statement'!D13)/'Income Statement'!D4 -> 0.13379597 | E8: =('Income Statement'!E15+'Income Statement'!E10+'Income Statement'!E13)/'Income Statement'!E4 -> 0.13722527 | F8: =('Income Statement'!F15+'Income Statement'!F10+'Income Statement'!F13)/'Income Statement'!F4 -> 0.13530239 | G8: =('Income Statement'!G15+'Income Statement'!G10+'Income Statement'!G13)/'Income Statement'!G4 -> 0.13463532 | I8: =A8 -> EBITDA (Operating Profit) | J8: =J5-J6-J7 -> 0.24786969 | K8: =K5-K6-K7 -> 0.24721443 | L8: =L5-L6-L7 -> 0.24514739 | M8: =M5-M6-M7 -> 0.23354242 | N8: =N5-N6-N7 -> 0.23689738 | P8: =I8 -> EBITDA (Operating Profit) | Q8: =Q5-Q6-Q7 -> 0.37475889 | R8: =R5-R6-R7 -> 0.31986947 | S8: =S5-S6-S7 -> 0.31682268 | T8: =T5-T6-T7 -> 0.33540944 | U8: =U5-U6-U7 -> 0.34171473 | V8: =V5-V6-V7 -> 0.31831056 | X8: =P8 -> EBITDA (Operating Profit) | Y8: =Y5-Y6-Y7 -> 0.11718602 | Z8: =Z5-Z6-Z7 -> 0.07965256 | AA8: =AA5-AA6-AA7 -> 0.11601097 | AB8: =AB5-AB6-AB7 -> 0.12024646 | AC8: =AC5-AC6-AC7 -> 0.10359408 | AD8: =AD5-AD6-AD7 -> 0.0941842 | AF8: EBITDA (Operating Profit) | AG8: =AG5-AG6-AG7 -> 0.15463084 | AH8: =AH5-AH6-AH7 -> 0.066294891 | AI8: =AI5-AI6-AI7 -> 0.1275828 | AJ8: =AJ5-AJ6-AJ7 -> 0.1302654 | AK8: =AK5-AK6-AK7 -> 0.15532226 | AL8: =AL5-AL6-AL7 -> 0.16098703 | AN8: EBITDA (Operating Profit) | AO8: =AO5-AO6-AO7 -> 0.18332909 | AP8: =AP5-AP6-AP7 -> 0.18470543 | AQ8: =AQ5-AQ6-AQ7 -> 0.20821425 | AR8: =AR5-AR6-AR7 -> 0.22115502 | AS8: =AS5-AS6-AS7 -> 0.23001785
A9: Depreciation & Amortisation expenses | B9: ='Income Statement'!B12/'Income Statement'!B4 -> 0.015054563 | C9: ='Income Statement'!C12/'Income Statement'!C4 -> 0.017154412 | D9: ='Income Statement'!D12/'Income Statement'!D4 -> 0.016079405 | E9: ='Income Statement'!E12/'Income Statement'!E4 -> 0.014913085 | F9: ='Income Statement'!F12/'Income Statement'!F4 -> 0.014388203 | G9: ='Income Statement'!G12/'Income Statement'!G4 -> 0.014648729 | I9: =A9 -> Depreciation & Amortisation expenses | J9: ='Income Statement'!J13/'Income Statement'!J4 -> 0.025186638 | K9: ='Income Statement'!K13/'Income Statement'!K4 -> 0.022837459 | L9: ='Income Statement'!L13/'Income Statement'!L4 -> 0.020802349 | M9: ='Income Statement'!M13/'Income Statement'!M4 -> 0.01876857 | N9: ='Income Statement'!N13/'Income Statement'!N4 -> 0.019645858 | P9: =I9 -> Depreciation & Amortisation expenses | Q9: ='Income Statement'!Q14/'Income Statement'!Q4 -> 0.032006206 | R9: ='Income Statement'!R14/'Income Statement'!R4 -> 0.03095826 | S9: ='Income Statement'!S14/'Income Statement'!S4 -> 0.026568684 | T9: ='Income Statement'!T14/'Income Statement'!T4 -> 0.023641562 | U9: ='Income Statement'!U14/'Income Statement'!U4 -> 0.020544331 | V9: ='Income Statement'!V14/'Income Statement'!V4 -> 0.020172331 | X9: =P9 -> Depreciation & Amortisation expenses | Y9: ='Income Statement'!Y13/'Income Statement'!Y4 -> 0.016530496 | Z9: ='Income Statement'!Z13/'Income Statement'!Z4 -> 0.017325818 | AA9: ='Income Statement'!AA13/'Income Statement'!AA4 -> 0.013854648 | AB9: ='Income Statement'!AB13/'Income Statement'!AB4 -> 0.010868762 | AC9: ='Income Statement'!AC13/'Income Statement'!AC4 -> 0.011432151 | AD9: ='Income Statement'!AD13/'Income Statement'!AD4 -> 0.011462882 | AF9: Depreciation & Amortisation expenses | AG9: ='Income Statement'!AG12/'Income Statement'!AG4 -> 0.070924102 | AH9: ='Income Statement'!AH12/'Income Statement'!AH4 -> 0.099230223 | AI9: ='Income Statement'!AI12/'Income Statement'!AI4 -> 0.069101516 | AJ9: ='Income Statement'!AJ12/'Income Statement'!AJ4 -> 0.059899151 | AK9: ='Income Statement'!AK12/'Income Statement'!AK4 -> 0.054230629 | AL9: ='Income Statement'!AL12/'Income Statement'!AL4 -> 0.052243967 | AN9: Depreciation & Amortisation expenses | AO9: ='Income Statement'!AO14/'Income Statement'!AO4 -> 0.080646573 | AP9: ='Income Statement'!AP14/'Income Statement'!AP4 -> 0.059303945 | AQ9: ='Income Statement'!AQ14/'Income Statement'!AQ4 -> 0.046091358 | AR9: ='Income Statement'!AR14/'Income Statement'!AR4 -> 0.041719464 | AS9: ='Income Statement'!AS14/'Income Statement'!AS4 -> 0.046256083
A10: EBIT | B10: =B8-B9 -> 0.12100104 | C10: =C8-C9 -> 0.12072289 | D10: =D8-D9 -> 0.11771656 | E10: =E8-E9 -> 0.12231218 | F10: =F8-F9 -> 0.12091419 | G10: =G8-G9 -> 0.11998659 | I10: =A10 -> EBIT | J10: =J8-J9 -> 0.22268306 | K10: =K8-K9 -> 0.22437697 | L10: =L8-L9 -> 0.22434504 | M10: =M8-M9 -> 0.21477385 | N10: =N8-N9 -> 0.21725152 | P10: =I10 -> EBIT | Q10: =('Income Statement'!Q18+'Income Statement'!Q13)/'Income Statement'!Q4 -> 0.39346166 | R10: =('Income Statement'!R18+'Income Statement'!R13)/'Income Statement'!R4 -> 0.33830702 | S10: =('Income Statement'!S18+'Income Statement'!S13)/'Income Statement'!S4 -> 0.31868481 | T10: =('Income Statement'!T18+'Income Statement'!T13)/'Income Statement'!T4 -> 0.33829137 | U10: =('Income Statement'!U18+'Income Statement'!U13)/'Income Statement'!U4 -> 0.35781403 | V10: =('Income Statement'!V18+'Income Statement'!V13)/'Income Statement'!V4 -> 0.33048746 | X10: =P10 -> EBIT | Y10: =Y8-Y9 -> 0.10065552 | Z10: =Z8-Z9 -> 0.062326742 | AA10: =AA8-AA9 -> 0.10215632 | AB10: =AB8-AB9 -> 0.1093777 | AC10: =AC8-AC9 -> 0.092161929 | AD10: =AD8-AD9 -> 0.082721318 | AF10: EBIT | AG10: =AG8-AG9 -> 0.083706734 | AH10: =AH8-AH9 -> -0.032935333 | AI10: =AI8-AI9 -> 0.058481287 | AJ10: =AJ8-AJ9 -> 0.070366245 | AK10: =AK8-AK9 -> 0.10109163 | AL10: =AL8-AL9 -> 0.10874306 | AN10: EBIT | AO10: =AO8-AO9 -> 0.10268251 | AP10: =AP8-AP9 -> 0.12540149 | AQ10: =AQ8-AQ9 -> 0.16212289 | AR10: =AR8-AR9 -> 0.17943556 | AS10: =AS8-AS9 -> 0.18376177
A11: Finance cost | B11: =Dmart_IS[[#This Row],[2020]]/'Income Statement'!B6 -> 0.002772542 | C11: =Dmart_IS[[#This Row],[2021]]/'Income Statement'!C6 -> 0.0017112263 | D11: =Dmart_IS[[#This Row],[2022]]/'Income Statement'!D6 -> 0.0017299291 | E11: =Dmart_IS[[#This Row],[2023]]/'Income Statement'!E6 -> 0.0015688091 | F11: =Dmart_IS[[#This Row],[2024]]/'Income Statement'!F6 -> 0.0011412522 | G11: =Dmart_IS[[#This Row],[2025]]/'Income Statement'!G6 -> 0.001167573 | I11: =A11 -> Finance cost | J11: ='Income Statement'!J12/'Income Statement'!J6 -> 0.002919708 | K11: ='Income Statement'!K12/'Income Statement'!K6 -> 0.0024663772 | L11: ='Income Statement'!L12/'Income Statement'!L6 -> 0.0020112325 | M11: ='Income Statement'!M12/'Income Statement'!M6 -> 0.0018660381 | N11: ='Income Statement'!N12/'Income Statement'!N6 -> 0.0053263591 | P11: =I11 -> Finance cost | Q11: ='Income Statement'!Q13/'Income Statement'!Q4 -> 0.0010639484 | R11: ='Income Statement'!R13/'Income Statement'!R4 -> 0.00083867744 | S11: ='Income Statement'!S13/'Income Statement'!S4 -> 0.00060363506 | T11: ='Income Statement'!T13/'Income Statement'!T4 -> 0.00056457149 | U11: ='Income Statement'!U13/'Income Statement'!U4 -> 0.00052929007 | V11: ='Income Statement'!V13/'Income Statement'!V4 -> 0.00055211941 | X11: =P11 -> Finance cost | Y11: ='Income Statement'!Y12/'Income Statement'!Y4 -> 0.0078852366 | Z11: ='Income Statement'!Z12/'Income Statement'!Z4 -> 0.0093790427 | AA11: ='Income Statement'!AA12/'Income Statement'!AA4 -> 0.0075697073 | AB11: ='Income Statement'!AB12/'Income Statement'!AB4 -> 0.0073937153 | AC11: ='Income Statement'!AC12/'Income Statement'!AC4 -> 0.012117297 | AD11: ='Income Statement'!AD12/'Income Statement'!AD4 -> 0.015763531 | AF11: Finance cost | AG11: =Trent_IS[[#This Row],[2020]]/'Income Statement'!AG4 -> 0.070511018 | AH11: =Trent_IS[[#This Row],[2021]]/'Income Statement'!AH4 -> 0.095894268 | AI11: =Trent_IS[[#This Row],[2022]]/'Income Statement'!AI4 -> 0.06774981 | AJ11: =Trent_IS[[#This Row],[2023]]/'Income Statement'!AJ4 -> 0.044797271 | AK11: =Trent_IS[[#This Row],[2024]]/'Income Statement'!AK4 -> 0.025785629 | AL11: =Trent_IS[[#This Row],[2025]]/'Income Statement'!AL4 -> 0.0080883078 | AN11: Finance cost | AO11: ='Income Statement'!AO13/'Income Statement'!AO4 -> 0.042878738 | AP11: ='Income Statement'!AP13/'Income Statement'!AP4 -> 0.020617772 | AQ11: ='Income Statement'!AQ13/'Income Statement'!AQ4 -> 0.013899495 | AR11: ='Income Statement'!AR13/'Income Statement'!AR4 -> 0.016426565 | AS11: ='Income Statement'!AS13/'Income Statement'!AS4 -> 0.021990078
A12: Other income | B12: ='Income Statement'!B5/'Income Statement'!B4 -> 0.0024121237 | C12: ='Income Statement'!C5/'Income Statement'!C4 -> 0.0081269731 | D12: ='Income Statement'!D5/'Income Statement'!D4 -> 0.0037929034 | E12: ='Income Statement'!E5/'Income Statement'!E4 -> 0.003019172 | F12: ='Income Statement'!F5/'Income Statement'!F4 -> 0.002883508 | G12: ='Income Statement'!G5/'Income Statement'!G4 -> 0.00209424 | I12: =A12 -> Other income | J12: ='Income Statement'!J5/'Income Statement'!J4 -> 0.015886183 | K12: ='Income Statement'!K5/'Income Statement'!K4 -> 0.0087182104 | L12: ='Income Statement'!L5/'Income Statement'!L4 -> 0.0049193456 | M12: ='Income Statement'!M5/'Income Statement'!M4 -> 0.0084516342 | N12: ='Income Statement'!N5/'Income Statement'!N4 -> 0.013102624 | P12: =I12 -> Other income | Q12: ='Income Statement'!Q5/'Income Statement'!Q4 -> 0.050549029 | R12: ='Income Statement'!R5/'Income Statement'!R4 -> 0.049525991 | S12: ='Income Statement'!S5/'Income Statement'!S4 -> 0.028162735 | T12: ='Income Statement'!T5/'Income Statement'!T4 -> 0.025882597 | U12: ='Income Statement'!U5/'Income Statement'!U4 -> 0.03644834 | V12: ='Income Statement'!V5/'Income Statement'!V4 -> 0.030996248 | X12: =P12 -> Other income | Y12: ='Income Statement'!Y5/'Income Statement'!Y4 -> 0.007267718 | Z12: ='Income Statement'!Z5/'Income Statement'!Z4 -> 0.0085936056 | AA12: ='Income Statement'!AA5/'Income Statement'!AA4 -> 0.0081252821 | AB12: ='Income Statement'!AB5/'Income Statement'!AB4 -> 0.0075908811 | AC12: ='Income Statement'!AC5/'Income Statement'!AC4 -> 0.010433795 | AD12: ='Income Statement'!AD5/'Income Statement'!AD4 -> 0.0080389043 | AF12: Other income | AG12: ='Income Statement'!AG5/'Income Statement'!AG4 -> 0.042863126 | AH12: ='Income Statement'!AH5/'Income Statement'!AH4 -> 0.077748982 | AI12: ='Income Statement'!AI5/'Income Statement'!AI4 -> 0.038952695 | AJ12: ='Income Statement'!AJ5/'Income Statement'!AJ4 -> 0.031657288 | AK12: ='Income Statement'!AK5/'Income Statement'!AK4 -> 0.023375146 | AL12: ='Income Statement'!AL5/'Income Statement'!AL4 -> 0.01275547 | AN12: Other income | AO12: ='Income Statement'!AO5/'Income Statement'!AO4 -> 0.0056392898 | AP12: ='Income Statement'!AP5/'Income Statement'!AP4 -> 0.0075823614 | AQ12: ='Income Statement'!AQ5/'Income Statement'!AQ4 -> 0.0029012234 | AR12: ='Income Statement'!AR5/'Income Statement'!AR4 -> 0.0048623671 | AS12: ='Income Statement'!AS5/'Income Statement'!AS4 -> 0.0059209051
A13: Profit before tax (PBT) | B13: ='Income Statement'!B15/'Income Statement'!B4 -> 0.070155045 | C13: ='Income Statement'!C15/'Income Statement'!C4 -> 0.061444158 | D13: ='Income Statement'!D15/'Income Statement'!D4 -> 0.066635525 | E13: ='Income Statement'!E15/'Income Statement'!E4 -> 0.071431406 | F13: ='Income Statement'!F15/'Income Statement'!F4 -> 0.068151403 | G13: ='Income Statement'!G15/'Income Statement'!G4 -> 0.061873158 | I13: =A13 -> Profit before tax (PBT) | J13: =J10+J12-J11 -> 0.23564953 | K13: =K10+K12-K11 -> 0.2306288 | L13: =L10+L12-L11 -> 0.22725315 | M13: =M10+M12-M11 -> 0.22135945 | N13: =N10+N12-N11 -> 0.22502778 | P13: =I13 -> Profit before tax (PBT) | Q13: ='Income Statement'!Q20/'Income Statement'!Q4 -> 0.38982715 | R13: ='Income Statement'!R20/'Income Statement'!R4 -> 0.33746834 | S13: ='Income Statement'!S20/'Income Statement'!S4 -> 0.31808117 | T13: ='Income Statement'!T20/'Income Statement'!T4 -> 0.33867912 | U13: ='Income Statement'!U20/'Income Statement'!U4 -> 0.35728474 | V13: ='Income Statement'!V20/'Income Statement'!V4 -> 0.32993534 | X13: =P13 -> Profit before tax (PBT) | Y13: =Y10+Y12-Y11 -> 0.100038 | Z13: =Z10+Z12-Z11 -> 0.061541305 | AA13: =AA10+AA12-AA11 -> 0.1027119 | AB13: =AB10+AB12-AB11 -> 0.10957486 | AC13: =AC10+AC12-AC11 -> 0.090478428 | AD13: =AD10+AD12-AD11 -> 0.074996692 | AF13: Profit before tax (PBT) | AG13: =AG10+AG12-AG11 -> 0.056058841 | AH13: =AH10+AH12-AH11 -> -0.051080618 | AI13: =AI10+AI12-AI11 -> 0.029684172 | AJ13: =AJ10+AJ12-AJ11 -> 0.057226262 | AK13: =AK10+AK12-AK11 -> 0.098681143 | AL13: =AL10+AL12-AL11 -> 0.11341023 | AN13: Profit before tax (PBT) | AO13: =AO10+AO12-AO11 -> 0.065443066 | AP13: =AP10+AP12-AP11 -> 0.11236608 | AQ13: =AQ10+AQ12-AQ11 -> 0.15112462 | AR13: =AR10+AR12-AR11 -> 0.16787136 | AS13: =AS10+AS12-AS11 -> 0.16769259
A14: Tax expense | B14: ='Income Statement'!B20/'Income Statement'!B4 -> 0.017844247 | C14: ='Income Statement'!C20/'Income Statement'!C4 -> 0.01590602 | D14: ='Income Statement'!D20/'Income Statement'!D4 -> 0.018456709 | E14: ='Income Statement'!E20/'Income Statement'!E4 -> 0.015914029 | F14: ='Income Statement'!F20/'Income Statement'!F4 -> 0.018226842 | G14: ='Income Statement'!G20/'Income Statement'!G4 -> 0.016260979 | I14: =A14 -> Tax expense | J14: =ABS('Income Statement'!J22/'Income Statement'!J4) -> 0.060553503 | K14: =ABS('Income Statement'!K22/'Income Statement'!K4) -> 0.055413796 | L14: =ABS('Income Statement'!L22/'Income Statement'!L4) -> 0.056953819 | M14: =ABS('Income Statement'!M22/'Income Statement'!M4) -> 0.052839221 | N14: =ABS('Income Statement'!N22/'Income Statement'!N4) -> 0.058872948 | P14: =I14 -> Tax expense | Q14: ='Income Statement'!Q24/'Income Statement'!Q4 -> 0.086427128 | R14: ='Income Statement'!R24/'Income Statement'!R4 -> 0.085698048 | S14: ='Income Statement'!S24/'Income Statement'!S4 -> 0.08032119 | T14: ='Income Statement'!T24/'Income Statement'!T4 -> 0.084142062 | U14: ='Income Statement'!U24/'Income Statement'!U4 -> 0.084034914 | V14: ='Income Statement'!V24/'Income Statement'!V4 -> 0.084428811 | X14: =P14 -> Tax expense | Y14: ='Income Statement'!Y27/'Income Statement'!Y4 -> 0.028928368 | Z14: ='Income Statement'!Z27/'Income Statement'!Z4 -> 0.01630937 | AA14: ='Income Statement'!AA27/'Income Statement'!AA4 -> 0.02451474 | AB14: ='Income Statement'!AB27/'Income Statement'!AB4 -> 0.028909427 | AC14: ='Income Statement'!AC27/'Income Statement'!AC4 -> 0.022061702 | AD14: ='Income Statement'!AD27/'Income Statement'!AD4 -> 0.019816065 | AF14: Tax expense | AG14: ='Income Statement'!AG24/'Income Statement'!AG4 -> 0.016927808 | AH14: ='Income Statement'!AH24/'Income Statement'!AH4 -> -0.0091362767 | AI14: ='Income Statement'!AI24/'Income Statement'!AI4 -> 0.017034162 | AJ14: ='Income Statement'!AJ24/'Income Statement'!AJ4 -> 0.019223443 | AK14: ='Income Statement'!AK24/'Income Statement'!AK4 -> 0.03582756 | AL14: ='Income Statement'!AL24/'Income Statement'!AL4 -> 0.028908157 | AN14: Tax expense | AO14: ='Income Statement'!AO26/'Income Statement'!AO4 -> 0.00079837823 | AP14: ='Income Statement'!AP26/'Income Statement'!AP4 -> 0.029085458 | AQ14: ='Income Statement'!AQ26/'Income Statement'!AQ4 -> 0.035362455 | AR14: ='Income Statement'!AR26/'Income Statement'!AR4 -> 0.039062836 | AS14: ='Income Statement'!AS26/'Income Statement'!AS4 -> 0.039001573
A15: Profit after tax (PAT) | B15: ='Income Statement'!B21/'Income Statement'!B4 -> 0.052310798 | C15: ='Income Statement'!C21/'Income Statement'!C4 -> 0.045538138 | D15: ='Income Statement'!D21/'Income Statement'!D4 -> 0.048178816 | E15: ='Income Statement'!E21/'Income Statement'!E4 -> 0.055517377 | F15: ='Income Statement'!F21/'Income Statement'!F4 -> 0.04992456 | G15: ='Income Statement'!G21/'Income Statement'!G4 -> 0.045612179 | I15: =A15 -> Profit after tax (PAT) | J15: =J13-J14 -> 0.17509603 | K15: =K13-K14 -> 0.175215 | L15: =L13-L14 -> 0.17029933 | M15: =M13-M14 -> 0.16852023 | N15: =N13-N14 -> 0.16615484 | P15: =I15 -> Profit after tax (PAT) | Q15: ='Income Statement'!Q30/'Income Statement'!Q4 -> 0.30340002 | R15: ='Income Statement'!R30/'Income Statement'!R4 -> 0.25177029 | S15: ='Income Statement'!S30/'Income Statement'!S4 -> 0.23775998 | T15: ='Income Statement'!T30/'Income Statement'!T4 -> 0.25453706 | U15: ='Income Statement'!U30/'Income Statement'!U4 -> 0.28083582 | V15: ='Income Statement'!V30/'Income Statement'!V4 -> 0.42949744 | X15: =P15 -> Profit after tax (PAT) | Y15: ='Income Statement'!Y28/'Income Statement'!Y4 -> 0.070919628 | Z15: ='Income Statement'!Z28/'Income Statement'!Z4 -> 0.045000924 | AA15: ='Income Statement'!AA28/'Income Statement'!AA4 -> 0.076322095 | AB15: ='Income Statement'!AB28/'Income Statement'!AB4 -> 0.08069008 | AC15: ='Income Statement'!AC28/'Income Statement'!AC4 -> 0.068436301 | AD15: ='Income Statement'!AD28/'Income Statement'!AD4 -> 0.055197168 | AF15: Profit after tax (PAT) | AG15: =AG13-AG14 -> 0.039131033 | AH15: =AH13-AH14 -> -0.041944342 | AI15: =AI13-AI14 -> 0.01265001 | AJ15: =AJ13-AJ14 -> 0.03800282 | AK15: =AK13-AK14 -> 0.062853583 | AL15: =AL13-AL14 -> 0.084502069 | AN15: Profit after tax (PAT) | AO15: =AO13-AO14 -> 0.064644688 | AP15: =AP13-AP14 -> 0.083280617 | AQ15: =AQ13-AQ14 -> 0.11576217 | AR15: =AR13-AR14 -> 0.12880852 | AS15: =AS13-AS14 -> 0.12869102

Sheet Cash Flow Statement
A1: Cash flow Statement | G1: #VALUE! | I1: Cash flow Statement | N1: #VALUE! | P1: Cash flow Statement | V1: #VALUE! | X1: Cash flow Statement | AD1: #VALUE! | AF1: Cash flow Statement | AL1: #VALUE! | AN1: Cash flow Statement | AS1: #VALUE!
A2: Cash flow from operating activities | B2: 2020 | C2: 2021 | D2: 2022 | E2: 2023 | F2: 2024 | G2: 2025 | I2: Particulars | J2: 2020 | K2: 2021 | L2: 2022 | M2: 2023 | N2: 2024 | P2: Particulars | Q2: 2020 | R2: 2021 | S2: 2022 | T2: 2023 | U2: 2024 | V2: 2025 | X2: Particulars | Y2: 2020 | Z2: 2021 | AA2: 2022 | AB2: 2023 | AC2: 2024 | AD2: 2025 | AF2: Particulars | AG2: 2020 | AH2: 2021 | AI2: 2022 | AJ2: 2023 | AK2: 2024 | AL2: 2025 | AN2: Particulars | AO2: 2020 | AP2: 2021 | AQ2: 2022 | AR2: 2023 | AS2: 2024
A3: Profit before tax | B3: 1744.77 | C3: 1483.45 | D3: 2064.12 | E3: 3060.09 | F3: 3461.33 | G3: 3672.67 | I3: Cash flow from operating activities | P3: Cash flow from operating activities | X3: Cash flow from operating activities | AF3: Cash flow from Operating activities | AN3: Profit before tax and share of profit in associate | AO3: 362.505 | AP3: 1006.608 | AQ3: 2023.643 | AR3: 2739.839 | AS3: 3434.567
A4: Adjustments for: | I4: Profit before tax | J4: 9173 | K4: 10606 | L4: 11874 | M4: 13345 | N4: 13926 | P4: Profit before tax | Q4: 20034.57 | R4: 17938.17 | S4: 20740.47 | T4: 25915.12 | U4: =26400.28+739.6 -> 27139.88 | V4: =26926.94+15654.65 -> 42581.59 | X4: Profit before tax | Y4: 2102 | Z4: 1327 | AA4: 2904 | AB4: 4447 | AC4: 4623 | AD4: 4535 | AF4: Profit/loss before taxes and exceptional items | AG4: 164.99 | AH4: -203.81 | AI4: 138.66 | AJ4: 555.13 | AK4: 1344.76 | AL4: 2029.74 | AN4: Adjustments for:
A5: Depreciation and amortisation expenses | B5: 374.41 | C5: 414.16 | D5: 498.08 | E5: 638.87 | F5: 730.76 | G5: 869.52 | I5: Adjustments for: | P5: Adjustemnts for: | X5: Adjustments for: | AF5: Adjustments for: | AN5: Depreciation on PPE | AO5: 523.191 | AP5: 503.754 | AQ5: 583.099 | AR5: 640.904 | AS5: 838.695
A6: Finance cost | B6: 69.12 | C6: 41.65 | D6: 53.79 | E6: 67.41 | F6: 58.13 | G6: 69.45 | I6: Depreciation and amortisation expenses | J6: 1002 | K6: 1134 | L6: 1106 | M6: 1152 | N6: 1216 | P6: Depreciation and amortisation expense | Q6: 1644.91 | R6: 1645.59 | S6: 1732.41 | T6: 1809.01 | U6: 1816.39 | V6: 1950.58 | X6: Depreciation and amortisation expense | Y6: 348 | Z6: 375 | AA6: 399 | AB6: 441 | AC6: 584 | AD6: 693 | AF6: Depreciation | AG6: 247.24 | AH6: 257.3 | AI6: 310.82 | AJ6: 493.69 | AK6: 671.11 | AL6: 895.18 | AN6: Amortisation of intangible assets | AO6: 5.511 | AP6: 27.508 | AQ6: 34.09 | AR6: 40.002 | AS6: 108.691
A7: Interest income | B7: -32.49 | C7: -178.13 | D7: -103.96 | E7: -107.56 | F7: -107.46 | G7: -87.83 | I7: Profit/Loss on sale of PPE | J7: 53 | K7: -57 | L7: -97 | M7: -100 | N7: 18 | P7: Share based payments to employees | Q7: 112.99 | R7: 26.27 | S7: 33.17 | T7: 60.41 | U7: 107.3 | V7: 133.79 | X7: Net unrealised exchange gain/loss | Y7: -1 | Z7: -1 | AA7: -3 | AB7: 7 | AC7: 0 | AD7: 9 | AF7: Amortisation of leasehold land | AG7: 0.73 | AH7: 0.73 | AI7: 0.73 | AJ7: 0.73 | AK7: 0.73 | AL7: 0.73 | AN7: Exceptional items | AO7: 66.529 | AP7: 185.037 | AQ7: 185.449 | AR7: 268.099 | AS7: 450.386
A8: Profit on sale of investment | B8: -10.16 | C8: -2.56 | D8: -3.66 | E8: -8.83 | F8: -27.11 | G8: -21.76 | I8: Contingent consideration true up for business combination | J8: -26 | K8: -22 | L8: -9 | M8: -2 | N8: 0 | P8: Finance costs | Q8: 54.68 | R8: 44.58 | S8: 39.36 | T8: 43.2 | U8: 45.96 | V8: 50.01 | X8: Share of profit/loss of associate and JV | Y8: 4 | Z8: 5 | AA8: 0 | AB8: -1 | AC8: -1 | AD8: -1 | AF8: Impairment loss | AG8: 0 | AH8: 1.49 | AI8: -0.19 | AJ8: -2.44 | AK8: -0.59 | AL8: 2.33 | AN8: Interest expense at amortised cost | AO8: 272.982 | AP8: -14.516 | AQ8: -22.829 | AR8: -23.8 | AS8: -41.9
A9: Expense on employee stock option scheme | B9: 8.46 | C9: 6.38 | D9: 6.42 | E9: 12.01 | F9: 18.84 | G9: 30.72 | I9: Fair value gain on financial liability on acquisition | J9: 0 | K9: 0 | L9: 0 | M9: 0 | N9: -132 | P9: Interest income | Q9: -1522.13 | R9: -1297.91 | S9: -1082.63 | T9: -1534 | U9: -1710.51 | V9: -1510.46 | X9: Loss on sale/disposal/scrapping of PPE (net) | Y9: -3 | Z9: 6 | AA9: 2 | AB9: 1 | AC9: 48 | AD9: 13 | AF9: Provision for doubtful debts and BD written off | AG9: 2.34 | AH9: 9.65 | AI9: 2.11 | AJ9: 6.35 | AK9: 14.12 | AL9: 7.3 | AN9: Interest income at amortised cost | AO9: -8.886 | AP9: -0.07 | AQ9: 0.367 | AR9: -0.0081 | AS9: -0.0008
A10: Rent income | B10: -2.88 | C10: -2.89 | D10: -3.55 | E10: -4.69 | F10: -4.98 | G10: -5.04 | I10: Finance income | J10: -492 | K10: -346 | L10: -198 | M10: -411 | N10: -546 | P10: Dividend income | Q10: -8.31 | R10: -0.07 | S10: -0.01 | T10: -0.02 | U10: -11.13 | V10: -12.14 | X10: Provision for doubtful TR (net) and bad TR WO | Y10: 4 | Z10: 35 | AA10: 3 | AB10: 3 | AC10: -1 | AD10: -1 | AF10: Finance income and cost (net) | AG10: 212.64 | AH10: 219.72 | AI10: 281.43 | AJ10: 352.37 | AK10: 298.83 | AL10: 107.16 | AN10: Dividend income from current investment | AO10: 0 | AP10: -5.838 | AQ10: -0.92 | AR10: -0.351 | AS10: -2.247
A11: Gain/Loss on disposal of sale of PPE (net) | B11: -2.45 | C11: 1.78 | D11: 3.85 | E11: 1.74 | F11: 1.87 | G11: 7.18 | I11: Dividend income | J11: -1 | K11: -1 | L11: -1 | M11: -2 | N11: -3 | P11: Loss on sale of PPE, lease termination -Net | Q11: 56.68 | R11: 54.61 | S11: -56.22 | T11: 4.4 | U11: -57.04 | V11: -135.69 | X11: Provision for asset write off of a subsidiary | Y11: 0 | Z11: 31 | AA11: 3 | AB11: 4 | AC11: 12 | AD11: 27 | AF11: Profit/Loss on fixed assets sold/discarded (net) | AG11: -4.79 | AH11: 0.99 | AI11: -7.92 | AJ11: -134.33 | AK11: -155.72 | AL11: -104.61 | AN11: Gain on acquisition of control over existing associate | AO11: 0 | AP11: 0 | AQ11: 2.906 | AR11: -32.236 | AS11: -64.615
A12: Operating profit before working capital changes | B12: =SUM(B3:B11) -> 2148.78 | C12: =SUM(C3:C11) -> 1763.84 | D12: =SUM(D3:D11) -> 2515.09 | E12: =SUM(E3:E11) -> 3659.04 | F12: =SUM(F3:F11) -> 4131.38 | G12: =SUM(G3:G11) -> 4534.91 | I12: Other non operating income- fair value gain on investments | J12: -139 | K12: -63 | L12: -59 | M12: -99 | N12: -249 | P12: Doubtful and bad debts | Q12: 37.59 | R12: 29.93 | S12: 14.98 | T12: 5.96 | U12: 14.81 | V12: 11.64 | X12: Interest income | Y12: -98 | Z12: -61 | AA12: 9 | AB12: 0 | AC12: 0 | AD12: 1 | AF12: Profit/loss on sale of investments | AG12: -14.69 | AH12: -4.27 | AI12: -4.85 | AJ12: -10.16 | AK12: -11.93 | AL12: -28.3 | AN12: Profit on sale of current investments | AO12: 0 | AP12: 25.871 | AQ12: 62.326 | AR12: 7.861 | AS12: 16.243
A13: Adjustments for: | I13: Interest expense | J13: 118 | K13: 117 | L13: 106 | M13: 114 | N13: 317 | P13: Doubtful and bad advances, loans and deposits | Q13: -2.68 | R13: 33.42 | S13: 0.93 | T13: 0.75 | U13: 24.61 | V13: 1.95 | X13: Gain on investments carried at fair value | Y13: -32 | Z13: -35 | AA13: -96 | AB13: -143 | AC13: -249 | AD13: -288 | AF13: Income from investments | AG13: -2.59 | AH13: -0.09 | AI13: -0.52 | AJ13: -1.43 | AK13: -1.4 | AL13: -0.38 | AN13: Excess provisions written back | AO13: 0 | AP13: 0 | AQ13: 2.571 | AR13: 84.364 | AS13: 76.196
A14: Increase/decrease in trade payables | B14: -29.82 | C14: 144.68 | D14: 11.07 | E14: 164.59 | F14: 231.02 | G14: 86 | I14: Movement in provision towards litigation | J14: 0 | K14: 0 | L14: 0 | M14: 0 | N14: -159 | P14: Share of profit/loss of associates and JV | Q14: -8.22 | R14: 6.92 | S14: -17.48 | T14: -49.04 | U14: -27.61 | V14: -121.77 | X14: Gain on investment in joint venture | Y14: 0 | Z14: -22 | AA14: -87 | AB14: -106 | AC14: -203 | AD14: -157 | AF14: Unrealised foreign exchange loss/gain | AG14: -1.1 | AH14: -0.65 | AI14: -1.55 | AJ14: -1.58 | AK14: -6.64 | AL14: -9.21 | AN14: Loss/gain on disposal of PPE | AO14: 1.435 | AP14: 5.892 | AQ14: 7.351 | AR14: 0.324 | AS14: 2.873
A15: Increase/decrease in current provisions | B15: -3.04 | C15: 6.24 | D15: 6.53 | E15: 7.99 | F15: -1.24 | G15: -23.23 | I15: Provision for expenses on employee stock option | J15: 2 | K15: -1 | L15: -1 | M15: 1 | N15: 0 | P15: Net gain/loss arising on fin instruments mandatorily measured at fair value | Q15: -974.03 | R15: -1144.02 | S15: -538.99 | T15: -393.97 | U15: -840.17 | V15: -896.84 | X15: Gain on pre-closure of lease contracts | Y15: -9 | Z15: -13 | AA15: -20 | AB15: -14 | AC15: -27 | AD15: -11 | AF15: Excess provision no longer required written back | AG15: -3.44 | AH15: -4.4 | AI15: -1.1 | AJ15: -4.77 | AK15: -4.03 | AL15: -4.34 | AN15: Bad debts and advances written off | AO15: 1.194 | AP15: 0 | AQ15: 0 | AR15: 6.947 | AS15: 8.485
A16: Decrease in other current financial liabilities | B16: 24.28 | C16: 48.87 | D16: -6.91 | E16: -7.11 | F16: 39.92 | G16: 43.17 | I16: Profit on sale of brand rights | J16: 0 | K16: 0 | L16: -29 | M16: -60 | N16: 0 | P16: Foreign currency translations and transactions -Net | Q16: -9.49 | R16: -6.42 | S16: -8.98 | T16: 31.37 | U16: -13.38 | V16: 6.78 | X16: Rent waiver | Y16: 0 | Z16: -61 | AA16: -34 | AB16: -2 | AC16: -1 | AD16: 1 | AF16: Share in profit and loss of JV and associates | AG16: 30.43 | AH16: 71.36 | AI16: -5.14 | AJ16: -83.47 | AK16: -123.57 | AL16: =-86.5-16.8 -> -103.3 | AN16: Allowance for expected credit loss | AO16: 5.309 | AP16: 0 | AQ16: 0 | AR16: 0.326 | AS16: -49.315
A17: Increase/decrease in other current liabilities | B17: -2.24 | C17: 20.03 | D17: 17.64 | E17: 62.81 | F17: -25.44 | G17: 42.88 | I17: Payment from retirement benefit scheme reserve | J17: 0 | K17: 0 | L17: 0 | M17: -1 | N17: -1 | P17: Impairment of investment in Joint ventures | Q17: -0.15 | R17: -4.67 | S17: 0 | T17: 1.42 | U17: 0.06 | V17: 7.87 | X17: Finance costs | Y17: 166 | Z17: 203 | AA17: 218 | AB17: 300 | AC17: 619 | AD17: 953 | AF17: Changes in the fair value of investments | AG17: -22.3 | AH17: -18.48 | AI17: =-25.94-64.74 -> -90.68 | AJ17: =-0.95-0.26 -> -1.21 | AK17: -42.39 | AL17: -51.64 | AN17: Unrealised foreign exchange fluctuation | AO17: -29.42 | AP17: -109.85 | AQ17: -128.768 | AR17: 0 | AS17: 0
A18: Increase in non-current provisions | B18: 0.43 | C18: 0.97 | D18: 2.42 | E18: 1.54 | F18: 2.77 | G18: 3.49 | I18: Share of loss of joint venture | J18: 0 | K18: 0 | L18: 0 | M18: 1 | N18: 4 | P18: Gain realised on disinvestment of shares held in joint venture | Q18: 0 | R18: 0 | S18: 0 | T18: 0 | U18: -9.84 | V18: 0 | AF18: Amortised cost of non convertible debentures | AG18: 0.21 | AH18: 0.99 | AI18: 0.32 | AJ18: 0.17 | AK18: 1.77 | AL18: 0.64 | AN18: Operating profit before working capital changes | AO18: =SUM(AO3,AO5:AO17) -> 1200.35 | AP18: =SUM(AP3,AP5:AP17) -> 1624.396 | AQ18: =SUM(AQ3,AQ5:AQ17) -> 2749.285 | AR18: =SUM(AR3,AR5:AR17) -> 3732.2709 | AS18: =SUM(AS3,AS5:AS17) -> 4778.0582
A19: Decrease in other non-current financial liabilities | B19: -0.31 | C19: -0.03 | D19: -0.03 | E19: 0.06 | F19: -0.1 | G19: 0.12 | I19: Transaction cost from acquisition | J19: 0 | K19: 0 | L19: 0 | M19: 2 | N19: 0 | P19: Gain recognised on fair valuation of net assets distributed pursuant | Q19: 0 | R19: 0 | S19: 0 | T19: 0 | U19: 0 | V19: -15583.12 | X19: Operating profit before working capital changes | Y19: =SUM(Y4,Y6:Y17) -> 2481 | Z19: =SUM(Z4,Z6:Z17) -> 1789 | AA19: =SUM(AA4,AA6:AA17) -> 3298 | AB19: =SUM(AB4,AB6:AB17) -> 4937 | AC19: =SUM(AC4,AC6:AC17) -> 5404 | AD19: =SUM(AD4,AD6:AD17) -> 5774 | AF19: Amortisation of deferred lease (income) | AG19: -0.52 | AH19: -0.48 | AI19: -0.59 | AJ19: -0.97 | AK19: -1.33 | AL19: -1.04 | AN19: Working capital adjustments
A20: Increase/decrease in trade receivables | B20: 44.82 | C20: -24.03 | D20: -23.31 | E20: 4.73 | F20: -104.21 | G20: 12.58 | I20: Government grants accrued (net) | J20: -104 | K20: 13 | L20: 0 | M20: 184 | N20: 167 | P20: Inventory write-offs/write downs (net of reversals) | Q20: 0 | R20: 0 | S20: 0 | T20: 0 | U20: 156.12 | V20: 235.05 | X20: Adjustments for: | AF20: Remeasurement of defined benefit plan | AG20: -2.73 | AH20: 1.1 | AI20: -2.01 | AJ20: 0.19 | AK20: -4.78 | AL20: -5.13 | AN20: Increase in inventories | AO20: -47.291 | AP20: -519.283 | AQ20: -556.833 | AR20: -160.173 | AS20: -478.77
A21: Increase in inventories | B21: -338.75 | C21: -300.88 | D21: -494.38 | E21: -500.82 | F21: -683.83 | G21: -1117.06 | I21: Inventory written off net of provision for inventory | J21: 138 | K21: 201 | L21: 156 | M21: -27 | N21: -11 | X21: Increase/decrease in trade receivables | Y21: 109 | Z21: -59 | AA21: -207 | AB21: -112 | AC21: -348 | AD21: -95 | AF21: Expired gift vouchers and credit notes written back | AG21: -3.32 | AH21: -4.73 | AI21: -3.59 | AJ21: -1.76 | AK21: -7.22 | AL21: -11.75 | AN21: Increase in trade receivables | AO21: -75.745 | AP21: 14.656 | AQ21: -123.38 | AR21: -73.018 | AS21: -133.215
A22: Increase in other non-current assets | B22: 0 | C22: 0 | D22: 0 | E22: 0 | F22: -19.4 | G22: -24.97 | I22: Bad debts/asset written off net of provision/write back | J22: 11 | K22: 77 | L22: -15 | M22: -8 | N22: -10 | P22: Operating profit before working capital changes | Q22: =SUM(Q4,Q6:Q21) -> 19416.41 | R22: =SUM(R4,R6:R21) -> 17326.4 | S22: =SUM(S4,S6:S21) -> 20857.01 | T22: =SUM(T4,T6:T21) -> 25894.61 | U22: =SUM(U4,U6:U21) -> 26635.45 | V22: =SUM(V4,V6:V21) -> 26719.24 | X22: Increase/decrease in inventories | Y22: -1057 | Z22: -316 | AA22: -5199 | AB22: -2977 | AC22: -2462 | AD22: -9072 | AF22: Gain/Loss on lease termination | AG22: -61.07 | AH22: -57.7 | AI22: -46.47 | AJ22: -87.48 | AK22: -52.35 | AL22: -0.7 | AN22: decrease/increase in current and non-current financial assets and other current and non-current assets | AO22: 24.468 | AP22: -92.185 | AQ22: -325.713 | AR22: -457.218 | AS22: -522.43
A23: Decrease in current investments | B23: 1.85 | C23: 11.73 | D23: -2.98 | E23: 0 | F23: 0 | G23: 0 | I23: Mark-to-market gain/loss on derivative financial instruments | J23: -12 | K23: 14 | L23: -4 | M23: 0 | N23: 0 | P23: Adjustemnts for: | X23: Increase/decrease in financial assets loan rec | Y23: -20 | Z23: -8 | AA23: -3 | AB23: -18 | AC23: -21 | AD23: 4 | AF23: Operating profit before working capital changes | AG23: =SUM(AG4,AG6:AG22) -> 542.03 | AH23: =SUM(AH4,AH6:AH22) -> 268.72 | AI23: =SUM(AI4,AI6:AI22) -> 569.46 | AJ23: =SUM(AJ4,AJ6:AJ22) -> 1079.03 | AK23: =SUM(AK4,AK6:AK22) -> 1919.37 | AL23: =SUM(AL4,AL6:AL22) -> 2722.68 | AN23: Decrease/increase in current financial liabilities and other current and non-current liab and provisions | AO23: -12.276 | AP23: 328.066 | AQ23: 420.733 | AR23: 16.928 | AS23: 465.027
A24: Increase/decrease in other non current financial assets | B24: -11.33 | C24: -15.26 | D24: -6.79 | E24: -18.99 | F24: -28.23 | G24: -50.92 | I24: Operating profit before working capital changes | J24: =SUM(J4,J6:J23) -> 9723 | K24: =SUM(K4:K23) -> 11672 | L24: =SUM(L4:L23) -> 12829 | M24: =SUM(M4:M23) -> 14089 | N24: =SUM(N4:N23) -> 14537 | P24: Trade receivables, advances and other assets | Q24: 1411 | R24: -65.6 | S24: -732.29 | T24: -884.21 | U24: -933.64 | V24: -1022.8 | X24: increase/decrease in other financial assets | Y24: -336 | Z24: 237 | AA24: -29 | AB24: 74 | AC24: -130 | AD24: 75 | AF24: Adjustments for: | AN24: Total cash from operations | AO24: =SUM(AO18,AO19:AO23) -> 1089.506 | AP24: =SUM(AP18,AP19:AP23) -> 1355.65 | AQ24: =SUM(AQ18,AQ19:AQ23) -> 2164.092 | AR24: =SUM(AR18,AR19:AR23) -> 3058.7899 | AS24: =SUM(AS18,AS19:AS23) -> 4108.6702
A25: Increase in bank balances other than cash and cash equiv | B25: -0.5 | C25: -2.07 | D25: -48.96 | E25: -48.71 | F25: -0.04 | G25: -0.15 | I25: Adjustments for: | P25: Inventories and biological assets other than bearer plants | Q25: -507.99 | R25: -1459.78 | S25: -466.37 | T25: -940.54 | U25: -2544.87 | V25: -2975.38 | X25: increase/decrease in other assets | Y25: 36 | Z25: -62 | AA25: -223 | AB25: -363 | AC25: -481 | AD25: -235 | AF25: increase/decrease in inventories | AG25: -88.96 | AH25: 179.42 | AI25: -439.39 | AJ25: -494.44 | AK25: -221.57 | AL25: -462.28 | AN25: Income tax paid | AO25: -77.519 | AP25: -124.228 | AQ25: -373.329 | AR25: -667.939 | AS25: -727.566
A26: Increase in other current assets | B26: -42.43 | C26: -4.79 | D26: -37.41 | E26: 13.91 | F26: -19.56 | G26: -71.21 | I26: Increase/decrease in Non-current assets | J26: -19 | K26: -4 | L26: 3 | M26: -14 | N26: -30 | P26: Trade payables, other liabilities and provisions | Q26: -606.87 | R26: 1112.6 | S26: 1099.11 | T26: 1057.93 | U26: 141.48 | V26: 1256.18 | X26: increase/decrease in gold loan | Y26: -768 | Z26: 2625 | AA26: =1188+1 -> 1189 | AB26: -99 | AC26: 42 | AD26: 2468 | AF26: increase/decrease in trade receivables & other current assets | AG26: -19.89 | AH26: -38.86 | AI26: -102.62 | AJ26: -101.23 | AK26: -207.69 | AL26: -202.76 | AN26: Net cash flows from/used in operating activities | AO26: =AO24+AO25 -> 1011.987 | AP26: =AP24+AP25 -> 1231.422 | AQ26: =AQ24+AQ25 -> 1790.763 | AR26: =AR24+AR25 -> 2390.8509 | AS26: =AS24+AS25 -> 3381.1042
A27: Increase in other financial assets | B27: -19.2 | C27: -12.59 | D27: 0.62 | E27: 0.12 | F27: -35.43 | G27: -13.41 | I27: Increase/decrease in Current assets | J27: 471 | K27: -412 | L27: -480 | M27: -1111 | N27: 220 | P27: Cash generated from operations | Q27: =SUM(Q22,Q24:Q26) -> 19712.55 | R27: =SUM(R22,R24:R26) -> 16913.62 | S27: =SUM(S22,S24:S26) -> 20757.46 | T27: =SUM(T22,T24:T26) -> 25127.79 | U27: =SUM(U22,U24:U26) -> 23298.42 | V27: =SUM(V22,V24:V26) -> 23977.24 | X27: increase/decrease in trade payables | Y27: -310 | Z27: 195 | AA27: 504 | AB27: -89 | AC27: 196 | AD27: 564 | AF27: increase/decrease in loans and other non-current assets | AG27: -22.35 | AH27: -22.35 | AI27: -45.55 | AJ27: -71.83 | AK27: -112.63 | AL27: -128.6 | AN27: Investing activities
A28: Cash flow from operating activities | B28: =SUM(B12,B14:B27) -> 1772.54 | C28: =SUM(C12,C14:C27) -> 1636.71 | D28: =SUM(D12,D14:D27) -> 1932.6 | E28: =SUM(E12,E14:E27) -> 3339.16 | F28: =SUM(F12,F14:F27) -> 3487.61 | G28: =SUM(G12,G14:G27) -> 3422.2 | I28: Increase/decrease in Inventories | J28: -331 | K28: -543 | L28: -758 | M28: -339 | N28: 74 | P28: Income tax paid | Q28: -5022.89 | R28: -4386.53 | S28: -4981.95 | T28: -6250.24 | U28: -6119.56 | V28: -6350.2 | X28: increase/decrease in other financial liabilities | Y28: -280 | Z28: 253 | AA28: 179 | AB28: 108 | AC28: 91 | AD28: 663 | AF28: increase/decrease in trade payables & other current liabilities | AG28: 26.32 | AH28: -10.81 | AI28: 134.1 | AJ28: 332.16 | AK28: 177.6 | AL28: 211.89 | AN28: Purchase of PPE and intangible assets | AO28: -559.674 | AP28: -834.8 | AQ28: -1800.992 | AR28: -3264.049 | AS28: -3779.01
A29: Direct taxes paid | B29: -492.4 | C29: -261.57 | D29: -560.25 | E29: -708.89 | F29: -741.77 | G29: -959.23 | I29: Increase/decrease in Non-current liabilities | J29: 56 | K29: 28 | L29: 86 | M29: -116 | N29: 128 | P29: Net cash from/used in operating activities | Q29: =Q27+Q28 -> 14689.66 | R29: =R27+R28 -> 12527.09 | S29: =S27+S28 -> 15775.51 | T29: =T27+T28 -> 18877.55 | U29: =U27+U28 -> 17178.86 | V29: =V27+V28 -> 17627.04 | X29: increase/decrease in other liabilities | Y29: 316 | Z29: -192 | AA29: 510 | AB29: 994 | AC29: 582 | AD29: 350 | AF29: increase/decrease in non current liabilities | AG29: 7.47 | AH29: -1.14 | AI29: 23.72 | AJ29: 42.18 | AK29: 92.79 | AL29: 14.06 | AN29: Proceeds from disposal of PPE and intangible assets | AO29: 24.059 | AP29: 19.351 | AQ29: 51.093 | AR29: 70.131 | AS29: 38.637
A30: Net cash flow from operating activities | B30: =B28+B29 -> 1280.14 | C30: =C28+C29 -> 1375.14 | D30: =D28+D29 -> 1372.35 | E30: =E28+E29 -> 2630.27 | F30: =F28+F29 -> 2745.84 | G30: =G28+G29 -> 2462.97 | I30: Increase/decrease in current liabilities | J30: 234 | K30: 830 | L30: 149 | M30: 620 | N30: 921 | P30: Cash flow from Investing activities | X30: increase/decrease in provisions | Y30: 38 | Z30: -52 | AA30: 59 | AB30: 69 | AC30: -5 | AD30: 52 | AN30: Change in advance received for capital assets | AO30: 107.443 | AP30: -107.443 | AQ30: 0 | AR30: 0 | AS30: -401.884
A31: Cash flow from investing activities | I31: Cash flows generated from operations | J31: =SUM(J24,J26:J30) -> 10134 | K31: =SUM(K24,K26:K30) -> 11571 | L31: =SUM(L24,L26:L30) -> 11829 | M31: =SUM(M24,M26:M30) -> 13129 | N31: =SUM(N24,N26:N30) -> 15850 | P31: Purchase of PPE, intangibles and ROU | Q31: -2441.15 | R31: -1836.64 | S31: -2141.64 | T31: -2742.99 | U31: -3562.53 | V31: -2278.7 | X31: Cash generated from operating activities | Y31: =SUM(Y21:Y30,Y19) -> 209 | Z31: =SUM(Z21:Z30,Z19) -> 4410 | AA31: =SUM(AA21:AA30,AA19) -> 78 | AB31: =SUM(AB21:AB30,AB19) -> 2524 | AC31: =SUM(AC21:AC30,AC19) -> 2868 | AD31: =SUM(AD21:AD30,AD19) -> 548 | AF31: Cash generated from operations | AG31: =SUM(AG23,AG25:AG30) -> 444.62 | AH31: =SUM(AH23,AH25:AH30) -> 374.98 | AI31: =SUM(AI23,AI25:AI30) -> 139.72 | AJ31: =SUM(AJ23,AJ25:AJ30) -> 785.87 | AK31: =SUM(AK23,AK25:AK30) -> 1647.87 | AL31: =SUM(AL23,AL25:AL30) -> 2154.99 | AN31: Acquisition under business combination | AO31: 0 | AP31: 0 | AQ31: -0.01 | AR31: -21.557 | AS31: -39.898
A32: Proceeds from disposal of PPE | B32: 6.15 | C32: 1.88 | D32: 20.92 | E32: 5.46 | F32: 9.45 | G32: 5.83 | I32: Taxes paid, net of refunds | J32: -2511 | K32: =-2408 -> -2408 | L32: -2781 | M32: -3138 | N32: -381 | P32: Sale of PPE | Q32: 27.02 | R32: 2.53 | S32: 133.1 | T32: 49.17 | U32: 107.48 | V32: 175.42 | X32: Direct taxes | Y32: -557 | Z32: -271 | AA32: -802 | AB32: -1154 | AC32: -1173 | AD32: -1089 | AF32: Direct taxes paid | AG32: -83.46 | AH32: -1.14 | AI32: -81.64 | AJ32: -190.99 | AK32: -298.89 | AL32: -494.09 | AN32: Purchase of investment in associate | AO32: 0 | AP32: 13.246 | AQ32: 23.242 | AR32: -10 | AS32: -200
A33: Realisation from FDs of IPO proceeds | B33: 92.58 | C33: 0 | D33: 0 | E33: 0 | F33: 0 | G33: 0 | I33: Net cash flow generated/used in operating activities | J33: =SUM(J31:J32) -> 7623 | K33: =SUM(K31:K32) -> 9163 | L33: =SUM(L31:L32) -> 9048 | M33: =SUM(M31:M32) -> 9991 | N33: =SUM(N31:N32) -> 15469 | P33: Purchase of current investments | Q33: -77847.64 | R33: -55913.52 | S33: -64874.32 | T33: -78483.49 | U33: -72237.17 | V33: -65999.55 | X33: Net cash generated from/used in operating activities | Y33: =Y31+Y32 -> -348 | Z33: =Z31+Z32 -> 4139 | AA33: =AA31+AA32 -> -724 | AB33: =AB31+AB32 -> 1370 | AC33: =AC31+AC32 -> 1695 | AD33: =AD31+AD32 -> -541 | AF33: Net cash from/used in Operating activities | AG33: =AG31+AG32 -> 361.16 | AH33: =AH31+AH32 -> 373.84 | AI33: =AI31+AI32 -> 58.08 | AJ33: =AJ31+AJ32 -> 594.88 | AK33: =AK31+AK32 -> 1348.98 | AL33: =AL31+AL32 -> 1660.9 | AN33: Government grant related to assets received | AO33: 0 | AP33: 0.07 | AQ33: 0.367 | AR33: 22.016 | AS33: 28.113
A34: Realisation from FDs of QIP proceeds | B34: 129 | C34: 783 | D34: 1050 | E34: 37.4 | F34: -136.26 | G34: 998.44 | I34: Cash flow from Investing activities | P34: Sale/redemption of current investments | Q34: 72405.47 | R34: 61084.47 | S34: 68260.67 | T34: 73172.8 | U34: 75201.73 | V34: 66919.64 | X34: Cash flow from investing activities | AF34: Cash flow from Investing activities | AN34: Interest received | AO34: 8.69 | AP34: 0 | AQ34: 0 | AR34: 0.351 | AS34: 2.247
A35: Interest received | B35: 11.84 | C35: 129.09 | D35: 42.8 | E35: 38.72 | F35: 262.29 | G35: 103.1 | I35: Purchase of PPE | J35: -850 | K35: -741 | L35: -1225 | M35: -1174 | N35: -1468 | P35: Investment in associate | Q35: 0 | R35: -1.87 | S35: -1.87 | T35: -1.88 | U35: -65.04 | V35: -29.99 | X35: Purchase of PPE | Y35: -355 | Z35: -146 | AA35: -224 | AB35: -432 | AC35: -691 | AD35: -494 | AF35: Purchase of PPE and investment property | AG35: -155.91 | AH35: -113.36 | AI35: -270.92 | AJ35: -503.4 | AK35: -736.95 | AL35: -1268.19 | AN35: Dividend income from current investment | AO35: 0 | AP35: 0 | AQ35: 0 | AR35: 0 | AS35: 0
A36: Gain on sale of investments | B36: 10.16 | C36: 2.56 | D36: 3.66 | E36: 5.66 | F36: 0 | G36: 0 | I36: Sale proceeds of PPE | J36: 52 | K36: 97 | L36: 146 | M36: 121 | N36: 20 | P36: Purchase of non-current investments | Q36: -1987.78 | R36: -1639.74 | S36: -4902.02 | T36: -2448.96 | U36: -2870.12 | V36: -373.69 | X36: Proceeds from sale of PPE | Y36: 10 | Z36: 7 | AA36: 8 | AB36: 12 | AC36: 20 | AD36: 24 | AF36: Sale of PPE and investment property | AG36: 41.68 | AH36: 22.34 | AI36: 60.82 | AJ36: 279.91 | AK36: 343.21 | AL36: 406.52 | AN36: Purchase of current investments | AO36: 0 | AP36: 0 | AQ36: 0 | AR36: 0 | AS36: 0
A37: Rent income received | B37: 2.88 | C37: 2.89 | D37: 3.55 | E37: 4.69 | F37: 4.9 | G37: 5.2 | I37: Purchase of intangible assets | J37: -12 | K37: -3422 | L37: -3 | M37: -18 | N37: -9 | P37: Redemption proceeds of non-current investments | Q37: 3429.63 | R37: 1712.05 | S37: 2731.24 | T37: 4057.6 | U37: 2627.78 | V37: 390.91 | X37: Investment in non convertible debentures | Y37: 0 | Z37: -5 | AA37: -100 | AB37: -353 | AC37: -393 | AD37: -663 | AF37: Purchase of investments | AG37: -2894.79 | AH37: -590.63 | AI37: -1322.04 | AJ37: -1609.56 | AK37: -1937.98 | AL37: -3884.85 | AN37: Proceeds from sale of current investments | AO37: 0 | AP37: 0 | AQ37: 0 | AR37: 0 | AS37: 0
A38: Total | B38: =SUM(B32:B37) -> 252.61 | C38: =SUM(C32:C37) -> 919.42 | D38: =SUM(D32:D37) -> 1120.93 | E38: =SUM(E32:E37) -> 91.93 | F38: =SUM(F32:F37) -> 140.38 | G38: =SUM(G32:G37) -> 1112.57 | I38: Sale proceeds of intangible assets | J38: 0 | K38: 0 | L38: 29 | M38: 60 | N38: 0 | P38: Payment towards business combination | Q38: 0 | R38: -2189.22 | S38: -71.25 | T38: -63.75 | U38: 0 | V38: -280.45 | X38: Inter-corporate deposits placed | Y38: -100 | Z38: -150 | AA38: -1094 | AB38: -570 | AC38: -821 | AD38: -332 | AF38: Sale of investments | AG38: 2237.45 | AH38: 730.59 | AI38: 1530.42 | AJ38: 1616.01 | AK38: 1808.09 | AL38: 3726.26 | AN38: Increase/decrease in other bank balances | AO38: -51.614 | AP38: -101.063 | AQ38: 21.702 | AR38: -86.759 | AS38: 35.015
A39: Purchase of PPE, intangible assets, investment property | B39: -1712.17 | C39: -2029.42 | D39: -2410.42 | E39: -2211.95 | F39: -2731.25 | G39: -3423.04 | I39: Investments in subsidiary | J39: 0 | K39: 0 | L39: 0 | M39: -264 | N39: 0 | P39: Dividend from associates and joint ventures | Q39: 8.34 | R39: 7.18 | S39: 0.01 | T39: 56 | U39: 24.52 | V39: 25.53 | X39: Proceeds from inter-corporate deposits | Y39: 300 | Z39: 100 | AA39: 750 | AB39: 864 | AC39: 678 | AD39: 575 | AF39: Loans given | AG39: -88.25 | AH39: -13.95 | AI39: 0 | AJ39: 10 | AK39: 2.36 | AL39: 5.81 | AN39: Net cash flows from/used in investing activities | AO39: =SUM(AO28:AO38) -> -471.096 | AP39: =SUM(AP28:AP38) -> -1010.639 | AQ39: =SUM(AQ28:AQ38) -> -1704.598 | AR39: =SUM(AR28:AR38) -> -3289.867 | AS39: =SUM(AS28:AS38) -> -4316.78
A40: Purchase of non-current investments | B40: 0 | C40: 0 | D40: 0 | E40: 0 | F40: 0 | G40: -2 | I40: Transaction cost on acquisition | J40: 0 | K40: 0 | L40: 0 | M40: -2 | N40: 0 | P40: Dividend from others | Q40: 8.31 | R40: 0.07 | S40: 16.06 | T40: 18.56 | U40: 11.13 | V40: 12.14 | X40: Bank deposits placed/matured | Y40: 331 | Z40: -73 | AA40: -975 | AB40: 243 | AC40: 309 | AD40: 325 | AF40: Repayment of loans given | AG40: 32.5 | AH40: 0 | AI40: 15 | AJ40: 7.7 | AK40: 73.58 | AL40: 0 | AN40: Financing activities
A41: Proceeds from sale of current investments | B41: 0 | C41: 0 | D41: 0 | E41: 0 | F41: 4323.81 | G41: 5073.51 | I41: Investment in joint venture | J41: 0 | K41: 0 | L41: 0 | M41: -70 | N41: 0 | P41: Interest received | Q41: 1513.35 | R41: 1274.92 | S41: 1034.55 | T41: 1323.74 | U41: 1138.35 | V41: 1072.28 | X41: Proceeds from sale of investment in JV | Y41: 0 | Z41: 43 | AA41: 0 | AB41: 0 | AC41: -29 | AD41: 0 | AF41: Interest received | AG41: 18.97 | AH41: 20.82 | AI41: 107.8 | AJ41: 146.86 | AK41: 0 | AL41: 125.85 | AN41: Proceeds from long-term borrowings | AO41: 773.482 | AP41: 854.806 | AQ41: 1477.72 | AR41: 2401.661 | AS41: 1771.127
A42: Purchase of current investments | B42: 0 | C42: 0 | D42: 0 | E42: 0 | F42: -4201.17 | G42: -4946.35 | I42: Continegent consideration paid on business combination | J42: -30 | K42: -33 | L42: -41 | M42: -40 | N42: -4 | P42: Investment in bank deposits | Q42: -5602.32 | R42: -4691.92 | S42: -4531.12 | T42: -8904.33 | U42: -4612.1 | V42: -6256.85 | X42: Purchase of investment in subsidiaries, JV and equity | Y42: -39 | Z42: 0 | AA42: -153 | AB42: -1 | AC42: 249 | AD42: 288 | AF42: Purchase of/ subscription to investments in subsidiaries, JV and associates | AG42: -22 | AH42: -45 | AI42: -66.27 | AJ42: -51.5 | AK42: -61.85 | AL42: -36.51 | AN42: Repayment of long-term borrowings | AO42: -1233.225 | AP42: -640.851 | AQ42: -1137.359 | AR42: -1276.522 | AS42: -5508.416
A43: QIP proceeds deposited FDs | B43: -3197 | C43: 0 | D43: 0 | E43: -193.08 | F43: 0 | G43: 0 | I43: Purchase of current investments | J43: -36090 | K43: -39876 | L43: -48522 | M43: -22649 | N43: -21337 | P43: Redemption/maturity of bank deposits | Q43: 4321.2 | R43: 6977.33 | S43: 4546.49 | T43: 6754.44 | U43: 5800 | V43: 6931.16 | X43: Purchase of mutual funds | Y43: -13 | Z43: -2651 | AA43: 2870 | AB43: -1750 | AC43: -7208 | AD43: -2384 | AF43: Dividend from investments in subsidiaries, JV and associates | AG43: 12.19 | AH43: 4.78 | AI43: 0 | AJ43: 0 | AN43: Repayment of lease liabilities | AO43: -11.155 | AP43: -18.865 | AQ43: -23.44 | AR43: -29.507 | AS43: -155.865
A44: Net cash flow from/used in investing activities | B44: =SUM(B38:B43) -> -4656.56 | C44: =SUM(C38:C43) -> -1110 | D44: =SUM(D38:D43) -> -1289.49 | E44: =SUM(E38:E43) -> -2313.1 | F44: =SUM(F38:F43) -> -2468.23 | G44: =SUM(G38:G43) -> -2185.31 | I44: Sale proceeds of current investments | J44: 37690 | K44: 38486 | L44: 47786 | M44: 23462 | N44: 19846 | P44: Investment in deposit with housing finance companies | Q44: -712.16 | R44: -78.38 | S44: -3011.37 | T44: -3520 | U44: 0 | V44: -1200 | X44: Loan given to Group's franchisees and vendors | Y44: 0 | Z44: -97 | AA44: -34 | AB44: 0 | AC44: 7200 | AD44: 2332 | AF44: Dividend from investments | AG44: 2.59 | AH44: 0.06 | AI44: 1.22 | AJ44: 1.34 | AK44: 1.32 | AL44: 1.44 | AN44: Repayment of deferred payment liabilities | AO44: 0 | AP44: -85.366 | AQ44: -0.797 | AR44: 4.441 | AS44: 7511.88
A45: Cash flow from financing activities | I45: Loans repaid/given to othes | J45: 0 | K45: 0 | L45: -4 | M45: -1 | N45: 1 | P45: Redemption/maturity of deposits with HFCs | Q45: 7.1 | R45: 6.66 | S45: 578.82 | T45: 5000 | U45: 0 | V45: 500 | X45: Proceeds from loan given to group's franchisees and vendors | Y45: 0 | Z45: 94 | AA45: 34 | AB45: 3 | AC45: -21471 | AD45: -14679 | AF45: Net cash from/used in Investing activities | AG45: =SUM(AG35:AG44) -> -815.57 | AH45: =SUM(AH35:AH44) -> 15.65 | AI45: =SUM(AI35:AI44) -> 56.03 | AJ45: =SUM(AJ35:AJ44) -> -102.64 | AK45: =SUM(AK35:AK44) -> -508.22 | AL45: =SUM(AL35:AL44) -> -923.67 | AN45: Proceeds from short term borrowings (net) | AO45: 246.704 | AP45: 0 | AQ45: 0 | AR45: 381.266 | AS45: 185.696
A46: Proceeds from issue of QIP | B46: 4076.51 | C46: 0 | D46: 0 | E46: 0.91 | F46: 0 | G46: 0 | I46: Investment in term deposits | J46: -4979 | K46: -2874 | L46: -3711 | M46: -3668 | N46: -9170 | P46: Loans given | Q46: 700.22 | R46: 971.43 | S46: -13.16 | T46: -8.56 | U46: -12.55 | V46: -17.55 | X46: Lease payments received from sub lease | Y46: 28 | Z46: 28 | AA46: 26 | AB46: 30 | AC46: 21904 | AD46: 15422 | AF46: Cash flow from Financing activities | AN46: Proceeds from issue of share capital | AO46: 0 | AP46: 0 | AQ46: 0 | AR46: 0 | AS46: 0
A47: Proceeds from exercise of share options | B47: 110.34 | C47: 0 | D47: 0 | E47: 14.63 | F47: 74.81 | G47: 0 | I47: Redemption/maturity of term deposits | J47: 5658 | K47: 6601 | L47: 3656 | M47: 2488 | N47: 6369 | P47: Loans realised | Q47: -3.61 | R47: -2.44 | S47: 7.32 | T47: 9.34 | U47: 11.29 | V47: 13.88 | X47: Interest received | Y47: 73 | Z47: 49 | AA47: 56 | AB47: 143 | AC47: 64 | AD47: 132 | AF47: Redemption of securities | AG47: -100 | AH47: 0 | AI47: 551.31 | AJ47: 46.31 | AK47: 35.73 | AL47: 93.49 | AN47: Interest paid | AO47: -277.351 | AP47: -179.148 | AQ47: -171.679 | AR47: -269.442 | AS47: -464.955
A48: Proceeds from long term borrowings | B48: 50 | C48: 0 | D48: 0 | E48: 0 | F48: 0 | G48: 0 | I48: Interest received | J48: 351 | K48: 277 | L48: 161 | M48: 259 | N48: 425 | P48: Net cash from/used in Investing activities | Q48: =SUM(Q31:Q47) -> -6174.02 | R48: =SUM(R31:R47) -> 5682.91 | S48: =SUM(S31:S47) -> -2238.49 | T48: =SUM(T31:T47) -> -5732.31 | U48: =SUM(U31:U47) -> 1562.77 | V48: =SUM(V31:V47) -> -395.82 | X48: Net cash from/used in investing activities | Y48: =SUM(Y35:Y47) -> 235 | Z48: =SUM(Z35:Z47) -> -2801 | AA48: =SUM(AA35:AA47) -> 1164 | AB48: =SUM(AB35:AB47) -> -1811 | AC48: =SUM(AC35:AC47) -> -189 | AD48: =SUM(AD35:AD47) -> 546 | AF48: Issue of securities (net) | AG48: 1032.42 | AH48: -0.26 | AI48: -300.9 | AJ48: 0 | AK48: -0.05 | AL48: 0 | AN48: Share issue expenses paid | AO48: 0 | AP48: 0 | AQ48: 0 | AR48: 0 | AS48: -61.1
A49: Proceeds from short term borrowings | B49: 261.03 | C49: 200 | D49: 248 | E49: 0 | F49: 0 | G49: 0 | I49: Dividend received | J49: 1 | K49: 1 | L49: 1 | M49: 2 | N49: 3 | P49: Cash flow from Financing activities | X49: Cash flow from financing activities | AF49: Short term borrowings taken | AG49: 93.45 | AH49: 0 | AI49: 0 | AJ49: 173.27 | AN49: Dividends paid | AO49: -72.172 | AP49: -108.258 | AQ49: -162.387 | AR49: -227.348 | AS49: -324.82
A50: Proceeds from commercial papers | B50: 789.46 | C50: 0 | D50: 0 | E50: 0 | F50: 0 | G50: 0 | I50: Stamp duty payment on issue of equity shares | J50: 0 | K50: -44 | L50: -1 | M50: 0 | N50: 0 | P50: Proceeds from issue of share capital | Q50: 625.3 | R50: 290.65 | S50: =291.82-0.34 -> 291.48 | T50: 2477.39 | U50: 1442.83 | V50: 797.33 | X50: Repayment/proceeds from long term borrowings | Y50: 693 | Z50: -12 | AA50: -7 | AB50: -7 | AC50: 3301 | AD50: =70-378 -> -308 | AF50: Repayment of short term borrowings | AG50: -186.49 | AH50: 0 | AI50: 0 | AJ50: -173.27 | AK50: -277.46 | AL50: -539.69 | AN50: Dividend distribution tax paid | AO50: 0 | AP50: 0 | AQ50: 0 | AR50: 0.351 | AS50: 0
A51: Proceeds of non convertible debentures | B51: 300 | C51: 0 | D51: 0 | E51: 0 | F51: 0 | G51: 0 | I51: Net cash flow from/used in Investing activities | J51: =SUM(J35:J50) -> 1791 | K51: =SUM(K35:K50) -> -1528 | L51: =SUM(L35:L50) -> -1728 | M51: =SUM(M35:M50) -> -1494 | N51: =SUM(N35:N50) -> -5324 | P51: Repayment of non-current borrowings | Q51: -3.42 | R51: -2.28 | S51: -0.35 | T51: -0.73 | U51: -1.57 | V51: -1.52 | X51: Repayment/proceeds from borrowings | Y51: 0 | Z51: -550 | AA51: 349 | AB51: 1684 | AC51: 2328 | AD51: 2529 | AF51: Finance cost | AG51: -251.15 | AH51: -248.88 | AI51: -69.42 | AJ51: -139.74 | AK51: -309.4 | AL51: -133.88 | AN51: Net cash used in/flows from financing activities | AO51: =SUM(AO41:AO50) -> -573.717 | AP51: =SUM(AP41:AP50) -> -177.682 | AQ51: =SUM(AQ41:AQ50) -> -17.942 | AR51: =SUM(AR41:AR50) -> 984.9 | AS51: =SUM(AS41:AS50) -> 2953.547
A52: Repayment of long term borrowings | B52: -200 | C52: 0 | D52: 0 | E52: 0 | F52: 0 | G52: 0 | I52: Cash flow from Financing activities | P52: Proceeds from current borrowings | Q52: 0 | R52: 0 | S52: 0 | T52: 0 | U52: 8 | V52: 89.5 | X52: Dividends paid including dividend distribution tax | Y52: -536 | Z52: -355 | AA52: -355 | AB52: -666 | AC52: -888 | AD52: -976 | AF52: Dividend paid | AG52: -52.01 | AH52: -35.54 | AI52: -246.25 | AJ52: -358.72 | AK52: 0 | AL52: 0 | AN52: Net change in cash and cash equivalents | AO52: =AO26+AO39+AO51 -> -32.826 | AP52: =AP26+AP39+AP51 -> 43.101 | AQ52: =AQ26+AQ39+AQ51 -> 68.223 | AR52: =AR26+AR39+AR51 -> 85.8839 | AS52: =AS26+AS39+AS51 -> 2017.8712
A53: Repayment of short term borrowings | B53: -315 | C53: -203.73 | D53: -248 | E53: 0 | F53: 0 | G53: 0 | I53: Dividend paid | J53: -5196 | K53: -8811 | L53: -7526 | M53: -8474 | N53: -9416 | P53: Repayment of current borrowings | Q53: 0 | R53: 0 | S53: 0 | T53: 0 | U53: 0 | V53: -52.5 | X53: Payment of lease liabilities excluding interest paid | Y53: -233 | Z53: -114 | AA53: -172 | AB53: -254 | AC53: -318 | AD53: -700 | AF53: Payment of lease liabilities | AG53: -84.28 | AH53: -87.24 | AI53: -42.72 | AJ53: -39.26 | AK53: -78.27 | AL53: -113.59 | AN53: Cash and cash equivalents at the beginning of year | AO53: 137.968 | AP53: 104.558 | AQ53: 150.75 | AR53: 154.332 | AS53: 242.212
A54: Repayment of commercial papers | B54: -1034.99 | C54: 0 | D54: 0 | E54: 0 | F54: 0 | G54: 0 | I54: Dividend distribution tax paid | J54: -1061 | K54: 0 | L54: 0 | M54: 0 | N54: 0 | P54: Payment of lease liabilities | Q54: =-49.35 -> -49.35 | R54: -54.73 | S54: -59.02 | T54: -59.11 | U54: -66.89 | V54: -65.52 | X54: Finance costs paid | Y54: -166 | Z54: -203 | AA54: -218 | AB54: -300 | AC54: -619 | AD54: -538 | AF54: Net cash from/used in Financing activities | AG54: =SUM(AG47:AG53) -> 451.94 | AH54: =SUM(AH47:AH53) -> -371.92 | AI54: =SUM(AI47:AI53) -> -107.98 | AJ54: =SUM(AJ47:AJ53) -> -491.41 | AK54: =SUM(AK47:AK53) -> -629.45 | AL54: =SUM(AL47:AL53) -> -693.67 | AN54: Unrealised exchange loss on translation of cash and cash equivalents in subsidiary | AO54: -0.584 | AP54: 3.091 | AQ54: -63.907 | AR54: 2.069 | AS54: 6.217
A55: Repayment of non convertible debentures | B55: -512 | C55: -34 | D55: 0 | E55: 0 | F55: 0 | G55: 0 | I55: Amount taken for short term purpose | J55: -99 | K55: 188 | L55: 55 | M55: 286 | N55: 0 | P55: Interest paid | Q55: -43.84 | R55: -41.23 | S55: -39.55 | T55: -41.42 | U55: -46.25 | V55: -50.01 | X55: Acquisition of treasury shares | Y55: 0 | Z55: 0 | AA55: 0 | AB55: 0 | AC55: -236 | AD55: -6 | AF55: Effect of exchange fluctuation on translation reserve | AG55: -0.01 | AH55: 0 | AI55: 0 | AJ55: 0.01 | AK55: 0.01 | AL55: -0.04 | AN55: Cash and cash equivalents at the end of the year | AO55: =SUM(AO52:AO54) -> 104.558 | AP55: =SUM(AP52:AP54) -> 150.75 | AQ55: =SUM(AQ52:AQ54) -> 155.066 | AR55: =SUM(AR52:AR54) -> 242.2849 | AS55: =SUM(AS52:AS54) -> 2266.3002
A56: Payment of lease liability | B56: -70.06 | C56: -98.17 | D56: -125.45 | E56: -153.27 | F56: -164.32 | G56: -189.85 | I56: Repayment of amount taken for short term purpose | J56: 0 | K56: -188 | L56: -55 | M56: -201 | N56: -85 | P56: Net increase/decrease in statutory restricted accounts balances | Q56: -1.13 | R56: 41.17 | S56: 15.26 | T56: 14.94 | U56: 12.12 | V56: 8.09 | X56: Acquisition of non controlling interest | Y56: 0 | Z56: 0 | AA56: 0 | AB56: 0 | AC56: -4696 | AD56: -1 | AF56: Net increase/decrease in Cash and cash equivalents | AG56: =AG33+AG45+AG54+AG55 -> -2.48 | AH56: =AH33+AH45+AH54+AH55 -> 17.57 | AI56: =AI33+AI45+AI54+AI55 -> 6.13 | AJ56: =AJ33+AJ45+AJ54+AJ55 -> 0.84 | AK56: =AK33+AK45+AK54+AK55 -> 211.32 | AL56: =AL33+AL45+AL54+AL55 -> 43.52
A57: Interest paid on lease liability | B57: -29.7 | C57: -37.5 | D57: -52.23 | E57: -66.37 | F57: -56.96 | G57: -67.29 | I57: Borrowings repaid | J57: 0 | K57: 0 | L57: 0 | M57: -7 | N57: 0 | P57: Dividends paid | Q57: -7301.62 | R57: -18881.39 | S57: -13788.32 | T57: -15417.53 | U57: -19899.2 | V57: -17782.22 | X57: Acquisition of ESOP right | Y57: 0 | Z57: 0 | AA57: 0 | AB57: 0 | AC57: -201 | AD57: 0 | AF57: Opening balance of cash and cash equivalents | AG57: 51.46 | AH57: 56 | AI57: 76.26 | AJ57: 82.39 | AK57: 83.23 | AL57: 294.55
A58: Interest paid | B58: -68.17 | C58: -6.1 | D58: -1.56 | E58: -1.04 | F58: -1.17 | G58: -2.16 | I58: Principal payments of lease liabilities | J58: -373 | K58: -406 | L58: -407 | M58: -467 | N58: -423 | P58: Dividend distribution tax paid/refund received | Q58: -1407.42 | R58: 13.98 | S58: 0 | T58: 20.43 | U58: 0 | V58: 19.45 | X58: Share based payments | Y58: 0 | Z58: 0 | AA58: 0 | AB58: 0 | AC58: 0 | AD58: -7 | AF58: Cash and cash equivalents taken over on acquisition | AG58: 7.02 | AH58: 2.06 | AI58: 0 | AJ58: 0 | AK58: 0 | AL58: 0.4
A59: Cash flow from/used in financing activities | B59: =SUM(B46:B58) -> 3357.42 | C59: =SUM(C46:C58) -> -179.5 | D59: =SUM(D46:D58) -> -179.24 | E59: =SUM(E46:E58) -> -205.14 | F59: =SUM(F46:F58) -> -147.64 | G59: =SUM(G46:G58) -> -259.3 | I59: Interest paid on lease liabilities | J59: -80 | K59: -86 | L59: -80 | M59: -84 | N59: -106 | P59: Net cash from/used in Financing activities | Q59: =SUM(Q50:Q58) -> -8181.48 | R59: =SUM(R50:R58) -> -18633.83 | S59: =SUM(S50:S58) -> -13580.5 | T59: =SUM(T50:T58) -> -13006.03 | U59: =SUM(U50:U58) -> -18550.96 | V59: =SUM(V50:V58) -> -17037.4 | AF59: Closing balance of cash and cash equivalents | AG59: =AG56+AG57+AG58 -> 56 | AH59: =AH56+AH57+AH58 -> 75.63 | AI59: =AI56+AI57+AI58 -> 82.39 | AJ59: =AJ56+AJ57+AJ58 -> 83.23 | AK59: =AK56+AK57+AK58 -> 294.55 | AL59: =AL56+AL57+AL58 -> 338.47
A60: Net increase/decrease in cash and cash equivalent | B60: =B30+B44+B59 -> -19 | C60: =C30+C44+C59 -> 85.64 | D60: =D30+D44+D59 -> -96.38 | E60: =E30+E44+E59 -> 112.03 | F60: =F30+F44+F59 -> 129.97 | G60: =G30+G44+G59 -> 18.36 | I60: Interest paid other than on lease liabilities | J60: -10 | K60: -6 | L60: -2 | M60: -4 | N60: -4 | P60: Ne increase/decrease in cash and cash equivalents | Q60: =Q29+Q48+Q59 -> 334.16 | R60: =R29+R48+R59 -> -423.83 | S60: =S29+S48+S59 -> -43.48 | T60: =T29+T48+T59 -> 139.21 | U60: =U29+U48+U59 -> 190.67 | V60: =V29+V48+V59 -> 193.82 | X60: Net cash from/used financing activities | Y60: =SUM(Y50:Y59) -> -242 | Z60: =SUM(Z50:Z59) -> -1234 | AA60: =SUM(AA50:AA59) -> -403 | AB60: =SUM(AB50:AB59) -> 457 | AC60: =SUM(AC50:AC59) -> -1329 | AD60: =SUM(AD50:AD59) -> -7
A61: Cash and cash equivalents at the beginning of the year | B61: 124.86 | C61: 105.86 | D61: 191.5 | E61: 95.12 | F61: 207.15 | G61: 337.12 | I61: Employee stock options paid | J61: 0 | K61: 0 | L61: 0 | M61: -2 | N61: 0 | P61: Opening cash and cash equivalents | Q61: 342.88 | R61: 677.04 | S61: 310.16 | T61: 266.68 | U61: 405.91 | V61: 596.58 | X61: Net increase/decrease in cash and cash equivalents | Y61: =Y33+Y48+Y60 -> -355 | Z61: =Z33+Z48+Z60 -> 104 | AA61: =AA33+AA48+AA60 -> 37 | AB61: =AB33+AB48+AB60 -> 16 | AC61: =AC33+AC48+AC60 -> 177 | AD61: =AD33+AD48+AD60 -> -2
A62: Cash and cash equivalents at the end of year | B62: =B60+B61 -> 105.86 | C62: =C60+C61 -> 191.5 | D62: =D60+D61 -> 95.12 | E62: =E60+E61 -> 207.15 | F62: =F60+F61 -> 337.12 | G62: =G60+G61 -> 355.48 | I62: Net cash flows used in financing activities | J62: =SUM(J53:J61) -> -6819 | K62: =SUM(K53:K61) -> -9309 | L62: =SUM(L53:L61) -> -8015 | M62: =SUM(M53:M61) -> -8953 | N62: =SUM(N53:N61) -> -10034 | P62: Cash and cash equivalents acquired on business combination | Q62: 0 | R62: 56.95 | S62: 0 | T62: 0 | U62: 0 | V62: =-199.74+31.72 -> -168.02 | X62: Opening balance | Y62: 430 | Z62: 75 | AA62: 181 | AB62: 219 | AC62: 232 | AD62: 409
I63: Net increase/decrease in cash and cash equivalents | J63: =J33+J51+J62 -> 2595 | K63: =K33+K51+K62 -> -1674 | L63: =L33+L51+L62 -> -695 | M63: =M33+M51+M62 -> -456 | N63: =N33+N51+N62 -> 111 | P63: Closing cash and cash equivalents | Q63: =Q60+Q61+Q62 -> 677.04 | R63: =R60+R61+R62 -> 310.16 | S63: =S60+S61+S62 -> 266.68 | T63: =T60+T61+T62 -> 405.89 | U63: =U60+U61+U62 -> 596.58 | V63: =V60+V61+V62 -> 622.38 | X63: Unrealised exchange gain/loss | Y63: 0 | Z63: 2 | AA63: 1 | AB63: -3 | AC63: 0 | AD63: 0
I64: Cash and cash equivalents at the beginning of the year | J64: 621 | K64: 3216 | L64: 1842 | M64: 1147 | N64: 701 | X64: Closing balance | Y64: =Y61+Y62+Y63 -> 75 | Z64: =Z61+Z62+Z63 -> 181 | AA64: =AA61+AA62+AA63 -> 219 | AB64: =AB61+AB62+AB63 -> 232 | AC64: =AC61+AC62+AC63 -> 409 | AD64: =AD61+AD62+AD63 -> 407
I65: Cash required under business combination | J65: 0 | K65: 300 | L65: 0 | M65: 10 | N65: 0
I66: Cash and cash equivalents at the end of the year | J66: =J63+J64+J65 -> 3216 | K66: =K63+K64+K65 -> 1842 | L66: =L63+L64+L65 -> 1147 | M66: =M63+M64+M65 -> 701 | N66: =N63+N64+N65 -> 812

Sheet Financial Ratio
A1: #VALUE! | I1: #VALUE! | P1: #VALUE! | X1: #VALUE! | AF1: #VALUE! | AN1: #VALUE!
A2: Metrics | B2: 2020 | C2: 2021 | D2: 2022 | E2: 2023 | F2: 2024 | G2: 2025 | I2: Metrics | J2: 2020 | K2: 2021 | L2: 2022 | M2: 2023 | N2: 2024 | P2: Metrics | Q2: 2020 | R2: 2021 | S2: 2022 | T2: 2023 | U2: 2024 | V2: 2025 | X2: Metrics | Y2: 2020 | Z2: 2021 | AA2: 2022 | AB2: 2023 | AC2: 2024 | AD2: 2025 | AF2: Metrics | AG2: 2020 | AH2: 2021 | AI2: 2022 | AJ2: 2023 | AK2: 2024 | AL2: 2025 | AN2: Metrics | AO2: 2020 | AP2: 2021 | AQ2: 2022 | AR2: 2023 | AS2: 2024
A3: Profitability | I3: Profitability | P3: Profitability | X3: Profitability | AF3: Profitability | AN3: Profitability
A4: Gross Profit margin | B4: ='Common Size Income Statement'!B5 -> 0.15147727 | C4: ='Common Size Income Statement'!C5 -> 0.14862988 | D4: ='Common Size Income Statement'!D5 -> 0.14781896 | E4: ='Common Size Income Statement'!E5 -> 0.15069272 | F4: ='Common Size Income Statement'!F5 -> 0.14795163 | G4: ='Common Size Income Statement'!G5 -> 0.14835983 | I4: Gross Profit margin | J4: ='Common Size Income Statement'!J5 -> 0.54103512 | K4: ='Common Size Income Statement'!K5 -> 0.52904653 | L4: ='Common Size Income Statement'!L5 -> 0.50930481 | M4: ='Common Size Income Statement'!M5 -> 0.47646088 | N4: ='Common Size Income Statement'!N5 -> 0.51919349 | P4: Gross Profit margin | Q4: ='Common Size Income Statement'!Q5 -> 0.66249662 | R4: ='Common Size Income Statement'!R5 -> 0.62126997 | S4: ='Common Size Income Statement'!S5 -> 0.5953518 | T4: ='Common Size Income Statement'!T5 -> 0.62092984 | U4: ='Common Size Income Statement'!U5 -> 0.63485887 | V4: ='Common Size Income Statement'!V5 -> 0.60816529 | X4: Gross Profit margin | Y4: ='Common Size Income Statement'!Y5 -> 0.2801159 | Z4: ='Common Size Income Statement'!Z5 -> 0.24163741 | AA4: ='Common Size Income Statement'!AA5 -> 0.2485503 | AB4: ='Common Size Income Statement'!AB5 -> 0.25187924 | AC4: ='Common Size Income Statement'!AC5 -> 0.2280949 | AD4: ='Common Size Income Statement'!AD5 -> 0.21503242 | AF4: Gross Profit margin | AG4: ='Common Size Income Statement'!AG5 -> 0.46019484 | AH4: ='Common Size Income Statement'!AH5 -> 0.40839812 | AI4: ='Common Size Income Statement'!AI5 -> 0.44830392 | AJ4: ='Common Size Income Statement'!AJ5 -> 0.4273564 | AK4: ='Common Size Income Statement'!AK5 -> 0.43767045 | AL4: ='Common Size Income Statement'!AL5 -> 0.43452813 | AN4: Gross Profit margin | AO4: ='Common Size Income Statement'!AO5 -> 0.57839757 | AP4: ='Common Size Income Statement'!AP5 -> 0.54961722 | AQ4: ='Common Size Income Statement'!AQ5 -> 0.53242008 | AR4: ='Common Size Income Statement'!AR5 -> 0.54629867 | AS4: ='Common Size Income Statement'!AS5 -> 0.56522722
A5: EBITDA margin | B5: ='Common Size Income Statement'!B8 -> 0.1360556 | C5: ='Common Size Income Statement'!C8 -> 0.1378773 | D5: ='Common Size Income Statement'!D8 -> 0.13379597 | E5: ='Common Size Income Statement'!E8 -> 0.13722527 | F5: ='Common Size Income Statement'!F8 -> 0.13530239 | G5: ='Common Size Income Statement'!G8 -> 0.13463532 | I5: EBITDA margin | J5: ='Common Size Income Statement'!J8 -> 0.24786969 | K5: ='Common Size Income Statement'!K8 -> 0.24721443 | L5: ='Common Size Income Statement'!L8 -> 0.24514739 | M5: ='Common Size Income Statement'!M8 -> 0.23354242 | N5: ='Common Size Income Statement'!N8 -> 0.23689738 | P5: EBITDA margin | Q5: ='Common Size Income Statement'!Q8 -> 0.37475889 | R5: ='Common Size Income Statement'!R8 -> 0.31986947 | S5: ='Common Size Income Statement'!S8 -> 0.31682268 | T5: ='Common Size Income Statement'!T8 -> 0.33540944 | U5: ='Common Size Income Statement'!U8 -> 0.34171473 | V5: ='Common Size Income Statement'!V8 -> 0.31831056 | X5: EBITDA margin | Y5: ='Common Size Income Statement'!Y8 -> 0.11718602 | Z5: ='Common Size Income Statement'!Z8 -> 0.07965256 | AA5: ='Common Size Income Statement'!AA8 -> 0.11601097 | AB5: ='Common Size Income Statement'!AB8 -> 0.12024646 | AC5: ='Common Size Income Statement'!AC8 -> 0.10359408 | AD5: ='Common Size Income Statement'!AD8 -> 0.0941842 | AF5: EBITDA margin | AG5: ='Common Size Income Statement'!AG8 -> 0.15463084 | AH5: ='Common Size Income Statement'!AH8 -> 0.066294891 | AI5: ='Common Size Income Statement'!AI8 -> 0.1275828 | AJ5: ='Common Size Income Statement'!AJ8 -> 0.1302654 | AK5: ='Common Size Income Statement'!AK8 -> 0.15532226 | AL5: ='Common Size Income Statement'!AL8 -> 0.16098703 | AN5: EBITDA margin | AO5: ='Common Size Income Statement'!AO8 -> 0.18332909 | AP5: ='Common Size Income Statement'!AP8 -> 0.18470543 | AQ5: ='Common Size Income Statement'!AQ8 -> 0.20821425 | AR5: ='Common Size Income Statement'!AR8 -> 0.22115502 | AS5: ='Common Size Income Statement'!AS8 -> 0.23001785
A6: Net profit margin | B6: ='Common Size Income Statement'!B15 -> 0.052310798 | C6: ='Common Size Income Statement'!C15 -> 0.045538138 | D6: ='Common Size Income Statement'!D15 -> 0.048178816 | E6: ='Common Size Income Statement'!E15 -> 0.055517377 | F6: ='Common Size Income Statement'!F15 -> 0.04992456 | G6: ='Common Size Income Statement'!G15 -> 0.045612179 | I6: Net profit margin | J6: ='Common Size Income Statement'!J15 -> 0.17509603 | K6: ='Common Size Income Statement'!K15 -> 0.175215 | L6: ='Common Size Income Statement'!L15 -> 0.17029933 | M6: ='Common Size Income Statement'!M15 -> 0.16852023 | N6: ='Common Size Income Statement'!N15 -> 0.16615484 | P6: Net profit margin | Q6: ='Common Size Income Statement'!Q15 -> 0.30340002 | R6: ='Common Size Income Statement'!R15 -> 0.25177029 | S6: ='Common Size Income Statement'!S15 -> 0.23775998 | T6: ='Common Size Income Statement'!T15 -> 0.25453706 | U6: ='Common Size Income Statement'!U15 -> 0.28083582 | V6: ='Common Size Income Statement'!V15 -> 0.42949744 | X6: Net profit margin | Y6: ='Common Size Income Statement'!Y15 -> 0.070919628 | Z6: ='Common Size Income Statement'!Z15 -> 0.045000924 | AA6: ='Common Size Income Statement'!AA15 -> 0.076322095 | AB6: ='Common Size Income Statement'!AB15 -> 0.08069008 | AC6: ='Common Size Income Statement'!AC15 -> 0.068436301 | AD6: ='Common Size Income Statement'!AD15 -> 0.055197168 | AF6: Net profit margin | AG6: ='Common Size Income Statement'!AG15 -> 0.039131033 | AH6: ='Common Size Income Statement'!AH15 -> -0.041944342 | AI6: ='Common Size Income Statement'!AI15 -> 0.01265001 | AJ6: ='Common Size Income Statement'!AJ15 -> 0.03800282 | AK6: ='Common Size Income Statement'!AK15 -> 0.062853583 | AL6: ='Common Size Income Statement'!AL15 -> 0.084502069 | AN6: Net profit margin | AO6: ='Common Size Income Statement'!AO15 -> 0.064644688 | AP6: ='Common Size Income Statement'!AP15 -> 0.083280617 | AQ6: ='Common Size Income Statement'!AQ15 -> 0.11576217 | AR6: ='Common Size Income Statement'!AR15 -> 0.12880852 | AS6: ='Common Size Income Statement'!AS15 -> 0.12869102
A7: Return on equity | B7: ='Income Statement'!B21/'Balance Sheet'!B35 -> 0.11741485 | C7: ='Income Statement'!C21/'Balance Sheet'!C35 -> 0.09023474 | D7: ='Income Statement'!D21/'Balance Sheet'!D35 -> 0.1091104 | E7: ='Income Statement'!E21/'Balance Sheet'!E35 -> 0.14791794 | F7: ='Income Statement'!F21/'Balance Sheet'!F35 -> 0.13561341 | G7: ='Income Statement'!G21/'Balance Sheet'!G35 -> 0.1263587 | I7: Return on equity | J7: ='Income Statement'!J27/'Balance Sheet'!J35 -> 0.85681674 | K7: ='Income Statement'!K27/'Balance Sheet'!K35 -> 0.97004608 | L7: ='Income Statement'!L27/'Balance Sheet'!L35 -> 0.18643855 | M7: ='Income Statement'!M27/'Balance Sheet'!M35 -> 0.20663312 | N7: ='Income Statement'!N27/'Balance Sheet'!N35 -> 0.19994944 | P7: Return on equity | Q7: ='Income Statement'!Q30/'Balance Sheet'!Q40 -> 0.23751114 | R7: ='Income Statement'!R30/'Balance Sheet'!R40 -> 0.22049703 | S7: ='Income Statement'!S30/'Balance Sheet'!S40 -> 0.24677919 | T7: ='Income Statement'!T30/'Balance Sheet'!T40 -> 0.28008425 | U7: ='Income Statement'!U30/'Balance Sheet'!U40 -> 0.27709131 | V7: ='Income Statement'!V30/'Balance Sheet'!V40 -> 0.49791912 | X7: Return on equity | Y7: ='Income Statement'!Y28/'Balance Sheet'!Y37 -> 0.22373745 | Z7: ='Income Statement'!Z28/'Balance Sheet'!Z37 -> 0.12983204 | AA7: ='Income Statement'!AA28/'Balance Sheet'!AA37 -> 0.23550841 | AB7: ='Income Statement'!AB28/'Balance Sheet'!AB37 -> 0.2750336 | AC7: ='Income Statement'!AC28/'Balance Sheet'!AC37 -> 0.37219206 | AD7: ='Income Statement'!AD28/'Balance Sheet'!AD37 -> 0.28707846 | AF7: Return on equity | AG7: ='Income Statement'!AG25/'Balance Sheet'!AG39 -> 0.042952792 | AH7: ='Income Statement'!AH25/'Balance Sheet'!AH39 -> -0.076830737 | AI7: ='Income Statement'!AI25/'Balance Sheet'!AI39 -> 0.014357204 | AJ7: ='Income Statement'!AJ25/'Balance Sheet'!AJ39 -> 0.14783869 | AK7: ='Income Statement'!AK25/'Balance Sheet'!AK39 -> 0.36011154 | AL7: ='Income Statement'!AL25/'Balance Sheet'!AL39 -> 0.27481839 | AN7: Return on equity | AO7: ='Income Statement'!AO27/'Balance Sheet'!AO35 -> 0.099556456 | AP7: ='Income Statement'!AP27/'Balance Sheet'!AP35 -> 0.17777123 | AQ7: ='Income Statement'!AQ27/'Balance Sheet'!AQ35 -> 0.29721366 | AR7: ='Income Statement'!AR27/'Balance Sheet'!AR35 -> 0.29667127 | AS7: ='Income Statement'!AS27/'Balance Sheet'!AS35 -> 0.15736806
