Workbook

Sheet Company Info
A1: COMPANY PROFILE
A3: Company | B3: #VALUE! | C3: #VALUE! | D3: #VALUE! | E3: #VALUE! | F3: #VALUE!
A4: Name | B4: #VALUE! | C4: #VALUE! | D4: #VALUE! | E4: #VALUE! | F4: #VALUE!
A5: Industry | B5: {=_FV(B4,"Industry")} -> Transport Infrastructure | C5: {=_FV(C4,"Industry")} -> Construction & Engineering | D5: {=_FV(D4,"Industry")} -> Construction & Engineering | E5: {=_FV(E4,"Industry")} -> Construction & Engineering | F5: {=_FV(F4,"Industry")} -> Construction & Engineering
A6: Ticker Symbol | B6: {=_FV(B4,"Ticker symbol",TRUE)} -> ADANIPORTS | C6: {=_FV(C4,"Ticker symbol",TRUE)} -> KPIL | D6: {=_FV(D4,"Ticker symbol",TRUE)} -> KEC | E6: {=_FV(E4,"Ticker symbol",TRUE)} -> LT | F6: {=_FV(F4,"Ticker symbol",TRUE)} -> RVNL
A7: Year of establishment | B7: {=_FV(B4,"Year incorporated",TRUE)} -> 1998 | C7: {=_FV(C4,"Year incorporated",TRUE)} -> 1981 | D7: {=_FV(D4,"Year incorporated",TRUE)} -> 2005 | E7: {=_FV(E4,"Year incorporated",TRUE)} -> 1946 | F7: {=_FV(F4,"Year incorporated",TRUE)} -> 2003
A8: Employees | B8: {=_FV(B4,"Employees")} -> 3118 | C8: {=_FV(C4,"Employees")} -> 9870 | D8: {=_FV(D4,"Employees")} -> 7692 | E8: {=_FV(E4,"Employees")} -> 58244 | F8: {=_FV(F4,"Employees")} -> 213
A9: Beta | B9: {=_FV(B4,"Beta")} -> 1.4608 | C9: {=_FV(C4,"Beta")} -> 0.5909 | D9: {=_FV(D4,"Beta")} -> 0.6763 | E9: {=_FV(E4,"Beta")} -> 1.0837 | F9: {=_FV(F4,"Beta")} -> 1.4107
A10: Shares Outstanding | B10: {=_FV(B4,"Shares outstanding",TRUE)} -> 2160139000 | C10: {=_FV(C4,"Shares outstanding",TRUE)} -> 170772600 | D10: {=_FV(D4,"Shares outstanding",TRUE)} -> 266200000 | E10: {=_FV(E4,"Shares outstanding",TRUE)} -> 1375581000 | F10: {=_FV(F4,"Shares outstanding",TRUE)} -> 2085020000
B11: =B10/10000000 -> 216.0139 | C11: =C10/10000000 -> 17.07726 | D11: =D10/10000000 -> 26.62 | E11: =E10/10000000 -> 137.5581 | F11: =F10/10000000 -> 208.502
A12: Current Market Price | B12: {=_FV(B4,"Price")} -> 1444.9 | C12: {=_FV(C4,"Price")} -> 1276 | D12: {=_FV(D4,"Price")} -> 722.25 | E12: {=_FV(E4,"Price")} -> 3918.5 | F12: {=_FV(F4,"Price")} -> 315.9
A13: Market cap | B13: {=_FV(B4,"Market cap",TRUE)} -> 3128529000000 | C13: {=_FV(C4,"Market cap",TRUE)} -> 221304100000 | D13: {=_FV(D4,"Market cap",TRUE)} -> 202139000000 | E13: {=_FV(E4,"Market cap",TRUE)} -> 5340693000000 | F13: {=_FV(F4,"Market cap",TRUE)} -> 663036400000
B14: =B13/10000000 -> 312852.9 | C14: =C13/10000000 -> 22130.41 | D14: =D13/10000000 -> 20213.9 | E14: =E13/10000000 -> 534069.3 | F14: =F13/10000000 -> 66303.64
A15: Change (%) | B15: {=_FV(B4,"Change (%)",TRUE)} -> -0.002348 | C15: {=_FV(C4,"Change (%)",TRUE)} -> -0.015356 | D15: {=_FV(D4,"Change (%)",TRUE)} -> -0.048858 | E15: {=_FV(E4,"Change (%)",TRUE)} -> 0.009272 | F15: {=_FV(F4,"Change (%)",TRUE)} -> -0.006604
A16: Change (Rs) | B16: {=_FV(B4,"Change")} -> -3.4 | C16: {=_FV(C4,"Change")} -> -19.9 | D16: {=_FV(D4,"Change")} -> -37.1 | E16: {=_FV(E4,"Change")} -> 36 | F16: {=_FV(F4,"Change")} -> -2.1

Sheet Balance Sheet
A1: Consolidated Balance Sheet
E2: #VALUE! | M2: #VALUE! | U2: #VALUE! | AC2: #VALUE! | AK2: #VALUE!
A3: Particulars | B3: 2020 | C3: 2021 | D3: 2022 | E3: 2023 | F3: 2024 | G3: 2025 | I3: Particulars | J3: 2020 | K3: 2021 | L3: 2022 | M3: 2023 | N3: 2024 | O3: 2025 | Q3: Particulars | R3: 2020 | S3: 2021 | T3: 2022 | U3: 2023 | V3: 2024 | W3: 2025 | Y3: Particulars | Z3: 2020 | AA3: 2021 | AB3: 2022 | AC3: 2023 | AD3: 2024 | AE3: 2025 | AG3: Particulars | AH3: 2020 | AI3: 2021 | AJ3: 2022 | AK3: 2023 | AL3: 2024 | AM3: 2025
A4: ASSETS | I4: ASSETS | Q4: ASSETS | Y4: ASSETS | AG4: ASSETS
A5: Non-current assets | I5: Non-current assets | Q5: Non-current Assets | Y5: Non-current assets | AG5: Non-current assets
A6: PPE | B6: 25744.92 | C6: 36791.51 | D6: 41488.7 | E6: 48414 | F6: 51803.83 | G6: 62394.43 | I6: PPE | J6: 1571.09 | K6: 1622.03 | L6: 1626.61 | M6: 1980.78 | N6: 1996.33 | O6: 2181.29 | Q6: PPE | R6: 894.23 | S6: 979.45 | T6: 1011.95 | U6: 1067.23 | V6: 1141.22 | W6: 1073.99 | Y6: PPE | Z6: 6853.43 | AA6: 7462.21 | AB6: 10577.98 | AC6: 11336.28 | AD6: 13297.64 | AE6: 14128.56 | AG6: PPE | AH6: 16.5636 | AI6: 19.22 | AJ6: 23.09 | AK6: 26.63 | AL6: 28.86 | AM6: 537.21
A7: Right-of-use assets | B7: 1742.96 | C7: 1775.95 | D7: 2772.25 | E7: 3541.9 | F7: 3809.11 | G7: 6177.54 | I7: Capital work in progress | J7: 50.06 | K7: 29.49 | L7: 19.91 | M7: 52.28 | N7: 33.32 | O7: 28.58 | Q7: Right of use assets | R7: 147 | S7: 136.32 | T7: 231.32 | U7: 214.57 | V7: 195.24 | W7: 289.57 | Y7: Capital work in progress | Z7: 796.55 | AA7: 236.12 | AB7: 1170.32 | AC7: 2949.09 | AD7: 2897.04 | AE7: 2390.86 | AG7: Right of use assets | AH7: 265.0926 | AI7: 253.05 | AJ7: 335.5 | AK7: 313.39 | AL7: 328.88 | AM7: 346.13
A8: Capital work-in-progress | B8: 3216.33 | C8: 3697.13 | D8: 4022.9 | E8: 6814.03 | F8: 10936.09 | G8: 11592.19 | I8: Right of use assets | J8: 100.15 | K8: 109.79 | L8: 133.7 | M8: 106.16 | N8: 102.93 | O8: 161.78 | Q8: Capital work in progress | R8: 83.96 | S8: 17.9 | T8: 2.46 | U8: 11.45 | V8: 13.92 | W8: 38.52 | Y8: Investment Property | Z8: 490.4 | AA8: 421.61 | AB8: 3962.98 | AC8: 3360.22 | AD8: =1936.44+254.93 -> 2191.37 | AE8: =1157.33+501.3 -> 1658.63 | AG8: Capital work in progress | AH8: 18.3638 | AI8: 47.07 | AJ8: 1.2 | AK8: 1.27 | AL8: 93.79 | AM8: 0.32
A9: Investment Properties | B9: 0 | C9: 0 | D9: 0 | E9: 2473.38 | F9: 1345.3 | G9: 1459.16 | I9: Investment property | J9: 0.82 | K9: 0.82 | L9: 0.82 | M9: 0 | N9: 0 | O9: 0 | Q9: Goodwill | R9: 222.56 | S9: 215.36 | T9: 249.7 | U9: 268.49 | V9: 272.13 | W9: 278.22 | Y9: Goodwill | Z9: 0 | AA9: 0 | AB9: 7685.17 | AC9: 7798.65 | AD9: 7800.88 | AE9: 8348.48 | AG9: Intangible assets | AH9: 23.6478 | AI9: 19.88 | AJ9: 20.9 | AK9: 14.73 | AL9: 8.86 | AM9: 3.32
A10: Goodwill | B10: 3286.25 | C10: 4036.43 | D10: 6711.43 | E10: 6963.4 | F10: 6906.93 | G10: 7093.59 | I10: Goodwill | J10: 105.88 | K10: 114.76 | L10: 184.21 | M10: 183.61 | N10: 184.3 | O10: 184.73 | Q10: Intangible assets | R10: 87.99 | S10: 66.37 | T10: 44.68 | U10: 32.52 | V10: 19.68 | W10: 4.83 | Y10: Intangible assets | Z10: 83.72 | AA10: 55.39 | AB10: 18729.37 | AC10: 18007.98 | AD10: 17384.52 | AE10: 17050.76 | AG10: Intangible assets under development | AH10: 6.3706 | AI10: 6.37 | AJ10: 0 | AK10: 0 | AL10: 0 | AM10: 140.14
A11: Other intangible assets | B11: 1940.38 | C11: 5533.03 | D11: 11580.54 | E11: 11445.51 | F11: 11282.64 | G11: 12491.6 | I11: Other Intangible assets | J11: 1666.52 | K11: 1624.94 | L11: 1613.23 | M11: 853.88 | N11: 789.48 | O11: 723.84 | Q11: Investments | R11: 0 | S11: 0 | T11: 0 | U11: 0 | V11: 0 | W11: 0 | Y11: Intangible assets under development | Z11: 0.66 | AA11: 48.01 | AB11: 79.23 | AC11: 116.48 | AD11: 147.97 | AE11: 197.82 | AG11: Investments in Joint ventures | AH11: 1574.9679 | AI11: 1720.15 | AJ11: 1872.31 | AK11: 1893.76 | AL11: 2395.17 | AM11: 1764.13
A12: Intangible assets under development | B12: 0 | C12: 0 | D12: 0 | E12: 0 | F12: 0 | G12: 113.91 | I12: Intangible assets under development | J12: 4.2 | K12: 4.54 | L12: 4.72 | M12: 0 | N12: 0 | O12: 0 | Q12: Trade receivables | R12: 18.9 | S12: 182.13 | T12: 467.69 | U12: 359.3 | V12: 288.34 | W12: 214.93 | Y12: Right of use assets | Z12: 412.82 | AA12: 417.37 | AB12: 1989.51 | AC12: 2137.87 | AD12: 2289.41 | AE12: 2869.02 | AG12: Investments | AH12: 9.97 | AI12: 10 | AJ12: 10 | AK12: 10 | AL12: 10 | AM12: 0
A13: Investments accounted using equity method | B13: 826.01 | C13: 649.53 | D13: 1189.85 | E13: 2498.38 | F13: 2707.26 | G13: 3082.64 | I13: Investments | J13: 1.36 | K13: 1.13 | L13: 1.49 | M13: 1.55 | N13: 0 | O13: 0 | Q13: Loans | R13: 10.95 | S13: 13.24 | T13: 0 | U13: 0 | V13: 0 | Y13: Investments | Z13: 27975.28 | AA13: 28569.12 | AB13: =2521.16+7074.44 -> 9595.6 | AC13: =1304.86+7920.03 -> 9224.89 | AD13: =1264.25+9425.94 -> 10690.19 | AE13: =2318.42+9126.23 -> 11444.65 | AG13: Lease receivables | AH13: 1386.1361 | AI13: 1262.95 | AJ13: 1826.88 | AK13: 4964.36 | AL13: 4492.36 | AM13: 3992.85
A14: Investments | B14: 340.1 | C14: 447.86 | D14: 1923.1 | E14: 1059.47 | F14: 919.61 | G14: 824.93 | I14: Trade receivables | J14: 186.7 | K14: 187.85 | L14: 213.82 | M14: 188.79 | N14: 131.05 | O14: 80.5 | Q14: Other financial assets | R14: 0 | S14: 0 | T14: 41.03 | U14: 76.2 | V14: 61.94 | W14: 66.07 | Y14: Loans | Z14: 3507 | AA14: 2567.05 | AB14: =46736.84+284.54 -> 47021.38 | AC14: =40920.92+356 -> 41276.92 | AD14: =52154.76+475.46 -> 52630.22 | AE14: =62847.35+348.96 -> 63196.31 | AG14: Loans | AH14: 9.117 | AI14: 8.17 | AJ14: 6.06 | AK14: 4.87 | AL14: 4.07 | AM14: 4.72
A15: Loans | B15: 0 | C15: 235 | D15: 87 | E15: 1582.15 | F15: 55 | G15: 24 | I15: Loans | J15: 76.53 | K15: 88.88 | L15: 0 | M15: 0 | N15: 0 | O15: 0 | Q15: Deferred tax assets (net) | R15: 22.37 | S15: 61.93 | T15: 214.13 | U15: 327.31 | V15: 353.66 | W15: 452.7 | Y15: Other financial assets | Z15: 304.48 | AA15: 403.84 | AB15: 2134.9 | AC15: 1965.78 | AD15: 1952.08 | AE15: 1863.04 | AG15: Others | AH15: 519.4188 | AI15: 744.32 | AJ15: 1086.56 | AK15: 1799.66 | AL15: 2010.59 | AM15: 1177.53
A16: Loans to Joint venture entities | B16: 1264.37 | C16: 751.26 | D16: 484.41 | E16: 6.7 | F16: 4.52 | G16: 704.15 | I16: Others | J16: 36.55 | K16: 43.18 | L16: 160.5 | M16: 156.34 | N16: 194.73 | O16: 292.36 | Q16: Non-current tax assets (net) | R16: 155.81 | S16: 168.51 | T16: 179.43 | U16: 268.03 | V16: 294.06 | W16: 138.92 | Y16: Deferred tax assets (net) | Z16: 1428.2 | AA16: 494 | AB16: 2840.1 | AC16: 3984.79 | AD16: 3863.72 | AE16: 3792.88 | AG16: Deferred tax assets (net) | AH16: 42.7848 | AI16: 43.13 | AJ16: 13.15 | AK16: 13.81 | AL16: 13.99 | AM16: 45.29
A17: Other financial assets | I17: Deferred tax assets (net) | J17: 118.63 | K17: 129.94 | L17: 198.02 | M17: 178.43 | N17: 187.66 | O17: 270.52 | Q17: Other non-current assets | R17: 212.04 | S17: 323.25 | T17: 209.6 | U17: 217.88 | V17: 233.43 | W17: 235.53 | Y17: Current tax assets (net) | Z17: 0 | AA17: 0 | AB17: 0 | AC17: 0 | AD17: 4245.78 | AE17: 4581.6 | AG17: Other non-current assets | AH17: 0.4429 | AI17: 102.32 | AJ17: 204.68 | AK17: 255.99 | AL17: 479.63 | AM17: 0.38
A18: Bank deposits having maturity over 12 months | B18: 6.9 | C18: 89.42 | D18: 3072.08 | E18: 1552.97 | F18: 1523.53 | G18: 1633.51 | I18: Non-current tax assets (net) | J18: 7.13 | K18: 3.17 | L18: 7.18 | M18: 0.59 | N18: 1.17 | O18: 2 | Q18: Total non-current assets | R18: =SUM(R6:R17) -> 1855.81 | S18: =SUM(S6:S17) -> 2164.46 | T18: =SUM(T6:T17) -> 2651.99 | U18: =SUM(U6:U17) -> 2842.98 | V18: =SUM(V6:V17) -> 2873.62 | W18: =SUM(W6:W17) -> 2793.28 | Y18: Other non-current assets | Z18: 4068.94 | AA18: 3646.05 | AB18: 6077.62 | AC18: 5989.04 | AD18: 2156.55 | AE18: 2659.78 | AG18: Total non-current assets | AH18: =SUM(AH6:AH17) -> 3872.8759 | AI18: =SUM(AI6:AI17) -> 4236.63 | AJ18: =SUM(AJ6:AJ17) -> 5400.33 | AK18: =SUM(AK6:AK17) -> 9298.47 | AL18: =SUM(AL6:AL17) -> 9866.2 | AM18: =SUM(AM6:AM17) -> 8012.02
A19: Other financial assets | B19: 5052.26 | C19: 5010.85 | D19: 4607.95 | E19: 4567.78 | F19: 3167.65 | G19: 3323.67 | I19: Other non-current assets | J19: 55.34 | K19: 72.39 | L19: 133.54 | M19: 127.19 | N19: 137.81 | O19: 148.11 | Q19: Current Assets | Y19: Total non-current assets | Z19: =SUM(Z6:Z18) -> 45921.48 | AA19: =SUM(AA6:AA18) -> 44320.77 | AB19: =SUM(AB6:AB18) -> 111864.16 | AC19: =SUM(AC6:AC18) -> 108147.99 | AD19: =SUM(AD6:AD18) -> 121547.37 | AE19: =SUM(AE6:AE18) -> 134182.39 | AG19: Current assets
A20: Deferred tax assets (net) | B20: 1209.62 | C20: 881.73 | D20: 1357.83 | E20: 2199.9 | F20: 1918.67 | G20: 1889.58 | I20: Total non-current assets | J20: =SUM(J6:J19) -> 3980.96 | K20: =SUM(K6:K19) -> 4032.91 | L20: =SUM(L6:L19) -> 4297.75 | M20: =SUM(M6:M19) -> 3829.6 | N20: =SUM(N6:N19) -> 3758.78 | O20: =SUM(O6:O19) -> 4073.71 | Q20: Inventories | R20: 775.82 | S20: 842.2 | T20: 1066.48 | U20: 1137.16 | V20: 1213.31 | W20: 1140.46 | Y20: Current Assets | AG20: Project work in progress | AH20: 9.1819 | AI20: 23.49 | AJ20: 49.91 | AK20: 58.93 | AL20: 64.72 | AM20: 0
A21: Other non-current assets | B21: 2753.66 | C21: 2593.44 | D21: 2299.36 | E21: 4338.04 | F21: 5065.37 | G21: 3583.21 | I21: Current Assets | Q21: Investments | R21: 22.5 | S21: 1.06 | T21: 12.64 | U21: 0 | V21: 0 | W21: 0 | Y21: Inventories | Z21: 2769.9 | AA21: 2858.56 | AB21: 5943.32 | AC21: 6828.78 | AD21: 6620.19 | AE21: 7670.55 | AG21: Investments | AH21: 0 | AI21: 0 | AJ21: 0 | AK21: 0 | AL21: 0 | AM21: 0
A22: Total non-current assets | B22: =SUM(B6:B21) -> 47383.76 | C22: =SUM(C6:C21) -> 62493.14 | D22: =SUM(D6:D21) -> 81597.4 | E22: =SUM(E6:E21) -> 97457.61 | F22: =SUM(F6:F21) -> 101445.51 | G22: =SUM(G6:G21) -> 116388.11 | I22: Inventories | J22: 1208.55 | K22: 1071.08 | L22: 1096.03 | M22: 1228.47 | N22: 1353.36 | O22: 1428.76 | Q22: Trade receivables | R22: 5425.88 | S22: 5384.69 | T22: 5106.1 | U22: 6896.06 | V22: 4136.62 | W22: 5051.1 | Y22: Investments | Z22: 6059.15 | AA22: 18454.4 | AB22: 29799.58 | AC22: 35573.42 | AD22: 34957.63 | AE22: 43360.62 | AG22: Trade receivables | AH22: 834.7555 | AI22: 979.83 | AJ22: 938.17 | AK22: 969.3 | AL22: 1077.38 | AM22: 1489.51
A23: Current Assets | I23: Investments | J23: 0 | K23: 0 | L23: 3.2 | M23: 3.08 | N23: 0 | O23: 150.11 | Q23: Cash and cash equivalents | R23: 152.68 | S23: 199.79 | T23: 207.63 | U23: 281.16 | V23: 205.1 | W23: 545.69 | Y23: Trade receivables | Z23: 27912.96 | AA23: 29948.24 | AB23: 46139.32 | AC23: 44731.53 | AD23: 48770.95 | AE23: 53713.68 | AG23: Lease receivables | AH23: 265.7442 | AI23: 230.29 | AJ23: 279.95 | AK23: 377.28 | AL23: 472 | AM23: 499.51
A24: Inventories | B24: 288.28 | C24: 991.85 | D24: 395.64 | E24: 451.97 | F24: 437.51 | G24: 521.8 | I24: Trade receivables | J24: 4616.01 | K24: 5016.82 | L24: 4578.77 | M24: 5251.25 | N24: 5805.29 | O24: 7816.87 | Q24: Bank balances | R24: 10.99 | S24: 49.38 | T24: 54.31 | U24: 63 | V24: 68.18 | W24: 110.24 | Y24: Cash and cash equivalents | Z24: 3262.83 | AA24: 3112.69 | AB24: 13770.24 | AC24: 16926.69 | AD24: 11958.5 | AE24: 12187 | AG24: Cash and cash equivalents | AH24: 273.8076 | AI24: 1421 | AJ24: 4607.98 | AK24: 836.67 | AL24: 1104.05 | AM24: 3044.8
A25: Investments | B25: 11.89 | C25: 1138.76 | D25: 47.79 | E25: 4028.69 | F25: 661.79 | G25: 751.88 | I25: Cash and cash equivalents | J25: 499.48 | K25: 537.53 | L25: 1061.76 | M25: 956.43 | N25: 1009.33 | O25: 1601.69 | Q25: Loans | R25: 102.01 | S25: 99.67 | T25: 0 | U25: 0 | V25: 0 | W25: 0 | Y25: Other bank balances | Z25: 675.56 | AA25: 650.59 | AB25: 5182.93 | AC25: 5592.91 | AD25: 3399.89 | AE25: 10778.34 | AG25: Bank Balances | AH25: 709.4773 | AI25: 625.97 | AJ25: 2215.52 | AK25: 1016.64 | AL25: 2008.59 | AM25: 718.44
A26: Trade receivables | B26: 2589.09 | C26: 2385.9 | D26: 2221.9 | E26: 3241.67 | F26: 3666.94 | G26: 4432.36 | I26: Bank balances | J26: 46.62 | K26: 54.33 | L26: 132.26 | M26: 103.44 | N26: 22.66 | O26: 157.58 | Q26: Other financial assets | R26: 6.07 | S26: 18.99 | T26: 113.74 | U26: 164.61 | V26: 148.51 | W26: 144.42 | Y26: Loans | Z26: 515.14 | AA26: 434.91 | AB26: =42269.2+280.34 -> 42549.54 | AC26: =40460.55+251.15 -> 40711.7 | AD26: =34814.59+106.54 -> 34921.13 | AE26: =36077.51+416.85 -> 36494.36 | AG26: Loans | AH26: 9.748 | AI26: 4.99 | AJ26: 4.51 | AK26: 4.13 | AL26: 4.15 | AM26: 2.28
A27: Customers bills discounted | B27: 613.05 | C27: 539.81 | D27: 299.24 | E27: 699.12 | F27: 0 | G27: 0 | I27: Loans | J27: 300.67 | K27: 460.26 | L27: 151.34 | M27: 57.52 | N27: 62.82 | O27: 68.68 | Q27: Contract assets | R27: 3664.77 | S27: 4582.93 | T27: 6092.09 | U27: 6241.18 | V27: 9088.37 | W27: 11043.51 | Y27: Other financial assets | Z27: 1997.59 | AA27: 1693.05 | AB27: 3655.82 | AC27: 4930.1 | AD27: 5563.92 | AE27: 5419.89 | AG27: Others | AH27: 2558.3492 | AI27: 655.89 | AJ27: 923.74 | AK27: 2597.07 | AL27: 1960.92 | AM27: 2584.18
A28: Cash and cash equivalents | B28: 7195.46 | C28: 4198.04 | D28: 8653.02 | E28: 931.99 | F28: 1575.73 | G28: 3406.32 | I28: Others | J28: 119.14 | K28: 122.68 | L28: 271.75 | M28: 422.87 | N28: 465.63 | O28: 403.02 | Q28: Current tax assets (net) | R28: 23.01 | S28: 14.21 | T28: 28.42 | U28: 53.16 | V28: 179.89 | W28: 16.7 | Y28: Other current assets | Z28: 49661.61 | AA28: 46479.35 | AB28: 60331.55 | AC28: 65920.39 | AD28: 71391.03 | AE28: 75559.83 | AG28: Current tax assets (net) | AH28: 24.6419 | AI28: 0 | AJ28: 2.22 | AK28: 12.03 | AL28: 0 | AM28: 58.65
A29: Bank balances other than above | B29: 118.4 | C29: 502.74 | D29: 2014.39 | E29: 3316.79 | F29: 6056.15 | G29: 3199.65 | I29: Current tax assets (net) | J29: 66.02 | K29: 67.06 | L29: 122.2 | M29: 185.78 | N29: 161.49 | O29: 191.85 | Q29: Other current assets | R29: 837.41 | S29: 690.57 | T29: 1008.37 | U29: 989.24 | V29: 1117.87 | W29: 1334.52 | Y29: Assets classified as held for sale | Z29: 2780.37 | AA29: 0 | AB29: 830.78 | AC29: 988.8 | AD29: 1005.36 | AE29: 157.44 | AG29: Other current assets | AH29: 3832.6669 | AI29: 6043.04 | AJ29: 5458.7 | AK29: 3173.27 | AL29: 3053.98 | AM29: 3075.13
A30: Loans | B30: 1784.88 | C30: 1014.81 | D30: 1240.65 | E30: 107.77 | F30: 64 | G30: 70.6 | I30: Other current assets | J30: 3636.18 | K30: 3615.53 | L30: 4979.58 | M30: 6519.77 | N30: 8379.78 | O30: 8667.99 | Q30: Total current assets | R30: =SUM(R20:R29) -> 11021.14 | S30: =SUM(S20:S29) -> 11883.49 | T30: =SUM(T20:T29) -> 13689.78 | U30: =SUM(U20:U29) -> 15825.57 | V30: =SUM(V20:V29) -> 16157.85 | W30: =SUM(W20:W29) -> 19386.64 | Y30: Total Current assets | Z30: =SUM(Z21:Z29) -> 95635.11 | AA30: =SUM(AA21:AA29) -> 103631.79 | AB30: =SUM(AB21:AB29) -> 208203.08 | AC30: =SUM(AC21:AC29) -> 222204.32 | AD30: =SUM(AD21:AD29) -> 218588.6 | AE30: =SUM(AE21:AE29) -> 245341.71 | AG30: Total current assets | AH30: =SUM(AH20:AH29) -> 8518.3725 | AI30: =SUM(AI20:AI29) -> 9984.5 | AJ30: =SUM(AJ20:AJ29) -> 14480.7 | AK30: =SUM(AK20:AK29) -> 9045.32 | AL30: =SUM(AL20:AL29) -> 9745.79 | AM30: =SUM(AM20:AM29) -> 11472.5
A31: Loans to Joint venture entities | B31: 68 | C31: 68 | D31: 61.77 | E31: 300.33 | F31: 205.01 | G31: 102.57 | I31: Total current assets | J31: =SUM(J22:J30) -> 10492.67 | K31: =SUM(K22:K30) -> 10945.29 | L31: =SUM(L22:L30) -> 12396.89 | M31: =SUM(M22:M30) -> 14728.61 | N31: =SUM(N22:N30) -> 17260.36 | O31: =SUM(O22:O30) -> 20486.55 | Q31: Total assets | R31: =R18+R30 -> 12876.95 | S31: =S18+S30 -> 14047.95 | T31: =T18+T30 -> 16341.77 | U31: =U18+U30 -> 18668.55 | V31: =V18+V30 -> 19031.47 | W31: =W18+W30 -> 22179.92 | Y31: Total Assets | Z31: =Z19+Z30 -> 141556.59 | AA31: =AA19+AA30 -> 147952.56 | AB31: =AB19+AB30 -> 320067.24 | AC31: =AC19+AC30 -> 330352.31 | AD31: =AD19+AD30 -> 340135.97 | AE31: =AE19+AE30 -> 379524.1 | AG31: Total assets | AH31: =AH18+AH30 -> 12391.248 | AI31: =AI18+AI30 -> 14221.13 | AJ31: =AJ18+AJ30 -> 19881.03 | AK31: =AK18+AK30 -> 18343.79 | AL31: =AL18+AL30 -> 19611.99 | AM31: =AM18+AM30 -> 19484.52
A32: Other financial assets | B32: 986.69 | C32: 622.67 | D32: 525.45 | E32: 1263.85 | F32: 3441.08 | G32: 4471.8 | I32: Assets classified as held for sale | J32: 1305.52 | K32: 375.33 | L32: 516.87 | M32: 1022.64 | N32: 1018.57 | O32: 1023.83 | Q32: EQUITY AND LIABILITIES | Y32: Equity and Liabilities | AG32: EQUITY AND LIABILITIES
A33: Other current assets | B33: 1164.17 | C33: 1013.2 | D33: 730.09 | E33: 1164.08 | F33: 1177.4 | G33: 1800.39 | I33: Total Assets | J33: =J31+J32+J20 -> 15779.15 | K33: =K31+K32+K20 -> 15353.53 | L33: =L31+L32+L20 -> 17211.51 | M33: =M31+M32+M20 -> 19580.85 | N33: =N31+N32+N20 -> 22037.71 | O33: =O31+O32+O20 -> 25584.09 | Q33: Equity | Y33: Equity | AG33: Equity
A34: Total current assets | B34: =SUM(B24:B33) -> 14819.91 | C34: =SUM(C24:C33) -> 12475.78 | D34: =SUM(D24:D33) -> 16189.94 | E34: =SUM(E24:E33) -> 15506.26 | F34: =SUM(F24:F33) -> 17285.61 | G34: =SUM(G24:G33) -> 18757.37 | I34: EQUITY AND LIABILITIES | Q34: Equity share capital | R34: 51.42 | S34: 51.42 | T34: 51.42 | U34: 51.42 | V34: 51.42 | W34: 53.24 | Y34: Equity share capital | Z34: 280.78 | AA34: 280.91 | AB34: 281.01 | AC34: 281.1 | AD34: 274.93 | AE34: 275.04 | AG34: Equity share capital | AH34: 2085.0201 | AI34: 2085.02 | AJ34: 2085.02 | AK34: 2085.02 | AL34: 2085.02 | AM34: 2085.02
A35: Assets held for sale | B35: 0 | C35: 354.86 | D35: 1898.48 | E35: 1941.26 | F35: 186.75 | G35: 186.75 | I35: Equity | Q35: Other equity | R35: 2746.16 | S35: 3308.27 | T35: 3568.51 | U35: 3720 | V35: 4044.28 | W35: 5294.21 | Y35: Other equity | Z35: 51894.57 | AA35: 60132.63 | AB35: 82126.65 | AC35: 89044.85 | AD35: 86084.31 | AE35: 97380.56 | AG35: Other equity | AH35: 3030.8791 | AI35: 3551.06 | AJ35: 4312.38 | AK35: 5161.18 | AL35: =6660.66+0.17 -> 6660.83 | AM35: 6538.7
A36: Total Assets | B36: =B22+B34+B35 -> 62203.67 | C36: =C22+C34+C35 -> 75323.78 | D36: =D22+D34+D35 -> 99685.82 | E36: =E22+E34+E35 -> 114905.13 | F36: =F22+F34+F35 -> 118917.87 | G36: =G22+G34+G35 -> 135332.23 | I36: Equity share capital | J36: 30.94 | K36: 29.78 | L36: 29.78 | M36: 32.49 | N36: 32.49 | O36: 34.16 | Q36: Total equity | R36: =R34+R35 -> 2797.58 | S36: =S34+S35 -> 3359.69 | T36: =T34+T35 -> 3619.93 | U36: =U34+U35 -> 3771.42 | V36: =V34+V35 -> 4095.7 | W36: =W34+W35 -> 5347.45 | Y36: Non-controlling interests | Z36: 0 | AA36: 0 | AB36: 12966.07 | AC36: 14241.27 | AD36: 16190.42 | AE36: 17748.08 | AG36: Total equity | AH36: =AH34+AH35 -> 5115.8992 | AI36: =AI34+AI35 -> 5636.08 | AJ36: =AJ34+AJ35 -> 6397.4 | AK36: =AK34+AK35 -> 7246.2 | AL36: =AL34+AL35 -> 8745.85 | AM36: =AM34+AM35 -> 8623.72
A37: EQUITY AND LIABILITIES | I37: Other equity | J37: 3327.48 | K37: 3708.72 | L37: 4248.79 | M37: 4688.13 | N37: 5105.5 | O37: 6479.17 | Q37: Liabilities | Y37: Total equity | Z37: =Z34+Z35+Z36 -> 52175.35 | AA37: =AA34+AA35+AA36 -> 60413.54 | AB37: =AB34+AB35+AB36 -> 95373.73 | AC37: =AC34+AC35+AC36 -> 103567.22 | AD37: =AD34+AD35+AD36 -> 102549.66 | AE37: =AE34+AE35+AE36 -> 115403.68 | AG37: Liabilities
A38: Equity | I38: Equity attributable to owners of the company | J38: =J36+J37 -> 3358.42 | K38: =K36+K37 -> 3738.5 | L38: =L36+L37 -> 4278.57 | M38: =M36+M37 -> 4720.62 | N38: =N36+N37 -> 5137.99 | O38: =O36+O37 -> 6513.33 | Q38: Non-current liabilities | Y38: Liabilities | AG38: Non-current liabilities
A39: Equity share capital | B39: 406.35 | C39: 406.35 | D39: 422.47 | E39: 432.03 | F39: 432.03 | G39: 432.03 | I39: Non-controlling interests | J39: 136.75 | K39: 120.44 | L39: 138.9 | M39: -26.76 | N39: -25.18 | O39: -44.47 | Q39: Borrowings | R39: 152.66 | S39: 218.71 | T39: 393.26 | U39: 493.16 | V39: 236.01 | W39: 358.46 | Y39: Non-current liabilities | AG39: Borrowings | AH39: 4256.654 | AI39: 5671.51 | AJ39: 6315.43 | AK39: 6030.59 | AL39: 5515.77 | AM39: 4889.51
A40: Other Equity | B40: 25217.14 | C40: 30221.91 | D40: 41565.75 | E40: 45151.55 | F40: 52512.74 | G40: 62003.36 | I40: Total equity | J40: =J38+J39 -> 3495.17 | K40: =K38+K39 -> 3858.94 | L40: =L38+L39 -> 4417.47 | M40: =M38+M39 -> 4693.86 | N40: =N38+N39 -> 5112.81 | O40: =O38+O39 -> 6468.86 | Q40: Lease Liabilities | R40: 111.08 | S40: 113.06 | T40: 167.44 | U40: 163.17 | V40: 148.14 | W40: 211.48 | Y40: Borrowings | Z40: 7185.71 | AA40: 15868.21 | AB40: 61618.31 | AC40: 61217.68 | AD40: 56506.97 | AE40: 57503.34 | AG40: Lease liabilities | AH40: 0 | AI40: 11.2 | AJ40: 27.91 | AK40: 11.15 | AL40: 27.85 | AM40: 12.03
A41: Total equity attributable to the owners | B41: =B39+B40 -> 25623.49 | C41: =C39+C40 -> 30628.26 | D41: =D39+D40 -> 41988.22 | E41: =E39+E40 -> 45583.58 | F41: =F39+F40 -> 52944.77 | G41: =G39+G40 -> 62435.39 | I41: Liabilities | Q41: Provisions | R41: 16.87 | S41: 13.93 | T41: 13.74 | U41: 24.12 | V41: 17.49 | W41: 19.69 | Y41: Lease liability | Z41: 24.18 | AA41: 59.99 | AB41: 1633.31 | AC41: 1646.31 | AD41: 1734.78 | AE41: 2265.24 | AG41: Other financial liabilities | AH41: 256.7812 | AI41: 334.57 | AJ41: 246.49 | AK41: 521.91 | AL41: 710.5 | AM41: 322.04
A42: Non-controlling interests | B42: 219.59 | C42: 1468.47 | D42: 392.77 | E42: 1338.51 | F42: 1598.23 | G42: 2537.95 | I42: Non-current liabilities | Q42: Deferred tax liabilities (net) | R42: 75.08 | S42: 55.15 | T42: 43.8 | U42: 7.21 | V42: 0 | W42: 15.55 | Y42: Other financial liabilities | Z42: 179.62 | AA42: 82.63 | AB42: 122.94 | AC42: 272.96 | AD42: 96.07 | AE42: 252.18 | AG42: Provisions | AH42: 21.6755 | AI42: 27.09 | AJ42: 30.27 | AK42: 31.84 | AL42: 15.49 | AM42: 28.92
A43: Total Equity | B43: =B41+B42 -> 25843.08 | C43: =C41+C42 -> 32096.73 | D43: =D41+D42 -> 42380.99 | E43: =E41+E42 -> 46922.09 | F43: =F41+F42 -> 54543 | G43: =G41+G42 -> 64973.34 | I43: Borrowings | J43: 1797.07 | K43: 1607.12 | L43: 1553.45 | M43: 1214.83 | N43: 1447.54 | O43: 1467.38 | Q43: Other non-current liabilities | R43: 0 | S43: 0 | T43: 0.47 | U43: 0.45 | V43: 0.43 | W43: 0.41 | Y43: Provisions | Z43: 611.23 | AA43: 639.02 | AB43: 817.77 | AC43: 869.99 | AD43: 987.38 | AE43: 1124.01 | AG43: Other non-current liabilities | AH43: 43.0882 | AI43: 32.01 | AJ43: 17.78 | AK43: 59.6 | AL43: 17.21 | AM43: 0
A44: Liabilities | I44: Lease Liabilities | J44: 0 | K44: 0 | L44: 74.31 | M44: 54.8 | N44: 45.76 | O44: 68.14 | Q44: Total non-current liabilities | R44: =SUM(R39:R42) -> 355.69 | S44: =SUM(S39:S42) -> 400.85 | T44: =SUM(T39:T42) -> 618.24 | U44: =SUM(U39:U42) -> 687.66 | V44: =SUM(V39:V42) -> 401.64 | W44: =SUM(W39:W42) -> 605.18 | Y44: Deferred tax liabilities (net) | Z44: 0 | AA44: 0 | AB44: 1039.33 | AC44: 630.43 | AD44: 533.63 | AE44: 410.01 | AG44: Total non-current liabilities | AH44: =SUM(AH39:AH43) -> 4578.1989 | AI44: =SUM(AI39:AI43) -> 6076.38 | AJ44: =SUM(AJ39:AJ43) -> 6637.88 | AK44: =SUM(AK39:AK43) -> 6655.09 | AL44: =SUM(AL39:AL43) -> 6286.82 | AM44: =SUM(AM39:AM43) -> 5252.5
A45: Non-current liabilities | I45: Total outstanding dues of micro and small enterprises | J45: 0 | K45: 0 | L45: 0 | M45: 0 | N45: 0 | O45: 0 | Q45: Current Liabilities | Y45: Other non-current liabilities | Z45: 0.22 | AA45: 0 | AB45: 21.27 | AC45: 81.73 | AD45: 618.02 | AE45: 594.74 | AG45: Current Liabilities
A46: Borrowings | B46: 26181.33 | C46: 32935.53 | D46: 39691.48 | E46: 46516.94 | F46: 37662.93 | G46: 35830.68 | I46: Total outstanding dues of creditors other than above | J46: 349.8 | K46: 338.2 | L46: 325.72 | M46: 161.4 | N46: 115.6 | O46: 79.43 | Q46: Borrowings | R46: 1909.14 | S46: 1624.71 | T46: 2469.45 | U46: 2701.29 | V46: 3552.27 | W46: 3342.64 | Y46: Total non-current liabilities | Z46: =SUM(Z40:Z45) -> 8000.96 | AA46: =SUM(AA40:AA45) -> 16649.85 | AB46: =SUM(AB40:AB45) -> 65252.93 | AC46: =SUM(AC40:AC45) -> 64719.1 | AD46: =SUM(AD40:AD45) -> 60476.85 | AE46: =SUM(AE40:AE45) -> 62149.52 | AG46: Borrowings | AH46: 0 | AI46: 230.29 | AJ46: 279.95 | AK46: 377.28 | AL46: 471.99 | AM46: 499.51
A47: Lease Liabilities | B47: 0 | C47: 0 | D47: 1983.78 | E47: 2681.74 | F47: 2953.28 | G47: 5389.61 | I47: Total Trade Payables | J47: =J45+J46 -> 349.8 | K47: =K45+K46 -> 338.2 | L47: =L45+L46 -> 325.72 | M47: =M45+M46 -> 161.4 | N47: =N45+N46 -> 115.6 | O47: =O45+O46 -> 79.43 | Q47: Lease Liabilities | R47: 34.55 | S47: 27.35 | T47: 34.46 | U47: 25.75 | V47: 24.57 | W47: 44.9 | Y47: Current Liabilities | AG47: Lease liabilities | AH47: 0 | AI47: 17.69 | AJ47: 20.18 | AK47: 22.32 | AL47: 16.91 | AM47: 18.31
A48: Other Financial Liabilities | B48: 734.33 | C48: 779.94 | D48: 227.56 | E48: 322.84 | F48: 360.11 | G48: 207.45 | I48: Other financial liabilities | J48: 486.36 | K48: 516.42 | L48: 444.6 | M48: 393.17 | N48: 428.87 | O48: 466.21 | Q48: Total outstanding dues of micro and small enterprises | R48: 137.2 | S48: 129.29 | T48: 154.83 | U48: 171.98 | V48: 167.62 | W48: 164.64 | Y48: Borrowings | Z48: 15044.11 | AA48: 6940.94 | AB48: 30476.96 | AC48: 30896.32 | AD48: 27834.27 | AE48: 35861.3 | AG48: Total outstanding dues of micro and small enterprises | AH48: 0 | AI48: 0.45 | AJ48: 1.12 | AK48: 35.53 | AL48: 9.32 | AM48: 2.52
A49: Provisions | B49: 8.23 | C49: 26.68 | D49: 34.23 | E49: 1201.75 | F49: 1100.75 | G49: 1149.36 | I49: Provisions | J49: 128.37 | K49: 127.82 | L49: 92.65 | M49: 76.05 | N49: 52.12 | O49: 60.1 | Q49: Total outstanding of creditors other than above | R49: 4870.05 | S49: 6045.63 | T49: 6692.5 | U49: 8216.35 | V49: 7502.6 | W49: 8831.57 | Y49: Current maturities of long term borrowings | Z49: 3555.48 | AA49: 999.56 | AB49: 31372.96 | AC49: 26399.38 | AD49: 29698.53 | AE49: 36194.7 | AG49: Total outstanding dues of creditors other than above | AH49: 690.0161 | AI49: 271.28 | AJ49: 222.84 | AK49: 585.03 | AL49: 240.68 | AM49: 342.35
A50: Deferred tax liabilities (net) | B50: 286.97 | C50: 1203.16 | D50: 3010.86 | E50: 3186.37 | F50: 4169.87 | G50: 4653.26 | I50: Deferred tax liabilities (net) | J50: 38.21 | K50: 32.51 | L50: 95.71 | M50: 60.21 | N50: 23.3 | O50: 11.27 | Q50: Total trade payables | R50: =R48+R49 -> 5007.25 | S50: =S48+S49 -> 6174.92 | T50: =T48+T49 -> 6847.33 | U50: =U48+U49 -> 8388.33 | V50: =V48+V49 -> 7670.22 | W50: =W48+W49 -> 8996.21 | Y50: Lease liability | Z50: 132.27 | AA50: 104.18 | AB50: 406.54 | AC50: 490.75 | AD50: 547.67 | AE50: 584.34 | AG50: Total trade payables | AH50: =AH48+AH49 -> 690.0161 | AI50: =AI48+AI49 -> 271.73 | AJ50: =AJ48+AJ49 -> 223.96 | AK50: =AK48+AK49 -> 620.56 | AL50: =AL48+AL49 -> 250 | AM50: =AM48+AM49 -> 344.87
A51: Other non-current liabilities | B51: 1453.26 | C51: 1065.79 | D51: 988.21 | E51: 1148.84 | F51: 1664.99 | G51: 2142.54 | I51: Other non-current liabilities | J51: 345.41 | K51: 529.79 | L51: 673.77 | M51: 326.51 | N51: 24.08 | O51: 19.3 | Q51: Trade acceptances | R51: 0 | S51: 0 | T51: 0 | U51: 0 | V51: 1560.79 | W51: 1507.27 | Y51: Due to micro and small enterprises | Z51: 379.88 | AA51: 351.47 | AB51: 575.91 | AC51: 851.7 | AD51: 1018.71 | AE51: 1417.65 | AG51: Other financial liabilities | AH51: 1464.1432 | AI51: 1257.82 | AJ51: 1752.59 | AK51: 1929.84 | AL51: 1472.45 | AM51: 2228.35
A52: Total non-current liabilities | B52: =SUM(B46:B51) -> 28664.12 | C52: =SUM(C46:C51) -> 36011.1 | D52: =SUM(D46:D51) -> 45936.12 | E52: =SUM(E46:E51) -> 55058.48 | F52: =SUM(F46:F51) -> 47911.93 | G52: =SUM(G46:G51) -> 49372.9 | I52: Total non-current liabilities | J52: =SUM(J43,J47,J48:J51,J44) -> 3145.22 | K52: =SUM(K43,K47,K48:K51,K44) -> 3151.86 | L52: =SUM(L43,L47,L48:L51,L44) -> 3260.21 | M52: =SUM(M43,M47,M48:M51,M44) -> 2286.97 | N52: =SUM(N43,N47,N48:N51,N44) -> 2137.27 | O52: =SUM(O43,O47,O48:O51,O44) -> 2171.83 | Q52: Other financial liabilities | R52: 368.21 | S52: 102.81 | T52: 41.6 | U52: 54.17 | V52: 29.69 | W52: 97.28 | Y52: Due to others | Z52: 36249.51 | AA52: 37118.33 | AB52: 50789.71 | AC52: 48932.42 | AD52: 52274.17 | AE52: 51041.69 | AG52: Other current liabilities | AH52: 472.6178 | AI52: 702.04 | AJ52: 4543.72 | AK52: 1464.25 | AL52: 2321.66 | AM52: 2416.93
A53: Current Liabilities | I53: Current Liabilities | Q53: Contract liabilities | R53: 2210.27 | S53: 2078.63 | T53: 2410.87 | U53: 2620.3 | V53: 1211.49 | W53: 1659.36 | Y53: Total trade payables | Z53: =Z51+Z52 -> 36629.39 | AA53: =AA51+AA52 -> 37469.8 | AB53: =AB51+AB52 -> 51365.62 | AC53: =AC51+AC52 -> 49784.12 | AD53: =AD51+AD52 -> 53292.88 | AE53: =AE51+AE52 -> 52459.34 | AG53: Provisions | AH53: 70.3732 | AI53: 21.46 | AJ53: 25.35 | AK53: 28.25 | AL53: 38.92 | AM53: 100.33
A54: Borrowings | B54: 1544.12 | C54: 400 | D54: 5761.56 | E54: 3302.37 | F54: 8616.3 | G54: 9979.35 | I54: Borrowings | J54: 1131.71 | K54: 894.91 | L54: 2155.49 | M54: 2467.63 | N54: 2461.66 | O54: 2721.24 | Q54: Other current liabilities | R54: 86.74 | S54: 94.89 | T54: 121.96 | U54: 216.76 | V54: 281.36 | W54: 305.45 | Y54: Other financial liabilities | Z54: 1709.09 | AA54: 2159.41 | AB54: 6664.35 | AC54: 7441.94 | AD54: 7575.67 | AE54: 6273.37 | AG54: Current tax liability (net) | AH54: 0 | AI54: 7.64 | AJ54: 0 | AK54: 0 | AL54: 7.39 | AM54: 0
A55: Customers bills discounted | B55: 613.05 | C55: 539.81 | D55: 299.24 | E55: 699.12 | F55: 0 | G55: 0 | I55: Lease Liabilities | J55: 0 | K55: 0 | L55: 54.53 | M55: 48.87 | N55: 53.24 | O55: 56.75 | Q55: Provisions | R55: 59.25 | S55: 65.05 | T55: 87.8 | U55: 94.44 | V55: 102.23 | W55: 100.87 | Y55: Other current liabilities | Z55: 20758.05 | AA55: 21499.49 | AB55: 34408.74 | AC55: 42166.55 | AD55: 52184.08 | AE55: 63326.97 | AG55: Total current liabilities | AH55: =SUM(AH46:AH47,AH50,AH51:AH54) -> 2697.1503 | AI55: =SUM(AI46:AI47,AI50,AI51:AI54) -> 2508.67 | AJ55: =SUM(AJ46:AJ47,AJ50,AJ51:AJ54) -> 6845.75 | AK55: =SUM(AK46:AK47,AK50,AK51:AK54) -> 4442.5 | AL55: =SUM(AL46:AL47,AL50,AL51:AL54) -> 4579.32 | AM55: =SUM(AM46:AM47,AM50,AM51:AM54) -> 5608.3
A56: Total outstanding dues of micro and small enterprises | B56: 1.96 | C56: 11.5 | D56: 41.86 | E56: 98.88 | F56: 152.5 | G56: 166.73 | I56: Total outstanding dues of micro and small enterprises | J56: 102 | K56: 175.24 | L56: 159.09 | M56: 153.4 | N56: 224.89 | O56: 273.46 | Q56: Current tax liabilities (net) | R56: 48.27 | S56: 119.05 | T56: 89.66 | U56: 107.98 | V56: 101.08 | W56: 172.9 | Y56: Provisions | Z56: 1555.39 | AA56: 1320.01 | AB56: 3355.86 | AC56: 3493.47 | AD56: 4115.89 | AE56: 4691.67 | AG56: Total Equity and Liabilities | AH56: =AH36+AH44+AH55 -> 12391.248 | AI56: =AI36+AI44+AI55 -> 14221.13 | AJ56: =AJ36+AJ44+AJ55 -> 19881.03 | AK56: =AK36+AK44+AK55 -> 18343.79 | AL56: =AL36+AL44+AL55 -> 19611.99 | AM56: =AM36+AM44+AM55 -> 19484.52
A57: Total outstanding dues of creditors other than above | B57: 726.78 | C57: 1002.35 | D57: 1117.71 | E57: 1729.35 | F57: 1759.6 | G57: 2553.77 | I57: Total outstanding dues of creditors other than above | J57: 3343.17 | K57: 3563.9 | L57: 4094.24 | M57: 4750.44 | N57: 5630.58 | O57: 6314.47 | Q57: Total Current liabilities | R57: =SUM(R46:R47,R50,R52:R56) -> 9723.68 | S57: =SUM(S46:S47,S50,S52:S56) -> 10287.41 | T57: =SUM(T46:T47,T50,T52:T56) -> 12103.13 | U57: =SUM(U46:U47,U50,U52:U56) -> 14209.02 | V57: =SUM(V46:V47,V50,V51:V56) -> 14533.7 | W57: =SUM(W46:W47,W50,W51:W56) -> 16226.88 | Y57: Current tax liabilities (net) | Z57: 628.92 | AA57: 395.78 | AB57: 1309.82 | AC57: 1393.46 | AD57: 1860.47 | AE57: 2579.21
A58: Total Trade payables | B58: =B56+B57 -> 728.74 | C58: =C56+C57 -> 1013.85 | D58: =D56+D57 -> 1159.57 | E58: =E56+E57 -> 1828.23 | F58: =F56+F57 -> 1912.1 | G58: =G56+G57 -> 2720.5 | I58: Total Trade Payables | J58: =J56+J57 -> 3445.17 | K58: =K56+K57 -> 3739.14 | L58: =L56+L57 -> 4253.33 | M58: =M56+M57 -> 4903.84 | N58: =N56+N57 -> 5855.47 | O58: =O56+O57 -> 6587.93 | Q58: Total Equity and Liabilities | R58: =R36+R44+R57 -> 12876.95 | S58: =S36+S44+S57 -> 14047.95 | T58: =T36+T44+T57 -> 16341.3 | U58: =U36+U44+U57 -> 18668.1 | V58: =V36+V44+V57 -> 19031.04 | W58: =W36+W44+W57 -> 22179.51 | Y58: Liabilities associated with assets classified as held for sale | Z58: 1367.58 | AA58: 0 | AB58: 79.73 | AC58: 0 | AD58: 0 | AE58: 0
A59: Lease Liabilities | B59: 0 | C59: 0 | D59: 32.16 | E59: 61.97 | F59: 71.2 | G59: 254.56 | I59: Other financial liabilities | J59: 923.3 | K59: 1284.49 | L59: 699.44 | M59: 563.21 | N59: 856.55 | O59: 1048.46 | Y59: Total Current Liabilities | Z59: =SUM(Z48:Z50,Z53,Z54:Z58) -> 81380.28 | AA59: =SUM(AA48:AA50,AA53,AA54:AA58) -> 70889.17 | AB59: =SUM(AB48:AB50,AB53,AB54:AB58) -> 159440.58 | AC59: =SUM(AC48:AC50,AC53,AC54:AC58) -> 162065.99 | AD59: =SUM(AD48:AD50,AD53,AD54:AD58) -> 177109.46 | AE59: =SUM(AE48:AE50,AE53,AE54:AE58) -> 201970.9
A60: Other Financial Liabilities | B60: 3336.14 | C60: 3292.34 | D60: 1954.51 | E60: 2620.76 | F60: 3756.8 | G60: 5359.74 | I60: Other current liabilities | J60: 2378.98 | K60: 1769.95 | L60: 1908.85 | M60: 3613.3 | N60: 4636.91 | O60: 5469.42 | Y60: Total Equity and Liabilities | Z60: =Z37+Z46+Z59 -> 141556.59 | AA60: =AA37+AA46+AA59 -> 147952.56 | AB60: =AB37+AB46+AB59 -> 320067.24 | AC60: =AC37+AC46+AC59 -> 330352.31 | AD60: =AD37+AD46+AD59 -> 340135.97 | AE60: =AE37+AE46+AE59 -> 379524.1
A61: Other Current liabilities | B61: 1346.66 | C61: 1721.19 | D61: 1654.87 | E61: 1814.19 | F61: 1832.45 | G61: 2242.68 | I61: Provisions | J61: 450.88 | K61: 620.6 | L61: 433.78 | M61: 416.6 | N61: 470.53 | O61: 616.58
A62: Provisions | B62: 106.3 | C62: 95.73 | D62: 107.52 | E62: 548.03 | F62: 193.44 | G62: 236.77 | I62: Current tax liabilities (net) | J62: 2.96 | K62: 33.64 | L62: 28.41 | M62: 121.9 | N62: 43.83 | O62: 112.68
A63: Current tax liabilities (net) | B63: 21.46 | C63: 38.49 | D63: 93.92 | E63: 528.43 | F63: 33.1 | G63: 144.84 | I63: Total current liabilities | J63: =SUM(J54,J58,J59:J62,J55) -> 8333 | K63: =SUM(K54,K58,K59:K62,K55) -> 8342.73 | L63: =SUM(L54,L58,L59:L62,L55) -> 9533.83 | M63: =SUM(M54,M58,M59:M62,M55) -> 12135.35 | N63: =SUM(N54,N58,N59:N62,N55) -> 14378.19 | O63: =SUM(O54,O58,O59:O62,O55) -> 16613.06
A64: Total Current liabilities | B64: =SUM(B54:B55,B58,B60:B63,B59) -> 7696.47 | C64: =SUM(C54:C55,C58,C60:C63,C59) -> 7101.41 | D64: =SUM(D54:D55,D58,D60:D63,D59) -> 11063.35 | E64: =SUM(E54:E55,E58,E60:E63,E59) -> 11403.1 | F64: =SUM(F54:F55,F58,F60:F63,F59) -> 16415.39 | G64: =SUM(G54:G55,G58,G60:G63,G59) -> 20938.44 | I64: Liabilities directly associated with assets held for sale | J64: 805.76 | K64: 0 | L64: 0 | M64: 464.67 | N64: 409.44 | O64: 330.34
A65: Liabilities associated with assets held for sale | B65: 0 | C65: 114.54 | D65: 305.36 | E65: 1521.46 | F65: 47.55 | G65: 47.55 | I65: Total equity and liabilities | J65: =J40+J52+J63+J64 -> 15779.15 | K65: =K40+K52+K63+K64 -> 15353.53 | L65: =L40+L52+L63+L64 -> 17211.51 | M65: =M40+M52+M63+M64 -> 19580.85 | N65: =N40+N52+N63+N64 -> 22037.71 | O65: =O40+O52+O63+O64 -> 25584.09
A66: Total Liabilities | B66: =B52+B64+B65 -> 36360.59 | C66: =C52+C64+C65 -> 43227.05 | D66: =D52+D64+D65 -> 57304.83 | E66: =E52+E64+E65 -> 67983.04 | F66: =F52+F64+F65 -> 64374.87 | G66: =G52+G64+G65 -> 70358.89
A67: Total Equity and Liabilities | B67: =B43+B66 -> 62203.67 | C67: =C43+C66 -> 75323.78 | D67: =D43+D66 -> 99685.82 | E67: =E43+E66 -> 114905.13 | F67: =F43+F66 -> 118917.87 | G67: =G43+G66 -> 135332.23
A69: Working Notes | B69: 2020 | C69: 2021 | D69: 2022 | E69: 2023 | F69: 2024 | G69: 2025 | I69: Working Notes | J69: 2020 | K69: 2021 | L69: 2022 | M69: 2023 | N69: 2024 | O69: 2025 | Q69: Working Notes | R69: 2020 | S69: 2021 | T69: 2022 | U69: 2023 | V69: 2024 | W69: 2025 | Y69: Working Notes | Z69: 2020 | AA69: 2021 | AB69: 2022 | AC69: 2023 | AD69: 2024 | AE69: 2025 | AG69: Working Notes | AH69: 2020 | AI69: 2021 | AJ69: 2022 | AK69: 2023 | AL69: 2024 | AM69: 2025
A70: Working Capital | B70: =B34-B64 -> 7123.44 | C70: =C34-C64 -> 5374.37 | D70: =D34-D64 -> 5126.59 | E70: =E34-E64 -> 4103.16 | F70: =F34-F64 -> 870.22 | G70: =G34-G64 -> -2181.07 | I70: Working Capital | J70: =J31-J63 -> 2159.67 | K70: =K31-K63 -> 2602.56 | L70: =L31-L63 -> 2863.06 | M70: =M31-M63 -> 2593.26 | N70: =N31-N63 -> 2882.17 | O70: =O31-O63 -> 3873.49 | Q70: Working Capital | R70: =R30-R57 -> 1297.46 | S70: =S30-S57 -> 1596.08 | T70: =T30-T57 -> 1586.65 | U70: =U30-U57 -> 1616.55 | V70: =V30-V57 -> 1624.15 | W70: =W30-W57 -> 3159.76 | Y70: Working Capital | Z70: =Z30-Z59 -> 14254.83 | AA70: =AA30-AA59 -> 32742.62 | AB70: =AB30-AB59 -> 48762.5 | AC70: =AC30-AC59 -> 60138.33 | AD70: =AD30-AD59 -> 41479.14 | AE70: =AE30-AE59 -> 43370.81 | AG70: Working Capital | AH70: =AH30-AH55 -> 5821.2222 | AI70: =AI30-AI55 -> 7475.83 | AJ70: =AJ30-AJ55 -> 7634.95 | AK70: =AK30-AK55 -> 4602.82 | AL70: =AL30-AL55 -> 5166.47 | AM70: =AM30-AM55 -> 5864.2

Sheet Income Statement
A1: Consolidated Income Statements
E2: #VALUE! | M2: #VALUE! | U2: #VALUE! | AC2: #VALUE! | AK2: #VALUE!
A3: Particulars | B3: 2020 | C3: 2021 | D3: 2022 | E3: 2023 | F3: 2024 | G3: 2025 | I3: Particulars | J3: 2020 | K3: 2021 | L3: 2022 | M3: 2023 | N3: 2024 | O3: 2025 | Q3: Particulars | R3: 2020 | S3: 2021 | T3: 2022 | U3: 2023 | V3: 2024 | W3: 2025 | Y3: Particulars | Z3: 2020 | AA3: 2021 | AB3: 2022 | AC3: 2023 | AD3: 2024 | AE3: 2025 | AG3: Particulars | AH3: 2020 | AI3: 2021 | AJ3: 2022 | AK3: 2023 | AL3: 2024 | AM3: 2025
A4: Income | I4: INCOME | Q4: INCOME | Y4: Continuing operations | AG4: Revenue
A5: Revenue from Operations | B5: 11438.77 | C5: 12549.6 | D5: 17118.79 | E5: 20851.91 | F5: 26710.56 | G5: 30475.33 | I5: Revenue from operations | J5: 12675.84 | K5: 12949.44 | L5: 14777.38 | M5: 16361.44 | N5: 19626.43 | O5: 22315.78 | Q5: Revenue from Operations | R5: 11965.37 | S5: 13114.2 | T5: 13742.26 | U5: 17281.71 | V5: 19914.17 | W5: 21846.7 | Y5: Income | AG5: Revenue from operations | AH5: 10068.681 | AI5: 14530.58 | AJ5: 15403.76 | AK5: 19381.71 | AL5: 20281.57 | AM5: 21889.23
A6: Gain arising from Infrastructure development | B6: 434.3 | C6: 0 | D6: 0 | E6: 0 | F6: 0 | G6: 603.27 | I6: Other income | J6: 44.04 | K6: 67.02 | L6: 88.92 | M6: 39.7 | N6: 63.99 | O6: 62.48 | Q6: Other income | R6: 11.1 | S6: 29.92 | T6: 13.43 | U6: 31.32 | V6: 52.41 | W6: 70.86 | Y6: Revenue from operations | Z6: 145452.36 | AA6: 135979.03 | AB6: 156521.23 | AC6: 183340.7 | AD6: 221112.91 | AE6: 255734.45 | AG6: Other income | AH6: 255.2419 | AI6: 245.6845 | AJ6: 739.19 | AK6: 800.23 | AL6: 996.44 | AM6: 1185.57
A7: Other income | B7: 1861.35 | C7: 1970.23 | D7: 2223.72 | E7: 1553.48 | F7: 1499.42 | G7: 1304.48 | I7: Total Income | J7: =J5+J6 -> 12719.88 | K7: =K5+K6 -> 13016.46 | L7: =L5+L6 -> 14866.3 | M7: =M5+M6 -> 16401.14 | N7: =N5+N6 -> 19690.42 | O7: =O5+O6 -> 22378.26 | Q7: Total income | R7: =R5+R6 -> 11976.47 | S7: =S5+S6 -> 13144.12 | T7: =T5+T6 -> 13755.69 | U7: =U5+U6 -> 17313.03 | V7: =V5+V6 -> 19966.58 | W7: =W5+W6 -> 21917.56 | Y7: Other income | Z7: 2360.9 | AA7: 3429.35 | AB7: 2267.08 | AC7: 2929.17 | AD7: 4158.03 | AE7: 4124.82 | AG7: Total income | AH7: =AH5+AH6 -> 10323.923 | AI7: =AI5+AI6 -> 14776.264 | AJ7: =AJ5+AJ6 -> 16142.95 | AK7: =AK5+AK6 -> 20181.94 | AL7: =AL5+AL6 -> 21278.01 | AM7: =AM5+AM6 -> 23074.8
A8: Total income | B8: =SUM(B5:B7) -> 13734.42 | C8: =SUM(C5:C7) -> 14519.83 | D8: =SUM(D5:D7) -> 19342.51 | E8: =SUM(E5:E7) -> 22405.39 | F8: =SUM(F5:F7) -> 28209.98 | G8: =SUM(G5:G7) -> 32383.08 | I8: EXPENSES | Q8: Expenses | Y8: Total income | Z8: =SUM(Z6:Z7) -> 147813.26 | AA8: =SUM(AA6:AA7) -> 139408.38 | AB8: =SUM(AB6:AB7) -> 158788.31 | AC8: =SUM(AC6:AC7) -> 186269.87 | AD8: =SUM(AD6:AD7) -> 225270.94 | AE8: =SUM(AE6:AE7) -> 259859.27 | AG8: Expenses
A9: Expenses | I9: Cost of materials consumed | J9: 5329.84 | K9: 4745.01 | L9: 6421.34 | M9: 6983.77 | N9: 8187.39 | O9: 8584.51 | Q9: Cost of materials consumed | R9: 5669.62 | S9: 5696.99 | T9: 6090.81 | U9: 6969.83 | V9: 8413.69 | W9: 9912.15 | Y9: Expenses | AG9: Expenses on operations | AH9: 9307.6557 | AI9: 13415.819 | AJ9: 14229.41 | AK9: 17903.33 | AL9: 18720.07 | AM9: 20181.86
A10: Operating expenses | B10: 3097.26 | C10: 3259.49 | D10: 4865.11 | E10: 5654.56 | F10: 7116.34 | G10: 8069.75 | I10: Changes in Inventories of finished goods and WIP | J10: -62.15 | K10: 13.9 | L10: 24.66 | M10: -13.46 | N10: 17.71 | O10: -3.72 | Q10: Changes in inventories of finished goods and WIP | R10: -78.03 | S10: 3.61 | T10: -141.79 | U10: 98.77 | V10: -5.7 | W10: 166.52 | Y10: Manufacturing, construction and operating expenses: | AG10: Employee benefit expenses | AH10: 161.1064 | AI10: 189.9382 | AJ10: 207.78 | AK10: 204.36 | AL10: 190.98 | AM10: 188.91
A11: Employee benefit expenses | B11: 546.52 | C11: 615.05 | D11: 779.43 | E11: 1178.17 | F11: 1896.4 | G11: 2008.66 | I11: Erection, sub-contracting and other project expenses | J11: 3978.06 | K11: 4553.35 | L11: 4693.16 | M11: 5413.5 | N11: 6595.43 | O11: 8357.68 | Q11: Erection and sub-contracting expenses | R11: 2826.65 | S11: 3907.01 | T11: 4509.15 | U11: 6552.24 | V11: 7176.82 | W11: 6831.64 | Y11: Cost of raw materials, components consumed | Z11: 15548.66 | AA11: 15571.4 | AB11: 17100.84 | AC11: 18995.11 | AD11: 19442.25 | AE11: 27655.02 | AG11: Finance costs | AH11: 51.9798 | AI11: 40.9855 | AJ11: 458.14 | AK11: 563.71 | AL11: 581.37 | AM11: 568.49
A12: Finance costs | I12: Employee benefit expenses | J12: 996.54 | K12: 1041.36 | L12: 1299.08 | M12: 1446.88 | N12: 1717.63 | O12: 2113.47 | Q12: Finance costs | R12: 307.98 | S12: 262.69 | T12: 316 | U12: 538.59 | V12: 655.13 | W12: 663.59 | Y12: Construction materials consumed | Z12: 30316.12 | AA12: 24558.23 | AB12: 33506.21 | AC12: 43237.35 | AD12: 54813.97 | AE12: 63526.44 | AG12: Depreciation, amortisation and impairment | AH12: 5.7372 | AI12: 20.2856 | AJ12: 22.92 | AK12: 20.91 | AL12: 22.32 | AM12: 20.94
A13: Interest and bank charges | B13: 1950.64 | C13: 2129.16 | D13: 2559.61 | E13: 2593.62 | F13: 2784.41 | G13: 2778 | I13: Finance costs | J13: 520.89 | K13: 435.73 | L13: 396.33 | M13: 466.75 | N13: 518.08 | O13: 576.53 | Q13: Employee benefit expense | R13: 1104.36 | S13: 1115.09 | T13: 1258.66 | U13: 1356.24 | V13: 1440.63 | W13: 1540.2 | Y13: Purchase of stock in trade | Z13: 841.09 | AA13: 1213.58 | AB13: 1069.5 | AC13: 1052.86 | AD13: 1063.77 | AE13: 1402.14 | AG13: Other expenses | AH13: 57.5203 | AI13: 119.2857 | AJ13: 86.71 | AK13: 90.98 | AL13: 124.1 | AM13: 165.63
A14: Derivative Loss/Gain (net) | B14: -137.5 | C14: 126.13 | D14: -15.69 | E14: -230.98 | F14: -51.47 | G14: -246.18 | I14: Depreciation and amortisation expense | J14: 339.64 | K14: 373.45 | L14: 350.78 | M14: 391.75 | N14: 473.29 | O14: 497.27 | Q14: Depreciation and amortisation | R14: 147.2 | S14: 152.53 | T14: 157.86 | U14: 161.48 | V14: 185.36 | W14: 183.68 | Y14: Stores, spares and tools consumed | Z14: 2184.46 | AA14: 2023.54 | AB14: 3091.07 | AC14: 4814.89 | AD14: 4432.02 | AE14: 4393.39 | AG14: CSR expenses | AH14: 11.4846 | AI14: 19.052 | AJ14: 0 | AK14: 0 | AL14: 0 | AM14: 0
A15: Total Finance costs | B15: =B13+B14 -> 1813.14 | C15: =C13+C14 -> 2255.29 | D15: =D13+D14 -> 2543.92 | E15: =E13+E14 -> 2362.64 | F15: =F13+F14 -> 2732.94 | G15: =G13+G14 -> 2531.82 | I15: Expected credit losses provision for loans and advances | J15: 79.47 | K15: 0 | L15: 95.26 | M15: 2.81 | N15: 0 | O15: 0 | Q15: Other expenses | R15: 1208.42 | S15: 1250.29 | T15: 1121.93 | U15: 1474.9 | V15: 1674.16 | W15: 1892.29 | Y15: Sub-contracting charges | Z15: 26454.05 | AA15: 22316.18 | AB15: 24772.33 | AC15: 25624.45 | AD15: 35054.35 | AE15: 40570.92 | AG15: Total expenses | AH15: =SUM(AH9:AH14) -> 9595.484 | AI15: =SUM(AI9:AI14) -> 13805.366 | AJ15: =SUM(AJ9:AJ14) -> 15004.96 | AK15: =SUM(AK9:AK14) -> 18783.29 | AL15: =SUM(AL9:AL14) -> 19638.84 | AM15: =SUM(AM9:AM14) -> 21125.83
A16: Depreciation and amortisation | B16: 1680.28 | C16: 2107.34 | D16: 3099.3 | E16: 3423.24 | F16: 3888.46 | G16: 4378.93 | I16: Other expenses | J16: 870.58 | K16: 1085.84 | L16: 1054.32 | M16: 1158.4 | N16: 1479.7 | O16: 1429.72 | Q16: Total expenses | R16: =SUM(R9:R15) -> 11186.2 | S16: =SUM(S9:S15) -> 12388.21 | T16: =SUM(T9:T15) -> 13312.62 | U16: =SUM(U9:U15) -> 17152.05 | V16: =SUM(V9:V15) -> 19540.09 | W16: =SUM(W9:W15) -> 21190.07 | Y16: Changes in inventories of finished goods, WIP | Z16: 647.7 | AA16: 343.37 | AB16: -2076.6 | AC16: -3156.64 | AD16: 1021.07 | AE16: -410.79 | AG16: Profit/loss before exceptional items and tax | AH16: =AH7-AH15 -> 728.4392 | AI16: =AI7-AI15 -> 970.898 | AJ16: =AJ7-AJ15 -> 1137.99 | AK16: =AK7-AK15 -> 1398.65 | AL16: =AL7-AL15 -> 1639.17 | AM16: =AM7-AM15 -> 1948.97
A17: Foreign exchange Gain/Loss (net) | B17: 1626.38 | C17: -715.24 | D17: 872.07 | E17: 1886.32 | F17: 112.82 | G17: 280.85 | I17: Total Expenses | J17: =SUM(J9:J16) -> 12052.87 | K17: =SUM(K9:K16) -> 12248.64 | L17: =SUM(L9:L16) -> 14334.93 | M17: =SUM(M9:M16) -> 15850.4 | N17: =SUM(N9:N16) -> 18989.23 | O17: =SUM(O9:O16) -> 21555.46 | Q17: Profit before exceptional items and tax | R17: =R7-R16 -> 790.27 | S17: =S7-S16 -> 755.91 | T17: =T7-T16 -> 443.07 | U17: =U7-U16 -> 160.98 | V17: =V7-V16 -> 426.49 | W17: =W7-W16 -> 727.49 | Y17: Other manufacturing, construction and operating expenses | Z17: 13328.71 | AA17: 12983.56 | AB17: 16471.05 | AC17: 20020.81 | AD17: 24486.49 | AE17: 27533.55 | AG17: Exceptional items | AH17: 12.4235 | AI17: 0 | AJ17: 0 | AK17: 0 | AL17: 0 | AM17: 0
A18: Other expenses | B18: 663.9 | C18: 691.62 | D18: 1077.74 | E18: 1185.73 | F18: 1833.9 | G18: 1975.55 | I18: Profit before share of profit/loss of JV and exceptional items | J18: =J7-J17 -> 667.01 | K18: =K7-K17 -> 767.82 | L18: =L7-L17 -> 531.37 | M18: =M7-M17 -> 550.74 | N18: =N7-N17 -> 701.19 | O18: =O7-O17 -> 822.8 | Q18: Exceptional items | R18: 0 | S18: 0 | T18: 43.64 | U18: 0 | V18: 0 | W18: 0 | Y18: Finance cost of financial services | Z18: 8041.88 | AA18: 7691.04 | AB18: 5952.54 | AC18: 6026.44 | AD18: 5714.9 | AE18: 6302.23 | AG18: Share in profit/loss of JV | AH18: 98.6199 | AI18: -16.5814 | AJ18: 68.72 | AK18: 103.52 | AL18: 80.11 | AM18: 104.94
A19: Total expenses | B19: =SUM(B10:B11,B15,B16:B18) -> 9427.48 | C19: =SUM(C10:C11,C15,C16:C18) -> 8213.55 | D19: =SUM(D10:D11,D15,D16:D18) -> 13237.57 | E19: =SUM(E10:E11,E15,E16:E18) -> 15690.66 | F19: =SUM(F10:F11,F15,F16:F18) -> 17580.86 | G19: =SUM(G10:G11,G15,G16:G18) -> 19245.56 | I19: Share of profit/loss from JV | J19: -23.38 | K19: -32.21 | L19: -19.89 | M19: 0 | N19: 0 | O19: 0 | Q19: Profit after exceptional items and tax | R19: =R17-R18 -> 790.27 | S19: =S17-S18 -> 755.91 | T19: =T17-T18 -> 399.43 | U19: =U17-U18 -> 160.98 | V19: =V17-V18 -> 426.49 | W19: =W17-W18 -> 727.49 | Y19: Employee benefits expense | Z19: 23114 | AA19: 24762.03 | AB19: 29695.79 | AC19: 37214.11 | AD19: 41171.02 | AE19: 46768.68 | AG19: Profit/Loss before tax | AH19: =AH16+AH17+AH18 -> 839.4826 | AI19: =AI16+AI17+AI18 -> 954.3166 | AJ19: =AJ16+AJ17+AJ18 -> 1206.71 | AK19: =AK16+AK17+AK18 -> 1502.17 | AL19: =AL16+AL17+AL18 -> 1719.28 | AM19: =AM16+AM17+AM18 -> 2053.91
A20: Profit before share of loss from JV, exceptional items and tax | B20: =B8-B19 -> 4306.94 | C20: =C8-C19 -> 6306.28 | D20: =D8-D19 -> 6104.94 | E20: =E8-E19 -> 6714.73 | F20: =F8-F19 -> 10629.12 | G20: =G8-G19 -> 13137.52 | I20: Profit before exceptiona items and tax | J20: =J18+J19 -> 643.63 | K20: =K18+K19 -> 735.61 | L20: =L18+L19 -> 511.48 | M20: =M18+M19 -> 550.74 | N20: =N18+N19 -> 701.19 | O20: =O18+O19 -> 822.8 | Q20: Tax expense | Y20: Sales, administration and other expense | Z20: 8646.71 | AA20: 8892 | AB20: 8733.89 | AC20: 8758.04 | AD20: 10419.42 | AE20: 11558.13 | AG20: Tax expense
A21: Share of loss from Joint ventures entities | B21: -4.39 | C21: -14.27 | D21: 17.39 | E21: 47.78 | F21: -161.69 | G21: 141.56 | I21: Exceptional items | J21: 4.06 | K21: 209.64 | L21: 184.93 | M21: 90.78 | N21: 0 | O21: 0 | Q21: Current tax | R21: 285.43 | S21: 280 | T21: 198.58 | U21: 121.74 | V21: 114.1 | W21: 269.96 | Y21: Finance cost | Z21: 2796.66 | AA21: 3913.44 | AB21: 3125.7 | AC21: 3207.16 | AD21: 3545.85 | AE21: 3334.37 | AG21: Current tax | AH21: 159.9869 | AI21: 206.0474 | AJ21: 226.31 | AK21: 324.72 | AL21: 382.62 | AM21: 485.05
A22: Profit before exceptional items and tax | B22: =B20+B21 -> 4302.55 | C22: =C20+C21 -> 6292.01 | D22: =D20+D21 -> 6122.33 | E22: =E20+E21 -> 6762.51 | F22: =F20+F21 -> 10467.43 | G22: =G20+G21 -> 13279.08 | I22: Profit before tax | J22: =J20+J21 -> 647.69 | K22: =K20+K21 -> 945.25 | L22: =L20+L21 -> 696.41 | M22: =M20+M21 -> 641.52 | N22: =N20+N21 -> 701.19 | O22: =O20+O21 -> 822.8 | Q22: Deferred tax | R22: -60.68 | S22: -76.81 | T22: -131.23 | U22: -136.79 | V22: -34.39 | W22: -113.21 | Y22: Depreciation, amortisation, impairment and obsolescnese | Z22: 2462.27 | AA22: 2904.21 | AB22: 2947.95 | AC22: 3502.25 | AD22: 3682.33 | AE22: 4121.18 | AG22: Earlier year tax | AH22: 0 | AI22: 0 | AJ22: -6.44 | AK22: -11.52 | AL22: -4.23 | AM22: -5.35
A23: Exceptional items | B23: -58.63 | C23: 0 | D23: -405.19 | E23: -1273.38 | F23: -373.7 | G23: -249.46 | I23: Tax expenses | Q23: Total tax expense | R23: =R21+R22 -> 224.75 | S23: =S21+S22 -> 203.19 | T23: =T21+T22 -> 67.35 | U23: =U21+U22 -> -15.05 | V23: =V21+V22 -> 79.71 | W23: =W21+W22 -> 156.75 | Y23: Total expenses | Z23: =SUM(Z11:Z22) -> 134382.31 | AA23: =SUM(AA11:AA22) -> 127172.58 | AB23: =SUM(AB11:AB22) -> 144390.27 | AC23: =SUM(AC11:AC22) -> 169296.83 | AD23: =SUM(AD11:AD22) -> 204847.44 | AE23: =SUM(AE11:AE22) -> 236755.26 | AG23: Deferred tax | AH23: -8.2478 | AI23: -5.0535 | AJ23: -4.73 | AK23: 6.28 | AL23: -0.86 | AM23: -0.26
A24: Profit before tax | B24: =B22+B23 -> 4243.92 | C24: =C22+C23 -> 6292.01 | D24: =D22+D23 -> 5717.14 | E24: =E22+E23 -> 5489.13 | F24: =F22+F23 -> 10093.73 | G24: =G22+G23 -> 13029.62 | I24: Current tax | J24: 226.14 | K24: 303.24 | L24: 191.59 | M24: 265.64 | N24: 223.4 | O24: 312.25 | Q24: Profit for the year | R24: =R19-R23 -> 565.52 | S24: =S17-S23 -> 552.72 | T24: =T17-T23 -> 375.72 | U24: =U17-U23 -> 176.03 | V24: =V17-V23 -> 346.78 | W24: =W17-W23 -> 570.74 | Y24: Profit before exceptional items and tax | Z24: =Z8-Z23 -> 13430.95 | AA24: =AA8-AA23 -> 12235.8 | AB24: =AB8-AB23 -> 14398.04 | AC24: =AC8-AC23 -> 16973.04 | AD24: =AD8-AD23 -> 20423.5 | AE24: =AE8-AE23 -> 23104.01 | AG24: Total tax expense | AH24: =AH21+AH23 -> 151.7391 | AI24: =AI21+AI23 -> 200.9939 | AJ24: =AJ21+AJ23+AJ22 -> 215.14 | AK24: =AK21+AK23+AK22 -> 319.48 | AL24: =AL21+AL23+AL22 -> 377.53 | AM24: =AM21+AM23+AM22 -> 479.44
A25: Tax expense | I25: Deferred tax | J25: 31.96 | K25: -20.03 | L25: -30.24 | M25: -59.14 | N25: -38.11 | O25: -56.72 | Y25: Exceptional items before tax (net) | Z25: 0 | AA25: 0 | AB25: 119.7 | AC25: -91.97 | AD25: 114.44 | AE25: 474.78 | AG25: Profit/loss for the year from continuing operations | AH25: =AH19-AH24 -> 687.7435 | AI25: =AI19-AI24 -> 753.3227 | AJ25: =AJ19-AJ24 -> 991.57 | AK25: =AK19-AK24 -> 1182.69 | AL25: =AL19-AL24 -> 1341.75 | AM25: =AM19-AM24 -> 1574.47
A26: Current tax | B26: 707.49 | C26: 1271.51 | D26: 888.2 | E26: 977.9 | F26: 1134.73 | G26: 2221.87 | I26: Total tax expenses | J26: =J24+J25 -> 258.1 | K26: =K24+K25 -> 283.21 | L26: =L24+L25 -> 161.35 | M26: =M24+M25 -> 206.5 | N26: =N24+N25 -> 185.29 | O26: =O24+O25 -> 255.53 | Q26: EPS | R26: =R24/'Company Info'!$D$11 -> 21.244177 | S26: =S24/'Company Info'!$D$11 -> 20.763336 | T26: =T24/'Company Info'!$D$11 -> 14.1142 | U26: =U24/'Company Info'!$D$11 -> 6.6126972 | V26: =V24/'Company Info'!$D$11 -> 13.027047 | W26: =W24/'Company Info'!$D$11 -> 21.44027 | Y26: Tax expense
A27: Deferred tax | B27: -144.6 | C27: 102.39 | D27: -124.24 | E27: -881.52 | F27: 399.85 | G27: -253.51 | I27: Profit for the year | J27: =J22-J26 -> 389.59 | K27: =K22-K26 -> 662.04 | L27: =L22-L26 -> 535.06 | M27: =M22-M26 -> 435.02 | N27: =N22-N26 -> 515.9 | O27: =O22-O26 -> 567.27 | Y27: Current tax | Z27: 3564.58 | AA27: 3923.39 | AB27: 22.77 | AC27: 448.35 | AD27: 20.83 | AE27: 0 | AG27: EPS | AH27: =AH25/'Company Info'!$F$11 -> 3.2984983 | AI27: =AI25/'Company Info'!$F$11 -> 3.6130239 | AJ27: =AJ25/'Company Info'!$F$11 -> 4.7556858 | AK27: =AK25/'Company Info'!$F$11 -> 5.6723197 | AL27: =AL25/'Company Info'!$F$11 -> 6.4351901 | AM27: =AM25/'Company Info'!$F$11 -> 7.5513424
A28: Less: Tax credit under Minimum alternate tax | B28: -103.5 | C28: -130.63 | D28: 0 | E28: 0 | F28: 455.16 | G28: 0 | Y28: Deferred tax | Z28: -301.38 | AA28: 87.43 | AB28: 0 | AC28: -676.31 | AD28: 0 | AE28: 0
A29: Total tax expense | B29: =SUM(B26:B28) -> 459.39 | C29: =SUM(C26:C28) -> 1243.27 | D29: =SUM(D26:D28) -> 763.96 | E29: =SUM(E26:E28) -> 96.38 | F29: =SUM(F26:F28) -> 1989.74 | G29: =SUM(G26:G28) -> 1968.36 | I29: EPS | J29: =J27/'Company Info'!$C$11 -> 22.813379 | K29: =K27/'Company Info'!$C$11 -> 38.767343 | L29: =L27/'Company Info'!$C$11 -> 31.331724 | M29: =M27/'Company Info'!$C$11 -> 25.473642 | N29: =N27/'Company Info'!$C$11 -> 30.209764 | O29: =O27/'Company Info'!$C$11 -> 33.217858 | Y29: Net Profit after tax from continuing operations | Z29: =Z24-(Z27+Z28) -> 10167.75 | AA29: =AA24-(AA27+AA28) -> 8224.98 | AB29: =AB24-(AB27+AB28)+AB25 -> 14494.97 | AC29: =AC24-(AC27+AC28)+AC25 -> 17109.03 | AD29: =AD24-(AD27+AD28)+AD25 -> 20517.11 | AE29: =AE24-(AE27+AE28)+AE25 -> 23578.79
A30: Profit for the year | B30: =B24-B29 -> 3784.53 | C30: =C24-C29 -> 5048.74 | D30: =D24-D29 -> 4953.18 | E30: =E24-E29 -> 5392.75 | F30: =F24-F29 -> 8103.99 | G30: =G24-G29 -> 11061.26 | Y30: Exceptional items before tax | Z30: 0 | AA30: -3693.78 | AB30: 0 | AC30: 0 | AD30: 0 | AE30: 0
Y31: Tax expense on exceptional items
A32: EPS | B32: =B30/'Company Info'!$B$11 -> 17.519845 | C32: =C30/'Company Info'!$B$11 -> 23.372292 | D32: =D30/'Company Info'!$B$11 -> 22.929913 | E32: =E30/'Company Info'!$B$11 -> 24.964829 | F32: =F30/'Company Info'!$B$11 -> 37.516058 | G32: =G30/'Company Info'!$B$11 -> 51.206242 | Y32: Current tax | Z32: 0 | AA32: 48.44 | AB32: 4499.4 | AC32: 5055.17 | AD32: 5127.7 | AE32: 6100.82
Y33: Deferred tax | Z33: 0 | AA33: -186.2 | AB33: -295.48 | AC33: -571.01 | AD33: -180.31 | AE33: -209.42
Y34: Exceptional items (net of tax) | Z34: =Z30-(Z32+Z33) -> 0 | AA34: =AA30-(AA32+AA33) -> -3556.02 | AB34: =AB30-(AB32+AB33) -> -4203.92 | AC34: =AC30-(AC32+AC33) -> -4484.16 | AD34: =AD30-(AD32+AD33) -> -4947.39 | AE34: =AE30-(AE32+AE33) -> -5891.4
Y35: Net Profit after tax from continuing operations | Z35: =Z29+Z34 -> 10167.75 | AA35: =AA29+AA34 -> 4668.96 | AB35: =AB29+AB34 -> 10291.05 | AC35: =AC29+AC34 -> 12624.87 | AD35: =AD29+AD34 -> 15569.72 | AE35: =AE29+AE34 -> 17687.39
Y36: Share in profit/loss after tax of joint ventures (net) | Z36: 71.96 | AA36: 14.4 | AB36: 128.19 | AC36: -94.25 | AD36: -22.62 | AE36: -14.06
Y37: Profit for the year from continuing operations | Z37: =Z35+Z36 -> 10239.71 | AA37: =AA35+AA36 -> 4683.36 | AB37: =AB35+AB36 -> 10419.24 | AC37: =AC35+AC36 -> 12530.62 | AD37: =AD35+AD36 -> 15547.1 | AE37: =AE35+AE36 -> 17673.33
Y38: Discontinued operations
Y39: Profit before tax from discontinued operations | Z39: 883.25 | AA39: 10790.5 | AB39: 0 | AC39: 0 | AD39: 0 | AE39: 0
Y40: Tax expense of discontinued operations | Z40: 228.68 | AA40: 2552.58 | AB40: 0 | AC40: 0 | AD40: 0 | AE40: 0
Y41: Net Profit after tax from dicontinued operations | Z41: =Z39-Z40 -> 654.57 | AA41: =AA39-AA40 -> 8237.92 | AB41: =AB39-AB40 -> 0 | AC41: =AC39-AC40 -> 0 | AD41: =AD39-AD40 -> 0 | AE41: =AE39-AE40 -> 0
Y42: Net after tax from continuing operations & discontinued operations | Z42: =Z37+Z41 -> 10894.28 | AA42: =AA37+AA41 -> 12921.28 | AB42: =AB37+AB41 -> 10419.24 | AC42: =AC37+AC41 -> 12530.62 | AD42: =AD37+AD41 -> 15547.1 | AE42: =AE37+AE41 -> 17673.33
Y44: EPS | Z44: =Z42/'Company Info'!$E$11 -> 79.197663 | AA44: =AA42/'Company Info'!$E$11 -> 93.933254 | AB44: =AB42/'Company Info'!$E$11 -> 75.744286 | AC44: =AC42/'Company Info'!$E$11 -> 91.093291 | AD44: =AD42/'Company Info'!$E$11 -> 113.02206 | AE44: =AE42/'Company Info'!$E$11 -> 128.47902

Sheet Cash Flow Statement
A1: Consolidated Statement of Cash Flows
E2: #VALUE! | M2: #VALUE! | U2: #VALUE! | AC2: #VALUE! | AK2: #VALUE!
A3: Particulars | B3: 2020 | C3: 2021 | D3: 2022 | E3: 2023 | F3: 2024 | G3: 2025 | I3: Particulars | J3: 2020 | K3: 2021 | L3: 2022 | M3: 2023 | N3: 2024 | O3: 2025 | Q3: Particulars | R3: 2020 | S3: 2021 | T3: 2022 | U3: 2023 | V3: 2024 | W3: 2025 | Y3: Particulars | Z3: 2020 | AA3: 2021 | AB3: 2022 | AC3: 2023 | AD3: 2024 | AE3: 2025 | AG3: Particulars | AH3: 2020 | AI3: 2021 | AJ3: 2022 | AK3: 2023 | AL3: 2024 | AM3: 2025
A4: Cash Flows from Operating Activities | I4: Cash flow from Operating activities | Q4: CASH FLOW FROM OPERATING ACTIVITIES | Y4: CASH FLOW FROM OPERATING ACTIVITIES | AG4: CASH FLOW FROM OPERATING ACTIVITIES
A5: Net profit before tax | B5: 4243.92 | C5: 6292.01 | D5: 5717.14 | E5: 5489.13 | F5: 10093.73 | G5: 13029.62 | I5: Profit for the year | J5: 389.59 | K5: 662.04 | L5: 535.06 | M5: 435.02 | N5: 515.9 | O5: 567.27 | Q5: Profit for the year after tax | R5: 565.52 | S5: 552.72 | T5: 332.08 | U5: 176.03 | V5: 346.78 | W5: 570.74 | Y5: Profit before tax | AG5: Net profit before taxation | AH5: 954.3166 | AI5: 1206.71 | AJ5: 1502.17 | AK5: 1719.28 | AL5: 2053.91 | AM5: 1550.17
A6: Adjustments for | I6: Adjustments for | Q6: Adjustments for | Y6: Continuing operations | Z6: 13430.95 | AA6: 12235.8 | AB6: 14398.04 | AC6: 16973.04 | AD6: 20423.5 | AE6: 23104.01 | AG6: Adjustments for
A7: Share of profit/loss of joint ventures entities | B7: 4.39 | C7: 14.27 | D7: -17.39 | E7: -47.78 | F7: 161.69 | G7: -141.56 | I7: Tax expenses | J7: 258.1 | K7: 283.21 | L7: 161.35 | M7: 206.5 | N7: 185.29 | O7: 255.53 | Q7: Income tax expense | R7: 224.75 | S7: 203.19 | T7: 67.35 | U7: -15.05 | V7: 79.71 | W7: 156.75 | Y7: Discontinued operations | Z7: 883.25 | AA7: 10790.5 | AB7: 0 | AC7: 0 | AD7: 0 | AE7: 0 | AG7: Depreciation, amortization and impairment | AH7: 34.8849 | AI7: 0.74 | AJ7: -0.21 | AK7: 0 | AL7: 0 | AM7: 0
A8: Depreciation and amortisation expense | B8: 1680.28 | C8: 2107.34 | D8: 3099.3 | E8: 3423.24 | F8: 3888.46 | G8: 4378.93 | I8: Share of loss of Joint venture | J8: 23.38 | K8: 32.21 | L8: 19.89 | M8: 0 | N8: 473.29 | O8: 497.27 | Q8: Depreciation and amortisation expense | R8: 147.2 | S8: 152.53 | T8: 157.86 | U8: 161.48 | V8: 185.36 | W8: 183.68 | Y8: Profit before tax including discontinued operations | Z8: =Z6+Z7 -> 14314.2 | AA8: =AA6+AA7 -> 23026.3 | AB8: =AB6+AB7 -> 14398.04 | AC8: =AC6+AC7 -> 16973.04 | AD8: =AD6+AD7 -> 20423.5 | AE8: =AE6+AE7 -> 23104.01 | AG8: Share in (Profit)/Losses of Joint Ventures | AH8: 16.5814 | AI8: 36.67 | AJ8: 37.07 | AK8: 42.32 | AL8: 37.78 | AM8: 47.09
A9: Unclaimed Liabilities/excess provision written back | B9: -1.84 | C9: -5.38 | D9: -20.47 | E9: -20.85 | F9: -99.12 | G9: -43.52 | I9: Depreciation and amortization expenses | J9: 339.64 | K9: 373.45 | L9: 350.78 | M9: 391.75 | N9: 518.08 | O9: 576.53 | Q9: Profit on sale of PPE | R9: -0.06 | S9: -8.34 | T9: -0.98 | U9: -4.46 | V9: -3.26 | W9: -8.56 | Y9: Adjustments for | AG9: Unwinding of Interest Cost on Lease obligation | AH9: 3.9101 | AI9: -68.72 | AJ9: -103.52 | AK9: -80.11 | AL9: -104.94 | AM9: =0.05+0.57-0.27+24.75-25.05+0.68+0.04 -> 0.77
A10: Cost of assets transferred under finance lease | B10: 19.8 | C10: 4.2 | D10: 8.62 | E10: 8.38 | F10: 5.27 | G10: 7.12 | I10: Finance costs | J10: 520.89 | K10: 435.73 | L10: 396.33 | M10: 466.75 | N10: -57.8 | O10: -43.34 | Q10: Loss on PPE discarded & intangible assets derecognised | R10: 0.5 | S10: 0.86 | T10: 0.67 | U10: 0.95 | V10: 2.64 | W10: 3.32 | Y10: Dividend received | Z10: -101.6 | AA10: -28.47 | AB10: -4.12 | AC10: -6.28 | AD10: -208.49 | AE10: -117.05 | AG10: Unwinding of Interest Cost Retention Money | AH10: 1.5859 | AI10: 3.01 | AJ10: 3.16 | AK10: 3.1 | AL10: 4.02 | AM10: 4.25
A11: Recognition of deferred income under long term land lease | B11: -71.8 | C11: -65.62 | D11: -65.63 | E11: -69.57 | F11: -75.37 | G11: -82.61 | I11: Impairment loss on PPE | J11: 6.89 | K11: 0 | L11: 37.71 | M11: 18.22 | N11: 2.13 | O11: -8.92 | Q11: Finance costs | R11: 307.98 | S11: 262.69 | T11: 316 | U11: 538.59 | V11: 655.13 | W11: 663.59 | Y11: Depreciation, amortisation, impairment and obsolescene | Z11: 2462.27 | AA11: 2904.21 | AB11: 2947.95 | AC11: 3502.25 | AD11: 3682.33 | AE11: 4121.18 | AG11: Unwinding of Interest Cost on Performance and Security Deposit | AH11: 8.3178 | AI11: 1.14 | AJ11: 0.3 | AK11: 0.09 | AL11: -2.03 | AM11: 0.02
A12: Financial guarantees income | B12: -1.52 | C12: -2.71 | D12: -4.38 | E12: -6.53 | F12: -8.54 | G12: 0 | I12: Gain on sale of subsidiary and Joint ventures (net) | J12: -12.3 | K12: -209.64 | L12: -262.41 | M12: 0 | N12: -0.93 | O12: -0.23 | Q12: Interest income | R12: -3.27 | S12: -4.74 | T12: -10.56 | U12: -23.2 | V12: -45.32 | W12: -55.24 | Y12: Exchange difference rate changes on cash and cash equivalents | Z12: 5.69 | AA12: -75.47 | AB12: -108.09 | AC12: -1.83 | AD12: -20.53 | AE12: -5.91 | AG12: Profit on sale of assets (net) | AH12: -0.0004 | AI12: -50 | AJ12: 0 | AK12: 18.22 | AL12: -14.5 | AM12: 1.12
A13: Amortisation of government grant | B13: -12.48 | C13: -12.95 | D13: -14.23 | E13: -16.34 | F13: -20.61 | G13: -23.82 | I13: Dividend income | J13: -0.07 | K13: -16.32 | L13: -0.1 | M13: -0.08 | N13: 81.7 | O13: 32.84 | Q13: Bad debts, loans and advances written off | R13: 27.6 | S13: 42.43 | T13: -10.68 | U13: 17.66 | V13: 2.17 | W13: 46.97 | Y13: Unrealised gain/loss on finance leases | Z13: -88.14 | AA13: 74.98 | AB13: -41.25 | AC13: -66.92 | AD13: -2.37 | AE13: -2.17 | AG13: Interest Income | AH13: -214.5683 | AI13: 429.87 | AJ13: 529.72 | AK13: =0.78+0.13+529.48 -> 530.39 | AL13: =-0.23-9.24-25.81+503.95 -> 468.67 | AM13: 457.82
A14: Finance cost | B14: 1950.64 | C14: 2129.16 | D14: 2559.61 | E14: 2593.62 | F14: 2784.41 | G14: 2778 | I14: Interest income | J14: -36.22 | K14: -30.13 | L14: -35.28 | M14: -34.05 | N14: 0.03 | O14: 0 | Q14: Exceptional items | R14: 26.8 | S14: 41.38 | T14: 43.64 | U14: 0 | V14: 90.91 | W14: 216.7 | Y14: Finance costs | Z14: 0 | AA14: -14.55 | AB14: 0 | AC14: 0 | AD14: 0 | AE14: 0 | AG14: Dividend Income | AH14: -0.7084 | AI14: -652.33 | AJ14: -763.47 | AK14: -956.39 | AL14: -1066.75 | AM14: -874.53
A15: Effect of exchange rate change | B15: 1709.73 | C15: -729.14 | D15: 917.91 | E15: 2527.76 | F15: 328.79 | G15: 719.33 | I15: Gain on disposal of PPE | J15: -0.56 | K15: -8.5 | L15: -18.61 | M15: 6.65 | N15: 42.35 | O15: -13.62 | Q15: Allowances for bad and doubtful debts, loans and advances | R15: 92.11 | S15: 2.74 | T15: 28.24 | U15: 32.8 | V15: -7.69 | W15: 9.71 | Y15: Interest income | Z15: 2796.66 | AA15: 3913.44 | AB15: 3125.7 | AC15: 3207.16 | AD15: 3545.85 | AE15: 3334.37 | AG15: Other Comprehensive Income | AH15: 2.4141 | AI15: =-7.83+0.04 -> -7.79 | AJ15: =0.03-3.04 -> -3.01 | AK15: 0 | AL15: =-0.19+1.4 -> 1.21 | AM15: 0
A16: Gain on account of dilution of stake in subsidiary | B16: -480.57 | C16: 0 | D16: -15.69 | E16: -230.98 | F16: -51.47 | G16: -246.18 | I16: Bad debts written off | J16: 7.68 | K16: 8.74 | L16: 0.25 | M16: 0 | N16: -0.23 | O16: -0.17 | Q16: Mark to market loss/gain on forward and commodity contracts | R16: -85.39 | S16: 32.72 | T16: -12.36 | U16: 15.38 | V16: 47.02 | W16: -2.09 | Y16: Profit/loss on sale of fixed assets | Z16: -829.78 | AA16: -1377.66 | AB16: -1053.65 | AC16: -1817.47 | AD16: -2447.07 | AE16: -2449.87 | AG16: Operating Profit Before Working Capital Changes | AH16: =SUM(AH5,AH7:AH15) -> 806.7337 | AI16: =SUM(AI5,AI7:AI15) -> 899.3 | AJ16: =SUM(AJ5,AJ7:AJ15) -> 1202.21 | AK16: =SUM(AK5,AK7:AK15) -> 1276.9 | AL16: =SUM(AL5,AL7:AL15) -> 1377.37 | AM16: =SUM(AM5,AM7:AM15) -> 1186.71
A17: Derivative Loss/gain (net) | B17: -137.5 | C17: 126.13 | D17: 12.53 | E17: -7.49 | F17: -5.31 | G17: -2.27 | I17: Liabilities written off | J17: -1.51 | K17: -4.4 | L17: -21.67 | M17: -0.57 | N17: 0 | O17: 0 | Q17: Net unrealised exchange gain/loss | R17: 0 | S17: 0 | T17: 16.59 | U17: -46.44 | V17: 0 | W17: 0 | Y17: Profit/loss on sale/fair valuation of investments | Z17: 33.28 | AA17: -528.81 | AB17: -17.6 | AC17: -167.65 | AD17: -95.44 | AE17: -187.64 | AG17: Adjustments for
A18: Provision of doubtful debts | B18: 19.47 | C18: 25 | D18: 41.25 | E18: 1 | F18: -860.19 | G18: -687.98 | I18: Allowance for expected credit loss | J18: 76.89 | K18: 26.77 | L18: 39.26 | M18: -10.27 | N18: 0 | O18: 0 | Q18: Operating profit before working capital changes | R18: =SUM(R5,R7:R17) -> 1303.74 | S18: =SUM(S5,S7:S17) -> 1278.18 | T18: =SUM(T5,T7:T17) -> 927.85 | U18: =SUM(U5,U7:U17) -> 853.74 | V18: =SUM(V5,V7:V17) -> 1353.45 | W18: =SUM(W5,W7:W17) -> 1785.57 | Y18: Gain/loss on disposal of discontinued operations | Z18: -733.84 | AA18: -1118.77 | AB18: -440.14 | AC18: -52.87 | AD18: -734.2 | AE18: -1133.12 | AG18: Trade Receivables (Current) | AH18: -196.7422 | AI18: -145.08 | AJ18: 41.66 | AK18: -31.91 | AL18: -108.08 | AM18: -383.03
A19: Interest income | B19: -1669.74 | C19: -1758.17 | D19: -1940.71 | E19: -1246.28 | F19: -209.51 | G19: -251.87 | I19: Impairment loss on asset held for sale | J19: 0.27 | K19: 0.86 | L19: 95.26 | M19: 2.81 | N19: 0 | O19: 0 | Q19: Adjustments for | Y19: Gain/loss on derivatives at fair value through profit or loss | Z19: 0 | AA19: -10707.92 | AB19: 0 | AC19: 0 | AD19: 0 | AE19: 0 | AG19: Lease receivables | AH19: 155.8103 | AI19: 123.19 | AJ19: -563.93 | AK19: -3137.49 | AL19: 472.01 | AM19: 499.51
A20: Dividend income | B20: -8 | C20: -7.01 | D20: -4.01 | E20: -0.35 | F20: -19.41 | G20: -20.52 | I20: Unrealised foreign exchange gain/loss (net) | J20: -95.14 | K20: 50.78 | L20: =0.68-29.27 -> -28.59 | M20: =0.05-9.76 -> -9.71 | N20: 0 | O20: 0 | Q20: Inventories | R20: -134.81 | S20: -66.38 | T20: -213.09 | U20: -46.8 | V20: -71.9 | W20: 72.85 | Y20: Employee stock option | Z20: -13.19 | AA20: 0 | AB20: 0 | AC20: 0 | AD20: 0 | AE20: 0 | AG20: Lease receivables (current) | AH20: -3.0986 | AI20: 35.46 | AJ20: -49.67 | AK20: -97.33 | AL20: -94.71 | AM20: -27.51
A21: Net gain on sale of current investments | B21: -48.7 | C21: -12.39 | D21: -5.41 | E21: -20.71 | F21: 373.7 | G21: 249.46 | I21: Net gain/loss arising on financial assets | J21: 0.19 | K21: -0.27 | L21: -0.3 | M21: -0.14 | N21: 0 | O21: 0 | Q21: Trade receivables | R21: -475.64 | S21: -324.1 | T21: 8.3 | U21: -1602.52 | V21: 144.68 | W21: -992.62 | Y21: Non cash items related to discontinued operations | Z21: 190.84 | AA21: 137.67 | AB21: 135.31 | AC21: 249.51 | AD21: 297.63 | AE21: 222.6 | AG21: Project work in progress | AH21: -4.7017 | AI21: -14.31 | AJ21: -44.44 | AK21: -9.02 | AL21: -5.79 | AM21: 64.72
A22: Gain on disposal of associate | B22: 0 | C22: -92.28 | D22: 405.19 | E22: 1273.38 | F22: 0 | G22: -603.27 | I22: Operating profit before working capital changes | J22: =SUM(J5,J7:J21) -> 1477.72 | K22: =SUM(K5,K7:K21) -> 1604.53 | L22: =SUM(L5,L7:L21) -> 1268.93 | M22: =SUM(M5,M7:M21) -> 1472.88 | N22: =SUM(N5,N7:N21) -> 1759.81 | O22: =SUM(O5,O7:O21) -> 1863.16 | Q22: Other financial assets | R22: -71.18 | S22: 0.36 | T22: 39.22 | U22: -86.09 | V22: 60.14 | W22: -23.42 | Y22: Business combination expenses | Z22: 49.44 | AA22: 3.13 | AB22: -1.65 | AC22: 0 | AD22: -2.65 | AE22: 0 | AG22: Other non current financial assets | AH22: 261.1774 | AI22: -216.16 | AJ22: -344.03 | AK22: -711.49 | AL22: -214.54 | AM22: 838.75
A23: Provision for royalty on storage | B23: 58.63 | C23: 0 | D23: -59.23 | E23: 0 | F23: 19.7 | G23: 8.61 | I23: Adjustments for | Q23: Contract assets | R23: -286.14 | S23: -994.49 | T23: -1580.48 | U23: -132.38 | V23: -1645.8 | W23: -2017.72 | Y23: Impairment of debt instruments | Z23: 84.28 | AA23: 0 | AB23: 12 | AC23: 716.2 | AD23: 1055.47 | AE23: 148.52 | AG23: Other financial assets | AH23: -2083.8398 | AI23: 1907.07 | AJ23: -252.53 | AK23: 1258.09 | AL23: 1425.98 | AM23: -532.75
A24: Diminution in value of inventories | B24: 0.16 | C24: 2.49 | D24: 1.83 | E24: 30.77 | F24: 0 | G24: 0 | I24: Trade and other receivables | J24: -695.49 | K24: -615.85 | L24: -950.18 | M24: -2321.71 | N24: -2486.27 | O24: -2338.81 | Q24: Other current assets | R24: 21.74 | S24: 147.02 | T24: -311.59 | U24: 27.65 | V24: -132.73 | W24: -221.95 | Y24: Impairment recognised on non-current assets held for sale | Z24: 350.59 | AA24: 151.26 | AB24: -6.11 | AC24: -10.16 | AD24: -511.73 | AE24: -187.44 | AG24: Other non current assets | AH24: -0.2068 | AI24: 1.25 | AJ24: -0.26 | AK24: 0.01 | AL24: -0.07 | AM24: 299.33
A25: Amortisation of fair valuation adjustment on security deposit | B25: 1.72 | C25: 1.72 | D25: 1.72 | E25: 1.72 | F25: 1.72 | G25: 2.67 | I25: Inventories | J25: -95.31 | K25: 137.47 | L25: 13.5 | M25: -132.44 | N25: -124.87 | O25: -75.4 | Q25: Other non-current assets | R25: -24.99 | S25: -110.35 | T25: 113.91 | U25: -18.86 | V25: -9.3 | W25: -6.56 | Y25: Gain/loss on de-recognition of lease liability | Z25: =3.93-1.85 -> 2.08 | AA25: =0.23-15.78 -> -15.55 | AB25: 0 | AC25: 0 | AD25: -52.27 | AE25: -33.29 | AG25: Other current assets | AH25: 1916.0358 | AI25: -2231.18 | AJ25: 568.87 | AK25: 351.03 | AL25: 121.65 | AM25: -38.07
A26: Loss on sale/discard of PPE (net) | B26: 3.86 | C26: 3.55 | D26: 3.52 | E26: -60.32 | F26: -8.89 | G26: -8.36 | I26: Trade, other payables and provisions | J26: 512.19 | K26: 51.1 | L26: 644.87 | M26: 1864.6 | N26: 1976.58 | O26: 1736.91 | Q26: Trade payables | R26: 156.71 | S26: 1183.86 | T26: 692.48 | U26: 1515.27 | V26: 1384.32 | W26: 1244.06 | Y26: Interest expenses | Z26: 1.33 | AA26: 1.16 | AB26: 0 | AC26: 0 | AD26: 1.38 | AE26: 11.57 | AG26: Trade payables | AH26: 522.0482 | AI26: -427.51 | AJ26: -47.77 | AK26: 397.21 | AL26: -370.37 | AM26: 91.78
A27: Operating profit before working capital changes | B27: =SUM(B5,B7:B26) -> 7260.45 | C27: =SUM(C5,C7:C26) -> 8020.22 | D27: =SUM(D5,D7:D26) -> 10621.47 | E27: =SUM(E5,E7:E26) -> 13621.8 | F27: =SUM(F5,F7:F26) -> 16299.05 | G27: =SUM(G5,G7:G26) -> 19061.78 | I27: Cash generated from Operations | J27: =SUM(J22,J24:J26) -> 1199.11 | K27: =SUM(K22,K24:K26) -> 1177.25 | L27: =SUM(L22,L24:L26) -> 977.12 | M27: =SUM(M22,M24:M26) -> 883.33 | N27: =SUM(N22,N24:N26) -> 1125.25 | O27: =SUM(O22,O24:O26) -> 1185.86 | Q27: Other current liabilities | R27: -56.46 | S27: -122.82 | T27: 0.58 | U27: 88.14 | V27: -576.31 | W27: -53.52 | Y27: Operating profit before working capital changes | Z27: =SUM(Z8,Z10:Z26) -> 18524.11 | AA27: =SUM(AA8,AA10:AA26) -> 16344.95 | AB27: =SUM(AB8,AB10:AB26) -> 18946.39 | AC27: =SUM(AC8,AC10:AC26) -> 22524.98 | AD27: =SUM(AD8,AD10:AD26) -> 24931.41 | AE27: =SUM(AE8,AE10:AE26) -> 26825.76 | AG27: Other current financial liabilities | AH27: 234.765 | AI27: 300.34 | AJ27: 840.19 | AK27: 181.21 | AL27: -13.69 | AM27: 284.08
A28: Adjustments for: | I28: Income tax paid | J28: -261.87 | K28: -246.25 | L28: -263.46 | M28: -226.94 | N28: -282.29 | O28: -271.91 | Q28: Contract liabilities | R28: -10.11 | S28: 55.13 | T28: 308.94 | U28: 220.87 | V28: 83.88 | W28: 27.17 | Y28: Adjustments for | AG28: Other non current liabilities | AH28: 20.7787 | AI28: -11.08 | AJ28: -14.23 | AK28: 0 | AL28: 0 | AM28: -81.33
A29: Decrease/Increase in trade receivables | B29: -175.66 | C29: 295.2 | D29: 230.18 | E29: -787.07 | F29: -329.79 | G29: -450.99 | I29: Net cash generated from/used in operating activities | J29: =J27+J28 -> 937.24 | K29: =K27+K28 -> 931 | L29: =L27+L28 -> 713.66 | M29: =M27+M28 -> 656.39 | N29: =N27+N28 -> 842.96 | O29: =O27+O28 -> 913.95 | Q29: Other financial liabilities | R29: 13.9 | S29: 6.91 | T29: -4.9 | U29: -4.76 | V29: -25.79 | W29: 444.81 | Y29: Increase/decrease in trade and other receivables | Z29: -11278.12 | AA29: 2783.81 | AB29: -9851.72 | AC29: -4495.26 | AD29: -10642.89 | AE29: -9252.32 | AG29: Other non current fnancial liabilities | AH29: 50.9097 | AI29: 102.08 | AJ29: -85.35 | AK29: 217.5 | AL29: -8.09 | AM29: 14.15
A30: Increase in inventories | B30: -44.65 | C30: -23.58 | D30: 605.43 | E30: -66.66 | F30: 8.09 | G30: -37.35 | I30: CASH FLOW FROM INVESTING ACTIVITIES | Q30: Provisions | R30: 0 | S30: 0 | T30: 21.37 | U30: 14.01 | V30: =-4.19+2.83 -> -1.36 | W30: =3.9-0.68 -> 3.22 | Y30: increase/decrease in inventories | Z30: 353.19 | AA30: 348.9 | AB30: -74.33 | AC30: -475.75 | AD30: 244.68 | AE30: -539.52 | AG30: Other current liabilities | AH30: -2522.6487 | AI30: 239.62 | AJ30: 3841.67 | AK30: -3372.81 | AL30: 838.4 | AM30: 167.62
A31: Decrease in Financial assets | B31: 512.56 | C31: 219.36 | D31: -89.15 | E31: -325.52 | F31: 436.12 | G31: -94.19 | I31: CapEx on PPE | J31: -469.77 | K31: -261.15 | L31: -308.1 | M31: -771.48 | N31: -351.58 | O31: -574.62 | Q31: Cash generated from operations | R31: =SUM(R18,R20:R30) -> 436.76 | S31: =SUM(S18,S20:S30) -> 1053.32 | T31: =SUM(T18,T20:T30) -> 2.59 | U31: =SUM(U18,U20:U30) -> 828.27 | V31: =SUM(V18,V20:V30) -> 563.28 | W31: =SUM(W18,W20:W30) -> 261.89 | Y31: increase/decrease in trade payables and customer advances | Z31: 3134.23 | AA31: 2219.78 | AB31: 9678.03 | AC31: 5412.71 | AD31: 14601.02 | AE31: 9683.41 | AG31: Short term provisions | AH31: 21.7558 | AI31: 1.55 | AJ31: 3.89 | AK31: 0.79 | AL31: 10.68 | AM31: -14.86
A32: Decrease/Increase in other assets | B32: -612.94 | C32: 56.57 | D32: 215.77 | E32: -205.51 | F32: -138.64 | G32: -759.97 | I32: Proceeds from disposal of PPE | J32: 6.03 | K32: 26.41 | L32: 46.68 | M32: 52.13 | N32: 32.92 | O32: 62.73 | Q32: Income tax paid | R32: -349.31 | S32: -208.78 | T32: -286.3 | U32: -221.54 | V32: -252.13 | W32: 157.19 | Y32: Cash generated from operations before financing activities | Z32: =SUM(Z27:Z31) -> 10733.41 | AA32: =SUM(AA27:AA31) -> 21697.44 | AB32: =SUM(AB27:AB31) -> 18698.37 | AC32: =SUM(AC27:AC31) -> 22966.68 | AD32: =SUM(AD27:AD31) -> 29134.22 | AE32: =SUM(AE27:AE31) -> 26717.33 | AG32: Long term provisions | AH32: 7.7635 | AI32: 5.41 | AJ32: 3.19 | AK32: 1.52 | AL32: -16.03 | AM32: 13.46
A33: Increase in provisions | B33: 6.28 | C33: 10.68 | D33: 10.47 | E33: -167.97 | F33: 40.9 | G33: 247.27 | I33: Proceeds from sale of subsidiary and joint venture (net) | J33: 87.33 | K33: 354.66 | L33: 156.71 | M33: 273.72 | N33: 4.86 | O33: -149.94 | Q33: Net cash flow generated from/used in operating activities | R33: =R31+R32 -> 87.45 | S33: =S31+S32 -> 844.54 | T33: =T31+T32 -> -283.71 | U33: =U31+U32 -> 606.73 | V33: =V31+V32 -> 311.15 | W33: =W31+W32 -> 419.08 | Y33: Increase/decrease in loans and advances towards financing activities | Z33: 6.92 | AA33: 4617.71 | AB33: 5004.65 | AC33: 4937.44 | AD33: -5587.89 | AE33: -11955.52 | AG33: Cash generated from operations | AH33: =SUM(AH16,AH18:AH32) -> -813.4597 | AI33: =SUM(AI16,AI18:AI32) -> 569.95 | AJ33: =SUM(AJ16,AJ18:AJ32) -> 5099.47 | AK33: =SUM(AK16,AK18:AK32) -> -3675.79 | AL33: =SUM(AL16,AL18:AL32) -> 3414.72 | AM33: =SUM(AM16,AM18:AM32) -> 2382.56
A34: Decrease/Increase in trade and other payables | B34: 84.34 | C34: -68.92 | D34: 109.74 | E34: 249.96 | F34: -620.32 | G34: 87.89 | I34: Proceeds from sale of mutual funds (net) | J34: 0 | K34: 0.5 | L34: -3.26 | M34: 0.2 | N34: -45 | O34: -50 | Q34: CASH FLOW FROM INVESTING ACTIVITIES | Y34: Cash generated from operations before financing activities | Z34: =SUM(Z32:Z33) -> 10740.33 | AA34: =SUM(AA32:AA33) -> 26315.15 | AB34: =SUM(AB32:AB33) -> 23703.02 | AC34: =SUM(AC32:AC33) -> 27904.12 | AD34: =SUM(AD32:AD33) -> 23546.33 | AE34: =SUM(AE32:AE33) -> 14761.81 | AG34: Direct taxes paid | AH34: -146.4166 | AI34: -150.52 | AJ34: -299.32 | AK34: -388.18 | AL34: -460.29 | AM34: -462.66
A35: Increase in other financial liabilities | B35: 76.31 | C35: 29.68 | D35: -9.5 | E35: 210.67 | F35: 404.63 | G35: 181.73 | I35: Loans given to/ received back from joint ventures | J35: -39.47 | K35: -41.98 | L35: -17.43 | M35: -2.81 | N35: 45 | O35: 50 | Q35: CapEx on PPE | R35: -206.45 | S35: -180.07 | T35: -143.14 | U35: -178.29 | V35: -237.38 | W35: -182.52 | Y35: Taxes paid | Z35: -4046.45 | AA35: -3471.01 | AB35: -4539.45 | AC35: -5127.16 | AD35: -5280.05 | AE35: -5601.1 | AG35: Cash flow from operating actitivities | AH35: =AH33+AH34 -> -959.8763 | AI35: =AI33+AI34 -> 419.43 | AJ35: =AJ33+AJ34 -> 4800.15 | AK35: =AK33+AK34 -> -4063.97 | AL35: =AL33+AL34 -> 2954.43 | AM35: =AM33+AM34 -> 1919.9
A36: Decrease/increase in other liabilities | B36: 1144.69 | C36: -110.6 | D36: -314.55 | E36: 237.48 | F36: 189.46 | G36: 455.15 | I36: Loans given to others | J36: -56.51 | K36: -108.59 | L36: 22.26 | M36: 99.11 | N36: 52.5 | O36: 30.55 | Q36: Acquisition of subsidiary | R36: 4.49 | S36: 66.33 | T36: -56.93 | U36: 0 | V36: 3.8 | W36: 33.4 | Y36: Net cash used in/from operating activities | Z36: =Z34+Z35 -> 6693.88 | AA36: =AA34+AA35 -> 22844.14 | AB36: =AB34+AB35 -> 19163.57 | AC36: =AC34+AC35 -> 22776.96 | AD36: =AD34+AD35 -> 18266.28 | AE36: =AE34+AE35 -> 9160.71 | AG36: CASH FLOW FROM INVESTING ACTIVITIES
A37: Cash generated from Operations | B37: =SUM(B27,B29:B36) -> 8251.38 | C37: =SUM(C27,C29:C36) -> 8428.61 | D37: =SUM(D27,D29:D36) -> 11379.86 | E37: =SUM(E27,E29:E36) -> 12767.18 | F37: =SUM(F27,F29:F36) -> 16289.5 | G37: =SUM(G27,G29:G36) -> 18691.32 | I37: Investments in joint ventures | J37: -112.2 | K37: -1.78 | L37: 35.28 | M37: 34.05 | N37: -1.79 | O37: -87.22 | Q37: Proceeds from sale of PPE | R37: -545.65 | S37: -617.81 | T37: 1.46 | U37: 15.72 | V37: 0 | W37: 70.07 | Y37: CASH FLOW FROM INVESTING ACTIVITIES | AG37: CapEx on fixed assets including capital advances | AH37: -17.5399 | AI37: -40.84 | AJ37: -14.25 | AK37: -10.13 | AL37: -116.36 | AM37: -431.63
A38: Direct taxes paid (net of refunds) | B38: -849.57 | C38: -872.83 | D38: -959.72 | E38: -833.93 | F38: -1271.92 | G38: -1465.04 | I38: Investments in other entities | J38: -0.09 | K38: 0 | L38: 0.1 | M38: 0.08 | N38: 0 | O38: 0 | Q38: Proceeds/purchase of short term investments (net) | R38: 536.36 | S38: 639.25 | T38: -11.58 | U38: 12.64 | V38: 15.7 | W38: 53.24 | Y38: Purchase of fixed assets | Z38: -3436.82 | AA38: -1807.7 | AB38: -3110.63 | AC38: -4143.79 | AD38: -4516.53 | AE38: -4418.83 | AG38: Capex on intangible assets under development | AH38: -3.8931 | AI38: 0.12 | AJ38: 0.44 | AK38: 0 | AL38: 0 | AM38: 0
A39: Net cash generated from Operating activities | B39: =B37+B38 -> 7401.81 | C39: =C37+C38 -> 7555.78 | D39: =D37+D38 -> 10420.14 | E39: =E37+E38 -> 11933.25 | F39: =F37+F38 -> 15017.58 | G39: =G37+G38 -> 17226.28 | I39: Interest received | J39: 34.54 | K39: 32.08 | L39: -62.24 | M39: 0 | N39: 0 | O39: 0 | Q39: Interest received | R39: 3.36 | S39: 3.35 | T39: 10.58 | U39: 23.42 | V39: -5.18 | W39: -42.06 | Y39: Sale of fixed assets | Z39: 137.39 | AA39: 885.36 | AB39: 70.75 | AC39: 350.37 | AD39: 306.06 | AE39: 878.17 | AG39: Sale of PPE | AH39: 0.2445 | AI39: -102.09 | AJ39: -102.09 | AK39: 0.42 | AL39: 14.74 | AM39: 0.38
A40: Cash Flow from Investing activities | I40: Dividend received | J40: 0.07 | K40: 16.32 | L40: -125.02 | M40: -11.13 | N40: 0 | O40: 0 | Q40: Bank balances not considered as cash and cash equivalents (net) | R40: 89.95 | S40: -38.43 | T40: -5.08 | U40: -8.69 | V40: 0 | W40: 0 | Y40: Purchase of non-current investments | Z40: -1870.64 | AA40: -1873.24 | AB40: -2156.24 | AC40: -3036.34 | AD40: -4889.46 | AE40: -2284.26 | AG40: Repayment of loans | AH40: 2.4839 | AI40: -90.6 | AJ40: -58.63 | AK40: -51.05 | AL40: -224.07 | AM40: 0
A41: Purchase of PPE | B41: -3621.41 | C41: -1953.51 | D41: -3813.7 | E41: -9124.78 | F41: -7416.3 | G41: -8048.92 | I41: Payment for acquisition of subsidiary | J41: -136.36 | K41: 0 | L41: 0 | M41: 0 | N41: 0 | O41: 0 | Q41: Net cash flow from/used in Investing activities | R41: =SUM(R35:R40) -> -117.94 | S41: =SUM(S35:S40) -> -127.38 | T41: =SUM(T35:T40) -> -204.69 | U41: =SUM(U35:U40) -> -135.2 | V41: =SUM(V35:V40) -> -223.06 | W41: =SUM(W35:W40) -> -67.87 | Y41: Sale of non-current investments | Z41: 2245.29 | AA41: 240.19 | AB41: 1026.06 | AC41: 827.15 | AD41: 2127.87 | AE41: 1726.33 | AG41: Investment in subsidiaries and joint ventures | AH41: -40.0869 | AI41: -2.46 | AJ41: -9.27 | AK41: -13.96 | AL41: -396.48 | AM41: -143.65
A42: Proceeds from sale of PPE | B42: 62.99 | C42: 3.8 | D42: 155 | E42: 0 | F42: 26.71 | G42: 50.72 | I42: Deposits with banks | J42: -57.47 | K42: -8.72 | L42: 0 | M42: 0 | N42: 0 | O42: 0 | Q42: CASH FLOW FROM FINANCING ACTIVITIES | Y42: Purchase/sale of current investments | Z42: 2065.74 | AA42: -16841.55 | AB42: 1437.04 | AC42: -6083.66 | AD42: 2803.49 | AE42: -5950.82 | AG42: Interest received | AH42: 214.5683 | AI42: 210.61 | AJ42: 244.95 | AK42: 216.81 | AL42: 315.03 | AM42: 880.27
A43: Payment of deposit given against Capital commitments (net) | B43: -379.25 | C43: -138.61 | D43: 12.91 | E43: 203.79 | F43: 2036.63 | G43: -266 | I43: Consideration paid to minority shareholders | J43: -3.42 | K43: 0 | L43: 0 | M43: 0 | N43: 0 | O43: 0 | Q43: Proceeds from other than short-term borrowings | R43: 81.44 | S43: 470.29 | T43: 172.55 | U43: 381.51 | V43: 169.9 | W43: 266.16 | Y43: Change in other bank balances and cash not available for immediate use | Z43: 1439.82 | AA43: 915.13 | AB43: -2729.33 | AC43: -661.77 | AD43: 2697.75 | AE43: -7201.57 | AG43: Dividend received | AH43: 20.7084 | AI43: 17.5 | AJ43: 10 | AK43: 0 | AL43: 0 | AM43: 25.05
A44: PPE purchased along with Adani Krishnapatnam port ltd | B44: 0 | C44: -398.19 | D44: -847 | E44: -961 | F44: 0 | G44: 0 | I44: Cash generated/used in Investing activities | J44: =SUM(J31:J43) -> -747.32 | K44: =SUM(K31:K43) -> 7.75 | L44: =SUM(L31:L43) -> -255.02 | M44: =SUM(M31:M43) -> -326.13 | N44: =SUM(N31:N43) -> -263.09 | O44: =SUM(O31:O43) -> -718.5 | Q44: Repayment of other than short term borrowings | R44: -326.36 | S44: -526.68 | T44: -15.81 | U44: -66.97 | V44: 0 | W44: -331.94 | Y44: Deposits/loans given to associates, joint ventures and third parties | Z44: -115.21 | AA44: -151.59 | AB44: -148.03 | AC44: 0 | AD44: 0 | AE44: -448.54 | AG44: Bank balances other than cash and cash equivalents | AH44: -50.3121 | AI44: 320.24 | AJ44: -1497.5 | AK44: 1212.89 | AL44: -991.95 | AM44: 1251.2
A45: Payment for acquisition of subsidiaries | B45: -273.46 | C45: -13666.98 | D45: -21.1 | E45: -13222.17 | F45: -3101.73 | G45: -5399.91 | I45: Cash flow from Financing activities | Q45: Repayment of lease liabilities | R45: -31.6 | S45: -25.58 | T45: -27.15 | U45: -30.09 | V45: 0 | W45: =870.16-21.4-44.34-16.1 -> 788.32 | Y45: Deposits/loans repaid by associates, joint ventures and third parties | Z45: 17.69 | AA45: 0 | AB45: 0 | AC45: 19.05 | AD45: 151.72 | AE45: 318.77 | AG45: Net cash from Investing activities | AH45: =SUM(AH37:AH44) -> 126.1731 | AI45: =SUM(AI37:AI44) -> 312.48 | AJ45: =SUM(AJ37:AJ44) -> -1426.35 | AK45: =SUM(AK37:AK44) -> 1354.98 | AL45: =SUM(AL37:AL44) -> -1399.09 | AM45: =SUM(AM37:AM44) -> 1581.62
A46: Equity investment in joint venture entities/associates | B46: -191.15 | C46: 0 | D46: 0 | E46: -1206.9 | F46: -16.03 | G46: 0 | I46: Buyback of equity shares | J46: 0 | K46: -176.87 | L46: 8 | M46: 0 | N46: 0 | O46: 982.21 | Q46: Net increase/decrease in short term borrowigs | R46: 703.78 | S46: -226.35 | T46: 741.28 | U46: -47.98 | V46: =438.05-17.04-9.57 -> 411.44 | W46: -19.04 | Y46: Interest received | Z46: 837.54 | AA46: 1275.45 | AB46: 968.55 | AC46: 1608.99 | AD46: 2408.16 | AE46: 2083.51 | AG46: CASH FLOW FROM FINANCING ACTIVITIES
A47: Proceeds from sale of stake in associate/investments | B47: 0 | C47: 252.06 | D47: 1464.22 | E47: 1510 | F47: -114.19 | G47: 0 | I47: Proceeds from Current/non current borrowings | J47: 406.99 | K47: 484.94 | L47: 0 | M47: -93.6 | N47: 136.59 | O47: 487.01 | Q47: Finance costs paid | R47: -268.9 | S47: -355.08 | T47: -272.48 | U47: -534.43 | V47: -648.85 | W47: -632.83 | Y47: Dividend received from joint ventures/associates | Z47: 12.53 | AA47: 175.05 | AB47: 156.83 | AC47: 151.14 | AD47: 129.83 | AE47: 27.27 | AG47: Proceeds from Long term borrowings | AH47: 1407.96 | AI47: 1429.69 | AJ47: 700 | AK47: -279.95 | AL47: -377.29 | AM47: -472
A48: Proceeds from sale of investments | B48: 78.47 | C48: 72.4 | D48: 1.81 | E48: 0 | F48: -403.04 | G48: 0 | I48: Proceeds from issue of non-convertible debentures | J48: 100 | K48: 0 | L48: 479.97 | M48: 227.76 | N48: 600 | O48: 500 | Q48: Dividend paid | R48: -155.84 | S48: -0.5 | T48: -102.53 | U48: -102.85 | V48: -77.16 | W48: -102.79 | Y48: Dividend received on other investments | Z48: 101.6 | AA48: 28.47 | AB48: 4.12 | AC48: 6.28 | AD48: 96.25 | AE48: 117.05 | AG48: Repayment of short term borrowings | AH48: -262.65 | AI48: -265.74 | AJ48: -230.29 | AK48: -3.1 | AL48: -4.02 | AM48: 0
A49: Investment in preference share of Joint ventures | B49: -289.36 | C49: -23.77 | D49: 0 | E49: -256 | F49: 247.77 | G49: 248.54 | I49: Redemption of non-convertible debentures | J49: 0 | K49: -133.33 | L49: 200 | M49: 274 | N49: -225 | O49: -573 | Q49: Net cash flow from/used in Financing activities | R49: =SUM(R43:R48) -> 2.52 | S49: =SUM(S43:S48) -> -663.9 | T49: =SUM(T43:T48) -> 495.86 | U49: =SUM(U43:U48) -> -400.81 | V49: =SUM(V43:V48) -> -144.67 | W49: =SUM(W43:W48) -> -32.12 | Y49: Settlement of derivative contracts related to current investments | Z49: 13.19 | AA49: 0 | AB49: 0 | AC49: 0 | AD49: 0 | AE49: 52.54 | AG49: Repayment of interest | AH49: -271.6644 | AI49: -245.08 | AJ49: -213.59 | AK49: -309.12 | AL49: -441.52 | AM49: -550.19
A50: Loans given | B50: -37532.03 | C50: -41467.26 | D50: -40655.69 | E50: -19975.68 | F50: -2882.65 | G50: 2761.32 | I50: Repayment of current/non current borrowings | J50: -490.34 | K50: -226.25 | L50: -233.33 | M50: -278.32 | N50: -441.35 | O50: -403.35 | Q50: Net Increase/decrease in cash and cash equivalents | R50: =R33+R41+R49 -> -27.97 | S50: =S33+S41+S49 -> 53.26 | T50: =T33+T41+T49 -> 7.46 | U50: =U33+U41+U49 -> 70.72 | V50: =V33+V41+V49 -> -56.58 | W50: =W33+W41+W49 -> 319.09 | Y50: Consideration received on disposal of subsidiaries | Z50: 0 | AA50: 295.78 | AB50: 1005.73 | AC50: 2887.3 | AD50: 214.67 | AE50: 1065.37 | AG50: Payment of lease liabilities | AH50: -23.2008 | AI50: =-4.88-22.92 -> -27.8 | AJ50: =2.57-24.3 -> -21.73 | AK50: -22.68 | AL50: -19.8 | AM50: =-17.79-4.25 -> -22.04
A51: Loans received back | B51: 37794.62 | C51: 42499.03 | D51: 41066.75 | E51: 21365.98 | F51: 3305.05 | G51: -71.37 | I51: Net increase/decrease in short term borrowings | J51: 688.29 | K51: -236.8 | L51: -313.15 | M51: -608.19 | N51: 86.79 | O51: 184.61 | Q51: Opening balance | R51: 175.23 | S51: =R54 -> 152.68 | T51: =S54 -> 199.79 | U51: =T54 -> 207.63 | V51: =U54 -> 281.16 | W51: =V54 -> 205.11 | Y51: Net proceeds from transfer of discontinued operations | Z51: 0 | AA51: 11530.82 | AB51: -59.52 | AC51: -96.99 | AD51: 651.33 | AE51: 634.2 | AG51: Dividend paid | AH51: -23.3395 | AI51: -475.38 | AJ51: -421.17 | AK51: -433.47 | AL51: -443.93 | AM51: -439.94
A52: Proceed from fixed deposits including margin | B52: 1064.74 | C52: -370.38 | D52: 116.27 | E52: 0 | F52: -18.23 | G52: -255.43 | I52: Payment of lease liability | J52: -32.2 | K52: -44.49 | L52: 380.11 | M52: 696.8 | N52: 0 | O52: 0 | Q52: Acquisition of subsidiary | R52: 5.42 | S52: -6.15 | T52: 12.71 | U52: 0 | V52: 0 | W52: 0 | Y52: Consideration received on disposal of joint ventures | Z52: 43.16 | AA52: 0 | AB52: -87.85 | AC52: -131.22 | AD52: -13.14 | AE52: -1049.85 | AG52: Net cash from/used in Financing activities | AH52: =SUM(AH47:AH51) -> 827.1053 | AI52: =SUM(AI47:AI51) -> 415.69 | AJ52: =SUM(AJ47:AJ51) -> -186.78 | AK52: =SUM(AK47:AK51) -> -1048.32 | AL52: =SUM(AL47:AL51) -> -1286.56 | AM52: =SUM(AM47:AM51) -> -1484.17
A53: Investments made in pass through certificate | B53: 0 | C53: -926.02 | D53: -634.47 | E53: 0 | F53: 206.4 | G53: 327.49 | I53: Finance costs paid | J53: -504.15 | K53: -432.89 | L53: -53.02 | M53: -62.44 | N53: -63.6 | O53: -81.69 | Q53: Effect of exchange differences on restatement of foreign | R53: 0 | S53: 0 | T53: -12.33 | U53: 2.81 | V53: -19.47 | W53: 21.51 | Y53: Consideration paid on acquisition of subsidiaries | Z53: -9895.93 | AA53: -121.77 | AB53: 9.91 | AC53: 6.66 | AD53: 0.01 | AE53: 29.71 | AG53: Net increase/decrease in cash and cash equivalents | AH53: =AH35+AH45+AH52 -> -6.5979 | AI53: =AI35+AI45+AI52 -> 1147.6 | AJ53: =AJ35+AJ45+AJ52 -> 3187.02 | AK53: =AK35+AK45+AK52 -> -3757.31 | AL53: =AL35+AL45+AL52 -> 268.78 | AM53: =AM35+AM45+AM52 -> 2017.35
A54: Proceeds from sale/purchase of investments in mutual funds | B54: 58.05 | C54: -188.45 | D54: -3790.49 | E54: 607.7 | F54: 213.9 | G54: 255.76 | I54: Dividend paid including tax | J54: -120.78 | K54: -126.57 | L54: -405.35 | M54: -491.69 | N54: -503.76 | O54: -566.17 | Q54: Closing balance | R54: =SUM(R50:R53) -> 152.68 | S54: =SUM(S50:S53) -> 199.79 | T54: =SUM(T50:T53) -> 207.63 | U54: =SUM(U50:U53) -> 281.16 | V54: =SUM(V50:V53) -> 205.11 | W54: =SUM(W50:W53) -> 545.71 | Y54: Cash and cash equivalents acquired pursuant to acquisition of subsidiaries | Z54: 210.72 | AA54: 7.07 | AB54: -55.07 | AC54: -14.87 | AD54: -4.97 | AE54: 0 | AG54: Opening cash balances | AH54: 285.2337 | AI54: =AH56 -> 278.6358 | AJ54: =AI56 -> 1426.2358 | AK54: =AJ56 -> 4613.2558 | AL54: =AK56 -> 855.9458 | AM54: =AL56 -> 1123.3258
A55: Sale of investments in short term debentures and commercial papers | B55: 492 | C55: 0 | D55: =-446+286.35 -> -159.65 | E55: =-64.64+58.75 -> -5.89 | F55: 0 | G55: 0 | I55: Dividend paid to minority shareholders | J55: -7.52 | K55: -4.42 | L55: =-22.34-15.9 -> -38.24 | M55: =-96.77-5.43 -> -102.2 | N55: -113.71 | O55: -129.96 | Y55: Cash and cash equivalents as held for sale | Z55: -14.34 | AA55: 13.69 | AB55: 0 | AC55: 0 | AD55: 0 | AE55: -1096.56 | AG55: Effects of exchange | AH55: 0 | AI55: 0 | AJ55: 0 | AK55: 0 | AL55: -1.4 | AM55: -0.04
A56: Dividend received | B56: 8 | C56: 7.01 | D56: 4.01 | E56: 0.35 | F56: 0 | G56: 0 | I56: Cash generated/used in Financing activities | J56: =SUM(J46:J55) -> 40.29 | K56: =SUM(K46:K55) -> -896.68 | L56: =SUM(L46:L55) -> 24.99 | M56: =SUM(M46:M55) -> -437.88 | N56: =SUM(N46:N55) -> -524.04 | O56: =SUM(O46:O55) -> 399.66 | Y56: Consideration paid on acquisition of additional stake in a joint venture | Z56: -48 | AA56: 0 | AB56: 0 | AC56: 0 | AD56: 0 | AE56: 0 | AG56: Closing cash balance | AH56: =SUM(AH53:AH55) -> 278.6358 | AI56: =SUM(AI53:AI55) -> 1426.2358 | AJ56: =SUM(AJ53:AJ55) -> 4613.2558 | AK56: =SUM(AK53:AK55) -> 855.9458 | AL56: =SUM(AL53:AL55) -> 1123.3258 | AM56: =SUM(AM53:AM55) -> 3140.6358
A57: Interest received | B57: 1977.37 | C57: 2156.2 | D57: 1819.31 | E57: 1461 | F57: 969.16 | G57: 610.53 | I57: Effect of exchange rate changes on the balance of cash and cash equivalents | J57: -0.37 | K57: 0.74 | L57: 0 | M57: 3.37 | N57: -3.13 | O57: 0.14 | Y57: Net cash used in/from investing activities | Z57: =SUM(Z38:Z56) -> -8256.27 | AA57: =SUM(AA38:AA56) -> -5428.84 | AB57: =SUM(AB38:AB56) -> -3667.68 | AC57: =SUM(AC38:AC56) -> -8311.7 | AD57: =SUM(AD38:AD56) -> 2163.04 | AE57: =SUM(AE38:AE56) -> -15517.51
A58: Net cash from/used in investing activities | B58: =SUM(B41:B57) -> -750.42 | C58: =SUM(C41:C57) -> -14142.67 | D58: =SUM(D41:D57) -> -5281.82 | E58: =SUM(E41:E57) -> -19603.6 | F58: =SUM(F41:F57) -> -6946.55 | G58: =SUM(G41:G57) -> -9787.27 | I58: Net increase/decrease in cash and cash equivalents | J58: =J29+J44+J56+J57 -> 229.84 | K58: =K29+K44+K56+K57 -> 42.81 | L58: =L29+L44+L56+L57 -> 483.63 | M58: =M29+M44+M56+M57 -> -104.25 | N58: =N29+N44+N56+N57 -> 52.7 | O58: =O29+O44+O56+O57 -> 595.25 | Y58: CASH FLOW FROM FINANCING ACTIVITIES
A59: Cash flows from Financing activities | I59: Cash and cash equivalents acquired in business combination | J59: 36.77 | K59: 0 | L59: 40.6 | M59: 0 | N59: 0 | O59: 0 | Y59: Proceeds from issue of share capital | Z59: 17.56 | AA59: 15.85 | AB59: 10.97 | AC59: 10.31 | AD59: 9.65 | AE59: 9.32
A60: Proceeds from non-current borrowings | B60: 12199.12 | C60: 13893.45 | D60: 7244.31 | E60: 7445.87 | F60: 1929.75 | G60: 3913.34 | I60: Reduction in cash and cash eq on loss of control of subsidiary | J60: -1.84 | K60: -14.06 | L60: 0 | M60: 0 | N60: 0 | O60: 0 | Y60: Proceeds from non-current borrowings | Z60: 42587.43 | AA60: 35737.52 | AB60: 24654.13 | AC60: 27940.93 | AD60: 23125.43 | AE60: 38199.71
A61: Repayment of non-current borrowings | B61: -7063.39 | C61: -7252.6 | D61: -2293.1 | E61: -1710.69 | F61: -474.97 | G61: -50.46 | I61: Opening cash balance | J61: 244.01 | K61: =J62 -> 508.41 | L61: =K62 -> 537.9 | M61: =L62 -> 1062.13 | N61: =M62 -> 961.25 | O61: =N62 -> 1010.82 | Y61: Repayment of non-current borrowings | Z61: -33685.03 | AA61: -38318.78 | AB61: -35806.44 | AC61: -32794.99 | AD61: -24356.65 | AE61: -30782.41
A62: Proceeds from current borrowings | B62: 3649.5 | C62: 5100 | D62: 2576.38 | E62: -5389.83 | F62: -5583.81 | G62: -6723.48 | I62: Closing bank balance | J62: =SUM(J57:J61) -> 508.41 | K62: =SUM(K57:K61) -> 537.9 | L62: =SUM(L57:L61) -> 1062.13 | M62: =SUM(M57:M61) -> 961.25 | N62: =SUM(N57:N61) -> 1010.82 | O62: =SUM(O57:O61) -> 1606.21 | Y62: Proceeds from/repayment of other borrowings | Z62: 4915.2 | AA62: -6151.2 | AB62: 2739.13 | AC62: 357.4 | AD62: -10000 | AE62: 0
A63: Repayment of current borrowings | B63: -4608.59 | C63: -6350 | D63: -5426.88 | E63: -25.02 | F63: 235.16 | G63: 386.51 | Y63: Payment to/from non-controlling interest | Z63: -60.05 | AA63: 796.02 | AB63: -1019.59 | AC63: -612.58 | AD63: -2253.33 | AE63: 0
A64: Net movement in other current borrowings | B64: -3775.12 | C64: 100 | D64: 800 | E64: 0 | F64: 0 | G64: 0 | Y64: Settlement of derivative contracts related to borrowings | Z64: 308.29 | AA64: 66.73 | AB64: 143.82 | AC64: 87.93 | AD64: =-26.55+49.65-459.89 -> -436.79 | AE64: =50.24-562.3 -> -512.06
A65: Interest & Finance charges paid | B65: -1923.87 | C65: -1937.73 | D65: -2550.51 | E65: -2371 | F65: -2808.51 | G65: -2578.5 | Y65: Dividends paid | Z65: -3929.61 | AA65: -3650.89 | AB65: -2528.38 | AC65: -3091.42 | AD65: -4216.95 | AE65: -3849.57
A66: Repayment of lease liabilities | B66: -13.42 | C66: -18.1 | D66: -61.7 | E66: -53.01 | F66: -47.53 | G66: -281.7 | Y66: Additional tax on dividend | Z66: -621.72 | AA66: 0 | AB66: 0 | AC66: 0 | AD66: -2871.15 | AE66: 8297.3
A67: Payment on buy-back of equity shares | B67: -1960 | C67: 0 | D67: 109.25 | E67: 945.5 | F67: 29.48 | G67: -244.95 | Y67: Repayment of lease liability | Z67: -258.03 | AA67: -381.64 | AB67: -407.2 | AC67: -423.34 | AD67: -808.09 | AE67: -1196.18
A68: Transaction costs for buy back of equity shares | B68: -10.72 | C68: 0 | D68: 43.13 | E68: -482.71 | F68: 0 | G68: 0 | Y68: Interest paid on lease liability | Z68: -162.79 | AA68: -203.57 | AB68: -155.59 | AC68: -158.1 | AD68: -167.21 | AE68: -193.84
A69: Payment on redemption of preference shares | B69: -12.4 | C69: 0 | D69: 0 | E69: 0 | F69: 0 | G69: 0 | Y69: Interest paid on lease liability | Z69: -2739.7 | AA69: -3184.42 | AB69: -2812.33 | AC69: -2888.63 | AD69: -3438.27 | AE69: -3415.65
A70: Loss/gain on settlement of derivative contracts | B70: 107.88 | C70: -20.94 | D70: 0 | E70: 0 | F70: 0 | G70: 0 | Y70: Net cash used in/from financing activities | Z70: =SUM(Z59:Z69) -> 6371.55 | AA70: =SUM(AA59:AA69) -> -15274.38 | AB70: =SUM(AB59:AB69) -> -15181.48 | AC70: =SUM(AC59:AC69) -> -11572.49 | AD70: =SUM(AD59:AD69) -> -25413.36 | AE70: =SUM(AE59:AE69) -> 6556.62
A71: Payment of dividend on equity and preference shares | B71: -699.93 | C71: -0.23 | D71: -1026.65 | E71: -1092.91 | F71: -1079.68 | G71: -1336.28 | Y71: Net decrease/increase in cash and cash equivalents | Z71: =Z36+Z57+Z70 -> 4809.16 | AA71: =AA36+AA57+AA70 -> 2140.92 | AB71: =AB36+AB57+AB70 -> 314.41 | AC71: =AC36+AC57+AC70 -> 2892.77 | AD71: =AD36+AD57+AD70 -> -4984.04 | AE71: =AE36+AE57+AE70 -> 199.82
A72: Payment of dividend distribution tax | B72: -144.69 | C72: 0 | D72: 0 | E72: 0 | F72: 0 | G72: 0 | Y72: Opening cash balance | Z72: 6460.23 | AA72: =Z74 -> 11117.95 | AB72: =AA74 -> 13257.01 | AC72: =AB74 -> 13653.72 | AD72: =AC74 -> 16810.17 | AE72: =AD74 -> 11841.98
A73: Net cash generated from/used in Financing activities | B73: =SUM(B60:B72) -> -4255.63 | C73: =SUM(C60:C72) -> 3513.85 | D73: =SUM(D60:D72) -> -585.77 | E73: =SUM(E60:E72) -> -2733.8 | F73: =SUM(F60:F72) -> -7800.11 | G73: =SUM(G60:G72) -> -6915.52 | Y73: Cash and cash equivalents for discontinued operations | Z73: -151.44 | AA73: -1.86 | AB73: 82.3 | AC73: 263.68 | AD73: 15.85 | AE73: 28.68
A74: Net increase/decrease in Cash and cash equivalents | B74: =B39+B58+B73 -> 2395.76 | C74: =C39+C58+C73 -> -3073.04 | D74: =D39+D58+D73 -> 4552.55 | E74: =E39+E58+E73 -> -10404.15 | F74: =F39+F58+F73 -> 270.92 | G74: =G39+G58+G73 -> 523.49 | Y74: Closing cash balance | Z74: =SUM(Z71:Z73) -> 11117.95 | AA74: =SUM(AA71:AA73) -> 13257.01 | AB74: =SUM(AB71:AB73) -> 13653.72 | AC74: =SUM(AC71:AC73) -> 16810.17 | AD74: =SUM(AD71:AD73) -> 11841.98 | AE74: =SUM(AE71:AE73) -> 12070.48
A75: Cash and cash equivalents at the beginning of the year | B75: 4798.19 | C75: =B78 -> 7195.46 | D75: =C78 -> 4200.97 | E75: =D78 -> 8542.21 | F75: =E78 -> 802.86 | G75: =F78 -> 1252.77
A76: Cash and cash equivalents on acquisition of subsidiaries | B76: 2.63 | C76: 78.55 | D76: 22.14 | E76: 2878.31 | F76: 178.99 | G76: 1307.36
A77: Reduction in cash and cash equivalents on account of loss of control of subsidiaries | B77: -1.12 | C77: 0 | D77: =-56-177.45 -> -233.45 | E77: -213.51 | F77: 0 | G77: -0.26
A78: Cash and cash equivalents at the end of the year | B78: =SUM(B74:B77) -> 7195.46 | C78: =SUM(C74:C77) -> 4200.97 | D78: =SUM(D74:D77) -> 8542.21 | E78: =SUM(E74:E77) -> 802.86 | F78: =SUM(F74:F77) -> 1252.77 | G78: =SUM(G74:G77) -> 3083.36

Sheet Ratio Analysis
A1: Ratio Analysis
E2: #VALUE! | M2: #VALUE! | U2: #VALUE! | AC2: #VALUE! | AK2: #VALUE!
A3: Ratio | B3: 2020 | C3: 2021 | D3: 2022 | E3: 2023 | F3: 2024 | G3: 2025 | I3: Ratio | J3: 2020 | K3: 2021 | L3: 2022 | M3: 2023 | N3: 2024 | O3: 2025 | Q3: Ratio | R3: 2020 | S3: 2021 | T3: 2022 | U3: 2023 | V3: 2024 | W3: 2025 | Y3: Ratio | Z3: 2020 | AA3: 2021 | AB3: 2022 | AC3: 2023 | AD3: 2024 | AE3: 2025 | AG3: Ratio | AH3: 2020 | AI3: 2021 | AJ3: 2022 | AK3: 2023 | AL3: 2024 | AM3: 2025
A4: Profitability | I4: Profitability | Q4: Profitability | Y4: Profitability | AG4: Profitability
A5: Gross Profit margin | B5: =('Income Statement'!B8-'Income Statement'!B10)/'Income Statement'!B8 -> 0.7744892 | C5: =('Income Statement'!C8-'Income Statement'!C10)/'Income Statement'!C8 -> 0.77551459 | D5: =('Income Statement'!D8-'Income Statement'!D10)/'Income Statement'!D8 -> 0.74847577 | E5: =('Income Statement'!E8-'Income Statement'!E10)/'Income Statement'!E8 -> 0.74762501 | F5: =('Income Statement'!F8-'Income Statement'!F10)/'Income Statement'!F8 -> 0.74773679 | G5: =('Income Statement'!G8-'Income Statement'!G10)/'Income Statement'!G8 -> 0.75080351 | I5: Gross Profit margin | J5: =('Income Statement'!J7-('Income Statement'!J9+'Income Statement'!J10))/'Income Statement'!J7 -> 0.58586952 | K5: =('Income Statement'!K7-('Income Statement'!K9+'Income Statement'!K10))/'Income Statement'!K7 -> 0.63439291 | L5: =('Income Statement'!L7-('Income Statement'!L9+'Income Statement'!L10))/'Income Statement'!L7 -> 0.56640186 | M5: =('Income Statement'!M7-('Income Statement'!M9+'Income Statement'!M10))/'Income Statement'!M7 -> 0.57501064 | N5: =('Income Statement'!N7-('Income Statement'!N9+'Income Statement'!N10))/'Income Statement'!N7 -> 0.58329482 | O5: =('Income Statement'!O7-('Income Statement'!O9+'Income Statement'!O10))/'Income Statement'!O7 -> 0.61655687 | Q5: Gross Profit margin | R5: =('Income Statement'!R7-('Income Statement'!R9+'Income Statement'!R10))/'Income Statement'!R7 -> 0.53311869 | S5: =('Income Statement'!S7-('Income Statement'!S9+'Income Statement'!S10))/'Income Statement'!S7 -> 0.56630037 | T5: =('Income Statement'!T7-('Income Statement'!T9+'Income Statement'!T10))/'Income Statement'!T7 -> 0.56752297 | U5: =('Income Statement'!U7-('Income Statement'!U9+'Income Statement'!U10))/'Income Statement'!U7 -> 0.59171791 | V5: =('Income Statement'!V7-('Income Statement'!V9+'Income Statement'!V10))/'Income Statement'!V7 -> 0.57889684 | W5: =('Income Statement'!W7-('Income Statement'!W9+'Income Statement'!W10))/'Income Statement'!W7 -> 0.54015547 | Y5: Gross Profit margin | Z5: =('Income Statement'!Z8-('Income Statement'!Z11+'Income Statement'!Z12+'Income Statement'!Z13+'Income Statement'!Z14+'Income Statement'!Z16+'Income Statement'!Z17))/'Income Statement'!Z8 -> 0.57468809 | AA5: =('Income Statement'!AA8-('Income Statement'!AA11+'Income Statement'!AA12+'Income Statement'!AA13+'Income Statement'!AA14+'Income Statement'!AA16+'Income Statement'!AA17))/'Income Statement'!AA8 -> 0.5933266 | AB5: =('Income Statement'!AB8-('Income Statement'!AB11+'Income Statement'!AB12+'Income Statement'!AB13+'Income Statement'!AB14+'Income Statement'!AB16+'Income Statement'!AB17))/'Income Statement'!AB8 -> 0.56443853 | AC5: =('Income Statement'!AC8-('Income Statement'!AC11+'Income Statement'!AC12+'Income Statement'!AC13+'Income Statement'!AC14+'Income Statement'!AC16+'Income Statement'!AC17))/'Income Statement'!AC8 -> 0.54386407 | AD5: =('Income Statement'!AD8-('Income Statement'!AD11+'Income Statement'!AD12+'Income Statement'!AD13+'Income Statement'!AD14+'Income Statement'!AD16+'Income Statement'!AD17))/'Income Statement'!AD8 -> 0.53274235 | AE5: =('Income Statement'!AE8-('Income Statement'!AE11+'Income Statement'!AE12+'Income Statement'!AE13+'Income Statement'!AE14+'Income Statement'!AE16+'Income Statement'!AE17))/'Income Statement'!AE8 -> 0.52243478 | AG5: Gross Profit margin | AH5: =('Income Statement'!AH7-'Income Statement'!AH9)/'Income Statement'!AH7 -> 0.098438111 | AI5: =('Income Statement'!AI7-'Income Statement'!AI9)/'Income Statement'!AI7 -> 0.092069618 | AJ5: =('Income Statement'!AJ7-'Income Statement'!AJ9)/'Income Statement'!AJ7 -> 0.11853719 | AK5: =('Income Statement'!AK7-'Income Statement'!AK9)/'Income Statement'!AK7 -> 0.11290342 | AL5: =('Income Statement'!AL7-'Income Statement'!AL9)/'Income Statement'!AL7 -> 0.12021519 | AM5: =('Income Statement'!AM7-'Income Statement'!AM9)/'Income Statement'!AM7 -> 0.12537227
A6: EBITDA margin | B6: =('Income Statement'!B20+'Income Statement'!B16+'Income Statement'!B15)/'Income Statement'!B8 -> 0.56794244 | C6: =('Income Statement'!C20+'Income Statement'!C16+'Income Statement'!C15)/'Income Statement'!C8 -> 0.73478202 | D6: =('Income Statement'!D20+'Income Statement'!D16+'Income Statement'!D15)/'Income Statement'!D8 -> 0.60737515 | E6: =('Income Statement'!E20+'Income Statement'!E16+'Income Statement'!E15)/'Income Statement'!E8 -> 0.55792869 | F6: =('Income Statement'!F20+'Income Statement'!F16+'Income Statement'!F15)/'Income Statement'!F8 -> 0.61150416 | G6: =('Income Statement'!G20+'Income Statement'!G16+'Income Statement'!G15)/'Income Statement'!G8 -> 0.61909707 | I6: EBITDA margin | J6: =('Income Statement'!J18+'Income Statement'!J14+'Income Statement'!J13)/'Income Statement'!J7 -> 0.12009076 | K6: =('Income Statement'!K18+'Income Statement'!K14+'Income Statement'!K13)/'Income Statement'!K7 -> 0.12115429 | L6: =('Income Statement'!L18+'Income Statement'!L14+'Income Statement'!L13)/'Income Statement'!L7 -> 0.085998534 | M6: =('Income Statement'!M18+'Income Statement'!M14+'Income Statement'!M13)/'Income Statement'!M7 -> 0.085923296 | N6: =('Income Statement'!N18+'Income Statement'!N14+'Income Statement'!N13)/'Income Statement'!N7 -> 0.085958552 | O6: =('Income Statement'!O18+'Income Statement'!O14+'Income Statement'!O13)/'Income Statement'!O7 -> 0.084751898 | Q6: EBITDA margin | R6: =('Income Statement'!R17+'Income Statement'!R12+'Income Statement'!R14)/'Income Statement'!R7 -> 0.10399141 | S6: =('Income Statement'!S17+'Income Statement'!S12+'Income Statement'!S14)/'Income Statement'!S7 -> 0.089099156 | T6: =('Income Statement'!T17+'Income Statement'!T12+'Income Statement'!T14)/'Income Statement'!T7 -> 0.066658234 | U6: =('Income Statement'!U17+'Income Statement'!U12+'Income Statement'!U14)/'Income Statement'!U7 -> 0.049734218 | V6: =('Income Statement'!V17+'Income Statement'!V12+'Income Statement'!V14)/'Income Statement'!V7 -> 0.063455033 | W6: =('Income Statement'!W17+'Income Statement'!W12+'Income Statement'!W14)/'Income Statement'!W7 -> 0.071849239 | Y6: EBITDA margin | Z6: =('Income Statement'!Z24+'Income Statement'!Z21+'Income Statement'!Z22)/'Income Statement'!Z8 -> 0.12644251 | AA6: =('Income Statement'!AA24+'Income Statement'!AA21+'Income Statement'!AA22)/'Income Statement'!AA8 -> 0.13667363 | AB6: =('Income Statement'!AB24+'Income Statement'!AB21+'Income Statement'!AB22)/'Income Statement'!AB8 -> 0.12892442 | AC6: =('Income Statement'!AC24+'Income Statement'!AC21+'Income Statement'!AC22)/'Income Statement'!AC8 -> 0.12714053 | AD6: =('Income Statement'!AD24+'Income Statement'!AD21+'Income Statement'!AD22)/'Income Statement'!AD8 -> 0.12274854 | AE6: =('Income Statement'!AE24+'Income Statement'!AE21+'Income Statement'!AE22)/'Income Statement'!AE8 -> 0.11760042 | AG6: EBITDA margin | AH6: =('Income Statement'!AH16+'Income Statement'!AH11+'Income Statement'!AH12)/'Income Statement'!AH7 -> 0.076148978 | AI6: =('Income Statement'!AI16+'Income Statement'!AI11+'Income Statement'!AI12)/'Income Statement'!AI7 -> 0.069853184 | AJ6: =('Income Statement'!AJ16+'Income Statement'!AJ11+'Income Statement'!AJ12)/'Income Statement'!AJ7 -> 0.10029456 | AK6: =('Income Statement'!AK16+'Income Statement'!AK11+'Income Statement'!AK12)/'Income Statement'!AK7 -> 0.098269542 | AL6: =('Income Statement'!AL16+'Income Statement'!AL11+'Income Statement'!AL12)/'Income Statement'!AL7 -> 0.10540741 | AM6: =('Income Statement'!AM16+'Income Statement'!AM11+'Income Statement'!AM12)/'Income Statement'!AM7 -> 0.11000745
A7: Net profit margin | B7: ='Income Statement'!B30/'Income Statement'!B8 -> 0.27555077 | C7: ='Income Statement'!C30/'Income Statement'!C8 -> 0.34771344 | D7: ='Income Statement'!D30/'Income Statement'!D8 -> 0.25607742 | E7: ='Income Statement'!E30/'Income Statement'!E8 -> 0.24068985 | F7: ='Income Statement'!F30/'Income Statement'!F8 -> 0.28727387 | G7: ='Income Statement'!G30/'Income Statement'!G8 -> 0.34157529 | I7: Net profit margin | J7: ='Income Statement'!J27/Table7[[#This Row],[2020]] -> 0.030628434 | K7: ='Income Statement'!K27/Table7[[#This Row],[2021]] -> 0.050861755 | L7: ='Income Statement'!L27/Table7[[#This Row],[2022]] -> 0.035991471 | M7: ='Income Statement'!M27/Table7[[#This Row],[2023]] -> 0.026523766 | N7: ='Income Statement'!N27/Table7[[#This Row],[2024]] -> 0.026200558 | O7: ='Income Statement'!O27/Table7[[#This Row],[2025]] -> 0.025349156 | Q7: Net profit margin | R7: ='Income Statement'!R24/Table8[[#This Row],[2020]] -> 0.047219256 | S7: ='Income Statement'!S24/Table8[[#This Row],[2021]] -> 0.042050742 | T7: ='Income Statement'!T24/Table8[[#This Row],[2022]] -> 0.027313788 | U7: ='Income Statement'!U24/Table8[[#This Row],[2023]] -> 0.010167487 | V7: ='Income Statement'!V24/Table8[[#This Row],[2024]] -> 0.017368022 | W7: ='Income Statement'!W24/Table8[[#This Row],[2025]] -> 0.026040307 | Y7: Net profit margin | Z7: ='Income Statement'!Z42/'Income Statement'!Z8 -> 0.073702995 | AA7: ='Income Statement'!AA42/'Income Statement'!AA8 -> 0.092686537 | AB7: ='Income Statement'!AB42/'Income Statement'!AB8 -> 0.065617173 | AC7: ='Income Statement'!AC42/'Income Statement'!AC8 -> 0.06727132 | AD7: ='Income Statement'!AD42/'Income Statement'!AD8 -> 0.069015116 | AE7: ='Income Statement'!AE42/'Income Statement'!AE8 -> 0.068011159 | AG7: Net profit margin | AH7: ='Income Statement'!AH25/Table10[[#This Row],[2020]] -> 0.066616487 | AI7: ='Income Statement'!AI25/Table10[[#This Row],[2021]] -> 0.050981946 | AJ7: ='Income Statement'!AJ25/Table10[[#This Row],[2022]] -> 0.061424337 | AK7: ='Income Statement'!AK25/Table10[[#This Row],[2023]] -> 0.058601403 | AL7: ='Income Statement'!AL25/Table10[[#This Row],[2024]] -> 0.063058059 | AM7: ='Income Statement'!AM25/Table10[[#This Row],[2025]] -> 0.068233311
A8: Return on Equity | B8: ='Income Statement'!B30/'Balance Sheet'!B43 -> 0.14644268 | C8: ='Income Statement'!C30/(AVERAGE('Balance Sheet'!B43:C43)) -> 0.17427534 | D8: ='Income Statement'!D30/(AVERAGE('Balance Sheet'!C43:D43)) -> 0.13301105 | E8: ='Income Statement'!E30/(AVERAGE('Balance Sheet'!D43:E43)) -> 0.12077411 | F8: ='Income Statement'!F30/(AVERAGE('Balance Sheet'!E43:F43)) -> 0.15973947 | G8: ='Income Statement'!G30/(AVERAGE('Balance Sheet'!F43:G43)) -> 0.18510038 | I8: Return on Equity | J8: ='Income Statement'!J27/'Balance Sheet'!J40 -> 0.11146525 | K8: ='Income Statement'!K27/(AVERAGE('Balance Sheet'!J40:K40)) -> 0.18004626 | L8: ='Income Statement'!L27/(AVERAGE('Balance Sheet'!K40:L40)) -> 0.12929761 | M8: ='Income Statement'!M27/(AVERAGE('Balance Sheet'!L40:M40)) -> 0.095489901 | N8: ='Income Statement'!N27/(AVERAGE('Balance Sheet'!M40:N40)) -> 0.1052141 | O8: ='Income Statement'!O27/(AVERAGE('Balance Sheet'!N40:O40)) -> 0.097959966 | Q8: Return on Equity | R8: ='Income Statement'!R24/'Balance Sheet'!R36 -> 0.20214614 | S8: ='Income Statement'!S24/AVERAGE('Balance Sheet'!R36:S36) -> 0.17953411 | T8: ='Income Statement'!T24/AVERAGE('Balance Sheet'!S36:T36) -> 0.10766202 | U8: ='Income Statement'!U24/AVERAGE('Balance Sheet'!T36:U36) -> 0.047631353 | V8: ='Income Statement'!V24/AVERAGE('Balance Sheet'!U36:V36) -> 0.088159326 | W8: ='Income Statement'!W24/AVERAGE('Balance Sheet'!V36:W36) -> 0.12087916 | Y8: Return on Equity | Z8: ='Income Statement'!Z42/'Balance Sheet'!Z37 -> 0.20880128 | AA8: ='Income Statement'!AA42/AVERAGE('Balance Sheet'!Z37:AA37) -> 0.22953028 | AB8: ='Income Statement'!AB42/AVERAGE('Balance Sheet'!AA37:AB37) -> 0.13376241 | AC8: ='Income Statement'!AC42/AVERAGE('Balance Sheet'!AB37:AC37) -> 0.12597326 | AD8: ='Income Statement'!AD42/AVERAGE('Balance Sheet'!AC37:AD37) -> 0.15085713 | AE8: ='Income Statement'!AE42/AVERAGE('Balance Sheet'!AD37:AE37) -> 0.16217535 | AG8: Return on Equity | AH8: ='Income Statement'!AH25/'Balance Sheet'!AH36 -> 0.13443257 | AI8: ='Income Statement'!AI25/AVERAGE('Balance Sheet'!AH36:AI36) -> 0.14012726 | AJ8: ='Income Statement'!AJ25/AVERAGE('Balance Sheet'!AI36:AJ36) -> 0.16480187 | AK8: ='Income Statement'!AK25/AVERAGE('Balance Sheet'!AJ36:AK36) -> 0.1733692 | AL8: ='Income Statement'!AL25/AVERAGE('Balance Sheet'!AK36:AL36) -> 0.16780213 | AM8: ='Income Statement'!AM25/AVERAGE('Balance Sheet'!AL36:AM36) -> 0.18129061
A9: Return on capital employed | B9: =('Income Statement'!B20+'Income Statement'!B15)/('Balance Sheet'!B36-'Balance Sheet'!B64) -> 0.11228021 | C9: =('Income Statement'!C20+'Income Statement'!C15)/('Balance Sheet'!C36-'Balance Sheet'!C64) -> 0.12549505 | D9: =('Income Statement'!D20+'Income Statement'!D15)/('Balance Sheet'!D36-'Balance Sheet'!D64) -> 0.09759218 | E9: =('Income Statement'!E20+'Income Statement'!E15)/('Balance Sheet'!E36-'Balance Sheet'!E64) -> 0.087702338 | F9: =('Income Statement'!F20+'Income Statement'!F15)/('Balance Sheet'!F36-'Balance Sheet'!F64) -> 0.13035841 | G9: =('Income Statement'!G20+'Income Statement'!G15)/('Balance Sheet'!G36-'Balance Sheet'!G64) -> 0.13697719 | I9: Return on capital employed | J9: =('Income Statement'!J18+'Income Statement'!J13)/('Balance Sheet'!J33-'Balance Sheet'!J63) -> 0.15953211 | K9: =('Income Statement'!K18+'Income Statement'!K13)/('Balance Sheet'!K33-'Balance Sheet'!K63) -> 0.17167085 | L9: =('Income Statement'!L18+'Income Statement'!L13)/('Balance Sheet'!L33-'Balance Sheet'!L63) -> 0.12083077 | M9: =('Income Statement'!M18+'Income Statement'!M13)/('Balance Sheet'!M33-'Balance Sheet'!M63) -> 0.13665838 | N9: =('Income Statement'!N18+'Income Statement'!N13)/('Balance Sheet'!N33-'Balance Sheet'!N63) -> 0.1591836 | O9: =('Income Statement'!O18+'Income Statement'!O13)/('Balance Sheet'!O33-'Balance Sheet'!O63) -> 0.1559832 | Q9: Return on capital employed | R9: =('Income Statement'!R17+'Income Statement'!R12)/('Balance Sheet'!R31-'Balance Sheet'!R57) -> 0.34828924 | S9: =('Income Statement'!S17+'Income Statement'!S12)/('Balance Sheet'!S31-'Balance Sheet'!S57) -> 0.27086535 | T9: =('Income Statement'!T17+'Income Statement'!T12)/('Balance Sheet'!T31-'Balance Sheet'!T57) -> 0.17908339 | U9: =('Income Statement'!U17+'Income Statement'!U12)/('Balance Sheet'!U31-'Balance Sheet'!U57) -> 0.15687079 | V9: =('Income Statement'!V17+'Income Statement'!V12)/('Balance Sheet'!V31-'Balance Sheet'!V57) -> 0.24047917 | W9: =('Income Statement'!W17+'Income Statement'!W12)/('Balance Sheet'!W31-'Balance Sheet'!W57) -> 0.23367557 | Y9: Return on capital employed | Z9: =('Income Statement'!Z24+'Income Statement'!Z21)/('Balance Sheet'!Z31-'Balance Sheet'!Z59) -> 0.26966775 | AA9: =('Income Statement'!AA24+'Income Statement'!AA21)/('Balance Sheet'!AA31-'Balance Sheet'!AA59) -> 0.20955787 | AB9: =('Income Statement'!AB24+'Income Statement'!AB21)/('Balance Sheet'!AB31-'Balance Sheet'!AB59) -> 0.10909609 | AC9: =('Income Statement'!AC24+'Income Statement'!AC21)/('Balance Sheet'!AC31-'Balance Sheet'!AC59) -> 0.11991587 | AD9: =('Income Statement'!AD24+'Income Statement'!AD21)/('Balance Sheet'!AD31-'Balance Sheet'!AD59) -> 0.14702731 | AE9: =('Income Statement'!AE24+'Income Statement'!AE21)/('Balance Sheet'!AE31-'Balance Sheet'!AE59) -> 0.14890399 | AG9: Return on capital employed | AH9: =('Income Statement'!AH16+'Income Statement'!AH11)/('Balance Sheet'!AH31-'Balance Sheet'!AH55) -> 0.080504549 | AI9: =('Income Statement'!AI16+'Income Statement'!AI11)/('Balance Sheet'!AI31-'Balance Sheet'!AI55) -> 0.086393764 | AJ9: =('Income Statement'!AJ16+'Income Statement'!AJ11)/('Balance Sheet'!AJ31-'Balance Sheet'!AJ55) -> 0.12244693 | AK9: =('Income Statement'!AK16+'Income Statement'!AK11)/('Balance Sheet'!AK31-'Balance Sheet'!AK55) -> 0.14116388 | AL9: =('Income Statement'!AL16+'Income Statement'!AL11)/('Balance Sheet'!AL31-'Balance Sheet'!AL55) -> 0.14771428 | AM9: =('Income Statement'!AM16+'Income Statement'!AM11)/('Balance Sheet'!AM31-'Balance Sheet'!AM55) -> 0.18142261
A10: Liquidity | I10: Liquidity | Q10: Liquidity | Y10: Liquidity | AG10: Liquidity
A11: Current Ratio | B11: ='Balance Sheet'!B34/'Balance Sheet'!B64 -> 1.9255464 | C11: ='Balance Sheet'!C34/'Balance Sheet'!C64 -> 1.7568032 | D11: ='Balance Sheet'!D34/'Balance Sheet'!D64 -> 1.463385 | E11: ='Balance Sheet'!E34/'Balance Sheet'!E64 -> 1.3598285 | F11: ='Balance Sheet'!F34/'Balance Sheet'!F64 -> 1.0530124 | G11: ='Balance Sheet'!G34/'Balance Sheet'!G64 -> 0.89583417 | I11: Current Ratio | J11: ='Balance Sheet'!J31/'Balance Sheet'!J63 -> 1.2591708 | K11: ='Balance Sheet'!K31/'Balance Sheet'!K63 -> 1.3119554 | L11: ='Balance Sheet'!L31/'Balance Sheet'!L63 -> 1.3003053 | M11: ='Balance Sheet'!M31/'Balance Sheet'!M63 -> 1.2136947 | N11: ='Balance Sheet'!N31/'Balance Sheet'!N63 -> 1.2004543 | O11: ='Balance Sheet'!O31/'Balance Sheet'!O63 -> 1.2331593 | Q11: Current Ratio | R11: ='Balance Sheet'!R30/'Balance Sheet'!R57 -> 1.133433 | S11: ='Balance Sheet'!S30/'Balance Sheet'!S57 -> 1.1551489 | T11: ='Balance Sheet'!T30/'Balance Sheet'!T57 -> 1.1310942 | U11: ='Balance Sheet'!U30/'Balance Sheet'!U57 -> 1.1137693 | V11: ='Balance Sheet'!V30/'Balance Sheet'!V57 -> 1.1117506 | W11: ='Balance Sheet'!W30/'Balance Sheet'!W57 -> 1.1947238 | Y11: Current Ratio | Z11: ='Balance Sheet'!Z30/'Balance Sheet'!Z59 -> 1.1751632 | AA11: ='Balance Sheet'!AA30/'Balance Sheet'!AA59 -> 1.4618847 | AB11: ='Balance Sheet'!AB30/'Balance Sheet'!AB59 -> 1.3058349 | AC11: ='Balance Sheet'!AC30/'Balance Sheet'!AC59 -> 1.3710731 | AD11: ='Balance Sheet'!AD30/'Balance Sheet'!AD59 -> 1.2342006 | AE11: ='Balance Sheet'!AE30/'Balance Sheet'!AE59 -> 1.2147379 | AG11: Current Ratio | AH11: ='Balance Sheet'!AH30/'Balance Sheet'!AH55 -> 3.1582862 | AI11: ='Balance Sheet'!AI30/'Balance Sheet'!AI55 -> 3.9799974 | AJ11: ='Balance Sheet'!AJ30/'Balance Sheet'!AJ55 -> 2.1152832 | AK11: ='Balance Sheet'!AK30/'Balance Sheet'!AK55 -> 2.0360878 | AL11: ='Balance Sheet'!AL30/'Balance Sheet'!AL55 -> 2.1282177 | AM11: ='Balance Sheet'!AM30/'Balance Sheet'!AM55 -> 2.0456288
A12: Quick ratio | B12: =('Balance Sheet'!B34-'Balance Sheet'!B24)/'Balance Sheet'!B64 -> 1.8880903 | C12: =('Balance Sheet'!C34-'Balance Sheet'!C24)/'Balance Sheet'!C64 -> 1.6171338 | D12: =('Balance Sheet'!D34-'Balance Sheet'!D24)/'Balance Sheet'!D64 -> 1.4276236 | E12: =('Balance Sheet'!E34-'Balance Sheet'!E24)/'Balance Sheet'!E64 -> 1.3201928 | F12: =('Balance Sheet'!F34-'Balance Sheet'!F24)/'Balance Sheet'!F64 -> 1.02636 | G12: =('Balance Sheet'!G34-'Balance Sheet'!G24)/'Balance Sheet'!G64 -> 0.8709135 | I12: Quick ratio | J12: =('Balance Sheet'!J31-'Balance Sheet'!J22)/'Balance Sheet'!J63 -> 1.114139 | K12: =('Balance Sheet'!K31-'Balance Sheet'!K22)/'Balance Sheet'!K63 -> 1.1835706 | L12: =('Balance Sheet'!L31-'Balance Sheet'!L22)/'Balance Sheet'!L63 -> 1.1853431 | M12: =('Balance Sheet'!M31-'Balance Sheet'!M22)/'Balance Sheet'!M63 -> 1.112464 | N12: =('Balance Sheet'!N31-'Balance Sheet'!N22)/'Balance Sheet'!N63 -> 1.1063284 | O12: =('Balance Sheet'!O31-'Balance Sheet'!O22)/'Balance Sheet'!O63 -> 1.1471571 | Q12: Quick ratio | R12: =('Balance Sheet'!R30-'Balance Sheet'!R20)/'Balance Sheet'!R57 -> 1.0536464 | S12: =('Balance Sheet'!S30-'Balance Sheet'!S20)/'Balance Sheet'!S57 -> 1.0732818 | T12: =('Balance Sheet'!T30-'Balance Sheet'!T20)/'Balance Sheet'!T57 -> 1.0429781 | U12: =('Balance Sheet'!U30-'Balance Sheet'!U20)/'Balance Sheet'!U57 -> 1.0337384 | V12: =('Balance Sheet'!V30-'Balance Sheet'!V20)/'Balance Sheet'!V57 -> 1.0282681 | W12: =('Balance Sheet'!W30-'Balance Sheet'!W20)/'Balance Sheet'!W57 -> 1.1244417 | Y12: Quick ratio | Z12: =('Balance Sheet'!Z30-'Balance Sheet'!Z21)/'Balance Sheet'!Z59 -> 1.1411267 | AA12: =('Balance Sheet'!AA30-'Balance Sheet'!AA21)/'Balance Sheet'!AA59 -> 1.4215603 | AB12: =('Balance Sheet'!AB30-'Balance Sheet'!AB21)/'Balance Sheet'!AB59 -> 1.2685589 | AC12: =('Balance Sheet'!AC30-'Balance Sheet'!AC21)/'Balance Sheet'!AC59 -> 1.3289373 | AD12: =('Balance Sheet'!AD30-'Balance Sheet'!AD21)/'Balance Sheet'!AD59 -> 1.1968215 | AE12: =('Balance Sheet'!AE30-'Balance Sheet'!AE21)/'Balance Sheet'!AE59 -> 1.1767594 | AG12: Quick ratio | AH12: =('Balance Sheet'!AH30-'Balance Sheet'!AH20)/'Balance Sheet'!AH55 -> 3.1548819 | AI12: =('Balance Sheet'!AI30-'Balance Sheet'!AI20)/'Balance Sheet'!AI55 -> 3.9706338 | AJ12: =('Balance Sheet'!AJ30-'Balance Sheet'!AJ20)/'Balance Sheet'!AJ55 -> 2.1079926 | AK12: =('Balance Sheet'!AK30-'Balance Sheet'!AK20)/'Balance Sheet'!AK55 -> 2.0228227 | AL12: =('Balance Sheet'!AL30-'Balance Sheet'!AL20)/'Balance Sheet'!AL55 -> 2.1140846 | AM12: =('Balance Sheet'!AM30-'Balance Sheet'!AM20)/'Balance Sheet'!AM55 -> 2.0456288
A13: Leverage | I13: Leverage | Q13: Leverage | Y13: Leverage | AG13: Leverage
A14: Debt-to-Equity | B14: =('Balance Sheet'!B46+'Balance Sheet'!B54)/'Balance Sheet'!B43 -> 1.0728385 | C14: =('Balance Sheet'!C46+'Balance Sheet'!C54)/'Balance Sheet'!C43 -> 1.0385958 | D14: =('Balance Sheet'!D46+'Balance Sheet'!D54)/'Balance Sheet'!D43 -> 1.0724865 | E14: =('Balance Sheet'!E46+'Balance Sheet'!E54)/'Balance Sheet'!E43 -> 1.0617453 | F14: =('Balance Sheet'!F46+'Balance Sheet'!F54)/'Balance Sheet'!F43 -> 0.84849073 | G14: =('Balance Sheet'!G46+'Balance Sheet'!G54)/'Balance Sheet'!G43 -> 0.70505887 | I14: Debt-to-Equity | J14: =('Balance Sheet'!J43+'Balance Sheet'!J54)/'Balance Sheet'!J40 -> 0.83795066 | K14: =('Balance Sheet'!K43+'Balance Sheet'!K54)/'Balance Sheet'!K40 -> 0.64837235 | L14: =('Balance Sheet'!L43+'Balance Sheet'!L54)/'Balance Sheet'!L40 -> 0.83960729 | M14: =('Balance Sheet'!M43+'Balance Sheet'!M54)/'Balance Sheet'!M40 -> 0.78452702 | N14: =('Balance Sheet'!N43+'Balance Sheet'!N54)/'Balance Sheet'!N40 -> 0.76458934 | O14: =('Balance Sheet'!O43+'Balance Sheet'!O54)/'Balance Sheet'!O40 -> 0.64750512 | Q14: Debt-to-Equity | R14: =('Balance Sheet'!R39+'Balance Sheet'!R46)/'Balance Sheet'!R36 -> 0.73699412 | S14: =('Balance Sheet'!S39+'Balance Sheet'!S46)/'Balance Sheet'!S36 -> 0.54868753 | T14: =('Balance Sheet'!T39+'Balance Sheet'!T46)/'Balance Sheet'!T36 -> 0.79081916 | U14: =('Balance Sheet'!U39+'Balance Sheet'!U46)/'Balance Sheet'!U36 -> 0.84701518 | V14: =('Balance Sheet'!V39+'Balance Sheet'!V46)/'Balance Sheet'!V36 -> 0.92494079 | W14: =('Balance Sheet'!W39+'Balance Sheet'!W46)/'Balance Sheet'!W36 -> 0.69212428 | Y14: Debt-to-Equity | Z14: =('Balance Sheet'!Z40+'Balance Sheet'!Z48+'Balance Sheet'!Z49)/'Balance Sheet'!Z37 -> 0.49420464 | AA14: =('Balance Sheet'!AA40+'Balance Sheet'!AA48+'Balance Sheet'!AA49)/'Balance Sheet'!AA37 -> 0.3940956 | AB14: =('Balance Sheet'!AB40+'Balance Sheet'!AB48+'Balance Sheet'!AB49)/'Balance Sheet'!AB37 -> 1.2945727 | AC14: =('Balance Sheet'!AC40+'Balance Sheet'!AC48+'Balance Sheet'!AC49)/'Balance Sheet'!AC37 -> 1.1443136 | AD14: =('Balance Sheet'!AD40+'Balance Sheet'!AD48+'Balance Sheet'!AD49)/'Balance Sheet'!AD37 -> 1.1120444 | AE14: =('Balance Sheet'!AE40+'Balance Sheet'!AE48+'Balance Sheet'!AE49)/'Balance Sheet'!AE37 -> 1.1226621 | AG14: Debt-to-Equity | AH14: =('Balance Sheet'!AH39+'Balance Sheet'!AH46)/'Balance Sheet'!AH36 -> 0.83204415 | AI14: =('Balance Sheet'!AI39+'Balance Sheet'!AI46)/'Balance Sheet'!AI36 -> 1.0471462 | AJ14: =('Balance Sheet'!AJ39+'Balance Sheet'!AJ46)/'Balance Sheet'!AJ36 -> 1.0309469 | AK14: =('Balance Sheet'!AK39+'Balance Sheet'!AK46)/'Balance Sheet'!AK36 -> 0.88430764 | AL14: =('Balance Sheet'!AL39+'Balance Sheet'!AL46)/'Balance Sheet'!AL36 -> 0.68464014 | AM14: =('Balance Sheet'!AM39+'Balance Sheet'!AM46)/'Balance Sheet'!AM36 -> 0.62490665
A15: Interest coverage ratio | B15: =('Income Statement'!B20+Table6[[#This Row],[2020]])/Table6[[#This Row],[2020]] -> 3.375404 | C15: =('Income Statement'!C20+Table6[[#This Row],[2021]])/Table6[[#This Row],[2021]] -> 3.7962169 | D15: =('Income Statement'!D20+Table6[[#This Row],[2022]])/Table6[[#This Row],[2022]] -> 3.399816 | E15: =('Income Statement'!E20+Table6[[#This Row],[2023]])/Table6[[#This Row],[2023]] -> 3.8420453 | F15: =('Income Statement'!F20+Table6[[#This Row],[2024]])/Table6[[#This Row],[2024]] -> 4.8892621 | G15: =('Income Statement'!G20+Table6[[#This Row],[2025]])/Table6[[#This Row],[2025]] -> 6.1889629 | I15: Interest coverage ratio | J15: =('Income Statement'!J18+'Income Statement'!J13)/'Income Statement'!J13 -> 2.2805199 | K15: =('Income Statement'!K18+'Income Statement'!K13)/'Income Statement'!K13 -> 2.7621463 | L15: =('Income Statement'!L18+'Income Statement'!L13)/'Income Statement'!L13 -> 2.3407262 | M15: =('Income Statement'!M18+'Income Statement'!M13)/'Income Statement'!M13 -> 2.1799464 | N15: =('Income Statement'!N18+'Income Statement'!N13)/'Income Statement'!N13 -> 2.3534396 | O15: =('Income Statement'!O18+'Income Statement'!O13)/'Income Statement'!O13 -> 2.427159 | Q15: Interest coverage ratio | R15: =('Income Statement'!R17+'Income Statement'!R12)/'Income Statement'!R12 -> 3.5659783 | S15: =('Income Statement'!S17+'Income Statement'!S12)/'Income Statement'!S12 -> 3.8775743 | T15: =('Income Statement'!T17+'Income Statement'!T12)/'Income Statement'!T12 -> 2.4021203 | U15: =('Income Statement'!U17+'Income Statement'!U12)/'Income Statement'!U12 -> 1.2988916 | V15: =('Income Statement'!V17+'Income Statement'!V12)/'Income Statement'!V12 -> 1.6510006 | W15: =('Income Statement'!W17+'Income Statement'!W12)/'Income Statement'!W12 -> 2.0962944 | Y15: Interest coverage ratio | Z15: =('Income Statement'!Z24+'Income Statement'!Z21)/'Income Statement'!Z21 -> 5.8024965 | AA15: =('Income Statement'!AA24+'Income Statement'!AA21)/'Income Statement'!AA21 -> 4.1266098 | AB15: =('Income Statement'!AB24+'Income Statement'!AB21)/'Income Statement'!AB21 -> 5.606341 | AC15: =('Income Statement'!AC24+'Income Statement'!AC21)/'Income Statement'!AC21 -> 6.2922336 | AD15: =('Income Statement'!AD24+'Income Statement'!AD21)/'Income Statement'!AD21 -> 6.7598319 | AE15: =('Income Statement'!AE24+'Income Statement'!AE21)/'Income Statement'!AE21 -> 7.9290481 | AG15: Interest coverage ratio | AH15: =('Income Statement'!AH16+'Income Statement'!AH11)/'Income Statement'!AH11 -> 15.01389 | AI15: =('Income Statement'!AI16+'Income Statement'!AI11)/'Income Statement'!AI11 -> 24.688817 | AJ15: =('Income Statement'!AJ16+'Income Statement'!AJ11)/'Income Statement'!AJ11 -> 3.483935 | AK15: =('Income Statement'!AK16+'Income Statement'!AK11)/'Income Statement'!AK11 -> 3.4811517 | AL15: =('Income Statement'!AL16+'Income Statement'!AL11)/'Income Statement'!AL11 -> 3.8194953 | AM15: =('Income Statement'!AM16+'Income Statement'!AM11)/'Income Statement'!AM11 -> 4.4283277
A16: Efficiency | I16: Efficiency | Q16: Efficiency | Y16: Efficiency | AG16: Efficiency
A17: Asset turnover ratio | B17: ='Income Statement'!B8/'Balance Sheet'!B36 -> 0.22079758 | C17: ='Income Statement'!C8/(AVERAGE('Balance Sheet'!B36:C36)) -> 0.21115537 | D17: ='Income Statement'!D8/(AVERAGE('Balance Sheet'!C36:D36)) -> 0.22104513 | E17: ='Income Statement'!E8/(AVERAGE('Balance Sheet'!D36:E36)) -> 0.20881952 | F17: ='Income Statement'!F8/(AVERAGE('Balance Sheet'!E36:F36)) -> 0.24129346 | G17: ='Income Statement'!G8/(AVERAGE('Balance Sheet'!F36:G36)) -> 0.25473406 | I17: Asset turnover ratio | J17: ='Income Statement'!J7/'Balance Sheet'!J33 -> 0.80611947 | K17: ='Income Statement'!K7/AVERAGE('Balance Sheet'!J33:K33) -> 0.83619271 | L17: ='Income Statement'!L7/AVERAGE('Balance Sheet'!K33:L33) -> 0.91302206 | M17: ='Income Statement'!M7/AVERAGE('Balance Sheet'!L33:M33) -> 0.8915514 | N17: ='Income Statement'!N7/AVERAGE('Balance Sheet'!M33:N33) -> 0.94623264 | O17: ='Income Statement'!O7/AVERAGE('Balance Sheet'!N33:O33) -> 0.9398326 | Q17: Asset turnover ratio | R17: ='Income Statement'!R7/'Balance Sheet'!R31 -> 0.9300704 | S17: ='Income Statement'!S7/'Balance Sheet'!S31 -> 0.93566108 | T17: ='Income Statement'!T7/'Balance Sheet'!T31 -> 0.84175031 | U17: ='Income Statement'!U7/'Balance Sheet'!U31 -> 0.92739018 | V17: ='Income Statement'!V7/'Balance Sheet'!V31 -> 1.0491349 | W17: ='Income Statement'!W7/'Balance Sheet'!W31 -> 0.98817128 | Y17: Asset turnover ratio | Z17: ='Income Statement'!Z8/'Balance Sheet'!Z31 -> 1.0441991 | AA17: ='Income Statement'!AA8/(AVERAGE('Balance Sheet'!Z31:AA31)) -> 0.96306718 | AB17: ='Income Statement'!AB8/(AVERAGE('Balance Sheet'!AA31:AB31)) -> 0.67855381 | AC17: ='Income Statement'!AC8/(AVERAGE('Balance Sheet'!AB31:AC31)) -> 0.57276836 | AD17: ='Income Statement'!AD8/(AVERAGE('Balance Sheet'!AC31:AD31)) -> 0.67196086 | AE17: ='Income Statement'!AE8/(AVERAGE('Balance Sheet'!AD31:AE31)) -> 0.72217226 | AG17: Asset turnover ratio | AH17: ='Income Statement'!AH7/'Balance Sheet'!AH31 -> 0.83316248 | AI17: ='Income Statement'!AI7/(AVERAGE('Balance Sheet'!AH31:AI31)) -> 1.1104805 | AJ17: ='Income Statement'!AJ7/(AVERAGE('Balance Sheet'!AI31:AJ31)) -> 0.94674062 | AK17: ='Income Statement'!AK7/(AVERAGE('Balance Sheet'!AJ31:AK31)) -> 1.05596 | AL17: ='Income Statement'!AL7/(AVERAGE('Balance Sheet'!AK31:AL31)) -> 1.1212 | AM17: ='Income Statement'!AM7/(AVERAGE('Balance Sheet'!AL31:AM31)) -> 1.180402
A18: Inventory turnover ratio | B18: ='Income Statement'!B10/'Balance Sheet'!B24 -> 10.74393 | C18: ='Income Statement'!C10/(AVERAGE('Balance Sheet'!B24:C24)) -> 5.0924359 | D18: ='Income Statement'!D10/(AVERAGE('Balance Sheet'!C24:D24)) -> 7.0128217 | E18: ='Income Statement'!E10/(AVERAGE('Balance Sheet'!D24:E24)) -> 13.342363 | F18: ='Income Statement'!F10/(AVERAGE('Balance Sheet'!E24:F24)) -> 16.001124 | G18: ='Income Statement'!G10/(AVERAGE('Balance Sheet'!F24:G24)) -> 16.824071 | I18: Inventory turnover ratio | J18: =('Income Statement'!J9+'Income Statement'!J10)/'Balance Sheet'!J22 -> 4.358686 | K18: =('Income Statement'!K9+'Income Statement'!K10)/AVERAGE('Balance Sheet'!J22:K22) -> 4.17516 | L18: =('Income Statement'!L9+'Income Statement'!L10)/AVERAGE('Balance Sheet'!K22:L22) -> 5.9489366 | M18: =('Income Statement'!M9+'Income Statement'!M10)/AVERAGE('Balance Sheet'!L22:M22) -> 5.9972553 | N18: =('Income Statement'!N9+'Income Statement'!N10)/AVERAGE('Balance Sheet'!M22:N22) -> 6.3560343 | O18: =('Income Statement'!O9+'Income Statement'!O10)/AVERAGE('Balance Sheet'!N22:O22) -> 6.1685262 | Q18: Inventory turnover ratio | R18: =('Income Statement'!R9+'Income Statement'!R10)/'Balance Sheet'!R20 -> 7.207329 | S18: =('Income Statement'!S9+'Income Statement'!S10)/AVERAGE('Balance Sheet'!R20:S20) -> 7.04639 | T18: =('Income Statement'!T9+'Income Statement'!T10)/AVERAGE('Balance Sheet'!S20:T20) -> 6.2336484 | U18: =('Income Statement'!U9+'Income Statement'!U10)/AVERAGE('Balance Sheet'!T20:U20) -> 6.4153855 | V18: =('Income Statement'!V9+'Income Statement'!V10)/AVERAGE('Balance Sheet'!U20:V20) -> 7.1543053 | W18: =('Income Statement'!W9+'Income Statement'!W10)/AVERAGE('Balance Sheet'!V20:W20) -> 8.5638529 | Y18: Inventory turnover ratio | Z18: =('Income Statement'!Z11+'Income Statement'!Z12+'Income Statement'!Z13+'Income Statement'!Z14+'Income Statement'!Z16+'Income Statement'!Z17)/'Balance Sheet'!Z21 -> 22.696393 | AA18: =('Income Statement'!AA11+'Income Statement'!AA12+'Income Statement'!AA13+'Income Statement'!AA14+'Income Statement'!AA16+'Income Statement'!AA17)/AVERAGE('Balance Sheet'!Z21:AA21) -> 20.145361 | AB18: =('Income Statement'!AB11+'Income Statement'!AB12+'Income Statement'!AB13+'Income Statement'!AB14+'Income Statement'!AB16+'Income Statement'!AB17)/AVERAGE('Balance Sheet'!AA21:AB21) -> 15.715295 | AC18: =('Income Statement'!AC11+'Income Statement'!AC12+'Income Statement'!AC13+'Income Statement'!AC14+'Income Statement'!AC16+'Income Statement'!AC17)/AVERAGE('Balance Sheet'!AB21:AC21) -> 13.304684 | AD18: =('Income Statement'!AD11+'Income Statement'!AD12+'Income Statement'!AD13+'Income Statement'!AD14+'Income Statement'!AD16+'Income Statement'!AD17)/AVERAGE('Balance Sheet'!AC21:AD21) -> 15.653179 | AE18: =('Income Statement'!AE11+'Income Statement'!AE12+'Income Statement'!AE13+'Income Statement'!AE14+'Income Statement'!AE16+'Income Statement'!AE17)/AVERAGE('Balance Sheet'!AD21:AE21) -> 17.367855 | AG18: Inventory turnover ratio | AH18: ='Income Statement'!AH9/'Balance Sheet'!AH20 -> 1013.696 | AI18: ='Income Statement'!AI9/AVERAGE('Balance Sheet'!AH20:AI20) -> 821.24512 | AJ18: ='Income Statement'!AJ9/AVERAGE('Balance Sheet'!AI20:AJ20) -> 387.72234 | AK18: ='Income Statement'!AK9/AVERAGE('Balance Sheet'!AJ20:AK20) -> 328.98438 | AL18: ='Income Statement'!AL9/AVERAGE('Balance Sheet'!AK20:AL20) -> 302.79127 | AM18: ='Income Statement'!AM9/AVERAGE('Balance Sheet'!AL20:AM20) -> 623.66687
A19: Receivables turnover | B19: ='Income Statement'!B8/'Balance Sheet'!B26 -> 5.3047287 | C19: ='Income Statement'!C8/AVERAGE('Balance Sheet'!B26:C26) -> 5.8371293 | D19: ='Income Statement'!D8/AVERAGE('Balance Sheet'!C26:D26) -> 8.395551 | E19: ='Income Statement'!E8/AVERAGE('Balance Sheet'!D26:E26) -> 8.2017399 | F19: ='Income Statement'!F8/AVERAGE('Balance Sheet'!E26:F26) -> 8.1666153 | G19: ='Income Statement'!G8/AVERAGE('Balance Sheet'!F26:G26) -> 7.9965133 | I19: Receivables turnover | J19: ='Income Statement'!J7/'Balance Sheet'!J22 -> 10.52491 | K19: ='Income Statement'!K7/(AVERAGE('Balance Sheet'!J24:K24)) -> 2.7025204 | L19: ='Income Statement'!L7/(AVERAGE('Balance Sheet'!K24:L24)) -> 3.0985692 | M19: ='Income Statement'!M7/(AVERAGE('Balance Sheet'!L24:M24)) -> 3.3369495 | N19: ='Income Statement'!N7/(AVERAGE('Balance Sheet'!M24:N24)) -> 3.5617689 | O19: ='Income Statement'!O7/(AVERAGE('Balance Sheet'!N24:O24)) -> 3.285567 | Q19: Receivables turnover | R19: ='Income Statement'!R7/('Balance Sheet'!R22+'Balance Sheet'!R12) -> 2.1996242 | S19: ='Income Statement'!S7/(AVERAGE('Balance Sheet'!R22:S22)+AVERAGE('Balance Sheet'!R12:S12)) -> 2.3873225 | T19: ='Income Statement'!T7/(AVERAGE('Balance Sheet'!S22:T22)+AVERAGE('Balance Sheet'!S12:T12)) -> 2.469468 | U19: ='Income Statement'!U7/(AVERAGE('Balance Sheet'!T22:U22)+AVERAGE('Balance Sheet'!T12:U12)) -> 2.6990144 | V19: ='Income Statement'!V7/(AVERAGE('Balance Sheet'!U22:V22)+AVERAGE('Balance Sheet'!U12:V12)) -> 3.4188413 | W19: ='Income Statement'!W7/(AVERAGE('Balance Sheet'!V22:W22)+AVERAGE('Balance Sheet'!V12:W12)) -> 4.5232861 | Y19: Receivables turnover | Z19: ='Income Statement'!Z8/'Balance Sheet'!Z23 -> 5.2955065 | AA19: ='Income Statement'!AA8/AVERAGE('Balance Sheet'!Z23:AA23) -> 4.8187172 | AB19: ='Income Statement'!AB8/AVERAGE('Balance Sheet'!AA23:AB23) -> 4.173831 | AC19: ='Income Statement'!AC8/AVERAGE('Balance Sheet'!AB23:AC23) -> 4.0996617 | AD19: ='Income Statement'!AD8/AVERAGE('Balance Sheet'!AC23:AD23) -> 4.8185019 | AE19: ='Income Statement'!AE8/AVERAGE('Balance Sheet'!AD23:AE23) -> 5.0711852 | AG19: Receivables turnover | AH19: ='Income Statement'!AH7/'Balance Sheet'!AH22 -> 12.367601 | AI19: ='Income Statement'!AI7/AVERAGE('Balance Sheet'!AH22:AI22) -> 16.286104 | AJ19: ='Income Statement'!AJ7/AVERAGE('Balance Sheet'!AI22:AJ22) -> 16.833107 | AK19: ='Income Statement'!AK7/AVERAGE('Balance Sheet'!AJ22:AK22) -> 21.160951 | AL19: ='Income Statement'!AL7/AVERAGE('Balance Sheet'!AK22:AL22) -> 20.792708 | AM19: ='Income Statement'!AM7/AVERAGE('Balance Sheet'!AL22:AM22) -> 17.978799
A20: Valuation | I20: Valuation | Q20: Valuation | Y20: Valuation | AG20: Valuation
A21: P/E Ratio | B21: =B28/('Income Statement'!B30/'Company Info'!$B$11) -> 14.343734 | C21: =C28/('Income Statement'!C30/'Company Info'!$B$11) -> 30.052679 | D21: =D28/('Income Statement'!D30/'Company Info'!$B$11) -> 33.763756 | E21: =E28/('Income Statement'!E30/'Company Info'!$B$11) -> 25.31161 | F21: =F28/('Income Statement'!F30/'Company Info'!$B$11) -> 36.165847 | G21: =G28/('Income Statement'!G30/'Company Info'!$B$11) -> 23.024537 | I21: P/E Ratio | J21: =J28/('Income Statement'!J27/'Company Info'!$C$11) -> 8.0062669 | K21: =K28/('Income Statement'!K27/'Company Info'!$C$11) -> 9.7246798 | L21: =L28/('Income Statement'!L27/'Company Info'!$C$11) -> 11.705388 | M21: =M28/('Income Statement'!M27/'Company Info'!$C$11) -> 21.084539 | N21: =N28/('Income Statement'!N27/'Company Info'!$C$11) -> 35.716929 | O21: =O28/('Income Statement'!O27/'Company Info'!$C$11) -> 29.33663 | Q21: P/E Ratio | R21: =R28/('Income Statement'!R24/'Company Info'!$D$11) -> 8.7318044 | S21: =S28/('Income Statement'!S24/'Company Info'!$D$11) -> 19.787283 | T21: =T28/('Income Statement'!T24/'Company Info'!$D$11) -> 26.848848 | U21: =U28/('Income Statement'!U24/'Company Info'!$D$11) -> 69.011174 | V21: =V28/('Income Statement'!V24/'Company Info'!$D$11) -> 54.118173 | W21: =W28/('Income Statement'!W24/'Company Info'!$D$11) -> 36.571367 | Y21: P/E Ratio | Z21: =Z28/('Income Statement'!Z42/'Company Info'!$E$11) -> 10.208635 | AA21: =AA28/('Income Statement'!AA42/'Company Info'!$E$11) -> 15.105407 | AB21: =AB28/('Income Statement'!AB42/'Company Info'!$E$11) -> 23.337074 | AC21: =AC28/('Income Statement'!AC42/'Company Info'!$E$11) -> 23.758061 | AD21: =AD28/('Income Statement'!AD42/'Company Info'!$E$11) -> 33.302348 | AE21: =AE28/('Income Statement'!AE42/'Company Info'!$E$11) -> 27.18187 | AG21: P/E Ratio | AH21: =AH28/('Income Statement'!AH25/'Company Info'!$F$11) -> 3.8805537 | AI21: =AI28/('Income Statement'!AI25/'Company Info'!$F$11) -> 8.0541954 | AJ21: =AJ28/('Income Statement'!AJ25/'Company Info'!$F$11) -> 6.8759799 | AK21: =AK28/('Income Statement'!AK25/'Company Info'!$F$11) -> 12.093818 | AL21: =AL28/('Income Statement'!AL25/'Company Info'!$F$11) -> 40.558243 | AM21: =AM28/('Income Statement'!AM25/'Company Info'!$F$11) -> 46.541394
A22: P/B ratio | B22: =B28/('Balance Sheet'!B43/'Company Info'!$B$11) -> 2.100535 | C22: =C28/('Balance Sheet'!C43/'Company Info'!$B$11) -> 4.7272156 | D22: =D28/('Balance Sheet'!D43/'Company Info'!$B$11) -> 3.9460608 | E22: =E28/('Balance Sheet'!E43/'Company Info'!$B$11) -> 2.9090602 | F22: =F28/('Balance Sheet'!F43/'Company Info'!$B$11) -> 5.3735156 | G22: =G28/('Balance Sheet'!G43/'Company Info'!$B$11) -> 3.9197675 | I22: P/B ratio | J22: =J28/('Balance Sheet'!J40/'Company Info'!$C$11) -> 0.89242055 | K22: =K28/('Balance Sheet'!K40/'Company Info'!$C$11) -> 1.6683667 | L22: =L28/('Balance Sheet'!L40/'Company Info'!$C$11) -> 1.4177991 | M22: =M28/('Balance Sheet'!M40/'Company Info'!$C$11) -> 1.9540839 | N22: =N28/('Balance Sheet'!N40/'Company Info'!$C$11) -> 3.6039602 | O22: =O28/('Balance Sheet'!O40/'Company Info'!$C$11) -> 2.5726001 | Q22: P/B ratio | R22: =R28/('Balance Sheet'!R36/'Company Info'!$D$11) -> 1.7651006 | S22: =S28/('Balance Sheet'!S36/'Company Info'!$D$11) -> 3.2553084 | T22: =T28/('Balance Sheet'!T36/'Company Info'!$D$11) -> 2.7866973 | U22: =U28/('Balance Sheet'!U36/'Company Info'!$D$11) -> 3.2210777 | V22: =V28/('Balance Sheet'!V36/'Company Info'!$D$11) -> 4.5821471 | W22: =W28/('Balance Sheet'!W36/'Company Info'!$D$11) -> 3.9033076 | Y22: P/B ratio | Z22: =Z28/('Balance Sheet'!Z37/'Company Info'!$E$11) -> 2.131576 | AA22: =AA28/('Balance Sheet'!AA37/'Company Info'!$E$11) -> 3.2307524 | AB22: =AB28/('Balance Sheet'!AB37/'Company Info'!$E$11) -> 2.5494921 | AC22: =AC28/('Balance Sheet'!AC37/'Company Info'!$E$11) -> 2.8744929 | AD22: =AD28/('Balance Sheet'!AD37/'Company Info'!$E$11) -> 5.0488215 | AE22: =AE28/('Balance Sheet'!AE37/'Company Info'!$E$11) -> 4.1627282 | AG22: P/B ratio | AH22: =AH28/('Balance Sheet'!AH36/'Company Info'!$F$11) -> 0.52167283 | AI22: =AI28/('Balance Sheet'!AI36/'Company Info'!$F$11) -> 1.0765298 | AJ22: =AJ28/('Balance Sheet'!AJ36/'Company Info'!$F$11) -> 1.0657479 | AK22: =AK28/('Balance Sheet'!AK36/'Company Info'!$F$11) -> 1.9738949 | AL22: =AL28/('Balance Sheet'!AL36/'Company Info'!$F$11) -> 6.2222679 | AM22: =AM28/('Balance Sheet'!AM36/'Company Info'!$F$11) -> 8.4972643
A23: EV/EBITDA | B23: =(B30+'Balance Sheet'!B46+'Balance Sheet'!B54-'Balance Sheet'!B28)/('Income Statement'!B20+'Income Statement'!B15+'Income Statement'!B16) -> 9.5911321 | C23: =(C30+'Balance Sheet'!C46+'Balance Sheet'!C54-'Balance Sheet'!C28)/('Income Statement'!C20+'Income Statement'!C15+'Income Statement'!C16) -> 16.95259 | D23: =(D30+'Balance Sheet'!D46+'Balance Sheet'!D54-'Balance Sheet'!D28)/('Income Statement'!D20+'Income Statement'!D15+'Income Statement'!D16) -> 17.367654 | E23: =(E30+'Balance Sheet'!E46+'Balance Sheet'!E54-'Balance Sheet'!E28)/('Income Statement'!E20+'Income Statement'!E15+'Income Statement'!E16) -> 14.830197 | F23: =(F30+'Balance Sheet'!F46+'Balance Sheet'!F54-'Balance Sheet'!F28)/('Income Statement'!F20+'Income Statement'!F15+'Income Statement'!F16) -> 19.581506 | G23: =(G30+'Balance Sheet'!G46+'Balance Sheet'!G54-'Balance Sheet'!G28)/('Income Statement'!G20+'Income Statement'!G15+'Income Statement'!G16) -> 14.818441 | I23: EV/EBITDA | J23: =(J30+'Balance Sheet'!J43+'Balance Sheet'!J54-'Balance Sheet'!J25)/('Income Statement'!J18+'Income Statement'!J14+'Income Statement'!J13) -> 3.6322856 | K23: =(K30+'Balance Sheet'!K43+'Balance Sheet'!K54-'Balance Sheet'!K25)/('Income Statement'!K18+'Income Statement'!K14+'Income Statement'!K13) -> 5.3282353 | L23: =(L30+'Balance Sheet'!L43+'Balance Sheet'!L54-'Balance Sheet'!L25)/('Income Statement'!L18+'Income Statement'!L14+'Income Statement'!L13) -> 6.9694208 | M23: =(M30+'Balance Sheet'!M43+'Balance Sheet'!M54-'Balance Sheet'!M25)/('Income Statement'!M18+'Income Statement'!M14+'Income Statement'!M13) -> 8.4430092 | N23: =(N30+'Balance Sheet'!N43+'Balance Sheet'!N54-'Balance Sheet'!N25)/('Income Statement'!N18+'Income Statement'!N14+'Income Statement'!N13) -> 12.599987 | O23: =(O30+'Balance Sheet'!O43+'Balance Sheet'!O54-'Balance Sheet'!O25)/('Income Statement'!O18+'Income Statement'!O14+'Income Statement'!O13) -> 10.138521 | Q23: EV/EBITDA | R23: =(R30+'Balance Sheet'!R39+'Balance Sheet'!R46-Table3[[#This Row],[2020]])/('Income Statement'!R17+'Income Statement'!R14+'Income Statement'!R12) -> 5.4977157 | S23: =(S30+'Balance Sheet'!S39+'Balance Sheet'!S46-Table3[[#This Row],[2021]])/('Income Statement'!S17+'Income Statement'!S14+'Income Statement'!S12) -> 10.742152 | T23: =(T30+'Balance Sheet'!T39+'Balance Sheet'!T46-Table3[[#This Row],[2022]])/('Income Statement'!T17+'Income Statement'!T14+'Income Statement'!T12) -> 13.897167 | U23: =(U30+'Balance Sheet'!U39+'Balance Sheet'!U46-Table3[[#This Row],[2023]])/('Income Statement'!U17+'Income Statement'!U14+'Income Statement'!U12) -> 17.491815 | V23: =(V30+'Balance Sheet'!V39+'Balance Sheet'!V46-Table3[[#This Row],[2024]])/('Income Statement'!V17+'Income Statement'!V14+'Income Statement'!V12) -> 17.640594 | W23: =(W30+'Balance Sheet'!W39+'Balance Sheet'!W46-Table3[[#This Row],[2025]])/('Income Statement'!W17+'Income Statement'!W14+'Income Statement'!W12) -> 15.258295 | Y23: EV/EBITDA | Z23: =(Z30+'Balance Sheet'!Z40+'Balance Sheet'!Z48+'Balance Sheet'!Z49-'Balance Sheet'!Z24)/('Income Statement'!Z24+'Income Statement'!Z21+'Income Statement'!Z22) -> 7.1556475 | AA23: =(AA30+'Balance Sheet'!AA40+'Balance Sheet'!AA48+'Balance Sheet'!AA49-'Balance Sheet'!AA24)/('Income Statement'!AA24+'Income Statement'!AA21+'Income Statement'!AA22) -> 11.330085 | AB23: =(AB30+'Balance Sheet'!AB40+'Balance Sheet'!AB48+'Balance Sheet'!AB49-'Balance Sheet'!AB24)/('Income Statement'!AB24+'Income Statement'!AB21+'Income Statement'!AB22) -> 17.236123 | AC23: =(AC30+'Balance Sheet'!AC40+'Balance Sheet'!AC48+'Balance Sheet'!AC49-'Balance Sheet'!AC24)/('Income Statement'!AC24+'Income Statement'!AC21+'Income Statement'!AC22) -> 16.860161 | AD23: =(AD30+'Balance Sheet'!AD40+'Balance Sheet'!AD48+'Balance Sheet'!AD49-'Balance Sheet'!AD24)/('Income Statement'!AD24+'Income Statement'!AD21+'Income Statement'!AD22) -> 22.415861 | AE23: =(AE30+'Balance Sheet'!AE40+'Balance Sheet'!AE48+'Balance Sheet'!AE49-'Balance Sheet'!AE24)/('Income Statement'!AE24+'Income Statement'!AE21+'Income Statement'!AE22) -> 19.560704 | AG23: EV/EBITDA | AH23: =(AH30+'Balance Sheet'!AH39+'Balance Sheet'!AH46-'Balance Sheet'!AH24)/('Income Statement'!AH16+'Income Statement'!AH11+'Income Statement'!AH12) -> 8.4610056 | AI23: =(AI30+'Balance Sheet'!AI39+'Balance Sheet'!AI46-'Balance Sheet'!AI24)/('Income Statement'!AI16+'Income Statement'!AI11+'Income Statement'!AI12) -> 10.219457 | AJ23: =(AJ30+'Balance Sheet'!AJ39+'Balance Sheet'!AJ46-'Balance Sheet'!AJ24)/('Income Statement'!AJ16+'Income Statement'!AJ11+'Income Statement'!AJ12) -> 5.4386309 | AK23: =(AK30+'Balance Sheet'!AK39+'Balance Sheet'!AK46-'Balance Sheet'!AK24)/('Income Statement'!AK16+'Income Statement'!AK11+'Income Statement'!AK12) -> 10.021045 | AL23: =(AL30+'Balance Sheet'!AL39+'Balance Sheet'!AL46-'Balance Sheet'!AL24)/('Income Statement'!AL16+'Income Statement'!AL11+'Income Statement'!AL12) -> 26.440675 | AM23: =(AM30+'Balance Sheet'!AM39+'Balance Sheet'!AM46-'Balance Sheet'!AM24)/('Income Statement'!AM16+'Income Statement'!AM11+'Income Statement'!AM12) -> 29.791305
A24: Cash Flow strength | I24: Cash Flow strength | Q24: Cash Flow strength | Y24: Cash Flow strength | AG24: Cash Flow strength
A25: Operating cash flow to debt | B25: ='Cash Flow Statement'!B39/('Balance Sheet'!B46+'Balance Sheet'!B54) -> 0.26696807 | C25: ='Cash Flow Statement'!C39/('Balance Sheet'!C46+'Balance Sheet'!C54) -> 0.22665846 | D25: ='Cash Flow Statement'!D39/('Balance Sheet'!D46+'Balance Sheet'!D54) -> 0.22925067 | E25: ='Cash Flow Statement'!E39/('Balance Sheet'!E46+'Balance Sheet'!E54) -> 0.23953062 | F25: ='Cash Flow Statement'!F39/('Balance Sheet'!F46+'Balance Sheet'!F54) -> 0.32449935 | G25: ='Cash Flow Statement'!G39/('Balance Sheet'!G46+'Balance Sheet'!G54) -> 0.3760373 | I25: Operating cash flow to debt | J25: ='Cash Flow Statement'!J29/('Balance Sheet'!J43+'Balance Sheet'!J54) -> 0.32001038 | K25: ='Cash Flow Statement'!K29/('Balance Sheet'!K43+'Balance Sheet'!K54) -> 0.37209786 | L25: ='Cash Flow Statement'!L29/('Balance Sheet'!L43+'Balance Sheet'!L54) -> 0.19241616 | M25: ='Cash Flow Statement'!M29/('Balance Sheet'!M43+'Balance Sheet'!M54) -> 0.17824769 | N25: ='Cash Flow Statement'!N29/('Balance Sheet'!N43+'Balance Sheet'!N54) -> 0.21563491 | O25: ='Cash Flow Statement'!O29/('Balance Sheet'!O43+'Balance Sheet'!O54) -> 0.21819836 | Q25: Operating cash flow to debt | R25: ='Cash Flow Statement'!R33/('Balance Sheet'!R39+'Balance Sheet'!R46) -> 0.042414395 | S25: ='Cash Flow Statement'!S33/('Balance Sheet'!S39+'Balance Sheet'!S46) -> 0.45813759 | T25: ='Cash Flow Statement'!T33/('Balance Sheet'!T39+'Balance Sheet'!T46) -> -0.099105393 | U25: ='Cash Flow Statement'!U33/('Balance Sheet'!U39+'Balance Sheet'!U46) -> 0.18993254 | V25: ='Cash Flow Statement'!V33/('Balance Sheet'!V39+'Balance Sheet'!V46) -> 0.0821349 | W25: ='Cash Flow Statement'!W33/('Balance Sheet'!W39+'Balance Sheet'!W46) -> 0.1132312 | Y25: Operating cash flow to debt | Z25: ='Cash Flow Statement'!Z36/('Balance Sheet'!Z40+'Balance Sheet'!Z48+'Balance Sheet'!Z49) -> 0.25960063 | AA25: ='Cash Flow Statement'!AA36/('Balance Sheet'!AA40+'Balance Sheet'!AA48+'Balance Sheet'!AA49) -> 0.95948668 | AB25: ='Cash Flow Statement'!AB36/('Balance Sheet'!AB40+'Balance Sheet'!AB48+'Balance Sheet'!AB49) -> 0.15521053 | AC25: ='Cash Flow Statement'!AC36/('Balance Sheet'!AC40+'Balance Sheet'!AC48+'Balance Sheet'!AC49) -> 0.19218893 | AD25: ='Cash Flow Statement'!AD36/('Balance Sheet'!AD40+'Balance Sheet'!AD48+'Balance Sheet'!AD49) -> 0.16017465 | AE25: ='Cash Flow Statement'!AE36/('Balance Sheet'!AE40+'Balance Sheet'!AE48+'Balance Sheet'!AE49) -> 0.070706674 | AG25: Operating cash flow to debt | AH25: ='Cash Flow Statement'!AH35/('Balance Sheet'!AH39+'Balance Sheet'!AH46) -> -0.22550019 | AI25: ='Cash Flow Statement'!AI35/('Balance Sheet'!AI39+'Balance Sheet'!AI46) -> 0.071068149 | AJ25: ='Cash Flow Statement'!AJ35/('Balance Sheet'!AJ39+'Balance Sheet'!AJ46) -> 0.72780492 | AK25: ='Cash Flow Statement'!AK35/('Balance Sheet'!AK39+'Balance Sheet'!AK46) -> -0.63421543 | AL25: ='Cash Flow Statement'!AL35/('Balance Sheet'!AL39+'Balance Sheet'!AL46) -> 0.49341156 | AM25: ='Cash Flow Statement'!AM35/('Balance Sheet'!AM39+'Balance Sheet'!AM46) -> 0.35626144
A26: Free cash flow margin | B26: =('Cash Flow Statement'!B39+'Cash Flow Statement'!B41)/'Income Statement'!B8 -> 0.27525007 | C26: =('Cash Flow Statement'!C39+'Cash Flow Statement'!C41)/'Income Statement'!C8 -> 0.38583578 | D26: =('Cash Flow Statement'!D39+'Cash Flow Statement'!D41)/'Income Statement'!D8 -> 0.3415503 | E26: =('Cash Flow Statement'!E39+'Cash Flow Statement'!E41)/'Income Statement'!E8 -> 0.12534796 | F26: =('Cash Flow Statement'!F39+'Cash Flow Statement'!F41)/'Income Statement'!F8 -> 0.26945358 | G26: =('Cash Flow Statement'!G39+'Cash Flow Statement'!G41)/'Income Statement'!G8 -> 0.28339985 | I26: Free cash flow margin | J26: =('Cash Flow Statement'!J29+'Cash Flow Statement'!J31)/'Income Statement'!J7 -> 0.036751133 | K26: =('Cash Flow Statement'!K29+'Cash Flow Statement'!K31)/'Income Statement'!K7 -> 0.051461765 | L26: =('Cash Flow Statement'!L29+'Cash Flow Statement'!L31)/'Income Statement'!L7 -> 0.027280493 | M26: =('Cash Flow Statement'!M29+'Cash Flow Statement'!M31)/'Income Statement'!M7 -> -0.0070171951 | N26: =('Cash Flow Statement'!N29+'Cash Flow Statement'!N31)/'Income Statement'!N7 -> 0.024955283 | O26: =('Cash Flow Statement'!O29+'Cash Flow Statement'!O31)/'Income Statement'!O7 -> 0.015163377 | Q26: Free cash flow margin | R26: =('Cash Flow Statement'!R33+'Cash Flow Statement'!R35)/'Income Statement'!R7 -> -0.0099361498 | S26: =('Cash Flow Statement'!S33+'Cash Flow Statement'!S35)/'Income Statement'!S7 -> 0.050552643 | T26: =('Cash Flow Statement'!T33+'Cash Flow Statement'!T35)/'Income Statement'!T7 -> -0.031030795 | U26: =('Cash Flow Statement'!U33+'Cash Flow Statement'!U35)/'Income Statement'!U7 -> 0.024746679 | V26: =('Cash Flow Statement'!V33+'Cash Flow Statement'!V35)/'Income Statement'!V7 -> 0.0036946738 | W26: =('Cash Flow Statement'!W33+'Cash Flow Statement'!W35)/'Income Statement'!W7 -> 0.010793172 | Y26: Free cash flow margin | Z26: =('Cash Flow Statement'!Z36+'Cash Flow Statement'!Z38)/'Income Statement'!Z8 -> 0.022034965 | AA26: =('Cash Flow Statement'!AA36+'Cash Flow Statement'!AA38)/'Income Statement'!AA8 -> 0.15089796 | AB26: =('Cash Flow Statement'!AB36+'Cash Flow Statement'!AB38)/'Income Statement'!AB8 -> 0.10109648 | AC26: =('Cash Flow Statement'!AC36+'Cash Flow Statement'!AC38)/'Income Statement'!AC8 -> 0.10003319 | AD26: =('Cash Flow Statement'!AD36+'Cash Flow Statement'!AD38)/'Income Statement'!AD8 -> 0.061036501 | AE26: =('Cash Flow Statement'!AE36+'Cash Flow Statement'!AE38)/'Income Statement'!AE8 -> 0.018247877 | AG26: Free cash flow margin | AH26: =('Cash Flow Statement'!AH35+'Cash Flow Statement'!AH37+'Cash Flow Statement'!AH38)/'Income Statement'!AH7 -> -0.095051976 | AI26: =('Cash Flow Statement'!AI35+'Cash Flow Statement'!AI37+'Cash Flow Statement'!AI38)/'Income Statement'!AI7 -> 0.025629618 | AJ26: =('Cash Flow Statement'!AJ35+'Cash Flow Statement'!AJ37+'Cash Flow Statement'!AJ38)/'Income Statement'!AJ7 -> 0.29649723 | AK26: =('Cash Flow Statement'!AK35+'Cash Flow Statement'!AK37+'Cash Flow Statement'!AK38)/'Income Statement'!AK7 -> -0.2018686 | AL26: =('Cash Flow Statement'!AL35+'Cash Flow Statement'!AL37+'Cash Flow Statement'!AL38)/'Income Statement'!AL7 -> 0.13338042 | AM26: =('Cash Flow Statement'!AM35+'Cash Flow Statement'!AM37+'Cash Flow Statement'!AM38)/'Income Statement'!AM7 -> 0.064497634
A28: Market Price | B28: 251.3 | C28: 702.4 | D28: 774.2 | E28: 631.9 | F28: 1356.8 | G28: 1179 | I28: Market Price | J28: 182.65 | K28: 377 | L28: 366.75 | M28: 537.1 | N28: 1079 | O28: 974.5 | Q28: Market Price | R28: 185.5 | S28: 410.85 | T28: 378.95 | U28: 456.35 | V28: 705 | W28: 784.1 | Y28: Market Price | Z28: 808.5 | AA28: 1418.9 | AB28: 1767.65 | AC28: 2164.2 | AD28: 3763.9 | AE28: 3492.3 | AG28: Market Price | AH28: 12.8 | AI28: 29.1 | AJ28: 32.7 | AK28: 68.6 | AL28: 261 | AM28: 351.45
A29: Outstanding shares | B29: ='Company Info'!$B$11 -> 216.0139 | C29: ='Company Info'!$B$11 -> 216.0139 | D29: ='Company Info'!$B$11 -> 216.0139 | E29: ='Company Info'!$B$11 -> 216.0139 | F29: ='Company Info'!$B$11 -> 216.0139 | G29: ='Company Info'!$B$11 -> 216.0139 | I29: Outstanding shares | J29: ='Company Info'!$C$11 -> 17.07726 | K29: ='Company Info'!$C$11 -> 17.07726 | L29: ='Company Info'!$C$11 -> 17.07726 | M29: ='Company Info'!$C$11 -> 17.07726 | N29: ='Company Info'!$C$11 -> 17.07726 | O29: ='Company Info'!$C$11 -> 17.07726 | Q29: Outstanding shares | R29: ='Company Info'!$D$11 -> 26.62 | S29: ='Company Info'!$D$11 -> 26.62 | T29: ='Company Info'!$D$11 -> 26.62 | U29: ='Company Info'!$D$11 -> 26.62 | V29: ='Company Info'!$D$11 -> 26.62 | W29: ='Company Info'!$D$11 -> 26.62 | Y29: Outstanding shares | Z29: ='Company Info'!$E$11 -> 137.5581 | AA29: ='Company Info'!$E$11 -> 137.5581 | AB29: ='Company Info'!$E$11 -> 137.5581 | AC29: ='Company Info'!$E$11 -> 137.5581 | AD29: ='Company Info'!$E$11 -> 137.5581 | AE29: ='Company Info'!$E$11 -> 137.5581 | AG29: Outstanding shares | AH29: ='Company Info'!$F$11 -> 208.502 | AI29: ='Company Info'!$F$11 -> 208.502 | AJ29: ='Company Info'!$F$11 -> 208.502 | AK29: ='Company Info'!$F$11 -> 208.502 | AL29: ='Company Info'!$F$11 -> 208.502 | AM29: ='Company Info'!$F$11 -> 208.502
A30: Market Cap | B30: =B28*B29 -> 54284.293 | C30: =C28*C29 -> 151728.16 | D30: =D28*D29 -> 167237.96 | E30: =E28*E29 -> 136499.18 | F30: =F28*F29 -> 293087.66 | G30: =G28*G29 -> 254680.39 | I30: Market Cap | J30: =J28*J29 -> 3119.1615 | K30: =K28*K29 -> 6438.127 | L30: =L28*L29 -> 6263.0851 | M30: =M28*M29 -> 9172.1963 | N30: =N28*N29 -> 18426.364 | O30: =O28*O29 -> 16641.79 | Q30: Market Cap | R30: =R28*R29 -> 4938.01 | S30: =S28*S29 -> 10936.827 | T30: =T28*T29 -> 10087.649 | U30: =U28*U29 -> 12148.037 | V30: =V28*V29 -> 18767.1 | W30: =W28*W29 -> 20872.742 | Y30: Market Cap | Z30: =Z28*Z29 -> 111215.72 | AA30: =AA28*AA29 -> 195181.19 | AB30: =AB28*AB29 -> 243154.58 | AC30: =AC28*AC29 -> 297703.24 | AD30: =AD28*AD29 -> 517754.93 | AE30: =AE28*AE29 -> 480394.15 | AG30: Market Cap | AH30: =AH28*AH29 -> 2668.8256 | AI30: =AI28*AI29 -> 6067.4082 | AJ30: =AJ28*AJ29 -> 6818.0154 | AK30: =AK28*AK29 -> 14303.237 | AL30: =AL28*AL29 -> 54419.022 | AM30: =AM28*AM29 -> 73278.028
A31: ROA | B31: ='Income Statement'!B30/'Balance Sheet'!B36 -> 0.060840944 | C31: ='Income Statement'!C30/AVERAGE('Balance Sheet'!B36:C36) -> 0.073421561 | D31: ='Income Statement'!D30/AVERAGE('Balance Sheet'!C36:D36) -> 0.056604666 | E31: ='Income Statement'!E30/AVERAGE('Balance Sheet'!D36:E36) -> 0.05026074 | F31: ='Income Statement'!F30/AVERAGE('Balance Sheet'!E36:F36) -> 0.069317304 | G31: ='Income Statement'!G30/AVERAGE('Balance Sheet'!F36:G36) -> 0.087010861 | I31: ROA | J31: ='Income Statement'!J27/'Balance Sheet'!J33 -> 0.024690177 | K31: ='Income Statement'!K27/AVERAGE('Balance Sheet'!J33:K33) -> 0.042530229 | L31: ='Income Statement'!L27/AVERAGE('Balance Sheet'!K33:L33) -> 0.032861007 | M31: ='Income Statement'!M27/AVERAGE('Balance Sheet'!L33:M33) -> 0.023647301 | N31: ='Income Statement'!N27/AVERAGE('Balance Sheet'!M33:N33) -> 0.024791824 | O31: ='Income Statement'!O27/AVERAGE('Balance Sheet'!N33:O33) -> 0.023823963 | Q31: ROA | R31: ='Income Statement'!R24/Table3[[#This Row],[2020]] -> 0.043917232 | S31: ='Income Statement'!S24/AVERAGE(Table3[[#This Row],[2020]:[2021]]) -> 0.04105642 | T31: ='Income Statement'!T24/AVERAGE(Table3[[#This Row],[2020]:[2021]]) -> 0.027908739 | U31: ='Income Statement'!U24/AVERAGE(Table3[[#This Row],[2020]:[2021]]) -> 0.013075629 | V31: ='Income Statement'!V24/AVERAGE(Table3[[#This Row],[2020]:[2021]]) -> 0.025759056 | W31: ='Income Statement'!W24/AVERAGE(Table3[[#This Row],[2020]:[2021]]) -> 0.042394958 | Y31: ROA | Z31: ='Income Statement'!Z42/Table4[[#This Row],[2020]] -> 0.076960599 | AA31: ='Income Statement'!AA42/AVERAGE(Table4[[#This Row],[2020]:[2021]]) -> 0.089263362 | AB31: ='Income Statement'!AB42/AVERAGE(Table4[[#This Row],[2020]:[2021]]) -> 0.071978658 | AC31: ='Income Statement'!AC42/AVERAGE(Table4[[#This Row],[2020]:[2021]]) -> 0.086564587 | AD31: ='Income Statement'!AD42/AVERAGE(Table4[[#This Row],[2020]:[2021]]) -> 0.10740317 | AE31: ='Income Statement'!AE42/AVERAGE(Table4[[#This Row],[2020]:[2021]]) -> 0.12209169 | AG31: ROA | AH31: ='Income Statement'!AH25/Table5[[#This Row],[2020]] -> 0.055502358 | AI31: ='Income Statement'!AI25/AVERAGE(Table5[[#This Row],[2020]:[2021]]) -> 0.056614459 | AJ31: ='Income Statement'!AJ25/AVERAGE(Table5[[#This Row],[2020]:[2021]]) -> 0.074519457 | AK31: ='Income Statement'!AK25/AVERAGE(Table5[[#This Row],[2020]:[2021]]) -> 0.088882698 | AL31: ='Income Statement'!AL25/AVERAGE(Table5[[#This Row],[2020]:[2021]]) -> 0.10083653 | AM31: ='Income Statement'!AM25/AVERAGE(Table5[[#This Row],[2020]:[2021]]) -> 0.11832614
A32: D/CE | B32: =('Balance Sheet'!B46+'Balance Sheet'!B54)/('Balance Sheet'!B36-'Balance Sheet'!B64) -> 0.50865665 | C32: =('Balance Sheet'!C46+'Balance Sheet'!C54)/('Balance Sheet'!C36-'Balance Sheet'!C64) -> 0.48863049 | D32: =('Balance Sheet'!D46+'Balance Sheet'!D54)/('Balance Sheet'!D36-'Balance Sheet'!D64) -> 0.51288392 | E32: =('Balance Sheet'!E46+'Balance Sheet'!E54)/('Balance Sheet'!E36-'Balance Sheet'!E64) -> 0.48133655 | F32: =('Balance Sheet'!F46+'Balance Sheet'!F54)/('Balance Sheet'!F36-'Balance Sheet'!F64) -> 0.45149376 | G32: =('Balance Sheet'!G46+'Balance Sheet'!G54)/('Balance Sheet'!G36-'Balance Sheet'!G64) -> 0.40045906 | I32: D/CE | J32: =('Balance Sheet'!J43+'Balance Sheet'!J54)/('Balance Sheet'!J33-'Balance Sheet'!J63) -> 0.3933281 | K32: =('Balance Sheet'!K43+'Balance Sheet'!K54)/('Balance Sheet'!K33-'Balance Sheet'!K63) -> 0.35688224 | L32: =('Balance Sheet'!L43+'Balance Sheet'!L54)/('Balance Sheet'!L33-'Balance Sheet'!L63) -> 0.48308083 | M32: =('Balance Sheet'!M43+'Balance Sheet'!M54)/('Balance Sheet'!M33-'Balance Sheet'!M63) -> 0.49458868 | N32: =('Balance Sheet'!N43+'Balance Sheet'!N54)/('Balance Sheet'!N33-'Balance Sheet'!N63) -> 0.51037141 | O32: =('Balance Sheet'!O43+'Balance Sheet'!O54)/('Balance Sheet'!O33-'Balance Sheet'!O63) -> 0.46690514 | Q32: D/CE | R32: =('Balance Sheet'!R39+'Balance Sheet'!R46)/('Balance Sheet'!R31-'Balance Sheet'!R57) -> 0.65386091 | S32: =('Balance Sheet'!S39+'Balance Sheet'!S46)/('Balance Sheet'!S31-'Balance Sheet'!S57) -> 0.49020088 | T32: =('Balance Sheet'!T39+'Balance Sheet'!T46)/('Balance Sheet'!T31-'Balance Sheet'!T57) -> 0.67538409 | U32: =('Balance Sheet'!U39+'Balance Sheet'!U46)/('Balance Sheet'!U31-'Balance Sheet'!U57) -> 0.71631988 | V32: =('Balance Sheet'!V39+'Balance Sheet'!V46)/('Balance Sheet'!V31-'Balance Sheet'!V57) -> 0.84225739 | W32: =('Balance Sheet'!W39+'Balance Sheet'!W46)/('Balance Sheet'!W31-'Balance Sheet'!W57) -> 0.62171596 | Y32: D/CE | Z32: =('Balance Sheet'!Z40+'Balance Sheet'!Z48)/('Balance Sheet'!Z31-'Balance Sheet'!Z59) -> 0.36941148 | AA32: =('Balance Sheet'!AA40+'Balance Sheet'!AA48)/('Balance Sheet'!AA31-'Balance Sheet'!AA59) -> 0.29597906 | AB32: =('Balance Sheet'!AB40+'Balance Sheet'!AB48)/('Balance Sheet'!AB31-'Balance Sheet'!AB59) -> 0.57334984 | AC32: =('Balance Sheet'!AC40+'Balance Sheet'!AC48)/('Balance Sheet'!AC31-'Balance Sheet'!AC59) -> 0.54736475 | AD32: =('Balance Sheet'!AD40+'Balance Sheet'!AD48)/('Balance Sheet'!AD31-'Balance Sheet'!AD59) -> 0.51734678 | AE32: =('Balance Sheet'!AE40+'Balance Sheet'!AE48)/('Balance Sheet'!AE31-'Balance Sheet'!AE59) -> 0.52584037 | AG32: D/CE | AH32: =('Balance Sheet'!AH39+'Balance Sheet'!AH46)/('Balance Sheet'!AH31-'Balance Sheet'!AH55) -> 0.43909748 | AI32: =('Balance Sheet'!AI39+'Balance Sheet'!AI46)/('Balance Sheet'!AI31-'Balance Sheet'!AI55) -> 0.50389073 | AJ32: =('Balance Sheet'!AJ39+'Balance Sheet'!AJ46)/('Balance Sheet'!AJ31-'Balance Sheet'!AJ55) -> 0.50596382 | AK32: =('Balance Sheet'!AK39+'Balance Sheet'!AK46)/('Balance Sheet'!AK31-'Balance Sheet'!AK55) -> 0.46095506 | AL32: =('Balance Sheet'!AL39+'Balance Sheet'!AL46)/('Balance Sheet'!AL31-'Balance Sheet'!AL55) -> 0.39831647 | AM32: =('Balance Sheet'!AM39+'Balance Sheet'!AM46)/('Balance Sheet'!AM31-'Balance Sheet'!AM55) -> 0.38836369

Sheet WACC & Key Assumptions
A1: WACC & KEY ASSUMPTIONS | Q1: Company | R1: Change in EBIT (Historical) | S1: Change in CE | T1: Incremental ROCE (Historical) | U1: Change in EBIT (Forecast) | V1: Capex | W1: Depreciation | X1: Effective Capital | Y1: Raw ROCE (Forecast) | Z1: Adjusted ROCE (Forecast)
Q2: =N13 -> Adani Ports | R2: =(('Income Statement'!G20+'Income Statement'!G15)-('Income Statement'!B20+'Income Statement'!B15)) -> 9549.26 | S2: =(('Balance Sheet'!G36-'Balance Sheet'!G64)-('Balance Sheet'!B36-'Balance Sheet'!B64)) -> 59886.59 | T2: =R2/S2 -> 0.15945573 | U2: =DCF!H5-DCF!D5 -> 13559.748 | V2: =AVERAGE(DCF!D9:H9) -> 13203.434 | W2: =AVERAGE(DCF!D8:H8) -> 7218.8762 | X2: =IF(V2-W2<=0,V2,MAX(V2-W2,0.1*V2)) -> 5984.5576 | Y2: =U2/X2 -> 2.2657895 | Z2: =MIN(MAX(Y2,0.08),0.15) -> 0.15
A3: Component | B3: #VALUE! | C3: #VALUE! | D3: #VALUE! | E3: #VALUE! | F3: #VALUE! | Q3: =N14 -> Kalpataru | R3: =(('Income Statement'!O18+'Income Statement'!O13)-('Income Statement'!J18+'Income Statement'!J13)) -> 211.43 | S3: =(('Balance Sheet'!O33-'Balance Sheet'!O63)-('Balance Sheet'!J33-'Balance Sheet'!J63)) -> 1524.88 | T3: =R3/S3 -> 0.13865353 | U3: =DCF!Q5-DCF!M5 -> 789.44053 | V3: =AVERAGE(DCF!M9:Q9) -> 827.20824 | W3: =AVERAGE(DCF!M8:Q8) -> 733.34895 | X3: =IF(V3-W3<=0,V3,MAX(V3-W3,0.1*V3)) -> 93.859284 | Y3: =U3/X3 -> 8.4108945 | Z3: =MIN(MAX(Y3,0.08),0.15) -> 0.15
A4: Risk free rate | B4: 0.06399 | C4: 0.06399 | D4: 0.06399 | E4: 0.06399 | F4: 0.06399 | I4: Revenue CAGR | J4: Adani Ports | K4: =(Table19[[#This Row],[2030]]/Table19[[#This Row],[2026]])^(1/5)-1 -> 0.1211603 | Q4: =N15 -> KEC | R4: =(('Income Statement'!W17+'Income Statement'!W12)-('Income Statement'!R17+'Income Statement'!R12)) -> 292.83 | S4: =(('Balance Sheet'!W31-'Balance Sheet'!W57)-('Balance Sheet'!R31-'Balance Sheet'!R57)) -> 2799.77 | T4: =R4/S4 -> 0.10459073 | U4: =DCF!Z5-DCF!V5 -> 741.69339 | V4: =AVERAGE(DCF!V9:Z9) -> 344.44525 | W4: =AVERAGE(DCF!V8:Z8) -> 301.76867 | X4: =IF(V4-W4<=0,V4,MAX(V4-W4,0.1*V4)) -> 42.676578 | Y4: =U4/X4 -> 17.379402 | Z4: =MIN(MAX(Y4,0.08),0.15) -> 0.15
A5: Beta | B5: ='Company Info'!B9 -> 1.4608 | C5: ='Company Info'!C9 -> 0.5909 | D5: ='Company Info'!D9 -> 0.6763 | E5: ='Company Info'!E9 -> 1.0837 | F5: ='Company Info'!F9 -> 1.4107 | I5: Revenue CAGR | J5: Kalpataru | K5: =(DCF!Q4/DCF!M4)^(1/5)-1 -> 0.078232555 | Q5: =N16 -> L&T | R5: =(('Income Statement'!AE24+'Income Statement'!AE21)-('Income Statement'!Z24+'Income Statement'!Z21)) -> 10210.77 | S5: =(('Balance Sheet'!AE31-'Balance Sheet'!AE59)-('Balance Sheet'!Z31-'Balance Sheet'!Z59)) -> 117376.89 | T5: =R5/S5 -> 0.086991315 | U5: =Table222629[[#This Row],[2030]]-Table222629[[#This Row],[2026]] -> 18691.306 | V5: =AVERAGE(DCF!AE9:AI9) -> 6667.7614 | W5: =AVERAGE(DCF!AE8:AI8) -> 6103.4298 | X5: =IF(V5-W5<=0,V5,MAX(V5-W5,0.1*V5)) -> 666.77614 | Y5: =U5/X5 -> 28.032356 | Z5: =MIN(MAX(Y5,0.08),0.15) -> 0.15
A6: Market risk premium | B6: 0.0675 | C6: 0.0675 | D6: 0.0675 | E6: 0.0675 | F6: 0.0675 | I6: Revenue CAGR | J6: KEC | K6: =(DCF!Z4/DCF!V4)^(1/5)-1 -> 0.083914725 | Q6: =N17 -> RVNL | R6: =(('Income Statement'!AM16+'Income Statement'!AM11)-('Income Statement'!AH16+'Income Statement'!AH11)) -> 1737.041 | S6: =(('Balance Sheet'!AM31-'Balance Sheet'!AM55)-('Balance Sheet'!AH31-'Balance Sheet'!AH55)) -> 4182.1219 | T6: =R6/S6 -> 0.4153492 | U6: =DCF!AR5-DCF!AN5 -> 1785.391 | V6: =AVERAGE(DCF!AN9:AR9) -> 211.63431 | W6: =AVEDEV(DCF!AN9:AR9) -> 34.490905 | X6: =IF(V6-W6<=0,V6,MAX(V6-W6,0.1*V6)) -> 177.14341 | Y6: =U6/X6 -> 10.078789 | Z6: =MIN(MAX(Y6,0.08),0.15) -> 0.15
A7: Cost of equity | B7: =B4+(B5*B6) -> 0.162594 | C7: =C4+(C5*C6) -> 0.10387575 | D7: =D4+(D5*D6) -> 0.10964025 | E7: =E4+(E5*E6) -> 0.13713975 | F7: =F4+(F5*F6) -> 0.15921225 | I7: Revenue CAGR | J7: L&T | K7: =(DCF!AI4/DCF!AE4)^(1/5)-1 -> 0.078127133 | Q7: =N18 -> Average | T7: =AVERAGE(T2:T6) -> 0.1810081 | Y7: =AVERAGE(Y2:Y6) -> 13.233446 | Z7: =AVERAGE(Z2:Z6) -> 0.15
A8: Cost of debt | B8: ='Income Statement'!G15/(AVERAGE('Balance Sheet'!F46:G46)+AVERAGE('Balance Sheet'!F54:G54)) -> 0.054986217 | C8: ='Income Statement'!O13/(AVERAGE('Balance Sheet'!N43:O43)+AVERAGE('Balance Sheet'!N54:O54)) -> 0.14239141 | D8: ='Income Statement'!W12/(AVERAGE('Balance Sheet'!V39:W39)+AVERAGE('Balance Sheet'!V46:W46)) -> 0.17720826 | E8: =('Income Statement'!AE18+'Income Statement'!AE21)/(AVERAGE('Balance Sheet'!AD40:AE40)+AVERAGE('Balance Sheet'!AD48:AE48)) -> 0.10845561 | F8: ='Income Statement'!AM11/(AVERAGE('Balance Sheet'!AL39:AM39)+AVERAGE('Balance Sheet'!AL46:AM46)) -> 0.099938647 | I8: Revenue CAGR | J8: RVNL | K8: =(DCF!AR4/DCF!AN4)^(1/5)-1 -> 0.11319802 | M8: GDP g | N8: 2020 | O8: =AVERAGE(-5.8%,9.7%) -> 0.0195
A9: Tax | B9: 0.25 | C9: 0.25 | D9: 0.25 | E9: 0.25 | F9: 0.25 | I9: Revenue CAGR | J9: Average | K9: =AVERAGE(K4:K8) -> 0.094926546 | M9: GDP g | N9: 2025 | O9: 0.078
A10: Cost of debt (after tax) | B10: =B8*(1-B9) -> 0.041239662 | C10: =C8*(1-C9) -> 0.10679356 | D10: =D8*(1-D9) -> 0.1329062 | E10: =E8*(1-E9) -> 0.081341709 | F10: =F8*(1-F9) -> 0.074953985 | I10: Earnings Growth | J10: Adani Ports | K10: =('Income Statement'!G30-'Income Statement'!B30)/'Income Statement'!B30 -> 1.9227566 | M10: GDP g | N10: Change | O10: =O9-O8 -> 0.0585
A11: Market Equity | B11: ='Company Info'!B14 -> 312852.9 | C11: ='Company Info'!C14 -> 22130.41 | D11: ='Company Info'!D14 -> 20213.9 | E11: ='Company Info'!E14 -> 534069.3 | F11: ='Company Info'!F14 -> 66303.64 | I11: Earnings Growth | J11: Kalpataru | K11: =('Income Statement'!O27-'Income Statement'!J27)/'Income Statement'!J27 -> 0.4560692 | M11: GDP g | N11: Sensitivity | O11: =K15/O10 -> 14.699628
A12: Market Debt | B12: ='Balance Sheet'!G46+'Balance Sheet'!G54 -> 45810.03 | C12: ='Balance Sheet'!O43+'Balance Sheet'!O54 -> 4188.62 | D12: ='Balance Sheet'!W39+'Balance Sheet'!W46 -> 3701.1 | E12: ='Balance Sheet'!AE40+'Balance Sheet'!AE48 -> 93364.64 | F12: ='Balance Sheet'!AM39+'Balance Sheet'!AM46 -> 5389.02 | I12: Earnings Growth | J12: KEC | K12: =('Income Statement'!W24-'Income Statement'!R24)/'Income Statement'!R24 -> 0.0092304428
A13: Total Capital | B13: =B11+B12 -> 358662.93 | C13: =C11+C12 -> 26319.03 | D13: =D11+D12 -> 23915 | E13: =E11+E12 -> 627433.94 | F13: =F11+F12 -> 71692.66 | I13: Earnings Growth | J13: L&T | K13: =('Income Statement'!AE42-'Income Statement'!Z42)/'Income Statement'!Z42 -> 0.62225774 | M13: Capex CAGR | N13: =J4 -> Adani Ports | O13: =(DCF!H9/DCF!D9)^(1/5)-1 -> 0.1211603
A14: Weight of Equity | B14: =B11/B13 -> 0.87227554 | C14: =C11/C13 -> 0.84085204 | D14: =D11/D13 -> 0.84523939 | E14: =E11/E13 -> 0.85119606 | F14: =F11/F13 -> 0.92483164 | I14: Earnings Growth | J14: RVNL | K14: =('Income Statement'!AM25-'Income Statement'!AH25)/'Income Statement'!AH25 -> 1.2893273 | M14: Capex CAGR | N14: =J5 -> Kalpataru | O14: =(DCF!Q9/DCF!M9)^(1/5)-1 -> 0.078232555
A15: Weight of Debt | B15: =B12/B13 -> 0.12772446 | C15: =C12/C13 -> 0.15914796 | D15: =D12/D13 -> 0.15476061 | E15: =E12/E13 -> 0.14880394 | F15: =F12/F13 -> 0.075168365 | I15: Earnings Growth | J15: Average | K15: =AVERAGE(K10:K14) -> 0.85992826 | M15: Capex CAGR | N15: =J6 -> KEC | O15: =(DCF!Z9/DCF!V9)^(1/5)-1 -> 0.083914725
A16: WACC | B16: =(B7*B14)+(B10*B15) -> 0.14709408 | C16: =(C7*C14)+(C10*C15) -> 0.10434011 | D16: =(D7*D14)+(D10*D15) -> 0.1132409 | E16: =(E7*E14)+(E10*E15) -> 0.12883678 | F16: =(F7*F14)+(F10*F15) -> 0.15287869 | I16: Capex Intensity | J16: Adani Ports | K16: =AVERAGE(DCF!D9:H9)/AVERAGE(DCF!D4:H4) -> 0.26018274 | M16: Capex CAGR | N16: =J7 -> L&T | O16: =(DCF!AI9/DCF!AE9)^(1/5)-1 -> 0.078127133
A17: Revenue CAGR | B17: =('Income Statement'!G8/'Income Statement'!B8)^(1/6)-1 -> 0.15367807 | C17: =('Income Statement'!O7/'Income Statement'!J7)^(1/6)-1 -> 0.098728906 | D17: =('Income Statement'!W7/'Income Statement'!R7)^(1/6)-1 -> 0.1059714 | E17: =('Income Statement'!AE8/'Income Statement'!Z8)^(1/6)-1 -> 0.098594625 | F17: =('Income Statement'!AM7/'Income Statement'!AH7)^(1/6)-1 -> 0.14344566 | I17: Capex Intensity | J17: Kalpataru | K17: =AVERAGE(DCF!M9:Q9)/AVERAGE(DCF!M4:Q4) -> 0.027623216 | M17: Capex CAGR | N17: =J8 -> RVNL | O17: =(DCF!AR9/DCF!AN9)^(1/5)-1 -> 0.11319802
A18: EBIT Margin | B18: =(AVERAGE('Income Statement'!B20:G20)+AVERAGE('Income Statement'!B15:G15))/AVERAGE('Income Statement'!B8:G8) -> 0.47045585 | C18: =(AVERAGE(Table7[[#This Row],[2020]:[2025]])+AVERAGE('Income Statement'!J13:O13))/AVERAGE('Income Statement'!J7:O7) -> 0.070203566 | D18: =(AVERAGE('Income Statement'!R17:W17)+AVERAGE('Income Statement'!R12:W12))/AVERAGE('Income Statement'!R7:W7) -> 0.061670003 | E18: =(AVERAGE('Income Statement'!Z24:AE24)+AVERAGE(Table9[[#This Row],[2020]:[2025]])+AVERAGE('Income Statement'!Z21:AE21))/AVERAGE('Income Statement'!Z8:AE8) -> 0.14338295 | F18: =(AVERAGE('Income Statement'!AH16:AM16)+AVERAGE('Income Statement'!AH11:AM11))/AVERAGE('Income Statement'!AH7:AM7) -> 0.095377141 | I18: Capex Intensity | J18: KEC | K18: =AVERAGE(DCF!V9:Z9)/AVERAGE(DCF!V4:Z4) -> 0.011500054 | M18: Capex CAGR | N18: Average | O18: =AVERAGE(O13:O17) -> 0.094926546
A19: Depreciation | B19: =AVERAGE('Income Statement'!B16:G16)/AVERAGE('Income Statement'!B8:G8) -> 0.14225292 | C19: =AVERAGE('Income Statement'!J14:O14)/AVERAGE('Income Statement'!J7:O7) -> 0.024488945 | D19: =AVERAGE('Income Statement'!R14:W14)/AVERAGE('Income Statement'!R7:W7) -> 0.010075204 | E19: =AVERAGE('Income Statement'!Z22:AE22)/AVERAGE('Income Statement'!Z8:AE8) -> 0.017558631 | F19: =AVERAGE('Income Statement'!AH12:AM12)/AVERAGE('Income Statement'!AH7:AM7) -> 0.0010693426 | I19: Capex Intensity | J19: L&T | K19: =AVERAGE(DCF!AE9:AI9)/AVERAGE(DCF!AE4:AI4) -> 0.019182126 | M19: Earnings | N19: =N13 -> Adani Ports | O19: =(DCF!H7/DCF!D7)^(1/5)-1 -> 0.1211603
A20: CapEx | B20: =ABS(AVERAGE('Cash Flow Statement'!B41:G41))/AVERAGE('Income Statement'!B8:G8) -> 0.26018274 | C20: =ABS(AVERAGE('Cash Flow Statement'!J31:O31))/AVERAGE('Income Statement'!J7:O7) -> 0.027623216 | D20: =ABS(AVERAGE('Cash Flow Statement'!R35:W35))/AVERAGE('Income Statement'!R7:W7) -> 0.011500054 | E20: =ABS(AVERAGE('Cash Flow Statement'!Z38:AE38))/AVERAGE('Income Statement'!Z8:AE8) -> 0.019182126 | F20: =ABS(AVERAGE('Cash Flow Statement'!AH37:AM37)+AVERAGE('Cash Flow Statement'!AH38:AJ38))/AVERAGE('Income Statement'!AH7:AM7) -> 0.0060259863 | I20: Capex Intensity | J20: RVNL | K20: =AVERAGE(DCF!AN9:AR9)/AVERAGE(DCF!AN4:AR4) -> 0.0060259863 | M20: Earnings | N20: =N14 -> Kalpataru | O20: =(DCF!Q7/DCF!M7)^(1/5)-1 -> 0.078232555
A21: Terminal Growth | B21: 0.065 | C21: 0.065 | D21: 0.065 | E21: 0.065 | F21: 0.065 | I21: Capex Intensity | J21: Average | K21: =AVERAGE(K16:K20) -> 0.064902825 | M21: Earnings | N21: =N15 -> KEC | O21: =(DCF!Z7/DCF!V7)^(1/5)-1 -> 0.083914725
M22: Earnings | N22: =N16 -> L&T | O22: =(DCF!AI7/DCF!AE7)^(1/5)-1 -> 0.078127133
M23: Earnings | N23: =N17 -> RVNL | O23: =(DCF!AR7/DCF!AN7)^(1/5)-1 -> 0.11319802
M24: Earnings | N24: =N18 -> Average | O24: =AVERAGE(O19:O23) -> 0.094926546

Sheet DCF
A1: DCF VALUATION
G2: #VALUE! | P2: #VALUE! | Y2: #VALUE! | AH2: #VALUE! | AQ2: #VALUE!
A3: Particulars | B3: 2025 | C3: Growth | D3: 2026 | E3: 2027 | F3: 2028 | G3: 2029 | H3: 2030 | J3: Particulars | K3: 2025 | L3: Growth | M3: 2026 | N3: 2027 | O3: 2028 | P3: 2029 | Q3: 2030 | S3: Particulars | T3: 2025 | U3: Growth | V3: 2026 | W3: 2027 | X3: 2028 | Y3: 2029 | Z3: 2030 | AB3: Particulars | AC3: 2025 | AD3: Growth | AE3: 2026 | AF3: 2027 | AG3: 2028 | AH3: 2029 | AI3: 2030 | AK3: Particulars | AL3: 2025 | AM3: Growth | AN3: 2026 | AO3: 2027 | AP3: 2028 | AQ3: 2029 | AR3: 2030
A4: Revenue | B4: ='Income Statement'!G8 -> 32383.08 | C4: ='WACC & Key Assumptions'!B17 -> 0.15367807 | D4: =Table19[[#This Row],[2025]]*(1+C4) -> 37359.649 | E4: =Table19[[#This Row],[2026]]*(1+$C$4) -> 43101.008 | F4: =Table19[[#This Row],[2027]]*(1+$C$4) -> 49724.688 | G4: =Table19[[#This Row],[2028]]*(1+$C$4) -> 57366.282 | H4: =Table19[[#This Row],[2029]]*(1+$C$4) -> 66182.222 | J4: Revenue | K4: ='Income Statement'!O7 -> 22378.26 | L4: ='WACC & Key Assumptions'!C17 -> 0.098728906 | M4: =Table22[[#This Row],[2025]]*(1+L4) -> 24587.641 | N4: =Table22[[#This Row],[2026]]*(1+$L$4) -> 27015.152 | O4: =Table22[[#This Row],[2027]]*(1+$L$4) -> 29682.328 | P4: =Table22[[#This Row],[2028]]*(1+$L$4) -> 32612.832 | Q4: =Table22[[#This Row],[2029]]*(1+$L$4) -> 35832.661 | S4: Revenue | T4: ='Income Statement'!W7 -> 21917.56 | U4: ='WACC & Key Assumptions'!D17 -> 0.1059714 | V4: =Table2226[[#This Row],[2025]]*(1+U4) -> 24240.194 | W4: =Table2226[[#This Row],[2026]]*(1+$U$4) -> 26808.962 | X4: =Table2226[[#This Row],[2027]]*(1+$U$4) -> 29649.945 | Y4: =Table2226[[#This Row],[2028]]*(1+$U$4) -> 32791.991 | Z4: =Table2226[[#This Row],[2029]]*(1+$U$4) -> 36267.004 | AB4: Revenue | AC4: ='Income Statement'!AE8 -> 259859.27 | AD4: ='WACC & Key Assumptions'!E17 -> 0.098594625 | AE4: =Table222629[[#This Row],[2025]]*(1+AD4) -> 285480 | AF4: =Table222629[[#This Row],[2026]]*(1+$AD$4) -> 313626.79 | AG4: =Table222629[[#This Row],[2027]]*(1+$AD$4) -> 344548.71 | AH4: =Table222629[[#This Row],[2028]]*(1+$AD$4) -> 378519.36 | AI4: =Table222629[[#This Row],[2029]]*(1+$AD$4) -> 415839.33 | AK4: Revenue | AL4: ='Income Statement'!AM7 -> 23074.8 | AM4: ='WACC & Key Assumptions'!F17 -> 0.14344566 | AN4: =Table22262931[[#This Row],[2025]]*(1+AM4) -> 26384.78 | AO4: =Table22262931[[#This Row],[2026]]*(1+$AM$4) -> 30169.562 | AP4: =Table22262931[[#This Row],[2027]]*(1+$AM$4) -> 34497.255 | AQ4: =Table22262931[[#This Row],[2028]]*(1+$AM$4) -> 39445.736 | AR4: =Table22262931[[#This Row],[2029]]*(1+$AM$4) -> 45104.056
A5: EBIT | B5: ='Income Statement'!G20+'Income Statement'!G15 -> 15669.34 | C5: ='WACC & Key Assumptions'!B18 -> 0.47045585 | D5: =D4*$C$5 -> 17576.065 | E5: =E4*$C$5 -> 20277.121 | F5: =F4*$C$5 -> 23393.27 | G5: =G4*$C$5 -> 26988.303 | H5: =H4*$C$5 -> 31135.813 | J5: EBIT | K5: ='Income Statement'!O18+'Income Statement'!O13 -> 1399.33 | L5: ='WACC & Key Assumptions'!C18 -> 0.070203566 | M5: =M4*$L$5 -> 1726.1401 | N5: =N4*$L$5 -> 1896.56 | O5: =O4*$L$5 -> 2083.8053 | P5: =P4*$L$5 -> 2289.5371 | Q5: =Q4*$L$5 -> 2515.5806 | S5: EBIT | T5: ='Income Statement'!W17+'Income Statement'!W12 -> 1391.08 | U5: ='WACC & Key Assumptions'!D18 -> 0.061670003 | V5: =V4*$U$5 -> 1494.8929 | W5: =W4*$U$5 -> 1653.3088 | X5: =X4*$U$5 -> 1828.5122 | Y5: =Y4*$U$5 -> 2022.2822 | Z5: =Z4*$U$5 -> 2236.5863 | AB5: EBIT | AC5: ='Income Statement'!AE24+'Income Statement'!AE21+'Income Statement'!AE18 -> 32740.61 | AD5: ='WACC & Key Assumptions'!E18 -> 0.14338295 | AE5: =AE4*$AD$5 -> 40932.965 | AF5: =AF4*$AD$5 -> 44968.735 | AG5: =AG4*$AD$5 -> 49402.411 | AH5: =AH4*$AD$5 -> 54273.223 | AI5: =AI4*$AD$5 -> 59624.271 | AK5: EBIT | AL5: ='Income Statement'!AM16+'Income Statement'!AM11 -> 2517.46 | AM5: ='WACC & Key Assumptions'!F18 -> 0.095377141 | AN5: =AN4*$AM$5 -> 2516.5049 | AO5: =AO4*$AM$5 -> 2877.4866 | AP5: =AP4*$AM$5 -> 3290.2495 | AQ5: =AQ4*$AM$5 -> 3762.2215 | AR5: =AR4*$AM$5 -> 4301.8959
A6: Tax | B6: ='Income Statement'!G29 -> 1968.36 | C6: 0.25 | D6: =D5*$C$6 -> 4394.0164 | E6: =E5*$C$6 -> 5069.2803 | F6: =F5*$C$6 -> 5848.3175 | G6: =G5*$C$6 -> 6747.0757 | H6: =H5*$C$6 -> 7783.9533 | J6: Tax | K6: ='Income Statement'!O26 -> 255.53 | L6: 0.25 | M6: =M5*$L$6 -> 431.53502 | N6: =N5*$L$6 -> 474.14 | O6: =O5*$L$6 -> 520.95133 | P6: =P5*$L$6 -> 572.38428 | Q6: =Q5*$L$6 -> 628.89515 | S6: Tax | T6: ='Income Statement'!W23 -> 156.75 | U6: =0.25 -> 0.25 | V6: =V5*$U$6 -> 373.72322 | W6: =W5*$U$6 -> 413.32719 | X6: =X5*$U$6 -> 457.12805 | Y6: =Y5*$U$6 -> 505.57055 | Z6: =Z5*$U$6 -> 559.14657 | AB6: Tax | AC6: =ABS('Income Statement'!AE34) -> 5891.4 | AD6: 0.25 | AE6: =AE5*$AD$6 -> 10233.241 | AF6: =AF5*$AD$6 -> 11242.184 | AG6: =AG5*$AD$6 -> 12350.603 | AH6: =AH5*$AD$6 -> 13568.306 | AI6: =AI5*$AD$6 -> 14906.068 | AK6: Tax | AL6: ='Income Statement'!AM24 -> 479.44 | AM6: 0.25 | AN6: =AN5*$AM$6 -> 629.12622 | AO6: =AO5*$AM$6 -> 719.37164 | AP6: =AP5*$AM$6 -> 822.56238 | AQ6: =AQ5*$AM$6 -> 940.55539 | AR6: =AR5*$AM$6 -> 1075.474
A7: NOPAT | B7: =B5-B6 -> 13700.98 | D7: =D5-D6 -> 13182.049 | E7: =E5-E6 -> 15207.841 | F7: =F5-F6 -> 17544.953 | G7: =G5-G6 -> 20241.227 | H7: =H5-H6 -> 23351.86 | J7: NOPAT | K7: =K5-K6 -> 1143.8 | M7: =M5-M6 -> 1294.6051 | N7: =N5-N6 -> 1422.42 | O7: =O5-O6 -> 1562.854 | P7: =P5-P6 -> 1717.1528 | Q7: =Q5-Q6 -> 1886.6855 | S7: NOPAT | T7: =T5-T6 -> 1234.33 | V7: =V5-V6 -> 1121.1697 | W7: =W5-W6 -> 1239.9816 | X7: =X5-X6 -> 1371.3842 | Y7: =Y5-Y6 -> 1516.7116 | Z7: =Z5-Z6 -> 1677.4397 | AB7: NOPAT | AC7: =AC5-AC6 -> 26849.21 | AE7: =AE5-AE6 -> 30699.724 | AF7: =AF5-AF6 -> 33726.552 | AG7: =AG5-AG6 -> 37051.808 | AH7: =AH5-AH6 -> 40704.917 | AI7: =AI5-AI6 -> 44718.203 | AK7: NOPAT | AL7: =AL5-AL6 -> 2038.02 | AN7: =AN5-AN6 -> 1887.3787 | AO7: =AO5-AO6 -> 2158.1149 | AP7: =AP5-AP6 -> 2467.6872 | AQ7: =AQ5-AQ6 -> 2821.6662 | AR7: =AR5-AR6 -> 3226.4219
A8: Depreciation | B8: ='Income Statement'!G16 -> 4378.93 | C8: ='WACC & Key Assumptions'!B19 -> 0.14225292 | D8: =D4*$C$8 -> 5314.5192 | E8: =E4*$C$8 -> 6131.2443 | F8: =F4*$C$8 -> 7073.4821 | G8: =G4*$C$8 -> 8160.5212 | H8: =H4*$C$8 -> 9414.6143 | J8: Depreciation | K8: ='Income Statement'!O14 -> 497.27 | L8: ='WACC & Key Assumptions'!C19 -> 0.024488945 | M8: =M4*$L$8 -> 602.12539 | N8: =N4*$L$8 -> 661.57257 | O8: =O4*$L$8 -> 726.8889 | P8: =P4*$L$8 -> 798.65385 | Q8: =Q4*$L$8 -> 877.50407 | S8: Depreciation | T8: ='Income Statement'!W14 -> 183.68 | U8: ='WACC & Key Assumptions'!D19 -> 0.010075204 | V8: =V4*$U$8 -> 244.2249 | W8: =W4*$U$8 -> 270.10575 | X8: =X4*$U$8 -> 298.72924 | Y8: =Y4*$U$8 -> 330.38599 | Z8: =Z4*$U$8 -> 365.39746 | AB8: Depreciation | AC8: ='Income Statement'!AE22 -> 4121.18 | AD8: ='WACC & Key Assumptions'!E19 -> 0.017558631 | AE8: =AE4*$AD$8 -> 5012.6378 | AF8: =AF4*$AD$8 -> 5506.857 | AG8: =AG4*$AD$8 -> 6049.8035 | AH8: =AH4*$AD$8 -> 6646.2816 | AI8: =AI4*$AD$8 -> 7301.5692 | AK8: Depreciation | AL8: ='Income Statement'!AM12 -> 20.94 | AM8: ='WACC & Key Assumptions'!F19 -> 0.0010693426 | AN8: =AN4*$AM$8 -> 28.214369 | AO8: =AO4*$AM$8 -> 32.261598 | AP8: =AP4*$AM$8 -> 36.889384 | AQ8: =AQ4*$AM$8 -> 42.181006 | AR8: =AR4*$AM$8 -> 48.231688
A9: CapEx | B9: =ABS('Cash Flow Statement'!G41) -> 8048.92 | C9: ='WACC & Key Assumptions'!B20 -> 0.26018274 | D9: =D4*$C$9 -> 9720.336 | E9: =E4*$C$9 -> 11214.139 | F9: =F4*$C$9 -> 12937.506 | G9: =G4*$C$9 -> 14925.717 | H9: =H4*$C$9 -> 17219.472 | J9: CapEx | K9: =ABS('Cash Flow Statement'!O31) -> 574.62 | L9: ='WACC & Key Assumptions'!C20 -> 0.027623216 | M9: =M4*$L$9 -> 679.18973 | N9: =N4*$L$9 -> 746.24539 | O9: =O4*$L$9 -> 819.92138 | P9: =P4*$L$9 -> 900.87132 | Q9: =Q4*$L$9 -> 989.81336 | S9: CapEx | T9: =ABS('Cash Flow Statement'!W35) -> 182.52 | U9: ='WACC & Key Assumptions'!D20 -> 0.011500054 | V9: =V4*$U$9 -> 278.76355 | W9: =W4*$U$9 -> 308.30452 | X9: =X4*$U$9 -> 340.97598 | Y9: =Y4*$U$9 -> 377.10968 | Z9: =Z4*$U$9 -> 417.07252 | AB9: CapEx | AC9: =ABS('Cash Flow Statement'!AE38) -> 4418.83 | AD9: ='WACC & Key Assumptions'!E20 -> 0.019182126 | AE9: =AE4*$AD$9 -> 5476.1133 | AF9: =AF4*$AD$9 -> 6016.0286 | AG9: =AG4*$AD$9 -> 6609.1767 | AH9: =AH4*$AD$9 -> 7260.806 | AI9: =AI4*$AD$9 -> 7976.6824 | AK9: CapEx | AL9: =ABS('Cash Flow Statement'!AM37) -> 431.63 | AM9: ='WACC & Key Assumptions'!F20 -> 0.0060259863 | AN9: =AN4*$AM$9 -> 158.99432 | AO9: =AO4*$AM$9 -> 181.80137 | AP9: =AP4*$AM$9 -> 207.87998 | AQ9: =AQ4*$AM$9 -> 237.69947 | AR9: =AR4*$AM$9 -> 271.79642
A10: Δ Working Capital | B10: =('Balance Sheet'!G70-'Balance Sheet'!F70) -> -3051.29 | C10: =ABS(('Balance Sheet'!G70)/'Balance Sheet'!B70)^(1/6)-1 -> -0.17902492 | D10: =Table19[[#This Row],[2025]]*(1+C10) -> -2505.033 | E10: =Table19[[#This Row],[2026]]*(1+$C$10) -> -2056.5697 | F10: =Table19[[#This Row],[2027]]*(1+$C$10) -> -1688.3925 | G10: =Table19[[#This Row],[2028]]*(1+$C$10) -> -1386.1281 | H10: =Table19[[#This Row],[2029]]*(1+$C$10) -> -1137.9766 | J10: Δ Working Capital | K10: ='Balance Sheet'!O70-'Balance Sheet'!N70 -> 991.32 | L10: =('Balance Sheet'!O70/'Balance Sheet'!J70)^(1/6)-1 -> 0.10226455 | M10: =Table22[[#This Row],[2025]]*(1+L10) -> 1092.6969 | N10: =Table22[[#This Row],[2026]]*(1+$L$10) -> 1204.4411 | O10: =Table22[[#This Row],[2027]]*(1+$L$10) -> 1327.6127 | P10: =Table22[[#This Row],[2028]]*(1+$L$10) -> 1463.3804 | Q10: =Table22[[#This Row],[2029]]*(1+$L$10) -> 1613.0323 | S10: Δ Working Capital | T10: ='Balance Sheet'!W70-'Balance Sheet'!V70 -> 1535.61 | U10: =('Balance Sheet'!W70/'Balance Sheet'!R70)^(1/6)-1 -> 0.15991639 | V10: =Table2226[[#This Row],[2025]]*(1+U10) -> 1781.1792 | W10: =Table2226[[#This Row],[2026]]*(1+$U$10) -> 2066.019 | X10: =Table2226[[#This Row],[2027]]*(1+$U$10) -> 2396.4093 | Y10: =Table2226[[#This Row],[2028]]*(1+$U$10) -> 2779.6344 | Z10: =Table2226[[#This Row],[2029]]*(1+$U$10) -> 3224.1435 | AB10: Δ Working Capital | AC10: ='Balance Sheet'!AE70-'Balance Sheet'!AD70 -> 1891.67 | AD10: =('Balance Sheet'!AE70/'Balance Sheet'!Z70)^(1/6)-1 -> 0.20375817 | AE10: =Table222629[[#This Row],[2025]]*(1+AD10) -> 2277.1132 | AF10: =Table222629[[#This Row],[2026]]*(1+$AD$10) -> 2741.0936 | AG10: =Table222629[[#This Row],[2027]]*(1+$AD$10) -> 3299.6139 | AH10: =Table222629[[#This Row],[2028]]*(1+$AD$10) -> 3971.9372 | AI10: =Table222629[[#This Row],[2029]]*(1+$AD$10) -> 4781.2518 | AK10: Δ Working Capital | AL10: ='Balance Sheet'!AM70-'Balance Sheet'!AL70 -> 697.73 | AM10: =('Balance Sheet'!AM70/'Balance Sheet'!AK70)^(1/6)-1 -> 0.041191939 | AN10: =Table22262931[[#This Row],[2025]]*(1+$AM$10) -> 726.47085 | AO10: =Table22262931[[#This Row],[2026]]*(1+$AM$10) -> 756.39559 | AP10: =Table22262931[[#This Row],[2027]]*(1+$AM$10) -> 787.553 | AQ10: =Table22262931[[#This Row],[2028]]*(1+$AM$10) -> 819.99383 | AR10: =Table22262931[[#This Row],[2029]]*(1+$AM$10) -> 853.77097
A11: Free Cash Flow to Firm | B11: =B7+B8-B9-B10 -> 13082.28 | D11: =D7+D8-D9-D10 -> 11281.265 | E11: =E7+E8-E9-E10 -> 12181.516 | F11: =F7+F8-F9-F10 -> 13369.321 | G11: =G7+G8-G9-G10 -> 14862.16 | H11: =H7+H8-H9-H10 -> 16684.979 | J11: Free Cash Flow to Firm | K11: =K7+K8-K9-K10 -> 75.13 | M11: =M7+M8-M9-M10 -> 124.84383 | N11: =N7+N8-N9-N10 -> 133.30613 | O11: =O7+O8-O9-O10 -> 142.20883 | P11: =P7+P8-P9-P10 -> 151.55498 | Q11: =Q7+Q8-Q9-Q10 -> 161.34384 | S11: Free Cash Flow to Firm | T11: =T7+T8-T9-T10 -> -300.12 | V11: =V7+V8-V9-V10 -> -694.54821 | W11: =W7+W8-W9-W10 -> -864.23616 | X11: =X7+X8-X9-X10 -> -1067.2719 | Y11: =Y7+Y8-Y9-Y10 -> -1309.6464 | Z11: =Z7+Z8-Z9-Z10 -> -1598.3789 | AB11: Free Cash Flow to Firm | AC11: =AC7+AC8-AC9-AC10 -> 24659.89 | AE11: =AE7+AE8-AE9-AE10 -> 27959.135 | AF11: =AF7+AF8-AF9-AF10 -> 30476.286 | AG11: =AG7+AG8-AG9-AG10 -> 33192.821 | AH11: =AH7+AH8-AH9-AH10 -> 36118.456 | AI11: =AI7+AI8-AI9-AI10 -> 39261.838 | AK11: Free Cash Flow to Firm | AL11: =AL7+AL8-AL9-AL10 -> 929.6 | AN11: =AN7+AN8-AN9-AN10 -> 1030.1279 | AO11: =AO7+AO8-AO9-AO10 -> 1252.1796 | AP11: =AP7+AP8-AP9-AP10 -> 1509.1436 | AQ11: =AQ7+AQ8-AQ9-AQ10 -> 1806.1539 | AR11: =AR7+AR8-AR9-AR10 -> 2149.0862
A12: Discount Factor | D12: =1/(1+'WACC & Key Assumptions'!$B$16)^1 -> 0.87176807 | E12: =1/(1+'WACC & Key Assumptions'!$B$16)^2 -> 0.75997958 | F12: =1/(1+'WACC & Key Assumptions'!$B$16)^3 -> 0.66252593 | G12: =1/(1+'WACC & Key Assumptions'!$B$16)^4 -> 0.57756896 | H12: =1/(1+'WACC & Key Assumptions'!$B$16)^5 -> 0.50350618 | J12: Discount Factor | M12: =1/(1+'WACC & Key Assumptions'!$C$16)^1 -> 0.90551814 | N12: =1/(1+'WACC & Key Assumptions'!$C$16)^2 -> 0.81996309 | O12: =1/(1+'WACC & Key Assumptions'!$C$16)^3 -> 0.74249145 | P12: =1/(1+'WACC & Key Assumptions'!$C$16)^4 -> 0.67233947 | Q12: =1/(1+'WACC & Key Assumptions'!$C$16)^5 -> 0.60881559 | S12: Discount Factor | V12: =1/(1+'WACC & Key Assumptions'!$D$16)^1 -> 0.89827817 | W12: =1/(1+'WACC & Key Assumptions'!$D$16)^2 -> 0.80690367 | X12: =1/(1+'WACC & Key Assumptions'!$D$16)^3 -> 0.72482395 | Y12: =1/(1+'WACC & Key Assumptions'!$D$16)^4 -> 0.65109353 | Z12: =1/(1+'WACC & Key Assumptions'!$D$16)^5 -> 0.58486311 | AB12: Discount Factor | AE12: =1/(1+'WACC & Key Assumptions'!$E$16)^1 -> 0.88586766 | AF12: =1/(1+'WACC & Key Assumptions'!$E$16)^2 -> 0.78476151 | AG12: =1/(1+'WACC & Key Assumptions'!$E$16)^3 -> 0.69519485 | AH12: =1/(1+'WACC & Key Assumptions'!$E$16)^4 -> 0.61585063 | AI12: =1/(1+'WACC & Key Assumptions'!$E$16)^5 -> 0.54556216 | AK12: Discount Factor | AN12: =1/(1+'WACC & Key Assumptions'!$F$16)^1 -> 0.86739395 | AO12: =1/(1+'WACC & Key Assumptions'!$F$16)^2 -> 0.75237226 | AP12: =1/(1+'WACC & Key Assumptions'!$F$16)^3 -> 0.65260314 | AQ12: =1/(1+'WACC & Key Assumptions'!$F$16)^4 -> 0.56606401 | AR12: =1/(1+'WACC & Key Assumptions'!$F$16)^5 -> 0.4910005
A13: PV of FCFF | D13: =D11*D12 -> 9834.6469 | E13: =E11*E12 -> 9257.7037 | F13: =F11*F12 -> 8857.5221 | G13: =G11*G12 -> 8583.9221 | H13: =H11*H12 -> 8400.9899 | J13: PV of FCFF | M13: =M11*M12 -> 113.04835 | N13: =N11*N12 -> 109.30611 | O13: =O11*O12 -> 105.58884 | P13: =P11*P12 -> 101.8964 | Q13: =Q11*Q12 -> 98.228647 | S13: PV of FCFF | V13: =V11*V12 -> -623.89749 | W13: =W11*W12 -> -697.35533 | X13: =X11*X12 -> -773.58421 | Y13: =Y11*Y12 -> -852.70232 | Z13: =Z11*Z12 -> -934.83283 | AB13: PV of FCFF | AE13: =AE11*AE12 -> 24768.094 | AF13: =AF11*AF12 -> 23916.617 | AG13: =AG11*AG12 -> 23075.478 | AH13: =AH11*AH12 -> 22243.574 | AI13: =AI11*AI12 -> 21419.773 | AK13: PV of FCFF | AN13: =AN11*AN12 -> 893.52666 | AO13: =AO11*AO12 -> 942.10517 | AP13: =AP11*AP12 -> 984.87183 | AQ13: =AQ11*AQ12 -> 1022.3987 | AR13: =AR11*AR12 -> 1055.2024
A15: Components | B15: Value | AB15: Components | AC15: Value | AK15: Components | AL15: Value
A16: Terminal Value | B16: =H11/('WACC & Key Assumptions'!B16-'WACC & Key Assumptions'!B21) -> 203242.16 | AB16: Terminal Value | AC16: =AI11/('WACC & Key Assumptions'!E16-'WACC & Key Assumptions'!E21) -> 615034.74 | AK16: Terminal Value | AL16: =AR11/('WACC & Key Assumptions'!F16-'WACC & Key Assumptions'!F21) -> 24455.145
A17: PV of Terminal Value | B17: =B16*H12 -> 102333.68 | AB17: PV of Terminal Value | AC17: =AC16*AI12 -> 335539.68 | AK17: PV of Terminal Value | AL17: =AL16*AR12 -> 12007.489
A18: PV of FCFF | B18: =SUM(D13:H13) -> 44934.785 | AB18: PV of FCFF | AC18: =SUM(AE13:AI13) -> 115423.54 | AK18: PV of FCFF | AL18: =SUM(AN13:AR13) -> 4898.1048
A19: Equity Value | B19: =B17+B18 -> 147268.47 | AB19: Equity Value | AC19: =AC17+AC18 -> 450963.22 | AK19: Equity Value | AL19: =AL17+AL18 -> 16905.593
A20: Net Debt | B20: =('WACC & Key Assumptions'!B12-'Balance Sheet'!G28) -> 42403.71 | AB20: Net Debt | AC20: =('Balance Sheet'!AE40+'Balance Sheet'!AE48+'Balance Sheet'!AE49)-'Balance Sheet'!AE24 -> 117372.34 | AK20: Net Debt | AL20: =('Balance Sheet'!AM39+'Balance Sheet'!AM46)-'Balance Sheet'!AM24 -> 2344.22
A21: Enterprise Value | B21: =B19-B20 -> 104864.76 | AB21: Enterprise Value | AC21: =AC19-AC20 -> 333590.88 | AK21: Enterprise Value | AL21: =AL19-AL20 -> 14561.373
A22: Outstanding shares | B22: ='Relative Valuation'!F4 -> 216.0139 | AB22: Outstanding shares | AC22: ='Relative Valuation'!F7 -> 137.5581 | AK22: Outstanding shares | AL22: ='Relative Valuation'!F8 -> 208.502
A23: Intrinsic Value/share | B23: =B21/B22 -> 485.45375 | AB23: Intrinsic Value/share | AC23: =AC21/AC22 -> 2425.0907 | AK23: Intrinsic Value/share | AL23: =AL21/AL22 -> 69.838051
A24: Current Market price | B24: ='Relative Valuation'!D4 -> 1444.9 | AB24: Current Market price | AC24: ='Relative Valuation'!D7 -> 3918.5 | AK24: Current Market price | AL24: ='Relative Valuation'!D8 -> 315.95
A25: #VALUE! | B25: =(B23-B24)/B24 -> -0.66402259 | AB25: #VALUE! | AC25: =(AC23-AC24)/AC24 -> -0.38111758 | AK25: #VALUE! | AL25: =(AL23-AL24)/AL24 -> -0.77895853

Sheet Relative Valuation
A1: RELATIVE VALUATION
A3: Company | B3: Enterprise Value | C3: EBITDA | D3: Market Price | E3: Net Income | F3: Outstanding Shares | G3: EPS | H3: Book Value | I3: Book Value/Share | J3: Revenue | K3: Sales/share | L3: EV/EBITDA | M3: P/E | N3: P/B | O3: P/Sales
A4: #VALUE! | B4: ='Company Info'!B14+'Balance Sheet'!G46+'Balance Sheet'!G54-'Balance Sheet'!G28 -> 355256.61 | C4: ='Income Statement'!G20+'Income Statement'!G15+'Income Statement'!G16 -> 20048.27 | D4: {=_FV(A4,"Price")} -> 1444.9 | E4: ='Income Statement'!G30 -> 11061.26 | F4: {=_FV(A4,"Shares outstanding",TRUE)/10000000} -> 216.0139 | G4: =E4/F4 -> 51.206242 | H4: ='Balance Sheet'!G43 -> 64973.34 | I4: =H4/F4 -> 300.78314 | J4: ='Income Statement'!G8 -> 32383.08 | K4: =J4/F4 -> 149.91202 | L4: =B4/C4 -> 17.720063 | M4: =D4/G4 -> 28.217263 | N4: =D4/I4 -> 4.8037931 | O4: =D4/K4 -> 9.6383199
A5: #VALUE! | B5: ='Company Info'!C14+'Balance Sheet'!O43+'Balance Sheet'!O54-'Balance Sheet'!O25 -> 24717.34 | C5: ='Income Statement'!O18+'Income Statement'!O13+'Income Statement'!O14 -> 1896.6 | D5: {=_FV(A5,"Price")} -> 1276 | E5: ='Income Statement'!O27 -> 567.27 | F5: {=_FV(A5,"Shares outstanding",TRUE)/10000000} -> 17.07726 | G5: =E5/F5 -> 33.217858 | H5: ='Balance Sheet'!O40 -> 6468.86 | I5: =H5/F5 -> 378.79964 | J5: ='Income Statement'!O7 -> 22378.26 | K5: =J5/F5 -> 1310.4128 | L5: =B5/C5 -> 13.032448 | M5: =D5/G5 -> 38.413073 | N5: =D5/I5 -> 3.3685354 | O5: =D5/K5 -> 0.97373897
A6: #VALUE! | B6: ='Company Info'!D14+'Balance Sheet'!W39+'Balance Sheet'!W46-'Balance Sheet'!W23 -> 23369.31 | C6: ='Income Statement'!W17+'Income Statement'!W14+'Income Statement'!W12 -> 1574.76 | D6: {=_FV(A6,"Price")} -> 722.25 | E6: ='Income Statement'!W24 -> 570.74 | F6: {=_FV(A6,"Shares outstanding",TRUE)/10000000} -> 26.62 | G6: =E6/F6 -> 21.44027 | H6: ='Balance Sheet'!W36 -> 5347.45 | I6: =H6/F6 -> 200.88092 | J6: ='Income Statement'!W7 -> 21917.56 | K6: =J6/F6 -> 823.34936 | L6: =B6/C6 -> 14.839918 | M6: =D6/G6 -> 33.686609 | N6: =D6/I6 -> 3.5954137 | O6: =D6/K6 -> 0.87720964
A7: #VALUE! | B7: ='Company Info'!E14+'Balance Sheet'!AE40+'Balance Sheet'!AE48+'Balance Sheet'!AE49-'Balance Sheet'!AE24 -> 651441.64 | C7: ='Income Statement'!AE24+'Income Statement'!AE21+'Income Statement'!AE22+'Income Statement'!AE18 -> 36861.79 | D7: {=_FV(A7,"Price")} -> 3918.5 | E7: ='Income Statement'!AE42 -> 17673.33 | F7: {=_FV(A7,"Shares outstanding",TRUE)/10000000} -> 137.5581 | G7: =E7/F7 -> 128.47902 | H7: ='Balance Sheet'!AE37 -> 115403.68 | I7: =H7/F7 -> 838.945 | J7: ='Income Statement'!AE8 -> 259859.27 | K7: =J7/F7 -> 1889.0874 | L7: =B7/C7 -> 17.672545 | M7: =D7/G7 -> 30.499143 | N7: =D7/I7 -> 4.6707472 | O7: =D7/K7 -> 2.074282
A8: #VALUE! | B8: ='Company Info'!F14+'Balance Sheet'!AM39+'Balance Sheet'!AM46-'Balance Sheet'!AM24 -> 68647.86 | C8: ='Income Statement'!AM16+'Income Statement'!AM12+'Income Statement'!AM11 -> 2538.4 | D8: {=_FV(A8,"Price")} -> 315.95 | E8: ='Income Statement'!AM25 -> 1574.47 | F8: {=_FV(A8,"Shares outstanding",TRUE)/10000000} -> 208.502 | G8: =E8/F8 -> 7.5513424 | H8: ='Balance Sheet'!AM36 -> 8623.72 | I8: =H8/F8 -> 41.360371 | J8: ='Income Statement'!AM7 -> 23074.8 | K8: =J8/F8 -> 110.66944 | L8: =B8/C8 -> 27.043752 | M8: =D8/G8 -> 41.840243 | N8: =D8/I8 -> 7.6389548 | O8: =D8/K8 -> 2.8548983
A9: #VALUE! | L9: 6.3 | M9: 13.5 | N9: 2.44 | O9: 0.9
A10: #VALUE! | L10: 29.4 | M10: 64.4 | N10: 7.8 | O10: 2.4
A11: #VALUE! | L11: 31.4 | M11: 10.8 | N11: 4.33 | O11: 3.9
A12: #VALUE! | L12: 17.7 | M12: 26.5 | N12: 8.41 | O12: 1.9
A13: #VALUE! | L13: 26.6 | M13: 41.7 | N13: 13.7 | O13: 3.8
A14: #VALUE! | L14: 17.2 | M14: 45.5 | N14: 4.26 | O14: 2.1
K17: Average | L17: =AVERAGE(L4:L14) -> 19.900793 | M17: =AVERAGE(M4:M14) -> 34.09603 | N17: =AVERAGE(N4:N14) -> 5.9106767 | O17: =AVERAGE(O4:O14) -> 2.8562226
A19: Component | B19: #VALUE! | H19: #VALUE!
B21: Value | C21: Component | D21: Value | E21: Target Value | F21: Target Price | G21: #VALUE! | H21: Value | I21: Component | J21: Value | K21: Target Value | L21: Target Price | M21: #VALUE! | O21: Company | P21: KEC | Q21: Kalpataru | R21: Adani | S21: RVNL
A22: EV/EBITDA | B22: =L17 -> 19.900793 | C22: EBITDA | D22: =C6 -> 1574.76 | E22: =B22*D22 -> 31338.973 | F22: =E22/$F$6 -> 1177.2717 | G22: =(F22-$D$6)/$D$6 -> 0.63000584 | H22: =B22 -> 19.900793 | I22: EBITDA | J22: =C5 -> 1896.6 | K22: =J22*H22 -> 37743.845 | L22: =K22/$F$5 -> 2210.1815 | M22: =(L22-$D$5)/$D$5 -> 0.73211718 | O22: Target Price | P22: =AVERAGE(F22:F25) -> 1361.8278 | Q22: =AVERAGE(L22:L25) -> 2331.1429 | R22: =AVERAGE(L29:L32) -> 1501.9655 | S22: =AVERAGE(F29:F32) -> 265.07916
A23: P/E | B23: =M17 -> 34.09603 | C23: Net Income | D23: =E6 -> 570.74 | E23: =B23*D23 -> 19459.968 | F23: =E23/$F$6 -> 731.02811 | G23: =(F23-$D$6)/$D$6 -> 0.012153832 | H23: =B23 -> 34.09603 | I23: Net Income | J23: =E5 -> 567.27 | K23: =J23*H23 -> 19341.655 | L23: =K23/$F$5 -> 1132.5971 | M23: =(L23-$D$5)/$D$5 -> -0.11238473 | O23: Current Price | P23: =D6 -> 722.25 | Q23: =D5 -> 1276 | R23: =D4 -> 1444.9 | S23: =D8 -> 315.95
A24: P/B | B24: =N17 -> 5.9106767 | C24: Book Value | D24: =H6 -> 5347.45 | E24: =B24*D24 -> 31607.048 | F24: =E24/$F$6 -> 1187.3422 | G24: =(F24-$D$6)/$D$6 -> 0.64394899 | H24: =B24 -> 5.9106767 | I24: Book Value | J24: =H5 -> 6468.86 | K24: =J24*H24 -> 38235.34 | L24: =K24/$F$5 -> 2238.9622 | M24: =(L24-$D$5)/$D$5 -> 0.7546726 | O24: Upside/Downside | P24: =(P22-P23)/P23 -> 0.88553515 | Q24: =(Q22-Q23)/Q23 -> 0.82691448 | R24: =(R22-R23)/R23 -> 0.039494414 | S24: =(S22-S23)/S23 -> -0.16100916
A25: P/Sales | B25: =O17 -> 2.8562226 | C25: Sales | D25: =J6 -> 21917.56 | E25: =B25*D25 -> 62601.431 | F25: =E25/$F$6 -> 2351.6691 | G25: =(F25-$D$6)/$D$6 -> 2.2560319 | H25: =B25 -> 2.8562226 | I25: Sales | J25: =J5 -> 22378.26 | K25: =J25*H25 -> 63917.292 | L25: =K25/$F$5 -> 3742.8307 | M25: =(L25-$D$5)/$D$5 -> 1.9332529
A26: RELATIVE VALUATION | B26: #VALUE! | H26: #VALUE!
B28: Value | C28: Component | D28: Value | E28: Target Value | F28: Target Price | G28: #VALUE! | H28: Value | I28: Component | J28: Value | K28: Target Value | L28: Target Price | M28: #VALUE!
B29: =B22 -> 19.900793 | C29: EBITDA | D29: =C8 -> 2538.4 | E29: =B29*D29 -> 50516.174 | F29: =E29/$F$8 -> 242.28148 | G29: =(F29-$D$8)/$D$8 -> -0.23316511 | H29: =H22 -> 19.900793 | I29: EBITDA | J29: =C4 -> 20048.27 | K29: =H29*J29 -> 398976.48 | L29: =K29/$F$8 -> 1913.5379 | M29: =(L29-$D$4)/$D$4 -> 0.32433932
B30: =B23 -> 34.09603 | C30: Net Income | D30: =E8 -> 1574.47 | E30: =B30*D30 -> 53683.176 | F30: =E30/$F$8 -> 257.4708 | G30: =(F30-$D$8)/$D$8 -> -0.18509005 | H30: =H23 -> 34.09603 | I30: Net Income | J30: =E4 -> 11061.26 | K30: =H30*J30 -> 377145.05 | L30: =K30/$F$8 -> 1808.8318 | M30: =(L30-$D$4)/$D$4 -> 0.25187336
B31: =B24 -> 5.9106767 | C31: Book Value | D31: =H8 -> 8623.72 | E31: =B31*D31 -> 50972.021 | F31: =E31/$F$8 -> 244.46778 | G31: =(F31-$D$8)/$D$8 -> -0.22624535 | H31: =H24 -> 5.9106767 | I31: Book Value | J31: =H4 -> 64973.34 | K31: =H31*J31 -> 384036.41 | L31: =K31/$F$8 -> 1841.8836 | M31: =(L31-$D$4)/$D$4 -> 0.27474813
B32: =B25 -> 2.8562226 | C32: Sales | D32: =J8 -> 23074.8 | E32: =B32*D32 -> 65906.766 | F32: =E32/$F$8 -> 316.09656 | G32: =(F32-$D$8)/$D$8 -> 0.0004638823 | H32: =H25 -> 2.8562226 | I32: Sales | J32: =J4 -> 32383.08 | K32: =H32*J32 -> 92493.286 | L32: =K32/$F$8 -> 443.60863 | M32: =(L32-$D$4)/$D$4 -> -0.69298316
