Workbook

Sheet Company Profile
A1: Company Profile
A2: Logo | B2: #VALUE! | C2: #VALUE! | D2: #VALUE! | E2: #VALUE! | F2: #VALUE! | G2: #VALUE!
A3: Company Name | B3: #VALUE! | C3: #VALUE! | D3: #VALUE! | E3: #VALUE! | F3: #VALUE! | G3: Reliance Jio Infocomm Limited
A4: Ticker Symbol | B4: {=_FV(B3,"Ticker symbol",TRUE)} -> BHARTIARTL | C4: {=_FV(C3,"Ticker symbol",TRUE)} -> INDUSTOWER | D4: {=_FV(D3,"Ticker symbol",TRUE)} -> RAILTEL | E4: {=_FV(E3,"Ticker symbol",TRUE)} -> 500483 | F4: {=_FV(F3,"Ticker symbol",TRUE)} -> 532822 | G4: ~
A5: Employees | B5: {=_FV(B3,"Employees")} -> 28701 | C5: {=_FV(C3,"Employees")} -> 3732 | D5: {=_FV(D3,"Employees")} -> 530 | E5: {=_FV(E3,"Employees")} -> 13047 | F5: {=_FV(F3,"Employees")} -> 9985 | G5: 90067
A6: Total Subscribers/Tenants | B6: 399560000 | C6: 411200 | D6: 460000 | E6: 7000 | F6: 197700000 | G6: 463780000
A7: Share Price | B7: {=_FV(B3,"Price")} -> 2019.8 | C7: {=_FV(C3,"Price")} -> 398.75 | D7: {=_FV(D3,"Price")} -> 349.25 | E7: {=_FV(E3,"Price")} -> 1849.85 | F7: {=_FV(F3,"Price")} -> 9.51 | G7: ~
A8: Outstanding Shares | B8: {=_FV(B3,"Shares outstanding",TRUE)} -> 6091080000 | C8: {=_FV(C3,"Shares outstanding",TRUE)} -> 2637135000 | D8: {=_FV(D3,"Shares outstanding",TRUE)} -> 320938400 | E8: {=_FV(E3,"Shares outstanding",TRUE)} -> 285000000 | F8: {=_FV(F3,"Shares outstanding",TRUE)} -> 108343000000 | G8: ~
A9: Market Cap | B9: {=_FV(B3,"Market cap",TRUE)} -> 11993430000000 | C9: {=_FV(C3,"Market cap",TRUE)} -> 1056964000000 | D9: {=_FV(D3,"Market cap",TRUE)} -> 112858000000 | E9: {=_FV(E3,"Market cap",TRUE)} -> 527079000000 | F9: {=_FV(F3,"Market cap",TRUE)} -> 1041177000000
A10: Change (%) | B10: {=_FV(B3,"Change (%)",TRUE)} -> 0.009294 | C10: {=_FV(C3,"Change (%)",TRUE)} -> -0.005115 | D10: {=_FV(D3,"Change (%)",TRUE)} -> -0.006825 | E10: {=_FV(E3,"Change (%)",TRUE)} -> 2.703e-05 | F10: {=_FV(F3,"Change (%)",TRUE)} -> -0.010406
A11: Beta | B11: {=_FV(B3,"Beta")} -> 0.7464 | C11: {=_FV(C3,"Beta")} -> 1.0382 | D11: {=_FV(D3,"Beta")} -> 1.3204 | E11: {=_FV(E3,"Beta")} -> 1.4164 | F11: {=_FV(F3,"Beta")} -> 0.9757
A12: Industry | B12: {=_FV(B3,"Industry")} -> Telecommunications Services | C12: {=_FV(C3,"Industry")} -> Telecommunications Services | D12: {=_FV(D3,"Industry")} -> Telecommunications Services | E12: {=_FV(E3,"Industry")} -> Telecommunications Services | F12: {=_FV(F3,"Industry")} -> Telecommunications Services | G12: Telecom & Digital Services
A13: P/E | B13: {=_FV(B3,"P/E",TRUE)} -> 30.35 | C13: {=_FV(C3,"P/E",TRUE)} -> 11.24 | D13: {=_FV(D3,"P/E",TRUE)} -> 34.96 | E13: {=_FV(E3,"P/E",TRUE)} -> 36.91 | F13: 0 | G13: 0
A14: Year Corporated | B14: {=_FV(B3,"Year incorporated",TRUE)} -> 1995 | C14: {=_FV(C3,"Year incorporated",TRUE)} -> 2006 | D14: {=_FV(D3,"Year incorporated",TRUE)} -> 2000 | E14: {=_FV(E3,"Year incorporated",TRUE)} -> 1986 | F14: {=_FV(F3,"Year incorporated",TRUE)} -> 1995 | G14: 2007

Sheet Balance Sheet
A1: Balance Sheet | F1: #VALUE! | N1: #VALUE! | V1: #VALUE! | AD1: #VALUE! | AL1: #VALUE! | AT1: #VALUE!
A2: Particulars | B2: 2020 | C2: 2021 | D2: 2022 | E2: 2023 | F2: 2024 | G2: 2025 | I2: Particulars | J2: 2020 | K2: 2021 | L2: 2022 | M2: 2023 | N2: 2024 | O2: 2025 | Q2: Particulars | R2: 2020 | S2: 2021 | T2: 2022 | U2: 2023 | V2: 2024 | W2: 2025 | Y2: Particulars | Z2: 2020 | AA2: 2021 | AB2: 2022 | AC2: 2023 | AD2: 2024 | AE2: 2025 | AG2: Particulars | AH2: 2020 | AI2: 2021 | AJ2: 2022 | AK2: 2023 | AL2: 2024 | AM2: 2025 | AO2: Particulars | AP2: 2020 | AQ2: 2021 | AR2: 2022 | AS2: 2023 | AT2: 2024 | AU2: 2025
A3: Non-Current assets | I3: Non-Current assets | Q3: Non-Current assets | Y3: Non-Current assets | AG3: Non-Current assets | AO3: Non-Current Assets
A4: Property, plant and equipment | B4: 54828.6 | C4: 55567.6 | D4: 63795 | E4: 65083.7 | F4: 106612.1 | G4: 143272.4 | I4: Property, plant and equipment | J4: 5070.2 | K4: 21581.9 | L4: 20869.9 | M4: 21172.3 | N4: 26649.3 | O4: 29408.2 | Q4: Property, plant and equipment | R4: 608.54 | S4: 576.58 | T4: 601.49 | U4: 646.83 | V4: 740.33 | W4: 898.56 | Y4: Property, plant and equipment | Z4: 9021.91 | AA4: 8209.78 | AB4: 7768.61 | AC4: 7459.8 | AD4: 7429.73 | AE4: 7637.93 | AG4: Property, plant and equipment | AH4: 66311.3 | AI4: 57570.4 | AJ4: 53632.7 | AK4: 59821.1 | AL4: 52176 | AM4: 56195.6 | AO4: Property, plant and equipment | AP4: 102864 | AQ4: 115146 | AR4: 132910 | AS4: 146010 | AT4: 146635 | AU4: 184757
A5: Capital work-in-progress | B5: 1233.2 | C5: 1283.1 | D5: 1714.9 | E5: 6959.8 | F5: 8907.7 | G5: 10596.2 | I5: Right-of-use assets | J5: 1631.9 | K5: 10211 | L5: 10921 | M5: 11188.2 | N5: 12637.7 | O5: 14933.7 | Q5: Capital work-in-progress | R5: 252.54 | S5: 214.84 | T5: 163.26 | U5: 156.93 | V5: 129.59 | W5: 123.71 | Y5: Capital work-in-progress | Z5: 285.95 | AA5: 394.46 | AB5: 778.68 | AC5: 1003.37 | AD5: 1176.53 | AE5: 1005.13 | AG5: Capital work-in-progress | AH5: 1041.5 | AI5: 599.6 | AJ5: 323.9 | AK5: 300.3 | AL5: 638.8 | AM5: 2471.6 | AO5: Capital work-in-progress | AP5: 21176 | AQ5: 16888 | AR5: 20161 | AS5: 44758 | AT5: 77862 | AU5: 56866
A6: Right-of-use assets | B6: 34502.8 | C6: 34836.9 | D6: 21968.2 | E6: 39702.6 | F6: 55936.7 | G6: 60241.5 | I6: Capital work-in-progress | J6: 54.5 | K6: 273.6 | L6: 178.7 | M6: 354.6 | N6: 421.9 | O6: 567.2 | Q6: Right-of-use assets | R6: 172.96 | S6: 170.26 | T6: 165.02 | U6: 169 | V6: 167.02 | W6: 169 | Y6: Right-of-use assets | Z6: 1595.62 | AA6: 1333.67 | AB6: 1148.76 | AC6: 996.8 | AD6: 1103.49 | AE6: 1430.42 | AG6: Right-of-use assets | AH6: 0 | AI6: 0 | AJ6: 0 | AK6: 0 | AL6: 0 | AM6: 0 | AO6: Intangible assets | AP6: 60563 | AQ6: 56008 | AR6: =79692+4787 -> 84479 | AS6: =75339+4704 -> 80043 | AT6: =69852+3787 -> 73639 | AU6: =147122+4376 -> 151498
A7: Goodwill | B7: 73.9 | C7: 73.9 | D7: 108.3 | E7: 108.3 | F7: 26501.7 | G7: 51697.4 | I7: Intangible assets | J7: 12 | K7: 7.3 | L7: 35.2 | M7: 23.1 | N7: 13.2 | O7: 38 | Q7: Intangible assets | R7: 7.85 | S7: 13.07 | T7: 8.41 | U7: 5.48 | V7: 5.98 | W7: 13.3 | Y7: Investment property | Z7: 280.26 | AA7: 276.94 | AB7: 376.47 | AC7: 397.01 | AD7: 385.71 | AE7: 194.98 | AG7: Investment property | AH7: 66 | AI7: 0 | AJ7: 0 | AK7: 0 | AL7: 0 | AM7: 0 | AO7: Intangible assets under development | AP7: 82 | AQ7: 93 | AR7: =28626+63 -> 28689 | AS7: =122357+256 -> 122613 | AT7: =129602+449 -> 130051 | AU7: =54176 -> 54176
A8: Other intangible assets | B8: 72274 | C8: 66910 | D8: 77864.2 | E8: 82514.5 | F8: 114252.6 | G8: 133256.9 | I8: Investment in joint venture | J8: 5731.8 | K8: 0 | L8: 0 | M8: 0 | N8: 0 | O8: 0 | Q8: Investments | R8: 0 | S8: 0 | T8: 0 | U8: 0 | V8: 0 | W8: 0 | Y8: Investment property under development | Z8: 97.74 | AA8: 116.21 | AB8: 19.8 | AC8: 0 | AD8: 0 | AE8: 0 | AG8: Intangible assets | AH8: 119459.2 | AI8: 109920 | AJ8: 103185.9 | AK8: 96434.1 | AL8: 87948.8 | AM8: 85124 | AO8: Investments | AP8: 1108 | AQ8: 1108 | AR8: 59 | AS8: 37 | AT8: 1108 | AU8: 1108
A9: Intangible assets under development | B9: 25.5 | C9: 23.2 | D9: 1670.8 | E9: 33595.9 | F9: 7996.4 | G9: 402.7 | I9: Investment | J9: 1700.2 | K9: 0 | L9: 0 | M9: 0 | N9: 2.8 | O9: 0 | Q9: Loans and Security deposits | R9: 3.32 | S9: 4.82 | T9: 0 | U9: 0 | V9: 0 | W9: 0 | Y9: Goodwill | Z9: 91.84 | AA9: 110.33 | AB9: 108.28 | AC9: 115.05 | AD9: 1783.73 | AE9: 1932.52 | AG9: Intangible assets under development | AH9: 96.6 | AI9: 6.3 | AJ9: 40.4 | AK9: 17576.1 | AL9: 17550.3 | AM9: 15740.6 | AO9: Other Financial assets | AP9: 3 | AQ9: 10 | AR9: 32 | AS9: 8 | AT9: 10 | AU9: 5
A10: Investments in subsidiaries, associates and Joint Ventures | B10: 30046.6 | C10: 33513.3 | D10: 45897.4 | E10: 43115 | F10: 31240.4 | G10: 3641.6 | I10: Other financial assets | J10: 145 | K10: 1053.3 | L10: 1101.2 | M10: 1175.2 | N10: 1323.3 | O10: 1465.3 | Q10: Other Non-current financial assets | R10: 219.3 | S10: 58.78 | T10: 339.83 | U10: 233.57 | V10: 434.16 | W10: 96.68 | Y10: Other intangible assets | Z10: 1680.81 | AA10: 1472.68 | AB10: 1514.23 | AC10: 1530.92 | AD10: 2764.75 | AE10: 2723.1 | AG10: Investments accounted for using the equity method | AH10: 1524.4 | AI10: 4.1 | AJ10: 5.3 | AK10: 5.8 | AL10: 0.3 | AM10: 0 | AO10: Deferred tax assets (net) | AP10: 1546 | AQ10: 0 | AR10: 0 | AS10: 0 | AT10: 0 | AU10: 0
A11: Investments | B11: 5.2 | C11: 15015.4 | D11: 31.2 | E11: 56.5 | F11: 92.4 | G11: 543.5 | I11: Income tax assets (net) | J11: 75.7 | K11: 728.2 | L11: 684.4 | M11: 725.1 | N11: 771.5 | O11: 856.1 | Q11: Deferred tax assets (net) | R11: 0 | S11: 24.23 | T11: 24.94 | U11: 31.2 | V11: 45.3 | W11: 66.15 | Y11: Intangible assets under development | Z11: 62.91 | AA11: 98.46 | AB11: 73.78 | AC11: 144.69 | AD11: 150.5 | AE11: 94.79 | AG11: Other non-current financial assets | AH11: 8245.9 | AI11: 7732.3 | AJ11: 8849.2 | AK11: 8850.1 | AL11: 7100.2 | AM11: 728 | AO11: Other non-current assets | AP11: 25920 | AQ11: 38401 | AR11: 24058 | AS11: 23895 | AT11: 25009 | AU11: 25729
A12: Derivative instruments | B12: 3.9 | C12: 0 | D12: 0 | E12: 8.1 | F12: 6.5 | G12: 0 | I12: Deferred tax assets (net) | J12: 133.1 | K12: 0 | L12: 0 | M12: 1221.8 | N12: 1075.6 | O12: 2.3 | Q12: Other non-current assets | R12: 18.06 | S12: 0.25 | T12: 0.68 | U12: 0.32 | V12: 3.04 | W12: 7.37 | Y12: Investments | AG12: Deferred tax assets (net) | AH12: 2 | AI12: 2.3 | AJ12: 6 | AK12: 13.5 | AL12: 13.8 | AM12: 11.6 | AO12: Total non-current assets | AP12: =SUM(AP4:AP11) -> 213262 | AQ12: =SUM(AQ4:AQ11) -> 227654 | AR12: =SUM(AR4:AR11) -> 290388 | AS12: =SUM(AS4:AS11) -> 417364 | AT12: =SUM(AT4:AT11) -> 454314 | AU12: =SUM(AU4:AU11) -> 474139
A13: Trade receivables | B13: 0 | C13: 0 | D13: 0 | E13: 0 | F13: 180.5 | G13: 213.1 | I13: Other non-current assets | J13: 248.2 | K13: 1458.6 | L13: 1865.9 | M13: 2004.5 | N13: 2482.3 | O13: 2969.6 | Q13: Total non-current assets | R13: =SUM(R4:R12) -> 1282.57 | S13: =SUM(S4:S12) -> 1062.83 | T13: =SUM(T4:T12) -> 1303.63 | U13: =SUM(U4:U12) -> 1243.33 | V13: =SUM(V4:V12) -> 1525.42 | W13: =SUM(W4:W12) -> 1374.77 | Y13: Investments in associates | Z13: 686.5 | AA13: 718.69 | AB13: 895.1 | AC13: 1019.69 | AD13: 1306.83 | AE13: 1630.75 | AG13: Other non-current assets | AH13: 13486.6 | AI13: 13546.1 | AJ13: 11150.2 | AK13: 10338.8 | AL13: 6659.7 | AM13: 6555.7 | AO13: Current assets
A14: Loans and security deposits | B14: 18725.2 | C14: 576.4 | D14: 1684 | E14: 1722.8 | F14: 0 | G14: 86.5 | I14: Total Non-current assets | J14: =SUM(J4:J13) -> 14802.6 | K14: =SUM(K4:K13) -> 35313.9 | L14: =SUM(L4:L13) -> 35656.3 | M14: =SUM(M4:M13) -> 37864.8 | N14: =SUM(N4:N13) -> 45377.6 | O14: =SUM(O4:O13) -> 50240.4 | Q14: Current Assets | Y14: Other investments | Z14: 214.82 | AA14: 232.24 | AB14: 237.33 | AC14: 171.3 | AD14: 152.11 | AE14: 167.48 | AG14: Total non-current assets | AH14: =SUM(AH4:AH13) -> 210233.5 | AI14: =SUM(AI4:AI13) -> 189381.1 | AJ14: =SUM(AJ4:AJ13) -> 177193.6 | AK14: =SUM(AK4:AK13) -> 193339.8 | AL14: =SUM(AL4:AL13) -> 172087.9 | AM14: =SUM(AM4:AM13) -> 166827.1 | AO14: Investments | AP14: 1381 | AQ14: 420 | AR14: 555 | AS14: 590 | AT14: 2523 | AU14: 19257
A15: Others | B15: 1272.1 | C15: 1114.1 | D15: 0 | E15: 0 | F15: 2655.7 | G15: 3747.1 | I15: Current Assets | Q15: Inventories | R15: 0.49 | S15: 1.21 | T15: 0.94 | U15: 0.92 | V15: 3.01 | W15: 0.01 | Y15: Other financial assets | Z15: 119.85 | AA15: 126.78 | AB15: 126.02 | AC15: 146.8 | AD15: 144.02 | AE15: 154.35 | AG15: Current assets | AO15: Trade receivables | AP15: 1609 | AQ15: 1410 | AR15: 4403 | AS15: 2609 | AT15: 1549 | AU15: 955
A16: Income tax assets (net) | B16: 1341 | C16: 1420.6 | D16: 1165.8 | E16: 1354 | F16: 1413.5 | G16: 2497.8 | I16: Inventories | J16: 0 | K16: 0 | L16: 0 | M16: 0 | N16: 0 | O16: 7.6 | Q16: Investments | R16: 0 | S16: 0 | T16: 30.05 | U16: 40.07 | V16: 90.29 | W16: 39.23 | Y16: Deferred tax assets (net) | Z16: 279.86 | AA16: 310.23 | AB16: 217.27 | AC16: 355.17 | AD16: 717.01 | AE16: 806.58 | AG16: Inventories | AH16: 2.5 | AI16: 0.6 | AJ16: 2.3 | AK16: 16.3 | AL16: 1.2 | AM16: 1.1 | AO16: Cash and cash equivalents | AP16: 7066 | AQ16: 178 | AR16: 429 | AS16: 891 | AT16: 967 | AU16: 5929
A17: Deferred tax assets (net) | B17: 22701.4 | C17: 15838.6 | D17: 16017.5 | E17: 14643.9 | F17: 19242.8 | G17: 24911.1 | I17: Investments | J17: 3738.1 | K17: 2271.4 | L17: 1652.1 | M17: 275.6 | N17: 0 | O17: 1486.1 | Q17: Trade receivables | R17: 507.07 | S17: 772.16 | T17: 684.76 | U17: 1048.34 | V17: 1267.79 | W17: 1581.36 | Y17: Non current tax assets | Z17: 1594 | AA17: 1888.71 | AB17: 1369.52 | AC17: 1268.51 | AD17: 1216.99 | AE17: 1187.09 | AG17: Other investments | AH17: 454.8 | AI17: 0 | AJ17: 0 | AK17: 0 | AL17: 0.2 | AM17: 0 | AO17: Other bank balances | AP17: 414 | AQ17: 411 | AR17: 386 | AS17: 408 | AT17: 397 | AU17: 412
A18: Other non-current assets | B18: 4558.1 | C18: 11502.1 | D18: 6032.3 | E18: 6135.1 | F18: 11215.9 | G18: 11663.8 | I18: Trade receivables | J18: 367.2 | K18: 3828.5 | L18: 7058.6 | M18: 4868.7 | N18: 6450.7 | O18: 4767.5 | Q18: Cash and cash equivalents | R18: 134.52 | S18: 250.97 | T18: 187.11 | U18: 187.97 | V18: 247.65 | W18: 308.04 | Y18: Other non-current assets | Z18: 207.29 | AA18: 207.09 | AB18: 164.29 | AC18: 132.52 | AD18: 231.01 | AE18: 380.68 | AG18: Trade receivables | AH18: 3094.3 | AI18: 2507 | AJ18: 2443.9 | AK18: 2164 | AL18: 2194.8 | AM18: 2000.3 | AO18: Other Financial assets | AP18: 1067 | AQ18: 614 | AR18: 3645 | AS18: 3978 | AT18: 1567 | AU18: 2463
A19: Total Non-current assets | B19: =SUM(B4:B18) -> 241591.5 | C19: =SUM(C4:C18) -> 237675.2 | D19: =SUM(D4:D18) -> 237949.6 | E19: =SUM(E4:E18) -> 295000.2 | F19: =SUM(F4:F18) -> 386254.9 | G19: =SUM(G4:G18) -> 446771.6 | I19: Cash and cash equivalents | J19: 145.2 | K19: 14.5 | L19: 980.2 | M19: 22.4 | N19: 63.1 | O19: 149.7 | Q19: Other bank balances | R19: 133.91 | S19: 337.44 | T19: 140.98 | U19: 84.68 | V19: 237.5 | W19: 218.34 | Y19: Total non-current assets | Z19: =SUM(Z4:Z18) -> 16219.36 | AA19: =SUM(AA4:AA18) -> 15496.27 | AB19: =SUM(AB4:AB18) -> 14798.14 | AC19: =SUM(AC4:AC18) -> 14741.63 | AD19: =SUM(AD4:AD18) -> 18562.41 | AE19: =SUM(AE4:AE18) -> 19345.8 | AG19: Cash and cash equivalents | AH19: 370.8 | AI19: 350.3 | AJ19: 1453.2 | AK19: 228.8 | AL19: 167.8 | AM19: 256.8 | AO19: Other current assets | AP19: 16906 | AQ19: 19402 | AR19: 19917 | AS19: 22041 | AT19: 26088 | AU19: 20927
A20: Current Assets | I20: Other bank balances | J20: 1.8 | K20: 0 | L20: 0 | M20: 0 | N20: 0 | O20: 1706.4 | Q20: Loans and advances | R20: 4.87 | S20: 5.3 | T20: 0.37 | U20: 0.21 | V20: 0.15 | W20: 0.34 | Y20: Current assets | AG20: Bank balances other than above | AH20: 2292.2 | AI20: 1866.2 | AJ20: 2043.4 | AK20: 626.6 | AL20: 368.4 | AM20: 10311.7 | AO20: Total current assets | AP20: =SUM(AP14:AP19) -> 28443 | AQ20: =SUM(AQ14:AQ19) -> 22435 | AR20: =SUM(AR14:AR19) -> 29335 | AS20: =SUM(AS14:AS19) -> 30517 | AT20: =SUM(AT14:AT19) -> 33091 | AU20: =SUM(AU14:AU19) -> 49943
A21: Inventories | B21: 3.1 | C21: 0.8 | D21: 0.4 | E21: 0 | F21: 363.9 | G21: 451.7 | I21: Other financial assets | J21: 446.6 | K21: 2955.9 | L21: 2375.5 | M21: 3251.8 | N21: 3576.8 | O21: 3883.9 | Q21: Other current financial assets | R21: 213.52 | S21: 136.07 | T21: 346.37 | U21: 471.55 | V21: 401.76 | W21: 1175.64 | Y21: Inventories | Z21: 72.97 | AA21: 34.44 | AB21: 37.88 | AC21: 160 | AD21: 83.54 | AE21: 157.84 | AG21: Loans to joint ventures and others | AH21: 0.9 | AI21: 0.9 | AJ21: 0 | AK21: 0 | AL21: 0 | AM21: 0 | AO21: Total Assets | AP21: =AP12+AP20 -> 241705 | AQ21: =AQ12+AQ20 -> 250089 | AR21: =AR12+AR20 -> 319723 | AS21: =AS12+AS20 -> 447881 | AT21: =AT12+AT20 -> 487405 | AU21: =AU12+AU20 -> 524082
A22: Investments | B22: 8675 | C22: 3744.3 | D22: 797.4 | E22: 3519.9 | F22: 269.5 | G22: 1653.2 | I22: Other current assets | J22: 252.4 | K22: 559.5 | L22: 244.9 | M22: 289.1 | N22: 399.4 | O22: 928.6 | Q22: Current tax assets (net) | R22: 27.48 | S22: 16.29 | T22: 15.45 | U22: 15.44 | V22: 22.5 | W22: 8.58 | Y22: Other investments | Z22: 661.78 | AA22: 1282.43 | AB22: 432.8 | AC22: 759.56 | AD22: 149.28 | AE22: 915.7 | AG22: Other current financial assets | AH22: 2303.3 | AI22: 211.7 | AJ22: 7.56 | AK22: 3.94 | AL22: 53.4 | AM22: 6926.2 | AO22: Equity and Liabilities
A23: Derivative instruments | B23: 189.7 | C23: 2.8 | D23: 31.6 | E23: 96.3 | F23: 116.8 | G23: 81.3 | I23: Total current assets | J23: =SUM(J16:J22) -> 4951.3 | K23: =SUM(K16:K22) -> 9629.8 | L23: =SUM(L16:L22) -> 12311.3 | M23: =SUM(M16:M22) -> 8707.6 | N23: =SUM(N16:N22) -> 10490 | O23: =SUM(O16:O22) -> 12929.8 | Q23: Other current assets | R23: 93.66 | S23: 127.66 | T23: 148.51 | U23: 246.63 | V23: 253.51 | W23: 454.9 | Y23: Trade receivables | Z23: 3228.87 | AA23: 2607.68 | AB23: 2582.13 | AC23: 2734.99 | AD23: 3758.36 | AE23: 4006.1 | AG23: Other current assets | AH23: 8167.3 | AI23: 9097.5 | AJ23: 10214 | AK23: 10778.5 | AL23: 10068.8 | AM23: 11543.4 | AO23: Equity
A24: Trade receivables | B24: 3810 | C24: 3178.2 | D24: 2771.7 | E24: 2116.5 | F24: 4727.7 | G24: 7455.7 | I24: Total assets | J24: =J14+J23 -> 19753.9 | K24: =K14+K23 -> 44943.7 | L24: =L14+L23 -> 47967.6 | M24: =M14+M23 -> 46572.4 | N24: =N14+N23 -> 55867.6 | O24: =O14+O23 -> 63170.2 | Q24: Total current assets | R24: =SUM(R15:R23) -> 1115.52 | S24: =SUM(S15:S23) -> 1647.1 | T24: =SUM(T15:T23) -> 1554.54 | U24: =SUM(U15:U23) -> 2095.81 | V24: =SUM(V15:V23) -> 2524.16 | W24: =SUM(W15:W23) -> 3786.44 | Y24: Cash and cash equivalents | Z24: 850 | AA24: 817.85 | AB24: 696.86 | AC24: 1004.48 | AD24: 732.05 | AE24: 533.9 | AG24: Current tax assets (net) | AH24: 0 | AI24: 0 | AJ24: 603.1 | AK24: 0 | AL24: 5.9 | AM24: 0 | AO24: Equity share capital | AP24: 45000 | AQ24: 45000 | AR24: 45000 | AS24: 45000 | AT24: 45000 | AU24: 45000
A25: Cash and cash equivalents | B25: 3366.8 | C25: 992.8 | D25: 310.2 | E25: 1392.5 | F25: 6915.5 | G25: 6105.6 | I25: Equity and Liabilities | Q25: Total Assets | R25: =R13+R24 -> 2398.09 | S25: =S13+S24 -> 2709.93 | T25: =T13+T24 -> 2858.17 | U25: =U13+U24 -> 3339.14 | V25: =V13+V24 -> 4049.58 | W25: =W13+W24 -> 5161.21 | Y25: Bank balances other than above | Z25: 59.13 | AA25: 109.25 | AB25: 46.53 | AC25: 58.09 | AD25: 110.4 | AE25: 53.51 | AG25: Assets classified as held for sale | AH25: 0 | AI25: 65.3 | AJ25: 0 | AK25: 49.3 | AL25: 49.3 | AM25: 0 | AO25: Other equity | AP25: 125956 | AQ25: 137973 | AR25: 153089 | AS25: 171519 | AT25: 191369 | AU25: 216377
A26: Other bank balances | B26: 30.8 | C26: 43.7 | D26: 31.2 | E26: 50.5 | F26: 9424.4 | G26: 10614.3 | I26: Equity | Q26: Equity and Liabilities | Y26: Other financial assets | Z26: 139.76 | AA26: 109.03 | AB26: 105.98 | AC26: 146.4 | AD26: 155.75 | AE26: 255.54 | AG26: Total current assets | AH26: =SUM(AH16:AH25) -> 16686.1 | AI26: =SUM(AI16:AI25) -> 14099.5 | AJ26: =SUM(AJ16:AJ25) -> 16767.46 | AK26: =SUM(AK16:AK25) -> 13867.44 | AL26: =SUM(AL16:AL25) -> 12909.8 | AM26: =SUM(AM16:AM25) -> 31039.5 | AO26: Total equity | AP26: =SUM(AP24:AP25) -> 170956 | AQ26: =SUM(AQ24:AQ25) -> 182973 | AR26: =SUM(AR24:AR25) -> 198089 | AS26: =SUM(AS24:AS25) -> 216519 | AT26: =SUM(AT24:AT25) -> 236369 | AU26: =SUM(AU24:AU25) -> 261377
A27: Loans | B27: 758 | C27: 1566.9 | D27: 1128.8 | E27: 4176.3 | F27: 0 | G27: 0 | I27: Equity share capital | J27: 1849.6 | K27: 2694.9 | L27: 2694.9 | M27: 2694.9 | N27: 2694.9 | O27: 2638.1 | Q27: Equity | Y27: Other current assets | Z27: 805.82 | AA27: 746.22 | AB27: 815.32 | AC27: 691.12 | AD27: 899.01 | AE27: 1261.1 | AG27: Total assets | AH27: =AH14+AH26 -> 226919.6 | AI27: =AI14+AI26 -> 203480.6 | AJ27: =AJ14+AJ26 -> 193961.06 | AK27: =AK14+AK26 -> 207207.24 | AL27: =AL14+AL26 -> 184997.7 | AM27: =AM14+AM26 -> 197866.6 | AO27: Non-Current Liabilities
A28: Others | B28: 24377.2 | C28: 19670 | D28: 19495 | E28: 20083.6 | F28: 24954.4 | G28: 26766.2 | I28: Other Equity | J28: 11692.7 | K28: 13182.1 | L28: 19455.6 | M28: 18414.6 | N28: 24343.9 | O28: 29860.2 | Q28: Equity share capital | R28: 320.94 | S28: 320.94 | T28: 320.94 | U28: 320.94 | V28: 320.94 | W28: 320.94 | Y28: Assets classified for sale | Z28: 123.78 | AA28: 130.24 | AB28: 152.28 | AC28: 256.35 | AD28: 110.54 | AE28: 54.99 | AG28: Equity and Liabilities | AO28: Borrowings | AP28: 0 | AQ28: 364 | AR28: 16162 | AS28: 22732 | AT28: 42373 | AU28: 44244
A29: Other current assets | B29: 17570.7 | C29: 10872.4 | D29: 8724.9 | E29: 9141.4 | F29: 11503.9 | G29: 14460.8 | I29: Total Equity | J29: =SUM(J27:J28) -> 13542.3 | K29: =SUM(K27:K28) -> 15877 | L29: =SUM(L27:L28) -> 22150.5 | M29: =SUM(M27:M28) -> 21109.5 | N29: =SUM(N27:N28) -> 27038.8 | O29: =SUM(O27:O28) -> 32498.3 | Q29: Other Equity | R29: 1048.39 | S29: 1091.88 | T29: 1205.77 | U29: 1327.94 | V29: 1506.3 | W29: 1678.68 | Y29: Total current assets | Z29: =SUM(Z21:Z28) -> 5942.11 | AA29: =SUM(AA21:AA28) -> 5837.14 | AB29: =SUM(AB21:AB28) -> 4869.78 | AC29: =SUM(AC21:AC28) -> 5810.99 | AD29: =SUM(AD21:AD28) -> 5998.93 | AE29: =SUM(AE21:AE28) -> 7238.68 | AG29: Equity | AO29: Lease Liabilities | AP29: 0 | AQ29: 0 | AR29: 7952 | AS29: 10302 | AT29: 9413 | AU29: 8707
A30: Total Current assets | B30: =SUM(B21:B29) -> 58781.3 | C30: =SUM(C21:C29) -> 40071.9 | D30: =SUM(D21:D29) -> 33291.2 | E30: =SUM(E21:E29) -> 40577 | F30: =SUM(F21:F29) -> 58276.1 | G30: =SUM(G21:G29) -> 67588.8 | I30: Non-Current Liabilities | Q30: Total Equity | R30: =SUM(R28:R29) -> 1369.33 | S30: =SUM(S28:S29) -> 1412.82 | T30: =SUM(T28:T29) -> 1526.71 | U30: =SUM(U28:U29) -> 1648.88 | V30: =SUM(V28:V29) -> 1827.24 | W30: =SUM(W28:W29) -> 1999.62 | Y30: Total Assets | Z30: =Z19+Z29 -> 22161.47 | AA30: =AA19+AA29 -> 21333.41 | AB30: =AB19+AB29 -> 19667.92 | AC30: =AC19+AC29 -> 20552.62 | AD30: =AD19+AD29 -> 24561.34 | AE30: =AE19+AE29 -> 26584.48 | AG30: Equity share capital | AH30: 28735.4 | AI30: 28735.4 | AJ30: 32118.8 | AK30: 48679.7 | AL30: 50119.8 | AM30: 71393 | AO30: Other Financial Liabilities | AP30: 13490 | AQ30: 15145 | AR30: 6225 | AS30: 5091 | AT30: 4461 | AU30: 5156
A31: Total Assets | B31: =B19+B30 -> 300372.8 | C31: =C19+C30 -> 277747.1 | D31: =D19+D30 -> 271240.8 | E31: =E19+E30 -> 335577.2 | F31: =F19+F30 -> 444531 | G31: =G19+G30 -> 514360.4 | I31: Borrowings | J31: 0 | K31: 1505.1 | L31: 2373.9 | M31: 2434 | N31: 1504.4 | O31: 153.2 | Q31: Non-Current Liabilities | Y31: Equity and Liabilities | AG31: Other equity | AH31: -22755.5 | AI31: -66963.4 | AJ31: -94083.6 | AK31: -123038.8 | AL31: -154286.6 | AM31: -141713.2 | AO31: Deferred payment liabilities | AP31: 18839 | AQ31: 18837 | AR31: 37184 | AS31: 112844 | AT31: 108270 | AU31: 104410
A32: Equity and Liabilities | I32: Lease Liabilities | J32: 1967.4 | K32: 11232.7 | L32: 12087.7 | M32: 12420.6 | N32: 13820.2 | O32: 16325.7 | Q32: Borrowings | R32: 0 | S32: 0 | T32: 0 | U32: 0 | V32: 0 | W32: 0 | Y32: Equity | AG32: Non-controlling interests | AH32: 0 | AI32: 0 | AJ32: 0 | AK32: 0 | AL32: 0 | AM32: 0 | AO32: Deferred tax liabilities (net) | AP32: 0 | AQ32: 2526 | AR32: 7606 | AS32: 13861 | AT32: 20784 | AU32: 29357
A33: Equity | I33: Other financial liabilities | J33: 63.5 | K33: 523.6 | L33: 570.8 | M33: 382.4 | N33: 392.3 | O33: 397.8 | Q33: Lease Liabilities | R33: 34.8 | S33: 22.17 | T33: 23.49 | U33: 36.27 | V33: 35.36 | W33: 35.25 | Y33: Equity share capital | Z33: 285 | AA33: 285 | AB33: 285 | AC33: 285 | AD33: 285 | AE33: 285 | AG33: Total equity | AH33: =SUM(AH30:AH32) -> 5979.9 | AI33: =SUM(AI30:AI32) -> -38228 | AJ33: =SUM(AJ30:AJ32) -> -61964.8 | AK33: =SUM(AK30:AK32) -> -74359.1 | AL33: =SUM(AL30:AL32) -> -104166.8 | AM33: =SUM(AM30:AM32) -> -70320.2 | AO33: Provisions | AP33: 0 | AQ33: 0 | AR33: 99 | AS33: 124 | AT33: 127 | AU33: 132
A34: Equity share capital | B34: 2727.8 | C34: 2746 | D34: 2795 | E34: 2836.6 | F34: 2876.6 | G34: 2900.1 | I34: Provisions | J34: 302.3 | K34: 1566.6 | L34: 1719.8 | M34: 1873.8 | N34: 2159.2 | O34: 2465.6 | Q34: Other non current financial liabilities | R34: 7.4 | S34: 30.14 | T34: 38.59 | U34: 52.32 | V34: 27.91 | W34: 79.68 | Y34: Other equity | Z34: -1563.36 | AA34: -169.54 | AB34: 642.59 | AC34: 1233.26 | AD34: 1501.42 | AE34: 2736.17 | AG34: Non-current liabilities | AO34: Other non-current liabilities | AP34: 0 | AQ34: 0 | AR34: 448 | AS34: 788 | AT34: 612 | AU34: 1037
A35: Other Equity | B35: 98701.4 | C35: 74614.1 | D35: 72075.5 | E35: 76156.8 | F35: 79142.2 | G35: 110771.8 | I35: Deferred tax liabilities (net) | J35: 0 | K35: 70.3 | L35: 91.8 | M35: 0 | N35: 0 | O35: 407.2 | Q35: Provisions | R35: 9.9 | S35: 9.83 | T35: 9.51 | U35: 8.69 | V35: 0 | W35: 0 | Y35: Non-controlling interests | Z35: 4.75 | AA35: 28.17 | AB35: 28.49 | AC35: 30.34 | AD35: 3.88 | AE35: 3.11 | AG35: Loans from banks and others | AH35: 8627.9 | AI35: 6484.6 | AJ35: 2836.3 | AK35: 935.1 | AL35: 0 | AM35: 0 | AO35: Total Non-current liabilities | AP35: =SUM(AP28:AP34) -> 32329 | AQ35: =SUM(AQ28:AQ34) -> 36872 | AR35: =SUM(AR28:AR34) -> 75676 | AS35: =SUM(AS28:AS34) -> 165742 | AT35: =SUM(AT28:AT34) -> 186040 | AU35: =SUM(AU28:AU34) -> 193043
A36: Non-controlling interests | B36: 0 | C36: 0 | D36: 0 | E36: 0 | F36: 23545.1 | G36: 39795.8 | I36: Other non-current liabilities | J36: 52.1 | K36: 217.8 | L36: 146.2 | M36: 189.3 | N36: 796.2 | O36: 1135.6 | Q36: Other non current liabilities | R36: 88.69 | S36: 115.12 | T36: 73.41 | U36: 80.54 | V36: 65.22 | W36: 107.16 | Y36: Total equity | Z36: =SUM(Z33:Z35) -> -1273.61 | AA36: =SUM(AA33:AA35) -> 143.63 | AB36: =SUM(AB33:AB35) -> 956.08 | AC36: =SUM(AC33:AC35) -> 1548.6 | AD36: =SUM(AD33:AD35) -> 1790.3 | AE36: =SUM(AE33:AE35) -> 3024.28 | AG36: Deferred payment obligations | AH36: 87652.5 | AI36: 150930.9 | AJ36: 173114.5 | AK36: 188355 | AL36: 202896.2 | AM36: 182768 | AO36: Current Liabilities
A37: Total Equity | B37: =SUM(B34:B36) -> 101429.2 | C37: =SUM(C34:C36) -> 77360.1 | D37: =SUM(D34:D36) -> 74870.5 | E37: =SUM(E34:E36) -> 78993.4 | F37: =SUM(F34:F36) -> 105563.9 | G37: =SUM(G34:G36) -> 153467.7 | I37: Total Non-current liabilities | J37: =SUM(J31:J36) -> 2385.3 | K37: =SUM(K31:K36) -> 15116.1 | L37: =SUM(L31:L36) -> 16990.2 | M37: =SUM(M31:M36) -> 17300.1 | N37: =SUM(N31:N36) -> 18672.3 | O37: =SUM(O31:O36) -> 20885.1 | Q37: Total non current liabilities | R37: =SUM(R33:R36) -> 140.79 | S37: =SUM(S33:S36) -> 177.26 | T37: =SUM(T33:T36) -> 145 | U37: =SUM(U33:U36) -> 177.82 | V37: =SUM(V33:V36) -> 128.49 | W37: =SUM(W33:W36) -> 222.09 | Y37: Non-current liabilities | AG37: Total Long term borrowings | AH37: =AH35+AH36 -> 96280.4 | AI37: =AI35+AI36 -> 157415.5 | AJ37: =AJ35+AJ36 -> 175950.8 | AK37: =AK35+AK36 -> 189290.1 | AL37: =AL35+AL36 -> 202896.2 | AM37: =AM35+AM36 -> 182768 | AO37: Borrowings | AP37: 23242 | AQ37: 10775 | AR37: 26324 | AS37: 12946 | AT37: 10367 | AU37: 26285
A38: Non-Current Liabilities | I38: Current Liabilities | Q38: Current Liabilities | Y38: Borrowings | Z38: 6797.78 | AA38: 8886.39 | AB38: 5990.92 | AC38: 5008.58 | AD38: 4745.73 | AE38: 6996.71 | AG38: Trade payables | AH38: 666 | AI38: 126.8 | AJ38: 85.2 | AK38: 105.8 | AL38: 38.6 | AM38: 0.4 | AO38: Lease Liabilities | AP38: 0 | AQ38: 0 | AR38: 2040 | AS38: 3407 | AT38: 3200 | AU38: 3794
A39: Borrowings | B39: 70471.2 | C39: 89908.8 | D39: 97322.8 | E39: 136230 | F39: 130962.6 | G39: 104863.8 | I39: Borrowings | J39: 2418.4 | K39: 5465.2 | L39: 3112.9 | M39: 2278.6 | N39: 2807.4 | O39: 2109.2 | Q39: Borrowings | R39: 0 | S39: 0 | T39: 0 | U39: 0 | V39: 0 | W39: 0 | Y39: Other financial liabilities | Z39: 33.43 | AA39: 8.79 | AB39: 49.18 | AC39: 132.59 | AD39: 159.74 | AE39: 37.25 | AG39: Lease Liabilities | AH39: 0 | AI39: 0 | AJ39: 11432.5 | AK39: 25061.2 | AL39: 24325 | AM39: 29216.6 | AO39: Total outstanding dues of micro and small enterprises | AP39: 38 | AQ39: 6 | AR39: 27 | AS39: 21 | AT39: 15 | AU39: 45
A40: Lease Liabilities | B40: 30703.9 | C40: 29998.6 | D40: 17435 | E40: 35136.9 | F40: 53927.1 | G40: 55670.1 | I40: Total outstanding dues of micro and small enterprises | J40: 18.9 | K40: 37.4 | L40: 52.2 | M40: 49.4 | N40: 70.2 | O40: 45.3 | Q40: Lease Liabilities | R40: 7.74 | S40: 8.01 | T40: 8.02 | U40: 5.52 | V40: 10.26 | W40: 9.29 | Y40: Lease liabilities | Z40: 1394.02 | AA40: 1153.06 | AB40: 955.72 | AC40: 771.58 | AD40: 822.38 | AE40: 1162.6 | AG40: Other non current financial liabilities | AH40: 27407.3 | AI40: 17281.9 | AJ40: 6846.1 | AK40: 6662.3 | AL40: 7330.1 | AM40: 135.8 | AO40: Total outstanding dues other than above | AP40: 4662 | AQ40: 2233 | AR40: 1944 | AS40: 3396 | AT40: 4321 | AU40: 4428
A41: Others | B41: 3146.9 | C41: 7429.1 | D41: 3420.1 | E41: 5187.4 | F41: =289+8503.6 -> 8792.6 | G41: 3864.2 | I41: Total outstanding dues of creditors other than above | J41: 788.3 | K41: 3221.4 | L41: 2077.1 | M41: 2072.5 | N41: 2209.5 | O41: 2399.7 | Q41: Total outstanding dues of micro and small enterprises | R41: 64.81 | S41: 140.64 | T41: 149.92 | U41: 149.02 | V41: 190.45 | W41: 206.29 | Y41: Provisions | Z41: 602.23 | AA41: 547.52 | AB41: 645.36 | AC41: 687.56 | AD41: 749.68 | AE41: 713 | AG41: Long term provisions | AH41: 342.1 | AI41: 41.6 | AJ41: 38.4 | AK41: 23.5 | AL41: 20.9 | AM41: 5 | AO41: Total Trade payables | AP41: =AP39+AP40 -> 4700 | AQ41: =AQ39+AQ40 -> 2239 | AR41: =AR39+AR40 -> 1971 | AS41: =AS39+AS40 -> 3417 | AT41: =AT39+AT40 -> 4336 | AU41: =AU39+AU40 -> 4473
A42: Deferred revenue | B42: 1218.5 | C42: 1390.6 | D42: 1751.4 | E42: 1531.1 | F42: 3413.9 | G42: 3518.5 | I42: Total Trade Payables | J42: =J40+J41 -> 807.2 | K42: =K40+K41 -> 3258.8 | L42: =L40+L41 -> 2129.3 | M42: =M40+M41 -> 2121.9 | N42: =N40+N41 -> 2279.7 | O42: =O40+O41 -> 2445 | Q42: Total outstanding dues of creditors other than above | R42: 314.06 | S42: 392.06 | T42: 343.11 | U42: 419.68 | V42: 580.07 | W42: 1223.46 | Y42: Deferred tax liabilities (net) | Z42: 30.37 | AA42: 27.84 | AB42: 30.46 | AC42: 33.31 | AD42: 195.9 | AE42: 140.73 | AG42: Deferred tax liabilities (net) | AH42: 3.8 | AI42: 2.2 | AJ42: 0 | AK42: 0 | AL42: 0.4 | AM42: 16.7 | AO42: Deferred payment liabilities | AP42: 0 | AQ42: 0 | AR42: 0 | AS42: 4423 | AT42: 4574 | AU42: 4736
A43: Provisions | B43: 191.9 | C43: 220.5 | D43: 260.3 | E43: 253.4 | F43: 544.3 | G43: 3039.6 | I43: Lease Liabilities | J43: 241.4 | K43: 2179.2 | L43: 2151.5 | M43: 2051.7 | N43: 2399 | O43: 2567.7 | Q43: Total Trade Payables | R43: =R41+R42 -> 378.87 | S43: =S41+S42 -> 532.7 | T43: =T41+T42 -> 493.03 | U43: =U41+U42 -> 568.7 | V43: =V41+V42 -> 770.52 | W43: =W41+W42 -> 1429.75 | Y43: Other non-current liabilities | Z43: 3206.82 | AA43: 2799.61 | AB43: 2609.6 | AC43: 2584.46 | AD43: 2426.96 | AE43: 2006.1 | AG43: Other non-current liabilities | AH43: 461.1 | AI43: 438.1 | AJ43: 507 | AK43: 436.2 | AL43: 412 | AM43: 430.4 | AO43: Other Financial Liabilities | AP43: 4957 | AQ43: 8086 | AR43: 6488 | AS43: 31494 | AT43: 31828 | AU43: 17621
A44: Deferred tax liabilities (net) | B44: 0 | C44: 0 | D44: 0 | E44: 0 | F44: 2511.8 | G44: 9354.9 | I44: Other financial liabilities | J44: 230.6 | K44: 2323.4 | L44: 651 | M44: 1159.2 | N44: 1769.7 | O44: 1860.7 | Q44: Other current financial liabilities | R44: 182.72 | S44: 162.8 | T44: 304.79 | U44: 406.44 | V44: 546.47 | W44: 628.99 | Y44: Total non-current liabilities | Z44: =SUM(Z38:Z43) -> 12064.65 | AA44: =SUM(AA38:AA43) -> 13423.21 | AB44: =SUM(AB38:AB43) -> 10281.24 | AC44: =SUM(AC38:AC43) -> 9218.08 | AD44: =SUM(AD38:AD43) -> 9100.39 | AE44: =SUM(AE38:AE43) -> 11056.39 | AG44: Total non-current liabilities | AH44: =SUM(AH37,AH38:AH43) -> 125160.7 | AI44: =SUM(AI37,AI38:AI43) -> 175306.1 | AJ44: =SUM(AJ37,AJ38:AJ43) -> 194860 | AK44: =SUM(AK37,AK38:AK43) -> 221579.1 | AL44: =SUM(AL37,AL38:AL43) -> 235023.2 | AM44: =SUM(AM37,AM38:AM43) -> 212572.9 | AO44: Other current liabilities | AP44: 5462 | AQ44: 9072 | AR44: 9055 | AS44: 9842 | AT44: 10605 | AU44: 12655
A45: Other non current liabilities | B45: 0 | C45: 0 | D45: 0 | E45: 0 | F45: 147 | G45: 141.4 | I45: Other current liabilities | J45: 97.8 | K45: 544.1 | L45: 516.3 | M45: 417.2 | N45: 644.9 | O45: 587.6 | Q45: Other current liabilities | R45: 295.03 | S45: 403.43 | T45: 352.68 | U45: 500.63 | V45: 698.52 | W45: 785.17 | Y45: Current Liabilities | AG45: Current Liabilities | AO45: Provisions | AP45: 59 | AQ45: 72 | AR45: 80 | AS45: 91 | AT45: 86 | AU45: 98
A46: Total Non-current Liabilities | B46: =SUM(B39:B45) -> 105732.4 | C46: =SUM(C39:C45) -> 128947.6 | D46: =SUM(D39:D45) -> 120189.6 | E46: =SUM(E39:E45) -> 178338.8 | F46: =SUM(F39:F45) -> 200299.3 | G46: =SUM(G39:G45) -> 180452.5 | I46: Provisions | J46: 20 | K46: 48.1 | L46: 53.5 | M46: 67.6 | N46: 74 | O46: 84.3 | Q46: Provisions | R46: 20.08 | S46: 12.91 | T46: 27.94 | U46: 31.15 | V46: 68.08 | W46: 86.3 | Y46: Borrowings | Z46: 2288.46 | AA46: 914.75 | AB46: 1905.87 | AC46: 2524.9 | AD46: 5372.03 | AE46: 3883.34 | AG46: Short term borrowings | AH46: 32.2 | AI46: 0 | AJ46: 14966.9 | AK46: 12295.9 | AL46: =4196.2+537.4 -> 4733.6 | AM46: =2326+11202.2 -> 13528.2 | AO46: Total Current liabilities | AP46: =SUM(AP37:AP38,AP41,AP42:AP45) -> 38420 | AQ46: =SUM(AQ37:AQ38,AQ41,AQ42:AQ45) -> 30244 | AR46: =SUM(AR37:AR38,AR41,AR42:AR45) -> 45958 | AS46: =SUM(AS37:AS38,AS41,AS42:AS45) -> 65620 | AT46: =SUM(AT37:AT38,AT41,AT42:AT45) -> 64996 | AU46: =SUM(AU37:AU38,AU41,AU42:AU45) -> 69662
A47: Current Liabilities | I47: Current tax liabilities (net) | J47: 10.9 | K47: 131.8 | L47: 212.4 | M47: 66.6 | N47: 181.8 | O47: 132.3 | Q47: Total current liabilities | R47: =SUM(R40,R43,R44:R46) -> 884.44 | S47: =SUM(S40,S43,S44:S46) -> 1119.85 | T47: =SUM(T40,T43,T44:T46) -> 1186.46 | U47: =SUM(U40,U43,U44:U46) -> 1512.44 | V47: =SUM(V40,V43,V44:V46) -> 2093.85 | W47: =SUM(W40,W43,W44:W46) -> 2939.5 | Y47: Trade Payables | Z47: 3844.99 | AA47: 3239.47 | AB47: 3006.46 | AC47: 3277.21 | AD47: 3656.23 | AE47: 3569.16 | AG47: Lease Liabilities | AH47: 0 | AI47: 0 | AJ47: 11410.9 | AK47: 11118.8 | AL47: 11854.2 | AM47: 7715.9 | AO47: Total Equity and Liabilities | AP47: =AP26+AP35+AP46 -> 241705 | AQ47: =AQ26+AQ35+AQ46 -> 250089 | AR47: =AR26+AR35+AR46 -> 319723 | AS47: =AS26+AS35+AS46 -> 447881 | AT47: =AT26+AT35+AT46 -> 487405 | AU47: =AU26+AU35+AU46 -> 524082
A48: Borrowings | B48: 7309.2 | C48: 1693.5 | D48: 10301.1 | E48: 4411 | F48: 20953.9 | G48: 43448.5 | I48: Total current liabilities | J48: =SUM(J39,J42,J43:J47) -> 3826.3 | K48: =SUM(K39,K42,K43:K47) -> 13950.6 | L48: =SUM(L39,L42,L43:L47) -> 8826.9 | M48: =SUM(M39,M42,M43:M47) -> 8162.8 | N48: =SUM(N39,N42,N43:N47) -> 10156.5 | O48: =SUM(O39,O42,O43:O47) -> 9786.8 | Q48: Total liabilities | R48: =R37+R47 -> 1025.23 | S48: =S37+S47 -> 1297.11 | T48: =T37+T47 -> 1331.46 | U48: =U37+U47 -> 1690.26 | V48: =V37+V47 -> 2222.34 | W48: =W37+W47 -> 3161.59 | Y48: Other financial liabilities | Z48: 2599.77 | AA48: 847.58 | AB48: 717.76 | AC48: 913.47 | AD48: 928.52 | AE48: 986.7 | AG48: Trade payables | AH48: 11767.2 | AI48: 13275.7 | AJ48: 13169.9 | AK48: 13536.4 | AL48: 13435.9 | AM48: 10748
A49: Current maturities of Long term borrowings | B49: 4582.8 | C49: 2805.4 | D49: 0 | E49: 0 | F49: 0 | G49: 0 | I49: Total liabilities | J49: =J37+J48 -> 6211.6 | K49: =K37+K48 -> 29066.7 | L49: =L37+L48 -> 25817.1 | M49: =M37+M48 -> 25462.9 | N49: =N37+N48 -> 28828.8 | O49: =O37+O48 -> 30671.9 | Q49: Total equity and liabilities | R49: =R30+R48 -> 2394.56 | S49: =S30+S48 -> 2709.93 | T49: =T30+T48 -> 2858.17 | U49: =U30+U48 -> 3339.14 | V49: =V30+V48 -> 4049.58 | W49: =W30+W48 -> 5161.21 | Y49: Lease liabilities | Z49: 298.58 | AA49: 282.08 | AB49: 269.03 | AC49: 271.58 | AD49: 323.03 | AE49: 314.67 | AG49: Other current financial liabilities | AH49: 37713.5 | AI49: 46681.9 | AJ49: 13960.6 | AK49: 15355.7 | AL49: 15438.5 | AM49: 14809.3 | AO49: Working Capital | AP49: =AP20-AP46 -> -9977 | AQ49: =AQ20-AQ46 -> -7809 | AR49: =AR20-AR46 -> -16623 | AS49: =AS20-AS46 -> -35103 | AT49: =AT20-AT46 -> -31905 | AU49: =AU20-AU46 -> -19719
A50: Lease Liabilities | B50: 5733.4 | C50: 6001.1 | D50: 4846.1 | E50: 5918.4 | F50: 9748.7 | G50: 9659.7 | I50: Total equity and liabilities | J50: =J29+J49 -> 19753.9 | K50: =K29+K49 -> 44943.7 | L50: =L29+L49 -> 47967.6 | M50: =M29+M49 -> 46572.4 | N50: =N29+N49 -> 55867.6 | O50: =O29+O49 -> 63170.2 | Y50: Provisions | Z50: 123.79 | AA50: 140.57 | AB50: 121.28 | AC50: 159.61 | AD50: 179.57 | AE50: 225.42 | AG50: Other current liabilities | AH50: 46216.8 | AI50: 6399.1 | AJ50: 7601.8 | AK50: 7701.1 | AL50: 8114.5 | AM50: 8480.2 | AP50: Ratio | AQ50: 2026 | AR50: 2027 | AS50: 2028 | AT50: 2029 | AU50: 2030
A51: Derivative instruments | B51: 3.5 | C51: 43 | D51: 17.6 | E51: 53.2 | F51: 1220.7 | G51: 192.1 | Y51: Current tax liabilities (net) | Z51: 290.92 | AA51: 490.81 | AB51: 486.6 | AC51: 614.3 | AD51: 1140.8 | AE51: 688.05 | AG51: Short term provisions | AH51: 4.93 | AI51: 4.58 | AJ51: 23.8 | AK51: 14.8 | AL51: 36.5 | AM51: 73.4 | AO51: Working Capital Forecast | AP51: =-(AVERAGE(AR49:AU49))/AVERAGE('Income Statement'!AP6:AU6) -> 0.30407195 | AQ51: =-DCF!AW4*'Balance Sheet'!$AP$51 -> -39649.793 | AR51: =-DCF!AX4*'Balance Sheet'!$AP$51 -> -44923.694 | AS51: =-DCF!AY4*'Balance Sheet'!$AP$51 -> -50899.087 | AT51: =-DCF!AZ4*'Balance Sheet'!$AP$51 -> -57669.279 | AU51: =-DCF!BA4*'Balance Sheet'!$AP$51 -> -65339.989
A52: Total outstanding dues of micro and small enterprises | B52: 12.2 | C52: 70.2 | D52: 48.1 | E52: 73.1 | F52: 0 | G52: 0 | I52: Working Capital | J52: =J23-J48 -> 1125 | K52: =K23-K48 -> -4320.8 | L52: =L23-L48 -> 3484.4 | M52: =M23-M48 -> 544.8 | N52: =N23-N48 -> 333.5 | O52: =O23-O48 -> 3143 | Q52: Working Capital | R52: =R24-R47 -> 231.08 | S52: =S24-S47 -> 527.25 | T52: =T24-T47 -> 368.08 | U52: =U24-U47 -> 583.37 | V52: =V24-V47 -> 430.31 | W52: =W24-W47 -> 846.94 | Y52: Other current liabilities | Z52: 1895.34 | AA52: 1846.82 | AB52: 1919.13 | AC52: 2024.84 | AD52: 2070.44 | AE52: 2825.05 | AG52: Current tax liability (net) | AH52: 0 | AI52: 0 | AJ52: 0 | AK52: 0 | AL52: 528.1 | AM52: 258.9
A53: Total outstanding dues of creditors other than above | B53: 18643.1 | C53: 22224.8 | D53: 25528.2 | E53: 25925.8 | F53: 35132.5 | G53: 38153.7 | J53: Ratio | K53: 2026 | L53: 2027 | M53: 2028 | N53: 2029 | O53: 2030 | R53: Ratio | S53: 2026 | T53: 2027 | U53: 2028 | V53: 2029 | W53: 2030 | Y53: Liabilities relating to assets held for sale | Z53: 28.58 | AA53: 4.49 | AB53: 4.52 | AC53: 0.03 | AD53: 0.03 | AE53: 11.52 | AG53: Total current liabilities | AH53: =SUM(AH46:AH51) -> 95734.63 | AI53: =SUM(AI46:AI51) -> 66361.28 | AJ53: =SUM(AJ46:AJ51) -> 61133.9 | AK53: =SUM(AK46:AK51) -> 60022.7 | AL53: =SUM(AL46:AL51) -> 53613.2 | AM53: =SUM(AM46:AM51) -> 55355
A54: Total Trade Payables | B54: =B52+B53 -> 18655.3 | C54: =C52+C53 -> 22295 | D54: =D52+D53 -> 25576.3 | E54: =E52+E53 -> 25998.9 | F54: =F52+F53 -> 35132.5 | G54: =G52+G53 -> 38153.7 | I54: Working Capital Forecast | J54: =ABS(AVERAGE(L52:O52))/AVERAGE('Income Statement'!J6:O6) -> 0.082019947 | K54: =DCF!M4*'Balance Sheet'!$J$54 -> 3203.0966 | L54: =DCF!N4*'Balance Sheet'!$J$54 -> 4105.5192 | M54: =DCF!O4*'Balance Sheet'!$J$54 -> 5262.1853 | N54: =DCF!P4*'Balance Sheet'!$J$54 -> 6744.7241 | O54: =DCF!Q4*'Balance Sheet'!$J$54 -> 8644.9451 | Q54: Working Capital Forecast | R54: =AVERAGE('Balance Sheet'!R52:W52)/AVERAGE('Income Statement'!R7:W7) -> 0.24225277 | S54: =DCF!V4*'Balance Sheet'!$R$54 -> 1035.7307 | T54: =DCF!W4*'Balance Sheet'!$R$54 -> 1247.0085 | U54: =DCF!X4*'Balance Sheet'!$R$54 -> 1501.3846 | V54: =DCF!Y4*'Balance Sheet'!$R$54 -> 1807.6506 | W54: =DCF!Z4*'Balance Sheet'!$R$54 -> 2176.3915 | Y54: Total Current Liabilities | Z54: =SUM(Z46:Z53) -> 11370.43 | AA54: =SUM(AA46:AA53) -> 7766.57 | AB54: =SUM(AB46:AB53) -> 8430.65 | AC54: =SUM(AC46:AC53) -> 9785.94 | AD54: =SUM(AD46:AD53) -> 13670.65 | AE54: =SUM(AE46:AE53) -> 12503.91 | AG54: Total Liabilities | AH54: =AH44+AH53 -> 220895.33 | AI54: =AI44+AI53 -> 241667.38 | AJ54: =AJ44+AJ53 -> 255993.9 | AK54: =AK44+AK53 -> 281601.8 | AL54: =AL44+AL53 -> 288636.4 | AM54: =AM44+AM53 -> 267927.9
A55: Others | B55: 9673.7 | C55: 11148.8 | D55: 7450.2 | E55: 12458.5 | F55: 25345.6 | G55: 33302.4 | Y55: Total Liabilities | Z55: =Z44+Z54 -> 23435.08 | AA55: =AA44+AA54 -> 21189.78 | AB55: =AB44+AB54 -> 18711.89 | AC55: =AC44+AC54 -> 19004.02 | AD55: =AD44+AD54 -> 22771.04 | AE55: =AE44+AE54 -> 23560.3 | AG55: Total Equity and Liabilities | AH55: =AH33+AH54 -> 226875.23 | AI55: =AI33+AI54 -> 203439.38 | AJ55: =AJ33+AJ54 -> 194029.1 | AK55: =AK33+AK54 -> 207242.7 | AL55: =AL33+AL54 -> 184469.6 | AM55: =AM33+AM54 -> 197607.7
A56: Deferred revenue | B56: 3524.7 | C56: 4252 | D56: 5099.9 | E56: 5530.5 | F56: 8726.2 | G56: 9772.9 | Y56: Total Equity and Liabilities | Z56: =Z36+Z55 -> 22161.47 | AA56: =AA36+AA55 -> 21333.41 | AB56: =AB36+AB55 -> 19667.97 | AC56: =AC36+AC55 -> 20552.62 | AD56: =AD36+AD55 -> 24561.34 | AE56: =AE36+AE55 -> 26584.58
A57: Provisions | B57: 40759 | C57: 20156.6 | D57: 20914.6 | E57: 21291.8 | F57: 28328.2 | G57: 36155.2
A58: Current tax liabilities (net) | B58: 226.8 | C58: 41.5 | D58: 20.4 | E58: 1.8 | F58: 3303.1 | G58: 2003.5 | Y58: Working Capital | Z58: =Z29-Z54 -> -5428.32 | AA58: =AA29-AA54 -> -1929.43 | AB58: =AB29-AB54 -> -3560.87 | AC58: =AC29-AC54 -> -3974.95 | AD58: =AD29-AD54 -> -7671.72 | AE58: =AE29-AE54 -> -5265.23 | AG58: Working Capital | AH58: =AH26-AH53 -> -79048.53 | AI58: =AI26-AI53 -> -52261.78 | AJ58: =AJ26-AJ53 -> -44366.44 | AK58: =AK26-AK53 -> -46155.26 | AL58: =AL26-AL53 -> -40703.4 | AM58: =AM26-AM53 -> -24315.5
A59: Other current liabilities | B59: 2742.8 | C59: 3002.5 | D59: 1954.5 | E59: 2580.9 | F59: 5908.9 | G59: 7752.2 | Z59: Ratio | AA59: 2026 | AB59: 2027 | AC59: 2028 | AD59: 2029 | AE59: 2030 | AH59: Ratio | AI59: 2026 | AJ59: 2027 | AK59: 2028 | AL59: 2029 | AM59: 2030
A60: Total Current Liabilities | B60: =SUM(B48:B51,B54,B55:B59) -> 93211.2 | C60: =SUM(C48:C51,C54,C55:C59) -> 71439.4 | D60: =SUM(D48:D51,D54,D55:D59) -> 76180.7 | E60: =SUM(E48:E51,E54,E55:E59) -> 78245 | F60: =SUM(F48:F51,F54,F55:F59) -> 138667.8 | G60: =SUM(G48:G51,G54,G55:G59) -> 180440.2 | Y60: Working Capital Forecast | Z60: =ABS(AVERAGE(AD58:AE58))/AVERAGE('Income Statement'!Z6:AE6) -> 0.34062398 | AA60: =-'Income Statement'!Z6*'Balance Sheet'!$Z$60 -> -5837.5014 | AB60: =-'Income Statement'!AA6*'Balance Sheet'!$Z$60 -> -5878.1004 | AC60: =-'Income Statement'!AB6*'Balance Sheet'!$Z$60 -> -5809.962 | AD60: =-'Income Statement'!AC6*'Balance Sheet'!$Z$60 -> -6199.8368 | AE60: =-'Income Statement'!AD6*'Balance Sheet'!$Z$60 -> -7169.7261 | AG60: Working Capital Forecast | AH60: =(AM58/AH58)^(1/6)-1 -> -0.17839154 | AI60: =AM58*(1+AH60) -> -19977.82 | AJ60: =AI60*(1+$AH$60) -> -16413.946 | AK60: =AJ60*(1+$AH$60) -> -13485.837 | AL60: =AK60*(1+$AH$60) -> -11080.078 | AM60: =AL60*(1+$AH$60) -> -9103.4856
A61: Total Liabilities | B61: =B46+B60 -> 198943.6 | C61: =C46+C60 -> 200387 | D61: =D46+D60 -> 196370.3 | E61: =E46+E60 -> 256583.8 | F61: =F46+F60 -> 338967.1 | G61: =G46+G60 -> 360892.7
A62: Total Equity and Liabilities | B62: =B37+B61 -> 300372.8 | C62: =C37+C61 -> 277747.1 | D62: =D37+D61 -> 271240.8 | E62: =E37+E61 -> 335577.2 | F62: =F37+F61 -> 444531 | G62: =G37+G61 -> 514360.4
A64: Working Capital | B64: =B30-B60 -> -34429.9 | C64: =C30-C60 -> -31367.5 | D64: =D30-D60 -> -42889.5 | E64: =E30-E60 -> -37668 | F64: =F30-F60 -> -80391.7 | G64: =G30-G60 -> -112851.4
B65: Ratio | C65: 2026 | D65: 2027 | E65: 2028 | F65: 2029 | G65: 2030
A66: Working Capital Forecast | B66: =ABS(AVERAGE(B64:G64))/AVERAGE('Income Statement'!B6:G6) -> 0.55854659 | C66: =-DCF!D4*'Balance Sheet'!$B$66 -> -117645.15 | D66: =-DCF!E4*'Balance Sheet'!$B$66 -> -141953.67 | E66: =-DCF!F4*'Balance Sheet'!$B$66 -> -171284.96 | F66: =-DCF!G4*'Balance Sheet'!$B$66 -> -206676.85 | G66: =-DCF!H4*'Balance Sheet'!$B$66 -> -249381.63

Sheet Income Statement
A1: Income Statement | F1: #VALUE! | N1: #VALUE! | V1: #VALUE! | AD1: #VALUE! | AL1: #VALUE! | AT1: #VALUE!
A2: Particulars | B2: 2020 | C2: 2021 | D2: 2022 | E2: 2023 | F2: 2024 | G2: 2025 | I2: Particulars | J2: 2020 | K2: 2021 | L2: 2022 | M2: 2023 | N2: 2024 | O2: 2025 | Q2: Particulars | R2: 2020 | S2: 2021 | T2: 2022 | U2: 2023 | V2: 2024 | W2: 2025 | Y2: Particulars | Z2: 2020 | AA2: 2021 | AB2: 2022 | AC2: 2023 | AD2: 2024 | AE2: 2025 | AG2: Particulars | AH2: 2020 | AI2: 2021 | AJ2: 2022 | AK2: 2023 | AL2: 2024 | AM2: 2025 | AO2: Particulars | AP2: 2020 | AQ2: 2021 | AR2: 2022 | AS2: 2023 | AT2: 2024 | AU2: 2025
A3: Income | I3: Income | Q3: Income | Y3: Income | AG3: Income | AO3: Income
A4: Revenue from Operations | B4: 54317.1 | C4: 64325.9 | D4: 70795 | E4: 84720.1 | F4: 149982.4 | G4: 172985.2 | I4: Revenue from Operations | J4: 6743 | K4: 13954.3 | L4: 27717.2 | M4: 28381.8 | N4: 28600.6 | O4: 30122.8 | Q4: Revenue from operations | R4: 1128.05 | S4: 1377.82 | T4: 1548.45 | U4: 1963.51 | V4: 2567.82 | W4: 3477.5 | Y4: Revenue from Operations | Z4: 17067.99 | AA4: 17100.1 | AB4: 16724.73 | AC4: 17838.26 | AD4: 20784.68 | AE4: 23108.59 | AG4: Service revenue | AH4: 44912.3 | AI4: 41933.1 | AJ4: 38489.5 | AK4: 42133.9 | AL4: 42554.9 | AM4: 43453.7 | AO4: Revenue from operations | AP4: 54316 | AQ4: 69888 | AR4: 77356 | AS4: 91373 | AT4: 100119 | AU4: 114141
A5: Other income | B5: 2242.5 | C5: 2387.9 | D5: 604 | E5: 2633.8 | F5: 1435.4 | G5: 1573.7 | I5: Other income | J5: 128.7 | K5: 196.9 | L5: 352.5 | M5: 361.3 | N5: 361.1 | O5: 345.8 | Q5: Other income | R5: 37.99 | S5: 32.12 | T5: 26.83 | U5: 37.01 | V5: 56.3 | W5: 66.01 | Y5: Other income | Z5: 69.68 | AA5: 156.76 | AB5: 332.09 | AC5: 363.15 | AD5: 264.12 | AE5: 130.3 | AG5: Sale of trading goods | AH5: 4.4 | AI5: 5.1 | AJ5: 8.9 | AK5: 8.7 | AL5: 17.8 | AM5: 2 | AO5: Other income | AP5: 87 | AQ5: 548 | AR5: 229 | AS5: 368 | AT5: 458 | AU5: 947
A6: Total Income | B6: =SUM(B4:B5) -> 56559.6 | C6: =SUM(C4:C5) -> 66713.8 | D6: =SUM(D4:D5) -> 71399 | E6: =SUM(E4:E5) -> 87353.9 | F6: =SUM(F4:F5) -> 151417.8 | G6: =SUM(G4:G5) -> 174558.9 | I6: Total Income | J6: =SUM(J4:J5) -> 6871.7 | K6: =SUM(K4:K5) -> 14151.2 | L6: =SUM(L4:L5) -> 28069.7 | M6: =SUM(M4:M5) -> 28743.1 | N6: =SUM(N4:N5) -> 28961.7 | O6: =SUM(O4:O5) -> 30468.6 | Q6: Finance income | R6: -0.25 | S6: 1.35 | T6: 2.45 | U6: 1.68 | V6: -1.95 | W6: 7.53 | Y6: Total Income | Z6: =SUM(Z4:Z5) -> 17137.67 | AA6: =SUM(AA4:AA5) -> 17256.86 | AB6: =SUM(AB4:AB5) -> 17056.82 | AC6: =SUM(AC4:AC5) -> 18201.41 | AD6: =SUM(AD4:AD5) -> 21048.8 | AE6: =SUM(AE4:AE5) -> 23238.89 | AG6: Other operating income | AH6: 40.8 | AI6: 14 | AJ6: 17.1 | AK6: 34.6 | AL6: 79 | AM6: 115.6 | AO6: Total Income | AP6: =AP4+AP5 -> 54403 | AQ6: =AQ4+AQ5 -> 70436 | AR6: =AR4+AR5 -> 77585 | AS6: =AS4+AS5 -> 91741 | AT6: =AT4+AT5 -> 100577 | AU6: =AU4+AU5 -> 115088
A7: Expenses | I7: Expenses | Q7: Total income | R7: =SUM(R4:R6) -> 1165.79 | S7: =SUM(S4:S6) -> 1411.29 | T7: =SUM(T4:T6) -> 1577.73 | U7: =SUM(U4:U6) -> 2002.2 | V7: =SUM(V4:V6) -> 2622.17 | W7: =SUM(W4:W6) -> 3551.04 | Y7: Expenses | AG7: Other income | AH7: 1039.3 | AI7: 174.2 | AJ7: 129.4 | AK7: 311.3 | AL7: 113.2 | AM7: 1020.6 | AO7: Expenses
A8: Network operating expenses | B8: 13641.9 | C8: 15120.5 | D8: 17187.7 | E8: 18385.7 | F8: 30018.8 | G8: 33504.3 | I8: Cost of material consumed | J8: 0 | K8: 0 | L8: 0 | M8: 0 | N8: 0 | O8: 3.8 | Q8: Expenses | Y8: Network transmission expense | Z8: 6777.56 | AA8: 6333.27 | AB8: 6199.49 | AC8: 6375.49 | AD8: 8078.73 | AE8: 10047.77 | AG8: Total income | AH8: =SUM(AH4:AH7) -> 45996.8 | AI8: =SUM(AI4:AI7) -> 42126.4 | AJ8: =SUM(AJ4:AJ7) -> 38644.9 | AK8: =SUM(AK4:AK7) -> 42488.5 | AL8: =SUM(AL4:AL7) -> 42764.9 | AM8: =SUM(AM4:AM7) -> 44591.9 | AO8: Network Operating expenses | AP8: 16930 | AQ8: 22058 | AR8: 25080 | AS8: 28702 | AT8: 30558 | AU8: 32932
A9: Access charges | B9: 9076.7 | C9: 8564.7 | D9: 3230.9 | E9: 4131.8 | F9: 7518.5 | G9: 7171.3 | I9: Power and fuel | J9: 2367.2 | K9: 5153.6 | L9: 10265.8 | M9: 10590.8 | N9: 11149.9 | O9: 11445 | Q9: Access and other charges | R9: 249.03 | S9: 338.17 | T9: 432.6 | U9: 514.96 | V9: 544.14 | W9: 569.94 | Y9: Employee benefit expense | Z9: 3039.14 | AA9: 3049.09 | AB9: 3040.34 | AC9: 3597.46 | AD9: 4342.82 | AE9: 4557.28 | AG9: Expenses | AO9: Access charges | AP9: 5795 | AQ9: 4631 | AR9: 719 | AS9: 881 | AT9: 1135 | AU9: 1685
A10: License fee/Spectrum charges | B10: 5365.3 | C10: 6789.9 | D10: 8462.3 | E10: 8792.5 | F10: 12035.8 | G10: 13829 | I10: Employee benefit expenses | J10: 293.5 | K10: 512.6 | L10: 772.2 | M10: 774.1 | N10: 782.3 | O10: 841.4 | Q10: License fee and spectrum charges | R10: 47.93 | S10: 56.56 | T10: 66.79 | U10: 77.26 | V10: 82.13 | W10: 99.52 | Y10: Finance costs | Z10: 470.74 | AA10: 420.2 | AB10: 360.25 | AC10: 432.46 | AD10: 630.09 | AE10: 729.06 | AG10: Cost of trading goods | AH10: 3.9 | AI10: 3 | AJ10: 7 | AK10: 7.8 | AL10: 15.6 | AM10: 1.7 | AO10: License fees/Spectrum charges | AP10: 5720 | AQ10: 7755 | AR10: 9074 | AS10: 9132 | AT10: 9213 | AU10: 10494
A11: Employee benefit expenses | B11: 1520.2 | C11: 1664.5 | D11: 1795.4 | E11: 1966.4 | F11: 5323.1 | G11: 6308.9 | I11: Repairs and maintenance | J11: 250.3 | K11: 724.6 | L11: 1346.7 | M11: 1350.6 | N11: 1399.1 | O11: 1441 | Q11: Expenses on project | R11: 340.08 | S11: 414.5 | T11: 459.47 | U11: 754.83 | V11: 1232.33 | W11: 2020.94 | Y11: Depreciation and amortisation expense | Z11: 2357.72 | AA11: 2313.87 | AB11: 2204.54 | AC11: 2261.81 | AD11: 2397.35 | AE11: 2592.1 | AG11: Employee benefit expenses | AH11: 2164.3 | AI11: 2030 | AJ11: 1735.1 | AK11: 1866.3 | AL11: 2122.4 | AM11: 2230.9 | AO11: Employee benefit expenses | AP11: 1463 | AQ11: 1337 | AR11: 1539 | AS11: 1756 | AT11: 1896 | AU11: 1987
A12: Sales and marketing expenses | B12: 1818 | C12: 2064.9 | D12: 3149.7 | E12: 4638.3 | F12: 10788.2 | G12: 11460.1 | I12: Other expenses | J12: 214.4 | K12: 303.6 | L12: 389.6 | M12: 5899.3 | N12: 575.4 | O12: -4453.1 | Q12: Employee benefit expenses | R12: 120.53 | S12: 126.7 | T12: 185.79 | U12: 195.27 | V12: 204.53 | W12: 209.72 | Y12: Operating and other expenses | Z12: 3962.34 | AA12: 3457.16 | AB12: 3258.18 | AC12: 3547.08 | AD12: 4045.93 | AE12: 3934.51 | AG12: Network expenses and IT outsourcing cost | AH12: 10991.6 | AI12: 9593.8 | AJ12: 9818.2 | AK12: 10078.3 | AL12: 9810.4 | AM12: 9439.1 | AO12: Finance costs | AP12: 6617 | AQ12: 3840 | AR12: 4377 | AS12: 4059 | AT12: 3999 | AU12: 4837
A13: Other expenses | B13: 2761.4 | C13: 2137.3 | D13: 2268.5 | E13: 3006.7 | F13: 6006.2 | G13: 7552.4 | I13: Total expenses | J13: =SUM(J8:J12) -> 3125.4 | K13: =SUM(K8:K12) -> 6694.4 | L13: =SUM(L8:L12) -> 12774.3 | M13: =SUM(M8:M12) -> 18614.8 | N13: =SUM(N8:N12) -> 13906.7 | O13: =SUM(O8:O12) -> 9278.1 | Q13: Administrative & other expenses | R13: 31.49 | S13: 109.9 | T13: 34.11 | U13: 35.7 | V13: 35.98 | W13: 38.18 | Y13: Total expenses | Z13: =SUM(Z8:Z12) -> 16607.5 | AA13: =SUM(AA8:AA12) -> 15573.59 | AB13: =SUM(AB8:AB12) -> 15062.8 | AC13: =SUM(AC8:AC12) -> 16214.3 | AD13: =SUM(AD8:AD12) -> 19494.92 | AE13: =SUM(AE8:AE12) -> 21860.72 | AG13: License fees and spectrum usage charges | AH13: 4848.2 | AI13: 4129.5 | AJ13: 4198.8 | AK13: 4002.1 | AL13: 3672.6 | AM13: 3696.2 | AO13: Depreciation and amortisation expense | AP13: 7396 | AQ13: 11534 | AR13: 13702 | AS13: 18641 | AT13: 21394 | AU13: 23098
A14: Total expenses | B14: =SUM(B8:B13) -> 34183.5 | C14: =SUM(C8:C13) -> 36341.8 | D14: =SUM(D8:D13) -> 36094.5 | E14: =SUM(E8:E13) -> 40921.4 | F14: =SUM(F8:F13) -> 71690.6 | G14: =SUM(G8:G13) -> 79826 | I14: EBITDA | J14: =J6-J13 -> 3746.3 | K14: =K6-K13 -> 7456.8 | L14: =L6-L13 -> 15295.4 | M14: =M6-M13 -> 10128.3 | N14: =N6-N13 -> 15055 | O14: =O6-O13 -> 21190.5 | Q14: CSR | R14: 5.19 | S14: 4.9 | T14: 2.78 | U14: 7.01 | V14: 4.84 | W14: 5.73 | Y14: Profit before exceptional items and tax | Z14: =Z6-Z13 -> 530.17 | AA14: =AA6-AA13 -> 1683.27 | AB14: =AB6-AB13 -> 1994.02 | AC14: =AC6-AC13 -> 1987.11 | AD14: =AD6-AD13 -> 1553.88 | AE14: =AE6-AE13 -> 1378.17 | AG14: Roaming and access charges | AH14: 5997.6 | AI14: 5290.6 | AJ14: 2915.5 | AK14: 3899.1 | AL14: 4117.7 | AM14: 4597.4 | AO14: Selling and Distribution expenses | AP14: 1277 | AQ14: 1172 | AR14: 1100 | AS14: 1822 | AT14: 2493 | AU14: 3641
A15: EBITDA | B15: =B6-B14 -> 22376.1 | C15: =C6-C14 -> 30372 | D15: =D6-D14 -> 35304.5 | E15: =E6-E14 -> 46432.5 | F15: =F6-F14 -> 79727.2 | G15: =G6-G14 -> 94732.9 | I15: Depreciation and ammortisation expense | J15: 1321.7 | K15: 2991.3 | L15: 5422.2 | M15: 5441 | N15: 6160 | O15: 6489.9 | Q15: Depreciation, amortisation and impairment | R15: 130.89 | S15: 159.32 | T15: 160.18 | U15: 154.31 | V15: 157.7 | W15: 180.4 | Y15: Exceptional items | Z15: -390.51 | AA15: -74.72 | AB15: 5.96 | AC15: 76.35 | AD15: -235.66 | AE15: 691.47 | AG15: Subscriber acquisition and servicing expenditure | AH15: 2929.9 | AI15: 1767.7 | AJ15: 1971.1 | AK15: 3678 | AL15: 4280.6 | AM15: 4092.3 | AO15: Other expenses | AP15: 1564 | AQ15: 2022 | AR15: 2013 | AS15: 2183 | AT15: 2404 | AU15: 3116
A16: Depreciation and ammortisation expense | B16: 20392.1 | C16: 21997.5 | D16: 24329.8 | E16: 26355 | F16: 39537.6 | G16: 45570.3 | I16: Less: adjusted with general reserve | J16: -40.2 | K16: -142.9 | L16: -97 | M16: -117.1 | N16: -100.1 | O16: -87.8 | Q16: Finance expenses | R16: 6.59 | S16: 4.06 | T16: 5.49 | U16: 6.02 | V16: 5.71 | W16: 3.11 | Y16: Profit before tax and share of profit/loss of associates | Z16: =Z14+Z15 -> 139.66 | AA16: =AA14+AA15 -> 1608.55 | AB16: =AB14+AB15 -> 1999.98 | AC16: =AC14+AC15 -> 2063.46 | AD16: =AD14+AD15 -> 1318.22 | AE16: =AE14+AE15 -> 2069.64 | AG16: Advertisement, business promotion expense and cotent cost | AH16: 1177.4 | AI16: 787.5 | AJ16: 979.1 | AK16: 941.2 | AL16: 564.7 | AM16: 500 | AO16: Total expenses | AP16: =SUM(AP8:AP15) -> 46762 | AQ16: =SUM(AQ8:AQ15) -> 54349 | AR16: =SUM(AR8:AR15) -> 57604 | AS16: =SUM(AS8:AS15) -> 67176 | AT16: =SUM(AT8:AT15) -> 73092 | AU16: =SUM(AU8:AU15) -> 81790
A17: Finance costs | B17: 11463.1 | C17: 11816.7 | D17: 13220.8 | E17: 14531.8 | F17: 22647.7 | G17: 21753.9 | I17: Finance costs | J17: 335 | K17: 836.4 | L17: 1603.3 | M17: 1670.4 | N17: 1863.8 | O17: 1857.9 | Q17: Total expenses | R17: =SUM(R9:R16) -> 931.73 | S17: =SUM(S9:S16) -> 1214.11 | T17: =SUM(T9:T16) -> 1347.21 | U17: =SUM(U9:U16) -> 1745.36 | V17: =SUM(V9:V16) -> 2267.36 | W17: =SUM(W9:W16) -> 3127.54 | Y17: Current tax | Z17: 334.18 | AA17: 406.49 | AB17: 431.31 | AC17: 432.77 | AD17: 601.63 | AE17: 610.53 | AG17: Other expense | AH17: 1932.1 | AI17: 1404.4 | AJ17: 854.6 | AK17: 887.4 | AL17: 941.7 | AM17: 887.1 | AO17: Profit before exceptional items and tax | AP17: =AP6-AP16 -> 7641 | AQ17: =AQ6-AQ16 -> 16087 | AR17: =AR6-AR16 -> 19981 | AS17: =AS6-AS16 -> 24565 | AT17: =AT6-AT16 -> 27485 | AU17: =AU6-AU16 -> 33298
A18: Share of profit of associates and joint ventures (net) | B18: 0 | C18: 0 | D18: 0 | E18: 0 | F18: -2709.4 | G18: -3703 | I18: Finance income | J18: -337 | K18: -199.2 | L18: -106 | M18: -216.5 | N18: -1128.4 | O18: -417.9 | Q18: Profit/Loss before exceptional items and tax | R18: =R7-R17 -> 234.06 | S18: =S7-S17 -> 197.18 | T18: =T7-T17 -> 230.52 | U18: =U7-U17 -> 256.84 | V18: =V7-V17 -> 354.81 | W18: =W7-W17 -> 423.5 | Y18: Deferred tax | Z18: -107.51 | AA18: -51.6 | AB18: 90.82 | AC18: -136.15 | AD18: -388.13 | AE18: -124.04 | AG18: Total Expenses | AH18: =SUM(AH10:AH17) -> 30045 | AI18: =SUM(AI10:AI17) -> 25006.5 | AJ18: =SUM(AJ10:AJ17) -> 22479.4 | AK18: =SUM(AK10:AK17) -> 25360.2 | AL18: =SUM(AL10:AL17) -> 25525.7 | AM18: =SUM(AM10:AM17) -> 25444.7 | AO18: Exceptional items | AP18: 146 | AQ18: 0 | AR18: 0 | AS18: 0 | AT18: 0 | AU18: 0
A19: Profit/Loss before exceptional items and tax | B19: =B15-(B16+B17+B18) -> -9479.1 | C19: =C15-(C16+C17+C18) -> -3442.2 | D19: =D15-(D16+D17+D18) -> -2246.1 | E19: =E15-(E16+E17+E18) -> 5545.7 | F19: =F15-(F16+F17+F18) -> 20251.3 | G19: =G15-(G16+G17+G18) -> 31111.7 | I19: Charity and donation | J19: 59.8 | K19: 80.6 | L19: 42.2 | M19: 98.4 | N19: 137.3 | O19: 194.7 | Q19: Exceptional items | R19: 49.3 | S19: 0 | T19: 50.1 | U19: 2.06 | V19: 26.72 | W19: 21.72 | AG19: EBITDA | AH19: =AH8-AH18 -> 15951.8 | AI19: =AI8-AI18 -> 17119.9 | AJ19: =AJ8-AJ18 -> 16165.5 | AK19: =AK8-AK18 -> 17128.3 | AL19: =AL8-AL18 -> 17239.2 | AM19: =AM8-AM18 -> 19147.2 | AO19: Profit before tax | AP19: =AP17-AP18 -> 7495 | AQ19: =AQ17-AQ18 -> 16087 | AR19: =AR17-AR18 -> 19981 | AS19: =AS17-AS18 -> 24565 | AT19: =AT17-AT18 -> 27485 | AU19: =AU17-AU18 -> 33298
A20: Exceptional items | B20: 41541.8 | C20: 15023 | D20: 2009.6 | E20: 4276.4 | F20: 7572.3 | G20: -7286.8 | I20: Profit before share of profit of joint venture and tax | J20: =J14-(SUM(J15:J19)) -> 2407 | K20: =K14-(SUM(K15:K19)) -> 3890.6 | L20: =L14-(SUM(L15:L19)) -> 8430.7 | M20: =M14-(SUM(M15:M19)) -> 3252.1 | N20: =N14-(SUM(N15:N19)) -> 8122.4 | O20: =O14-(SUM(O15:O19)) -> 13153.7 | Q20: Profit/Loss before tax | R20: =R18-R19 -> 184.76 | S20: =S18-S19 -> 197.18 | T20: =T18-T19 -> 180.42 | U20: =U18-U19 -> 254.78 | V20: =V18-V19 -> 328.09 | W20: =W18-W19 -> 401.78 | Y20: Total tax expense | Z20: =SUM(Z17:Z19) -> 226.67 | AA20: =SUM(AA17:AA19) -> 354.89 | AB20: =SUM(AB17:AB19) -> 522.13 | AC20: =SUM(AC17:AC19) -> 296.62 | AD20: =SUM(AD17:AD19) -> 213.5 | AE20: =SUM(AE17:AE19) -> 486.49 | AG20: Finance costs | AH20: 15392 | AI20: 17998.1 | AJ20: 20980.8 | AK20: 23354.3 | AL20: 25765.5 | AM20: 24543.4 | AO20: Current tax | AP20: 0 | AQ20: 0 | AR20: 58 | AS20: 16 | AT20: 0 | AU20: 0
A21: Profit/Loss before tax | B21: =B19-B20 -> -51020.9 | C21: =C19-C20 -> -18465.2 | D21: =D19-D20 -> -4255.7 | E21: =E19-E20 -> 1269.3 | F21: =F19-F20 -> 12679 | G21: =G19-G20 -> 38398.5 | I21: Share of profit of joint venture | J21: 1380.5 | K21: 866.3 | L21: 0 | M21: -492.8 | N21: 0 | O21: 0 | Q21: Current tax | R21: 55.98 | S21: 83.06 | T21: 72.5 | U21: 71.51 | V21: 96.71 | W21: 121.45 | Y21: Profit/Loss before share in profit/loss of associates | Z21: =Z16-Z20 -> -87.01 | AA21: =AA16-AA20 -> 1253.66 | AB21: =AB16-AB20 -> 1477.85 | AC21: =AC16-AC20 -> 1766.84 | AD21: =AD16-AD20 -> 1104.72 | AE21: =AE16-AE20 -> 1583.15 | AG21: Depreciation | AH21: 15208 | AI21: 14501.3 | AJ21: 14656.9 | AK21: 14258.4 | AL21: 13871.5 | AM21: 13393.7 | AO21: Deferred tax | AP21: 1933 | AQ21: 4072 | AR21: 5069 | AS21: 6250 | AT21: 7019 | AU21: 8503
A22: Current tax | B22: 0 | C22: -131.2 | D22: 0 | E22: -17.8 | F22: 4149.8 | G22: 4112.1 | I22: Profit before tax | J22: =J20+J21 -> 3787.5 | K22: =K20+K21 -> 4756.9 | L22: =L20+L21 -> 8430.7 | M22: =M20+M21 -> 2759.3 | N22: =N20+N21 -> 8122.4 | O22: =O20+O21 -> 13153.7 | Q22: Deferred tax | R22: -13.41 | S22: -27.77 | T22: -0.71 | U22: -6.25 | V22: -0.74 | W22: 1.38 | Y22: Share in profit/loss of associates | Z22: 2.18 | AA22: -2.14 | AB22: 6.82 | AC22: 34.03 | AD22: 19.99 | AE22: 42.54 | AG22: Amortisation | AH22: 9148.4 | AI22: 9137.2 | AJ22: 8927.4 | AK22: 8791.3 | AL22: 8762 | AM22: 8579.5 | AO22: Total tax expenses | AP22: =SUM(AP20:AP21) -> 1933 | AQ22: =SUM(AQ20:AQ21) -> 4072 | AR22: =SUM(AR20:AR21) -> 5127 | AS22: =SUM(AS20:AS21) -> 6266 | AT22: =SUM(AT20:AT21) -> 7019 | AU22: =SUM(AU20:AU21) -> 8503
A23: Deferred tax | B23: -14932.7 | C23: 6863.6 | D23: -392 | E23: 1376.7 | F23: -28.8 | G23: -3194.9 | I23: Current tax | J23: 580.6 | K23: 985.2 | L23: 2037.3 | M23: 2032.7 | N23: 1938.8 | O23: 1740.5 | Q23: Tax impact of earlier years | R23: 1.12 | S23: -0.56 | T23: -0.11 | U23: 0.45 | V23: -14.09 | W23: -20.86 | Y23: Profit/Loss for the period | Z23: =Z21+Z22 -> -84.83 | AA23: =AA21+AA22 -> 1251.52 | AB23: =AB21+AB22 -> 1484.67 | AC23: =AC21+AC22 -> 1800.87 | AD23: =AD21+AD22 -> 1124.71 | AE23: =AE21+AE22 -> 1625.69 | AG23: Profit before share of profit/loss of joint ventures and associate, exceptional items and tax | AH23: =AH19-(SUM(AH20:AH22)) -> -23796.6 | AI23: =AI19-(SUM(AI20:AI22)) -> -24516.7 | AJ23: =AJ19-(SUM(AJ20:AJ22)) -> -28399.6 | AK23: =AK19-(SUM(AK20:AK22)) -> -29275.7 | AL23: =AL19-(SUM(AL20:AL22)) -> -31159.8 | AM23: =AM19-(SUM(AM20:AM22)) -> -27369.4 | AO23: Profit for the year | AP23: =AP19-AP22 -> 5562 | AQ23: =AQ19-AQ22 -> 12015 | AR23: =AR19-AR22 -> 14854 | AS23: =AS19-AS22 -> 18299 | AT23: =AT19-AT22 -> 20466 | AU23: =AU19-AU22 -> 24795
A24: Total tax expense | B24: =B22+B23 -> -14932.7 | C24: =C22+C23 -> 6732.4 | D24: =D22+D23 -> -392 | E24: =E22+E23 -> 1358.9 | F24: =F22+F23 -> 4121 | G24: =G22+G23 -> 917.2 | I24: Deferred tax | J24: -91.8 | K24: -7.3 | L24: 20.3 | M24: -1313.4 | N24: 147.4 | O24: 1481.5 | Q24: Total tax expense | R24: =SUM(R21:R23) -> 43.69 | S24: =SUM(S21:S23) -> 54.73 | T24: =SUM(T21:T23) -> 71.68 | U24: =SUM(U21:U23) -> 65.71 | V24: =SUM(V21:V23) -> 81.88 | W24: =SUM(W21:W23) -> 101.97 | AG24: Add: Share in profits/loss of joint ventures (net) | AH24: 367.7 | AI24: 231.4 | AJ24: 1.2 | AK24: 0.5 | AL24: -5.5 | AM24: 1.8
A25: Profit/Loss for the year | B25: =B21-B24 -> -36088.2 | C25: =C21-C24 -> -25197.6 | D25: =D21-D24 -> -3863.7 | E25: =E21-E24 -> -89.6 | F25: =F21-F24 -> 8558 | G25: =G21-G24 -> 37481.3 | I25: Total tax expense | J25: =SUM(J23:J24) -> 488.8 | K25: =SUM(K23:K24) -> 977.9 | L25: =SUM(L23:L24) -> 2057.6 | M25: =SUM(M23:M24) -> 719.3 | N25: =SUM(N23:N24) -> 2086.2 | O25: =SUM(O23:O24) -> 3222 | Q25: Profit/Loss for the year | R25: =R20-R24 -> 141.07 | S25: =S20-S24 -> 142.45 | T25: =T20-T24 -> 108.74 | U25: =U20-U24 -> 189.07 | V25: =V20-V24 -> 246.21 | W25: =W20-W24 -> 299.81 | AG25: Add: Share in profit/loss of associate | AH25: -12.4 | AI25: 0 | AJ25: 0 | AK25: 0 | AL25: 0 | AM25: 0 | AO25: Earnings per Share | AP25: 2020 | AQ25: 2021 | AR25: 2022 | AS25: 2023 | AT25: 2024 | AU25: 2025
I26: Profit for the year | J26: =J22-J25 -> 3298.7 | K26: =K22-K25 -> 3779 | L26: =L22-L25 -> 6373.1 | M26: =M22-M25 -> 2040 | N26: =N22-N25 -> 6036.2 | O26: =O22-O25 -> 9931.7 | AG26: Profit/Loss before exceptional items and tax | AH26: =AH23+(SUM(AH24:AH25)) -> -23441.3 | AI26: =AI23+(SUM(AI24:AI25)) -> -24285.3 | AJ26: =AJ23+(SUM(AJ24:AJ25)) -> -28398.4 | AK26: =AK23+(SUM(AK24:AK25)) -> -29275.2 | AL26: =AL23+(SUM(AL24:AL25)) -> -31165.3 | AM26: =AM23+(SUM(AM24:AM25)) -> -27367.6 | AO26: Basic | AP26: 1.24 | AQ26: 2.67 | AR26: 3.3 | AS26: 4.07 | AT26: 4.55 | AU26: 5.51
A27: Earnings/Loss per share | B27: 2020 | C27: 2021 | D27: 2022 | E27: 2023 | F27: 2024 | G27: 2025 | Q27: Earnings per share | R27: 2020 | S27: 2021 | T27: 2022 | U27: 2023 | V27: 2024 | W27: 2025 | Y27: Earnings per share | Z27: 2020 | AA27: 2021 | AB27: 2022 | AC27: 2023 | AD27: 2024 | AE27: 2025 | AG27: Exceptional items (net) | AH27: -38355.7 | AI27: -19968.1 | AJ27: 164.3 | AK27: -22.4 | AL27: 755.5 | AM27: 0
A28: Basic | B28: -71.08 | C28: -46.18 | D28: -6.96 | E28: -0.16 | F28: 13.09 | G28: 58 | I28: Earnings per share | J28: 2020 | K28: 2021 | L28: 2022 | M28: 2023 | N28: 2024 | O28: 2025 | Q28: Basic | R28: 4.4 | S28: 4.44 | T28: 6.51 | U28: 5.89 | V28: 7.67 | W28: 9.34 | Y28: Basic | Z28: -3.02 | AA28: 43.88 | AB28: 51.99 | AC28: 63.02 | AD28: 39.42 | AE28: 57.03 | AG28: Profit/Loss before tax | AH28: =AH26+AH27 -> -61797 | AI28: =AI26+AI27 -> -44253.4 | AJ28: =AJ26+AJ27 -> -28234.1 | AK28: =AK26+AK27 -> -29297.6 | AL28: =AL26+AL27 -> -30409.8 | AM28: =AM26+AM27 -> -27367.6 | AO28: Subscribers base | AP28: 387500000 | AQ28: 422900000 | AR28: 409280000 | AS28: 438560000 | AT28: 481800000 | AU28: 476580000
I29: Basic | J29: 17.84 | K29: 17.516 | L29: 23.65 | M29: 7.57 | N29: 22.4 | O29: 37.31 | AG29: Current tax | AH29: 0.4 | AI29: -18 | AJ29: 17.3 | AK29: 11.5 | AL29: 828.5 | AM29: -2.7 | AO29: In 000s | AP29: =AP28/10000000 -> 38.75 | AQ29: =AQ28/10000000 -> 42.29 | AR29: =AR28/10000000 -> 40.928 | AS29: =AS28/10000000 -> 43.856 | AT29: =AT28/10000000 -> 48.18 | AU29: =AU28/10000000 -> 47.658
AG30: Deferred tax | AH30: 12080.7 | AI30: -2.3 | AJ30: -6 | AK30: -8 | AL30: 0.1 | AM30: 18.5
A31: Customer Base | B31: 423287000 | C31: 471362000 | D31: 489729000 | E31: 518446000 | F31: 561970000 | G31: 590514000 | I31: Towers base | J31: 95372 | K31: 179225 | L31: 188447 | M31: 192874 | N31: 219736 | O31: 260000 | Q31: Subscriber Base | R31: 300000 | S31: 400000 | T31: 472000 | U31: 516000 | V31: 568000 | W31: 575000 | AG31: Total tax expense | AH31: =SUM(AH29:AH30) -> 12081.1 | AI31: =SUM(AI29:AI30) -> -20.3 | AJ31: =SUM(AJ29:AJ30) -> 11.3 | AK31: =SUM(AK29:AK30) -> 3.5 | AL31: =SUM(AL29:AL30) -> 828.6 | AM31: =SUM(AM29:AM30) -> 15.8 | AO31: 2019 | AP31: 30.67
A32: in crores | B32: =B31/10000000 -> 42.3287 | C32: =C31/10000000 -> 47.1362 | D32: =D31/10000000 -> 48.9729 | E32: =E31/10000000 -> 51.8446 | F32: =F31/10000000 -> 56.197 | G32: =G31/10000000 -> 59.0514 | I32: In 000s | J32: =J31/10000000 -> 0.0095372 | K32: =K31/10000000 -> 0.0179225 | L32: =L31/10000000 -> 0.0188447 | M32: =M31/10000000 -> 0.0192874 | N32: =N31/10000000 -> 0.0219736 | O32: =O31/10000000 -> 0.026 | Q32: In 000s | R32: =R31/10000000 -> 0.03 | S32: =S31/10000000 -> 0.04 | T32: =T31/10000000 -> 0.0472 | U32: =U31/10000000 -> 0.0516 | V32: =V31/10000000 -> 0.0568 | W32: =W31/10000000 -> 0.0575 | AG32: Profit/Loss after tax | AH32: =AH28-AH31 -> -73878.1 | AI32: =AI28-AI31 -> -44233.1 | AJ32: =AJ28-AJ31 -> -28245.4 | AK32: =AK28-AK31 -> -29301.1 | AL32: =AL28-AL31 -> -31238.4 | AM32: =AM28-AM31 -> -27383.4
A34: 2019 Customer | B34: 32.73 | I34: 2019 | J34: 123546 | Q34: 2019 | R34: 142000 | AG34: Earnings/Loss per share | AH34: 2020 | AI34: 2021 | AJ34: 2022 | AK34: 2023 | AL34: 2024 | AM34: 2025
J35: =J34/10000000 -> 0.0123546 | R35: =R34/10000000 -> 0.0142 | AG35: Basic | AH35: -27.26 | AI35: -15.4 | AJ35: -9.83 | AK35: -8.43 | AL35: -6.41 | AM35: -4.01
AG37: Subscriber Base | AH37: 293700000 | AI37: 247200000 | AJ37: 243800000 | AK37: 223000000 | AL37: 212600000 | AM37: 198200000
AG38: In 000s | AH38: =AH37/10000000 -> 29.37 | AI38: =AI37/10000000 -> 24.72 | AJ38: =AJ37/10000000 -> 24.38 | AK38: =AK37/10000000 -> 22.3 | AL38: =AL37/10000000 -> 21.26 | AM38: =AM37/10000000 -> 19.82
AG40: 2019 | AH40: 39.48

Sheet Cash Flow Statement
A1: Cash Flow Statement | F1: #VALUE! | N1: #VALUE! | V1: #VALUE! | AD1: #VALUE! | AL1: #VALUE! | AT1: #VALUE!
A2: Particulars | B2: 2020 | C2: 2021 | D2: 2022 | E2: 2023 | F2: 2024 | G2: 2025 | I2: Particulars | J2: 2020 | K2: 2021 | L2: 2022 | M2: 2023 | N2: 2024 | O2: 2025 | Q2: Particulars | R2: 2020 | S2: 2021 | T2: 2022 | U2: 2023 | V2: 2024 | W2: 2025 | Y2: Particulars | Z2: 2020 | AA2: 2021 | AB2: 2022 | AC2: 2023 | AD2: 2024 | AE2: 2025 | AG2: Particulars | AH2: 2020 | AI2: 2021 | AJ2: 2022 | AK2: 2023 | AL2: 2024 | AM2: 2025 | AO2: Particulars | AP2: 2020 | AQ2: 2021 | AR2: 2022 | AS2: 2023 | AT2: 2024 | AU2: 2025
A3: Profit/Loss before tax | B3: -51020.9 | C3: -18465.2 | D3: -4255.7 | E3: 1269.3 | F3: 12679 | G3: 38398.5 | I3: Profit before tax | J3: 3787.5 | K3: 4756.9 | L3: 8430.7 | M3: 2759.3 | N3: 8122.4 | O3: 13153.7 | Q3: Profit before tax | R3: 141.07 | S3: 142.45 | T3: 208.94 | U3: 189.07 | V3: 246.21 | W3: 299.81 | Y3: Operating Activities | AG3: Operating activities | AO3: Operating activities
A4: Adjustments for | I4: Adjustments for | Q4: Adjustments for | Y4: Profit/Loss for the year | Z4: -84.83 | AA4: 1251.52 | AB4: 1999.98 | AC4: 2063.46 | AD4: 1163.09 | AE4: 2280.73 | AG4: Loss before tax | AH4: -61797 | AI4: -44253.4 | AJ4: -28234.1 | AK4: -29297.6 | AL4: -30409.8 | AM4: -27367.6 | AO4: Profit/Loss before exceptional items and tax | AP4: 7641 | AQ4: 16087 | AR4: 19981 | AS4: 24565 | AT4: 27485 | AU4: 33298
A5: Depreciation and amortisation expense | B5: 20392.1 | C5: 21997.5 | D5: 24329.8 | E5: 26355 | F5: 39537.6 | G5: 45570.3 | I5: Depreciation and amortization expense | J5: 1281.5 | K5: 2848.4 | L5: 5325.2 | M5: 5323.9 | N5: 6059.9 | O5: 6402.1 | Q5: Other comprehensive income | R5: -5.01 | S5: 1.19 | T5: -0.38 | U5: 2.1 | V5: -2.06 | W5: -3.87 | Y5: Adjustments for | AG5: Adjustments for | AO5: Exceptional items | AP5: -195 | AQ5: 0
A6: Finance costs | B6: 11248.5 | C6: 11754.3 | D6: 13155.7 | E6: 14397.3 | F6: 21933.7 | G6: 21625.8 | I6: Finance income | J6: -337 | K6: -199.2 | L6: -106 | M6: -83 | N6: -647.9 | O6: -417.9 | Q6: Depreciation, amortisation and Impairment | R6: 180.19 | S6: 159.32 | T6: 160.18 | U6: 154.31 | V6: 157.7 | W6: 180.4 | Y6: Income tax expense recognised in consolidated statement of P&L | Z6: 226.67 | AA6: 354.89 | AB6: 2204.54 | AC6: 2261.81 | AD6: 2469.67 | AE6: 2628.32 | AG6: Share in profit of joint ventures and associate | AH6: -355.3 | AI6: -231.4 | AJ6: -1.2 | AK6: -0.5 | AL6: 5.5 | AM6: -1.8 | AO6: Profit/Loss before tax | AP6: =AP4+AP5 -> 7446 | AQ6: =AQ4+AQ5 -> 16087 | AR6: =AR4+AR5 -> 19981 | AS6: =AS4+AS5 -> 24565 | AT6: =AT4+AT5 -> 27485 | AU6: =AU4+AU5 -> 33298
A7: Interest income | B7: -239 | C7: -332.2 | D7: -142.8 | E7: -249.9 | F7: -264.5 | G7: -204.8 | I7: Finance costs | J7: 335 | K7: 836.4 | L7: 1603.3 | M7: 1670.4 | N7: 1863.8 | O7: 1857.9 | Q7: Amortisation of deferred government grant | R7: -2.13 | S7: -3.02 | T7: -2.66 | U7: -3.59 | V7: -3.19 | W7: -6.3 | Y7: Share in profit/loss of associate | Z7: -2.18 | AA7: 2.14 | AB7: -4.33 | AC7: -6 | AD7: -8.9 | AE7: -5.2 | AG7: Depreciation of PPE and investment property | AH7: 15208 | AI7: 14501.3 | AJ7: 14656.9 | AK7: 14258.4 | AL7: 13871.5 | AM7: 13393.7 | AO7: Adjustments for
A8: Dividend income | B8: -863.1 | C8: -1716.3 | D8: -45 | E8: -1518.1 | F8: -649.3 | G8: -530.6 | I8: Share of profit of joint venture | J8: -1380.5 | K8: -866.3 | L8: -255.1 | M8: -261.4 | N8: -279.3 | O8: -268.7 | Q8: Non cash income | R8: 0.25 | S8: -1.35 | T8: -2.45 | U8: -1.68 | V8: 1.95 | W8: -7.53 | Y8: Depreciation and amortisation expenses | Z8: 2357.72 | AA8: 2313.87 | AB8: 0 | AC8: -46.74 | AD8: -1.97 | AE8: -733.02 | AG8: Amortisation of intangible assets | AH8: 9148.4 | AI8: 9137.2 | AJ8: 8927.4 | AK8: 8791.3 | AL8: 8762 | AM8: 8579.5 | AO8: Depreciation and amortisation expense | AP8: 7396 | AQ8: 11534 | AR8: 13702 | AS8: 18641 | AT8: 21394 | AU8: 23098
A9: Net loss/gain on derivative financial instruments | B9: -381 | C9: 271.3 | D9: -8.7 | E9: -350.2 | F9: 631.9 | G9: 42 | I9: Gain disposal of PPE | J9: -38.4 | K9: -82.3 | L9: -117 | M9: 5307.7 | N9: 0 | O9: 0 | Q9: Non cash expense | R9: 0.04 | S9: -0.66 | T9: 0.55 | U9: 0.59 | V9: 3.02 | W9: 0.1 | Y9: Gain on disposal of PPE | Z9: -8.51 | AA9: -42.27 | AB9: -3.59 | AC9: -6.53 | AD9: 0 | AE9: -311.2 | AG9: Share-based payment expense | AH9: -10.2 | AI9: 3.5 | AJ9: -1.6 | AK9: 0.2 | AL9: -48.6 | AM9: -77.9 | AO9: Effect of exchange rate change | AP9: 58 | AQ9: -160 | AR9: 60 | AS9: 73 | AT9: -72 | AU9: 13
A10: Net gain on FVTPL investments | B10: -446.2 | C10: -255.4 | D10: -97.5 | E10: -198.7 | F10: -2709.4 | G10: -3703 | I10: Provision for doubtful debts and advances | J10: 68.1 | K10: -46.1 | L10: 0 | M10: 492.8 | N10: -80.9 | O10: -5077.1 | Q10: Non cash expense (Interest credited) | R10: 3.14 | S10: 2.23 | T10: 2.27 | U10: 2.17 | V10: 2.69 | W10: 3.01 | Y10: Gain on disposal of assets held for sale | Z10: 0 | AA10: -67.38 | AB10: -6.45 | AC10: -18 | AD10: -7.65 | AE10: -1.71 | AG10: Loss on disposal of PPE and intangible assets | AH10: 2.6 | AI10: 0.5 | AJ10: -67.9 | AK10: -64.2 | AL10: -755.5 | AM10: 0 | AO10: Interest income | AP10: 0 | AQ10: -9 | AR10: -6 | AS10: -12 | AT10: -8 | AU10: -717
A11: Exceptional items | B11: 41525.2 | C11: 15023 | D11: 970.2 | E11: 4276.4 | F11: 7572.3 | G11: -7286.8 | I11: Revenue equalisation | J11: -129.7 | K11: -207.4 | L11: -343.6 | M11: -616.5 | N11: -490.7 | O11: -533 | Q11: Interest expense for Lease liabilities | R11: 3.41 | S11: 2.49 | T11: 2.67 | U11: 2.35 | V11: 0.07 | W11: 0.09 | Y11: Gain on modificatio/termination lease | Z11: -3.01 | AA11: -31.94 | AB11: 360.25 | AC11: 432.46 | AD11: -15.01 | AE11: -15.66 | AG11: Gain on sale of stake in Indus | AH11: 0 | AI11: -2118.9 | AJ11: -126.6 | AK11: 22.4 | AL11: 0 | AM11: 0 | AO11: Gain on investments (net) | AP11: -83 | AQ11: -473 | AR11: -55 | AS11: -155 | AT11: -362 | AU11: -201
A12: Loss on sale of PPE | B12: 0.1 | C12: 7.3 | D12: -24.3 | E12: -6.1 | F12: 119.4 | G12: 166.9 | I12: Others | J12: -187.9 | K12: -123.7 | L12: -113.8 | M12: -64.4 | N12: -50.7 | O12: -37.1 | Q12: Non cash expense (Loss on sale of fixed assets) | R12: 0.02 | S12: 0.03 | T12: 0.09 | U12: 0.14 | V12: 0.03 | W12: 0.01 | Y12: Interest income on financial assets carried at amortised cost | Z12: -4.75 | AA12: -11.53 | AB12: 0 | AC12: -29.61 | AD12: 634.73 | AE12: 747.53 | AG12: Impact due to cancellation of lease contract | AH12: -217.2 | AI12: -169.6 | AJ12: 13.7 | AK12: 0 | AL12: 0 | AM12: 0 | AO12: Loss on sale/discard of PPE | AP12: 1 | AQ12: 0 | AR12: -13 | AS12: -14 | AT12: 13 | AU12: 28
A13: Employee share-based payment expenses | B13: 30.2 | C13: 64.8 | D13: 61.7 | E13: 96.1 | F13: 4.4 | G13: -103.1 | I13: Operating profit before working capital changes | J13: =SUM(J3,J5:J12) -> 3398.6 | K13: =SUM(K3,K5:K12) -> 6916.7 | L13: =SUM(L3,L5:L12) -> 14423.7 | M13: =SUM(M3,M5:M12) -> 14528.8 | N13: =SUM(N3,N5:N12) -> 14496.6 | O13: =SUM(O3,O5:O12) -> 15079.9 | Q13: Non cash expense (Forex loss) | R13: 0.12 | S13: 0.02 | T13: 0 | U13: 0.07 | V13: 0 | W13: 0 | Y13: Finance cost | Z13: 470.74 | AA13: 420.2 | AB13: 23.12 | AC13: 46.32 | AD13: 0 | AE13: 12.85 | AG13: Accelerated depreciation on account of network | AH13: 5974.3 | AI13: 574.5 | AJ13: 20980.8 | AK13: 23354.3 | AL13: 25765.5 | AM13: 24543.4 | AO13: Finance cost | AP13: 6617 | AQ13: 3840 | AR13: 4377 | AS13: 4059 | AT13: 3999 | AU13: 4837
A14: Provision for doubtful debts/bad debts written off | B14: 0 | C14: 0 | D14: 173.7 | E14: 274.1 | F14: 427.8 | G14: 374.1 | I14: Changes in other financial assets | J14: 33.6 | K14: -312.9 | L14: 538 | M14: -950 | N14: -450 | O14: -385.2 | Q14: Non cash income | R14: -0.26 | S14: -0.12 | T14: -0.6 | U14: -0.73 | V14: -3.9 | W14: -2.69 | Y14: Loss on sale of investment | Z14: 6.48 | AA14: 0 | AB14: -10.56 | AC14: -41.82 | AD14: 194.94 | AE14: -194.94 | AG14: License fees and SUC on AGR | AH14: 27514.3 | AI14: 19440.5 | AJ14: 175.6 | AK14: 117 | AL14: 211.9 | AM14: 152.8 | AO14: Operating profit before working capital changes | AP14: =SUM(AP6,AP8:AP13) -> 21435 | AQ14: =SUM(AQ6,AQ8:AQ13) -> 30819 | AR14: =SUM(AR6,AR8:AR13) -> 38046 | AS14: =SUM(AS6,AS8:AS13) -> 47157 | AT14: =SUM(AT6,AT8:AT13) -> 52449 | AU14: =SUM(AU6,AU8:AU13) -> 60356
A15: Other non-cash itmes | B15: 493.5 | C15: 260.7 | D15: 114.5 | E15: 79.7 | F15: 82.3 | G15: 39.6 | I15: Changes in other non current and current assets | J15: 61 | K15: -106.9 | L15: 253.1 | M15: -49.4 | N15: -91.1 | O15: -481.7 | Q15: Provision for expected credit loss | R15: 12.51 | S15: 83.16 | T15: -50.1 | U15: 2.06 | V15: 0 | W15: 0 | Y15: Bad debts written off | Z15: 18.01 | AA15: 47.33 | AB15: 2.71 | AC15: 46.46 | AD15: 54.3 | AE15: 132.55 | AG15: One time spectrum charges | AH15: 3887.1 | AI15: 502.7 | AJ15: 47.9 | AK15: 8.6 | AL15: -47.8 | AM15: -49.9 | AO15: Adjustments for
A16: Operating Profit/Loss before working capital changes | B16: =SUM(B3,B5:B15) -> 20739.4 | C16: =SUM(C3,C5:C15) -> 28609.8 | D16: =SUM(D3,D5:D15) -> 34231.6 | E16: =SUM(E3,E5:E15) -> 44424.9 | F16: =SUM(F3,F5:F15) -> 79365.2 | G16: =SUM(G3,G5:G15) -> 94388.9 | I16: Changes in trade receivables | J16: -187.3 | K16: 2425.1 | L16: -3099.2 | M16: -3118.4 | N16: 0 | O16: -7.6 | Q16: Interest income | R16: -27.66 | S16: -26.43 | T16: -23.37 | U16: -29.59 | V16: -37.93 | W16: -49.21 | Y16: Allowance for trade receivables | Z16: 64.9 | AA16: 20.02 | AB16: 0 | AC16: -11.52 | AD16: 40.58 | AE16: 129.07 | AG16: Impairment of investment in associates | AH16: 159.6 | AI16: 0 | AJ16: -7 | AK16: -17.5 | AL16: -74.3 | AM16: -110.7 | AO16: Trade and other receivables | AP16: -6805 | AQ16: 813 | AR16: -6367 | AS16: -2349 | AT16: -208 | AU16: 3285
A17: Working capital adjustments | I17: Changes in other financial liabilities | J17: -228.1 | K17: -11.1 | L17: -11 | M17: -220.8 | N17: -1505.2 | O17: 6770 | Q17: Operating profit/loss before working capital changes | R17: =SUM(R3,R5:R16) -> 305.69 | S17: =SUM(S3,S5:S16) -> 359.31 | T17: =SUM(T3,T5:T16) -> 295.14 | U17: =SUM(U3,U5:U16) -> 317.27 | V17: =SUM(V3,V5:V16) -> 364.59 | W17: =SUM(W3,W5:W16) -> 413.82 | Y17: Provision for inventories and CWIP | Z17: 30.23 | AA17: 15.09 | AB17: 0.52 | AC17: -0.8 | AD17: 0 | AE17: 102.95 | AG17: Impairment of brand | AH17: 0 | AI17: 724.6 | AJ17: -105.7 | AK17: -276.1 | AL17: -43.3 | AM17: -970.3 | AO17: Trade and other payables | AP17: 3119 | AQ17: 1110 | AR17: 303 | AS17: 2490 | AT17: 3205 | AU17: 2510
A18: Trade receivables | B18: -631.5 | C18: 451 | D18: 168.8 | E18: 373.8 | F18: -1494.1 | G18: 2965.8 | I18: Changes in provisions | J18: 7.7 | K18: -19.3 | L18: 36.2 | M18: 5.1 | N18: -14.8 | O18: -1.8 | Q18: increase/decrease in financial current assets | R18: -151.18 | S18: -268.4 | T18: -51.36 | U18: -340.88 | V18: -280.91 | W18: -977.32 | Y18: Demerger of surplus land | Z18: 5.92 | AA18: 22.1 | AB18: -29.42 | AC18: -28.4 | AD18: 6.06 | AE18: 11.16 | AG18: Finance costs | AH18: 15392 | AI18: 17998.1 | AJ18: 0 | AK18: 0 | AL18: -23.9 | AM18: -19.2 | AO18: Cash generated from operations | AP18: =SUM(AP14,AP16:AP17) -> 17749 | AQ18: =SUM(AQ14,AQ16:AQ17) -> 32742 | AR18: =SUM(AR14,AR16:AR17) -> 31982 | AS18: =SUM(AS14,AS16:AS17) -> 47298 | AT18: =SUM(AT14,AT16:AT17) -> 55446 | AU18: =SUM(AU14,AU16:AU17) -> 66151
A19: Trade payables | B19: -718.4 | C19: 351.6 | D19: 1472 | E19: -1103.3 | F19: 639.8 | G19: 858.6 | I19: Changes in other non current and current liabilities | J19: -98.3 | K19: -339.6 | L19: -55.7 | M19: -28.7 | N19: 15.6 | O19: 18.2 | Q19: increase/decrease in non financial current assets | R19: 22.31 | S19: 21.4 | T19: 28.59 | U19: -67.08 | V19: 20.43 | W19: -146.69 | Y19: Allowance for doubtful advances | Z19: 3.45 | AA19: 0.29 | AB19: -16.48 | AC19: -17.81 | AD19: 4.63 | AE19: 28.35 | AG19: Provision for gratuity and compensated absences | AH19: -28.5 | AI19: 8.9 | AJ19: 0 | AK19: 0 | AL19: 0 | AM19: -1.3 | AO19: Taxes paid | AP19: -1167 | AQ19: -138 | AR19: -134 | AS19: 1344 | AT19: -105 | AU19: 57
A20: Inventories | B20: 2.9 | C20: 15 | D20: -11.3 | E20: -2 | F20: -77.1 | G20: -141.6 | I20: Changes in trade payables | J20: -125.6 | K20: 7.9 | L20: -1051 | M20: -42.6 | N20: =814.8+186.2 -> 1001 | O20: =303+224.8 -> 527.8 | Q20: increase/decrease in financial current liabilities | R20: 139.53 | S20: 134.15 | T20: 102.34 | U20: 177.33 | V20: 341.62 | W20: 741.74 | Y20: Gain on investments at fair value through OCI | Z20: -25.53 | AA20: -44.54 | AB20: 0 | AC20: 0 | AD20: 4.11 | AE20: 5 | AG20: Bad debts/advances written off | AH20: 533.2 | AI20: 387.3 | AJ20: 0 | AK20: 0 | AL20: 0 | AM20: 0 | AO20: Net cash flow from/used in operating activities | AP20: =AP18+AP19 -> 16582 | AQ20: =AQ18+AQ19 -> 32604 | AR20: =AR18+AR19 -> 31848 | AS20: =AS18+AS19 -> 48642 | AT20: =AT18+AT19 -> 55341 | AU20: =AU18+AU19 -> 66208
A21: Provisions | B21: -12146 | C21: -6686.1 | D21: 376.4 | E21: 342.2 | F21: 1733.2 | G21: 2269.9 | I21: Cash generated from operations | J21: =SUM(J13:J20) -> 2861.6 | K21: =SUM(K13:K20) -> 8559.9 | L21: =SUM(L13:L20) -> 11034.1 | M21: =SUM(M13:M20) -> 10124 | N21: =SUM(N13:N20) -> 13452.1 | O21: =SUM(O13:O20) -> 21519.6 | Q21: increase/decrease in non financial current liabilities | R21: -52.17 | S21: 99 | T21: -38.08 | U21: 150.89 | V21: 225.88 | W21: 116.12 | Y21: Exchange fluctuation | Z21: 0 | AA21: -20.93 | AB21: 0 | AC21: 0 | AD21: =-24.2-8.33-3.9 -> -36.43 | AE21: =-26.44-38.35+8.14 -> -56.65 | AG21: Allowance for doubtful debts/advances | AH21: -196 | AI21: -43.7 | AJ21: 0 | AK21: 0 | AL21: 0 | AM21: 0 | AO21: Investing activities
A22: Other financial and non financial liabilities | B22: 964.6 | C22: 1069.2 | D22: -237.2 | E22: 613.8 | F22: 4151.6 | G22: 4815.4 | I22: Income tax paid | J22: -546.5 | K22: -1078.8 | L22: -1912.9 | M22: -2219.2 | N22: -1870 | O22: -1874.6 | Q22: increase/decrease in financial non current assets | R22: -21.52 | S22: 16.19 | T22: -6.14 | U22: 7.09 | V22: -50.31 | W22: 52.04 | Y22: Operating profits before working capital changes | Z22: =SUM(Z4,Z6:Z21) -> 3055.31 | AA22: =SUM(AA4,AA6:AA21) -> 4228.86 | AB22: =SUM(AB4,AB6:AB21) -> 4520.29 | AC22: =SUM(AC4,AC6:AC21) -> 4643.28 | AD22: =SUM(AD4,AD6:AD21) -> 4502.15 | AE22: =SUM(AE4,AE6:AE21) -> 4760.13 | AG22: Liabilities/provisions no longer required written back | AH22: -22.9 | AI22: -4.6 | AJ22: 0 | AK22: 0 | AL22: 0 | AM22: 0 | AO22: Purchase of PPE and intangible assets | AP22: -51771 | AQ22: -26116 | AR22: -29511 | AS22: -33905 | AT22: -49016 | AU22: -41622
A23: Other financial and non financial assets | B23: -3875.4 | C23: 10715.5 | D23: 420.6 | E23: -877.8 | F23: -2539.8 | G23: -2386.8 | I23: Net cash flow from Operating activities | J23: =J21+J22 -> 2315.1 | K23: =K21+K22 -> 7481.1 | L23: =L21+L22 -> 9121.2 | M23: =M21+M22 -> 7904.8 | N23: =N21+N22 -> 11582.1 | O23: =O21+O22 -> 19645 | Q23: increase/decrease in non financial non current assets | R23: -0.62 | S23: -9.26 | T23: -1.14 | U23: -5.9 | V23: -16.82 | W23: -25.17 | Y23: Adjustments for working capital changes | AG23: Other income | AH23: -1025.8 | AI23: -163.6 | AJ23: 0 | AK23: 0 | AL23: 0 | AM23: 0 | AO23: Proceeds from disposal of PPE | AP23: 967 | AQ23: 369 | AR23: 31 | AS23: 94 | AT23: 94 | AU23: 78
A24: Cash flow from operating activities | B24: =SUM(B16,B18:B23) -> 4335.6 | C24: =SUM(C16,C18:C23) -> 34526 | D24: =SUM(D16,D18:D23) -> 36420.9 | E24: =SUM(E16,E18:E23) -> 43771.6 | F24: =SUM(F16,F18:F23) -> 81778.8 | G24: =SUM(G16,G18:G23) -> 102770.2 | I24: Investing activities | Q24: increase/decrease in financial non current liabilities | R24: -0.09 | S24: 17.73 | T24: 10.9 | U24: 15.34 | V24: -26.36 | W24: 59.29 | Y24: Inventories | Z24: -6.32 | AA24: 31.51 | AB24: -5.41 | AC24: -120.87 | AD24: 75.42 | AE24: -78.73 | AG24: Operating Loss/Profit before working capital changes | AH24: =SUM(AH4,AH6:AH23) -> 14166.6 | AI24: =SUM(AI4,AI6:AI23) -> 16293.9 | AJ24: =SUM(AJ4,AJ6:AJ23) -> 16258.2 | AK24: =SUM(AK4,AK6:AK23) -> 16896.3 | AL24: =SUM(AL4,AL6:AL23) -> 17213.2 | AM24: =SUM(AM4,AM6:AM23) -> 18070.7 | AO24: Upfront fibre payments | AP24: -16439 | AQ24: 0 | AR24: -19306 | AS24: 0 | AT24: -4423 | AU24: -4574
A25: Income tax paid | B25: -309.2 | C25: -133.7 | D25: 333.5 | E25: -189 | F25: -2880.6 | G25: -4438 | I25: Purchase of PPE | J25: -829.8 | K25: -2118.4 | L25: -3285.1 | M25: -3622.6 | N25: -8952.9 | O25: -6784 | Q25: increase/decrease in non financial non current liabilities | R25: -30.36 | S25: 23.58 | T25: -42.16 | U25: 6.48 | V25: -21.7 | W25: 37.58 | Y25: Trade receivables | Z25: -205.15 | AA25: 515.76 | AB25: 52.67 | AC25: -67.82 | AD25: -303.24 | AE25: -465.06 | AG25: Working capital adjustments | AO25: Purchase of investments | AP25: -102638 | AQ25: -93806 | AR25: -71362 | AS25: -107695 | AT25: -89154 | AU25: -150048
A26: Net cash flows from operating activities | B26: =B24+B25 -> 4026.4 | C26: =C24+C25 -> 34392.3 | D26: =D24+D25 -> 36754.4 | E26: =E24+E25 -> 43582.6 | F26: =F24+F25 -> 78898.2 | G26: =G24+G25 -> 98332.2 | I26: Proceeds from sale of PPE | J26: 101 | K26: 166.6 | L26: 415.4 | M26: 454.5 | N26: 506.4 | O26: 526.9 | Q26: Net cash generated from Operations before tax | R26: =SUM(R17:R25) -> 211.59 | S26: =SUM(S17:S25) -> 393.7 | T26: =SUM(T17:T25) -> 298.09 | U26: =SUM(U17:U25) -> 260.54 | V26: =SUM(V17:V25) -> 556.42 | W26: =SUM(W17:W25) -> 271.41 | Y26: Other assets | Z26: -145.23 | AA26: 70.2 | AB26: -23.18 | AC26: 178.22 | AD26: -232.81 | AE26: -446.47 | AG26: decrease/increase in trade receivables | AH26: -80.7 | AI26: 313.6 | AJ26: -38.3 | AK26: 184.7 | AL26: -170.7 | AM26: 103.5 | AO26: Proceeds from sale of investments | AP26: 101503 | AQ26: 95240 | AR26: 71282 | AS26: 107814 | AT26: 87599 | AU26: 133816
A27: Investing activities | I27: Investments in mutual funds | J27: -8016.2 | K27: -9832.9 | L27: -10553.5 | M27: -19504 | N27: -15757.2 | O27: -31911.4 | Q27: Income tax paid | R27: -38.27 | S27: -44.93 | T27: -48.33 | U27: -31 | V27: -26.8 | W27: -37.79 | Y27: Trade payables | Z27: -25.5 | AA27: -554.67 | AB27: -296.7 | AC27: 133.09 | AD27: -424.9 | AE27: -213.01 | AG27: decrease in inventories | AH27: 1.7 | AI27: 1.9 | AJ27: -1.7 | AK27: -14 | AL27: 15.1 | AM27: 0.1 | AO27: Interest income | AP27: 10 | AQ27: 7 | AR27: 6 | AS27: 13 | AT27: 84 | AU27: 789
A28: Purchase of PPE (including CWIP) | B28: -11434.2 | C28: -14766.6 | D28: -16736.7 | E28: -16173.8 | F28: -38191.5 | G28: -37907.7 | I28: Proceeds from sale of mutual funds | J28: 6407.8 | K28: 13126.8 | L28: 11192.6 | M28: 20886.4 | N28: 15763.9 | O28: 30496.7 | Q28: Net cash generated from operating activities | R28: =R26+R27 -> 173.32 | S28: =S26+S27 -> 348.77 | T28: =T26+T27 -> 249.76 | U28: =U26+U27 -> 229.54 | V28: =V26+V27 -> 529.62 | W28: =W26+W27 -> 233.62 | Y28: Other liabilities | Z28: 8.34 | AA28: -553.58 | AB28: -160.1 | AC28: -180.9 | AD28: -179.55 | AE28: 226.54 | AG28: increase/decrease in other financial and non financial assets | AH28: -2806.7 | AI28: -683.6 | AJ28: -3005.1 | AK28: 1062.6 | AL28: 1117.4 | AM28: -5081.8 | AO28: Fixed deposit/Escrow account with banks | AP28: -2 | AQ28: -4 | AR28: 2 | AS28: 2 | AT28: 8 | AU28: -10
A29: Proceeds from sale of PPE | B29: 487.2 | C29: 82.1 | D29: 89 | E29: 82.7 | F29: 122.8 | G29: 338.2 | I29: Proceeds from sale of government securities | J29: 946.7 | K29: 0 | L29: 0 | M29: 0 | N29: 275 | O29: 0 | Q29: Investing activities | Y29: Provisions | Z29: 2.79 | AA29: -25.85 | AB29: -39.07 | AC29: -20.38 | AD29: -40.49 | AE29: -20.72 | AG29: increase/decrease in trade payables | AH29: -1097.4 | AI29: 552.2 | AJ29: -343.2 | AK29: -247.7 | AL29: -1057.7 | AM29: -3440 | AO29: Net cash flow/used in Investing activities | AP29: =SUM(AP22:AP28) -> -68370 | AQ29: =SUM(AQ22:AQ28) -> -24310 | AR29: =SUM(AR22:AR28) -> -48858 | AS29: =SUM(AS22:AS28) -> -33677 | AT29: =SUM(AT22:AT28) -> -54808 | AU29: =SUM(AU22:AU28) -> -61571
A30: Purchase of intangible assets | B30: -441.1 | C30: -382.5 | D30: -677.8 | E30: -282.6 | F30: -1860 | G30: -1772.2 | I30: Redemption of certificate of deposits, commercial papers and bonds | J30: 293.8 | K30: 0 | L30: 0 | M30: 0 | N30: 0 | O30: -1828.8 | Q30: Purchase of Tangible & Intangible assets | R30: -61.74 | S30: -89.36 | T30: -115.82 | U30: -177.07 | V30: -209.67 | W30: -325.05 | Y30: Adjustments of translation difference on working capital | Z30: 119.78 | AA30: -35.98 | AB30: 66.63 | AC30: 23.51 | AD30: 5.16 | AE30: -13.86 | AG30: decrease/increase in financial and non-financial liabilities | AH30: -5262.4 | AI30: -1628.6 | AJ30: 3047.6 | AK30: -358.1 | AL30: 738.4 | AM30: -837.4 | AO30: Financing activities
A31: Payment towards spectrum | B31: -1542.4 | C31: -6241.2 | D31: -17444.2 | E31: -8312.4 | F31: -12154.7 | G31: -21348.7 | I31: Investment/proceeds from bank deposits | J31: -0.7 | K31: -4.2 | L31: -1.6 | M31: -2.1 | N31: -2.8 | O31: 2.8 | Q31: Capital advances | R31: -15.41 | S31: 0 | T31: 0.55 | U31: 0.66 | V31: 3.61 | W31: 2.5 | Y31: Cash generated from operations before tax | Z31: =SUM(Z22,Z24:Z30) -> 2804.02 | AA31: =SUM(AA22,AA24:AA30) -> 3676.25 | AB31: =SUM(AB22,AB24:AB30) -> 4115.13 | AC31: =SUM(AC22,AC24:AC30) -> 4588.13 | AD31: =SUM(AD22,AD24:AD30) -> 3401.74 | AE31: =SUM(AE22,AE24:AE30) -> 3748.82 | AG31: Cash flow from operating activities | AH31: =SUM(AH24,AH26:AH30) -> 4921.1 | AI31: =SUM(AI24,AI26:AI30) -> 14849.4 | AJ31: =SUM(AJ24,AJ26:AJ30) -> 15917.5 | AK31: =SUM(AK24,AK26:AK30) -> 17523.8 | AL31: =SUM(AL24,AL26:AL30) -> 17855.7 | AM31: =SUM(AM24,AM26:AM30) -> 8815.1 | AO31: Proceeds from issue of preference share capital | AP31: 125000 | AQ31: 0 | AR31: 0 | AS31: 0 | AT31: 0 | AU31: 0
A32: Proceeds from sale/purchase of current investments | B32: -6545.5 | C32: 5187.5 | D32: 1004.8 | E32: 0 | F32: 1901.5 | G32: 710 | I32: Proceeds from exercise of stock options | J32: 0 | K32: 0.6 | L32: 0 | M32: 0 | N32: 0 | O32: 0 | Q32: Increase/decrease in short term investment | R32: 7.01 | S32: 0 | T32: 154.37 | U32: -103.41 | V32: -96.79 | W32: -93.73 | Y32: Income tax refund/paid (net) | Z32: -279.26 | AA32: -496.42 | AB32: 88.69 | AC32: -203.78 | AD32: -219.74 | AE32: -838.01 | AG32: Income tax refund | AH32: 2406.4 | AI32: 790.3 | AJ32: 1469.5 | AK32: 1344.9 | AL32: 2970.4 | AM32: 475.5 | AO32: Proceeds from non-current borrowings | AP32: 8343 | AQ32: 421 | AR32: 24447 | AS32: 9288 | AT32: 23626 | AU32: 10737
A33: Proceeds from sale of business | B33: 0 | C33: 0 | D33: 66.3 | E33: 0 | F33: 0 | G33: 0 | I33: Interest received | J33: 85.2 | K33: 39.2 | L33: 58.5 | M33: 57.8 | N33: 626.1 | O33: 284.1 | Q33: Interest income received | R33: 27.8 | S33: 15.56 | T33: 37 | U33: 18.88 | V33: 29.28 | W33: 50.34 | Y33: Net cash flow from operating activities | Z33: =Z31+Z32 -> 2524.76 | AA33: =AA31+AA32 -> 3179.83 | AB33: =AB31+AB32 -> 4203.82 | AC33: =AC31+AC32 -> 4384.35 | AD33: =AD31+AD32 -> 3182 | AE33: =AE31+AE32 -> 2910.81 | AG33: Net cash flows from operating activities | AH33: =AH31+AH32 -> 7327.5 | AI33: =AI31+AI32 -> 15639.7 | AJ33: =AJ31+AJ32 -> 17387 | AK33: =AK31+AK32 -> 18868.7 | AL33: =AL31+AL32 -> 20826.1 | AM33: =AM31+AM32 -> 9290.6 | AO33: Repayment of non-current borrowings | AP33: -14770 | AQ33: 0 | AR33: -159 | AS33: -8499 | AT33: -2613 | AU33: -8798
A34: Purchase/Sale of current investments (net) | B34: 0 | C34: 0 | D34: 3119.5 | E34: -2523.8 | F34: -30.4 | G34: -73.4 | I34: Dividend received | J34: 0 | K34: 420 | L34: 0 | M34: 0 | N34: -4.7 | O34: -1696.8 | Q34: Subsidy/Advances received | R34: 0.92 | S34: 2.25 | T34: 2.66 | U34: 1.49 | V34: 0.37 | W34: -0.58 | Y34: Investing activities | AG34: Investing activities | AO34: Payment towards transfer of non current borrowings | AP34: -66987 | AQ34: 0 | AR34: 0 | AS34: 0 | AT34: 0 | AU34: 0
A35: Acquisition of a subsidiary, net of cash proceeds | B35: 0 | C35: 0 | D35: 0 | E35: 0 | F35: -642.8 | G35: 0 | I35: Net cash flow from/used in Investing activities | J35: =SUM(J25:J34) -> -1012.2 | K35: =SUM(K25:K34) -> 1797.7 | L35: =SUM(L25:L34) -> -2173.7 | M35: =SUM(M25:M34) -> -1730 | N35: =SUM(N25:N34) -> -7546.2 | O35: =SUM(O25:O34) -> -10910.5 | Q35: Increase/decrease in term deposit | R35: -6.56 | S35: -51.17 | T35: -287.39 | U35: 109.28 | V35: -145.86 | W35: 284.22 | Y35: Payment to purchase of PPE and intangible assets | Z35: -1680.98 | AA35: -1363.63 | AB35: -1656.44 | AC35: -1493.14 | AD35: -2082.34 | AE35: -2205.59 | AG35: Purchase of PPE and intangible assets | AH35: -7966.2 | AI35: -4709.7 | AJ35: -6008.9 | AK35: -3942.2 | AL35: -1613.9 | AM35: -10005 | AO35: Current borrowings (net) | AP35: 19641 | AQ35: -12467 | AR35: 7062 | AS35: -7382 | AT35: -3796 | AU35: 15240
A36: Cash disposed off on sale of subsidiaries | B36: 0 | C36: 0 | D36: 0 | E36: 0 | F36: 0 | G36: -6.9 | I36: Financing activities | Q36: Net cash used in Investing activities | R36: =SUM(R30:R35) -> -47.98 | S36: =SUM(S30:S35) -> -122.72 | T36: =SUM(T30:T35) -> -208.63 | U36: =SUM(U30:U35) -> -150.17 | V36: =SUM(V30:V35) -> -419.06 | W36: =SUM(W30:W35) -> -82.3 | Y36: Advance received towards assets held for sale | Z36: 176.79 | AA36: 9.11 | AB36: 6.2 | AC36: 8.12 | AD36: 34.23 | AE36: 33.99 | AG36: Payment towards spectrum and licenses | AH36: 0 | AI36: -574.7 | AJ36: -103.5 | AK36: -1680 | AL36: 0 | AM36: -331.5 | AO36: Repayment of deferred payment liabilities | AP36: -1370 | AQ36: -2 | AR36: 0 | AS36: 0 | AT36: 0 | AU36: 0
A37: Cash acquired on acquisition of subsidiaries | B37: 0 | C37: 0 | D37: 0 | E37: 0 | F37: 0 | G37: 102.3 | I37: Proceeds from borrowings | J37: 2385.3 | K37: 14964 | L37: 16242.2 | M37: 12931.5 | N37: 8555.8 | O37: 6258.4 | Q37: Financing activities | Y37: Proceeds from disposal of PPE and intangible assets | Z37: 3.55 | AA37: 11.36 | AB37: 3.44 | AC37: 41.67 | AD37: 10.5 | AE37: 6.21 | AG37: Payment towards deferred spectrum liability | AH37: -397.8 | AI37: 0 | AJ37: 120.7 | AK37: 85.7 | AL37: -448.3 | AM37: -503.7 | AO37: Repayment of lease liabilities | AP37: -672 | AQ37: -789 | AR37: -1458 | AS37: -4067 | AT37: -3657 | AU37: -3547
A38: Proceeds from sale of investment in joint venture | B38: 0 | C38: 0 | D38: 0 | E38: 0 | F38: 0 | G38: 4.5 | I38: Repayment of borrowings | J38: 0 | K38: -13332.5 | L38: -18914.4 | M38: -13698.4 | N38: -8958.4 | O38: -8309.1 | Q38: Payment for lease liability of right to use assets | R38: -6.67 | S38: -9.45 | T38: -9.09 | U38: -9.51 | V38: -11.63 | W38: -21.19 | Y38: Proceeds from disposal of assets held for sale | Z38: 15.09 | AA38: 0.41 | AB38: -169.59 | AC38: -90.51 | AD38: 4.93 | AE38: 829.55 | AG38: Proceeds from sale of PPE and intangible assets | AH38: 165.1 | AI38: 178.2 | AJ38: 187 | AK38: 0 | AL38: 84 | AM38: 114.7 | AO38: Finance cost paid | AP38: -10348 | AQ38: -2345 | AR38: -12977 | AS38: -3843 | AT38: -13573 | AU38: -13307
A39: Purchase/sale of non-current investments | B39: 1.1 | C39: -10.2 | D39: -8.9 | E39: -25.3 | F39: 6.9 | G39: 30 | I39: Sale/Purchase of treasury shares (net) | J39: -3.9 | K39: 7.8 | L39: -15.4 | M39: -7.5 | N39: -13 | O39: -25.8 | Q39: Dividend paid | R39: -46.2 | S39: -100.15 | T39: -94.67 | U39: -69 | V39: -65.79 | W39: -91.46 | Y39: Purchase of investments in associates | Z39: -49.38 | AA39: -34.31 | AB39: -29.56 | AC39: -1.84 | AD39: -267.21 | AE39: -281.44 | AG39: Proceeds from sale of stake in Indus | AH39: 0 | AI39: 3747.2 | AJ39: 18 | AK39: 29 | AL39: 0 | AM39: 55 | AO39: Net cash flow from/used in Financing activities | AP39: =SUM(AP31:AP38) -> 58837 | AQ39: =SUM(AQ31:AQ38) -> -15182 | AR39: =SUM(AR31:AR38) -> 16915 | AS39: =SUM(AS31:AS38) -> -14503 | AT39: =SUM(AT31:AT38) -> -13 | AU39: =SUM(AU31:AU38) -> 325
A40: Investment in subsidiaries, joint ventures and associates | B40: -440.5 | C40: -1178.5 | D40: -2653.5 | E40: -1183.2 | F40: -30 | G40: -878.8 | I40: Cash paid to Vodafone Idea | J40: 0 | K40: -3764.2 | L40: 0 | M40: 0 | N40: 0 | O40: 0 | Q40: Dividend distribution tax paid | R40: -9.59 | S40: 0 | T40: 0 | U40: 0 | V40: 0 | W40: 0 | Y40: Purchase of non-current investments | Z40: -37.94 | AA40: -29.25 | AB40: 0 | AC40: 0 | AD40: 0 | AE40: 228.76 | AG40: Net sale of current investments | AH40: 6542.3 | AI40: 495.2 | AJ40: 0.8 | AK40: 0 | AL40: 0 | AM40: 3.4 | AO40: Net increase/decrease in Cash and cash equivalents | AP40: =AP20+AP29+AP39 -> 7049 | AQ40: =AQ20+AQ29+AQ39 -> -6888 | AR40: =AR20+AR29+AR39 -> -95 | AS40: =AS20+AS29+AS39 -> 462 | AT40: =AT20+AT29+AT39 -> 520 | AU40: =AU20+AU29+AU39 -> 4962
A41: Loan given to subsidiaries | B41: -6718.4 | C41: -6132.2 | D41: -5605 | E41: -4790.8 | F41: 0 | G41: 0 | I41: Stamp duty on issue of shares pursuant to merger of erstwhile Indus towers | J41: 0 | K41: -0.8 | L41: 0 | M41: 0 | N41: 0.4 | O41: 0.8 | Q41: Net cash generated from/used in financing activities | R41: =SUM(R38:R40) -> -62.46 | S41: =SUM(S38:S40) -> -109.6 | T41: =SUM(T38:T40) -> -103.76 | U41: =SUM(U38:U40) -> -78.51 | V41: =SUM(V38:V40) -> -77.42 | W41: =SUM(W38:W40) -> -112.65 | Y41: Fixed deposits transferred as part of land demerger | Z41: -2.9 | AA41: 0 | AB41: 0 | AC41: 0 | AD41: -99.06 | AE41: 0 | AG41: Interest received | AH41: 517.2 | AI41: 179.7 | AJ41: 58.6 | AK41: 94.1 | AL41: 23.7 | AM41: 19.4 | AO41: Opening balance | AP41: 17 | AQ41: =AP42 -> 7066 | AR41: =AQ42 -> 178 | AS41: =AR42 -> 83 | AT41: =AS42 -> 545 | AU41: =AT42 -> 1065
A42: Loan repayment by subsidiaries | B42: 3286.7 | C42: 8153.9 | D42: 5494 | E42: 1566.8 | F42: 0 | G42: 0 | I42: Dividend paid | J42: -2570.1 | K42: -5985.4 | L42: 0 | M42: -2963.8 | N42: 0 | O42: -2640 | Q42: Effect of exchange difference on translation of cash and cash eq | R42: 0 | S42: 0 | T42: 0 | U42: 0 | V42: 0 | W42: 0 | Y42: Dividend income from investments at fair value | Z42: 0 | AA42: 20.93 | AB42: 65.04 | AC42: 43.07 | AD42: -904.53 | AE42: 0 | AG42: Fixed deposits with banks having maturity of 3 to 12 months | AH42: -1650.4 | AI42: 1647.7 | AJ42: -3 | AK42: -0.2 | AL42: 42.2 | AM42: 452.3 | AO42: Closing balance | AP42: =SUM(AP40:AP41) -> 7066 | AQ42: =SUM(AQ40:AQ41) -> 178 | AR42: =SUM(AR40:AR41) -> 83 | AS42: =SUM(AS40:AS41) -> 545 | AT42: =SUM(AT40:AT41) -> 1065 | AU42: =SUM(AU40:AU41) -> 6027
A43: Dividend received | B43: 863.1 | C43: 1716.3 | D43: 45 | E43: 1518.1 | F43: 107.2 | G43: 109 | I43: Tax on dividend paid | J43: -528.5 | K43: 0 | L43: 0 | M43: 0 | N43: 0 | O43: -108.7 | Q43: Net increase/decrease in cash and cash equivalents | R43: =R28+R36+R41 -> 62.88 | S43: =S28+S36+S41 -> 116.45 | T43: =T28+T36+T41 -> -62.63 | U43: =U28+U36+U41 -> 0.86 | V43: =V28+V36+V41 -> 33.14 | W43: =W28+W36+W41 -> 38.67 | Y43: Net cash outflow on acquisition of subsidiary | Z43: 0 | AA43: -1.58 | AB43: -0.22 | AC43: -50.8 | AD43: -11.67 | AE43: -14.07 | AG43: Dividend received from joint venture (Indus) | AH43: 0 | AI43: 111.5 | AJ43: 0 | AK43: 0 | AL43: 5.5 | AM43: -6052.9
A44: Interest received | B44: 212.5 | C44: 348.1 | D44: 137.8 | E44: 118 | F44: 567.1 | G44: 423.9 | I44: Interest paid | J44: -130 | K44: -145 | L44: -441.8 | M44: -366.6 | N44: -406.6 | O44: -276.2 | Q44: Opening balance | R44: 71.64 | S44: =R45 -> 134.52 | T44: =S45 -> 250.97 | U44: =T45 -> 188.34 | V44: =U45 -> 189.2 | W44: =V45 -> 222.34 | Y44: Purchase of current investments | Z44: -7260.75 | AA44: -6389.26 | AB44: -6071.27 | AC44: -7608.75 | AD44: -7593.63 | AE44: -7700.81 | AG44: Net cash flows from/used in investing activities | AH44: =SUM(AH35:AH43) -> -2789.8 | AI44: =SUM(AI35:AI43) -> 1075.1 | AJ44: =SUM(AJ35:AJ43) -> -5730.3 | AK44: =SUM(AK35:AK43) -> -5413.6 | AL44: =SUM(AL35:AL43) -> -1906.8 | AM44: =SUM(AM35:AM43) -> -16248.3
A45: Net cash flows from/used in investing activities | B45: =SUM(B28:B44) -> -22271.5 | C45: =SUM(C28:C44) -> -13223.3 | D45: =SUM(D28:D44) -> -33169.7 | E45: =SUM(E28:E44) -> -30006.3 | F45: =SUM(F28:F44) -> -50203.9 | G45: =SUM(G28:G44) -> -60269.8 | I45: Repayment of leasehold liabilities | J45: -338.2 | K45: -1120.7 | L45: -2852.2 | M45: -3027.8 | N45: -3173.4 | O45: -3547.3 | Q45: Closing balance | R45: =SUM(R42:R44) -> 134.52 | S45: =SUM(S42:S44) -> 250.97 | T45: =SUM(T42:T44) -> 188.34 | U45: =SUM(U42:U44) -> 189.2 | V45: =SUM(V42:V44) -> 222.34 | W45: =SUM(W42:W44) -> 261.01 | Y45: Proceeds from sale of current investments | Z45: 7220.48 | AA45: 5813.14 | AB45: 6950.32 | AC45: 7299.27 | AD45: 8233.06 | AE45: 6960.83 | AG45: Financing activities
A46: Financing activities | I46: Net cash flow from/used in financing activities | J46: =SUM(J37:J45) -> -1185.4 | K46: =SUM(K37:K45) -> -9376.8 | L46: =SUM(L37:L45) -> -5981.6 | M46: =SUM(M37:M45) -> -7132.6 | N46: =SUM(N37:N45) -> -3995.2 | O46: =SUM(O37:O45) -> -8647.9 | Y46: Proceeds from sale of investments in associate | Z46: 72.1 | AA46: 0 | AB46: 0 | AC46: 0 | AD46: 5.63 | AE46: 0 | AG46: Proceeds from allotment of equity shares under rights issue | AH46: 24916.4 | AI46: 0 | AJ46: 4499.7 | AK46: =-2750-7903.9 -> -10653.9 | AL46: 0 | AM46: 17695.9
A47: Net proceeds from issue of shares | B47: 24875.9 | C47: 0 | D47: 5222.6 | E47: 5224.2 | F47: -87 | G47: -3734.8 | I47: Net increase/decrease in cash and cash equivalents | J47: =J23+J35+J46 -> 117.5 | K47: =K23+K35+K46 -> -98 | L47: =L23+L35+L46 -> 965.9 | M47: =M23+M35+M46 -> -957.8 | N47: =N23+N35+N46 -> 40.7 | O47: =O23+O35+O46 -> 86.6 | Y47: Fixed deposits liquidated | Z47: 6.54 | AA47: -50.96 | AB47: 0 | AC47: 0 | AD47: 48.33 | AE47: 39.04 | AG47: Proceeds from issue of shares under ESOS | AH47: 0 | AI47: 0 | AJ47: 0 | AK47: 0 | AL47: 0.1 | AM47: 0.1
A48: Net proceeds from issue of shares (QIP) | B48: 14305.5 | C48: 0 | D48: 0 | E48: 0 | F48: 439.1 | G48: 82.9 | I48: Opening balance | J48: -5.4 | K48: =J50 -> 112.1 | L48: =K50 -> 14.3 | M48: =L50 -> 980.2 | N48: =M50 -> 22.4 | O48: =N50 -> 63.1 | Y48: Earmarked funds | Z48: 2.72 | AA48: -0.98 | AB48: 0 | AC48: 0 | AD48: -49.74 | AE48: -95.32 | AG48: Proceeds from issue of share capital through preferential allt | AH48: 0 | AI48: 0 | AJ48: 0 | AK48: 0 | AL48: 0 | AM48: 6441.2
A49: Net proceeds from issuance of FCCBs | B49: 7045.6 | C49: 0 | D49: 0 | E49: 0 | F49: -169.3 | G49: -8629.2 | I49: Cash and cash equivalents pursuant to merger of Indus | J49: 0 | K49: 0.2 | L49: 0 | M49: 0 | N49: 0 | O49: 0 | Y49: Interest received | Z49: 4.9 | AA49: 10.42 | AB49: 7.11 | AC49: 11.28 | AD49: =-0.28+27.81 -> 27.53 | AE49: =2.31+17.77 -> 20.08 | AG49: Payment of interest and finance charges | AH49: -15258.5 | AI49: -2825.6 | AJ49: =-6939.7 -> -6939.7 | AK49: 432 | AL49: -2867.8 | AM49: -2090.2
A50: Proceeds from borrowings | B50: 24604.7 | C50: 13854 | D50: 10661.3 | E50: 5738.3 | F50: 6712.3 | G50: 23559.7 | I50: Closing balance | J50: =SUM(J47:J49) -> 112.1 | K50: =K48+K49+K47 -> 14.3 | L50: =SUM(L47:L49) -> 980.2 | M50: =SUM(M47:M49) -> 22.4 | N50: =SUM(N47:N49) -> 63.1 | O50: =SUM(O47:O49) -> 149.7 | Y50: Net cash from/used in Investing activities | Z50: =SUM(Z35:Z49) -> -1529.78 | AA50: =SUM(AA35:AA49) -> -2004.6 | AB50: =SUM(AB35:AB49) -> -894.97 | AC50: =SUM(AC35:AC49) -> -1841.63 | AD50: =SUM(AD35:AD49) -> -2643.97 | AE50: =SUM(AE35:AE49) -> -2178.77 | AG50: Repayment of long term borrowings | AH50: -4051.7 | AI50: -4322 | AJ50: -2799.7 | AK50: -2094 | AL50: -5916.4 | AM50: -1711.4
A51: Repayment of borrowings | B51: -25203.2 | C51: -23707.4 | D51: -11138.9 | E51: -6812.4 | F51: -10080.3 | G51: -17859.4 | Y51: Financing Activities | AG51: Proceeds from short term borrowings | AH51: 3391.6 | AI51: 0 | AJ51: 500 | AK51: 1600 | AL51: 2000 | AM51: 1000
A52: Payment of lease liabilities | B52: -4312.6 | C52: -5184.6 | D52: -4984.5 | E52: -4449.9 | F52: -7855.2 | G52: -7153.8 | Y52: Proceeds from short term borrowings | Z52: 3417.16 | AA52: 2929.55 | AB52: 1098.61 | AC52: 0 | AD52: 5294.03 | AE52: 9682.55 | AG52: Repayment of short term borrowings | AH52: -7422.5 | AI52: -28.3 | AJ52: -8064.1 | AK52: -5946 | AL52: -3482.4 | AM52: -1000
A53: Repayment of short term borrowings | B53: -12736.8 | C53: -1409.7 | D53: 6482.4 | E53: -6950.1 | F53: 1551.6 | G53: 3692.7 | Y53: Repayment of short term borrowings | Z53: -3171.84 | AA53: -4064.45 | AB53: -1435.78 | AC53: -341.5 | AD53: -4123.63 | AE53: -9550.21 | AG53: Payment of lease liabilities | AH53: -6594 | AI53: -9555.5 | AJ53: 2250 | AK53: 1982.4 | AL53: -8713.8 | AM53: -13288.9
A54: Interest and other finance charges paid | B54: -7465.3 | C54: -5679.3 | D54: -10442.7 | E54: -3487.8 | F54: -14026.3 | G54: -17547.6 | Y54: Proceeds from long term borrowings | Z54: 1139.52 | AA54: 5372.55 | AB54: 3418.07 | AC54: 1239.38 | AD54: 1807.19 | AE54: 4373.47 | AG54: Net cash flows from/used in financing activities | AH54: =SUM(AH46:AH53) -> -5018.7 | AI54: =SUM(AI46:AI53) -> -16731.4 | AJ54: =SUM(AJ46:AJ53) -> -10553.8 | AK54: =SUM(AK46:AK53) -> -14679.5 | AL54: =SUM(AL46:AL53) -> -18980.3 | AM54: =SUM(AM46:AM53) -> 7046.7
A55: Proceeds from exercise of share options | B55: 0.3 | C55: 0.5 | D55: 0.7 | E55: 0.3 | F55: 0.6 | G55: 1.4 | Y55: Repayment of long term borrowings | Z55: -969.41 | AA55: -4517.35 | AB55: -5498.8 | AC55: -1844.29 | AD55: -2309.55 | AE55: -4001.83 | AG55: Net increase/decrease in cash and cash equivalents | AH55: =AH33+AH44+AH54 -> -481 | AI55: =AI33+AI44+AI54 -> -16.6 | AJ55: =AJ33+AJ44+AJ54 -> 1102.9 | AK55: =AK33+AK44+AK54 -> -1224.4 | AL55: =AL33+AL44+AL54 -> -61 | AM55: =AM33+AM44+AM54 -> 89
A56: Purchase of treasury shares | B56: 0 | C56: 0 | D56: 0 | E56: 0 | F56: -136.8 | G56: -367.5 | Y56: Repayment of lease liabilities | Z56: -314.28 | AA56: -369.94 | AB56: -364.11 | AC56: -352.67 | AD56: -351.77 | AE56: -398.95 | AG56: Opening balance | AH56: 755.8 | AI56: =AH58 -> 366.9 | AJ56: =AI58 -> 350.3 | AK56: =AJ58 -> 1453.2 | AL56: =AK58 -> 228.8 | AM56: =AL58 -> 167.8
A57: Payment of/proceeds from maturity of derivatives | B57: 0 | C57: 0 | D57: 0 | E57: 0 | F57: 57.3 | G57: -1642.7 | Y57: Dividends paid including dividend tax | Z57: -150.77 | AA57: -114 | AB57: -399 | AC57: -589.95 | AD57: -598.5 | AE57: -475.95 | AG57: Add: Cash and cash equivalents of VMPL | AH57: 92.1 | AI57: 0 | AJ57: 0 | AK57: 0 | AL57: 0 | AM57: 0
A58: Dividends paid | B58: 0 | C58: -1091.1 | D58: -89.8 | E58: =-1698.4-64.6 -> -1763 | F58: -4184.5 | G58: -6934.9 | Y58: Dividends paid to non-controlling interest | Z58: -2.14 | AA58: -1.21 | AB58: -2.59 | AC58: -3.06 | AD58: -2.91 | AE58: -1.24 | AG58: Closing balance | AH58: =SUM(AH55:AH57) -> 366.9 | AI58: =SUM(AI55:AI57) -> 350.3 | AJ58: =SUM(AJ55:AJ57) -> 1453.2 | AK58: =SUM(AK55:AK57) -> 228.8 | AL58: =SUM(AL55:AL57) -> 167.8 | AM58: =SUM(AM55:AM57) -> 256.8
A59: Net cash flows from/used in financing activities | B59: =SUM(B47:B58) -> 21114.1 | C59: =SUM(C47:C58) -> -23217.6 | D59: =SUM(D47:D58) -> -4288.9 | E59: =SUM(E47:E58) -> -12500.4 | F59: =SUM(F47:F58) -> -27778.5 | G59: =SUM(G47:G58) -> -36533.2 | Y59: Finance cost paid | Z59: -385.01 | AA59: -251.5 | AB59: -247.63 | AC59: -348.71 | AD59: -527.81 | AE59: -563.47
A60: Net increase/decrease in Cash and cash equivalents | B60: =B26+B45+B59 -> 2869 | C60: =C26+C45+C59 -> -2048.6 | D60: =D26+D45+D59 -> -704.2 | E60: =E26+E45+E59 -> 1075.9 | F60: =F26+F45+F59 -> 915.8 | G60: =G26+G45+G59 -> 1529.2 | Y60: Net decrease/increase in working capital borrowings | Z60: -505.56 | AA60: -188.42 | AB60: 0 | AC60: 0 | AD60: 0 | AE60: 0
A61: Opening balance | B61: 170.7 | C61: =B62 -> 3039.7 | D61: =C62 -> 991.1 | E61: =D62 -> 286.9 | F61: =E62 -> 1362.8 | G61: =F62 -> 2278.6 | Y61: Net cash from/used in financing activties | Z61: =SUM(Z52:Z60) -> -942.33 | AA61: =SUM(AA52:AA60) -> -1204.77 | AB61: =SUM(AB52:AB60) -> -3431.23 | AC61: =SUM(AC52:AC60) -> -2240.8 | AD61: =SUM(AD52:AD60) -> -812.95 | AE61: =SUM(AE52:AE60) -> -935.63
A62: Closing Balance | B62: =SUM(B60:B61) -> 3039.7 | C62: =SUM(C60:C61) -> 991.1 | D62: =SUM(D60:D61) -> 286.9 | E62: =SUM(E60:E61) -> 1362.8 | F62: =SUM(F60:F61) -> 2278.6 | G62: =SUM(G60:G61) -> 3807.8 | Y62: Net decrease/increase in cash and cash equivalents | Z62: =Z33+Z50+Z61 -> 52.65 | AA62: =AA33+AA50+AA61 -> -29.54 | AB62: =AB33+AB50+AB61 -> -122.38 | AC62: =AC33+AC50+AC61 -> 301.92 | AD62: =AD33+AD50+AD61 -> -274.92 | AE62: =AE33+AE50+AE61 -> -203.59
Y63: Opening balance | Z63: 789.06 | AA63: =Z65 -> 850 | AB63: =AA65 -> 817.85 | AC63: =AB65 -> 696.86 | AD63: =AC65 -> 1004.48 | AE63: =AD65 -> 732.05
Y64: Exchange difference on translation of foreign currency | Z64: 8.29 | AA64: -2.61 | AB64: 1.39 | AC64: 5.7 | AD64: 2.49 | AE64: =5.56-0.12 -> 5.44
Y65: Closing balance | Z65: =SUM(Z62:Z64) -> 850 | AA65: =SUM(AA62:AA64) -> 817.85 | AB65: =SUM(AB62:AB64) -> 696.86 | AC65: =SUM(AC62:AC64) -> 1004.48 | AD65: =SUM(AD62:AD64) -> 732.05 | AE65: =SUM(AE62:AE64) -> 533.9

Sheet Ratio Analysis
A1: Ratio Analysis
G2: #VALUE! | P2: #VALUE! | Y2: #VALUE! | AH2: #VALUE! | AQ2: #VALUE! | AZ2: #VALUE!
A3: Ratio | B3: Type | C3: 2020 | D3: 2021 | E3: 2022 | F3: 2023 | G3: 2024 | H3: 2025 | J3: Ratio | K3: Type | L3: 2020 | M3: 2021 | N3: 2022 | O3: 2023 | P3: 2024 | Q3: 2025 | S3: Ratio | T3: Type | U3: 2020 | V3: 2021 | W3: 2022 | X3: 2023 | Y3: 2024 | Z3: 2025 | AB3: Ratio | AC3: Type | AD3: 2020 | AE3: 2021 | AF3: 2022 | AG3: 2023 | AH3: 2024 | AI3: 2025 | AK3: Ratio | AL3: Type | AM3: 2020 | AN3: 2021 | AO3: 2022 | AP3: 2023 | AQ3: 2024 | AR3: 2025 | AT3: Ratio | AU3: Type | AV3: 2020 | AW3: 2021 | AX3: 2022 | AY3: 2023 | AZ3: 2024 | BA3: 2025
A4: Profitability Ratio | B4: Operating Profit Margin | C4: =('Income Statement'!B6-(SUM('Income Statement'!B8:B13)))/'Income Statement'!B6 -> 0.39561984 | D4: =('Income Statement'!C6-(SUM('Income Statement'!C8:C13)))/'Income Statement'!C6 -> 0.45525813 | E4: =('Income Statement'!D6-(SUM('Income Statement'!D8:D13)))/'Income Statement'!D6 -> 0.49446771 | F4: =('Income Statement'!E6-(SUM('Income Statement'!E8:E13)))/'Income Statement'!E6 -> 0.53154467 | G4: =('Income Statement'!F6-(SUM('Income Statement'!F8:F13)))/'Income Statement'!F6 -> 0.52653783 | H4: =('Income Statement'!G6-(SUM('Income Statement'!G8:G13)))/'Income Statement'!G6 -> 0.54269877 | J4: Profitability Ratio | K4: Operating Profit Margin | L4: =('Income Statement'!J6-'Income Statement'!J13)/'Income Statement'!J6 -> 0.54517805 | M4: =('Income Statement'!K6-'Income Statement'!K13)/'Income Statement'!K6 -> 0.52693764 | N4: =('Income Statement'!L6-'Income Statement'!L13)/'Income Statement'!L6 -> 0.54490785 | O4: =('Income Statement'!M6-'Income Statement'!M13)/'Income Statement'!M6 -> 0.35237327 | P4: =('Income Statement'!N6-'Income Statement'!N13)/'Income Statement'!N6 -> 0.51982446 | Q4: =('Income Statement'!O6-'Income Statement'!O13)/'Income Statement'!O6 -> 0.6954865 | S4: Profitability Ratio | T4: Operating Profit Margin | U4: =('Income Statement'!R7-'Income Statement'!R9-'Income Statement'!R10-'Income Statement'!R11-'Income Statement'!R12-'Income Statement'!R13)/'Income Statement'!R7 -> 0.32315426 | V4: =('Income Statement'!S7-'Income Statement'!S9-'Income Statement'!S10-'Income Statement'!S11-'Income Statement'!S12-'Income Statement'!S13)/'Income Statement'!S7 -> 0.25895457 | W4: =('Income Statement'!T7-'Income Statement'!T9-'Income Statement'!T10-'Income Statement'!T11-'Income Statement'!T12-'Income Statement'!T13)/'Income Statement'!T7 -> 0.25287597 | X4: =('Income Statement'!U7-'Income Statement'!U9-'Income Statement'!U10-'Income Statement'!U11-'Income Statement'!U12-'Income Statement'!U13)/'Income Statement'!U7 -> 0.21185696 | Y4: =('Income Statement'!V7-'Income Statement'!V9-'Income Statement'!V10-'Income Statement'!V11-'Income Statement'!V12-'Income Statement'!V13)/'Income Statement'!V7 -> 0.19947601 | Z4: =('Income Statement'!W7-'Income Statement'!W9-'Income Statement'!W10-'Income Statement'!W11-'Income Statement'!W12-'Income Statement'!W13)/'Income Statement'!W7 -> 0.17255227 | AB4: Profitability Ratio | AC4: Operating Profit Margin | AD4: =('Income Statement'!Z6-(SUM('Income Statement'!Z8+'Income Statement'!Z9+'Income Statement'!Z12)))/'Income Statement'!Z6 -> 0.19597938 | AE4: =('Income Statement'!AA6-(SUM('Income Statement'!AA8+'Income Statement'!AA9+'Income Statement'!AA12)))/'Income Statement'!AA6 -> 0.25597588 | AF4: =('Income Statement'!AB6-(SUM('Income Statement'!AB8+'Income Statement'!AB9+'Income Statement'!AB12)))/'Income Statement'!AB6 -> 0.26727198 | AG4: =('Income Statement'!AC6-(SUM('Income Statement'!AC8+'Income Statement'!AC9+'Income Statement'!AC12)))/'Income Statement'!AC6 -> 0.25719876 | AH4: =('Income Statement'!AD6-(SUM('Income Statement'!AD8+'Income Statement'!AD9+'Income Statement'!AD12)))/'Income Statement'!AD6 -> 0.21765231 | AI4: =('Income Statement'!AE6-(SUM('Income Statement'!AE8+'Income Statement'!AE9+'Income Statement'!AE12)))/'Income Statement'!AE6 -> 0.20221835 | AK4: Profitability Ratio | AL4: Operating Profit Margin | AM4: ='Income Statement'!AH19/'Income Statement'!AH8 -> 0.34680239 | AN4: ='Income Statement'!AI19/'Income Statement'!AI8 -> 0.40639362 | AO4: ='Income Statement'!AJ19/'Income Statement'!AJ8 -> 0.41830875 | AP4: ='Income Statement'!AK19/'Income Statement'!AK8 -> 0.40312791 | AQ4: ='Income Statement'!AL19/'Income Statement'!AL8 -> 0.40311564 | AR4: ='Income Statement'!AM19/'Income Statement'!AM8 -> 0.4293874 | AT4: Profitability Ratio | AU4: Operating Profit Margin | AV4: =('Income Statement'!AP6-'Income Statement'!AP8-'Income Statement'!AP9-'Income Statement'!AP10-'Income Statement'!AP11-'Income Statement'!AP14-'Income Statement'!AP15)/'Income Statement'!AP6 -> 0.39802952 | AW4: =('Income Statement'!AQ6-'Income Statement'!AQ8-'Income Statement'!AQ9-'Income Statement'!AQ10-'Income Statement'!AQ11-'Income Statement'!AQ14-'Income Statement'!AQ15)/'Income Statement'!AQ6 -> 0.4466608 | AX4: =('Income Statement'!AR6-'Income Statement'!AR8-'Income Statement'!AR9-'Income Statement'!AR10-'Income Statement'!AR11-'Income Statement'!AR14-'Income Statement'!AR15)/'Income Statement'!AR6 -> 0.49055874 | AY4: =('Income Statement'!AS6-'Income Statement'!AS8-'Income Statement'!AS9-'Income Statement'!AS10-'Income Statement'!AS11-'Income Statement'!AS14-'Income Statement'!AS15)/'Income Statement'!AS6 -> 0.5152004 | AZ4: =('Income Statement'!AT6-'Income Statement'!AT8-'Income Statement'!AT9-'Income Statement'!AT10-'Income Statement'!AT11-'Income Statement'!AT14-'Income Statement'!AT15)/'Income Statement'!AT6 -> 0.52574644 | BA4: =('Income Statement'!AU6-'Income Statement'!AU8-'Income Statement'!AU9-'Income Statement'!AU10-'Income Statement'!AU11-'Income Statement'!AU14-'Income Statement'!AU15)/'Income Statement'!AU6 -> 0.53205373
B5: Gross Profit Margin | C5: =('Income Statement'!B6-'Income Statement'!B8)/'Income Statement'!B6 -> 0.75880487 | D5: =('Income Statement'!C6-'Income Statement'!C8)/'Income Statement'!C6 -> 0.77335274 | E5: =('Income Statement'!D6-'Income Statement'!D8)/'Income Statement'!D6 -> 0.75927254 | F5: =('Income Statement'!E6-'Income Statement'!E8)/'Income Statement'!E6 -> 0.78952628 | G5: =('Income Statement'!F6-'Income Statement'!F8)/'Income Statement'!F6 -> 0.80174854 | H5: =('Income Statement'!G6-'Income Statement'!G8)/'Income Statement'!G6 -> 0.80806307 | K5: Gross Profit Margin | L5: =('Income Statement'!J6-'Income Statement'!J8-'Income Statement'!J9-'Income Statement'!J11)/'Income Statement'!J6 -> 0.61908989 | M5: =('Income Statement'!K6-'Income Statement'!K8-'Income Statement'!K9-'Income Statement'!K11)/'Income Statement'!K6 -> 0.58461473 | N5: =('Income Statement'!L6-'Income Statement'!L8-'Income Statement'!L9-'Income Statement'!L11)/'Income Statement'!L6 -> 0.58629768 | O5: =('Income Statement'!M6-'Income Statement'!M8-'Income Statement'!M9-'Income Statement'!M11)/'Income Statement'!M6 -> 0.58454725 | P5: =('Income Statement'!N6-'Income Statement'!N8-'Income Statement'!N9-'Income Statement'!N11)/'Income Statement'!N6 -> 0.56670361 | Q5: =('Income Statement'!O6-'Income Statement'!O8-'Income Statement'!O9-'Income Statement'!O11)/'Income Statement'!O6 -> 0.57694807 | T5: Gross Profit Margin | U5: =('Income Statement'!R7-'Income Statement'!R9-'Income Statement'!R10-'Income Statement'!R11)/'Income Statement'!R7 -> 0.4535551 | V5: =('Income Statement'!S7-'Income Statement'!S9-'Income Statement'!S10-'Income Statement'!S11)/'Income Statement'!S7 -> 0.42660261 | W5: =('Income Statement'!T7-'Income Statement'!T9-'Income Statement'!T10-'Income Statement'!T11)/'Income Statement'!T7 -> 0.39225343 | X5: =('Income Statement'!U7-'Income Statement'!U9-'Income Statement'!U10-'Income Statement'!U11)/'Income Statement'!U7 -> 0.32721506 | Y5: =('Income Statement'!V7-'Income Statement'!V9-'Income Statement'!V10-'Income Statement'!V11)/'Income Statement'!V7 -> 0.29119775 | Z5: =('Income Statement'!W7-'Income Statement'!W9-'Income Statement'!W10-'Income Statement'!W11)/'Income Statement'!W7 -> 0.2423628 | AC5: Gross Profit Margin | AD5: =('Income Statement'!Z6-'Income Statement'!Z8)/'Income Statement'!Z6 -> 0.60452267 | AE5: =('Income Statement'!AA6-'Income Statement'!AA8)/'Income Statement'!AA6 -> 0.63299986 | AF5: =('Income Statement'!AB6-'Income Statement'!AB8)/'Income Statement'!AB6 -> 0.63653893 | AG5: =('Income Statement'!AC6-'Income Statement'!AC8)/'Income Statement'!AC6 -> 0.64972549 | AH5: =('Income Statement'!AD6-'Income Statement'!AD8)/'Income Statement'!AD6 -> 0.61619047 | AI5: =('Income Statement'!AE6-'Income Statement'!AE8)/'Income Statement'!AE6 -> 0.56763124 | AL5: Gross Profit Margin | AM5: =('Income Statement'!AH8-'Income Statement'!AH10-'Income Statement'!AH12-'Income Statement'!AH13-'Income Statement'!AH14)/'Income Statement'!AH8 -> 0.5251561 | AN5: =('Income Statement'!AI8-'Income Statement'!AI10-'Income Statement'!AI12-'Income Statement'!AI13-'Income Statement'!AI14)/'Income Statement'!AI8 -> 0.54857524 | AO5: =('Income Statement'!AJ8-'Income Statement'!AJ10-'Income Statement'!AJ12-'Income Statement'!AJ13-'Income Statement'!AJ14)/'Income Statement'!AJ8 -> 0.56166273 | AP5: =('Income Statement'!AK8-'Income Statement'!AK10-'Income Statement'!AK12-'Income Statement'!AK13-'Income Statement'!AK14)/'Income Statement'!AK8 -> 0.57665486 | AQ5: =('Income Statement'!AL8-'Income Statement'!AL10-'Income Statement'!AL12-'Income Statement'!AL13-'Income Statement'!AL14)/'Income Statement'!AL8 -> 0.58806638 | AR5: =('Income Statement'!AM8-'Income Statement'!AM10-'Income Statement'!AM12-'Income Statement'!AM13-'Income Statement'!AM14)/'Income Statement'!AM8 -> 0.60229548 | AU5: Gross Profit Margin | AV5: =('Income Statement'!AP6-'Income Statement'!AP8-'Income Statement'!AP9-'Income Statement'!AP10)/'Income Statement'!AP6 -> 0.4771428 | AW5: =('Income Statement'!AQ6-'Income Statement'!AQ8-'Income Statement'!AQ9-'Income Statement'!AQ10)/'Income Statement'!AQ6 -> 0.5109887 | AX5: =('Income Statement'!AR6-'Income Statement'!AR8-'Income Statement'!AR9-'Income Statement'!AR10)/'Income Statement'!AR6 -> 0.55051879 | AY5: =('Income Statement'!AS6-'Income Statement'!AS8-'Income Statement'!AS9-'Income Statement'!AS10)/'Income Statement'!AS6 -> 0.57799675 | AZ5: =('Income Statement'!AT6-'Income Statement'!AT8-'Income Statement'!AT9-'Income Statement'!AT10)/'Income Statement'!AT6 -> 0.59328674 | BA5: =('Income Statement'!AU6-'Income Statement'!AU8-'Income Statement'!AU9-'Income Statement'!AU10)/'Income Statement'!AU6 -> 0.60803038
B6: Net Profit Margin | C6: ='Income Statement'!B25/Table7[[#This Row],[2020]] -> -0.63805614 | D6: ='Income Statement'!C25/Table7[[#This Row],[2021]] -> -0.37769697 | E6: ='Income Statement'!D25/Table7[[#This Row],[2022]] -> -0.054114203 | F6: ='Income Statement'!E25/Table7[[#This Row],[2023]] -> -0.0010257126 | G6: ='Income Statement'!F25/Table7[[#This Row],[2024]] -> 0.056519115 | H6: ='Income Statement'!G25/Table7[[#This Row],[2025]] -> 0.21472007 | K6: Net Profit Margin | L6: ='Income Statement'!J26/Table10[[#This Row],[2020]] -> 0.48004133 | M6: ='Income Statement'!K26/Table10[[#This Row],[2021]] -> 0.26704449 | N6: ='Income Statement'!L26/Table10[[#This Row],[2022]] -> 0.22704553 | O6: ='Income Statement'!M26/Table10[[#This Row],[2023]] -> 0.070973555 | P6: ='Income Statement'!N26/Table10[[#This Row],[2024]] -> 0.20842009 | Q6: ='Income Statement'!O26/Table10[[#This Row],[2025]] -> 0.32596509 | T6: Net Profit Margin | U6: ='Income Statement'!R25/'Income Statement'!R7 -> 0.12100807 | V6: ='Income Statement'!S25/'Income Statement'!S7 -> 0.10093602 | W6: ='Income Statement'!T25/'Income Statement'!T7 -> 0.068921805 | X6: ='Income Statement'!U25/'Income Statement'!U7 -> 0.094431126 | Y6: ='Income Statement'!V25/'Income Statement'!V7 -> 0.093895514 | Z6: ='Income Statement'!W25/'Income Statement'!W7 -> 0.084428787 | AC6: Net Profit Margin | AD6: ='Income Statement'!Z23/Table14[[#This Row],[2020]] -> -0.0049499144 | AE6: ='Income Statement'!AA23/Table14[[#This Row],[2021]] -> 0.072523043 | AF6: ='Income Statement'!AB23/Table14[[#This Row],[2022]] -> 0.087042602 | AG6: ='Income Statement'!AC23/Table14[[#This Row],[2023]] -> 0.098941236 | AH6: ='Income Statement'!AD23/Table14[[#This Row],[2024]] -> 0.05343345 | AI6: ='Income Statement'!AE23/Table14[[#This Row],[2025]] -> 0.069955579 | AL6: Net Profit Margin | AM6: ='Income Statement'!AH32/'Income Statement'!AH8 -> -1.6061574 | AN6: ='Income Statement'!AI32/'Income Statement'!AI8 -> -1.050009 | AO6: ='Income Statement'!AJ32/'Income Statement'!AJ8 -> -0.73089593 | AP6: ='Income Statement'!AK32/'Income Statement'!AK8 -> -0.68962425 | AQ6: ='Income Statement'!AL32/'Income Statement'!AL8 -> -0.73046821 | AR6: ='Income Statement'!AM32/'Income Statement'!AM8 -> -0.61408911 | AU6: Net Profit Margin | AV6: ='Income Statement'!AP23/Table18[[#This Row],[2020]] -> 0.10223701 | AW6: ='Income Statement'!AQ23/Table18[[#This Row],[2021]] -> 0.17058039 | AX6: ='Income Statement'!AR23/Table18[[#This Row],[2022]] -> 0.19145453 | AY6: ='Income Statement'!AS23/Table18[[#This Row],[2023]] -> 0.19946371 | AZ6: ='Income Statement'!AT23/Table18[[#This Row],[2024]] -> 0.20348589 | BA6: ='Income Statement'!AU23/Table18[[#This Row],[2025]] -> 0.21544383
A7: Liquidity Ratio | B7: Current Ratio | C7: ='Balance Sheet'!B30/'Balance Sheet'!B60 -> 0.63062486 | D7: ='Balance Sheet'!C30/'Balance Sheet'!C60 -> 0.56092156 | E7: ='Balance Sheet'!D30/'Balance Sheet'!D60 -> 0.43700307 | F7: ='Balance Sheet'!E30/'Balance Sheet'!E60 -> 0.51858905 | G7: ='Balance Sheet'!F30/'Balance Sheet'!F60 -> 0.4202569 | H7: ='Balance Sheet'!G30/'Balance Sheet'!G60 -> 0.37457728 | J7: Liquidity Ratio | K7: Current Ratio | L7: ='Balance Sheet'!J23/'Balance Sheet'!J48 -> 1.2940177 | M7: ='Balance Sheet'!K23/'Balance Sheet'!K48 -> 0.69027855 | N7: ='Balance Sheet'!L23/'Balance Sheet'!L48 -> 1.3947479 | O7: ='Balance Sheet'!M23/'Balance Sheet'!M48 -> 1.0667418 | P7: ='Balance Sheet'!N23/'Balance Sheet'!N48 -> 1.0328361 | Q7: ='Balance Sheet'!O23/'Balance Sheet'!O48 -> 1.3211469 | S7: Liquidity Ratio | T7: Current Ratio | U7: ='Balance Sheet'!R24/'Balance Sheet'!R47 -> 1.2612727 | V7: ='Balance Sheet'!S24/'Balance Sheet'!S47 -> 1.470822 | W7: ='Balance Sheet'!T24/'Balance Sheet'!T47 -> 1.3102338 | X7: ='Balance Sheet'!U24/'Balance Sheet'!U47 -> 1.3857145 | Y7: ='Balance Sheet'!V24/'Balance Sheet'!V47 -> 1.2055114 | Z7: ='Balance Sheet'!W24/'Balance Sheet'!W47 -> 1.2881238 | AB7: Liquidity Ratio | AC7: Current Ratio | AD7: ='Balance Sheet'!Z29/'Balance Sheet'!Z54 -> 0.52259325 | AE7: ='Balance Sheet'!AA29/'Balance Sheet'!AA54 -> 0.75157244 | AF7: ='Balance Sheet'!AB29/'Balance Sheet'!AB54 -> 0.57762806 | AG7: ='Balance Sheet'!AC29/'Balance Sheet'!AC54 -> 0.5938101 | AH7: ='Balance Sheet'!AD29/'Balance Sheet'!AD54 -> 0.4388182 | AI7: ='Balance Sheet'!AE29/'Balance Sheet'!AE54 -> 0.57891332 | AK7: Liquidity Ratio | AL7: Current Ratio | AM7: ='Balance Sheet'!AH26/'Balance Sheet'!AH53 -> 0.17429534 | AN7: ='Balance Sheet'!AI26/'Balance Sheet'!AI53 -> 0.21246576 | AO7: ='Balance Sheet'!AJ26/'Balance Sheet'!AJ53 -> 0.27427434 | AP7: ='Balance Sheet'!AK26/'Balance Sheet'!AK53 -> 0.23103659 | AQ7: ='Balance Sheet'!AL26/'Balance Sheet'!AL53 -> 0.24079518 | AR7: ='Balance Sheet'!AM26/'Balance Sheet'!AM53 -> 0.56073525 | AT7: Liquidity Ratio | AU7: Current Ratio | AV7: ='Balance Sheet'!AP20/'Balance Sheet'!AP46 -> 0.74031754 | AW7: ='Balance Sheet'!AQ20/'Balance Sheet'!AQ46 -> 0.74180003 | AX7: ='Balance Sheet'!AR20/'Balance Sheet'!AR46 -> 0.63830019 | AY7: ='Balance Sheet'!AS20/'Balance Sheet'!AS46 -> 0.46505639 | AZ7: ='Balance Sheet'!AT20/'Balance Sheet'!AT46 -> 0.50912364 | BA7: ='Balance Sheet'!AU20/'Balance Sheet'!AU46 -> 0.71693319
B8: Quick Ratio | C8: =('Balance Sheet'!B30-'Balance Sheet'!B21)/'Balance Sheet'!B60 -> 0.6305916 | D8: =('Balance Sheet'!C30-'Balance Sheet'!C21)/'Balance Sheet'!C60 -> 0.56091037 | E8: =('Balance Sheet'!D30-'Balance Sheet'!D21)/'Balance Sheet'!D60 -> 0.43699782 | F8: =('Balance Sheet'!E30-'Balance Sheet'!E21)/'Balance Sheet'!E60 -> 0.51858905 | G8: =('Balance Sheet'!F30-'Balance Sheet'!F21)/'Balance Sheet'!F60 -> 0.41763264 | H8: =('Balance Sheet'!G30-'Balance Sheet'!G21)/'Balance Sheet'!G60 -> 0.37207396 | K8: Quick Ratio | L8: =('Balance Sheet'!J23-'Balance Sheet'!J16)/'Balance Sheet'!J48 -> 1.2940177 | M8: =('Balance Sheet'!K23-'Balance Sheet'!K16)/'Balance Sheet'!K48 -> 0.69027855 | N8: =('Balance Sheet'!L23-'Balance Sheet'!L16)/'Balance Sheet'!L48 -> 1.3947479 | O8: =('Balance Sheet'!M23-'Balance Sheet'!M16)/'Balance Sheet'!M48 -> 1.0667418 | P8: =('Balance Sheet'!N23-'Balance Sheet'!N16)/'Balance Sheet'!N48 -> 1.0328361 | Q8: =('Balance Sheet'!O23-'Balance Sheet'!O16)/'Balance Sheet'!O48 -> 1.3203703 | T8: Quick Ratio | U8: =('Balance Sheet'!R24-'Balance Sheet'!R15)/'Balance Sheet'!R47 -> 1.2607186 | V8: =('Balance Sheet'!S24-'Balance Sheet'!S15)/'Balance Sheet'!S47 -> 1.4697415 | W8: =('Balance Sheet'!T24-'Balance Sheet'!T15)/'Balance Sheet'!T47 -> 1.3094415 | X8: =('Balance Sheet'!U24-'Balance Sheet'!U15)/'Balance Sheet'!U47 -> 1.3851062 | Y8: =('Balance Sheet'!V24-'Balance Sheet'!V15)/'Balance Sheet'!V47 -> 1.2040738 | Z8: =('Balance Sheet'!W24-'Balance Sheet'!W15)/'Balance Sheet'!W47 -> 1.2881204 | AC8: Quick Ratio | AD8: =('Balance Sheet'!Z29-'Balance Sheet'!Z21)/'Balance Sheet'!Z54 -> 0.51617573 | AE8: =('Balance Sheet'!AA29-'Balance Sheet'!AA21)/'Balance Sheet'!AA54 -> 0.74713805 | AF8: =('Balance Sheet'!AB29-'Balance Sheet'!AB21)/'Balance Sheet'!AB54 -> 0.57313493 | AG8: =('Balance Sheet'!AC29-'Balance Sheet'!AC21)/'Balance Sheet'!AC54 -> 0.57746011 | AH8: =('Balance Sheet'!AD29-'Balance Sheet'!AD21)/'Balance Sheet'!AD54 -> 0.4327073 | AI8: =('Balance Sheet'!AE29-'Balance Sheet'!AE21)/'Balance Sheet'!AE54 -> 0.56629006 | AL8: Quick Ratio | AM8: =('Balance Sheet'!AH26-'Balance Sheet'!AH16)/'Balance Sheet'!AH53 -> 0.17426923 | AN8: =('Balance Sheet'!AI26-'Balance Sheet'!AI16)/'Balance Sheet'!AI53 -> 0.21245672 | AO8: =('Balance Sheet'!AJ26-'Balance Sheet'!AJ16)/'Balance Sheet'!AJ53 -> 0.27423672 | AP8: =('Balance Sheet'!AK26-'Balance Sheet'!AK16)/'Balance Sheet'!AK53 -> 0.23076503 | AQ8: =('Balance Sheet'!AL26-'Balance Sheet'!AL16)/'Balance Sheet'!AL53 -> 0.24077279 | AR8: =('Balance Sheet'!AM26-'Balance Sheet'!AM16)/'Balance Sheet'!AM53 -> 0.56071538 | AU8: Quick Ratio | AV8: 0 | AW8: 0 | AX8: 0 | AY8: 0 | AZ8: 0 | BA8: 0
A9: Leverage Ratio | B9: Debt-to-Equity | C9: =('Balance Sheet'!B39+'Balance Sheet'!B48+'Balance Sheet'!B49)/'Balance Sheet'!B37 -> 0.81202652 | D9: =('Balance Sheet'!C39+'Balance Sheet'!C48+'Balance Sheet'!C49)/'Balance Sheet'!C37 -> 1.2203668 | E9: =('Balance Sheet'!D39+'Balance Sheet'!D48+'Balance Sheet'!D49)/'Balance Sheet'!D37 -> 1.4374674 | F9: =('Balance Sheet'!E39+'Balance Sheet'!E48+'Balance Sheet'!E49)/'Balance Sheet'!E37 -> 1.7804146 | G9: =('Balance Sheet'!F39+'Balance Sheet'!F48+'Balance Sheet'!F49)/'Balance Sheet'!F37 -> 1.4390952 | H9: =('Balance Sheet'!G39+'Balance Sheet'!G48+'Balance Sheet'!G49)/'Balance Sheet'!G37 -> 0.96640726 | J9: Leverage Ratio | K9: Debt-to-Equity | L9: =('Balance Sheet'!J31+'Balance Sheet'!J39)/'Balance Sheet'!J29 -> 0.17858119 | M9: =('Balance Sheet'!K31+'Balance Sheet'!K39)/'Balance Sheet'!K29 -> 0.43901871 | N9: =('Balance Sheet'!L31+'Balance Sheet'!L39)/'Balance Sheet'!L29 -> 0.24770547 | O9: =('Balance Sheet'!M31+'Balance Sheet'!M39)/'Balance Sheet'!M29 -> 0.22324546 | P9: =('Balance Sheet'!N31+'Balance Sheet'!N39)/'Balance Sheet'!N29 -> 0.15946714 | Q9: =('Balance Sheet'!O31+'Balance Sheet'!O39)/'Balance Sheet'!O29 -> 0.069615949 | S9: Leverage Ratio | T9: Debt-to-Equity | U9: =('Balance Sheet'!R33+'Balance Sheet'!R40)/'Balance Sheet'!R30 -> 0.031066288 | V9: =('Balance Sheet'!S33+'Balance Sheet'!S40)/'Balance Sheet'!S30 -> 0.021361532 | W9: =('Balance Sheet'!T33+'Balance Sheet'!T40)/'Balance Sheet'!T30 -> 0.020639152 | X9: =('Balance Sheet'!U33+'Balance Sheet'!U40)/'Balance Sheet'!U30 -> 0.025344476 | Y9: =('Balance Sheet'!V33+'Balance Sheet'!V40)/'Balance Sheet'!V30 -> 0.024966616 | Z9: =('Balance Sheet'!W33+'Balance Sheet'!W40)/'Balance Sheet'!W30 -> 0.022274232 | AB9: Leverage Ratio | AC9: Debt-to-Equity | AD9: =('Balance Sheet'!Z38+'Balance Sheet'!Z46+'Balance Sheet'!Z40+'Balance Sheet'!Z49)/'Balance Sheet'!Z36 -> -8.4632187 | AE9: =('Balance Sheet'!AA38+'Balance Sheet'!AA46+'Balance Sheet'!AA40+'Balance Sheet'!AA49)/'Balance Sheet'!AA36 -> 78.230732 | AF9: =('Balance Sheet'!AB38+'Balance Sheet'!AB46+'Balance Sheet'!AB40+'Balance Sheet'!AB49)/'Balance Sheet'!AB36 -> 9.5405615 | AG9: =('Balance Sheet'!AC38+'Balance Sheet'!AC46+'Balance Sheet'!AC40+'Balance Sheet'!AC49)/'Balance Sheet'!AC36 -> 5.5383185 | AH9: =('Balance Sheet'!AD38+'Balance Sheet'!AD46+'Balance Sheet'!AD40+'Balance Sheet'!AD49)/'Balance Sheet'!AD36 -> 6.2912193 | AI9: =('Balance Sheet'!AE38+'Balance Sheet'!AE46+'Balance Sheet'!AE40+'Balance Sheet'!AE49)/'Balance Sheet'!AE36 -> 4.086037 | AK9: Leverage Ratio | AL9: Debt-to-Equity | AM9: =('Balance Sheet'!AH37+'Balance Sheet'!AH46+'Balance Sheet'!AH39+'Balance Sheet'!AH47)/'Balance Sheet'!AH33 -> 16.106055 | AN9: =('Balance Sheet'!AI37+'Balance Sheet'!AI46+'Balance Sheet'!AI39+'Balance Sheet'!AI47)/'Balance Sheet'!AI33 -> -4.1178063 | AO9: =('Balance Sheet'!AJ37+'Balance Sheet'!AJ46+'Balance Sheet'!AJ39+'Balance Sheet'!AJ47)/'Balance Sheet'!AJ33 -> -3.4497182 | AP9: =('Balance Sheet'!AK37+'Balance Sheet'!AK46+'Balance Sheet'!AK39+'Balance Sheet'!AK47)/'Balance Sheet'!AK33 -> -3.1975374 | AQ9: =('Balance Sheet'!AL37+'Balance Sheet'!AL46+'Balance Sheet'!AL39+'Balance Sheet'!AL47)/'Balance Sheet'!AL33 -> -2.3405634 | AR9: =('Balance Sheet'!AM37+'Balance Sheet'!AM46+'Balance Sheet'!AM39+'Balance Sheet'!AM47)/'Balance Sheet'!AM33 -> -3.3166672 | AT9: Leverage Ratio | AU9: Debt-to-Equity | AV9: =('Balance Sheet'!AP28+'Balance Sheet'!AP29+'Balance Sheet'!AP37+'Balance Sheet'!AP38)/'Balance Sheet'!AP26 -> 0.13595311 | AW9: =('Balance Sheet'!AQ28+'Balance Sheet'!AQ29+'Balance Sheet'!AQ37+'Balance Sheet'!AQ38)/'Balance Sheet'!AQ26 -> 0.060877834 | AX9: =('Balance Sheet'!AR28+'Balance Sheet'!AR29+'Balance Sheet'!AR37+'Balance Sheet'!AR38)/'Balance Sheet'!AR26 -> 0.26492132 | AY9: =('Balance Sheet'!AS28+'Balance Sheet'!AS29+'Balance Sheet'!AS37+'Balance Sheet'!AS38)/'Balance Sheet'!AS26 -> 0.22809546 | AZ9: =('Balance Sheet'!AT28+'Balance Sheet'!AT29+'Balance Sheet'!AT37+'Balance Sheet'!AT38)/'Balance Sheet'!AT26 -> 0.27648719 | BA9: =('Balance Sheet'!AU28+'Balance Sheet'!AU29+'Balance Sheet'!AU37+'Balance Sheet'!AU38)/'Balance Sheet'!AU26 -> 0.31766376
B10: Net Debt to EBITDA | C10: =('Balance Sheet'!B39+'Balance Sheet'!B40+'Balance Sheet'!B48+'Balance Sheet'!B49+'Balance Sheet'!B50-'Balance Sheet'!B25)/'Income Statement'!B15 -> 5.1587944 | D10: =('Balance Sheet'!C39+'Balance Sheet'!C40+'Balance Sheet'!C48+'Balance Sheet'!C49+'Balance Sheet'!C50-'Balance Sheet'!C25)/'Income Statement'!C15 -> 4.2609838 | E10: =('Balance Sheet'!D39+'Balance Sheet'!D40+'Balance Sheet'!D48+'Balance Sheet'!D49+'Balance Sheet'!D50-'Balance Sheet'!D25)/'Income Statement'!D15 -> 3.6707728 | F10: =('Balance Sheet'!E39+'Balance Sheet'!E40+'Balance Sheet'!E48+'Balance Sheet'!E49+'Balance Sheet'!E50-'Balance Sheet'!E25)/'Income Statement'!E15 -> 3.8831379 | G10: =('Balance Sheet'!F39+'Balance Sheet'!F40+'Balance Sheet'!F48+'Balance Sheet'!F49+'Balance Sheet'!F50-'Balance Sheet'!F25)/'Income Statement'!F15 -> 2.6173853 | H10: =('Balance Sheet'!G39+'Balance Sheet'!G40+'Balance Sheet'!G48+'Balance Sheet'!G49+'Balance Sheet'!G50-'Balance Sheet'!G25)/'Income Statement'!G15 -> 2.1907542 | K10: Net Debt to EBITDA | L10: =('Balance Sheet'!J31+'Balance Sheet'!J32+'Balance Sheet'!J39+'Balance Sheet'!J43-'Balance Sheet'!J19)/'Income Statement'!J14 -> 1.1963804 | M10: =('Balance Sheet'!K31+'Balance Sheet'!K32+'Balance Sheet'!K39+'Balance Sheet'!K43-'Balance Sheet'!K19)/'Income Statement'!K14 -> 2.7314263 | N10: =('Balance Sheet'!L31+'Balance Sheet'!L32+'Balance Sheet'!L39+'Balance Sheet'!L43-'Balance Sheet'!L19)/'Income Statement'!L14 -> 1.2255842 | O10: =('Balance Sheet'!M31+'Balance Sheet'!M32+'Balance Sheet'!M39+'Balance Sheet'!M43-'Balance Sheet'!M19)/'Income Statement'!M14 -> 1.8919759 | P10: =('Balance Sheet'!N31+'Balance Sheet'!N32+'Balance Sheet'!N39+'Balance Sheet'!N43-'Balance Sheet'!N19)/'Income Statement'!N14 -> 1.3595417 | Q10: =('Balance Sheet'!O31+'Balance Sheet'!O32+'Balance Sheet'!O39+'Balance Sheet'!O43-'Balance Sheet'!O19)/'Income Statement'!O14 -> 0.99129799 | T10: Net Debt to EBITDA | U10: =('Balance Sheet'!R33+'Balance Sheet'!R40-'Balance Sheet'!R18)/('Income Statement'!R18+'Income Statement'!R15+'Income Statement'!R16) -> -0.24756419 | V10: =('Balance Sheet'!S33+'Balance Sheet'!S40-'Balance Sheet'!S18)/('Income Statement'!S18+'Income Statement'!S15+'Income Statement'!S16) -> -0.61235301 | W10: =('Balance Sheet'!T33+'Balance Sheet'!T40-'Balance Sheet'!T18)/('Income Statement'!T18+'Income Statement'!T15+'Income Statement'!T16) -> -0.39274086 | X10: =('Balance Sheet'!U33+'Balance Sheet'!U40-'Balance Sheet'!U18)/('Income Statement'!U18+'Income Statement'!U15+'Income Statement'!U16) -> -0.35040871 | Y10: =('Balance Sheet'!V33+'Balance Sheet'!V40-'Balance Sheet'!V18)/('Income Statement'!V18+'Income Statement'!V15+'Income Statement'!V16) -> -0.38985373 | Z10: =('Balance Sheet'!W33+'Balance Sheet'!W40-'Balance Sheet'!W18)/('Income Statement'!W18+'Income Statement'!W15+'Income Statement'!W16) -> -0.43409499 | AC10: Net Debt to EBITDA | AD10: =('Balance Sheet'!Z38+'Balance Sheet'!Z40+'Balance Sheet'!Z46+'Balance Sheet'!Z49-'Balance Sheet'!Z24)/('Income Statement'!Z14+'Income Statement'!Z11+Table14[[#This Row],[2020]]) -> 2.9562173 | AE10: =('Balance Sheet'!AA38+'Balance Sheet'!AA40+'Balance Sheet'!AA46+'Balance Sheet'!AA49-'Balance Sheet'!AA24)/('Income Statement'!AA14+'Income Statement'!AA11+Table14[[#This Row],[2021]]) -> 2.3585302 | AF10: =('Balance Sheet'!AB38+'Balance Sheet'!AB40+'Balance Sheet'!AB46+'Balance Sheet'!AB49-'Balance Sheet'!AB24)/('Income Statement'!AB14+'Income Statement'!AB11+Table14[[#This Row],[2022]]) -> 1.8479998 | AG10: =('Balance Sheet'!AC38+'Balance Sheet'!AC40+'Balance Sheet'!AC46+'Balance Sheet'!AC49-'Balance Sheet'!AC24)/('Income Statement'!AC14+'Income Statement'!AC11+Table14[[#This Row],[2023]]) -> 1.6175059 | AH10: =('Balance Sheet'!AD38+'Balance Sheet'!AD40+'Balance Sheet'!AD46+'Balance Sheet'!AD49-'Balance Sheet'!AD24)/('Income Statement'!AD14+'Income Statement'!AD11+Table14[[#This Row],[2024]]) -> 2.2987087 | AI10: =('Balance Sheet'!AE38+'Balance Sheet'!AE40+'Balance Sheet'!AE46+'Balance Sheet'!AE49-'Balance Sheet'!AE24)/('Income Statement'!AE14+'Income Statement'!AE11+Table14[[#This Row],[2025]]) -> 2.5159799 | AL10: Net Debt to EBITDA | AM10: =('Balance Sheet'!AH37+'Balance Sheet'!AH39+'Balance Sheet'!AH46+'Balance Sheet'!AH47-'Balance Sheet'!AH19)/('Income Statement'!AH19) -> 6.0144811 | AN10: =('Balance Sheet'!AI37+'Balance Sheet'!AI39+'Balance Sheet'!AI46+'Balance Sheet'!AI47-'Balance Sheet'!AI19)/('Income Statement'!AI19) -> 9.1744227 | AO10: =('Balance Sheet'!AJ37+'Balance Sheet'!AJ39+'Balance Sheet'!AJ46+'Balance Sheet'!AJ47-'Balance Sheet'!AJ19)/('Income Statement'!AJ19) -> 13.133395 | AP10: =('Balance Sheet'!AK37+'Balance Sheet'!AK39+'Balance Sheet'!AK46+'Balance Sheet'!AK47-'Balance Sheet'!AK19)/('Income Statement'!AK19) -> 13.868113 | AQ10: =('Balance Sheet'!AL37+'Balance Sheet'!AL39+'Balance Sheet'!AL46+'Balance Sheet'!AL47-'Balance Sheet'!AL19)/('Income Statement'!AL19) -> 14.132976 | AR10: =('Balance Sheet'!AM37+'Balance Sheet'!AM39+'Balance Sheet'!AM46+'Balance Sheet'!AM47-'Balance Sheet'!AM19)/('Income Statement'!AM19) -> 12.167414 | AU10: Net Debt to EBITDA | AV10: =('Balance Sheet'!AP28+'Balance Sheet'!AP29+'Balance Sheet'!AP37+'Balance Sheet'!AP38-'Balance Sheet'!AP16)/('Income Statement'!AP17+'Income Statement'!AP12+'Income Statement'!AP13) -> 0.74702134 | AW10: =('Balance Sheet'!AQ28+'Balance Sheet'!AQ29+'Balance Sheet'!AQ37+'Balance Sheet'!AQ38-'Balance Sheet'!AQ16)/('Income Statement'!AQ17+'Income Statement'!AQ12+'Income Statement'!AQ13) -> 0.34839961 | AX10: =('Balance Sheet'!AR28+'Balance Sheet'!AR29+'Balance Sheet'!AR37+'Balance Sheet'!AR38-'Balance Sheet'!AR16)/('Income Statement'!AR17+'Income Statement'!AR12+'Income Statement'!AR13) -> 1.3675512 | AY10: =('Balance Sheet'!AS28+'Balance Sheet'!AS29+'Balance Sheet'!AS37+'Balance Sheet'!AS38-'Balance Sheet'!AS16)/('Income Statement'!AS17+'Income Statement'!AS12+'Income Statement'!AS13) -> 1.0260446 | AZ10: =('Balance Sheet'!AT28+'Balance Sheet'!AT29+'Balance Sheet'!AT37+'Balance Sheet'!AT38-'Balance Sheet'!AT16)/('Income Statement'!AT17+'Income Statement'!AT12+'Income Statement'!AT13) -> 1.217633 | BA10: =('Balance Sheet'!AU28+'Balance Sheet'!AU29+'Balance Sheet'!AU37+'Balance Sheet'!AU38-'Balance Sheet'!AU16)/('Income Statement'!AU17+'Income Statement'!AU12+'Income Statement'!AU13) -> 1.2591413
A11: Efficiency Ratio | B11: Asset Turnover | C11: ='Income Statement'!B6/'Balance Sheet'!B31 -> 0.18829801 | D11: ='Income Statement'!C6/AVERAGE('Balance Sheet'!B31:C31) -> 0.23079572 | E11: ='Income Statement'!D6/AVERAGE('Balance Sheet'!C31:D31) -> 0.26011138 | F11: ='Income Statement'!E6/AVERAGE('Balance Sheet'!D31:E31) -> 0.28790807 | G11: ='Income Statement'!F6/AVERAGE('Balance Sheet'!E31:F31) -> 0.38819692 | H11: ='Income Statement'!G6/AVERAGE('Balance Sheet'!F31:G31) -> 0.36408482 | J11: Efficiency Ratio | K11: Asset Turnover | L11: ='Income Statement'!J6/'Balance Sheet'!J24 -> 0.34786548 | M11: ='Income Statement'!K6/AVERAGE('Balance Sheet'!J24:K24) -> 0.43745672 | N11: ='Income Statement'!L6/AVERAGE('Balance Sheet'!K24:L24) -> 0.60422575 | O11: ='Income Statement'!M6/AVERAGE('Balance Sheet'!L24:M24) -> 0.6080622 | P11: ='Income Statement'!N6/AVERAGE('Balance Sheet'!M24:N24) -> 0.56543733 | Q11: ='Income Statement'!O6/AVERAGE('Balance Sheet'!N24:O24) -> 0.5119147 | S11: Efficiency Ratio | T11: Asset Turnover | U11: ='Income Statement'!R7/'Balance Sheet'!Z30 -> 0.052604362 | V11: ='Income Statement'!R7/AVERAGE('Balance Sheet'!Z30:AA30) -> 0.05360585 | W11: ='Income Statement'!S7/AVERAGE('Balance Sheet'!AA30:AB30) -> 0.068841181 | X11: ='Income Statement'!T7/AVERAGE('Balance Sheet'!AB30:AC30) -> 0.078453944 | Y11: ='Income Statement'!U7/AVERAGE('Balance Sheet'!AC30:AD30) -> 0.088761882 | Z11: ='Income Statement'!V7/AVERAGE('Balance Sheet'!AD30:AE30) -> 0.10253702 | AB11: Efficiency Ratio | AC11: Asset Turnover | AD11: ='Income Statement'!Z6/'Balance Sheet'!Z30 -> 0.77330926 | AE11: ='Income Statement'!AA6/AVERAGE('Balance Sheet'!Z30:AA30) -> 0.79351225 | AF11: ='Income Statement'!AB6/AVERAGE('Balance Sheet'!AA30:AB30) -> 0.83201301 | AG11: ='Income Statement'!AC6/AVERAGE('Balance Sheet'!AB30:AC30) -> 0.90508034 | AH11: ='Income Statement'!AD6/AVERAGE('Balance Sheet'!AC30:AD30) -> 0.9331391 | AI11: ='Income Statement'!AE6/AVERAGE('Balance Sheet'!AD30:AE30) -> 0.90873076 | AK11: Efficiency Ratio | AL11: Asset Turnover | AM11: ='Income Statement'!AH8/'Balance Sheet'!AH27 -> 0.20270087 | AN11: ='Income Statement'!AI8/AVERAGE('Balance Sheet'!AH27:AI27) -> 0.19575456 | AO11: ='Income Statement'!AJ8/AVERAGE('Balance Sheet'!AI27:AJ27) -> 0.19446829 | AP11: ='Income Statement'!AK8/AVERAGE('Balance Sheet'!AJ27:AK27) -> 0.21182382 | AQ11: ='Income Statement'!AL8/AVERAGE('Balance Sheet'!AK27:AL27) -> 0.21807425 | AR11: ='Income Statement'!AM8/AVERAGE('Balance Sheet'!AL27:AM27) -> 0.23293841 | AT11: Efficiency Ratio | AU11: Asset Turnover | AV11: ='Income Statement'!AP6/'Balance Sheet'!AP21 -> 0.22508016 | AW11: ='Income Statement'!AQ6/AVERAGE('Balance Sheet'!AP21:AQ21) -> 0.28644514 | AX11: ='Income Statement'!AR6/AVERAGE('Balance Sheet'!AQ21:AR21) -> 0.27231789 | AY11: ='Income Statement'!AS6/AVERAGE('Balance Sheet'!AR21:AS21) -> 0.23903211 | AZ11: ='Income Statement'!AT6/AVERAGE('Balance Sheet'!AS21:AT21) -> 0.21507218 | BA11: ='Income Statement'!AU6/AVERAGE('Balance Sheet'!AT21:AU21) -> 0.227562
B12: Return on Capital Employed | C12: =('Income Statement'!B19+'Income Statement'!B16)/('Balance Sheet'!B31-'Balance Sheet'!B60) -> 0.052678682 | D12: =('Income Statement'!C19+'Income Statement'!C16)/('Balance Sheet'!C31-'Balance Sheet'!C60) -> 0.08993993 | E12: =('Income Statement'!D19+'Income Statement'!D16)/('Balance Sheet'!D31-'Balance Sheet'!D60) -> 0.11321485 | F12: =('Income Statement'!E19+'Income Statement'!E16)/('Balance Sheet'!E31-'Balance Sheet'!E60) -> 0.123967 | G12: =('Income Statement'!F19+'Income Statement'!F16)/('Balance Sheet'!F31-'Balance Sheet'!F60) -> 0.19547595 | H12: =('Income Statement'!G19+'Income Statement'!G16)/('Balance Sheet'!G31-'Balance Sheet'!G60) -> 0.22964169 | K12: Return on Capital Employed | L12: =('Income Statement'!J20+'Income Statement'!J15)/('Balance Sheet'!J24-'Balance Sheet'!J48) -> 0.23410307 | M12: =('Income Statement'!K20+'Income Statement'!K15)/('Balance Sheet'!K24-'Balance Sheet'!K48) -> 0.2220462 | N12: =('Income Statement'!L20+'Income Statement'!L15)/('Balance Sheet'!L24-'Balance Sheet'!L48) -> 0.35392571 | O12: =('Income Statement'!M20+'Income Statement'!M15)/('Balance Sheet'!M24-'Balance Sheet'!M48) -> 0.22632623 | P12: =('Income Statement'!N20+'Income Statement'!N15)/('Balance Sheet'!N24-'Balance Sheet'!N48) -> 0.31244927 | Q12: =('Income Statement'!O20+'Income Statement'!O15)/('Balance Sheet'!O24-'Balance Sheet'!O48) -> 0.36797207 | T12: Return on Capital Employed | U12: =('Income Statement'!R18+'Income Statement'!R16)/('Balance Sheet'!R25-'Balance Sheet'!R47) -> 0.15898656 | V12: =('Income Statement'!S18+'Income Statement'!S16)/('Balance Sheet'!S25-'Balance Sheet'!S47) -> 0.12655967 | W12: =('Income Statement'!T18+'Income Statement'!T16)/('Balance Sheet'!T25-'Balance Sheet'!T47) -> 0.14117879 | X12: =('Income Statement'!U18+'Income Statement'!U16)/('Balance Sheet'!U25-'Balance Sheet'!U47) -> 0.14389883 | Y12: =('Income Statement'!V18+'Income Statement'!V16)/('Balance Sheet'!V25-'Balance Sheet'!V47) -> 0.18434037 | Z12: =('Income Statement'!W18+'Income Statement'!W16)/('Balance Sheet'!W25-'Balance Sheet'!W47) -> 0.19201876 | AC12: Return on Capital Employed | AD12: =('Income Statement'!Z14+'Income Statement'!Z10)/('Balance Sheet'!Z30-'Balance Sheet'!Z54) -> 0.092753803 | AE12: =('Income Statement'!AA14+'Income Statement'!AA10)/('Balance Sheet'!AA30-'Balance Sheet'!AA54) -> 0.15504495 | AF12: =('Income Statement'!AB14+'Income Statement'!AB10)/('Balance Sheet'!AB30-'Balance Sheet'!AB54) -> 0.20950551 | AG12: =('Income Statement'!AC14+'Income Statement'!AC10)/('Balance Sheet'!AC30-'Balance Sheet'!AC54) -> 0.22472759 | AH12: =('Income Statement'!AD14+'Income Statement'!AD10)/('Balance Sheet'!AD30-'Balance Sheet'!AD54) -> 0.2005355 | AI12: =('Income Statement'!AE14+'Income Statement'!AE10)/('Balance Sheet'!AE30-'Balance Sheet'!AE54) -> 0.14965516 | AL12: Return on Capital Employed | AM12: =('Income Statement'!AH19+'Income Statement'!AH21)/('Balance Sheet'!AH27-'Balance Sheet'!AH53) -> 0.23752569 | AN12: =('Income Statement'!AI19+'Income Statement'!AI21)/('Balance Sheet'!AI27-'Balance Sheet'!AI53) -> 0.23061083 | AO12: =('Income Statement'!AJ19+'Income Statement'!AJ21)/('Balance Sheet'!AJ27-'Balance Sheet'!AJ53) -> 0.23204893 | AP12: =('Income Statement'!AK19+'Income Statement'!AK21)/('Balance Sheet'!AK27-'Balance Sheet'!AK53) -> 0.21324726 | AQ12: =('Income Statement'!AL19+'Income Statement'!AL21)/('Balance Sheet'!AL27-'Balance Sheet'!AL53) -> 0.23679125 | AR12: =('Income Statement'!AM19+'Income Statement'!AM21)/('Balance Sheet'!AM27-'Balance Sheet'!AM53) -> 0.22833861 | AU12: Return on Capital Employed | AV12: =('Income Statement'!AP17+Table18[[#This Row],[2020]])/('Balance Sheet'!AP21-'Balance Sheet'!AP46) -> 0.070137984 | AW12: =('Income Statement'!AQ17+Table18[[#This Row],[2021]])/('Balance Sheet'!AQ21-'Balance Sheet'!AQ46) -> 0.090641134 | AX12: =('Income Statement'!AR17+Table18[[#This Row],[2022]])/('Balance Sheet'!AR21-'Balance Sheet'!AR46) -> 0.08897412 | AY12: =('Income Statement'!AS17+Table18[[#This Row],[2023]])/('Balance Sheet'!AS21-'Balance Sheet'!AS46) -> 0.074880775 | AZ12: =('Income Statement'!AT17+Table18[[#This Row],[2024]])/('Balance Sheet'!AT21-'Balance Sheet'!AT46) -> 0.074534397 | BA12: =('Income Statement'!AU17+Table18[[#This Row],[2025]])/('Balance Sheet'!AU21-'Balance Sheet'!AU46) -> 0.083920162
A13: Valuation Ratios | B13: Price to Earnings | C13: {=C18/Table8[2020]} -> -5.8545301 | D13: {=D18/Table8[2021]} -> -11.069727 | E13: {=E18/Table8[2022]} -> -106.90086 | F13: {=F18/Table8[2023]} -> -4634 | G13: {=G18/Table8[2024]} -> 93.337662 | H13: {=H18/Table8[2025]} -> 29.886207 | J13: Valuation Ratios | K13: Price to Earnings | L13: =L18/'Income Statement'!J26 -> 0.070073059 | M13: =M18/'Income Statement'!K26 -> 0.067597248 | N13: =N18/'Income Statement'!L26 -> 0.03473192 | O13: =O18/'Income Statement'!M26 -> 0.070098039 | P13: =P18/'Income Statement'!N26 -> 0.052019482 | Q13: =Q18/'Income Statement'!O26 -> 0.036297915 | S13: Valuation Ratios | T13: Price to Earnings | U13: =U18/'Income Statement'!R25 -> 0 | V13: =V18/'Income Statement'!S25 -> 0.9041769 | W13: =W18/'Income Statement'!T25 -> 0.79087732 | X13: =X18/'Income Statement'!U25 -> 0.53472259 | Y13: =Y18/'Income Statement'!V25 -> 1.6065554 | Z13: =Z18/'Income Statement'!W25 -> 0.99246189 | AB13: Valuation Ratios | AC13: Price to Earnings | AD13: =AD18/'Income Statement'!Z23 -> -2.9535542 | AE13: =AE18/'Income Statement'!AA23 -> 0.89127621 | AF13: =AF18/'Income Statement'!AB23 -> 0.90882149 | AG13: =AG18/'Income Statement'!AC23 -> 0.70302132 | AH13: =AH18/'Income Statement'!AD23 -> 1.8331837 | AI13: =AI18/'Income Statement'!AE23 -> 0.98299799 | AK13: Valuation Ratios | AL13: Price to Earnings | AM13: =AM18/'Income Statement'!AH32 -> -4.2637805e-05 | AN13: =AN18/'Income Statement'!AI32 -> -0.00022607504 | AO13: =AO18/'Income Statement'!AJ32 -> -0.00039652474 | AP13: =AP18/'Income Statement'!AK32 -> -0.00019794479 | AQ13: =AQ18/'Income Statement'!AL32 -> -0.00042575804 | AR13: =AR18/'Income Statement'!AM32 -> -0.00026695005 | AT13: Valuation Ratios | AU13: Price to Earnings | AV13: NA | AW13: NA | AX13: NA | AY13: NA | AZ13: NA | BA13: NA
A14: Key Performing Ratios | B14: Average Revenue Per user | C14: ='Income Statement'!B6/'Income Statement'!B32 -> 1336.1998 | D14: ='Income Statement'!C6/'Income Statement'!C32 -> 1415.3411 | E14: ='Income Statement'!D6/'Income Statement'!D32 -> 1457.9288 | F14: ='Income Statement'!E6/'Income Statement'!E32 -> 1684.918 | G14: ='Income Statement'!F6/'Income Statement'!F32 -> 2694.4107 | H14: ='Income Statement'!G6/'Income Statement'!G32 -> 2956.0502 | J14: Key Performing Ratios | K14: Average Revenue Per towers | L14: ='Income Statement'!J6/'Income Statement'!J32 -> 720515.46 | M14: ='Income Statement'!K6/'Income Statement'!K32 -> 789577.35 | N14: ='Income Statement'!L6/'Income Statement'!L32 -> 1489527.6 | O14: ='Income Statement'!M6/'Income Statement'!M32 -> 1490252.7 | P14: ='Income Statement'!N6/'Income Statement'!N32 -> 1318022.5 | Q14: ='Income Statement'!O6/'Income Statement'!O32 -> 1171869.2 | S14: Key Performing Ratios | T14: Average Revenue Per user | U14: ='Income Statement'!R7/'Income Statement'!R32 -> 38859.667 | V14: ='Income Statement'!S7/'Income Statement'!S32 -> 35282.25 | W14: ='Income Statement'!T7/'Income Statement'!T32 -> 33426.483 | X14: ='Income Statement'!U7/'Income Statement'!U32 -> 38802.326 | Y14: ='Income Statement'!V7/'Income Statement'!V32 -> 46164.965 | Z14: ='Income Statement'!W7/'Income Statement'!W32 -> 61757.217 | AK14: Key Performing Ratios | AL14: Average Revenue Per user | AM14: ='Income Statement'!AH8/'Income Statement'!AH38 -> 1566.1151 | AN14: ='Income Statement'!AI8/'Income Statement'!AI38 -> 1704.1424 | AO14: ='Income Statement'!AJ8/'Income Statement'!AJ38 -> 1585.1066 | AP14: ='Income Statement'!AK8/'Income Statement'!AK38 -> 1905.3139 | AQ14: ='Income Statement'!AL8/'Income Statement'!AL38 -> 2011.5193 | AR14: ='Income Statement'!AM8/'Income Statement'!AM38 -> 2249.8436 | AT14: Key Performing Ratios | AU14: Average Revenue Per user | AV14: ='Income Statement'!AP6/'Income Statement'!AP29 -> 1403.9484 | AW14: ='Income Statement'!AQ6/'Income Statement'!AQ29 -> 1665.5474 | AX14: ='Income Statement'!AR6/'Income Statement'!AR29 -> 1895.646 | AY14: ='Income Statement'!AS6/'Income Statement'!AS29 -> 2091.8688 | AZ14: ='Income Statement'!AT6/'Income Statement'!AT29 -> 2087.5259 | BA14: ='Income Statement'!AU6/'Income Statement'!AU29 -> 2414.8726
B15: Subscriber Growth Rate | C15: =('Income Statement'!B32-'Income Statement'!B34)/'Income Statement'!B34 -> 0.29326917 | D15: =('Income Statement'!C32-'Income Statement'!B32)/'Income Statement'!B32 -> 0.11357542 | E15: =('Income Statement'!D32-'Income Statement'!C32)/'Income Statement'!C32 -> 0.038965805 | F15: =('Income Statement'!E32-'Income Statement'!D32)/'Income Statement'!D32 -> 0.058638553 | G15: =('Income Statement'!F32-'Income Statement'!E32)/'Income Statement'!E32 -> 0.083950884 | H15: =('Income Statement'!G32-'Income Statement'!F32)/'Income Statement'!F32 -> 0.050792747 | K15: Subscriber Growth Rate | L15: =('Income Statement'!J32-'Income Statement'!J35)/'Income Statement'!J35 -> -0.22804461 | M15: =('Income Statement'!K32-'Income Statement'!J32)/'Income Statement'!J32 -> 0.87922032 | N15: =('Income Statement'!L32-'Income Statement'!K32)/'Income Statement'!K32 -> 0.051454875 | O15: =('Income Statement'!M32-'Income Statement'!L32)/'Income Statement'!L32 -> 0.023492016 | P15: =('Income Statement'!N32-'Income Statement'!M32)/'Income Statement'!M32 -> 0.13927227 | Q15: =('Income Statement'!O32-'Income Statement'!N32)/'Income Statement'!N32 -> 0.18323807 | T15: Subscriber Growth Rate | U15: =('Income Statement'!R32-'Income Statement'!R35)/'Income Statement'!R35 -> 1.1126761 | V15: =('Income Statement'!S32-'Income Statement'!R32)/'Income Statement'!R32 -> 0.33333333 | W15: =('Income Statement'!T32-'Income Statement'!S32)/'Income Statement'!S32 -> 0.18 | X15: =('Income Statement'!U32-'Income Statement'!T32)/'Income Statement'!T32 -> 0.093220339 | Y15: =('Income Statement'!V32-'Income Statement'!U32)/'Income Statement'!U32 -> 0.10077519 | Z15: =('Income Statement'!W32-'Income Statement'!V32)/'Income Statement'!V32 -> 0.012323944 | AL15: Subscriber Growth Rate | AM15: =('Income Statement'!AH38-'Income Statement'!AH40)/'Income Statement'!AH40 -> -0.25607903 | AN15: =('Income Statement'!AI38-'Income Statement'!AH38)/'Income Statement'!AH38 -> -0.15832482 | AO15: =('Income Statement'!AJ38-'Income Statement'!AI38)/'Income Statement'!AI38 -> -0.013754045 | AP15: =('Income Statement'!AK38-'Income Statement'!AJ38)/'Income Statement'!AJ38 -> -0.085315833 | AQ15: =('Income Statement'!AL38-'Income Statement'!AK38)/'Income Statement'!AK38 -> -0.046636771 | AR15: =('Income Statement'!AM38-'Income Statement'!AL38)/'Income Statement'!AL38 -> -0.067732832 | AU15: Subscriber Growth Rate | AV15: =('Income Statement'!AP29-'Income Statement'!AP31)/'Income Statement'!AP31 -> 0.26344963 | AW15: =('Income Statement'!AQ29-'Income Statement'!AP29)/'Income Statement'!AP29 -> 0.091354839 | AX15: =('Income Statement'!AR29-'Income Statement'!AQ29)/'Income Statement'!AQ29 -> -0.032206195 | AY15: =('Income Statement'!AS29-'Income Statement'!AR29)/'Income Statement'!AR29 -> 0.071540266 | AZ15: =('Income Statement'!AT29-'Income Statement'!AS29)/'Income Statement'!AS29 -> 0.098595403 | BA15: =('Income Statement'!AU29-'Income Statement'!AT29)/'Income Statement'!AT29 -> -0.010834371
A17: Year | C17: 2020 | D17: 2021 | E17: 2022 | F17: 2023 | G17: 2024 | H17: 2025 | J17: Year | L17: 2020 | M17: 2021 | N17: 2022 | O17: 2023 | P17: 2024 | Q17: 2025 | S17: Year | U17: 2020 | V17: 2021 | W17: 2022 | X17: 2023 | Y17: 2024 | Z17: 2025 | AB17: Year | AD17: 2020 | AE17: 2021 | AF17: 2022 | AG17: 2023 | AH17: 2024 | AI17: 2025 | AK17: Year | AM17: 2020 | AN17: 2021 | AO17: 2022 | AP17: 2023 | AQ17: 2024 | AR17: 2025 | AT17: Year | AV17: 2020 | AW17: 2021 | AX17: 2022 | AY17: 2023 | AZ17: 2024 | BA17: 2025
A18: Current Market Price | C18: 416.14 | D18: 511.2 | E18: 744.03 | F18: 741.44 | G18: 1221.79 | H18: 1733.4 | J18: Current Market Price | L18: 231.15 | M18: 255.45 | N18: 221.35 | O18: 143 | P18: 314 | Q18: 360.5 | S18: Current Market Price | U18: 0 | V18: 128.8 | W18: 86 | X18: 101.1 | Y18: 395.55 | Z18: 297.55 | AB18: Current Market Price | AD18: 250.55 | AE18: 1115.45 | AF18: 1349.3 | AG18: 1266.05 | AH18: 2061.8 | AI18: 1598.05 | AK18: Current Market Price | AM18: 3.15 | AN18: 10 | AO18: 11.2 | AP18: 5.8 | AQ18: 13.3 | AR18: 7.31 | AT18: Current Market Price | AV18: NA | AW18: NA | AX18: NA | AY18: NA | AZ18: NA | BA18: NA
A19: Market Cap | C19: =C18*('Company Profile'!$B$8/10000000) -> 253474.2 | D19: =D18*('Company Profile'!$B$8/10000000) -> 311376.01 | E19: =E18*('Company Profile'!$B$8/10000000) -> 453194.63 | F19: =F18*('Company Profile'!$B$8/10000000) -> 451617.04 | G19: =G18*('Company Profile'!$B$8/10000000) -> 744202.06 | H19: =H18*('Company Profile'!$B$8/10000000) -> 1055827.8 | L19: =L18*('Company Profile'!$C$8/10000000) -> 60957.376 | M19: =M18*('Company Profile'!$C$8/10000000) -> 67365.614 | N19: =N18*('Company Profile'!$C$8/10000000) -> 58372.983 | O19: =O18*('Company Profile'!$C$8/10000000) -> 37711.031 | P19: =P18*('Company Profile'!$C$8/10000000) -> 82806.039 | Q19: =Q18*('Company Profile'!$C$8/10000000) -> 95068.717 | U19: 0 | V19: =V18*('Company Profile'!$D$8/10000000) -> 4133.6866 | W19: =W18*('Company Profile'!$D$8/10000000) -> 2760.0702 | X19: =X18*('Company Profile'!$D$8/10000000) -> 3244.6872 | Y19: =Y18*('Company Profile'!$D$8/10000000) -> 12694.718 | Z19: =Z18*('Company Profile'!$D$8/10000000) -> 9549.5221 | AD19: =AD18*('Company Profile'!$E$8/10000000) -> 7140.675 | AE19: =AE18*('Company Profile'!$E$8/10000000) -> 31790.325 | AF19: =AF18*('Company Profile'!$E$8/10000000) -> 38455.05 | AG19: =AG18*('Company Profile'!$E$8/10000000) -> 36082.425 | AH19: =AH18*('Company Profile'!$E$8/10000000) -> 58761.3 | AI19: =AI18*('Company Profile'!$E$8/10000000) -> 45544.425 | AM19: =AM18*('Company Profile'!$F$8/10000000) -> 34128.045 | AN19: =AN18*('Company Profile'!$F$8/10000000) -> 108343 | AO19: =AO18*('Company Profile'!$F$8/10000000) -> 121344.16 | AP19: =AP18*('Company Profile'!$F$8/10000000) -> 62838.94 | AQ19: =AQ18*('Company Profile'!$F$8/10000000) -> 144096.19 | AR19: =AR18*('Company Profile'!$F$8/10000000) -> 79198.733 | AU19: ROE | AV19: ='Income Statement'!AP23/'Balance Sheet'!AP26 -> 0.032534687 | AW19: ='Income Statement'!AQ23/'Balance Sheet'!AQ26 -> 0.065665426 | AX19: ='Income Statement'!AR23/'Balance Sheet'!AR26 -> 0.074986496 | AY19: ='Income Statement'!AS23/'Balance Sheet'!AS26 -> 0.084514523 | AZ19: ='Income Statement'!AT23/'Balance Sheet'!AT26 -> 0.086584958 | BA19: ='Income Statement'!AU23/'Balance Sheet'!AU26 -> 0.094862976
A20: Efficiency ratio | B20: Return on Equity | C20: ='Income Statement'!B25/'Balance Sheet'!B37 -> -0.35579695 | D20: ='Income Statement'!C25/'Balance Sheet'!C37 -> -0.3257183 | E20: ='Income Statement'!D25/'Balance Sheet'!D37 -> -0.051605105 | F20: ='Income Statement'!E25/'Balance Sheet'!E37 -> -0.001134272 | G20: ='Income Statement'!F25/'Balance Sheet'!F37 -> 0.081069381 | H20: ='Income Statement'!G25/'Balance Sheet'!G37 -> 0.24422924 | K20: ROE | L20: ='Income Statement'!J26/'Balance Sheet'!J29 -> 0.24358492 | M20: ='Income Statement'!K26/'Balance Sheet'!K29 -> 0.23801726 | N20: ='Income Statement'!L26/'Balance Sheet'!L29 -> 0.28771811 | O20: ='Income Statement'!M26/'Balance Sheet'!M29 -> 0.096638954 | P20: ='Income Statement'!N26/'Balance Sheet'!N29 -> 0.22324216 | Q20: ='Income Statement'!O26/'Balance Sheet'!O29 -> 0.30560675 | T20: ROE | U20: ='Income Statement'!R25/'Balance Sheet'!R30 -> 0.10302119 | V20: ='Income Statement'!S25/'Balance Sheet'!S30 -> 0.10082672 | W20: ='Income Statement'!T25/'Balance Sheet'!T30 -> 0.071225053 | X20: ='Income Statement'!U25/'Balance Sheet'!U30 -> 0.11466571 | Y20: ='Income Statement'!V25/'Balance Sheet'!V30 -> 0.1347442 | Z20: ='Income Statement'!W25/'Balance Sheet'!W30 -> 0.14993349 | AC20: ROE | AD20: ='Income Statement'!Z23/'Balance Sheet'!Z36 -> 0.066605947 | AE20: ='Income Statement'!AA23/'Balance Sheet'!AA36 -> 8.7135 | AF20: ='Income Statement'!AB23/'Balance Sheet'!AB36 -> 1.5528721 | AG20: ='Income Statement'!AC23/'Balance Sheet'!AC36 -> 1.162902 | AH20: ='Income Statement'!AD23/'Balance Sheet'!AD36 -> 0.62822432 | AI20: ='Income Statement'!AE23/'Balance Sheet'!AE36 -> 0.53754613 | AL20: ROE | AM20: ='Income Statement'!AH32/'Balance Sheet'!AH33 -> -12.354404 | AN20: ='Income Statement'!AI32/'Balance Sheet'!AI33 -> 1.1570864 | AO20: ='Income Statement'!AJ32/'Balance Sheet'!AJ33 -> 0.45582976 | AP20: ='Income Statement'!AK32/'Balance Sheet'!AK33 -> 0.39404861 | AQ20: ='Income Statement'!AL32/'Balance Sheet'!AL33 -> 0.29988826 | AR20: ='Income Statement'!AM32/'Balance Sheet'!AM33 -> 0.38941016
A21: Leverage ratio | B21: ICR | C21: =('Income Statement'!B15+'Income Statement'!B16)/'Income Statement'!B17 -> 3.7309454 | D21: =('Income Statement'!C15+'Income Statement'!C16)/'Income Statement'!C17 -> 4.4318211 | E21: =('Income Statement'!D15+'Income Statement'!D16)/'Income Statement'!D17 -> 4.5106423 | F21: =('Income Statement'!E15+'Income Statement'!E16)/'Income Statement'!E17 -> 5.0088427 | G21: =('Income Statement'!F15+'Income Statement'!F16)/'Income Statement'!F17 -> 5.2660888 | H21: =('Income Statement'!G15+'Income Statement'!G16)/'Income Statement'!G17 -> 6.4495654 | L21: =('Income Statement'!J14+'Income Statement'!J15)/'Income Statement'!J17 -> 15.128358 | M21: =('Income Statement'!K14+'Income Statement'!K15)/'Income Statement'!K17 -> 12.49175 | N21: =('Income Statement'!L14+'Income Statement'!L15)/'Income Statement'!L17 -> 12.921849 | O21: =('Income Statement'!M14+'Income Statement'!M15)/'Income Statement'!M17 -> 9.3207016 | P21: =('Income Statement'!N14+'Income Statement'!N15)/'Income Statement'!N17 -> 11.382659 | Q21: =('Income Statement'!O14+'Income Statement'!O15)/'Income Statement'!O17 -> 14.898757 | U21: =('Income Statement'!R18+'Income Statement'!R15)/'Income Statement'!R16 -> 55.379363 | V21: =('Income Statement'!S18+'Income Statement'!S15)/'Income Statement'!S16 -> 87.807882 | W21: =('Income Statement'!T18+'Income Statement'!T15)/'Income Statement'!T16 -> 71.165756 | X21: =('Income Statement'!U18+'Income Statement'!U15)/'Income Statement'!U16 -> 68.297342 | Y21: =('Income Statement'!V18+'Income Statement'!V15)/'Income Statement'!V16 -> 89.756567 | Z21: =('Income Statement'!W18+'Income Statement'!W15)/'Income Statement'!W16 -> 194.18006 | AD21: =('Income Statement'!Z14+'Income Statement'!Z11)/'Income Statement'!Z10 -> 6.1347878 | AE21: =('Income Statement'!AA14+'Income Statement'!AA11)/'Income Statement'!AA10 -> 9.5124703 | AF21: =('Income Statement'!AB14+'Income Statement'!AB11)/'Income Statement'!AB10 -> 11.654573 | AG21: =('Income Statement'!AC14+'Income Statement'!AC11)/'Income Statement'!AC10 -> 9.8250012 | AH21: =('Income Statement'!AD14+'Income Statement'!AD11)/'Income Statement'!AD10 -> 6.2708978 | AI21: =('Income Statement'!AE14+'Income Statement'!AE11)/'Income Statement'!AE10 -> 5.4457383 | AM21: =('Income Statement'!AH19+Table16[[#This Row],[2020]]+'Income Statement'!AH22)/'Income Statement'!AH20 -> 2.618776 | AN21: =('Income Statement'!AI19+Table16[[#This Row],[2021]]+'Income Statement'!AI22)/'Income Statement'!AI20 -> 2.2645946 | AO21: =('Income Statement'!AJ19+Table16[[#This Row],[2022]]+'Income Statement'!AJ22)/'Income Statement'!AJ20 -> 1.8945798 | AP21: =('Income Statement'!AK19+Table16[[#This Row],[2023]]+'Income Statement'!AK22)/'Income Statement'!AK20 -> 1.7203684 | AQ21: =('Income Statement'!AL19+Table16[[#This Row],[2024]]+'Income Statement'!AL22)/'Income Statement'!AL20 -> 1.5475229 | AR21: =('Income Statement'!AM19+Table16[[#This Row],[2025]]+'Income Statement'!AM22)/'Income Statement'!AM20 -> 1.6754158 | AV21: =('Income Statement'!AP17+'Income Statement'!AP13)/'Income Statement'!AP12 -> 2.27248 | AW21: =('Income Statement'!AQ17+'Income Statement'!AQ13)/'Income Statement'!AQ12 -> 7.1929688 | AX21: =('Income Statement'!AR17+'Income Statement'!AR13)/'Income Statement'!AR12 -> 7.6954535 | AY21: =('Income Statement'!AS17+'Income Statement'!AS13)/'Income Statement'!AS12 -> 10.644494 | AZ21: =('Income Statement'!AT17+'Income Statement'!AT13)/'Income Statement'!AT12 -> 12.222806 | BA21: =('Income Statement'!AU17+'Income Statement'!AU13)/'Income Statement'!AU12 -> 11.659293
B22: D/CE | C22: =('Balance Sheet'!B39+'Balance Sheet'!B48)/('Balance Sheet'!B31-'Balance Sheet'!B60) -> 0.37545761 | D22: =('Balance Sheet'!C39+'Balance Sheet'!C48)/('Balance Sheet'!C31-'Balance Sheet'!C60) -> 0.44400815 | E22: =('Balance Sheet'!D39+'Balance Sheet'!D48)/('Balance Sheet'!D31-'Balance Sheet'!D60) -> 0.55174738 | F22: =('Balance Sheet'!E39+'Balance Sheet'!E48)/('Balance Sheet'!E31-'Balance Sheet'!E60) -> 0.54653479 | G22: =('Balance Sheet'!F39+'Balance Sheet'!F48)/('Balance Sheet'!F31-'Balance Sheet'!F60) -> 0.4966812 | H22: =('Balance Sheet'!G39+'Balance Sheet'!G48)/('Balance Sheet'!G31-'Balance Sheet'!G60) -> 0.44415492 | L22: =('Balance Sheet'!J31+'Balance Sheet'!J39)/('Balance Sheet'!J24-'Balance Sheet'!J48) -> 0.15183706 | M22: =('Balance Sheet'!K31+'Balance Sheet'!K39)/('Balance Sheet'!K24-'Balance Sheet'!K48) -> 0.22489845 | N22: =('Balance Sheet'!L31+'Balance Sheet'!L39)/('Balance Sheet'!L24-'Balance Sheet'!L48) -> 0.14018145 | O22: =('Balance Sheet'!M31+'Balance Sheet'!M39)/('Balance Sheet'!M24-'Balance Sheet'!M48) -> 0.12269329 | P22: =('Balance Sheet'!N31+'Balance Sheet'!N39)/('Balance Sheet'!N24-'Balance Sheet'!N48) -> 0.094327198 | Q22: =('Balance Sheet'!O31+'Balance Sheet'!O39)/('Balance Sheet'!O24-'Balance Sheet'!O48) -> 0.042380216 | U22: =('Balance Sheet'!R32+'Balance Sheet'!R39)/('Balance Sheet'!R25-'Balance Sheet'!R47) -> 0 | V22: =('Balance Sheet'!S32+'Balance Sheet'!S39)/('Balance Sheet'!S25-'Balance Sheet'!S47) -> 0 | W22: =('Balance Sheet'!T32+'Balance Sheet'!T39)/('Balance Sheet'!T25-'Balance Sheet'!T47) -> 0 | X22: =('Balance Sheet'!U32+'Balance Sheet'!U39)/('Balance Sheet'!U25-'Balance Sheet'!U47) -> 0 | Y22: =('Balance Sheet'!V32+'Balance Sheet'!V39)/('Balance Sheet'!V25-'Balance Sheet'!V47) -> 0 | Z22: =('Balance Sheet'!W32+'Balance Sheet'!W39)/('Balance Sheet'!W25-'Balance Sheet'!W47) -> 0 | AD22: =('Balance Sheet'!Z38+'Balance Sheet'!Z46)/('Balance Sheet'!Z30-'Balance Sheet'!Z54) -> 0.84201708 | AE22: =('Balance Sheet'!AA38+'Balance Sheet'!AA46)/('Balance Sheet'!AA30-'Balance Sheet'!AA54) -> 0.72243352 | AF22: =('Balance Sheet'!AB38+'Balance Sheet'!AB46)/('Balance Sheet'!AB30-'Balance Sheet'!AB54) -> 0.70273207 | AG22: =('Balance Sheet'!AC38+'Balance Sheet'!AC46)/('Balance Sheet'!AC30-'Balance Sheet'!AC54) -> 0.69970316 | AH22: =('Balance Sheet'!AD38+'Balance Sheet'!AD46)/('Balance Sheet'!AD30-'Balance Sheet'!AD54) -> 0.92902837 | AI22: =('Balance Sheet'!AE38+'Balance Sheet'!AE46)/('Balance Sheet'!AE30-'Balance Sheet'!AE54) -> 0.77269954 | AM22: =('Balance Sheet'!AH37+'Balance Sheet'!AH46)/('Balance Sheet'!AH27-'Balance Sheet'!AH53) -> 0.73417404 | AN22: =('Balance Sheet'!AI37+'Balance Sheet'!AI46)/('Balance Sheet'!AI27-'Balance Sheet'!AI53) -> 1.1480184 | AO22: =('Balance Sheet'!AJ37+'Balance Sheet'!AJ46)/('Balance Sheet'!AJ27-'Balance Sheet'!AJ53) -> 1.4373393 | AP22: =('Balance Sheet'!AK37+'Balance Sheet'!AK46)/('Balance Sheet'!AK27-'Balance Sheet'!AK53) -> 1.369614 | AQ22: =('Balance Sheet'!AL37+'Balance Sheet'!AL46)/('Balance Sheet'!AL27-'Balance Sheet'!AL53) -> 1.5803219 | AR22: =('Balance Sheet'!AM37+'Balance Sheet'!AM46)/('Balance Sheet'!AM27-'Balance Sheet'!AM53) -> 1.3774051 | AV22: =('Balance Sheet'!AP28+'Balance Sheet'!AP37)/('Balance Sheet'!AP21-'Balance Sheet'!AP46) -> 0.1143321 | AW22: =('Balance Sheet'!AQ28+'Balance Sheet'!AQ37)/('Balance Sheet'!AQ21-'Balance Sheet'!AQ46) -> 0.050667516 | AX22: =('Balance Sheet'!AR28+'Balance Sheet'!AR37)/('Balance Sheet'!AR21-'Balance Sheet'!AR46) -> 0.1551915 | AY22: =('Balance Sheet'!AS28+'Balance Sheet'!AS37)/('Balance Sheet'!AS21-'Balance Sheet'!AS46) -> 0.093334136 | AZ22: =('Balance Sheet'!AT28+'Balance Sheet'!AT37)/('Balance Sheet'!AT21-'Balance Sheet'!AT46) -> 0.12485529 | BA22: =('Balance Sheet'!AU28+'Balance Sheet'!AU37)/('Balance Sheet'!AU21-'Balance Sheet'!AU46) -> 0.15520664

Sheet WACC
A1: Peer Data
A2: Peer Company | B2: Levered Beta | C2: Debt/Equity | D2: Tax Rate | E2: Unlevered Beta
A3: #VALUE! | B3: {=_FV(A3,"Beta")} -> 0.7464 | C3: ='Ratio Analysis'!H9 -> 0.96640726 | D3: 0.25 | E3: =B3/(1+(1-D3)*C3) -> 0.43274446
A4: WACC
A5: Parameters | B5: #VALUE! | C5: #VALUE! | D5: #VALUE! | E5: #VALUE! | F5: #VALUE! | G5: Parameters | H5: #VALUE!
A6: Risk Free Rate | B6: 0.0633 | C6: 0.0633 | D6: 0.0633 | E6: 0.0633 | F6: 0.0633 | G6: Debt/Equity | H6: ='Ratio Analysis'!BA9 -> 0.31766376
A7: Levered Beta | B7: ='Company Profile'!B11 -> 0.7464 | C7: ='Company Profile'!C11 -> 1.0382 | D7: ='Company Profile'!D11 -> 1.3204 | E7: ='Company Profile'!E11 -> 1.4164 | F7: ='Company Profile'!F11 -> 0.9757 | G7: Levered Beta | H7: =E3*(1+(1-D3)*H6) -> 0.53584488
A8: Market Risk Premium | B8: 0.0726 | C8: 0.0726 | D8: 0.0726 | E8: 0.0726 | F8: 0.0726 | G8: Risk Free rate | H8: =F6 -> 0.0633
A9: Cost of Equity | B9: =B6+(B7*B8) -> 0.11748864 | C9: =C6+(C7*C8) -> 0.13867332 | D9: =D6+(D7*D8) -> 0.15916104 | E9: =E6+(E7*E8) -> 0.16613064 | F9: =F6+(F7*F8) -> 0.13413582 | G9: Market risk premium | H9: =F8 -> 0.0726
A10: Total Debt | B10: ='Balance Sheet'!G39+'Balance Sheet'!G40+'Balance Sheet'!G48+'Balance Sheet'!G49+'Balance Sheet'!G50 -> 213642.1 | C10: ='Balance Sheet'!O31+'Balance Sheet'!O32+'Balance Sheet'!O39+'Balance Sheet'!O43 -> 21155.8 | D10: ='Balance Sheet'!W32+'Balance Sheet'!W33+'Balance Sheet'!W39+'Balance Sheet'!W40 -> 44.54 | E10: ='Balance Sheet'!AE38+'Balance Sheet'!AE40+'Balance Sheet'!AE46+'Balance Sheet'!AE49 -> 12357.32 | F10: ='Balance Sheet'!AM37+'Balance Sheet'!AM39+'Balance Sheet'!AM46+'Balance Sheet'!AM47 -> 233228.7 | G10: Cost of Equity | H10: =H8+(H7*H9) -> 0.10220234
A11: Interest Expense | B11: ='Income Statement'!G17 -> 21753.9 | C11: ='Income Statement'!O17 -> 1857.9 | D11: ='Income Statement'!W16 -> 3.11 | E11: =Table14[[#This Row],[2025]] -> 2592.1 | F11: ='Income Statement'!AM20 -> 24543.4 | G11: Total Debt | H11: ='Balance Sheet'!AU28+'Balance Sheet'!AU29+'Balance Sheet'!AU37+'Balance Sheet'!AU38 -> 83030
A12: Pre-tax Cost of Debt | B12: =B11/B10 -> 0.10182403 | C12: =C11/C10 -> 0.087819889 | D12: =D11/D10 -> 0.069824877 | E12: =E11/E10 -> 0.20976231 | F12: =F11/F10 -> 0.10523319 | G12: Interest Expense | H12: ='Income Statement'!AU12 -> 4837
A13: Tax Rate | B13: 0.25 | C13: 0.25 | D13: 0.25 | E13: 0.25 | F13: 0.25 | G13: Pre-tax cost of debt | H13: =H12/H11 -> 0.058256052
A14: After tax Cost of Debt | B14: =B12*(1-B13) -> 0.076368024 | C14: =C12*(1-C13) -> 0.065864916 | D14: =D12*(1-D13) -> 0.052368657 | E14: =E12*(1-E13) -> 0.15732173 | F14: =F12*(1-F13) -> 0.078924892 | G14: Tax rate | H14: 0.25
A15: Equity Value | B15: ='Company Profile'!B9/10000000 -> 1199343 | C15: ='Company Profile'!C9/10000000 -> 105696.4 | D15: ='Company Profile'!D9/10000000 -> 11285.8 | E15: ='Company Profile'!E9/10000000 -> 52707.9 | F15: ='Company Profile'!F9/10000000 -> 104117.7 | G15: After tax cost of debt | H15: =H13*(1-H14) -> 0.043692039
A16: Total Value | B16: =B10+B15 -> 1412985.1 | C16: =C10+C15 -> 126852.2 | D16: =D10+D15 -> 11330.34 | E16: =E10+E15 -> 65065.22 | F16: =F10+F15 -> 337346.4 | G16: Equity value | H16: ='Balance Sheet'!AU26 -> 261377
A17: Weight of Equity | B17: =B15/B16 -> 0.84880088 | C17: =C15/C16 -> 0.83322481 | D17: =D15/D16 -> 0.99606896 | E17: =E15/E16 -> 0.81007795 | F17: =F15/F16 -> 0.30863735 | G17: Total Value | H17: =H11+H16 -> 344407
A18: Weight of Debt | B18: =B10/B16 -> 0.15119912 | C18: =C10/C16 -> 0.16677519 | D18: =D10/D16 -> 0.0039310383 | E18: =E10/E16 -> 0.18992205 | F18: =F10/F16 -> 0.69136265 | G18: Weight of Equity | H18: =H16/H17 -> 0.75891895
G19: Weight of Debt | H19: =H11/H17 -> 0.24108105
A20: WACC | B20: =(B9*B17)+(B14*B18) -> 0.11127124 | C20: =(C9*C17)+(C14*C18) -> 0.12653068 | D20: =(D9*D17)+(D14*D18) -> 0.15874124 | E20: =(E9*E17)+(E14*E18) -> 0.16445763 | F20: =(F9*F17)+(F14*F18) -> 0.095965047 | G20: WACC | H20: =(H10*H18)+(H15*H19) -> 0.088096614
A21: Terminal Growth | B21: 0.0325 | C21: 0.035 | D21: 0.0325 | E21: 0.03 | F21: 0.0275 | G21: Terminal Growth | H21: 0.0325
A22: Cash and Cash Equivalents | B22: ='Balance Sheet'!G25 -> 6105.6 | C22: ='Balance Sheet'!O19 -> 149.7 | D22: ='Balance Sheet'!W18 -> 308.04 | E22: ='Balance Sheet'!AE24 -> 533.9 | F22: ='Balance Sheet'!AM19 -> 256.8 | G22: Cash and Cash Equivalents | H22: ='Balance Sheet'!AU16 -> 5929

Sheet DCF
A1: VALUATION
A2: #VALUE! | J2: #VALUE! | S2: #VALUE! | AB2: #VALUE! | AK2: #VALUE! | AT2: #VALUE!
A3: Year | B3: 2025 | C3: Ratio/Growth | D3: 2026 | E3: 2027 | F3: 2028 | G3: 2029 | H3: 2030 | J3: Year | K3: 2025 | L3: Ratio/Growth | M3: 2026 | N3: 2027 | O3: 2028 | P3: 2029 | Q3: 2030 | S3: Year | T3: 2025 | U3: Ratio/Growth | V3: 2026 | W3: 2027 | X3: 2028 | Y3: 2029 | Z3: 2030 | AB3: Year | AC3: 2025 | AD3: Ratio/Growth | AE3: 2026 | AF3: 2027 | AG3: 2028 | AH3: 2029 | AI3: 2030 | AK3: Year | AL3: 2025 | AM3: Ratio/Growth | AN3: 2026 | AO3: 2027 | AP3: 2028 | AQ3: 2029 | AR3: 2030 | AT3: Year | AU3: 2025 | AV3: Ratio/Growth | AW3: 2026 | AX3: 2027 | AY3: 2028 | AZ3: 2029 | BA3: 2030
A4: Revenue | B4: ='Income Statement'!G6 -> 174558.9 | C4: =('Income Statement'!G6/'Income Statement'!B6)^(1/6)-1 -> 0.20662581 | D4: =Table33[[#This Row],[2025]]*(1+Table33[[#This Row],[Ratio/Growth]]) -> 210627.27 | E4: =Table33[[#This Row],[2026]]*(1+$C$4) -> 254148.31 | F4: =Table33[[#This Row],[2027]]*(1+$C$4) -> 306661.91 | G4: =Table33[[#This Row],[2028]]*(1+$C$4) -> 370026.17 | H4: =Table33[[#This Row],[2029]]*(1+$C$4) -> 446483.13 | J4: Revenue | K4: ='Income Statement'!O6 -> 30468.6 | L4: =('Income Statement'!O6/'Income Statement'!J6)^(1/6)-1 -> 0.28173443 | M4: =Table35[[#This Row],[2025]]*(1+Table35[[#This Row],[Ratio/Growth]]) -> 39052.654 | N4: =Table35[[#This Row],[2026]]*(1+$L$4) -> 50055.131 | O4: =Table35[[#This Row],[2027]]*(1+$L$4) -> 64157.385 | P4: =Table35[[#This Row],[2028]]*(1+$L$4) -> 82232.729 | Q4: =Table35[[#This Row],[2029]]*(1+$L$4) -> 105400.52 | S4: Revenue | T4: ='Income Statement'!W7 -> 3551.04 | U4: =('Income Statement'!W7/'Income Statement'!R7)^(1/6)-1 -> 0.20398906 | V4: =Table38[[#This Row],[2025]]*(1+U4) -> 4275.4133 | W4: =Table38[[#This Row],[2026]]*(1+$U$4) -> 5147.5508 | X4: =Table38[[#This Row],[2027]]*(1+$U$4) -> 6197.5949 | Y4: =Table38[[#This Row],[2028]]*(1+$U$4) -> 7461.8364 | Z4: =Table38[[#This Row],[2029]]*(1+$U$4) -> 8983.9694 | AB4: Revenue | AC4: ='Income Statement'!AE6 -> 23238.89 | AD4: =('Income Statement'!AE6/'Income Statement'!Z6)^(1/6)-1 -> 0.052068298 | AE4: =Table40[[#This Row],[2025]]*(1+Table40[[#This Row],[Ratio/Growth]]) -> 24448.899 | AF4: =Table40[[#This Row],[2026]]*(1+$AD$4) -> 25721.912 | AG4: =Table40[[#This Row],[2027]]*(1+$AD$4) -> 27061.208 | AH4: =Table40[[#This Row],[2028]]*(1+$AD$4) -> 28470.239 | AI4: =Table40[[#This Row],[2029]]*(1+$AD$4) -> 29952.636 | AK4: Revenue | AL4: ='Income Statement'!AM8 -> 44591.9 | AM4: =('Income Statement'!AM8/'Income Statement'!AJ8)^(1/4)-1 -> 0.03643232 | AN4: =Table36[[#This Row],[2025]]*(1+Table36[[#This Row],[Ratio/Growth]]) -> 46216.486 | AO4: =Table36[[#This Row],[2026]]*(1+$AM$4) -> 47900.26 | AP4: =Table36[[#This Row],[2027]]*(1+$AM$4) -> 49645.378 | AQ4: =Table36[[#This Row],[2028]]*(1+$AM$4) -> 51454.074 | AR4: =Table36[[#This Row],[2029]]*(1+$AM$4) -> 53328.665 | AT4: Revenue | AU4: ='Income Statement'!AU6 -> 115088 | AV4: =('Income Statement'!AU6/'Income Statement'!AP6)^(1/6)-1 -> 0.13301206 | AW4: =Table44[[#This Row],[2025]]*(1+AV4) -> 130396.09 | AX4: =Table44[[#This Row],[2026]]*(1+$AV$4) -> 147740.34 | AY4: =Table44[[#This Row],[2027]]*(1+$AV$4) -> 167391.59 | AZ4: =Table44[[#This Row],[2028]]*(1+$AV$4) -> 189656.69 | BA4: =Table44[[#This Row],[2029]]*(1+$AV$4) -> 214883.32
A5: EBITDA | B5: ='Income Statement'!G15 -> 94732.9 | C5: =AVERAGE('Income Statement'!B15:G15)/AVERAGE('Income Statement'!B6:G6) -> 0.50813105 | D5: =D4*$C$5 -> 107026.26 | E5: =E4*$C$5 -> 129140.64 | F5: =F4*$C$5 -> 155824.43 | G5: =G4*$C$5 -> 188021.78 | H5: =H4*$C$5 -> 226871.94 | J5: EBITDA | K5: ='Income Statement'!O14 -> 21190.5 | L5: =AVERAGE('Income Statement'!J14:O14)/AVERAGE('Income Statement'!J6:O6) -> 0.53088383 | M5: =M4*$L$5 -> 20732.422 | N5: =N4*$L$5 -> 26573.46 | O5: =O4*$L$5 -> 34060.118 | P5: =P4*$L$5 -> 43656.026 | Q5: =Q4*$L$5 -> 55955.432 | S5: EBITDA | T5: ='Income Statement'!W18+'Income Statement'!W16+'Income Statement'!W15 -> 607.01 | U5: =(AVERAGE('Income Statement'!R18:W18)+AVERAGE('Income Statement'!R16:W16)+AVERAGE('Income Statement'!R15:W15))/AVERAGE('Income Statement'!R7:W7) -> 0.21659711 | V5: =V4*$U$5 -> 926.04216 | W5: =W4*$U$5 -> 1114.9446 | X5: =X4*$U$5 -> 1342.3811 | Y5: =Y4*$U$5 -> 1616.2122 | Z5: =Z4*$U$5 -> 1945.9018 | AB5: EBITDA | AC5: ='Income Statement'!AE14+'Income Statement'!AE11+'Income Statement'!AE10 -> 4699.33 | AD5: =(AVERAGE('Income Statement'!Z14:AE14)+AVERAGE('Income Statement'!Z10:AE10)+AVERAGE('Income Statement'!Z11:AE11))/AVERAGE('Income Statement'!Z6:AE6) -> 0.23079433 | AE5: =AE4*$AD$5 -> 5642.6674 | AF5: =AF4*$AD$5 -> 5936.4715 | AG5: =AG4*$AD$5 -> 6245.5735 | AH5: =AH4*$AD$5 -> 6570.7698 | AI5: =AI4*$AD$5 -> 6912.8986 | AK5: EBITDA | AL5: ='Income Statement'!AM19 -> 19147.2 | AM5: =AVERAGE('Income Statement'!AH19:AM19)/AVERAGE('Income Statement'!AH8:AM8) -> 0.40041518 | AN5: =AN4*$AM$5 -> 18505.783 | AO5: =AO4*$AM$5 -> 19179.991 | AP5: =AP4*$AM$5 -> 19878.763 | AQ5: =AQ4*$AM$5 -> 20602.992 | AR5: =AR4*$AM$5 -> 21353.607 | AT5: EBITDA | AU5: ='Income Statement'!AU17+'Income Statement'!AU12+'Income Statement'!AU13 -> 61233 | AV5: =(AVERAGE('Income Statement'!AP17:AU17)+AVERAGE('Income Statement'!AP13:AU13)+AVERAGE('Income Statement'!AP12:AU12))/AVERAGE('Income Statement'!AP6:AU6) -> 0.49536316 | AW5: =AW4*$AV$5 -> 64593.42 | AX5: =AX4*$AV$5 -> 73185.124 | AY5: =AY4*$AV$5 -> 82919.628 | AZ5: =AZ4*$AV$5 -> 93948.939 | BA5: =BA4*$AV$5 -> 106445.28
A6: Depreciation | B6: ='Income Statement'!G16 -> 45570.3 | C6: =AVERAGE('Income Statement'!B16:G16)/AVERAGE(Table7[[#This Row],[2020]:[2025]]) -> 0.29306155 | D6: =D4*$C$6 -> 61726.755 | E6: =E4*$C$6 -> 74481.096 | F6: =F4*$C$6 -> 89870.813 | G6: =G4*$C$6 -> 108440.44 | H6: =H4*$C$6 -> 130847.04 | J6: Depreciation | K6: ='Income Statement'!O15 -> 6489.9 | L6: =AVERAGE('Income Statement'!J15:O15)/AVERAGE(Table10[[#This Row],[2020]:[2025]]) -> 0.20271662 | M6: =M4*$L$6 -> 7916.6221 | N6: =N4*$L$6 -> 10147.007 | O6: =O4*$L$6 -> 13005.768 | P6: =P4*$L$6 -> 16669.941 | Q6: =Q4*$L$6 -> 21366.438 | S6: Depreciation | T6: ='Income Statement'!W15 -> 180.4 | U6: =AVERAGE('Income Statement'!R15:W15)/AVERAGE('Income Statement'!R7:W7) -> 0.076462545 | V6: =V4*$U$6 -> 326.90898 | W6: =W4*$U$6 -> 393.59484 | X6: =X4*$U$6 -> 473.88388 | Y6: =Y4*$U$6 -> 570.551 | Z6: =Z4*$U$6 -> 686.93716 | AB6: Depreciation | AC6: ='Income Statement'!AE11 -> 2592.1 | AD6: =AVERAGE('Income Statement'!Z11:AE11)/AVERAGE(Table14[[#This Row],[2020]:[2025]]) -> 0.12398924 | AE6: =AE4*$AD$6 -> 3031.4005 | AF6: =AF4*$AD$6 -> 3189.2404 | AG6: =AG4*$AD$6 -> 3355.2987 | AH6: =AH4*$AD$6 -> 3530.0034 | AI6: =AI4*$AD$6 -> 3713.8046 | AK6: Depreciation | AL6: ='Income Statement'!AM21 -> 13393.7 | AM6: =AVERAGE('Income Statement'!AM21:AM21)/AVERAGE('Income Statement'!AH8:AM8) -> 0.31316447 | AN6: =AN4*$AM$6 -> 14473.362 | AO6: =AO4*$AM$6 -> 15000.66 | AP6: =AP4*$AM$6 -> 15547.169 | AQ6: =AQ4*$AM$6 -> 16113.588 | AR6: =AR4*$AM$6 -> 16700.643 | AT6: Depreciation | AU6: ='Income Statement'!AU13 -> 23098 | AV6: =AVERAGE('Income Statement'!AP13:AU13)/AVERAGE(Table18[[#This Row],[2020]:[2025]]) -> 0.18783712 | AW6: =AW4*$AV$6 -> 24493.227 | AX6: =AX4*$AV$6 -> 27751.121 | AY6: =AY4*$AV$6 -> 31442.355 | AZ6: =AZ4*$AV$6 -> 35624.567 | BA6: =BA4*$AV$6 -> 40363.064
A7: EBIT | B7: =B5-B6 -> 49162.6 | D7: =D5-D6 -> 45299.502 | E7: =E5-E6 -> 54659.549 | F7: =F5-F6 -> 65953.622 | G7: =G5-G6 -> 79581.343 | H7: =H5-H6 -> 96024.902 | J7: EBIT | K7: =K5-K6 -> 14700.6 | M7: =M5-M6 -> 12815.8 | N7: =N5-N6 -> 16426.453 | O7: =O5-O6 -> 21054.35 | P7: =P5-P6 -> 26986.085 | Q7: =Q5-Q6 -> 34588.995 | S7: EBIT | T7: =T5-T6 -> 426.61 | V7: =V5-V6 -> 599.13318 | W7: =W5-W6 -> 721.34979 | X7: =X5-X6 -> 868.49725 | Y7: =Y5-Y6 -> 1045.6612 | Z7: =Z5-Z6 -> 1258.9646 | AB7: EBIT | AC7: =DCF!AC5-DCF!AC6 -> 2107.23 | AE7: =AE5-AE6 -> 2611.2669 | AF7: =AF5-AF6 -> 2747.2311 | AG7: =AG5-AG6 -> 2890.2748 | AH7: =AH5-AH6 -> 3040.7665 | AI7: =AI5-AI6 -> 3199.094 | AK7: EBIT | AL7: =AL5-AL6 -> 5753.5 | AN7: =AN5-AN6 -> 4032.421 | AO7: =AO5-AO6 -> 4179.3315 | AP7: =AP5-AP6 -> 4331.5942 | AQ7: =AQ5-AQ6 -> 4489.4042 | AR7: =AR5-AR6 -> 4652.9636 | AT7: EBIT | AU7: =AU5-AU6 -> 38135 | AW7: =AW5-AW6 -> 40100.194 | AX7: =AX5-AX6 -> 45434.003 | AY7: =AY5-AY6 -> 51477.273 | AZ7: =AZ5-AZ6 -> 58324.371 | BA7: =BA5-BA6 -> 66082.216
A8: Tax | B8: =B7*Table33[[#This Row],[Ratio/Growth]] -> 12290.65 | C8: 0.25 | D8: =D7*$C$8 -> 11324.876 | E8: =E7*$C$8 -> 13664.887 | F8: =F7*$C$8 -> 16488.406 | G8: =G7*$C$8 -> 19895.336 | H8: =H7*$C$8 -> 24006.226 | J8: Tax | K8: =K7*Table35[[#This Row],[Ratio/Growth]] -> 3675.15 | L8: 0.25 | M8: =M7*$C$8 -> 3203.9501 | N8: =N7*$C$8 -> 4106.6131 | O8: =O7*$C$8 -> 5263.5875 | P8: =P7*$C$8 -> 6746.5213 | Q8: =Q7*$C$8 -> 8647.2487 | S8: Tax | T8: =T7*Table38[[#This Row],[Ratio/Growth]] -> 106.6525 | U8: 0.25 | V8: =V7*$U$8 -> 149.78329 | W8: =W7*$U$8 -> 180.33745 | X8: =X7*$U$8 -> 217.12431 | Y8: =Y7*$U$8 -> 261.4153 | Z8: =Z7*$U$8 -> 314.74116 | AB8: Tax | AC8: =AC7*Table40[[#This Row],[Ratio/Growth]] -> 526.8075 | AD8: 0.25 | AE8: =AE7*$AD$8 -> 652.81673 | AF8: =AF7*$AD$8 -> 686.80778 | AG8: =AG7*$AD$8 -> 722.56869 | AH8: =AH7*$AD$8 -> 760.19161 | AI8: =AI7*$AD$8 -> 799.7735 | AK8: Tax | AL8: =AL7*Table36[[#This Row],[Ratio/Growth]] -> 1438.375 | AM8: 0.25 | AN8: =AN7*$AM$8 -> 1008.1053 | AO8: =AO7*$AM$8 -> 1044.8329 | AP8: =AP7*$AM$8 -> 1082.8985 | AQ8: =AQ7*$AM$8 -> 1122.3511 | AR8: =AR7*$AM$8 -> 1163.2409 | AT8: Tax | AU8: =Table44[[#This Row],[Ratio/Growth]]*AU7 -> 9533.75 | AV8: 0.25 | AW8: =AW7*$AV$8 -> 10025.048 | AX8: =AX7*$AV$8 -> 11358.501 | AY8: =AY7*$AV$8 -> 12869.318 | AZ8: =AZ7*$AV$8 -> 14581.093 | BA8: =BA7*$AV$8 -> 16520.554
A9: NOPAT | B9: =B7-B8 -> 36871.95 | D9: =D7-D8 -> 33974.627 | E9: =E7-E8 -> 40994.661 | F9: =F7-F8 -> 49465.217 | G9: =G7-G8 -> 59686.007 | H9: =H7-H8 -> 72018.677 | J9: NOPAT | K9: =K7-K8 -> 11025.45 | M9: =M7-M8 -> 9611.8503 | N9: =N7-N8 -> 12319.839 | O9: =O7-O8 -> 15790.762 | P9: =P7-P8 -> 20239.564 | Q9: =Q7-Q8 -> 25941.746 | S9: NOPAT | T9: =T7-T8 -> 319.9575 | V9: =V7-V8 -> 449.34988 | W9: =W7-W8 -> 541.01234 | X9: =X7-X8 -> 651.37294 | Y9: =Y7-Y8 -> 784.24589 | Z9: =Z7-Z8 -> 944.22347 | AB9: NOPAT | AC9: =AC7-AC8 -> 1580.4225 | AE9: =AE7-AE8 -> 1958.4502 | AF9: =AF7-AF8 -> 2060.4233 | AG9: =AG7-AG8 -> 2167.7061 | AH9: =AH7-AH8 -> 2280.5748 | AI9: =AI7-AI8 -> 2399.3205 | AK9: NOPAT | AL9: =AL7-AL8 -> 4315.125 | AN9: =AN7-AN8 -> 3024.3158 | AO9: =AO7-AO8 -> 3134.4986 | AP9: =AP7-AP8 -> 3248.6956 | AQ9: =AQ7-AQ8 -> 3367.0532 | AR9: =AR7-AR8 -> 3489.7227 | AT9: NOPAT | AU9: =AU7-AU8 -> 28601.25 | AW9: =AW7-AW8 -> 30075.145 | AX9: =AX7-AX8 -> 34075.502 | AY9: =AY7-AY8 -> 38607.955 | AZ9: =AZ7-AZ8 -> 43743.278 | BA9: =BA7-BA8 -> 49561.662
A10: CapEx | B10: =ABS('Cash Flow Statement'!G28) -> 37907.7 | C10: =ABS(AVERAGE('Cash Flow Statement'!B28:G28))/AVERAGE('Income Statement'!B6:G6) -> 0.22238459 | D10: =D4*$C$10 -> 46840.261 | E10: =E4*$C$10 -> 56518.668 | F10: =F4*$C$10 -> 68196.883 | G10: =G4*$C$10 -> 82288.12 | H10: =H4*$C$10 -> 99290.969 | J10: CapEx | K10: =ABS('Cash Flow Statement'!O25) -> 6784 | L10: =ABS(AVERAGE('Cash Flow Statement'!J25:O25))/AVERAGE('Income Statement'!J6:O6) -> 0.18644675 | M10: =M4*$L$10 -> 7281.2405 | N10: =N4*$L$10 -> 9332.6166 | O10: =O4*$L$10 -> 11961.936 | P10: =P4*$L$10 -> 15332.025 | Q10: =Q4*$L$10 -> 19651.585 | S10: CapEx | T10: =ABS('Cash Flow Statement'!W30) -> 325.05 | U10: =ABS(AVERAGE('Cash Flow Statement'!R30:W30))/AVERAGE('Income Statement'!R7:W7) -> 0.079374902 | V10: =V4*$U$10 -> 339.36051 | W10: =W4*$U$10 -> 408.58634 | X10: =X4*$U$10 -> 491.93348 | Y10: =Y4*$U$10 -> 592.28253 | Z10: =Z4*$U$10 -> 713.10169 | AB10: CapEx | AC10: =ABS('Cash Flow Statement'!AE35) -> 2205.59 | AD10: =ABS(AVERAGE('Cash Flow Statement'!Z35:AE35))/AVERAGE('Income Statement'!Z6:AE6) -> 0.091996477 | AE10: =AE4*$AD$10 -> 2249.2126 | AF10: =AF4*$AD$10 -> 2366.3253 | AG10: =AG4*$AD$10 -> 2489.5358 | AH10: =AH4*$AD$10 -> 2619.1617 | AI10: =AI4*$AD$10 -> 2755.537 | AK10: CapEx | AL10: =-'Cash Flow Statement'!AM35 -> 10005 | AM10: =ABS(AVERAGE('Cash Flow Statement'!AM35:AM35))/AVERAGE('Income Statement'!AH8:AM8) -> 0.23393167 | AN10: =AN4*$AM$10 -> 10811.5 | AO10: =AO4*$AM$10 -> 11205.388 | AP10: =AP4*$AM$10 -> 11613.626 | AQ10: =AQ4*$AM$10 -> 12036.737 | AR10: =AR4*$AM$10 -> 12475.263 | AT10: CapEx | AU10: =ABS('Cash Flow Statement'!AU22) -> 41622 | AV10: =ABS(AVERAGE('Cash Flow Statement'!AP22:AU22))/AVERAGE('Income Statement'!AP6:AU6) -> 0.45493792 | AW10: =AW4*$AV$10 -> 59322.127 | AX10: =AX4*$AV$10 -> 67212.685 | AY10: =AY4*$AV$10 -> 76152.783 | AZ10: =AZ4*$AV$10 -> 86282.021 | BA10: =BA4*$AV$10 -> 97758.571
A11: Change in Working Capital | B11: =('Balance Sheet'!G64-'Balance Sheet'!F64) -> -32459.7 | D11: =('Balance Sheet'!C66-'Balance Sheet'!G64) -> -4793.745 | E11: =('Balance Sheet'!D66-'Balance Sheet'!C66) -> -24308.524 | F11: =('Balance Sheet'!E66-'Balance Sheet'!D66) -> -29331.292 | G11: =('Balance Sheet'!F66-'Balance Sheet'!E66) -> -35391.894 | H11: =('Balance Sheet'!G66-'Balance Sheet'!F66) -> -42704.773 | J11: Change in Working Capital | K11: ='Balance Sheet'!O52-'Balance Sheet'!N52 -> 2809.5 | M11: =('Balance Sheet'!K54-'Balance Sheet'!O52) -> 60.096576 | N11: ='Balance Sheet'!L54-'Balance Sheet'!K54 -> 902.4226 | O11: ='Balance Sheet'!M54-'Balance Sheet'!L54 -> 1156.6661 | P11: ='Balance Sheet'!N54-'Balance Sheet'!M54 -> 1482.5388 | Q11: ='Balance Sheet'!O54-'Balance Sheet'!N54 -> 1900.221 | S11: Change in Working Capital | T11: ='Balance Sheet'!W52-'Balance Sheet'!V52 -> 416.63 | V11: ='Balance Sheet'!S54-'Balance Sheet'!W52 -> 188.79073 | W11: ='Balance Sheet'!T54-'Balance Sheet'!S54 -> 211.27774 | X11: ='Balance Sheet'!U54-'Balance Sheet'!T54 -> 254.37608 | Y11: ='Balance Sheet'!V54-'Balance Sheet'!U54 -> 306.26602 | Z11: ='Balance Sheet'!W54-'Balance Sheet'!V54 -> 368.74094 | AB11: Change in Working Capital | AC11: ='Balance Sheet'!AE58-'Balance Sheet'!AD58 -> 2406.49 | AE11: ='Balance Sheet'!AA60-'Balance Sheet'!AE58 -> -572.27143 | AF11: ='Balance Sheet'!AB60-'Balance Sheet'!AA60 -> -40.598973 | AG11: ='Balance Sheet'!AC60-'Balance Sheet'!AB60 -> 68.138422 | AH11: ='Balance Sheet'!AD60-'Balance Sheet'!AC60 -> -389.87481 | AI11: ='Balance Sheet'!AE60-'Balance Sheet'!AD60 -> -969.88933 | AK11: Change in Working Capital | AL11: ='Balance Sheet'!AM58-'Balance Sheet'!AL58 -> 16387.9 | AN11: ='Balance Sheet'!AI60-'Balance Sheet'!AM58 -> 4337.6796 | AO11: ='Balance Sheet'!AJ60-'Balance Sheet'!AI60 -> 3563.8742 | AP11: ='Balance Sheet'!AK60-'Balance Sheet'!AJ60 -> 2928.1092 | AQ11: ='Balance Sheet'!AL60-'Balance Sheet'!AK60 -> 2405.7593 | AR11: ='Balance Sheet'!AM60-'Balance Sheet'!AL60 -> 1976.5922 | AT11: Change in Working Capital | AU11: ='Balance Sheet'!AU49-'Balance Sheet'!AT49 -> 12186 | AW11: ='Balance Sheet'!AQ51-'Balance Sheet'!AU49 -> -19930.793 | AX11: ='Balance Sheet'!AR51-'Balance Sheet'!AQ51 -> -5273.9007 | AY11: ='Balance Sheet'!AS51-'Balance Sheet'!AR51 -> -5975.393 | AZ11: ='Balance Sheet'!AT51-'Balance Sheet'!AS51 -> -6770.1924 | BA11: ='Balance Sheet'!AU51-'Balance Sheet'!AT51 -> -7670.7096
A12: Free Cash Flow | B12: =B9+B6-B10-B11 -> 76994.25 | D12: =D9+D6-D10-D11 -> 53654.866 | E12: =E9+E6-E10-E11 -> 83265.613 | F12: =F9+F6-F10-F11 -> 100470.44 | G12: =G9+G6-G10-G11 -> 121230.22 | H12: =H9+H6-H10-H11 -> 146279.52 | J12: Free Cash Flow | K12: =K9+K6-K10-K11 -> 7921.85 | M12: =M9+M6-M10-M11 -> 10187.135 | N12: =N9+N6-N10-N11 -> 12231.807 | O12: =O9+O6-O10-O11 -> 15677.929 | P12: =P9+P6-P10-P11 -> 20094.941 | Q12: =Q9+Q6-Q10-Q11 -> 25756.378 | S12: Free Cash Flow | T12: =T9+T6-T10-T11 -> -241.3225 | V12: =V9+V6-V10-V11 -> 248.10762 | W12: =W9+W6-W10-W11 -> 314.7431 | X12: =X9+X6-X10-X11 -> 378.94725 | Y12: =Y9+Y6-Y10-Y11 -> 456.24834 | Z12: =Z9+Z6-Z10-Z11 -> 549.31801 | AB12: Free Cash Flow | AC12: =AC9+AC6-AC10-AC11 -> -439.5575 | AE12: =AE9+AE6-AE10-AE11 -> 3312.9095 | AF12: =AF9+AF6-AF10-AF11 -> 2923.9374 | AG12: =AG9+AG6-AG10-AG11 -> 2965.3305 | AH12: =AH9+AH6-AH10-AH11 -> 3581.2913 | AI12: =AI9+AI6-AI10-AI11 -> 4327.4775 | AK12: Free Cash Flow | AL12: =AL9+AL6-AL10-AL11 -> -8684.075 | AN12: =AN9+AN6-AN10-AN11 -> 2348.4981 | AO12: =AO9+AO6-AO10-AO11 -> 3365.8965 | AP12: =AP9+AP6-AP10-AP11 -> 4254.1291 | AQ12: =AQ9+AQ6-AQ10-AQ11 -> 5038.1446 | AR12: =AR9+AR6-AR10-AR11 -> 5738.5104 | AT12: Free Cash Flow | AU12: =AU9+AU6-AU10-AU11 -> -2108.75 | AW12: =AW9+AW6-AW10-AW11 -> 15177.038 | AX12: =AX9+AX6-AX10-AX11 -> -112.16119 | AY12: =AY9+AY6-AY10-AY11 -> -127.07998 | AZ12: =AZ9+AZ6-AZ10-AZ11 -> -143.98315 | BA12: =BA9+BA6-BA10-BA11 -> -163.13465
A13: Discount Factor | C13: =WACC!B20 -> 0.11127124 | D13: =1/(1+$C$13)^1 -> 0.89987031 | E13: =1/(1+$C$13)^2 -> 0.80976658 | F13: =1/(1+$C$13)^3 -> 0.72868491 | G13: =1/(1+$C$13)^4 -> 0.65572192 | H13: =1/(1+$C$13)^5 -> 0.59006469 | J13: Discount Factor | L13: =WACC!C20 -> 0.12653068 | M13: =1/(1+$L$13)^1 -> 0.8876811 | N13: =1/(1+$L$13)^2 -> 0.78797774 | O13: =1/(1+$L$13)^3 -> 0.69947295 | P13: =1/(1+$L$13)^4 -> 0.62090892 | Q13: =1/(1+$L$13)^5 -> 0.55116911 | S13: Discount Factor | U13: =WACC!D20 -> 0.15874124 | V13: =1/(1+$U$13)^1 -> 0.86300545 | W13: =1/(1+$U$13)^2 -> 0.74477841 | X13: =1/(1+$U$13)^3 -> 0.64274782 | Y13: =1/(1+$U$13)^4 -> 0.55469487 | Z13: =1/(1+$U$13)^5 -> 0.4787047 | AB13: Discount Factor | AD13: =WACC!E20 -> 0.16445763 | AE13: =1/(1+$AD$13)^1 -> 0.8587689 | AF13: =1/(1+$AD$13)^2 -> 0.73748402 | AG13: =1/(1+$AD$13)^3 -> 0.63332834 | AH13: =1/(1+$AD$13)^4 -> 0.54388268 | AI13: =1/(1+$AD$13)^5 -> 0.46706953 | AK13: Discount Factor | AM13: =WACC!F20 -> 0.095965047 | AN13: =1/(1+$AM$13)^1 -> 0.91243786 | AO13: =1/(1+$AM$13)^2 -> 0.83254285 | AP13: =1/(1+$AM$13)^3 -> 0.75964361 | AQ13: =1/(1+$AM$13)^4 -> 0.69312759 | AR13: =1/(1+$AM$13)^5 -> 0.63243585 | AT13: Discount Factor | AV13: =WACC!H20 -> 0.088096614 | AW13: =1/(1+$AV$13)^1 -> 0.91903604 | AX13: =1/(1+$AV$13)^2 -> 0.84462724 | AY13: =1/(1+$AV$13)^3 -> 0.77624287 | AZ13: =1/(1+$AV$13)^4 -> 0.71339517 | BA13: =1/(1+$AV$13)^5 -> 0.65563587
A14: PV of FCF | D14: =D12*D13 -> 48282.421 | E14: =E12*E13 -> 67425.711 | F14: =F12*F13 -> 73211.292 | G14: =G12*G13 -> 79493.315 | H14: =H12*H13 -> 86314.378 | J14: PV of FCF | M14: =M12*M13 -> 9042.9275 | N14: =N12*N13 -> 9638.3919 | O14: =O12*O13 -> 10966.287 | P14: =P12*P13 -> 12477.128 | Q14: =Q12*Q13 -> 14196.12 | S14: PV of FCF | V14: =V12*V13 -> 214.11823 | W14: =W12*W13 -> 234.41387 | X14: =X12*X13 -> 243.56752 | Y14: =Y12*Y13 -> 253.07862 | Z14: =Z12*Z13 -> 262.96111 | AB14: PV of FCF | AE14: =AE12*AE13 -> 2845.0236 | AF14: =AF12*AF13 -> 2156.3571 | AG14: =AG12*AG13 -> 1878.0279 | AH14: =AH12*AH13 -> 1947.8023 | AI14: =AI12*AI13 -> 2021.2329 | AK14: PV of FCF | AN14: =AN12*AN13 -> 2142.8586 | AO14: =AO12*AO13 -> 2802.253 | AP14: =AP12*AP13 -> 3231.622 | AQ14: =AQ12*AQ13 -> 3492.077 | AR14: =AR12*AR13 -> 3629.2397 | AT14: PV of FCF | AW14: =AW12*AW13 -> 13948.245 | AX14: =AX12*AX13 -> -94.734397 | AY14: =AY12*AY13 -> -98.64493 | AZ14: =AZ12*AZ13 -> -102.71689 | BA14: =BA12*BA13 -> -106.95693
A16: Parameter | B16: Value | J16: Parameter | K16: Value | S16: Parameter | T16: Value | AB16: Parameter | AC16: Value | AK16: Parameter | AL16: Value | AT16: Parameter | AU16: Value
A17: PV of FCF | B17: =SUM(D14:H14) -> 354727.12 | J17: PV of FCF | K17: =SUM(M14:Q14) -> 56320.854 | S17: PV of FCF | T17: =SUM(V14:Z14) -> 1208.1393 | AB17: PV of FCF | AC17: =SUM(AE14:AI14) -> 10848.444 | AK17: PV of FCF | AL17: =SUM(AN14:AR14) -> 15298.05 | AT17: PV of FCF | AU17: =SUM(AW14:BA14) -> 13545.192
A18: Terminal Value of FCF | B18: =(H12*(1+WACC!B21))/(DCF!C13-WACC!B21) -> 1917369.9 | J18: Terminal Value of FCF | K18: =(Q12*(1+WACC!C21))/(WACC!C20-WACC!C21) -> 291244.96 | S18: Terminal Value of FCF | T18: =(Z12*(1+WACC!D21))/(WACC!D20-WACC!D21) -> 4492.7543 | AB18: Terminal Value of FCF | AC18: =(AI12*(1+WACC!E21))/(WACC!E20-WACC!E21) -> 33150.232 | AK18: Terminal Value of FCF | AL18: =(AR12*(1+WACC!F21))/(WACC!F20-WACC!F21) -> 86121.601 | AT18: Terminal Value of FCF | AU18: =(AW12*(1+WACC!H21))/(WACC!H20-WACC!H21) -> 281856.95
A19: PV of Terminal Value | B19: =B18*H13 -> 1131372.3 | J19: PV of Terminal Value | K19: =K18*Q13 -> 160525.23 | S19: PV of Terminal Value | T19: =T18*Z13 -> 2150.7026 | AB19: PV of Terminal Value | AC19: =AC18*AI13 -> 15483.463 | AK19: PV of Terminal Value | AL19: =AL18*AR13 -> 54466.388 | AT19: PV of Terminal Value | AU19: =AU18*BA13 -> 184795.52
A20: Enterprise Value | B20: =B17+B19 -> 1486099.4 | J20: Enterprise Value | K20: =K17+K19 -> 216846.08 | S20: Enterprise Value | T20: =T17+T19 -> 3358.8419 | AB20: Enterprise Value | AC20: =AC17+AC19 -> 26331.907 | AK20: Enterprise Value | AL20: =AL17+AL19 -> 69764.438 | AT20: Enterprise Value | AU20: =AU17+AU19 -> 198340.72
A21: Less: Debt | B21: =WACC!B10 -> 213642.1 | J21: Less: Debt | K21: =WACC!C10 -> 21155.8 | S21: Less: Debt | T21: =WACC!D10 -> 44.54 | AB21: Less: Debt | AC21: =WACC!E10 -> 12357.32 | AK21: Less: Debt | AL21: =WACC!F10 -> 233228.7 | AT21: Less: Debt | AU21: =WACC!H11 -> 83030
A22: Add: Cash | B22: =WACC!B22 -> 6105.6 | J22: Add: Cash | K22: =Table31[[#This Row],[Column3]] -> 149.7 | S22: Add: Cash | T22: =Table31[[#This Row],[Column4]] -> 308.04 | AB22: Add: Cash | AC22: =Table31[[#This Row],[Column5]] -> 533.9 | AK22: Add: Cash | AL22: =Table31[[#This Row],[Column6]] -> 256.8 | AT22: Add: Cash | AU22: =Table31[[#This Row],[Column8]] -> 5929
A23: Equity Value | B23: =B20-B21+B22 -> 1278562.9 | J23: Equity Value | K23: =K20-K21+K22 -> 195839.98 | S23: Equity Value | T23: =T20-T21+T22 -> 3622.3419 | AB23: Equity Value | AC23: =AC20-AC21+AC22 -> 14508.487 | AK23: Equity Value | AL23: =AL20-AL21+AL22 -> -163207.46 | AT23: Equity Value | AU23: =AU20-AU21+AU22 -> 121239.72
A24: Outstanding Shares | B24: ='Company Profile'!B8/10000000 -> 609.108 | J24: Outstanding Shares | K24: ='Company Profile'!C8/10000000 -> 263.7135 | S24: Outstanding Shares | T24: ='Company Profile'!D8/10000000 -> 32.09384 | AB24: Outstanding Shares | AC24: ='Company Profile'!E8/10000000 -> 28.5 | AK24: Outstanding Shares | AL24: ='Company Profile'!F8/10000000 -> 10834.3 | AT24: Outstanding Shares | AU24: {='Income Statement'!AU23/Table19[2025]} -> 4500
A25: Intrinsic Value per Share | B25: =B23/B24 -> 2099.0742 | J25: Intrinsic Value per Share | K25: =K23/K24 -> 742.62403 | S25: Intrinsic Value per Share | T25: =T23/T24 -> 112.8672 | AB25: Intrinsic Value per Share | AC25: =AC23/AC24 -> 509.06972 | AK25: Intrinsic Value per Share | AL25: =AL23/AL24 -> -15.06396 | AT25: Intrinsic Value per Share | AU25: =AU23/AU24 -> 26.942159
A26: Current Market Price | B26: ='Company Profile'!B7 -> 2019.8 | J26: Current Market Price | K26: ='Company Profile'!C7 -> 398.75 | S26: Current Market Price | T26: ='Company Profile'!D7 -> 349.25 | AB26: Current Market Price | AC26: ='Company Profile'!E7 -> 1849.85 | AK26: Current Market Price | AL26: ='Company Profile'!F7 -> 9.51
A27: #VALUE! | B27: =(B25-B26)/B26 -> 0.039248534 | J27: #VALUE! | K27: =(K25-K26)/K26 -> 0.86238002 | S27: #VALUE! | T27: =(T25-T26)/T26 -> -0.67682977 | AB27: #VALUE! | AC27: =(AC25-AC26)/AC26 -> -0.72480486 | AK27: #VALUE! | AL27: =(AL25-AL26)/AL26 -> -2.5840126

Sheet Relative Valuation Model
A2: Particulars | B2: #VALUE! | C2: #VALUE! | D2: #VALUE! | E2: #VALUE! | F2: #VALUE! | G2: #VALUE! | J2: Target Valuation | K2: #VALUE! | L2: #VALUE!
A3: Current Market Price | B3: ='Company Profile'!B7 -> 2019.8 | C3: ='Company Profile'!C7 -> 398.75 | D3: ='Company Profile'!D7 -> 349.25 | E3: ='Company Profile'!E7 -> 1849.85 | F3: ='Company Profile'!F7 -> 9.51 | J3: P/E Valuation | K3: {=G13*Table19[2025]} -> 124.4923 | L3: 0
A4: Market Cap | B4: ='Company Profile'!B9/10000000 -> 1199343 | C4: ='Company Profile'!C9/10000000 -> 105696.4 | D4: ='Company Profile'!D9/10000000 -> 11285.8 | E4: ='Company Profile'!E9/10000000 -> 52707.9 | F4: ='Company Profile'!F9/10000000 -> 104117.7 | J4: P/B Valuation | K4: =G14*(F10/F11) -> -42.610204 | L4: 0
A5: Net Debt | B5: =WACC!B10-WACC!B22 -> 207536.5 | C5: =WACC!C10-WACC!C22 -> 21006.1 | D5: =WACC!D10-WACC!D22 -> -263.5 | E5: =WACC!E10-WACC!E22 -> 11823.42 | F5: =WACC!F10-WACC!F22 -> 232971.9 | J5: EV/EBITDA Valuation | K5: =G15*F8 -> 269308.3 | L5: =G15*G8 -> 861251.51
A6: Enterprise Value | B6: =B4+B5 -> 1406879.5 | C6: =C4+C5 -> 126702.5 | D6: =D4+D5 -> 11022.3 | E6: =E4+E5 -> 64531.32 | F6: =F4+F5 -> 337089.6 | J6: Equity value (EV/EBITDA) | K6: =(K5-F5)/F11 -> 3.3538297 | L6: =(L5-WACC!H11)/'Relative Valuation Model'!G11 -> 172.93811
A7: Revenue | B7: ='Income Statement'!G6 -> 174558.9 | C7: ='Income Statement'!O6 -> 30468.6 | D7: =Table11[[#This Row],[2025]] -> 3551.04 | E7: ='Income Statement'!AE6 -> 23238.89 | F7: ='Income Statement'!AM8 -> 44591.9 | G7: ='Income Statement'!AU6 -> 115088 | J7: EV/Revenue Valuation | K7: =G16*F7 -> 228830.96 | L7: =G16*G7 -> 590593.75
A8: EBITDA | B8: ='Income Statement'!G15 -> 94732.9 | C8: ='Income Statement'!O14 -> 21190.5 | D8: ='Income Statement'!W18+'Income Statement'!W16+'Income Statement'!W15 -> 607.01 | E8: ='Income Statement'!AE14+'Income Statement'!AE11+'Income Statement'!AE10 -> 4699.33 | F8: ='Income Statement'!AM19 -> 19147.2 | G8: ='Income Statement'!AU17+'Income Statement'!AU12+'Income Statement'!AU13 -> 61233 | J8: Equity Value (EV/Revenue) | K8: =(K7-F5)/F11 -> -0.38220654 | L8: =(L7-WACC!H11)/'Relative Valuation Model'!G11 -> 112.79194
A9: EPS | B9: {=Table8[2025]} -> 58 | C9: {=Table9[2025]} -> 37.31 | D9: {=Table12[2025]} -> 9.34 | E9: {=Table13[2025]} -> 57.03 | F9: {=Table15[2025]} -> -4.01 | G9: {=Table19[2025]} -> 5.51 | J9: P/S Valuatiion | K9: =G17*(F7/F11) -> 15.010286 | L9: 0
A10: Book Value | B10: ='Balance Sheet'!G37 -> 153467.7 | C10: ='Balance Sheet'!O29 -> 32498.3 | D10: ='Balance Sheet'!W30 -> 1999.62 | E10: ='Balance Sheet'!AE36 -> 3024.28 | F10: ='Balance Sheet'!AM33 -> -70320.2 | G10: ='Balance Sheet'!AU26 -> 261377 | J10: Target Price | K10: =AVERAGE(K3:K4,K6,K8:K9) -> 19.972802 | L10: =AVERAGE(L6,L8) -> 142.86503
A11: Outstanding Shares | B11: ='Company Profile'!B8/10000000 -> 609.108 | C11: ='Company Profile'!C8/10000000 -> 263.7135 | D11: ='Company Profile'!D8/10000000 -> 32.09384 | E11: ='Company Profile'!E8/10000000 -> 28.5 | F11: ='Company Profile'!F8/10000000 -> 10834.3 | G11: =DCF!AU24 -> 4500 | J11: Current Market Price | K11: =F3 -> 9.51 | L11: 0
A12: Valuation Multiples | B12: #VALUE! | C12: #VALUE! | D12: #VALUE! | E12: #VALUE! | F12: #VALUE! | G12: Average | J12: #VALUE! | K12: =(K10-K11)/K11 -> 1.1001894 | L12: 0
A13: P/E | B13: =B3/B9 -> 34.824138 | C13: =C3/C9 -> 10.687483 | D13: =D3/D9 -> 37.392934 | E13: =E3/E9 -> 32.436437 | F13: =F3/F9 -> -2.3715711 | G13: =AVERAGE(B13:F13) -> 22.593884
A14: P/B | B14: =B3/(B10/B11) -> 8.0165164 | C14: =C3/(C10/C11) -> 3.235731 | D14: =D3/(D10/D11) -> 5.6054518 | E14: =E3/(E10/E11) -> 17.432488 | F14: =F3/(F10/F11) -> -1.4652147 | G14: =AVERAGE(B14:F14) -> 6.5649945
A15: EV/EBITDA | B15: =B6/B8 -> 14.851013 | C15: =C6/C8 -> 5.9792124 | D15: =D6/D8 -> 18.15835 | E15: =E6/E8 -> 13.732026 | F15: =F6/F8 -> 17.605164 | G15: =AVERAGE(B15:F15) -> 14.065153
A16: EV/Revenue | B16: =B6/B7 -> 8.0596263 | C16: =C6/C7 -> 4.1584615 | D16: =D6/D7 -> 3.1039639 | E16: =E6/E7 -> 2.7768676 | F16: =F6/F7 -> 7.5594357 | G16: =AVERAGE(B16:F16) -> 5.131671
A17: P/S | B17: =B3/(B7/B11) -> 7.0479153 | C17: =C3/(C7/C11) -> 3.4512829 | D17: =D3/(D7/D11) -> 3.1564763 | E17: =E3/(E7/E11) -> 2.2686421 | F17: =F3/(F7/F11) -> 2.3106033 | G17: =AVERAGE(B17:F17) -> 3.646984

Sheet Summary
A2: Parameter | B2: #VALUE! | C2: #VALUE! | D2: #VALUE! | E2: #VALUE! | F2: #VALUE! | G2: #VALUE!
A3: Equity Value | B3: =DCF!B23 -> 1278562.9 | C3: =DCF!K23 -> 195839.98 | D3: =DCF!T23 -> 3622.3419 | E3: =DCF!AC23 -> 14508.487 | F3: ='Relative Valuation Model'!K10*'Relative Valuation Model'!F11 -> 216391.32 | G3: ='Relative Valuation Model'!L10*'Relative Valuation Model'!G11 -> 642892.63 | J3: Revenue CAGR | K3: Bharti Airtel | L3: =(DCF!H4/DCF!D4)^(1/5)-1 -> 0.16213904
A4: Market Cap | B4: ='Relative Valuation Model'!B4 -> 1199343 | C4: ='Relative Valuation Model'!C4 -> 105696.4 | D4: ='Relative Valuation Model'!D4 -> 11285.8 | E4: ='Relative Valuation Model'!E4 -> 52707.9 | F4: ='Relative Valuation Model'!F4 -> 104117.7 | J4: Revenue CAGR | K4: Indus Towers | L4: =(Table35[[#This Row],[2030]]/Table35[[#This Row],[2026]])^(1/5)-1 -> 0.21965905
A5: Intrinsic Value/Share | B5: =DCF!B25 -> 2099.0742 | C5: =DCF!K25 -> 742.62403 | D5: =DCF!T25 -> 112.8672 | E5: =DCF!AC25 -> 509.06972 | F5: ='Relative Valuation Model'!K10 -> 19.972802 | G5: ='Relative Valuation Model'!L10 -> 142.86503 | J5: Revenue CAGR | K5: RailTel | L5: =(DCF!Z4/DCF!V4)^(1/5)-1 -> 0.16010696
A6: Current Market Price | B6: ='Company Profile'!B7 -> 2019.8 | C6: ='Company Profile'!C7 -> 398.75 | D6: ='Company Profile'!D7 -> 349.25 | E6: ='Company Profile'!E7 -> 1849.85 | F6: ='Company Profile'!F7 -> 9.51 | J6: Revenue CAGR | K6: Tata Comm | L6: =(DCF!AI4/DCF!AE4)^(1/5)-1 -> 0.041442142
A7: Valuation Method | B7: DCF | C7: DCF | D7: DCF | E7: DCF | F7: Relative | G7: Relative | J7: Revenue CAGR | K7: VI | L7: =(DCF!AR4/DCF!AN4)^(1/5)-1 -> 0.029041188
A8: #VALUE! | B8: =(B5-B6)/B6 -> 0.039248534 | C8: =(C5-C6)/C6 -> 0.86238002 | D8: =(D5-D6)/D6 -> -0.67682977 | E8: =(E5-E6)/E6 -> -0.72480486 | F8: =(F5-F6)/F6 -> 1.1001894 | J8: Revenue CAGR | K8: Jio | L8: =(DCF!BA4/DCF!AW4)^(1/5)-1 -> 0.1050645
J9: Revenue CAGR | K9: Average | L9: =AVERAGE(L3:L8) -> 0.11957548 | N9: GDP | O9: 2020 | P9: 0.0195
J10: Capex Intensity | K10: =K3 -> Bharti Airtel | L10: =AVERAGE(Table33[[#This Row],[2026]:[2030]])/AVERAGE(DCF!D4:H4) -> 0.22238459 | N10: GDP | O10: 2025 | P10: 0.078
J11: Capex Intensity | K11: =K4 -> Indus Towers | L11: =AVERAGE(DCF!M10:Q10)/AVERAGE(DCF!M4:Q4) -> 0.18644675 | N11: GDP | O11: Change | P11: =P10-P9 -> 0.0585
J12: Capex Intensity | K12: =K5 -> RailTel | L12: =AVERAGE(DCF!V10:Z10)/AVERAGE(DCF!V4:Z4) -> 0.079374902 | N12: GDP | O12: Sensitivity | P12: =L23/P11 -> 83.834806
J13: Capex Intensity | K13: =K6 -> Tata Comm | L13: =AVERAGE(DCF!AE10:AI10)/AVERAGE(DCF!AE4:AI4) -> 0.091996477
J14: Capex Intensity | K14: =K7 -> VI | L14: =AVERAGE(DCF!AN10:AR10)/AVERAGE(DCF!AN4:AR4) -> 0.23393167
J15: Capex Intensity | K15: =K8 -> Jio | L15: =AVERAGE(DCF!AW10:BA10)/AVERAGE(DCF!AW4:BA4) -> 0.45493792
J16: Capex Intensity | K16: Average | L16: =AVERAGE(L10:L15) -> 0.21151205
J17: Earnings growth | K17: =K10 -> Bharti Airtel | L17: =('Income Statement'!G25-'Income Statement'!B25)/ABS('Income Statement'!B25) -> 2.0386026
J18: Earnings growth | K18: =K11 -> Indus Towers | L18: =('Income Statement'!O26-'Income Statement'!J26)/'Income Statement'!J26 -> 2.0107921
J19: Earnings growth | K19: =K12 -> RailTel | L19: =('Income Statement'!W25-'Income Statement'!R25)/'Income Statement'!R25 -> 1.125257
J20: Earnings growth | K20: =K13 -> Tata Comm | L20: =('Income Statement'!AE23-'Income Statement'!Z23)/ABS('Income Statement'!Z23) -> 20.164093
J21: Earnings growth | K21: =K14 -> VI | L21: =('Income Statement'!AM32-'Income Statement'!AH32)/ABS('Income Statement'!AH32) -> 0.62934347
J22: Earnings growth | K22: =K15 -> Jio | L22: =('Income Statement'!AU23-'Income Statement'!AP23)/'Income Statement'!AP23 -> 3.4579288
J23: Earnings growth | K23: Average | L23: =AVERAGE(L17:L22) -> 4.9043362

Sheet Senstivity Analysis
A2: #VALUE! | I2: #VALUE! | Q2: #VALUE! | Y2: #VALUE! | AG2: #VALUE!
A3: Subscribers | B3: ='Ratio Analysis'!H14 -> 2956.0502 | C3: 3200 | D3: 3400 | E3: 3600 | F3: 3800 | G3: 4000 | I3: Towers | J3: ='Ratio Analysis'!Q14 -> 1171869.2 | K3: 1300000 | L3: 1500000 | M3: 1700000 | N3: 1900000 | O3: 2100000 | Q3: Subscribers | R3: ='Ratio Analysis'!Z14 -> 61757.217 | S3: 63000 | T3: 65000 | U3: 67000 | V3: 69000 | W3: 71000 | Y3: Subscribers | Z3: ='Ratio Analysis'!AR14 -> 2249.8436 | AA3: 2500 | AB3: 2750 | AC3: 3000 | AD3: 3250 | AE3: 3500 | AG3: Subscribers | AH3: ='Ratio Analysis'!BA14 -> 2414.8726 | AI3: 2600 | AJ3: 2800 | AK3: 3000 | AL3: 3200 | AM3: 3400
