Workbook

Sheet Company Profile
A1: COMPANY PROFILE
A2: Logo | B2: #VALUE! | C2: #VALUE! | D2: #VALUE! | E2: #VALUE! | F2: #VALUE!
A3: Company name | B3: Tata Consultancy Services | C3: Infosys | D3: HCL Technologies | E3: Wipro | F3: LT Mindtree
A4: Listed Name | B4: #VALUE! | C4: #VALUE! | D4: #VALUE! | E4: #VALUE! | F4: #VALUE!
A5: Ticker symbol | B5: {=_FV(B4,"Ticker symbol",TRUE)} -> TCS | C5: {=_FV(C4,"Ticker symbol",TRUE)} -> INFY | D5: {=_FV(D4,"Ticker symbol",TRUE)} -> HCLTECH | E5: {=_FV(E4,"Ticker symbol",TRUE)} -> WIPRO | F5: {=_FV(F4,"Ticker symbol",TRUE)} -> LTIM
A6: Industry | B6: {=_FV(B4,"Industry")} -> Software & IT Services | C6: {=_FV(C4,"Industry")} -> Software & IT Services | D6: {=_FV(D4,"Industry")} -> Software & IT Services | E6: {=_FV(E4,"Industry")} -> Software & IT Services | F6: {=_FV(F4,"Industry")} -> Software & IT Services
A7: Employees | B7: {=_FV(B4,"Employees")} -> 613069 | C7: {=_FV(C4,"Employees")} -> 331991 | D7: {=_FV(D4,"Employees")} -> 226640 | E7: {=_FV(E4,"Employees")} -> 235492 | F7: {=_FV(F4,"Employees")} -> 86447
A8: In crores | B8: 0.0613 | C8: 0.0323578 | D8: 0.0218621 | E8: 0.023 | F8: 0.0083889
A9: Share Price | B9: {=_FV(B4,"Price")} -> 3025.2 | C9: {=_FV(C4,"Price")} -> 1513.5 | D9: {=_FV(D4,"Price")} -> 1540.5 | E9: {=_FV(E4,"Price")} -> 239.84 | F9: {=_FV(F4,"Price")} -> 5650
A10: Outstanding shares | B10: {=_FV(B4,"Shares outstanding",TRUE)} -> 3618087000 | C10: {=_FV(C4,"Shares outstanding",TRUE)} -> 4145310000 | D10: {=_FV(D4,"Shares outstanding",TRUE)} -> 2705510000 | E10: {=_FV(E4,"Shares outstanding",TRUE)} -> 10472250000 | F10: {=_FV(F4,"Shares outstanding",TRUE)} -> 296468400
A11: In Crores | B11: 361.81 | C11: 414.46 | D11: 270.89 | E11: 1047.087 | F11: 29.633
A12: Market cap (INR) | B12: {=_FV(B4,"Market cap",TRUE)} -> 10824590000000 | C12: {=_FV(C4,"Market cap",TRUE)} -> 6121794000000 | D12: {=_FV(D4,"Market cap",TRUE)} -> 4091814000000 | E12: {=_FV(E4,"Market cap",TRUE)} -> 2476583000000 | F12: {=_FV(F4,"Market cap",TRUE)} -> 1650588000000
A13: In crores | B13: =B12/10000000 -> 1082459 | C13: =C12/10000000 -> 612179.4 | D13: =D12/10000000 -> 409181.4 | E13: =E12/10000000 -> 247658.3 | F13: =F12/10000000 -> 165058.8
A14: Conversion | B14: #VALUE! | C14: #VALUE! | D14: #VALUE! | E14: #VALUE! | F14: #VALUE!
B15: {=_FV(B14,"Price")} -> 0.01127 | C15: {=_FV(C14,"Price")} -> 0.01127 | D15: {=_FV(D14,"Price")} -> 0.01127 | E15: {=_FV(E14,"Price")} -> 0.01127 | F15: {=_FV(F14,"Price")} -> 0.01127
A16: In USD | B16: =B12*B15 -> 121993129300 | C16: =C12*C15 -> 68992618380 | D16: =D12*D15 -> 46114743780 | E16: =E12*E15 -> 27911090410 | F16: =F12*F15 -> 18602126760
A17: Beta | B17: {=_FV(B4,"Beta")} -> 0.9429 | C17: {=_FV(C4,"Beta")} -> 0.8999 | D17: {=_FV(D4,"Beta")} -> 1.0408 | E17: {=_FV(E4,"Beta")} -> 0.8684 | F17: {=_FV(F4,"Beta")} -> 1.3531
A18: Change (%) | B18: {=_FV(B4,"Change (%)",TRUE)} -> 0.011164 | C18: {=_FV(C4,"Change (%)",TRUE)} -> 0.024851 | D18: {=_FV(D4,"Change (%)",TRUE)} -> 0.01858 | E18: {=_FV(E4,"Change (%)",TRUE)} -> 0.014166 | F18: {=_FV(F4,"Change (%)",TRUE)} -> 0.014818

Sheet Balance Sheet
A1: Consolidated Balance Sheet | E1: #VALUE! | H1: Consolidated Balance Sheet | L1: #VALUE! | O1: Consolidated Balance Sheet | S1: #VALUE! | V1: Consolidated Balance Sheet | Z1: #VALUE! | AC1: Consolidated Balance Sheet | AG1: #VALUE!
A2: Particulars | B2: 2020 | C2: 2021 | D2: 2022 | E2: 2023 | F2: 2024 | H2: Particulars | I2: 2020 | J2: 2021 | K2: 2022 | L2: 2023 | M2: 2024 | O2: Particulars | P2: 2020 | Q2: 2021 | R2: 2022 | S2: 2023 | T2: 2024 | V2: Particulars | W2: 2020 | X2: 2021 | Y2: 2022 | Z2: 2023 | AA2: 2024 | AC2: Particulars | AD2: 2020 | AE2: 2021 | AF2: 2022 | AG2: 2023 | AH2: 2024
A3: ASSETS | H3: ASSETS | O3: ASSETS | V3: ASSETS | AC3: ASSETS
A4: Non-Current Assets | H4: Non current assets | O4: Non current assets | V4: Non current assets | AC4: Non current assets
A5: Property, plant and equipment | B5: 10941 | C5: 11110 | D5: 10774 | E5: 10230 | F5: 9376 | H5: Property, plant and equipment | I5: 12435 | J5: 12560 | K5: 13075 | L5: 13346 | M5: 12370 | O5: Property, plant and equipment | P5: 5494 | Q5: 5642 | R5: 5612 | S5: 5371 | T5: 4891 | V5: Property, plant and equipment | W5: 6061.7 | X5: 6575.1 | Y5: 7461 | Z5: 8233.6 | AA5: 7412.8 | AC5: Property, plant and equipment | AD5: 403.1 | AE5: 385.7 | AF5: 918.3 | AG5: 969.7 | AH5: 1655.5
A6: Capital work-in-progress | B6: 906 | C6: 926 | D6: 1205 | E6: 1234 | F6: 1564 | H6: Right-of-use assets | I6: 4168 | J6: 4794 | K6: 4823 | L6: 6882 | M6: 6552 | O6: Capital work in progress | P6: 400 | Q6: 312 | R6: 129 | S6: 40 | T6: 108 | V6: Right-of-use assets | W6: 1674.8 | X6: 1642 | Y6: 1887 | Z6: 1870.2 | AA6: 1795.5 | AC6: Right of use asset | AD6: 769.2 | AE6: 622.1 | AF6: 1112.4 | AG6: 1253.9 | AH6: 1901.3
A7: Right-of-use assets | B7: 7994 | C7: 7633 | D7: 7636 | E7: 7560 | F7: 7886 | H7: Capital work in progress | I7: 954 | J7: 922 | K7: 416 | L7: 288 | M7: 293 | O7: Right of use assets | P7: 2648 | Q7: 2410 | R7: 2305 | S7: 2337 | T7: 2910 | V7: Capital work in progress | W7: 1881.1 | X7: 1853.2 | Y7: 1601.5 | Z7: 617.1 | AA7: 723.4 | AC7: Capital work in progress | AD7: 38.2 | AE7: 40.3 | AF7: 458.9 | AG7: 812.6 | AH7: 466.9
A8: Goodwill | B8: 1710 | C8: 1798 | D8: 1787 | E8: 1858 | F8: 1832 | H8: Goodwill | I8: 5286 | J8: 6079 | K8: 6195 | L8: 7248 | M8: 7303 | O8: Goodwill | P8: 16154 | Q8: 17192 | R8: 17417 | S8: 18567 | T8: 20132 | V8: Goodwill | W8: 12689.4 | X8: 13514.7 | Y8: 24286.1 | Z8: 30348.5 | AA8: 31144.9 | AC8: Goodwill | AD8: 636.8 | AE8: 657.4 | AF8: 1163.2 | AG8: 1189.2 | AH8: 1192.7
A9: Other Tangible assets | B9: 283 | C9: 480 | D9: 1101 | E9: 867 | F9: 510 | H9: Other intangible assets | I9: 1900 | J9: 2072 | K9: 1707 | L9: 1749 | M9: 1397 | O9: Other intangible assets | P9: 13194 | Q9: 11901 | R9: 9743 | S9: 8344 | T9: 7130 | V9: Other intangible assets | W9: 1636.2 | X9: 1308.5 | Y9: 4355.5 | Z9: 4304.5 | AA9: 3274.8 | AC9: Other tangible assets | AD9: 110.6 | AE9: 240.8 | AF9: 279 | AG9: 266.3 | AH9: 231.3
A10: Financial Assets | H10: Financial assets | O10: Financial Assets | V10: Investments accounted for using the equity method | W10: 138.3 | X10: 146.4 | Y10: 77.4 | Z10: 78 | AA10: 104.4 | AC10: Intangible assets under development | AD10: 21 | AE10: 25.9 | AF10: 43.9 | AG10: 89.7 | AH10: 83.8
A11: Investments | B11: 216 | C11: 213 | D11: 223 | E11: 266 | F11: 281 | H11: Investments | I11: 4137 | J11: 11863 | K11: 13651 | L11: 12569 | M11: 11708 | O11: Investments | P11: 77 | Q11: 89 | R11: =9+103 -> 112 | S11: 110 | T11: 94 | V11: Financial assets | AC11: Financial Assets
A12: Trade receivables | B12: 74 | C12: 55 | D12: 145 | E12: 149 | F12: 127 | H12: Loans | I12: 21 | J12: 32 | K12: 34 | L12: 39 | M12: 34 | O12: Others | P12: 2373 | Q12: 2569 | R12: 1220 | S12: 1279 | T12: 1346 | V12: Investments | W12: 930.2 | X12: 1057.6 | Y12: 1910.9 | Z12: 2072 | AA12: 2162.9 | AC12: Investments | AD12: 0.2 | AE12: 101.3 | AF12: 651.3 | AG12: 716.5 | AH12: 1990.2
A13: Unbilled receivables | B13: 324 | C13: 273 | D13: 55 | E13: 199 | F13: 16 | H13: Other financial assets | I13: 737 | J13: 1141 | K13: 1460 | L13: 2798 | M13: 3105 | O13: Deferred tax assets (net) | P13: 2317 | Q13: 1181 | R13: 1176 | S13: 1252 | T13: 1031 | V13: Derivative assets | W13: 0 | X13: 1.6 | Y13: 0.6 | Z13: 2.9 | AA13: 2.5 | AC13: Loans | AD13: 56 | AE13: 45.7 | AF13: 0 | AG13: 3.9 | AH13: 6.6
A14: Loans | B14: 29 | C14: 29 | D14: 311 | E14: 173 | F14: 2 | H14: Deferred tax assets (net) | I14: 1744 | J14: 1098 | K14: 1212 | L14: 1245 | M14: 454 | O14: Other non current assets | P14: 1829 | Q14: 1847 | R14: =2006+1072+200 -> 3278 | S14: =1853+681 -> 2534 | T14: =1894+624 -> 2518 | V14: Trade receivables | W14: 604.9 | X14: 435.8 | Y14: 476.5 | Z14: 86.3 | AA14: 404.5 | AC14: Other financial assets | AD14: 11.8 | AE14: 159.5 | AF14: 550.5 | AG14: 192.4 | AH14: 471.5
A15: Other financial assets | B15: 1184 | C15: 1573 | D15: 2253 | E15: 2149 | F15: 3272 | H15: Income tax assets (net) | I15: 5384 | J15: 5811 | K15: 6098 | L15: 6453 | M15: 3045 | O15: Total non current assets | P15: =SUM(P5:P9,P11:P14) -> 44486 | Q15: =SUM(Q5:Q9,Q11:Q14) -> 43143 | R15: =SUM(R5:R9,R11:R14) -> 40992 | S15: =SUM(S5:S9,S11:S14) -> 39834 | T15: =SUM(T5:T9,T11:T14) -> 40160 | V15: Other financial assets | W15: 588.1 | X15: 608.8 | Y15: 608.4 | Z15: 633 | AA15: 555 | AC15: Deferred tax assets (net) | AD15: 222.2 | AE15: 54.6 | AF15: 38.7 | AG15: 380.9 | AH15: 225
A16: Income tax assets (net) | B16: 2462 | C16: 1845 | D16: 1983 | E16: 3307 | F16: 3403 | H16: Other non current assets | I16: 1426 | J16: 1281 | K16: 2029 | L16: 2318 | M16: 2121 | O16: Current assets | V16: Deferred tax assets (net) | W16: 600.5 | X16: 166.4 | Y16: 229.8 | Z16: 210 | AA16: 181.7 | AC16: Income tax assets (net) | AD16: 81.7 | AE16: 93 | AF16: 221.8 | AG16: 233.4 | AH16: 297
A17: Deferred tax assets (net) | B17: 2828 | C17: 3931 | D17: 3708 | E17: 2583 | F17: 1600 | H17: Total non current assets | I17: =SUM(I5:I9,I11:I16) -> 38192 | J17: =SUM(J5:J9,J11:J16) -> 47653 | K17: =SUM(K5:K9,K11:K16) -> 50700 | L17: =SUM(L5:L9,L11:L16) -> 54935 | M17: =SUM(M5:M9,M11:M16) -> 48382 | O17: Inventories | P17: 91 | Q17: 94 | R17: 161 | S17: 228 | T17: 185 | V17: Non current tax assets (net) | W17: 1141.4 | X17: 1432.3 | Y17: 1025.6 | Z17: 1192.2 | AA17: 904.3 | AC17: Other non current assets | AD17: 145.1 | AE17: 151.5 | AF17: 205.8 | AG17: 201.8 | AH17: 194.8
A18: Other assets | B18: 1711 | C18: 1613 | D18: 2023 | E18: 2806 | F18: 3596 | H18: Current assets | O18: Financial Assets | V18: Other non current assets | W18: 1347.2 | X18: 1671.2 | Y18: 1509.9 | Z18: 1375.8 | AA18: 1057.7 | AC18: Total non current assets | AD18: =SUM(AD5:AD10,AD12:AD17) -> 2495.9 | AE18: =SUM(AE5:AE10,AE12:AE17) -> 2577.8 | AF18: =SUM(AF5:AF10,AF12:AF17) -> 5643.8 | AG18: =SUM(AG5:AG10,AG12:AG17) -> 6310.3 | AH18: =SUM(AH5:AH10,AH12:AH17) -> 8716.6
A19: Total non-current assets | B19: =SUM(B3:B9,B11:B18) -> 30662 | C19: =SUM(C3:C9,C11:C18) -> 31479 | D19: =SUM(D3:D9,D11:D18) -> 33204 | E19: =SUM(E3:E9,E11:E18) -> 33381 | F19: =SUM(F3:F9,F11:F18) -> 33465 | H19: Financial assets | O19: Investments | P19: 6989 | Q19: 6773 | R19: 6239 | S19: 5385 | T19: 7043 | V19: Total non current assets | W19: =SUM(W5:W10,W12:W18) -> 29293.8 | X19: =SUM(X5:X10,X12:X18) -> 30413.6 | Y19: =SUM(Y5:Y10,Y12:Y18) -> 45430.2 | Z19: =SUM(Z5:Z10,Z12:Z18) -> 51024.1 | AA19: =SUM(AA5:AA10,AA12:AA18) -> 49724.4 | AC19: Current Assets
A20: Current Assets | H20: Investments | I20: 4655 | J20: 2342 | K20: 6673 | L20: 6909 | M20: 12915 | O20: Trade receivables | P20: 14131 | Q20: 13663 | R20: =15476+5195 -> 20671 | S20: =19572+5934 -> 25506 | T20: =19483+6038 -> 25521 | V20: Current Assets | AC20: Inventories | AD20: 0 | AE20: 0 | AF20: 4.1 | AG20: 3.3 | AH20: 3
A21: Inventories | B21: 5 | C21: 8 | D21: 20 | E21: 28 | F21: 28 | H21: Trade receivables | I21: 18487 | J21: 19294 | K21: 22698 | L21: 25424 | M21: 30193 | O21: Cash and cash equivalents | P21: 4848 | Q21: 6521 | R21: 10510 | S21: 9065 | T21: 9456 | V21: Inventories | W21: 186.5 | X21: 106.4 | Y21: 133.4 | Z21: 118.8 | AA21: 90.7 | AC21: Financial Assets
A22: Financial Assets | H22: Cash and cash equivalents | I22: 18649 | J22: 24714 | K22: 17472 | L22: 12173 | M22: 14786 | O22: Other bank balances | P22: 128 | Q22: 2367 | R22: 2126 | S22: 5659 | T22: 10694 | V22: Financial assets | AC22: Investments | AD22: 2218.6 | AE22: 3628.2 | AF22: 5397.1 | AG22: 4741.8 | AH22: 6753.4
A23: Investments | B23: 26140 | C23: 29160 | D23: 30262 | E23: 36897 | F23: 31481 | H23: Loans | I23: 239 | J23: 159 | K23: 248 | L23: 289 | M23: 248 | O23: Loans | P23: 3422 | Q23: 4841 | R23: 3008 | S23: 2603 | T23: 795 | V23: Investments | W23: 18963.5 | X23: 17570.7 | Y23: 24165.5 | Z23: 30923.2 | AA23: 31117.1 | AC23: Trade receivables | AD23: 2312.1 | AE23: 2083.5 | AF23: 4557.4 | AG23: 5623.4 | AH23: 5706
A24: Trade receivables | B24: 30532 | C24: 30079 | D24: 34074 | E24: 41049 | F24: 44434 | H24: Other financial assets | I24: 5457 | J24: 6410 | K24: 8727 | L24: 11604 | M24: 12085 | O24: Others | P24: 5937 | Q24: 5889 | R24: 1520 | S24: 1120 | T24: 1235 | V24: Trade receivables | W24: 10447.4 | X24: 9429.8 | Y24: 11521.9 | Z24: 12635 | AA24: 11547.7 | AC24: Unbilled revenue | AD24: 442 | AE24: 607.1 | AF24: 1069.7 | AG24: 1601.1 | AH24: 1326.1
A25: Unbilled receivables | B25: 5732 | C25: 6583 | D25: 7736 | E25: 8905 | F25: 9143 | H25: Income tax assets (net) | I25: 7 | J25: 0 | K25: 54 | L25: 6 | M25: 6397 | O25: Current tax assets (net) | P25: 157 | Q25: 131 | R25: 234 | S25: 195 | T25: 161 | V25: Cash and cash equivalents | W25: 14449.9 | X25: 16979.3 | Y25: 10383.6 | Z25: 9188 | AA25: 9695.3 | AC25: Cash and cash equivalents | AD25: 485.3 | AE25: 675.9 | AF25: 1446.2 | AG25: 2338.9 | AH25: 1820
A26: Cash and Cash Equivalents | B26: 8646 | C26: 6858 | D26: 12488 | E26: 7123 | F26: 9016 | H26: Other current assets | I26: 7082 | J26: 7814 | K26: 11313 | L26: 14476 | M26: 12808 | O26: Other current assets | P26: 2717 | Q26: 2772 | R26: 3572 | S26: 3816 | T26: 4241 | V26: Derivative assets | W26: 302.5 | X26: 406.4 | Y26: 303.2 | Z26: 184.4 | AA26: 133.3 | AC26: Other bank balances | AD26: 39.9 | AE26: 83.5 | AF26: 391.1 | AG26: 593.1 | AH26: 996
A27: Other balances with banks | B27: 1020 | C27: 2471 | D27: 5733 | E27: 3909 | F27: 4270 | H27: Total current assets | I27: =SUM(I20:I26) -> 54576 | J27: =SUM(J20:J26) -> 60733 | K27: =SUM(K20:K26) -> 67185 | L27: =SUM(L20:L26) -> 70881 | M27: =SUM(M20:M26) -> 89432 | O27: Total current assets | P27: =SUM(P17,P19:P26) -> 38420 | Q27: =SUM(Q17,Q19:Q26) -> 43051 | R27: =SUM(R17,R19:R26) -> 48041 | S27: =SUM(S17,S19:S26) -> 53577 | T27: =SUM(T17,T19:T26) -> 59331 | V27: Unbilled receivables | W27: 2520.9 | X27: 2712.4 | Y27: 6080.9 | Z27: 6051.5 | AA27: 5834.5 | AC27: Loans | AD27: 12.9 | AE27: 30 | AF27: 0 | AG27: 0 | AH27: 0
A28: Loans | B28: 8475 | C28: 11472 | D28: 6445 | E28: 1325 | F28: 491 | H28: Total assets | I28: =I17+I27 -> 92768 | J28: =J17+J27 -> 108386 | K28: =K17+K27 -> 117885 | L28: =L17+L27 -> 125816 | M28: =M17+M27 -> 137814 | O28: Total assets | P28: =P15+P27 -> 82906 | Q28: =Q15+Q27 -> 86194 | R28: =R15+R27 -> 89033 | S28: =S15+S27 -> 93411 | T28: =T15+T27 -> 99491 | V28: Other financial assets | W28: 861.4 | X28: 724.5 | Y28: 4291.4 | Z28: 909.6 | AA28: 1053.6 | AC28: Other financial assets | AD28: 161.3 | AE28: 185.8 | AF28: 480.7 | AG28: 183 | AH28: 263.5
A29: Other financial assets | B29: 1473 | C29: 1394 | D29: 1390 | E29: 1319 | F29: 1703 | H29: EQUITY AND LIABILITIES | O29: EQUITY | V29: Current tax assets (net) | W29: 288.2 | X29: 246.1 | Y29: 237.3 | Z29: 509.1 | AA29: 648.4 | AC29: Income tax assets (net) | AD29: 0.7 | AE29: 0 | AF29: 0 | AG29: 0 | AH29: 25.1
A30: Income tax assets (net) | B30: 8 | C30: 19 | D30: 11 | E30: 8 | F30: 151 | H30: Equity | O30: Equity share capital | P30: 543 | Q30: 543 | R30: 543 | S30: 543 | T30: 543 | V30: Contract assets | W30: 1714.3 | X30: 1650.7 | Y30: 2064.7 | Z30: 2300.1 | AA30: 1985.4 | AC30: Other current assets | AD30: 656.2 | AE30: 837.3 | AF30: 1592.3 | AG30: 2101.2 | AH30: 1953.3
A31: Other assets | B31: 8206 | C31: 11236 | D31: 10151 | E31: 9707 | F31: 12267 | H31: Equity share capital | I31: 2122 | J31: 2124 | K31: 2098 | L31: 2069 | M31: 2071 | O31: Other equity | P31: 50724 | Q31: 59370 | R31: 61371 | S31: 64862 | T31: 67720 | V31: Other current assets | W31: 2250.5 | X31: 2492.3 | Y31: 2893.3 | Z31: 3289.9 | AA31: 2960.2 | AC31: Total current assets | AD31: =SUM(AD22:AD30,AD20) -> 6329 | AE31: =SUM(AE22:AE30,AE20) -> 8131.3 | AF31: =SUM(AF22:AF30,AF20) -> 14938.6 | AG31: =SUM(AG22:AG30,AG20) -> 17185.8 | AH31: =SUM(AH22:AH30,AH20) -> 18846.4
A32: Total current assets | B32: =SUM(B21,B23:B31) -> 90237 | C32: =SUM(C21,C23:C31) -> 99280 | D32: =SUM(D21,D23:D31) -> 108310 | E32: =SUM(E21,E23:E31) -> 110270 | F32: =SUM(F21,F23:F31) -> 112984 | H32: Other equity | I32: 63328 | J32: 74227 | K32: 73252 | L32: 73338 | M32: 86045 | O32: Equity distributable to shareholders of the company | P32: =P30+P31 -> 51267 | Q32: =Q30+Q31 -> 59913 | R32: =R30+R31 -> 61914 | S32: =S30+S31 -> 65405 | T32: =T30+T31 -> 68263 | V32: Assets held for sale | W32: 0 | X32: 0 | Y32: 0 | Z32: 0 | AA32: 0 | AC32: Total assets | AD32: =AD18+AD31 -> 8824.9 | AE32: =AE18+AE31 -> 10709.1 | AF32: =AF18+AF31 -> 20582.4 | AG32: =AG18+AG31 -> 23496.1 | AH32: =AH18+AH31 -> 27563
A33: Total Assets | B33: =B19+B32 -> 120899 | C33: =C19+C32 -> 130759 | D33: =D19+D32 -> 141514 | E33: =E19+E32 -> 143651 | F33: =F19+F32 -> 146449 | H33: Total equity distributable to equity holders of the company | I33: =I31+I32 -> 65450 | J33: =J31+J32 -> 76351 | K33: =K31+K32 -> 75350 | L33: =L31+L32 -> 75407 | M33: =M31+M32 -> 88116 | O33: Non controlling interest | P33: 154 | Q33: 169 | R33: 92 | S33: -7 | T33: 8 | V33: Total current assets | W33: =SUM(W21,W23:W32) -> 51985.1 | X33: =SUM(X21,X23:X32) -> 52318.6 | Y33: =SUM(Y21,Y23:Y32) -> 62075.2 | Z33: =SUM(Z21,Z23:Z32) -> 66109.6 | AA33: =SUM(AA21,AA23:AA32) -> 65066.2 | AC33: EQUITY AND LIABILITIES
A34: EQUITY AND LIABILITIES | H34: Non controlling interest | I34: 394 | J34: 431 | K34: 386 | L34: 388 | M34: 345 | O34: Total equity | P34: =P32+P33 -> 51421 | Q34: =Q32+Q33 -> 60082 | R34: =R32+R33 -> 62006 | S34: =S32+S33 -> 65398 | T34: =T32+T33 -> 68271 | V34: Total assets | W34: =W19+W33 -> 81278.9 | X34: =X19+X33 -> 82732.2 | Y34: =Y19+Y33 -> 107505.4 | Z34: =Z19+Z33 -> 117133.7 | AA34: =AA19+AA33 -> 114790.6 | AC34: Equity
A35: Equity | H35: Total equity | I35: =I33+I34 -> 65844 | J35: =J33+J34 -> 76782 | K35: =K33+K34 -> 75736 | L35: =L33+L34 -> 75795 | M35: =M33+M34 -> 88461 | O35: LIABILITIES | V35: EQUITY AND LIABILITIES | AC35: Equity share capital | AD35: 17.4 | AE35: 17.5 | AF35: 29.6 | AG35: 29.6 | AH35: 29.6
A36: Share capital | B36: 375 | C36: 370 | D36: 366 | E36: 366 | F36: 362 | H36: Liabilities | O36: Non current liabilities | V36: EQUITY | AC36: Other equity
A37: Other equity | B37: 83751 | C37: 86063 | D37: 88773 | E37: 90058 | F37: 90127 | H37: Non current liabilities | O37: Financial Liabilities | V37: Equity share capital | W37: 1142.7 | X37: 1095.8 | Y37: 1096.4 | Z37: 1097.6 | AA37: 1045 | AC37: Other reserves | AD37: 633.6 | AE37: 1129.4 | AF37: 1880.3 | AG37: 1112.4 | AH37: 1695.6
A38: Equity distributable to shareholders of the company | B38: =SUM(B36:B37) -> 84126 | C38: =SUM(C36:C37) -> 86433 | D38: =SUM(D36:D37) -> 89139 | E38: =SUM(E36:E37) -> 90424 | F38: =SUM(F36:F37) -> 90489 | H38: Financial liabilities | O38: Borrowings | P38: 2848 | Q38: 3828 | R38: 3923 | S38: 2111 | T38: 2223 | V38: Other equity | W38: 54179 | X38: 53805.2 | Y38: 64306.6 | Z38: 76570.3 | AA38: 73488 | AC38: Retained earnings | AD38: 4753 | AE38: 6156.5 | AF38: 12377.3 | AG38: 15450.1 | AH38: 18291.9
A39: Non controlling interests | B39: 623 | C39: 675 | D39: 707 | E39: 782 | F39: 830 | H39: Lease liabilities | I39: 4014 | J39: 4587 | K39: 4602 | L39: 7057 | M39: 6400 | O39: Lease liabilities | P39: 2179 | Q39: 1903 | R39: 1659 | S39: 1664 | T39: 2339 | V39: Equity attributable to the shareholders of the company | W39: =W37+W38 -> 55321.7 | X39: =X37+X38 -> 54901 | Y39: =Y37+Y38 -> 65403 | Z39: =Z37+Z38 -> 77667.9 | AA39: =AA37+AA38 -> 74533 | AC39: Non controlling interest | AD39: 1.1 | AE39: 3.7 | AF39: 5.7 | AG39: 7.1 | AH39: =0.1+9.2 -> 9.3
A40: Total Equity | B40: =B38+B39 -> 84749 | C40: =C38+C39 -> 87108 | D40: =D38+D39 -> 89846 | E40: =E38+E39 -> 91206 | F40: =F38+F39 -> 91319 | H40: Other financial liabilities | I40: 807 | J40: 1514 | K40: 2337 | L40: 2058 | M40: 2130 | O40: Others | P40: 1194 | Q40: 973 | R40: 452 | S40: 506 | T40: 730 | V40: Non controlling interest | W40: 187.5 | X40: 149.8 | Y40: 51.5 | Z40: 58.9 | AA40: 134 | AC40: Total equity | AD40: =SUM(AD35:AD39) -> 5405.1 | AE40: =SUM(AE35:AE39) -> 7307.1 | AF40: =SUM(AF35:AF39) -> 14292.9 | AG40: =SUM(AG35:AG39) -> 16599.2 | AH40: =SUM(AH35:AH39) -> 20026.4
A41: Liabilities | H41: Deferred tax liabilities (net) | I41: 968 | J41: 875 | K41: 1156 | L41: 1220 | M41: 1794 | O41: Long-term provisions | P41: 1048 | Q41: 1333 | R41: 1415 | S41: 1315 | T41: 1612 | V41: Total equity | W41: =W39+W40 -> 55509.2 | X41: =X39+X40 -> 55050.8 | Y41: =Y39+Y40 -> 65454.5 | Z41: =Z39+Z40 -> 77726.8 | AA41: =AA39+AA40 -> 74667 | AC41: Liabilities
A42: Non-current Liabilities | H42: Other non-current liabilities | I42: 279 | J42: 763 | K42: 451 | L42: 500 | M42: 235 | O42: Deferred tax liabilities (net) | P42: 87 | Q42: 147 | R42: 112 | S42: 161 | T42: 771 | V42: LIABILITIES | AC42: Non current liabilities
A43: Financial Liabilities | H43: Total non-current liabilities | I43: =SUM(I39:I42) -> 6068 | J43: =SUM(J39:J42) -> 7739 | K43: =SUM(K39:K42) -> 8546 | L43: =SUM(L39:L42) -> 10835 | M43: =SUM(M39:M42) -> 10559 | O43: Other non current liabilities | P43: 399 | Q43: 545 | R43: =33+658 -> 691 | S43: =41+784 -> 825 | T43: =1048+57 -> 1105 | V43: Non current liabilities | AC43: Financial liabilities
A44: Lease liabilities | B44: 6906 | C44: 6503 | D44: 6368 | E44: 6203 | F44: 6516 | H44: Current liabilities | O44: Total non current liabilities | P44: =SUM(P38:P43) -> 7755 | Q44: =SUM(Q38:Q43) -> 8729 | R44: =SUM(R38:R43) -> 8252 | S44: =SUM(S38:S43) -> 6582 | T44: =SUM(T38:T43) -> 8780 | V44: Financial liabilities | AC44: Lease liabilities | AD44: 757.1 | AE44: 637.5 | AF44: 1133.6 | AG44: 1187.2 | AH44: 1727.2
A45: Other financial liabilities | B45: 291 | C45: 280 | D45: 572 | E45: 353 | F45: 365 | H45: Financial liabilities | O45: Current Liabilities | V45: Borrowings | W45: 484 | X45: 745.8 | Y45: 5646.3 | Z45: 6127.2 | AA45: 6230 | AC45: Other financial liabilities | AD45: 288.4 | AE45: 44.5 | AF45: 24.9 | AG45: 177.4 | AH45: 31.8
A46: Unearned and deferred revenue | B46: 697 | C46: 1197 | D46: 1110 | E46: 1003 | F46: 482 | H46: Trade payables | I46: 2852 | J46: 2645 | K46: 872 | L46: 1242 | M46: 1959 | O46: Financial Liabilities | V46: Derivative liabilities | W46: 13.8 | X46: 0 | Y46: 4.8 | Z46: 17.9 | AA46: 0.4 | AC46: Other non current liabilities | AD46: 0 | AE46: 47.9 | AF46: 0 | AG46: 0 | AH46: 0
A47: Employee benefit obligations | B47: 417 | C47: 749 | D47: 677 | E47: 536 | F47: 686 | H47: Lease liabilities | I47: 619 | J47: 738 | K47: 4134 | L47: 3865 | M47: 3956 | O47: Borrowings | P47: 1845 | Q47: 0 | R47: 62 | S47: 140 | T47: 104 | V47: Lease liabilities | W47: 1263.8 | X47: 1351.3 | Y47: 1517.7 | Z47: 1595.3 | AA47: 1396.2 | AC47: Deferred tax liabilities (net) | AD47: 10.1 | AE47: 3.5 | AF47: 10.5 | AG47: 14.7 | AH47: 18.7
A48: Deferred tax liabilities | B48: 779 | C48: 767 | D48: 590 | E48: 792 | F48: 977 | H48: Other financial liabilities | I48: 10481 | J48: 11390 | K48: 15837 | L48: 18558 | M48: 16959 | O48: Trade payables | P48: 1166 | Q48: 1726 | R48: =2297+3981 -> 6278 | S48: =2526+3902 -> 6428 | T48: =2570+3283 -> 5853 | V48: Other financial liabilities | W48: 15.1 | X48: 229.1 | Y48: 296.1 | Z48: 264.9 | AA48: 498.5 | AC48: Long term provisions | AD48: 33 | AE48: 36.3 | AF48: 28.2 | AG48: 35 | AH48: 15.7
A49: Total non-current liabilities | B49: =SUM(B44:B48) -> 9090 | C49: =SUM(C44:C48) -> 9496 | D49: =SUM(D44:D48) -> 9317 | E49: =SUM(E44:E48) -> 8887 | F49: =SUM(F44:F48) -> 9026 | H49: Other current liabilities | I49: 4842 | J49: 6233 | K49: 9178 | L49: 10830 | M49: 10539 | O49: Lease liabilities | P49: 715 | Q49: 691 | R49: 699 | S49: 871 | T49: 1090 | V49: Deferred tax liabilities (net) | W49: 279.3 | X49: 460.6 | Y49: 1214.1 | Z49: 1515.3 | AA49: 1746.7 | AC49: Total non current liabilities | AD49: =SUM(AD44:AD48) -> 1088.6 | AE49: =SUM(AE44:AE48) -> 769.7 | AF49: =SUM(AF44:AF48) -> 1197.2 | AG49: =SUM(AG44:AG48) -> 1414.3 | AH49: =SUM(AH44:AH48) -> 1793.4
A50: Current Liabilities | H50: Provisions | I50: 572 | J50: 713 | K50: 975 | L50: 1307 | M50: 1796 | O50: Others | P50: 14340 | Q50: 8421 | R50: =4796+3380 -> 8176 | S50: =5210+3917 -> 9127 | T50: =5691+4155 -> 9846 | V50: Non-current tax liabilities (net) | W50: 1320.5 | X50: 1106.9 | Y50: 1781.8 | Z50: 2177.7 | AA50: 3709 | AC50: Current Liabilities
A51: Financial Liabilities | H51: Income tax liabilities (net) | I51: 1490 | J51: 2146 | K51: 2607 | L51: 3384 | M51: 3585 | O51: Other current liabilities | P51: 3889 | Q51: 4299 | R51: 1267 | S51: 1595 | T51: 2183 | V51: Other non current liabilities | W51: 377.1 | X51: 478 | Y51: 485.1 | Z51: 638.6 | AA51: 875.1 | AC51: Financial liabilities
A52: Lease liabilities | B52: 1268 | C52: 1292 | D52: 1450 | E52: 1485 | F52: 1505 | H52: Total current liabilities | I52: =SUM(I46:I51) -> 20856 | J52: =SUM(J46:J51) -> 23865 | K52: =SUM(K46:K51) -> 33603 | L52: =SUM(L46:L51) -> 39186 | M52: =SUM(M46:M51) -> 38794 | O52: Short term provisions | P52: 706 | Q52: 963 | R52: 955 | S52: 1120 | T52: 1337 | V52: Long term provisions | W52: 376.8 | X52: 305.7 | Y52: 272.1 | Z52: 294.7 | AA52: 421.9 | AC52: Borrowings | AD52: 32 | AE52: 41.4 | AF52: 51.9 | AG52: 125.3 | AH52: 40.7
A53: Trade payables | B53: 6740 | C53: 7860 | D53: 8045 | E53: 10515 | F53: 9981 | H53: Total equity and liabilities | I53: =I35+I43+I52 -> 92768 | J53: =J35+J43+J52 -> 108386 | K53: =K35+K43+K52 -> 117885 | L53: =L35+L43+L52 -> 125816 | M53: =M35+M43+M52 -> 137814 | O53: Current tax liabilities (net) | P53: 1069 | Q53: 1283 | R53: 1338 | S53: 2150 | T53: 2313 | V53: Total non-current liabilities | W53: =SUM(W45:W52) -> 4130.4 | X53: =SUM(X45:X52) -> 4677.4 | Y53: =SUM(Y45:Y52) -> 11218 | Z53: =SUM(Z45:Z52) -> 12631.6 | AA53: =SUM(AA45:AA52) -> 14877.8 | AC53: Trade payables
A54: Other financial liabilities | B54: 6100 | C54: 6150 | D54: 7687 | E54: 9068 | F54: 8362 | O54: Total current liabilities | P54: =SUM(P47:P53) -> 23730 | Q54: =SUM(Q47:Q53) -> 17383 | R54: =SUM(R47:R53) -> 18775 | S54: =SUM(S47:S53) -> 21431 | T54: =SUM(T47:T53) -> 22726 | V54: Current Liabilities | AC54: Due to micro and small enterprises | AD54: 7.9 | AE54: 8.2 | AF54: 17 | AG54: 15.4 | AH54: 11.8
A55: Unearned and deferred revenue | B55: 2915 | C55: 3650 | D55: 3635 | E55: 3843 | F55: 3640 | O55: Total Equity and Liabilities | P55: =P34+P44+P54 -> 82906 | Q55: =Q34+Q44+Q54 -> 86194 | R55: =R34+R44+R54 -> 89033 | S55: =S34+S44+S54 -> 93411 | T55: =T34+T44+T54 -> 99777 | V55: Financial liabilities | AC55: Others | AD55: 687.1 | AE55: 819.5 | AF55: 1308 | AG55: 1278.4 | AH55: 1482.1
A56: Other liabilities | B56: 3283 | C56: 4068 | D56: 8392 | E56: 4892 | F56: 6524 | I56: =I27-I52 -> 33720 | M56: =M27-M52 -> 50638 | V56: Borrowings | W56: 5402 | X56: 7587.4 | Y56: 9523.3 | Z56: 8882.1 | AA56: 7916.6 | AC56: Other financial liabilities | AD56: 801.1 | AE56: 783.1 | AF56: 1598.1 | AG56: 1643.7 | AH56: 1488.7
A57: Provisions | B57: 293 | C57: 1394 | D57: 1411 | E57: 345 | F57: 140 | P57: =P27-P54 -> 14690 | S57: =S27-S54 -> 32146 | T57: =T27-T54 -> 36605 | V57: Trade payables | W57: 5840 | X57: 5181.6 | Y57: 6252.2 | Z57: 5972.3 | AA57: 5765.5 | AC57: Lease liabilities | AD57: 122.8 | AE57: 119.4 | AF57: 205.6 | AG57: 228.7 | AH57: 302.7
A58: Employee benefit obligations | B58: 2749 | C58: 3498 | D58: 3810 | E58: 4065 | F58: 4519 | V58: Derivative liabilities | W58: 723.1 | X58: 107 | Y58: 58.5 | Z58: 282.5 | AA58: 55.8 | AC58: Other current liabilities | AD58: 413.4 | AE58: 492.1 | AF58: 1046.2 | AG58: 1207 | AH58: 1412.6
A59: Income tax liabilities (net) | B59: 3712 | C59: 6243 | D59: 7921 | E59: 9345 | F59: 11433 | V59: Lease liabilities | W59: 656 | X59: 766.9 | Y59: 905.6 | Z59: 862 | AA59: 922.1 | AC59: Short term provisions | AD59: 258.8 | AE59: 354.2 | AF59: 629.2 | AG59: 813.4 | AH59: 848.6
A60: Total current liabilities | B60: =SUM(B52:B59) -> 27060 | C60: =SUM(C52:C59) -> 34155 | D60: =SUM(D51:D59) -> 42351 | E60: =SUM(E51:E59) -> 43558 | F60: =SUM(F51:F59) -> 46104 | V60: Other financial liabilities | W60: 3981 | X60: 2616.6 | Y60: 6962.2 | Z60: 3347.2 | AA60: 3318.3 | AC60: Income tax liabilities (net) | AD60: 8.1 | AE60: 14.4 | AF60: 236.3 | AG60: 170.7 | AH60: 156
A61: Total Equity and Liabilities | B61: =B49+B60+B40 -> 120899 | C61: =C49+C60+C40 -> 130759 | D61: =D49+D60+D40 -> 141514 | E61: =E49+E60+E40 -> 143651 | F61: =F49+F60+F40 -> 146449 | V61: Contract liabilities | W61: 1877.5 | X61: 2253.5 | Y61: 2791.5 | Z61: 2268.2 | AA61: 1765.3 | AC61: Total current liabilities | AD61: =SUM(AD52,AD54:AD60) -> 2331.2 | AE61: =SUM(AE52,AE54:AE60) -> 2632.3 | AF61: =SUM(AF52,AF54:AF60) -> 5092.3 | AG61: =SUM(AG52,AG54:AG60) -> 5482.6 | AH61: =SUM(AH52,AH54:AH60) -> 5743.2
V62: Current tax liabilities (net) | W62: 1173.1 | X62: 1732.4 | Y62: 1323.1 | Z62: 1884.6 | AA62: 2175.6 | AC62: Total Equity and liabilities | AD62: =AD40+AD49+AD61 -> 8824.9 | AE62: =AE40+AE49+AE61 -> 10709.1 | AF62: =AF40+AF49+AF61 -> 20582.4 | AG62: =AG40+AG49+AG61 -> 23496.1 | AH62: =AH40+AH49+AH61 -> 27563
V63: Other current liabilities | W63: 650.3 | X63: 975 | Y63: 1208.4 | Z63: 1433 | AA63: 1523.8
V64: Short term provisions | W64: 1336.3 | X64: 1783.6 | Y64: 1808.1 | Z64: 1843.4 | AA64: 1802.8
A65: Working capital | B65: =B32-B60 -> 63177 | F65: =F32-F60 -> 66880 | V65: Total current liabilities | W65: =SUM(W56:W64) -> 21639.3 | X65: =SUM(X56:X64) -> 23004 | Y65: =SUM(Y56:Y64) -> 30832.9 | Z65: =SUM(Z56:Z64) -> 26775.3 | AA65: =SUM(AA56:AA64) -> 25245.8 | AD65: =AD31-AD61 -> 3997.8 | AG65: =AG31-AG61 -> 11703.2 | AH65: =AH31-AH61 -> 13103.2
V66: Total Equity and Liabilities | W66: =W41+W53+W65 -> 81278.9 | X66: =X41+X53+X65 -> 82732.2 | Y66: =Y41+Y53+Y65 -> 107505.4 | Z66: =Z41+Z53+Z65 -> 117133.7 | AA66: =AA41+AA53+AA65 -> 114790.6
W68: =W33-W65 -> 30345.8 | Z68: =Z33-Z65 -> 39334.3 | AA68: =AA33-AA65 -> 39820.4

Sheet Income Statement
A1: Consolidated Income Statement | E1: #VALUE! | H1: Consolidated Income Statement | L1: #VALUE! | O1: Consolidated Income Statement | S1: #VALUE! | V1: Consolidated Income Statement | Z1: #VALUE! | AC1: Consolidated Income Statement | AG1: #VALUE!
A2: Particulars | B2: 2020 | C2: 2021 | D2: 2022 | E2: 2023 | F2: 2024 | H2: Particulars | I2: 2020 | J2: 2021 | K2: 2022 | L2: 2023 | M2: 2024 | O2: Particulars | P2: 2020 | Q2: 2021 | R2: 2022 | S2: 2023 | T2: 2024 | V2: Particulars | W2: 2020 | X2: 2021 | Y2: 2022 | Z2: 2023 | AA2: 2024 | AC2: Particulars | AD2: 2020 | AE2: 2021 | AF2: 2022 | AG2: 2023 | AH2: 2024
A3: Revenue from Operations | B3: 156949 | C3: 164177 | D3: 191754 | E3: 225458 | F3: 240893 | H3: Revenue from Operations | I3: 90791 | J3: 100472 | K3: 121641 | L3: 146767 | M3: 162990 | O3: Revenue from operations | P3: 70676 | Q3: 75379 | R3: 85651 | S3: 101456 | T3: 109913 | V3: Revenue from operations | W3: 61023.2 | X3: 61943 | Y3: 79093.4 | Z3: 90487.6 | AA3: 89760.3 | AC3: Revenue from operations | AD3: 10878.6 | AE3: 12369.8 | AF3: 26108.7 | AG3: 33183 | AH3: 35517
A4: Other Income | B4: 4592 | C4: 3134 | D4: 4018 | E4: 3449 | F4: 4422 | H4: Other income | I4: 2803 | J4: 2201 | K4: 2295 | L4: 2701 | M4: 3600 | O4: Other income | P4: 589 | Q4: 927 | R4: 1067 | S4: 1358 | T4: 1495 | V4: Other operating income | W4: 114.4 | X4: -8.1 | Y4: 218.6 | Z4: 0 | AA4: 0 | AC4: Other income | AD4: 329.2 | AE4: 274.4 | AF4: 765.8 | AG4: 556.9 | AH4: 701.9
A5: Total Income | B5: =B3+B4 -> 161541 | C5: =C3+C4 -> 167311 | D5: =D3+D4 -> 195772 | E5: =E3+E4 -> 228907 | F5: =F3+F4 -> 245315 | H5: Total income | I5: =I3+I4 -> 93594 | J5: =J3+J4 -> 102673 | K5: =K3+K4 -> 123936 | L5: =L3+L4 -> 149468 | M5: =M3+M4 -> 166590 | O5: Total Income | P5: =P3+P4 -> 71265 | Q5: =Q3+Q4 -> 76306 | R5: =R3+R4 -> 86718 | S5: =S3+S4 -> 102814 | T5: =T3+T4 -> 111408 | V5: Other income | W5: 2725 | X5: 2390.7 | Y5: 2061.2 | Z5: 2274.6 | AA5: 2630.8 | AC5: Total income | AD5: =AD3+AD4 -> 11207.8 | AE5: =AE3+AE4 -> 12644.2 | AF5: =AF3+AF4 -> 26874.5 | AG5: =AG3+AG4 -> 33739.9 | AH5: =AH3+AH4 -> 36218.9
A6: Expenses | H6: Expenses | O6: Expenses | V6: Total income | W6: =SUM(W3:W5) -> 63862.6 | X6: =SUM(X3:X5) -> 64325.6 | Y6: =SUM(Y3:Y5) -> 81373.2 | Z6: =SUM(Z3:Z5) -> 92762.2 | AA6: =SUM(AA3:AA5) -> 92391.1 | AC6: Expenses
A7: Employee benefit expenses | B7: 85952 | C7: 91814 | D7: 107554 | E7: 127522 | F7: 140131 | H7: Employee benefit expenses | I7: 50887 | J7: 55541 | K7: 63986 | L7: 78359 | M7: 85950 | O7: Purchase of stock-in-trade | P7: 1536 | Q7: 1698 | R7: 1473 | S7: 2072 | T7: 1754 | V7: Expenses | AC7: Employee benefit expenses | AD7: 6516.6 | AE7: 7428.9 | AF7: 15989.2 | AG7: 20879.9 | AH7: 22732.3
A8: Cost of equipments and software licenses | B8: 1905 | C8: 1462 | D8: 1163 | E8: 1881 | F8: 3702 | H8: Cost of technical sub contractors | I8: 6714 | J8: 7084 | K8: 12606 | L8: 14062 | M8: 12937 | O8: Changes in inventories of stock in trade | P8: 0 | Q8: -3 | R8: -67 | S8: -67 | T8: 43 | V8: Purchase of stock in trade | W8: 936 | X8: 695.7 | Y8: 673.5 | Z8: 649.4 | AA8: 383.2 | AC8: Operating expenses | AD8: 2150.6 | AE8: 2019.4 | AF8: 2359.1 | AG8: 2828.6 | AH8: 2559.9
A9: Finance costs | B9: 924 | C9: 637 | D9: 784 | E9: 779 | F9: 778 | H9: Travel expenses | I9: 2710 | J9: 554 | K9: 827 | L9: 1525 | M9: 1894 | O9: Employee benefit expenses | P9: 34928 | Q9: 38853 | R9: 46130 | S9: 55280 | T9: 62480 | V9: Changes in inventories of finished goods and stock in trade | W9: 202.2 | X9: 31.5 | Y9: -36.9 | Z9: 15 | AA9: 27.8 | AC9: Finance costs | AD9: 82.6 | AE9: 78.8 | AF9: 123.4 | AG9: 150.4 | AH9: 221.7
A10: Depreciation and ammortisation expenses | B10: 3529 | C10: 4065 | D10: 4604 | E10: 5022 | F10: 4985 | H10: Cost of software package and others | I10: 2703 | J10: 4223 | K10: 6811 | L10: 10902 | M10: 15911 | O10: Finance cost | P10: 505 | Q10: 511 | R10: 12515 | S10: 14950 | T10: 14578 | V10: Employee benefit expenses | W10: 32657.1 | X10: 33237.1 | Y10: 45007.5 | Z10: 53764.4 | AA10: 54930.1 | AC10: Depreciation and ammortization expenses | AD10: 273 | AE10: 332.5 | AF10: 597.1 | AG10: 722.7 | AH10: 818.9
A11: Other expenses | B11: 26983 | C11: 24355 | D11: 29980 | E11: 36796 | F11: 32764 | H11: Communication expenses | I11: 528 | J11: 634 | K11: 611 | L11: 713 | M11: 620 | O11: Depreciation, ammortization and impairment expenses | P11: 3420 | Q11: 4611 | R11: 319 | S11: 353 | T11: 553 | V11: Finance cost | W11: 732.8 | X11: 508.8 | Y11: 532.5 | Z11: 1007.7 | AA11: 1255.2 | AC11: Other expenses | AD11: 182.1 | AE11: 196.4 | AF11: 2511.8 | AG11: 3366.8 | AH11: 3837.4
A12: Total Expenses | B12: =SUM(B7:B11) -> 119293 | C12: =SUM(C7:C11) -> 122333 | D12: =SUM(D7:D11) -> 144085 | E12: =SUM(E7:E11) -> 172000 | F12: =SUM(F7:F11) -> 182360 | H12: Consultancy and professional charges | I12: 1326 | J12: 1261 | K12: 1885 | L12: 1684 | M12: 1655 | O12: Outsourcing costs | P12: 10700 | Q12: 10158 | R12: 4326 | S12: 4145 | T12: 4173 | V12: Depreciation, ammortization and impairment expenses | W12: 2085.5 | X12: 2763.4 | Y12: 3077.8 | Z12: 3340.2 | AA12: 3407.1 | AC12: Total expenses | AD12: =SUM(AD7:AD11) -> 9204.9 | AE12: =SUM(AE7:AE11) -> 10056 | AF12: =SUM(AF7:AF11) -> 21580.6 | AG12: =SUM(AG7:AG11) -> 27948.4 | AH12: =SUM(AH7:AH11) -> 30170.2
A13: Profit before exceptional items and tax | B13: =B5-B12 -> 42248 | C13: =C5-C12 -> 44978 | D13: =D5-D12 -> 51687 | E13: =E5-E12 -> 56907 | F13: =F5-F12 -> 62955 | H13: Depreciation and ammortization expenses | I13: 2893 | J13: 3267 | K13: 3476 | L13: 4225 | M13: 4812 | O13: Other expenses | P13: 6196 | Q13: 4625 | R13: =5070-(-1) -> 5071 | S13: =6593 -> 6593 | T13: 6860 | V13: Sub-contracting/technical fees/third party application | W13: 9052.1 | X13: 8360.9 | Y13: 10858.9 | Z13: 11524.7 | AA13: 10303 | AC13: Profit before tax | AD13: =AD5-AD12 -> 2002.9 | AE13: =AE5-AE12 -> 2588.2 | AF13: =AF5-AF12 -> 5293.9 | AG13: =AG5-AG12 -> 5791.5 | AH13: =AH5-AH12 -> 6048.7
A14: Exceptional items | H14: Finance cost | I14: 170 | J14: 195 | K14: 200 | L14: 284 | M14: 416 | O14: Total expenses | P14: =SUM(P7:P13) -> 57285 | Q14: =SUM(Q7:Q13) -> 60453 | R14: =SUM(R7:R13) -> 69767 | S14: =SUM(S7:S13) -> 83326 | T14: =SUM(T7:T13) -> 90441 | V14: Facility expenses | W14: 1973.3 | X14: 2025.5 | Y14: 2526.9 | Z14: 1349.2 | AA14: 1455.6 | AC14: Tax expense
A15: Provision towards legal claim | B15: 0 | C15: 1218 | D15: 0 | E15: 0 | F15: 958 | H15: Other expenses | I15: 3656 | J15: 3286 | K15: 3424 | L15: 4392 | M15: 4787 | O15: Profit before tax | P15: =P5-P14 -> 13980 | Q15: =Q5-Q14 -> 15853 | R15: =R5-R14 -> 16951 | S15: =S5-S14 -> 19488 | T15: =T5-T14 -> 20967 | V15: Travel | W15: 1816.9 | X15: 525.8 | Y15: 732 | Z15: 1444.5 | AA15: 1510.2 | AC15: Current tax | AD15: 391.3 | AE15: 631.4 | AF15: 1359.8 | AG15: 1439.1 | AH15: 1460
A16: Profit before tax | B16: =B13-B15 -> 42248 | C16: =C13-C15 -> 43760 | D16: =D13-D15 -> 51687 | E16: =E13-E15 -> 56907 | F16: =F13-F15 -> 61997 | H16: Total expenses | I16: =SUM(I7:I15) -> 71587 | J16: =SUM(J7:J15) -> 76045 | K16: =SUM(K7:K15) -> 93826 | L16: =SUM(L7:L15) -> 116146 | M16: =SUM(M7:M15) -> 128982 | O16: Tax expenses | V16: Communication | W16: 481.2 | X16: 606.9 | Y16: 576 | Z16: 591.1 | AA16: 487.8 | AC16: Deferred tax | AD16: 91.1 | AE16: 18.6 | AF16: -15.9 | AG16: -57.9 | AH16: 4.1
A17: Tax expenses | H17: Profit before tax | I17: =I5-I16 -> 22007 | J17: =J5-J16 -> 26628 | K17: =K5-K16 -> 30110 | L17: =L5-L16 -> 33322 | M17: =M5-M16 -> 37608 | O17: Current tax | P17: 2821 | Q17: 3719 | R17: 3442 | S17: 4665 | T17: 4626 | V17: Marketing and brand building | W17: 253.2 | X17: 556.1 | Y17: 756.1 | Z17: 295.1 | AA17: 355.5 | AC17: Total tax expenses | AD17: =SUM(AD15:AD16) -> 482.4 | AE17: =SUM(AE15:AE16) -> 650 | AF17: =SUM(AF15:AF16) -> 1343.9 | AG17: =SUM(AG15:AG16) -> 1381.2 | AH17: =SUM(AH15:AH16) -> 1464.1
A18: Current tax | B18: 10378 | C18: 11635 | D18: 13654 | E18: 14757 | F18: 15864 | H18: Tax expense | O18: Deferred tax | P18: 102 | Q18: 965 | R18: -14 | S18: -22 | T18: 631 | V18: Legal and professional charges | W18: 473.3 | X18: 101.1 | Y18: 201 | Z18: 1328.8 | AA18: 955.9 | AC18: Profit/Loss for the year | AD18: =AD13-AD17 -> 1520.5 | AE18: =AE13-AE17 -> 1938.2 | AF18: =AF13-AF17 -> 3950 | AG18: =AG13-AG17 -> 4410.3 | AH18: =AH13-AH17 -> 4584.6
A19: Deferred tax | B19: -577 | C19: -437 | D19: -416 | E19: -153 | F19: 34 | H19: Current tax | I19: 5775 | J19: 6672 | K19: 7811 | L19: 9287 | M19: 12130 | O19: Total tax expense | P19: =P17+P18 -> 2923 | Q19: =Q17+Q18 -> 4684 | R19: =R17+R18 -> 3428 | S19: =S17+S18 -> 4643 | T19: =T17+T18 -> 5257 | V19: Allowance for lifetime expected credit loss | W19: 104.3 | X19: 150.6 | Y19: -79.7 | Z19: -60.4 | AA19: 64
A20: Total tax expense | B20: =B18+B19 -> 9801 | C20: =C18+C19 -> 11198 | D20: =D18+D19 -> 13238 | E20: =E18+E19 -> 14604 | F20: =F18+F19 -> 15898 | H20: Deferred tax | I20: -407 | J20: 533 | K20: 153 | L20: -73 | M20: -1272 | O20: Profit for the year | P20: =P15-P19 -> 11057 | Q20: =Q15-Q19 -> 11169 | R20: =R15-R19 -> 13523 | S20: =S15-S19 -> 14845 | T20: =T15-T19 -> 15710 | V20: Other expenses | W20: 845.7 | X20: 872.3 | Y20: 1412.5 | Z20: =869.4+1871.7 -> 2741.1 | AA20: =673.6+1837.8 -> 2511.4 | AD20: =AD13+AD9 -> 2085.5 | AH20: =AH13+AH9 -> 6270.4
A21: Profit for the year | B21: =B16-B20 -> 32447 | C21: =C16-C20 -> 32562 | D21: =D16-D20 -> 38449 | E21: =E16-E20 -> 42303 | F21: =F16-F20 -> 46099 | H21: Total tax expense | I21: =I19+I20 -> 5368 | J21: =J19+J20 -> 7205 | K21: =K19+K20 -> 7964 | L21: =L19+L20 -> 9214 | M21: =M19+M20 -> 10858 | V21: Total expenses | W21: =SUM(W8:W20) -> 51613.6 | X21: =SUM(X8:X20) -> 50435.7 | Y21: =SUM(Y8:Y20) -> 66238.1 | Z21: =SUM(Z8:Z20) -> 77990.8 | AA21: =SUM(AA8:AA20) -> 77646.8
H22: Profit for the period | I22: =I17-I21 -> 16639 | J22: =J17-J21 -> 19423 | K22: =K17-K21 -> 22146 | L22: =L17-L21 -> 24108 | M22: =M17-M21 -> 26750 | V22: Share of net profit/loss of associates | W22: 2.9 | X22: 13 | Y22: 5.7 | Z22: -5.7 | AA22: -23.3
V23: Profit before tax | W23: =W6-W21+W22 -> 12251.9 | X23: =(X6-X21)+X22 -> 13902.9 | Y23: =(Y6-Y21)+Y22 -> 15140.8 | Z23: =(Z6-Z21)+Z22 -> 14765.7 | AA23: =(AA6-AA21)+AA22 -> 14721
P24: =P15+P10 -> 14485 | T24: =T15+T10 -> 35545 | V24: Tax expense
A25: EBIT | B25: =B13+B9 -> 43172 | F25: =F13+F9 -> 63733 | I25: =I17+I14 -> 22177 | M25: =M17+M14 -> 38024 | V25: Current tax | W25: 2432.4 | X25: 2606.5 | Y25: 3241.5 | Z25: 3219.8 | AA25: 3497.3
V26: Deferred tax | W26: 47.7 | X26: 428.4 | Y26: -344.1 | Z26: 179.4 | AA26: 111.6
V27: Total tax expense | W27: =W25+W26 -> 2480.1 | X27: =X25+X26 -> 3034.9 | Y27: =Y25+Y26 -> 2897.4 | Z27: =Z25+Z26 -> 3399.2 | AA27: =AA25+AA26 -> 3608.9
V28: Profit for the year | W28: =W23-W27 -> 9771.8 | X28: =X23-X27 -> 10868 | Y28: =Y23-Y27 -> 12243.4 | Z28: =Z23-Z27 -> 11366.5 | AA28: =AA23-AA27 -> 11112.1
W31: =W23+W11 -> 12984.7 | AA31: =AA23+AA11 -> 15976.2

Sheet Cash flow statement
A1: Consolidated Cash flow Statement | E1: #VALUE! | H1: Consolidated Cash flow Statement | L1: #VALUE! | O1: Consolidated Cash flow Statement | S1: #VALUE! | V1: Consolidated Cash flow Statement | Z1: #VALUE! | AC1: Consolidated Cash flow Statement | AG1: #VALUE!
A2: Particulars | B2: 2020 | C2: 2021 | D2: 2022 | E2: 2023 | F2: 2024 | H2: Particulars | I2: 2020 | J2: 2021 | K2: 2022 | L2: 2023 | M2: 2024 | O2: Particulars | P2: 2020 | Q2: 2021 | R2: 2022 | S2: 2023 | T2: 2024 | V2: Particulars | W2: 2020 | X2: 2021 | Y2: 2022 | Z2: 2023 | AA2: 2024 | AC2: Particulars | AD2: 2020 | AE2: 2021 | AF2: 2022 | AG2: 2023 | AH2: 2024
A3: Profit for the year | B3: 32447 | C3: 32562 | D3: 38449 | E3: 42303 | F3: 46099 | H3: Profit for the period | I3: 16639 | J3: 19423 | K3: 22146 | L3: 24108 | M3: 26248 | O3: Profits before tax | P3: 13980 | Q3: 15853 | R3: 16951 | S3: 19488 | T3: 20967 | V3: Profit/Loss for the year | W3: 9771.8 | X3: 10868 | Y3: 12243.4 | Z3: 11366.5 | AA3: 11112.1 | AC3: Net profit after tax | AD3: 1520.5 | AE3: 1938.2 | AF3: 3950 | AG3: 4410.3 | AH3: 4584.6
A4: Adjustments: | H4: Adjustments: | O4: Adjustments for: | V4: Adjustments: | AC4: Adjustments:
A5: Depreciation and ammortization | B5: 3529 | C5: 4065 | D5: 4604 | E5: 5022 | F5: 4985 | H5: Income tax expense | I5: 5368 | J5: 7205 | K5: 7964 | L5: 9214 | M5: 9740 | O5: Depreciation, ammortization and impairment expense | P5: 3420 | Q5: 4611 | R5: 4326 | S5: 4145 | T5: 4173 | V5: Gain on sale of PPE and intangibles assets,net | W5: -1.1 | X5: -51.6 | Y5: -31.3 | Z5: -8.9 | AA5: -207.2 | AC5: Depreciation and ammortization expense | AD5: 273 | AE5: 332.5 | AF5: 597.1 | AG5: 722.7 | AH5: 818.9
A6: Bad debts and advances written off | B6: 144 | C6: 201 | D6: 135 | E6: 140 | F6: 114 | H6: Depreciation and ammortization | I6: 2893 | J6: 3267 | K6: 3476 | L6: 4225 | M6: 4678 | O6: Interest income | P6: -441 | Q6: -645 | R6: -583 | S6: -769 | T6: -1273 | V6: Depreciation, ammortization and impairment | W6: 2085.5 | X6: 2763.4 | Y6: 3077.8 | Z6: 3340.2 | AA6: 3407.1 | AC6: Income tax expense | AD6: 482.4 | AE6: 650 | AF6: 1343.9 | AG6: 1381.2 | AH6: 1464.1
A7: Provision towards legal claim | B7: 0 | C7: 1218 | D7: 0 | E7: 0 | F7: 0 | H7: Interest and dividend income | I7: -1613 | J7: -1615 | K7: -1645 | L7: -1817 | M7: -2067 | O7: Provision for doubtful debts | P7: 200 | Q7: 19 | R7: 21 | S7: 25 | T7: 117 | V7: Unrealized exchange gain/loss, net and exchange gain/loss on borrowings | W7: 637.6 | X7: -225.1 | Y7: -102.1 | Z7: 15.2 | AA7: 65.5 | AC7: Expense recognised in respect of equity settled stock option | AD7: 31.9 | AE7: 16.8 | AF7: 53.8 | AG7: 113.6 | AH7: 124.4
A8: Tax expense | B8: 9801 | C8: 11198 | D8: 13238 | E8: 14604 | F8: 15898 | H8: Finance cost | I8: 170 | J8: 195 | K8: 200 | L8: 284 | M8: 470 | O8: Income on investments carried at fair value | P8: -94 | Q8: -97 | R8: -104 | S8: -106 | T8: -165 | V8: Share based compensation expenses | W8: 126.2 | X8: 231 | Y8: 411 | Z8: 396.9 | AA8: 558.4 | AC8: Income from investments | AD8: -103.7 | AE8: -98.2 | AF8: -204 | AG8: -167 | AH8: -314
A9: Net gain on lease | B9: -14 | C9: -100 | D9: =-7+9 -> 2 | E9: 2 | F9: -7 | H9: Impairment loss recognised/reversed | I9: 161 | J9: 190 | K9: 170 | L9: 283 | M9: 121 | O9: Profits on sale of investments | P9: -16 | Q9: -3 | R9: -10 | S9: 0 | T9: 0 | V9: Share of net profit/loss of associates accounted for using equity method | W9: -2.9 | X9: -13 | Y9: -5.7 | Z9: 5.7 | AA9: 23.3 | AC9: Interest income | AD9: -17.9 | AE9: -56 | AF9: -86.8 | AG9: -173.6 | AH9: -301.4
A10: Unrealised foreign exchange gain | B10: -117 | C10: -21 | D10: -120 | E10: -189 | F10: -17 | H10: Exchange differences on translation | I10: 184 | J10: -62 | K10: 119 | L10: 161 | M10: 76 | O10: Interest expense | P10: 251 | Q10: 298 | R10: 225 | S10: 238 | T10: 269 | V10: Income tax expense | W10: 2480.1 | X10: 3034.9 | Y10: 2897.4 | Z10: 3399.2 | AA10: 3608.9 | AC10: Finance costs | AD10: -6.4 | AE10: -16.2 | AF10: 123.4 | AG10: 150.4 | AH10: 221.7
A11: Net gain on disposal of PPE | B11: -46 | C11: -13 | D11: -23 | E11: -26 | F11: -7 | H11: Stock compensation expense | I11: 249 | J11: 333 | K11: 415 | L11: 519 | M11: 652 | O11: Profit on sale of PPE (net) | P11: 0 | Q11: -102 | R11: -15 | S11: -162 | T11: -4 | V11: Dividend and interest income/expenses, net | W11: -1894.5 | X11: -1661.4 | Y11: =-944.7-30.1 -> -974.8 | Z11: -810.8 | AA11: -1134.4 | AC11: Allowance for expected credit loss | AD11: 82.6 | AE11: 78.8 | AF11: -9.4 | AG11: -60.6 | AH11: 76.5
A12: Net gain on investments | B12: -214 | C12: -204 | D12: -198 | E12: -224 | F12: -312 | H12: Other adjustments | I12: -131 | J12: -91 | K12: 76 | L12: 628 | M12: =-1934+75+1464 -> -395 | O12: Other non-cash charges (net) | P12: 177 | Q12: 88 | R12: =81+1-1 -> 81 | S12: =308-170+15 -> 153 | T12: =-41+312 -> 271 | V12: Gain on sale of business and loss control in subsidiary, net | W12: -114.4 | X12: 8.1 | Y12: -218.6 | Z12: =-167.1+6 -> -161.1 | AA12: =-130+488 -> 358 | AC12: Unrealised foreign exchange loss/gain, net | AD12: -0.3 | AE12: -17.6 | AF12: 47 | AG12: 69.5 | AH12: 26.3
A13: Interest income | B13: -3562 | C13: -2504 | D13: -2663 | E13: -3248 | F13: -3781 | H13: Changes in assets and liabilities | O13: Net change in | V13: Changes in operating assets and liabilities | AC13: Change in fair value of contingent consideration | AD13: 23.6 | AE13: 23.2 | AF13: 7.1 | AG13: -55.6 | AH13: 0
A14: Dividend income | B14: -10 | C14: -8 | D14: -4 | E14: -15 | F14: -41 | H14: Trade receivables and unbilled revenue | I14: -3861 | J14: -1835 | K14: -7937 | L14: -7076 | M14: -2667 | O14: Trade receivables | P14: -1957 | Q14: 633 | R14: -2809 | S14: -3240 | T14: 248 | V14: Trade receivables | W14: -332.7 | X14: 1284.8 | Y14: -1183.3 | Z14: -98.5 | AA14: 846.4 | AC14: Gain from modification in leases | AD14: 0 | AE14: =-59.2-8.3-14.5 -> -82 | AF14: -2.1 | AG14: -8.3 | AH14: -51.3
A15: Finance costs | B15: 924 | C15: 637 | D15: 784 | E15: 779 | F15: 778 | H15: Loans, other financial assets and other assets | I15: 76 | J15: -534 | K15: -1914 | L15: -3108 | M15: -1172 | O15: Inventories | P15: 24 | Q15: 72 | R15: 207 | S15: -37 | T15: 60 | V15: Unbilled receivables and contract assets | W15: -356.1 | X15: -106.2 | Y15: -3139.6 | Z15: 155.8 | AA15: 591.9 | AC15: Net gain on sale of PPE | AD15: 0.9 | AE15: -0.3 | AF15: -2.7 | AG15: -1.8 | AH15: -7.1
A16: Operating profit before working capital changes | B16: =SUM(B3,B5:B15) -> 42882 | C16: =SUM(C3,C5:C15) -> 47031 | D16: =SUM(D3,D5:D15) -> 54204 | E16: =SUM(E3,E5:E15) -> 59148 | F16: =SUM(F3,F5:F15) -> 63709 | H16: Trade payables | I16: -373 | J16: -245 | K16: 1489 | L16: -279 | M16: 91 | O16: Other financial assets and other assets | P16: -1229 | Q16: 344 | R16: 219 | S16: 917 | T16: 164 | V16: Inventories | W16: 208.5 | X16: 80.3 | Y16: -25.6 | Z16: 16.2 | AA16: 28.7 | AC16: Operating profit before working capital changes | AD16: =SUM(AD3,AD5:AD15) -> 2286.6 | AE16: =SUM(AE3,AE5:AE15) -> 2769.2 | AF16: =SUM(AF3,AF5:AF15) -> 5817.3 | AG16: =SUM(AG3,AG5:AG15) -> 6380.8 | AH16: =SUM(AH3,AH5:AH15) -> 6642.7
A17: Net change in | H17: Other financial liabilities, other liabilities and provisions | I17: 1791 | J17: 3382 | K17: 6938 | L17: 4119 | M17: -1334 | O17: Trade payables | P17: -208 | Q17: 538 | R17: 718 | S17: -175 | T17: -681 | V17: Other assets | W17: -8 | X17: 93.1 | Y17: -653 | Z17: 105.5 | AA17: 886.9 | AC17: Change in working capital
A18: Inventories | B18: 5 | C18: -3 | D18: -12 | E18: -8 | F18: 0 | H18: Cash generated from operations | I18: =SUM(I3,I5:I12,I14:I17) -> 21553 | J18: =SUM(J3,J5:J12,J14:J17) -> 29613 | K18: =SUM(K3,K5:K12,K14:K17) -> 31497 | L18: =SUM(L3,L5:L12,L14:L17) -> 31261 | M18: =SUM(M3,M5:M12,M14:M17) -> 34441 | O18: Provisions, other financial liabilities and other liabilities | P18: 1810 | Q18: 1454 | R18: 1116 | S18: 1230 | T18: 2514 | V18: Trade payables, other liabilities and provisions | W18: -1240.1 | X18: 569.8 | Y18: 969.5 | Z18: -982.4 | AA18: -43.5 | AC18: Decrease in inventories | AD18: -313.1 | AE18: -20.3 | AF18: 0.5 | AG18: 0.8 | AH18: 0.3
A19: Trade receivables | B19: -3295 | C19: 1260 | D19: -4210 | E19: -6501 | F19: -3327 | H19: Income tax paid | I19: -4550 | J19: -6389 | K19: -7612 | L19: -8794 | M19: -9231 | O19: Cash generated from operations | P19: =SUM(P3,P5:P12,P14:P18) -> 15917 | Q19: =SUM(Q3,Q5:Q12,Q14:Q18) -> 23063 | R19: =SUM(R3,R5:R12,R14:R18) -> 20343 | S19: =SUM(S3,S5:S12,S14:S18) -> 21707 | T19: =SUM(T3,T5:T12,T14:T18) -> 26660 | V19: Contract liabilities | W19: -657.2 | X19: 370.4 | Y19: 383.2 | Z19: -652.2 | AA19: -505.3 | AC19: Decrease/Increase in trade receivables and unbilled revenue | AD19: -278.6 | AE19: -196.8 | AF19: -1823.8 | AG19: -1969 | AH19: 504.6
A20: Unbilled receivables | B20: -508 | C20: -201 | D20: -934 | E20: -1182 | F20: -5 | H20: Net cash generated by operating activities | I20: =I18+I19 -> 17003 | J20: =J18+J19 -> 23224 | K20: =K18+K19 -> 23885 | L20: =L18+L19 -> 22467 | M20: =M18+M19 -> 25210 | O20: Income tax paid | P20: -2558 | Q20: -3445 | R20: -3443 | S20: -3698 | T20: -4212 | V20: Cash generated from operations | W20: =SUM(W3,W5:W19) -> 10702.7 | X20: =SUM(X3,X5:X19) -> 17246.5 | Y20: =SUM(Y3,Y5:Y19) -> 13648.3 | Z20: =SUM(Z3,Z5:Z19) -> 16087.3 | AA20: =SUM(AA3,AA5:AA19) -> 19596.8 | AC20: Increase in other assets | AD20: 0 | AE20: 0 | AF20: -186.4 | AG20: -208.5 | AH20: -329.7
A21: Loans and other financial assets | B21: -2 | C21: -17 | D21: -116 | E21: 261 | F21: -301 | H21: CASH FLOW FROM INVESTING ACTIVITIES | O21: Net cash flow from operating activities | P21: =P19+P20 -> 13359 | Q21: =Q19+Q20 -> 19618 | R21: =R19+R20 -> 16900 | S21: =S19+S20 -> 18009 | T21: =T19+T20 -> 22448 | V21: Income tax paid | W21: -638.4 | X21: -2491.5 | Y21: -2568.6 | Z21: -3021.8 | AA21: -1536 | AC21: Increase in trade and other liabilities | AD21: 360.4 | AE21: 487.5 | AF21: 790.9 | AG21: 412.2 | AH21: 422.3
A22: Other assets | B22: -3492 | C22: -2805 | D22: 807 | E22: -25 | F22: -3160 | H22: Expenditure on PPE and intangibles | I22: -3307 | J22: -2107 | K22: -2161 | L22: -2579 | M22: -2201 | O22: CASH FLOW FROM INVESTING ACTIVITIES | V22: Net cash flow from operating activties | W22: =W20+W21 -> 10064.3 | X22: =X20+X21 -> 14755 | Y22: =Y20+Y21 -> 11079.7 | Z22: =Z20+Z21 -> 13065.5 | AA22: =AA20+AA21 -> 18060.8 | AC22: Decrease/Increase in working capital | AD22: =SUM(AD18:AD21) -> -231.3 | AE22: =SUM(AE18:AE21) -> 270.4 | AF22: =SUM(AF18:AF21) -> -1218.8 | AG22: =SUM(AG18:AG21) -> -1764.5 | AH22: =SUM(AH18:AH21) -> 597.5
A23: Trade payables | B23: 446 | C23: -93 | D23: 186 | E23: 2036 | F23: -632 | H23: Deposits placed with corporation | I23: -108 | J23: -207 | K23: =-906+753 -> -153 | L23: =-996+762 -> -234 | M23: -847 | O23: Investments in bank deposits | P23: -265 | Q23: -2427 | R23: -2625 | S23: -8346 | T23: -13924 | V23: CASH FLOW FROM INVESTING ACTIVITIES | AC23: Cash generated from operations | AD23: =SUM(AD16,AD22) -> 2055.3 | AE23: =SUM(AE16,AE22) -> 3039.6 | AF23: =SUM(AF16,AF22) -> 4598.5 | AG23: =SUM(AG16,AG22) -> 4616.3 | AH23: =SUM(AH16,AH22) -> 7240.2
A24: Unearned and deferred revenue | B24: 375 | C24: 1091 | D24: -103 | E24: 39 | F24: -740 | H24: Interest and dividend received | I24: 1929 | J24: 1418 | K24: 1898 | L24: 1525 | M24: 710 | O24: Proceeds from bank deposits on maturity | P24: 2074 | Q24: 188 | R24: 2866 | S24: 4484 | T24: 10315 | V24: Purchase of PPE | W24: -2349.7 | X24: -1957.7 | Y24: -2015.3 | Z24: -1483.4 | AA24: -1051 | AC24: Income tax paid | AD24: -411.8 | AE24: -640 | AF24: -1347.8 | AG24: -1521.7 | AH24: -1570.7
A25: Other financial liabilities | B25: 1208 | C25: 122 | D25: 1153 | E25: 1417 | F25: -695 | H25: Payments towards acquisition of business, net cash acq | I25: -1860 | J25: -1221 | K25: 0 | L25: -910 | M25: 1768 | O25: Purchase of investments in securities | P25: -35420 | Q25: -20792 | R25: -32574 | S25: -34620 | T25: -41674 | V25: Proceeds from sale of PPE | W25: 127 | X25: 75.3 | Y25: 73.6 | Z25: 54.6 | AA25: 402.2 | AC25: Net cash generated from operating activities | AD25: =AD23+AD24 -> 1643.5 | AE25: =AE23+AE24 -> 2399.6 | AF25: =AF23+AF24 -> 3250.7 | AG25: =AG23+AG24 -> 3094.6 | AH25: =AH23+AH24 -> 5669.5
A26: Other liabilties and provisions | B26: 596 | C26: 1509 | D26: 460 | E26: -254 | F26: 1978 | H26: Payments of contingent consideration pertaining of acq | I26: -6 | J26: -158 | K26: -53 | L26: -60 | M26: 0 | O26: Proceeds from sale/maturity of investments in securities | P26: 30785 | Q26: 21109 | R26: 33215 | S26: 35626 | T26: 40329 | V26: Purchase of investments | W26: -117824.7 | X26: -117225.1 | Y26: -101548.6 | Z26: -80663.2 | AA26: -97506.9 | AC26: CASH FLOW FROM INVESTING ACTIVITIES
A27: Cash generated from operations | B27: =SUM(B18:B26,B16) -> 38215 | C27: =SUM(C18:C26,C16) -> 47894 | D27: =SUM(D18:D26,D16) -> 51435 | E27: =SUM(E18:E26,E16) -> 54931 | F27: =SUM(F18:F26,F16) -> 56827 | H27: Redemption of escrow pertaining to buyback | I27: 257 | J27: 0 | K27: =-420+420 -> 0 | L27: =-483+483 -> 0 | M27: -101 | O27: Investments in equity instruments | P27: -15 | Q27: -3 | R27: -1 | S27: 0 | T27: -8 | V27: Proceeds from sale of investments | W27: 121282.6 | X27: 118905.9 | Y27: 95373.5 | Z27: 74088.5 | AA27: 97859.8 | AC27: Purchase of PPE | AD27: -246.5 | AE27: -271.9 | AF27: -1057.3 | AG27: -939.3 | AH27: -843.2
A28: Taxes paid | B28: -5846 | C28: -9092 | D28: -11486 | E28: -12966 | F28: -12489 | H28: Other receipts | I28: 46 | J28: 49 | K28: 67 | L28: 71 | M28: 128 | O28: Deposits placed with body corporates | P28: -5015 | Q28: -6641 | R28: =-5478+40-9 -> -5447 | S28: =-2602+9 -> -2593 | T28: -1079 | V28: Proceeds from sale of hosted data centre services business and loss of control in subsidiary, net of related expenses and cash | W28: 0 | X28: 0 | Y28: 165.2 | Z28: 2741 | AA28: 0 | AC28: Sale of PPE | AD28: 3.9 | AE28: 5.4 | AF28: 4.4 | AG28: 4.7 | AH28: 10.2
A29: Net cash generated from Operating activities | B29: =B27+B28 -> 32369 | C29: =C27+C28 -> 38802 | D29: =D27+D28 -> 39949 | E29: =E27+E28 -> 41965 | F29: =F27+F28 -> 44338 | H29: Other payments | I29: 0 | J29: -45 | K29: -22 | L29: 0 | M29: 0 | O29: Proceeds from maturity of deposits placed with body corp | P29: 3261 | Q29: 5219 | R29: 7111 | S29: 3208 | T29: 1605 | V29: Payment for business acquisitions including deposits and escrow, net | W29: -1000.3 | X29: -987.3 | Y29: -12984.6 | Z29: -4556.6 | AA29: -529.1 | AC29: Purchase of Investments | AD29: -460.4 | AE29: -1461.1 | AF29: 14390.4 | AG29: 20638.5 | AH29: 28666.5
A30: CASH FLOW FROM INVESTING ACTIVITIES | H30: Payments to acquire investments | O30: Payments for business acquisitions, net of cash acquired | P30: -6091 | Q30: -1211 | R30: 0 | S30: -706 | T30: -2043 | V30: Proceeds from sale of business | W30: 745.9 | X30: 0 | Y30: -2741 | Z30: 1.1 | AA30: =-48.4+30 -> -18.4 | AC30: Sale of Investments | AD30: -10.3 | AE30: -40.8 | AF30: -14854.7 | AG30: -20012.8 | AH30: -31997
A31: Bank deposits placed | B31: -7663 | C31: -6605 | D31: -15947 | E31: -4548 | F31: -9471 | H31: Preference, equity securities and others | I31: -41 | J31: 0 | K31: 0 | L31: 0 | M31: 0 | O31: Purchase of non-controlling interest | P31: 0 | Q31: -12 | R31: 0 | S31: 0 | T31: 0 | V31: Interest received | W31: 2383.7 | X31: 1962.4 | Y31: 1227.5 | Z31: 1411.2 | AA31: 2011.1 | AC31: Payment towards contingent consideration | AD31: -48.8 | AE31: -1.8 | AF31: -42.7 | AG31: -49.6 | AH31: -5.9
A32: Inter-corporate deposits placed | B32: -14905 | C32: -21076 | D32: -14619 | E32: -8293 | F32: 0 | H32: Tax free bonds and government bonds | I32: -19 | J32: -318 | K32: 0 | L32: -27 | M32: 0 | O32: Investment in limited liability partnership | P32: -3 | Q32: -4 | R32: -2 | S32: -3 | T32: 0 | V32: Dividend received | W32: 36.7 | X32: 0.4 | Y32: 0.2 | Z32: 0.3 | AA32: 0.3 | AC32: Payment towards transfer of business under common control | AD32: 6.4 | AE32: 16 | AF32: -142.8 | AG32: -99 | AH32: 0
A33: Purchase of investments | B33: -80002 | C33: -54462 | D33: -75374 | E33: -129745 | F33: -141011 | H33: Liquid mutual funds and fixed maturity plan securities | I33: -34839 | J33: -35196 | K33: -54064 | L33: -70631 | M33: -66191 | O33: Distribution from LLP | P33: 1 | Q33: 0 | R33: 0 | S33: 1 | T33: 13 | V33: Cash generated from investing activities | W33: =SUM(W24:W32) -> 3401.2 | X33: =SUM(X24:X32) -> 773.9 | Y33: =SUM(Y24:Y32) -> -22449.5 | Z33: =SUM(Z24:Z32) -> -8406.5 | AA33: =SUM(AA24:AA32) -> 1168 | AC33: Interest received | AD33: 103.7 | AE33: 98.2 | AF33: 57.4 | AG33: 126.6 | AH33: 257.3
A34: Payment of purchase of PPE | B34: -2538 | C34: -2719 | D34: -2483 | E34: -2532 | F34: -2202 | H34: Non-convertible debentures | I34: -993 | J34: -3689 | K34: -1609 | L34: -249 | M34: -1526 | O34: Purchase of PPE and intangibles | P34: -1866 | Q34: -1904 | R34: -1645 | S34: -1661 | T34: -1048 | V34: CASH FLOW FROM FINANCING ACTIVITIES | AC34: Net cash used in Investing activities | AD34: =SUM(AD27:AD33) -> -652 | AE34: =SUM(AE27:AE33) -> -1656 | AF34: =SUM(AF27:AF33) -> -1645.3 | AG34: =SUM(AG27:AG33) -> -330.9 | AH34: =SUM(AH27:AH33) -> -3912.1
A35: Payment including advances for acquiring right of use assests | B35: -519 | C35: -101 | D35: -15 | E35: -213 | F35: -30 | H35: Certificates of deposits | I35: -1114 | J35: 0 | K35: -4184 | L35: -10348 | M35: -8509 | O35: Proceeds from sale of PPE | P35: 37 | Q35: 151 | R35: 90 | S35: 217 | T35: 32 | V35: Proceeds from issuance of equity shares and shares pending allotment | W35: 1.4 | X35: 0.6 | Y35: 0.6 | Z35: 1.2 | AA35: 1.3 | AC35: CASH FLOW FROM FINANCING ACTIVTIES
A36: Payments for purchase of intangible assets | B36: -192 | C36: -356 | D36: -497 | E36: -355 | F36: -442 | H36: Government securities | I36: -1561 | J36: -7510 | K36: -4254 | L36: -1569 | M36: -10387 | O36: Interest received | P36: 282 | Q36: 676 | R36: 590 | S36: 636 | T36: 1041 | V36: Repayment of borrowings | W36: -13238 | X36: -9720.6 | Y36: -19181 | Z36: -16891 | AA36: -13055.7 | AC36: Proceeds from issue of share capital | AD36: 0 | AE36: 0.1 | AF36: 0.2 | AG36: 1.2 | AH36: 1.2
A37: Proceeds from bank deposits | B37: 11965 | C37: 4767 | D37: 11950 | E37: 6252 | F37: 8089 | H37: Others | I37: -29 | J37: -25 | K37: =-24 -> -24 | L37: =-20-400-3003 -> -3423 | M37: -14 | O37: Income taxes paid | P37: -139 | Q37: -91 | R37: -101 | S37: -174 | T37: -282 | V37: Proceeds from borrowings | W37: 10634.2 | X37: 10341.8 | Y37: 26012 | Z37: 16103.4 | AA37: 12050 | AC37: Share issue expenses paid | AD37: 32 | AE37: 9.4 | AF37: 0 | AG37: -1 | AH37: 0
A38: Proceeds from inter-corporate deposits | B38: 14432 | C38: 18018 | D38: 19498 | E38: 13654 | F38: 846 | H38: Proceeds on sale of investments | O38: Net cash flow generated/used in investing activities | P38: =SUM(P23:P37) -> -12374 | Q38: =SUM(Q23:Q37) -> -5742 | R38: =SUM(R23:R37) -> 1477 | S38: =SUM(S23:S37) -> -3931 | T38: =SUM(T23:T37) -> -6723 | V38: Repayment of lease liabilities | W38: -678.4 | X38: -866 | Y38: -973 | Z38: -971.1 | AA38: -1006 | AC38: Net repayment of/proceeds from short term borrowings | AD38: -210.4 | AE38: 175.9 | AF38: 10.5 | AG38: 66.5 | AH38: -86.6
A39: Proceeds from disposal/redemption of investments | B39: 84089 | C39: 51630 | D39: =73852+3 -> 73855 | E39: =122687+2 -> 122689 | F39: =147204+3 -> 147207 | H39: Tax free bonds and government bonds | I39: 87 | J39: 0 | K39: 20 | L39: 221 | M39: 150 | O39: CASH FLOW FROM FINANCING ACTIVITIES | V39: Payment for deferred contingent consideration in respect of business combination | W39: 0 | X39: -9519.9 | Y39: -30.9 | Z39: -178.4 | AA39: -129.4 | AC39: Deposit under credit support agreement received/paid | AD39: -139.7 | AE39: -160.2 | AF39: -47.5 | AG39: -59.4 | AH39: 58.6
A40: Proceeds from disposal of PPE | B40: 161 | C40: 37 | D40: 31 | E40: =37+0 -> 37 | F40: =17+7 -> 24 | H40: Non-convertible debentures | I40: 1888 | J40: 1251 | K40: 2201 | L40: 470 | M40: 1230 | O40: Proceeds from long term borrowings | P40: 152 | Q40: 3752 | R40: 25 | S40: 36 | T40: 6 | V40: Payment for buy back of shares, including transaction cost | W40: -10531.1 | X40: -2144.5 | Y40: 0 | Z40: -870.8 | AA40: -1045.6 | AC40: Payment towards lease liabilities (net) | AD40: -4 | AE40: -2.1 | AF40: -200.4 | AG40: -227.1 | AH40: -247.8
A41: Interest received | B41: 3729 | C41: 2730 | D41: 2700 | E41: 3080 | F41: 2990 | H41: Government securities | I41: 1674 | J41: 2704 | K41: 1457 | L41: 1882 | M41: 304 | O41: Repayment of long term borrowings | P41: -394 | Q41: -3262 | R41: -85 | S41: -1884 | T41: -187 | V41: Interest paid | W41: -460.1 | X41: -333.5 | Y41: -508.9 | Z41: -3281.4 | AA41: -521.8 | AC41: Interest paid on lease liabilities | AD41: 0 | AE41: 0 | AF41: -109.5 | AG41: -111.7 | AH41: -128.3
A42: Dividend received | B42: 8 | C42: 8 | D42: 4 | E42: 13 | F42: 26 | H42: Commercial paper | I42: 500 | J42: 0 | K42: 0 | L42: 2298 | M42: 6479 | O42: Proceeds from short term borrowings | P42: 933 | Q42: 815 | R42: 52 | S42: 88 | T42: 352 | V42: Payment of cash dividend | W42: -686.3 | X42: -545.9 | Y42: -546.7 | Z42: 0 | AA42: -32.2 | AC42: Interest paid | AD42: -486.4 | AE42: -531.9 | AF42: -6 | AG42: -37.5 | AH42: -90.6
A43: Net cash generated from/used in investing activities | B43: =SUM(B31:B42) -> 8565 | C43: =SUM(C31:C42) -> -8129 | D43: =SUM(D31:D42) -> -897 | E43: =SUM(E31:E42) -> 39 | F43: =SUM(F31:F42) -> 6026 | H43: Certificates of deposits | I43: 2545 | J43: 1149 | K43: 787 | L43: 10404 | M43: 9205 | O43: Repayment of short term borrowings | P43: -937 | Q43: -1556 | R43: -52 | S43: -88 | T43: -352 | V43: Payment of cash dividend to Non controlling interest | W43: -141.5 | X43: -96 | Y43: -113.5 | Z43: 0 | AA43: -14517.3 | AC43: Dividend paid | AD43: -81.5 | AE43: 0 | AF43: -1327.7 | AG43: -1562.7 | AH43: -1775.3
A44: CASH FLOW FINANCING ACTIVITIES | H44: Liquid mutual funds and fixed maturity plan securities | I44: 34685 | J44: 36353 | K44: 53669 | L44: 71851 | M44: 64767 | O44: Payments for deferred and contingent consideration on business acquisitions | P44: -295 | Q44: -6518 | R44: =-371-746-804 -> -1921 | S44: =-31 -> -31 | T44: -5 | V44: Cash generated/used in financing activities | W44: =SUM(W35:W43) -> -15099.8 | X44: =SUM(X35:X43) -> -12884 | Y44: =SUM(Y35:Y43) -> 4658.6 | Z44: =SUM(Z35:Z43) -> -6088.1 | AA44: =SUM(AA35:AA43) -> -18256.7 | AC44: Net cash generated/used in financing activities | AD44: =SUM(AD36:AD43) -> -890 | AE44: =SUM(AE36:AE43) -> -508.8 | AF44: =SUM(AF36:AF43) -> -1680.4 | AG44: =SUM(AG36:AG43) -> -1931.7 | AH44: =SUM(AH36:AH43) -> -2268.8
A45: Repayment of lease liabilities | B45: -1062 | C45: -1336 | D45: -1417 | E45: -1515 | F45: -1614 | H45: Preference, equity securities | I45: 27 | J45: 73 | K45: 0 | L45: 99 | M45: 26 | O45: Dividend paid | P45: -1357 | Q45: -3256 | R45: =-11389-2 -> -11391 | S45: -12995 | T45: =-14073+7 -> -14066 | V45: Net increase/decrease in cash and cash equivalents | W45: =W22+W33+W44 -> -1634.3 | X45: =X22+X33+X44 -> 2644.9 | Y45: =Y22+Y33+Y44 -> -6711.2 | Z45: =Z22+Z33+Z44 -> -1429.1 | AA45: =AA22+AA33+AA44 -> 972.1 | AC45: Net decrease/increase in cash and cash equivalents | AD45: =AD25+AD34+AD44 -> 101.5 | AE45: =AE25+AE34+AE44 -> 234.8 | AF45: =AF25+AF34+AF44 -> -75 | AG45: =AG25+AG34+AG44 -> 832 | AH45: =AH25+AH34+AH44 -> -511.4
A46: Interest paid | B46: -924 | C46: -634 | D46: -698 | E46: -779 | F46: -699 | H46: Others | I46: 0 | J46: 23 | K46: 9 | L46: 0 | M46: 0 | O46: Corporate dividend tax | P46: -268 | Q46: 0 | R46: 0 | S46: 0 | V46: Effect of exchange rate changes on cash and cash equivalents | W46: 192.2 | X46: -89 | Y46: 128.2 | Z46: 237.3 | AA46: -23.9 | AC46: Cash and cash equivalents at the beginning of the year | AD46: 415 | AE46: 525.2 | AF46: 1519.1 | AG46: 1446.2 | AH46: 2337.7
A47: Dividend paid | B47: -37634 | C47: -10850 | D47: -13317 | E47: -41347 | F47: -25137 | H47: Net cash generated/used in investing activities | I47: =SUM(I22:I29,I31:I37,I39:I46) -> -239 | J47: =SUM(J22:J29,J31:J37,J39:J46) -> -7456 | K47: =SUM(K22:K29,K31:K37,K39:K46) -> -6416 | L47: =SUM(L22:L29,L31:L37,L39:L46) -> -1209 | M47: =SUM(M22:M29,M31:M37,M39:M46) -> -5009 | O47: Interest paid | P47: -136 | Q47: -139 | R47: -69 | S47: -80 | T47: -64 | V47: Cash and cash equivalents at the beginning of the year | W47: 15852.5 | X47: 14410.4 | Y47: 16966.3 | Z47: 10383.3 | AA47: 9186.1 | AC47: Effect of exchange difference on translation | AD47: 8.7 | AE47: -0.6 | AF47: 2.1 | AG47: 59.5 | AH47: -6.3
A48: Dividend paid to non-controlling interest | B48: -68 | C48: -57 | D48: -58 | E48: -63 | F48: -81 | H48: CASH FLOW FROM FINANCING ACTIVITIES | O48: Payment of lease liabilities including interest | P48: -866 | Q48: -1016 | R48: -1067 | S48: -927 | T48: -1148 | V48: Cash and cash equivalents at the end of the year | W48: =W45+W46+W47 -> 14410.4 | X48: =X45+X46+X47 -> 16966.3 | Y48: =Y45+Y46+Y47 -> 10383.3 | Z48: =Z45+Z46+Z47 -> 9191.5 | AA48: =AA45+AA46+AA47 -> 10134.3 | AC48: Cash and Cash equivalents at the end of the year | AD48: =AD45+AD46+AD47 -> 525.2 | AE48: =AE45+AE46+AE47 -> 759.4 | AF48: =AF45+AF46+AF47 -> 1446.2 | AG48: =AG45+AG46+AG47 -> 2337.7 | AH48: =AH45+AH46+AH47 -> 1820
A49: Purchase of non-controlling interests | B49: -227 | C49: 0 | D49: -24 | E49: 0 | F49: -425 | H49: Payment of lease liabilities | I49: -571 | J49: -698 | K49: -915 | L49: -1231 | M49: -2024 | O49: Net cash flow generated/used in financing activities | P49: =SUM(P40:P48) -> -3168 | Q49: =SUM(Q40:Q48) -> -11180 | R49: =SUM(R40:R48) -> -14508 | S49: =SUM(S40:S48) -> -15881 | T49: =SUM(T40:T48) -> -15464
A50: Transfer of funds to buy back escrow account | B50: 0 | C50: -160 | D50: -180 | E50: 18 | F50: 425 | H50: Payment of dividends | I50: -9515 | J50: -9117 | K50: -12652 | L50: -13631 | M50: -14692 | O50: Net increase/decrease in cash and cash equivalents | P50: =P21+P38+P49 -> -2183 | Q50: =Q21+Q38+Q49 -> 2696 | R50: =R21+R38+R49 -> 3869 | S50: =S21+S38+S49 -> -1803 | T50: =T21+T38+T49 -> 261
A51: Transfer of funds from buy-back escrow account | B51: 0 | C51: 160 | D51: 162 | E51: 0 | F51: -46 | H51: Payment of dividend to non controlling interests | I51: -33 | J51: -20 | K51: -79 | L51: -22 | M51: -39 | O51: Effects of exchange differences on cash and cash eq | P51: 42 | Q51: 65 | R51: 120 | S51: 358 | T51: 115 | W51: =(-W42-W43)/'Company Profile'!$E$11 -> 0.79057423 | X51: =(-X42-X43)/'Company Profile'!$E$11 -> 0.61303406 | Y51: =(-Y42-Y43)/'Company Profile'!$E$11 -> 0.63051112 | Z51: =(-Z42-Z43)/'Company Profile'!$E$11 -> 0 | AA51: =(-AA42-AA43)/'Company Profile'!$E$11 -> 13.895216 | AD51: =-AD43/'Company Profile'!$F$11 -> 2.7503122 | AE51: =-AE43/'Company Profile'!$F$11 -> 0 | AF51: =-AF43/'Company Profile'!$F$11 -> 44.804778 | AG51: =-AG43/'Company Profile'!$F$11 -> 52.735126 | AH51: =-AH43/'Company Profile'!$F$11 -> 59.90956
A52: Expenses for buy back of equity shares | B52: 0 | C52: -31 | D52: -49 | E52: -4192 | F52: -3959 | H52: Shares issued on exercise of employee stock options | I52: 6 | J52: 15 | K52: 21 | L52: 35 | M52: 5 | O52: Cash and cash equivalents at the beginning of the year | P52: 5901 | Q52: 3760 | R52: 6521 | S52: 10510 | T52: 9065
A53: Tax on buy-back of equity shares | B53: 0 | C53: -3726 | D53: 0 | E53: 0 | F53: 0 | H53: Payment towards purchase of non controlling interest | I53: 0 | J53: -49 | K53: -2 | L53: 0 | M53: -18 | O53: Cash and cash equivalents at the end of the year | P53: =P50+P51+P52 -> 3760 | Q53: =Q50+Q51+Q52 -> 6521 | R53: =R50+R51+R52 -> 10510 | S53: =S50+S51+S52 -> 9065 | T53: =T50+T51+T52 -> 9441
A54: Buy-back of equity shares | B54: 0 | C54: -16000 | D54: -18000 | E54: 0 | F54: -17000 | H54: Other receipts | I54: 0 | J54: 83 | K54: =236-126 -> 110 | L54: =132-479 -> -347 | M54: -736
A55: Net cash used in financing activities | B55: =SUM(B45:B54) -> -39915 | C55: =SUM(C45:C54) -> -32634 | D55: =SUM(D45:D54) -> -33581 | E55: =SUM(E45:E54) -> -47878 | F55: =SUM(F45:F54) -> -48536 | H55: Buyback of equity shares including transaction cost | I55: -7478 | J55: 0 | K55: -11125 | L55: -11499 | M55: 0 | P55: =-P45/'Company Profile'!$D$11 -> 5.0094134 | Q55: =-Q45/'Company Profile'!$D$11 -> 12.019639 | R55: =-R45/'Company Profile'!$D$11 -> 42.050279 | S55: =-S45/'Company Profile'!$D$11 -> 47.971501 | T55: =-T45/'Company Profile'!$D$11 -> 51.925136
A56: Net cash in cash and cash equivalents | B56: =B29+B43+B55 -> 1019 | C56: =C29+C43+C55 -> -1961 | D56: =D29+D43+D55 -> 5471 | E56: =E29+E43+E55 -> -5874 | F56: =F29+F43+F55 -> 1828 | H56: Net cash generated from/used in financing activities | I56: =SUM(I49:I55) -> -17591 | J56: =SUM(J49:J55) -> -9786 | K56: =SUM(K49:K55) -> -24642 | L56: =SUM(L49:L55) -> -26695 | M56: =SUM(M49:M55) -> -17504
A57: Cash and cash equivalents at the beginning of the year | B57: 7224 | C57: 8646 | D57: 6858 | E57: 12488 | F57: 7123 | H57: Net increase/decrease in cash and cash equivalents | I57: =I20+I47+I56 -> -827 | J57: =J20+J47+J56 -> 5982 | K57: =K20+K47+K56 -> -7173 | L57: =L20+L47+L56 -> -5437 | M57: =M20+M47+M56 -> 2697
A58: Exchange difference on translation of foreign currency cash and cash equivalents | B58: 403 | C58: 173 | D58: 159 | E58: 509 | F58: 65 | H58: Cash and cash equivalents at the beginning of the year | I58: 19568 | J58: 18649 | K58: 24714 | L58: 17472 | M58: 12173
A59: Cash and cash equivalents at the end of the year | B59: =B56+B58+B57 -> 8646 | C59: =C56+C58+C57 -> 6858 | D59: =D56+D58+D57 -> 12488 | E59: =E56+E58+E57 -> 7123 | F59: =F56+F58+F57 -> 9016 | H59: Effect of exchange rate changes on cash and cash eq | I59: -92 | J59: 83 | K59: -69 | L59: 138 | M59: -84
H60: Cash and cash equivalents at the end of the year | I60: =I57+I58+I59 -> 18649 | J60: =J57+J58+J59 -> 24714 | K60: =K57+K58+K59 -> 17472 | L60: =L57+L58+L59 -> 12173 | M60: =M57+M58+M59 -> 14786
B61: =(-B34-B36) -> 2730 | F61: =(-F34-F36) -> 2644
A62: DPS | B62: =-B47/'Company Profile'!$B$11 -> 104.01592 | C62: =-C47/'Company Profile'!$B$11 -> 29.988115 | D62: =-D47/'Company Profile'!$B$11 -> 36.806611 | E62: =-E47/'Company Profile'!$B$11 -> 114.27821 | F62: =-F47/'Company Profile'!$B$11 -> 69.475692 | I62: =-I50/'Company Profile'!$C$11 -> 22.957583 | J62: =-J50/'Company Profile'!$C$11 -> 21.997298 | K62: =-K50/'Company Profile'!$C$11 -> 30.526468 | L62: =-L50/'Company Profile'!$C$11 -> 32.888578 | M62: =-M50/'Company Profile'!$C$11 -> 35.448535

Sheet Financial Ratios
A1: FINANCIAL RATIO | F1: #VALUE! | I1: FINANCIAL RATIO | N1: #VALUE! | Q1: FINANCIAL RATIO | V1: #VALUE! | Y1: FINANCIAL RATIO | AD1: #VALUE! | AG1: FINANCIAL RATIO | AL1: #VALUE!
A2: Category | B2: Ratio name | C2: 2020 | D2: 2021 | E2: 2022 | F2: 2023 | G2: 2024 | I2: Category | J2: Ratio name | K2: 2020 | L2: 2021 | M2: 2022 | N2: 2023 | O2: 2024 | Q2: Category | R2: Ratio name | S2: 2020 | T2: 2021 | U2: 2022 | V2: 2023 | W2: 2024 | Y2: Category | Z2: Ratio name | AA2: 2020 | AB2: 2021 | AC2: 2022 | AD2: 2023 | AE2: 2024 | AG2: Category | AH2: Ratio name | AI2: 2020 | AJ2: 2021 | AK2: 2022 | AL2: 2023 | AM2: 2024
A3: Profitability | B3: Gross Profit Margin | C3: =('Income Statement'!B3-'Income Statement'!B8)/'Income Statement'!B3 -> 0.9878623 | D3: =('Income Statement'!C3-'Income Statement'!C8)/'Income Statement'!C3 -> 0.99109498 | E3: =('Income Statement'!D3-'Income Statement'!D8)/'Income Statement'!D3 -> 0.99393494 | F3: =('Income Statement'!E3-'Income Statement'!E8)/'Income Statement'!E3 -> 0.99165698 | G3: =('Income Statement'!F3-'Income Statement'!F8)/'Income Statement'!F3 -> 0.98463218 | I3: Profitability | J3: Gross Profit Margin | K3: =('Income Statement'!I3-'Income Statement'!I8-'Income Statement'!I10)/'Income Statement'!I3 -> 0.89627827 | L3: =('Income Statement'!J3-'Income Statement'!J8-'Income Statement'!J10)/'Income Statement'!J3 -> 0.88746118 | M3: =('Income Statement'!K3-'Income Statement'!K8-'Income Statement'!K10)/'Income Statement'!K3 -> 0.84037454 | N3: =('Income Statement'!L3-'Income Statement'!L8-'Income Statement'!L10)/'Income Statement'!L3 -> 0.82990727 | O3: =('Income Statement'!M3-'Income Statement'!M8-'Income Statement'!M10)/'Income Statement'!M3 -> 0.82300755 | Q3: Profitability | R3: Gross Profit Margin | S3: =('Income Statement'!P3-('Income Statement'!P7+'Income Statement'!P8))/'Income Statement'!P3 -> 0.97826702 | T3: =('Income Statement'!Q3-('Income Statement'!Q7+'Income Statement'!Q8))/'Income Statement'!Q3 -> 0.97751363 | U3: =('Income Statement'!R3-('Income Statement'!R7+'Income Statement'!R8))/'Income Statement'!R3 -> 0.98358455 | V3: =('Income Statement'!S3-('Income Statement'!S7+'Income Statement'!S8))/'Income Statement'!S3 -> 0.98023774 | W3: =('Income Statement'!T3-('Income Statement'!T7+'Income Statement'!T8))/'Income Statement'!T3 -> 0.98365071 | Y3: Profitability | Z3: Gross Profit Margin | AA3: =('Income Statement'!W3-('Income Statement'!W8+'Income Statement'!W9))/'Income Statement'!W3 -> 0.98134808 | AB3: =('Income Statement'!X3-('Income Statement'!X8+'Income Statement'!X9))/'Income Statement'!X3 -> 0.98826017 | AC3: =('Income Statement'!Y3-('Income Statement'!Y8+'Income Statement'!Y9))/'Income Statement'!Y3 -> 0.99195129 | AD3: =('Income Statement'!Z3-('Income Statement'!Z8+'Income Statement'!Z9))/'Income Statement'!Z3 -> 0.99265756 | AE3: =('Income Statement'!AA3-('Income Statement'!AA8+'Income Statement'!AA9))/'Income Statement'!AA3 -> 0.99542114 | AG3: Profitability | AH3: Gross Profit Margin
B4: EBITDA Margin | C4: =('Income Statement'!B16+'Income Statement'!B9+'Income Statement'!B10+'Income Statement'!B15)/'Income Statement'!B3 -> 0.29755526 | D4: =('Income Statement'!C16+'Income Statement'!C9+'Income Statement'!C10+'Income Statement'!C15)/'Income Statement'!C3 -> 0.30260024 | E4: =('Income Statement'!D16+'Income Statement'!D9+'Income Statement'!D10+'Income Statement'!D15)/'Income Statement'!D3 -> 0.29764699 | F4: =('Income Statement'!E16+'Income Statement'!E9+'Income Statement'!E10+'Income Statement'!E15)/'Income Statement'!E3 -> 0.27813606 | G4: =('Income Statement'!F16+'Income Statement'!F9+'Income Statement'!F10+'Income Statement'!F15)/'Income Statement'!F3 -> 0.28526358 | J4: EBITDA Margin | K4: =('Income Statement'!I17+'Income Statement'!I14+'Income Statement'!I13)/'Income Statement'!I3 -> 0.27612869 | L4: =('Income Statement'!J17+'Income Statement'!J14+'Income Statement'!J13)/'Income Statement'!J3 -> 0.29948642 | M4: =('Income Statement'!K17+'Income Statement'!K14+'Income Statement'!K13)/'Income Statement'!K3 -> 0.27775174 | N4: =('Income Statement'!L17+'Income Statement'!L14+'Income Statement'!L13)/'Income Statement'!L3 -> 0.2577623 | O4: =('Income Statement'!M17+'Income Statement'!M14+'Income Statement'!M13)/'Income Statement'!M3 -> 0.26281367 | R4: EBITDA Margin | S4: =('Income Statement'!P15+'Income Statement'!P10+'Income Statement'!P11)/'Income Statement'!P3 -> 0.25333918 | T4: =('Income Statement'!Q15+'Income Statement'!Q10+'Income Statement'!Q11)/'Income Statement'!Q3 -> 0.27826052 | U4: =('Income Statement'!R15+'Income Statement'!R10+'Income Statement'!R11)/'Income Statement'!R3 -> 0.34774842 | V4: =('Income Statement'!S15+'Income Statement'!S10+'Income Statement'!S11)/'Income Statement'!S3 -> 0.34291713 | W4: =('Income Statement'!T15+'Income Statement'!T10+'Income Statement'!T11)/'Income Statement'!T3 -> 0.32842339 | Z4: EBITDA Margin | AA4: =('Income Statement'!W23+'Income Statement'!W11+'Income Statement'!W12)/'Income Statement'!W3 -> 0.24695853 | AB4: =('Income Statement'!X23+'Income Statement'!X11+'Income Statement'!X12)/'Income Statement'!X3 -> 0.27727265 | AC4: =('Income Statement'!Y23+'Income Statement'!Y11+'Income Statement'!Y12)/'Income Statement'!Y3 -> 0.23707541 | AD4: =('Income Statement'!Z23+'Income Statement'!Z11+'Income Statement'!Z12)/'Income Statement'!Z3 -> 0.21122894 | AE4: =('Income Statement'!AA23+'Income Statement'!AA11+'Income Statement'!AA12)/'Income Statement'!AA3 -> 0.21594513 | AH4: EBITDA Margin | AI4: =('Income Statement'!AD13+'Income Statement'!AD9+'Income Statement'!AD10)/'Income Statement'!AD3 -> 0.21680179 | AJ4: =('Income Statement'!AE13+'Income Statement'!AE9+'Income Statement'!AE10)/'Income Statement'!AE3 -> 0.24248573 | AK4: =('Income Statement'!AF13+'Income Statement'!AF9+'Income Statement'!AF10)/'Income Statement'!AF3 -> 0.23035999 | AL4: =('Income Statement'!AG13+'Income Statement'!AG9+'Income Statement'!AG10)/'Income Statement'!AG3 -> 0.20084381 | AM4: =('Income Statement'!AH13+'Income Statement'!AH9+'Income Statement'!AH10)/'Income Statement'!AH3 -> 0.19960301
B5: EBIT Margin | C5: =('Income Statement'!B13+'Income Statement'!B9)/'Income Statement'!B3 -> 0.27507025 | D5: =('Income Statement'!C13+'Income Statement'!C9)/'Income Statement'!C3 -> 0.27784038 | E5: =('Income Statement'!D13+'Income Statement'!D9)/'Income Statement'!D3 -> 0.27363706 | F5: =('Income Statement'!E13+'Income Statement'!E9)/'Income Statement'!E3 -> 0.2558614 | G5: =('Income Statement'!F13+'Income Statement'!F9)/'Income Statement'!F3 -> 0.26456975 | J5: EBIT Margin | K5: =('Income Statement'!I17+'Income Statement'!I14)/'Income Statement'!I3 -> 0.2442643 | L5: =('Income Statement'!J17+'Income Statement'!J14)/'Income Statement'!J3 -> 0.2669699 | M5: =('Income Statement'!K17+'Income Statement'!K14)/'Income Statement'!K3 -> 0.24917585 | N5: =('Income Statement'!L17+'Income Statement'!L14)/'Income Statement'!L3 -> 0.22897518 | O5: =('Income Statement'!M17+'Income Statement'!M14)/'Income Statement'!M3 -> 0.23329039 | R5: EBIT Margin | S5: =('Income Statement'!P15+'Income Statement'!P10)/'Income Statement'!P3 -> 0.20494935 | T5: =('Income Statement'!Q15+'Income Statement'!Q10)/'Income Statement'!Q3 -> 0.21708964 | U5: =('Income Statement'!R15+'Income Statement'!R10)/'Income Statement'!R3 -> 0.344024 | V5: =('Income Statement'!S15+'Income Statement'!S10)/'Income Statement'!S3 -> 0.33943779 | W5: =('Income Statement'!T15+'Income Statement'!T10)/'Income Statement'!T3 -> 0.32339214 | Z5: EBIT Margin | AA5: =('Income Statement'!W23+'Income Statement'!W11)/'Income Statement'!W3 -> 0.21278301 | AB5: =('Income Statement'!X23+'Income Statement'!X11)/'Income Statement'!X3 -> 0.23266067 | AC5: =('Income Statement'!Y23+'Income Statement'!Y11)/'Income Statement'!Y3 -> 0.19816192 | AD5: =('Income Statement'!Z23+'Income Statement'!Z11)/'Income Statement'!Z3 -> 0.1743156 | AE5: =('Income Statement'!AA23+'Income Statement'!AA11)/'Income Statement'!AA3 -> 0.17798737 | AH5: EBIT Margin | AI5: =('Income Statement'!AD13+'Income Statement'!AD9)/'Income Statement'!AD3 -> 0.19170665 | AJ5: =('Income Statement'!AE13+'Income Statement'!AE9)/'Income Statement'!AE3 -> 0.21560575 | AK5: =('Income Statement'!AF13+'Income Statement'!AF9)/'Income Statement'!AF3 -> 0.20749022 | AL5: =('Income Statement'!AG13+'Income Statement'!AG9)/'Income Statement'!AG3 -> 0.17906458 | AM5: =('Income Statement'!AH13+'Income Statement'!AH9)/'Income Statement'!AH3 -> 0.17654644
B6: Net Profit margin | C6: ='Income Statement'!B21/'Income Statement'!B3 -> 0.20673595 | D6: ='Income Statement'!C21/'Income Statement'!C3 -> 0.19833472 | E6: ='Income Statement'!D21/'Income Statement'!D3 -> 0.20051211 | F6: ='Income Statement'!E21/'Income Statement'!E3 -> 0.1876314 | G6: ='Income Statement'!F21/'Income Statement'!F3 -> 0.19136712 | J6: Net Profit margin | K6: ='Income Statement'!I22/'Income Statement'!I3 -> 0.18326706 | L6: ='Income Statement'!J22/'Income Statement'!J3 -> 0.19331754 | M6: ='Income Statement'!K22/'Income Statement'!K3 -> 0.18206033 | N6: ='Income Statement'!L22/'Income Statement'!L3 -> 0.16426036 | O6: ='Income Statement'!M22/'Income Statement'!M3 -> 0.1641205 | R6: Net Profit margin | S6: ='Income Statement'!P20/'Income Statement'!P3 -> 0.15644632 | T6: ='Income Statement'!Q20/'Income Statement'!Q3 -> 0.14817124 | U6: ='Income Statement'!R20/'Income Statement'!R3 -> 0.15788491 | V6: ='Income Statement'!S20/'Income Statement'!S3 -> 0.14631959 | W6: ='Income Statement'!T20/'Income Statement'!T3 -> 0.14293123 | Z6: Net Profit margin | AA6: ='Income Statement'!W28/'Income Statement'!W3 -> 0.16013254 | AB6: ='Income Statement'!X28/'Income Statement'!X3 -> 0.17545162 | AC6: ='Income Statement'!Y28/'Income Statement'!Y3 -> 0.15479673 | AD6: ='Income Statement'!Z28/'Income Statement'!Z3 -> 0.1256139 | AE6: ='Income Statement'!AA28/'Income Statement'!AA3 -> 0.12379749 | AH6: Net Profit margin | AI6: ='Income Statement'!AD18/'Income Statement'!AD3 -> 0.13976982 | AJ6: ='Income Statement'!AE18/'Income Statement'!AE3 -> 0.15668806 | AK6: ='Income Statement'!AF18/'Income Statement'!AF3 -> 0.15129057 | AL6: ='Income Statement'!AG18/'Income Statement'!AG3 -> 0.13290842 | AM6: ='Income Statement'!AH18/'Income Statement'!AH3 -> 0.12908185
B7: Return on Assets | C7: ='Income Statement'!B21/'Balance Sheet'!B33 -> 0.26838105 | D7: ='Income Statement'!C21/(AVERAGE('Balance Sheet'!B33:C33)) -> 0.25877977 | E7: ='Income Statement'!D21/(AVERAGE('Balance Sheet'!C33:D33)) -> 0.28242977 | F7: ='Income Statement'!E21/(AVERAGE('Balance Sheet'!D33:E33)) -> 0.29669139 | G7: ='Income Statement'!F21/(AVERAGE('Balance Sheet'!E33:F33)) -> 0.31781455 | J7: Return on Assets | K7: ='Income Statement'!I22/'Balance Sheet'!I28 -> 0.17936142 | L7: ='Income Statement'!J22/(AVERAGE('Balance Sheet'!I28:J28)) -> 0.19311572 | M7: ='Income Statement'!K22/(AVERAGE('Balance Sheet'!J28:K28)) -> 0.19574758 | N7: ='Income Statement'!L22/(AVERAGE('Balance Sheet'!K28:L28)) -> 0.197849 | O7: ='Income Statement'!M22/(AVERAGE('Balance Sheet'!L28:M28)) -> 0.20293593 | R7: Return on Assets | S7: ='Income Statement'!P20/'Balance Sheet'!P28 -> 0.13336791 | T7: ='Income Statement'!Q20/(AVERAGE('Balance Sheet'!P28:Q28)) -> 0.13209935 | U7: ='Income Statement'!R20/(AVERAGE('Balance Sheet'!Q28:R28)) -> 0.15434836 | V7: ='Income Statement'!S20/(AVERAGE('Balance Sheet'!R28:S28)) -> 0.16273487 | W7: ='Income Statement'!T20/(AVERAGE('Balance Sheet'!S28:T28)) -> 0.16288063 | Z7: Return on Assets | AA7: ='Income Statement'!W28/(AVERAGE('Balance Sheet'!W34)) -> 0.12022554 | AB7: ='Income Statement'!X28/(AVERAGE('Balance Sheet'!W34:X34)) -> 0.13252762 | AC7: ='Income Statement'!Y28/(AVERAGE('Balance Sheet'!X34:Y34)) -> 0.12871693 | AD7: ='Income Statement'!Z28/(AVERAGE('Balance Sheet'!Y34:Z34)) -> 0.10119788 | AE7: ='Income Statement'!AA28/(AVERAGE('Balance Sheet'!Z34:AA34)) -> 0.095825233 | AH7: Return on Assets | AI7: ='Income Statement'!AD18/'Balance Sheet'!AD32 -> 0.17229657 | AJ7: ='Income Statement'!AE18/(AVERAGE('Balance Sheet'!AD32:AE32)) -> 0.19844374 | AK7: ='Income Statement'!AF18/(AVERAGE('Balance Sheet'!AE32:AF32)) -> 0.25246473 | AL7: ='Income Statement'!AG18/(AVERAGE('Balance Sheet'!AF32:AG32)) -> 0.20011117 | AM7: ='Income Statement'!AH18/(AVERAGE('Balance Sheet'!AG32:AH32)) -> 0.17958013
B8: Return on Equity | C8: ='Income Statement'!B21/'Balance Sheet'!B40 -> 0.38285997 | D8: ='Income Statement'!C21/(AVERAGE('Balance Sheet'!B40:C40)) -> 0.37894296 | E8: ='Income Statement'!D21/(AVERAGE('Balance Sheet'!C40:D40)) -> 0.43456492 | F8: ='Income Statement'!E21/(AVERAGE('Balance Sheet'!D40:E40)) -> 0.46730221 | G8: ='Income Statement'!F21/(AVERAGE('Balance Sheet'!E40:F40)) -> 0.50512533 | J8: Return on Equity | K8: ='Income Statement'!I22/'Balance Sheet'!I35 -> 0.25270336 | L8: ='Income Statement'!J22/(AVERAGE('Balance Sheet'!I35:J35)) -> 0.27236268 | M8: ='Income Statement'!K22/(AVERAGE('Balance Sheet'!J35:K35)) -> 0.29040507 | N8: ='Income Statement'!L22/(AVERAGE('Balance Sheet'!K35:L35)) -> 0.31819232 | O8: ='Income Statement'!M22/(AVERAGE('Balance Sheet'!L35:M35)) -> 0.32571109 | R8: Return on Equity | S8: ='Income Statement'!P20/'Balance Sheet'!P34 -> 0.21502888 | T8: ='Income Statement'!Q20/(AVERAGE('Balance Sheet'!P34:Q34)) -> 0.20033542 | U8: ='Income Statement'!R20/(AVERAGE('Balance Sheet'!Q34:R34)) -> 0.22152873 | V8: ='Income Statement'!S20/(AVERAGE('Balance Sheet'!R34:S34)) -> 0.23303821 | W8: ='Income Statement'!T20/(AVERAGE('Balance Sheet'!S34:T34)) -> 0.23505824 | Z8: Return on Equity | AA8: ='Income Statement'!W28/'Balance Sheet'!W41 -> 0.17603929 | AB8: ='Income Statement'!X28/(AVERAGE('Balance Sheet'!W41:X41)) -> 0.19659913 | AC8: ='Income Statement'!Y28/(AVERAGE('Balance Sheet'!X41:Y41)) -> 0.20320102 | AD8: ='Income Statement'!Z28/(AVERAGE('Balance Sheet'!Y41:Z41)) -> 0.15877073 | AE8: ='Income Statement'!AA28/(AVERAGE('Balance Sheet'!Z41:AA41)) -> 0.14583402 | AH8: Return on Equity | AI8: ='Income Statement'!AD18/'Balance Sheet'!AD40 -> 0.28130839 | AJ8: ='Income Statement'!AE18/(AVERAGE('Balance Sheet'!AD40:AE40)) -> 0.30493542 | AK8: ='Income Statement'!AF18/(AVERAGE('Balance Sheet'!AE40:AF40)) -> 0.36574074 | AL8: ='Income Statement'!AG18/(AVERAGE('Balance Sheet'!AF40:AG40)) -> 0.28552931 | AM8: ='Income Statement'!AH18/(AVERAGE('Balance Sheet'!AG40:AH40)) -> 0.25034948
B9: Return on capital employed | C9: =('Income Statement'!B13+'Income Statement'!B9)/('Balance Sheet'!B33-'Balance Sheet'!B60) -> 0.46006458 | D9: =('Income Statement'!C13+'Income Statement'!C9)/('Balance Sheet'!C33-'Balance Sheet'!C60) -> 0.47218542 | E9: =('Income Statement'!D13+'Income Statement'!D9)/('Balance Sheet'!D33-'Balance Sheet'!D60) -> 0.52913889 | F9: =('Income Statement'!E13+'Income Statement'!E9)/('Balance Sheet'!E33-'Balance Sheet'!E60) -> 0.57632402 | G9: =('Income Statement'!F13+'Income Statement'!F9)/('Balance Sheet'!F33-'Balance Sheet'!F60) -> 0.63513877 | J9: Return on capital employed | K9: =('Income Statement'!I17+'Income Statement'!I14)/('Balance Sheet'!I28-'Balance Sheet'!I52) -> 0.30839081 | L9: =('Income Statement'!J17+'Income Statement'!J14)/('Balance Sheet'!J28-'Balance Sheet'!J52) -> 0.31735308 | M9: =('Income Statement'!K17+'Income Statement'!K14)/('Balance Sheet'!K28-'Balance Sheet'!K52) -> 0.35962602 | N9: =('Income Statement'!L17+'Income Statement'!L14)/('Balance Sheet'!L28-'Balance Sheet'!L52) -> 0.38792566 | O9: =('Income Statement'!M17+'Income Statement'!M14)/('Balance Sheet'!M28-'Balance Sheet'!M52) -> 0.38400323 | R9: Return on capital employed | S9: =('Income Statement'!P15+'Income Statement'!P10)/('Balance Sheet'!P28-'Balance Sheet'!P54) -> 0.24477829 | T9: =('Income Statement'!Q15+'Income Statement'!Q10)/('Balance Sheet'!Q28-'Balance Sheet'!Q54) -> 0.23781082 | U9: =('Income Statement'!R15+'Income Statement'!R10)/('Balance Sheet'!R28-'Balance Sheet'!R54) -> 0.41939708 | V9: =('Income Statement'!S15+'Income Statement'!S10)/('Balance Sheet'!S28-'Balance Sheet'!S54) -> 0.47843846 | W9: =('Income Statement'!T15+'Income Statement'!T10)/('Balance Sheet'!T28-'Balance Sheet'!T54) -> 0.46303654 | Z9: Return on capital employed | AA9: =('Income Statement'!W23+'Income Statement'!W11)/('Balance Sheet'!W34-'Balance Sheet'!W65) -> 0.21771943 | AB9: =('Income Statement'!X23+'Income Statement'!X11)/('Balance Sheet'!X34-'Balance Sheet'!X65) -> 0.24128803 | AC9: =('Income Statement'!Y23+'Income Statement'!Y11)/('Balance Sheet'!Y34-'Balance Sheet'!Y65) -> 0.20441879 | AD9: =('Income Statement'!Z23+'Income Statement'!Z11)/('Balance Sheet'!Z34-'Balance Sheet'!Z65) -> 0.17456484 | AE9: =('Income Statement'!AA23+'Income Statement'!AA11)/('Balance Sheet'!AA34-'Balance Sheet'!AA65) -> 0.17841572 | AH9: Return on capital employed | AI9: =('Income Statement'!AD13+'Income Statement'!AD9)/('Balance Sheet'!AD32-'Balance Sheet'!AD61) -> 0.32115743 | AJ9: =('Income Statement'!AE13+'Income Statement'!AE9)/('Balance Sheet'!AE32-'Balance Sheet'!AE61) -> 0.33020503 | AK9: =('Income Statement'!AF13+'Income Statement'!AF9)/('Balance Sheet'!AF32-'Balance Sheet'!AF61) -> 0.3497266 | AL9: =('Income Statement'!AG13+'Income Statement'!AG9)/('Balance Sheet'!AG32-'Balance Sheet'!AG61) -> 0.32985816 | AM9: =('Income Statement'!AH13+'Income Statement'!AH9)/('Balance Sheet'!AH32-'Balance Sheet'!AH61) -> 0.28737202
B10: Earning Per Share | C10: ='Income Statement'!B21/'Company Profile'!$B$11 -> 89.679666 | D10: ='Income Statement'!C21/'Company Profile'!$B$11 -> 89.997513 | E10: ='Income Statement'!D21/'Company Profile'!$B$11 -> 106.26848 | F10: ='Income Statement'!E21/'Company Profile'!$B$11 -> 116.92048 | G10: ='Income Statement'!F21/'Company Profile'!$B$11 -> 127.41218 | J10: Earning Per Share | K10: ='Income Statement'!I22/'Company Profile'!$B$11 -> 45.988226 | L10: ='Income Statement'!J22/'Company Profile'!$B$11 -> 53.682872 | M10: ='Income Statement'!K22/'Company Profile'!$B$11 -> 61.208922 | N10: ='Income Statement'!L22/'Company Profile'!$B$11 -> 66.631657 | O10: ='Income Statement'!M22/'Company Profile'!$B$11 -> 73.933833 | R10: Earning Per Share | S10: ='Income Statement'!P20/'Company Profile'!$D$11 -> 40.817306 | T10: ='Income Statement'!Q20/'Company Profile'!$D$11 -> 41.230758 | U10: ='Income Statement'!R20/'Company Profile'!$D$11 -> 49.920632 | V10: ='Income Statement'!S20/'Company Profile'!$D$11 -> 54.800842 | W10: ='Income Statement'!T20/'Company Profile'!$D$11 -> 57.99402 | Z10: Earning Per Share | AA10: ='Income Statement'!W28/'Company Profile'!$E$11 -> 9.3323668 | AB10: ='Income Statement'!X28/'Company Profile'!$E$11 -> 10.379271 | AC10: ='Income Statement'!Y28/'Company Profile'!$E$11 -> 11.69282 | AD10: ='Income Statement'!Z28/'Company Profile'!$E$11 -> 10.855354 | AE10: ='Income Statement'!AA28/'Company Profile'!$E$11 -> 10.612394 | AH10: Earning Per Share | AI10: ='Income Statement'!AD18/'Company Profile'!$F$11 -> 51.311038 | AJ10: ='Income Statement'!AE18/'Company Profile'!$F$11 -> 65.40681 | AK10: ='Income Statement'!AF18/'Company Profile'!$F$11 -> 133.29734 | AL10: ='Income Statement'!AG18/'Company Profile'!$F$11 -> 148.8307 | AM10: ='Income Statement'!AH18/'Company Profile'!$F$11 -> 154.71265
A11: Efficiency | B11: Asset Turnover ratio | C11: ='Income Statement'!B3/'Balance Sheet'!B33 -> 1.2981828 | D11: ='Income Statement'!C3/(AVERAGE('Balance Sheet'!B33:C33)) -> 1.3047628 | E11: ='Income Statement'!D3/(AVERAGE('Balance Sheet'!C33:D33)) -> 1.4085422 | F11: ='Income Statement'!E3/(AVERAGE('Balance Sheet'!D33:E33)) -> 1.5812459 | G11: ='Income Statement'!F3/(AVERAGE('Balance Sheet'!E33:F33)) -> 1.6607584 | I11: Efficiency | J11: Asset Turnover ratio | K11: ='Income Statement'!I3/'Balance Sheet'!I28 -> 0.97868877 | L11: ='Income Statement'!J3/(AVERAGE('Balance Sheet'!I28:J28)) -> 0.99895602 | M11: ='Income Statement'!K3/(AVERAGE('Balance Sheet'!J28:K28)) -> 1.0751798 | N11: ='Income Statement'!L3/(AVERAGE('Balance Sheet'!K28:L28)) -> 1.2044842 | O11: ='Income Statement'!M3/(AVERAGE('Balance Sheet'!L28:M28)) -> 1.2365057 | Q11: Efficiency | R11: Asset Turnover ratio | S11: ='Income Statement'!P3/'Balance Sheet'!P28 -> 0.85248354 | T11: ='Income Statement'!Q3/(AVERAGE('Balance Sheet'!P28:Q28)) -> 0.89153164 | U11: ='Income Statement'!R3/(AVERAGE('Balance Sheet'!Q28:R28)) -> 0.97760048 | V11: ='Income Statement'!S3/(AVERAGE('Balance Sheet'!R28:S28)) -> 1.1121878 | W11: ='Income Statement'!T3/(AVERAGE('Balance Sheet'!S28:T28)) -> 1.1395735 | Y11: Efficiency | Z11: Asset Turnover ratio | AA11: ='Income Statement'!W3/'Balance Sheet'!W34 -> 0.75078772 | AB11: ='Income Statement'!X3/(AVERAGE('Balance Sheet'!W34:X34)) -> 0.75535131 | AC11: ='Income Statement'!Y3/(AVERAGE('Balance Sheet'!X34:Y34)) -> 0.83152226 | AD11: ='Income Statement'!Z3/(AVERAGE('Balance Sheet'!Y34:Z34)) -> 0.80562645 | AE11: ='Income Statement'!AA3/(AVERAGE('Balance Sheet'!Z34:AA34)) -> 0.77404826 | AG11: Efficiency | AH11: Asset Turnover ratio | AI11: ='Income Statement'!AD3/'Balance Sheet'!AD32 -> 1.2327165 | AJ11: ='Income Statement'!AE3/(AVERAGE('Balance Sheet'!AD32:AE32)) -> 1.2664892 | AK11: ='Income Statement'!AF3/(AVERAGE('Balance Sheet'!AE32:AF32)) -> 1.6687407 | AL11: ='Income Statement'!AG3/(AVERAGE('Balance Sheet'!AF32:AG32)) -> 1.505632 | AM11: ='Income Statement'!AH3/(AVERAGE('Balance Sheet'!AG32:AH32)) -> 1.3912114
B12: Revenue per employee | C12: ='Income Statement'!B3/'Company Profile'!$B$8 -> 2560342.6 | D12: ='Income Statement'!C3/'Company Profile'!$B$8 -> 2678254.5 | E12: ='Income Statement'!D3/'Company Profile'!$B$8 -> 3128124 | F12: ='Income Statement'!E3/'Company Profile'!$B$8 -> 3677944.5 | G12: ='Income Statement'!F3/'Company Profile'!$B$8 -> 3929739 | J12: Revenue per employee | K12: ='Income Statement'!I3/'Company Profile'!$C$8 -> 2805845.9 | L12: ='Income Statement'!J3/'Company Profile'!$C$8 -> 3105031.9 | M12: ='Income Statement'!K3/'Company Profile'!$C$8 -> 3759248.2 | N12: ='Income Statement'!L3/'Company Profile'!$C$8 -> 4535753.4 | O12: ='Income Statement'!M3/'Company Profile'!$C$8 -> 5037116.2 | R12: Revenue per employee | S12: ='Income Statement'!P3/'Company Profile'!$D$8 -> 3232809.3 | T12: ='Income Statement'!Q3/'Company Profile'!$D$8 -> 3447930.4 | U12: ='Income Statement'!R3/'Company Profile'!$D$8 -> 3917784.7 | V12: ='Income Statement'!S3/'Company Profile'!$D$8 -> 4640725.3 | W12: ='Income Statement'!T3/'Company Profile'!$D$8 -> 5027559.1 | Z12: Revenue per employee | AA12: ='Income Statement'!W3/'Company Profile'!$E$8 -> 2653182.6 | AB12: ='Income Statement'!X3/'Company Profile'!$E$8 -> 2693173.9 | AC12: ='Income Statement'!Y3/'Company Profile'!$E$8 -> 3438843.5 | AD12: ='Income Statement'!Z3/'Company Profile'!$E$8 -> 3934243.5 | AE12: ='Income Statement'!AA3/'Company Profile'!$E$8 -> 3902621.7 | AH12: Revenue per employee | AI12: ='Income Statement'!AD3/'Company Profile'!$F$8 -> 1296785 | AJ12: ='Income Statement'!AE3/'Company Profile'!$F$8 -> 1474543.7 | AK12: ='Income Statement'!AF3/'Company Profile'!$F$8 -> 3112291.2 | AL12: ='Income Statement'!AG3/'Company Profile'!$F$8 -> 3955584.2 | AM12: ='Income Statement'!AH3/'Company Profile'!$F$8 -> 4233809
B13: PAT per employee | C13: ='Income Statement'!B21/'Company Profile'!$B$8 -> 529314.85 | D13: ='Income Statement'!C21/'Company Profile'!$B$8 -> 531190.86 | E13: ='Income Statement'!D21/'Company Profile'!$B$8 -> 627226.75 | F13: ='Income Statement'!E21/'Company Profile'!$B$8 -> 690097.88 | G13: ='Income Statement'!F21/'Company Profile'!$B$8 -> 752022.84 | J13: PAT per employee | K13: ='Income Statement'!I22/'Company Profile'!$C$8 -> 514219.14 | L13: ='Income Statement'!J22/'Company Profile'!$C$8 -> 600257.13 | M13: ='Income Statement'!K22/'Company Profile'!$C$8 -> 684409.94 | N13: ='Income Statement'!L22/'Company Profile'!$C$8 -> 745044.47 | O13: ='Income Statement'!M22/'Company Profile'!$C$8 -> 826694.03 | R13: PAT per employee | S13: ='Income Statement'!P20/'Company Profile'!$D$8 -> 505761.11 | T13: ='Income Statement'!Q20/'Company Profile'!$D$8 -> 510884.13 | U13: ='Income Statement'!R20/'Company Profile'!$D$8 -> 618559.06 | V13: ='Income Statement'!S20/'Company Profile'!$D$8 -> 679029 | W13: ='Income Statement'!T20/'Company Profile'!$D$8 -> 718595.19 | Z13: PAT per employee | AA13: ='Income Statement'!W28/'Company Profile'!$E$8 -> 424860.87 | AB13: ='Income Statement'!X28/'Company Profile'!$E$8 -> 472521.74 | AC13: ='Income Statement'!Y28/'Company Profile'!$E$8 -> 532321.74 | AD13: ='Income Statement'!Z28/'Company Profile'!$E$8 -> 494195.65 | AE13: ='Income Statement'!AA28/'Company Profile'!$E$8 -> 483134.78 | AH13: PAT per employee | AI13: ='Income Statement'!AD18/'Company Profile'!$F$8 -> 181251.42 | AJ13: ='Income Statement'!AE18/'Company Profile'!$F$8 -> 231043.4 | AK13: ='Income Statement'!AF18/'Company Profile'!$F$8 -> 470860.3 | AL13: ='Income Statement'!AG18/'Company Profile'!$F$8 -> 525730.43 | AM13: ='Income Statement'!AH18/'Company Profile'!$F$8 -> 546507.89
B14: Operating Cash flow margin | C14: ='Cash flow statement'!B29/'Income Statement'!B3 -> 0.20623897 | D14: ='Cash flow statement'!C29/'Income Statement'!C3 -> 0.23634248 | E14: ='Cash flow statement'!D29/'Income Statement'!D3 -> 0.20833464 | F14: ='Cash flow statement'!E29/'Income Statement'!E3 -> 0.18613223 | G14: ='Cash flow statement'!F29/'Income Statement'!F3 -> 0.18405682 | J14: Operating Cash flow margin | K14: ='Cash flow statement'!I20/'Income Statement'!I3 -> 0.18727627 | L14: ='Cash flow statement'!J20/'Income Statement'!J3 -> 0.23114898 | M14: ='Cash flow statement'!K20/'Income Statement'!K3 -> 0.19635649 | N14: ='Cash flow statement'!L20/'Income Statement'!L3 -> 0.15307937 | O14: ='Cash flow statement'!M20/'Income Statement'!M3 -> 0.15467207 | R14: Operating Cash flow margin | S14: ='Cash flow statement'!P21/'Income Statement'!P3 -> 0.18901749 | T14: ='Cash flow statement'!Q21/'Income Statement'!Q3 -> 0.26025816 | U14: ='Cash flow statement'!R21/'Income Statement'!R3 -> 0.19731235 | V14: ='Cash flow statement'!S21/'Income Statement'!S3 -> 0.17750552 | W14: ='Cash flow statement'!T21/'Income Statement'!T3 -> 0.20423426 | Z14: Operating Cash flow margin | AA14: ='Cash flow statement'!W22/'Income Statement'!W3 -> 0.1649258 | AB14: ='Cash flow statement'!X22/'Income Statement'!X3 -> 0.23820286 | AC14: ='Cash flow statement'!Y22/'Income Statement'!Y3 -> 0.14008375 | AD14: ='Cash flow statement'!Z22/'Income Statement'!Z3 -> 0.14438995 | AE14: ='Cash flow statement'!AA22/'Income Statement'!AA3 -> 0.20121145 | AH14: Operating Cash flow margin | AI14: ='Cash flow statement'!AD25/'Income Statement'!AD3 -> 0.15107643 | AJ14: ='Cash flow statement'!AE25/'Income Statement'!AE3 -> 0.19398859 | AK14: ='Cash flow statement'!AF25/'Income Statement'!AF3 -> 0.12450639 | AL14: ='Cash flow statement'!AG25/'Income Statement'!AG3 -> 0.093258596 | AM14: ='Cash flow statement'!AH25/'Income Statement'!AH3 -> 0.15962778
A15: Liquidity | B15: Current Ratio | C15: ='Balance Sheet'!B32/'Balance Sheet'!B60 -> 3.3347007 | D15: ='Balance Sheet'!C32/'Balance Sheet'!C60 -> 2.9067486 | E15: ='Balance Sheet'!D32/'Balance Sheet'!D60 -> 2.5574367 | F15: ='Balance Sheet'!E32/'Balance Sheet'!E60 -> 2.5315671 | G15: ='Balance Sheet'!F32/'Balance Sheet'!F60 -> 2.4506334 | I15: Liquidity | J15: Current Ratio | K15: ='Balance Sheet'!I27/'Balance Sheet'!I52 -> 2.6168009 | L15: ='Balance Sheet'!J27/'Balance Sheet'!J52 -> 2.5448565 | M15: ='Balance Sheet'!K27/'Balance Sheet'!K52 -> 1.9993751 | N15: ='Balance Sheet'!L27/'Balance Sheet'!L52 -> 1.8088348 | O15: ='Balance Sheet'!M27/'Balance Sheet'!M52 -> 2.3053049 | Q15: Liquidity | R15: Current Ratio | S15: ='Balance Sheet'!P27/'Balance Sheet'!P54 -> 1.6190476 | T15: ='Balance Sheet'!Q27/'Balance Sheet'!Q54 -> 2.4766151 | U15: ='Balance Sheet'!R27/'Balance Sheet'!R54 -> 2.558775 | V15: ='Balance Sheet'!S27/'Balance Sheet'!S54 -> 2.4999767 | W15: ='Balance Sheet'!T27/'Balance Sheet'!T54 -> 2.6107102 | Y15: Liquidity | Z15: Current Ratio | AA15: ='Balance Sheet'!W33/'Balance Sheet'!W65 -> 2.4023467 | AB15: ='Balance Sheet'!X33/'Balance Sheet'!X65 -> 2.2743262 | AC15: ='Balance Sheet'!Y33/'Balance Sheet'!Y65 -> 2.013278 | AD15: ='Balance Sheet'!Z33/'Balance Sheet'!Z65 -> 2.4690517 | AE15: ='Balance Sheet'!AA33/'Balance Sheet'!AA65 -> 2.5773079 | AG15: Liquidity | AH15: Current Ratio | AI15: ='Balance Sheet'!AD31/'Balance Sheet'!AD61 -> 2.7149108 | AJ15: ='Balance Sheet'!AE31/'Balance Sheet'!AE61 -> 3.0890476 | AK15: ='Balance Sheet'!AF31/'Balance Sheet'!AF61 -> 2.9335664 | AL15: ='Balance Sheet'!AG31/'Balance Sheet'!AG61 -> 3.1346077 | AM15: ='Balance Sheet'!AH31/'Balance Sheet'!AH61 -> 3.2815155
B16: Quick ratio | C16: =('Balance Sheet'!B32-'Balance Sheet'!B21)/'Balance Sheet'!B60 -> 3.3345159 | D16: =('Balance Sheet'!C32-'Balance Sheet'!C21)/'Balance Sheet'!C60 -> 2.9065144 | E16: =('Balance Sheet'!D32-'Balance Sheet'!D21)/'Balance Sheet'!D60 -> 2.5569644 | F16: =('Balance Sheet'!E32-'Balance Sheet'!E21)/'Balance Sheet'!E60 -> 2.5309243 | G16: =('Balance Sheet'!F32-'Balance Sheet'!F21)/'Balance Sheet'!F60 -> 2.450026 | J16: Quick ratio | R16: Quick ratio | S16: =('Balance Sheet'!P27-'Balance Sheet'!P17)/'Balance Sheet'!P54 -> 1.6152128 | T16: =('Balance Sheet'!Q27-'Balance Sheet'!Q17)/'Balance Sheet'!Q54 -> 2.4712075 | U16: =('Balance Sheet'!R27-'Balance Sheet'!R17)/'Balance Sheet'!R54 -> 2.5501997 | V16: =('Balance Sheet'!S27-'Balance Sheet'!S17)/'Balance Sheet'!S54 -> 2.4893379 | W16: =('Balance Sheet'!T27-'Balance Sheet'!T17)/'Balance Sheet'!T54 -> 2.6025697 | Z16: Quick ratio | AA16: =('Balance Sheet'!W33-'Balance Sheet'!W21)/'Balance Sheet'!W65 -> 2.3937281 | AB16: =('Balance Sheet'!X33-'Balance Sheet'!X21)/'Balance Sheet'!X65 -> 2.2697009 | AC16: =('Balance Sheet'!Y33-'Balance Sheet'!Y21)/'Balance Sheet'!Y65 -> 2.0089515 | AD16: =('Balance Sheet'!Z33-'Balance Sheet'!Z21)/'Balance Sheet'!Z65 -> 2.4646148 | AE16: =('Balance Sheet'!AA33-'Balance Sheet'!AA21)/'Balance Sheet'!AA65 -> 2.5737152 | AH16: Quick ratio | AI16: =('Balance Sheet'!AD31-'Balance Sheet'!AD20)/'Balance Sheet'!AD61 -> 2.7149108 | AJ16: =('Balance Sheet'!AE31-'Balance Sheet'!AE20)/'Balance Sheet'!AE61 -> 3.0890476 | AK16: =('Balance Sheet'!AF31-'Balance Sheet'!AF20)/'Balance Sheet'!AF61 -> 2.9327612 | AL16: =('Balance Sheet'!AG31-'Balance Sheet'!AG20)/'Balance Sheet'!AG61 -> 3.1340058 | AM16: =('Balance Sheet'!AH31-'Balance Sheet'!AH20)/'Balance Sheet'!AH61 -> 3.2809932
B17: Cash ratio | C17: ='Balance Sheet'!B26/'Balance Sheet'!B60 -> 0.3195122 | D17: ='Balance Sheet'!C26/'Balance Sheet'!C60 -> 0.20079051 | E17: ='Balance Sheet'!D26/'Balance Sheet'!D60 -> 0.29486907 | F17: ='Balance Sheet'!E26/'Balance Sheet'!E60 -> 0.16352909 | G17: ='Balance Sheet'!F26/'Balance Sheet'!F60 -> 0.19555787 | J17: Cash ratio | K17: ='Balance Sheet'!I22/'Balance Sheet'!I52 -> 0.89417913 | L17: ='Balance Sheet'!J22/'Balance Sheet'!J52 -> 1.0355751 | M17: ='Balance Sheet'!K22/'Balance Sheet'!K52 -> 0.51995358 | N17: ='Balance Sheet'!L22/'Balance Sheet'!L52 -> 0.31064666 | O17: ='Balance Sheet'!M22/'Balance Sheet'!M52 -> 0.38114141 | R17: Cash ratio | S17: ='Balance Sheet'!P21/'Balance Sheet'!P54 -> 0.20429836 | T17: ='Balance Sheet'!Q21/'Balance Sheet'!Q54 -> 0.37513663 | U17: ='Balance Sheet'!R21/'Balance Sheet'!R54 -> 0.55978695 | V17: ='Balance Sheet'!S21/'Balance Sheet'!S54 -> 0.42298539 | W17: ='Balance Sheet'!T21/'Balance Sheet'!T54 -> 0.4160873 | Z17: Cash ratio | AA17: ='Balance Sheet'!W25/'Balance Sheet'!W65 -> 0.6677619 | AB17: ='Balance Sheet'!X25/'Balance Sheet'!X65 -> 0.73810207 | AC17: ='Balance Sheet'!Y25/'Balance Sheet'!Y65 -> 0.33677014 | AD17: ='Balance Sheet'!Z25/'Balance Sheet'!Z65 -> 0.34315208 | AE17: ='Balance Sheet'!AA25/'Balance Sheet'!AA65 -> 0.38403616 | AH17: Cash ratio | AI17: ='Balance Sheet'!AD25/'Balance Sheet'!AD61 -> 0.20817605 | AJ17: ='Balance Sheet'!AE25/'Balance Sheet'!AE61 -> 0.25677164 | AK17: ='Balance Sheet'!AF25/'Balance Sheet'!AF61 -> 0.28399741 | AL17: ='Balance Sheet'!AG25/'Balance Sheet'!AG61 -> 0.42660417 | AM17: ='Balance Sheet'!AH25/'Balance Sheet'!AH61 -> 0.3168965
A18: Leverage | B18: Debt to Equity ratio | C18: =('Balance Sheet'!B52+'Balance Sheet'!B44)/'Balance Sheet'!B40 -> 0.096449516 | D18: =('Balance Sheet'!C52+'Balance Sheet'!C44)/'Balance Sheet'!C40 -> 0.089486614 | E18: =('Balance Sheet'!D52+'Balance Sheet'!D44)/'Balance Sheet'!D40 -> 0.08701556 | F18: =('Balance Sheet'!E52+'Balance Sheet'!E44)/'Balance Sheet'!E40 -> 0.0842927 | G18: =('Balance Sheet'!F52+'Balance Sheet'!F44)/'Balance Sheet'!F40 -> 0.087834952 | I18: Leverage | J18: Debt to Equity ratio | K18: =('Balance Sheet'!I39+'Balance Sheet'!I47)/'Balance Sheet'!I35 -> 0.070363283 | L18: =('Balance Sheet'!J39+'Balance Sheet'!J47)/'Balance Sheet'!J35 -> 0.069352192 | M18: =('Balance Sheet'!K39+'Balance Sheet'!K47)/'Balance Sheet'!K35 -> 0.11534805 | N18: =('Balance Sheet'!L39+'Balance Sheet'!L47)/'Balance Sheet'!L35 -> 0.14409921 | O18: =('Balance Sheet'!M39+'Balance Sheet'!M47)/'Balance Sheet'!M35 -> 0.11706854 | Q18: Leverage | R18: Debt to Equity ratio | S18: =('Balance Sheet'!P38+'Balance Sheet'!P47)/'Balance Sheet'!P34 -> 0.091266214 | T18: =('Balance Sheet'!Q38+'Balance Sheet'!Q47)/'Balance Sheet'!Q34 -> 0.063712926 | U18: =('Balance Sheet'!R38+'Balance Sheet'!R47)/'Balance Sheet'!R34 -> 0.064267974 | V18: =('Balance Sheet'!S38+'Balance Sheet'!S47)/'Balance Sheet'!S34 -> 0.034420013 | W18: =('Balance Sheet'!T38+'Balance Sheet'!T47)/'Balance Sheet'!T34 -> 0.03408475 | Y18: Leverage | Z18: Debt to Equity ratio | AA18: =('Balance Sheet'!W45+'Balance Sheet'!W56)/'Balance Sheet'!W41 -> 0.10603648 | AB18: =('Balance Sheet'!X45+'Balance Sheet'!X56)/'Balance Sheet'!X41 -> 0.15137291 | AC18: =('Balance Sheet'!Y45+'Balance Sheet'!Y56)/'Balance Sheet'!Y41 -> 0.23175794 | AD18: =('Balance Sheet'!Z45+'Balance Sheet'!Z56)/'Balance Sheet'!Z41 -> 0.19310328 | AE18: =('Balance Sheet'!AA45+'Balance Sheet'!AA56)/'Balance Sheet'!AA41 -> 0.18946255 | AG18: Leverage | AH18: Debt to Equity ratio | AI18: =('Balance Sheet'!AD52)/'Balance Sheet'!AD40 -> 0.0059203345 | AJ18: =('Balance Sheet'!AE52)/'Balance Sheet'!AE40 -> 0.0056657224 | AK18: =('Balance Sheet'!AF52)/'Balance Sheet'!AF40 -> 0.0036311735 | AL18: =('Balance Sheet'!AG52)/'Balance Sheet'!AG40 -> 0.0075485566 | AM18: =('Balance Sheet'!AH52)/'Balance Sheet'!AH40 -> 0.0020323173
B19: Interest coverage ratio | C19: =('Income Statement'!B13+'Income Statement'!B9)/'Income Statement'!B9 -> 46.722944 | D19: =('Income Statement'!C13+'Income Statement'!C9)/'Income Statement'!C9 -> 71.609105 | E19: =('Income Statement'!D13+'Income Statement'!D9)/'Income Statement'!D9 -> 66.927296 | F19: =('Income Statement'!E13+'Income Statement'!E9)/'Income Statement'!E9 -> 74.051348 | G19: =('Income Statement'!F13+'Income Statement'!F9)/'Income Statement'!F9 -> 81.919023 | J19: Interest coverage ratio | K19: =('Income Statement'!I17+'Income Statement'!I14)/'Income Statement'!I14 -> 130.45294 | L19: =('Income Statement'!J17+'Income Statement'!J14)/'Income Statement'!J14 -> 137.55385 | M19: =('Income Statement'!K17+'Income Statement'!K14)/'Income Statement'!K14 -> 151.55 | N19: =('Income Statement'!L17+'Income Statement'!L14)/'Income Statement'!L14 -> 118.33099 | O19: =('Income Statement'!M17+'Income Statement'!M14)/'Income Statement'!M14 -> 91.403846 | R19: Interest coverage ratio | S19: =('Income Statement'!P15+'Income Statement'!P10)/'Income Statement'!P10 -> 28.683168 | T19: =('Income Statement'!Q15+'Income Statement'!Q10)/'Income Statement'!Q10 -> 32.023483 | U19: =('Income Statement'!R15+'Income Statement'!R10)/'Income Statement'!R10 -> 2.3544547 | V19: =('Income Statement'!S15+'Income Statement'!S10)/'Income Statement'!S10 -> 2.3035452 | W19: =('Income Statement'!T15+'Income Statement'!T10)/'Income Statement'!T10 -> 2.4382631 | Z19: Interest coverage ratio | AA19: =('Income Statement'!W23+'Income Statement'!W11)/'Income Statement'!W11 -> 17.719296 | AB19: =('Income Statement'!X23+'Income Statement'!X11)/'Income Statement'!X11 -> 28.324882 | AC19: =('Income Statement'!Y23+'Income Statement'!Y11)/'Income Statement'!Y11 -> 29.433427 | AD19: =('Income Statement'!Z23+'Income Statement'!Z11)/'Income Statement'!Z11 -> 15.652873 | AE19: =('Income Statement'!AA23+'Income Statement'!AA11)/'Income Statement'!AA11 -> 12.728011 | AH19: Interest coverage ratio | AI19: =('Income Statement'!AD13+'Income Statement'!AD9)/'Income Statement'!AD9 -> 25.248184 | AJ19: =('Income Statement'!AE13+'Income Statement'!AE9)/'Income Statement'!AE9 -> 33.845178 | AK19: =('Income Statement'!AF13+'Income Statement'!AF9)/'Income Statement'!AF9 -> 43.900324 | AL19: =('Income Statement'!AG13+'Income Statement'!AG9)/'Income Statement'!AG9 -> 39.507314 | AM19: =('Income Statement'!AH13+'Income Statement'!AH9)/'Income Statement'!AH9 -> 28.283266
B20: Financial leverage ratio | C20: ='Balance Sheet'!B33/'Balance Sheet'!B40 -> 1.4265537 | D20: ='Balance Sheet'!C33/'Balance Sheet'!C40 -> 1.5011136 | E20: ='Balance Sheet'!D33/'Balance Sheet'!D40 -> 1.5750729 | F20: ='Balance Sheet'!E33/'Balance Sheet'!E40 -> 1.575017 | G20: ='Balance Sheet'!F33/'Balance Sheet'!F40 -> 1.6037079 | J20: Financial leverage ratio | K20: ='Balance Sheet'!I28/'Balance Sheet'!I35 -> 1.4089059 | L20: ='Balance Sheet'!J28/'Balance Sheet'!J35 -> 1.4116069 | M20: ='Balance Sheet'!K28/'Balance Sheet'!K35 -> 1.5565253 | N20: ='Balance Sheet'!L28/'Balance Sheet'!L35 -> 1.6599512 | O20: ='Balance Sheet'!M28/'Balance Sheet'!M35 -> 1.5579069 | R20: Financial leverage ratio | S20: ='Balance Sheet'!P28/'Balance Sheet'!P34 -> 1.6122985 | T20: ='Balance Sheet'!Q28/'Balance Sheet'!Q34 -> 1.434606 | U20: ='Balance Sheet'!R28/'Balance Sheet'!R34 -> 1.4358772 | V20: ='Balance Sheet'!S28/'Balance Sheet'!S34 -> 1.4283464 | W20: ='Balance Sheet'!T28/'Balance Sheet'!T34 -> 1.4572952 | Z20: Financial leverage ratio | AA20: ='Balance Sheet'!W34/'Balance Sheet'!W41 -> 1.464242 | AB20: ='Balance Sheet'!X34/'Balance Sheet'!X41 -> 1.5028337 | AC20: ='Balance Sheet'!Y34/'Balance Sheet'!Y41 -> 1.6424448 | AD20: ='Balance Sheet'!Z34/'Balance Sheet'!Z41 -> 1.5069924 | AE20: ='Balance Sheet'!AA34/'Balance Sheet'!AA41 -> 1.5373672 | AH20: Financial leverage ratio | AI20: ='Balance Sheet'!AD32/'Balance Sheet'!AD40 -> 1.6326987 | AJ20: ='Balance Sheet'!AE32/'Balance Sheet'!AE40 -> 1.4655746 | AK20: ='Balance Sheet'!AF32/'Balance Sheet'!AF40 -> 1.4400437 | AL20: ='Balance Sheet'!AG32/'Balance Sheet'!AG40 -> 1.4154959 | AM20: ='Balance Sheet'!AH32/'Balance Sheet'!AH40 -> 1.3763332
A21: Valuation | B21: P/E Ratio | C21: ='Company Profile'!$B$9/'Financial Ratios'!C10 -> 33.733399 | D21: ='Company Profile'!$B$9/'Financial Ratios'!D10 -> 33.614262 | E21: ='Company Profile'!$B$9/'Financial Ratios'!E10 -> 28.467518 | F21: ='Company Profile'!$B$9/'Financial Ratios'!F10 -> 25.873995 | G21: ='Company Profile'!$B$9/'Financial Ratios'!G10 -> 23.743413 | I21: Valuation | J21: P/E Ratio | K21: ='Company Profile'!$C$9/'Financial Ratios'!K10 -> 32.910598 | L21: ='Company Profile'!$C$9/'Financial Ratios'!L10 -> 28.19335 | M21: ='Company Profile'!$C$9/'Financial Ratios'!M10 -> 24.726787 | N21: ='Company Profile'!$C$9/'Financial Ratios'!N10 -> 22.714428 | O21: ='Company Profile'!$C$9/'Financial Ratios'!O10 -> 20.471007 | Q21: Valuation | R21: P/E Ratio | S21: ='Company Profile'!$D$9/'Financial Ratios'!S10 -> 37.741344 | T21: ='Company Profile'!$D$9/'Financial Ratios'!T10 -> 37.362883 | U21: ='Company Profile'!$D$9/'Financial Ratios'!U10 -> 30.858984 | V21: ='Company Profile'!$D$9/'Financial Ratios'!V10 -> 28.110882 | W21: ='Company Profile'!$D$9/'Financial Ratios'!W10 -> 26.563084 | Y21: Valuation | Z21: P/E Ratio | AA21: ='Company Profile'!$E$9/'Financial Ratios'!AA10 -> 25.699804 | AB21: ='Company Profile'!$E$9/'Financial Ratios'!AB10 -> 23.107595 | AC21: ='Company Profile'!$E$9/'Financial Ratios'!AC10 -> 20.511733 | AD21: ='Company Profile'!$E$9/'Financial Ratios'!AD10 -> 22.094167 | AE21: ='Company Profile'!$E$9/'Financial Ratios'!AE10 -> 22.59999 | AG21: Valuation | AH21: P/E Ratio | AI21: ='Company Profile'!$F$9/'Financial Ratios'!AI10 -> 110.11276 | AJ21: ='Company Profile'!$F$9/'Financial Ratios'!AJ10 -> 86.382442 | AK21: ='Company Profile'!$F$9/'Financial Ratios'!AK10 -> 42.386443 | AL21: ='Company Profile'!$F$9/'Financial Ratios'!AL10 -> 37.962599 | AM21: ='Company Profile'!$F$9/'Financial Ratios'!AM10 -> 36.519315
B22: P/B Ratio | C22: ='Company Profile'!$B$9/('Balance Sheet'!B40/'Company Profile'!$B$11) -> 12.915168 | D22: ='Company Profile'!$B$9/('Balance Sheet'!C40/'Company Profile'!$B$11) -> 12.565409 | E22: ='Company Profile'!$B$9/('Balance Sheet'!D40/'Company Profile'!$B$11) -> 12.182486 | F22: ='Company Profile'!$B$9/('Balance Sheet'!E40/'Company Profile'!$B$11) -> 12.000829 | G22: ='Company Profile'!$B$9/('Balance Sheet'!F40/'Company Profile'!$B$11) -> 11.985979 | J22: P/B Ratio | K22: ='Company Profile'!$C$9/(('Balance Sheet'!I35)/'Company Profile'!$C$11) -> 9.5268393 | L22: ='Company Profile'!$C$9/(('Balance Sheet'!J35)/'Company Profile'!$C$11) -> 8.1696909 | M22: ='Company Profile'!$C$9/(('Balance Sheet'!K35)/'Company Profile'!$C$11) -> 8.2825236 | N22: ='Company Profile'!$C$9/(('Balance Sheet'!L35)/'Company Profile'!$C$11) -> 8.2760764 | O22: ='Company Profile'!$C$9/(('Balance Sheet'!M35)/'Company Profile'!$C$11) -> 7.0910934 | R22: P/B Ratio | S22: ='Company Profile'!$D$9/(('Balance Sheet'!P34)/'Company Profile'!$D$11) -> 8.115479 | T22: ='Company Profile'!$D$9/(('Balance Sheet'!Q34)/'Company Profile'!$D$11) -> 6.9456084 | U22: ='Company Profile'!$D$9/(('Balance Sheet'!R34)/'Company Profile'!$D$11) -> 6.7300914 | V22: ='Company Profile'!$D$9/(('Balance Sheet'!S34)/'Company Profile'!$D$11) -> 6.3810215 | W22: ='Company Profile'!$D$9/(('Balance Sheet'!T34)/'Company Profile'!$D$11) -> 6.1124935 | Z22: P/B Ratio | AA22: ='Company Profile'!$E$9/(('Balance Sheet'!W41)/'Company Profile'!$E$11) -> 4.5241752 | AB22: ='Company Profile'!$E$9/(('Balance Sheet'!X41)/'Company Profile'!$E$11) -> 4.5618473 | AC22: ='Company Profile'!$E$9/(('Balance Sheet'!Y41)/'Company Profile'!$E$11) -> 3.8367621 | AD22: ='Company Profile'!$E$9/(('Balance Sheet'!Z41)/'Company Profile'!$E$11) -> 3.230975 | AE22: ='Company Profile'!$E$9/(('Balance Sheet'!AA41)/'Company Profile'!$E$11) -> 3.363378 | AH22: P/B Ratio | AI22: =('Company Profile'!$F$9/(('Balance Sheet'!AD40)/'Company Profile'!$F$11)) -> 30.975643 | AJ22: =('Company Profile'!$F$9/(('Balance Sheet'!AE40)/'Company Profile'!$F$11)) -> 22.912845 | AK22: =('Company Profile'!$F$9/(('Balance Sheet'!AF40)/'Company Profile'!$F$11)) -> 11.713959 | AL22: =('Company Profile'!$F$9/(('Balance Sheet'!AG40)/'Company Profile'!$F$11)) -> 10.086417 | AM22: =('Company Profile'!$F$9/(('Balance Sheet'!AH40)/'Company Profile'!$F$11)) -> 8.3602869
B23: EV/EBITDA | C23: =(('Company Profile'!$B$13+'Balance Sheet'!B44+'Balance Sheet'!B52)-'Balance Sheet'!B26)/('Income Statement'!B13+'Income Statement'!B9+'Income Statement'!B10) -> 23.16839 | D23: =(('Company Profile'!$B$13+'Balance Sheet'!C44+'Balance Sheet'!C52)-'Balance Sheet'!C26)/('Income Statement'!C13+'Income Statement'!C9+'Income Statement'!C10) -> 21.807488 | E23: =(('Company Profile'!$B$13+'Balance Sheet'!D44+'Balance Sheet'!D52)-'Balance Sheet'!D26)/('Income Statement'!D13+'Income Statement'!D9+'Income Statement'!D10) -> 18.883732 | F23: =(('Company Profile'!$B$13+'Balance Sheet'!E44+'Balance Sheet'!E52)-'Balance Sheet'!E26)/('Income Statement'!E13+'Income Statement'!E9+'Income Statement'!E10) -> 17.270906 | G23: =(('Company Profile'!$B$13+'Balance Sheet'!F44+'Balance Sheet'!F52)-'Balance Sheet'!F26)/('Income Statement'!F13+'Income Statement'!F9+'Income Statement'!F10) -> 15.737711 | J23: EV/EBITDA | K23: =(('Company Profile'!$C$13+'Balance Sheet'!I39+'Balance Sheet'!I47)-'Balance Sheet'!I22)/('Income Statement'!I17+'Income Statement'!I14+'Income Statement'!I13) -> 23.859729 | L23: =(('Company Profile'!$C$13+'Balance Sheet'!J39+'Balance Sheet'!J47)-'Balance Sheet'!J22)/('Income Statement'!J17+'Income Statement'!J14+'Income Statement'!J13) -> 19.700578 | M23: =(('Company Profile'!$C$13+'Balance Sheet'!K39+'Balance Sheet'!K47)-'Balance Sheet'!K22)/('Income Statement'!K17+'Income Statement'!K14+'Income Statement'!K13) -> 17.860753 | N23: =(('Company Profile'!$C$13+'Balance Sheet'!L39+'Balance Sheet'!L47)-'Balance Sheet'!L22)/('Income Statement'!L17+'Income Statement'!L14+'Income Statement'!L13) -> 16.148883 | O23: =(('Company Profile'!$C$13+'Balance Sheet'!M39+'Balance Sheet'!M47)-'Balance Sheet'!M22)/('Income Statement'!M17+'Income Statement'!M14+'Income Statement'!M13) -> 14.187819 | R23: EV/EBITDA | S23: =(('Company Profile'!$D$13+'Balance Sheet'!P38+'Balance Sheet'!P47+'Balance Sheet'!P39+'Balance Sheet'!P48)-'Balance Sheet'!P21)/('Income Statement'!P15+'Income Statement'!P10+'Income Statement'!P11) -> 23.031075 | T23: =(('Company Profile'!$D$13+'Balance Sheet'!Q38+'Balance Sheet'!Q47+'Balance Sheet'!Q39+'Balance Sheet'!Q48)-'Balance Sheet'!Q21)/('Income Statement'!Q15+'Income Statement'!Q10+'Income Statement'!Q11) -> 19.552677 | U23: =(('Company Profile'!$D$13+'Balance Sheet'!R38+'Balance Sheet'!R47+'Balance Sheet'!R39+'Balance Sheet'!R48)-'Balance Sheet'!R21)/('Income Statement'!R15+'Income Statement'!R10+'Income Statement'!R11) -> 13.785241 | V23: =(('Company Profile'!$D$13+'Balance Sheet'!S38+'Balance Sheet'!S47+'Balance Sheet'!S39+'Balance Sheet'!S48)-'Balance Sheet'!S21)/('Income Statement'!S15+'Income Statement'!S10+'Income Statement'!S11) -> 11.797862 | W23: =(('Company Profile'!$D$13+'Balance Sheet'!T38+'Balance Sheet'!T47+'Balance Sheet'!T39+'Balance Sheet'!T48)-'Balance Sheet'!T21)/('Income Statement'!T15+'Income Statement'!T10+'Income Statement'!T11) -> 11.36474 | Z23: EV/EBITDA | AA23: =(('Company Profile'!$E$13+'Balance Sheet'!W45+'Balance Sheet'!W56+'Balance Sheet'!W47+'Balance Sheet'!W59)-'Balance Sheet'!W25)/('Income Statement'!W23+'Income Statement'!W11+'Income Statement'!W12) -> 15.992767 | AB23: =(('Company Profile'!$E$13+'Balance Sheet'!X45+'Balance Sheet'!X56+'Balance Sheet'!X47+'Balance Sheet'!X59)-'Balance Sheet'!X25)/('Income Statement'!X23+'Income Statement'!X11+'Income Statement'!X12) -> 14.039534 | AC23: =(('Company Profile'!$E$13+'Balance Sheet'!Y45+'Balance Sheet'!Y56+'Balance Sheet'!Y47+'Balance Sheet'!Y59)-'Balance Sheet'!Y25)/('Income Statement'!Y23+'Income Statement'!Y11+'Income Statement'!Y12) -> 13.592141 | AD23: =(('Company Profile'!$E$13+'Balance Sheet'!Z45+'Balance Sheet'!Z56+'Balance Sheet'!Z47+'Balance Sheet'!Z59)-'Balance Sheet'!Z25)/('Income Statement'!Z23+'Income Statement'!Z11+'Income Statement'!Z12) -> 13.390303 | AE23: =(('Company Profile'!$E$13+'Balance Sheet'!AA45+'Balance Sheet'!AA56+'Balance Sheet'!AA47+'Balance Sheet'!AA59)-'Balance Sheet'!AA25)/('Income Statement'!AA23+'Income Statement'!AA11+'Income Statement'!AA12) -> 13.12614 | AH23: EV/EBITDA | AI23: =(('Company Profile'!$F$13+'Balance Sheet'!AD52+'Balance Sheet'!AD44+'Balance Sheet'!AD57)-'Balance Sheet'!AD25)/('Income Statement'!AD13+'Income Statement'!AD10+'Income Statement'!AD9) -> 70.165529 | AJ23: =(('Company Profile'!$F$13+'Balance Sheet'!AE52+'Balance Sheet'!AE44+'Balance Sheet'!AE57)-'Balance Sheet'!AE25)/('Income Statement'!AE13+'Income Statement'!AE10+'Income Statement'!AE9) -> 55.069578 | AK23: =(('Company Profile'!$F$13+'Balance Sheet'!AF52+'Balance Sheet'!AF44+'Balance Sheet'!AF57)-'Balance Sheet'!AF25)/('Income Statement'!AF13+'Income Statement'!AF10+'Income Statement'!AF9) -> 27.434773 | AL23: =(('Company Profile'!$F$13+'Balance Sheet'!AG52+'Balance Sheet'!AG44+'Balance Sheet'!AG57)-'Balance Sheet'!AG25)/('Income Statement'!AG13+'Income Statement'!AG10+'Income Statement'!AG9) -> 24.646806 | AM23: =(('Company Profile'!$F$13+'Balance Sheet'!AH52+'Balance Sheet'!AH44+'Balance Sheet'!AH57)-'Balance Sheet'!AH25)/('Income Statement'!AH13+'Income Statement'!AH10+'Income Statement'!AH9) -> 23.318156
B24: Dividend Yield | C24: =(-'Cash flow statement'!B47/'Company Profile'!$B$11)/'Company Profile'!$B$9 -> 0.034383155 | D24: =(-'Cash flow statement'!C47/'Company Profile'!$B$11)/'Company Profile'!$B$9 -> 0.0099127712 | E24: =(-'Cash flow statement'!D47/'Company Profile'!$B$11)/'Company Profile'!$B$9 -> 0.01216667 | F24: =(-'Cash flow statement'!E47/'Company Profile'!$B$11)/'Company Profile'!$B$9 -> 0.037775424 | G24: =(-'Cash flow statement'!F47/'Company Profile'!$B$11)/'Company Profile'!$B$9 -> 0.022965652 | J24: Dividend Yield | K24: =(-'Cash flow statement'!I50/'Company Profile'!$C$11)/'Company Profile'!$C$9 -> 0.015168539 | L24: =(-'Cash flow statement'!J50/'Company Profile'!$C$11)/'Company Profile'!$C$9 -> 0.014534059 | M24: =(-'Cash flow statement'!K50/'Company Profile'!$C$11)/'Company Profile'!$C$9 -> 0.020169454 | N24: =(-'Cash flow statement'!L50/'Company Profile'!$C$11)/'Company Profile'!$C$9 -> 0.021730147 | O24: =(-'Cash flow statement'!M50/'Company Profile'!$C$11)/'Company Profile'!$C$9 -> 0.023421563 | R24: Dividend Yield | S24: =((-'Cash flow statement'!P45)/'Company Profile'!$D$11)/'Company Profile'!$D$9 -> 0.0032518101 | T24: =((-'Cash flow statement'!Q45)/'Company Profile'!$D$11)/'Company Profile'!$D$9 -> 0.0078024271 | U24: =((-'Cash flow statement'!R45)/'Company Profile'!$D$11)/'Company Profile'!$D$9 -> 0.027296513 | V24: =((-'Cash flow statement'!S45)/'Company Profile'!$D$11)/'Company Profile'!$D$9 -> 0.031140215 | W24: =((-'Cash flow statement'!T45)/'Company Profile'!$D$11)/'Company Profile'!$D$9 -> 0.033706677 | Z24: Dividend Yield | AA24: =(((-('Cash flow statement'!W42+'Cash flow statement'!W43))/'Company Profile'!$E$11)/'Company Profile'!$E$9) -> 0.0032962568 | AB24: =(((-('Cash flow statement'!X42+'Cash flow statement'!X43))/'Company Profile'!$E$11)/'Company Profile'!$E$9) -> 0.0025560126 | AC24: =(((-('Cash flow statement'!Y42+'Cash flow statement'!Y43))/'Company Profile'!$E$11)/'Company Profile'!$E$9) -> 0.0026288823 | AD24: =(((-('Cash flow statement'!Z42+'Cash flow statement'!Z43))/'Company Profile'!$E$11)/'Company Profile'!$E$9) -> 0 | AE24: =(((-('Cash flow statement'!AA42+'Cash flow statement'!AA43))/'Company Profile'!$E$11)/'Company Profile'!$E$9) -> 0.057935357 | AH24: Dividend Yield | AI24: =(((-'Cash flow statement'!AD43)/'Company Profile'!$F$11)/'Company Profile'!$F$9) -> 0.00048678091 | AJ24: =(((-'Cash flow statement'!AE43)/'Company Profile'!$F$11)/'Company Profile'!$F$9) -> 0 | AK24: =(((-'Cash flow statement'!AF43)/'Company Profile'!$F$11)/'Company Profile'!$F$9) -> 0.0079300493 | AL24: =(((-'Cash flow statement'!AG43)/'Company Profile'!$F$11)/'Company Profile'!$F$9) -> 0.0093336507 | AM24: =(((-'Cash flow statement'!AH43)/'Company Profile'!$F$11)/'Company Profile'!$F$9) -> 0.010603462
B25: PEG Ratio | C25: =C21/3.81 -> 8.8539106 | D25: =D21/0.35 -> 96.04075 | E25: =E21/18.08 -> 1.5745309 | F25: =F21/10.02 -> 2.582235 | G25: =G21/8.97 -> 2.6469803 | J25: PEG Ratio | K25: =K21/10.42 -> 3.1584067 | L25: =L21/16.73 -> 1.6851972 | M25: =M21/14.02 -> 1.7636796 | N25: =N21/8.86 -> 2.5637052 | O25: =O21/10.96 -> 1.8677926 | R25: PEG Ratio | S25: =S21/9.12 -> 4.1383053 | T25: =T21/1.01 -> 36.992954 | U25: =U21/21.08 -> 1.4638987 | V25: =V21/9.78 -> 2.8743233 | W25: =W21/5.83 -> 4.5562751 | Z25: PEG Ratio | AA25: =AA21/AA26 -> -0.68365137 | AB25: =AB21/AB26 -> 2.0598686 | AC25: =AC21/AC26 -> 1.6207758 | AD25: =AD21/AD26 -> -3.0848183 | AE25: =AE21/AE26 -> -10.097594 | AH25: PEG Ratio | AI25: =AI21/AI26 -> -189.84958 | AJ25: =AJ21/AJ26 -> 3.1444698 | AK25: =AK21/AK26 -> 0.40835771 | AL25: =AL21/AL26 -> 3.2577073 | AM25: =AM21/AM26 -> 9.2404552
A26: Leverage | B26: Debt/Capital employed | C26: =('Balance Sheet'!B44+'Balance Sheet'!B52)/('Balance Sheet'!B33-'Balance Sheet'!B60) -> 0.08710664 | D26: =('Balance Sheet'!C44+'Balance Sheet'!C52)/('Balance Sheet'!C33-'Balance Sheet'!C60) -> 0.080690241 | E26: =('Balance Sheet'!D44+'Balance Sheet'!D52)/('Balance Sheet'!D33-'Balance Sheet'!D60) -> 0.07883989 | F26: =('Balance Sheet'!E44+'Balance Sheet'!E52)/('Balance Sheet'!E33-'Balance Sheet'!E60) -> 0.076808568 | G26: =('Balance Sheet'!F44+'Balance Sheet'!F52)/('Balance Sheet'!F33-'Balance Sheet'!F60) -> 0.079934227 | I26: Leverage | J26: Debt/Capital Employed | K26: =('Balance Sheet'!I39+'Balance Sheet'!I47)/('Balance Sheet'!I28-'Balance Sheet'!I52) -> 0.064425965 | L26: =('Balance Sheet'!J39+'Balance Sheet'!J47)/('Balance Sheet'!J28-'Balance Sheet'!J52) -> 0.063002094 | M26: =('Balance Sheet'!K39+'Balance Sheet'!K47)/('Balance Sheet'!K28-'Balance Sheet'!K52) -> 0.10365203 | N26: =('Balance Sheet'!L39+'Balance Sheet'!L47)/('Balance Sheet'!L28-'Balance Sheet'!L52) -> 0.12607642 | O26: =('Balance Sheet'!M39+'Balance Sheet'!M47)/('Balance Sheet'!M28-'Balance Sheet'!M52) -> 0.10458493 | Q26: Leverage | R26: Debt/Capital employed | S26: =('Balance Sheet'!P38+'Balance Sheet'!P39+'Balance Sheet'!P47+'Balance Sheet'!P49)/('Balance Sheet'!P28-'Balance Sheet'!P54) -> 0.12821076 | T26: =('Balance Sheet'!Q38+'Balance Sheet'!Q39+'Balance Sheet'!Q47+'Balance Sheet'!Q49)/('Balance Sheet'!Q28-'Balance Sheet'!Q54) -> 0.093328102 | U26: =('Balance Sheet'!R38+'Balance Sheet'!R39+'Balance Sheet'!R47+'Balance Sheet'!R49)/('Balance Sheet'!R28-'Balance Sheet'!R54) -> 0.090281534 | V26: =('Balance Sheet'!S38+'Balance Sheet'!S39+'Balance Sheet'!S47+'Balance Sheet'!S49)/('Balance Sheet'!S28-'Balance Sheet'!S54) -> 0.066490692 | W26: =('Balance Sheet'!T38+'Balance Sheet'!T39+'Balance Sheet'!T47+'Balance Sheet'!T49)/('Balance Sheet'!T28-'Balance Sheet'!T54) -> 0.074982088 | AA26: =((9.33-14.95)/14.95)*100 -> -37.591973 | AB26: =((AB10-AA10)/AA10)*100 -> 11.217995 | AC26: =((AC10-AB10)/AB10)*100 -> 12.655502 | AD26: =((AD10-AC10)/AC10)*100 -> -7.1622262 | AE26: =((AE10-AD10)/AD10)*100 -> -2.238156 | AI26: -0.58 | AJ26: =((AJ10-AI10)/AI10)*100 -> 27.471227 | AK26: =((AK10-AJ10)/AJ10)*100 -> 103.79734 | AL26: =((AL10-AK10)/AK10)*100 -> 11.653165 | AM26: =((AM10-AL10)/AL10)*100 -> 3.9521121
Y27: Leverage | Z27: Debt/Capital employed | AA27: =('Balance Sheet'!W45+'Balance Sheet'!W47+'Balance Sheet'!W56+'Balance Sheet'!W59)/('Balance Sheet'!W34-'Balance Sheet'!W65) -> 0.13088284 | AB27: =('Balance Sheet'!X45+'Balance Sheet'!X47+'Balance Sheet'!X56+'Balance Sheet'!X59)/('Balance Sheet'!X34-'Balance Sheet'!X65) -> 0.17498267 | AC27: =('Balance Sheet'!Y45+'Balance Sheet'!Y47+'Balance Sheet'!Y56+'Balance Sheet'!Y59)/('Balance Sheet'!Y34-'Balance Sheet'!Y65) -> 0.22945515 | AD27: =('Balance Sheet'!Z45+'Balance Sheet'!Z47+'Balance Sheet'!Z56+'Balance Sheet'!Z59)/('Balance Sheet'!Z34-'Balance Sheet'!Z65) -> 0.19330356 | AE27: =('Balance Sheet'!AA45+'Balance Sheet'!AA47+'Balance Sheet'!AA56+'Balance Sheet'!AA59)/('Balance Sheet'!AA34-'Balance Sheet'!AA65) -> 0.18387332 | AG27: Leverage | AH27: Debt/Capital Employed | AI27: =('Balance Sheet'!AD44+'Balance Sheet'!AD52+'Balance Sheet'!AD57)/('Balance Sheet'!AD32-'Balance Sheet'!AD61) -> 0.14042842 | AJ27: =('Balance Sheet'!AE44+'Balance Sheet'!AE52+'Balance Sheet'!AE57)/('Balance Sheet'!AE32-'Balance Sheet'!AE61) -> 0.098838649 | AK27: =('Balance Sheet'!AF44+'Balance Sheet'!AF52+'Balance Sheet'!AF57)/('Balance Sheet'!AF32-'Balance Sheet'!AF61) -> 0.089805747 | AL27: =('Balance Sheet'!AG44+'Balance Sheet'!AG52+'Balance Sheet'!AG57)/('Balance Sheet'!AG32-'Balance Sheet'!AG61) -> 0.085558054 | AM27: =('Balance Sheet'!AH44+'Balance Sheet'!AH52+'Balance Sheet'!AH57)/('Balance Sheet'!AH32-'Balance Sheet'!AH61) -> 0.094895462
B29: Market Price | C29: 2269 | D29: 3191.1 | E29: 3748 | F29: 3224.95 | G29: 3897.7 | J29: Market Price | K29: 926.25 | L29: 1380 | M29: 1886.85 | N29: 1435 | O29: 1525 | R29: Market Price | S29: 695 | T29: =992 -> 992 | U29: 1161 | V29: 1089.95 | W29: 1549 | Z29: Market Price | AA29: =135.5 -> 135.5 | AB29: =209.43 -> 209.43 | AC29: =295.85 -> 295.85 | AD29: 183.98 | AE29: 241.85 | AH29: Market Price | AI29: 2480.05 | AJ29: 4082 | AK29: =6148.95 -> 6148.95 | AL29: =4760 -> 4760 | AM29: =4955 -> 4955
B30: Outstanding Shares | C30: ='Company Profile'!$B$11 -> 361.81 | D30: ='Company Profile'!$B$11 -> 361.81 | E30: ='Company Profile'!$B$11 -> 361.81 | F30: ='Company Profile'!$B$11 -> 361.81 | G30: ='Company Profile'!$B$11 -> 361.81 | J30: Outstanding Shares | K30: ='Company Profile'!$C$11 -> 414.46 | L30: ='Company Profile'!$C$11 -> 414.46 | M30: ='Company Profile'!$C$11 -> 414.46 | N30: ='Company Profile'!$C$11 -> 414.46 | O30: ='Company Profile'!$C$11 -> 414.46 | R30: Outstanding Shares | S30: ='Company Profile'!$D$11 -> 270.89 | T30: ='Company Profile'!$D$11 -> 270.89 | U30: ='Company Profile'!$D$11 -> 270.89 | V30: ='Company Profile'!$D$11 -> 270.89 | W30: ='Company Profile'!$D$11 -> 270.89 | Z30: Outstanding Shares | AA30: ='Company Profile'!$E$11 -> 1047.087 | AB30: ='Company Profile'!$E$11 -> 1047.087 | AC30: ='Company Profile'!$E$11 -> 1047.087 | AD30: ='Company Profile'!$E$11 -> 1047.087 | AE30: ='Company Profile'!$E$11 -> 1047.087 | AH30: Outstanding Shares | AI30: ='Company Profile'!$F$11 -> 29.633 | AJ30: ='Company Profile'!$F$11 -> 29.633 | AK30: ='Company Profile'!$F$11 -> 29.633 | AL30: ='Company Profile'!$F$11 -> 29.633 | AM30: ='Company Profile'!$F$11 -> 29.633
B31: Market Cap | C31: =C29*C30 -> 820946.89 | D31: =D29*D30 -> 1154571.9 | E31: =E29*E30 -> 1356063.9 | F31: =F29*F30 -> 1166819.2 | G31: =G29*G30 -> 1410226.8 | J31: Market Cap | K31: =K29*K30 -> 383893.57 | L31: =L29*L30 -> 571954.8 | M31: =M29*M30 -> 782023.85 | N31: =N29*N30 -> 594750.1 | O31: =O29*O30 -> 632051.5 | R31: Market Cap | S31: =S29*S30 -> 188268.55 | T31: =T29*T30 -> 268722.88 | U31: =U29*U30 -> 314503.29 | V31: =V29*V30 -> 295256.56 | W31: =W29*W30 -> 419608.61 | Z31: Market Cap | AA31: =AA29*AA30 -> 141880.29 | AB31: =AB29*AB30 -> 219291.43 | AC31: =AC29*AC30 -> 309780.69 | AD31: =AD29*AD30 -> 192643.07 | AE31: =AE29*AE30 -> 253237.99 | AH31: Market Cap | AI31: =AI29*AI30 -> 73491.322 | AJ31: =AJ29*AJ30 -> 120961.91 | AK31: =AK29*AK30 -> 182211.84 | AL31: =AL29*AL30 -> 141053.08 | AM31: =AM29*AM30 -> 146831.51

Sheet WACC
A1: WACC CALCULATION | H1: KEY ASSUMPTIONS
A2: Component | B2: #VALUE! | C2: #VALUE! | D2: #VALUE! | E2: #VALUE! | F2: #VALUE! | H2: Parameter | I2: #VALUE! | J2: #VALUE! | K2: #VALUE! | L2: #VALUE! | M2: #VALUE!
A3: Risk-Free Rate (Rf) | B3: 0.0679 | C3: 0.0679 | D3: 0.0679 | E3: 0.0679 | F3: 0.0679 | H3: Terminal growth rate | I3: 0.04 | J3: 0.04 | K3: 0.04 | L3: 0.04 | M3: 0.04
A4: Beta | B4: ='Company Profile'!B17 -> 0.9429 | C4: ='Company Profile'!C17 -> 0.8999 | D4: ='Company Profile'!D17 -> 1.0408 | E4: ='Company Profile'!E17 -> 0.8684 | F4: ='Company Profile'!F17 -> 1.3531 | H4: Risk-free rate (Rf) | I4: =B3 -> 0.0679 | J4: =C3 -> 0.0679 | K4: =D3 -> 0.0679 | L4: =E3 -> 0.0679 | M4: =F3 -> 0.0679
A5: Market Risk Premium | B5: 0.0726 | C5: 0.0726 | D5: 0.0726 | E5: 0.0726 | F5: 0.0726 | H5: Cost of equity (Ke) | I5: =B6 -> 0.13635454 | J5: =C6 -> 0.13323274 | K5: =D6 -> 0.14346208 | L5: =E6 -> 0.13094584 | M5: =F6 -> 0.16613506
A6: Cost of Equity (Ke) | B6: =B3+B4*B5 -> 0.13635454 | C6: =C3+C4*C5 -> 0.13323274 | D6: =D3+D4*D5 -> 0.14346208 | E6: =E3+E4*E5 -> 0.13094584 | F6: =F3+F4*F5 -> 0.16613506 | H6: Dividend Payout ratio | I6: =(AVERAGE('Cash flow statement'!B62:F62)/AVERAGE('Financial Ratios'!C10:G10)) -> 0.66863859 | J6: =(AVERAGE('Cash flow statement'!I62:M62))/(AVERAGE('Financial Ratios'!K10:O10)) -> 0.47709605 | K6: =(AVERAGE('Cash flow statement'!P55:T55))/(AVERAGE('Financial Ratios'!S10:W10)) -> 0.64950833 | L6: =(AVERAGE('Cash flow statement'!W51:AA51))/(AVERAGE('Financial Ratios'!AA10:AE10)) -> 0.30127994 | M6: =(AVERAGE('Cash flow statement'!AD51:AH51))/(AVERAGE('Financial Ratios'!AI10:AM10)) -> 0.28939989
A7: Cost of Debt (Pre tax) | B7: =(AVERAGE('Income Statement'!B9:F9))/((AVERAGE('Balance Sheet'!B44:F44)+AVERAGE('Balance Sheet'!B52:F52))) -> 0.098794815 | C7: =((AVERAGE('Income Statement'!I14:M14))/((AVERAGE('Balance Sheet'!I39:M39)+AVERAGE('Balance Sheet'!I47:M47)))) -> 0.031647153 | D7: 0.068 | E7: =(AVERAGE('Income Statement'!W11:AA11))/(AVERAGE('Balance Sheet'!W45:AA45)+AVERAGE('Balance Sheet'!W56:AA56)) -> 0.068955858 | F7: =(AVERAGE('Income Statement'!AD9:AH9))/(AVERAGE('Balance Sheet'!AD44:AH44)+AVERAGE('Balance Sheet'!AD57:AH57)) -> 0.10229219
A8: Tax rate | B8: 0.25 | C8: 0.25 | D8: 0.25 | E8: 0.25 | F8: 0.25
A9: Cost of debt (Kd) | B9: =B7*(1-B8) -> 0.074096111 | C9: =C7*(1-C8) -> 0.023735365 | D9: =D7*(1-D8) -> 0.051 | E9: =E7*(1-E8) -> 0.051716893 | F9: =F7*(1-F8) -> 0.076719144
A10: Market value of equity | B10: ='Company Profile'!B13 -> 1082459 | C10: ='Company Profile'!C13 -> 612179.4 | D10: ='Company Profile'!D13 -> 409181.4 | E10: ='Company Profile'!E13 -> 247658.3 | F10: ='Company Profile'!F13 -> 165058.8
A11: Debt | B11: =AVERAGE('Balance Sheet'!B44:F44)+AVERAGE('Balance Sheet'!B52:F52) -> 7899.2 | C11: =AVERAGE('Balance Sheet'!I39:M39)+AVERAGE('Balance Sheet'!I47:M47) -> 7994.4 | D11: =AVERAGE('Balance Sheet'!P38:T38)+AVERAGE('Balance Sheet'!P39:T39)+AVERAGE('Balance Sheet'!P47:T47)+AVERAGE('Balance Sheet'!P49:T49) -> 6178.8 | E11: =AVERAGE('Balance Sheet'!W45:AA45)+AVERAGE('Balance Sheet'!W47:AA47)+AVERAGE('Balance Sheet'!W56:AA56)+AVERAGE('Balance Sheet'!W59:AA59) -> 13956.32 | F11: =AVERAGE('Balance Sheet'!AD44:AH44)+AVERAGE('Balance Sheet'!AD52:AH52)+AVERAGE('Balance Sheet'!AD57:AH57) -> 1342.62
A12: Total Capital | B12: =B10+B11 -> 1090358.2 | C12: =C10+C11 -> 620173.8 | D12: =D10+D11 -> 415360.2 | E12: =E10+E11 -> 261614.62 | F12: =F10+F11 -> 166401.42
A13: We | B13: =B10/B12 -> 0.99275541 | C13: =C10/C12 -> 0.98710942 | D13: =D10/D12 -> 0.98512424 | E13: =E10/E12 -> 0.94665313 | F13: =F10/F12 -> 0.99193144
A14: Wd | B14: =B11/B12 -> 0.0072445917 | C14: =C11/C12 -> 0.01289058 | D14: =D11/D12 -> 0.014875763 | E14: =E11/E12 -> 0.053346866 | F14: =F11/F12 -> 0.008068561
A15: WACC | B15: =(B13*B6)+(B9*B14) -> 0.1359035 | C15: =(C13*C6)+(C9*C14) -> 0.13182126 | D15: =(D13*D6)+(D9*D14) -> 0.14208664 | E15: =(E13*E6)+(E9*E14) -> 0.12671922 | F15: =(F13*F6)+(F9*F14) -> 0.1654136

Sheet Valuation
A1: Valuation | H1: #VALUE! | K1: Valuation | R1: #VALUE! | U1: Valuation | AB1: #VALUE! | AE1: Valuation | AL1: #VALUE! | AO1: Valuation | AV1: #VALUE!
A2: Year | B2: 2024 | C2: CAGR | D2: 2025 | E2: 2026 | F2: 2027 | G2: 2028 | H2: 2029 | I2: 2030 | K2: Year | L2: 2024 | M2: CAGR | N2: 2025 | O2: 2026 | P2: 2027 | Q2: 2028 | R2: 2029 | S2: 2030 | U2: Year | V2: 2024 | W2: CAGR | X2: 2025 | Y2: 2026 | Z2: 2027 | AA2: 2028 | AB2: 2029 | AC2: 2030 | AE2: Year | AF2: 2024 | AG2: CAGR | AH2: 2025 | AI2: 2026 | AJ2: 2027 | AK2: 2028 | AL2: 2029 | AM2: 2030 | AO2: Year | AP2: 2024 | AQ2: CAGR | AR2: 2025 | AS2: 2026 | AT2: 2027 | AU2: 2028 | AV2: 2029 | AW2: 2030
A3: Revenue | B3: ='Income Statement'!F5 -> 245315 | C3: =('Income Statement'!F5/'Income Statement'!B5)^(1/5)-1 -> 0.087146989 | D3: =B3*(1+$C$3) -> 266693.46 | E3: =D3*(1+$C$3) -> 289935 | F3: =E3*(1+$C$3) -> 315201.96 | G3: =F3*(1+$C$3) -> 342670.86 | H3: =G3*(1+$C$3) -> 372533.59 | I3: =H3*(1+$C$3) -> 404998.77 | K3: Revenue | L3: ='Income Statement'!M5 -> 166590 | M3: =('Income Statement'!M5/'Income Statement'!I5)^(1/5)-1 -> 0.12222563 | N3: =L3*(1+M3) -> 186951.57 | O3: =N3*(1+$M$3) -> 209801.84 | P3: =O3*(1+$M$3) -> 235445 | Q3: =P3*(1+$M$3) -> 264222.42 | R3: =Q3*(1+$M$3) -> 296517.17 | S3: =R3*(1+$M$3) -> 332759.17 | U3: Revenue | V3: ='Income Statement'!T5 -> 111408 | W3: =('Income Statement'!T5/'Income Statement'!P5)^(1/5)-1 -> 0.093472884 | X3: =V3*(1+W3) -> 121821.63 | Y3: =X3*(1+$W$3) -> 133208.65 | Z3: =Y3*(1+$W$3) -> 145660.04 | AA3: =Z3*(1+$W$3) -> 159275.31 | AB3: =AA3*(1+$W$3) -> 174163.23 | AC3: =AB3*(1+$W$3) -> 190442.77 | AE3: Revenue | AF3: ='Income Statement'!AA6 -> 92391.1 | AG3: =('Income Statement'!AA6/'Income Statement'!W6)^(1/5)-1 -> 0.076655364 | AH3: =AF3*(1+AG3) -> 99473.373 | AI3: =AH3*(1+$AG$3) -> 107098.54 | AJ3: =AI3*(1+$AG$3) -> 115308.22 | AK3: =AJ3*(1+$AG$3) -> 124147.21 | AL3: =AK3*(1+$AG$3) -> 133663.76 | AM3: =AL3*(1+$AG$3) -> 143909.81 | AO3: Revenue | AP3: ='Income Statement'!AH5 -> 36218.9 | AQ3: =('Income Statement'!AH5/'Income Statement'!AD5)^(1/5)-1 -> 0.2643956 | AR3: =AP3*(1+AQ3) -> 45795.018 | AS3: =AR3*(1+$AQ$3) -> 57903.019 | AT3: =AS3*(1+$AQ$3) -> 73212.323 | AU3: =AT3*(1+$AQ$3) -> 92569.339 | AV3: =AU3*(1+$AQ$3) -> 117044.27 | AW3: =AV3*(1+$AQ$3) -> 147990.25
A4: EBIT | B4: =('Income Statement'!F16+'Income Statement'!F9) -> 62775 | C4: =('Income Statement'!F25/'Income Statement'!B25)^(1/5)-1 -> 0.081016788 | D4: =B4*(1+$C$4) -> 67860.829 | E4: =D4*(1+$C$4) -> 73358.695 | F4: =E4*(1+$C$4) -> 79301.981 | G4: =F4*(1+$C$4) -> 85726.773 | H4: =G4*(1+$C$4) -> 92672.081 | I4: =H4*(1+$C$4) -> 100180.08 | K4: EBIT | L4: ='Income Statement'!M17+'Income Statement'!M14 -> 38024 | M4: =('Income Statement'!M25/'Income Statement'!I25)^(1/5)-1 -> 0.11386101 | N4: =L4*(1+M4) -> 42353.451 | O4: =N4*(1+$M$4) -> 47175.858 | P4: =O4*(1+$M$4) -> 52547.348 | Q4: =P4*(1+$M$4) -> 58530.442 | R4: =Q4*(1+$M$4) -> 65194.777 | S4: =R4*(1+$M$4) -> 72617.92 | U4: EBIT | V4: ='Income Statement'!T15+'Income Statement'!T10 -> 35545 | W4: =('Income Statement'!T24/'Income Statement'!P24)^(1/5)-1 -> 0.19666339 | X4: =V4*(1+W4) -> 42535.4 | Y4: =X4*(1+$W$4) -> 50900.556 | Z4: =Y4*(1+$W$4) -> 60910.832 | AA4: =Z4*(1+$W$4) -> 72889.762 | AB4: =AA4*(1+$W$4) -> 87224.51 | AC4: =AB4*(1+$W$4) -> 104378.38 | AE4: EBIT | AF4: ='Income Statement'!AA23+'Income Statement'!AA11 -> 15976.2 | AG4: =('Income Statement'!AA31/'Income Statement'!W31)^(1/5)-1 -> 0.042337383 | AH4: =AF4*(1+AG4) -> 16652.59 | AI4: =AH4*(1+$AG$4) -> 17357.618 | AJ4: =AI4*(1+$AG$4) -> 18092.494 | AK4: =AJ4*(1+$AG$4) -> 18858.483 | AL4: =AK4*(1+$AG$4) -> 19656.901 | AM4: =AL4*(1+$AG$4) -> 20489.123 | AO4: EBIT | AP4: ='Income Statement'!AH13+'Income Statement'!AH9 -> 6270.4 | AQ4: =('Income Statement'!AH20/'Income Statement'!AD20)^(1/5)-1 -> 0.24628397 | AR4: =AP4*(1+AQ4) -> 7814.699 | AS4: =AR4*(1+$AQ$4) -> 9739.3342 | AT4: =AS4*(1+$AQ$4) -> 12137.976 | AU4: =AT4*(1+$AQ$4) -> 15127.365 | AV4: =AU4*(1+$AQ$4) -> 18852.993 | AW4: =AV4*(1+$AQ$4) -> 23496.183
A5: EBIT Margin | B5: =B4/B3 -> 0.25589548 | D5: =D4/D3 -> 0.25445254 | E5: =E4/E3 -> 0.25301773 | F5: =F4/F3 -> 0.25159102 | G5: =G4/G3 -> 0.25017235 | H5: =H4/H3 -> 0.24876168 | I5: =I4/I3 -> 0.24735896 | K5: EBIT Margin | L5: =L4/L3 -> 0.22824899 | N5: =N4/N3 -> 0.22654772 | O5: =O4/O3 -> 0.22485912 | P5: =P4/P3 -> 0.22318311 | Q5: =Q4/Q3 -> 0.22151959 | R5: =R4/R3 -> 0.21986847 | S5: =S4/S3 -> 0.21822966 | U5: EBIT Margin | V5: =V4/V3 -> 0.31905249 | X5: =X4/X3 -> 0.34916132 | Y5: =Y4/Y3 -> 0.3821115 | Z5: =Z4/Z3 -> 0.41817118 | AA5: =AA4/AA3 -> 0.45763379 | AB5: =AB4/AB3 -> 0.50082047 | AC5: =AC4/AC3 -> 0.54808265 | AE5: EBIT Margin | AF5: =AF4/AF3 -> 0.17291925 | AH5: =AH4/AH3 -> 0.16740752 | AI5: =AI4/AI3 -> 0.16207147 | AJ5: =AJ4/AJ3 -> 0.1569055 | AK5: =AK4/AK3 -> 0.1519042 | AL5: =AL4/AL3 -> 0.14706231 | AM5: =AM4/AM3 -> 0.14237475 | AO5: EBIT Margin | AP5: =AP4/AP3 -> 0.17312508 | AR5: =AR4/AR3 -> 0.17064518 | AS5: =AS4/AS3 -> 0.1682008 | AT5: =AT4/AT3 -> 0.16579144 | AU5: =AU4/AU3 -> 0.16341658 | AV5: =AV4/AV3 -> 0.16107575 | AW5: =AW4/AW3 -> 0.15876845
A6: Tax | B6: =B4*0.25 -> 15693.75 | C6: 0.25 | D6: =D4*$C$6 -> 16965.207 | E6: =E4*$C$6 -> 18339.674 | F6: =F4*$C$6 -> 19825.495 | G6: =G4*$C$6 -> 21431.693 | H6: =H4*$C$6 -> 23168.02 | I6: =I4*$C$6 -> 25045.019 | K6: Tax | L6: =L4*M6 -> 9506 | M6: 0.25 | N6: =N4*$M$6 -> 10588.363 | O6: =O4*$M$6 -> 11793.964 | P6: =P4*$M$6 -> 13136.837 | Q6: =Q4*$M$6 -> 14632.611 | R6: =R4*$M$6 -> 16298.694 | S6: =S4*$M$6 -> 18154.48 | U6: Tax | V6: =V4*W6 -> 8886.25 | W6: 0.25 | X6: =X4*$W$6 -> 10633.85 | Y6: =Y4*$W$6 -> 12725.139 | Z6: =Z4*$W$6 -> 15227.708 | AA6: =AA4*$W$6 -> 18222.441 | AB6: =AB4*$W$6 -> 21806.127 | AC6: =AC4*$W$6 -> 26094.594 | AE6: Tax | AF6: =AF4*AG6 -> 3994.05 | AG6: 0.25 | AH6: =AH4*$AG$6 -> 4163.1476 | AI6: =AI4*$AG$6 -> 4339.4044 | AJ6: =AJ4*$AG$6 -> 4523.1234 | AK6: =AK4*$AG$6 -> 4714.6206 | AL6: =AL4*$AG$6 -> 4914.2253 | AM6: =AM4*$AG$6 -> 5122.2808 | AO6: Tax | AP6: =AP4*AQ6 -> 1567.6 | AQ6: 0.25 | AR6: =AR4*$AQ$6 -> 1953.6748 | AS6: =AS4*$AQ$6 -> 2434.8335 | AT6: =AT4*$AQ$6 -> 3034.494 | AU6: =AU4*$AQ$6 -> 3781.8413 | AV6: =AV4*$AQ$6 -> 4713.2482 | AW6: =AW4*$AQ$6 -> 5874.0456
A7: NOPAT | B7: =B4-B6 -> 47081.25 | D7: =D4-D6 -> 50895.622 | E7: =E4-E6 -> 55019.021 | F7: =F4-F6 -> 59476.486 | G7: =G4-G6 -> 64295.08 | H7: =H4-H6 -> 69504.061 | I7: =I4-I6 -> 75135.056 | K7: NOPAT | L7: =L4-L6 -> 28518 | N7: =N4-N6 -> 31765.088 | O7: =O4-O6 -> 35381.893 | P7: =P4-P6 -> 39410.511 | Q7: =Q4-Q6 -> 43897.832 | R7: =R4-R6 -> 48896.083 | S7: =S4-S6 -> 54463.44 | U7: NOPAT | V7: =V4-V6 -> 26658.75 | X7: =X4-X6 -> 31901.55 | Y7: =Y4-Y6 -> 38175.417 | Z7: =Z4-Z6 -> 45683.124 | AA7: =AA4-AA6 -> 54667.322 | AB7: =AB4-AB6 -> 65418.382 | AC7: =AC4-AC6 -> 78283.783 | AE7: NOPAT | AF7: =AF4-AF6 -> 11982.15 | AH7: =AH4-AH6 -> 12489.443 | AI7: =AI4-AI6 -> 13018.213 | AJ7: =AJ4-AJ6 -> 13569.37 | AK7: =AK4-AK6 -> 14143.862 | AL7: =AL4-AL6 -> 14742.676 | AM7: =AM4-AM6 -> 15366.842 | AO7: NOPAT | AP7: =AP4-AP6 -> 4702.8 | AR7: =AR4-AR6 -> 5861.0243 | AS7: =AS4-AS6 -> 7304.5006 | AT7: =AT4-AT6 -> 9103.4821 | AU7: =AU4-AU6 -> 11345.524 | AV7: =AV4-AV6 -> 14139.744 | AW7: =AW4-AW6 -> 17622.137
A8: Add: Depreciation & Ammortization | B8: ='Income Statement'!F10 -> 4985 | C8: =('Income Statement'!F10/'Income Statement'!B10)^(1/5)-1 -> 0.071525969 | D8: =B8*(1+C8) -> 5341.557 | E8: =D8*(1+$C$8) -> 5723.617 | F8: =E8*(1+$C$8) -> 6133.0042 | G8: =F8*(1+$C$8) -> 6571.6733 | H8: =G8*(1+$C$8) -> 7041.7186 | I8: =H8*(1+$C$8) -> 7545.3844 | K8: Add: Depreciation & Ammortization | L8: ='Income Statement'!M13 -> 4812 | M8: =('Income Statement'!M13/'Income Statement'!I13)^(1/5)-1 -> 0.10712189 | N8: =L8*(1+M8) -> 5327.4705 | O8: =N8*(1+$M$8) -> 5898.1592 | P8: =O8*(1+$M$8) -> 6529.9812 | Q8: =P8*(1+$M$8) -> 7229.4851 | R8: =Q8*(1+$M$8) -> 8003.9212 | S8: =R8*(1+$M$8) -> 8861.3163 | U8: Add: Depreciation & Ammortization | V8: ='Cash flow statement'!T5 -> 4173 | W8: =('Cash flow statement'!T5/'Cash flow statement'!P5)^(1/5)-1 -> 0.04060152 | X8: =V8*(1+W8) -> 4342.4301 | Y8: =X8*(1+$W$8) -> 4518.7394 | Z8: =Y8*(1+$W$8) -> 4702.2071 | AA8: =Z8*(1+$W$8) -> 4893.1238 | AB8: =AA8*(1+$W$8) -> 5091.7921 | AC8: =AB8*(1+$W$8) -> 5298.5266 | AE8: Add: Depreciation & Ammortization | AF8: ='Income Statement'!AA12 -> 3407.1 | AG8: =('Income Statement'!AA12/'Income Statement'!W12)^(1/5)-1 -> 0.10315093 | AH8: =AF8*(1+AG8) -> 3758.5455 | AI8: =AH8*(1+$AG$8) -> 4146.243 | AJ8: =AI8*(1+$AG$8) -> 4573.9319 | AK8: =AJ8*(1+$AG$8) -> 5045.7372 | AL8: =AK8*(1+$AG$8) -> 5566.2097 | AM8: =AL8*(1+$AG$8) -> 6140.3695 | AO8: Add: Depreciation & Ammortization | AP8: ='Income Statement'!AH10 -> 818.9 | AQ8: =('Income Statement'!AH10/'Income Statement'!AD10)^(1/5)-1 -> 0.24570052 | AR8: =AP8*(1+AQ8) -> 1020.1042 | AS8: =AR8*(1+$AQ$8) -> 1270.7443 | AT8: =AS8*(1+$AQ$8) -> 1582.9668 | AU8: =AT8*(1+$AQ$8) -> 1971.9026 | AV8: =AU8*(1+$AQ$8) -> 2456.4 | AW8: =AV8*(1+$AQ$8) -> 3059.9388
A9: Less: CapEx | B9: =(-'Cash flow statement'!F34) -> 2202 | C9: =ABS(AVERAGE('Cash flow statement'!B34:F34))/AVERAGE('Income Statement'!B5:F5) -> 0.012488412 | D9: =D3*$C$9 -> 3330.5778 | E9: =E3*$C$9 -> 3620.8276 | F9: =F3*$C$9 -> 3936.3718 | G9: =G3*$C$9 -> 4279.4147 | H9: =H3*$C$9 -> 4652.3529 | I9: =I3*$C$9 -> 5057.7914 | K9: Less: CapEx | L9: =-'Cash flow statement'!M22 -> 2201 | M9: =ABS(AVERAGE('Cash flow statement'!I22:M22))/AVERAGE('Income Statement'!I5:M5) -> 0.019418132 | N9: =N3*$M$9 -> 3630.2502 | O9: =O3*$M$9 -> 4073.9598 | P9: =P3*$M$9 -> 4571.9021 | Q9: =Q3*$M$9 -> 5130.7058 | R9: =R3*$M$9 -> 5757.8095 | S9: =S3*$M$9 -> 6461.5614 | U9: Less: CapEx | V9: =-'Cash flow statement'!T34 -> 1048 | W9: =ABS(AVERAGE('Cash flow statement'!P34:T34))/AVERAGE('Income Statement'!P5:T5) -> 0.018113268 | X9: =X3*$W$9 -> 2206.5878 | Y9: =Y3*$W$9 -> 2412.8439 | Z9: =Z3*$W$9 -> 2638.3794 | AA9: =AA3*$W$9 -> 2884.9963 | AB9: =AB3*$W$9 -> 3154.6653 | AC9: =AC3*$W$9 -> 3449.5409 | AE9: Less: CapEx | AF9: =-'Cash flow statement'!AA24 -> 1051 | AG9: =ABS(AVERAGE('Cash flow statement'!W24:AA24))/AVERAGE('Income Statement'!W6:AA6) -> 0.022439245 | AH9: =AH3*$AG$9 -> 2232.1074 | AI9: =AI3*$AG$9 -> 2403.2104 | AJ9: =AJ3*$AG$9 -> 2587.4294 | AK9: =AK3*$AG$9 -> 2785.7698 | AL9: =AL3*$AG$9 -> 2999.3139 | AM9: =AM3*$AG$9 -> 3229.2275 | AO9: Less: CapEx | AP9: =-'Cash flow statement'!AH27 -> 843.2 | AQ9: =ABS(AVERAGE('Cash flow statement'!AD27:AH27))/AVERAGE('Income Statement'!AD5:AH5) -> 0.02782609 | AR9: =AR3*$AQ$9 -> 1274.2963 | AS9: =AS3*$AQ$9 -> 1611.2146 | AT9: =AT3*$AQ$9 -> 2037.2127 | AU9: =AU3*$AQ$9 -> 2575.8427 | AV9: =AV3*$AQ$9 -> 3256.8842 | AW9: =AW3*$AQ$9 -> 4117.9901
A10: Less: Change in Working capital | B10: =('Balance Sheet'!F32-'Balance Sheet'!F60)-('Balance Sheet'!E32-'Balance Sheet'!E60) -> 168 | C10: =('Balance Sheet'!F65/'Balance Sheet'!B65)^(1/5)-1 -> 0.011457067 | D10: =B10*(1+C10) -> 169.92479 | E10: =D10*(1+$C$10) -> 171.87163 | F10: =E10*(1+$C$10) -> 173.84077 | G10: =F10*(1+$C$10) -> 175.83248 | H10: =G10*(1+$C$10) -> 177.847 | I10: =H10*(1+$C$10) -> 179.88461 | K10: Less: Change in Working capital | L10: ='Balance Sheet'!M56-('Balance Sheet'!L27-'Balance Sheet'!L52) -> 18943 | M10: =('Balance Sheet'!M56/'Balance Sheet'!I56)^(1/5)-1 -> 0.08472037 | N10: =L10*(1+M10) -> 20547.858 | O10: =N10*(1+$M$10) -> 22288.68 | P10: =O10*(1+$M$10) -> 24176.985 | Q10: =P10*(1+$M$10) -> 26225.268 | R10: =Q10*(1+$M$10) -> 28447.083 | S10: =R10*(1+$M$10) -> 30857.13 | U10: Less: Change in Working capital | V10: ='Balance Sheet'!T57-'Balance Sheet'!S57 -> 4459 | W10: =('Balance Sheet'!T57/'Balance Sheet'!P57)^(1/5)-1 -> 0.20033846 | X10: =V10*(1+W10) -> 5352.3092 | Y10: =X10*(1+$W$10) -> 6424.5826 | Z10: =Y10*(1+$W$10) -> 7711.6736 | AA10: =Z10*(1+$W$10) -> 9256.6185 | AB10: =AA10*(1+$W$10) -> 11111.075 | AC10: =AB10*(1+$W$10) -> 13337.051 | AE10: Less: Change in Working capital | AF10: ='Balance Sheet'!AA68-'Balance Sheet'!Z68 -> 486.1 | AG10: =('Balance Sheet'!AA68/'Balance Sheet'!W68)^(1/5)-1 -> 0.055848009 | AH10: =AF10*(1+AG10) -> 513.24772 | AI10: =AH10*(1+$AG$10) -> 541.91158 | AJ10: =AI10*(1+$AG$10) -> 572.17626 | AK10: =AJ10*(1+$AG$10) -> 604.13117 | AL10: =AK10*(1+$AG$10) -> 637.87069 | AM10: =AL10*(1+$AG$10) -> 673.4945 | AO10: Less: Change in Working capital | AP10: ='Balance Sheet'!AH65-'Balance Sheet'!AG65 -> 1400 | AQ10: =('Balance Sheet'!AH65/'Balance Sheet'!AD65)^(1/5)-1 -> 0.26797667 | AR10: =AP10*(1+AQ10) -> 1775.1673 | AS10: =AR10*(1+$AQ$10) -> 2250.8708 | AT10: =AS10*(1+$AQ$10) -> 2854.0516 | AU10: =AT10*(1+$AQ$10) -> 3618.8708 | AV10: =AU10*(1+$AQ$10) -> 4588.6438 | AW10: =AV10*(1+$AQ$10) -> 5818.2932
A11: Free cash flow to firm (FCFF) | B11: =B7+B8-B9-B10 -> 49696.25 | D11: =D7+D8-D9-D10 -> 52736.676 | E11: =E7+E8-E9-E10 -> 56949.939 | F11: =F7+F8-F9-F10 -> 61499.278 | G11: =G7+G8-G9-G10 -> 66411.506 | H11: =H7+H8-H9-H10 -> 71715.579 | I11: =I7+I8-I9-I10 -> 77442.765 | K11: Free cash flow to firm (FCFF) | L11: =L7+L8-L9-L10 -> 12186 | N11: =N7+N8-N9-N10 -> 12914.451 | O11: =O7+O8-O9-O10 -> 14917.412 | P11: =P7+P8-P9-P10 -> 17191.605 | Q11: =Q7+Q8-Q9-Q10 -> 19771.343 | R11: =R7+R8-R9-R10 -> 22695.112 | S11: =S7+S8-S9-S10 -> 26006.065 | U11: Free cash flow to firm (FCFF) | V11: =V7+V8-V9-V10 -> 25324.75 | X11: =X7+X8-X9-X10 -> 28685.083 | Y11: =Y7+Y8-Y9-Y10 -> 33856.73 | Z11: =Z7+Z8-Z9-Z10 -> 40035.278 | AA11: =AA7+AA8-AA9-AA10 -> 47418.831 | AB11: =AB7+AB8-AB9-AB10 -> 56244.434 | AC11: =AC7+AC8-AC9-AC10 -> 66795.718 | AE11: Free cash flow to firm (FCFF) | AF11: =AF7+AF8-AF9-AF10 -> 13852.15 | AH11: =AH7+AH8-AH9-AH10 -> 13502.633 | AI11: =AI7+AI8-AI9-AI10 -> 14219.334 | AJ11: =AJ7+AJ8-AJ9-AJ10 -> 14983.696 | AK11: =AK7+AK8-AK9-AK10 -> 15799.698 | AL11: =AL7+AL8-AL9-AL10 -> 16671.701 | AM11: =AM7+AM8-AM9-AM10 -> 17604.49 | AO11: Free cash flow to firm (FCFF) | AP11: =AP7+AP8-AP9-AP10 -> 3278.5 | AR11: =AR7+AR8-AR9-AR10 -> 3831.6648 | AS11: =AS7+AS8-AS9-AS10 -> 4713.1595 | AT11: =AT7+AT8-AT9-AT10 -> 5795.1846 | AU11: =AU7+AU8-AU9-AU10 -> 7122.7128 | AV11: =AV7+AV8-AV9-AV10 -> 8750.6165 | AW11: =AW7+AW8-AW9-AW10 -> 10745.792
A14: Revenue CAGR | B14: TCS | C14: =(I3/D3)^(1/6)-1 -> 0.072112163
A15: Revenue CAGR | B15: Infosys | C15: =(S3/N3)^(1/6)-1 -> 0.10086354
A16: Revenue CAGR | B16: HCL | C16: =(AC3/X3)^(1/6)-1 -> 0.077308322
A17: Revenue CAGR | B17: Wipro | C17: =(AM3/AH3)^(1/6)-1 -> 0.063483094
A18: Revenue CAGR | B18: LTM | C18: =(AW3/AR3)^(1/6)-1 -> 0.21591294
A19: Revenue CAGR | B19: Average | C19: =AVERAGE(C14:C18) -> 0.10593601 | E19: GDP g | F19: 2020 | G19: =AVERAGE(-5.8%,9.7%) -> 0.0195
A20: Capex intensity | B20: TCS | C20: =AVERAGE(D9:I9)/AVERAGE(D3:I3) -> 0.012488412 | E20: GDP g | F20: 2025 | G20: 0.078
A21: Capex intensity | B21: Infosys | C21: =AVERAGE(N9:S9)/AVERAGE(N3:S3) -> 0.019418132 | E21: GDP g | F21: Change | G21: =G20-G19 -> 0.0585
A22: Capex intensity | B22: HCL | C22: =AVERAGE(X9:AC9)/AVERAGE(X3:AC3) -> 0.018113268 | E22: GDP g | F22: Sensitivity | G22: =C31/G21 -> 12.313122
A23: Capex intensity | B23: Wipro | C23: =AVERAGE(AH9:AM9)/AVERAGE(AH3:AM3) -> 0.022439245
A24: Capex intensity | B24: LTM | C24: =AVERAGE(AR9:AW9)/AVERAGE(AR3:AW3) -> 0.02782609
A25: Capex intensity | B25: Average | C25: =AVERAGE(C20:C24) -> 0.020057029
A26: Earnings growth | B26: TCS | C26: =('Income Statement'!F21-'Income Statement'!B21)/'Income Statement'!B21 -> 0.42074768
A27: Earnings growth | B27: Infosys | C27: =('Income Statement'!M22-'Income Statement'!I22)/'Income Statement'!I22 -> 0.60766873
A28: Earnings growth | B28: HCL | C28: =('Income Statement'!T20-'Income Statement'!P20)/'Income Statement'!P20 -> 0.42081939
A29: Earnings growth | B29: Wipro | C29: =('Income Statement'!AA28-'Income Statement'!W28)/'Income Statement'!W28 -> 0.13715999
A30: Earnings growth | B30: LTM | C30: =('Income Statement'!AH18-'Income Statement'!AD18)/'Income Statement'!AD18 -> 2.0151924
A31: Earnings growth | B31: Average | C31: =AVERAGE(C26:C30) -> 0.72031763
A32: EBITDA Margin | B32: =B26 -> TCS | C32: =(AVERAGE(D4:I4)+AVERAGE(D8:I8))/AVERAGE(D3:I3) -> 0.26980337
A33: EBITDA Margin | B33: =B27 -> Infosys | C33: =(AVERAGE(N4:S4)+AVERAGE(N8:S8))/AVERAGE(N3:S3) -> 0.24924352
A34: EBITDA Margin | B34: =B28 -> HCL | C34: =(AVERAGE(X4:AC4)+AVERAGE(X8:AC8))/AVERAGE(X3:AC3) -> 0.48420939
A35: EBITDA Margin | B35: =B29 -> Wipro | C35: =(AVERAGE(AH4:AM4)+AVERAGE(AH8:AM8))/AVERAGE(AH3:AM3) -> 0.19394426
A36: EBITDA Margin | B36: =B30 -> LTM | C36: =(AVERAGE(AR4:AW4)+AVERAGE(AR8:AW8))/AVERAGE(AR3:AW3) -> 0.18433674
A37: EBITDA Margin | B37: =B31 -> Average | C37: =AVERAGE(C32:C36) -> 0.27630745
A38: NPM | B38: =B32 -> TCS | C38: =AVERAGE(D7:I7)/AVERAGE(D3:I3) -> 0.18791115
A39: NPM | B39: =B33 -> Infosys | C39: =AVERAGE(N7:S7)/AVERAGE(N3:S3) -> 0.16635991
A40: NPM | B40: =B34 -> HCL | C40: =AVERAGE(X7:AC7)/AVERAGE(X3:AC3) -> 0.33975689
A41: NPM | B41: =B35 -> Wipro | C41: =AVERAGE(AH7:AM7)/AVERAGE(AH3:AM3) -> 0.11516073
A42: NPM | B42: =B36 -> LTM | C42: =AVERAGE(AR7:AW7)/AVERAGE(AR3:AW3) -> 0.12230996
A43: NPM | B43: =B37 -> Average | C43: =AVERAGE(C38:C42) -> 0.18629973

Sheet Calc
A1: Year | B1: Metrics | C1: Company | D1: Amount | F1: Company | G1: Change in EBIT (Historical) | H1: Change in CE | I1: Incremental ROCE (Historical) | J1: Change in EBIT (Forecast) | K1: Capex | L1: Depreciation | M1: Effective Capital | N1: Raw ROCE (Forecast) | O1: Adjusted ROCE (Forecast)
A2: 2020-24 | B2: Avg Capex | C2: =Valuation!B14 -> TCS | D2: =ABS(AVERAGE('Cash flow statement'!B34:F34)) -> 2494.8 | F2: =C2 -> TCS | G2: =(('Income Statement'!F13+'Income Statement'!F9)-('Income Statement'!B13+'Income Statement'!B9)) -> 20561 | H2: =(('Balance Sheet'!F33-'Balance Sheet'!F60)-('Balance Sheet'!B33-'Balance Sheet'!B60)) -> 6506 | I2: =G2/H2 -> 3.1603136 | J2: =Valuation!I4-Valuation!D4 -> 32319.246 | K2: =D8 -> 4146.2227 | L2: =AVERAGE(Valuation!D8:I8) -> 6392.8257 | M2: =IF(K2-L2<=0,K2,MAX(K2-L2,0.1*K2)) -> 4146.2227 | N2: =J2/M2 -> 7.794865 | O2: =MIN(MAX(N2,0.2),0.25) -> 0.25
A3: 2020-24 | B3: Avg Capex | C3: =Valuation!B15 -> Infosys | D3: =ABS(AVERAGE('Cash flow statement'!I22:M22)) -> 2471 | F3: =C3 -> Infosys | G3: =(('Income Statement'!M17+'Income Statement'!M14)-('Income Statement'!I17+'Income Statement'!I14)) -> 15847 | H3: =(('Balance Sheet'!M28-'Balance Sheet'!M52)-('Balance Sheet'!I28-'Balance Sheet'!I52)) -> 27108 | I3: =G3/H3 -> 0.58458758 | J3: =Valuation!S4-Valuation!N4 -> 30264.469 | K3: =D9 -> 4937.6982 | L3: =AVERAGE(Valuation!N8:S8) -> 6975.0556 | M3: =IF(K3-L3<=0,K3,MAX(K3-L3,0.1*K3)) -> 4937.6982 | N3: =J3/M3 -> 6.1292668 | O3: =MIN(MAX(N3,0.2),0.25) -> 0.25
A4: 2020-24 | B4: Avg Capex | C4: =Valuation!B16 -> HCL | D4: =ABS(AVERAGE('Cash flow statement'!P34:T34)) -> 1624.8 | F4: =C4 -> HCL | G4: =(('Income Statement'!T15+'Income Statement'!T10)-('Income Statement'!P15+'Income Statement'!P10)) -> 21060 | H4: =(('Balance Sheet'!T28-'Balance Sheet'!T54)-('Balance Sheet'!P28-'Balance Sheet'!P54)) -> 17589 | I4: =G4/H4 -> 1.1973392 | J4: =Valuation!AC4-Valuation!X4 -> 61842.977 | K4: =D10 -> 2791.1689 | L4: =AVERAGE(Valuation!X8:AC8) -> 4807.8032 | M4: =IF(K4-L4<=0,K4,MAX(K4-L4,0.1*K4)) -> 2791.1689 | N4: =J4/M4 -> 22.156659 | O4: =MIN(MAX(N4,0.2),0.25) -> 0.25
A5: 2020-24 | B5: Avg Capex | C5: =Valuation!B17 -> Wipro | D5: =ABS(AVERAGE('Cash flow statement'!W24:AA24)) -> 1771.42 | F5: =C5 -> Wipro | G5: =(('Income Statement'!AA23+'Income Statement'!AA11)-('Income Statement'!W23+'Income Statement'!W11)) -> 2991.5 | H5: =(('Balance Sheet'!AA34-'Balance Sheet'!AA65)-('Balance Sheet'!W34-'Balance Sheet'!W65)) -> 29905.2 | I5: =G5/H5 -> 0.10003277 | J5: =Valuation!AM4-Valuation!AH4 -> 3836.5326 | K5: =D11 -> 2706.1764 | L5: =AVERAGE(Valuation!AH8:AM8) -> 4871.8395 | M5: =IF(K5-L5<=0,K5,MAX(K5-L5,0.1*K5)) -> 2706.1764 | N5: =J5/M5 -> 1.4176949 | O5: =MIN(MAX(N5,0.2),0.25) -> 0.25
A6: 2020-24 | B6: Avg Capex | C6: =Valuation!B18 -> LTM | D6: =ABS(AVERAGE('Cash flow statement'!AD27:AH27)) -> 671.64 | F6: =C6 -> LTM | G6: =(('Income Statement'!AH13+'Income Statement'!AH9)-('Income Statement'!AD13+'Income Statement'!AD9)) -> 4184.9 | H6: =(('Balance Sheet'!AH32-'Balance Sheet'!AH61)-('Balance Sheet'!AD32-'Balance Sheet'!AD61)) -> 15326.1 | I6: =G6/H6 -> 0.27305707 | J6: =Valuation!AW4-Valuation!AR4 -> 15681.484 | K6: =D12 -> 2478.9068 | L6: =AVERAGE(Valuation!AR8:AW8) -> 1893.6761 | M6: =IF(K6-L6<=0,K6,MAX(K6-L6,0.1*K6)) -> 585.23068 | N6: =J6/M6 -> 26.795389 | O6: =MIN(MAX(N6,0.2),0.25) -> 0.25
A7: 2020-24 | B7: Avg Capex | C7: Average | D7: =AVERAGE(D2:D6) -> 1806.732 | F7: =B7 -> Avg Capex | I7: =AVERAGE(I2:I6) -> 1.063066 | N7: =AVERAGE(N2:N6) -> 12.858775 | O7: =AVERAGE(O2:O6) -> 0.25
A8: 2025-30 | B8: Avg Capex | C8: =C2 -> TCS | D8: =AVERAGE(Valuation!D9:I9) -> 4146.2227
A9: 2025-30 | B9: Avg Capex | C9: =C3 -> Infosys | D9: =AVERAGE(Valuation!N9:S9) -> 4937.6982
A10: 2025-30 | B10: Avg Capex | C10: =C4 -> HCL | D10: =AVERAGE(Valuation!X9:AC9) -> 2791.1689
A11: 2025-30 | B11: Avg Capex | C11: =C5 -> Wipro | D11: =AVERAGE(Valuation!AH9:AM9) -> 2706.1764
A12: 2025-30 | B12: Avg Capex | C12: =C6 -> LTM | D12: =AVERAGE(Valuation!AR9:AW9) -> 2478.9068
A13: 2025-30 | B13: Avg Capex | C13: =C7 -> Average | D13: =AVERAGE(D8:D12) -> 3412.0346
A14: =A8 -> 2025-30 | B14: Capex CAGR | C14: =C8 -> TCS | D14: =(Valuation!I9/Valuation!D9)^(1/6)-1 -> 0.072112163
A15: =A9 -> 2025-30 | B15: Capex CAGR | C15: =C9 -> Infosys | D15: =(Valuation!S9/Valuation!N9)^(1/6)-1 -> 0.10086354
A16: =A10 -> 2025-30 | B16: Capex CAGR | C16: =C10 -> HCL | D16: =(Valuation!AC9/Valuation!X9)^(1/6)-1 -> 0.077308322
A17: =A11 -> 2025-30 | B17: Capex CAGR | C17: =C11 -> Wipro | D17: =(Valuation!AM9/Valuation!AH9)^(1/6)-1 -> 0.063483094
A18: =A12 -> 2025-30 | B18: Capex CAGR | C18: =C12 -> LTM | D18: =(Valuation!AW9/Valuation!AR9)^(1/6)-1 -> 0.21591294
A19: =A13 -> 2025-30 | B19: Capex CAGR | C19: =C13 -> Average | D19: =AVERAGE(D14:D18) -> 0.10593601
A20: =A14 -> 2025-30 | B20: Earnings CAGR | C20: =C14 -> TCS | D20: =(Valuation!I7/Valuation!D7)^(1/6)-1 -> 0.067071938
A21: =A15 -> 2025-30 | B21: Earnings CAGR | C21: =C15 -> Infosys | D21: =(Valuation!S7/Valuation!N7)^(1/6)-1 -> 0.094021443
A22: =A16 -> 2025-30 | B22: Earnings CAGR | C22: =C16 -> HCL | D22: =(Valuation!AC7/Valuation!X7)^(1/6)-1 -> 0.16138622
A23: =A17 -> 2025-30 | B23: Earnings CAGR | C23: =C17 -> Wipro | D23: =(Valuation!AM7/Valuation!AH7)^(1/6)-1 -> 0.03515868
A24: =A18 -> 2025-30 | B24: Earnings CAGR | C24: =C18 -> LTM | D24: =(Valuation!AW7/Valuation!AR7)^(1/6)-1 -> 0.20138123
A25: =A19 -> 2025-30 | B25: Earnings CAGR | C25: =C19 -> Average | D25: =AVERAGE(D20:D24) -> 0.1118039

Sheet FCFF
A1: FCFF | F1: #VALUE! | I1: FCFF | N1: #VALUE! | Q1: FCFF | V1: #VALUE! | Y1: FCFF | AD1: #VALUE! | AG1: FCFF | AL1: #VALUE!
A2: Year | B2: 2025 | C2: 2026 | D2: 2027 | E2: 2028 | F2: 2029 | G2: 2030 | I2: Year | J2: 2025 | K2: 2026 | L2: 2027 | M2: 2028 | N2: 2029 | O2: 2030 | Q2: Year | R2: 2025 | S2: 2026 | T2: 2027 | U2: 2028 | V2: 2029 | W2: 2030 | Y2: Year | Z2: 2025 | AA2: 2026 | AB2: 2027 | AC2: 2028 | AD2: 2029 | AE2: 2030 | AG2: Year | AH2: 2025 | AI2: 2026 | AJ2: 2027 | AK2: 2028 | AL2: 2029 | AM2: 2030
A3: FCFF | B3: =Valuation!D11 -> 52736.676 | C3: =Valuation!E11 -> 56949.939 | D3: =Valuation!F11 -> 61499.278 | E3: =Valuation!G11 -> 66411.506 | F3: =Valuation!H11 -> 71715.579 | G3: =Valuation!I11 -> 77442.765 | I3: FCFF | J3: =Valuation!N11 -> 12914.451 | K3: =Valuation!O11 -> 14917.412 | L3: =Valuation!P11 -> 17191.605 | M3: =Valuation!Q11 -> 19771.343 | N3: =Valuation!R11 -> 22695.112 | O3: =Valuation!S11 -> 26006.065 | Q3: FCFF | R3: =Valuation!X11 -> 28685.083 | S3: =Valuation!Y11 -> 33856.73 | T3: =Valuation!Z11 -> 40035.278 | U3: =Valuation!AA11 -> 47418.831 | V3: =Valuation!AB11 -> 56244.434 | W3: =Valuation!AC11 -> 66795.718 | Y3: FCFF | Z3: =Valuation!AH11 -> 13502.633 | AA3: =Valuation!AI11 -> 14219.334 | AB3: =Valuation!AJ11 -> 14983.696 | AC3: =Valuation!AK11 -> 15799.698 | AD3: =Valuation!AL11 -> 16671.701 | AE3: =Valuation!AM11 -> 17604.49 | AG3: FCFF | AH3: =Valuation!AR11 -> 3831.6648 | AI3: =Valuation!AS11 -> 4713.1595 | AJ3: =Valuation!AT11 -> 5795.1846 | AK3: =Valuation!AU11 -> 7122.7128 | AL3: =Valuation!AV11 -> 8750.6165 | AM3: =Valuation!AW11 -> 10745.792
A4: Factor | B4: =1/(1+WACC!$B$15)^1 -> 0.88035647 | C4: =1/(1+WACC!$B$15)^2 -> 0.77502752 | D4: =1/(1+WACC!$B$15)^3 -> 0.68230049 | E4: =1/(1+WACC!$B$15)^4 -> 0.60066765 | F4: =1/(1+WACC!$B$15)^5 -> 0.52880165 | G4: =1/(1+WACC!$B$15)^6 -> 0.46553396 | I4: Factor | J4: =1/(1+WACC!$C$15)^1 -> 0.88353174 | K4: =1/(1+WACC!$C$15)^2 -> 0.78062833 | L4: =1/(1+WACC!$C$15)^3 -> 0.68970991 | M4: =1/(1+WACC!$C$15)^4 -> 0.60938059 | N4: =1/(1+WACC!$C$15)^5 -> 0.53840709 | O4: =1/(1+WACC!$C$15)^6 -> 0.47569975 | Q4: Factor | R4: =1/(1+WACC!$D$15)^1 -> 0.87559032 | S4: =1/(1+WACC!$D$15)^2 -> 0.7666584 | T4: =1/(1+WACC!$D$15)^3 -> 0.67127868 | U4: =1/(1+WACC!$D$15)^4 -> 0.58776511 | V4: =1/(1+WACC!$D$15)^5 -> 0.51464144 | W4: =1/(1+WACC!$D$15)^6 -> 0.45061506 | Y4: Factor | Z4: =1/(1+WACC!$E$15)^1 -> 0.88753256 | AA4: =1/(1+WACC!$E$15)^2 -> 0.78771405 | AB4: =1/(1+WACC!$E$15)^3 -> 0.69912187 | AC4: =1/(1+WACC!$E$15)^4 -> 0.62049342 | AD4: =1/(1+WACC!$E$15)^5 -> 0.55070812 | AE4: =1/(1+WACC!$E$15)^6 -> 0.48877139 | AG4: Factor | AH4: =1/(1+WACC!$F$15)^1 -> 0.85806447 | AI4: =1/(1+WACC!$F$15)^2 -> 0.73627463 | AJ4: =1/(1+WACC!$F$15)^3 -> 0.63177109 | AK4: =1/(1+WACC!$F$15)^4 -> 0.54210033 | AL4: =1/(1+WACC!$F$15)^5 -> 0.46515703 | AM4: =1/(1+WACC!$F$15)^6 -> 0.39913472
A5: PV of FCFF | B5: =B3*B4 -> 46427.074 | C5: =C3*C4 -> 44137.77 | D5: =D3*D4 -> 41960.987 | E5: =E3*E4 -> 39891.243 | F5: =F3*F4 -> 37923.317 | G5: =G3*G4 -> 36052.237 | I5: PV of FCFF | J5: =J3*J4 -> 11410.327 | K5: =K3*K4 -> 11644.955 | L5: =L3*L4 -> 11857.22 | M5: =M3*M4 -> 12048.272 | N5: =N3*N4 -> 12219.209 | O5: =O3*O4 -> 12371.079 | Q5: PV of FCFF | R5: =R3*R4 -> 25116.381 | S5: =S3*S4 -> 25956.546 | T5: =T3*T4 -> 26874.828 | U5: =U3*U4 -> 27871.134 | V5: =V3*V4 -> 28945.716 | W5: =W3*W4 -> 30099.156 | Y5: PV of FCFF | Z5: =Z3*Z4 -> 11984.027 | AA5: =AA3*AA4 -> 11200.769 | AB5: =AB3*AB4 -> 10475.43 | AC5: =AC3*AC4 -> 9803.6088 | AD5: =AD3*AD4 -> 9181.2411 | AE5: =AE3*AE4 -> 8604.5709 | AG5: PV of FCFF | AH5: =AH3*AH4 -> 3287.8154 | AI5: =AI3*AI4 -> 3470.1798 | AJ5: =AJ3*AJ4 -> 3661.2301 | AK5: =AK3*AK4 -> 3861.2249 | AL5: =AL3*AL4 -> 4070.4108 | AM5: =AM3*AM4 -> 4289.0188
A7: Terminal Value | B7: =G3/(WACC!B15-WACC!I3) -> 807507.15 | I7: Terminal Value | J7: =O3/(WACC!C15-WACC!J3) -> 283224.89 | Q7: Terminal Value | R7: =W3/(WACC!D15-WACC!K3) -> 654304.23 | Y7: Terminal Value | Z7: =AE3/(WACC!E15-WACC!L3) -> 203005.62 | AG7: Terminal Value | AH7: =AM3/(WACC!F15-WACC!M3) -> 85682.83
A8: PV of TV | B8: =B7/(1+WACC!I5)^6 -> 375027.63 | I8: PV of TV | J8: =J7/(1+WACC!C15)^6 -> 134730.01 | Q8: PV of TV | R8: =R7/(1+WACC!D15)^6 -> 294839.34 | Y8: PV of TV | Z8: =Z7/(1+WACC!E15)^6 -> 99223.338 | AG8: PV of TV | AH8: =AH7*AL4 -> 39855.971
A9: PV of FCFF | B9: =SUM(B5:G5) -> 246392.63 | I9: PV of FCFF | J9: =SUM(J5:O5) -> 71551.062 | Q9: PV of FCFF | R9: =SUM(R5:W5) -> 164863.76 | Y9: PV of FCFF | Z9: =SUM(Z5:AE5) -> 61249.647 | AG9: PV of FCFF | AH9: =SUM(AH5:AM5) -> 22639.88
A10: Equity Value | B10: =B8+B9 -> 621420.26 | I10: Equity Value | J10: =J8+J9 -> 206281.07 | Q10: Equity Value | R10: =R8+R9 -> 459703.1 | Y10: Equity Value | Z10: =Z8+Z9 -> 160472.99 | AG10: Equity Value | AH10: =AH8+AH9 -> 62495.851
A11: Net debt | B11: =WACC!B11-AVERAGE('Balance Sheet'!B26:F26) -> -927 | I11: Net debt | J11: =WACC!C11-AVERAGE('Balance Sheet'!I22:M22) -> -9564.4 | Q11: Net debt | R11: =WACC!D11-AVERAGE('Balance Sheet'!P21:T21) -> -1901.2 | Y11: Net debt | Z11: =WACC!E11-AVERAGE('Balance Sheet'!W25:AA25) -> 1817.1 | AG11: Net debt | AH11: =WACC!F11-AVERAGE('Balance Sheet'!AD25:AH25) -> -10.64
A12: Enterprise Value | B12: =B10-B11 -> 622347.26 | I12: Enterprise Value | J12: =J10-J11 -> 215845.47 | Q12: Enterprise Value | R12: =R10-R11 -> 461604.3 | Y12: Enterprise Value | Z12: =Z10-Z11 -> 158655.89 | AG12: Enterprise Value | AH12: =AH10-AH11 -> 62506.491
A13: Shares Outstanding | B13: ='Company Profile'!B11 -> 361.81 | I13: Shares Outstanding | J13: ='Company Profile'!C11 -> 414.46 | Q13: Shares Outstanding | R13: ='Company Profile'!D11 -> 270.89 | Y13: Shares Outstanding | Z13: ='Company Profile'!E11 -> 1047.087 | AG13: Shares Outstanding | AH13: ='Company Profile'!F11 -> 29.633
A14: Intrinsic Value per Share | B14: =B12/B13 -> 1720.0941 | I14: Intrinsic Value per Share | J14: =J12/J13 -> 520.78722 | Q14: Intrinsic Value per Share | R14: =R12/R13 -> 1704.0286 | Y14: Intrinsic Value per Share | Z14: =Z12/Z13 -> 151.52121 | AG14: Intrinsic Value per Share | AH14: =AH12/AH13 -> 2109.3541
A15: Current Market Price | B15: ='Company Profile'!B9 -> 3025.2 | I15: Current Market Price | J15: ='Company Profile'!C9 -> 1513.5 | Q15: Current Market Price | R15: ='Company Profile'!D9 -> 1540.5 | Y15: Current Market Price | Z15: ='Company Profile'!E9 -> 239.84 | AG15: Current Market Price | AH15: ='Company Profile'!F9 -> 5650
A16: Upside/Downside | B16: =(B14-B15)/B15 -> -0.43141143 | I16: Upside/Downside | J16: =(J14-J15)/J15 -> -0.65590537 | Q16: Upside/Downside | R16: =(R14-R15)/R15 -> 0.10615293 | Y16: Upside/Downside | Z16: =(Z14-Z15)/Z15 -> -0.36824047 | AG16: Upside/Downside | AH16: =(AH14-AH15)/AH15 -> -0.62666299

Sheet DDM
A1: DDM | H1: #VALUE! | R1: #VALUE! | AB1: #VALUE! | AL1: #VALUE! | AV1: #VALUE!
A2: Year | B2: 2024 | C2: CAGR | D2: 2025 | E2: 2026 | F2: 2027 | G2: 2028 | H2: 2029 | I2: 2030 | K2: Year | L2: 2024 | M2: CAGR | N2: 2025 | O2: 2026 | P2: 2027 | Q2: 2028 | R2: 2029 | S2: 2030 | U2: Year | V2: 2024 | W2: CAGR | X2: 2025 | Y2: 2026 | Z2: 2027 | AA2: 2028 | AB2: 2029 | AC2: 2030 | AE2: Year | AF2: 2024 | AG2: CAGR | AH2: 2025 | AI2: 2026 | AJ2: 2027 | AK2: 2028 | AL2: 2029 | AM2: 2030 | AO2: Year | AP2: 2024 | AQ2: CAGR | AR2: 2025 | AS2: 2026 | AT2: 2027 | AU2: 2028 | AV2: 2029 | AW2: 2030
A3: EPS | B3: ='Financial Ratios'!G10 -> 127.41218 | C3: =('Financial Ratios'!G10/'Financial Ratios'!C10)^(1/5)-1 -> 0.072762024 | D3: =B3*(1+C3) -> 136.68295 | E3: =D3*(1+$C$3) -> 146.62827 | F3: =E3*(1+$C$3) -> 157.29724 | G3: =F3*(1+$C$3) -> 168.74251 | H3: =G3*(1+$C$3) -> 181.02056 | I3: =H3*(1+$C$3) -> 194.19198 | K3: EPS | L3: ='Financial Ratios'!O10 -> 73.933833 | M3: =('Financial Ratios'!O10/'Financial Ratios'!K10)^(1/5)-1 -> 0.099611601 | N3: =L3*(1+M3) -> 81.2985 | O3: =N3*(1+$M$3) -> 89.396774 | P3: =O3*(1+$M$3) -> 98.30173 | Q3: =P3*(1+$M$3) -> 108.09372 | R3: =Q3*(1+$M$3) -> 118.86111 | S3: =R3*(1+$M$3) -> 130.70106 | U3: EPS | V3: ='Financial Ratios'!W10 -> 57.99402 | W3: =('Financial Ratios'!W10/'Financial Ratios'!S10)^(1/5)-1 -> 0.072772853 | X3: =V3*(1+W3) -> 62.21441 | Y3: =X3*(1+$W$3) -> 66.74193 | Z3: =Y3*(1+$W$3) -> 71.598931 | AA3: =Z3*(1+$W$3) -> 76.809389 | AB3: =AA3*(1+$W$3) -> 82.399028 | AC3: =AB3*(1+$W$3) -> 88.39544 | AE3: EPS | AF3: ='Financial Ratios'!AE10 -> 10.612394 | AG3: =('Financial Ratios'!AE10/'Financial Ratios'!AA10)^(1/5)-1 -> 0.026040053 | AH3: =AF3*(1+AG3) -> 10.888741 | AI3: =AH3*(1+$AG$3) -> 11.172285 | AJ3: =AI3*(1+$AG$3) -> 11.463212 | AK3: =AJ3*(1+$AG$3) -> 11.761714 | AL3: =AK3*(1+$AG$3) -> 12.06799 | AM3: =AL3*(1+$AG$3) -> 12.382241 | AO3: EPS | AP3: ='Financial Ratios'!AM10 -> 154.71265 | AQ3: =('Financial Ratios'!AM10/'Financial Ratios'!AI10)^(1/5)-1 -> 0.2469901 | AR3: =AP3*(1+AQ3) -> 192.92514 | AS3: =AR3*(1+$AQ$3) -> 240.57574 | AT3: =AS3*(1+$AQ$3) -> 299.99557 | AU3: =AT3*(1+$AQ$3) -> 374.09151 | AV3: =AU3*(1+$AQ$3) -> 466.48841 | AW3: =AV3*(1+$AQ$3) -> 581.70642
A4: DPS | B4: ='Cash flow statement'!F62 -> 69.475692 | C4: =WACC!I6 -> 0.66863859 | D4: =D3*$C$4 -> 91.391492 | E4: =E3*$C$4 -> 98.041322 | F4: =F3*$C$4 -> 105.17501 | G4: =G3*$C$4 -> 112.82775 | H4: =H3*$C$4 -> 121.03733 | I4: =I3*$C$4 -> 129.84425 | K4: DPS | L4: ='Cash flow statement'!M62 -> 35.448535 | M4: =WACC!J6 -> 0.47709605 | N4: =N3*$M$4 -> 38.787193 | O4: =O3*$M$4 -> 42.650848 | P4: =P3*$M$4 -> 46.899367 | Q4: =Q3*$M$4 -> 51.571088 | R4: =R3*$M$4 -> 56.708167 | S4: =S3*$M$4 -> 62.356958 | U4: DPS | V4: ='Cash flow statement'!T55 -> 51.925136 | W4: =WACC!K6 -> 0.64950833 | X4: =X3*$W$4 -> 40.408777 | Y4: =Y3*$W$4 -> 43.349439 | Z4: =Z3*$W$4 -> 46.504102 | AA4: =AA3*$W$4 -> 49.888338 | AB4: =AB3*$W$4 -> 53.518855 | AC4: =AC3*$W$4 -> 57.413574 | AE4: DPS | AF4: ='Cash flow statement'!AA51 -> 13.895216 | AG4: =WACC!L6 -> 0.30127994 | AH4: =AH3*$AG$4 -> 3.2805594 | AI4: =AI3*$AG$4 -> 3.3659854 | AJ4: =AJ3*$AG$4 -> 3.4536358 | AK4: =AK3*$AG$4 -> 3.5435687 | AL4: =AL3*$AG$4 -> 3.6358434 | AM4: =AM3*$AG$4 -> 3.7305209 | AO4: DPS | AP4: ='Cash flow statement'!AH51 -> 59.90956 | AQ4: =WACC!M6 -> 0.28939989 | AR4: =AR3*$AQ$4 -> 55.832515 | AS4: =AS3*$AQ$4 -> 69.622594 | AT4: =AT3*$AQ$4 -> 86.818685 | AU4: =AU3*$AQ$4 -> 108.26204 | AV4: =AV3*$AQ$4 -> 135.00169 | AW4: =AW3*$AQ$4 -> 168.34577
A5: Shares Outstanding | D5: ='Company Profile'!B11 -> 361.81 | E5: ='Company Profile'!B11 -> 361.81 | F5: ='Company Profile'!B11 -> 361.81 | G5: ='Company Profile'!B11 -> 361.81 | H5: ='Company Profile'!B11 -> 361.81 | I5: ='Company Profile'!B11 -> 361.81 | K5: Shares Outstanding | N5: ='Company Profile'!C11 -> 414.46 | O5: 414.46 | P5: 414.46 | Q5: 414.46 | R5: 414.46 | S5: 414.46 | U5: Shares Outstanding | X5: ='Company Profile'!D11 -> 270.89 | Y5: 270.89 | Z5: 270.89 | AA5: 270.89 | AB5: 270.89 | AC5: 270.89 | AE5: Shares Outstanding | AH5: ='Company Profile'!E11 -> 1047.087 | AI5: 1047.087 | AJ5: 1047.087 | AK5: 1047.087 | AL5: 1047.087 | AM5: 1047.087 | AO5: Shares Outstanding | AR5: ='Company Profile'!F11 -> 29.633 | AS5: 29.633 | AT5: 29.633 | AU5: 29.633 | AV5: 29.633 | AW5: 29.633
A6: Dividend | D6: =D4*D5 -> 33066.356 | E6: =E4*E5 -> 35472.331 | F6: =F4*F5 -> 38053.369 | G6: =G4*G5 -> 40822.21 | H6: =H4*H5 -> 43792.516 | I6: =I4*I5 -> 46978.948 | K6: Dividend | N6: =N4*N5 -> 16075.74 | O6: =O4*O5 -> 17677.07 | P6: =P4*P5 -> 19437.912 | Q6: =Q4*Q5 -> 21374.153 | R6: =R4*R5 -> 23503.267 | S6: =S4*S5 -> 25844.465 | U6: Dividend | X6: =X4*X5 -> 10946.334 | Y6: =Y4*Y5 -> 11742.93 | Z6: =Z4*Z5 -> 12597.496 | AA6: =AA4*AA5 -> 13514.252 | AB6: =AB4*AB5 -> 14497.722 | AC6: =AC4*AC5 -> 15552.763 | AE6: Dividend | AH6: =AH4*AH5 -> 3435.0311 | AI6: =AI4*AI5 -> 3524.4795 | AJ6: =AJ4*AJ5 -> 3616.2572 | AK6: =AK4*AK5 -> 3710.4247 | AL6: =AL4*AL5 -> 3807.0443 | AM6: =AM4*AM5 -> 3906.18 | AO6: Dividend | AR6: =AR4*AR5 -> 1654.4849 | AS6: =AS4*AS5 -> 2063.1263 | AT6: =AT4*AT5 -> 2572.6981 | AU6: =AU4*AU5 -> 3208.129 | AV6: =AV4*AV5 -> 4000.5052 | AW6: =AW4*AW5 -> 4988.5903
A7: Factor | D7: =1/(1+WACC!$I$5)^1 -> 0.88000704 | E7: =1/(1+WACC!$I$5)^2 -> 0.7744124 | F7: =1/(1+WACC!$I$5)^3 -> 0.68148837 | G7: =1/(1+WACC!$I$5)^4 -> 0.59971456 | H7: =1/(1+WACC!$I$5)^5 -> 0.52775304 | I7: =1/(1+WACC!$I$5)^6 -> 0.46442639 | K7: Factor | N7: =1/(1+WACC!$J$5)^1 -> 0.88243126 | O7: =1/(1+WACC!$J$5)^2 -> 0.77868494 | P7: =1/(1+WACC!$J$5)^3 -> 0.68713593 | Q7: =1/(1+WACC!$J$5)^4 -> 0.60635023 | R7: =1/(1+WACC!$J$5)^5 -> 0.5350624 | S7: =1/(1+WACC!$J$5)^6 -> 0.47215579 | U7: Factor | X7: =1/(1+WACC!$K$5)^1 -> 0.87453709 | Y7: =1/(1+WACC!$K$5)^2 -> 0.76481512 | Z7: =1/(1+WACC!$K$5)^3 -> 0.66885919 | AA7: =1/(1+WACC!$K$5)^4 -> 0.58494217 | AB7: =1/(1+WACC!$K$5)^5 -> 0.51155362 | AC7: =1/(1+WACC!$K$5)^6 -> 0.44737262 | AE7: Factor | AH7: =1/(1+WACC!$L$5)^1 -> 0.88421564 | AI7: =1/(1+WACC!$L$5)^2 -> 0.7818373 | AJ7: =1/(1+WACC!$L$5)^3 -> 0.69131277 | AK7: =1/(1+WACC!$L$5)^4 -> 0.61126956 | AL7: =1/(1+WACC!$L$5)^5 -> 0.54049411 | AM7: =1/(1+WACC!$L$5)^6 -> 0.47791334 | AO7: Factor | AR7: =1/(1+WACC!$M$5)^1 -> 0.8575336 | AS7: =1/(1+WACC!$M$5)^2 -> 0.73536388 | AT7: =1/(1+WACC!$M$5)^3 -> 0.63059924 | AU7: =1/(1+WACC!$M$5)^4 -> 0.54076004 | AV7: =1/(1+WACC!$M$5)^5 -> 0.4637199 | AW7: =1/(1+WACC!$M$5)^6 -> 0.3976554
A8: PV of Dividend | D8: =D6*D7 -> 29098.626 | E8: =E6*E7 -> 27470.213 | F8: =F6*F7 -> 25932.928 | G8: =G6*G7 -> 24481.674 | H8: =H6*H7 -> 23111.633 | I8: =I6*I7 -> 21818.263 | K8: PV of Dividend | N8: =N6*N7 -> 14185.736 | O8: =O6*O7 -> 13764.868 | P8: =P6*P7 -> 13356.488 | Q8: =Q6*Q7 -> 12960.223 | R8: =R6*R7 -> 12575.714 | S8: =S6*S7 -> 12202.614 | U8: PV of Dividend | X8: =X6*X7 -> 9572.9748 | Y8: =Y6*Y7 -> 8981.1701 | Z8: =Z6*Z7 -> 8425.951 | AA8: =AA6*AA7 -> 7905.0558 | AB8: =AB6*AB7 -> 7416.3625 | AC8: =AC6*AC7 -> 6957.8804 | AE8: PV of Dividend | AH8: =AH6*AH7 -> 3037.3082 | AI8: =AI6*AI7 -> 2755.5695 | AJ8: =AJ6*AJ7 -> 2499.9647 | AK8: =AK6*AK7 -> 2268.0697 | AL8: =AL6*AL7 -> 2057.685 | AM8: =AM6*AM7 -> 1866.8155 | AO8: PV of Dividend | AR8: =AR6*AR7 -> 1418.7764 | AS8: =AS6*AS7 -> 1517.1486 | AT8: =AT6*AT7 -> 1622.3415 | AU8: =AU6*AU7 -> 1734.828 | AV8: =AV6*AV7 -> 1855.1139 | AW8: =AW6*AW7 -> 1983.7399
A10: Terminal Value | B10: =I6/(WACC!I5-WACC!I3) -> 487563.41 | K10: Terminal Value | L10: =S6/(WACC!J5-WACC!J3) -> 277203.75 | U10: Terminal Value | V10: =AC6/(WACC!K5-WACC!K3) -> 150323.32 | AE10: Terminal Value | AF10: =AM6/(WACC!M5-WACC!M3) -> 30968.233 | AO10: Terminal Value | AP10: =AW6/(WACC!M5-WACC!M3) -> 39549.593
A11: PV of TV | B11: =B10/(1+WACC!I5)^5 -> 257313.07 | K11: PV of TV | L11: =L10/(1+WACC!J5)^5 -> 148321.3 | U11: PV of TV | V11: =V10/(1+WACC!K5)^5 -> 76898.438 | AE11: PV of TV | AF11: =AF10/(1+WACC!M5)^5 -> 14360.586 | AO11: PV of TV | AP11: =AP10/(1+WACC!M5)^5 -> 18339.934
A12: PV of Dividend | B12: =SUM(D8:I8) -> 151913.34 | K12: PV of Dividend | L12: =SUM(N8:S8) -> 79045.643 | U12: PV of Dividend | V12: =SUM(X8:AC8) -> 49259.395 | AE12: PV of Dividend | AF12: =SUM(AH8:AM8) -> 14485.413 | AO12: PV of Dividend | AP12: =SUM(AR8:AW8) -> 10131.948
A13: Equity Value | B13: =B11+B12 -> 409226.41 | K13: Equity Value | L13: =L11+L12 -> 227366.94 | U13: Equity Value | V13: =V11+V12 -> 126157.83 | AE13: Equity Value | AF13: =AF11+AF12 -> 28845.999 | AO13: Equity Value | AP13: =AP11+AP12 -> 28471.882
A14: Net Debt | B14: =FCFF!B11 -> -927 | K14: Net Debt | L14: =FCFF!J11 -> -9564.4 | U14: Net Debt | V14: =FCFF!R11 -> -1901.2 | AE14: Net Debt | AF14: =FCFF!Z11 -> 1817.1 | AO14: Net Debt | AP14: =FCFF!AH11 -> -10.64
A15: Enterprise Value | B15: =B13+B14 -> 408299.41 | K15: Enterprise Value | L15: =L13+L14 -> 217802.54 | U15: Enterprise Value | V15: =V13+V14 -> 124256.63 | AE15: Enterprise Value | AF15: =AF13+AF14 -> 30663.099 | AO15: Enterprise Value | AP15: =AP13+AP14 -> 28461.242
A16: Shares Outstanding | B16: =D5 -> 361.81 | K16: Shares Outstanding | L16: =N5 -> 414.46 | U16: Shares Outstanding | V16: =X5 -> 270.89 | AE16: Shares Outstanding | AF16: =AH5 -> 1047.087 | AO16: Shares Outstanding | AP16: =AR5 -> 29.633
A17: Intrinsic Value per share | B17: =B15/B16 -> 1128.4912 | K17: Intrinsic Value per share | L17: =L15/L16 -> 525.5092 | U17: Intrinsic Value per share | V17: =V15/V16 -> 458.69775 | AE17: Intrinsic Value per share | AF17: =AF15/AF16 -> 29.284194 | AO17: Intrinsic Value per share | AP17: =AP15/AP16 -> 960.45766
A18: Current Market price | B18: ='Company Profile'!B9 -> 3025.2 | K18: Current Market price | L18: ='Company Profile'!C9 -> 1513.5 | U18: Current Market price | V18: ='Company Profile'!D9 -> 1540.5 | AE18: Current Market price | AF18: =FCFF!Z15 -> 239.84 | AO18: Current Market price | AP18: ='Company Profile'!F9 -> 5650
A19: Upside/Downside | B19: =(B17-B18)/B18 -> -0.62696971 | K19: Upside/Downside | L19: =(L17-L18)/L18 -> -0.65278546 | U19: Upside/Downside | V19: =(V17-V18)/V18 -> -0.702241 | AE19: Upside/Downside | AF19: =(AF17-AF18)/AF18 -> -0.87790113 | AO19: Upside/Downside | AP19: =(AP17-AP18)/AP18 -> -0.83000749

Sheet RIM
A1: RIM | H1: #VALUE! | K1: RIM | R1: #VALUE! | U1: RIM | AB1: #VALUE! | AE1: RIM | AL1: #VALUE! | AO1: RIM | AV1: #VALUE!
A2: Year | B2: 2024 | C2: CAGR | D2: 2025 | E2: 2026 | F2: 2027 | G2: 2028 | H2: 2029 | I2: 2030 | K2: Year | L2: 2024 | M2: CAGR | N2: 2025 | O2: 2026 | P2: 2027 | Q2: 2028 | R2: 2029 | S2: 2030 | U2: Year | V2: 2024 | W2: CAGR | X2: 2025 | Y2: 2026 | Z2: 2027 | AA2: 2028 | AB2: 2029 | AC2: 2030 | AE2: Year | AF2: 2024 | AG2: CAGR | AH2: 2025 | AI2: 2026 | AJ2: 2027 | AK2: 2028 | AL2: 2029 | AM2: 2030 | AO2: Year | AP2: 2024 | AQ2: CAGR | AR2: 2025 | AS2: 2026 | AT2: 2027 | AU2: 2028 | AV2: 2029 | AW2: 2030
A3: EPS | B3: =DDM!B3 -> 127.41218 | D3: =DDM!D3 -> 136.68295 | E3: =DDM!E3 -> 146.62827 | F3: =DDM!F3 -> 157.29724 | G3: =DDM!G3 -> 168.74251 | H3: =DDM!H3 -> 181.02056 | I3: =DDM!I3 -> 194.19198 | K3: EPS | L3: =DDM!L3 -> 73.933833 | N3: =DDM!N3 -> 81.2985 | O3: =DDM!O3 -> 89.396774 | P3: =DDM!P3 -> 98.30173 | Q3: =DDM!Q3 -> 108.09372 | R3: =DDM!R3 -> 118.86111 | S3: =DDM!S3 -> 130.70106 | U3: EPS | V3: =DDM!V3 -> 57.99402 | X3: =DDM!X3 -> 62.21441 | Y3: =DDM!Y3 -> 66.74193 | Z3: =DDM!Z3 -> 71.598931 | AA3: =DDM!AA3 -> 76.809389 | AB3: =DDM!AB3 -> 82.399028 | AC3: =DDM!AC3 -> 88.39544 | AE3: EPS | AF3: =DDM!AF3 -> 10.612394 | AH3: =DDM!AH3 -> 10.888741 | AI3: =DDM!AI3 -> 11.172285 | AJ3: =DDM!AJ3 -> 11.463212 | AK3: =DDM!AK3 -> 11.761714 | AL3: =DDM!AL3 -> 12.06799 | AM3: =DDM!AM3 -> 12.382241 | AO3: EPS | AP3: =DDM!AP3 -> 154.71265 | AR3: =DDM!AR3 -> 192.92514 | AS3: =DDM!AS3 -> 240.57574 | AT3: =DDM!AT3 -> 299.99557 | AU3: =DDM!AU3 -> 374.09151 | AV3: =DDM!AV3 -> 466.48841 | AW3: =DDM!AW3 -> 581.70642
A4: Share outstanding | D4: =DDM!D5 -> 361.81 | E4: =DDM!E5 -> 361.81 | F4: =DDM!F5 -> 361.81 | G4: =DDM!G5 -> 361.81 | H4: =DDM!H5 -> 361.81 | I4: =DDM!I5 -> 361.81 | K4: Share outstanding | N4: =DDM!N5 -> 414.46 | O4: =DDM!O5 -> 414.46 | P4: =DDM!P5 -> 414.46 | Q4: =DDM!Q5 -> 414.46 | R4: =DDM!R5 -> 414.46 | S4: =DDM!S5 -> 414.46 | U4: Share outstanding | X4: =DDM!X5 -> 270.89 | Y4: =DDM!Y5 -> 270.89 | Z4: =DDM!Z5 -> 270.89 | AA4: =DDM!AA5 -> 270.89 | AB4: =DDM!AB5 -> 270.89 | AC4: =DDM!AC5 -> 270.89 | AE4: Share outstanding | AH4: =DDM!AH5 -> 1047.087 | AI4: =DDM!AI5 -> 1047.087 | AJ4: =DDM!AJ5 -> 1047.087 | AK4: =DDM!AK5 -> 1047.087 | AL4: =DDM!AL5 -> 1047.087 | AM4: =DDM!AM5 -> 1047.087 | AO4: Share outstanding | AR4: =DDM!AR5 -> 29.633 | AS4: =DDM!AS5 -> 29.633 | AT4: =DDM!AT5 -> 29.633 | AU4: =DDM!AU5 -> 29.633 | AV4: =DDM!AV5 -> 29.633 | AW4: =DDM!AW5 -> 29.633
A5: Net Income | B5: ='Income Statement'!F21 -> 46099 | D5: =D3*D4 -> 49453.257 | E5: =E3*E4 -> 53051.576 | F5: =F3*F4 -> 56911.716 | G5: =G3*G4 -> 61052.727 | H5: =H3*H4 -> 65495.047 | I5: =I3*I4 -> 70260.6 | K5: Net Income | L5: ='Income Statement'!M22 -> 26750 | N5: =N4*N3 -> 33694.976 | O5: =O4*O3 -> 37051.387 | P5: =P4*P3 -> 40742.135 | Q5: =Q4*Q3 -> 44800.524 | R5: =R4*R3 -> 49263.176 | S5: =S4*S3 -> 54170.36 | U5: Net Income | V5: ='Income Statement'!T20 -> 15710 | X5: =X3*X4 -> 16853.262 | Y5: =Y3*Y4 -> 18079.721 | Z5: =Z3*Z4 -> 19395.434 | AA5: =AA3*AA4 -> 20806.895 | AB5: =AB3*AB4 -> 22321.073 | AC5: =AC3*AC4 -> 23945.441 | AE5: Net Income | AF5: ='Income Statement'!AA28 -> 11112.1 | AH5: =AH3*AH4 -> 11401.46 | AI5: =AI3*AI4 -> 11698.354 | AJ5: =AJ3*AJ4 -> 12002.98 | AK5: =AK3*AK4 -> 12315.538 | AL5: =AL3*AL4 -> 12636.236 | AM5: =AM3*AM4 -> 12965.284 | AO5: Net Income | AP5: ='Income Statement'!AH18 -> 4584.6 | AR5: =AR3*AR4 -> 5716.9508 | AS5: =AS3*AS4 -> 7128.9811 | AT5: =AT3*AT4 -> 8889.7688 | AU5: =AU3*AU4 -> 11085.454 | AV5: =AV3*AV4 -> 13823.451 | AW5: =AW3*AW4 -> 17237.706
A6: Book Value | B6: ='Balance Sheet'!F40 -> 91319 | C6: =('Balance Sheet'!F40/'Balance Sheet'!B40)^(1/5)-1 -> 0.015045039 | D6: =B6*(1+C6) -> 92692.898 | E6: =D6*(1+$C$6) -> 94087.466 | F6: =E6*(1+$C$6) -> 95503.016 | G6: =F6*(1+$C$6) -> 96939.862 | H6: =G6*(1+$C$6) -> 98398.326 | I6: =H6*(1+$C$6) -> 99878.733 | K6: Book Value | L6: ='Balance Sheet'!M35 -> 88461 | M6: =('Balance Sheet'!M35/'Balance Sheet'!I35)^(1/5)-1 -> 0.06083326 | N6: =L6*(1+M6) -> 93842.371 | O6: =N6*(1+$M$6) -> 99551.108 | P6: =O6*(1+$M$6) -> 105607.13 | Q6: =P6*(1+$M$6) -> 112031.55 | R6: =Q6*(1+$M$6) -> 118846.8 | S6: =R6*(1+$M$6) -> 126076.64 | U6: Book Value | V6: ='Balance Sheet'!T34 -> 68271 | W6: =('Balance Sheet'!T34/'Balance Sheet'!P34)^(1/5)-1 -> 0.058325229 | X6: =V6*(1+W6) -> 72252.922 | Y6: =X6*(1+$W$6) -> 76467.09 | Z6: =Y6*(1+$W$6) -> 80927.05 | AA6: =Z6*(1+$W$6) -> 85647.139 | AB6: =AA6*(1+$W$6) -> 90642.528 | AC6: =AB6*(1+$W$6) -> 95929.274 | AE6: Book Value | AF6: ='Balance Sheet'!AA41 -> 74667 | AG6: =('Balance Sheet'!AA34/'Balance Sheet'!W34)^(1/5)-1 -> 0.071484028 | AH6: =AF6*(1+AG6) -> 80004.498 | AI6: =AH6*(1+$AG$6) -> 85723.542 | AJ6: =AI6*(1+$AG$6) -> 91851.406 | AK6: =AJ6*(1+$AG$6) -> 98417.314 | AL6: =AK6*(1+$AG$6) -> 105452.58 | AM6: =AL6*(1+$AG$6) -> 112990.76 | AO6: Book Value | AP6: ='Balance Sheet'!AH40 -> 20026.4 | AQ6: =('Balance Sheet'!AH40/'Balance Sheet'!AD40)^(1/5)-1 -> 0.29945077 | AR6: =AP6*(1+AQ6) -> 26023.321 | AS6: =AR6*(1+$AQ$6) -> 33816.024 | AT6: =AS6*(1+$AQ$6) -> 43942.259 | AU6: =AT6*(1+$AQ$6) -> 57100.802 | AV6: =AU6*(1+$AQ$6) -> 74199.681 | AW6: =AV6*(1+$AQ$6) -> 96418.833
A7: Cost of equity (Ke) | D7: =WACC!I5 -> 0.13635454 | E7: 0.12378022 | F7: 0.12378022 | G7: 0.12378022 | H7: 0.12378022 | I7: 0.12378022 | K7: Cost of equity (Ke) | N7: =WACC!J5 -> 0.13323274 | O7: 0.1243102 | P7: 0.1243102 | Q7: 0.1243102 | R7: 0.1243102 | S7: 0.1243102 | U7: Cost of equity (Ke) | X7: =WACC!K5 -> 0.14346208 | Y7: 0.12219754 | Z7: 0.12219754 | AA7: 0.12219754 | AB7: 0.12219754 | AC7: 0.12219754 | AE7: Cost of equity (Ke) | AH7: =WACC!L5 -> 0.13094584 | AI7: 0.1215514 | AJ7: 0.1215514 | AK7: 0.1215514 | AL7: 0.1215514 | AM7: 0.1215514 | AO7: Cost of equity (Ke) | AR7: =WACC!M5 -> 0.16613506 | AS7: 0.1611184 | AT7: 0.1611184 | AU7: 0.1611184 | AV7: 0.1611184 | AW7: 0.1611184
A8: Required Return | D8: =D6*D7 -> 12639.097 | E8: =E6*E7 -> 11646.167 | F8: =F6*F7 -> 11821.384 | G8: =G6*G7 -> 11999.237 | H8: =H6*H7 -> 12179.766 | I8: =I6*I7 -> 12363.012 | K8: Required Return | N8: =N6*N7 -> 12502.876 | O8: =O6*O7 -> 12375.218 | P8: =P6*P7 -> 13128.043 | Q8: =Q6*Q7 -> 13926.665 | R8: =R6*R7 -> 14773.869 | S8: =S6*S7 -> 15672.612 | U8: Required Return | X8: =X6*X7 -> 10365.554 | Y8: =Y6*Y7 -> 9344.0903 | Z8: =Z6*Z7 -> 9889.0865 | AA8: =AA6*AA7 -> 10465.87 | AB8: =AB6*AB7 -> 11076.294 | AC8: =AC6*AC7 -> 11722.321 | AE8: Required Return | AH8: =AH6*AH7 -> 10476.256 | AI8: =AI6*AI7 -> 10419.817 | AJ8: =AJ6*AJ7 -> 11164.667 | AK8: =AK6*AK7 -> 11962.762 | AL8: =AL6*AL7 -> 12817.909 | AM8: =AM6*AM7 -> 13734.185 | AO8: Required Return | AR8: =AR6*AR7 -> 4323.386 | AS8: =AS6*AS7 -> 5448.3837 | AT8: =AT6*AT7 -> 7079.9064 | AU8: =AU6*AU7 -> 9199.9899 | AV8: =AV6*AV7 -> 11954.934 | AW8: =AW6*AW7 -> 15534.848
A9: Residual Income | D9: =D5-D8 -> 36814.159 | E9: =E5-E8 -> 41405.408 | F9: =F5-F8 -> 45090.331 | G9: =G5-G8 -> 49053.49 | H9: =H5-H8 -> 53315.281 | I9: =I5-I8 -> 57897.588 | K9: Residual Income | N9: =N5-N8 -> 21192.1 | O9: =O5-O8 -> 24676.169 | P9: =P5-P8 -> 27614.092 | Q9: =Q5-Q8 -> 30873.859 | R9: =R5-R8 -> 34489.307 | S9: =S5-S8 -> 38497.748 | U9: Residual Income | X9: =X5-X8 -> 6487.7071 | Y9: =Y5-Y8 -> 8735.6312 | Z9: =Z5-Z8 -> 9506.3479 | AA9: =AA5-AA8 -> 10341.026 | AB9: =AB5-AB8 -> 11244.779 | AC9: =AC5-AC8 -> 12223.119 | AE9: Residual Income | AH9: =AH5-AH8 -> 925.20348 | AI9: =AI5-AI8 -> 1278.5378 | AJ9: =AJ5-AJ8 -> 838.31308 | AK9: =AK5-AK8 -> 352.77594 | AL9: =AL5-AL8 -> -181.67324 | AM9: =AM5-AM8 -> -768.90075 | AO9: Residual Income | AR9: =AR5-AR8 -> 1393.5648 | AS9: =AS5-AS8 -> 1680.5973 | AT9: =AT5-AT8 -> 1809.8623 | AU9: =AU5-AU8 -> 1885.4638 | AV9: =AV5-AV8 -> 1868.517 | AW9: =AW5-AW8 -> 1702.8584
A10: PV Factor | D10: =DDM!D7 -> 0.88000704 | E10: =DDM!E7 -> 0.7744124 | F10: =DDM!F7 -> 0.68148837 | G10: =DDM!G7 -> 0.59971456 | H10: =DDM!H7 -> 0.52775304 | I10: =DDM!I7 -> 0.46442639 | K10: PV Factor | N10: =DDM!N7 -> 0.88243126 | O10: =DDM!O7 -> 0.77868494 | P10: =DDM!P7 -> 0.68713593 | Q10: =DDM!Q7 -> 0.60635023 | R10: =DDM!R7 -> 0.5350624 | S10: =DDM!S7 -> 0.47215579 | U10: PV Factor | X10: =DDM!X7 -> 0.87453709 | Y10: =DDM!Y7 -> 0.76481512 | Z10: =DDM!Z7 -> 0.66885919 | AA10: =DDM!AA7 -> 0.58494217 | AB10: =DDM!AB7 -> 0.51155362 | AC10: =DDM!AC7 -> 0.44737262 | AE10: PV Factor | AH10: =DDM!AH7 -> 0.88421564 | AI10: =DDM!AI7 -> 0.7818373 | AJ10: =DDM!AJ7 -> 0.69131277 | AK10: =DDM!AK7 -> 0.61126956 | AL10: =DDM!AL7 -> 0.54049411 | AM10: =DDM!AM7 -> 0.47791334 | AO10: PV Factor | AR10: =DDM!AR7 -> 0.8575336 | AS10: =DDM!AS7 -> 0.73536388 | AT10: =DDM!AT7 -> 0.63059924 | AU10: =DDM!AU7 -> 0.54076004 | AV10: =DDM!AV7 -> 0.4637199 | AW10: =DDM!AW7 -> 0.3976554
A11: PV of RI | D11: =D9*D10 -> 32396.719 | E11: =E9*E10 -> 32064.862 | F11: =F9*F10 -> 30728.536 | G11: =G9*G10 -> 29418.092 | H11: =H9*H10 -> 28137.302 | I11: =I9*I10 -> 26889.168 | K11: PV of RI | N11: =N9*N10 -> 18700.572 | O11: =O9*O10 -> 19214.961 | P11: =P9*P10 -> 18974.635 | Q11: =Q9*Q10 -> 18720.372 | R11: =R9*R10 -> 18453.931 | S11: =S9*S10 -> 18176.935 | U11: PV of RI | X11: =X9*X10 -> 5673.7405 | Y11: =Y9*Y10 -> 6681.1428 | Z11: =Z9*Z10 -> 6358.4082 | AA11: =AA9*AA10 -> 6048.9021 | AB11: =AB9*AB10 -> 5752.3073 | AC11: =AC9*AC10 -> 5468.2889 | AE11: PV of RI | AH11: =AH9*AH10 -> 818.07939 | AI11: =AI9*AI10 -> 999.60852 | AJ11: =AJ9*AJ10 -> 579.53653 | AK11: =AK9*AK10 -> 215.64119 | AL11: =AL9*AL10 -> -98.193313 | AM11: =AM9*AM10 -> -367.46793 | AO11: PV of RI | AR11: =AR9*AR10 -> 1195.0287 | AS11: =AS9*AS10 -> 1235.8506 | AT11: =AT9*AT10 -> 1141.2978 | AU11: =AU9*AU10 -> 1019.5835 | AV11: =AV9*AV10 -> 866.46853 | AW11: =AW9*AW10 -> 677.15083
A13: Terminal Value | B13: =I9/(WACC!I5-WACC!I3) -> 600880.75 | K13: Terminal Value | L13: =S9/(WACC!J5-WACC!J3) -> 412920.91 | U13: Terminal Value | V13: =AC9/(WACC!K5-WACC!K3) -> 118141.06 | AE13: Terminal Value | AF13: =AK9/(WACC!L5-WACC!L3) -> 3878.9673 | AO13: Terminal Value | AP13: =AW9/(WACC!M5-WACC!M3) -> 13500.278
A14: PV of TV | B14: =B13/(1+WACC!I5)^5 -> 317116.64 | K14: PV of TV | L14: =L13/(1+WACC!J5)^5 -> 220938.45 | U14: PV of TV | V14: =V13/(1+WACC!K5)^5 -> 60435.485 | AE14: PV of TV | AF14: =AF13*AL10 -> 2096.559 | AO14: PV of TV | AP14: =AP13*AV10 -> 6260.3476
A15: PV of Dividend | B15: =SUM(D11:I11) -> 179634.68 | K15: PV of Dividend | L15: =SUM(N11:S11) -> 112241.41 | U15: PV of Dividend | V15: =SUM(X11:AC11) -> 35982.79 | AE15: PV of Dividend | AF15: =SUM(AH11:AM11) -> 2147.2044 | AO15: PV of Dividend | AP15: =SUM(AR11:AW11) -> 6135.3799
A16: Equity Value | B16: =B14+B15 -> 496751.32 | K16: Equity Value | L16: =L14+L15 -> 333179.86 | U16: Equity Value | V16: =V14+V15 -> 96418.275 | AE16: Equity Value | AF16: =AF14+AF15 -> 4243.7634 | AO16: Equity Value | AP16: =AP14+AP15 -> 12395.727
A17: Net Debt | B17: =DDM!B14 -> -927 | K17: Net Debt | L17: =DDM!L14 -> -9564.4 | U17: Net Debt | V17: =DDM!V14 -> -1901.2 | AE17: Net Debt | AF17: =DDM!AF14 -> 1817.1 | AO17: Net Debt | AP17: =DDM!AP14 -> -10.64
A18: Enterprise Value | B18: =B16+B17 -> 495824.32 | K18: Enterprise Value | L18: =L16+L17 -> 323615.46 | U18: Enterprise Value | V18: =V16+V17 -> 94517.075 | AE18: Enterprise Value | AF18: =AF16+AF17 -> 6060.8634 | AO18: Enterprise Value | AP18: =AP16+AP17 -> 12385.087
A19: Shares Outstanding | B19: =D4 -> 361.81 | K19: Shares Outstanding | L19: =N4 -> 414.46 | U19: Shares Outstanding | V19: =X4 -> 270.89 | AE19: Shares Outstanding | AF19: =AH4 -> 1047.087 | AO19: Shares Outstanding | AP19: =AR4 -> 29.633
A20: Intrinsic Value per share | B20: =B18/B19 -> 1370.3997 | K20: Intrinsic Value per share | L20: =L18/L19 -> 780.81229 | U20: Intrinsic Value per share | V20: =V18/V19 -> 348.91312 | AE20: Intrinsic Value per share | AF20: =AF18/AF19 -> 5.7883092 | AO20: Intrinsic Value per share | AP20: =AP18/AP19 -> 417.94916
A21: Current Market price | B21: =DDM!B18 -> 3025.2 | K21: Current Market price | L21: =DDM!L18 -> 1513.5 | U21: Current Market price | V21: =DDM!V18 -> 1540.5 | AE21: Current Market price | AF21: =DDM!AF18 -> 239.84 | AO21: Current Market price | AP21: =DDM!AP18 -> 5650
A22: Upside/Downside | B22: =(B20-B21)/B21 -> -0.54700525 | K22: Upside/Downside | L22: =(L20-L21)/L21 -> -0.48410156 | U22: Upside/Downside | V22: =(V20-V21)/V21 -> -0.77350658 | AE22: Upside/Downside | AF22: =(AF20-AF21)/AF21 -> -0.97586596 | AO22: Upside/Downside | AP22: =(AP20-AP21)/AP21 -> -0.9260267

Sheet Summary
A1: SUMMARY
A2: VALUATION MODELS | B2: #VALUE! | E2: #VALUE! | H2: #VALUE! | K2: #VALUE! | N2: #VALUE!
B3: DCF | C3: DDM | D3: RIM | E3: DCF | F3: DDM | G3: RIM | H3: DCF | I3: DDM | J3: RIM | K3: DCF | L3: DDM | M3: RIM | N3: DCF | O3: DDM | P3: RIM
A4: Company name | B4: {=_FV('Company Profile'!B4,"Official name",TRUE)} -> TATA CONSULTANCY SERVICES LIMITED | E4: {=_FV('Company Profile'!C4,"Official name",TRUE)} -> INFOSYS LIMITED | H4: {=_FV('Company Profile'!D4,"Official name",TRUE)} -> HCL TECHNOLOGIES LIMITED | K4: {=_FV('Company Profile'!E4,"Official name",TRUE)} -> WIPRO LIMITED | N4: {=_FV('Company Profile'!F4,"Official name",TRUE)} -> LTIMINDTREE LIMITED
A5: Intrinsic Value per share | B5: =FCFF!B14 -> 1720.0941 | C5: =DDM!B17 -> 1128.4912 | D5: =RIM!B20 -> 1370.3997 | E5: =FCFF!J14 -> 520.78722 | F5: =DDM!L17 -> 525.5092 | G5: =RIM!V20 -> 348.91312 | H5: =FCFF!R14 -> 1704.0286 | I5: =DDM!V17 -> 458.69775 | J5: =RIM!V20 -> 348.91312 | K5: =FCFF!Z14 -> 151.52121 | L5: =DDM!AF17 -> 29.284194 | M5: =RIM!AF20 -> 5.7883092 | N5: =FCFF!AH14 -> 2109.3541 | O5: =DDM!AP17 -> 960.45766 | P5: =RIM!AP20 -> 417.94916
A6: Current Market Price | C6: =FCFF!B15 -> 3025.2 | F6: =RIM!L21 -> 1513.5 | I6: =DDM!V18 -> 1540.5 | L6: =DDM!AF18 -> 239.84 | O6: =RIM!AP21 -> 5650
A7: Upside/Downside | B7: =(B5-$C$6)/$C$6 -> -0.43141143 | C7: =(C5-$C$6)/$C$6 -> -0.62696971 | D7: =(D5-$C$6)/$C$6 -> -0.54700525 | E7: =(E5-$F$6)/$F$6 -> -0.65590537 | F7: =(F5-$F$6)/$F$6 -> -0.65278546 | G7: =(G5-$F$6)/$F$6 -> -0.76946606 | H7: =(H5-$I$6)/$I$6 -> 0.10615293 | I7: =(I5-$I$6)/$I$6 -> -0.702241 | J7: =(J5-$I$6)/$I$6 -> -0.77350658 | K7: =(K5-$L$6)/$L$6 -> -0.36824047 | L7: =(L5-$L$6)/$L$6 -> -0.87790113 | M7: =(M5-$L$6)/$L$6 -> -0.97586596 | N7: =(N5-$O$6)/$O$6 -> -0.62666299 | O7: =(O5-$O$6)/$O$6 -> -0.83000749 | P7: =(P5-$O$6)/$O$6 -> -0.9260267
