Workbook

Sheet Company Basic info
A1: Company Basic Info
A2: Logo | C2: #VALUE! | D2: #VALUE! | E2: #VALUE! | F2: #VALUE! | G2: #VALUE!
A3: Attribute | C3: Bharat Electronics Limited | D3: Mazagon Dock Shipbuilders | E3: Bharat Dynamics Limited | F3: Hindustan Aeronautics Limited | G3: GRSE
A4: Company Name | C4: #VALUE! | D4: #VALUE! | E4: #VALUE! | F4: #VALUE! | G4: #VALUE!
A5: Ticker Symbol | C5: {=_FV(C4,"Ticker symbol",TRUE)} -> 500049 | D5: {=_FV(D4,"Ticker symbol",TRUE)} -> 543237 | E5: {=_FV(E4,"Ticker symbol",TRUE)} -> 541143 | F5: {=_FV(F4,"Ticker symbol",TRUE)} -> 541154 | G5: {=_FV(G4,"Ticker symbol",TRUE)} -> GRSE
A6: Industry/Sector | C6: {=_FV(C4,"Industry")} -> Aerospace & Defense | D6: {=_FV(D4,"Industry")} -> Aerospace & Defense | E6: {=_FV(E4,"Industry")} -> Aerospace & Defense | F6: {=_FV(F4,"Industry")} -> Aerospace & Defense | G6: {=_FV(G4,"Industry")} -> Aerospace & Defense
A7: Listed Exchange | C7: {=_FV(C4,"Exchange")} -> Bombay Stock Exchange | D7: {=_FV(D4,"Exchange")} -> Bombay Stock Exchange | E7: {=_FV(E4,"Exchange")} -> Bombay Stock Exchange | F7: {=_FV(F4,"Exchange")} -> Bombay Stock Exchange | G7: {=_FV(G4,"Exchange")} -> National Stock Exchange of India
A8: Year of Corporation | C8: {=_FV(C4,"Year incorporated",TRUE)} -> 1954 | D8: {=_FV(D4,"Year incorporated",TRUE)} -> 1934 | E8: {=_FV(E4,"Year incorporated",TRUE)} -> 1970 | F8: {=_FV(F4,"Year incorporated",TRUE)} -> 1963 | G8: {=_FV(G4,"Year incorporated",TRUE)} -> 1934
A9: Market Capitalization (in ₹) | C9: {=_FV(C4,"Market cap",TRUE)} -> 3028076000000 | D9: {=_FV(D4,"Market cap",TRUE)} -> 1077146000000 | E9: {=_FV(E4,"Market cap",TRUE)} -> 530672500000 | F9: {=_FV(F4,"Market cap",TRUE)} -> 3094155000000 | G9: {=_FV(G4,"Market cap",TRUE)} -> 294868300000
C10: =C9/10000000 -> 302807.6 | D10: =D9/10000000 -> 107714.6 | E10: =E9/10000000 -> 53067.25 | F10: =F9/10000000 -> 309415.5 | G10: =G9/10000000 -> 29486.83
A11: Market Price | C11: {=_FV(C4,"Price")} -> 416.7 | D11: {=_FV(D4,"Price")} -> 2705.35 | E11: {=_FV(E4,"Price")} -> 1514.45 | F11: {=_FV(F4,"Price")} -> 4789.5 | G11: {=_FV(G4,"Price")} -> 2682.5
A12: Daily change (%) | C12: {=_FV(C4,"Change (%)",TRUE)} -> 0.005914 | D12: {=_FV(D4,"Change (%)",TRUE)} -> 0.013031 | E12: {=_FV(E4,"Change (%)",TRUE)} -> 0.046758 | F12: {=_FV(F4,"Change (%)",TRUE)} -> 0.035131 | G12: {=_FV(G4,"Change (%)",TRUE)} -> 0.042112
A13: Change (in Rs) | C13: {=_FV(C4,"Change")} -> 2.45 | D13: {=_FV(D4,"Change")} -> 34.8 | E13: {=_FV(E4,"Change")} -> 67.65 | F13: {=_FV(F4,"Change")} -> 162.55 | G13: {=_FV(G4,"Change")} -> 108.4
A14: No. of Shares Outstanding | C14: {=_FV(C4,"Shares outstanding",TRUE)} -> 7309779000 | D14: {=_FV(D4,"Shares outstanding",TRUE)} -> 403380000 | E14: {=_FV(E4,"Shares outstanding",TRUE)} -> 366562500 | F14: {=_FV(F4,"Shares outstanding",TRUE)} -> 668775000 | G14: {=_FV(G4,"Shares outstanding",TRUE)} -> 114552000
C15: =C14/10000000 -> 730.9779 | D15: =D14/10000000 -> 40.338 | E15: =E14/10000000 -> 36.65625 | F15: =F14/10000000 -> 66.8775 | G15: =G14/10000000 -> 11.4552
A16: Beta | C16: {=_FV(C4,"Beta")} -> 1.096 | D16: {=_FV(D4,"Beta")} -> 1.9085 | E16: {=_FV(E4,"Beta")} -> 1.2893 | F16: {=_FV(F4,"Beta")} -> 1.4937 | G16: {=_FV(G4,"Beta")} -> 1.5609

Sheet Balance Sheet 
A1: BALANCE SHEET | F1: #VALUE! | M1: #VALUE! | T1: #VALUE! | AB1: #VALUE! | AI1: #VALUE!
A2: Particulars | B2: 2020 | C2: 2021 | D2: 2022 | E2: 2023 | F2: 2024 | H2: Particulars | I2: 2020 | J2: 2021 | K2: 2022 | L2: 2023 | M2: 2024 | O2: Particulars | P2: 2020 | Q2: 2021 | R2: 2022 | S2: 2023 | T2: 2024 | V2: Particulars | W2: 2020 | X2: 2021 | Y2: 2022 | Z2: 2023 | AA2: 2024 | AB2: 2025 | AD2: Particulars | AE2: 2020 | AF2: 2021 | AG2: 2022 | AH2: 2023 | AI2: 2024
A3: ASSETS | H3: EQUITIES AND LIABILITIES | O3: Assets | V3: Assets | AD3: Assets
A4: NON-CURRENT ASSETS | H4: SHAREHOLDER'S FUNDS | O4: Non-current assets | V4: Non-current assets | AD4: Non-Current assets
A5: Property, plant and equipment | B5: 2496.63 | C5: 2485.5 | D5: 2509.37 | E5: 2694.31 | F5: 2788.47 | H5: Equity Share Capital | I5: 201.69 | J5: 201.69 | K5: 201.69 | L5: 201.69 | M5: 201.69 | O5: PPE | P5: 753.0516 | Q5: 742.7311 | R5: 704.2644 | S5: 646.2838 | T5: 672.355 | V5: PPE | W5: 6350.59 | X5: 6547.01 | Y5: 5927.58 | Z5: 5798.62 | AA5: 5780.23 | AB5: 5970.26 | AD5: PPE | AE5: 299.2331 | AF5: 334.9742 | AG5: =482.9569+11.6104 -> 494.5673 | AH5: =488.2643+10.9865 -> 499.2508 | AI5: =475.1622+9.8172 -> 484.9794
A6: Capital work-in-progress | B6: 199.44 | C6: 397.47 | D6: 445.93 | E6: 361.23 | F6: 456.42 | H6: Total Share Capital | I6: =I5 -> 201.69 | J6: 201.69 | K6: =K5 -> 201.69 | L6: 201.69 | M6: 201.69 | O6: Capital work-in-progress | P6: 42.0585 | Q6: 21.4986 | R6: 40.7318 | S6: 74.3466 | T6: 72.8748 | V6: Capital work-in-progress | W6: 860 | X6: 791.56 | Y6: 949.1 | Z6: 636.9 | AA6: 936.88 | AB6: 1091.08 | AD6: Capital work-in-progress | AE6: 51.5152 | AF6: 151.2972 | AG6: 9.6598 | AH6: 4.8445 | AI6: 116.186
A7: Investment property | B7: 0.09 | C7: 0.08 | D7: 0.07 | E7: 0.06 | F7: 0.04 | H7: Reserves and Surplus | I7: 2857.69 | J7: 3230.02 | K7: 3655.99 | L7: 3975.87 | M7: 6041.78 | O7: Investment property | P7: 0.0097 | Q7: 0.0097 | R7: 0.0097 | S7: 0.0097 | T7: 0.0097 | V7: Investment Property | W7: 0.03 | X7: 0.03 | Y7: 0.03 | Z7: 0.03 | AA7: 0.02 | AB7: 0.02 | AD7: Intangible assets | AE7: 4.4556 | AF7: 5.2286 | AG7: 6.0869 | AH7: 8.3596 | AI7: 7.5872
A8: Investment in associate | B8: 0 | C8: 189.89 | D8: 232.92 | E8: 200.73 | F8: 151.57 | H8: Total Reserves and Surplus | I8: =I7 -> 2857.69 | J8: =J7 -> 3230.02 | K8: =K7 -> 3655.99 | L8: 3975.87 | M8: =M7 -> 6041.78 | O8: Right of use assets | P8: 41.5145 | Q8: 39.7504 | R8: 56.8232 | S8: 54.5603 | T8: 52.8974 | V8: Goodwill | W8: 0 | X8: 0 | Y8: 0 | Z8: 0 | AA8: 0 | AB8: 0 | AD8: Intangible assets under development | AE8: 0 | AF8: 0 | AG8: 0 | AH8: 1.196 | AI8: 13.1439
A9: Other intangible assets | B9: 22.97 | C9: 166.56 | D9: 165.82 | E9: 268.49 | F9: 246.7 | H9: Total Shareholders Funds | I9: =I6+I8 -> 3059.38 | J9: =J6+J8 -> 3431.71 | K9: =K6+K8 -> 3857.68 | L9: =L6+L8 -> 4177.56 | M9: =M6+M8 -> 6243.47 | O9: Intangible assets | P9: 137.792 | Q9: 132.4979 | R9: 112.749 | S9: 107.383 | T9: 98.3599 | V9: Other intangible assets | W9: 1006.87 | X9: 944.07 | Y9: 838.27 | Z9: 1035.75 | AA9: 956.64 | AB9: 700.52 | AD9: Investments | AE9: 0.0044 | AF9: 0.0044 | AG9: 0.0044 | AH9: 0.0044 | AI9: 0.0044
A10: Intangible assets under development | B10: 483.43 | C10: 485.21 | D10: 560.11 | E10: 493.71 | F10: 437.3 | H10: NON-CURRENT LIABILITIES | O10: Investments | P10: 3.9043 | Q10: 4.5226 | R10: 0 | S10: 0 | T10: 0 | V10: Intangible assets under development | W10: 1182.69 | X10: 1286.27 | Y10: 1523.84 | Z10: 1248.1 | AA10: 1556.55 | AB10: 2006.67 | AD10: Other financial assets | AE10: 76.6042 | AF10: 694.559 | AG10: 1141.2663 | AH10: 90.4406 | AI10: 90.1645
A11: Financial assets | H11: Trade Payables | I11: 15.62 | J11: 15.44 | K11: 17.73 | L11: =18.02 -> 18.02 | M11: 17.65 | O11: Loans | P11: 3.0035 | Q11: 2.5196 | R11: 2.0369 | S11: 1.7386 | T11: 1.7022 | V11: Investments accounted for using the equity method | W11: 157.54 | X11: 160.96 | Y11: 167.79 | Z11: 168.33 | AA11: 201.64 | AB11: 244.72 | AD11: Non-current tax assets | AE11: 120.6002 | AF11: 117.1477 | AG11: 153.9376 | AH11: 205.8435 | AI11: 198.4275
A12: Investments | B12: 1161.67 | C12: 1116.05 | D12: 1339.1 | E12: 449.26 | F12: 530.66 | H12: Other Financial Liabilities | I12: 36 | J12: 30.41 | K12: =0.97+4.74 -> 5.71 | L12: =0.48+0.31 -> 0.79 | M12: =0.81+0.69 -> 1.5 | O12: Other financial assets | P12: 46.7689 | Q12: 44.0411 | R12: 40.8576 | S12: 106.0314 | T12: 108.2881 | V12: Investments | W12: 833.26 | X12: 894.55 | Y12: 1194.91 | Z12: 1289.59 | AA12: 1389.69 | AB12: 1509.48 | AD12: Other non-current assets | AE12: 24.0806 | AF12: 2.543 | AG12: 0.1078 | AH12: 0.1634 | AI12: 0.2016
A13: Trade receivables | B13: 0 | C13: 0 | D13: 0 | E13: 0 | F13: 0 | H13: Other long-term liabilities | I13: 154.84 | J13: 148.02 | K13: 140.37 | L13: 133.5 | M13: 126.63 | O13: Deferred tax assets (net) | P13: 54.2497 | Q13: 47.7325 | R13: 57.1071 | S13: 56.4202 | T13: 70.7281 | V13: Trade receivables | W13: 0 | X13: 0 | Y13: 0 | Z13: 0 | AA13: 0 | AB13: 0 | AD13: Total non-current assets | AE13: =SUM(AE5:AE12) -> 576.4933 | AF13: =SUM(AF5:AF12) -> 1305.7541 | AG13: =SUM(AG5:AG12) -> 1805.6301 | AH13: =SUM(AH5:AH12) -> 810.1028 | AI13: =SUM(AI5:AI12) -> 910.6945
A14: Loans | B14: 33.09 | C14: 7.36 | D14: 7.28 | E14: 6.56 | F14: 7.03 | H14: Long term Provisions | I14: 1215.07 | J14: 730.16 | K14: 564.73 | L14: 410.85 | M14: 425.21 | O14: Other non-current assets | P14: 28.8457 | Q14: 27.4555 | R14: 26.0653 | S14: 25.2152 | T14: 23.825 | V14: Contract assets | W14: 0 | X14: 0 | Y14: 0 | Z14: 0 | AA14: 0 | AB14: 0 | AD14: Current Assets
A15: Other financial assets | B15: 28.45 | C15: 28.71 | D15: 24.17 | E15: 20.45 | F15: 18.83 | H15: Total Non-Current Liabilities | I15: =SUM(I11:I14) -> 1421.53 | J15: =SUM(J11:J14) -> 924.03 | K15: =SUM(K11:K14) -> 728.54 | L15: =L11+L12+L13+L14 -> 563.16 | M15: =SUM(M11:M14) -> 570.99 | O15: Total non-current assets | P15: =SUM(P5:P14) -> 1111.1984 | Q15: =SUM(Q5:Q14) -> 1062.759 | R15: =SUM(R5:R14) -> 1040.645 | S15: =SUM(S5:S14) -> 1071.9888 | T15: =SUM(T5:T14) -> 1101.0402 | V15: Loans | W15: 47.96 | X15: 46.13 | Y15: 6.93 | Z15: 6.21 | AA15: 5.61 | AB15: 5.57 | AD15: Inventories | AE15: 441.0222 | AF15: 787.8745 | AG15: 1172.268 | AH15: 2918.5049 | AI15: 3984.4414
A16: Deferred tax assets (net) | B16: 497.4 | C16: 463.46 | D16: 620.94 | E16: 503.72 | F16: 574.68 | H16: CURRENT LIABILITIES | O16: Current Assets | V16: Other financial assets | W16: 345.13 | X16: 344.76 | Y16: 410.3 | Z16: 412.98 | AA16: 395.47 | AB16: 389.11 | AD16: Current Investments | AE16: 54.0043 | AF16: 825.8196 | AG16: 196.6782 | AH16: 233.664 | AI16: 0
A17: Inventories | B17: 52.55 | C17: 39.38 | D17: 27.34 | E17: 5.87 | F17: 0 | H17: Trade Payables | I17: =20.07+4708.17 -> 4728.24 | J17: =39.36+6232.46 -> 6271.82 | K17: 6165.65 | L17: 4462.79 | M17: 4466.42 | O17: Inventories | P17: 856.5177 | Q17: 1397.01 | R17: 1654.4513 | S17: 1822.4375 | T17: 1982.4731 | V17: Deferred tax assets (net) | W17: 470.11 | X17: 52.35 | Y17: 565.57 | Z17: 1125.71 | AA17: 1454.33 | AB17: 1567.99 | AD17: Trade receivables | AE17: 535.28 | AF17: 178.1374 | AG17: 154.9433 | AH17: 50.845 | AI17: 194.207
A18: Other non-current assets | B18: 340.78 | C18: 396.69 | D18: 683.82 | E18: 439.04 | F18: 252 | H18: Other Current Liabilities | I18: 43.63 | J18: 16.49 | K18: 19.23 | L18: 17.28 | M18: 56.26 | O18: Trade receivables | P18: 338.368 | Q18: 322.6927 | R18: 304.1613 | S18: 184.5727 | T18: 310.4472 | V18: Other non-current assets | W18: 629.4 | X18: 706.86 | Y18: 1814.64 | Z18: 3596.54 | AA18: 2400.63 | AB18: 2686.83 | AD18: Cash and cash equivalents | AE18: 729.2275 | AF18: 9.3205 | AG18: 9.7126 | AH18: 13.9855 | AI18: 5.27
A19: Total Non-current assets | B19: =SUM(B5:B18) -> 5316.5 | C19: =SUM(C5:C18) -> 5776.36 | D19: =SUM(D5:D18) -> 6616.87 | E19: =SUM(E5:E18) -> 5443.43 | F19: =SUM(F5:F18) -> 5463.7 | H19: Other Financial Liabilities | I19: 124.08 | J19: 158.11 | K19: =169.73+6.9 -> 176.63 | L19: =146.58+5.73 -> 152.31 | M19: =196.74+0.12 -> 196.86 | O19: Cash and cash equivalents | P19: 297.4947 | Q19: 456.9167 | R19: 265.0437 | S19: 1052.8837 | T19: 593.842 | V19: Total non-current assets | W19: =SUM(W5:W18) -> 11883.58 | X19: =SUM(X5:X18) -> 11774.55 | Y19: =SUM(Y5:Y18) -> 13398.96 | Z19: =SUM(Z5:Z18) -> 15318.76 | AA19: =SUM(AA5:AA18) -> 15077.69 | AB19: =SUM(AB5:AB18) -> 16172.25 | AD19: Bank Balances other than above | AE19: 1882.0938 | AF19: 2271.8514 | AG19: 2548.0263 | AH19: 4313.8207 | AI19: 3715.0684
A20: CURRENT ASSETS | H20: Contract Liability | I20: 11437.25 | J20: =14176.08+90 -> 14266.08 | K20: =18707.76 -> 18707.76 | L20: =19333.34 -> 19333.34 | M20: 17723.39 | O20: Bank Balances other than cash | P20: 366 | Q20: 1104.038 | R20: 1634.49 | S20: 2805.98 | T20: 3634.64 | V20: Current Assets | AD20: Other financial assets | AE20: 207.3275 | AF20: 143.8003 | AG20: 127.513 | AH20: 234.2292 | AI20: 222.3479
A21: Inventories | B21: 3910.2 | C21: 4967.98 | D21: 5591.9 | E21: 6448.04 | F21: 7446.89 | H21: Short Term Provisions | I21: 126.75 | J21: 70.27 | K21: 114.67 | L21: 174.13 | M21: 191.42 | O21: Loans | P21: 2.3696 | Q21: 1.9687 | R21: 1.8374 | S21: 2.0216 | T21: 1.9985 | V21: Inventories | W21: 19435.9 | X21: 16544.77 | Y21: 14347.28 | Z21: 12148.69 | AA21: 13217.54 | AB21: 21675.7 | AD21: Other current assets | AE21: 958.1844 | AF21: 1260.2192 | AG21: 1620.3632 | AH21: 2200.7017 | AI21: 1324.2874
A22: Financial assets | H22: Total Current Liabilities | I22: =SUM(I17:I21) -> 16459.95 | J22: =SUM(J17:J21) -> 20782.77 | K22: =SUM(K17:K21) -> 25183.94 | L22: =SUM(L17:L21) -> 24139.85 | M22: 22634.35 | O22: Other financial assets | P22: 2425.5043 | Q22: 1215.9431 | R22: 1291.6231 | S22: 1324.1177 | T22: 1061.6302 | V22: Investments | W22: 0 | X22: 0 | Y22: 0 | Z22: 0 | AA22: 0 | AB22: 0 | AD22: Assets classified as held for sale | AE22: 0.528 | AF22: 0.4339 | AG22: 0.4587 | AH22: 0.079 | AI22: 0.1599
A23: Trade receivables | B23: 6732.91 | C23: 6561.99 | D23: 6108.09 | E23: 7033.48 | F23: 7392.38 | H23: Total Capital And Liabilities | I23: =I9+I15+I22 -> 20940.86 | J23: =J9+J15+J22 -> 25138.51 | K23: =K9+K15+K22 -> 29770.16 | L23: =L9+L15+L22 -> 28880.57 | M23: =M9+M15+M22 -> 29448.81 | O23: Current tax assets | P23: 36.4539 | Q23: 42.2326 | R23: 29.1205 | S23: 119.4887 | T23: 46.708 | V23: Trade receivables | W23: 11234.73 | X23: 5637.86 | Y23: 4641.53 | Z23: 4719.07 | AA23: 4616.85 | AB23: 4647.79 | AD23: Total current assets | AE23: =SUM(AE15:AE22) -> 4807.6677 | AF23: =SUM(AF15:AF22) -> 5477.4568 | AG23: =SUM(AG15:AG22) -> 5829.9633 | AH23: =SUM(AH15:AH22) -> 9965.83 | AI23: =SUM(AI15:AI22) -> 9445.782
A24: Cash & Cash equivalents | B24: 1556.22 | C24: 3042.9 | D24: 1300.86 | E24: 3945.69 | F24: 1206.32 | H24: ASSETS | O24: Other Current assets | P24: 251.3545 | Q24: 358.1953 | R24: 342.5079 | S24: 288.6407 | T24: 1607.2715 | V24: Contract assets | W24: 7841.73 | X24: 8346.16 | Y24: 7808.65 | Z24: 9376.4 | AA24: 11893.96 | AB24: 15889.16 | AD24: Total Assets | AE24: =AE13+AE23 -> 5384.161 | AF24: =AF13+AF23 -> 6783.2109 | AG24: =AG13+AG23 -> 7635.5934 | AH24: =AH13+AH23 -> 10775.933 | AI24: =AI13+AI23 -> 10356.477
A25: Bank Balances | B25: 1.48 | C25: 2030.86 | D25: 6262.88 | E25: 4165.89 | F25: 9850.27 | H25: NON-CURRENT ASSETS | O25: Total current assets | P25: =SUM(P17:P24) -> 4574.0627 | Q25: =SUM(Q17:Q24) -> 4898.9971 | R25: =SUM(R17:R24) -> 5523.2352 | S25: =SUM(S17:S24) -> 7600.1426 | T25: =SUM(T17:T24) -> 9239.0105 | V25: Cash and cash equivalents | W25: 279.32 | X25: 7146.15 | Y25: 3070.37 | Z25: 4440.77 | AA25: 4254.69 | AB25: 4548.55 | AD25: Equity and Liabilities
A26: Loans | B26: 32.62 | C26: 1.52 | D26: 1.48 | E26: 1.72 | F26: 1.41 | H26: Property, Plant and equipment | I26: 819.22 | J26: 794.93 | K26: 956.56 | L26: =777.63+229.34 -> 1006.97 | M26: 819.65 | O26: Total assets | P26: =P15+P25 -> 5685.2611 | Q26: =Q15+Q25 -> 5961.7561 | R26: =R15+R25 -> 6563.8802 | S26: =S15+S25 -> 8672.1314 | T26: =T15+T25 -> 10340.051 | V26: Bank balances | W26: 37.24 | X26: 31.2 | Y26: 11277.35 | Z26: 15875.84 | AA26: 22176.92 | AB26: 33633.7 | AD26: Equity
A27: Other finance assets | B27: 29.03 | C27: 60.66 | D27: 102.54 | E27: 203.42 | F27: 294.4 | H27: Other Intangible Assets | I27: 17.13 | J27: 11.92 | K27: 8.06 | L27: 17.36 | M27: 18.29 | O27: Equity and Liabilities | V27: Loans | W27: 19.43 | X27: 14.7 | Y27: 7.51 | Z27: 7.76 | AA27: 10.77 | AB27: 7.43 | AD27: Equity share capital | AE27: 114.552 | AF27: 114.552 | AG27: 114.552 | AH27: 114.552 | AI27: 114.552
A28: Current tax assets (net) | B28: 279.89 | C28: 133.64 | D28: 144.74 | E28: 403.14 | F28: 449.61 | H28: Capital Work-In-Progress | I28: 79.96 | J28: 80.15 | K28: 86.94 | L28: 61.62 | M28: 68.24 | O28: Equity | V28: Other financial assets | W28: 1219.03 | X28: 1055.1 | Y28: 1023.23 | Z28: 1119.27 | AA28: 1514.19 | AB28: 1346.93 | AD28: Oher equity | AE28: 925.679 | AF28: 1022.5656 | AG28: 1143.3387 | AH28: 1299.2655 | AI28: 1558.8869
A29: Other current assets | B29: 6052.24 | C29: 6913.76 | D29: 7781.22 | E29: 7846.36 | F29: 7421.7 | H29: Intangible Assets Under Development | I29: 0 | J29: 0 | K29: 0 | L29: 0 | M29: 3.39 | O29: Equity share capital | P29: 183.2812 | Q29: 183.2812 | R29: 183.2812 | S29: 183.2812 | T29: 183.2812 | V29: Current tax assets (net) | W29: 35.31 | X29: 0 | Y29: 0 | Z29: 0 | AA29: 0 | AB29: 0 | AD29: Total equity | AE29: =AE27+AE28 -> 1040.231 | AF29: =AF27+AF28 -> 1137.1176 | AG29: =AG27+AG28 -> 1257.8907 | AH29: =AH27+AH28 -> 1413.8175 | AI29: =AI27+AI28 -> 1673.4389
A30: Total Current Assets | B30: =B21+SUM(B23:B29) -> 18594.59 | C30: =C21+SUM(C23:C29) -> 23713.31 | D30: =D21+SUM(D23:D29) -> 27293.71 | E30: =E21+SUM(E23:E29) -> 30047.74 | F30: =F21+SUM(F23:F29) -> 34062.98 | H30: Investments | I30: 484.18 | J30: 518.65 | K30: 542.32 | L30: 6 | M30: 678.79 | O30: Other equity | P30: 2423.5485 | Q30: 2501.466 | R30: 2847.2762 | S30: 3028.2165 | T30: 3453.5421 | V30: Other current assets | W30: 1291.11 | X30: 1395.41 | Y30: 2808.99 | Z30: 4189.13 | AA30: 5332.57 | AB30: 8345.34 | AD30: Liabilities
A31: TOTAL ASSETS | B31: =B19+B21+B23+B24+B25+B26+B27+B28+B29 -> 23911.09 | C31: =C19+C21+C23+C24+C25+C26+C27+C28+C29 -> 29489.67 | D31: =D19+D21+D23+D24+D25+D26+D27+D28+D29 -> 33910.58 | E31: =E19+E21+E23+E24+E25+E26+E27+E28+E29 -> 35491.17 | F31: =F19+F21+F23+F24+F25+F26+F27+F28+F29 -> 39526.68 | H31: Trade receivable | I31: 15.62 | J31: 15.44 | K31: 17.73 | L31: 18.02 | M31: 17.65 | O31: Total equity | P31: =SUM(P29:P30) -> 2606.8297 | Q31: =SUM(Q29:Q30) -> 2684.7472 | R31: =SUM(R29:R30) -> 3030.5574 | S31: =SUM(S29:S30) -> 3211.4977 | T31: =SUM(T29:T30) -> 3636.8233 | V31: Total current assets | W31: =SUM(W21:W30) -> 41393.8 | X31: =SUM(X21:X30) -> 40171.35 | Y31: =SUM(Y21:Y30) -> 44984.91 | Z31: =SUM(Z21:Z30) -> 51876.93 | AA31: =SUM(AA21:AA30) -> 63017.49 | AB31: =SUM(AB21:AB30) -> 90094.6 | AD31: Non-current liabilities
A32: EQUITY AND LIABILITIES | H32: Loans | I32: 6.89 | J32: 7.1 | K32: 0 | L32: 0 | M32: 20 | O32: Non-current Liabilities | V32: Assets held for sale | W32: 0 | X32: 0 | Y32: 8.11 | Z32: 8.11 | AA32: 0 | AB32: 0 | AD32: Lease Liabilities | AE32: 0 | AF32: 0 | AG32: 9.7354 | AH32: 9.2316 | AI32: 8.2884
A33: Equity share capital | B33: 243.66 | C33: 243.66 | D33: 243.66 | E33: 730.98 | F33: 730.98 | H33: Other Financial assets | I33: 153.45 | J33: 141.59 | K33: 141.16 | L33: 131.67 | M33: 137.45 | O33: Lease liabilities | P33: 7.7119 | Q33: 6.5271 | R33: 5.2075 | S33: 3.7411 | T33: 2.115 | V33: Total assets | W33: =W19+W31 -> 53277.38 | X33: =X19+X31 -> 51945.9 | Y33: =Y19+Y31+Y32 -> 58391.98 | Z33: =Z19+Z31+Z32 -> 67203.8 | AA33: =AA19+AA31+AA32 -> 78095.18 | AB33: =AB19+AB31+AB32 -> 106266.85 | AD33: Total outstanding dues of micro and small ent | AE33: 0 | AF33: 0 | AG33: 0 | AH33: 0 | AI33: 0
A34: Other equity | B34: 9609.28 | C34: 10815.92 | D34: 12042.27 | E34: 13130.65 | F34: 15595.49 | H34: Deferred Tax Assets [Net] | I34: 414.72 | J34: 423.61 | K34: 446.83 | L34: 450.1 | M34: 599.8 | O34: Other financial liabilities | P34: 45.4038 | Q34: 43.2539 | R34: 41.0616 | S34: 45.5747 | T34: 46.3966 | V34: Equity and Liabilities | AD34: Total outstanding dues other than above | AE34: 10.7505 | AF34: 9.2367 | AG34: 8.1892 | AH34: 8.1736 | AI34: 7.8356
A35: Non controlling interest | B35: 0 | C35: 14.99 | D35: 16.34 | E35: 17.75 | F35: 17.92 | H35: Non-current tax assets [Net] | I35: 225.94 | J35: 218.82 | K35: 313.2 | L35: 265.5 | M35: 178.56 | O35: Provisions | P35: 0.2913 | Q35: 29.0682 | R35: 44.6564 | S35: 0.37 | T35: 0.4007 | V35: Equity | AD35: Total trade payables | AE35: =AE33+AE34 -> 10.7505 | AF35: =AF33+AF34 -> 9.2367 | AG35: =AG33+AG34 -> 8.1892 | AH35: =AH33+AH34 -> 8.1736 | AI35: =AI33+AI34 -> 7.8356
A36: Total shareholder's funds | B36: =B33+B34+B35 -> 9852.94 | C36: =C33+C34+C35 -> 11074.57 | D36: =D33+D34+D35 -> 12302.27 | E36: =E33+E34+E35 -> 13879.38 | F36: =F33+F34+F35 -> 16344.39 | H36: Other Non-Current Assets | I36: 651.75 | J36: 842.06 | K36: 727.92 | L36: 838.14 | M36: 1118.8 | O36: Other non-current liabilities | P36: 710.3609 | Q36: 677.1887 | R36: 861.3395 | S36: 3205.2818 | T36: 3648.5577 | V36: Equity share capital | W36: 334.39 | X36: 334.39 | Y36: 334.39 | Z36: 334.39 | AA36: 334.39 | AB36: 334.39 | AD36: Provisions | AE36: 76.6246 | AF36: 82.8666 | AG36: 89.0743 | AH36: 89.3337 | AI36: 92.0135
A37: LIABILITIES | H37: Total Non-Current Assets | I37: =SUM(I26:I36) -> 2868.86 | J37: =SUM(J26:J36) -> 3054.27 | K37: =SUM(K26:K36) -> 3240.72 | L37: =SUM(L26:L36) -> 2795.38 | M37: =SUM(M26:M36) -> 3660.62 | O37: Total non-current Liabilities | P37: =SUM(P33:P36) -> 763.7679 | Q37: =SUM(Q33:Q36) -> 756.0379 | R37: =SUM(R33:R36) -> 952.265 | S37: =SUM(S33:S36) -> 3254.9676 | T37: =SUM(T33:T36) -> 3697.47 | V37: Other equity | W37: 12914.12 | X37: 15077.88 | Y37: 18978.74 | Z37: 23237.76 | AA37: 28803.78 | AB37: 34647.22 | AD37: Deferred tax liabilities (net) | AE37: 9.5378 | AF37: 5.5087 | AG37: 10.7813 | AH37: 14.519 | AI37: 13.9839
A38: NON-CURRENT LIABILITIES | H38: CURRENT ASSETS | O38: Current Liabilities | V38: Equity attributable to the owners | W38: =W36+W37 -> 13248.51 | X38: =X36+X37 -> 15412.27 | Y38: =Y36+Y37 -> 19313.13 | Z38: =Z36+Z37 -> 23572.15 | AA38: =AA36+AA37 -> 29138.17 | AB38: =AB36+AB37 -> 34981.61 | AD38: Total non-current liabilities | AE38: =SUM(AE35,AE36:AE37,AE32) -> 96.9129 | AF38: =SUM(AF35,AF36:AF37,AF32) -> 97.612 | AG38: =SUM(AG35,AG36:AG37,AG32) -> 117.7802 | AH38: =SUM(AH35,AH36:AH37,AH32) -> 121.2579 | AI38: =SUM(AI35,AI36:AI37,AI32) -> 122.1214
A39: Deferred income | B39: 68.89 | C39: 164.99 | D39: 148.43 | E39: 133.95 | F39: 117.76 | H39: Inventories | I39: 4622.69 | J39: 5888.61 | K39: 7700.1 | L39: 7356.86 | M39: 5713.37 | O39: Borrowings | P39: 2.1663 | Q39: 0 | R39: 0 | S39: 0 | T39: 0 | V39: Non-controlling interests | W39: 4.31 | X39: 3.91 | Y39: 3.75 | Z39: 3.74 | AA39: 3.64 | AB39: 3.56 | AD39: Current Liabilities
A40: Financial liabilities | H40: Trade Receivables | I40: 1432.82 | J40: 965.94 | K40: 1005.41 | L40: 1002.33 | M40: 1846.93 | O40: Total outstanding dues of micro and small enterprises (Trade Payables) | P40: 13.8062 | Q40: 29.3769 | R40: 39.9637 | S40: 42.7606 | T40: 12.0705 | V40: Total equity | W40: =W38+W39 -> 13252.82 | X40: =X38+X39 -> 15416.18 | Y40: =Y38+Y39 -> 19316.88 | Z40: =Z38+Z39 -> 23575.89 | AA40: =AA38+AA39 -> 29141.81 | AB40: =AB38+AB39 -> 34985.17 | AD40: Borrowings | AE40: 0 | AF40: 0 | AG40: 0 | AH40: 301.1718 | AI40: 55.5848
A41: Borrowings | B41: 0 | C41: 0 | D41: 0 | H41: Cash And Cash Equivalents | I41: =483.28+5315 -> 5798.28 | J41: =739.91+7288 -> 8027.91 | K41: 11480.47 | L41: 13286.42 | M41: =3523.48+10686.15 -> 14209.63 | O41: Total outstanding dues of creditors other than above (Trade Payables) | P41: 331.6791 | Q41: 713.2242 | R41: 512.5061 | S41: 421.6177 | T41: 786.3166 | V41: Liabilities | AD41: Lease Liabilities | AE41: 0 | AF41: 0 | AG41: 1.4688 | AH41: 1.7041 | AI41: 1.7974
A42: Trade payables | B42: 0.2 | C42: 0.29 | D42: 0.34 | E42: 0.37 | F42: 0 | H42: Short Term Loans And Advances | I42: 2.11 | J42: 2.12 | K42: 0 | L42: 0 | M42: 0 | O42: Total Trade Payables | P42: =P40+P41 -> 345.4853 | Q42: =Q40+Q41 -> 742.6011 | R42: =R40+R41 -> 552.4698 | S42: =S40+S41 -> 464.3783 | T42: =T40+T41 -> 798.3871 | V42: Non-current liabilities | AD42: Total outstanding dues of micro and small ent | AE42: 2.9343 | AF42: 0.9536 | AG42: 2.2852 | AH42: 2.3615 | AI42: 0.5032
A43: Lease liabilities | B43: 0 | C43: 1.17 | D43: 51.51 | E43: 59.42 | F43: 60.25 | H43: Other financial assets | I43: 187.85 | J43: 139.59 | K43: 140.66 | L43: 221.4 | M43: 307.56 | O43: Lease liabilities | P43: 1.061 | Q43: 1.1848 | R43: 1.3196 | S43: 1.4664 | T43: 1.6261 | V43: Borrowings | W43: 0 | X43: 0 | Y43: 0 | Z43: 0 | AA43: 0 | AB43: 0 | AD43: Total outstanding dues other than above | AE43: 543.8437 | AF43: 781.7614 | AG43: 409.4031 | AH43: 1171.5059 | AI43: 991.9169
A44: Other financial liabilities | B44: 49.34 | C44: 6.71 | D44: 20.22 | E44: 4.73 | F44: 4.8 | H44: Contract assets | I44: 55.47 | J44: 213.7 | K44: 407 | L44: 283.23 | M44: 57.3 | O44: Other financial liabilities | P44: 165.5462 | Q44: 144.1785 | R44: 164.3659 | S44: 167.6158 | T44: 290.4003 | V44: Trade payables | W44: 0 | X44: 0 | Y44: 0 | Z44: 0 | AA44: 0 | AB44: 0 | AD44: Total trade payables | AE44: =AE42+AE43 -> 546.778 | AF44: =AF42+AF43 -> 782.715 | AG44: =AG42+AG43 -> 411.6883 | AH44: =AH42+AH43 -> 1173.8674 | AI44: =AI42+AI43 -> 992.4201
A45: Long term provisions | B45: 1160.57 | C45: 1412.03 | D45: 1805.32 | E45: 844.65 | F45: 967.28 | H45: Assets held for sale | I45: 0.22 | J45: 0.35 | K45: 0.44 | L45: 0.32 | M45: 0.07 | O45: Other current liabilities | P45: 1474.1556 | Q45: 1403.0258 | R45: 1553.5965 | S45: 1220.7882 | T45: 1515.4221 | V45: Lease Liabilities | W45: 0 | X45: 0 | Y45: 2.41 | Z45: 2.51 | AA45: 1.08 | AB45: 1.14 | AD45: Other financial liabilities | AE45: 24.2641 | AF45: 24.0122 | AG45: 23.9335 | AH45: 28.9456 | AI45: 35.4652
A46: Other non-current liabilities | B46: 1.12 | C46: 0 | D46: 0 | E46: 0 | F46: 0 | H46: Other CurrentAssets | I46: 5972.56 | J46: 6846.02 | K46: 5795.36 | L46: 3934.63 | M46: 3653.33 | O46: Provisions | P46: 326.2491 | Q46: 229.9808 | R46: 309.306 | S46: 351.7174 | T46: 399.9218 | V46: Other financial liabilities | W46: 552.07 | X46: 495.6 | Y46: 524.7 | Z46: 525.03 | AA46: 505.86 | AB46: 496.65 | AD46: Other current liabilities | AE46: 3523.3862 | AF46: 4579.8352 | AG46: 5656.7692 | AH46: 7706.3711 | AI46: 7333.0421
A47: Deferred tax liabilities (net) | B47: 0 | C47: 0.36 | D47: 1.45 | E47: 2.89 | F47: 5.47 | H47: Total Current Assets | I47: =SUM(I39:I46) -> 18072 | J47: 22084.24 | K47: =SUM(K39:K46) -> 26529.44 | L47: =SUM(L39:L46) -> 26085.19 | M47: =SUM(M39:M46) -> 25788.19 | O47: Current tax liabilities (net) | P47: 0 | Q47: 0 | R47: 0 | S47: 0 | T47: 0 | V47: Provisions | W47: 1288.75 | X47: 1215.72 | Y47: 1263.01 | Z47: 1347.1 | AA47: 1578.34 | AB47: 1868.06 | AD47: Provisions | AE47: 152.589 | AF47: 161.9189 | AG47: 166.0627 | AH47: 28.7974 | AI47: 38.0392
A48: Total non-current liabilities | B48: =SUM(B39:B47) -> 1280.12 | C48: =SUM(C39:C47) -> 1585.55 | D48: =SUM(D39:D47) -> 2027.27 | E48: =SUM(E39:E47) -> 1046.01 | F48: =SUM(F39:F47) -> 1155.56 | H48: Total Assets | I48: =I37+I47 -> 20940.86 | J48: =J37+J47 -> 25138.51 | K48: =K37+K47 -> 29770.16 | L48: =L37+L47 -> 28880.57 | M48: =M37+M47 -> 29448.81 | O48: Total current liabilities | P48: =SUM(P39,P42,P43:P47) -> 2314.6635 | Q48: =SUM(Q39,Q42,Q43:Q47) -> 2520.971 | R48: =SUM(R39,R42,R43:R47) -> 2581.0578 | S48: =SUM(S39,S42,S43:S47) -> 2205.9661 | T48: =SUM(T39,T42,T43:T47) -> 3005.7574 | V48: Deferred tax liabilities (net) | W48: 0 | X48: 0 | Y48: 0 | Z48: 0 | AA48: 0 | AB48: 0 | AD48: Total current liabilities | AE48: =SUM(AE44,AE45:AE47,AE41,AE40) -> 4247.0173 | AF48: =SUM(AF44,AF45:AF47,AF41,AF40) -> 5548.4813 | AG48: =SUM(AG44,AG45:AG47,AG41,AG40) -> 6259.9225 | AH48: =SUM(AH44,AH45:AH47,AH41,AH40) -> 9240.8574 | AI48: =SUM(AI44,AI45:AI47,AI41,AI40) -> 8456.3488
A49: CURRENT LIABILITIES | O49: Total Liabilities | P49: =P37+P48 -> 3078.4314 | Q49: =Q37+Q48 -> 3277.0089 | R49: =R37+R48 -> 3533.3228 | S49: =S37+S48 -> 5460.9337 | T49: =T37+T48 -> 6703.2274 | V49: Other non-current liabilities | W49: 7056.54 | X49: 9307.69 | Y49: 12262.44 | Z49: 10926 | AA49: 10543.76 | AB49: 24820.58 | AD49: Total Equity and Liabilities | AE49: =AE29+AE38+AE48 -> 5384.1612 | AF49: =AF29+AF38+AF48+AF41 -> 6783.2109 | AG49: =AG29+AG38+AG48+AG41 -> 7637.0622 | AH49: =AH29+AH38+AH48+AH41 -> 10777.637 | AI49: =AI29+AI38+AI48+AI41 -> 10253.706
A50: Deferred income | B50: 4.22 | C50: 17.11 | D50: 16.54 | E50: 16.65 | F50: 16.37 | O50: Total Equity and Liabilities | P50: =P31+P49 -> 5685.2611 | Q50: =Q31+Q49 -> 5961.7561 | R50: =R31+R49 -> 6563.8802 | S50: =S31+S49 -> 8672.4314 | T50: =T31+T49 -> 10340.051 | V50: Total non-current liabilities | W50: =SUM(W43:W49) -> 8897.36 | X50: =SUM(X43:X49) -> 11019.01 | Y50: =SUM(Y43:Y49) -> 14052.56 | Z50: =SUM(Z43:Z49) -> 12800.64 | AA50: =SUM(AA43:AA49) -> 12629.04 | AB50: =SUM(AB43:AB49) -> 27186.43
A51: Financial liabilities | H51: Working Capital | I51: =I47-I22 -> 1612.05 | J51: =J47-J22 -> 1301.47 | K51: =K47-K22 -> 1345.5 | L51: =L47-L22 -> 1945.34 | M51: =M47-M22 -> 3153.84 | V51: Current Liabilities | AD51: Working Capital | AE51: =AE23-AE48 -> 560.6504 | AF51: =AF23-AF48 -> -71.0245 | AG51: =AG23-AG48 -> -429.9592 | AH51: =AH23-AH48 -> 724.9726 | AI51: =AI23-AI48 -> 989.4332
A52: Lease liabilities | B52: 0 | C52: 1.35 | D52: 1.19 | E52: 1.92 | F52: 2.26 | O52: Working Capital | P52: =P25-P48 -> 2259.3992 | Q52: =Q25-Q48 -> 2378.0261 | R52: =R25-R48 -> 2942.1774 | S52: =S25-S48 -> 5394.1765 | T52: =T25-T48 -> 6233.2531 | V52: Borrowings | W52: 5886.5 | X52: 9.07 | Y52: 0 | Z52: 0 | AA52: 0 | AB52: 0
A53: Trade Payables | B53: =64.78+2359.97 -> 2424.75 | C53: =153.43+3145.47 -> 3298.9 | D53: =248.44+3120.86 -> 3369.3 | E53: =207.54+3122.84 -> 3330.38 | F53: =213.06+3493.25 -> 3706.31 | V53: Total outstanding dues of micro and small ent | W53: 47.79 | X53: 46.98 | Y53: 45.75 | Z53: 64.07 | AA53: 146.05 | AB53: 177.09
A54: Other financial liabilities | B54: 831.95 | C54: 958.95 | D54: 960.43 | E54: 1290.23 | F54: 1317.14 | V54: Total outstanding dues of creditors other than above | W54: 4035.95 | X54: 2194.04 | Y54: 2511.86 | Z54: 3070.9 | AA54: 3266.82 | AB54: 4928.58
A55: Other current liabilities | B55: 9201.75 | C55: 12202.96 | D55: 14809.07 | E55: 15299.06 | F55: 16289.84 | V55: Total Trade payables | W55: =W53+W54 -> 4083.74 | X55: =X53+X54 -> 2241.02 | Y55: =Y53+Y54 -> 2557.61 | Z55: =Z53+Z54 -> 3134.97 | AA55: =AA53+AA54 -> 3412.87 | AB55: =AB53+AB54 -> 5105.67
A56: Short term provisions | B56: 315.36 | C56: 350.28 | D56: 423.82 | E56: 627.54 | F56: 694.53 | V56: Lease Liabilities | W56: 0 | X56: 0 | Y56: 0.08 | Z56: 0.14 | AA56: 0.02 | AB56: 0.02
A57: Current tax liabilities (net) | B57: 0 | C57: 0 | D57: 0.69 | E57: 0 | F57: 0.28 | V57: Other financial liabilities | W57: 2505.39 | X57: 1967.48 | Y57: 1853.6 | Z57: 2109.43 | AA57: 2451.38 | AB57: 2829.32
A58: Total Current Liabilities | B58: =SUM(B50:B57) -> 12778.03 | C58: =SUM(C50:C57) -> 16829.55 | D58: =SUM(D50:D57) -> 19581.04 | E58: =SUM(E50:E57) -> 20565.78 | F58: =SUM(F50:F57) -> 22026.73 | V58: Other current liabilities | W58: 13028.89 | X58: 16894.22 | Y58: 14755.15 | Z58: 18537.14 | AA58: 22549.68 | AB58: 27603.27
A59: TOTAL EQUITY AND LIABILITIES | B59: =B36+B48+B50+B53+B54+B55+B56+B57 -> 23911.09 | C59: =C36+C48+C50+C53+C54+C55+C56+C57+C52 -> 29489.67 | D59: =D36+D48+D50+D53+D54+D55+D56+D57+D52 -> 33910.58 | E59: =E36+E48+E50+E53+E54+E55+E56+E57+E52 -> 35491.17 | F59: =F36+F48+F50+F53+F54+F55+F56+F57+F52 -> 39526.68 | V59: Provisions | W59: 5041.92 | X59: 3976.38 | Y59: 5056.96 | Z59: 6778.31 | AA59: 7610.71 | AB59: 8417.36
V60: Current tax liabilities (net) | W60: 580.76 | X60: 422.54 | Y60: 799.14 | Z60: 267.28 | AA60: 299.67 | AB60: 139.61
V61: Total current liabilities | W61: =SUM(W52,W55,W56:W60) -> 31127.2 | X61: =SUM(X52,X55,X56:X60) -> 25510.71 | Y61: =SUM(Y52,Y55,Y56:Y60) -> 25022.54 | Z61: =SUM(Z52,Z55,Z56:Z60) -> 30827.27 | AA61: =SUM(AA52,AA55,AA56:AA60) -> 36324.33 | AB61: =SUM(AB52,AB55,AB56:AB60) -> 44095.25
V62: Total equity and liabilities | W62: =W40+W50+W61 -> 53277.38 | X62: =X40+X50+X61 -> 51945.9 | Y62: =Y40+Y50+Y61 -> 58391.98 | Z62: =Z40+Z50+Z61 -> 67203.8 | AA62: =AA40+AA50+AA61 -> 78095.18 | AB62: =AB40+AB50+AB61 -> 106266.85
V64: Working Capital | W64: =W31-W61 -> 10266.6 | X64: =X31-X61 -> 14660.64 | Y64: =Y31-Y61 -> 19962.37 | Z64: =Z31-Z61 -> 21049.66 | AA64: =AA31-AA61 -> 26693.16 | AB64: =AB31-AB61 -> 45999.35
A65: Working Capital | B65: =B30-B58 -> 5816.56 | C65: =C30-C58 -> 6883.76 | D65: =D30-D58 -> 7712.67 | E65: =E30-E58 -> 9481.96 | F65: =F30-F58 -> 12036.25

Sheet Income Statement
A1: INCOME STATEMENT | F1: #VALUE! | M1: #VALUE! | T1: #VALUE! | AA1: #VALUE! | AI1: #VALUE!
A2: Particulars | B2: Mar 24 | C2: Mar 23 | D2: Mar 22 | E2: Mar 21 | F2: Mar 20 | H2: Particulars | I2: Mar 24 | J2: Mar 23 | K2: Mar 22 | L2: Mar 21 | M2: Mar 20 | O2: Particulars | P2: 2020 | Q2: 2021 | R2: 2022 | S2: 2023 | T2: 2024 | V2: Particulars | W2: 2020 | X2: 2021 | Y2: 2022 | Z2: 2023 | AA2: 2024 | AC2: Particulars | AD2: 2020 | AE2: 2021 | AF2: 2022 | AG2: 2023 | AH2: 2024 | AI2: 2025
A3: INCOME | H3: INCOME | O3: Income | V3: Income | AC3: Income
A4: Revenue From Operations [Gross] | B4: 9068.01 | C4: 7584.03 | D4: 5717.61 | E4: 4041.58 | F4: 4977.65 | H4: Revenue From Operations [Gross] | I4: 19819.93 | J4: 17333.37 | K4: 15043.67 | L4: 13818.16 | M4: 12967.67 | O4: Revenue from Operations | P4: 1433.2953 | Q4: 1140.8353 | R4: 1757.51 | S4: 2561.1451 | T4: 3592.6423 | V4: Revenue from Operations | W4: 3104.872 | X4: 1913.7595 | Y4: 2817.4028 | Z4: 2489.3925 | AA4: 2369.2751 | AC4: Revenue from Operations | AD4: 21445.16 | AE4: 22754.54 | AF4: 24620.02 | AG4: 26927.46 | AH4: 30381.08 | AI4: 30980.95
A5: Revenue From Operations [Net] | B5: 9068.01 | C5: 7584.03 | D5: 5717.61 | E5: 4041.58 | F5: 4977.65 | H5: Revenue From Operations [Net] | I5: 19819.93 | J5: 17333.37 | K5: 15043.67 | L5: 13818.16 | M5: =M4 -> 12967.67 | O5: Other income | P5: 225.4994 | Q5: 187.5956 | R5: 160.65 | S5: 201.8355 | T5: 299.6219 | V5: Other income | W5: 88.0503 | X5: 94.6136 | Y5: 111.2104 | Z5: 155.4022 | AA5: 361.8293 | AC5: Other income | AD5: 296.57 | AE5: 358.23 | AF5: 984.93 | AG5: 1670.12 | AH5: 1896.6 | AI5: 2561.69
A6: Other Operating Revenues | B6: 398.57 | C6: 243.15 | D6: 15.67 | E6: 6.24 | F6: 0 | H6: Other Operating Revenues | I6: 349.46 | J6: 312.83 | K6: 270.09 | L6: 245.67 | M6: 0 | O6: Total income | P6: =P4+P5 -> 1658.7947 | Q6: =Q4+Q5 -> 1328.4309 | R6: =R4+R5 -> 1918.16 | S6: =S4+S5 -> 2762.9806 | T6: =T4+T5 -> 3892.2642 | V6: Total income | W6: =W4+W5 -> 3192.9223 | X6: =X4+X5 -> 2008.3731 | Y6: =Y4+Y5 -> 2928.6132 | Z6: =Z4+Z5 -> 2644.7947 | AA6: =AA4+AA5 -> 2731.1044 | AC6: Total Income | AD6: =AD4+AD5 -> 21741.73 | AE6: =AE4+AE5 -> 23112.77 | AF6: =AF4+AF5 -> 25604.95 | AG6: =AG4+AG5 -> 28597.58 | AH6: =AH4+AH5 -> 32277.68 | AI6: =AI4+AI5 -> 33542.64
A7: Total Operating Revenues | B7: 9466.58 | C7: 7827.18 | D7: 5733.28 | E7: 4047.82 | F7: =F5+F6 -> 4977.65 | H7: Total Operating Revenues | I7: 20169.39 | J7: 17646.2 | K7: 15313.76 | L7: 14063.83 | M7: 0 | O7: Expenses | V7: Expenses | AC7: Expenses
A8: Other Income | B8: 1138.02 | C8: 713.48 | D8: 433.63 | E8: 574.1 | F8: 557.67 | H8: Other Income | I8: 755.84 | J8: 360.02 | K8: 233.59 | L8: 126.1 | M8: 99.4 | O8: Cost of materials consumed | P8: 691.6971 | Q8: 447.2489 | R8: 935.2037 | S8: 1495.2439 | T8: 2060.3678 | V8: Cost of materials consumed | W8: 1014.0885 | X8: 970.0831 | Y8: 1263.3655 | Z8: 1210.3346 | AA8: 1119.959 | AC8: Cost of materials consumed | AD8: 8164.53 | AE8: 7764.72 | AF8: 8752.24 | AG8: 9993.68 | AH8: 12346.33 | AI8: 19234.46
A9: Total Revenue | B9: 10604.6 | C9: 8540.66 | D9: 6166.91 | E9: =E7+E8 -> 4621.92 | F9: =F7+F8 -> 5535.32 | H9: Total Revenue | I9: 20925.23 | J9: 18006.22 | K9: 15547.35 | L9: 14189.93 | M9: =M5+M8 -> 13067.07 | O9: Purchase of products for resale | P9: 54.2626 | Q9: 23.9227 | R9: 8.365 | S9: 112.1006 | T9: 197.0656 | V9: Changes in inventories of finished goods and WIP | W9: 503.6633 | X9: -128.9075 | Y9: -84.3558 | Z9: -19.0372 | AA9: -222.6315 | AC9: Purchases of stock-in-trade | AD9: 587.15 | AE9: 821.16 | AF9: 656.68 | AG9: 799.15 | AH9: 671.4 | AI9: 679.37
A10: EXPENSES | H10: EXPENSES | O10: Changes in inventories of WIP and scrap | P10: -24.1995 | Q10: 11.329 | R10: 0.3871 | S10: 4.7266 | T10: -6.0555 | V10: Employee benefit expenses | W10: 534.0307 | X10: 501.0886 | Y10: 570.6627 | Z10: 532.4643 | AA10: 600.0076 | AC10: Changes in Inventories of Finished goods, SIT, WIP and scrap | AD10: 635.68 | AE10: 2458.14 | AF10: 592.3 | AG10: -690.72 | AH10: -1958.64 | AI10: -7625.79
A11: Cost Of Materials Consumed | B11: 0 | C11: 0 | D11: 0 | E11: 1881.91 | F11: 2503.18 | H11: Cost Of Materials Consumed | I11: 10497.62 | J11: 9378.44 | K11: 8125.98 | L11: 6723.94 | M11: =5869.26+27.74 -> 5897 | O11: Sub-contracting charges | P11: 170.0721 | Q11: 129.926 | R11: 254.5935 | S11: 317.9334 | T11: 524.9324 | V11: Finance costs | W11: 4.6557 | X11: 3.9128 | Y11: 3.4243 | Z11: 4.5364 | AA11: 3.1052 | AC11: Employee benefit expenses | AD11: 4777.62 | AE11: 4305.17 | AF11: 4604.42 | AG11: 4910.37 | AH11: 5290.69 | AI11: 5730.37
A12: Operating And Direct Expenses | B12: 6627.6 | C12: 5155.53 | D12: 4215.14 | E12: 1155.21 | F12: =362.23+744.09+16.52+113.7 -> 1236.54 | H12: Purchase Of Stock-In Trade | I12: 628.86 | J12: 827.85 | K12: 1053.49 | L12: 1233.21 | M12: 950.97 | O12: Employee benefit expenses | P12: 296.9415 | Q12: 269.3804 | R12: 290.286 | S12: 316.9107 | T12: 348.9333 | V12: Depreciation and amortisation expense | W12: 96.4384 | X12: 94.5384 | Y12: 90.3547 | Z12: 77.2579 | AA12: 67.0392 | AC12: Finance costs | AD12: 348.46 | AE12: 259.17 | AF12: 58.2 | AG12: 57.97 | AH12: 32.11 | AI12: 8.68
A13: Employee Benefit Expenses | B13: 896.55 | C13: 792.71 | D13: 798.73 | E13: 652.81 | F13: 792.92 | H13: Changes In Inventories Of FG,WIP And Stock-In Trade | I13: -560.57 | J13: -397.45 | K13: -276.97 | L13: -129.33 | M13: 249.31 | O13: Finance cost | P13: 1.3356 | Q13: 2.701 | R13: 0.7641 | S13: 6.4807 | T13: 11.4892 | V13: Other expenses | W13: 297.5917 | X13: 226.7766 | Y13: 341.6636 | Z13: 357.4352 | AA13: 335.3895 | AC13: Depreciation and amortization expenses | AD13: 998.52 | AE13: 1178.28 | AF13: 1110.53 | AG13: 1784.67 | AH13: 1407.17 | AI13: 1340.37
A14: Finance Costs | B14: 5.12 | C14: 6.37 | D14: 7.16 | E14: 8.36 | F14: 9.26 | H14: Employee Benefit Expenses | I14: 2466.7 | J14: 2297.73 | K14: 2109.39 | L14: 1940.68 | M14: 2074.74 | O14: Depreciation and amortisation expense | P14: 30.0892 | Q14: 29.0876 | R14: 35.7101 | S14: 39.1663 | T14: 41.3266 | V14: Total expenses | W14: =SUM(W8:W13) -> 2450.4683 | X14: =SUM(X8:X13) -> 1667.492 | Y14: =SUM(Y8:Y13) -> 2185.115 | Z14: =SUM(Z8:Z13) -> 2162.9912 | AA14: =SUM(AA8:AA13) -> 1902.869 | AC14: Impairement loss | AD14: 31.79 | AE14: 63.85 | AF14: 176.43 | AG14: 597.43 | AH14: 14.95 | AI14: 24.75
A15: Provsions and Contingencies | B15: 168.5 | C15: 117.39 | D15: 102.55 | E15: 19.82 | F15: 38.64 | H15: Finance Costs | I15: 7.02 | J15: 14.79 | K15: 4.85 | L15: 6.08 | M15: 3.6 | O15: Other expenses-project related | P15: 73.119 | Q15: 75.3111 | R15: 23.488 | S15: 57.0743 | T15: 99.0402 | V15: Profit/loss before exceptional items and tax | W15: =W6-W14 -> 742.454 | X15: =X6-X14 -> 340.8811 | Y15: =Y6-Y14 -> 743.4982 | Z15: =Z6-Z14 -> 481.8035 | AA15: =AA6-AA14 -> 828.2354 | AC15: Other expenses | AD15: 1448.69 | AE15: 1216.03 | AF15: 1210.86 | AG15: 1560.59 | AH15: 1530.53 | AI15: 1784.62
A16: Depreciation And Amortisation Expenses | B16: 83.13 | C16: 75.58 | D16: 74.51 | E16: 59.65 | F16: 68.69 | H16: Depreciation And Amortisation Expenses | I16: 412.43 | J16: 407.87 | K16: 380.18 | L16: 366.33 | M16: 371.86 | O16: Other expenses | P16: 130.9991 | Q16: 111.6574 | R16: 104.443 | S16: 108.1262 | T16: 134.2437 | V16: Exceptional items | W16: 0 | X16: 0 | Y16: -33.5857 | Z16: 0 | AA16: 0 | AC16: Direct input to WIP/Expenses capitalised | AD16: 178.29 | AE16: 259.77 | AF16: 323.15 | AG16: 516.03 | AH16: 425.99 | AI16: 372.33
A17: Other Expenses | B17: 362.32 | C17: 963.75 | D17: 182.16 | E17: 114.2 | F17: 138.4 | H17: Other Expenses | I17: 2138.61 | J17: 1492.11 | K17: 992.63 | L17: 1114.21 | M17: 1041.19 | O17: Total expenses | P17: =SUM(P8:P16) -> 1424.3167 | Q17: =SUM(Q8:Q16) -> 1100.5641 | R17: =SUM(R8:R16) -> 1653.2405 | S17: =SUM(S8:S16) -> 2457.7627 | T17: =SUM(T8:T16) -> 3411.3433 | V17: Profit before tax | W17: =W15+W16 -> 742.454 | X17: =X15+X16 -> 340.8811 | Y17: =Y15+Y16 -> 709.9125 | Z17: =Z15+Z16 -> 481.8035 | AA17: =AA15+AA16 -> 828.2354 | AC17: Provisions | AD17: 1453.27 | AE17: 1450.26 | AF17: 3729.54 | AG17: 3724.8 | AH17: 3303.04 | AI17: 2527.84
A18: Total Expenses | B18: 8143.22 | C18: 7111.33 | D18: 5380.25 | E18: 3891.96 | F18: =SUM(F11:F17) -> 4787.63 | H18: Total Expenses | I18: 15590.67 | J18: 14021.34 | K18: 12389.55 | L18: 11255.12 | M18: =SUM(M11:M17) -> 10588.67 | O18: Profit before exceptional items and tax | P18: =P6-P17 -> 234.478 | Q18: =Q6-Q17 -> 227.8668 | R18: =R6-R17 -> 264.9195 | S18: =S6-S17 -> 305.2179 | T18: =T6-T17 -> 480.9209 | V18: Tax expense | AC18: Total Gross expenses | AD18: =SUM(AD8:AD17) -> 18624 | AE18: =SUM(AE8:AE17) -> 19776.55 | AF18: =SUM(AF8:AF17) -> 21214.35 | AG18: =SUM(AG8:AG17) -> 23253.97 | AH18: =SUM(AH8:AH17) -> 23063.57 | AI18: =SUM(AI8:AI17) -> 24077
O19: Exceptional items | P19: -10.607 | Q19: -20.7494 | R19: -7.6854 | S19: 0 | T19: 0 | V19: Current tax | W19: 190.0293 | X19: 72.0437 | Y19: 216.5356 | Z19: 127.7536 | AA19: 228.7472 | AC19: Less: Expenses relating to capital and other accounts | AD19: 734.97 | AE19: 933.94 | AF19: 834.16 | AG19: 1163.02 | AH19: 984.27 | AI19: 1355.07
A20: Profit/Loss Before Exceptional, Extraordinary Items And Tax | B20: 2461.38 | C20: 1429.33 | D20: 786.66 | E20: =E9-E18 -> 729.96 | F20: =F9-F18 -> 747.69 | H20: Profit/Loss Before Exceptional, Extraordinary Items And Tax | I20: 5334.56 | J20: 3984.88 | K20: 3157.8 | L20: 2934.81 | M20: =M9-M18 -> 2478.4 | O20: Profit before tax | P20: =P18+P19 -> 223.871 | Q20: =Q18+Q19 -> 207.1174 | R20: =R18+R19 -> 257.2341 | S20: =S18+S19 -> 305.2179 | T20: =T18+T19 -> 480.9209 | V20: Deferred tax | W20: 17.5239 | X20: 11.0722 | Y20: -6.5475 | AA20: -13.2326 | AC20: Total expenses | AD20: =AD18-AD19 -> 17889.03 | AE20: =AE18-AE19 -> 18842.61 | AF20: =AF18-AF19 -> 20380.19 | AG20: =AG18-AG19 -> 22090.95 | AH20: =AH18-AH19 -> 22079.3 | AI20: =AI18-AI19 -> 22721.93
A21: Exceptional Items | B21: 0 | C21: 0 | D21: -13.97 | E21: 126.14 | F21: 12.32 | H21: Profit/Loss Before Tax | I21: 5334.56 | J21: 3984.88 | K21: 3157.8 | L21: 2934.81 | M21: =M20 -> 2478.4 | O21: Tax expense | V21: Total tax expense | W21: =W19+W20 -> 207.5532 | X21: =X19+X20 -> 83.1159 | Y21: =Y19+Y20 -> 209.9881 | Z21: =Z19+Z20 -> 127.7536 | AA21: =AA19+AA20 -> 215.5146 | AC21: Profit/loss before share of Profit/Loss of joint ventures, exceptional items and tax | AD21: =AD6-AD20 -> 3852.7 | AE21: =AE6-AE20 -> 4270.16 | AF21: =AF6-AF20 -> 5224.76 | AG21: =AG6-AG20 -> 6506.63 | AH21: =AH6-AH20 -> 10198.38 | AI21: =AI6-AI20 -> 10820.71
A22: Profit/Loss Before Tax | B22: 2461.38 | C22: 1429.33 | D22: 772.69 | E22: =E20-E21 -> 603.82 | F22: =F20-F21 -> 735.37 | H22: Tax Expenses-Continued Operations | O22: Current tax | P22: 58.0878 | Q22: 58.8711 | R22: 62.82 | S22: 73.539 | T22: 124.5575 | V22: Profit/Loss for the year | W22: =W17-W21 -> 534.9008 | X22: =X17-X21 -> 257.7652 | Y22: =Y17-Y21 -> 499.9244 | Z22: =Z17-Z21 -> 354.0499 | AA22: =AA17-AA21 -> 612.7208 | AC22: Share of profit/loss of joint ventures accounted using equity method | AD22: 7.02 | AE22: 4.81 | AF22: -0.23 | AG22: 2.87 | AH22: 26.5 | AI22: 40.65
A23: Tax Expenses-Continued Operations | H23: Current Tax | I23: 1449.59 | J23: 874.46 | K23: 910.52 | L23: 824.93 | M23: 757.67 | O23: Deferred tax | P23: 2.3015 | Q23: -5.2249 | R23: 4.8948 | S23: 3.5549 | T23: -0.9043 | AC23: Profit/loss before exceptional items and tax | AD23: =AD21+AD22 -> 3859.72 | AE23: =AE21+AE22 -> 4274.97 | AF23: =AF21+AF22 -> 5224.53 | AG23: =AG21+AG22 -> 6509.5 | AH23: =AH21+AH22 -> 10224.88 | AI23: =AI21+AI22 -> 10861.36
A24: Current Tax | B24: 763.88 | C24: 358.87 | D24: 209.44 | E24: 148.63 | F24: 180.43 | H24: Deferred Tax | I24: -66.13 | J24: 123.76 | K24: -101.65 | L24: 69.38 | M24: -31.43 | O24: Total tax expense | P24: =SUM(P22:P23) -> 60.3893 | Q24: =SUM(Q22:Q23) -> 53.6462 | R24: =SUM(R22:R23) -> 67.7148 | S24: =SUM(S22:S23) -> 77.0939 | T24: =SUM(T22:T23) -> 123.6532 | W24: =W15+W11 -> 747.1097 | X24: =X15+X11 -> 344.7939 | Y24: =Y15+Y11 -> 746.9225 | Z24: =Z15+Z11 -> 486.3399 | AA24: =AA15+AA11 -> 831.3406 | AC24: Exceptional items | AD24: 118.92 | AE24: 2.02 | AF24: 0 | AG24: 0 | AH24: 0 | AI24: 5.89
A25: Deferred Tax | B25: -149.69 | C25: -3.27 | D25: -23.22 | E25: -8.88 | F25: 170.32 | H25: Tax For Earlier Years | I25: -68.9 | J25: -20.01 | K25: 0 | L25: -24.92 | M25: -40.47 | O25: Profit for the period | P25: =P20-P24 -> 163.4817 | Q25: =Q20-Q24 -> 153.4712 | R25: =R20-R24 -> 189.5193 | S25: =S20-S24 -> 228.124 | T25: =T20-T24 -> 357.2677 | V25: Revenue YoY | X25: =(X6/W6)-1 -> -0.37099218 | Y25: =(Y6/X6)-1 -> 0.45820177 | Z25: =(Z6/Y6)-1 -> -0.096912252 | AA25: =(AA6/Z6)-1 -> 0.0326338 | AC25: Profit/Loss before tax | AD25: =AD23+AD24 -> 3978.64 | AE25: =AE23+AE24 -> 4276.99 | AF25: =AF23+AF24 -> 5224.53 | AG25: =AG23+AG24 -> 6509.5 | AH25: =AH23+AH24 -> 10224.88 | AI25: =AI23+AI24 -> 10867.25
A26: Tax For Earlier Years | B26: 1.76 | C26: 1.01 | D26: 0 | E26: 10.6 | F26: 0.92 | H26: Total Tax Expenses | I26: 1314.56 | J26: 978.21 | K26: 808.87 | L26: 869.39 | M26: =SUM(M23:M25) -> 685.77 | V26: EPS | W26: =W22/'Company Basic info'!$E$15 -> 14.592349 | X26: =X22/'Company Basic info'!$E$15 -> 7.0319577 | Y26: =Y22/'Company Basic info'!$E$15 -> 13.638176 | Z26: =Z22/'Company Basic info'!$E$15 -> 9.6586503 | AA26: =AA22/'Company Basic info'!$E$15 -> 16.715316 | AC26: Tax expense
A27: Total Tax Expenses | B27: 615.95 | C27: 356.61 | D27: 186.22 | E27: =SUM(E24:E26) -> 150.35 | F27: =SUM(F24:F26) -> 351.67 | H27: Profit/Loss After Tax And Before Extraordinary Items | I27: 4020 | J27: 3006.67 | K27: 2348.93 | L27: 2065.42 | M27: =M21-M26 -> 1792.63 | P27: =P18+P13 -> 235.8136 | Q27: =Q18+Q13 -> 230.5678 | R27: =R18+R13 -> 265.6836 | S27: =S18+S13 -> 311.6986 | T27: =T18+T13 -> 492.4101 | AC27: Current tax | AD27: 1180 | AE27: 645 | AF27: 1900 | AG27: 2250 | AH27: 2905 | AI27: 2880
A28: Profit/Loss After Tax And Before Extraordinary Items | B28: 1845.43 | C28: 1072.72 | D28: 586.47 | E28: =E22-E27 -> 453.47 | F28: =F22-F27 -> 383.7 | H28: Profit/Loss From Continuing Operations | I28: 4020 | J28: 3006.67 | K28: 2348.93 | L28: 2065.42 | M28: =M27 -> 1792.63 | O28: EPS | P28: =P25/'Company Basic info'!$G$15 -> 14.271396 | Q28: =Q25/'Company Basic info'!$G$15 -> 13.397514 | R28: =R25/'Company Basic info'!$G$15 -> 16.54439 | S28: =S25/'Company Basic info'!$G$15 -> 19.914449 | T28: =T25/'Company Basic info'!$G$15 -> 31.188255 | AC28: Earlier year tax refund/liability | AD28: 0 | AE28: -49.33 | AF28: -1192.73 | AG28: -973.46 | AH28: 0 | AI28: -256.08
A29: Profit/Loss From Continuing Operations | B29: 1845.43 | C29: 1072.72 | D29: 586.47 | E29: =E28+60.39 -> 513.86 | F29: =F28+93.37 -> 477.07 | H29: Profit/Loss For The Period | I29: 4020 | J29: 3006.67 | K29: 2348.93 | L29: 2065.42 | M29: =M28+32.09 -> 1824.72 | AC29: Deferred tax | AD29: -84.01 | AE29: 442.26 | AF29: -562.62 | AG29: -594.77 | AH29: -301.07 | AI29: -120.71
A30: Profit/Loss For The Period | B30: 1845.43 | C30: 1072.72 | D30: 586.47 | E30: =E29 -> 513.86 | F30: =F29 -> 477.07 | AC30: Total tax expense | AD30: =SUM(AD27:AD29) -> 1095.99 | AE30: =SUM(AE27:AE29) -> 1037.93 | AF30: =SUM(AF27:AF29) -> 144.65 | AG30: =SUM(AG27:AG29) -> 681.77 | AH30: =SUM(AH27:AH29) -> 2603.93 | AI30: =SUM(AI27:AI29) -> 2503.21
H31: OTHER ADDITIONAL INFORMATION | AC31: Profit/loss for the period from Continuing operations | AD31: =AD25-AD30 -> 2882.65 | AE31: =AE25-AE30 -> 3239.06 | AF31: =AF25-AF30 -> 5079.88 | AG31: =AG25-AG30 -> 5827.73 | AH31: =AH25-AH30 -> 7620.95 | AI31: =AI25-AI30 -> 8364.04
A32: OTHER ADDITIONAL INFORMATION | H32: EARNINGS PER SHARE | AC32: Profit/Loss from discontinued operations | AD32: 0 | AE32: 0 | AF32: 0 | AG32: 0 | AH32: 0 | AI32: 0
A33: EARNINGS PER SHARE | H33: Basic EPS (Rs.) | I33: 5.5 | J33: 4.11 | K33: 9.64 | L33: 8.48 | M33: 7.49 | AC33: Tax expense of discontinued operations | AD33: 0 | AE33: 0 | AF33: 0 | AG33: 0 | AH33: 0 | AI33: 0
A34: Basic EPS (Rs.) | B34: 91.5 | C34: 53.19 | D34: 29.08 | E34: 23.78 | F34: 21.36 | H34: Diluted EPS (Rs.) | I34: 5.5 | J34: 4.11 | K34: 9.64 | L34: 8.48 | M34: 7.49 | AC34: Profit/loss from discontinued operations after tax | AD34: =AD32-AD33 -> 0 | AE34: =AE32-AE33 -> 0 | AF34: =AF32-AF33 -> 0 | AG34: =AG32-AG33 -> 0 | AH34: =AH32-AH33 -> 0 | AI34: =AI32-AI33 -> 0
A35: Diluted EPS (Rs.) | B35: 91.5 | C35: 53.19 | D35: 29.08 | E35: 23.78 | F35: 21.36 | AC35: Profit/Loss for the period | AD35: =AD31+AD34 -> 2882.65 | AE35: =AE31+AE34 -> 3239.06 | AF35: =AF31+AF34 -> 5079.88 | AG35: =AG31+AG34 -> 5827.73 | AH35: =AH31+AH34 -> 7620.95 | AI35: =AI31+AI34 -> 8364.04
I36: =I20+I15 -> 5341.58 | J36: =J20+J15 -> 3999.67 | K36: =K20+K15 -> 3162.65 | L36: =L20+L15 -> 2940.89 | M36: =M20+M15 -> 2482
A37: EBIT | B37: =B20+B14 -> 2466.5 | C37: =C20+C14 -> 1435.7 | D37: =D20+D14 -> 793.82 | E37: =E20+E14 -> 738.32 | F37: =F20+F14 -> 756.95 | AD37: =AD21+AD12 -> 4201.16 | AE37: =AE21+AE12 -> 4529.33 | AF37: =AF21+AF12 -> 5282.96 | AG37: =AG21+AG12 -> 6564.6 | AH37: =AH21+AH12 -> 10230.49 | AI37: =AI21+AI12 -> 10829.39
AC38: EPS | AD38: =AD35/'Company Basic info'!$F$15 -> 43.103435 | AE38: =AE35/'Company Basic info'!$F$15 -> 48.432731 | AF38: =AF35/'Company Basic info'!$F$15 -> 75.957983 | AG38: =AG35/'Company Basic info'!$F$15 -> 87.140369 | AH38: =AH35/'Company Basic info'!$F$15 -> 113.95387 | AI38: =AI35/'Company Basic info'!$F$15 -> 125.06508

Sheet Cash Flow Statement
A1: CASH FLOW STATEMENT | F1: #VALUE! | M1: #VALUE! | T1: #VALUE! | AA1: #VALUE! | AI1: #VALUE!
A2: Particulars | B2: 2020 | C2: 2021 | D2: 2022 | E2: 2023 | F2: 2024 | H2: Particulars | I2: Mar 20 | J2: Mar 21 | K2: Mar 22 | L2: Mar 23 | M2: Mar 24 | O2: Particulars | P2: 2020 | Q2: 2021 | R2: 2022 | S2: 2023 | T2: 2024 | V2: Particulars | W2: 2020 | X2: 2021 | Y2: 2022 | Z2: 2023 | AA2: 2024 | AC2: Particulars | AD2: 2020 | AE2: 2021 | AF2: 2022 | AG2: 2023 | AH2: 2024 | AI2: 2025
A3: CASH FLOW FROM OPERATING ACTIVITIES | H3: CASH FLOW FROM OPERATING ACTIVITIES | O3: Cash flow from Operating Activities | V3: Cash flow from Operating activities | AC3: Cash flow from Operating activities
A4: Profit after share of associate but before exceptional items and tax | B4: 2510.49 | C4: 2972.2 | D4: 3212 | E4: 3968.8 | F4: 5308.34 | H4: Profit before tax but after exceptional items | I4: 726.78 | J4: 603.82 | K4: 749.33 | L4: 1402.68 | M4: 2424.83 | O4: Profit before exceptional items and tax | P4: 742.454 | Q4: 340.8811 | R4: 743.4982 | S4: 481.8035 | T4: 828.2352 | V4: Profit before tax | W4: 223.871 | X4: 207.1174 | Y4: 257.2416 | Z4: 305.2179 | AA4: 480.9209 | AC4: Profit after tax | AD4: 2882.65 | AE4: 3239.06 | AF4: 5079.88 | AG4: 5827.73 | AH4: 7620.95 | AI4: 8364.05
A5: Adjustments for | H5: Ajustments for | O5: Adjustments for | V5: Adjustments for | AC5: Adjustments for
A6: Depreciation and ammortization expense | B6: 371.86 | C6: 387.32 | D6: 401.13 | E6: 428.82 | F6: 443.2 | H6: Plus: Non cash expenditure and non operating expenses | O6: Depreciation and amoritsation expense | P6: 96.4384 | Q6: 94.5384 | R6: 90.3547 | S6: 77.2579 | T6: 67.0392 | V6: Interest income | W6: -203.9684 | X6: -152.6823 | Y6: -130.19 | Z6: -178.34 | AA6: -271.3547 | AC6: Income tax expense | AD6: 1095.99 | AE6: 1037.93 | AF6: 144.65 | AG6: 681.77 | AH6: 2603.93 | AI6: 2503.21
A7: Provision for doubtful advances | B7: 0 | C7: 0 | D7: 0 | E7: -2.6 | F7: 19.13 | H7: Depreciation / Ammortization | I7: 71.14 | J7: 71.08 | K7: 74.51 | L7: 75.58 | M7: 83.13 | O7: Finance costs | P7: 4.6557 | Q7: 3.9128 | R7: 3.4243 | S7: 4.5364 | T7: 3.1052 | V7: Unrealised fair value gain (net) | W7: -6.9694 | X7: -3.1796 | Y7: -4.217 | Z7: -2.6817 | AA7: -5.727 | AC7: Gain/loss on sale of PPE | AD7: -0.23 | AE7: -0.12 | AF7: -1.57 | AG7: -3.18 | AH7: -5.9 | AI7: -1.88
A8: Provision for performance warranty | B8: 0 | C8: 0 | D8: 0 | E8: 32.15 | F8: 168.52 | H8: Finance cost | I8: 9.26 | J8: 8.36 | K8: 7.16 | L8: 6.37 | M8: 5.12 | O8: Interest income | P8: -53.934 | Q8: -56.2886 | R8: -63.7516 | S8: -111.7617 | T8: -319.0637 | V8: Actuarial Gain/loss on remeasurements of defined benefit plan | W8: 4.751 | X8: 3.5552 | Y8: 1.123 | Z8: 0.5433 | AA8: 1.0975 | AC8: Finance cost | AD8: 348.46 | AE8: 259.17 | AF8: 55.86 | AG8: 25.82 | AH8: 31.41 | AI8: 8.68
A9: Provision for onerous contract | B9: 0 | C9: 0 | D9: 0 | E9: 18.44 | F9: 31.32 | H9: Ammortization of prepaid rentals | I9: 0.15 | J9: 0.15 | K9: 0.15 | L9: 0.15 | M9: 0.15 | O9: Profit on sale of PPE | P9: 0.0062 | Q9: -0.1029 | R9: 0.009 | S9: -0.1006 | T9: 0.0624 | V9: Depreciation and amortisation expense | W9: 30.0892 | X9: 29.0876 | Y9: 36.296 | Z9: 39.1663 | AA9: 41.3266 | AC9: Interest income | AD9: -66.29 | AE9: -89.23 | AF9: -687.69 | AG9: -1499.13 | AH9: -1634.43 | AI9: -2287.44
H10: Forex variation | I10: 0 | J10: 0 | K10: 0 | L10: -0.1 | M10: 0.02 | O10: Deferred revenue on customer provided assets | P10: -13.0684 | Q10: -13.4462 | R10: -26.5432 | S10: -10.2106 | T10: -8.2889 | V10: Retirement/write off of assets-net | W10: -1.1053 | X10: -1.5397 | Y10: -0.2822 | Z10: -0.2448 | AA10: 3.0643 | AC10: Share of Profit/Loss of Joint venture | AD10: -7.02 | AE10: -4.81 | AF10: 0.23 | AG10: -2.87 | AH10: -26.5 | AI10: -40.65
A11: Provision for obselete / redundant materials | B11: 0 | C11: 0 | D11: 0 | E11: 177.21 | F11: 72.35 | H11: (-) Non Operating income | O11: Provision for expenses | P11: 21.0192 | Q11: 10.95 | R11: 104.8495 | S11: 26.2219 | T11: 25.3708 | V11: Finance cost | W11: 1.3356 | X11: 2.701 | Y11: 0.7641 | Z11: 6.4807 | AA11: 11.4892 | AC11: Other adjustments | AD11: 0.22 | AE11: -0.14 | AF11: 0.19 | AG11: -0.25 | AH11: 0.45 | AI11: 0.34
A12: Provision for doubtful debts, liquidated damages, customer's claims and disallowances | B12: 0 | C12: 0 | D12: 0 | E12: 375.36 | F12: 831.18 | H12: Profit/Loss on sale of fixed assets | I12: 2.03 | J12: 0 | K12: 2.56 | L12: -0.9 | M12: -1.48 | O12: Liabilities/provisions no required written back | P12: -8.4491 | Q12: -8.2125 | R12: -23.6508 | S12: -9.5993 | T12: -0.1058 | V12: Unrealised loss/gain on foreign exchange fluctuation | W12: -0.2459 | X12: -0.8647 | Y12: -0.449 | Z12: 3.5268 | AA12: 2.5971 | AC12: Net gain/loss on fair value adjustments | AD12: 0.37 | AE12: 0.64 | AF12: 3.13 | AG12: -2.91 | AH12: 2.21 | AI12: -1.68
A13: Provision for intangible assets under development | B13: 0 | C13: 72.13 | D13: 0 | E13: 5.44 | F13: 96.66 | H13: Interest income | I13: -527.78 | J13: -368.24 | K13: -347.48 | L13: -601.77 | M13: -994.41 | O13: Fair value adjustment to investment carried at fair value through P&L | P13: -1.6128 | Q13: -2.0062 | R13: 3.1758 | S13: 1.3024 | T13: -1.2544 | V13: Liquidated damages written back | W13: 0 | X13: -3.397 | Y13: 0 | Z13: -8.4707 | AA13: -6.7567 | AC13: Depreciation, amortisation and impairment expense | AD13: 1030.31 | AE13: 1242.13 | AF13: 1286.96 | AG13: 2382.1 | AH13: 1422.12 | AI13: 1362.67
A14: Intangible assets under development charged off | B14: 0 | C14: 0.75 | D14: 0 | E14: 19.5 | F14: 0 | H14: Ammortization gain on deferred depsoits of vendors | I14: -0.14 | J14: -0.09 | K14: -0.07 | L14: -0.05 | M14: -0.04 | O14: Gain on sale of financial assets measured at fair value through P&L | P14: 0 | Q14: 0 | R14: 0 | S14: 0 | T14: 0 | V14: Liabilities no longer required written back | W14: -6.3903 | X14: 8.9493 | Y14: -6.5455 | Z14: 0 | AA14: 0 | AC14: Reversal of provision for impairment in value of investments | AD14: 1.33 | AE14: 0.25 | AF14: 0.86 | AG14: 0.03 | AH14: 0 | AI14: -7.83
A15: Provision for impairement of capital work in progress | B15: 0 | C15: 14.68 | D15: 0 | E15: 0 | F15: 0 | H15: Ammortization of deferred revenue | I15: -8.07 | J15: -8.04 | K15: -7.63 | L15: -6.87 | M15: -6.87 | O15: Operating profit before working capital changes | P15: =SUM(P4,P6:P14) -> 787.5092 | Q15: =SUM(Q4,Q6:Q14) -> 370.2259 | R15: =SUM(R4,R6:R14) -> 831.3659 | S15: =SUM(S4,S6:S14) -> 459.4499 | T15: =SUM(T4,T6:T14) -> 595.1 | V15: Operating profit before working capital changes | W15: =SUM(W4,W6:W14) -> 41.3675 | X15: =SUM(X4,X6:X14) -> 89.7472 | Y15: =SUM(Y4,Y6:Y14) -> 153.741 | Z15: =SUM(Z4,Z6:Z14) -> 165.1978 | AA15: =SUM(AA4,AA6:AA14) -> 256.6572 | AC15: Provision for doubtful debts | AD15: 37.67 | AE15: 14.26 | AF15: 1054.18 | AG15: 104.16 | AH15: 35.34 | AI15: 0.83
A16: Contract costs charged off | B16: 12.47 | C16: 0 | D16: 0 | E16: 41.8 | F16: 0.02 | H16: Interest income on deferred payment liability to foreign supplier | I16: -3.74 | J16: -3.71 | K16: -3.98 | L16: -4.74 | M16: -4.33 | O16: Changes in working capital | V16: Adjustments for: | AC16: Provision for doubtful contract assets | AD16: 33.42 | AE16: 29.55 | AF16: 67.77 | AG16: 26.78 | AH16: 23.86 | AI16: 150.1
A17: Corporate Social responsibility | B17: 31.17 | C17: 47.11 | D17: 53.48 | E17: 0 | F17: 0 | H17: Interest income deferred deposit with MbPT | I17: -0.19 | J17: -0.2 | K17: -0.22 | L17: -0.23 | M17: -0.25 | O17: Adjustments for | V17: Increase/decrease in trade and other receivables | W17: -303.5833 | X17: 360.3222 | Y17: 27.4111 | Z17: 100.8141 | AA17: -140.811 | AC17: Provision for doubtful claims | AD17: 463.28 | AE17: 211.75 | AF17: 787.29 | AG17: 2450.52 | AH17: 38.98 | AI17: 4.09
A18: Transfer from government grants | B18: -19.98 | C18: -17.36 | D18: -17.13 | E18: -16.55 | F18: -16.57 | H18: Operating profit before working capital changes | I18: =SUM(I4:I17) -> 269.44 | J18: =SUM(J4:J17) -> 303.13 | K18: =SUM(K4:K17) -> 474.33 | L18: =SUM(L4:L17) -> 870.12 | M18: =SUM(M4:M17) -> 1505.87 | O18: Trade receivables | P18: 187.5571 | Q18: 15.6753 | R18: 18.5313 | S18: 119.5886 | T18: -125.8745 | V18: Increase/decrease in other financial assets | W18: 334.8856 | X18: -554.4276 | Y18: -430.42 | Z18: 944.1095 | AA18: 12.1574 | AC18: Provision for doubtful advances | AD18: 213.84 | AE18: 325.61 | AF18: 515.44 | AG18: 439.01 | AH18: 10.15 | AI18: 2.4
A19: Interest income | B19: -70.58 | C19: -60.5 | D19: -176.45 | E19: -260.88 | F19: -571.95 | H19: Movement in working capital | O19: Loans | P19: 0.0654 | Q19: 0.8848 | R19: 0.614 | S19: 0.1141 | T19: 0.0595 | V19: Increase/decrease in other non current assets | W19: -15.5191 | X19: 24.9901 | Y19: -34.3547 | Z19: -51.9615 | AA19: 7.3778 | AC19: Provision for replacement and other charges | AD19: 182.13 | AE19: 430.09 | AF19: 0 | AG19: 0 | AH19: 1166.11 | AI19: 1263.73
A20: Interest on lease liability | B20: 0.28 | C20: 0.24 | D20: 3.06 | E20: 3.7 | F20: 4.21 | H20: Decrease / Increase in inventories | I20: -832.4 | J20: -1265.92 | K20: -1811.49 | L20: 343.24 | M20: 1643.49 | O20: Other financial assets | P20: -978.3477 | Q20: 1206.397 | R20: -69.6539 | S20: -95.8605 | T20: 390.8946 | V20: Increase/decrease in other current assets | W20: -396.6191 | X20: -302.0348 | Y20: -360.144 | Z20: -580.3385 | AA20: 876.4143 | AC20: Provision for warranty | AD20: 521.6 | AE20: 438.75 | AF20: 0 | AG20: 0 | AH20: 324.25 | AI20: 370.15
A21: Finance cost | B21: 3.32 | C21: 6.13 | D21: 1.99 | E21: 11.25 | F21: 2.93 | H21: Decrease / Increase in trade receivables and loans and advances | I21: 46.11 | J21: 470.75 | K21: -37.56 | L21: 7.76 | M21: -859.65 | O21: Inventories | P21: 797.7006 | Q21: -544.0886 | R21: -261.412 | S21: -179.51 | T21: -163.1565 | V21: Increase/decrease in assets held for sale | W21: -0.0973 | X21: 0.0943 | Y21: -0.0248 | Z21: 0.3797 | AA21: -0.0809 | AC21: Provision for raw materials and components | AD21: -207.21 | AE21: -321.83 | AF21: 560.05 | AG21: 281.4 | AH21: 1001.64 | AI21: 76.78
A22: Profit on sale of property, plant and equipment | B22: -0.21 | C22: -1.21 | D22: -0.45 | E22: -1.52 | F22: -7.02 | H22: Decrease / Increase Other current and non-current assets | I22: 387.03 | J22: -3136.06 | K22: -2489.61 | L22: 1808.26 | M22: 565.9 | O22: Other assets | P22: 18.7543 | Q22: -106.8408 | R22: 15.6874 | S22: 53.3272 | T22: -1318.6308 | V22: Increase/decrease in Inventories | W22: -91.4531 | X22: -346.8523 | Y22: -384.3935 | Z22: -1746.2369 | AA22: -1065.9365 | AC22: Provision for liquidated damages | AD22: 0 | AE22: 0 | AF22: 743.95 | AG22: 422.9 | AH22: 702.71 | AI22: 658.43
A23: Operating Profit before working capital changes | B23: =SUM(B4:B22) -> 2838.82 | C23: =SUM(C4:C22) -> 3421.49 | D23: =SUM(D4:D22) -> 3477.63 | E23: =SUM(E4:E22) -> 4800.92 | F23: =SUM(F4:F22) -> 6382.32 | H23: Decrease / Increase in trade payables and provisions | I23: 1829.63 | J23: 1106.34 | K23: -528.66 | L23: -1801.94 | M23: 24.44 | O23: Adjustments for increase/decrease in operating liabilities | V23: Increase/decrease in Trade payables | W23: 173.1744 | X23: 235.288 | Y23: -362.1053 | Z23: 761.4678 | AA23: -180.3596 | AC23: Operating profit before working capital changes | AD23: =SUM(AD4,AD6:AD22) -> 6530.52 | AE23: =SUM(AE4,AE6:AE22) -> 6813.06 | AF23: =SUM(AF4,AF6:AF22) -> 9611.18 | AG23: =SUM(AG4,AG6:AG22) -> 11133.88 | AH23: =SUM(AH4,AH6:AH22) -> 13317.28 | AI23: =SUM(AI4,AI6:AI22) -> 12425.98
A24: Increase/ Decrease in | H24: Decrease / Increase in other current and non-current liabilities | I24: -1587.2 | J24: 2746.65 | K24: 4532.81 | L24: 600.31 | M24: -1519.14 | O24: Trade payables | P24: -173.9719 | Q24: 397.1158 | R24: -190.1313 | S24: -88.0915 | T24: 334.0088 | V24: Increase/decrease in provisions | W24: 22.3954 | X24: 10.0196 | Y24: 16.897 | Z24: -124.9321 | AA24: 18.6783 | AC24: Adjustments for
A25: Trade Receivables | B25: -1350.35 | C25: 162.03 | D25: 453.9 | E25: -1300.75 | F25: -1190.08 | H25: Cash flow from operations | I25: =I18+SUM(I20:I24) -> 112.61 | J25: =J18+SUM(J20:J24) -> 224.89 | K25: =K18+SUM(K20:K24) -> 139.82 | L25: =L18+SUM(L20:L24) -> 1827.75 | M25: =M18+SUM(M20:M24) -> 1360.91 | O25: Other financial liabilities | P25: 41.601 | Q25: -22.5313 | R25: 26.8995 | S25: 17.3623 | T25: 123.7122 | V25: Increase/decrease in other financial liabilities | W25: 2.7395 | X25: -0.2519 | Y25: 1.5911 | Z25: 3.8624 | AA25: 4.8229 | AC25: Increase/decrease in trade receivables | AD25: -1883.81 | AE25: 5078.18 | AF25: 611.37 | AG25: -1749.45 | AH25: -2474.43 | AI25: -4177.07
A26: Loans | B26: -5.97 | C26: 40.79 | D26: 0.12 | E26: 0.48 | F26: -0.16 | H26: Direct tax paid | I26: -208.15 | J26: -156.68 | K26: -302.45 | L26: -312.15 | M26: -677.16 | O26: Other liabilities | P26: 51.4426 | Q26: -88.0383 | R26: 364.0412 | S26: 2079.5551 | T26: 748.8828 | V26: Increase/decrease in other current liabilities | W26: 737.6515 | X26: 1058.0822 | Y26: 1078.132 | Z26: 2051.2272 | AA26: -371.625 | AC26: Increase/decrease in Loans, Financial assets and other assets | AD26: -30.02 | AE26: -217.4 | AF26: -1351.44 | AG26: -1624.92 | AH26: -1361.94 | AI26: -2620.31
A27: Other financial assets | B27: 4.21 | C27: -27.13 | D27: -34.56 | E27: -111.37 | F27: 45.65 | H27: Net cash from / used in Operating activities | I27: =I25+I26 -> -95.54 | J27: =J25+J26 -> 68.21 | K27: =K25+K26 -> -162.63 | L27: =L25+L26 -> 1515.6 | M27: =M25+M26 -> 683.75 | O27: Provisions | P27: -54.4451 | Q27: -82.9644 | R27: -2.8596 | S27: -14.9568 | T27: -17.311 | V27: Increase/decrease in other non-current liabilities | W27: -1.6875 | X27: -4.0291 | Y27: 5.2726 | Z27: 3.7377 | AA27: -0.5351 | AC27: Increase/decrease in Inventories | AD27: 46.23 | AE27: 2461.04 | AF27: 1765.67 | AG27: 1917.19 | AH27: -2070.49 | AI27: -8534.94
A28: Other assets | B28: -1365.28 | C28: -902.72 | D28: -1154.59 | E28: 140.44 | F28: 592.55 | H28: CASH FLOW FROM INVESTING ACTIVITIES | O28: Cash generated from operations | P28: =SUM(P15,P18:P22,P24:P27) -> 677.8655 | Q28: =SUM(Q15,Q18:Q22,Q24:Q27) -> 1145.8354 | R28: =SUM(R15,R18:R22,R24:R27) -> 733.0825 | S28: =SUM(S15,S18:S22,S24:S27) -> 2350.9784 | T28: =SUM(T15,T18:T22,T24:T27) -> 567.6851 | V28: Cash generated from/used in operations | W28: =SUM(W17:W27,W15) -> 503.2545 | X28: =SUM(X17:X27,X15) -> 570.9479 | Y28: =SUM(Y17:Y27,Y15) -> -288.3975 | Z28: =SUM(Z17:Z27,Z15) -> 1527.3272 | AA28: =SUM(AA17:AA27,AA15) -> -583.2402 | AC28: Increase/decrease in trade payables | AD28: 1454.5 | AE28: -1842.72 | AF28: 302.01 | AG28: 577.36 | AH28: 277.9 | AI28: 1692.8
A29: Inventories | B29: 473.64 | C29: -996.51 | D29: -611.88 | E29: -1011.88 | F29: -1065.33 | H29: Purchase of property, plant and equipment | I29: -109.5 | J29: -41.9 | K29: -32.01 | L29: -135.57 | M29: 103.03 | O29: Income tax paid | P29: -173.6441 | Q29: -77.8224 | R29: -203.4235 | S29: -218.1218 | T29: -155.9665 | V29: Taxes paid | W29: 124.5821 | X29: -53.6462 | Y29: -67.7148 | Z29: -77.0939 | AA29: -123.6532 | AC29: Increase/decrease in financial liabilities, provisions and other liabilities | AD29: -2770.13 | AE29: 3689.14 | AF29: 261.79 | AG29: 1331.36 | AH29: 2503.83 | AI29: 18395.15
A30: Trade payables | B30: 1016.02 | C30: 848.86 | D30: 70.45 | E30: -38.89 | F30: 375.56 | H30: Capital work in progress | I30: 8.81 | J30: -0.19 | K30: -6.79 | L30: 25.32 | M30: -10.01 | O30: Net cash flow before exceptional items | P30: =P28+P29 -> 504.2214 | Q30: =Q28+Q29 -> 1068.013 | R30: =R28+R29 -> 529.659 | S30: =S28+S29 -> 2132.8566 | T30: =T28+T29 -> 411.7186 | V30: Net cash from/used in operating activities | W30: =W28+W29 -> 627.8366 | X30: =X28+X29 -> 517.3017 | Y30: =Y28+Y29 -> -356.1123 | Z30: =Z28+Z29 -> 1450.2333 | AA30: =AA28+AA29 -> -706.8934 | AC30: Cash generated from Operations | AD30: =SUM(AD25:AD29,AD23) -> 3347.29 | AE30: =SUM(AE25:AE29,AE23) -> 15981.3 | AF30: =SUM(AF25:AF29,AF23) -> 11200.58 | AG30: =SUM(AG25:AG29,AG23) -> 11585.42 | AH30: =SUM(AH25:AH29,AH23) -> 10192.15 | AI30: =SUM(AI25:AI29,AI23) -> 17181.61
A31: Other financial liabilities | B31: -99.25 | C31: 78.91 | D31: 60.93 | E31: 327.16 | F31: 33.51 | H31: Proceeds from sale of property, plant and equipment | I31: 0.17 | J31: 0.16 | K31: 1.27 | L31: 1.31 | M31: 1.66 | O31: Exceptional items | P31: 0 | Q31: 0 | R31: 0 | S31: 0 | T31: 0 | V31: Cash flow from Investing activities | AC31: Income tax paid | AD31: -1819.9 | AE31: -718.58 | AF31: -1027.45 | AG31: -2755.7 | AH31: -1969.33 | AI31: -3538.15
A32: Provisions | B32: 33.04 | C32: 146.5 | D32: 267.55 | E32: -1029.41 | F32: -86.94 | H32: Capital advance | I32: -1.01 | J32: 1.03 | K32: -2.39 | L32: -5.26 | M32: -431.17 | O32: Net cash from/used in operating activities | P32: =P30+P31 -> 504.2214 | Q32: =Q30+Q31 -> 1068.013 | R32: =R30+R31 -> 529.659 | S32: =S30+S31 -> 2132.8566 | T32: =T30+T31 -> 411.7186 | V32: Purchase of PPE | W32: -67.3676 | X32: -163.844 | Y32: -54.8278 | Z32: -42.2584 | AA32: -48.0691 | AC32: Net cash used in/generated from Operating activities | AD32: =AD30+AD31 -> 1527.39 | AE32: =AE30+AE31 -> 15262.72 | AF32: =AF30+AF31 -> 10173.13 | AG32: =AG30+AG31 -> 8829.72 | AH32: =AH30+AH31 -> 8222.82 | AI32: =AI30+AI31 -> 13643.46
A33: Other liabilities | B33: 1758.8 | C33: 2977.06 | D33: 2606.11 | E33: 489.99 | F33: 990.78 | H33: Interest received | I33: 527.78 | J33: 368.24 | K33: 347.48 | L33: 601.77 | M33: 994.41 | O33: Cash Flow from Investing activities | V33: Investments in Mutual fund (net) | W33: -51.8494 | X33: -771.8153 | Y33: 629.1414 | Z33: -36.5728 | AA33: 233.664 | AC33: Cash flow from Investing activities
A34: Current tax asstes | B34: -159.03 | C34: -122.99 | D34: -124.15 | E34: 0 | F34: 0 | H34: Dividend received | I34: 31.33 | J34: 26.1 | K34: 23.36 | L34: 26.65 | M34: 36.55 | O34: Purchase of PPE | P34: -56.8884 | Q34: -56.6091 | R34: -102.0442 | S34: -108.2571 | T34: -80.8897 | V34: Investments in fixed deposits (net) | W34: 249.7652 | X34: -389.7576 | Y34: -276.1749 | Z34: -1765.7944 | AA34: 598.7523 | AC34: Purchase of PPE | AD34: -890.23 | AE34: -762.98 | AF34: -799.29 | AG34: -782.42 | AH34: -916.42 | AI34: -930.09
H35: Fixed deposits / Term deposits | I35: 0 | J35: 0 | K35: 0 | L35: -658 | M35: 731.85 | O35: Bank deposits | P35: -11.654 | Q35: -738.038 | R35: -530.452 | S35: -1171.49 | T35: -828.66 | V35: Interest received | W35: 114.4014 | X35: 152.6823 | Y35: 130.19 | Z35: 178.34 | AA35: 271.3547 | AC35: Purchase of Intangible assets | AD35: -490.49 | AE35: -554.3 | AF35: -701.28 | AG35: -998.8 | AH35: -838.75 | AI35: -826.83
A36: Cash generated from Operations | B36: =B23+SUM(B25:B34) -> 3144.65 | C36: =C23+SUM(C25:C34) -> 5626.29 | D36: =D23+SUM(D25:D34) -> 5011.51 | E36: =E23+SUM(E25:E34) -> 2266.69 | F36: =F23+SUM(F25:F34) -> 6077.86 | H36: Principal portion of lease payments | I36: -3.86 | J36: -5.19 | K36: -4.52 | L36: -5.88 | M36: -6.51 | O36: Proceeds from sale of PPE | P36: 0.0036 | Q36: 0.1121 | R36: 0.0045 | S36: 0.1936 | T36: 0.1747 | V36: Net cash from/used in investing activities | W36: =SUM(W32:W35) -> 244.9496 | X36: =SUM(X32:X35) -> -1172.7346 | Y36: =SUM(Y32:Y35) -> 428.3287 | Z36: =SUM(Z32:Z35) -> -1666.2856 | AA36: =SUM(AA32:AA35) -> 1055.7019 | AC36: Proceeds from sale of PPE | AD36: 1.57 | AE36: 1.23 | AF36: 3.17 | AG36: 5.06 | AH36: 7.97 | AI36: 3.35
A37: Income taxes paid (net) | B37: -574.24 | C37: -533.07 | D37: -804.29 | E37: -1067.33 | F37: -1418.37 | H37: Net cash from / used in Investing activities | I37: =SUM(I29:I36) -> 453.72 | J37: =SUM(J29:J36) -> 348.25 | K37: =SUM(K29:K36) -> 326.4 | L37: =SUM(L29:L36) -> -149.66 | M37: =SUM(M29:M36) -> 1419.81 | O37: Redemption/Investments in mutual funds during the year | P37: 0 | Q37: 0 | R37: 0 | S37: 0 | T37: 0 | V37: Cash flow from financing activities | AC37: Investment in joint ventures | AD37: -1 | AE37: 0 | AF37: -10 | AG37: 0 | AH37: -10.5 | AI37: -12.89
A38: Cash flow before Expectional items | B38: =B36+B37 -> 2570.41 | C38: =C36+C37 -> 5093.22 | D38: =D36+D37 -> 4207.22 | E38: =E36+E37 -> 1199.36 | F38: =F36+F37 -> 4659.49 | H38: CASH FLOW FROM FINANCING ACTIVITIES | O38: Gain on sale of financial assets measured at fair value through P&L | P38: 0 | Q38: 0 | R38: 0 | S38: 0 | T38: 0 | V38: Interest and other borrowing cost paid | W38: -1.5849 | X38: -2.3371 | Y38: -0.1379 | Z38: -4.4206 | AA38: -10.6224 | AC38: Purchase of other non current investments | AD38: -75.92 | AE38: -61.29 | AF38: -234.55 | AG38: -94.68 | AH38: -100.1 | AI38: -106.9
A39: Exceptional items | B39: 0 | C39: 0 | D39: 0 | E39: 0 | F39: 0 | H39: Buy back of equity share capital | I39: -277.88 | J39: 0 | K39: 0 | L39: 0 | M39: 0 | O39: Interest received | P39: 35.3625 | Q39: 60.751 | R39: 59.48 | S39: 108.52 | T39: 186.9702 | V39: Principal component of lease rent | W39: -1.0712 | X39: -1.6332 | Y39: -1.1835 | Z39: -1.6253 | AA39: -1.704 | AC39: Investment in short term deposits | AD39: 59.55 | AE39: 6.04 | AF39: -11246.15 | AG39: -4598.49 | AH39: -6301.08 | AI39: -11456.78
A40: Net cash from/used in operating activities | B40: =B38+B39 -> 2570.41 | C40: =C38+C39 -> 5093.22 | D40: =D38+D39 -> 4207.22 | E40: =E38+E39 -> 1199.36 | F40: =F38+F39 -> 4659.49 | H40: Payment of buy back tax | I40: -59.52 | J40: 0 | K40: 0 | L40: 0 | M40: 0 | O40: Net cash from/used in investing activities | P40: =SUM(P34:P39) -> -33.1763 | Q40: =SUM(Q34:Q39) -> -733.784 | R40: =SUM(R34:R39) -> -573.0117 | S40: =SUM(S34:S39) -> -1171.0335 | T40: =SUM(T34:T39) -> -722.4048 | V40: Interest component of lease rent | W40: -0.4782 | X40: -0.3639 | Y40: -0.6262 | Z40: -0.888 | AA40: -0.8541 | AC40: Interest received | AD40: 66.29 | AE40: 89.23 | AF40: 200.91 | AG40: 738.91 | AH40: 1745.88 | AI40: 2554.55
A41: CASH FLOW FROM INVESTING ACTIVITIES | H41: Dividend paid | I41: -261.8 | J41: -155.28 | K41: -180.11 | L41: -216.42 | M41: -447.75 | O41: Cash flow from Financing activities | V41: Borrowings | W41: 0 | X41: 0 | Y41: 0 | Z41: 299.9997 | AA41: -245.5997 | AC41: Dividend received from Joint ventures | AD41: 1.35 | AE41: 1.11 | AF41: 1.96 | AG41: 2.4 | AH41: 2.95 | AI41: 4.91
A42: Purchase of property, plant & equipment and other tangible assets | B42: -762.2 | C42: -469.25 | D42: -554.56 | E42: -590.45 | F42: -652.53 | H42: Finance cost - Lease | I42: -5.04 | J42: -4.55 | K42: -3.1 | L42: -1.55 | M42: -0.75 | O42: Proceeds from issue of equity shares | P42: 0 | Q42: 0 | R42: 0 | S42: 0 | T42: 0 | V42: Dividend paid | W42: -70.4302 | X42: -16.0373 | Y42: -13.1735 | Z42: -9.7369 | AA42: -8.0186 | AC42: Share application money paid | AD42: -10 | AE42: 10 | AF42: 0 | AG42: 0 | AH42: 0 | AI42: -0.41
A43: Less: Receipt of grant | B43: 15.62 | C43: 0 | D43: 0 | E43: 2.28 | F43: 0.1 | H43: Finance cost - Othes | I43: -0.34 | J43: 0 | K43: 0 | L43: -0.02 | M43: 0 | O43: Finance costs | P43: -3.2655 | Q43: -2.5226 | R43: -2.0341 | S43: -3.1463 | T43: -1.715 | V43: Interim dividend | W43: -79.2685 | X43: -44.1025 | Y43: -56.7032 | Z43: -63.0036 | AA43: -90.7252 | AC43: Net cash used in/generated from Investing activities | AD43: =SUM(AD34:AD42) -> -1338.88 | AE43: =SUM(AE34:AE42) -> -1270.96 | AF43: =SUM(AF34:AF42) -> -12785.23 | AG43: =SUM(AG34:AG42) -> -5728.02 | AH43: =SUM(AH34:AH42) -> -6410.05 | AI43: =SUM(AI34:AI42) -> -10771.09
A44: Purchase of property, plant & equipment and other tangible assets (net) | B44: =B42+B43 -> -746.58 | C44: =C42+C43 -> -469.25 | D44: =D42+D43 -> -554.56 | E44: =E42+E43 -> -588.17 | F44: =F42+F43 -> -652.43 | H44: Net cash from / used in Financing activities | I44: =SUM(I39:I43) -> -604.58 | J44: =SUM(J39:J43) -> -159.83 | K44: =SUM(K39:K43) -> -183.21 | L44: =SUM(L39:L43) -> -217.99 | M44: =SUM(M39:M43) -> -448.5 | O44: Repayment of lease liabilities | P44: -0.9472 | Q44: -1.061 | R44: -1.1848 | S44: -1.3196 | T44: -1.4664 | V44: Net cash from/used in financing activities | W44: =SUM(W38:W43) -> -152.833 | X44: =SUM(X38:X43) -> -64.474 | Y44: =SUM(Y38:Y43) -> -71.8243 | Z44: =SUM(Z38:Z43) -> 220.3253 | AA44: =SUM(AA38:AA43) -> -357.524 | AC44: Cash flow from Financing activities
A45: Proceeds from sale of property, plant & equipment | B45: 0.86 | C45: 1.33 | D45: 7.4 | E45: 1.7 | F45: 8.53 | H45: Net increase / decrease in cash and cash equivalents | I45: =I27+I37+I44 -> -246.4 | J45: =J27+J37+J44 -> 256.63 | K45: =K27+K37+K44 -> -19.44 | L45: =L27+L37+L44 -> 1147.95 | M45: =M27+M37+M44 -> 1655.06 | O45: Dividends paid | P45: -186.6592 | Q45: -169.0572 | R45: -145.3006 | S45: -166.9166 | T45: -145.1741 | V45: Net increase/decrease in cash and cash equivalents | W45: =W30+W36+W44 -> 719.9532 | X45: =X30+X36+X44 -> -719.9069 | Y45: =Y30+Y36+Y44 -> 0.3921 | Z45: =Z30+Z36+Z44 -> 4.273 | AA45: =AA30+AA36+AA44 -> -8.7155 | AC45: Repayment of Borrowings-current (net) | AD45: 1752.67 | AE45: -5859.8 | AF45: -9.07 | AG45: 0 | AH45: -0.31 | AI45: -0.02
A46: Increase/decrease in term deposits & other bank balances | B46: 172.3 | C46: -1992.23 | D46: -4234.8 | E46: 2094.39 | F46: -5690.04 | H46: Cash and cash equivalents at the beginning of the period | I46: 729.68 | J46: 483.28 | K46: 739.91 | L46: 720.47 | M46: 1868.42 | O46: Net cash from/used in financing activities | P46: =SUM(P42:P45) -> -190.8719 | Q46: =SUM(Q42:Q45) -> -172.6408 | R46: =SUM(R42:R45) -> -148.5195 | S46: =SUM(S42:S45) -> -171.3825 | T46: =SUM(T42:T45) -> -148.3555 | V46: Opening cash balance | W46: 9.2743 | X46: =W47 -> 729.2275 | Y46: =X47 -> 9.3206 | Z46: =Y47 -> 9.7127 | AA46: =Z47 -> 13.9857 | AC46: Payment of lease liabilities | AD46: -0.06 | AE46: -2.97 | AF46: -0.07 | AG46: -3.68 | AH46: -25.65 | AI46: -37.14
A47: Other investments | B47: -146.12 | C47: -195.57 | D47: -266.15 | E47: 922.04 | F47: -32.51 | H47: Cash and cash equivalents at the end of the period | I47: =I45+I46 -> 483.28 | J47: =J45+J46 -> 739.91 | K47: =K45+K46 -> 720.47 | L47: =L45+L46 -> 1868.42 | M47: =M45+M46 -> 3523.48 | O47: Net increase/decrease in cash and cash equivalents | P47: =P32+P40+P46 -> 280.1732 | Q47: =Q32+Q40+Q46 -> 161.5882 | R47: =R32+R40+R46 -> -191.8722 | S47: =S32+S40+S46 -> 790.4406 | T47: =T32+T40+T46 -> -459.0417 | V47: Closing cash balance | W47: =W45+W46 -> 729.2275 | X47: =X45+X46 -> 9.3206 | Y47: =Y45+Y46 -> 9.7127 | Z47: =Z45+Z46 -> 13.9857 | AA47: =AA45+AA46 -> 5.2702 | AC47: Interest paid | AD47: -348.29 | AE47: -259 | AF47: -116.99 | AG47: -55.68 | AH47: 0 | AI47: 0
A48: Interest received | B48: 70.58 | C48: 60.5 | D48: 176.45 | E48: 277.69 | F48: 442.6 | O48: Cash and cash equivalents at the beginning of the year | P48: 15.1552 | Q48: =P49 -> 295.3284 | R48: =Q49 -> 456.9166 | S48: =R49 -> 265.0444 | T48: =S49 -> 1055.485 | AC48: Dividend paid | AD48: -1340.38 | AE48: -1003.16 | AF48: -1337.55 | AG48: -1671.94 | AH48: -1972.89 | AI48: -2541.35
A49: Net cash from/used in Investing activities | B49: =SUM(B44:B48) -> -648.96 | C49: =SUM(C44:C48) -> -2595.22 | D49: =SUM(D44:D48) -> -4871.66 | E49: =SUM(E44:E48) -> 2707.65 | F49: =SUM(F44:F48) -> -5923.85 | H49: CapEx | I49: =ABS(I29) -> 109.5 | J49: =ABS(J29) -> 41.9 | K49: =ABS(K29) -> 32.01 | L49: =ABS(L29) -> 135.57 | M49: =ABS(M29) -> 103.03 | O49: Cash and cash equivalents at the end of the year | P49: =P47+P48 -> 295.3284 | Q49: =Q47+Q48 -> 456.9166 | R49: =R47+R48 -> 265.0444 | S49: =S47+S48 -> 1055.485 | T49: =T47+T48 -> 596.4433 | V49: DPS | W49: =ABS(SUM(W42:W43))/'Company Basic info'!$G$15 -> 13.068187 | X49: =ABS(SUM(X42:X43))/'Company Basic info'!$G$15 -> 5.25 | Y49: =ABS(SUM(Y42:Y43))/'Company Basic info'!$G$15 -> 6.0999983 | Z49: =ABS(SUM(Z42:Z43))/'Company Basic info'!$G$15 -> 6.3499983 | AA49: =ABS(SUM(AA42:AA43))/'Company Basic info'!$G$15 -> 8.6199979 | AC49: Net cash used in/generated from Financing activities | AD49: =SUM(AD45:AD48) -> 63.94 | AE49: =SUM(AE45:AE48) -> -7124.93 | AF49: =SUM(AF45:AF48) -> -1463.68 | AG49: =SUM(AG45:AG48) -> -1731.3 | AH49: =SUM(AH45:AH48) -> -1998.85 | AI49: =SUM(AI45:AI48) -> -2578.51
A50: CASH FLOW FROM FINANCING ACTIVITIES | V50: CapEx | W50: =ABS(W32) -> 67.3676 | X50: =ABS(X32) -> 163.844 | Y50: =ABS(Y32) -> 54.8278 | Z50: =ABS(Z32) -> 42.2584 | AA50: =ABS(AA32) -> 48.0691 | AC50: Effect of exchange differences on translation of foreign currency | AD50: 0 | AE50: 0 | AF50: 0 | AG50: 0 | AH50: 0 | AI50: 0
A51: Proceeds/Repayment from borrowings (net) | B51: -25.01 | C51: -8.33 | D51: 0 | E51: 0 | F51: 0 | O51: DPS | P51: =ABS(P45/'Company Basic info'!$E$15) -> 5.0921521 | Q51: =ABS(Q45/'Company Basic info'!$E$15) -> 4.6119611 | R51: =ABS(R45/'Company Basic info'!$E$15) -> 3.9638697 | S51: =ABS(S45/'Company Basic info'!$E$15) -> 4.5535645 | T51: =ABS(T45/'Company Basic info'!$E$15) -> 3.9604188 | AC51: Net increase/decrease in Cash and cash equivalents | AD51: =AD32+AD43+AD49 -> 252.45 | AE51: =AE32+AE43+AE49 -> 6866.83 | AF51: =AF32+AF43+AF49 -> -4075.78 | AG51: =AG32+AG43+AG49 -> 1370.4 | AH51: =AH32+AH43+AH49 -> -186.08 | AI51: =AI32+AI43+AI49 -> 293.86
A52: Corporate Social responsibility expenditure | B52: -50.42 | C52: -36.7 | D52: -47.57 | E52: 0 | F52: 0 | O52: CapEx | P52: =ABS(P34) -> 56.8884 | Q52: =ABS(Q34) -> 56.6091 | R52: =ABS(R34) -> 102.0442 | S52: =ABS(S34) -> 108.2571 | T52: =ABS(T34) -> 80.8897 | AC52: Opening balance | AD52: 26.87 | AE52: 279.32 | AF52: 7146.15 | AG52: =AF53 -> 3070.37 | AH52: 4440.77 | AI52: 4254.69
A53: Dividends paid | B53: -980.17 | C53: -1022.74 | D53: -1023.31 | E53: -1242.8 | F53: -1462.09 | AC53: Closing balance | AD53: =AD50+AD51+AD52 -> 279.32 | AE53: =AE50+AE51+AE52 -> 7146.15 | AF53: =AF50+AF51+AF52 -> 3070.37 | AG53: =AG50+AG51+AG52 -> 4440.77 | AH53: =AH50+AH51+AH52 -> 4254.69 | AI53: =AI50+AI51+AI52 -> 4548.55
A54: Repayment of lease liabilities | B54: -1.32 | C54: -1.59 | D54: -1.67 | E54: -4.33 | F54: -5.78
A55: Interest on lease liability | B55: -0.28 | C55: -0.24 | D55: -3.06 | E55: -3.7 | F55: -4.21 | AC55: DPS | AD55: =ABS(AD48)/'Company Basic info'!$F$15 -> 20.042316 | AE55: =ABS(AE48)/'Company Basic info'!$F$15 -> 14.999963 | AF55: =ABS(AF48)/'Company Basic info'!$F$15 -> 20 | AG55: =ABS(AG48)/'Company Basic info'!$F$15 -> 25.000037 | AH55: =ABS(AH48)/'Company Basic info'!$F$15 -> 29.500056 | AI55: =ABS(AI48)/'Company Basic info'!$F$15 -> 38.000075
A56: Finance cost | B56: -3.32 | C56: -6.13 | D56: -1.99 | E56: -11.25 | F56: -2.93 | AC56: CapEx | AD56: =ABS(AD34) -> 890.23 | AE56: =ABS(AE34) -> 762.98 | AF56: =ABS(AF34) -> 799.29 | AG56: =ABS(AG34) -> 782.42 | AH56: =ABS(AH34) -> 916.42 | AI56: =ABS(AI34) -> 930.09
A57: Net cash from / used in Financing activities | B57: =SUM(B51:B56) -> -1060.52 | C57: =SUM(C51:C56) -> -1075.73 | D57: =SUM(D51:D56) -> -1077.6 | E57: =SUM(E51:E56) -> -1262.08 | F57: =SUM(F51:F56) -> -1475.01
A58: Net Increase/Decrease in cash and cash equivalents | B58: =B40+B49+B57 -> 860.93 | C58: =C40+C49+C57 -> 1422.27 | D58: =D40+D49+D57 -> -1742.04 | E58: =E40+E49+E57 -> 2644.93 | F58: =F40+F49+F57 -> -2739.37
A59: Cash and Cash equivalents at the beginning of the year | B59: 759.7 | C59: 1620.63 | D59: 3042.9 | E59: 1300.86 | F59: 3945.69
A60: Cash and Cash equivalents at the end of the year | B60: =B58+B59 -> 1620.63 | C60: =C58+C59 -> 3042.9 | D60: =D58+D59 -> 1300.86 | E60: =E58+E59 -> 3945.79 | F60: =F58+F59 -> 1206.32
A62: CapEx | B62: =ABS(B42) -> 762.2 | C62: =ABS(C42) -> 469.25 | D62: =ABS(D42) -> 554.56 | E62: =ABS(E42) -> 590.45 | F62: =ABS(F42) -> 652.53

Sheet Ratio Analysis
A1: Ratio Analysis
F2: #VALUE! | K2: #VALUE! | R2: #VALUE! | X2: #VALUE! | AE2: #VALUE!
A3: Profitability ratios | C3: 2020 | D3: 2021 | E3: 2022 | F3: 2023 | G3: 2024 | I3: 2020 | J3: 2021 | K3: 2022 | L3: 2023 | M3: 2024 | O3: 2020 | P3: 2021 | Q3: 2022 | R3: 2023 | S3: 2024 | U3: 2020 | V3: 2021 | W3: 2022 | X3: 2023 | Y3: 2024 | AA3: 2020 | AB3: 2021 | AC3: 2022 | AD3: 2023 | AE3: 2024 | AF3: 2025
A4: Gross Profit margin | C4: =('Income Statement'!M9-('Income Statement'!M11+'Income Statement'!M12+'Income Statement'!M13))/'Income Statement'!M9 -> 0.45685758 | D4: =('Income Statement'!L9-('Income Statement'!L11+'Income Statement'!L12+'Income Statement'!L13))/'Income Statement'!L9 -> 0.44835387 | E4: =('Income Statement'!K9-('Income Statement'!K11+'Income Statement'!K12+'Income Statement'!K13))/'Income Statement'!K9 -> 0.42739438 | F4: =('Income Statement'!J9-('Income Statement'!J11+'Income Statement'!J12+'Income Statement'!J13))/'Income Statement'!J9 -> 0.45525268 | G4: =('Income Statement'!I9-('Income Statement'!I11+'Income Statement'!I12+'Income Statement'!I13))/'Income Statement'!I9 -> 0.49506361 | I4: =('Income Statement'!F9-('Income Statement'!F11+'Income Statement'!F12))/'Income Statement'!F9 -> 0.32438956 | J4: =('Income Statement'!E9-('Income Statement'!E11+'Income Statement'!E12))/'Income Statement'!E9 -> 0.3428878 | K4: =('Income Statement'!D9-'Income Statement'!D12)/'Income Statement'!D9 -> 0.31649075 | L4: =('Income Statement'!C9-'Income Statement'!C12)/'Income Statement'!C9 -> 0.39635461 | M4: =('Income Statement'!B9-'Income Statement'!B12)/'Income Statement'!B9 -> 0.37502593 | O4: =('Income Statement'!W6-('Income Statement'!W8+'Income Statement'!W9))/'Income Statement'!W6 -> 0.52465119 | P4: =('Income Statement'!X6-('Income Statement'!X8+'Income Statement'!X9))/'Income Statement'!X6 -> 0.58116567 | Q4: =('Income Statement'!Y6-('Income Statement'!Y8+'Income Statement'!Y9))/'Income Statement'!Y6 -> 0.59741706 | R4: =('Income Statement'!Z6-('Income Statement'!Z8+'Income Statement'!Z9))/'Income Statement'!Z6 -> 0.54956905 | S4: =('Income Statement'!AA6-('Income Statement'!AA8+'Income Statement'!AA9))/'Income Statement'!AA6 -> 0.67144152 | U4: =('Income Statement'!P6-('Income Statement'!P8+'Income Statement'!P9+'Income Statement'!P10))/'Income Statement'!P6 -> 0.56488877 | V4: =('Income Statement'!Q6-('Income Statement'!Q8+'Income Statement'!Q9+'Income Statement'!Q10))/'Income Statement'!Q6 -> 0.63678909 | W4: =('Income Statement'!R6-('Income Statement'!R8+'Income Statement'!R9+'Income Statement'!R10))/'Income Statement'!R6 -> 0.50788474 | X4: =('Income Statement'!S6-('Income Statement'!S8+'Income Statement'!S9+'Income Statement'!S10))/'Income Statement'!S6 -> 0.41654636 | Y4: =('Income Statement'!T6-('Income Statement'!T8+'Income Statement'!T9+'Income Statement'!T10))/'Income Statement'!T6 -> 0.42157629 | AA4: =('Income Statement'!AD6-('Income Statement'!AD8+'Income Statement'!AD9+'Income Statement'!AD10))/'Income Statement'!AD6 -> 0.56823307 | AB4: =('Income Statement'!AE6-('Income Statement'!AE8+'Income Statement'!AE9+'Income Statement'!AE10))/'Income Statement'!AE6 -> 0.52216805 | AC4: =('Income Statement'!AF6-('Income Statement'!AF8+'Income Statement'!AF9+'Income Statement'!AF10))/'Income Statement'!AF6 -> 0.60940287 | AD4: =('Income Statement'!AG6-('Income Statement'!AG8+'Income Statement'!AG9+'Income Statement'!AG10))/'Income Statement'!AG6 -> 0.64674948 | AE4: =('Income Statement'!AH6-('Income Statement'!AH8+'Income Statement'!AH9+'Income Statement'!AH10))/'Income Statement'!AH6 -> 0.65737655 | AF4: =('Income Statement'!AI6-('Income Statement'!AI8+'Income Statement'!AI9+'Income Statement'!AI10))/'Income Statement'!AI6 -> 0.63365913
A5: Operating profit margin | C5: ='Income Statement'!M21/'Income Statement'!M9 -> 0.18966761 | D5: ='Income Statement'!L21/'Income Statement'!L9 -> 0.20682343 | E5: ='Income Statement'!K21/'Income Statement'!K9 -> 0.20310857 | F5: ='Income Statement'!J20/'Income Statement'!J9 -> 0.22130575 | G5: ='Income Statement'!I20/'Income Statement'!I9 -> 0.25493435 | I5: ='Income Statement'!F20/'Income Statement'!F9 -> 0.1350762 | J5: ='Income Statement'!E20/'Income Statement'!E9 -> 0.15793436 | K5: ='Income Statement'!D20/'Income Statement'!D9 -> 0.12756145 | L5: ='Income Statement'!C20/'Income Statement'!C9 -> 0.16735592 | M5: ='Income Statement'!B20/'Income Statement'!B9 -> 0.23210494 | O5: =('Income Statement'!W6-('Income Statement'!W8+'Income Statement'!W9+'Income Statement'!W10+'Income Statement'!W12+'Income Statement'!W13))/'Income Statement'!W6 -> 0.23398931 | P5: =('Income Statement'!X6-('Income Statement'!X8+'Income Statement'!X9+'Income Statement'!X10+'Income Statement'!X12+'Income Statement'!X13))/'Income Statement'!X6 -> 0.17167821 | Q5: =('Income Statement'!Y6-('Income Statement'!Y8+'Income Statement'!Y9+'Income Statement'!Y10+'Income Statement'!Y12+'Income Statement'!Y13))/'Income Statement'!Y6 -> 0.25504307 | R5: =('Income Statement'!Z6-('Income Statement'!Z8+'Income Statement'!Z9+'Income Statement'!Z10+'Income Statement'!Z12+'Income Statement'!Z13))/'Income Statement'!Z6 -> 0.18388569 | S5: =('Income Statement'!AA6-('Income Statement'!AA8+'Income Statement'!AA9+'Income Statement'!AA10+'Income Statement'!AA12+'Income Statement'!AA13))/'Income Statement'!AA6 -> 0.30439722 | U5: =('Income Statement'!P18+'Income Statement'!P13)/'Income Statement'!P6 -> 0.14215961 | V5: =('Income Statement'!Q18+'Income Statement'!Q13)/'Income Statement'!Q6 -> 0.17356401 | W5: =('Income Statement'!R18+'Income Statement'!R13)/'Income Statement'!R6 -> 0.13850961 | X5: =('Income Statement'!S18+'Income Statement'!S13)/'Income Statement'!S6 -> 0.11281245 | Y5: =('Income Statement'!T18+'Income Statement'!T13)/'Income Statement'!T6 -> 0.12650994 | AA5: =('Income Statement'!AD21+'Income Statement'!AD12)/'Income Statement'!AD6 -> 0.19323025 | AB5: =('Income Statement'!AE21+'Income Statement'!AE12)/'Income Statement'!AE6 -> 0.19596656 | AC5: =('Income Statement'!AF21+'Income Statement'!AF12)/'Income Statement'!AF6 -> 0.20632573 | AD5: =('Income Statement'!AG21+'Income Statement'!AG12)/'Income Statement'!AG6 -> 0.22955089 | AE5: =('Income Statement'!AH21+'Income Statement'!AH12)/'Income Statement'!AH6 -> 0.31695246 | AF5: =('Income Statement'!AI21+'Income Statement'!AI12)/'Income Statement'!AI6 -> 0.32285443
A6: Net profit margin | C6: ='Income Statement'!M29/'Income Statement'!M9 -> 0.13964263 | D6: ='Income Statement'!L29/'Income Statement'!L9 -> 0.14555533 | E6: ='Income Statement'!K29/'Income Statement'!K9 -> 0.15108234 | F6: ='Income Statement'!J29/'Income Statement'!J9 -> 0.16697952 | G6: ='Income Statement'!I29/'Income Statement'!I9 -> 0.19211258 | I6: ='Income Statement'!F30/'Income Statement'!F9 -> 0.086186526 | J6: ='Income Statement'!E30/'Income Statement'!E9 -> 0.1111789 | K6: ='Income Statement'!D30/'Income Statement'!D9 -> 0.095099491 | L6: ='Income Statement'!C30/'Income Statement'!C9 -> 0.12560153 | M6: ='Income Statement'!B30/'Income Statement'!B9 -> 0.17402165 | O6: ='Income Statement'!W22/Table11[[#This Row],[2020]] -> 0.16752703 | P6: ='Income Statement'!X22/Table11[[#This Row],[2021]] -> 0.12834528 | Q6: ='Income Statement'!Y22/Table11[[#This Row],[2022]] -> 0.17070346 | R6: ='Income Statement'!Z22/Table11[[#This Row],[2023]] -> 0.13386669 | S6: ='Income Statement'!AA22/Table11[[#This Row],[2024]] -> 0.22434909 | U6: ='Income Statement'!P25/Table2[[#This Row],[2020]] -> 0.098554511 | V6: ='Income Statement'!Q25/Table2[[#This Row],[2021]] -> 0.11552818 | W6: ='Income Statement'!R25/Table2[[#This Row],[2022]] -> 0.098802655 | X6: ='Income Statement'!S25/Table2[[#This Row],[2023]] -> 0.08256446 | Y6: ='Income Statement'!T25/Table2[[#This Row],[2024]] -> 0.09178917 | AA6: ='Income Statement'!AD35/Table12[[#This Row],[2020]] -> 0.13258605 | AB6: ='Income Statement'!AE35/Table12[[#This Row],[2021]] -> 0.14014158 | AC6: ='Income Statement'!AF35/Table12[[#This Row],[2022]] -> 0.19839445 | AD6: ='Income Statement'!AG35/Table12[[#This Row],[2023]] -> 0.20378403 | AE6: ='Income Statement'!AH35/Table12[[#This Row],[2024]] -> 0.23610588 | AF6: ='Income Statement'!AI35/Table12[[#This Row],[2025]] -> 0.24935545
A7: Return on capital employed | C7: ='Income Statement'!M21/('Balance Sheet '!F31-'Balance Sheet '!F58) -> 0.14162326 | D7: ='Income Statement'!L21/('Balance Sheet '!E31-'Balance Sheet '!E58) -> 0.19663205 | E7: ='Income Statement'!K21/('Balance Sheet '!D31-'Balance Sheet '!D58) -> 0.22036995 | F7: ='Income Statement'!J21/('Balance Sheet '!C31-'Balance Sheet '!C58) -> 0.31475847 | G7: ='Income Statement'!I21/('Balance Sheet '!B31-'Balance Sheet '!B58) -> 0.47916386 | I7: ='Income Statement'!F22/('Balance Sheet '!M48-'Balance Sheet '!M22) -> 0.10791317 | J7: ='Income Statement'!E22/('Balance Sheet '!L48-'Balance Sheet '!L22) -> 0.12736884 | K7: ='Income Statement'!D22/('Balance Sheet '!K48-'Balance Sheet '!K22) -> 0.1684808 | L7: ='Income Statement'!C22/('Balance Sheet '!J48-'Balance Sheet '!J22) -> 0.3281486 | M7: ='Income Statement'!B22/('Balance Sheet '!I48-'Balance Sheet '!I22) -> 0.5493036 | O7: =('Income Statement'!W15+'Income Statement'!W11)/('Balance Sheet '!P26-'Balance Sheet '!P48) -> 0.22165497 | P7: =('Income Statement'!X15+'Income Statement'!X11)/('Balance Sheet '!Q26-'Balance Sheet '!Q48) -> 0.10020791 | Q7: =('Income Statement'!Y15+'Income Statement'!Y11)/('Balance Sheet '!R26-'Balance Sheet '!R48) -> 0.18753598 | R7: =('Income Statement'!Z15+'Income Statement'!Z11)/('Balance Sheet '!S26-'Balance Sheet '!S48) -> 0.075213032 | S7: =('Income Statement'!AA15+'Income Statement'!AA11)/('Balance Sheet '!T26-'Balance Sheet '!T48) -> 0.11334979 | U7: =('Income Statement'!P18+'Income Statement'!P13)/('Balance Sheet '!AE24-'Balance Sheet '!AE48) -> 0.20737362 | V7: =('Income Statement'!Q18+'Income Statement'!Q13)/('Balance Sheet '!AF24-'Balance Sheet '!AF48) -> 0.18673546 | W7: =('Income Statement'!R18+'Income Statement'!R13)/('Balance Sheet '!AG24-'Balance Sheet '!AG48) -> 0.1931302 | X7: =('Income Statement'!S18+'Income Statement'!S13)/('Balance Sheet '!AH24-'Balance Sheet '!AH48) -> 0.203051 | Y7: =('Income Statement'!T18+'Income Statement'!T13)/('Balance Sheet '!AI24-'Balance Sheet '!AI48) -> 0.25914579 | AA7: =('Income Statement'!AD21+'Income Statement'!AD12)/('Balance Sheet '!W33-'Balance Sheet '!W61) -> 0.18966708 | AB7: =('Income Statement'!AE21+'Income Statement'!AE12)/('Balance Sheet '!X33-'Balance Sheet '!X61) -> 0.17133715 | AC7: =('Income Statement'!AF21+'Income Statement'!AF12)/('Balance Sheet '!Y33-'Balance Sheet '!Y61) -> 0.15831731 | AD7: =('Income Statement'!AG21+'Income Statement'!AG12)/('Balance Sheet '!Z33-'Balance Sheet '!Z61) -> 0.18046251 | AE7: =('Income Statement'!AH21+'Income Statement'!AH12)/('Balance Sheet '!AA33-'Balance Sheet '!AA61) -> 0.24491936 | AF7: =('Income Statement'!AI21+'Income Statement'!AI12)/('Balance Sheet '!AB33-'Balance Sheet '!AB61) -> 0.17418548
A8: Return on Assets | C8: ='Income Statement'!F9/'Balance Sheet '!B31 -> 0.23149593 | D8: ='Income Statement'!E9/AVERAGE('Balance Sheet '!B31:C31) -> 0.17310315 | E8: ='Income Statement'!D9/AVERAGE('Balance Sheet '!C31:D31) -> 0.19453898 | F8: ='Income Statement'!C9/AVERAGE('Balance Sheet '!D31:E31) -> 0.24612232 | G8: ='Income Statement'!B9/AVERAGE('Balance Sheet '!E31:F31) -> 0.28272205 | I8: ='Income Statement'!M9/'Balance Sheet '!I48 -> 0.62399873 | J8: ='Income Statement'!L9/AVERAGE('Balance Sheet '!I48:J48) -> 0.6158908 | K8: ='Income Statement'!K9/AVERAGE('Balance Sheet '!J48:K48) -> 0.56629855 | L8: ='Income Statement'!J9/AVERAGE('Balance Sheet '!K48:L48) -> 0.6140152 | M8: ='Income Statement'!I9/AVERAGE('Balance Sheet '!L48:M48) -> 0.71748508 | O8: ='Income Statement'!W6/'Balance Sheet '!P26 -> 0.56161401 | P8: ='Income Statement'!X6/AVERAGE('Balance Sheet '!P26:Q26) -> 0.34487338 | Q8: ='Income Statement'!Y6/AVERAGE('Balance Sheet '!Q26:R26) -> 0.46761907 | R8: ='Income Statement'!Z6/AVERAGE('Balance Sheet '!R26:S26) -> 0.34717678 | S8: ='Income Statement'!AA6/AVERAGE('Balance Sheet '!S26:T26) -> 0.28730047 | U8: ='Income Statement'!P6/'Balance Sheet '!AE24 -> 0.30808787 | V8: ='Income Statement'!Q6/AVERAGE('Balance Sheet '!AE24:AF24) -> 0.21835955 | W8: ='Income Statement'!R6/AVERAGE('Balance Sheet '!AF24:AG24) -> 0.26606367 | X8: ='Income Statement'!S6/AVERAGE('Balance Sheet '!AG24:AH24) -> 0.30013597 | Y8: ='Income Statement'!T6/AVERAGE('Balance Sheet '!AH24:AI24) -> 0.36836919 | AA8: ='Income Statement'!AD6/'Balance Sheet '!W33 -> 0.40808557 | AB8: ='Income Statement'!AE6/AVERAGE('Balance Sheet '!W33:X33) -> 0.43930906 | AC8: ='Income Statement'!AF6/AVERAGE('Balance Sheet '!X33:Y33) -> 0.46411894 | AD8: ='Income Statement'!AG6/AVERAGE('Balance Sheet '!Y33:Z33) -> 0.45539078 | AE8: ='Income Statement'!AH6/AVERAGE('Balance Sheet '!Z33:AA33) -> 0.44429328 | AF8: ='Income Statement'!AI6/AVERAGE('Balance Sheet '!AA33:AB33) -> 0.36387796
A9: Return on Equity | C9: ='Income Statement'!M29/'Balance Sheet '!B36 -> 0.18519548 | D9: ='Income Statement'!L29/'Balance Sheet '!C36 -> 0.18650115 | E9: ='Income Statement'!K29/'Balance Sheet '!D36 -> 0.19093468 | F9: ='Income Statement'!L29/'Balance Sheet '!E36 -> 0.14881212 | G9: ='Income Statement'!I29/'Balance Sheet '!F36 -> 0.24595595 | I9: ='Income Statement'!F30/'Balance Sheet '!I9 -> 0.15593682 | J9: ='Income Statement'!E30/'Balance Sheet '!J9 -> 0.14973876 | K9: ='Income Statement'!D30/'Balance Sheet '!K9 -> 0.15202661 | L9: ='Income Statement'!C30/'Balance Sheet '!L9 -> 0.25678147 | M9: ='Income Statement'!B30/'Balance Sheet '!M9 -> 0.29557762 | O9: ='Income Statement'!W22/'Balance Sheet '!P31 -> 0.20519208 | P9: ='Income Statement'!X22/'Balance Sheet '!Q31 -> 0.096010976 | Q9: ='Income Statement'!Y22/'Balance Sheet '!R31 -> 0.1649612 | R9: ='Income Statement'!Z22/'Balance Sheet '!S31 -> 0.11024448 | S9: ='Income Statement'!AA22/'Balance Sheet '!T31 -> 0.16847692 | U9: ='Income Statement'!P25/'Balance Sheet '!AE29 -> 0.15715903 | V9: ='Income Statement'!Q25/'Balance Sheet '!AF29 -> 0.13496511 | W9: ='Income Statement'!R25/'Balance Sheet '!AG29 -> 0.15066436 | X9: ='Income Statement'!S25/'Balance Sheet '!AH29 -> 0.16135322 | Y9: ='Income Statement'!T25/'Balance Sheet '!AI29 -> 0.21349312 | AA9: ='Income Statement'!AD35/'Balance Sheet '!W40 -> 0.2175122 | AB9: ='Income Statement'!AE35/'Balance Sheet '!X40 -> 0.21010782 | AC9: ='Income Statement'!AF35/'Balance Sheet '!Y40 -> 0.26297622 | AD9: ='Income Statement'!AG35/'Balance Sheet '!Z40 -> 0.24719024 | AE9: ='Income Statement'!AH35/'Balance Sheet '!AA40 -> 0.26151258 | AF9: ='Income Statement'!AI35/'Balance Sheet '!AB40 -> 0.23907387
A10: Liquidity ratios
A11: Current Ratio | C11: ='Balance Sheet '!B30/'Balance Sheet '!B58 -> 1.4552001 | D11: ='Balance Sheet '!C30/'Balance Sheet '!C58 -> 1.4090282 | E11: ='Balance Sheet '!D30/'Balance Sheet '!D58 -> 1.3938846 | F11: ='Balance Sheet '!E30/'Balance Sheet '!E58 -> 1.4610552 | G11: ='Balance Sheet '!F30/'Balance Sheet '!F58 -> 1.5464384 | I11: ='Balance Sheet '!I47/'Balance Sheet '!I22 -> 1.0979377 | J11: ='Balance Sheet '!J47/'Balance Sheet '!J22 -> 1.0626225 | K11: ='Balance Sheet '!K47/'Balance Sheet '!K22 -> 1.0534269 | L11: ='Balance Sheet '!L47/'Balance Sheet '!L22 -> 1.0805863 | M11: ='Balance Sheet '!M47/'Balance Sheet '!M22 -> 1.1393387 | O11: ='Balance Sheet '!P25/'Balance Sheet '!P48 -> 1.9761243 | P11: ='Balance Sheet '!Q25/'Balance Sheet '!Q48 -> 1.9432977 | Q11: ='Balance Sheet '!R25/'Balance Sheet '!R48 -> 2.1399115 | R11: ='Balance Sheet '!S25/'Balance Sheet '!S48 -> 3.4452672 | S11: ='Balance Sheet '!T25/'Balance Sheet '!T48 -> 3.0737712 | U11: ='Balance Sheet '!AE23/'Balance Sheet '!AE48 -> 1.1320104 | V11: ='Balance Sheet '!AF23/'Balance Sheet '!AF48 -> 0.98719929 | W11: ='Balance Sheet '!AG23/'Balance Sheet '!AG48 -> 0.93131557 | X11: ='Balance Sheet '!AH23/'Balance Sheet '!AH48 -> 1.078453 | Y11: ='Balance Sheet '!AI23/'Balance Sheet '!AI48 -> 1.1170048 | AA11: ='Balance Sheet '!W31/'Balance Sheet '!W61 -> 1.3298273 | AB11: ='Balance Sheet '!X31/'Balance Sheet '!X61 -> 1.5746857 | AC11: ='Balance Sheet '!Y31/'Balance Sheet '!Y61 -> 1.7977755 | AD11: ='Balance Sheet '!Z31/'Balance Sheet '!Z61 -> 1.682826 | AE11: ='Balance Sheet '!AA31/'Balance Sheet '!AA61 -> 1.7348562 | AF11: ='Balance Sheet '!AB31/'Balance Sheet '!AB61 -> 2.0431815
A12: Quick ratio | C12: =('Balance Sheet '!B30-'Balance Sheet '!B21)/'Balance Sheet '!B58 -> 1.1491904 | D12: =('Balance Sheet '!C30-'Balance Sheet '!C21)/'Balance Sheet '!C58 -> 1.1138343 | E12: =('Balance Sheet '!D30-'Balance Sheet '!D21)/'Balance Sheet '!D58 -> 1.1083073 | F12: =('Balance Sheet '!E30-'Balance Sheet '!E21)/'Balance Sheet '!E58 -> 1.1475227 | G12: =('Balance Sheet '!F30-'Balance Sheet '!F21)/'Balance Sheet '!F58 -> 1.2083541 | I12: =('Balance Sheet '!I47-'Balance Sheet '!I39)/'Balance Sheet '!I22 -> 0.817093 | J12: =('Balance Sheet '!J47-'Balance Sheet '!J39)/'Balance Sheet '!J22 -> 0.77928159 | K12: =('Balance Sheet '!K47-'Balance Sheet '!K39)/'Balance Sheet '!K22 -> 0.74767252 | L12: =('Balance Sheet '!L47-'Balance Sheet '!L39)/'Balance Sheet '!L22 -> 0.77582628 | M12: =('Balance Sheet '!M47-'Balance Sheet '!M39)/'Balance Sheet '!M22 -> 0.88691833 | O12: =('Balance Sheet '!P25-'Balance Sheet '!P17)/'Balance Sheet '!P48 -> 1.6060844 | P12: =('Balance Sheet '!Q25-'Balance Sheet '!Q17)/'Balance Sheet '!Q48 -> 1.3891422 | Q12: =('Balance Sheet '!R25-'Balance Sheet '!R17)/'Balance Sheet '!R48 -> 1.4989141 | R12: =('Balance Sheet '!S25-'Balance Sheet '!S17)/'Balance Sheet '!S48 -> 2.6191269 | S12: =('Balance Sheet '!T25-'Balance Sheet '!T17)/'Balance Sheet '!T48 -> 2.4142126 | U12: =('Balance Sheet '!AE23-'Balance Sheet '!AE15)/'Balance Sheet '!AE48 -> 1.0281676 | V12: =('Balance Sheet '!AF23-'Balance Sheet '!AF15)/'Balance Sheet '!AF48 -> 0.84520106 | W12: =('Balance Sheet '!AG23-'Balance Sheet '!AG15)/'Balance Sheet '!AG48 -> 0.74404999 | X12: =('Balance Sheet '!AH23-'Balance Sheet '!AH15)/'Balance Sheet '!AH48 -> 0.76262676 | Y12: =('Balance Sheet '!AI23-'Balance Sheet '!AI15)/'Balance Sheet '!AI48 -> 0.64582726 | AA12: =('Balance Sheet '!W31-'Balance Sheet '!W21)/'Balance Sheet '!W61 -> 0.70542484 | AB12: =('Balance Sheet '!X31-'Balance Sheet '!X21)/'Balance Sheet '!X61 -> 0.92614357 | AC12: =('Balance Sheet '!Y31-'Balance Sheet '!Y21)/'Balance Sheet '!Y61 -> 1.2244013 | AD12: =('Balance Sheet '!Z31-'Balance Sheet '!Z21)/'Balance Sheet '!Z61 -> 1.2887369 | AE12: =('Balance Sheet '!AA31-'Balance Sheet '!AA21)/'Balance Sheet '!AA61 -> 1.3709806 | AF12: =('Balance Sheet '!AB31-'Balance Sheet '!AB21)/'Balance Sheet '!AB61 -> 1.5516161
A13: Solvency ratio
A14: Debt-to-Equity ratio | C14: =('Balance Sheet '!B43+'Balance Sheet '!B52)/'Balance Sheet '!B36 -> 0 | D14: =('Balance Sheet '!C43+'Balance Sheet '!C52)/'Balance Sheet '!C36 -> 0.00022754834 | E14: =('Balance Sheet '!D43+'Balance Sheet '!D52)/'Balance Sheet '!D36 -> 0.0042837623 | F14: =('Balance Sheet '!E43+'Balance Sheet '!E52)/'Balance Sheet '!E36 -> 0.0044195058 | G14: =('Balance Sheet '!F43+'Balance Sheet '!F52)/'Balance Sheet '!F36 -> 0.0038245539 | I14: 0 | J14: 0 | K14: 0 | L14: 0 | M14: 0 | O14: =('Balance Sheet '!P33+'Balance Sheet '!P39+'Balance Sheet '!P43)/'Balance Sheet '!P31 -> 0.0041963616 | P14: =('Balance Sheet '!Q33+'Balance Sheet '!Q39+'Balance Sheet '!Q43)/'Balance Sheet '!Q31 -> 0.0028724865 | Q14: =('Balance Sheet '!R33+'Balance Sheet '!R39+'Balance Sheet '!R43)/'Balance Sheet '!R31 -> 0.0021537622 | R14: =('Balance Sheet '!S33+'Balance Sheet '!S39+'Balance Sheet '!S43)/'Balance Sheet '!S31 -> 0.0016215176 | S14: =('Balance Sheet '!T33+'Balance Sheet '!T39+'Balance Sheet '!T43)/'Balance Sheet '!T31 -> 0.0010286725 | U14: =('Balance Sheet '!AE32+'Balance Sheet '!AE40+'Balance Sheet '!AE41)/'Balance Sheet '!AE29 -> 0 | V14: =('Balance Sheet '!AF32+'Balance Sheet '!AF40+'Balance Sheet '!AF41)/'Balance Sheet '!AF29 -> 0 | W14: =('Balance Sheet '!AG32+'Balance Sheet '!AG40+'Balance Sheet '!AG41)/'Balance Sheet '!AG29 -> 0.0089071332 | X14: =('Balance Sheet '!AH32+'Balance Sheet '!AH40+'Balance Sheet '!AH41)/'Balance Sheet '!AH29 -> 0.22075515 | Y14: =('Balance Sheet '!AI32+'Balance Sheet '!AI40+'Balance Sheet '!AI41)/'Balance Sheet '!AI29 -> 0.039242903 | AA14: =('Balance Sheet '!W43+'Balance Sheet '!W45+'Balance Sheet '!W52+'Balance Sheet '!W56)/'Balance Sheet '!W40 -> 0.44416962 | AB14: =('Balance Sheet '!X43+'Balance Sheet '!X45+'Balance Sheet '!X52+'Balance Sheet '!X56)/'Balance Sheet '!X40 -> 0.0005883429 | AC14: =('Balance Sheet '!Y43+'Balance Sheet '!Y45+'Balance Sheet '!Y52+'Balance Sheet '!Y56)/'Balance Sheet '!Y40 -> 0.0001289028 | AD14: =('Balance Sheet '!Z43+'Balance Sheet '!Z45+'Balance Sheet '!Z52+'Balance Sheet '!Z56)/'Balance Sheet '!Z40 -> 0.00011240297 | AE14: =('Balance Sheet '!AA43+'Balance Sheet '!AA45+'Balance Sheet '!AA52+'Balance Sheet '!AA56)/'Balance Sheet '!AA40 -> 3.7746454e-05 | AF14: =('Balance Sheet '!AB43+'Balance Sheet '!AB45+'Balance Sheet '!AB52+'Balance Sheet '!AB56)/'Balance Sheet '!AB40 -> 3.3156906e-05
A15: Interest Coverage ratio | C15: ='Income Statement'!M21/'Income Statement'!M15 -> 688.44444 | D15: ='Income Statement'!L21/'Income Statement'!L15 -> 482.69901 | E15: ='Income Statement'!K21/'Income Statement'!K15 -> 651.09278 | F15: ='Income Statement'!J21/'Income Statement'!J15 -> 269.4307 | G15: ='Income Statement'!I21/'Income Statement'!I15 -> 759.90883 | I15: ='Income Statement'!F22/'Income Statement'!F14 -> 79.413607 | J15: ='Income Statement'!E22/'Income Statement'!E14 -> 72.227273 | K15: ='Income Statement'!D22/'Income Statement'!D14 -> 107.9176 | L15: ='Income Statement'!C22/'Income Statement'!C14 -> 224.38462 | M15: ='Income Statement'!B22/'Income Statement'!B14 -> 480.73828 | O15: =('Income Statement'!W15+'Income Statement'!W11)/'Income Statement'!W11 -> 160.47205 | P15: =('Income Statement'!X15+'Income Statement'!X11)/'Income Statement'!X11 -> 88.11948 | Q15: =('Income Statement'!Y15+'Income Statement'!Y11)/'Income Statement'!Y11 -> 218.12414 | R15: =('Income Statement'!Z15+'Income Statement'!Z11)/'Income Statement'!Z11 -> 107.20834 | S15: =('Income Statement'!AA15+'Income Statement'!AA11)/'Income Statement'!AA11 -> 267.7253 | U15: =('Income Statement'!P18+'Income Statement'!P13)/'Income Statement'!P13 -> 176.56005 | V15: =('Income Statement'!Q18+'Income Statement'!Q13)/'Income Statement'!Q13 -> 85.363865 | W15: =('Income Statement'!R18+'Income Statement'!R13)/'Income Statement'!R13 -> 347.70789 | X15: =('Income Statement'!S18+'Income Statement'!S13)/'Income Statement'!S13 -> 48.09644 | Y15: =('Income Statement'!T18+'Income Statement'!T13)/'Income Statement'!T13 -> 42.858519 | AA15: =('Income Statement'!AD21+'Income Statement'!AD12)/'Income Statement'!AD12 -> 12.056362 | AB15: =('Income Statement'!AE21+'Income Statement'!AE12)/'Income Statement'!AE12 -> 17.47629 | AC15: =('Income Statement'!AF21+'Income Statement'!AF12)/'Income Statement'!AF12 -> 90.772509 | AD15: =('Income Statement'!AG21+'Income Statement'!AG12)/'Income Statement'!AG12 -> 113.24133 | AE15: =('Income Statement'!AH21+'Income Statement'!AH12)/'Income Statement'!AH12 -> 318.6076 | AF15: =('Income Statement'!AI21+'Income Statement'!AI12)/'Income Statement'!AI12 -> 1247.6256
A16: Efficiency ratios
A17: Asset turnover ratio | C17: ='Income Statement'!M9/'Balance Sheet '!B31 -> 0.54648575 | D17: ='Income Statement'!L9/'Balance Sheet '!C31 -> 0.48118307 | E17: ='Income Statement'!K9/'Balance Sheet '!D31 -> 0.4584808 | F17: ='Income Statement'!J9/'Balance Sheet '!E31 -> 0.50734366 | G17: ='Income Statement'!I9/'Balance Sheet '!F31 -> 0.52939508 | I17: ='Income Statement'!F9/'Balance Sheet '!I48 -> 0.26433107 | J17: ='Income Statement'!E9/'Balance Sheet '!J48 -> 0.18385815 | K17: ='Income Statement'!D9/'Balance Sheet '!K48 -> 0.20715072 | L17: ='Income Statement'!C9/'Balance Sheet '!L48 -> 0.29572339 | M17: ='Income Statement'!B9/'Balance Sheet '!M48 -> 0.36010284 | O17: ='Income Statement'!W6/'Balance Sheet '!P26 -> 0.56161401 | P17: ='Income Statement'!X6/'Balance Sheet '!Q26 -> 0.33687609 | Q17: ='Income Statement'!Y6/'Balance Sheet '!R26 -> 0.44617103 | R17: ='Income Statement'!Z6/'Balance Sheet '!S26 -> 0.30497632 | S17: ='Income Statement'!AA6/'Balance Sheet '!T26 -> 0.26412872 | U17: ='Income Statement'!P6/'Balance Sheet '!AE24 -> 0.30808787 | V17: ='Income Statement'!Q6/'Balance Sheet '!AF24 -> 0.19584101 | W17: ='Income Statement'!R6/'Balance Sheet '!AG24 -> 0.25121296 | X17: ='Income Statement'!S6/'Balance Sheet '!AH24 -> 0.25640292 | Y17: ='Income Statement'!T6/'Balance Sheet '!AI24 -> 0.375829 | AA17: ='Income Statement'!AD6/'Balance Sheet '!W33 -> 0.40808557 | AB17: ='Income Statement'!AE6/'Balance Sheet '!X33 -> 0.44493925 | AC17: ='Income Statement'!AF6/'Balance Sheet '!Y33 -> 0.43850114 | AD17: ='Income Statement'!AG6/'Balance Sheet '!Z33 -> 0.42553516 | AE17: ='Income Statement'!AH6/'Balance Sheet '!AA33 -> 0.41331206 | AF17: ='Income Statement'!AI6/'Balance Sheet '!AB33 -> 0.31564538
A18: Inventory turnover ratio | C18: ='Income Statement'!M11/'Balance Sheet '!B21 -> 1.508107 | D18: ='Income Statement'!L11/'Balance Sheet '!C21 -> 1.3534555 | E18: ='Income Statement'!K11/'Balance Sheet '!D21 -> 1.4531698 | F18: ='Income Statement'!J11/'Balance Sheet '!E21 -> 1.4544637 | G18: ='Income Statement'!I11/'Balance Sheet '!F21 -> 1.409665 | I18: ='Income Statement'!F11/'Balance Sheet '!I39 -> 0.54149856 | J18: ='Income Statement'!E11/'Balance Sheet '!J39 -> 0.31958476 | K18: ='Income Statement'!D11/'Balance Sheet '!K39 -> 0 | L18: ='Income Statement'!C11/'Balance Sheet '!L39 -> 0 | M18: ='Income Statement'!B11/'Balance Sheet '!M39 -> 0 | O18: =('Income Statement'!W8+'Income Statement'!W9)/Table9[[#This Row],[2020]] -> 4.4855063 | P18: =('Income Statement'!X8+'Income Statement'!X9)/AVERAGE(Table9[[#This Row],[2020]:[2021]]) -> 2.544927 | Q18: =('Income Statement'!Y8+'Income Statement'!Y9)/AVERAGE(Table9[[#This Row],[2020]:[2021]]) -> 3.567024 | R18: =('Income Statement'!Z8+'Income Statement'!Z9)/AVERAGE(Table9[[#This Row],[2020]:[2021]]) -> 3.6041997 | S18: =('Income Statement'!AA8+'Income Statement'!AA9)/AVERAGE(Table9[[#This Row],[2020]:[2021]]) -> 2.7148112 | U18: =('Income Statement'!P8+'Income Statement'!P9+'Income Statement'!P10)/'Balance Sheet '!AE15 -> 1.6365621 | V18: =('Income Statement'!Q8+'Income Statement'!Q9+'Income Statement'!Q10)/AVERAGE('Balance Sheet '!AE15:AF15) -> 0.78525819 | W18: =('Income Statement'!R8+'Income Statement'!R9+'Income Statement'!R10)/AVERAGE('Balance Sheet '!AF15:AG15) -> 0.96315018 | X18: =('Income Statement'!S8+'Income Statement'!S9+'Income Statement'!S10)/AVERAGE('Balance Sheet '!AG15:AH15) -> 0.78814989 | Y18: =('Income Statement'!T8+'Income Statement'!T9+'Income Statement'!T10)/AVERAGE('Balance Sheet '!AH15:AI15) -> 0.65229477 | AA18: =('Income Statement'!AD8+'Income Statement'!AD9+'Income Statement'!AD10)/'Balance Sheet '!W21 -> 0.48299075 | AB18: =('Income Statement'!AE8+'Income Statement'!AE9+'Income Statement'!AE10)/(AVERAGE('Balance Sheet '!W21:X21)) -> 0.61388629 | AC18: =('Income Statement'!AF8+'Income Statement'!AF9+'Income Statement'!AF10)/(AVERAGE('Balance Sheet '!X21:Y21)) -> 0.64749474 | AD18: =('Income Statement'!AG8+'Income Statement'!AG9+'Income Statement'!AG10)/(AVERAGE('Balance Sheet '!Y21:Z21)) -> 0.76253936 | AE18: =('Income Statement'!AH8+'Income Statement'!AH9+'Income Statement'!AH10)/(AVERAGE('Balance Sheet '!Z21:AA21)) -> 0.87195377 | AF18: =('Income Statement'!AI8+'Income Statement'!AI9+'Income Statement'!AI10)/(AVERAGE('Balance Sheet '!AA21:AB21)) -> 0.7043221
A19: Days Sales outstanding | C19: =('Balance Sheet '!B23/'Income Statement'!M9)*365 -> 188.0691 | D19: =('Balance Sheet '!C23/'Income Statement'!L9)*365 -> 168.79057 | E19: =('Balance Sheet '!D23/'Income Statement'!K9)*365 -> 143.39761 | F19: =('Balance Sheet '!E23/'Income Statement'!J9)*365 -> 142.57408 | G19: =('Balance Sheet '!F23/'Income Statement'!I9)*365 -> 128.94571 | I19: =('Income Statement'!F11/'Balance Sheet '!B21)*365 -> 233.66086 | J19: =('Income Statement'!E11/'Balance Sheet '!C21)*365 -> 138.26488 | K19: =('Income Statement'!D11/'Balance Sheet '!D21)*365 -> 0 | L19: ='Income Statement'!D11/'Balance Sheet '!D21*365 -> 0 | M19: ='Income Statement'!B11/'Balance Sheet '!F21*365 -> 0 | O19: =(Table9[[#This Row],[2020]]/'Income Statement'!W6)*365 -> 34.008208 | P19: =(Table9[[#This Row],[2021]]/'Income Statement'!X6)*365 -> 83.039648 | Q19: =(Table9[[#This Row],[2022]]/'Income Statement'!Y6)*365 -> 33.033024 | R19: =(Table9[[#This Row],[2023]]/'Income Statement'!Z6)*365 -> 145.30525 | S19: =(Table9[[#This Row],[2024]]/'Income Statement'!AA6)*365 -> 79.364352 | U19: =('Balance Sheet '!AE17/'Income Statement'!P6)*365 -> 117.78263 | V19: =('Balance Sheet '!AF17/'Income Statement'!Q6)*365 -> 48.945076 | W19: =('Balance Sheet '!AG17/'Income Statement'!R6)*365 -> 29.483622 | X19: =('Balance Sheet '!AH17/'Income Statement'!S6)*365 -> 6.7168134 | Y19: =('Balance Sheet '!AI17/'Income Statement'!T6)*365 -> 18.211907 | AA19: =('Balance Sheet '!W23/'Income Statement'!AD6)*365 -> 188.60856 | AB19: =('Balance Sheet '!X23/'Income Statement'!AE6)*365 -> 89.03385 | AC19: =('Balance Sheet '!Y23/'Income Statement'!AF6)*365 -> 66.165271 | AD19: =('Balance Sheet '!Z23/'Income Statement'!AG6)*365 -> 60.23099 | AE19: =('Balance Sheet '!AA23/'Income Statement'!AH6)*365 -> 52.207911 | AF19: =('Balance Sheet '!AB23/'Income Statement'!AI6)*365 -> 50.575725
A20: Market Value ratios
A21: Price-to-Earnings ratio (P/E) | C21: =C26/'Income Statement'!M34 -> 3.2843792 | D21: =D26/'Income Statement'!L33 -> 4.9528302 | E21: =E26/'Income Statement'!K33 -> 7.2946058 | F21: =F26/'Income Statement'!J33 -> 24.075426 | G21: =G26/'Income Statement'!I33 -> 37.272727 | I21: =I26/'Income Statement'!F34 -> 3.8871723 | J21: =J26/'Income Statement'!E35 -> 4.4638352 | K21: =K26/'Income Statement'!D35 -> 4.1213893 | L21: =L26/'Income Statement'!C35 -> 6.2327505 | M21: =M26/'Income Statement'!B35 -> 10.186339 | O21: ='Company Basic info'!$E$11/('Income Statement'!W22/'Company Basic info'!$E$15) -> 103.78384 | P21: ='Company Basic info'!$E$11/('Income Statement'!X22/'Company Basic info'!$E$15) -> 215.36677 | Q21: ='Company Basic info'!$E$11/('Income Statement'!Y22/'Company Basic info'!$E$15) -> 111.04491 | R21: ='Company Basic info'!$E$11/('Income Statement'!Z22/'Company Basic info'!$E$15) -> 156.79727 | S21: ='Company Basic info'!$E$11/('Income Statement'!AA22/'Company Basic info'!$E$15) -> 90.602535 | U21: ='Company Basic info'!$G$11/('Income Statement'!P25/'Company Basic info'!$G$15) -> 187.96339 | V21: ='Company Basic info'!$G$11/('Income Statement'!Q25/'Company Basic info'!$G$15) -> 200.22372 | W21: ='Company Basic info'!$G$11/('Income Statement'!R25/'Company Basic info'!$G$15) -> 162.13955 | X21: ='Company Basic info'!$G$11/('Income Statement'!S25/'Company Basic info'!$G$15) -> 134.70119 | Y21: ='Company Basic info'!$G$11/('Income Statement'!T25/'Company Basic info'!$G$15) -> 86.009942 | AA21: ='Company Basic info'!$F$11/('Income Statement'!AD35/'Company Basic info'!$F$15) -> 111.11643 | AB21: ='Company Basic info'!$F$11/('Income Statement'!AE35/'Company Basic info'!$F$15) -> 98.889735 | AC21: ='Company Basic info'!$F$11/('Income Statement'!AF35/'Company Basic info'!$F$15) -> 63.054597 | AD21: ='Company Basic info'!$F$11/('Income Statement'!AG35/'Company Basic info'!$F$15) -> 54.963045 | AE21: ='Company Basic info'!$F$11/('Income Statement'!AH35/'Company Basic info'!$F$15) -> 42.030165 | AF21: ='Company Basic info'!$F$11/('Income Statement'!AI35/'Company Basic info'!$F$15) -> 38.296061
A22: Price-to-Book (P/B) Ratio | C22: =C26/C27 -> 1.82505 | D22: =D26/D27 -> 2.7722214 | E22: =E26/E27 -> 4.178295 | F22: =F26/F27 -> 5.2113618 | G22: =G26/G27 -> 9.1683385 | I22: =I26/I27 -> 1.0958924 | J22: =J26/J27 -> 1.2490382 | K22: =K26/K27 -> 1.2545216 | L22: =L26/L27 -> 3.2044489 | M22: =M26/M27 -> 6.0280868 | O22: ='Company Basic info'!$E$11/('Balance Sheet '!P31/'Company Basic info'!$E$15) -> 21.295621 | P22: ='Company Basic info'!$E$11/('Balance Sheet '!Q31/'Company Basic info'!$E$15) -> 20.677574 | Q22: ='Company Basic info'!$E$11/('Balance Sheet '!R31/'Company Basic info'!$E$15) -> 18.318101 | R22: ='Company Basic info'!$E$11/('Balance Sheet '!S31/'Company Basic info'!$E$15) -> 17.286034 | S22: ='Company Basic info'!$E$11/('Balance Sheet '!T31/'Company Basic info'!$E$15) -> 15.264436 | U22: ='Company Basic info'!$G$11/('Balance Sheet '!AE29/'Company Basic info'!$G$15) -> 29.540144 | V22: ='Company Basic info'!$G$11/('Balance Sheet '!AF29/'Company Basic info'!$G$15) -> 27.023216 | W22: ='Company Basic info'!$G$11/('Balance Sheet '!AG29/'Company Basic info'!$G$15) -> 24.428652 | X22: ='Company Basic info'!$G$11/('Balance Sheet '!AH29/'Company Basic info'!$G$15) -> 21.73447 | Y22: ='Company Basic info'!$G$11/('Balance Sheet '!AI29/'Company Basic info'!$G$15) -> 18.362531 | AA22: ='Company Basic info'!$F$11/('Balance Sheet '!W40/'Company Basic info'!$F$15) -> 24.16918 | AB22: ='Company Basic info'!$F$11/('Balance Sheet '!X40/'Company Basic info'!$F$15) -> 20.777507 | AC22: ='Company Basic info'!$F$11/('Balance Sheet '!Y40/'Company Basic info'!$F$15) -> 16.581859 | AD22: ='Company Basic info'!$F$11/('Balance Sheet '!Z40/'Company Basic info'!$F$15) -> 13.586329 | AE22: ='Company Basic info'!$F$11/('Balance Sheet '!AA40/'Company Basic info'!$F$15) -> 10.991417 | AF22: ='Company Basic info'!$F$11/('Balance Sheet '!AB40/'Company Basic info'!$F$15) -> 9.1555875
A23: Dividend Yield | C23: =(-'Cash Flow Statement'!B52/'Ratio Analysis'!C28)/'Ratio Analysis'!C26 -> 0.0028038982 | D23: =(-'Cash Flow Statement'!C52/'Ratio Analysis'!D28)/'Ratio Analysis'!D26 -> 0.0011953946 | E23: =(-'Cash Flow Statement'!D52/'Ratio Analysis'!E28)/'Ratio Analysis'!E26 -> 0.00092544112 | F23: =(-'Cash Flow Statement'!E53/'Ratio Analysis'!F28)/'Ratio Analysis'!F26 -> 0.017182247 | G23: =(-'Cash Flow Statement'!F53/'Ratio Analysis'!G28)/'Ratio Analysis'!G26 -> 0.0097569651 | I23: =(-'Cash Flow Statement'!I41/'Ratio Analysis'!I28)/'Ratio Analysis'!I26 -> 0.078085121 | J23: =(-'Cash Flow Statement'!J41/'Ratio Analysis'!J28)/'Ratio Analysis'!J26 -> 0.036226736 | K23: =(-'Cash Flow Statement'!K41/'Ratio Analysis'!K28)/'Ratio Analysis'!K26 -> 0.037216324 | L23: =(-'Cash Flow Statement'!L41/'Ratio Analysis'!L28)/'Ratio Analysis'!L26 -> 0.016166699 | M23: =(-'Cash Flow Statement'!M41/'Ratio Analysis'!M28)/'Ratio Analysis'!M26 -> 0.011896797 | O23: ='Cash Flow Statement'!P51/'Company Basic info'!$E$11 -> 0.0033623772 | P23: ='Cash Flow Statement'!Q51/'Company Basic info'!$E$11 -> 0.0030453043 | Q23: ='Cash Flow Statement'!R51/'Company Basic info'!$E$11 -> 0.0026173659 | R23: ='Cash Flow Statement'!S51/'Company Basic info'!$E$11 -> 0.0030067447 | S23: ='Cash Flow Statement'!T51/'Company Basic info'!$E$11 -> 0.0026150872 | U23: ='Cash Flow Statement'!W49/'Company Basic info'!$G$11 -> 0.0048716449 | V23: ='Cash Flow Statement'!X49/'Company Basic info'!$G$11 -> 0.0019571295 | W23: ='Cash Flow Statement'!Y49/'Company Basic info'!$G$11 -> 0.0022739975 | X23: ='Cash Flow Statement'!Z49/'Company Basic info'!$G$11 -> 0.0023671941 | Y23: ='Cash Flow Statement'!AA49/'Company Basic info'!$G$11 -> 0.0032134195 | AA23: ='Cash Flow Statement'!AD55/'Company Basic info'!$F$11 -> 0.0041846364 | AB23: ='Cash Flow Statement'!AE55/'Company Basic info'!$F$11 -> 0.0031318431 | AC23: ='Cash Flow Statement'!AF55/'Company Basic info'!$F$11 -> 0.0041758012 | AD23: ='Cash Flow Statement'!AG55/'Company Basic info'!$F$11 -> 0.0052197593 | AE23: ='Cash Flow Statement'!AH55/'Company Basic info'!$F$11 -> 0.0061593185 | AF23: ='Cash Flow Statement'!AI55/'Company Basic info'!$F$11 -> 0.007934038
A24: EV/EBITDA | C24: =((C26*C28)-'Balance Sheet '!B24)/'Income Statement'!M20 -> 6.6276178 | D24: =((D26*D28)-'Balance Sheet '!C24)/'Income Statement'!L20 -> 9.424208 | E24: =((E26*E28)-'Balance Sheet '!D24)/'Income Statement'!K20 -> 15.866 | F24: =((F26*F28)-'Balance Sheet '!E24)/'Income Statement'!J20 -> 17.161064 | G24: =((G26*G28)-'Balance Sheet '!F24)/'Income Statement'!I20 -> 27.86445 | I24: =((I26*I28)-'Balance Sheet '!I41)/'Income Statement'!F20 -> -3.2707788 | J24: =((J26*J28)-'Balance Sheet '!J41)/'Income Statement'!E20 -> -5.1257233 | K24: =((K26*K28)-'Balance Sheet '!K41)/'Income Statement'!D20 -> -8.4419279 | L24: =((L26*L28)-'Balance Sheet '!L41)/'Income Statement'!C20 -> 0.070213037 | M24: =((M26*M28)-'Balance Sheet '!M41)/'Income Statement'!B20 -> 9.5176482 | O24: =('Company Basic info'!$E$10+'Balance Sheet '!P33+'Balance Sheet '!P39+'Balance Sheet '!P43-'Balance Sheet '!P19)/('Income Statement'!W15+'Income Statement'!W11+'Income Statement'!W12) -> 62.569869 | P24: =('Company Basic info'!$E$10+'Balance Sheet '!Q33+'Balance Sheet '!Q39+'Balance Sheet '!Q43-'Balance Sheet '!Q19)/('Income Statement'!X15+'Income Statement'!X11+'Income Statement'!X12) -> 119.76821 | Q24: =('Company Basic info'!$E$10+'Balance Sheet '!R33+'Balance Sheet '!R39+'Balance Sheet '!R43-'Balance Sheet '!R19)/('Income Statement'!Y15+'Income Statement'!Y11+'Income Statement'!Y12) -> 63.071983 | R24: =('Company Basic info'!$E$10+'Balance Sheet '!S33+'Balance Sheet '!S39+'Balance Sheet '!S43-'Balance Sheet '!S19)/('Income Statement'!Z15+'Income Statement'!Z11+'Income Statement'!Z12) -> 92.299107 | S24: =('Company Basic info'!$E$10+'Balance Sheet '!T33+'Balance Sheet '!T39+'Balance Sheet '!T43-'Balance Sheet '!T19)/('Income Statement'!AA15+'Income Statement'!AA11+'Income Statement'!AA12) -> 58.4131 | U24: =('Company Basic info'!$G$10+'Balance Sheet '!AE32+'Balance Sheet '!AE40+'Balance Sheet '!AE41-'Balance Sheet '!AE18)/('Income Statement'!P18+'Income Statement'!P13+'Income Statement'!P14) -> 108.15081 | V24: =('Company Basic info'!$G$10+'Balance Sheet '!AF32+'Balance Sheet '!AF40+'Balance Sheet '!AF41-'Balance Sheet '!AF18)/('Income Statement'!Q18+'Income Statement'!Q13+'Income Statement'!Q14) -> 113.5255 | W24: =('Company Basic info'!$G$10+'Balance Sheet '!AG32+'Balance Sheet '!AG40+'Balance Sheet '!AG41-'Balance Sheet '!AG18)/('Income Statement'!R18+'Income Statement'!R13+'Income Statement'!R14) -> 97.839874 | X24: =('Company Basic info'!$G$10+'Balance Sheet '!AH32+'Balance Sheet '!AH40+'Balance Sheet '!AH41-'Balance Sheet '!AH18)/('Income Statement'!S18+'Income Statement'!S13+'Income Statement'!S14) -> 84.890087 | Y24: =('Company Basic info'!$G$10+'Balance Sheet '!AI32+'Balance Sheet '!AI40+'Balance Sheet '!AI41-'Balance Sheet '!AI18)/('Income Statement'!T18+'Income Statement'!T13+'Income Statement'!T14) -> 55.359189 | AA24: =('Company Basic info'!$F$10+'Balance Sheet '!W43+'Balance Sheet '!W45+'Balance Sheet '!W52+'Balance Sheet '!W56-'Balance Sheet '!W25)/('Income Statement'!AD21+'Income Statement'!AD12+'Income Statement'!AD13) -> 60.585013 | AB24: =('Company Basic info'!$F$10+'Balance Sheet '!X43+'Balance Sheet '!X45+'Balance Sheet '!X52+'Balance Sheet '!X56-'Balance Sheet '!X25)/('Income Statement'!AE21+'Income Statement'!AE12+'Income Statement'!AE13) -> 52.960595 | AC24: =('Company Basic info'!$F$10+'Balance Sheet '!Y43+'Balance Sheet '!Y45+'Balance Sheet '!Y52+'Balance Sheet '!Y56-'Balance Sheet '!Y25)/('Income Statement'!AF21+'Income Statement'!AF12+'Income Statement'!AF13) -> 47.915555 | AD24: =('Company Basic info'!$F$10+'Balance Sheet '!Z43+'Balance Sheet '!Z45+'Balance Sheet '!Z52+'Balance Sheet '!Z56-'Balance Sheet '!Z25)/('Income Statement'!AG21+'Income Statement'!AG12+'Income Statement'!AG13) -> 36.527431 | AE24: =('Company Basic info'!$F$10+'Balance Sheet '!AA43+'Balance Sheet '!AA45+'Balance Sheet '!AA52+'Balance Sheet '!AA56-'Balance Sheet '!AA25)/('Income Statement'!AH21+'Income Statement'!AH12+'Income Statement'!AH13) -> 26.22193 | AF24: =('Company Basic info'!$F$10+'Balance Sheet '!AB43+'Balance Sheet '!AB45+'Balance Sheet '!AB52+'Balance Sheet '!AB56-'Balance Sheet '!AB25)/('Income Statement'!AI21+'Income Statement'!AI12+'Income Statement'!AI13) -> 25.051284
A26: Market Price per share | C26: 24.6 | D26: 42 | E26: 70.32 | F26: 98.95 | G26: 205 | I26: 83.03 | J26: 106.15 | K26: 119.85 | L26: 331.52 | M26: 932.05 | O26: 189.95 | P26: 166.5 | Q26: 274.2 | R26: 495 | S26: 888.5 | U26: 198.1 | V26: 185.8 | W26: 226 | X26: 455.4 | Y26: 798 | AA26: 463 | AB26: 508.5 | AC26: 746 | AD26: 1380 | AE26: 3392 | AF26: 4400
A27: Book value per share | C27: ='Balance Sheet '!B36/'Ratio Analysis'!C28 -> 13.479083 | D27: ='Balance Sheet '!C36/'Ratio Analysis'!D28 -> 15.150305 | E27: ='Balance Sheet '!D36/'Ratio Analysis'!E28 -> 16.829831 | F27: ='Balance Sheet '!E36/'Ratio Analysis'!F28 -> 18.987359 | G27: ='Balance Sheet '!F36/'Ratio Analysis'!G28 -> 22.359558 | I27: ='Balance Sheet '!I9/'Ratio Analysis'!I28 -> 75.764735 | J27: ='Balance Sheet '!J9/'Ratio Analysis'!J28 -> 84.985389 | K27: ='Balance Sheet '!K9/'Ratio Analysis'!K28 -> 95.534423 | L27: ='Balance Sheet '!L9/'Ratio Analysis'!L28 -> 103.45617 | M27: ='Balance Sheet '!M9/'Ratio Analysis'!M28 -> 154.61788 | O27: ='Company Basic info'!$E$15 -> 36.65625 | P27: ='Company Basic info'!$E$15 -> 36.65625 | Q27: ='Company Basic info'!$E$15 -> 36.65625 | R27: ='Company Basic info'!$E$15 -> 36.65625 | S27: ='Company Basic info'!$E$15 -> 36.65625 | U27: ='Company Basic info'!$G$15 -> 11.4552 | V27: ='Company Basic info'!$G$15 -> 11.4552 | W27: ='Company Basic info'!$G$15 -> 11.4552 | X27: ='Company Basic info'!$G$15 -> 11.4552 | Y27: ='Company Basic info'!$G$15 -> 11.4552 | AA27: ='Company Basic info'!$F$15 -> 66.8775 | AB27: ='Company Basic info'!$F$15 -> 66.8775 | AC27: ='Company Basic info'!$F$15 -> 66.8775 | AD27: ='Company Basic info'!$F$15 -> 66.8775 | AE27: ='Company Basic info'!$F$15 -> 66.8775 | AF27: ='Company Basic info'!$F$15 -> 66.8775
A28: Shares outstanding (Total) | C28: 730.98 | D28: 730.98 | E28: 730.98 | F28: 730.98 | G28: 730.98 | I28: 40.38 | J28: 40.38 | K28: 40.38 | L28: 40.38 | M28: 40.38 | O28: =O26*O27 -> 6962.8547 | P28: =P26*P27 -> 6103.2656 | Q28: =Q26*Q27 -> 10051.144 | R28: =R26*R27 -> 18144.844 | S28: =S26*S27 -> 32569.078 | U28: =U26*U27 -> 2269.2751 | V28: =V26*V27 -> 2128.3762 | W28: =W26*W27 -> 2588.8752 | X28: =X26*X27 -> 5216.6981 | Y28: =Y26*Y27 -> 9141.2496 | AA28: =AA26*AA27 -> 30964.282 | AB28: =AB26*AB27 -> 34007.209 | AC28: =AC26*AC27 -> 49890.615 | AD28: =AD26*AD27 -> 92290.95 | AE28: =AE26*AE27 -> 226848.48 | AF28: =AF26*AF27 -> 294261
A30: Market Cap | C30: =C26*C28 -> 17982.108 | D30: =D26*D28 -> 30701.16 | E30: =E26*E28 -> 51402.514 | F30: =F26*F28 -> 72330.471 | G30: =G26*G28 -> 149850.9 | I30: =I26*I28 -> 3352.7514 | J30: =J26*J28 -> 4286.337 | K30: =K26*K28 -> 4839.543 | L30: =L26*L28 -> 13386.778 | M30: =M26*M28 -> 37636.179
A31: D/CE | C31: =('Balance Sheet '!B41+'Balance Sheet '!B52)/(Table3[[#This Row],[2020]]-'Balance Sheet '!B58) -> 0 | D31: =('Balance Sheet '!C41+'Balance Sheet '!C52)/(Table3[[#This Row],[2021]]-'Balance Sheet '!C58) -> 0.00010663406 | E31: =('Balance Sheet '!D41+'Balance Sheet '!D52)/(Table3[[#This Row],[2022]]-'Balance Sheet '!D58) -> 8.3045234e-05 | F31: =('Balance Sheet '!E41+'Balance Sheet '!E52)/(Table3[[#This Row],[2023]]-'Balance Sheet '!E58) -> 0.00012863985 | G31: =('Balance Sheet '!F41+'Balance Sheet '!F52)/(Table3[[#This Row],[2024]]-'Balance Sheet '!F58) -> 0.00012914323 | I31: 0 | J31: 0 | K31: 0 | L31: 0 | M31: 0 | O31: =('Balance Sheet '!P33+'Balance Sheet '!P39+'Balance Sheet '!P43)/('Balance Sheet '!P26-'Balance Sheet '!P48) -> 0.0032454779 | P31: =('Balance Sheet '!Q33+'Balance Sheet '!Q39+'Balance Sheet '!Q43)/('Balance Sheet '!Q26-'Balance Sheet '!Q48) -> 0.0022413199 | Q31: =('Balance Sheet '!R33+'Balance Sheet '!R39+'Balance Sheet '!R43)/('Balance Sheet '!R26-'Balance Sheet '!R48) -> 0.0016388127 | R31: =('Balance Sheet '!S33+'Balance Sheet '!S39+'Balance Sheet '!S43)/('Balance Sheet '!S26-'Balance Sheet '!S48) -> 0.00080534594 | S31: =('Balance Sheet '!T33+'Balance Sheet '!T39+'Balance Sheet '!T43)/('Balance Sheet '!T26-'Balance Sheet '!T48) -> 0.00051008323 | U31: =('Balance Sheet '!W43+'Balance Sheet '!W45+'Balance Sheet '!W52+'Balance Sheet '!W56)/('Balance Sheet '!W33-'Balance Sheet '!W61) -> 0.26575405 | V31: =('Balance Sheet '!X43+'Balance Sheet '!X45+'Balance Sheet '!X52+'Balance Sheet '!X56)/('Balance Sheet '!X33-'Balance Sheet '!X61) -> 0.00034310327 | W31: =('Balance Sheet '!Y43+'Balance Sheet '!Y45+'Balance Sheet '!Y52+'Balance Sheet '!Y56)/('Balance Sheet '!Y33-'Balance Sheet '!Y61) -> 7.4619173e-05 | X31: =('Balance Sheet '!Z43+'Balance Sheet '!Z45+'Balance Sheet '!Z52+'Balance Sheet '!Z56)/('Balance Sheet '!Z33-'Balance Sheet '!Z61) -> 7.284917e-05 | Y31: =('Balance Sheet '!AA43+'Balance Sheet '!AA45+'Balance Sheet '!AA52+'Balance Sheet '!AA56)/('Balance Sheet '!AA33-'Balance Sheet '!AA61) -> 2.6334154e-05 | AA31: =('Balance Sheet '!AE32+'Balance Sheet '!AE40+'Balance Sheet '!AE41)/('Balance Sheet '!AE24-'Balance Sheet '!AE48) -> 0 | AB31: =('Balance Sheet '!AF32+'Balance Sheet '!AF40+'Balance Sheet '!AF41)/('Balance Sheet '!AF24-'Balance Sheet '!AF48) -> 0 | AC31: =('Balance Sheet '!AG32+'Balance Sheet '!AG40+'Balance Sheet '!AG41)/('Balance Sheet '!AG24-'Balance Sheet '!AG48) -> 0.0081445352 | AD31: =('Balance Sheet '!AH32+'Balance Sheet '!AH40+'Balance Sheet '!AH41)/('Balance Sheet '!AH24-'Balance Sheet '!AH48) -> 0.20331737 | AE31: =('Balance Sheet '!AI32+'Balance Sheet '!AI40+'Balance Sheet '!AI41)/('Balance Sheet '!AI24-'Balance Sheet '!AI48) -> 0.034561151 | AF31: =('Balance Sheet '!AI32+'Balance Sheet '!AI40)/('Balance Sheet '!AI24-'Balance Sheet '!AI48) -> 0.033615214

Sheet WACC
A1: WACC & Key Assumptions
A2: Component | B2: #VALUE! | C2: #VALUE! | D2: #VALUE! | E2: #VALUE! | F2: #VALUE!
A3: Risk free rate | B3: 0.07365 | C3: 0.07365 | D3: 0.07365 | E3: 0.07365 | F3: 0.07365
A4: Equity risk premium | B4: 0.0726 | C4: 0.0726 | D4: 0.0726 | E4: 0.0726 | F4: 0.0726
A5: Beta | B5: ='Company Basic info'!C16 -> 1.096 | C5: ='Company Basic info'!D16 -> 1.9085 | D5: ='Company Basic info'!E16 -> 1.2893 | E5: ='Company Basic info'!G16 -> 1.5609 | F5: ='Company Basic info'!F16 -> 1.4937
A6: Cost of Equity | B6: =B3+(B4*B5) -> 0.1532196 | C6: =C3+(C4*C5) -> 0.2122071 | D6: =D3+(D4*D5) -> 0.16725318 | E6: =E3+(E4*E5) -> 0.18697134 | F6: =F3+(F4*F5) -> 0.18209262
A7: Cost of debt | B7: =AVERAGE('Income Statement'!B14:F14)/(AVERAGE('Balance Sheet '!B41:F41)+AVERAGE('Balance Sheet '!B43:F43)+AVERAGE('Balance Sheet '!B52:F52)) -> 0.20254649 | C7: 0 | D7: =AVERAGE('Income Statement'!W11:AA11)/(AVERAGE('Balance Sheet '!P33:T33)+AVERAGE('Balance Sheet '!P39)+AVERAGE('Balance Sheet '!P43:T43)) -> 0.45883343 | E7: =AVERAGE('Income Statement'!P13:T13)/(AVERAGE('Balance Sheet '!AG32:AI32)+AVERAGE('Balance Sheet '!AH40:AI40)+AVERAGE('Balance Sheet '!AG41:AI41)) -> 0.024080558 | F7: =AVERAGE('Income Statement'!AD12:AI12)/(AVERAGE('Balance Sheet '!Y45:AB45)+AVERAGE('Balance Sheet '!Y56:AB56)+AVERAGE('Balance Sheet '!W52:X52)) -> 0.043202521
A8: Tax rate | B8: 0.25 | C8: 0.25 | D8: 0.25 | E8: 0.25 | F8: 0.25
A9: After tax cost of debt | B9: =B7*(1-B8) -> 0.15190987 | C9: =C7*(1-C8) -> 0 | D9: =D7*(1-D8) -> 0.34412507 | E9: =E7*(1-E8) -> 0.018060419 | F9: =F7*(1-F8) -> 0.03240189
A10: Market value of equity | B10: ='Company Basic info'!C10 -> 302807.6 | C10: ='Company Basic info'!D10 -> 107714.6 | D10: ='Company Basic info'!E10 -> 53067.25 | E10: ='Company Basic info'!G10 -> 29486.83 | F10: ='Company Basic info'!F10 -> 309415.5
A11: Market value of debt | B11: =('Balance Sheet '!F43+'Balance Sheet '!F52) -> 62.51 | C11: =0 -> 0 | D11: ='Balance Sheet '!T33+'Balance Sheet '!T43 -> 3.7411 | E11: ='Balance Sheet '!AI32+'Balance Sheet '!AI40+'Balance Sheet '!AI41 -> 65.6706 | F11: ='Balance Sheet '!AB45+'Balance Sheet '!AB56 -> 1.16
A12: Total Capital | B12: =B10+B11 -> 302870.11 | C12: =C10+C11 -> 107714.6 | D12: =D10+D11 -> 53070.991 | E12: =E10+E11 -> 29552.501 | F12: =F10+F11 -> 309416.66
A13: Weight of equity | B13: =B10/B12 -> 0.99979361 | C13: =C10/C12 -> 1 | D13: =D10/D12 -> 0.99992951 | E13: =E10/E12 -> 0.99777783 | F13: =F10/F12 -> 0.99999625
A14: Weight of Debt | B14: =(1-B13) -> 0.00020639211 | C14: =(1-C13) -> 0 | D14: =(1-D13) -> 7.0492371e-05 | E14: =(1-E13) -> 0.0022221673 | F14: =(1-F13) -> 3.7489901e-06
A15: WACC | B15: =(B13*B6)+(B9*B14) -> 0.15321933 | C15: =(C13*C6)+(C9*C14) -> 0.2122071 | D15: =(D13*D6)+(D9*D14) -> 0.16726565 | E15: =(E13*E6)+(E9*E14) -> 0.18659599 | F15: =(F13*F6)+(F9*F14) -> 0.18209206
A16: Terminal Growth | B16: 0.055 | C16: 0.055 | D16: 0.055 | E16: 0.055 | F16: 0.055

Sheet DCF
A1: VALUATION
H2: #VALUE! | R2: #VALUE! | AB2: #VALUE! | AL2: #VALUE! | AU2: #VALUE!
A3: Year | B3: 2024 | C3: Growth | D3: 2025 | E3: 2026 | F3: 2027 | G3: 2028 | H3: 2029 | I3: 2030 | K3: Year | L3: 2024 | M3: Growth | N3: 2025 | O3: 2026 | P3: 2027 | Q3: 2028 | R3: 2029 | S3: 2030 | U3: Year | V3: 2024 | W3: Growth | X3: 2025 | Y3: 2026 | Z3: 2027 | AA3: 2028 | AB3: 2029 | AC3: 2030 | AE3: Year | AF3: 2024 | AG3: Growth | AH3: 2025 | AI3: 2026 | AJ3: 2027 | AK3: 2028 | AL3: 2029 | AM3: 2030 | AO3: Year | AP3: 2025 | AQ3: Growth | AR3: 2026 | AS3: 2027 | AT3: 2028 | AU3: 2029 | AV3: 2030
A4: Revenue | B4: ='Income Statement'!B9 -> 10604.6 | C4: =('Income Statement'!B9/'Income Statement'!F9)^(1/5)-1 -> 0.13885993 | D4: =Table22[[#This Row],[2024]]*(1+C4) -> 12077.154 | E4: =Table22[[#This Row],[2025]]*(1+$C$4) -> 13754.187 | F4: =Table22[[#This Row],[2026]]*(1+$C$4) -> 15664.092 | G4: =Table22[[#This Row],[2027]]*(1+$C$4) -> 17839.207 | H4: =Table22[[#This Row],[2028]]*(1+$C$4) -> 20316.358 | I4: =Table22[[#This Row],[2029]]*(1+$C$4) -> 23137.486 | K4: Revenue | L4: ='Income Statement'!I9 -> 20925.23 | M4: =('Income Statement'!I9/'Income Statement'!M9)^(1/5)-1 -> 0.098748777 | N4: =Table23[[#This Row],[2024]]*(1+M4) -> 22991.571 | O4: =Table23[[#This Row],[2025]]*(1+$M$4) -> 25261.96 | P4: =Table23[[#This Row],[2026]]*(1+$M$4) -> 27756.548 | Q4: =Table23[[#This Row],[2027]]*(1+$M$4) -> 30497.473 | R4: =Table23[[#This Row],[2028]]*(1+$M$4) -> 33509.061 | S4: =Table23[[#This Row],[2029]]*(1+$M$4) -> 36818.04 | U4: Revenue | V4: ='Income Statement'!AA6 -> 2731.1044 | W4: =('Income Statement'!AA6/'Income Statement'!X6)^(1/4)-1 -> 0.079874974 | X4: =Table24[[#This Row],[2024]]*(1+W4) -> 2949.2513 | Y4: =Table24[[#This Row],[2025]]*(1+$W$4) -> 3184.8227 | Z4: =Table24[[#This Row],[2026]]*(1+$W$4) -> 3439.2103 | AA4: =Table24[[#This Row],[2027]]*(1+$W$4) -> 3713.9171 | AB4: =Table24[[#This Row],[2028]]*(1+$W$4) -> 4010.5662 | AC4: =Table24[[#This Row],[2029]]*(1+$W$4) -> 4330.91 | AE4: Revenue | AF4: ='Income Statement'!T6 -> 3892.2642 | AG4: =('Income Statement'!T6/'Income Statement'!P6)^(1/5)-1 -> 0.18599248 | AH4: =Table25[[#This Row],[2024]]*(1+$AG$4) -> 4616.1961 | AI4: =Table25[[#This Row],[2025]]*(1+$AG$4) -> 5474.7738 | AJ4: =Table25[[#This Row],[2026]]*(1+$AG$4) -> 6493.0406 | AK4: =Table25[[#This Row],[2027]]*(1+$AG$4) -> 7700.6973 | AL4: =Table25[[#This Row],[2028]]*(1+$AG$4) -> 9132.969 | AM4: =Table25[[#This Row],[2029]]*(1+$AG$4) -> 10831.633 | AO4: Revenue | AP4: ='Income Statement'!AI6 -> 33542.64 | AQ4: =('Income Statement'!AI6/'Income Statement'!AD6)^(1/6)-1 -> 0.074939092 | AR4: =Table26[[#This Row],[2025]]*(1+AQ4) -> 36056.295 | AS4: =Table26[[#This Row],[2026]]*(1+$AQ$4) -> 38758.321 | AT4: =Table26[[#This Row],[2027]]*(1+$AQ$4) -> 41662.834 | AU4: =Table26[[#This Row],[2028]]*(1+$AQ$4) -> 44785.009 | AV4: =Table26[[#This Row],[2029]]*(1+$AQ$4) -> 48141.157
A5: EBIT | B5: ='Income Statement'!B20+'Income Statement'!B14 -> 2466.5 | C5: =('Income Statement'!B37/'Income Statement'!F37)^(1/5)-1 -> 0.26649298 | D5: =Table22[[#This Row],[2024]]*(1+C5) -> 3123.8049 | E5: =Table22[[#This Row],[2025]]*(1+$C$5) -> 3956.277 | F5: =Table22[[#This Row],[2026]]*(1+$C$5) -> 5010.597 | G5: =Table22[[#This Row],[2027]]*(1+$C$5) -> 6345.8859 | H5: =Table22[[#This Row],[2028]]*(1+$C$5) -> 8037.0199 | I5: =Table22[[#This Row],[2029]]*(1+$C$5) -> 10178.829 | K5: EBIT | L5: ='Income Statement'!I36 -> 5341.58 | M5: =('Income Statement'!I36/'Income Statement'!M36)^(1/5)-1 -> 0.16566456 | N5: =Table23[[#This Row],[2024]]*(1+M5) -> 6226.4905 | O5: =Table23[[#This Row],[2025]]*(1+$M$5) -> 7257.9993 | P5: =Table23[[#This Row],[2026]]*(1+$M$5) -> 8460.3925 | Q5: =Table23[[#This Row],[2027]]*(1+$M$5) -> 9861.9797 | R5: =Table23[[#This Row],[2028]]*(1+$M$5) -> 11495.76 | S5: =Table23[[#This Row],[2029]]*(1+$M$5) -> 13400.2 | U5: EBIT | V5: ='Income Statement'!AA24 -> 831.3406 | W5: =('Income Statement'!AA24/'Income Statement'!X24)^(1/4)-1 -> 0.24610562 | X5: =Table24[[#This Row],[2024]]*(1+W5) -> 1035.9382 | Y5: =Table24[[#This Row],[2025]]*(1+$W$5) -> 1290.8884 | Z5: =Table24[[#This Row],[2026]]*(1+$W$5) -> 1608.5833 | AA5: =Table24[[#This Row],[2027]]*(1+$W$5) -> 2004.4647 | AB5: =Table24[[#This Row],[2028]]*(1+$W$5) -> 2497.7747 | AC5: =Table24[[#This Row],[2029]]*(1+$W$5) -> 3112.4911 | AE5: EBIT | AF5: ='Income Statement'!T27 -> 492.4101 | AG5: =('Income Statement'!T27/'Income Statement'!P27)^(1/5)-1 -> 0.15864828 | AH5: =Table25[[#This Row],[2024]]*(1+$AG$5) -> 570.53011 | AI5: =Table25[[#This Row],[2025]]*(1+$AG$5) -> 661.04374 | AJ5: =Table25[[#This Row],[2026]]*(1+$AG$5) -> 765.91719 | AK5: =Table25[[#This Row],[2027]]*(1+$AG$5) -> 887.42863 | AL5: =Table25[[#This Row],[2028]]*(1+$AG$5) -> 1028.2177 | AM5: =Table25[[#This Row],[2029]]*(1+$AG$5) -> 1191.3426 | AO5: EBIT | AP5: ='Income Statement'!AI37 -> 10829.39 | AQ5: =('Income Statement'!AI37/'Income Statement'!AD37)^(1/6)-1 -> 0.1709521 | AR5: =Table26[[#This Row],[2025]]*(1+AQ5) -> 12680.697 | AS5: =Table26[[#This Row],[2026]]*(1+$AQ$5) -> 14848.489 | AT5: =Table26[[#This Row],[2027]]*(1+$AQ$5) -> 17386.869 | AU5: =Table26[[#This Row],[2028]]*(1+$AQ$5) -> 20359.191 | AV5: =Table26[[#This Row],[2029]]*(1+$AQ$5) -> 23839.637
A6: Tax | B6: =B5*Table22[[#This Row],[Growth]] -> 616.625 | C6: 0.25 | D6: =D5*$C$6 -> 780.95123 | E6: =E5*$C$6 -> 989.06925 | F6: =F5*$C$6 -> 1252.6493 | G6: =G5*$C$6 -> 1586.4715 | H6: =H5*$C$6 -> 2009.255 | I6: =I5*$C$6 -> 2544.7073 | K6: Tax | L6: =L5*Table23[[#This Row],[Growth]] -> 1335.395 | M6: 0.25 | N6: =N5*$M$6 -> 1556.6226 | O6: =O5*$M$6 -> 1814.4998 | P6: =P5*$M$6 -> 2115.0981 | Q6: =Q5*$M$6 -> 2465.4949 | R6: =R5*$M$6 -> 2873.9401 | S6: =S5*$M$6 -> 3350.0501 | U6: Tax | V6: =V5*$W$6 -> 207.83515 | W6: 0.25 | X6: =X5*$W$6 -> 258.98455 | Y6: =Y5*$W$6 -> 322.7221 | Z6: =Z5*$W$6 -> 402.14582 | AA6: =AA5*$W$6 -> 501.11617 | AB6: =AB5*$W$6 -> 624.44367 | AC6: =AC5*$W$6 -> 778.12277 | AE6: Tax | AF6: =AF5*Table25[[#This Row],[Growth]] -> 123.10253 | AG6: 0.25 | AH6: =AH5*$AG$6 -> 142.63253 | AI6: =AI5*$AG$6 -> 165.26093 | AJ6: =AJ5*$AG$6 -> 191.4793 | AK6: =AK5*$AG$6 -> 221.85716 | AL6: =AL5*$AG$6 -> 257.05441 | AM6: =AM5*$AG$6 -> 297.83565 | AO6: Tax | AP6: =DCF!AP5*AQ6 -> 2707.3475 | AQ6: 0.25 | AR6: =AR5*$AQ$6 -> 3170.1742 | AS6: =AS5*$AQ$6 -> 3712.1222 | AT6: =AT5*$AQ$6 -> 4346.7172 | AU6: =AU5*$AQ$6 -> 5089.7977 | AV6: =AV5*$AQ$6 -> 5959.9092
A7: NOPAT | B7: =B5-B6 -> 1849.875 | D7: =D5-D6 -> 2342.8537 | E7: =E5-E6 -> 2967.2077 | F7: =F5-F6 -> 3757.9478 | G7: =G5-G6 -> 4759.4144 | H7: =H5-H6 -> 6027.765 | I7: =I5-I6 -> 7634.122 | K7: NOPAT | L7: =L5-L6 -> 4006.185 | N7: =N5-N6 -> 4669.8679 | O7: =O5-O6 -> 5443.4995 | P7: =P5-P6 -> 6345.2944 | Q7: =Q5-Q6 -> 7396.4848 | R7: =R5-R6 -> 8621.8202 | S7: =S5-S6 -> 10050.15 | U7: NOPAT | V7: =V5-V6 -> 623.50545 | X7: =X5-X6 -> 776.95364 | Y7: =Y5-Y6 -> 968.1663 | Z7: =Z5-Z6 -> 1206.4375 | AA7: =AA5-AA6 -> 1503.3485 | AB7: =AB5-AB6 -> 1873.331 | AC7: =AC5-AC6 -> 2334.3683 | AE7: NOPAT | AF7: =AF5-AF6 -> 369.30758 | AH7: =AH5-AH6 -> 427.89759 | AI7: =AI5-AI6 -> 495.7828 | AJ7: =AJ5-AJ6 -> 574.43789 | AK7: =AK5-AK6 -> 665.57147 | AL7: =AL5-AL6 -> 771.16324 | AM7: =AM5-AM6 -> 893.50696 | AO7: NOPAT | AP7: =AP5-AP6 -> 8122.0425 | AR7: =AR5-AR6 -> 9510.5227 | AS7: =AS5-AS6 -> 11136.366 | AT7: =AT5-AT6 -> 13040.152 | AU7: =AU5-AU6 -> 15269.393 | AV7: =AV5-AV6 -> 17879.728
A8: Add: Depreciation | B8: ='Income Statement'!B16 -> 83.13 | C8: =('Income Statement'!B16/'Income Statement'!F16)^(1/5)-1 -> 0.038897863 | D8: =Table22[[#This Row],[2024]]*(1+C8) -> 86.363579 | E8: =Table22[[#This Row],[2025]]*(1+$C$8) -> 89.722938 | F8: =Table22[[#This Row],[2026]]*(1+$C$8) -> 93.212969 | G8: =Table22[[#This Row],[2027]]*(1+$C$8) -> 96.838754 | H8: =Table22[[#This Row],[2028]]*(1+$C$8) -> 100.60557 | I8: =Table22[[#This Row],[2029]]*(1+$C$8) -> 104.51892 | K8: Add: Depreciation | L8: ='Income Statement'!I16 -> 412.43 | M8: =('Income Statement'!I16/'Income Statement'!M16)^(1/5)-1 -> 0.020925747 | N8: =Table23[[#This Row],[2024]]*(1+M8) -> 421.06041 | O8: =Table23[[#This Row],[2025]]*(1+$M$8) -> 429.87141 | P8: =Table23[[#This Row],[2026]]*(1+$M$8) -> 438.86679 | Q8: =Table23[[#This Row],[2027]]*(1+$M$8) -> 448.05041 | R8: =Table23[[#This Row],[2028]]*(1+$M$8) -> 457.4262 | S8: =Table23[[#This Row],[2029]]*(1+$M$8) -> 466.99818 | U8: Add: Depreciation | V8: ='Income Statement'!AA12 -> 67.0392 | W8: =AVERAGE('Income Statement'!W12:AA12)/AVERAGE('Income Statement'!W6:AA6) -> 0.031514487 | X8: =X4*$W$8 -> 92.944141 | Y8: =Y4*$W$8 -> 100.36805 | Z8: =Z4*$W$8 -> 108.38495 | AA8: =AA4*$W$8 -> 117.04219 | AB8: =AB4*$W$8 -> 126.39093 | AC8: =AC4*$W$8 -> 136.48641 | AE8: Add: Depreciation | AF8: ='Income Statement'!T14 -> 41.3266 | AG8: =('Income Statement'!T14/'Income Statement'!P14)^(1/5)-1 -> 0.065525401 | AH8: =Table25[[#This Row],[2024]]*(1+AG8) -> 44.034542 | AI8: =Table25[[#This Row],[2025]]*(1+$AG$8) -> 46.919923 | AJ8: =Table25[[#This Row],[2026]]*(1+$AG$8) -> 49.99437 | AK8: =Table25[[#This Row],[2027]]*(1+$AG$8) -> 53.270271 | AL8: =Table25[[#This Row],[2028]]*(1+$AG$8) -> 56.760827 | AM8: =Table25[[#This Row],[2029]]*(1+$AG$8) -> 60.480103 | AO8: Add: Depreciation | AP8: ='Income Statement'!AI13 -> 1340.37 | AQ8: =('Income Statement'!AI13/'Income Statement'!AD13)^(1/6)-1 -> 0.050295058 | AR8: =Table26[[#This Row],[2025]]*(1+AQ8) -> 1407.784 | AS8: =Table26[[#This Row],[2026]]*(1+$AQ$8) -> 1478.5886 | AT8: =Table26[[#This Row],[2027]]*(1+$AQ$8) -> 1552.9543 | AU8: =Table26[[#This Row],[2028]]*(1+$AQ$8) -> 1631.0602 | AV8: =Table26[[#This Row],[2029]]*(1+$AQ$8) -> 1713.0944
A9: Less: CapEx | B9: ='Cash Flow Statement'!B62 -> 762.2 | C9: =('Cash Flow Statement'!B62/'Cash Flow Statement'!F62)^(1/5)-1 -> 0.031558097 | D9: =Table22[[#This Row],[2024]]*(1+C9) -> 786.25358 | E9: =Table22[[#This Row],[2025]]*(1+$C$9) -> 811.06625 | F9: =Table22[[#This Row],[2026]]*(1+$C$9) -> 836.66196 | G9: =Table22[[#This Row],[2027]]*(1+$C$9) -> 863.06541 | H9: =Table22[[#This Row],[2028]]*(1+$C$9) -> 890.30212 | I9: =Table22[[#This Row],[2029]]*(1+$C$9) -> 918.39836 | K9: Less: CapEx | L9: ='Cash Flow Statement'!M49 -> 103.03 | M9: =AVERAGE('Cash Flow Statement'!I49:M49)/AVERAGE(Table6[[#This Row],[Mar 24]:[Mar 20]]) -> 0.0051630987 | N9: =N4*$M$9 -> 118.70775 | O9: =O4*$M$9 -> 130.42999 | P9: =P4*$M$9 -> 143.3098 | Q9: =Q4*$M$9 -> 157.46146 | R9: =R4*$M$9 -> 173.01059 | S9: =S4*$M$9 -> 190.09517 | U9: Less: CapEx | V9: ='Cash Flow Statement'!T52 -> 80.8897 | W9: =AVERAGE('Cash Flow Statement'!P52:T52)/AVERAGE('Income Statement'!W6:AA6) -> 0.029964035 | X9: =X4*$W$9 -> 88.37147 | Y9: =Y4*$W$9 -> 95.430139 | Z9: =Z4*$W$9 -> 103.05262 | AA9: =AA4*$W$9 -> 111.28394 | AB9: =AB4*$W$9 -> 120.17275 | AC9: =AC4*$W$9 -> 129.77154 | AE9: Less: CapEx | AF9: ='Cash Flow Statement'!AA50 -> 48.0691 | AG9: =AVERAGE('Cash Flow Statement'!W50:AA50)/AVERAGE('Income Statement'!P6:T6) -> 0.032555915 | AH9: =AH4*$AG$9 -> 150.28449 | AI9: =AI4*$AG$9 -> 178.23627 | AJ9: =AJ4*$AG$9 -> 211.38688 | AK9: =AK4*$AG$9 -> 250.70324 | AL9: =AL4*$AG$9 -> 297.33216 | AM9: =AM4*$AG$9 -> 352.63371 | AO9: Less: CapEx | AP9: ='Cash Flow Statement'!AI56 -> 930.09 | AQ9: =AVERAGE('Cash Flow Statement'!AD56:AI56)/AVERAGE('Income Statement'!AD6:AI6) -> 0.030819455 | AR9: =AR4*$AQ$9 -> 1111.2353 | AS9: =AS4*$AQ$9 -> 1194.5103 | AT9: =AT4*$AQ$9 -> 1284.0258 | AU9: =AU4*$AQ$9 -> 1380.2496 | AV9: =AV4*$AQ$9 -> 1483.6842
A10: Less: Change in WC | B10: =('Balance Sheet '!F65-'Balance Sheet '!E65) -> 2554.29 | C10: =('Balance Sheet '!F65/'Balance Sheet '!B65)^(1/5)-1 -> 0.15655156 | D10: =Table22[[#This Row],[2024]]*(1+C10) -> 2954.1681 | E10: =Table22[[#This Row],[2025]]*(1+$C$10) -> 3416.6477 | F10: =Table22[[#This Row],[2026]]*(1+$C$10) -> 3951.5292 | G10: =Table22[[#This Row],[2027]]*(1+$C$10) -> 4570.1472 | H10: =Table22[[#This Row],[2028]]*(1+$C$10) -> 5285.6109 | I10: =Table22[[#This Row],[2029]]*(1+$C$10) -> 6113.0815 | K10: Less: Change in WC | L10: ='Balance Sheet '!M51-'Balance Sheet '!L51 -> 1208.5 | M10: =('Balance Sheet '!M51/'Balance Sheet '!I51)^(1/5)-1 -> 0.14364762 | N10: =Table23[[#This Row],[2024]]*(1+M10) -> 1382.0981 | O10: =Table23[[#This Row],[2025]]*(1+$M$10) -> 1580.6333 | P10: =Table23[[#This Row],[2026]]*(1+$M$10) -> 1807.6875 | Q10: =Table23[[#This Row],[2027]]*(1+$M$10) -> 2067.3575 | R10: =Table23[[#This Row],[2028]]*(1+$M$10) -> 2364.3284 | S10: =Table23[[#This Row],[2029]]*(1+$M$10) -> 2703.9586 | U10: Less: Change in WC | V10: ='Balance Sheet '!T52-'Balance Sheet '!S52 -> 839.0766 | W10: =('Balance Sheet '!T52/'Balance Sheet '!P52)^(1/5)-1 -> 0.22502333 | X10: =Table24[[#This Row],[2024]]*(1+W10) -> 1027.8884 | Y10: =Table24[[#This Row],[2025]]*(1+$W$10) -> 1259.1873 | Z10: =Table24[[#This Row],[2026]]*(1+$W$10) -> 1542.5338 | AA10: =Table24[[#This Row],[2027]]*(1+$W$10) -> 1889.6399 | AB10: =Table24[[#This Row],[2028]]*(1+$W$10) -> 2314.8529 | AC10: =Table24[[#This Row],[2029]]*(1+$W$10) -> 2835.7488 | AE10: Less: Change in WC | AF10: ='Balance Sheet '!AI51-'Balance Sheet '!AH51 -> 264.4606 | AG10: =('Balance Sheet '!AI51/'Balance Sheet '!AE51)^(1/5)-1 -> 0.12031169 | AH10: =Table25[[#This Row],[2024]]*(1+AG10) -> 296.2783 | AI10: =Table25[[#This Row],[2025]]*(1+$AG$10) -> 331.92405 | AJ10: =Table25[[#This Row],[2026]]*(1+$AG$10) -> 371.85839 | AK10: =Table25[[#This Row],[2027]]*(1+$AG$10) -> 416.5973 | AL10: =Table25[[#This Row],[2028]]*(1+$AG$10) -> 466.71883 | AM10: =Table25[[#This Row],[2029]]*(1+$AG$10) -> 522.87056 | AO10: Less: Change in WC | AP10: ='Balance Sheet '!AB64-'Balance Sheet '!AA64 -> 19306.19 | AQ10: =AVERAGE('Balance Sheet '!X64:AA64)/AVERAGE('Income Statement'!AE6:AH6) -> 0.75156119 | AR10: =AR4*$AQ$10 -> 27098.512 | AS10: =AS4*$AQ$10 -> 29129.25 | AT10: =AT4*$AQ$10 -> 31312.169 | AU10: =AU4*$AQ$10 -> 33658.675 | AV10: =AV4*$AQ$10 -> 36181.025
A11: Free Cash Flow to Firm (FCFF) | B11: =B7+B8-B9-B10 -> -1383.485 | D11: =D7+D8-D9-D10 -> -1311.2044 | E11: =E7+E8-E9-E10 -> -1170.7833 | F11: =F7+F8-F9-F10 -> -937.03042 | G11: =G7+G8-G9-G10 -> -576.95946 | H11: =H7+H8-H9-H10 -> -47.542494 | I11: =I7+I8-I9-I10 -> 707.16101 | K11: Free Cash Flow to Firm (FCFF) | L11: =L7+L8-L9-L10 -> 3107.085 | N11: =N7+N8-N9-N10 -> 3590.1224 | O11: =O7+O8-O9-O10 -> 4162.3076 | P11: =P7+P8-P9-P10 -> 4833.1639 | Q11: =Q7+Q8-Q9-Q10 -> 5619.7163 | R11: =R7+R8-R9-R10 -> 6541.9074 | S11: =S7+S8-S9-S10 -> 7623.0946 | U11: Free Cash Flow to Firm (FCFF) | V11: =V7+V8-V9-V10 -> -229.42165 | X11: =X7+X8-X9-X10 -> -246.36209 | Y11: =Y7+Y8-Y9-Y10 -> -286.08306 | Z11: =Z7+Z8-Z9-Z10 -> -330.76399 | AA11: =AA7+AA8-AA9-AA10 -> -380.53311 | AB11: =AB7+AB8-AB9-AB10 -> -435.3037 | AC11: =AC7+AC8-AC9-AC10 -> -494.66564 | AE11: Free Cash Flow to Firm (FCFF) | AF11: =AF7+AF8-AF9-AF10 -> 98.104475 | AH11: =AH7+AH8-AH9-AH10 -> 25.369339 | AI11: =AI7+AI8-AI9-AI10 -> 32.542408 | AJ11: =AJ7+AJ8-AJ9-AJ10 -> 41.186994 | AK11: =AK7+AK8-AK9-AK10 -> 51.541196 | AL11: =AL7+AL8-AL9-AL10 -> 63.873076 | AM11: =AM7+AM8-AM9-AM10 -> 78.482796 | AO11: Free Cash Flow to Firm (FCFF) | AP11: =AP7+AP8-AP9-AP10 -> -10773.867 | AR11: =AR7+AR8-AR9-AR10 -> -17291.44 | AS11: =AS7+AS8-AS9-AS10 -> -17708.805 | AT11: =AT7+AT8-AT9-AT10 -> -18003.089 | AU11: =AU7+AU8-AU9-AU10 -> -18138.471 | AV11: =AV7+AV8-AV9-AV10 -> -18071.887
A12: Discount factor | D12: =1/(1+WACC!$B$15)^1 -> 0.86713774 | E12: =1/(1+WACC!$B$15)^2 -> 0.75192786 | F12: =1/(1+WACC!$B$15)^3 -> 0.65202502 | G12: =1/(1+WACC!$B$15)^4 -> 0.5653955 | H12: =1/(1+WACC!$B$15)^5 -> 0.49027577 | I12: =1/(1+WACC!$B$15)^6 -> 0.42513663 | K12: Discount factor | N12: =1/(1+WACC!$C$15)^1 -> 0.82494155 | O12: =1/(1+WACC!$C$15)^2 -> 0.68052856 | P12: =1/(1+WACC!$C$15)^3 -> 0.56139628 | Q12: =1/(1+WACC!$C$15)^4 -> 0.46311911 | R12: =1/(1+WACC!$C$15)^5 -> 0.3820462 | S12: =1/(1+WACC!$C$15)^6 -> 0.31516578 | U12: Discount factor | X12: =1/(1+WACC!$D$15)^1 -> 0.85670301 | Y12: =1/(1+WACC!$D$15)^2 -> 0.73394006 | Z12: =1/(1+WACC!$D$15)^3 -> 0.62876866 | AA12: =1/(1+WACC!$D$15)^4 -> 0.53866801 | AB12: =1/(1+WACC!$D$15)^5 -> 0.4614785 | AC12: =1/(1+WACC!$D$15)^6 -> 0.39535003 | AE12: Discount factor | AH12: =1/(1+WACC!$E$15)^1 -> 0.84274682 | AI12: =1/(1+WACC!$E$15)^2 -> 0.7102222 | AJ12: =1/(1+WACC!$E$15)^3 -> 0.59853751 | AK12: =1/(1+WACC!$E$15)^4 -> 0.50441558 | AL12: =1/(1+WACC!$E$15)^5 -> 0.42509463 | AM12: =1/(1+WACC!$E$15)^6 -> 0.35824715 | AO12: Discount factor | AR12: =1/(1+WACC!$F$15)^1 -> 0.8459578 | AS12: =1/(1+WACC!$F$15)^2 -> 0.7156446 | AT12: =1/(1+WACC!$F$15)^3 -> 0.60540514 | AU12: =1/(1+WACC!$F$15)^4 -> 0.5121472 | AV12: =1/(1+WACC!$F$15)^5 -> 0.43325492
A13: PV of FCFF | D13: =D11*D12 -> -1136.9948 | E13: =E11*E12 -> -880.34454 | F13: =F11*F12 -> -610.96728 | G13: =G11*G12 -> -326.21028 | H13: =H11*H12 -> -23.308933 | I13: =I11*I12 -> 300.64005 | K13: PV of FCFF | N13: =N11*N12 -> 2961.6411 | O13: =O11*O12 -> 2832.5692 | P13: =P11*P12 -> 2713.3203 | Q13: =Q11*Q12 -> 2602.598 | R13: =R11*R12 -> 2499.3108 | S13: =S11*S12 -> 2402.5386 | U13: PV of FCFF | X13: =X11*X12 -> -211.05915 | Y13: =Y11*Y12 -> -209.96782 | Z13: =Z11*Z12 -> -207.97403 | AA13: =AA11*AA12 -> -204.98101 | AB13: =AB11*AB12 -> -200.8833 | AC13: =AC11*AC12 -> -195.56607 | AE13: PV of FCFF | AH13: =AH11*AH12 -> 21.37993 | AI13: =AI11*AI12 -> 23.112341 | AJ13: =AJ11*AJ12 -> 24.65196 | AK13: =AK11*AK12 -> 25.998182 | AL13: =AL11*AL12 -> 27.152102 | AM13: =AM11*AM12 -> 28.116237 | AO13: PV of FCFF | AR13: =AR11*AR12 -> -14627.829 | AS13: =AS11*AS12 -> -12673.211 | AT13: =AT11*AT12 -> -10899.163 | AU13: =AU11*AU12 -> -9289.5672 | AV13: =AV11*AV12 -> -7829.7341
A15: Revenue CAGR | B15: BEL | C15: =(I4/D4)^(1/6)-1 -> 0.11444488
A16: Revenue CAGR | B16: MDL | C16: =(S4/N4)^(1/6)-1 -> 0.081638168
A17: Revenue CAGR | B17: BDL | C17: =(AC4/X4)^(1/6)-1 -> 0.066132617 | E17: GDP Growth | F17: 2020 | G17: =AVERAGE(-5.8%,9.7%) -> 0.0195
A18: Revenue CAGR | B18: GRSE | C18: =(AM4/AH4)^(1/6)-1 -> 0.15274951 | E18: GDP Growth | F18: 2025 | G18: 0.078
A19: Revenue CAGR | B19: HAL | C19: =(AV4/AR4)^(1/5)-1 -> 0.059514942 | E19: GDP Growth | F19: Change | G19: =G18-G17 -> 0.0585
A20: Revenue CAGR | B20: Average | C20: =AVERAGE(C15:C19) -> 0.094896023 | E20: GDP Growth | F20: Earnings to GDP | G20: =C26/G19 -> 24.969914
A21: Earnings growth | B21: =B15 -> BEL | C21: =('Income Statement'!I29-'Income Statement'!M29)/'Income Statement'!M29 -> 1.2030777
A22: Earnings growth | B22: =B16 -> MDL | C22: =('Income Statement'!B30-'Income Statement'!F30)/'Income Statement'!F30 -> 2.8682583
A23: Earnings growth | B23: =B17 -> BDL | C23: =('Income Statement'!AA22-'Income Statement'!W22)/'Income Statement'!W22 -> 0.14548492
A24: Earnings growth | B24: =B18 -> GRSE | C24: =('Income Statement'!T25-'Income Statement'!P25)/'Income Statement'!P25 -> 1.1853681
A25: Earnings growth | B25: =B19 -> HAL | C25: =('Income Statement'!AI35-'Income Statement'!AD35)/'Income Statement'!AD35 -> 1.9015108
A26: Earnings growth | B26: =B20 -> Average | C26: =AVERAGE(C21:C25) -> 1.46074
A27: Capex senstivity | B27: =B21 -> BEL | C27: =AVERAGE(D9:I9)/AVERAGE(D4:I4) -> 0.049672371
A28: Capex senstivity | B28: =B22 -> MDL | C28: =AVERAGE(N9:S9)/AVERAGE(N4:S4) -> 0.0051630987
A29: Capex senstivity | B29: =B23 -> BDL | C29: =AVERAGE(X9:AC9)/AVERAGE(X4:AC4) -> 0.029964035
A30: Capex senstivity | B30: =B24 -> GRSE | C30: =AVERAGE(AH9:AM9)/AVERAGE(AH4:AM4) -> 0.032555915
A31: Capex senstivity | B31: =B25 -> HAL | C31: =AVERAGE(AR9:AV9)/AVERAGE(AR4:AV4) -> 0.030819455
A32: Capex senstivity | B32: =B26 -> Average | C32: =AVERAGE(C27:C31) -> 0.029634975

Sheet Relative Model
A1: Relative Valuation Model
A3: Company | B3: Current Market Price | C3: EPS | D3: P/E | E3: Shares Outstanding | F3: Book Value | G3: P/B | H3: EV | I3: EBITDA | J3: EV/EBITDA | K3: Revenue | L3: EV/Sales
A4: #VALUE! | B4: {=_FV(A4,"Price")} -> 4789.5 | C4: ='Income Statement'!AI35/'Company Basic info'!F15 -> 125.06508 | D4: =B4/C4 -> 38.296061 | E4: {=_FV(A4,"Shares outstanding",TRUE)/10000000} -> 66.8775 | F4: ='Balance Sheet '!AB40/E4 -> 523.12317 | G4: =B4/F4 -> 9.1555875 | H4: ='Company Basic info'!F10+'Balance Sheet '!AB45+'Balance Sheet '!AB56-'Balance Sheet '!AB25 -> 304868.11 | I4: =('Income Statement'!AI21+'Income Statement'!AI12+'Income Statement'!AI13) -> 12169.76 | J4: =H4/I4 -> 25.051284 | K4: ='Income Statement'!AI6 -> 33542.64 | L4: =H4/K4 -> 9.0889718
A5: #VALUE! | B5: {=_FV(A5,"Price")} -> 1514.45 | C5: ='Income Statement'!AA22/'Company Basic info'!E15 -> 16.715316 | D5: =B5/C5 -> 90.602535 | E5: {=_FV(A5,"Shares outstanding",TRUE)/10000000} -> 36.65625 | F5: ='Balance Sheet '!T31/E5 -> 99.214276 | G5: =B5/F5 -> 15.264436 | H5: ='Company Basic info'!E10+'Balance Sheet '!T43+'Balance Sheet '!T33-'Balance Sheet '!T19 -> 52477.149 | I5: =('Income Statement'!AA15+'Income Statement'!AA11+'Income Statement'!AA12) -> 898.3798 | J5: =H5/I5 -> 58.4131 | K5: ='Income Statement'!AA6 -> 2731.1044 | L5: =H5/K5 -> 19.214626
A6: #VALUE! | B6: {=_FV(A6,"Price")} -> 416.7 | C6: ='Income Statement'!F30/'Company Basic info'!C15 -> 0.65264627 | D6: =B6/C6 -> 638.47756 | E6: {=_FV(A6,"Shares outstanding",TRUE)/10000000} -> 730.9779 | F6: ='Balance Sheet '!F36/E6 -> 22.359623 | G6: =B6/F6 -> 18.636272 | H6: ='Company Basic info'!C10+'Balance Sheet '!F43+'Balance Sheet '!F52-'Balance Sheet '!F24 -> 301663.79 | I6: ='Income Statement'!B20+'Income Statement'!B14+'Income Statement'!B16 -> 2549.63 | J6: =H6/I6 -> 118.31669 | K6: ='Income Statement'!B9 -> 10604.6 | L6: =H6/K6 -> 28.446503
A7: #VALUE! | B7: {=_FV(A7,"Price")} -> 2705.35 | C7: ='Income Statement'!M29/'Company Basic info'!D15 -> 45.235758 | D7: =B7/C7 -> 59.805564 | E7: {=_FV(A7,"Shares outstanding",TRUE)/10000000} -> 40.338 | F7: ='Balance Sheet '!M9/E7 -> 154.77887 | G7: =B7/F7 -> 17.478807 | H7: ='Company Basic info'!D10-'Balance Sheet '!M41 -> 93504.97 | I7: ='Income Statement'!I20+'Income Statement'!I15+'Income Statement'!I16 -> 5754.01 | J7: =H7/I7 -> 16.250401 | K7: ='Income Statement'!I9 -> 20925.23 | L7: =H7/K7 -> 4.4685277
A8: #VALUE! | B8: {=_FV(A8,"Price")} -> 2682 | C8: ='Income Statement'!T25/'Company Basic info'!G15 -> 31.188255 | D8: =B8/C8 -> 85.99391 | E8: {=_FV(A8,"Shares outstanding",TRUE)/10000000} -> 11.4552 | F8: ='Balance Sheet '!AI29/E8 -> 146.08552 | G8: =B8/F8 -> 18.359109 | H8: ='Company Basic info'!G10+'Balance Sheet '!AI32+'Balance Sheet '!AI40+'Balance Sheet '!AI41-'Balance Sheet '!AI18 -> 29547.231 | I8: ='Income Statement'!T18+'Income Statement'!T13+'Income Statement'!T14 -> 533.7367 | J8: =H8/I8 -> 55.359189 | K8: ='Income Statement'!T6 -> 3892.2642 | L8: =H8/K8 -> 7.5912706
A10: Average | D10: =AVERAGE(D4:D8) -> 182.63513 | G10: =AVERAGE(G4:G8) -> 15.778842 | J10: =AVERAGE(J4:J8) -> 54.678133 | L10: =AVERAGE(L4:L8) -> 13.76198
C12: #VALUE! | H12: #VALUE!
A13: Components | B13: Average | C13: Metric | D13: Value | E13: Target Price | F13: Current Market Price | G13: Upside/Downside | H13: Metric | I13: Value | J13: Target Price | K13: Current market Price | L13: Upside/Downside
A14: P/E | B14: =D10 -> 182.63513 | C14: EPS | D14: =C5 -> 16.715316 | E14: =B14*D14 -> 3052.8038 | F14: =$B$5 -> 1514.45 | G14: =(E14-F14)/F14 -> 1.0157838 | H14: EPS | I14: =C4 -> 125.06508 | J14: =B14*I14 -> 22841.277 | K14: =$B$4 -> 4789.5 | L14: =(J14-K14)/K14 -> 3.7690316
A15: P/B | B15: =G10 -> 15.778842 | C15: Book Value | D15: =F5 -> 99.214276 | E15: =B15*D15 -> 1565.4864 | F15: =$B$5 -> 1514.45 | G15: =(E15-F15)/F15 -> 0.033699632 | H15: Book Value | I15: =F4 -> 523.12317 | J15: =B15*I15 -> 8254.278 | K15: =$B$4 -> 4789.5 | L15: =(J15-K15)/K15 -> 0.72341122
A16: EV/EBITDA | B16: =J10 -> 54.678133 | C16: EBITDA | D16: =I5 -> 898.3798 | E16: =(B16*D16)/E5 -> 1340.0643 | F16: =$B$5 -> 1514.45 | G16: =(E16-F16)/F16 -> -0.1151479 | H16: EBITDA | I16: =I4 -> 12169.76 | J16: =(B16*I16)/E4 -> 9949.83 | K16: =$B$4 -> 4789.5 | L16: =(J16-K16)/K16 -> 1.0774256
A17: EV/Sales | B17: =L10 -> 13.76198 | C17: Sales | D17: =K5 -> 2731.1044 | E17: =(B17*D17)/E5 -> 1025.3478 | F17: =$B$5 -> 1514.45 | G17: =(E17-F17)/F17 -> -0.32295701 | H17: Sales | I17: =K4 -> 33542.64 | J17: =(B17*I17)/E4 -> 6902.3683 | K17: =$B$4 -> 4789.5 | L17: =(J17-K17)/K17 -> 0.4411459
E18: =AVERAGE(E14:E17) -> 1745.9256 | J18: =AVERAGE(J14:J17) -> 11986.938
B19: #VALUE! | F19: #VALUE! | J19: #VALUE!
A20: Metric | B20: Value | C20: Target Price | D20: Current Price | E20: Upside/Downside | F20: Value | G20: Target Price | H20: Current Price | I20: Upside/Downside | J20: Value | K20: Target Price | L20: Current Price | M20: Upside/Downside
A21: EPS | B21: =C6 -> 0.65264627 | C21: =B14*B21 -> 119.19613 | D21: =$B$6 -> 416.7 | E21: =(C21-D21)/D21 -> -0.71395216 | F21: =C7 -> 45.235758 | G21: =B14*F21 -> 8261.6384 | H21: =$B$7 -> 2705.35 | I21: =(G21-H21)/H21 -> 2.053815 | J21: =C8 -> 31.188255 | K21: =B14*J21 -> 5696.0709 | L21: =$B$8 -> 2682 | M21: =(K21-L21)/L21 -> 1.1238147
A22: Book Value | B22: =F6 -> 22.359623 | C22: =B15*B22 -> 352.80896 | D22: =$B$6 -> 416.7 | E22: =(C22-D22)/D22 -> -0.15332623 | F22: =F7 -> 154.77887 | G22: =B15*F22 -> 2442.2313 | H22: =$B$7 -> 2705.35 | I22: =(G22-H22)/H22 -> -0.097258636 | J22: =F8 -> 146.08552 | K22: =B15*J22 -> 2305.0604 | L22: =$B$8 -> 2682 | M22: =(K22-L22)/L22 -> -0.1405442
A23: EBITDA | B23: =I6 -> 2549.63 | C23: =(B16*B23)/E6 -> 190.71576 | D23: =$B$6 -> 416.7 | E23: =(C23-D23)/D23 -> -0.54231878 | F23: =I7 -> 5754.01 | G23: =(B16*F23)/E7 -> 7799.5569 | H23: =$B$7 -> 2705.35 | I23: =(G23-H23)/H23 -> 1.8830121 | J23: =I8 -> 533.7367 | K23: =(B16*J23)/E8 -> 2547.6401 | L23: =$B$8 -> 2682 | M23: =(K23-L23)/L23 -> -0.050096921
A24: Sales | B24: =K6 -> 10604.6 | C24: =(B17*B24)/E6 -> 199.65076 | D24: =$B$6 -> 416.7 | E24: =(C24-D24)/D24 -> -0.52087651 | F24: =K7 -> 20925.23 | G24: =(B17*F24)/E7 -> 7138.9904 | H24: =$B$7 -> 2705.35 | I24: =(G24-H24)/H24 -> 1.6388417 | J24: =K8 -> 3892.2642 | K24: =(B17*J24)/E8 -> 4676.0652 | L24: =$B$8 -> 2682 | M24: =(K24-L24)/L24 -> 0.74349931
B25: Average | C25: =AVERAGE(C21:C24) -> 215.5929 | G25: =AVERAGE(G21:G24) -> 6410.6042 | K25: =AVERAGE(K21:K24) -> 3806.2091

Sheet Calc
A1: Year | B1: Metrics | C1: Company | D1: Amount | G1: Company | H1: Change in EBIT (Historical) | I1: Change in CE | J1: Incremental ROCE (Historical) | K1: Change in EBIT (Forecast) | L1: Capex | M1: Depreciation | N1: Effective Capital | O1: Raw ROCE (Forecast) | P1: Adjusted ROCE (Forecast)
A2: 2020-24 | B2: Avg Capex | C2: BEL | D2: =ABS(AVERAGE('Cash Flow Statement'!B42:F42)) -> 605.798 | G2: =C2 -> BEL | H2: =(('Income Statement'!I21+'Income Statement'!I15)-('Income Statement'!M20+'Income Statement'!M15)) -> 2859.58 | I2: =(('Balance Sheet '!F31-'Balance Sheet '!F58)-('Balance Sheet '!B31-'Balance Sheet '!B58)) -> 6366.89 | J2: =H2/I2 -> 0.44913294 | K2: =DCF!I5-DCF!D5 -> 7055.0244 | L2: =D8 -> 850.95795 | M2: =AVERAGE(DCF!D8:I8) -> 95.210455 | N2: =IF(L2-M2<=0,L2,MAX(L2-M2,0.1*L2)) -> 755.74749 | O2: =K2/N2 -> 9.3351608 | P2: =MIN(MAX(O2,0.1),0.25) -> 0.25
A3: 2020-24 | B3: Avg Capex | C3: MDL | D3: =ABS(AVERAGE('Cash Flow Statement'!I29:M29)) -> 43.19 | G3: =C3 -> MDL | H3: =(('Income Statement'!B20+'Income Statement'!B14)-('Income Statement'!F20+'Income Statement'!F14)) -> 1709.55 | I3: =(('Balance Sheet '!M48-'Balance Sheet '!M22)-('Balance Sheet '!I48-'Balance Sheet '!I22)) -> 2333.55 | J3: =H3/I3 -> 0.73259626 | K3: =DCF!S5-DCF!N5 -> 7173.7098 | L3: =D9 -> 152.16913 | M3: =AVERAGE(DCF!N8:S8) -> 443.71223 | N3: =IF(L3-M3<=0,L3,MAX(L3-M3,0.1*L3)) -> 152.16913 | O3: =K3/N3 -> 47.143004 | P3: =MIN(MAX(O3,0.1),0.25) -> 0.25
A4: 2020-24 | B4: Avg Capex | C4: BDL | D4: =ABS(AVERAGE('Cash Flow Statement'!P34:T34)) -> 80.9377 | G4: =C4 -> BDL | H4: =(('Income Statement'!AA15+'Income Statement'!AA11)-('Income Statement'!W15+'Income Statement'!W11)) -> 84.2309 | I4: =(('Balance Sheet '!T26-'Balance Sheet '!T48)-('Balance Sheet '!P26-'Balance Sheet '!P48)) -> 3963.6957 | J4: =H4/I4 -> 0.021250597 | K4: =DCF!AC5-DCF!X5 -> 2076.5529 | L4: =D10 -> 108.01374 | M4: =AVERAGE(DCF!X8:AC8) -> 113.60278 | N4: =IF(L4-M4<=0,L4,MAX(L4-M4,0.1*L4)) -> 108.01374 | O4: =K4/N4 -> 19.224895 | P4: =MIN(MAX(O4,0.1),0.25) -> 0.25
A5: 2020-24 | B5: Avg Capex | C5: GRSE | D5: =ABS(AVERAGE('Cash Flow Statement'!W32:AA32)) -> 75.27338 | G5: =C5 -> GRSE | H5: =(('Income Statement'!T18+'Income Statement'!T13)-('Income Statement'!P18+'Income Statement'!P13)) -> 256.5965 | I5: =(('Balance Sheet '!AI24-'Balance Sheet '!AI48)-('Balance Sheet '!AE24-'Balance Sheet '!AE48)) -> 762.984 | J5: =H5/I5 -> 0.33630653 | K5: =Table25[[#This Row],[2030]]-Table25[[#This Row],[2025]] -> 620.8125 | L5: =D11 -> 240.09612 | M5: =AVERAGE(DCF!AH8:AM8) -> 51.910006 | N5: =IF(L5-M5<=0,L5,MAX(L5-M5,0.1*L5)) -> 188.18612 | O5: =K5/N5 -> 3.2989282 | P5: =MIN(MAX(O5,0.1),0.25) -> 0.25
A6: 2020-25 | B6: Avg Capex | C6: HAL | D6: =ABS(AVERAGE('Cash Flow Statement'!AD34:AI34)) -> 846.905 | G6: =C6 -> HAL | H6: =(('Income Statement'!AI21+'Income Statement'!AI12)-('Income Statement'!AD21+'Income Statement'!AD12)) -> 6628.23 | I6: =(('Balance Sheet '!AB33-'Balance Sheet '!AB61)-('Balance Sheet '!W33-'Balance Sheet '!W61)) -> 40021.42 | J6: =H6/I6 -> 0.16561706 | K6: =DCF!AV5-DCF!AR5 -> 11158.94 | L6: =D12 -> 1290.7411 | M6: =AVERAGE(DCF!AR8:AV8) -> 1556.6963 | N6: =IF(L6-M6<=0,L6,MAX(L6-M6,0.1*L6)) -> 1290.7411 | O6: =K6/N6 -> 8.6453747 | P6: =MIN(MAX(O6,0.1),0.25) -> 0.25
A7: 2020-24 | B7: Avg Capex | C7: Average | D7: =AVERAGE(D2:D6) -> 330.42082 | G7: =C7 -> Average | J7: =AVERAGE(J2:J6) -> 0.34098068 | O7: =AVERAGE(O2:O6) -> 17.529473 | P7: =AVERAGE(P2:P6) -> 0.25
A8: =A14 -> 2025-30 | B8: Avg Capex | C8: =C2 -> BEL | D8: =AVERAGE(DCF!D9:I9) -> 850.95795
A9: =A15 -> 2025-30 | B9: Avg Capex | C9: =C3 -> MDL | D9: =AVERAGE(Table23[[#This Row],[2025]:[2030]]) -> 152.16913
A10: =A16 -> 2025-30 | B10: Avg Capex | C10: =C4 -> BDL | D10: =AVERAGE(DCF!X9:AC9) -> 108.01374
A11: =A17 -> 2025-30 | B11: Avg Capex | C11: =C5 -> GRSE | D11: =AVERAGE(DCF!AH9:AM9) -> 240.09612
A12: =A18 -> 2026-30 | B12: Avg Capex | C12: =C6 -> HAL | D12: =AVERAGE(DCF!AR9:AV9) -> 1290.7411
A13: =A19 -> 2025-30 | B13: Avg Capex | C13: =C7 -> Average | D13: =AVERAGE(D8:D12) -> 528.3956
A14: 2025-30 | B14: Capex CAGR | C14: =C8 -> BEL | D14: =(DCF!I9/DCF!D9)^(1/6)-1 -> 0.026230088
A15: 2025-30 | B15: Capex CAGR | C15: =C9 -> MDL | D15: =(DCF!S9/DCF!N9)^(1/6)-1 -> 0.081638168
A16: 2025-30 | B16: Capex CAGR | C16: =C10 -> BDL | D16: =(DCF!AC9/DCF!X9)^(1/6)-1 -> 0.066132617
A17: 2025-30 | B17: Capex CAGR | C17: =C11 -> GRSE | D17: =(DCF!AM9/DCF!AH9)^(1/6)-1 -> 0.15274951
A18: 2026-30 | B18: Capex CAGR | C18: =C12 -> HAL | D18: =(DCF!AV9/DCF!AR9)^(1/5)-1 -> 0.059514942
A19: 2025-30 | B19: Capex CAGR | C19: =C13 -> Average | D19: =AVERAGE(D14:D18) -> 0.077253065
A20: =A14 -> 2025-30 | B20: =B14 -> Capex CAGR | C20: =C14 -> BEL | D20: =(DCF!I7/DCF!B7)^(1/7)-1 -> 0.22446181
A21: =A15 -> 2025-30 | B21: =B15 -> Capex CAGR | C21: =C15 -> MDL | D21: =(DCF!S7/DCF!L7)^(1/7)-1 -> 0.14041541
A22: =A16 -> 2025-30 | B22: =B16 -> Capex CAGR | C22: =C16 -> BDL | D22: =(DCF!AC7/DCF!V7)^(1/7)-1 -> 0.20754733
A23: =A17 -> 2025-30 | B23: =B17 -> Capex CAGR | C23: =C17 -> GRSE | D23: =(DCF!AM7/DCF!AF7)^(1/7)-1 -> 0.13452919
A24: =A18 -> 2026-30 | B24: =B18 -> Capex CAGR | C24: =C18 -> HAL | D24: =(DCF!AV7/DCF!AP7)^(1/6)-1 -> 0.14055423
A25: =A19 -> 2025-30 | B25: =B19 -> Capex CAGR | C25: =C19 -> Average | D25: =AVERAGE(D20:D24) -> 0.1695016
