Workbook

Sheet Company Profile
A1: COMPANY PROFILE
A2: Parameters | B2: #VALUE! | C2: #VALUE! | D2: #VALUE! | E2: #VALUE! | F2: #VALUE! | G2: #VALUE!
A3: Company | B3: #VALUE! | C3: #VALUE! | D3: #VALUE! | E3: #VALUE! | F3: #VALUE! | G3: #VALUE!
A4: Industry | B4: {=_FV(B3,"Industry")} -> Pharmaceuticals | C4: {=_FV(C3,"Industry")} -> Pharmaceuticals | D4: {=_FV(D3,"Industry")} -> Pharmaceuticals | E4: {=_FV(E3,"Industry")} -> Pharmaceuticals | F4: {=_FV(F3,"Industry")} -> Pharmaceuticals | G4: {=_FV(G3,"Industry")} -> Pharmaceuticals
A5: Beta | B5: {=_FV(B3,"Beta")} -> 0.6846 | C5: {=_FV(C3,"Beta")} -> 0.4776 | D5: {=_FV(D3,"Beta")} -> 0.4693 | E5: {=_FV(E3,"Beta")} -> 0.7232 | F5: {=_FV(F3,"Beta")} -> 0.615 | G5: {=_FV(G3,"Beta")} -> 0.8713
A6: Share Price | B6: {=_FV(B3,"Price")} -> 3817.5 | C6: {=_FV(C3,"Price")} -> 1511.5 | D6: {=_FV(D3,"Price")} -> 1198.7 | E6: {=_FV(E3,"Price")} -> 6691.5 | F6: {=_FV(F3,"Price")} -> 2234.4 | G6: {=_FV(G3,"Price")} -> 1697.8
A7: Shares Outstanding | B7: {=_FV(B3,"Shares outstanding",TRUE)} -> 338445400 | C7: {=_FV(C3,"Shares outstanding",TRUE)} -> 807771200 | D7: {=_FV(D3,"Shares outstanding",TRUE)} -> 832515300 | E7: {=_FV(E3,"Shares outstanding",TRUE)} -> 265468600 | F7: {=_FV(F3,"Shares outstanding",TRUE)} -> 412758500 | G7: {=_FV(G3,"Shares outstanding",TRUE)} -> 2399335000
A8: In crores | B8: =B7/10000000 -> 33.84454 | C8: =C7/10000000 -> 80.77712 | D8: =D7/10000000 -> 83.25153 | E8: =E7/10000000 -> 26.54686 | F8: =F7/10000000 -> 41.27585 | G8: =G7/10000000 -> 239.9335
A9: Market Cap | B9: {=_FV(B3,"Market cap",TRUE)} -> 1211635000000 | C9: {=_FV(C3,"Market cap",TRUE)} -> 1216261000000 | D9: {=_FV(D3,"Market cap",TRUE)} -> 1003514000000 | E9: {=_FV(E3,"Market cap",TRUE)} -> 1767092000000 | F9: {=_FV(F3,"Market cap",TRUE)} -> 933577100000 | G9: {=_FV(G3,"Market cap",TRUE)} -> 4058235000000
A10: Year Incorporated | B10: {=_FV(B3,"Year incorporated",TRUE)} -> 1972 | C10: {=_FV(C3,"Year incorporated",TRUE)} -> 1935 | D10: {=_FV(D3,"Year incorporated",TRUE)} -> 1984 | E10: {=_FV(E3,"Year incorporated",TRUE)} -> 1990 | F10: {=_FV(F3,"Year incorporated",TRUE)} -> 1991 | G10: {=_FV(G3,"Year incorporated",TRUE)} -> 1993
A11: Change | B11: {=_FV(B3,"Change")} -> 237.5 | C11: {=_FV(C3,"Change")} -> 5.8 | D11: {=_FV(D3,"Change")} -> -6.7 | E11: {=_FV(E3,"Change")} -> 35 | F11: {=_FV(F3,"Change")} -> -28.9 | G11: {=_FV(G3,"Change")} -> 6.4
A12: Change (%) | B12: {=_FV(B3,"Change (%)",TRUE)} -> 0.066341 | C12: {=_FV(C3,"Change (%)",TRUE)} -> 0.003852 | D12: {=_FV(D3,"Change (%)",TRUE)} -> -0.005558 | E12: {=_FV(E3,"Change (%)",TRUE)} -> 0.005258 | F12: {=_FV(F3,"Change (%)",TRUE)} -> -0.012769 | G12: {=_FV(G3,"Change (%)",TRUE)} -> 0.003784
A13: P/E | B13: {=_FV(B3,"P/E",TRUE)} -> 60.374 | C13: {=_FV(C3,"P/E",TRUE)} -> 22.4324 | D13: {=_FV(D3,"P/E",TRUE)} -> 17.2931 | E13: {=_FV(E3,"P/E",TRUE)} -> 71.4383 | F13: {=_FV(F3,"P/E",TRUE)} -> 53.19 | G13: {=_FV(G3,"P/E",TRUE)} -> 39.3612

Sheet Balance Sheet
A1: BALANCE SHEET
A2: #VALUE! | I2: #VALUE! | Q2: #VALUE! | Y2: #VALUE! | AG2: #VALUE! | AO2: #VALUE!
A3: Particulars | B3: 2020 | C3: 2021 | D3: 2022 | E3: 2023 | F3: 2024 | G3: 2025 | I3: Particulars | J3: 2020 | K3: 2021 | L3: 2022 | M3: 2023 | N3: 2024 | O3: 2025 | Q3: Particulars | R3: 2020 | S3: 2021 | T3: 2022 | U3: 2023 | V3: 2024 | W3: 2025 | Y3: Particulars | Z3: 2020 | AA3: 2021 | AB3: 2022 | AC3: 2023 | AD3: 2024 | AE3: 2025 | AG3: Particulars | AH3: 2020 | AI3: 2021 | AJ3: 2022 | AK3: 2023 | AL3: 2024 | AM3: 2025 | AO3: Particulars | AP3: 2020 | AQ3: 2021 | AR3: 2022 | AS3: 2023 | AT3: 2024 | AU3: 2025
A4: ASSETS | I4: ASSETS | Q4: ASSETS | Y4: ASSETS | AG4: ASSETS | AO4: ASSETS
A5: Non-Current Assets | I5: Non-Current Assets | Q5: Non-Current Assets | Y5: Non-Current Assets | AG5: Non-Current Assets | AO5: Non-Current Assets
A6: Property, plant and equipment | B6: 2773.16 | C6: 3694.66 | D6: 4314.12 | E6: 4714.17 | F6: 4733 | G6: 5437 | I6: Property, plant and equipment | J6: 10567.43 | K6: 10234.99 | L6: 4969.57 | M6: 4733.25 | N6: 10192.32 | O6: 10035.94 | Q6: Property, plant and equipment | R6: 1551.3441 | S6: 1620.0707 | T6: 1652.363 | U6: 2409.4343 | V6: 2812.53 | W6: 2740.57 | Y6: PPE | Z6: 4912.7 | AA6: 4777.9 | AB6: 4732.2 | AC6: 4886.9 | AD6: 6248.7 | AE6: 7298.4 | AG6: PPE | AH6: 2817.89 | AI6: 2757.79 | AJ6: 2575.08 | AK6: 2626.67 | AL6: 3139.4 | AM6: 3209.24 | AO6: PPE | AP6: 4805.32 | AQ6: 4618.14 | AR6: 4838.79 | AS6: 4583.6 | AT6: 4641.94 | AU6: 4813.88
A7: Right-of-use assets | B7: 5.09 | C7: 4.26 | D7: 3.44 | E7: 3.15 | F7: 2 | G7: 1 | I7: Capital work-in-progress | J7: 658.91 | K7: 936.52 | L7: 358.94 | M7: 328.87 | N7: 1107.73 | O7: 1234.34 | Q7: Capital work-in-progress | R7: 313.2586 | S7: 371.6162 | T7: 669.8734 | U7: 493.182 | V7: 207.1 | W7: 306.13 | Y7: Capital work-in-progress | Z7: 472.5 | AA7: 436.4 | AB7: 953.9 | AC7: 1279.6 | AD7: 1351 | AE7: 2399.4 | AG7: Capital WIP | AH7: 576.61 | AI7: 745.41 | AJ7: 544.34 | AK7: 688.24 | AL7: 280.8 | AM7: 367.26 | AO7: RoU assets | AP7: 322.73 | AQ7: 338.13 | AR7: 325.61 | AS7: 407.18 | AT7: 427.03 | AU7: 448.38
A8: Capital work-in-progress | B8: 919.69 | C8: 710.62 | D8: 469.93 | E8: 211.88 | F8: 778 | G8: 1022 | I8: Goodwill (net) | J8: 6481.46 | K8: 6287.64 | L8: 120.8 | M8: 120.8 | N8: 8568.99 | O8: 8939.42 | Q8: Investment properties | R8: 5.5582 | S8: 5.5035 | T8: 5.4243 | U8: 5.3696 | V8: 5.32 | W8: 0.05 | Y8: Goodwill | Z8: 465.9 | AA8: 491.3 | AB8: 559.9 | AC8: 547.3 | AD8: 550.1 | AE8: 1313.9 | AG8: ROU Assets | AH8: 135.42 | AI8: 125.55 | AJ8: 127.51 | AK8: 144.93 | AL8: 157.57 | AM8: 246.41 | AO8: Capital WIP | AP8: 421 | AQ8: 570.84 | AR8: 382.9 | AS8: 689.17 | AT8: 864.32 | AU8: 1212.76
A9: Intangible assets | B9: 3.6 | C9: 4.95 | D9: 7.49 | E9: 5.28 | F9: 4 | G9: 4 | I9: Other intangible assets | J9: 5798.02 | K9: 5030.35 | L9: 4622.41 | M9: 3857.62 | N9: 4486.84 | O9: 3610.92 | Q9: Goodwill | R9: 20.4422 | S9: 20.4422 | T9: 20.4422 | U9: 20.0225 | V9: 20.02 | W9: 6492.63 | Y9: Other tangible assets | Z9: 1812.4 | AA9: 1581.1 | AB9: 2913.6 | AC9: 2687.3 | AD9: 3626.8 | AE9: 9614.1 | AG9: Goodwill | AH9: 342.09 | AI9: 341.23 | AJ9: 259.48 | AK9: 337.5 | AL9: 338.03 | AM9: 338.88 | AO9: Investment properties | AP9: 124.3 | AQ9: 121.75 | AR9: 61.42 | AS9: 59.83 | AT9: 113.61 | AU9: 111.25
A10: Investments | B10: 0.01 | C10: 0.01 | D10: 72.01 | E10: 77.05 | F10: 82 | G10: 65 | I10: Intangible assets under development | J10: 561.43 | K10: 630.31 | L10: 469.7 | M10: 524.04 | N10: 4246.15 | O10: 5409.62 | Q10: Other intangible assets | R10: 22.2521 | S10: 18.4286 | T10: 1842.6052 | U10: 1701.4633 | V10: 1588.34 | W10: 9604.03 | Y10: Intangible assets under development | Z10: 2461 | AA10: 1098.7 | AB10: 611.2 | AC10: 13.8 | AD10: 68.3 | AE10: 66.2 | AG10: Other tangible assets | AH10: 4237.72 | AI10: 3840.06 | AJ10: 3460.58 | AK10: 5012.35 | AL10: 4503.11 | AM10: 4152.37 | AO10: Goodwill | AP10: 2934 | AQ10: 3007.29 | AR10: 3137.93 | AS10: 2983.86 | AT10: 3112.04 | AU10: 3270.27
A11: Loans | B11: 35.32 | C11: 55.33 | D11: 0 | E11: 0 | F11: 0 | G11: 0 | I11: Investments in associates | J11: 215.39 | K11: 232.73 | L11: 0 | M11: 0 | N11: 0 | O11: 0 | Q11: Intangible assets under development | R11: 3.6946 | S11: 0.3336 | T11: 31.5979 | U11: 56.9536 | V11: 74.7 | W11: 519.54 | Y11: Investment in equity accounted investees | Z11: 252.9 | AA11: 276.3 | AB11: 337.5 | AC11: 431.8 | AD11: 419.6 | AE11: 481.1 | AG11: Intangible assets under development | AH11: 135.32 | AI11: 143.97 | AJ11: 85.48 | AK11: 77.16 | AL11: 79.71 | AM11: 110.88 | AO11: Intangible assets | AP11: 1496.54 | AQ11: 1430.21 | AR11: 1319.58 | AS11: 1126.01 | AT11: 1312.6 | AU11: 1362.61
A12: Other financial assets | B12: 0 | C12: 1.45 | D12: 57.75 | E12: 51.09 | F12: 56 | G12: 62 | I12: Investments in joint venture | J12: 27.57 | K12: 27.83 | L12: 15340.41 | M12: 12401.74 | N12: 0 | O12: 0 | Q12: RoU Assets | R12: 0 | S12: 0 | T12: 67.3571 | U12: 114.3647 | V12: 119.06 | W12: 167.25 | Y12: Investments | Z12: 81.3 | AA12: 32.8 | AB12: 495.8 | AC12: 166.8 | AD12: 105.9 | AE12: 239.3 | AG12: Investments | AH12: 2.09 | AI12: 42.09 | AJ12: 42.33 | AK12: 42.7 | AL12: 31.8 | AM12: 43.57 | AO12: Intangible assets under development | AP12: 403.53 | AQ12: 398.05 | AR12: 383.28 | AS12: 404.13 | AT12: 288.4 | AU12: 353.51
A13: Income tax assets | B13: 0 | C13: 68.6 | D13: 29.17 | E13: 29.17 | F13: 1 | G13: 1 | I13: Investments | J13: 5002.79 | K13: 6221.83 | L13: 15.42 | M13: 14.4 | N13: 6441.23 | O13: 4697.7 | Q13: Investment in associates and joint ventures | R13: 164.3798 | S13: 165.7868 | T13: 167.7428 | U13: 181.4112 | V13: 189.28 | W13: 190.9 | Y13: Trade receivables | Z13: 11.3 | AA13: 173.7 | AB13: 11.8 | AC13: 5.4 | AD13: 0 | AE13: 0 | AG13: Loans | AH13: 2.29 | AI13: 214 | AJ13: 1.75 | AK13: 2.5 | AL13: 2.5 | AM13: 3.37 | AO13: Investment in associates | AP13: 234.97 | AQ13: 228.38 | AR13: 45.81 | AS13: 90.9 | AT13: 130.05 | AU13: 140.47
A14: Deferred tax assets | B14: 4.38 | C14: 3.23 | D14: 14.47 | E14: 14.24 | F14: 10 | G14: 11 | I14: Loans | J14: 0.79 | K14: 0.71 | L14: 3656.63 | M14: 632.7 | N14: 0.85 | O14: 2.79 | Q14: Investments | R14: 0.0125 | S14: 40.0125 | T14: 67.265 | U14: 89.5373 | V14: 120.53 | W14: 160.19 | Y14: Other financial assets | Z14: 73.1 | AA14: 79.3 | AB14: 76.8 | AC14: 277.3 | AD14: 121.2 | AE14: 887.5 | AG14: Other financial assets | AH14: 126.28 | AI14: 52.11 | AJ14: 66.85 | AK14: 48.68 | AL14: 36.87 | AM14: 32.86 | AO14: Investments | AP14: 219.53 | AQ14: 195.3 | AR14: 309.82 | AS14: 481.62 | AT14: 512.16 | AU14: 499.07
A15: Other non-current assets | B15: 114.62 | C15: 56.25 | D15: 54.83 | E15: 21 | F15: 129 | G15: 248 | I15: Other financial assets | J15: 104.88 | K15: 95.78 | L15: 65.13 | M15: 53.89 | N15: 117.95 | O15: 177.04 | Q15: Loans | R15: 0.0993 | S15: 0.0743 | T15: 0.0288 | U15: 0 | V15: 0 | W15: 0 | Y15: Deferred tax assets | Z15: 431.7 | AA15: 1219.9 | AB15: 1068.6 | AC15: 1277 | AD15: 1057.8 | AE15: 1832.5 | AG15: Income tax assets | AH15: 188.88 | AI15: 55.89 | AJ15: 122.21 | AK15: 135.8 | AL15: 308.79 | AM15: 226.35 | AO15: Loans | AP15: 52.39 | AQ15: 52.99 | AR15: 0.04 | AS15: 0 | AT15: 16.98 | AU15: 32.54
A16: Total Non-current assets | B16: =SUM(B6:B15) -> 3855.87 | C16: =SUM(C6:C15) -> 4599.36 | D16: =SUM(D6:D15) -> 5023.21 | E16: =SUM(E6:E15) -> 5127.03 | F16: =SUM(F6:F15) -> 5795 | G16: =SUM(G6:G15) -> 6851 | I16: Deferred tax assets (net) | J16: 3175.29 | K16: 3556.44 | L16: 324.04 | M16: 1032.39 | N16: 4103.65 | O16: 4407.55 | Q16: Other financial assets | R16: 30.9299 | S16: 22.4287 | T16: 22.9265 | U16: 110.1814 | V16: 29.5 | W16: 200.33 | Y16: Tax assets | Z16: 340 | AA16: 437.9 | AB16: 274.5 | AC16: 328.5 | AD16: 371.8 | AE16: 182.1 | AG16: Deferred tax assets | AH16: 433.21 | AI16: 421.66 | AJ16: 493.65 | AK16: 543.67 | AL16: 555.13 | AM16: 594.15 | AO16: Other financial assets | AP16: 42.04 | AQ16: 42.88 | AR16: 417.04 | AS16: 99.32 | AT16: 508.56 | AU16: 283.46
A17: Current Assets | I17: Income tax assets (net) | J17: 3384.25 | K17: 3432.78 | L17: 883.67 | M17: 586.13 | N17: 2285.03 | O17: 420.67 | Q17: Income tax assets | R17: 54.5116 | S17: 55.6056 | T17: 79.8242 | U17: 102.5153 | V17: 81.98 | W17: 189.49 | Y17: Other non-current assets | Z17: 40.7 | AA17: 20.9 | AB17: 30.7 | AC17: 62.9 | AD17: 137.3 | AE17: 94 | AG17: Other non current assets | AH17: 31.02 | AI17: 23.65 | AJ17: 25.93 | AK17: 22.47 | AL17: 15.38 | AM17: 41.83 | AO17: Income tax assets | AP17: 468.62 | AQ17: 468.16 | AR17: 483.62 | AS17: 548 | AT17: 463.67 | AU17: 487.86
A18: Inventories | B18: 1863.86 | C18: 2145.23 | D18: 2828.62 | E18: 3000.41 | F18: 3184 | G18: 3236 | I18: Other non-current assets | J18: 620.09 | K18: 636.74 | L18: 235.01 | M18: 236.51 | N18: 473.93 | O18: 540.12 | Q18: Deferred tax assets | R18: 47.9389 | S18: 49.011 | T18: 39.2862 | U18: 29.7769 | V18: 80.39 | W18: 107.89 | Y18: Total non current assets | Z18: =SUM(Z6:Z17) -> 11355.5 | AA18: =SUM(AA6:AA17) -> 10626.2 | AB18: =SUM(AB6:AB17) -> 12066.5 | AC18: =SUM(AC6:AC17) -> 11964.6 | AD18: =SUM(AD6:AD17) -> 14058.5 | AE18: =SUM(AE6:AE17) -> 24408.5 | AG18: Total non-current assets | AH18: =SUM(AH6:AH17) -> 9028.82 | AI18: =SUM(AI6:AI17) -> 8763.41 | AJ18: =SUM(AJ6:AJ17) -> 7805.19 | AK18: =SUM(AK6:AK17) -> 9682.67 | AL18: =SUM(AL6:AL17) -> 9449.09 | AM18: =SUM(AM6:AM17) -> 9367.17 | AO18: Deferred tax assets | AP18: 239.77 | AQ18: 314.69 | AR18: 448.83 | AS18: 456.54 | AT18: 587.8 | AU18: 644.87
A19: Investments | B19: 971.35 | C19: 0 | D19: 0 | E19: 0 | F19: 0 | G19: 0 | I19: Total non-current assets | J19: =SUM(J6:J18) -> 36598.3 | K19: =SUM(K6:K18) -> 37324.65 | L19: =SUM(L6:L18) -> 31061.73 | M19: =SUM(M6:M18) -> 24522.34 | N19: =SUM(N6:N18) -> 42024.67 | O19: =SUM(O6:O18) -> 39476.11 | Q19: Other non-current assets | R19: 36.6462 | S19: 96.6766 | T19: 74.1843 | U19: 73.355 | V19: 66.28 | W19: 92.26 | Y19: Current Assets | AG19: Current assets | AO19: Other non current assets | AP19: 191.64 | AQ19: 155.57 | AR19: 218.91 | AS19: 258.17 | AT19: 297.25 | AU19: 437.59
A20: Trade Receivables | B20: 1413.35 | C20: 1676.52 | D20: 2423.88 | E20: 1792.53 | F20: 2156 | G20: 2731 | I20: Current Assets | Q20: Total non-current assets | R20: =SUM(R6:R19) -> 2251.068 | S20: =SUM(S6:S19) -> 2465.9903 | T20: =SUM(T6:T19) -> 4740.9209 | U20: =SUM(U6:U19) -> 5387.5671 | V20: =SUM(V6:V19) -> 5395.03 | W20: =SUM(W6:W19) -> 20771.26 | Y20: Inventories | Z20: 3557.9 | AA20: 3506.7 | AB20: 4541.2 | AC20: 5088.4 | AD20: 6355.2 | AE20: 7108.5 | AG20: Inventories | AH20: 2148.22 | AI20: 2681.2 | AJ20: 2462.32 | AK20: 2229.64 | AL20: 2279.07 | AM20: 2541.25 | AO20: Total non current assets | AP20: =SUM(AP6:AP19) -> 11956.38 | AQ20: =SUM(AQ6:AQ19) -> 11942.38 | AR20: =SUM(AR6:AR19) -> 12373.58 | AS20: =SUM(AS6:AS19) -> 12188.33 | AT20: =SUM(AT6:AT19) -> 13276.41 | AU20: =SUM(AU6:AU19) -> 14098.52
A21: Cash and cash Equivalents | B21: 43.15 | C21: 2030.32 | D21: 1214.76 | E21: 169.7 | F21: 363 | G21: 415 | I21: Inventories | J21: 7874.99 | K21: 8997.02 | L21: 3403.74 | M21: 3989.19 | N21: 9868.29 | O21: 10243.33 | Q21: Current assets | Y21: Investments | Z21: 2252.9 | AA21: 2368.7 | AB21: 1378.5 | AC21: 2017.3 | AD21: 4405 | AE21: 3330.7 | AG21: Investments | AH21: 0.02 | AI21: 139.05 | AJ21: 183.98 | AK21: 156.09 | AL21: 141.04 | AM21: 112.21 | AO21: Current Assets
A22: Bank Balance | B22: 79.48 | C22: 125.71 | D22: 1604.12 | E22: 4043.39 | F22: 3617 | G22: 3300 | I22: Investments | J22: 4897.36 | K22: 3130.06 | L22: 193.04 | M22: 200.26 | N22: 8584.54 | O22: 13656.1 | Q22: Inventories | R22: 899.1345 | S22: 1183.5377 | T22: 1760.2381 | U22: 1498.4582 | V22: 1553.46 | W22: 2093.71 | Y22: Trade receivables | Z22: 3986.9 | AA22: 5027.8 | AB22: 4964.1 | AC22: 6676.4 | AD22: 8029.8 | AE22: 9042 | AG22: Trade receivables | AH22: 1649.34 | AI22: 1523.37 | AJ22: 1632.48 | AK22: 1943.82 | AL22: 1844.3 | AM22: 1866.45 | AO22: Inventories | AP22: 4377.6 | AQ22: 4669.18 | AR22: 5350.24 | AS22: 5156.43 | AT22: 5237.95 | AU22: 5642.11
A23: Loans | B23: 0.09 | C23: 0 | D23: 0 | E23: 0 | F23: 0 | G23: 0 | I23: Trade receivables | J23: 9421.24 | K23: 9061.4 | L23: 4245.16 | M23: 7125.02 | N23: 11249.37 | O23: 13046.11 | Q23: Investments | R23: 665.0325 | S23: 1306.1741 | T23: 874.4618 | U23: 1075.4741 | V23: 2258.11 | W23: 1690.84 | Y23: Derivative Instruments | Z23: 36 | AA23: 110.5 | AB23: 121.8 | AC23: 190.6 | AD23: 16.9 | AE23: 55.7 | AG23: Cash and cash equivalents | AH23: 661.82 | AI23: 572.56 | AJ23: 398.4 | AK23: 508.53 | AL23: 835.14 | AM23: 573.48 | AO23: Investments | AP23: 1016.52 | AQ23: 2286.37 | AR23: 2194.97 | AS23: 3089.86 | AT23: 4807.01 | AU23: 7293.23
A24: Other financial assets | B24: 3.89 | C24: 9.47 | D24: 4.89 | E24: 6.07 | F24: 7 | G24: 16 | I24: Cash and cash equivalents | J24: 5676.61 | K24: 6273.03 | L24: 419.53 | M24: 410.28 | N24: 9285.65 | O24: 10268.77 | Q24: Trade Receivables | R24: 531.092 | S24: 330.6113 | T24: 388.166 | U24: 576.4214 | V24: 848.28 | W24: 1538.34 | Y24: Cash and cash equivalents | Z24: 222.8 | AA24: 205.3 | AB24: 1482.9 | AC24: 1485.2 | AD24: 710.7 | AE24: 1465.4 | AG24: Bank balances | AH24: 4.83 | AI24: 30.94 | AJ24: 5.01 | AK24: 62.93 | AL24: 3.9 | AM24: 5.98 | AO24: Trade receivables | AP24: 3891.31 | AQ24: 3445.68 | AR24: 3424.44 | AS24: 4057 | AT24: 4770.66 | AU24: 5506.37
A25: Income tax assets | B25: 79.05 | C25: 34.27 | D25: 57.68 | E25: 97.87 | F25: 28 | G25: 13 | I25: Bank balances | J25: 810.94 | K25: 172.48 | L25: 115.43 | M25: 11 | N25: 1235.03 | O25: 1062.85 | Q25: Cash and cash equivalents | R25: 226.0753 | S25: 167.182 | T25: 302.5347 | U25: 304.8207 | V25: 382.01 | W25: 407.36 | Y25: Bank Balances | Z25: 0 | AA25: 0 | AB25: 595.9 | AC25: 934 | AD25: 1017 | AE25: 994.8 | AG25: Loans | AH25: 3.64 | AI25: 3.08 | AJ25: 2.61 | AK25: 1.71 | AL25: 3.05 | AM25: 4.22 | AO25: Cash and cash equivalents | AP25: 742.38 | AQ25: 793.29 | AR25: 677.74 | AS25: 627.63 | AT25: 640.07 | AU25: 588.69
A26: Other current assets | B26: 225.61 | C26: 153.19 | D26: 217.55 | E26: 201.77 | F26: 320 | G26: 370 | I26: Loans | J26: 148.38 | K26: 56.01 | L26: 9.1 | M26: 3347.03 | N26: 65.02 | O26: 48.38 | Q26: Bank Balances | R26: 193.802 | S26: 533.5598 | T26: 103.4068 | U26: 148.3779 | V26: 326.09 | W26: 147.14 | Y26: Other financial assets | Z26: 211.2 | AA26: 337.7 | AB26: 185.8 | AC26: 157.4 | AD26: 2252.7 | AE26: 314.2 | AG26: Other financial assets | AH26: 81.69 | AI26: 120.79 | AJ26: 167.98 | AK26: 108.41 | AL26: 200.68 | AM26: 182.85 | AO26: Bank Balances | AP26: 261.53 | AQ26: 607.94 | AR26: 1250.74 | AS26: 936.99 | AT26: 234.9 | AU26: 211.15
A27: Total Current assets | B27: =SUM(B18:B26) -> 4679.83 | C27: =SUM(C18:C26) -> 6174.71 | D27: =SUM(D18:D26) -> 8351.5 | E27: =SUM(E18:E26) -> 9311.74 | F27: =SUM(F18:F26) -> 9675 | G27: =SUM(G18:G26) -> 10081 | I27: Other financial assets | J27: 929.34 | K27: 875.93 | L27: 402.18 | M27: 582.4 | N27: 917.2 | O27: 1740.66 | Q27: Loans | R27: 34.4979 | S27: 18.4114 | T27: 1.1944 | U27: 1.6326 | V27: 2.86 | W27: 3.95 | Y27: Other current assets | Z27: 1042.4 | AA27: 1042.4 | AB27: 1265 | AC27: 1233 | AD27: 2018 | AE27: 2706.8 | AG27: Other current assets | AH27: 429.5 | AI27: 450.51 | AJ27: 312.21 | AK27: 302.59 | AL27: 304.3 | AM27: 336.13 | AO27: Loans | AP27: 5.6 | AQ27: 2.58 | AR27: 3.57 | AS27: 7.59 | AT27: 0.24 | AU27: 15.64
A28: Total Assets | B28: =B16+B27 -> 8535.7 | C28: =C16+C27 -> 10774.07 | D28: =D16+D27 -> 13374.71 | E28: =E16+E27 -> 14438.77 | F28: =F16+F27 -> 15470 | G28: =G16+G27 -> 16932 | I28: Other current assets | J28: 1895.3 | K28: 1876.15 | L28: =915.57+21.4 -> 936.97 | M28: =778.57+21.4 -> 799.97 | N28: 2228.01 | O28: 2527.86 | Q28: Others | R28: 4.4869 | S28: 9.9912 | T28: 13.9371 | U28: 55.9797 | V28: 503.03 | W28: 301.41 | Y28: Total current assets | Z28: =SUM(Z20:Z27) -> 11310.1 | AA28: =SUM(AA20:AA27) -> 12599.1 | AB28: =SUM(AB20:AB27) -> 14535.2 | AC28: =SUM(AC20:AC27) -> 17782.3 | AD28: =SUM(AD20:AD27) -> 24805.3 | AE28: =SUM(AE20:AE27) -> 25018.1 | AG28: Total current assets | AH28: =SUM(AH20:AH27) -> 4979.06 | AI28: =SUM(AI20:AI27) -> 5521.5 | AJ28: =SUM(AJ20:AJ27) -> 5164.99 | AK28: =SUM(AK20:AK27) -> 5313.72 | AL28: =SUM(AL20:AL27) -> 5611.48 | AM28: =SUM(AM20:AM27) -> 5622.57 | AO28: Other financial assets | AP28: 522.28 | AQ28: 481.66 | AR28: 898.39 | AS28: 2080.57 | AT28: 2801.52 | AU28: 2936.9
A29: EQUITY AND LIABILITIES | I29: Total current assets | J29: =SUM(J21:J28) -> 31654.16 | K29: =SUM(K21:K28) -> 30442.08 | L29: =SUM(L21:L28) -> 9725.15 | M29: =SUM(M21:M28) -> 16465.15 | N29: =SUM(N21:N28) -> 43433.11 | O29: =SUM(O21:O28) -> 52594.06 | Q29: Other current assets | R29: 265.381 | S29: 354.4653 | T29: 959.8978 | U29: 663.3918 | V29: 691.68 | W29: 802.82 | Y29: Total assets | Z29: =Z18+Z28 -> 22665.6 | AA29: =AA18+AA28 -> 23225.3 | AB29: =AB18+AB28 -> 26601.7 | AC29: =AC18+AC28 -> 29746.9 | AD29: =AD18+AD28 -> 38863.8 | AE29: =AE18+AE28 -> 49426.6 | AG29: Non-current assets held for sale | AH29: 1.86 | AI29: 1.72 | AJ29: 129.66 | AK29: 15.46 | AL29: 0 | AM29: 0 | AO29: Other current assets | AP29: 886.62 | AQ29: 894.33 | AR29: 910.74 | AS29: 848.99 | AT29: 900.1 | AU29: 1054.88
A30: Equity | I30: Total Assets | J30: =J19+J29 -> 68252.46 | K30: =K19+K29 -> 67766.73 | L30: =L19+L29 -> 40786.88 | M30: =M19+M29 -> 40987.49 | N30: =N19+N29 -> 85457.78 | O30: =O19+O29 -> 92070.17 | Q30: Assets held for sale | R30: 2.7105 | S30: 2.702 | T30: 2.9816 | U30: 3.3156 | V30: 2.7 | W30: 2.7 | Y30: EQUITY AND LIABILITIES | AG30: Total assets | AH30: =AH28+AH29+AH18 -> 14009.74 | AI30: =AI28+AI29+AI18 -> 14286.63 | AJ30: =AJ28+AJ29+AJ18 -> 13099.84 | AK30: =AK28+AK29+AK18 -> 15011.85 | AL30: =AL28+AL29+AL18 -> 15060.57 | AM30: =AM28+AM29+AM18 -> 14989.74 | AO30: Total current assets | AP30: =SUM(AP22:AP29) -> 11703.84 | AQ30: =SUM(AQ22:AQ29) -> 13181.03 | AR30: =SUM(AR22:AR29) -> 14710.83 | AS30: =SUM(AS22:AS29) -> 16805.06 | AT30: =SUM(AT22:AT29) -> 19392.45 | AU30: =SUM(AU22:AU29) -> 23248.97
A31: Equity share capital | B31: 53.09 | C31: 53.09 | D31: 53.09 | E31: 53.09 | F31: 53 | G31: 53 | I31: EQUITY AND LIABILITIES | Q31: Total current assets | R31: =SUM(R22:R30) -> 2822.2126 | S31: =SUM(S22:S30) -> 3906.6348 | T31: =SUM(T22:T30) -> 4406.8183 | U31: =SUM(U22:U30) -> 4327.872 | V31: =SUM(V22:V30) -> 6568.22 | W31: =SUM(W22:W30) -> 6988.27 | Y31: Equity | AG31: EQUITY AND LIABILITIES | AO31: Assets classified for sale | AP31: 2.34 | AQ31: 28.48 | AR31: 16.71 | AS31: 469.89 | AT31: 48.96 | AU31: 39.55
A32: Other Equity | B32: 7256.83 | C32: 9241.52 | D32: 11675.09 | E32: 12714 | F32: 13518 | G32: 14916 | I32: Equity | Q32: Total assets | R32: =R20+R31 -> 5073.2806 | S32: =S20+S31 -> 6372.6251 | T32: =T20+T31 -> 9147.7392 | U32: =U20+U31 -> 9715.4391 | V32: =V20+V31 -> 11963.25 | W32: =W20+W31 -> 27759.53 | Y32: Equity share capital | Z32: 83 | AA32: 83.1 | AB32: 83.2 | AC32: 83.2 | AD32: 83.4 | AE32: 83.4 | AG32: Equity | AO32: Total assets | AP32: =AP30+AP20+AP31 -> 23662.56 | AQ32: =AQ30+AQ20+AQ31 -> 25151.89 | AR32: =AR30+AR20+AR31 -> 27101.12 | AS32: =AS30+AS20+AS31 -> 29463.28 | AT32: =AT30+AT20+AT31 -> 32717.82 | AU32: =AU30+AU20+AU31 -> 37387.04
A33: Total Equity | B33: =SUM(B31:B32) -> 7309.92 | C33: =SUM(C31:C32) -> 9294.61 | D33: =SUM(D31:D32) -> 11728.18 | E33: =SUM(E31:E32) -> 12767.09 | F33: =SUM(F31:F32) -> 13571 | G33: =SUM(G31:G32) -> 14969 | I33: Equity share capital | J33: 239.93 | K33: 239.93 | L33: 239.93 | M33: 239.93 | N33: 239.93 | O33: 239.93 | Q33: EQUITY AND LIABILITIES | Y33: Other equity | Z33: 13940.6 | AA33: 15515.7 | AB33: 17558.5 | AC33: 19129.2 | AD33: 28171.4 | AE33: 33466.2 | AG33: Equity share capital | AH33: 84.62 | AI33: 84.62 | AJ33: 84.62 | AK33: 169.23 | AL33: 169.23 | AM33: 169.23 | AO33: Equity and Liabilities
A34: LIABILITIES | I34: Other equity | J34: 45024.52 | K34: 46222.85 | L34: 24348.02 | M34: 23508.43 | N34: 63426.82 | O34: 71978.09 | Q34: Equity | Y34: Non-controlling interests | Z34: 0 | AA34: 0 | AB34: 0 | AC34: 0 | AD34: 0 | AE34: 377.8 | AG34: Other equity | AH34: 4738.6 | AI34: 5752.55 | AJ34: 5868.33 | AK34: 6028.84 | AL34: 6686.92 | AM34: 7421.46 | AO34: Equity
A35: Non-current liabilities | I35: Non-controlling interests | J35: 3860.24 | K35: 3017.05 | L35: 0 | M35: 0 | N35: 3459.19 | O35: 267.93 | Q35: Equity share capital | R35: 40.0588 | S35: 40.0588 | T35: 40.0588 | U35: 40.0588 | V35: 40.06 | W35: 41.26 | Y35: Total equity | Z35: =SUM(Z32:Z34) -> 14023.6 | AA35: =SUM(AA32:AA34) -> 15598.8 | AB35: =SUM(AB32:AB34) -> 17641.7 | AC35: =SUM(AC32:AC34) -> 19212.4 | AD35: =SUM(AD32:AD34) -> 28254.8 | AE35: =SUM(AE32:AE34) -> 33927.4 | AG35: Non-controlling interests | AH35: 0 | AI35: 0 | AJ35: 0 | AK35: 0 | AL35: 0 | AM35: 0 | AO35: Equity share capital | AP35: 161.25 | AQ35: 161.29 | AR35: 161.36 | AS35: 161.43 | AT35: 161.47 | AU35: 161.52
A36: Lease Liabilities | B36: 4.47 | C36: 3.69 | D36: 2.87 | E36: 2.77 | F36: 2 | G36: 2 | I36: Total equity | J36: =SUM(J33:J35) -> 49124.69 | K36: =SUM(K33:K35) -> 49479.83 | L36: =SUM(L33:L35) -> 24587.95 | M36: =SUM(M33:M35) -> 23748.36 | N36: =SUM(N33:N35) -> 67125.94 | O36: =SUM(O33:O35) -> 72485.95 | Q36: Other equity | R36: 3445.2514 | S36: 4681.945 | T36: 6115.1733 | U36: 7395.164 | V36: 9323.03 | W36: 14291.13 | Y36: LIABILITIES | AG36: Total equity | AH36: =SUM(AH33:AH35) -> 4823.22 | AI36: =SUM(AI33:AI35) -> 5837.17 | AJ36: =SUM(AJ33:AJ35) -> 5952.95 | AK36: =SUM(AK33:AK35) -> 6198.07 | AL36: =SUM(AL33:AL35) -> 6856.15 | AM36: =SUM(AM33:AM35) -> 7590.69 | AO36: Other equity | AP36: 15601.75 | AQ36: 18165.24 | AR36: 20680.33 | AS36: 23246.35 | AT36: 26544.96 | AU36: 31031.93
A37: Other financial liabilities | B37: 0 | C37: 0 | D37: 0 | E37: 0 | F37: 0 | G37: 0 | I37: LIABILITIES | Q37: Non-controlling interests | R37: 186.2611 | S37: 140.8874 | T37: 161.0799 | U37: 188.0701 | V37: 212.7 | W37: 235.79 | Y37: Non-current liabilities | AG37: Non-current liabilities | AO37: Non-controlling interest | AP37: 294.28 | AQ37: 259.06 | AR37: 275.69 | AS37: 305.76 | AT37: 95.9 | AU37: 95.8
A38: Borrowings | B38: 0 | C38: 0 | D38: 0 | E38: 0 | F38: 0 | G38: 0 | I38: Non-current liabilities | Q38: Total Equity | R38: =SUM(R35:R37) -> 3671.5713 | S38: =SUM(S35:S37) -> 4862.8912 | T38: =SUM(T35:T37) -> 6316.312 | U38: =SUM(U35:U37) -> 7623.2929 | V38: =SUM(V35:V37) -> 9575.79 | W38: =SUM(W35:W37) -> 14568.18 | Y38: Borrowings | Z38: 2200 | AA38: 130.4 | AB38: 380 | AC38: 380 | AD38: 380 | AE38: 380 | AG38: Borrowings | AH38: 3275.22 | AI38: 2941.07 | AJ38: 2123.22 | AK38: 2496.22 | AL38: 1603.78 | AM38: 1191.75 | AO38: Total equity | AP38: =SUM(AP35:AP37) -> 16057.28 | AQ38: =SUM(AQ35:AQ37) -> 18585.59 | AR38: =SUM(AR35:AR37) -> 21117.38 | AS38: =SUM(AS35:AS37) -> 23713.54 | AT38: =SUM(AT35:AT37) -> 26802.33 | AU38: =SUM(AU35:AU37) -> 31289.25
A39: Provisions | B39: 20.52 | C39: 25.25 | D39: 26.71 | E39: 30.62 | F39: 37 | G39: 0 | I39: Borrowings | J39: 2028.92 | K39: 898.13 | L39: 4865.64 | M39: 7586.73 | N39: 1.33 | O39: 2.52 | Q39: LIABILITIES | Y39: Lease Liabilities | Z39: 10.2 | AA39: 0 | AB39: 249.9 | AC39: 194.6 | AD39: 219 | AE39: 406.4 | AG39: Other financial liabilities | AH39: 110.62 | AI39: 29.71 | AJ39: 5.04 | AK39: 20.87 | AL39: 9.24 | AM39: 13.8 | AO39: Share application money pending allotment | AP39: 0 | AQ39: 0 | AR39: 0 | AS39: 0 | AT39: 0 | AU39: 0
A40: Deferred tax liabilities (net) | B40: 273.96 | C40: 338.06 | D40: 421.4 | E40: 537.21 | F40: 582 | G40: 509 | I40: Other financial liabilities | J40: 42.41 | K40: 19.58 | L40: 0 | M40: 391.22 | N40: 302.29 | O40: 355.74 | Q40: Non-current Liabilities | Y40: Other financial liabilities | Z40: 0 | AA40: 0 | AB40: 0 | AC40: 0 | AD40: 0 | AE40: 19.8 | AG40: Provisions | AH40: 338.34 | AI40: 369.62 | AJ40: 368.74 | AK40: 393.06 | AL40: 444.69 | AM40: 501.27 | AO40: Liabilities
A41: Total Non-current liabilities | B41: =SUM(B36:B40) -> 298.95 | C41: =SUM(C36:C40) -> 367 | D41: =SUM(D36:D40) -> 450.98 | E41: =SUM(E36:E40) -> 570.6 | F41: =SUM(F36:F40) -> 621 | G41: =SUM(G36:G40) -> 511 | I41: Provisions | J41: 511 | K41: 327.12 | L41: 397.63 | M41: 206.16 | N41: 0 | O41: 10.68 | Q41: Borrowings | R41: 58.1927 | S41: 57.4199 | T41: 49.194 | U41: 23.1465 | V41: 24.87 | W41: 5526.19 | Y41: Provisions | Z41: 79.3 | AA41: 74.5 | AB41: 50.8 | AC41: 25.8 | AD41: 23.9 | AE41: 29.8 | AG41: Other non-current liabilities | AH41: 8.18 | AI41: 5.46 | AJ41: 4.42 | AK41: 1.46 | AL41: 0.96 | AM41: 0.46 | AO41: Non-current liabilities
A42: Current Liabilities | I42: Lease Liabilities | J42: 0 | K42: 0 | L42: 189.68 | M42: 181.51 | N42: 413.89 | O42: 465.04 | Q42: Lease Liabilities | R42: 3.8282 | S42: 5.5105 | T42: 2.99 | U42: 5.178 | V42: 7.71 | W42: 14.03 | Y42: Deferred tax liabilities | Z42: 47.3 | AA42: 2 | AB42: 28.9 | AC42: 1.4 | AD42: 84.1 | AE42: 1403.8 | AG42: Lease liabilities | AH42: 0 | AI42: 0 | AJ42: 36.82 | AK42: 52.93 | AL42: 64.46 | AM42: 145.86 | AO42: Borrowings | AP42: 2369.28 | AQ42: 1202.75 | AR42: 416.24 | AS42: 0 | AT42: 0 | AU42: 11.98
A43: Borrowings | B43: 33.63 | C43: 0.35 | D43: 0 | E43: 0 | F43: 0 | G43: 2 | I43: Deferred tax liabilities | J43: 58.14 | K43: 44.51 | L43: 0 | M43: 0 | N43: 171.86 | O43: 192.44 | Q43: Provisions | R43: 63.0049 | S43: 72.2443 | T43: 80.0043 | U43: 97.8888 | V43: 123.12 | W43: 155.06 | Y43: Other non-current liabilities | Z43: 207.9 | AA43: 205.5 | AB43: 161.7 | AC43: 166.9 | AD43: 314 | AE43: 225.6 | AG43: Deferred tax liabilities | AH43: 0 | AI43: 0 | AJ43: 193.56 | AK43: 401.94 | AL43: 656.05 | AM43: 828.72 | AO43: Lease liabilities | AP43: 0 | AQ43: 0 | AR43: 158.28 | AS43: 208.82 | AT43: 225.42 | AU43: 240.49
A44: Lease Liabilities | B44: 0.75 | C44: 0.79 | D44: 0.82 | E44: 0.49 | F44: 1 | G44: 0 | I44: Other non-current liabilities | J44: 780.87 | K44: 751.93 | L44: 618.75 | M44: 507.45 | N44: 499.94 | O44: =385.24+8.76 -> 394 | Q44: Deferred tax liabilities | R44: 8.1665 | S44: 13.0319 | T44: 55.6206 | U44: 77.3121 | V44: 89.07 | W44: 1812.51 | Y44: Total non-current liabilities | Z44: =SUM(Z38:Z43) -> 2544.7 | AA44: =SUM(AA38:AA43) -> 412.4 | AB44: =SUM(AB38:AB43) -> 871.3 | AC44: =SUM(AC38:AC43) -> 768.7 | AD44: =SUM(AD38:AD43) -> 1021 | AE44: =SUM(AE38:AE43) -> 2465.4 | AG44: Total non-current liabilities | AH44: =SUM(AH38:AH43) -> 3732.36 | AI44: =SUM(AI38:AI43) -> 3345.86 | AJ44: =SUM(AJ38:AJ43) -> 2731.8 | AK44: =SUM(AK38:AK43) -> 3366.48 | AL44: =SUM(AL38:AL43) -> 2779.18 | AM44: =SUM(AM38:AM43) -> 2681.86 | AO44: Other financial liabilities | AP44: 276.9 | AQ44: 295.61 | AR44: 100.37 | AS44: 113.7 | AT44: 67.81 | AU44: 102.39
A45: Total outstanding dues of micro and small enterprises | B45: 11.74 | C45: 32.48 | D45: 24.78 | E45: 37.49 | F45: 35 | G45: 37 | I45: Total non-current liabilities | J45: =SUM(J39:J44) -> 3421.34 | K45: =SUM(K39:K44) -> 2041.27 | L45: =SUM(L39:L44) -> 6071.7 | M45: =SUM(M39:M44) -> 8873.07 | N45: =SUM(N39:N44) -> 1389.31 | O45: =SUM(O39:O44) -> 1420.42 | Q45: Other non-current liabilities | R45: 17.7873 | S45: 7.8869 | T45: 20.1542 | U45: 25.4946 | V45: 22.96 | W45: 20 | Y45: Current Liabilities | AG45: Current liabilities | AO45: Provisions | AP45: 133.27 | AQ45: 116.17 | AR45: 100.22 | AS45: 102.16 | AT45: 129.26 | AU45: 148.69
A46: Total outstanding dues of creditors other than above | B46: 578.98 | C46: 730.72 | D46: 770.92 | E46: 725.02 | F46: 789 | G46: 873 | I46: Current Liabilities | Q46: Total non-current liabilities | R46: =SUM(R41:R45) -> 150.9796 | S46: =SUM(S41:S45) -> 156.0935 | T46: =SUM(T41:T45) -> 207.9631 | U46: =SUM(U41:U45) -> 229.02 | V46: =SUM(V41:V45) -> 267.73 | W46: =SUM(W41:W45) -> 7527.79 | Y46: Borrowings | Z46: 1212.5 | AA46: 1653.2 | AB46: 2314.5 | AC46: 2708.2 | AD46: 1272.3 | AE46: 3804.5 | AG46: Borrowings | AH46: 1090.85 | AI46: 704.4 | AJ46: 1894.88 | AK46: 2801.08 | AL46: 2333.64 | AM46: 1834.34 | AO46: Deferred tax liabilities | AP46: 365.21 | AQ46: 296.61 | AR46: 243.96 | AS46: 163.28 | AT46: 185.29 | AU46: 53.53
A47: Total trade payables | B47: =B45+B46 -> 590.72 | C47: =C45+C46 -> 763.2 | D47: =D45+D46 -> 795.7 | E47: =E45+E46 -> 762.51 | F47: =F45+F46 -> 824 | G47: =G45+G46 -> 910 | I47: Borrowings | J47: 5549.38 | K47: 2444.9 | L47: 3.07 | M47: 5.94 | N47: 2844.36 | O47: 1867.11 | Q47: Current Liabilities | Y47: Lease Liabilities | Z47: 0 | AA47: 0 | AB47: 0 | AC47: 0 | AD47: 130.7 | AE47: 85.7 | AG47: Total outstanding dues of micro and small enterprises | AH47: 13.19 | AI47: 19.96 | AJ47: 20.36 | AK47: 17.96 | AL47: 16.12 | AM47: 23.13 | AO47: Other non-current liabilities | AP47: 67.48 | AQ47: 63.61 | AR47: 51.46 | AS47: 52.11 | AT47: 61.94 | AU47: 56.75
A48: Other financial liabilities | B48: 105.57 | C48: 80.42 | D48: 62.89 | E48: 43.39 | F48: 100 | G48: 134 | I48: Trade Payables | J48: 3583.64 | K48: 3973.66 | L48: =105.28+2605.16 -> 2710.44 | M48: =119.42+3006.16 -> 3125.58 | N48: 5653.3 | O48: 6184.34 | Q48: Borrowings | R48: 44.2802 | S48: 158.6039 | T48: 818.8332 | U48: 139.4899 | V48: 171.17 | W48: 2956.84 | Y48: Total outstanding dues of micro and small enterprises | Z48: 7.7 | AA48: 5.5 | AB48: 15.8 | AC48: 12.5 | AD48: 28.2 | AE48: 21 | AG48: Total outstanding dues of creditors | AH48: 2035.62 | AI48: 2046.85 | AJ48: 1654.08 | AK48: 1660.84 | AL48: 2073.2 | AM48: 1796.89 | AO48: Total non current liabilities | AP48: =SUM(AP42:AP47) -> 3212.14 | AQ48: =SUM(AQ42:AQ47) -> 1974.75 | AR48: =SUM(AR42:AR47) -> 1070.53 | AS48: =SUM(AS42:AS47) -> 640.07 | AT48: =SUM(AT42:AT47) -> 669.72 | AU48: =SUM(AU42:AU47) -> 613.83
A49: Current Tax liabilities | B49: 9.93 | C49: 5.98 | D49: 1.68 | E49: 2.21 | F49: 43 | G49: 0 | I49: Other financial liabilities | J49: 1888.73 | K49: 4237.35 | L49: 4067.81 | M49: 4064.01 | N49: 1506.7 | O49: 1947.84 | Q49: Lease Liabilities | R49: 0 | S49: 0 | T49: 2.0572 | U49: 2.5565 | V49: 3.42 | W49: 14.39 | Y49: Total outstanding dues of creditors other than above | Z49: 1359.4 | AA49: 1519.3 | AB49: 1795.1 | AC49: 2253.7 | AD49: 2586.2 | AE49: 2626.8 | AG49: Total Trade payables | AH49: =SUM(AH47:AH48) -> 2048.81 | AI49: =SUM(AI47:AI48) -> 2066.81 | AJ49: =SUM(AJ47:AJ48) -> 1674.44 | AK49: =SUM(AK47:AK48) -> 1678.8 | AL49: =SUM(AL47:AL48) -> 2089.32 | AM49: =SUM(AM47:AM48) -> 1820.02 | AO49: Current Liabilities
A50: Other current liabilities | B50: 183.77 | C50: 259.21 | D50: 330.31 | E50: 287.56 | F50: 303 | G50: 352 | I50: Other current liabilities | J50: 646.29 | K50: 727.99 | L50: 746.31 | M50: 343.77 | N50: 1084.46 | O50: 1169.79 | Q50: Total outstanding dues of micro and small enterprises | R50: 81.0221 | S50: 102.702 | T50: 114.472 | U50: 60.5007 | V50: 79.4 | W50: 86.29 | Y50: Total trade payables | Z50: =Z48+Z49 -> 1367.1 | AA50: =AA48+AA49 -> 1524.8 | AB50: =AB48+AB49 -> 1810.9 | AC50: =AC48+AC49 -> 2266.2 | AD50: =AD48+AD49 -> 2614.4 | AE50: =AE48+AE49 -> 2647.8 | AG50: Lease liabilities | AH50: 0 | AI50: 0 | AJ50: 14.73 | AK50: 18.33 | AL50: 20.06 | AM50: 30.37 | AO50: Borrowings | AP50: 447.15 | AQ50: 334.73 | AR50: 407.9 | AS50: 520.36 | AT50: 247.02 | AU50: 80.12
A51: Provisions | B51: 2.46 | C51: 2.51 | D51: 4.15 | E51: 4.92 | F51: 7 | G51: 54 | I51: Provisions | J51: 3836.36 | K51: 4582.65 | L51: 2562.55 | M51: 809.5 | N51: 5357.56 | O51: 6155.13 | Q51: Total outstanding dues of creditors other than above | R51: 664.088 | S51: 564.2574 | T51: 961.9252 | U51: 947.6762 | V51: 697.66 | W51: 1047.11 | Y51: Derivative Instruments | Z51: 6.8 | AA51: 160.2 | AB51: 32.6 | AC51: 47.9 | AD51: 46.8 | AE51: 128.6 | AG51: Other financial liabilities | AH51: 1753.78 | AI51: 1507.3 | AJ51: 279.27 | AK51: 420.98 | AL51: 284.66 | AM51: 392.62 | AO51: Total outstanding dues of micro and small enterprises | AP51: 81.19 | AQ51: 69.33 | AR51: 175.12 | AS51: 225.91 | AT51: 253.54 | AU51: 278.6
A52: Total Current liabilities | B52: =SUM(B43:B44,B47,B48:B51) -> 926.83 | C52: =SUM(C43:C44,C47,C48:C51) -> 1112.46 | D52: =SUM(D43:D44,D47,D48:D51) -> 1195.55 | E52: =SUM(E43:E44,E47,E48:E51) -> 1101.08 | F52: =SUM(F43:F44,F47,F48:F51) -> 1278 | G52: =SUM(G43:G44,G47,G48:G51) -> 1452 | I52: Lease Liabilities | J52: 0 | K52: 0 | L52: 15.65 | M52: 16.64 | N52: 125.69 | O52: 136.82 | Q52: Total Trade payables | R52: =R50+R51 -> 745.1101 | S52: =S50+S51 -> 666.9594 | T52: =T50+T51 -> 1076.3972 | U52: =U50+U51 -> 1008.1769 | V52: =V50+V51 -> 777.06 | W52: =W50+W51 -> 1133.4 | Y52: Other financial liabilities | Z52: 2267 | AA52: 2700.6 | AB52: 2341.7 | AC52: 2483.2 | AD52: 3454 | AE52: 3969.8 | AG52: Provisions | AH52: 418.58 | AI52: 431.06 | AJ52: 411.03 | AK52: 393.71 | AL52: 400.14 | AM52: 408.13 | AO52: Total outstanding dues of creditors other than above | AP52: 2200.62 | AQ52: 1997.49 | AR52: 2332.98 | AS52: 2231.14 | AT52: 2220.44 | AU52: 2558.89
A53: Total Equity and Liabilities | B53: =B33+B41+B52 -> 8535.7 | C53: =C33+C41+C52 -> 10774.07 | D53: =D33+D41+D52 -> 13374.71 | E53: =E33+E41+E52 -> 14438.77 | F53: =F33+F41+F52 -> 15470 | G53: =G33+G41+G52 -> 16932 | I53: Current tax liabillities | J53: 202.03 | K53: 179.08 | L53: 0 | M53: 0.62 | N53: =411.7+0.63 -> 412.33 | O53: 733.18 | Q53: Other financial liabilities | R53: 120.5857 | S53: 183.5869 | T53: 221.489 | U53: 236.4918 | V53: 561.49 | W53: 674.16 | Y53: Liabilities for current tax | Z53: 18.1 | AA53: 57.2 | AB53: 138.8 | AC53: 544.2 | AD53: 1143.7 | AE53: 1319 | AG53: Current tax liabilities | AH53: 35.12 | AI53: 53.99 | AJ53: 41.48 | AK53: 31.31 | AL53: 167.93 | AM53: 95.57 | AO53: Total trade payables | AP53: =AP51+AP52 -> 2281.81 | AQ53: =AQ51+AQ52 -> 2066.82 | AR53: =AR51+AR52 -> 2508.1 | AS53: =AS51+AS52 -> 2457.05 | AT53: =AT51+AT52 -> 2473.98 | AU53: =AU51+AU52 -> 2837.49
I54: Total current liabilities | J54: =SUM(J47:J53) -> 15706.43 | K54: =SUM(K47:K53) -> 16145.63 | L54: =SUM(L47:L53) -> 10105.83 | M54: =SUM(M47:M53) -> 8366.06 | N54: =SUM(N47:N53) -> 16984.4 | O54: =SUM(O47:O53) -> 18194.21 | Q54: Provisions | R54: 215.6704 | S54: 234.2185 | T54: 264.5026 | U54: 307.6304 | V54: 427.31 | W54: 663.87 | Y54: Provisions | Z54: 478.9 | AA54: 466.9 | AB54: 501.5 | AC54: 586.6 | AD54: 234.1 | AE54: 302.8 | AG54: Other current liabilities | AH54: 107.02 | AI54: 128.06 | AJ54: 99.26 | AK54: 103.09 | AL54: 129.5 | AM54: 136.14 | AO54: Lease liabilities | AP54: 0 | AQ54: 0 | AR54: 73.36 | AS54: 73.94 | AT54: 86.97 | AU54: 105.6
I55: Total Equity and Liabilities | J55: =J36+J45+J54 -> 68252.46 | K55: =K36+K45+K54 -> 67666.73 | L55: =L36+L45+L54 -> 40765.48 | M55: =M36+M45+M54 -> 40987.49 | N55: =N36+N45+N54 -> 85499.65 | O55: =O36+O45+O54 -> 92100.58 | Q55: Income tax liabilities | R55: 65.6224 | S55: 11.0847 | T55: 15.0896 | U55: 46.2555 | V55: 8.38 | W55: 18.08 | Y55: Other current liabilities | Z55: 546.9 | AA55: 651.2 | AB55: 877.4 | AC55: 1027.8 | AD55: 692 | AE55: 775.6 | AG55: Total current liabilities | AH55: =SUM(AH46,AH49,AH50:AH54) -> 5454.16 | AI55: =SUM(AI46,AI49,AI50:AI54) -> 4891.62 | AJ55: =SUM(AJ46,AJ49,AJ50:AJ54) -> 4415.09 | AK55: =SUM(AK46,AK49,AK50:AK54) -> 5447.3 | AL55: =SUM(AL46,AL49,AL50:AL54) -> 5425.25 | AM55: =SUM(AM46,AM49,AM50:AM54) -> 4717.19 | AO55: Other financial liabilities | AP55: 530.36 | AQ55: 733.99 | AR55: 370.83 | AS55: 394.54 | AT55: 492.14 | AU55: 374.54
Q56: Other current liabilities | R56: 59.4609 | S56: 99.187 | T56: 225.0953 | U56: 122.5352 | V56: 170.9 | W56: 202.82 | Y56: Total current liabilities | Z56: =SUM(Z46,Z50,Z51:Z55) -> 5897.3 | AA56: =SUM(AA46,AA50,AA51:AA55) -> 7214.1 | AB56: =SUM(AB46,AB50,AB51:AB55) -> 8017.4 | AC56: =SUM(AC46,AC50,AC51:AC55) -> 9664.1 | AD56: =SUM(AD46,AD50,AD51:AD55) -> 9457.3 | AE56: =SUM(AE46,AE50,AE51:AE55) -> 12948.1 | AG56: Total equity and liabilities | AH56: =AH36+AH44+AH55 -> 14009.74 | AI56: =AI36+AI44+AI55 -> 14074.65 | AJ56: =AJ36+AJ44+AJ55 -> 13099.84 | AK56: =AK36+AK44+AK55 -> 15011.85 | AL56: =AL36+AL44+AL55 -> 15060.58 | AM56: =AM36+AM44+AM55 -> 14989.74 | AO56: Other current liabilities | AP56: 176.29 | AQ56: 359.22 | AR56: 311.06 | AS56: 284.13 | AT56: 311.87 | AU56: 292.85
Q57: Total current liabilities | R57: =SUM(R48,R52,R53:R56) -> 1250.7297 | S57: =SUM(S48,S52,S53:S56) -> 1353.6404 | T57: =SUM(T48,T52,T53:T56) -> 2621.4069 | U57: =SUM(U48,U52,U53:U56) -> 1860.5797 | V57: =SUM(V48,V52,V53:V56) -> 2116.31 | W57: =SUM(W48,W52,W53:W56) -> 5649.17 | Y57: Total equity and liabilities | Z57: =Z35+Z44+Z56 -> 22465.6 | AA57: =AA35+AA44+AA56 -> 23225.3 | AB57: =AB35+AB44+AB56 -> 26530.4 | AC57: =AC35+AC44+AC56 -> 29645.2 | AD57: =AD35+AD44+AD56 -> 38733.1 | AE57: =AE35+AE44+AE56 -> 49340.9 | AO57: Provisions | AP57: 948.19 | AQ57: 1078.32 | AR57: 1221 | AS57: 1286.67 | AT57: 1611.76 | AU57: 1716.61
Q58: Total Equity and Liabilities | R58: =R38+R46+R57 -> 5073.2806 | S58: =S38+S46+S57 -> 6372.6251 | T58: =T38+T46+T57 -> 9145.682 | U58: =U38+U46+U57 -> 9712.8926 | V58: =V38+V46+V57 -> 11959.83 | W58: =W38+W46+W57 -> 27745.14 | AO58: Income tax liabilities | AP58: 9.34 | AQ58: 18.06 | AR58: 20.62 | AS58: 16.58 | AT58: 22.03 | AU58: 76.75
AO59: Total current liabilities | AP59: =SUM(AP50,AP53,AP54:AP58) -> 4393.14 | AQ59: =SUM(AQ50,AQ53,AQ54:AQ58) -> 4591.14 | AR59: =SUM(AR50,AR53,AR54:AR58) -> 4912.87 | AS59: =SUM(AS50,AS53,AS54:AS58) -> 5033.27 | AT59: =SUM(AT50,AT53,AT54:AT58) -> 5245.77 | AU59: =SUM(AU50,AU53,AU54:AU58) -> 5483.96
AO60: Liabilities directly associated with assets classified as held for sale | AP60: 0 | AQ60: 0.41 | AR60: 0.34 | AS60: 76.4 | AT60: 0 | AU60: 0
AO61: Total Equity and liabilities | AP61: =AP38+AP48+AP59+AP60+AP39 -> 23662.56 | AQ61: =AQ38+AQ48+AQ59+AQ60+AQ39 -> 25151.89 | AR61: =AR38+AR48+AR59+AR60+AR39 -> 27101.12 | AS61: =AS38+AS48+AS59+AS60+AS39 -> 29463.28 | AT61: =AT38+AT48+AT59+AT60+AT39 -> 32717.82 | AU61: =AU38+AU48+AU59+AU60+AU39 -> 37387.04

Sheet Balance Sheet Forecast
A2: #VALUE! | H2: #VALUE! | O2: #VALUE! | V2: #VALUE! | AC2: #VALUE! | AJ2: #VALUE!
A3: Particulars | B3: 2026 | C3: 2027 | D3: 2028 | E3: 2029 | F3: 2030 | H3: Particulars | I3: 2026 | J3: 2027 | K3: 2028 | L3: 2029 | M3: 2030 | O3: Particulars | P3: 2026 | Q3: 2027 | R3: 2028 | S3: 2029 | T3: 2030 | V3: Particulars | W3: 2026 | X3: 2027 | Y3: 2028 | Z3: 2029 | AA3: 2030 | AC3: Particulars | AD3: 2026 | AE3: 2027 | AF3: 2028 | AG3: 2029 | AH3: 2030 | AJ3: Particulars | AK3: 2026 | AL3: 2027 | AM3: 2028 | AN3: 2029 | AO3: 2030
A4: ASSETS | H4: ASSETS | O4: ASSETS | V4: ASSETS | AC4: ASSETS | AJ4: ASSETS
A5: Non-current Assets | H5: Non-current Assets | O5: Non-current Assets | V5: Non-current Assets | AC5: Non-current Assets | AJ5: Non-current Assets
A6: Property, Plant and Equipment | B6: =Table1[[#This Row],[2025]]+'Income Statement'!B58-'Income Statement'!B59 -> 6372.4947 | C6: =Table25[[#This Row],[2026]]+'Income Statement'!C58-'Income Statement'!C59 -> 7369.225 | D6: =Table25[[#This Row],[2027]]+'Income Statement'!D58-'Income Statement'!D59 -> 8435.286 | E6: =Table25[[#This Row],[2028]]+'Income Statement'!E58-'Income Statement'!E59 -> 9579.4043 | F6: =Table25[[#This Row],[2029]]+'Income Statement'!F58-'Income Statement'!F59 -> 10811.01 | H6: Property, Plant and Equipment | I6: =Table2[[#This Row],[2025]]+'Income Statement'!J69-'Income Statement'!J70 -> 10721.884 | J6: =Table26[[#This Row],[2026]]+'Income Statement'!K69-'Income Statement'!K70 -> 11494.881 | K6: =Table26[[#This Row],[2027]]+'Income Statement'!L69-'Income Statement'!L70 -> 12357.245 | L6: =Table26[[#This Row],[2028]]+'Income Statement'!M69-'Income Statement'!M70 -> 13312.374 | M6: =Table26[[#This Row],[2029]]+'Income Statement'!N69-'Income Statement'!N70 -> 14364.687 | O6: Property, Plant and Equipment | P6: =Table3[[#This Row],[2025]]+'Income Statement'!R69-'Income Statement'!R70 -> 3279.2546 | Q6: =Table27[[#This Row],[2026]]+'Income Statement'!S69-'Income Statement'!S70 -> 3881.9688 | R6: =Table27[[#This Row],[2027]]+'Income Statement'!T69-'Income Statement'!T70 -> 4559.474 | S6: =Table27[[#This Row],[2028]]+'Income Statement'!U69-'Income Statement'!U70 -> 5324.4099 | T6: =Table27[[#This Row],[2029]]+'Income Statement'!V69-'Income Statement'!V70 -> 6191.7102 | V6: Property, Plant and Equipment | W6: =Table4[[#This Row],[2025]]+'Income Statement'!Z71-'Income Statement'!Z72 -> 8362.2111 | X6: =Table28[[#This Row],[2026]]+'Income Statement'!AA71-'Income Statement'!AA72 -> 9502.1226 | Y6: =Table28[[#This Row],[2027]]+'Income Statement'!AB71-'Income Statement'!AB72 -> 10732.529 | Z6: =Table28[[#This Row],[2028]]+'Income Statement'!AC71-'Income Statement'!AC72 -> 12068.481 | AA6: =Table28[[#This Row],[2029]]+'Income Statement'!AD71-'Income Statement'!AD72 -> 13525.894 | AC6: Property, Plant and Equipment | AD6: =Table5[[#This Row],[2025]]+'Income Statement'!AH71-'Income Statement'!AH72 -> 3453.6832 | AE6: =Table29[[#This Row],[2026]]+'Income Statement'!AI71-'Income Statement'!AI72 -> 3708.4442 | AF6: =Table29[[#This Row],[2027]]+'Income Statement'!AJ71-'Income Statement'!AJ72 -> 3974.6411 | AG6: =Table29[[#This Row],[2028]]+'Income Statement'!AK71-'Income Statement'!AK72 -> 4253.4115 | AH6: =Table29[[#This Row],[2029]]+'Income Statement'!AL71-'Income Statement'!AL72 -> 4545.9195 | AJ6: Property, Plant and Equipment | AK6: =Table6[[#This Row],[2025]]+'Income Statement'!AP71-'Income Statement'!AP72 -> 5005.9468 | AL6: =Table30[[#This Row],[2026]]+'Income Statement'!AQ71-'Income Statement'!AQ72 -> 5253.1906 | AM6: =Table30[[#This Row],[2027]]+'Income Statement'!AR71-'Income Statement'!AR72 -> 5553.1553 | AN6: =Table30[[#This Row],[2028]]+'Income Statement'!AS71-'Income Statement'!AS72 -> 5904.474 | AO6: =Table30[[#This Row],[2029]]+'Income Statement'!AT71-'Income Statement'!AT72 -> 6306.7239
A7: Intangible assets (Patents, R&D) | B7: ='Balance Sheet'!G8+'Balance Sheet'!G9+'Income Statement Forecast'!B11 -> 1368.012 | C7: =Table25[[#This Row],[2026]]+'Income Statement Forecast'!C11 -> 1743.2223 | D7: =Table25[[#This Row],[2027]]+'Income Statement Forecast'!D11 -> 2154.8551 | E7: =Table25[[#This Row],[2028]]+'Income Statement Forecast'!E11 -> 2606.4479 | F7: =Table25[[#This Row],[2029]]+'Income Statement Forecast'!F11 -> 3101.8821 | H7: Intangible assets (Patents, R&D) | I7: ='Balance Sheet'!O9+'Income Statement'!J78-'Income Statement'!J77 -> 6548.0895 | J7: =Table26[[#This Row],[2026]]+'Income Statement'!K78-'Income Statement'!K77 -> 9249.9841 | K7: =Table26[[#This Row],[2027]]+'Income Statement'!L78-'Income Statement'!L77 -> 11785.796 | L7: =Table26[[#This Row],[2028]]+'Income Statement'!M78-'Income Statement'!M77 -> 14214.175 | M7: =Table26[[#This Row],[2029]]+'Income Statement'!N78-'Income Statement'!N77 -> 16585.358 | O7: Intangible assets (Patents, R&D) | P7: ='Balance Sheet'!W10+'Income Statement'!R78-'Income Statement'!R77 -> 9554.8562 | Q7: =Table27[[#This Row],[2026]]+'Income Statement'!S78-'Income Statement'!S77 -> 9573.3567 | R7: =Table27[[#This Row],[2027]]+'Income Statement'!T78-'Income Statement'!T77 -> 9664.0764 | S7: =Table27[[#This Row],[2028]]+'Income Statement'!U78-'Income Statement'!U77 -> 9832.3922 | T7: =Table27[[#This Row],[2029]]+'Income Statement'!V78-'Income Statement'!V77 -> 10084.607 | V7: Intangible assets (Patents, R&D) | W7: ='Balance Sheet'!AE9+'Income Statement'!Z80-'Income Statement'!Z79 -> 11240.508 | X7: ='Income Statement'!AA80-'Income Statement'!AA79+Table28[[#This Row],[2026]] -> 12966.697 | Y7: ='Income Statement'!AB80-'Income Statement'!AB79+Table28[[#This Row],[2027]] -> 14814.155 | Z7: ='Income Statement'!AC80-'Income Statement'!AC79+Table28[[#This Row],[2028]] -> 16805.283 | AA7: ='Income Statement'!AD80-'Income Statement'!AD79+Table28[[#This Row],[2029]] -> 18963.691 | AC7: Intangible assets (Patents, R&D) | AD7: ='Balance Sheet'!AM10+'Income Statement'!AH80-'Income Statement'!AH79 -> 4381.9349 | AE7: =Table29[[#This Row],[2026]]+'Income Statement'!AI80-'Income Statement'!AI79 -> 4628.3001 | AF7: =Table29[[#This Row],[2027]]+'Income Statement'!AJ80-'Income Statement'!AJ79 -> 4892.2327 | AG7: =Table29[[#This Row],[2028]]+'Income Statement'!AK80-'Income Statement'!AK79 -> 5174.5746 | AH7: =Table29[[#This Row],[2029]]+'Income Statement'!AL80-'Income Statement'!AL79 -> 5476.2434 | AJ7: Intangible assets (Patents, R&D) | AK7: ='Balance Sheet'!AU11+'Income Statement'!AP80-'Income Statement'!AP79 -> 3951.3488 | AL7: =Table30[[#This Row],[2026]]+'Income Statement'!AQ80-'Income Statement'!AQ79 -> 6298.1986 | AM7: =Table30[[#This Row],[2027]]+'Income Statement'!AR80-'Income Statement'!AR79 -> 8468.3555 | AN7: =Table30[[#This Row],[2028]]+'Income Statement'!AS80-'Income Statement'!AS79 -> 10516.592 | AO7: =Table30[[#This Row],[2029]]+'Income Statement'!AT80-'Income Statement'!AT79 -> 12489.341
A8: Other non-current assets | B8: ='Income Statement'!B62 -> 288.45634 | C8: ='Income Statement'!C62 -> 316.45611 | D8: ='Income Statement'!D62 -> 347.17521 | E8: ='Income Statement'!E62 -> 380.8779 | F8: ='Income Statement'!F62 -> 417.85414 | H8: Other non-current assets | I8: ='Income Statement'!J73 -> 18411.023 | J8: ='Income Statement'!K73 -> 19971.848 | K8: ='Income Statement'!L73 -> 21664.994 | L8: ='Income Statement'!M73 -> 23501.68 | M8: ='Income Statement'!N73 -> 25494.074 | O8: Other non-current assets | P8: ='Income Statement'!R73 -> 2872.3565 | Q8: ='Income Statement'!S73 -> 3244.9877 | R8: ='Income Statement'!T73 -> 3665.9604 | S8: ='Income Statement'!U73 -> 4141.546 | T8: ='Income Statement'!V73 -> 4678.8293 | V8: Other non-current assets | W8: ='Income Statement'!Z75 -> 5692.189 | X8: ='Income Statement'!AA75 -> 6314.4622 | Y8: ='Income Statement'!AB75 -> 7004.7625 | Z8: ='Income Statement'!AC75 -> 7770.5269 | AA8: ='Income Statement'!AD75 -> 8620.005 | AC8: Other non-current assets | AD8: ='Income Statement'!AH75 -> 2393.3055 | AE8: ='Income Statement'!AI75 -> 2540.7802 | AF8: ='Income Statement'!AJ75 -> 2697.3423 | AG8: ='Income Statement'!AK75 -> 2863.5518 | AH8: ='Income Statement'!AL75 -> 3040.003 | AJ8: Other non-current assets | AK8: ='Income Statement'!AP75 -> 8079.7437 | AL8: ='Income Statement'!AQ75 -> 8760.9587 | AM8: ='Income Statement'!AR75 -> 9499.6082 | AN8: ='Income Statement'!AS75 -> 10300.535 | AO8: ='Income Statement'!AT75 -> 11168.989
A9: Total non-current assets | B9: =SUM(B6:B8) -> 8028.9631 | C9: =SUM(C6:C8) -> 9428.9034 | D9: =SUM(D6:D8) -> 10937.316 | E9: =SUM(E6:E8) -> 12566.73 | F9: =SUM(F6:F8) -> 14330.746 | H9: Total non-current assets | I9: =SUM(I6:I8) -> 35680.996 | J9: =SUM(J6:J8) -> 40716.713 | K9: =SUM(K6:K8) -> 45808.035 | L9: =SUM(L6:L8) -> 51028.229 | M9: =SUM(M6:M8) -> 56444.119 | O9: Total non-current assets | P9: =P6+P7+P8 -> 15706.467 | Q9: =Q6+Q7+Q8 -> 16700.313 | R9: =R6+R7+R8 -> 17889.511 | S9: =S6+S7+S8 -> 19298.348 | T9: =T6+T7+T8 -> 20955.146 | V9: Total non-current assets | W9: =SUM(W6:W8) -> 25294.908 | X9: =SUM(X6:X8) -> 28783.282 | Y9: =SUM(Y6:Y8) -> 32551.447 | Z9: =SUM(Z6:Z8) -> 36644.291 | AA9: =SUM(AA6:AA8) -> 41109.59 | AC9: Total non-current assets | AD9: =SUM(AD6:AD8) -> 10228.924 | AE9: =SUM(AE6:AE8) -> 10877.525 | AF9: =SUM(AF6:AF8) -> 11564.216 | AG9: =SUM(AG6:AG8) -> 12291.538 | AH9: =SUM(AH6:AH8) -> 13062.166 | AJ9: Total non-current assets | AK9: =SUM(AK6:AK8) -> 17037.039 | AL9: =SUM(AL6:AL8) -> 20312.348 | AM9: =SUM(AM6:AM8) -> 23521.119 | AN9: =SUM(AN6:AN8) -> 26721.601 | AO9: =SUM(AO6:AO8) -> 29965.053
A10: Current Assets | H10: Current Assets | O10: Current Assets | V10: Current Assets | AC10: Current Assets | AJ10: Current Assets
A11: Cash and Cash equivalents (B&L) | B11: =B32-(SUM(B6:B8,B12:B14)) -> 1370.4179 | C11: =C32-(SUM(C6:C8,C12:C14)) -> 767.85449 | D11: =D32-(SUM(D6:D8,D12:D14)) -> 122.61044 | E11: 0 | F11: 0 | H11: Cash and Cash equivalents | I11: =I32-(SUM(I6:I8,I12:I14)) -> 35848.081 | J11: =J32-(SUM(J6:J8,J12:J14)) -> 36498.269 | K11: =K32-(SUM(K6:K8,K12:K14)) -> 37587.012 | L11: =L32-(SUM(L6:L8,L12:L14)) -> 39155.793 | M11: =M32-(SUM(M6:M8,M12:M14)) -> 41263.453 | O11: Cash and Cash equivalents (B&L) | P11: =P32-(SUM(P6:P8,P12:P14)) -> 7729.9371 | Q11: =Q32-(SUM(Q6:Q8,Q12:Q14)) -> 9046.172 | R11: =R32-(SUM(R6:R8,R12:R14)) -> 10680.094 | S11: =S32-(SUM(S6:S8,S12:S14)) -> 12711.655 | T11: =T32-(SUM(T6:T8,T12:T14)) -> 15243.078 | V11: Cash and Cash equivalents (B&L) | W11: =W32-(SUM(W6:W8,W12:W14)) -> 9586.6307 | X11: =X32-(SUM(X6:X8,X12:X14)) -> 9502.8242 | Y11: =Y32-(SUM(Y6:Y8,Y12:Y14)) -> 9440.8186 | Z11: =Z32-(SUM(Z6:Z8,Z12:Z14)) -> 9396.9292 | AA11: =AA32-(SUM(AA6:AA8,AA12:AA14)) -> 9367.7309 | AC11: Cash and Cash equivalents | AD11: =AD32-(SUM(AD6:AD8,AD12:AD14)) -> 922.19755 | AE11: =AE32-(SUM(AE6:AE8,AE12:AE14)) -> 930.24221 | AF11: =AF32-(SUM(AF6:AF8,AF12:AF14)) -> 938.77052 | AG11: =AG32-(SUM(AG6:AG8,AG12:AG14)) -> 948.00117 | AH11: =AH32-(SUM(AH6:AH8,AH12:AH14)) -> 958.10184 | AJ11: Cash and Cash equivalents | AK11: =AK32-(SUM(AK6:AK8,AK12:AK14)) -> 1210.9451 | AL11: 0 | AM11: 0 | AN11: 0 | AO11: 0
A12: Trade receivables | B12: ='Income Statement Forecast'!B7/'Income Statement'!$B$44 -> 2567.7851 | C12: ='Income Statement Forecast'!C7/'Income Statement'!$B$44 -> 2817.0339 | D12: ='Income Statement Forecast'!D7/'Income Statement'!$B$44 -> 3090.4897 | E12: ='Income Statement Forecast'!E7/'Income Statement'!$B$44 -> 3390.5048 | F12: ='Income Statement Forecast'!F7/'Income Statement'!$B$44 -> 3719.6604 | H12: Trade receivables | I12: ='Income Statement'!J76/'Income Statement'!$J$53 -> 11465.177 | J12: ='Income Statement'!K76/'Income Statement'!$J$53 -> 12437.156 | K12: ='Income Statement'!L76/'Income Statement'!$J$53 -> 13491.537 | L12: ='Income Statement'!M76/'Income Statement'!$J$53 -> 14635.304 | M12: ='Income Statement'!N76/'Income Statement'!$J$53 -> 15876.036 | O12: Trade receivables | P12: ='Income Statement'!R76/'Income Statement'!$R$48 -> 897.91476 | Q12: ='Income Statement'!S76/'Income Statement'!$R$48 -> 1014.4014 | R12: ='Income Statement'!T76/'Income Statement'!$R$48 -> 1145.9998 | S12: ='Income Statement'!U76/'Income Statement'!$R$48 -> 1294.6705 | T12: ='Income Statement'!V76/'Income Statement'!$R$48 -> 1462.6283 | V12: Trade receivables | W12: ='Income Statement'!Z78/'Income Statement'!$Z$49 -> 6518.2335 | X12: ='Income Statement'!AA78/'Income Statement'!$Z$49 -> 7230.8102 | Y12: ='Income Statement'!AB78/'Income Statement'!$Z$49 -> 8021.2862 | Z12: ='Income Statement'!AC78/'Income Statement'!$Z$49 -> 8898.1775 | AA12: ='Income Statement'!AD78/'Income Statement'!$Z$49 -> 9870.931 | AC12: Trade receivables | AD12: ='Income Statement Forecast'!AD7/'Income Statement'!$AH$48 -> 2066.3727 | AE12: ='Income Statement Forecast'!AE7/'Income Statement'!$AH$48 -> 2192.8025 | AF12: ='Income Statement Forecast'!AF7/'Income Statement'!$AH$48 -> 2327.2392 | AG12: ='Income Statement Forecast'!AG7/'Income Statement'!$AH$48 -> 2470.1243 | AH12: ='Income Statement Forecast'!AH7/'Income Statement'!$AH$48 -> 2621.9386 | AJ12: Trade receivables | AK12: ='Income Statement Forecast'!AK7/'Income Statement'!$AP$49 -> 5444.0269 | AL12: ='Income Statement Forecast'!AL7/'Income Statement'!$AP$49 -> 5903.0208 | AM12: ='Income Statement Forecast'!AM7/'Income Statement'!$AP$49 -> 6400.7133 | AN12: ='Income Statement Forecast'!AN7/'Income Statement'!$AP$49 -> 6940.3671 | AO12: ='Income Statement Forecast'!AO7/'Income Statement'!$AP$49 -> 7525.5202
A13: Inventory | B13: ='Income Statement Forecast'!B9/'Income Statement'!$B$45 -> 3460.6439 | C13: ='Income Statement Forecast'!C9/'Income Statement'!$B$45 -> 3796.5604 | D13: ='Income Statement Forecast'!D9/'Income Statement'!$B$45 -> 4165.101 | E13: ='Income Statement Forecast'!E9/'Income Statement'!$B$45 -> 4569.4361 | F13: ='Income Statement Forecast'!F9/'Income Statement'!$B$45 -> 5013.0442 | H13: Inventory | I13: ='Income Statement'!J71/'Income Statement'!$J$54 -> 11789.473 | J13: ='Income Statement'!K71/'Income Statement'!$J$54 -> 12788.945 | K13: ='Income Statement'!L71/'Income Statement'!$J$54 -> 13873.149 | L13: ='Income Statement'!M71/'Income Statement'!$J$54 -> 15049.268 | M13: ='Income Statement'!N71/'Income Statement'!$J$54 -> 16325.095 | O13: Inventory | P13: ='Income Statement'!R71/'Income Statement'!$R$49 -> 2210.8281 | Q13: ='Income Statement'!S71/'Income Statement'!$R$49 -> 2497.6391 | R13: ='Income Statement'!T71/'Income Statement'!$R$49 -> 2821.6582 | S13: ='Income Statement'!U71/'Income Statement'!$R$49 -> 3187.7123 | T13: ='Income Statement'!V71/'Income Statement'!$R$49 -> 3601.2546 | V13: Inventory | W13: ='Income Statement'!Z73/'Income Statement'!$Z$50 -> 6896.9062 | X13: ='Income Statement'!AA73/'Income Statement'!$Z$50 -> 7650.8797 | Y13: ='Income Statement'!AB73/'Income Statement'!$Z$50 -> 8487.2779 | Z13: ='Income Statement'!AC73/'Income Statement'!$Z$50 -> 9415.1117 | AA13: ='Income Statement'!AD73/'Income Statement'!$Z$50 -> 10444.377 | AC13: Inventory | AD13: ='Income Statement'!AH73/'Income Statement'!$AH$49 -> 3060.9411 | AE13: ='Income Statement'!AI73/'Income Statement'!$AH$49 -> 3249.5553 | AF13: ='Income Statement'!AJ73/'Income Statement'!$AH$49 -> 3449.792 | AG13: ='Income Statement'!AK73/'Income Statement'!$AH$49 -> 3662.3671 | AH13: ='Income Statement'!AL73/'Income Statement'!$AH$49 -> 3888.0411 | AJ13: Inventory | AK13: ='Income Statement Forecast'!AK9/'Income Statement'!$AP$50 -> 6767.4899 | AL13: ='Income Statement Forecast'!AL9/'Income Statement'!$AP$50 -> 7338.0669 | AM13: ='Income Statement Forecast'!AM9/'Income Statement'!$AP$50 -> 7956.7502 | AN13: ='Income Statement Forecast'!AN9/'Income Statement'!$AP$50 -> 8627.596 | AO13: ='Income Statement Forecast'!AO9/'Income Statement'!$AP$50 -> 9355.0019
A14: Other current assets | B14: ='Income Statement Forecast'!B7*'Income Statement'!$B$47 -> 3063.8537 | C14: ='Income Statement Forecast'!C7*'Income Statement'!$B$47 -> 3361.2547 | D14: ='Income Statement Forecast'!D7*'Income Statement'!$B$47 -> 3687.5393 | E14: ='Income Statement Forecast'!E7*'Income Statement'!$B$47 -> 4045.5141 | F14: ='Income Statement Forecast'!F7*'Income Statement'!$B$47 -> 4438.259 | H14: Other current assets | I14: ='Income Statement'!J76*'Income Statement'!$J$56 -> 5803.9502 | J14: ='Income Statement'!K76*'Income Statement'!$J$56 -> 6295.9897 | K14: ='Income Statement'!L76*'Income Statement'!$J$56 -> 6829.7427 | L14: ='Income Statement'!M76*'Income Statement'!$J$56 -> 7408.7454 | M14: ='Income Statement'!N76*'Income Statement'!$J$56 -> 8036.834 | O14: Other current assets | P14: ='Income Statement'!R80 -> 1593.9655 | Q14: ='Income Statement'!S80 -> 1800.7509 | R14: ='Income Statement'!T80 -> 2034.3625 | S14: ='Income Statement'!U80 -> 2298.2807 | T14: ='Income Statement'!V80 -> 2596.4369 | V14: Other current assets | W14: ='Income Statement'!Z82 -> 3914.3526 | X14: ='Income Statement'!AA82 -> 4342.2717 | Y14: ='Income Statement'!AB82 -> 4816.9712 | Z14: ='Income Statement'!AC82 -> 5343.5651 | AA14: ='Income Statement'!AD82 -> 5927.7264 | AC14: Other current assets | AD14: ='Income Statement'!AH82 -> 848.27606 | AE14: ='Income Statement'!AI82 -> 900.54658 | AF14: ='Income Statement'!AJ82 -> 956.03799 | AG14: ='Income Statement'!AK82 -> 1014.9488 | AH14: ='Income Statement'!AL82 -> 1077.4896 | AJ14: Other current assets | AK14: ='Income Statement'!AP82 -> 10624.65 | AL14: ='Income Statement'!AQ82 -> 11520.43 | AM14: ='Income Statement'!AR82 -> 12491.734 | AN14: ='Income Statement'!AS82 -> 13544.931 | AO14: ='Income Statement'!AT82 -> 14686.925
A15: Total current assets | B15: =SUM(B11:B14) -> 10462.701 | C15: =SUM(C11:C14) -> 10742.704 | D15: =SUM(D11:D14) -> 11065.74 | E15: =SUM(E11:E14) -> 12005.455 | F15: =SUM(F11:F14) -> 13170.964 | H15: Total current assets | I15: =SUM(I11:I14) -> 64906.681 | J15: =SUM(J11:J14) -> 68020.361 | K15: =SUM(K11:K14) -> 71781.441 | L15: =SUM(L11:L14) -> 76249.11 | M15: =SUM(M11:M14) -> 81501.419 | O15: Total current assets | P15: =SUM(P11:P14) -> 12432.646 | Q15: =SUM(Q11:Q14) -> 14358.963 | R15: =SUM(R11:R14) -> 16682.114 | S15: =SUM(S11:S14) -> 19492.318 | T15: =SUM(T11:T14) -> 22903.398 | V15: Total current assets | W15: =SUM(W11:W14) -> 26916.123 | X15: =SUM(X11:X14) -> 28726.786 | Y15: =SUM(Y11:Y14) -> 30766.354 | Z15: =SUM(Z11:Z14) -> 33053.783 | AA15: =SUM(AA11:AA14) -> 35610.765 | AC15: Total current assets | AD15: =SUM(AD11:AD14) -> 6897.7874 | AE15: =SUM(AE11:AE14) -> 7273.1466 | AF15: =SUM(AF11:AF14) -> 7671.8397 | AG15: =SUM(AG11:AG14) -> 8095.4413 | AH15: =SUM(AH11:AH14) -> 8545.5711 | AJ15: Total current assets | AK15: =SUM(AK11:AK14) -> 24047.112 | AL15: =SUM(AL11:AL14) -> 24761.517 | AM15: =SUM(AM11:AM14) -> 26849.198 | AN15: =SUM(AN11:AN14) -> 29112.894 | AO15: =SUM(AO11:AO14) -> 31567.448
A16: Total Assets | B16: =B9+B15 -> 18491.664 | C16: =C9+C15 -> 20171.607 | D16: =D9+D15 -> 22003.057 | E16: =E9+E15 -> 24572.185 | F16: =F9+F15 -> 27501.71 | H16: Total Assets | I16: =I9+I15 -> 100587.68 | J16: =J9+J15 -> 108737.07 | K16: =K9+K15 -> 117589.48 | L16: =L9+L15 -> 127277.34 | M16: =M9+M15 -> 137945.54 | O16: Total Assets | P16: =P9+P15 -> 28139.113 | Q16: =Q9+Q15 -> 31059.277 | R16: =R9+R15 -> 34571.625 | S16: =S9+S15 -> 38790.666 | T16: =T9+T15 -> 43858.544 | V16: Total Assets | W16: =W9+W15 -> 52211.031 | X16: =X9+X15 -> 57510.067 | Y16: =Y9+Y15 -> 63317.8 | Z16: =Z9+Z15 -> 69698.074 | AA16: =AA9+AA15 -> 76720.355 | AC16: Total Assets | AD16: =AD9+AD15 -> 17126.711 | AE16: =AE9+AE15 -> 18150.671 | AF16: =AF9+AF15 -> 19236.056 | AG16: =AG9+AG15 -> 20386.979 | AH16: =AH9+AH15 -> 21607.737 | AJ16: Total Assets | AK16: =AK9+AK15 -> 41084.151 | AL16: =AL9+AL15 -> 45073.865 | AM16: =AM9+AM15 -> 50370.317 | AN16: =AN9+AN15 -> 55834.495 | AO16: =AO9+AO15 -> 61532.501
A17: EQUITY & LIABILITIES | H17: EQUITY & LIABILITIES | O17: EQUITY & LIABILITIES | V17: EQUITY & LIABILITIES | AC17: EQUITY & LIABILITIES | AJ17: EQUITY & LIABILITIES
A18: Equity | H18: Equity | O18: Equity | V18: Equity | AC18: Equity | AJ18: Equity
A19: Equity Share capital | B19: ='Balance Sheet'!$G$31 -> 53 | C19: ='Balance Sheet'!$G$31 -> 53 | D19: ='Balance Sheet'!$G$31 -> 53 | E19: ='Balance Sheet'!$G$31 -> 53 | F19: ='Balance Sheet'!$G$31 -> 53 | H19: Equity Share capital | I19: ='Balance Sheet'!$O$33 -> 239.93 | J19: ='Balance Sheet'!$O$33 -> 239.93 | K19: ='Balance Sheet'!$O$33 -> 239.93 | L19: ='Balance Sheet'!$O$33 -> 239.93 | M19: ='Balance Sheet'!$O$33 -> 239.93 | O19: Equity Share capital | P19: ='Balance Sheet'!$W$35 -> 41.26 | Q19: ='Balance Sheet'!$W$35 -> 41.26 | R19: ='Balance Sheet'!$W$35 -> 41.26 | S19: ='Balance Sheet'!$W$35 -> 41.26 | T19: ='Balance Sheet'!$W$35 -> 41.26 | V19: Equity Share capital | W19: ='Balance Sheet'!$AE$32 -> 83.4 | X19: ='Balance Sheet'!$AE$32 -> 83.4 | Y19: ='Balance Sheet'!$AE$32 -> 83.4 | Z19: ='Balance Sheet'!$AE$32 -> 83.4 | AA19: ='Balance Sheet'!$AE$32 -> 83.4 | AC19: Equity Share capital | AD19: ='Balance Sheet'!$AM$33 -> 169.23 | AE19: ='Balance Sheet'!$AM$33 -> 169.23 | AF19: ='Balance Sheet'!$AM$33 -> 169.23 | AG19: ='Balance Sheet'!$AM$33 -> 169.23 | AH19: ='Balance Sheet'!$AM$33 -> 169.23 | AJ19: Equity Share capital | AK19: ='Balance Sheet'!$AU$35 -> 161.52 | AL19: ='Balance Sheet'!$AU$35 -> 161.52 | AM19: ='Balance Sheet'!$AU$35 -> 161.52 | AN19: ='Balance Sheet'!$AU$35 -> 161.52 | AO19: ='Balance Sheet'!$AU$35 -> 161.52
A20: Other equity | B20: ='Balance Sheet'!G32+Table31[[#This Row],[2026]]-'Income Statement'!B64 -> 16266.888 | C20: =Table25[[#This Row],[2026]]+Table31[[#This Row],[2027]]-'Income Statement'!C64 -> 17736.41 | D20: =Table25[[#This Row],[2027]]+Table31[[#This Row],[2028]]-'Income Statement'!D64 -> 19337.003 | E20: =Table25[[#This Row],[2028]]+Table31[[#This Row],[2029]]-'Income Statement'!E64 -> 21082.245 | F20: =Table25[[#This Row],[2029]]+Table31[[#This Row],[2030]]-'Income Statement'!F64 -> 22986.972 | H20: Other equity | I20: ='Balance Sheet'!O34+Table32[[#This Row],[2026]]-'Income Statement'!J75 -> 78276.81 | J20: =Table26[[#This Row],[2026]]+Table32[[#This Row],[2027]]-'Income Statement'!K75 -> 85047.165 | K20: =Table26[[#This Row],[2027]]+Table32[[#This Row],[2028]]-'Income Statement'!L75 -> 92403.615 | L20: =Table26[[#This Row],[2028]]+Table32[[#This Row],[2029]]-'Income Statement'!M75 -> 100468.7 | M20: =Table26[[#This Row],[2029]]+Table32[[#This Row],[2030]]-'Income Statement'!N75 -> 109376.56 | O20: Other equity | P20: ='Balance Sheet'!W36+Table33[[#This Row],[2026]]-'Income Statement'!R75 -> 16337.045 | Q20: =Table27[[#This Row],[2026]]+Table33[[#This Row],[2027]]-'Income Statement'!S75 -> 18833.802 | R20: =Table27[[#This Row],[2027]]+Table33[[#This Row],[2028]]-'Income Statement'!T75 -> 21867.816 | S20: =Table27[[#This Row],[2028]]+Table33[[#This Row],[2029]]-'Income Statement'!U75 -> 25546.467 | T20: =Table27[[#This Row],[2029]]+Table33[[#This Row],[2030]]-'Income Statement'!V75 -> 30003.851 | V20: Other equity | W20: ='Balance Sheet'!AE33+Table34[[#This Row],[2026]]-'Income Statement'!Z77 -> 36891.521 | X20: =Table28[[#This Row],[2026]]+Table34[[#This Row],[2027]]-'Income Statement'!AA77 -> 40610.908 | Y20: =Table28[[#This Row],[2027]]+Table34[[#This Row],[2028]]-'Income Statement'!AB77 -> 44666.302 | Z20: =Table28[[#This Row],[2028]]+Table34[[#This Row],[2029]]-'Income Statement'!AC77 -> 49102.671 | AA20: =Table28[[#This Row],[2029]]+Table34[[#This Row],[2030]]-'Income Statement'!AD77 -> 53968.539 | AC20: Other equity | AD20: ='Balance Sheet'!AM34+Table35[[#This Row],[2026]]-'Income Statement'!AH77 -> 7870.7667 | AE20: =Table29[[#This Row],[2026]]+Table35[[#This Row],[2027]]-'Income Statement'!AI77 -> 8345.6655 | AF20: =Table29[[#This Row],[2027]]+Table35[[#This Row],[2028]]-'Income Statement'!AJ77 -> 8848.1558 | AG20: =Table29[[#This Row],[2028]]+Table35[[#This Row],[2029]]-'Income Statement'!AK77 -> 9380.267 | AH20: =Table29[[#This Row],[2029]]+Table35[[#This Row],[2030]]-'Income Statement'!AL77 -> 9944.0817 | AJ20: Other equity | AK20: ='Balance Sheet'!AU36+Table36[[#This Row],[2026]]-'Income Statement'!AP77 -> 33095.765 | AL20: =Table30[[#This Row],[2026]]+Table36[[#This Row],[2027]]-'Income Statement'!AQ77 -> 35121.682 | AM20: =Table30[[#This Row],[2027]]+Table36[[#This Row],[2028]]-'Income Statement'!AR77 -> 37070.557 | AN20: =Table30[[#This Row],[2028]]+Table36[[#This Row],[2029]]-'Income Statement'!AS77 -> 38892.559 | AO20: =Table30[[#This Row],[2029]]+Table36[[#This Row],[2030]]-'Income Statement'!AT77 -> 40868.102
A21: Total equity | B21: =SUM(B19:B20) -> 16319.888 | C21: =SUM(C19:C20) -> 17789.41 | D21: =SUM(D19:D20) -> 19390.003 | E21: =SUM(E19:E20) -> 21135.245 | F21: =SUM(F19:F20) -> 23039.972 | H21: Total equity | I21: =I19+I20 -> 78516.74 | J21: =J19+J20 -> 85287.095 | K21: =K19+K20 -> 92643.545 | L21: =L19+L20 -> 100708.63 | M21: =M19+M20 -> 109616.49 | O21: Total equity | P21: =P19+P20 -> 16378.305 | Q21: =Q19+Q20 -> 18875.062 | R21: =R19+R20 -> 21909.076 | S21: =S19+S20 -> 25587.727 | T21: =T19+T20 -> 30045.111 | V21: Total equity | W21: =W19+W20 -> 36974.921 | X21: =X19+X20 -> 40694.308 | Y21: =Y19+Y20 -> 44749.702 | Z21: =Z19+Z20 -> 49186.071 | AA21: =AA19+AA20 -> 54051.939 | AC21: Total equity | AD21: =AD19+AD20 -> 8039.9967 | AE21: =AE19+AE20 -> 8514.8955 | AF21: =AF19+AF20 -> 9017.3858 | AG21: =AG19+AG20 -> 9549.497 | AH21: =AH19+AH20 -> 10113.312 | AJ21: Total equity | AK21: =AK19+AK20 -> 33257.285 | AL21: =AL19+AL20 -> 35283.202 | AM21: =AM19+AM20 -> 37232.077 | AN21: =AN19+AN20 -> 39054.079 | AO21: =AO19+AO20 -> 41029.622
A22: Non-current liabilities | H22: Non-current liabilities | O22: Non-current liabilities | V22: Non-current liabilities | AC22: Non-current liabilities | AJ22: Non-current liabilities
A23: Long-term borrowings (B&L) | B23: 0 | C23: 0 | D23: 0 | E23: =E16-(SUM(E19:E20,E24:E25,E28:E30)) -> 570.60775 | F23: =F16-(SUM(F19:F20,F24:F25,F28:F30)) -> 1317.5256 | H23: Long-term borrowings | I23: ='Income Statement'!$J$66 -> 5364.71 | J23: ='Income Statement'!$J$66 -> 5364.71 | K23: ='Income Statement'!$J$66 -> 5364.71 | L23: ='Income Statement'!$J$66 -> 5364.71 | M23: ='Income Statement'!$J$66 -> 5364.71 | O23: Long-term borrowings | P23: ='Balance Sheet'!$W$41 -> 5526.19 | Q23: ='Balance Sheet'!$W$41 -> 5526.19 | R23: ='Balance Sheet'!$W$41 -> 5526.19 | S23: ='Balance Sheet'!$W$41 -> 5526.19 | T23: ='Balance Sheet'!$W$41 -> 5526.19 | V23: Long-term borrowings | W23: ='Balance Sheet'!$AE$38 -> 380 | X23: ='Balance Sheet'!$AE$38 -> 380 | Y23: ='Balance Sheet'!$AE$38 -> 380 | Z23: ='Balance Sheet'!$AE$38 -> 380 | AA23: ='Balance Sheet'!$AE$38 -> 380 | AC23: Long-term borrowings | AD23: ='Income Statement'!AH85 -> 1543.3761 | AE23: ='Income Statement'!AI85 -> 1638.4785 | AF23: ='Income Statement'!AJ85 -> 1739.441 | AG23: ='Income Statement'!AK85 -> 1846.6249 | AH23: ='Income Statement'!AL85 -> 1960.4133 | AJ23: Long-term borrowings | AK23: 0 | AL23: =AL16-(SUM(AL19:AL20,AL24:AL25,AL28:AL30)) -> 1333.0819 | AM23: =AM16-(SUM(AM19:AM20,AM24:AM25,AM28:AM30)) -> 3996.7659 | AN23: =AN16-(SUM(AN19:AN20,AN24:AN25,AN28:AN30)) -> 6897.3907 | AO23: =AO16-(SUM(AO19:AO20,AO24:AO25,AO28:AO30)) -> 9815.7798
A24: Lease liabilities | B24: 2 | C24: 2 | D24: 2 | E24: 2 | F24: 2 | H24: Lease liabilities | I24: =AVERAGE('Balance Sheet'!N42:O42) -> 439.465 | J24: =$I$24 -> 439.465 | K24: =$I$24 -> 439.465 | L24: =$I$24 -> 439.465 | M24: =$I$24 -> 439.465 | O24: Lease liabilities | P24: ='Balance Sheet'!$W$42 -> 14.03 | Q24: ='Balance Sheet'!$W$42 -> 14.03 | R24: ='Balance Sheet'!$W$42 -> 14.03 | S24: ='Balance Sheet'!$W$42 -> 14.03 | T24: ='Balance Sheet'!$W$42 -> 14.03 | V24: Lease liabilities | W24: ='Balance Sheet'!$AE$39 -> 406.4 | X24: ='Balance Sheet'!$AE$39 -> 406.4 | Y24: ='Balance Sheet'!$AE$39 -> 406.4 | Z24: ='Balance Sheet'!$AE$39 -> 406.4 | AA24: ='Balance Sheet'!$AE$39 -> 406.4 | AC24: Lease liabilities | AD24: ='Balance Sheet'!AM42+'Balance Sheet'!AM50 -> 176.23 | AE24: =$AD$24 -> 176.23 | AF24: =$AD$24 -> 176.23 | AG24: =$AD$24 -> 176.23 | AH24: =$AD$24 -> 176.23 | AJ24: Lease liabilities | AK24: ='Balance Sheet'!AU54+'Balance Sheet'!AU43 -> 346.09 | AL24: =$AK$24 -> 346.09 | AM24: =$AK$24 -> 346.09 | AN24: =$AK$24 -> 346.09 | AO24: =$AK$24 -> 346.09
A25: Other non-current liabilities | B25: ='Income Statement Forecast'!B7*'Income Statement'!$B$51 -> 624.77092 | C25: ='Income Statement Forecast'!C7*'Income Statement'!$B$51 -> 685.41595 | D25: ='Income Statement Forecast'!D7*'Income Statement'!$B$51 -> 751.95081 | E25: ='Income Statement Forecast'!E7*'Income Statement'!$B$51 -> 824.94786 | F25: ='Income Statement Forecast'!F7*'Income Statement'!$B$51 -> 905.0351 | H25: Other non-current liabilities | I25: ='Income Statement'!J76*'Income Statement'!$J$59 -> 1210.3038 | J25: ='Income Statement'!K76*'Income Statement'!$J$59 -> 1312.9093 | K25: ='Income Statement'!L76*'Income Statement'!$J$59 -> 1424.2134 | L25: ='Income Statement'!M76*'Income Statement'!$J$59 -> 1544.9534 | M25: ='Income Statement'!N76*'Income Statement'!$J$59 -> 1675.9294 | O25: Other non-current liabilities | P25: ='Income Statement'!R82 -> 574.34751 | Q25: ='Income Statement'!S82 -> 648.85769 | R25: ='Income Statement'!T82 -> 733.03409 | S25: ='Income Statement'!U82 -> 828.1307 | T25: ='Income Statement'!V82 -> 935.5642 | V25: Other non-current liabilities | W25: ='Income Statement'!Z84 -> 699.43298 | X25: ='Income Statement'!AA84 -> 775.89536 | Y25: ='Income Statement'!AB84 -> 860.71666 | Z25: ='Income Statement'!AC84 -> 954.81066 | AA25: ='Income Statement'!AD84 -> 1059.1911 | AC25: Other non-current liabilities | AD25: ='Income Statement'!AH84 -> 1031.0561 | AE25: ='Income Statement'!AI84 -> 1094.5895 | AF25: ='Income Statement'!AJ84 -> 1162.0378 | AG25: ='Income Statement'!AK84 -> 1233.6422 | AH25: ='Income Statement'!AL84 -> 1309.6589 | AJ25: Other non-current liabilities | AK25: ='Income Statement'!AP84 -> 798.4097 | AL25: ='Income Statement'!AQ84 -> 865.72479 | AM25: ='Income Statement'!AR84 -> 938.71534 | AN25: ='Income Statement'!AS84 -> 1017.8599 | AO25: ='Income Statement'!AT84 -> 1103.6772
A26: Total non-current liabilities | B26: =SUM(B23:B25) -> 626.77092 | C26: =SUM(C23:C25) -> 687.41595 | D26: =SUM(D23:D25) -> 753.95081 | E26: =SUM(E23:E25) -> 1397.5556 | F26: =SUM(F23:F25) -> 2224.5607 | H26: Total non-current liabilities | I26: =SUM(I23:I25) -> 7014.4788 | J26: =SUM(J23:J25) -> 7117.0843 | K26: =SUM(K23:K25) -> 7228.3884 | L26: =SUM(L23:L25) -> 7349.1284 | M26: =SUM(M23:M25) -> 7480.1044 | O26: Total non-current liabilities | P26: =SUM(P23:P25) -> 6114.5675 | Q26: =SUM(Q23:Q25) -> 6189.0777 | R26: =SUM(R23:R25) -> 6273.2541 | S26: =SUM(S23:S25) -> 6368.3507 | T26: =SUM(T23:T25) -> 6475.7842 | V26: Total non-current liabilities | W26: =SUM(W23:W25) -> 1485.833 | X26: =SUM(X23:X25) -> 1562.2954 | Y26: =SUM(Y23:Y25) -> 1647.1167 | Z26: =SUM(Z23:Z25) -> 1741.2107 | AA26: =SUM(AA23:AA25) -> 1845.5911 | AC26: Total non-current liabilities | AD26: =SUM(AD23:AD25) -> 2750.6622 | AE26: =SUM(AE23:AE25) -> 2909.298 | AF26: =SUM(AF23:AF25) -> 3077.7088 | AG26: =SUM(AG23:AG25) -> 3256.4971 | AH26: =SUM(AH23:AH25) -> 3446.3022 | AJ26: Total non-current liabilities | AK26: =SUM(AK23:AK25) -> 1144.4997 | AL26: =SUM(AL23:AL25) -> 2544.8967 | AM26: =SUM(AM23:AM25) -> 5281.5712 | AN26: =SUM(AN23:AN25) -> 8261.3406 | AO26: =SUM(AO23:AO25) -> 11265.547
A27: Current Liabilities | H27: Current Liabilities | O27: Current Liabilities | V27: Current Liabilities | AC27: Current Liabilities | AJ27: Current Liabilities
A28: Short term borrowings | B28: 2 | C28: 2 | D28: 2 | E28: 2 | F28: 2 | H28: Short term borrowings | I28: 0 | J28: 0 | K28: 0 | L28: 0 | M28: 0 | O28: Short term borrowings | P28: ='Balance Sheet'!$W$48 -> 2956.84 | Q28: ='Balance Sheet'!$W$48 -> 2956.84 | R28: ='Balance Sheet'!$W$48 -> 2956.84 | S28: ='Balance Sheet'!$W$48 -> 2956.84 | T28: ='Balance Sheet'!$W$48 -> 2956.84 | V28: Short term borrowings | W28: ='Income Statement'!Z86 -> 4083.1577 | X28: ='Income Statement'!AA86 -> 4529.5307 | Y28: ='Income Statement'!AB86 -> 5024.7014 | Z28: ='Income Statement'!AC86 -> 5574.0044 | AA28: ='Income Statement'!AD86 -> 6183.3576 | AC28: Short term borrowings | AD28: ='Income Statement'!AH86 -> 2703.7345 | AE28: ='Income Statement'!AI86 -> 2870.3378 | AF28: ='Income Statement'!AJ86 -> 3047.2071 | AG28: ='Income Statement'!AK86 -> 3234.9751 | AH28: ='Income Statement'!AL86 -> 3434.3133 | AJ28: Short term borrowings | AK28: ='Income Statement'!AP86 -> 492.1441 | AL28: ='Income Statement'!AQ86 -> 533.63748 | AM28: ='Income Statement'!AR86 -> 578.62926 | AN28: ='Income Statement'!AS86 -> 627.41437 | AO28: ='Income Statement'!AT86 -> 680.31265
A29: Trade Payables | B29: ='Income Statement Forecast'!B9/'Income Statement'!$B$48 -> 1010.0135 | C29: ='Income Statement Forecast'!C9/'Income Statement'!$B$48 -> 1108.0531 | D29: ='Income Statement Forecast'!D9/'Income Statement'!$B$48 -> 1215.6143 | E29: ='Income Statement Forecast'!E9/'Income Statement'!$B$48 -> 1333.6223 | F29: ='Income Statement Forecast'!F9/'Income Statement'!$B$48 -> 1463.0925 | H29: Trade Payables | I29: ='Income Statement'!J71/'Income Statement'!$J$57 -> 5371.2569 | J29: ='Income Statement'!K71/'Income Statement'!$J$57 -> 5826.614 | K29: ='Income Statement'!L71/'Income Statement'!$J$57 -> 6320.5749 | L29: ='Income Statement'!M71/'Income Statement'!$J$57 -> 6856.4121 | M29: ='Income Statement'!N71/'Income Statement'!$J$57 -> 7437.6757 | O29: Trade Payables | P29: ='Income Statement'!R71/'Income Statement'!$R$52 -> 1392.1777 | Q29: ='Income Statement'!S71/'Income Statement'!$R$52 -> 1572.7851 | R29: ='Income Statement'!T71/'Income Statement'!$R$52 -> 1776.8227 | S29: ='Income Statement'!U71/'Income Statement'!$R$52 -> 2007.3301 | T29: ='Income Statement'!V71/'Income Statement'!$R$52 -> 2267.7413 | V29: Trade Payables | W29: ='Income Statement'!Z73/'Income Statement'!$Z$53 -> 2811.903 | X29: ='Income Statement'!AA73/'Income Statement'!$Z$53 -> 3119.3017 | Y29: ='Income Statement'!AB73/'Income Statement'!$Z$53 -> 3460.3054 | Z29: ='Income Statement'!AC73/'Income Statement'!$Z$53 -> 3838.5879 | AA29: ='Income Statement'!AD73/'Income Statement'!$Z$53 -> 4258.2243 | AC29: Trade Payables | AD29: ='Income Statement'!AH73/'Income Statement'!$AH$52 -> 2468.0214 | AE29: ='Income Statement'!AI73/'Income Statement'!$AH$52 -> 2620.1001 | AF29: ='Income Statement'!AJ73/'Income Statement'!$AH$52 -> 2781.5499 | AG29: ='Income Statement'!AK73/'Income Statement'!$AH$52 -> 2952.9481 | AH29: ='Income Statement'!AL73/'Income Statement'!$AH$52 -> 3134.9079 | AJ29: Trade Payables | AK29: ='Income Statement'!AP73/'Income Statement'!$AP$53 -> 3250.5932 | AL29: ='Income Statement'!AQ73/'Income Statement'!$AP$53 -> 3524.6555 | AM29: ='Income Statement'!AR73/'Income Statement'!$AP$53 -> 3821.8245 | AN29: ='Income Statement'!AS73/'Income Statement'!$AP$53 -> 4144.0483 | AO29: ='Income Statement'!AT73/'Income Statement'!$AP$53 -> 4493.4394
A30: Other current liabilities | B30: ='Income Statement Forecast'!B7*'Income Statement'!$B$52 -> 532.99147 | C30: ='Income Statement Forecast'!C7*'Income Statement'!$B$52 -> 584.72769 | D30: ='Income Statement Forecast'!D7*'Income Statement'!$B$52 -> 641.48852 | E30: ='Income Statement Forecast'!E7*'Income Statement'!$B$52 -> 703.76223 | F30: ='Income Statement Forecast'!F7*'Income Statement'!$B$52 -> 772.08458 | H30: Other current liabilities | I30: ='Income Statement'!J76*'Income Statement'!$J$61 -> 9685.2015 | J30: ='Income Statement'!K76*'Income Statement'!$J$61 -> 10506.281 | K30: ='Income Statement'!L76*'Income Statement'!$J$61 -> 11396.968 | L30: ='Income Statement'!M76*'Income Statement'!$J$61 -> 12363.165 | M30: ='Income Statement'!N76*'Income Statement'!$J$61 -> 13411.272 | O30: Other current liabilities | P30: ='Income Statement'!R81 -> 1297.2226 | Q30: ='Income Statement'!S81 -> 1465.5115 | R30: ='Income Statement'!T81 -> 1655.6325 | S30: ='Income Statement'!U81 -> 1870.4179 | T30: ='Income Statement'!V81 -> 2113.0675 | V30: Other current liabilities | W30: ='Income Statement'!Z83 -> 6855.2162 | X30: ='Income Statement'!AA83 -> 7604.6321 | Y30: ='Income Statement'!AB83 -> 8435.9745 | Z30: ='Income Statement'!AC83 -> 9358.1998 | AA30: ='Income Statement'!AD83 -> 10381.243 | AC30: Other current liabilities | AD30: ='Income Statement'!AH83 -> 1164.2963 | AE30: ='Income Statement'!AI83 -> 1236.0398 | AF30: ='Income Statement'!AJ83 -> 1312.2042 | AG30: ='Income Statement'!AK83 -> 1393.0619 | AH30: ='Income Statement'!AL83 -> 1478.9019 | AJ30: Other current liabilities | AK30: ='Income Statement'!AP83 -> 2939.6294 | AL30: ='Income Statement'!AQ83 -> 3187.4738 | AM30: ='Income Statement'!AR83 -> 3456.2145 | AN30: ='Income Statement'!AS83 -> 3747.6132 | AO30: ='Income Statement'!AT83 -> 4063.5803
A31: Total Current Liabilities | B31: =SUM(B28:B30) -> 1545.0049 | C31: =SUM(C28:C30) -> 1694.7808 | D31: =SUM(D28:D30) -> 1859.1028 | E31: =SUM(E28:E30) -> 2039.3846 | F31: =SUM(F28:F30) -> 2237.1771 | H31: Total Current Liabilities | I31: =SUM(I28:I30) -> 15056.458 | J31: =SUM(J28:J30) -> 16332.895 | K31: =SUM(K28:K30) -> 17717.543 | L31: =SUM(L28:L30) -> 19219.577 | M31: =SUM(M28:M30) -> 20848.948 | O31: Total Current Liabilities | P31: =SUM(P28:P30) -> 5646.2403 | Q31: =SUM(Q28:Q30) -> 5995.1366 | R31: =SUM(R28:R30) -> 6389.2952 | S31: =SUM(S28:S30) -> 6834.5881 | T31: =SUM(T28:T30) -> 7337.6488 | V31: Total Current Liabilities | W31: =SUM(W28:W30) -> 13750.277 | X31: =SUM(X28:X30) -> 15253.465 | Y31: =SUM(Y28:Y30) -> 16920.981 | Z31: =SUM(Z28:Z30) -> 18770.792 | AA31: =SUM(AA28:AA30) -> 20822.825 | AC31: Total Current Liabilities | AD31: =SUM(AD28:AD30) -> 6336.0521 | AE31: =SUM(AE28:AE30) -> 6726.4777 | AF31: =SUM(AF28:AF30) -> 7140.9612 | AG31: =SUM(AG28:AG30) -> 7580.9851 | AH31: =SUM(AH28:AH30) -> 8048.1231 | AJ31: Total Current Liabilities | AK31: =SUM(AK28:AK30) -> 6682.3667 | AL31: =SUM(AL28:AL30) -> 7245.7668 | AM31: =SUM(AM28:AM30) -> 7856.6682 | AN31: =SUM(AN28:AN30) -> 8519.0759 | AO31: =SUM(AO28:AO30) -> 9237.3324
A32: Total Equity and Liabilities | B32: =B21+B26+B31 -> 18491.664 | C32: =C21+C26+C31 -> 20171.607 | D32: =D21+D26+D31 -> 22003.057 | E32: =E21+E26+E31 -> 24572.185 | F32: =F21+F26+F31 -> 27501.71 | H32: Total Equity and Liabilities | I32: =I21+I26+I31 -> 100587.68 | J32: =J21+J26+J31 -> 108737.07 | K32: =K21+K26+K31 -> 117589.48 | L32: =L21+L26+L31 -> 127277.34 | M32: =M21+M26+M31 -> 137945.54 | O32: Total Equity and Liabilities | P32: =P21+P26+P31 -> 28139.113 | Q32: =Q21+Q26+Q31 -> 31059.277 | R32: =R21+R26+R31 -> 34571.625 | S32: =S21+S26+S31 -> 38790.666 | T32: =T21+T26+T31 -> 43858.544 | V32: Total Equity and Liabilities | W32: =W21+W26+W31 -> 52211.031 | X32: =X21+X26+X31 -> 57510.067 | Y32: =Y21+Y26+Y31 -> 63317.8 | Z32: =Z21+Z26+Z31 -> 69698.074 | AA32: =AA21+AA26+AA31 -> 76720.355 | AC32: Total Equity and Liabilities | AD32: =AD21+AD26+AD31 -> 17126.711 | AE32: =AE21+AE26+AE31 -> 18150.671 | AF32: =AF21+AF26+AF31 -> 19236.056 | AG32: =AG21+AG26+AG31 -> 20386.979 | AH32: =AH21+AH26+AH31 -> 21607.737 | AJ32: Total Equity and Liabilities | AK32: =AK21+AK26+AK31 -> 41084.151 | AL32: =AL21+AL26+AL31 -> 45073.865 | AM32: =AM21+AM26+AM31 -> 50370.317 | AN32: =AN21+AN26+AN31 -> 55834.495 | AO32: =AO21+AO26+AO31 -> 61532.501
A34: Working Capital | B34: =B15-B31 -> 8917.6956 | C34: =C15-C31 -> 9047.9227 | D34: =D15-D31 -> 9206.6376 | E34: =E15-E31 -> 9966.0704 | F34: =F15-F31 -> 10933.786
A35: Change in working capital | C35: =C34-B34 -> 130.22709 | D35: =D34-C34 -> 158.71486 | E35: =E34-D34 -> 759.43281 | F35: =F34-E34 -> 967.7161

Sheet Income Statement
A1: INCOME STATEMENT
A2: #VALUE! | I2: #VALUE! | Q2: #VALUE! | Y2: #VALUE! | AG2: #VALUE! | AO2: #VALUE!
A3: Particulars | B3: 2020 | C3: 2021 | D3: 2022 | E3: 2023 | F3: 2024 | G3: 2025 | I3: Particulars | J3: 2020 | K3: 2021 | L3: 2022 | M3: 2023 | N3: 2024 | O3: 2025 | Q3: Particulars | R3: 2020 | S3: 2021 | T3: 2022 | U3: 2023 | V3: 2024 | W3: 2025 | Y3: Particulars | Z3: 2020 | AA3: 2021 | AB3: 2022 | AC3: 2023 | AD3: 2024 | AE3: 2025 | AG3: Particulars | AH3: 2020 | AI3: 2021 | AJ3: 2022 | AK3: 2023 | AL3: 2024 | AM3: 2025 | AO3: Particulars | AP3: 2020 | AQ3: 2021 | AR3: 2022 | AS3: 2023 | AT3: 2024 | AU3: 2025
A4: INCOME | I4: INCOME | Q4: INCOME | Y4: INCOME | AG4: INCOME | AO4: INCOME
A5: Revenue from Operations | B5: 5394.42 | C5: 6969.4 | D5: 8959.83 | E5: 7767.51 | F5: 7845 | G5: 9360 | I5: Revenue from operations | J5: 32837.5 | K5: 33498.14 | L5: 38654.49 | M5: 43885.68 | N5: 48496.85 | O5: 52578.44 | Q5: Revenue from operations | R5: 5871.8685 | S5: 6223.8982 | T5: 7781.5551 | U5: 8749.433 | V5: 10260.44 | W5: 12207.44 | Y5: Sales | Z5: 16357.4 | AA5: 18420.2 | AB5: 20514.4 | AC5: 23459.5 | AD5: 27139.6 | AE5: 31632 | AG5: Revenue from operations | AH5: 7939.31 | AI5: 8004.83 | AJ5: 8508.04 | AK5: 9620.15 | AL5: 10727.84 | AM5: 11516.09 | AO5: Revenue from sale of products | AP5: 16694.85 | AQ5: 18988.52 | AR5: 21623.36 | AS5: 22473.18 | AT5: 25446.63 | AU5: 27145.4
A6: Other income | B6: 189.63 | C6: 62.56 | D6: 113.87 | E6: 344.66 | F6: 339 | G6: 352 | I6: Other income | J6: 635.98 | K6: 835.52 | L6: 921.51 | M6: 634.52 | N6: 1354.19 | O6: 1965.04 | Q6: Other income | R6: 103.7844 | S6: 161.4821 | T6: 196.0296 | U6: 128.5668 | V6: 280.22 | W6: 536.79 | Y6: Service income and license fees | Z6: 1102.6 | AA6: 552 | AB6: 924.7 | AC6: 1128.4 | AD6: 776.8 | AE6: 921.5 | AG6: Other income | AH6: 121.3 | AI6: 56.65 | AJ6: 196.56 | AK6: 45.14 | AL6: 57.91 | AM6: 23.27 | AO6: Other operating revenue | AP6: 437.14 | AQ6: 171.07 | AR6: 139.98 | AS6: 279.94 | AT6: 327.46 | AU6: 402.22
A7: Total income | B7: =SUM(B5:B6) -> 5584.05 | C7: =SUM(C5:C6) -> 7031.96 | D7: =SUM(D5:D6) -> 9073.7 | E7: =SUM(E5:E6) -> 8112.17 | F7: =SUM(F5:F6) -> 8184 | G7: =SUM(G5:G6) -> 9712 | I7: Total income | J7: =SUM(J5:J6) -> 33473.48 | K7: =SUM(K5:K6) -> 34333.66 | L7: =SUM(L5:L6) -> 39576 | M7: =SUM(M5:M6) -> 44520.2 | N7: =SUM(N5:N6) -> 49851.04 | O7: =SUM(O5:O6) -> 54543.48 | Q7: Total income | R7: =SUM(R5:R6) -> 5975.6529 | S7: =SUM(S5:S6) -> 6385.3803 | T7: =SUM(T5:T6) -> 7977.5847 | U7: =SUM(U5:U6) -> 8877.9998 | V7: =SUM(V5:V6) -> 10540.66 | W7: =SUM(W5:W6) -> 12744.23 | Y7: Other operating income | Z7: 57 | AA7: 75.3 | AB7: 106.1 | AC7: 81.8 | AD7: 94.7 | AE7: 90.4 | AG7: Total income | AH7: =SUM(AH5:AH6) -> 8060.61 | AI7: =SUM(AI5:AI6) -> 8061.48 | AJ7: =SUM(AJ5:AJ6) -> 8704.6 | AK7: =SUM(AK5:AK6) -> 9665.29 | AL7: =SUM(AL5:AL6) -> 10785.75 | AM7: =SUM(AM5:AM6) -> 11539.36 | AO7: Other income | AP7: 344.2 | AQ7: 265.99 | AR7: 280.91 | AS7: 475.45 | AT7: 746.57 | AU7: 861.87
A8: EXPENSES | I8: EXPENSES | Q8: EXPENSES | Y8: Other income | Z8: 620.6 | AA8: 291.4 | AB8: 484.4 | AC8: 1055.5 | AD8: 894.3 | AE8: 1097.3 | AG8: EXPENSES | AO8: Total income | AP8: =SUM(AP5:AP7) -> 17476.19 | AQ8: =SUM(AQ5:AQ7) -> 19425.58 | AR8: =SUM(AR5:AR7) -> 22044.25 | AS8: =SUM(AS5:AS7) -> 23228.57 | AT8: =SUM(AT5:AT7) -> 26520.66 | AU8: =SUM(AU5:AU7) -> 28409.49
A9: Cost of raw materials consumed | B9: 2198.41 | C9: 2397.44 | D9: 3476.56 | E9: 3008.36 | F9: 3232 | G9: 3821 | I9: Cost of materials consumed | J9: 5515.23 | K9: 6153.13 | L9: 7049.12 | M9: 7777.57 | N9: 6904.33 | O9: 6449.1 | Q9: Cost of raw materials and components consumed | R9: 1297.3217 | S9: 1373.1783 | T9: 2057.5616 | U9: 1813.6635 | V9: 1842.29 | W9: 2016.35 | Y9: Total income | Z9: =SUM(Z5:Z8) -> 18137.6 | AA9: =SUM(AA5:AA8) -> 19338.9 | AB9: =SUM(AB5:AB8) -> 22029.6 | AC9: =SUM(AC5:AC8) -> 25725.2 | AD9: =SUM(AD5:AD8) -> 28905.4 | AE9: =SUM(AE5:AE8) -> 33741.2 | AG9: Cost of raw materials consumed | AH9: 1377.35 | AI9: 1420.69 | AJ9: 1537.5 | AK9: 1480.42 | AL9: 1657.59 | AM9: 1520.32 | AO9: EXPENSE
A10: Purchase of stock in trade | B10: 16.11 | C10: 5.31 | D10: 14.41 | E10: 22.33 | F10: 6 | G10: 0 | I10: Purchase of stock in trade | J10: 3414.37 | K10: 3175.17 | L10: 3410.03 | M10: 3571.5 | N10: 3466.15 | O10: 4147.95 | Q10: Purchase of stock in trade | R10: 591.2053 | S10: 654.8245 | T10: 813.7544 | U10: 809.2376 | V10: 1409.85 | W10: 1655.69 | Y10: EXPENSES | AG10: Purchase of stock in trade | AH10: 922.7 | AI10: 1004.97 | AJ10: 830.65 | AK10: 1088.58 | AL10: 1183.63 | AM10: 1530.5 | AO10: Cost of materials consumed | AP10: 4376.81 | AQ10: 4886.43 | AR10: 5533.13 | AS10: 5519.62 | AT10: 5220.51 | AU10: 5409.6
A11: Changes in inventories of finished good, WIP and SIT | B11: -105.98 | C11: -78.67 | D11: -523.83 | E11: 23.03 | F11: -109 | G11: -96 | I11: Changes in inventories of finished goods, WIP and SIT | J11: 300.85 | K11: -638.22 | L11: -107.61 | M11: -686.91 | N11: 292.13 | O11: 150.31 | Q11: Changes in inventories | R11: -10.4559 | S11: -247.3942 | T11: -449.5876 | U11: 290.7409 | V11: -53.67 | W11: -183 | Y11: Cost of materials consumed | Z11: 2984.8 | AA11: 4295.8 | AB11: 4312.4 | AC11: 4219.8 | AD11: 4490.1 | AE11: 5683.5 | AG11: Changes in inventories of finished good, WIP and SIT | AH11: -133.13 | AI11: -279.24 | AJ11: 73.86 | AK11: 166.19 | AL11: -155.01 | AM11: -274.92 | AO11: Purchase of stock in trade | AP11: 1859.37 | AQ11: 2658.17 | AR11: 3687.16 | AS11: 2828.66 | AT11: 3536.03 | AU11: 3851.49
A12: Employee benefit expense | B12: 621.05 | C12: 825.76 | D12: 946.16 | E12: 975.02 | F12: 1094 | G12: 1243 | I12: Employee benefits expense | J12: 6362.35 | K12: 6862.23 | L12: 7300.83 | M12: 8296.03 | N12: 9429.06 | O12: 9973.12 | Q12: Employee benefit expenses | R12: 1335.5266 | S12: 1415.7831 | T12: 1620.5933 | U12: 1918.4715 | V12: 2260.6 | W12: 2692.37 | Y12: Purchase of stock in trade | Z12: 2545.9 | AA12: 2573.6 | AB12: 3483.7 | AC12: 3367 | AD12: 4399.1 | AE12: 4841.1 | AG12: Employee benefit expense | AH12: 1429.04 | AI12: 1439.62 | AJ12: 1526.45 | AK12: 1677.69 | AL12: 1984.4 | AM12: 2203.37 | AO12: Changes in inventories of finished good, WIP and SIT | AP12: -244.76 | AQ12: -192.71 | AR12: -724.69 | AS12: -96 | AT12: 63.03 | AU12: -332.1
A13: Finance costs | B13: 6.1 | C13: 0.87 | D13: 0.8 | E13: 0.67 | F13: 3 | G13: 2 | I13: Finance costs | J13: 302.73 | K13: 141.43 | L13: 127.35 | M13: 172 | N13: 238.47 | O13: 231.36 | Q13: Finance costs | R13: 21.9718 | S13: 20.1474 | T13: 58.6104 | U13: 44.469 | V13: 32.75 | W13: 429.41 | Y13: Changes in inventories of finished goods, WIP and SIT | Z13: 23.7 | AA13: -790.5 | AB13: -353.9 | AC13: 70.9 | AD13: -680.5 | AE13: -544.7 | AG13: Finance costs | AH13: 450.71 | AI13: 358.28 | AJ13: 255.06 | AK13: 333.44 | AL13: 353.56 | AM13: 252.31 | AO13: Employee benefit expense | AP13: 3027.01 | AQ13: 3251.83 | AR13: 3529.91 | AS13: 3830.08 | AT13: 4310.04 | AU13: 4832.83
A14: Depreciation and amortisation expense | B14: 186.24 | C14: 255.59 | D14: 311.51 | E14: 343.18 | F14: 378 | G14: 402 | I14: Depreciation and amortisation expense | J14: 2052.78 | K14: 2079.95 | L14: 2143.74 | M14: 2529.43 | N14: 2556.64 | O14: 2575.39 | Q14: Depreciation and amortisation expense | R14: 99.0584 | S14: 118.9703 | T14: 166.6192 | U14: 325.9195 | V14: 378.42 | W14: 621.22 | Y14: Employee benefit expense | Z14: 3380.2 | AA14: 3629.9 | AB14: 3885.8 | AC14: 4646.6 | AD14: 5030.1 | AE14: 5580 | AG14: Depreciation and amortisation expense | AH14: 654.38 | AI14: 657.79 | AJ14: 662.16 | AK14: 706.59 | AL14: 808.27 | AM14: 794.93 | AO14: Finance costs | AP14: 197.36 | AQ14: 160.7 | AR14: 106.35 | AS14: 109.54 | AT14: 89.88 | AU14: 62.01
A15: Other expenses | B15: 842.66 | C15: 959.62 | D15: 1164.59 | E15: 1370.95 | F15: 1417 | G15: 1424 | I15: Other expenses | J15: 10270.55 | K15: 9478.11 | L15: 10758.36 | M15: 13154.6 | N15: 15418.18 | O15: 16771.8 | Q15: Impairment of non-current assets | R15: 90.5799 | S15: 0 | T15: 0 | U15: 0 | V15: 0 | W15: 0 | Y15: Depreciation and amortisation expense | Z15: 1163.1 | AA15: 1228.8 | AB15: 1165.2 | AC15: 1250.2 | AD15: 1470 | AE15: 1703.7 | AG15: Other expenses | AH15: 2172.99 | AI15: 1933.11 | AJ15: 2108.31 | AK15: 2365.22 | AL15: 2689.58 | AM15: 2815.83 | AO15: Depreciation and amortisation expense | AP15: 1174.65 | AQ15: 1067.66 | AR15: 1051.95 | AS15: 1172.11 | AT15: 1051.02 | AU15: 1106.95
A16: Total expense | B16: =SUM(B9:B15) -> 3764.59 | C16: =SUM(C9:C15) -> 4365.92 | D16: =SUM(D9:D15) -> 5390.2 | E16: =SUM(E9:E15) -> 5743.54 | F16: =SUM(F9:F15) -> 6021 | G16: =SUM(G9:G15) -> 6796 | I16: Net gain/loss on foreign currency transactions | J16: -15.61 | K16: -23.65 | L16: -153.96 | M16: 126.1 | N16: -36.13 | O16: -185.53 | Q16: Impairment losses on financial assets | R16: 0 | S16: 17.7106 | T16: 0 | U16: 0 | V16: 0 | W16: 0 | Y16: Impairment of non-current assets | Z16: 1676.7 | AA16: 676.8 | AB16: 930.4 | AC16: 69.9 | AD16: 0.3 | AE16: 169.3 | AG16: Total expense | AH16: =SUM(AH9:AH15) -> 6874.04 | AI16: =SUM(AI9:AI15) -> 6535.22 | AJ16: =SUM(AJ9:AJ15) -> 6993.99 | AK16: =SUM(AK9:AK15) -> 7818.13 | AL16: =SUM(AL9:AL15) -> 8522.02 | AM16: =SUM(AM9:AM15) -> 8842.34 | AO16: Other expenses | AP16: 4907.57 | AQ16: 4303.44 | AR16: 5185.05 | AS16: 5643.79 | AT16: 6353.43 | AU16: 6657.9
A17: Profit before tax | B17: =B7-B16 -> 1819.46 | C17: =C7-C16 -> 2666.04 | D17: =D7-D16 -> 3683.5 | E17: =E7-E16 -> 2368.63 | F17: =F7-F16 -> 2163 | G17: =G7-G16 -> 2916 | I17: Total expenses | J17: =SUM(J9:J16) -> 28203.25 | K17: =SUM(K9:K16) -> 27228.15 | L17: =SUM(L9:L16) -> 30527.86 | M17: =SUM(M9:M16) -> 34940.32 | N17: =SUM(N9:N16) -> 38268.83 | O17: =SUM(O9:O16) -> 40113.5 | Q17: Other expenses | R17: 1124.2452 | S17: 1352.2256 | T17: 1749.8805 | U17: 2016.6829 | V17: 2287.69 | W17: 3008.1 | Y17: Finance costs | Z17: 98.3 | AA17: 97 | AB17: 95.8 | AC17: 142.8 | AD17: 171.1 | AE17: 282.9 | AG17: Profit before exceptional items and tax | AH17: =AH7-AH16 -> 1186.57 | AI17: =AI7-AI16 -> 1526.26 | AJ17: =AJ7-AJ16 -> 1710.61 | AK17: =AK7-AK16 -> 1847.16 | AL17: =AL7-AL16 -> 2263.73 | AM17: =AM7-AM16 -> 2697.02 | AO17: Total expense | AP17: =SUM(AP10:AP16) -> 15298.01 | AQ17: =SUM(AQ10:AQ16) -> 16135.52 | AR17: =SUM(AR10:AR16) -> 18368.86 | AS17: =SUM(AS10:AS16) -> 19007.8 | AT17: =SUM(AT10:AT16) -> 20623.94 | AU17: =SUM(AU10:AU16) -> 21588.68
A18: Current tax | B18: 392.79 | C18: 616.46 | D18: 644 | E18: 439.17 | F18: 514 | G18: 799 | I18: Profit before exceptional items and tax | J18: =J7-J17 -> 5270.23 | K18: =K7-K17 -> 7105.51 | L18: =L7-L17 -> 9048.14 | M18: =M7-M17 -> 9579.88 | N18: =N7-N17 -> 11582.21 | O18: =O7-O17 -> 14429.98 | Q18: Total expenses | R18: =SUM(R9:R17) -> 4549.453 | S18: =SUM(S9:S17) -> 4705.4456 | T18: =SUM(T9:T17) -> 6017.4318 | U18: =SUM(U9:U17) -> 7219.1849 | V18: =SUM(V9:V17) -> 8157.93 | W18: =SUM(W9:W17) -> 10240.14 | Y18: Selling and other expenses | Z18: 4435.3 | AA18: 4792 | AB18: 5519.1 | AC18: 5946.5 | AD18: 6838.9 | AE18: 8367.6 | AG18: Exceptional items | AH18: 0 | AI18: 0 | AJ18: 484.7 | AK18: 0 | AL18: -88.38 | AM18: 24.21 | AO18: Profit before exceptional items and tax | AP18: =AP8-AP17 -> 2178.18 | AQ18: =AQ8-AQ17 -> 3290.06 | AR18: =AR8-AR17 -> 3675.39 | AS18: =AS8-AS17 -> 4220.77 | AT18: =AT8-AT17 -> 5896.72 | AU18: =AU8-AU17 -> 6820.81
A19: Deferred tax | B19: 50.13 | C19: 65.29 | D19: 79.05 | E19: 106.08 | F19: 49 | G19: -74 | I19: Exceptional items | J19: 260.64 | K19: 4306.14 | L19: 4566.82 | M19: 171.45 | N19: 494.32 | O19: 677.85 | Q19: Share of net profit/loss of associates and joint ventures | R19: 11.5352 | S19: 11.6771 | T19: 14.4477 | U19: 12.4242 | V19: 15.21 | W19: 12.24 | Y19: Total expenses | Z19: =SUM(Z11:Z18) -> 16308 | AA19: =SUM(AA11:AA18) -> 16503.4 | AB19: =SUM(AB11:AB18) -> 19038.5 | AC19: =SUM(AC11:AC18) -> 19713.7 | AD19: =SUM(AD11:AD18) -> 21719.1 | AE19: =SUM(AE11:AE18) -> 26083.4 | AG19: Profit before tax | AH19: =AH17-AH18 -> 1186.57 | AI19: =AI17-AI18 -> 1526.26 | AJ19: =AJ17-AJ18 -> 1225.91 | AK19: =AK17-AK18 -> 1847.16 | AL19: =AL17-AL18 -> 2352.11 | AM19: =AM17-AM18 -> 2672.81 | AO19: Exceptional items | AP19: 0 | AQ19: 0 | AR19: -182.12 | AS19: -182.42 | AT19: -194.82 | AU19: 0
A20: Total tax expense | B20: =SUM(B18:B19) -> 442.92 | C20: =SUM(C18:C19) -> 681.75 | D20: =SUM(D18:D19) -> 723.05 | E20: =SUM(E18:E19) -> 545.25 | F20: =SUM(F18:F19) -> 563 | G20: =SUM(G18:G19) -> 725 | I20: Profit before tax | J20: =J18-J19 -> 5009.59 | K20: =K18-K19 -> 2799.37 | L20: =L18-L19 -> 4481.32 | M20: =M18-M19 -> 9408.43 | N20: =N18-N19 -> 11087.89 | O20: =O18-O19 -> 13752.13 | Q20: Profit before tax | R20: =R7-R18+R19 -> 1437.7351 | S20: =S7-S18+S19 -> 1691.6118 | T20: =T7-T18+T19 -> 1974.6006 | U20: =U7-U18+U19 -> 1671.2391 | V20: =V7-V18+V19 -> 2397.94 | W20: =W7-W18+W19 -> 2516.33 | Y20: Profit before tax and before share of equity accounted investees | Z20: =Z9-Z19 -> 1829.6 | AA20: =AA9-AA19 -> 2835.5 | AB20: =AB9-AB19 -> 2991.1 | AC20: =AC9-AC19 -> 6011.5 | AD20: =AD9-AD19 -> 7186.3 | AE20: =AE9-AE19 -> 7657.8 | AG20: Current tax | AH20: 260.24 | AI20: 334.08 | AJ20: 346.22 | AK20: 354.77 | AL20: 461.73 | AM20: 619.01 | AO20: Profit before tax | AP20: =AP18+AP19 -> 2178.18 | AQ20: =AQ18+AQ19 -> 3290.06 | AR20: =AR18+AR19 -> 3493.27 | AS20: =AS18+AS19 -> 4038.35 | AT20: =AT18+AT19 -> 5701.9 | AU20: =AU18+AU19 -> 6820.81
A21: Profit after tax for the year | B21: =B17-B20 -> 1376.54 | C21: =C17-C20 -> 1984.29 | D21: =D17-D20 -> 2960.45 | E21: =E17-E20 -> 1823.38 | F21: =F17-F20 -> 1600 | G21: =G17-G20 -> 2191 | I21: Current tax | J21: 1320.14 | K21: 957.3 | L21: 354.39 | M21: 1869.22 | N21: 1989.3 | O21: 3320.05 | Q21: Current tax | R21: 408.3995 | S21: 394.7395 | T21: 469.0322 | U21: 327.5558 | V21: 492.51 | W21: 596.04 | Y21: Share of profit of equity accounted investees | Z21: 56.1 | AA21: 48 | AB21: 70.3 | AC21: 37 | AD21: 14.7 | AE21: 21.7 | AG21: Deferred tax | AH21: -59.23 | AI21: -52.98 | AJ21: 106.53 | AK21: 227.62 | AL21: 234 | AM21: 142.55 | AO21: Current tax | AP21: 682.87 | AQ21: 1052.72 | AR21: 1136.9 | AS21: 1264.77 | AT21: 1696.84 | AU21: 1708.35
I22: Deferred tax | J22: -497.34 | K22: -33.1 | L22: 797.53 | M22: -1021.63 | N22: -549.85 | O22: -925.5 | Q22: Deferred tax | R22: -32.6752 | S22: 2.4183 | T22: 52.6113 | U22: 34.0075 | V22: -35.36 | W22: -86.3 | Y22: Profit before tax | Z22: =Z20+Z21 -> 1885.7 | AA22: =AA20+AA21 -> 2883.5 | AB22: =AB20+AB21 -> 3061.4 | AC22: =AC20+AC21 -> 6048.5 | AD22: =AD20+AD21 -> 7201 | AE22: =AE20+AE21 -> 7679.5 | AG22: Excess/short provision for tax of earlier years | AH22: 13.66 | AI22: -6.72 | AJ22: -4.02 | AK22: 19.54 | AL22: 0 | AM22: 0 | AO22: Deferred tax | AP22: -51.67 | AQ22: -163.96 | AR22: -203.1 | AS22: -61.91 | AT22: -150.25 | AU22: -178.59
A23: Working notes | B23: 2020 | C23: 2021 | D23: 2022 | E23: 2023 | F23: 2024 | G23: 2025 | I23: Deferred tax - exceptional | J23: 0 | K23: -409.51 | L23: -76.42 | M23: 0 | N23: 0 | O23: 377.48 | Q23: Adjustment of tax relating to earlier periods | R23: 5.8706 | S23: 1.4261 | T23: 0 | U23: 0 | V23: 0 | W23: 0 | Y23: Current tax | Z23: 661.6 | AA23: 817.2 | AB23: 1101.3 | AC23: 814.4 | AD23: 1945.9 | AE23: 2258.1 | AG23: One time impact on current and deferred tax due to change in law | AH23: -52.82 | AI23: 0 | AJ23: 0 | AK23: 0 | AL23: 0 | AM23: 0 | AO23: Total tax expense | AP23: =AP21+AP22 -> 631.2 | AQ23: =AQ21+AQ22 -> 888.76 | AR23: =AR21+AR22 -> 933.8 | AS23: =AS21+AS22 -> 1202.86 | AT23: =AT21+AT22 -> 1546.59 | AU23: =AU21+AU22 -> 1529.76
A24: R&D Expense | B24: 51.26 | C24: 512.60 | D24: 207.00 | E24: 231.00 | F24: 285.90 | G24: 236.00 | I24: Total tax expense | J24: =SUM(J21:J23) -> 822.8 | K24: =SUM(K21:K23) -> 514.69 | L24: =SUM(L21:L23) -> 1075.5 | M24: =SUM(M21:M23) -> 847.59 | N24: =SUM(N21:N23) -> 1439.45 | O24: =SUM(O21:O23) -> 2772.03 | Q24: Total tax expense | R24: =SUM(R21:R23) -> 381.5949 | S24: =SUM(S21:S23) -> 398.5839 | T24: =SUM(T21:T23) -> 521.6435 | U24: =SUM(U21:U23) -> 361.5633 | V24: =SUM(V21:V23) -> 457.15 | W24: =SUM(W21:W23) -> 509.74 | Y24: Deferred tax | Z24: -801.9 | AA24: 114.7 | AB24: -222.4 | AC24: 726.8 | AD24: -322.8 | AE24: -303.8 | AG24: Total tax expense | AH24: =SUM(AH20:AH23) -> 161.85 | AI24: =SUM(AI20:AI23) -> 274.38 | AJ24: =SUM(AJ20:AJ23) -> 448.73 | AK24: =SUM(AK20:AK23) -> 601.93 | AL24: =SUM(AL20:AL23) -> 695.73 | AM24: =SUM(AM20:AM23) -> 761.56 | AO24: Profit after tax before share of profit/loss from associates | AP24: =AP18-AP23 -> 1546.98 | AQ24: =AQ18-AQ23 -> 2401.3 | AR24: =AR18-AR23 -> 2741.59 | AS24: =AS18-AS23 -> 3017.91 | AT24: =AT18-AT23 -> 4350.13 | AU24: =AU18-AU23 -> 5291.05
A25: Export Revenue | B25: 4526.61 | C25: =0.88*C7 -> 6188.1248 | D25: =0.9*D7 -> 8166.33 | E25: =0.88*E7 -> 7138.7096 | F25: =0.87*F7 -> 7120.08 | G25: =0.86*G7 -> 8352.32 | I25: Profit for the year before share of profit/loss of associates and joint venture | J25: =J20-J24 -> 4186.79 | K25: =K20-K24 -> 2284.68 | L25: =L20-L24 -> 3405.82 | M25: =M20-M24 -> 8560.84 | N25: =N20-N24 -> 9648.44 | O25: =O20-O24 -> 10980.1 | Q25: Profit for the year | R25: =R20-R24 -> 1056.1402 | S25: =S20-S24 -> 1293.0279 | T25: =T20-T24 -> 1452.9571 | U25: =U20-U24 -> 1309.6758 | V25: =V20-V24 -> 1940.79 | W25: =W20-W24 -> 2006.59 | Y25: Total tax expense | Z25: =SUM(Z23:Z24) -> -140.3 | AA25: =SUM(AA23:AA24) -> 931.9 | AB25: =SUM(AB23:AB24) -> 878.9 | AC25: =SUM(AC23:AC24) -> 1541.2 | AD25: =SUM(AD23:AD24) -> 1623.1 | AE25: =SUM(AE23:AE24) -> 1954.3 | AG25: Profit for the year | AH25: =AH19-AH24 -> 1024.72 | AI25: =AI19-AI24 -> 1251.88 | AJ25: =AJ19-AJ24 -> 777.18 | AK25: =AK19-AK24 -> 1245.23 | AL25: =AL19-AL24 -> 1656.38 | AM25: =AM19-AM24 -> 1911.25 | AO25: Share of profit/loss from associates | AP25: -47.46 | AQ25: -12.79 | AR25: -12.82 | AS25: -2.6 | AT25: -1.59 | AU25: -21.85
A26: Cost of Goods Sold | B26: =B9+B10+B11 -> 2108.54 | C26: =C9+C10+C11 -> 2324.08 | D26: =D9+D10+D11 -> 2967.14 | E26: =E9+E10+E11 -> 3053.72 | F26: =F9+F10+F11 -> 3129 | G26: =G9+G10+G11 -> 3725 | I26: Share of profit/loss of associates | J26: -13.83 | K26: -13.55 | L26: -21.73 | M26: -47.67 | N26: -38.27 | O26: -25.22 | Y26: Profit for the year | Z26: =Z22-Z25 -> 2026 | AA26: =AA22-AA25 -> 1951.6 | AB26: =AB22-AB25 -> 2182.5 | AC26: =AC22-AC25 -> 4507.3 | AD26: =AD22-AD25 -> 5577.9 | AE26: =AE22-AE25 -> 5725.2 | AO26: Profit for the year | AP26: =AP24+AP25 -> 1499.52 | AQ26: =AQ24+AQ25 -> 2388.51 | AR26: =AR24+AR25 -> 2728.77 | AS26: =AS24+AS25 -> 3015.31 | AT26: =AT24+AT25 -> 4348.54 | AU26: =AU24+AU25 -> 5269.2
A27: CapEx to revenue ratio | B27: =ABS('Cash Flow Statement'!B33)/'Income Statement'!B7 -> 0.21189101 | C27: =ABS('Cash Flow Statement'!C33)/'Income Statement'!C7 -> 0.12943617 | D27: =ABS('Cash Flow Statement'!D33)/'Income Statement'!D7 -> 0.078600791 | E27: =ABS('Cash Flow Statement'!E33)/'Income Statement'!E7 -> 0.058309922 | F27: =ABS('Cash Flow Statement'!F33)/'Income Statement'!F7 -> 0.12255621 | G27: =ABS('Cash Flow Statement'!G33)/'Income Statement'!G7 -> 0.14806425 | I27: Share of profit/loss of joint venture | J27: -1 | K27: 1.22 | L27: 5.19 | M27: -0.23 | N27: -0.14 | O27: 9.87 | Q27: Working Notes | R27: 2020 | S27: 2021 | T27: 2022 | U27: 2023 | V27: 2024 | W27: 2025 | AG27: Working Notes | AH27: 2020 | AI27: 2021 | AJ27: 2022 | AK27: 2023 | AL27: 2024 | AM27: 2025
A28: CapEx as % of revenue (average) | B28: =AVERAGE(B27:G27) -> 0.12480973 | I28: Profit for the year before non controlling interests | J28: =SUM(J25:J27) -> 4171.96 | K28: =SUM(K25:K27) -> 2272.35 | L28: =SUM(L25:L27) -> 3389.28 | M28: =SUM(M25:M27) -> 8512.94 | N28: =SUM(N25:N27) -> 9610.03 | O28: =SUM(O25:O27) -> 10964.75 | Q28: R&D | R28: 143.7 | S28: 119 | T28: 167 | U28: 1000 | V28: 223 | W28: 256.3 | Y28: Working Notes | Z28: 2020 | AA28: 2021 | AB28: 2022 | AC28: 2023 | AD28: 2024 | AE28: 2025 | AG28: R&D | AH28: 380.9 | AI28: 487 | AJ28: 516 | AK28: 516 | AL28: =0.047*AL7 -> 506.93025 | AM28: 581 | AO28: Working Notes | AP28: 2020 | AQ28: 2021 | AR28: 2022 | AS28: 2023 | AT28: 2024 | AU28: 2025
A29: Depreciation to PPE ratio | B29: =B14/'Balance Sheet'!B6 -> 0.067158044 | C29: =C14/'Balance Sheet'!C6 -> 0.069178219 | D29: =D14/'Balance Sheet'!D6 -> 0.072207078 | E29: =E14/'Balance Sheet'!E6 -> 0.072797544 | F29: =F14/'Balance Sheet'!F6 -> 0.079864779 | G29: =G14/'Balance Sheet'!G6 -> 0.073937833 | I29: Non controlling interests | J29: 407.03 | K29: -631.47 | L29: 116.55 | M29: 39.36 | N29: 33.65 | O29: 35.71 | Q29: Export Revenue | R29: =0.1*R7 -> 597.56529 | S29: =0.092*S7 -> 587.45499 | T29: =0.024*T7 -> 191.46203 | U29: =0.034*U7 -> 301.85199 | V29: =0.079*V7 -> 832.71214 | W29: =0.09*W7 -> 1146.9807 | Y29: R&D | Z29: 1541 | AA29: 1654.1 | AB29: 1748.2 | AC29: 1938.1 | AD29: 2287.3 | AE29: 2738 | AG29: Export Revenue | AH29: 4422 | AI29: 4307 | AJ29: =0.45*AJ7 -> 3917.07 | AK29: =0.41*AK7 -> 3962.7689 | AL29: =0.425*AL7 -> 4583.9437 | AM29: =0.24*AM7 -> 2769.4464 | AO29: R&D | AP29: 1362 | AQ29: =0.0482*AQ8 -> 936.31296 | AR29: =0.05*AR8 -> 1102.2125 | AS29: 3862 | AT29: 1571 | AU29: 4317
A30: Depreciation as % of PPE (average) | B30: =AVERAGE(B29:G29) -> 0.072523916 | I30: Profit for the year | J30: =J28-J29 -> 3764.93 | K30: =K28-K29 -> 2903.82 | L30: =L28-L29 -> 3272.73 | M30: =M28-M29 -> 8473.58 | N30: =N28-N29 -> 9576.38 | O30: =O28-O29 -> 10929.04 | Q30: COGS | R30: =R9+R10+R11 -> 1878.0711 | S30: =S9+S10+S11 -> 1780.6086 | T30: =T9+T10+T11 -> 2421.7284 | U30: =U9+U10+U11 -> 2913.642 | V30: =V9+V10+V11 -> 3198.47 | W30: =W9+W10+W11 -> 3489.04 | Y30: Export Revenue | Z30: =0.834*Z9 -> 15126.758 | AA30: =0.8*AA9 -> 15471.12 | AB30: =0.69*AB9 -> 15200.424 | AC30: =0.79*AC9 -> 20322.908 | AD30: =0.834*AD9 -> 24107.104 | AE30: =0.835*AE9 -> 28173.902 | AG30: COGS | AH30: =SUM(AH9:AH11) -> 2166.92 | AI30: =SUM(AI9:AI11) -> 2146.42 | AJ30: =SUM(AJ9:AJ11) -> 2442.01 | AK30: =SUM(AK9:AK11) -> 2735.19 | AL30: =SUM(AL9:AL11) -> 2686.21 | AM30: =SUM(AM9:AM11) -> 2775.9 | AO30: Export Revenue | AP30: =0.515*AP8 -> 9000.2378 | AQ30: =0.5*AQ8 -> 9712.79 | AR30: =0.587*AR8 -> 12939.975 | AS30: =0.57*AS8 -> 13240.285 | AT30: =0.573*AT8 -> 15196.338 | AU30: =0.57*AU8 -> 16193.409
A31: Revenue CAGR | B31: =(G7/B7)^(1/6)-1 -> 0.096629428 | Q31: CapEx to revenue ratio | R31: =ABS('Cash Flow Statement'!R44)/'Income Statement'!R7 -> 0.038149773 | S31: =ABS('Cash Flow Statement'!S44)/'Income Statement'!S7 -> 0.048302276 | T31: =ABS('Cash Flow Statement'!T44)/'Income Statement'!T7 -> 0.058271321 | U31: =ABS('Cash Flow Statement'!U44)/'Income Statement'!U7 -> 0.088873679 | V31: =ABS('Cash Flow Statement'!V44)/'Income Statement'!V7 -> 0.029915584 | W31: =ABS('Cash Flow Statement'!W44)/'Income Statement'!W7 -> 0.036156755 | Y31: COGS | Z31: =SUM(Z11+Z12+Z13) -> 5554.4 | AA31: =SUM(AA11+AA12+AA13) -> 6078.9 | AB31: =SUM(AB11+AB12+AB13) -> 7442.2 | AC31: =SUM(AC11+AC12+AC13) -> 7657.7 | AD31: =SUM(AD11+AD12+AD13) -> 8208.7 | AE31: =SUM(AE11+AE12+AE13) -> 9979.9 | AG31: CapEx to revenue ratio | AH31: =ABS('Cash Flow Statement'!AH22)/'Income Statement'!AH7 -> 0.050465163 | AI31: =ABS('Cash Flow Statement'!AI22)/'Income Statement'!AI7 -> 0.041574252 | AJ31: =ABS('Cash Flow Statement'!AJ22)/'Income Statement'!AJ7 -> 0 | AK31: =ABS('Cash Flow Statement'!AK22)/'Income Statement'!AK7 -> 0.20692602 | AL31: =ABS('Cash Flow Statement'!AL22)/'Income Statement'!AL7 -> 0.040125165 | AM31: =ABS('Cash Flow Statement'!AM22)/'Income Statement'!AM7 -> 0.053024604 | AO31: COGS | AP31: =SUM(AP10:AP12) -> 5991.42 | AQ31: =SUM(AQ10:AQ12) -> 7351.89 | AR31: =SUM(AR10:AR12) -> 8495.6 | AS31: =SUM(AS10:AS12) -> 8252.28 | AT31: =SUM(AT10:AT12) -> 8819.57 | AU31: =SUM(AU10:AU12) -> 8928.99
A32: COGS to revenue ratio | B32: =B26/B7 -> 0.37760049 | C32: =C26/C7 -> 0.33050245 | D32: =D26/D7 -> 0.32700442 | E32: =E26/E7 -> 0.37643688 | F32: =F26/F7 -> 0.38233138 | G32: =G26/G7 -> 0.38354613 | I32: Working Notes | J32: 2020 | K32: 2021 | L32: 2022 | M32: 2023 | N32: 2024 | O32: 2025 | Q32: Average | R32: =AVERAGE(R31:W31) -> 0.049944898 | Y32: CapEx to revenue ratio | Z32: =ABS('Cash Flow Statement'!Z28)/'Income Statement'!Z9 -> 0.00072225653 | AA32: =ABS('Cash Flow Statement'!AA28)/'Income Statement'!AA9 -> 0.05036998 | AB32: =ABS('Cash Flow Statement'!AB28)/'Income Statement'!AB9 -> 0.066546828 | AC32: =ABS('Cash Flow Statement'!AC28)/'Income Statement'!AC9 -> 0.044015207 | AD32: =ABS('Cash Flow Statement'!AD28)/'Income Statement'!AD9 -> 0.056747182 | AE32: =ABS('Cash Flow Statement'!AE28)/'Income Statement'!AE9 -> 0.081514588 | AG32: Average | AH32: =AVERAGE(AL31:AM31) -> 0.046574885 | AO32: CapEx to revenue ratio | AP32: =ABS('Cash Flow Statement'!AP29)/'Income Statement'!AP8 -> 0.032774306 | AQ32: =ABS('Cash Flow Statement'!AQ29)/'Income Statement'!AQ8 -> 0.032413961 | AR32: =ABS('Cash Flow Statement'!AR29)/'Income Statement'!AR8 -> 0.024682627 | AS32: =ABS('Cash Flow Statement'!AS29)/'Income Statement'!AS8 -> 0.036185181 | AT32: =ABS('Cash Flow Statement'!AT29)/'Income Statement'!AT8 -> 0.041411111 | AU32: =ABS('Cash Flow Statement'!AU29)/'Income Statement'!AU8 -> 0.040907457
A33: Average of COGS | B33: =AVERAGE(B32:G32) -> 0.36290362 | I33: R&D | J33: 2302.5 | K33: 2149.9 | L33: 2220 | M33: 2367.6 | N33: 3241 | O33: 3248.4 | Q33: Depreciation | R33: ='Balance Sheet'!R6/('Balance Sheet'!R6+'Balance Sheet'!R10)*'Income Statement'!R14 -> 97.657623 | S33: ='Balance Sheet'!S6/('Balance Sheet'!S6+'Balance Sheet'!S10)*'Income Statement'!S14 -> 117.63221 | T33: ='Balance Sheet'!T6/('Balance Sheet'!T6+'Balance Sheet'!T10)*'Income Statement'!T14 -> 78.774794 | U33: ='Balance Sheet'!U6/('Balance Sheet'!U6+'Balance Sheet'!U10)*'Income Statement'!U14 -> 191.02437 | V33: ='Balance Sheet'!V6/('Balance Sheet'!V6+'Balance Sheet'!V10)*'Income Statement'!V14 -> 241.84255 | W33: ='Balance Sheet'!W6/('Balance Sheet'!W6+'Balance Sheet'!W10)*'Income Statement'!W14 -> 137.9143 | Y33: Average | Z33: =AVERAGE(AA32:AE32) -> 0.059838757 | AG33: Depreciation | AH33: ='Balance Sheet'!AH6/('Balance Sheet'!AH6+'Balance Sheet'!AH10)*'Income Statement'!AH14 -> 261.34818 | AI33: ='Balance Sheet'!AI6/('Balance Sheet'!AI6+'Balance Sheet'!AI10)*'Income Statement'!AI14 -> 274.94512 | AJ33: ='Balance Sheet'!AJ6/('Balance Sheet'!AJ6+'Balance Sheet'!AJ10)*'Income Statement'!AJ14 -> 282.5068 | AK33: ='Balance Sheet'!AK6/('Balance Sheet'!AK6+'Balance Sheet'!AK10)*'Income Statement'!AK14 -> 242.96032 | AL33: ='Balance Sheet'!AL6/('Balance Sheet'!AL6+'Balance Sheet'!AL10)*'Income Statement'!AL14 -> 332.02218 | AM33: ='Balance Sheet'!AM6/('Balance Sheet'!AM6+'Balance Sheet'!AM10)*'Income Statement'!AM14 -> 346.54392 | AO33: Average | AP33: =AVERAGE(AP32:AU32) -> 0.034729107
A34: Other income CAGR | B34: =(G6/B6)^(1/6)-1 -> 0.1085942 | I34: Export revenue | J34: 4204.755 | K34: =0.68*K7 -> 23346.889 | L34: =0.48*L7 -> 18996.48 | M34: =0.689*M7 -> 30674.418 | N34: =0.727*N7 -> 36241.706 | O34: =0.7*O7 -> 38180.436 | Q34: Amortisation | R34: ='Balance Sheet'!R10/('Balance Sheet'!R6+'Balance Sheet'!R10)*'Income Statement'!R14 -> 1.400777 | S34: ='Balance Sheet'!S10/('Balance Sheet'!S6+'Balance Sheet'!S10)*'Income Statement'!S14 -> 1.3380879 | T34: ='Balance Sheet'!T10/('Balance Sheet'!T6+'Balance Sheet'!T10)*'Income Statement'!T14 -> 87.844406 | U34: ='Balance Sheet'!U10/('Balance Sheet'!U6+'Balance Sheet'!U10)*'Income Statement'!U14 -> 134.89513 | V34: ='Balance Sheet'!V10/('Balance Sheet'!V6+'Balance Sheet'!V10)*'Income Statement'!V14 -> 136.57745 | W34: ='Balance Sheet'!W10/('Balance Sheet'!W6+'Balance Sheet'!W10)*'Income Statement'!W14 -> 483.3057 | Y34: Depreciation | Z34: ='Balance Sheet'!Z6/('Balance Sheet'!Z6+'Balance Sheet'!Z9)*'Income Statement'!Z15 -> 849.64705 | AA34: ='Balance Sheet'!AA6/('Balance Sheet'!AA6+'Balance Sheet'!AA9)*'Income Statement'!AA15 -> 923.27151 | AB34: ='Balance Sheet'!AB6/('Balance Sheet'!AB6+'Balance Sheet'!AB9)*'Income Statement'!AB15 -> 721.17495 | AC34: ='Balance Sheet'!AC6/('Balance Sheet'!AC6+'Balance Sheet'!AC9)*'Income Statement'!AC15 -> 806.63336 | AD34: ='Balance Sheet'!AD6/('Balance Sheet'!AD6+'Balance Sheet'!AD9)*'Income Statement'!AD15 -> 930.13913 | AE34: ='Balance Sheet'!AE6/('Balance Sheet'!AE6+'Balance Sheet'!AE9)*'Income Statement'!AE15 -> 735.21266 | AG34: Amortisation | AH34: ='Balance Sheet'!AH10/('Balance Sheet'!AH6+'Balance Sheet'!AH10)*'Income Statement'!AH14 -> 393.03182 | AI34: ='Balance Sheet'!AI10/('Balance Sheet'!AI6+'Balance Sheet'!AI10)*'Income Statement'!AI14 -> 382.84488 | AJ34: ='Balance Sheet'!AJ10/('Balance Sheet'!AJ6+'Balance Sheet'!AJ10)*'Income Statement'!AJ14 -> 379.6532 | AK34: ='Balance Sheet'!AK10/('Balance Sheet'!AK6+'Balance Sheet'!AK10)*'Income Statement'!AK14 -> 463.62968 | AL34: ='Balance Sheet'!AL10/('Balance Sheet'!AL6+'Balance Sheet'!AL10)*'Income Statement'!AL14 -> 476.24782 | AM34: ='Balance Sheet'!AM10/('Balance Sheet'!AM6+'Balance Sheet'!AM10)*'Income Statement'!AM14 -> 448.38608 | AO34: Depreciation | AP34: ='Balance Sheet'!AP6/('Balance Sheet'!AP6+'Balance Sheet'!AP11)*'Income Statement'!AP15 -> 895.69891 | AQ34: ='Balance Sheet'!AQ6/('Balance Sheet'!AQ6+'Balance Sheet'!AQ11)*'Income Statement'!AQ15 -> 815.19809 | AR34: ='Balance Sheet'!AR6/('Balance Sheet'!AR6+'Balance Sheet'!AR11)*'Income Statement'!AR15 -> 826.54422 | AS34: ='Balance Sheet'!AS6/('Balance Sheet'!AS6+'Balance Sheet'!AS11)*'Income Statement'!AS15 -> 940.95453 | AT34: ='Balance Sheet'!AT6/('Balance Sheet'!AT6+'Balance Sheet'!AT11)*'Income Statement'!AT15 -> 819.33647 | AU34: ='Balance Sheet'!AU6/('Balance Sheet'!AU6+'Balance Sheet'!AU11)*'Income Statement'!AU15 -> 862.74315
A35: Average interest paid(5 yrs historical) | B35: =AVERAGE(B13:G13) -> 2.24 | I35: COGS | J35: =J9+J10+J11 -> 9230.45 | K35: =K9+K10+K11 -> 8690.08 | L35: =L9+L10+L11 -> 10351.54 | M35: =M9+M10+M11 -> 10662.16 | N35: =N9+N10+N11 -> 10662.61 | O35: =O9+O10+O11 -> 10747.36 | Q35: Average (Depreciation) | R35: =AVERAGE(R33:W33)/AVERAGE('Balance Sheet'!R6:W6) -> 0.067638412 | Y35: Amortisation | Z35: ='Balance Sheet'!Z9/('Balance Sheet'!Z9+'Balance Sheet'!Z6)*'Income Statement'!Z15 -> 313.45295 | AA35: ='Balance Sheet'!AA9/('Balance Sheet'!AA9+'Balance Sheet'!AA6)*'Income Statement'!AA15 -> 305.52849 | AB35: ='Balance Sheet'!AB9/('Balance Sheet'!AB9+'Balance Sheet'!AB6)*'Income Statement'!AB15 -> 444.02505 | AC35: ='Balance Sheet'!AC9/('Balance Sheet'!AC9+'Balance Sheet'!AC6)*'Income Statement'!AC15 -> 443.56664 | AD35: ='Balance Sheet'!AD9/('Balance Sheet'!AD9+'Balance Sheet'!AD6)*'Income Statement'!AD15 -> 539.86087 | AE35: ='Balance Sheet'!AE9/('Balance Sheet'!AE9+'Balance Sheet'!AE6)*'Income Statement'!AE15 -> 968.48734 | AG35: Average (Depreciation) | AH35: =AVERAGE(AH33:AM33)/AVERAGE('Balance Sheet'!AH6:AM6) -> 0.10161856 | AO35: Amortisation | AP35: ='Balance Sheet'!AP11/('Balance Sheet'!AP11+'Balance Sheet'!AP6)*'Income Statement'!AP15 -> 278.95109 | AQ35: ='Balance Sheet'!AQ11/('Balance Sheet'!AQ11+'Balance Sheet'!AQ6)*'Income Statement'!AQ15 -> 252.46191 | AR35: ='Balance Sheet'!AR11/('Balance Sheet'!AR11+'Balance Sheet'!AR6)*'Income Statement'!AR15 -> 225.40578 | AS35: ='Balance Sheet'!AS11/('Balance Sheet'!AS11+'Balance Sheet'!AS6)*'Income Statement'!AS15 -> 231.15547 | AT35: ='Balance Sheet'!AT11/('Balance Sheet'!AT11+'Balance Sheet'!AT6)*'Income Statement'!AT15 -> 231.68353 | AU35: ='Balance Sheet'!AU11/('Balance Sheet'!AU11+'Balance Sheet'!AU6)*'Income Statement'!AU15 -> 244.20685
I36: CapEx to revenue ratio | J36: =ABS('Cash Flow Statement'!J30)/'Income Statement'!J7 -> 0.046066319 | K36: =ABS('Cash Flow Statement'!K30)/'Income Statement'!K7 -> 0.034081132 | L36: =ABS('Cash Flow Statement'!L30)/'Income Statement'!L7 -> 0.03777643 | M36: =ABS('Cash Flow Statement'!M30)/'Income Statement'!M7 -> 0.046845702 | N36: =ABS('Cash Flow Statement'!N30)/'Income Statement'!N7 -> 0.044167785 | O36: =ABS('Cash Flow Statement'!O30)/'Income Statement'!O7 -> 0.039025379 | Q36: Average (Amortisation) | R36: =AVERAGE(T34:W34)/AVERAGE('Balance Sheet'!T10:W10) -> 0.057179534 | Y36: Average (Depreciation) | Z36: =AVERAGE(Z34:AE34)/AVERAGE('Balance Sheet'!Z6:AE6) -> 0.1511431 | AG36: Average (Amortisation) | AH36: =AVERAGE(AH34:AM34)/AVERAGE('Balance Sheet'!AH10:AM10) -> 0.1009194 | AO36: Average (Depreciation) | AP36: =AVERAGE(AP34:AU34)/AVERAGE('Balance Sheet'!AP6:AU6) -> 0.18233819
A37: R&D expense ratio (Average) | B37: =AVERAGE('Ratio Analysis'!B25:G25) -> 0.032099707 | I37: Average | J37: =AVERAGE(J36:O36) -> 0.041327124 | Q37: Revenue CAGR | R37: =(W5/R5)^(1/6)-1 -> 0.12973013 | Y37: Average (Amortisation) | Z37: =AVERAGE(Z35:AE35)/AVERAGE('Balance Sheet'!Z9:AE9) -> 0.13559166 | AG37: Revenue CAGR | AH37: =(AM7/AH7)^(1/6)-1 -> 0.0616197 | AO37: Average (Amortisation) | AP37: =AVERAGE(AS35:AU35)/AVERAGE('Balance Sheet'!AS11:AU11) -> 0.18600498
A38: SG&A to Revenue ratio | B38: =(B12+B15)/B7 -> 0.26212337 | C38: =(C12+C15)/C7 -> 0.25389507 | D38: =(D12+D15)/D7 -> 0.23262286 | E38: =(E12+E15)/E7 -> 0.28919142 | F38: =(F12+F15)/F7 -> 0.30681818 | G38: =(G12+G15)/G7 -> 0.27460873 | I38: Depreciation | J38: ='Balance Sheet'!J6/('Balance Sheet'!J6+'Balance Sheet'!J9)*'Income Statement'!J14 -> 1325.5125 | K38: ='Balance Sheet'!K6/('Balance Sheet'!K6+'Balance Sheet'!K9)*'Income Statement'!K14 -> 1394.5492 | L38: ='Balance Sheet'!L6/('Balance Sheet'!L6+'Balance Sheet'!L9)*'Income Statement'!L14 -> 1110.6639 | M38: ='Balance Sheet'!M6/('Balance Sheet'!M6+'Balance Sheet'!M9)*'Income Statement'!M14 -> 1393.6219 | N38: ='Balance Sheet'!N6/('Balance Sheet'!N6+'Balance Sheet'!N9)*'Income Statement'!N14 -> 1775.176 | O38: ='Balance Sheet'!O6/('Balance Sheet'!O6+'Balance Sheet'!O9)*'Income Statement'!O14 -> 1893.9492 | Q38: COGS to Revenue ratio | R38: =R30/R7 -> 0.31428718 | S38: =S30/S7 -> 0.27885709 | T38: =T30/T7 -> 0.30356662 | U38: =U30/U7 -> 0.32818676 | V38: =V30/V7 -> 0.30344115 | W38: =W30/W7 -> 0.27377409 | Y38: Revenue CAGR | Z38: =((AE5+AE6+AE7)/(Z5+Z6+Z7))^(1/6)-1 -> 0.10932053 | AG38: COGS to Revenue ratio | AH38: =AH30/AH7 -> 0.26882829 | AI38: =AI30/AI7 -> 0.26625632 | AJ38: =AJ30/AJ7 -> 0.28054247 | AK38: =AK30/AK7 -> 0.28299099 | AL38: =AL30/AL7 -> 0.24905176 | AM38: =AM30/AM7 -> 0.24055927 | AO38: Revenue CAGR | AP38: =(AU8/AP8)^(1/6)-1 -> 0.084349907
A39: Average | B39: =AVERAGE(B38:G38) -> 0.26987661 | I39: Amortisation | J39: ='Balance Sheet'!J9/('Balance Sheet'!J6+'Balance Sheet'!J9)*'Income Statement'!J14 -> 727.26747 | K39: ='Balance Sheet'!K9/('Balance Sheet'!K6+'Balance Sheet'!K9)*'Income Statement'!K14 -> 685.40082 | L39: ='Balance Sheet'!L9/('Balance Sheet'!L6+'Balance Sheet'!L9)*'Income Statement'!L14 -> 1033.0761 | M39: ='Balance Sheet'!M9/('Balance Sheet'!M6+'Balance Sheet'!M9)*'Income Statement'!M14 -> 1135.8081 | N39: ='Balance Sheet'!N9/('Balance Sheet'!N6+'Balance Sheet'!N9)*'Income Statement'!N14 -> 781.46397 | O39: ='Balance Sheet'!O9/('Balance Sheet'!O6+'Balance Sheet'!O9)*'Income Statement'!O14 -> 681.4408 | Q39: Average | R39: =AVERAGE(R38:W38) -> 0.30035215 | Y39: COGS to Revenue ratio | Z39: =Z31/Z9 -> 0.30623677 | AA39: =AA31/AA9 -> 0.31433536 | AB39: =AB31/AB9 -> 0.33782729 | AC39: =AC31/AC9 -> 0.2976731 | AD39: =AD31/AD9 -> 0.283985 | AE39: =AE31/AE9 -> 0.29577786 | AG39: Average | AH39: =AVERAGE(AH38:AM38) -> 0.26470485 | AO39: COGS to Revenue ratio | AP39: =AP31/AP8 -> 0.34283331 | AQ39: =AQ31/AQ8 -> 0.37846438 | AR39: =AR31/AR8 -> 0.38538848 | AS39: =AS31/AS8 -> 0.35526423 | AT39: =AT31/AT8 -> 0.3325547 | AU39: =AU31/AU8 -> 0.31429603
A40: Other non-current assets | B40: =('Balance Sheet'!B12+'Balance Sheet'!B13+'Balance Sheet'!B14+'Balance Sheet'!B15+'Balance Sheet'!B10)/'Income Statement'!B7 -> 0.021312488 | C40: =('Balance Sheet'!C12+'Balance Sheet'!C13+'Balance Sheet'!C14+'Balance Sheet'!C15+'Balance Sheet'!C10)/'Income Statement'!C7 -> 0.018421606 | D40: =('Balance Sheet'!D12+'Balance Sheet'!D13+'Balance Sheet'!D14+'Balance Sheet'!D15+'Balance Sheet'!D10)/'Income Statement'!D7 -> 0.025152914 | E40: =('Balance Sheet'!E12+'Balance Sheet'!E13+'Balance Sheet'!E14+'Balance Sheet'!E15+'Balance Sheet'!E10)/'Income Statement'!E7 -> 0.023735942 | F40: =('Balance Sheet'!F12+'Balance Sheet'!F13+'Balance Sheet'!F14+'Balance Sheet'!F15+'Balance Sheet'!F10)/'Income Statement'!F7 -> 0.033968719 | G40: =('Balance Sheet'!G12+'Balance Sheet'!G13+'Balance Sheet'!G14+'Balance Sheet'!G15+'Balance Sheet'!G10)/'Income Statement'!G7 -> 0.039847611 | I40: Average (Depreciation) | J40: =AVERAGE(J38:O38)/AVERAGE('Balance Sheet'!J6:O6) -> 0.17529784 | Q40: Other Income CAGR | R40: =(W6/R6)^(1/6)-1 -> 0.31505946 | Y40: Average | Z40: =AVERAGE(Z39:AE39) -> 0.30597256 | AG40: Other Income CAGR | AH40: =(AM6/AH6)^(1/6)-1 -> -0.24056735 | AO40: Average | AP40: =AVERAGE(AP39:AU39) -> 0.35146685
A41: Average | B41: =AVERAGE(B40:G40) -> 0.027073214 | I41: Average (Amortisation) | J41: =AVERAGE(J39:O39)/AVERAGE('Balance Sheet'!J9:O9) -> 0.1840629 | Q41: R&D Expense ratio (Average) | R41: =AVERAGE('Ratio Analysis'!R25:W25) -> 0.036253796 | Y41: Other Income CAGR | Z41: =(AE8/Z8)^(1/6)-1 -> 0.099644403 | AG41: R&D Expense ratio (Average) | AH41: =AVERAGE('Ratio Analysis'!AH25:AM25) -> 0.05294676 | AO41: Other Income CAGR | AP41: =((AU6+AU7)/(AP6+AP7))^(1/6)-1 -> 0.083485215
A42: Dividend Payout | B42: =ABS('Cash Flow Statement'!B46)/'Income Statement'!B21 -> 0.74398129 | C42: =ABS('Cash Flow Statement'!C46)/'Income Statement'!C21 -> 0 | D42: =ABS('Cash Flow Statement'!D46)/'Income Statement'!D21 -> 0.17934436 | E42: =ABS('Cash Flow Statement'!E46)/'Income Statement'!E21 -> 0.43677676 | F42: =ABS('Cash Flow Statement'!F46)/'Income Statement'!F21 -> 0.4975 | G42: =ABS('Cash Flow Statement'!G46)/'Income Statement'!G21 -> 0.36330443 | I42: Revenue CAGR | J42: =(O7/J7)^(1/6)-1 -> 0.084776653 | Q42: SG&A to Revenue ratio | R42: =(R12+R17)/R7 -> 0.41163231 | S42: =(S12+S17)/S7 -> 0.4334916 | T42: =(T12+T17)/T7 -> 0.42249301 | U42: =(U12+U17)/U7 -> 0.44324786 | V42: =(V12+V17)/V7 -> 0.43149955 | W42: =(W12+W17)/W7 -> 0.44729811 | Y42: R&D Expense ratio (Average) | Z42: =AVERAGE('Ratio Analysis'!Z25:AE25) -> 0.080911161 | AG42: SG&A to Revenue ratio | AH42: =(AH12+AH15)/AH7 -> 0.44686817 | AI42: =(AI12+AI15)/AI7 -> 0.41837603 | AJ42: =(AJ12+AJ15)/AJ7 -> 0.41756772 | AK42: =(AK12+AK15)/AK7 -> 0.41829164 | AL42: =(AL12+AL15)/AL7 -> 0.4333477 | AM42: =(AM12+AM15)/AM7 -> 0.43496346 | AO42: R&D Expense ratio (Average) | AP42: =AVERAGE('Ratio Analysis'!AP25:AU25) -> 0.092264747
A43: Average | B43: =AVERAGE(E42:G42) -> 0.43252706 | I43: COGS to Revenue ratio | J43: =J35/J7 -> 0.27575412 | K43: =K35/K7 -> 0.25310672 | L43: =L35/L7 -> 0.26156105 | M43: =M35/M7 -> 0.23949039 | N43: =N35/N7 -> 0.21388942 | O43: =O35/O7 -> 0.19704207 | Q43: Average | R43: =AVERAGE(R42:W42) -> 0.43161041 | Y43: SG&A to Revenue ratio | Z43: =(Z18+Z14)/Z9 -> 0.43090045 | AA43: =(AA18+AA14)/AA9 -> 0.43549013 | AB43: =(AB18+AB14)/AB9 -> 0.42692105 | AC43: =(AC18+AC14)/AC9 -> 0.41177911 | AD43: =(AD18+AD14)/AD9 -> 0.41061532 | AE43: =(AE18+AE14)/AE9 -> 0.41337 | AG43: Average | AH43: =AVERAGE(AH42:AM42) -> 0.42823579 | AO43: SG&A to Revenue ratio | AP43: =(AP16+AP13)/AP8 -> 0.4540223 | AQ43: =(AQ16+AQ13)/AQ8 -> 0.38893408 | AR43: =(AR16+AR13)/AR8 -> 0.39533937 | AS43: =(AS16+AS13)/AS8 -> 0.40785421 | AT43: =(AT16+AT13)/AT8 -> 0.40208162 | AU43: =(AU16+AU13)/AU8 -> 0.40446801
A44: Average Receivables turnover | B44: =AVERAGE('Ratio Analysis'!B22:G22) -> 4.1493647 | I44: Average | J44: =AVERAGE(J43:O43) -> 0.24014063 | Q44: Other non-current Assets | R44: =('Balance Sheet'!R19+'Balance Sheet'!R18+'Balance Sheet'!R17+'Balance Sheet'!R16+'Balance Sheet'!R7+'Balance Sheet'!R8+'Balance Sheet'!R9+'Balance Sheet'!R11+'Balance Sheet'!R12+'Balance Sheet'!R13)/'Income Statement'!R7 -> 0.1133533 | S44: =('Balance Sheet'!S19+'Balance Sheet'!S18+'Balance Sheet'!S17+'Balance Sheet'!S16+'Balance Sheet'!S7+'Balance Sheet'!S8+'Balance Sheet'!S9+'Balance Sheet'!S11+'Balance Sheet'!S12+'Balance Sheet'!S13)/'Income Statement'!S7 -> 0.12331359 | T44: =('Balance Sheet'!T19+'Balance Sheet'!T18+'Balance Sheet'!T17+'Balance Sheet'!T16+'Balance Sheet'!T7+'Balance Sheet'!T8+'Balance Sheet'!T9+'Balance Sheet'!T11+'Balance Sheet'!T12+'Balance Sheet'!T13)/'Income Statement'!T7 -> 0.14774633 | U44: =('Balance Sheet'!U19+'Balance Sheet'!U18+'Balance Sheet'!U17+'Balance Sheet'!U16+'Balance Sheet'!U7+'Balance Sheet'!U8+'Balance Sheet'!U9+'Balance Sheet'!U11+'Balance Sheet'!U12+'Balance Sheet'!U13)/'Income Statement'!U7 -> 0.13371618 | V44: =('Balance Sheet'!V19+'Balance Sheet'!V18+'Balance Sheet'!V17+'Balance Sheet'!V16+'Balance Sheet'!V7+'Balance Sheet'!V8+'Balance Sheet'!V9+'Balance Sheet'!V11+'Balance Sheet'!V12+'Balance Sheet'!V13)/'Income Statement'!V7 -> 0.082881907 | W44: =('Balance Sheet'!W19+'Balance Sheet'!W18+'Balance Sheet'!W17+'Balance Sheet'!W16+'Balance Sheet'!W7+'Balance Sheet'!W8+'Balance Sheet'!W9+'Balance Sheet'!W11+'Balance Sheet'!W12+'Balance Sheet'!W13)/'Income Statement'!W7 -> 0.64864413 | Y44: Average | Z44: =AVERAGE(Z43:AE43) -> 0.42151268 | AG44: Other non-current Assets | AH44: =('Balance Sheet'!AH17+'Balance Sheet'!AH16+'Balance Sheet'!AH15+'Balance Sheet'!AH14+'Balance Sheet'!AH12+'Balance Sheet'!AH9+'Balance Sheet'!AH8+'Balance Sheet'!AH7)/'Income Statement'!AH7 -> 0.2277247 | AI44: =('Balance Sheet'!AI17+'Balance Sheet'!AI16+'Balance Sheet'!AI15+'Balance Sheet'!AI14+'Balance Sheet'!AI12+'Balance Sheet'!AI9+'Balance Sheet'!AI8+'Balance Sheet'!AI7)/'Income Statement'!AI7 -> 0.22422558 | AJ44: =('Balance Sheet'!AJ17+'Balance Sheet'!AJ16+'Balance Sheet'!AJ15+'Balance Sheet'!AJ14+'Balance Sheet'!AJ12+'Balance Sheet'!AJ9+'Balance Sheet'!AJ8+'Balance Sheet'!AJ7)/'Income Statement'!AJ7 -> 0.19326563 | AK44: =('Balance Sheet'!AK17+'Balance Sheet'!AK16+'Balance Sheet'!AK15+'Balance Sheet'!AK14+'Balance Sheet'!AK12+'Balance Sheet'!AK9+'Balance Sheet'!AK8+'Balance Sheet'!AK7)/'Income Statement'!AK7 -> 0.20320032 | AL44: =('Balance Sheet'!AL17+'Balance Sheet'!AL16+'Balance Sheet'!AL15+'Balance Sheet'!AL14+'Balance Sheet'!AL12+'Balance Sheet'!AL9+'Balance Sheet'!AL8+'Balance Sheet'!AL7)/'Income Statement'!AL7 -> 0.15987483 | AM44: =('Balance Sheet'!AM17+'Balance Sheet'!AM16+'Balance Sheet'!AM15+'Balance Sheet'!AM14+'Balance Sheet'!AM12+'Balance Sheet'!AM9+'Balance Sheet'!AM8+'Balance Sheet'!AM7)/'Income Statement'!AM7 -> 0.16390077 | AO44: Average | AP44: =AVERAGE(AP43:AU43) -> 0.40878327
A45: Average inventory turnover | B45: =AVERAGE('Ratio Analysis'!B21:G21) -> 1.1173125 | I45: Other Income CAGR | J45: =(O6/J6)^(1/6)-1 -> 0.20685378 | Q45: Average | R45: =AVERAGE(R44:W44) -> 0.20827591 | Y45: Other non-current Assets | Z45: =('Balance Sheet'!Z17+'Balance Sheet'!Z16+'Balance Sheet'!Z15+'Balance Sheet'!Z14+'Balance Sheet'!Z13+'Balance Sheet'!Z11+'Balance Sheet'!Z8+'Balance Sheet'!Z7)/'Income Statement'!Z9 -> 0.11512549 | AA45: =('Balance Sheet'!AA17+'Balance Sheet'!AA16+'Balance Sheet'!AA15+'Balance Sheet'!AA14+'Balance Sheet'!AA13+'Balance Sheet'!AA11+'Balance Sheet'!AA8+'Balance Sheet'!AA7)/'Income Statement'!AA9 -> 0.16214469 | AB45: =('Balance Sheet'!AB17+'Balance Sheet'!AB16+'Balance Sheet'!AB15+'Balance Sheet'!AB14+'Balance Sheet'!AB13+'Balance Sheet'!AB11+'Balance Sheet'!AB8+'Balance Sheet'!AB7)/'Income Statement'!AB9 -> 0.15042034 | AC45: =('Balance Sheet'!AC17+'Balance Sheet'!AC16+'Balance Sheet'!AC15+'Balance Sheet'!AC14+'Balance Sheet'!AC13+'Balance Sheet'!AC11+'Balance Sheet'!AC8+'Balance Sheet'!AC7)/'Income Statement'!AC9 -> 0.16364499 | AD45: =('Balance Sheet'!AD17+'Balance Sheet'!AD16+'Balance Sheet'!AD15+'Balance Sheet'!AD14+'Balance Sheet'!AD13+'Balance Sheet'!AD11+'Balance Sheet'!AD8+'Balance Sheet'!AD7)/'Income Statement'!AD9 -> 0.13868689 | AE45: =('Balance Sheet'!AE17+'Balance Sheet'!AE16+'Balance Sheet'!AE15+'Balance Sheet'!AE14+'Balance Sheet'!AE13+'Balance Sheet'!AE11+'Balance Sheet'!AE8+'Balance Sheet'!AE7)/'Income Statement'!AE9 -> 0.21310742 | AG45: Average | AH45: =AVERAGE(AH44:AM44) -> 0.19536531 | AO45: Other non-current Assets | AP45: =('Balance Sheet'!AP19+'Balance Sheet'!AP18+'Balance Sheet'!AP17+'Balance Sheet'!AP16+'Balance Sheet'!AP15+'Balance Sheet'!AP13+'Balance Sheet'!AP10+'Balance Sheet'!AP9+'Balance Sheet'!AP9+'Balance Sheet'!AP8+'Balance Sheet'!AP7)/'Income Statement'!AP8 -> 0.29501625 | AQ45: =('Balance Sheet'!AQ19+'Balance Sheet'!AQ18+'Balance Sheet'!AQ17+'Balance Sheet'!AQ16+'Balance Sheet'!AQ15+'Balance Sheet'!AQ13+'Balance Sheet'!AQ10+'Balance Sheet'!AQ9+'Balance Sheet'!AQ9+'Balance Sheet'!AQ8+'Balance Sheet'!AQ7)/'Income Statement'!AQ8 -> 0.27913864 | AR45: =('Balance Sheet'!AR19+'Balance Sheet'!AR18+'Balance Sheet'!AR17+'Balance Sheet'!AR16+'Balance Sheet'!AR15+'Balance Sheet'!AR13+'Balance Sheet'!AR10+'Balance Sheet'!AR9+'Balance Sheet'!AR9+'Balance Sheet'!AR8+'Balance Sheet'!AR7)/'Income Statement'!AR8 -> 0.25328737 | AS45: =('Balance Sheet'!AS19+'Balance Sheet'!AS18+'Balance Sheet'!AS17+'Balance Sheet'!AS16+'Balance Sheet'!AS15+'Balance Sheet'!AS13+'Balance Sheet'!AS10+'Balance Sheet'!AS9+'Balance Sheet'!AS9+'Balance Sheet'!AS8+'Balance Sheet'!AS7)/'Income Statement'!AS8 -> 0.24335549 | AT45: =('Balance Sheet'!AT19+'Balance Sheet'!AT18+'Balance Sheet'!AT17+'Balance Sheet'!AT16+'Balance Sheet'!AT15+'Balance Sheet'!AT13+'Balance Sheet'!AT10+'Balance Sheet'!AT9+'Balance Sheet'!AT9+'Balance Sheet'!AT8+'Balance Sheet'!AT7)/'Income Statement'!AT8 -> 0.25017929 | AU45: =('Balance Sheet'!AU19+'Balance Sheet'!AU18+'Balance Sheet'!AU17+'Balance Sheet'!AU16+'Balance Sheet'!AU15+'Balance Sheet'!AU13+'Balance Sheet'!AU10+'Balance Sheet'!AU9+'Balance Sheet'!AU9+'Balance Sheet'!AU8+'Balance Sheet'!AU7)/'Income Statement'!AU8 -> 0.25275709
A46: Other current assets | B46: =('Balance Sheet'!B26+'Balance Sheet'!B25+'Balance Sheet'!B24+'Balance Sheet'!B22)/'Income Statement'!B7 -> 0.069488991 | C46: =('Balance Sheet'!C26+'Balance Sheet'!C25+'Balance Sheet'!C24+'Balance Sheet'!C22)/'Income Statement'!C7 -> 0.045881945 | D46: =('Balance Sheet'!D26+'Balance Sheet'!D25+'Balance Sheet'!D24+'Balance Sheet'!D22)/'Income Statement'!D7 -> 0.2076595 | E46: =('Balance Sheet'!E26+'Balance Sheet'!E25+'Balance Sheet'!E24+'Balance Sheet'!E22)/'Income Statement'!E7 -> 0.53612042 | F46: =('Balance Sheet'!F26+'Balance Sheet'!F25+'Balance Sheet'!F24+'Balance Sheet'!F22)/'Income Statement'!F7 -> 0.48533724 | G46: =('Balance Sheet'!G26+'Balance Sheet'!G25+'Balance Sheet'!G24+'Balance Sheet'!G22)/'Income Statement'!G7 -> 0.38086903 | I46: R&D Expense ratio (Average) | J46: =AVERAGE('Ratio Analysis'!J25:O25) -> 0.060874742 | Q46: Dividend Payout ratio | R46: =ABS('Cash Flow Statement'!R61)/'Income Statement'!R25 -> 0.34490307 | S46: =ABS('Cash Flow Statement'!S61)/'Income Statement'!S25 -> 0 | T46: =ABS('Cash Flow Statement'!T61)/'Income Statement'!T25 -> 0.00033001663 | U46: =ABS('Cash Flow Statement'!U61)/'Income Statement'!U25 -> 0.00034298565 | V46: =ABS('Cash Flow Statement'!V61)/'Income Statement'!V25 -> 0.0017054911 | W46: =ABS('Cash Flow Statement'!W61)/'Income Statement'!W25 -> 0.0060699994 | Y46: Average | Z46: =AVERAGE(Z45:AE45) -> 0.1571883 | AG46: Dividend Payout ratio | AH46: =ABS('Cash Flow Statement'!AH34)/'Income Statement'!AH25 -> 0.70116715 | AI46: =ABS('Cash Flow Statement'!AI34)/'Income Statement'!AI25 -> 0.27035339 | AJ46: =ABS('Cash Flow Statement'!AJ34)/'Income Statement'!AJ25 -> 0.87095654 | AK46: =ABS('Cash Flow Statement'!AK34)/'Income Statement'!AK25 -> 0.69307678 | AL46: =ABS('Cash Flow Statement'!AL34)/'Income Statement'!AL25 -> 0.61298736 | AM46: =ABS('Cash Flow Statement'!AM34)/'Income Statement'!AM25 -> 0.56666056 | AO46: Average | AP46: =AVERAGE(AP45:AU45) -> 0.26228902
A47: Average | B47: =AVERAGE(B46:G46) -> 0.28755952 | I47: SG&A to Revenue ratio | J47: =(J12+J15)/J7 -> 0.49689784 | K47: =(K12+K15)/K7 -> 0.4759277 | L47: =(L12+L15)/L7 -> 0.45631671 | M47: =(M12+M15)/M7 -> 0.48181792 | N47: =(N12+N15)/N7 -> 0.49842972 | O47: =(O12+O15)/O7 -> 0.49034128 | Q47: Average | R47: =AVERAGE(V46:W46) -> 0.0038877452 | Y47: Dividend Payout ratio | Z47: =ABS('Cash Flow Statement'!Z43)/'Income Statement'!Z26 -> 0.19328727 | AA47: =ABS('Cash Flow Statement'!AA43)/'Income Statement'!AA26 -> 0.21249231 | AB47: =ABS('Cash Flow Statement'!AB43)/'Income Statement'!AB26 -> 0.18996564 | AC47: =ABS('Cash Flow Statement'!AC43)/'Income Statement'!AC26 -> 0.11046525 | AD47: =ABS('Cash Flow Statement'!AD43)/'Income Statement'!AD26 -> 0.11918464 | AE47: =ABS('Cash Flow Statement'!AE43)/'Income Statement'!AE26 -> 0.11636275 | AG47: Average | AH47: =AVERAGE(AK46:AM46) -> 0.62424157 | AO47: Dividend Payout ratio | AP47: =ABS('Cash Flow Statement'!AP52)/'Income Statement'!AP26 -> 0.37629375 | AQ47: =ABS('Cash Flow Statement'!AQ52)/'Income Statement'!AQ26 -> 0 | AR47: =ABS('Cash Flow Statement'!AR52)/'Income Statement'!AR26 -> 0.14781385 | AS47: =ABS('Cash Flow Statement'!AS52)/'Income Statement'!AS26 -> 0.13381709 | AT47: =ABS('Cash Flow Statement'!AT52)/'Income Statement'!AT26 -> 0.15779319 | AU47: =ABS('Cash Flow Statement'!AU52)/'Income Statement'!AU26 -> 0.19923897
A48: Average Payable turnover | B48: =AVERAGE('Ratio Analysis'!B23:G23) -> 3.8282863 | I48: Average | J48: =AVERAGE(J47:O47) -> 0.48328853 | Q48: Average receivables turnover | R48: =AVERAGE('Ratio Analysis'!R22:W22) -> 15.359044 | Y48: Average | Z48: =AVERAGE(Z47:AE47) -> 0.15695964 | AG48: Average receivables turnover | AH48: =AVERAGE('Ratio Analysis'!AH22:AM22) -> 5.937014 | AO48: Average | AP48: =AVERAGE(AR47:AU47) -> 0.15966578
A49: Other non-current Liabilities | B49: =('Balance Sheet'!B39+'Balance Sheet'!B40)/'Income Statement'!B7 -> 0.052735917 | C49: =('Balance Sheet'!C39+'Balance Sheet'!C40)/'Income Statement'!C7 -> 0.051665538 | D49: =('Balance Sheet'!D39+'Balance Sheet'!D40)/'Income Statement'!D7 -> 0.049385587 | E49: =('Balance Sheet'!E39+'Balance Sheet'!E40)/'Income Statement'!E7 -> 0.0699973 | F49: =('Balance Sheet'!F39+'Balance Sheet'!F40)/'Income Statement'!F7 -> 0.075635386 | G49: =('Balance Sheet'!G39+'Balance Sheet'!G40)/'Income Statement'!G7 -> 0.05240939 | I49: Other non-current Assets | J49: =('Balance Sheet'!J18+'Balance Sheet'!J17+'Balance Sheet'!J16+'Balance Sheet'!J15+'Balance Sheet'!J8+'Balance Sheet'!J7)/'Income Statement'!J7 -> 0.43093458 | K49: =('Balance Sheet'!K18+'Balance Sheet'!K17+'Balance Sheet'!K16+'Balance Sheet'!K15+'Balance Sheet'!K8+'Balance Sheet'!K7)/'Income Statement'!K7 -> 0.43531333 | L49: =('Balance Sheet'!L18+'Balance Sheet'!L17+'Balance Sheet'!L16+'Balance Sheet'!L15+'Balance Sheet'!L8+'Balance Sheet'!L7)/'Income Statement'!L7 -> 0.050222104 | M49: =('Balance Sheet'!M18+'Balance Sheet'!M17+'Balance Sheet'!M16+'Balance Sheet'!M15+'Balance Sheet'!M8+'Balance Sheet'!M7)/'Income Statement'!M7 -> 0.052977974 | N49: =('Balance Sheet'!N18+'Balance Sheet'!N17+'Balance Sheet'!N16+'Balance Sheet'!N15+'Balance Sheet'!N8+'Balance Sheet'!N7)/'Income Statement'!N7 -> 0.33414107 | O49: =('Balance Sheet'!O18+'Balance Sheet'!O17+'Balance Sheet'!O16+'Balance Sheet'!O15+'Balance Sheet'!O8+'Balance Sheet'!O7)/'Income Statement'!O7 -> 0.28819467 | Q49: Average inventory turnover | R49: =AVERAGE('Ratio Analysis'!R21:W21) -> 1.8735922 | Y49: Average receivables turnover | Z49: =AVERAGE('Ratio Analysis'!Z22:AE22) -> 5.5555771 | AG49: Average inventory turnover | AH49: =AVERAGE('Ratio Analysis'!AH21:AM21) -> 1.0593943 | AO49: Average receivables turnover | AP49: =AVERAGE('Ratio Analysis'!AP22:AU22) -> 5.6584465
A50: Other current liabilities | B50: =('Balance Sheet'!B48+'Balance Sheet'!B49+Table1[[#This Row],[2020]]+'Balance Sheet'!B51)/'Income Statement'!B7 -> 0.054034258 | C50: =('Balance Sheet'!C48+'Balance Sheet'!C49+Table1[[#This Row],[2021]]+'Balance Sheet'!C51)/'Income Statement'!C7 -> 0.049505401 | D50: =('Balance Sheet'!D48+'Balance Sheet'!D49+Table1[[#This Row],[2022]]+'Balance Sheet'!D51)/'Income Statement'!D7 -> 0.043976548 | E50: =('Balance Sheet'!E48+'Balance Sheet'!E49+Table1[[#This Row],[2023]]+'Balance Sheet'!E51)/'Income Statement'!E7 -> 0.041675655 | F50: =('Balance Sheet'!F48+'Balance Sheet'!F49+Table1[[#This Row],[2024]]+'Balance Sheet'!F51)/'Income Statement'!F7 -> 0.055351906 | G50: =('Balance Sheet'!G48+'Balance Sheet'!G49+Table1[[#This Row],[2025]]+'Balance Sheet'!G51)/'Income Statement'!G7 -> 0.055601318 | I50: Average | J50: =AVERAGE(N49:O49) -> 0.31116787 | Q50: Other current assets | R50: =('Balance Sheet'!R29+'Balance Sheet'!R28+'Balance Sheet'!R26)/'Income Statement'!R7 -> 0.077593178 | S50: =('Balance Sheet'!S29+'Balance Sheet'!S28+'Balance Sheet'!S26)/'Income Statement'!S7 -> 0.14063631 | T50: =('Balance Sheet'!T29+'Balance Sheet'!T28+'Balance Sheet'!T26)/'Income Statement'!T7 -> 0.13503356 | U50: =('Balance Sheet'!U29+'Balance Sheet'!U28+'Balance Sheet'!U26)/'Income Statement'!U7 -> 0.097741543 | V50: =('Balance Sheet'!V29+'Balance Sheet'!V28+'Balance Sheet'!V26)/'Income Statement'!V7 -> 0.14427939 | W50: =('Balance Sheet'!W29+'Balance Sheet'!W28+'Balance Sheet'!W26)/'Income Statement'!W7 -> 0.098191103 | Y50: Average inventory turnover | Z50: =AVERAGE('Ratio Analysis'!Z21:AE21) -> 1.6065241 | AG50: Other current assets | AH50: =('Balance Sheet'!AH27+'Balance Sheet'!AH26+'Balance Sheet'!AH25+'Balance Sheet'!AH24+'Balance Sheet'!AH21)/'Income Statement'!AH7 -> 0.064471547 | AI50: =('Balance Sheet'!AI27+'Balance Sheet'!AI26+'Balance Sheet'!AI25+'Balance Sheet'!AI24+'Balance Sheet'!AI21)/'Income Statement'!AI7 -> 0.092336643 | AJ50: =('Balance Sheet'!AJ27+'Balance Sheet'!AJ26+'Balance Sheet'!AJ25+'Balance Sheet'!AJ24+'Balance Sheet'!AJ21)/'Income Statement'!AJ7 -> 0.077176435 | AK50: =('Balance Sheet'!AK27+'Balance Sheet'!AK26+'Balance Sheet'!AK25+'Balance Sheet'!AK24+'Balance Sheet'!AK21)/'Income Statement'!AK7 -> 0.065360688 | AL50: =('Balance Sheet'!AL27+'Balance Sheet'!AL26+'Balance Sheet'!AL25+'Balance Sheet'!AL24+'Balance Sheet'!AL21)/'Income Statement'!AL7 -> 0.060540064 | AM50: =('Balance Sheet'!AM27+'Balance Sheet'!AM26+'Balance Sheet'!AM25+'Balance Sheet'!AM24+'Balance Sheet'!AM21)/'Income Statement'!AM7 -> 0.055582805 | AO50: Average inventory turnover | AP50: =AVERAGE('Ratio Analysis'!AP21:AU21) -> 1.5998314
A51: Average ONCL | B51: =AVERAGE(B49:G49) -> 0.058638187 | I51: Dividend Payout ratio | J51: =ABS(Table14[[#This Row],[2020]])/'Income Statement'!J30 -> 0.36632554 | K51: =ABS(Table14[[#This Row],[2021]])/'Income Statement'!K30 -> 0.53704086 | L51: =ABS(Table14[[#This Row],[2022]])/'Income Statement'!L30 -> 0.65966945 | M51: =ABS(Table14[[#This Row],[2023]])/'Income Statement'!M30 -> 0.29726279 | N51: =ABS(Table14[[#This Row],[2024]])/'Income Statement'!N30 -> 0.30263732 | O51: =ABS(Table14[[#This Row],[2025]])/'Income Statement'!O30 -> 0.33067589 | Q51: Average | R51: =AVERAGE(R50:W50) -> 0.11557918 | Y51: Other current assets | Z51: =('Balance Sheet'!Z27+'Balance Sheet'!Z26+'Balance Sheet'!Z25+'Balance Sheet'!Z23)/'Income Statement'!Z9 -> 0.071100917 | AA51: =('Balance Sheet'!AA27+'Balance Sheet'!AA26+'Balance Sheet'!AA25+'Balance Sheet'!AA23)/'Income Statement'!AA9 -> 0.077077807 | AB51: =('Balance Sheet'!AB27+'Balance Sheet'!AB26+'Balance Sheet'!AB25+'Balance Sheet'!AB23)/'Income Statement'!AB9 -> 0.098435741 | AC51: =('Balance Sheet'!AC27+'Balance Sheet'!AC26+'Balance Sheet'!AC25+'Balance Sheet'!AC23)/'Income Statement'!AC9 -> 0.09776406 | AD51: =('Balance Sheet'!AD27+'Balance Sheet'!AD26+'Balance Sheet'!AD25+'Balance Sheet'!AD23)/'Income Statement'!AD9 -> 0.18351588 | AE51: =('Balance Sheet'!AE27+'Balance Sheet'!AE26+'Balance Sheet'!AE25+'Balance Sheet'!AE23)/'Income Statement'!AE9 -> 0.1206685 | AG51: Average | AH51: =AVERAGE(AH50:AM50) -> 0.069244697 | AO51: Other current assets | AP51: =('Balance Sheet'!AP29+'Balance Sheet'!AP28+'Balance Sheet'!AP27+'Balance Sheet'!AP26+'Balance Sheet'!AP23)/'Income Statement'!AP8 -> 0.15406962 | AQ51: =('Balance Sheet'!AQ29+'Balance Sheet'!AQ28+'Balance Sheet'!AQ27+'Balance Sheet'!AQ26+'Balance Sheet'!AQ23)/'Income Statement'!AQ8 -> 0.21996151 | AR51: =('Balance Sheet'!AR29+'Balance Sheet'!AR28+'Balance Sheet'!AR27+'Balance Sheet'!AR26+'Balance Sheet'!AR23)/'Income Statement'!AR8 -> 0.23853885 | AS51: =('Balance Sheet'!AS29+'Balance Sheet'!AS28+'Balance Sheet'!AS27+'Balance Sheet'!AS26+'Balance Sheet'!AS23)/'Income Statement'!AS8 -> 0.29980322 | AT51: =('Balance Sheet'!AT29+'Balance Sheet'!AT28+'Balance Sheet'!AT27+'Balance Sheet'!AT26+'Balance Sheet'!AT23)/'Income Statement'!AT8 -> 0.32969655 | AU51: =('Balance Sheet'!AU29+'Balance Sheet'!AU28+'Balance Sheet'!AU27+'Balance Sheet'!AU26+'Balance Sheet'!AU23)/'Income Statement'!AU8 -> 0.40520967
A52: Average OCL | B52: =AVERAGE(B50:G50) -> 0.050024181 | I52: Average | J52: =AVERAGE(M51:O51) -> 0.310192 | Q52: Average Payables turnover | R52: =AVERAGE('Ratio Analysis'!R23:W23) -> 2.9753317 | Y52: Average | Z52: =AVERAGE(Z51:AE51) -> 0.10809382 | AG52: Average Payables turnover | AH52: =AVERAGE('Ratio Analysis'!AH23:AM23) -> 1.3139041 | AO52: Average | AP52: =AVERAGE(AS51:AU51) -> 0.34490314
A53: Working Capital | B53: 3753 | C53: 5062.25 | D53: 7155.95 | E53: 8210.66 | F53: 8397 | G53: 8629 | I53: Average receivables turnover | J53: =AVERAGE('Ratio Analysis'!J22:O22) -> 5.1606263 | Q53: Other non-current liabilities | R53: =('Balance Sheet'!R45+'Balance Sheet'!R44+'Balance Sheet'!R43)/'Income Statement'!R7 -> 0.014886859 | S53: =('Balance Sheet'!S45+'Balance Sheet'!S44+'Balance Sheet'!S43)/'Income Statement'!S7 -> 0.014590063 | T53: =('Balance Sheet'!T45+'Balance Sheet'!T44+'Balance Sheet'!T43)/'Income Statement'!T7 -> 0.019527101 | U53: =('Balance Sheet'!U45+'Balance Sheet'!U44+'Balance Sheet'!U43)/'Income Statement'!U7 -> 0.022605937 | V53: =('Balance Sheet'!V45+'Balance Sheet'!V44+'Balance Sheet'!V43)/'Income Statement'!V7 -> 0.02230885 | W53: =('Balance Sheet'!W45+'Balance Sheet'!W44+'Balance Sheet'!W43)/'Income Statement'!W7 -> 0.15595842 | Y53: Average Payables turnover | Z53: =AVERAGE('Ratio Analysis'!Z23:AE23) -> 3.9404084 | AG53: Other non-current liabilities | AH53: =('Balance Sheet'!AH43+'Balance Sheet'!AH42+'Balance Sheet'!AH41+'Balance Sheet'!AH40+'Balance Sheet'!AH39)/'Income Statement'!AH7 -> 0.056712829 | AI53: =('Balance Sheet'!AI43+'Balance Sheet'!AI42+'Balance Sheet'!AI41+'Balance Sheet'!AI40+'Balance Sheet'!AI39)/'Income Statement'!AI7 -> 0.050212864 | AJ53: =('Balance Sheet'!AJ43+'Balance Sheet'!AJ42+'Balance Sheet'!AJ41+'Balance Sheet'!AJ40+'Balance Sheet'!AJ39)/'Income Statement'!AJ7 -> 0.069914758 | AK53: =('Balance Sheet'!AK43+'Balance Sheet'!AK42+'Balance Sheet'!AK41+'Balance Sheet'!AK40+'Balance Sheet'!AK39)/'Income Statement'!AK7 -> 0.090039719 | AL53: =('Balance Sheet'!AL43+'Balance Sheet'!AL42+'Balance Sheet'!AL41+'Balance Sheet'!AL40+'Balance Sheet'!AL39)/'Income Statement'!AL7 -> 0.10897712 | AM53: =('Balance Sheet'!AM43+'Balance Sheet'!AM42+'Balance Sheet'!AM41+'Balance Sheet'!AM40+'Balance Sheet'!AM39)/'Income Statement'!AM7 -> 0.12913281 | AO53: Average Payables turnover | AP53: =AVERAGE('Ratio Analysis'!AP23:AU23) -> 3.3307284
I54: Average inventory turnover | J54: =AVERAGE('Ratio Analysis'!J21:O21) -> 1.2051869 | Q54: Average | R54: =AVERAGE(R53:W53) -> 0.041646205 | Y54: Other non-current liabilities | Z54: =('Balance Sheet'!Z43+'Balance Sheet'!Z42+'Balance Sheet'!Z41+'Balance Sheet'!Z40)/'Income Statement'!Z9 -> 0.018442352 | AA54: =('Balance Sheet'!AA43+'Balance Sheet'!AA42+'Balance Sheet'!AA41+'Balance Sheet'!AA40)/'Income Statement'!AA9 -> 0.014582008 | AB54: =('Balance Sheet'!AB43+'Balance Sheet'!AB42+'Balance Sheet'!AB41+'Balance Sheet'!AB40)/'Income Statement'!AB9 -> 0.010957984 | AC54: =('Balance Sheet'!AC43+'Balance Sheet'!AC42+'Balance Sheet'!AC41+'Balance Sheet'!AC40)/'Income Statement'!AC9 -> 0.0075451308 | AD54: =('Balance Sheet'!AD43+'Balance Sheet'!AD42+'Balance Sheet'!AD41+'Balance Sheet'!AD40)/'Income Statement'!AD9 -> 0.014599348 | AE54: =('Balance Sheet'!AE43+'Balance Sheet'!AE42+'Balance Sheet'!AE41+'Balance Sheet'!AE40)/'Income Statement'!AE9 -> 0.049761123 | AG54: Average | AH54: =AVERAGE(AH53:AM53) -> 0.084165017 | AO54: Other non-current liabilities | AP54: =('Balance Sheet'!AP47+'Balance Sheet'!AP46+'Balance Sheet'!AP45+'Balance Sheet'!AP44+'Balance Sheet'!AP43)/'Income Statement'!AP8 -> 0.048229048 | AQ54: =('Balance Sheet'!AQ47+'Balance Sheet'!AQ46+'Balance Sheet'!AQ45+'Balance Sheet'!AQ44+'Balance Sheet'!AQ43)/'Income Statement'!AQ8 -> 0.039741413 | AR54: =('Balance Sheet'!AR47+'Balance Sheet'!AR46+'Balance Sheet'!AR45+'Balance Sheet'!AR44+'Balance Sheet'!AR43)/'Income Statement'!AR8 -> 0.029680756 | AS54: =('Balance Sheet'!AS47+'Balance Sheet'!AS46+'Balance Sheet'!AS45+'Balance Sheet'!AS44+'Balance Sheet'!AS43)/'Income Statement'!AS8 -> 0.027555291 | AT54: =('Balance Sheet'!AT47+'Balance Sheet'!AT46+'Balance Sheet'!AT45+'Balance Sheet'!AT44+'Balance Sheet'!AT43)/'Income Statement'!AT8 -> 0.025252765 | AU54: =('Balance Sheet'!AU47+'Balance Sheet'!AU46+'Balance Sheet'!AU45+'Balance Sheet'!AU44+'Balance Sheet'!AU43)/'Income Statement'!AU8 -> 0.021184822
I55: Other current assets | J55: =('Balance Sheet'!J28+'Balance Sheet'!J27+'Balance Sheet'!J26+'Balance Sheet'!J25)/'Income Statement'!J7 -> 0.11304352 | K55: =('Balance Sheet'!K28+'Balance Sheet'!K27+'Balance Sheet'!K26+'Balance Sheet'!K25)/'Income Statement'!K7 -> 0.086811892 | L55: =('Balance Sheet'!L28+'Balance Sheet'!L27+'Balance Sheet'!L26+'Balance Sheet'!L25)/'Income Statement'!L7 -> 0.036984031 | M55: =('Balance Sheet'!M28+'Balance Sheet'!M27+'Balance Sheet'!M26+'Balance Sheet'!M25)/'Income Statement'!M7 -> 0.10647751 | N55: =('Balance Sheet'!N28+'Balance Sheet'!N27+'Balance Sheet'!N26+'Balance Sheet'!N25)/'Income Statement'!N7 -> 0.089170858 | O55: =('Balance Sheet'!O28+'Balance Sheet'!O27+'Balance Sheet'!O26+'Balance Sheet'!O25)/'Income Statement'!O7 -> 0.09863232 | Q55: Other current liabilities | R55: =('Balance Sheet'!R56+Table3[[#This Row],[2020]]+'Balance Sheet'!R54+'Balance Sheet'!R53)/'Income Statement'!R7 -> 0.077203179 | S55: =('Balance Sheet'!S56+Table3[[#This Row],[2021]]+'Balance Sheet'!S54+'Balance Sheet'!S53)/'Income Statement'!S7 -> 0.082700963 | T55: =('Balance Sheet'!T56+Table3[[#This Row],[2022]]+'Balance Sheet'!T54+'Balance Sheet'!T53)/'Income Statement'!T7 -> 0.091027113 | U55: =('Balance Sheet'!U56+Table3[[#This Row],[2023]]+'Balance Sheet'!U54+'Balance Sheet'!U53)/'Income Statement'!U7 -> 0.080301072 | V55: =('Balance Sheet'!V56+Table3[[#This Row],[2024]]+'Balance Sheet'!V54+'Balance Sheet'!V53)/'Income Statement'!V7 -> 0.11081659 | W55: =('Balance Sheet'!W56+Table3[[#This Row],[2025]]+'Balance Sheet'!W54+'Balance Sheet'!W53)/'Income Statement'!W7 -> 0.12232438 | Y55: Average | Z55: =AVERAGE(Z54:AE54) -> 0.019314658 | AG55: Other current liabilities | AH55: =('Balance Sheet'!AH54+'Balance Sheet'!AH53+'Balance Sheet'!AH52+'Balance Sheet'!AH51+'Balance Sheet'!AH50)/'Income Statement'!AH7 -> 0.28713708 | AI55: =('Balance Sheet'!AI54+'Balance Sheet'!AI53+'Balance Sheet'!AI52+'Balance Sheet'!AI51+'Balance Sheet'!AI50)/'Income Statement'!AI7 -> 0.26302987 | AJ55: =('Balance Sheet'!AJ54+'Balance Sheet'!AJ53+'Balance Sheet'!AJ52+'Balance Sheet'!AJ51+'Balance Sheet'!AJ50)/'Income Statement'!AJ7 -> 0.097163569 | AK55: =('Balance Sheet'!AK54+'Balance Sheet'!AK53+'Balance Sheet'!AK52+'Balance Sheet'!AK51+'Balance Sheet'!AK50)/'Income Statement'!AK7 -> 0.10009219 | AL55: =('Balance Sheet'!AL54+'Balance Sheet'!AL53+'Balance Sheet'!AL52+'Balance Sheet'!AL51+'Balance Sheet'!AL50)/'Income Statement'!AL7 -> 0.092927242 | AM55: =('Balance Sheet'!AM54+'Balance Sheet'!AM53+'Balance Sheet'!AM52+'Balance Sheet'!AM51+'Balance Sheet'!AM50)/'Income Statement'!AM7 -> 0.092104761 | AO55: Average | AP55: =AVERAGE(AR54:AU54) -> 0.025918409
I56: Average | J56: =AVERAGE(M55:O55) -> 0.098093562 | Q56: Average | R56: =AVERAGE(R55:W55) -> 0.094062216 | Y56: Other current liabilities | Z56: =('Balance Sheet'!Z55+'Balance Sheet'!Z54+'Balance Sheet'!Z53+'Balance Sheet'!Z52+'Balance Sheet'!Z51)/'Income Statement'!Z9 -> 0.18291836 | AA56: =('Balance Sheet'!AA55+'Balance Sheet'!AA54+'Balance Sheet'!AA53+'Balance Sheet'!AA52+'Balance Sheet'!AA51)/'Income Statement'!AA9 -> 0.2087037 | AB56: =('Balance Sheet'!AB55+'Balance Sheet'!AB54+'Balance Sheet'!AB53+'Balance Sheet'!AB52+'Balance Sheet'!AB51)/'Income Statement'!AB9 -> 0.17667139 | AC56: =('Balance Sheet'!AC55+'Balance Sheet'!AC54+'Balance Sheet'!AC53+'Balance Sheet'!AC52+'Balance Sheet'!AC51)/'Income Statement'!AC9 -> 0.18229985 | AD56: =('Balance Sheet'!AD55+'Balance Sheet'!AD54+'Balance Sheet'!AD53+'Balance Sheet'!AD52+'Balance Sheet'!AD51)/'Income Statement'!AD9 -> 0.19271832 | AE56: =('Balance Sheet'!AE55+'Balance Sheet'!AE54+'Balance Sheet'!AE53+'Balance Sheet'!AE52+'Balance Sheet'!AE51)/'Income Statement'!AE9 -> 0.19251835 | AG56: Average | AH56: =AVERAGE(AK55:AM55) -> 0.095041396 | AO56: Other current liabilities | AP56: =('Balance Sheet'!AP58+'Balance Sheet'!AP57+Table6[[#This Row],[2020]]+'Balance Sheet'!AP55+'Balance Sheet'!AP54)/'Income Statement'!AP8 -> 0.095225561 | AQ56: =('Balance Sheet'!AQ58+'Balance Sheet'!AQ57+Table6[[#This Row],[2021]]+'Balance Sheet'!AQ55+'Balance Sheet'!AQ54)/'Income Statement'!AQ8 -> 0.11271684 | AR56: =('Balance Sheet'!AR58+'Balance Sheet'!AR57+Table6[[#This Row],[2022]]+'Balance Sheet'!AR55+'Balance Sheet'!AR54)/'Income Statement'!AR8 -> 0.09058462 | AS56: =('Balance Sheet'!AS58+'Balance Sheet'!AS57+Table6[[#This Row],[2023]]+'Balance Sheet'!AS55+'Balance Sheet'!AS54)/'Income Statement'!AS8 -> 0.088505663 | AT56: =('Balance Sheet'!AT58+'Balance Sheet'!AT57+Table6[[#This Row],[2024]]+'Balance Sheet'!AT55+'Balance Sheet'!AT54)/'Income Statement'!AT8 -> 0.095200119 | AU56: =('Balance Sheet'!AU58+'Balance Sheet'!AU57+Table6[[#This Row],[2025]]+'Balance Sheet'!AU55+'Balance Sheet'!AU54)/'Income Statement'!AU8 -> 0.090334251
A57: Forecast | B57: 2026 | C57: 2027 | D57: 2028 | E57: 2029 | F57: 2030 | I57: Average Payables turnover | J57: =AVERAGE('Ratio Analysis'!J23:O23) -> 2.6452876 | Q57: Working Capital | R57: ='Balance Sheet'!R31-Table3[[#This Row],[2020]] -> 1571.4829 | S57: ='Balance Sheet'!S31-Table3[[#This Row],[2021]] -> 2552.9944 | T57: ='Balance Sheet'!T31-Table3[[#This Row],[2022]] -> 1785.4114 | U57: ='Balance Sheet'!U31-Table3[[#This Row],[2023]] -> 2467.2923 | V57: ='Balance Sheet'!V31-Table3[[#This Row],[2024]] -> 4451.91 | W57: ='Balance Sheet'!W31-Table3[[#This Row],[2025]] -> 1339.1 | Y57: Average | Z57: =AVERAGE(Z56:AE56) -> 0.18930499 | AG57: Working Capital | AH57: ='Balance Sheet'!AH28-'Balance Sheet'!AH55 -> -475.1 | AI57: ='Balance Sheet'!AI28-'Balance Sheet'!AI55 -> 629.88 | AJ57: ='Balance Sheet'!AJ28-'Balance Sheet'!AJ55 -> 749.9 | AK57: ='Balance Sheet'!AK28-'Balance Sheet'!AK55 -> -133.58 | AL57: ='Balance Sheet'!AL28-'Balance Sheet'!AL55 -> 186.23 | AM57: ='Balance Sheet'!AM28-'Balance Sheet'!AM55 -> 905.38 | AO57: Average | AP57: =AVERAGE(AP56:AU56) -> 0.095427843
A58: CapEx | B58: ='Income Statement Forecast'!B7*'Income Statement'!$B$28 -> 1329.8073 | C58: ='Income Statement Forecast'!C7*'Income Statement'!$B$28 -> 1458.8885 | D58: ='Income Statement Forecast'!D7*'Income Statement'!$B$28 -> 1600.5061 | E58: ='Income Statement Forecast'!E7*'Income Statement'!$B$28 -> 1755.8782 | F58: ='Income Statement Forecast'!F7*'Income Statement'!$B$28 -> 1926.3417 | I58: Other non-current liabilities | J58: =('Balance Sheet'!J44+'Balance Sheet'!J43+'Balance Sheet'!J40)/'Income Statement'!J7 -> 0.02633189 | K58: =('Balance Sheet'!K44+'Balance Sheet'!K43+'Balance Sheet'!K40)/'Income Statement'!K7 -> 0.023767347 | L58: =('Balance Sheet'!L44+'Balance Sheet'!L43+'Balance Sheet'!L40)/'Income Statement'!L7 -> 0.015634475 | M58: =('Balance Sheet'!M44+'Balance Sheet'!M43+'Balance Sheet'!M40)/'Income Statement'!M7 -> 0.020185669 | N58: =('Balance Sheet'!N44+'Balance Sheet'!N43+'Balance Sheet'!N40)/'Income Statement'!N7 -> 0.019540014 | O58: =('Balance Sheet'!O44+'Balance Sheet'!O43+'Balance Sheet'!O40)/'Income Statement'!O7 -> 0.017273925 | Q58: WC to revenue ratio | R58: =R57/R7 -> 0.26298095 | S58: =S57/S7 -> 0.39981869 | T58: =T57/T7 -> 0.2238035 | U58: =U57/U7 -> 0.27791083 | V58: =V57/V7 -> 0.42235591 | W58: =W57/W7 -> 0.105075 | Y58: Working Capital | Z58: ='Balance Sheet'!Z28-'Balance Sheet'!Z56 -> 5412.8 | AA58: ='Balance Sheet'!AA28-'Balance Sheet'!AA56 -> 5385 | AB58: ='Balance Sheet'!AB28-'Balance Sheet'!AB56 -> 6517.8 | AC58: ='Balance Sheet'!AC28-'Balance Sheet'!AC56 -> 8118.2 | AD58: ='Balance Sheet'!AD28-'Balance Sheet'!AD56 -> 15348 | AE58: ='Balance Sheet'!AE28-'Balance Sheet'!AE56 -> 12070 | AG58: Long term borrowings Interest expense | AH58: ='Balance Sheet'!AH38/('Balance Sheet'!AH38+'Balance Sheet'!AH46)*'Income Statement'!AH13 -> 338.10141 | AI58: ='Balance Sheet'!AI38/('Balance Sheet'!AI38+'Balance Sheet'!AI46)*'Income Statement'!AI13 -> 289.05095 | AJ58: ='Balance Sheet'!AJ38/('Balance Sheet'!AJ38+'Balance Sheet'!AJ46)*'Income Statement'!AJ13 -> 134.77726 | AK58: ='Balance Sheet'!AK38/('Balance Sheet'!AK38+'Balance Sheet'!AK46)*'Income Statement'!AK13 -> 157.12525 | AL58: ='Balance Sheet'!AL38/('Balance Sheet'!AL38+'Balance Sheet'!AL46)*'Income Statement'!AL13 -> 144.01117 | AM58: ='Balance Sheet'!AM38/('Balance Sheet'!AM38+'Balance Sheet'!AM46)*'Income Statement'!AM13 -> 99.365995 | AO58: Working Capital | AP58: ='Balance Sheet'!AP30-'Balance Sheet'!AP59 -> 7310.7 | AQ58: ='Balance Sheet'!AQ30-'Balance Sheet'!AQ59 -> 8589.89 | AR58: ='Balance Sheet'!AR30-'Balance Sheet'!AR59 -> 9797.96 | AS58: ='Balance Sheet'!AS30-'Balance Sheet'!AS59 -> 11771.79 | AT58: ='Balance Sheet'!AT30-'Balance Sheet'!AT59 -> 14146.68 | AU58: ='Balance Sheet'!AU30-'Balance Sheet'!AU59 -> 17765.01
A59: Depreciation and Amortisation | B59: ='Balance Sheet'!G6*'Income Statement'!B30 -> 394.31253 | C59: ='Balance Sheet Forecast'!B6*'Income Statement'!B30 -> 462.15828 | D59: ='Balance Sheet Forecast'!C6*'Income Statement'!B30 -> 534.44506 | E59: ='Balance Sheet Forecast'!D6*'Income Statement'!B30 -> 611.75998 | F59: ='Balance Sheet Forecast'!E6*'Income Statement'!B30 -> 694.73591 | I59: Average | J59: =AVERAGE(J58:O58) -> 0.020455553 | Q59: Average | R59: =AVERAGE(W58) -> 0.105075 | Y59: STD to Revenue | Z59: ='Balance Sheet'!Z46/'Income Statement'!Z9 -> 0.066850079 | AA59: ='Balance Sheet'!AA46/'Income Statement'!AA9 -> 0.085485731 | AB59: ='Balance Sheet'!AB46/'Income Statement'!AB9 -> 0.10506319 | AC59: ='Balance Sheet'!AC46/'Income Statement'!AC9 -> 0.10527421 | AD59: ='Balance Sheet'!AD46/'Income Statement'!AD9 -> 0.044015997 | AE59: ='Balance Sheet'!AE46/'Income Statement'!AE9 -> 0.11275533 | AG59: Short term Borrowings Interest expense | AH59: ='Balance Sheet'!AH46/('Balance Sheet'!AH46+'Balance Sheet'!AH38)*'Income Statement'!AH13 -> 112.60859 | AI59: ='Balance Sheet'!AI46/('Balance Sheet'!AI46+'Balance Sheet'!AI38)*'Income Statement'!AI13 -> 69.229052 | AJ59: ='Balance Sheet'!AJ46/('Balance Sheet'!AJ46+'Balance Sheet'!AJ38)*'Income Statement'!AJ13 -> 120.28274 | AK59: ='Balance Sheet'!AK46/('Balance Sheet'!AK46+'Balance Sheet'!AK38)*'Income Statement'!AK13 -> 176.31475 | AL59: ='Balance Sheet'!AL46/('Balance Sheet'!AL46+'Balance Sheet'!AL38)*'Income Statement'!AL13 -> 209.54883 | AM59: ='Balance Sheet'!AM46/('Balance Sheet'!AM46+'Balance Sheet'!AM38)*'Income Statement'!AM13 -> 152.94401 | AO59: Long term borrowings Interest expense | AP59: ='Balance Sheet'!AP42/('Balance Sheet'!AP42+'Balance Sheet'!AP50)*'Income Statement'!AP14 -> 166.02618 | AQ59: ='Balance Sheet'!AQ42/('Balance Sheet'!AQ42+'Balance Sheet'!AQ50)*'Income Statement'!AQ14 -> 125.71346 | AR59: ='Balance Sheet'!AR42/('Balance Sheet'!AR42+'Balance Sheet'!AR50)*'Income Statement'!AR14 -> 53.713112 | AS59: ='Balance Sheet'!AS42/('Balance Sheet'!AS42+'Balance Sheet'!AS50)*'Income Statement'!AS14 -> 0 | AT59: ='Balance Sheet'!AT42/('Balance Sheet'!AT42+'Balance Sheet'!AT50)*'Income Statement'!AT14 -> 0 | AU59: ='Balance Sheet'!AU42/('Balance Sheet'!AU42+'Balance Sheet'!AU50)*'Income Statement'!AU14 -> 8.066013
A60: COGS | B60: ='Income Statement Forecast'!B7*'Income Statement'!$B$33 -> 3866.6208 | C60: ='Income Statement Forecast'!C7*'Income Statement'!$B$33 -> 4241.9445 | D60: ='Income Statement Forecast'!D7*'Income Statement'!$B$33 -> 4653.7195 | E60: ='Income Statement Forecast'!E7*'Income Statement'!$B$33 -> 5105.4882 | F60: ='Income Statement Forecast'!F7*'Income Statement'!$B$33 -> 5601.1371 | I60: Other current liabilities | J60: =('Balance Sheet'!J53+'Balance Sheet'!J50+'Balance Sheet'!J51+'Balance Sheet'!J49)/'Income Statement'!J7 -> 0.19637665 | K60: =('Balance Sheet'!K53+'Balance Sheet'!K50+'Balance Sheet'!K51+'Balance Sheet'!K49)/'Income Statement'!K7 -> 0.28331002 | L60: =('Balance Sheet'!L53+'Balance Sheet'!L50+'Balance Sheet'!L51+'Balance Sheet'!L49)/'Income Statement'!L7 -> 0.18639251 | M60: =('Balance Sheet'!M53+'Balance Sheet'!M50+'Balance Sheet'!M51+'Balance Sheet'!M49)/'Income Statement'!M7 -> 0.11720298 | N60: =('Balance Sheet'!N53+'Balance Sheet'!N50+'Balance Sheet'!N51+'Balance Sheet'!N49)/'Income Statement'!N7 -> 0.16772067 | O60: =('Balance Sheet'!O53+'Balance Sheet'!O50+'Balance Sheet'!O51+'Balance Sheet'!O49)/'Income Statement'!O7 -> 0.18344887 | Q60: Average Finance cost LTD | R60: ='Balance Sheet'!R41/('Balance Sheet'!R41+'Balance Sheet'!R48)*'Income Statement'!R13 -> 12.477429 | S60: ='Balance Sheet'!S41/('Balance Sheet'!S41+'Balance Sheet'!S48)*'Income Statement'!S13 -> 5.3552511 | T60: ='Balance Sheet'!T41/('Balance Sheet'!T41+'Balance Sheet'!T48)*'Income Statement'!T13 -> 3.3216471 | U60: ='Balance Sheet'!U41/('Balance Sheet'!U41+'Balance Sheet'!U48)*'Income Statement'!U13 -> 6.328852 | V60: ='Balance Sheet'!V41/('Balance Sheet'!V41+'Balance Sheet'!V48)*'Income Statement'!V13 -> 4.1547261 | W60: ='Balance Sheet'!W41/('Balance Sheet'!W41+'Balance Sheet'!W48)*'Income Statement'!W13 -> 279.7351 | Y60: Average | Z60: =AVERAGE(AE59) -> 0.11275533 | AG60: Average LTB interest rate | AH60: =AVERAGE(AH58:AM58)/AVERAGE('Balance Sheet'!AH38:AM38) -> 0.085276932 | AO60: Short term Borrowings Interest expense | AP60: ='Balance Sheet'!AP50/('Balance Sheet'!AP50+'Balance Sheet'!AP42)*'Income Statement'!AP14 -> 31.333825 | AQ60: ='Balance Sheet'!AQ50/('Balance Sheet'!AQ50+'Balance Sheet'!AQ42)*'Income Statement'!AQ14 -> 34.986544 | AR60: ='Balance Sheet'!AR50/('Balance Sheet'!AR50+'Balance Sheet'!AR42)*'Income Statement'!AR14 -> 52.636888 | AS60: ='Balance Sheet'!AS50/('Balance Sheet'!AS50+'Balance Sheet'!AS42)*'Income Statement'!AS14 -> 109.54 | AT60: ='Balance Sheet'!AT50/('Balance Sheet'!AT50+'Balance Sheet'!AT42)*'Income Statement'!AT14 -> 89.88 | AU60: ='Balance Sheet'!AU50/('Balance Sheet'!AU50+'Balance Sheet'!AU42)*'Income Statement'!AU14 -> 53.943987
A61: Other income | B61: =G6*(1+B34) -> 390.22516 | C61: =B61*(1+$B$34) -> 432.60135 | D61: =C61*(1+$B$34) -> 479.57935 | E61: =D61*(1+$B$34) -> 531.65888 | F61: =E61*(1+$B$34) -> 589.39396 | I61: Average | J61: =AVERAGE(L60:O60) -> 0.16369126 | Q61: Average Finance cost STD | R61: ='Balance Sheet'!R48/('Balance Sheet'!R41+'Balance Sheet'!R48)*'Income Statement'!R13 -> 9.4943707 | S61: ='Balance Sheet'!S48/('Balance Sheet'!S41+'Balance Sheet'!S48)*'Income Statement'!S13 -> 14.792149 | T61: ='Balance Sheet'!T48/('Balance Sheet'!T41+'Balance Sheet'!T48)*'Income Statement'!T13 -> 55.288753 | U61: ='Balance Sheet'!U48/('Balance Sheet'!U41+'Balance Sheet'!U48)*'Income Statement'!U13 -> 38.140148 | V61: ='Balance Sheet'!V48/('Balance Sheet'!V41+'Balance Sheet'!V48)*'Income Statement'!V13 -> 28.595274 | W61: ='Balance Sheet'!W48/('Balance Sheet'!W41+'Balance Sheet'!W48)*'Income Statement'!W13 -> 149.6749 | Y61: Average Finance cost STD | Z61: ='Balance Sheet'!Z46/('Balance Sheet'!Z46+'Balance Sheet'!Z38)*'Income Statement'!Z17 -> 34.927106 | AA61: ='Balance Sheet'!AA46/('Balance Sheet'!AA46+'Balance Sheet'!AA38)*'Income Statement'!AA17 -> 89.908275 | AB61: ='Balance Sheet'!AB46/('Balance Sheet'!AB46+'Balance Sheet'!AB38)*'Income Statement'!AB17 -> 82.289516 | AC61: ='Balance Sheet'!AC46/('Balance Sheet'!AC46+'Balance Sheet'!AC38)*'Income Statement'!AC17 -> 125.2286 | AD61: ='Balance Sheet'!AD46/('Balance Sheet'!AD46+'Balance Sheet'!AD38)*'Income Statement'!AD17 -> 131.75 | AE61: ='Balance Sheet'!AE46/('Balance Sheet'!AE46+'Balance Sheet'!AE38)*'Income Statement'!AE17 -> 257.20948 | AG61: Average STB Interest rate | AH61: =AVERAGE(AH59:AM59)/AVERAGE('Balance Sheet'!AH46:AM46) -> 0.078892296 | AO61: Average LTB interest rate | AP61: =AVERAGE(AU59)/'Balance Sheet'!AU42 -> 0.6732899
A62: Other non-current assets | B62: ='Income Statement Forecast'!B7*'Income Statement'!$B$41 -> 288.45634 | C62: ='Income Statement Forecast'!C7*'Income Statement'!$B$41 -> 316.45611 | D62: ='Income Statement Forecast'!D7*'Income Statement'!$B$41 -> 347.17521 | E62: ='Income Statement Forecast'!E7*'Income Statement'!$B$41 -> 380.8779 | F62: ='Income Statement Forecast'!F7*'Income Statement'!$B$41 -> 417.85414 | I62: Working Capital | J62: ='Balance Sheet'!J29-'Balance Sheet'!J54 -> 15947.73 | K62: ='Balance Sheet'!K29-'Balance Sheet'!K54 -> 14296.45 | L62: ='Balance Sheet'!L29-'Balance Sheet'!L54 -> -380.68 | M62: ='Balance Sheet'!M29-'Balance Sheet'!M54 -> 8099.09 | N62: ='Balance Sheet'!N29-'Balance Sheet'!N54 -> 26448.71 | O62: ='Balance Sheet'!O29-'Balance Sheet'!O54 -> 34399.85 | Q62: Interest rate LTD | R62: =R60/'Balance Sheet'!R41 -> 0.21441571 | S62: =S60/'Balance Sheet'!S41 -> 0.093264724 | T62: =T60/'Balance Sheet'!T41 -> 0.067521386 | U62: =U60/'Balance Sheet'!U41 -> 0.27342588 | V62: =V60/'Balance Sheet'!V41 -> 0.16705774 | W62: =W60/'Balance Sheet'!W41 -> 0.050619885 | Y62: Average Finance cost LTD | Z62: ='Balance Sheet'!Z38/('Balance Sheet'!Z38+'Balance Sheet'!Z46)*'Income Statement'!Z17 -> 63.372894 | AA62: ='Balance Sheet'!AA38/('Balance Sheet'!AA38+'Balance Sheet'!AA46)*'Income Statement'!AA17 -> 7.0917246 | AB62: ='Balance Sheet'!AB38/('Balance Sheet'!AB38+'Balance Sheet'!AB46)*'Income Statement'!AB17 -> 13.510484 | AC62: ='Balance Sheet'!AC38/('Balance Sheet'!AC38+'Balance Sheet'!AC46)*'Income Statement'!AC17 -> 17.571401 | AD62: ='Balance Sheet'!AD38/('Balance Sheet'!AD38+'Balance Sheet'!AD46)*'Income Statement'!AD17 -> 39.349997 | AE62: ='Balance Sheet'!AE38/('Balance Sheet'!AE38+'Balance Sheet'!AE46)*'Income Statement'!AE17 -> 25.690525 | AG62: LT Borrowings to Revenue ratio | AH62: ='Balance Sheet'!AH38/'Income Statement'!AH7 -> 0.40632409 | AI62: ='Balance Sheet'!AI38/'Income Statement'!AI7 -> 0.36483003 | AJ62: ='Balance Sheet'!AJ38/'Income Statement'!AJ7 -> 0.24391931 | AK62: ='Balance Sheet'!AK38/'Income Statement'!AK7 -> 0.25826644 | AL62: ='Balance Sheet'!AL38/'Income Statement'!AL7 -> 0.14869434 | AM62: ='Balance Sheet'!AM38/'Income Statement'!AM7 -> 0.10327696 | AO62: Average STB Interest rate | AP62: =AVERAGE(AR60:AU60)/AVERAGE('Balance Sheet'!AR50:AU50) -> 0.24374771
A63: SG&A | B63: ='Income Statement Forecast'!B7*'Income Statement'!$B$39 -> 2875.448 | C63: ='Income Statement Forecast'!C7*'Income Statement'!$B$39 -> 3154.5609 | D63: ='Income Statement Forecast'!D7*'Income Statement'!$B$39 -> 3460.7812 | E63: ='Income Statement Forecast'!E7*'Income Statement'!$B$39 -> 3796.7431 | F63: ='Income Statement Forecast'!F7*'Income Statement'!$B$39 -> 4165.3369 | I63: WC to revenue ratio | J63: =J62/J7 -> 0.4764288 | K63: =K62/K7 -> 0.41639749 | L63: =L62/L7 -> -0.009618961 | M63: =M62/M7 -> 0.18191944 | N63: =N62/N7 -> 0.53055483 | O63: =O62/O7 -> 0.63068675 | Q63: Interest rate STD | R63: =R61/'Balance Sheet'!R48 -> 0.21441571 | S63: =S61/'Balance Sheet'!S48 -> 0.093264724 | T63: =T61/'Balance Sheet'!T48 -> 0.067521386 | U63: =U61/'Balance Sheet'!U48 -> 0.27342588 | V63: =V61/'Balance Sheet'!V48 -> 0.16705774 | W63: =W61/'Balance Sheet'!W48 -> 0.050619885 | Y63: Interest rate STD | Z63: =AVERAGE(AC61:AE61)/AVERAGE('Balance Sheet'!AC46:AE46) -> 0.066048565 | AG63: ST Borrowings to Revenue ratio | AH63: ='Balance Sheet'!AH46/'Income Statement'!AH7 -> 0.13533095 | AI63: ='Balance Sheet'!AI46/'Income Statement'!AI7 -> 0.087378496 | AJ63: ='Balance Sheet'!AJ46/'Income Statement'!AJ7 -> 0.2176872 | AK63: ='Balance Sheet'!AK46/'Income Statement'!AK7 -> 0.28980817 | AL63: ='Balance Sheet'!AL46/'Income Statement'!AL7 -> 0.21636326 | AM63: ='Balance Sheet'!AM46/'Income Statement'!AM7 -> 0.15896376 | AO63: LT Borrowings to Revenue ratio | AP63: ='Balance Sheet'!AP42/'Income Statement'!AP8 -> 0.13557188 | AQ63: ='Balance Sheet'!AQ42/'Income Statement'!AQ8 -> 0.061915783 | AR63: ='Balance Sheet'!AR42/'Income Statement'!AR8 -> 0.018882021 | AS63: ='Balance Sheet'!AS42/'Income Statement'!AS8 -> 0 | AT63: ='Balance Sheet'!AT42/'Income Statement'!AT8 -> 0 | AU63: ='Balance Sheet'!AU42/'Income Statement'!AU8 -> 0.00042169008
A64: Dividends Paid | B64: ='Income Statement Forecast'!B20*'Income Statement'!$B$43 -> 1029.6447 | C64: ='Income Statement Forecast'!C20*'Income Statement'!$B$43 -> 1120.0678 | D64: ='Income Statement Forecast'!D20*'Income Statement'!$B$43 -> 1219.9696 | E64: ='Income Statement Forecast'!E20*'Income Statement'!$B$43 -> 1330.2208 | F64: ='Income Statement Forecast'!F20*'Income Statement'!$B$43 -> 1451.7803 | I64: Average | J64: =O63 -> 0.63068675 | Y64: Interest rate LTD | Z64: =AVERAGE(AC62:AE62)/AVERAGE('Balance Sheet'!AC38:AE38) -> 0.072466599 | AG64: Average LTB | AH64: =AVERAGE(AL62:AM62) -> 0.12598565 | AO64: ST Borrowings to Revenue ratio | AP64: ='Balance Sheet'!AP50/'Income Statement'!AP8 -> 0.02558624 | AQ64: ='Balance Sheet'!AQ50/'Income Statement'!AQ8 -> 0.017231403 | AR64: ='Balance Sheet'!AR50/'Income Statement'!AR8 -> 0.018503691 | AS64: ='Balance Sheet'!AS50/'Income Statement'!AS8 -> 0.022401723 | AT64: ='Balance Sheet'!AT50/'Income Statement'!AT8 -> 0.0093142478 | AU64: ='Balance Sheet'!AU50/'Income Statement'!AU8 -> 0.0028201844
A65: CapEx Intensity | B65: =B58/'Income Statement Forecast'!B7 -> 0.12480973 | C65: =C58/'Income Statement Forecast'!C7 -> 0.12480973 | D65: =D58/'Income Statement Forecast'!D7 -> 0.12480973 | E65: =E58/'Income Statement Forecast'!E7 -> 0.12480973 | F65: =F58/'Income Statement Forecast'!F7 -> 0.12480973 | I65: Average Finance cost | J65: =AVERAGE('Income Statement'!N13:O13)/AVERAGE('Balance Sheet'!N47:O47) -> 0.099720469 | Y65: Investments to revenue ratio | Z65: ='Balance Sheet'!Z21/'Income Statement'!Z9 -> 0.12421158 | AA65: ='Balance Sheet'!AA21/'Income Statement'!AA9 -> 0.1224837 | AB65: ='Balance Sheet'!AB21/'Income Statement'!AB9 -> 0.062574899 | AC65: ='Balance Sheet'!AC21/'Income Statement'!AC9 -> 0.078417272 | AD65: ='Balance Sheet'!AD21/'Income Statement'!AD9 -> 0.15239367 | AE65: ='Balance Sheet'!AE21/'Income Statement'!AE9 -> 0.098713146 | AG65: Average STB | AH65: =AVERAGE(AJ63:AM63) -> 0.2207056 | AO65: Average LTB | AP65: =AVERAGE(AU63) -> 0.00042169008
I66: Borrowings (Average) | J66: =AVERAGE('Cash Flow Statement'!M44:O44) -> 5364.71 | Y66: Average | Z66: =AVERAGE(AD65:AE65) -> 0.12555341 | AG66: Investments to revenue | AH66: =('Balance Sheet'!AH21+'Balance Sheet'!AH12)/'Income Statement'!AH7 -> 0.00026176679 | AI66: =('Balance Sheet'!AI21+'Balance Sheet'!AI12)/'Income Statement'!AI7 -> 0.022469819 | AJ66: =('Balance Sheet'!AJ21+'Balance Sheet'!AJ12)/'Income Statement'!AJ7 -> 0.025998897 | AK66: =('Balance Sheet'!AK21+'Balance Sheet'!AK12)/'Income Statement'!AK7 -> 0.020567412 | AL66: =('Balance Sheet'!AL21+'Balance Sheet'!AL12)/'Income Statement'!AL7 -> 0.016024848 | AM66: =('Balance Sheet'!AM21+'Balance Sheet'!AM12)/'Income Statement'!AM7 -> 0.013499882 | AO66: Average STB | AP66: =AVERAGE(AP64:AU64) -> 0.015976248
AG67: Average | AH67: =AVERAGE(AI66:AM66) -> 0.019712172 | AO67: Investments to revenue | AP67: =('Balance Sheet'!AP14+'Balance Sheet'!AP23)/'Income Statement'!AP8 -> 0.070727659 | AQ67: =('Balance Sheet'!AQ14+'Balance Sheet'!AQ23)/'Income Statement'!AQ8 -> 0.12775268 | AR67: =('Balance Sheet'!AR14+'Balance Sheet'!AR23)/'Income Statement'!AR8 -> 0.11362555 | AS67: =('Balance Sheet'!AS14+'Balance Sheet'!AS23)/'Income Statement'!AS8 -> 0.15375376 | AT67: =('Balance Sheet'!AT14+'Balance Sheet'!AT23)/'Income Statement'!AT8 -> 0.20056703 | AU67: =('Balance Sheet'!AU14+'Balance Sheet'!AU23)/'Income Statement'!AU8 -> 0.27428511
I68: Forecast | J68: 2026 | K68: 2027 | L68: 2028 | M68: 2029 | N68: 2030 | Q68: Forecast | R68: 2026 | S68: 2027 | T68: 2028 | U68: 2029 | V68: 2030 | AO68: Average | AP68: =AVERAGE(AS67:AU67) -> 0.2095353
I69: CapEx | J69: =J76*$J$37 -> 2445.2224 | K69: =K76*$J$37 -> 2652.5201 | L69: =L76*$J$37 -> 2877.3919 | M69: =M76*$J$37 -> 3121.3276 | N69: =N76*$J$37 -> 3385.9433 | Q69: CapEx | R69: =$R$32*'Income Statement Forecast'!P7 -> 724.05236 | S69: =$R$32*'Income Statement Forecast'!Q7 -> 824.51786 | T69: =$R$32*'Income Statement Forecast'!R7 -> 940.07539 | U69: =$R$32*'Income Statement Forecast'!S7 -> 1073.3314 | V69: =$R$32*'Income Statement Forecast'!T7 -> 1227.4349
I70: Depreciation | J70: ='Balance Sheet'!O6*'Income Statement'!J40 -> 1759.2786 | K70: ='Balance Sheet Forecast'!I6*'Income Statement'!J40 -> 1879.523 | L70: ='Balance Sheet Forecast'!J6*'Income Statement'!J40 -> 2015.0277 | M70: ='Balance Sheet Forecast'!K6*'Income Statement'!J40 -> 2166.1983 | N70: ='Balance Sheet Forecast'!L6*'Income Statement'!J40 -> 2333.6304 | Q70: Depreciation | R70: ='Balance Sheet'!W6*'Income Statement'!R35 -> 185.3678 | S70: ='Balance Sheet Forecast'!P6*'Income Statement'!$R$35 -> 221.80357 | T70: ='Balance Sheet Forecast'!Q6*'Income Statement'!$R$35 -> 262.57021 | U70: ='Balance Sheet Forecast'!R6*'Income Statement'!$R$35 -> 308.39558 | V70: ='Balance Sheet Forecast'!S6*'Income Statement'!$R$35 -> 360.13463 | Y70: Forecast | Z70: 2026 | AA70: 2027 | AB70: 2028 | AC70: 2029 | AD70: 2030 | AG70: Forecast | AH70: 2026 | AI70: 2027 | AJ70: 2028 | AK70: 2029 | AL70: 2030 | AO70: Forecast | AP70: 2026 | AQ70: 2027 | AR70: 2028 | AS70: 2029 | AT70: 2030
I71: COGS | J71: =$J$44*J76 -> 14208.519 | K71: =$J$44*K76 -> 15413.07 | L71: =$J$44*L76 -> 16719.738 | M71: =$J$44*M76 -> 18137.182 | N71: =$J$44*N76 -> 19674.791 | Q71: COGS | R71: =R76*$R$39 -> 4142.1904 | S71: =S76*$R$39 -> 4679.5573 | T71: =T76*$R$39 -> 5286.6369 | U71: =U76*$R$39 -> 5972.473 | V71: =V76*$R$39 -> 6747.2827 | Y71: CapEx | Z71: =Z78*$Z$33 -> 2166.9139 | AA71: =AA78*$Z$33 -> 2403.8021 | AB71: =AB78*$Z$33 -> 2666.587 | AC71: =AC78*$Z$33 -> 2958.0997 | AD71: =AD78*$Z$33 -> 3281.4807 | AG71: CapEx | AH71: =$AH$32*AH78 -> 570.56152 | AI71: =$AH$32*AI78 -> 605.71935 | AJ71: =$AH$32*AJ78 -> 643.0436 | AK71: =$AH$32*AK78 -> 682.66775 | AL71: =$AH$32*AL78 -> 724.73353 | AO71: CapEx | AP71: ='Income Statement Forecast'!AK7*'Income Statement'!$AP$33 -> 1069.8209 | AQ71: ='Income Statement Forecast'!AL7*'Income Statement'!$AP$33 -> 1160.0191 | AR71: ='Income Statement Forecast'!AM7*'Income Statement'!$AP$33 -> 1257.822 | AS71: ='Income Statement Forecast'!AN7*'Income Statement'!$AP$33 -> 1363.8709 | AT71: ='Income Statement Forecast'!AO7*'Income Statement'!$AP$33 -> 1478.861
I72: Other income | J72: =O6*(1+J45) -> 2371.516 | K72: =Table3942[[#This Row],[2026]]*(1+$J$45) -> 2862.073 | L72: =Table3942[[#This Row],[2027]]*(1+$J$45) -> 3454.1036 | M72: =Table3942[[#This Row],[2028]]*(1+$J$45) -> 4168.598 | N72: =Table3942[[#This Row],[2029]]*(1+$J$45) -> 5030.8883 | Q72: Other income | R72: =W6*(1+R40) -> 705.91077 | S72: =Table394245[[#This Row],[2026]]*(1+$R$40) -> 928.31463 | T72: =Table394245[[#This Row],[2027]]*(1+$R$40) -> 1220.7889 | U72: =Table394245[[#This Row],[2028]]*(1+$R$40) -> 1605.41 | V72: =Table394245[[#This Row],[2029]]*(1+$R$40) -> 2111.2097 | Y72: Depreciation | Z72: ='Balance Sheet'!AE6*'Income Statement'!$Z$36 -> 1103.1028 | AA72: ='Balance Sheet Forecast'!W6*'Income Statement'!$Z$36 -> 1263.8905 | AB72: ='Balance Sheet Forecast'!X6*'Income Statement'!$Z$36 -> 1436.1803 | AC72: ='Balance Sheet Forecast'!Y6*'Income Statement'!$Z$36 -> 1622.1478 | AD72: ='Balance Sheet Forecast'!Z6*'Income Statement'!$Z$36 -> 1824.0677 | AG72: Depreciation | AH72: ='Balance Sheet'!AM6*'Income Statement'!$AH$35 -> 326.11834 | AI72: ='Balance Sheet Forecast'!AD6*'Income Statement'!AH35 -> 350.9583 | AJ72: ='Balance Sheet Forecast'!AE6*'Income Statement'!$AH$35 -> 376.84675 | AK72: ='Balance Sheet Forecast'!AF6*'Income Statement'!$AH$35 -> 403.89729 | AL72: ='Balance Sheet Forecast'!AG6*'Income Statement'!$AH$35 -> 432.22554 | AO72: Depreciation | AP72: ='Balance Sheet'!AU6*'Income Statement'!AP36 -> 877.75418 | AQ72: ='Balance Sheet Forecast'!AK6*'Income Statement'!$AP$36 -> 912.77529 | AR72: ='Balance Sheet Forecast'!AL6*'Income Statement'!$AP$36 -> 957.85728 | AS72: ='Balance Sheet Forecast'!AM6*'Income Statement'!$AP$36 -> 1012.5523 | AT72: ='Balance Sheet Forecast'!AN6*'Income Statement'!$AP$36 -> 1076.6111
I73: Other non-current assets | J73: =J76*$J$50 -> 18411.023 | K73: =K76*$J$50 -> 19971.848 | L73: =L76*$J$50 -> 21664.994 | M73: =M76*$J$50 -> 23501.68 | N73: =N76*$J$50 -> 25494.074 | Q73: Other non-current assets | R73: =R76*$R$45 -> 2872.3565 | S73: =S76*$R$45 -> 3244.9877 | T73: =T76*$R$45 -> 3665.9604 | U73: =U76*$R$45 -> 4141.546 | V73: =V76*$R$45 -> 4678.8293 | Y73: COGS | Z73: =$Z$40*Z78 -> 11080.046 | AA73: =$Z$40*AA78 -> 12291.323 | AB73: =$Z$40*AB78 -> 13635.017 | AC73: =$Z$40*AC78 -> 15125.604 | AD73: =$Z$40*AD78 -> 16779.143 | AG73: COGS | AH73: =AH78*$AH$39 -> 3242.7434 | AI73: =AI78*$AH$39 -> 3442.5603 | AJ73: =AJ78*$AH$39 -> 3654.6899 | AK73: =AK78*$AH$39 -> 3879.8907 | AL73: =AL78*$AH$39 -> 4118.9685 | AO73: COGS | AP73: ='Income Statement Forecast'!AK7*'Income Statement'!$AP$40 -> 10826.843 | AQ73: ='Income Statement Forecast'!AL7*'Income Statement'!$AP$40 -> 11739.67 | AR73: ='Income Statement Forecast'!AM7*'Income Statement'!$AP$40 -> 12729.459 | AS73: ='Income Statement Forecast'!AN7*'Income Statement'!$AP$40 -> 13802.699 | AT73: ='Income Statement Forecast'!AO7*'Income Statement'!$AP$40 -> 14966.426
I74: SG&A | J74: =J76*$J$48 -> 28594.971 | K74: =K76*$J$48 -> 31019.157 | L74: =L76*$J$48 -> 33648.857 | M74: =M76*$J$48 -> 36501.495 | N74: =N76*$J$48 -> 39595.969 | Q74: SG&A | R74: =R76*$R$43 -> 5952.3878 | S74: =S76*$R$43 -> 6724.5919 | T74: =T76*$R$43 -> 7596.9741 | U74: =U76*$R$43 -> 8582.5305 | V74: =V76*$R$43 -> 9695.9433 | Y74: Other income | Z74: =AE8*(1+Z41) -> 1206.6398 | AA74: =Table39424550[[#This Row],[2026]]*(1+$Z$41) -> 1326.8747 | AB74: =Table39424550[[#This Row],[2027]]*(1+$Z$41) -> 1459.0903 | AC74: =Table39424550[[#This Row],[2028]]*(1+$Z$41) -> 1604.4805 | AD74: =Table39424550[[#This Row],[2029]]*(1+$Z$41) -> 1764.358 | AG74: Other income | AH74: =AM6*(1+$AH$40) -> 17.671998 | AI74: =Table3942455049[[#This Row],[2026]]*(1+$AH$40) -> 13.420692 | AJ74: =Table3942455049[[#This Row],[2027]]*(1+$AH$40) -> 10.192112 | AK74: =Table3942455049[[#This Row],[2028]]*(1+$AH$40) -> 7.7402224 | AL74: =Table3942455049[[#This Row],[2029]]*(1+$AH$40) -> 5.8781776 | AO74: Other income | AP74: =(AU6+AU7)*(1+AP41) -> 1369.6228 | AQ74: =Table394245504973[[#This Row],[2026]]*(1+$AP$41) -> 1483.9661 | AR74: =Table394245504973[[#This Row],[2027]]*(1+$AP$41) -> 1607.8553 | AS74: =Table394245504973[[#This Row],[2028]]*(1+$AP$41) -> 1742.0875 | AT74: =Table394245504973[[#This Row],[2029]]*(1+$AP$41) -> 1887.526
I75: Dividends Paid | J75: =$J$52*'Income Statement Forecast'!I20 -> 2832.4005 | K75: =$J$52*'Income Statement Forecast'!J20 -> 3044.4846 | L75: =$J$52*'Income Statement Forecast'!K20 -> 3308.0393 | M75: =$J$52*'Income Statement Forecast'!L20 -> 3626.6995 | N75: =$J$52*'Income Statement Forecast'!M20 -> 4005.671 | Q75: Dividends Paid | R75: =$R$47*'Income Statement Forecast'!P20 -> 7.9850403 | S75: =$R$47*'Income Statement Forecast'!Q20 -> 9.7446413 | T75: =$R$47*'Income Statement Forecast'!R20 -> 11.841507 | U75: =$R$47*'Income Statement Forecast'!S20 -> 14.357479 | V75: =$R$47*'Income Statement Forecast'!T20 -> 17.396807 | Y75: Other non-current assets | Z75: =$Z$46*Z78 -> 5692.189 | AA75: =$Z$46*AA78 -> 6314.4622 | AB75: =$Z$46*AB78 -> 7004.7625 | AC75: =$Z$46*AC78 -> 7770.5269 | AD75: =$Z$46*AD78 -> 8620.005 | AG75: Other non-current assets | AH75: =AH78*$AH$45 -> 2393.3055 | AI75: =AI78*$AH$45 -> 2540.7802 | AJ75: =AJ78*$AH$45 -> 2697.3423 | AK75: =AK78*$AH$45 -> 2863.5518 | AL75: =AL78*$AH$45 -> 3040.003 | AO75: Other non-current assets | AP75: ='Income Statement Forecast'!AK7*'Income Statement'!$AP$46 -> 8079.7437 | AQ75: ='Income Statement Forecast'!AL7*'Income Statement'!$AP$46 -> 8760.9587 | AR75: ='Income Statement Forecast'!AM7*'Income Statement'!$AP$46 -> 9499.6082 | AS75: ='Income Statement Forecast'!AN7*'Income Statement'!$AP$46 -> 10300.535 | AT75: ='Income Statement Forecast'!AO7*'Income Statement'!$AP$46 -> 11168.989
I76: Revenue | J76: =O7*(1+J42) -> 59167.494 | K76: =Table3942[[#This Row],[2026]]*(1+$J$42) -> 64183.516 | L76: =Table3942[[#This Row],[2027]]*(1+$J$42) -> 69624.779 | M76: =Table3942[[#This Row],[2028]]*(1+$J$42) -> 75527.335 | N76: =Table3942[[#This Row],[2029]]*(1+$J$42) -> 81930.29 | Q76: Revenue | R76: =W5*(1+R37) -> 13791.113 | S76: =Table394245[[#This Row],[2026]]*(1+$R$37) -> 15580.236 | T76: =Table394245[[#This Row],[2027]]*(1+$R$37) -> 17601.462 | U76: =Table394245[[#This Row],[2028]]*(1+$R$37) -> 19884.902 | V76: =Table394245[[#This Row],[2029]]*(1+$R$37) -> 22464.573 | Y76: SG&A | Z76: =Z78*$Z$44 -> 15264.048 | AA76: =AA78*$Z$44 -> 16932.722 | AB76: =AB78*$Z$44 -> 18783.816 | AC76: =AC78*$Z$44 -> 20837.273 | AD76: =AD78*$Z$44 -> 23115.215 | AG76: SG&A | AH76: =AH78*$AH$43 -> 5246.0648 | AI76: =AI78*$AH$43 -> 5569.3257 | AJ76: =AJ78*$AH$43 -> 5912.5059 | AK76: =AK78*$AH$43 -> 6276.8327 | AL76: =AL78*$AH$43 -> 6663.6093 | AO76: SG&A | AP76: ='Income Statement Forecast'!AK7*'Income Statement'!$AP$44 -> 12592.46 | AQ76: ='Income Statement Forecast'!AL7*'Income Statement'!$AP$44 -> 13654.149 | AR76: ='Income Statement Forecast'!AM7*'Income Statement'!$AP$44 -> 14805.35 | AS76: ='Income Statement Forecast'!AN7*'Income Statement'!$AP$44 -> 16053.612 | AT76: ='Income Statement Forecast'!AO7*'Income Statement'!$AP$44 -> 17407.117
I77: Amortisation | J77: ='Balance Sheet'!O9*'Income Statement'!J41 -> 664.6364 | K77: ='Balance Sheet Forecast'!I7*'Income Statement'!J41 -> 1205.2603 | L77: ='Balance Sheet Forecast'!J7*'Income Statement'!$J$41 -> 1702.5789 | M77: ='Balance Sheet Forecast'!K7*'Income Statement'!$J$41 -> 2169.3277 | N77: ='Balance Sheet Forecast'!L7*'Income Statement'!$J$41 -> 2616.3022 | Q77: Amortisation | R77: ='Balance Sheet'!W10*'Income Statement'!R36 -> 549.15396 | S77: ='Balance Sheet Forecast'!P7*'Income Statement'!$R$36 -> 546.34223 | T77: ='Balance Sheet Forecast'!Q7*'Income Statement'!$R$36 -> 547.40008 | U77: ='Balance Sheet Forecast'!R7*'Income Statement'!$R$36 -> 552.58739 | V77: ='Balance Sheet Forecast'!S7*'Income Statement'!$R$36 -> 562.2116 | Y77: Dividends Paid | Z77: ='Income Statement Forecast'!W20*'Income Statement'!$Z$48 -> 637.73591 | AA77: ='Income Statement Forecast'!X20*'Income Statement'!$Z$48 -> 692.48598 | AB77: ='Income Statement Forecast'!Y20*'Income Statement'!$Z$48 -> 755.0449 | AC77: ='Income Statement Forecast'!Z20*'Income Statement'!$Z$48 -> 825.97574 | AD77: ='Income Statement Forecast'!AA20*'Income Statement'!$Z$48 -> 905.94099 | AG77: Dividends Paid | AH77: ='Income Statement Forecast'!AD20*'Income Statement'!$AH$47 -> 746.42615 | AI77: ='Income Statement Forecast'!AE20*'Income Statement'!$AH$47 -> 788.94192 | AJ77: ='Income Statement Forecast'!AF20*'Income Statement'!$AH$47 -> 834.77927 | AK77: ='Income Statement Forecast'!AG20*'Income Statement'!$AH$47 -> 883.98792 | AL77: ='Income Statement Forecast'!AH20*'Income Statement'!$AH$47 -> 936.65647 | AO77: Dividends Paid | AP77: ='Income Statement Forecast'!AK20*'Income Statement'!$AP$48 -> 392.13417 | AQ77: ='Income Statement Forecast'!AL20*'Income Statement'!$AP$48 -> 384.92971 | AR77: ='Income Statement Forecast'!AM20*'Income Statement'!$AP$48 -> 370.29164 | AS77: ='Income Statement Forecast'!AN20*'Income Statement'!$AP$48 -> 346.18522 | AT77: ='Income Statement Forecast'!AO20*'Income Statement'!$AP$48 -> 375.35846
I78: Research and Development Expenses | J78: =J76*$J$46 -> 3601.8059 | K78: =K76*$J$46 -> 3907.1549 | L78: =L76*$J$46 -> 4238.3905 | M78: =M76*$J$46 -> 4597.707 | N78: =N76*$J$46 -> 4987.4852 | Q78: Research and Development Expenses | R78: =R76*$R$41 -> 499.98019 | S78: =S76*$R$41 -> 564.84268 | T78: =T76*$R$41 -> 638.1198 | U78: =U76*$R$41 -> 720.90316 | V78: =V76*$R$41 -> 814.42603 | Y78: Revenue | Z78: =(AE5+AE7+AE6)*(1+Z38) -> 36212.549 | AA78: =Table39424550[[#This Row],[2026]]*(1+$Z$38) -> 40171.324 | AB78: =Table39424550[[#This Row],[2027]]*(1+$Z$38) -> 44562.874 | AC78: =Table39424550[[#This Row],[2028]]*(1+$Z$38) -> 49434.511 | AD78: =Table39424550[[#This Row],[2029]]*(1+$Z$38) -> 54838.718 | AG78: Revenue | AH78: =AM7*(1+AH37) -> 12250.412 | AI78: =Table3942455049[[#This Row],[2026]]*(1+$AH$37) -> 13005.279 | AJ78: =Table3942455049[[#This Row],[2027]]*(1+$AH$37) -> 13806.66 | AK78: =Table3942455049[[#This Row],[2028]]*(1+$AH$37) -> 14657.422 | AL78: =Table3942455049[[#This Row],[2029]]*(1+$AH$37) -> 15560.608 | AO78: Revenue | AP78: =AU5*(1+AP38) -> 29435.112 | AQ78: =Table394245504973[[#This Row],[2026]]*(1+$AP$38) -> 31917.961 | AR78: =Table394245504973[[#This Row],[2027]]*(1+$AP$38) -> 34610.238 | AS78: =Table394245504973[[#This Row],[2028]]*(1+$AP$38) -> 37529.608 | AT78: =Table394245504973[[#This Row],[2029]]*(1+$AP$38) -> 40695.227
I79: Working Capital | J79: =J76*$J$64 -> 37316.154 | K79: =K76*$J$64 -> 40479.693 | L79: =L76*$J$64 -> 43911.426 | M79: =M76*$J$64 -> 47634.089 | N79: =N76*$J$64 -> 51672.348 | Q79: Working Capital | R79: =R76*$R$59 -> 1449.1012 | S79: =S76*$R$59 -> 1637.0933 | T79: =T76*$R$59 -> 1849.4736 | U79: =U76*$R$59 -> 2089.4061 | V79: =V76*$R$59 -> 2360.465 | Y79: Amortisation | Z79: ='Balance Sheet'!AE9*'Income Statement'!$Z$37 -> 1303.5918 | AA79: ='Balance Sheet Forecast'!W7*'Income Statement'!$Z$37 -> 1524.1191 | AB79: ='Balance Sheet Forecast'!X7*'Income Statement'!$Z$37 -> 1758.176 | AC79: ='Balance Sheet Forecast'!Y7*'Income Statement'!$Z$37 -> 2008.6759 | AD79: ='Balance Sheet Forecast'!Z7*'Income Statement'!$Z$37 -> 2278.6562 | AG79: Amortisation | AH79: ='Balance Sheet'!AM10*'Income Statement'!$AH$36 -> 419.05467 | AI79: ='Balance Sheet Forecast'!AD7*'Income Statement'!$AH$36 -> 442.22223 | AJ79: ='Balance Sheet Forecast'!AE7*'Income Statement'!$AH$36 -> 467.08525 | AK79: ='Balance Sheet Forecast'!AF7*'Income Statement'!$AH$36 -> 493.72117 | AL79: ='Balance Sheet Forecast'!AG7*'Income Statement'!$AH$36 -> 522.21494 | AO79: Amortisation | AP79: ='Balance Sheet'!AU11*'Income Statement'!$AP$37 -> 253.45224 | AQ79: ='Balance Sheet Forecast'!AK7*'Income Statement'!$AP$37 -> 734.97055 | AR79: ='Balance Sheet Forecast'!AL7*'Income Statement'!$AP$37 -> 1171.4963 | AS79: ='Balance Sheet Forecast'!AM7*'Income Statement'!$AP$37 -> 1575.1563 | AT79: ='Balance Sheet Forecast'!AN7*'Income Statement'!$AP$37 -> 1956.1385
I80: Capex senstivity | J80: =J69/J76 -> 0.041327124 | K80: =K69/K76 -> 0.041327124 | L80: =L69/L76 -> 0.041327124 | M80: =M69/M76 -> 0.041327124 | N80: =N69/N76 -> 0.041327124 | Q80: Other current assets | R80: =R76*$R$51 -> 1593.9655 | S80: =S76*$R$51 -> 1800.7509 | T80: =T76*$R$51 -> 2034.3625 | U80: =U76*$R$51 -> 2298.2807 | V80: =V76*$R$51 -> 2596.4369 | Y80: Research and Development Expenses | Z80: =Z78*$Z$42 -> 2929.9994 | AA80: =AA78*$Z$42 -> 3250.3084 | AB80: =AB78*$Z$42 -> 3605.6339 | AC80: =AC78*$Z$42 -> 3999.8037 | AD80: =AD78*$Z$42 -> 4437.0644 | AG80: Research and Development Expenses | AH80: =AH78*$AH$41 -> 648.61962 | AI80: =AI78*$AH$41 -> 688.58736 | AJ80: =AJ78*$AH$41 -> 731.01791 | AK80: =AK78*$AH$41 -> 776.06302 | AL80: =AL78*$AH$41 -> 823.88379 | AO80: Research and Development Expenses | AP80: ='Income Statement Forecast'!AK7*'Income Statement'!$AP$42 -> 2842.1911 | AQ80: ='Income Statement Forecast'!AL7*'Income Statement'!$AP$42 -> 3081.8203 | AR80: ='Income Statement Forecast'!AM7*'Income Statement'!$AP$42 -> 3341.6532 | AS80: ='Income Statement Forecast'!AN7*'Income Statement'!$AP$42 -> 3623.3931 | AT80: ='Income Statement Forecast'!AO7*'Income Statement'!$AP$42 -> 3928.887
Q81: Other current liabilities | R81: =R76*$R$56 -> 1297.2226 | S81: =S76*$R$56 -> 1465.5115 | T81: =T76*$R$56 -> 1655.6325 | U81: =U76*$R$56 -> 1870.4179 | V81: =V76*$R$56 -> 2113.0675 | Y81: Working Capital | Z81: ='Balance Sheet Forecast'!W15-'Balance Sheet Forecast'!W31 -> 13165.846 | AA81: ='Balance Sheet Forecast'!X15-'Balance Sheet Forecast'!X31 -> 13473.321 | AB81: ='Balance Sheet Forecast'!Y15-'Balance Sheet Forecast'!Y31 -> 13845.373 | AC81: ='Balance Sheet Forecast'!Z15-'Balance Sheet Forecast'!Z31 -> 14282.991 | AD81: ='Balance Sheet Forecast'!AA15-'Balance Sheet Forecast'!AA31 -> 14787.94 | AG81: Working Capital | AH81: ='Balance Sheet Forecast'!AD15-'Balance Sheet Forecast'!AD31 -> 561.73535 | AI81: ='Balance Sheet Forecast'!AE15-'Balance Sheet Forecast'!AE31 -> 546.66896 | AJ81: ='Balance Sheet Forecast'!AF15-'Balance Sheet Forecast'!AF31 -> 530.8785 | AK81: ='Balance Sheet Forecast'!AG15-'Balance Sheet Forecast'!AG31 -> 514.4562 | AL81: ='Balance Sheet Forecast'!AH15-'Balance Sheet Forecast'!AH31 -> 497.44799 | AO81: Working Capital | AP81: ='Balance Sheet Forecast'!AK15-'Balance Sheet Forecast'!AK31 -> 17364.745 | AQ81: ='Balance Sheet Forecast'!AL15-'Balance Sheet Forecast'!AL31 -> 17515.75 | AR81: ='Balance Sheet Forecast'!AM15-'Balance Sheet Forecast'!AM31 -> 18992.529 | AS81: ='Balance Sheet Forecast'!AN15-'Balance Sheet Forecast'!AN31 -> 20593.819 | AT81: ='Balance Sheet Forecast'!AO15-'Balance Sheet Forecast'!AO31 -> 22330.115
Q82: Other non-current liabilities | R82: =R76*$R$54 -> 574.34751 | S82: =S76*$R$54 -> 648.85769 | T82: =T76*$R$54 -> 733.03409 | U82: =U76*$R$54 -> 828.1307 | V82: =V76*$R$54 -> 935.5642 | Y82: Other current assets | Z82: =Z78*$Z$52 -> 3914.3526 | AA82: =AA78*$Z$52 -> 4342.2717 | AB82: =AB78*$Z$52 -> 4816.9712 | AC82: =AC78*$Z$52 -> 5343.5651 | AD82: =AD78*$Z$52 -> 5927.7264 | AG82: Other current assets | AH82: =AH78*$AH$51 -> 848.27606 | AI82: =AI78*$AH$51 -> 900.54658 | AJ82: =AJ78*$AH$51 -> 956.03799 | AK82: =AK78*$AH$51 -> 1014.9488 | AL82: =AL78*$AH$51 -> 1077.4896 | AO82: Other current assets | AP82: ='Income Statement Forecast'!AK7*'Income Statement'!$AP$52 -> 10624.65 | AQ82: ='Income Statement Forecast'!AL7*'Income Statement'!$AP$52 -> 11520.43 | AR82: ='Income Statement Forecast'!AM7*'Income Statement'!$AP$52 -> 12491.734 | AS82: ='Income Statement Forecast'!AN7*'Income Statement'!$AP$52 -> 13544.931 | AT82: ='Income Statement Forecast'!AO7*'Income Statement'!$AP$52 -> 14686.925
Q83: Capex senstivity | R83: =R69/R76 -> 0.052501373 | S83: =S69/S76 -> 0.052920756 | T83: =T69/T76 -> 0.053408938 | U83: =U69/U76 -> 0.053977205 | V83: =V69/V76 -> 0.054638695 | Y83: Other current liabilities | Z83: =Z78*$Z$57 -> 6855.2162 | AA83: =AA78*$Z$57 -> 7604.6321 | AB83: =AB78*$Z$57 -> 8435.9745 | AC83: =AC78*$Z$57 -> 9358.1998 | AD83: =AD78*$Z$57 -> 10381.243 | AG83: Other current liabilities | AH83: =AH78*$AH$56 -> 1164.2963 | AI83: =AI78*$AH$56 -> 1236.0398 | AJ83: =AJ78*$AH$56 -> 1312.2042 | AK83: =AK78*$AH$56 -> 1393.0619 | AL83: =AL78*$AH$56 -> 1478.9019 | AO83: Other current liabilities | AP83: ='Income Statement Forecast'!AK7*'Income Statement'!$AP$57 -> 2939.6294 | AQ83: ='Income Statement Forecast'!AL7*'Income Statement'!$AP$57 -> 3187.4738 | AR83: ='Income Statement Forecast'!AM7*'Income Statement'!$AP$57 -> 3456.2145 | AS83: ='Income Statement Forecast'!AN7*'Income Statement'!$AP$57 -> 3747.6132 | AT83: ='Income Statement Forecast'!AO7*'Income Statement'!$AP$57 -> 4063.5803
Y84: Other non-current liabilities | Z84: =Z78*$Z$55 -> 699.43298 | AA84: =AA78*$Z$55 -> 775.89536 | AB84: =AB78*$Z$55 -> 860.71666 | AC84: =AC78*$Z$55 -> 954.81066 | AD84: =AD78*$Z$55 -> 1059.1911 | AG84: Other non-current liabilities | AH84: =AH78*$AH$54 -> 1031.0561 | AI84: =AI78*$AH$54 -> 1094.5895 | AJ84: =AJ78*$AH$54 -> 1162.0378 | AK84: =AK78*$AH$54 -> 1233.6422 | AL84: =AL78*$AH$54 -> 1309.6589 | AO84: Other non-current liabilities | AP84: ='Income Statement Forecast'!AK7*'Income Statement'!$AP$55 -> 798.4097 | AQ84: ='Income Statement Forecast'!AL7*'Income Statement'!$AP$55 -> 865.72479 | AR84: ='Income Statement Forecast'!AM7*'Income Statement'!$AP$55 -> 938.71534 | AS84: ='Income Statement Forecast'!AN7*'Income Statement'!$AP$55 -> 1017.8599 | AT84: ='Income Statement Forecast'!AO7*'Income Statement'!$AP$55 -> 1103.6772
Y85: Investments | Z85: =Z78*$Z$66 -> 4546.6089 | AA85: =AA78*$Z$66 -> 5043.6466 | AB85: =AB78*$Z$66 -> 5595.0207 | AC85: =AC78*$Z$66 -> 6206.6714 | AD85: =AD78*$Z$66 -> 6885.188 | AG85: LT Borrowings | AH85: =AH78*$AH$64 -> 1543.3761 | AI85: =AI78*$AH$64 -> 1638.4785 | AJ85: =AJ78*$AH$64 -> 1739.441 | AK85: =AK78*$AH$64 -> 1846.6249 | AL85: =AL78*$AH$64 -> 1960.4133 | AO85: LT Borrowings | AP85: ='Income Statement Forecast'!AK7*'Income Statement'!$AP$65 -> 12.990051 | AQ85: ='Income Statement Forecast'!AL7*'Income Statement'!$AP$65 -> 14.085261 | AR85: ='Income Statement Forecast'!AM7*'Income Statement'!$AP$65 -> 15.272811 | AS85: ='Income Statement Forecast'!AN7*'Income Statement'!$AP$65 -> 16.560484 | AT85: ='Income Statement Forecast'!AO7*'Income Statement'!$AP$65 -> 17.956724
Y86: Borrowings | Z86: =Z78*$Z$60 -> 4083.1577 | AA86: =AA78*$Z$60 -> 4529.5307 | AB86: =AB78*$Z$60 -> 5024.7014 | AC86: =AC78*$Z$60 -> 5574.0044 | AD86: =AD78*$Z$60 -> 6183.3576 | AG86: ST Borrowings | AH86: =AH78*$AH$65 -> 2703.7345 | AI86: =AI78*$AH$65 -> 2870.3378 | AJ86: =AJ78*$AH$65 -> 3047.2071 | AK86: =AK78*$AH$65 -> 3234.9751 | AL86: =AL78*$AH$65 -> 3434.3133 | AO86: ST Borrowings | AP86: =$AP$66*'Income Statement Forecast'!AK7 -> 492.1441 | AQ86: =$AP$66*'Income Statement Forecast'!AL7 -> 533.63748 | AR86: =$AP$66*'Income Statement Forecast'!AM7 -> 578.62926 | AS86: =$AP$66*'Income Statement Forecast'!AN7 -> 627.41437 | AT86: =$AP$66*'Income Statement Forecast'!AO7 -> 680.31265
Y87: Capex senstivitiy | Z87: =Z71/Z78 -> 0.059838757 | AA87: =AA71/AA78 -> 0.059838757 | AB87: =AB71/AB78 -> 0.059838757 | AC87: =AC71/AC78 -> 0.059838757 | AD87: =AD71/AD78 -> 0.059838757 | AG87: Investments | AH87: =AH78*$AH$67 -> 241.48222 | AI87: =AI78*$AH$67 -> 256.36228 | AJ87: =AJ78*$AH$67 -> 272.15925 | AK87: =AK78*$AH$67 -> 288.92962 | AL87: =AL78*$AH$67 -> 306.73338 | AO87: Investments | AP87: ='Income Statement Forecast'!AK7*'Income Statement'!$AP$68 -> 6454.6793 | AQ87: ='Income Statement Forecast'!AL7*'Income Statement'!$AP$68 -> 6998.8828 | AR87: ='Income Statement Forecast'!AM7*'Income Statement'!$AP$68 -> 7588.969 | AS87: ='Income Statement Forecast'!AN7*'Income Statement'!$AP$68 -> 8228.8065 | AT87: ='Income Statement Forecast'!AO7*'Income Statement'!$AP$68 -> 8922.59
AG88: Capex senstivitiy | AH88: =AH71/AH78 -> 0.046574885 | AI88: =AI71/AI78 -> 0.046574885 | AJ88: =AJ71/AJ78 -> 0.046574885 | AK88: =AK71/AK78 -> 0.046574885 | AL88: =AL71/AL78 -> 0.046574885 | AO88: Capex senstivitiy | AP88: =AP71/AP78 -> 0.036345061 | AQ88: =AQ71/AQ78 -> 0.036343772 | AR88: =AR71/AR78 -> 0.036342485 | AS88: =AS71/AS78 -> 0.036341198 | AT88: =AT71/AT78 -> 0.036339913

Sheet Cash Flow Statement
A2: #VALUE! | I2: #VALUE! | Q2: #VALUE! | Y2: #VALUE! | AG2: #VALUE! | AO2: #VALUE!
A3: Particulars | B3: 2020 | C3: 2021 | D3: 2022 | E3: 2023 | F3: 2024 | G3: 2025 | I3: Particulars | J3: 2020 | K3: 2021 | L3: 2022 | M3: 2023 | N3: 2024 | O3: 2025 | Q3: Particulars | R3: 2020 | S3: 2021 | T3: 2022 | U3: 2023 | V3: 2024 | W3: 2025 | Y3: Particulars | Z3: 2020 | AA3: 2021 | AB3: 2022 | AC3: 2023 | AD3: 2024 | AE3: 2025 | AG3: Particulars | AH3: 2020 | AI3: 2021 | AJ3: 2022 | AK3: 2023 | AL3: 2024 | AM3: 2025 | AO3: Particulars | AP3: 2020 | AQ3: 2021 | AR3: 2022 | AS3: 2023 | AT3: 2024 | AU3: 2025
A4: Operating Activities | I4: Operating activities | Q4: Operating activities | Y4: Operating Activities | AG4: Operating activities | AO4: Operating activities
A5: Profit before tax | B5: 1819.46 | C5: 2666.04 | D5: 3683.5 | E5: 2368.63 | F5: 2163 | G5: 2916 | I5: Profit before tax | J5: 5009.59 | K5: 2799.37 | L5: 4841.32 | M5: 9408.43 | N5: 11087.89 | O5: 13752.13 | Q5: Profit before tax | R5: 1437.7351 | S5: 1691.6118 | T5: 1974.6006 | U5: 1671.2391 | V5: =2397.94+1.41 -> 2399.35 | W5: =2516.33+8.45 -> 2524.78 | Y5: Profit before tax | Z5: 1885.7 | AA5: 2883.5 | AB5: 3061.4 | AC5: 6048.5 | AD5: 7201 | AE5: 7679.5 | AG5: Profit before tax | AH5: 1186.57 | AI5: 1526.26 | AJ5: 1225.91 | AK5: 1847.16 | AL5: 2352.11 | AM5: 2672.81 | AO5: Profit before tax | AP5: 2178.18 | AQ5: 3290.06 | AR5: 3675.39 | AS5: 4220.77 | AT5: 5896.72 | AU5: 6820.81
A6: Adjustments for: | I6: Adjustments for | Q6: Adjustments for | Y6: Adjustments for | AG6: Adjustments for | AO6: Depreciation, amortisation and impairment expense | AP6: 1174.65 | AQ6: 1067.66 | AR6: 1051.95 | AS6: 1172.11 | AT6: 1051.02 | AU6: 1106.95
A7: Depreciation and Amortisation expense | B7: 186.24 | C7: 255.59 | D7: 311.51 | E7: 343.18 | F7: 378 | G7: 402 | I7: Depreciation and amortisation expense | J7: 2052.78 | K7: 2079.95 | L7: 2143.74 | M7: 2529.43 | N7: 2556.64 | O7: 2575.39 | Q7: Share of profit/loss of associates and joint ventures | R7: -11.5352 | S7: -11.6771 | T7: -14.4477 | U7: -12.4242 | V7: -15.21 | W7: -12.24 | Y7: Fair value changes and profit on sale of fi nancial instruments measured at FVTPL | Z7: 1163.1 | AA7: -55.7 | AB7: -27.7 | AC7: -87.6 | AD7: -314.9 | AE7: -355.4 | AG7: Depreciation, amortisation and impairment expense | AH7: 654.38 | AI7: 657.79 | AJ7: 662.16 | AK7: 706.59 | AL7: 808.27 | AM7: 794.93 | AO7: Interest expense | AP7: 197.36 | AQ7: 160.7 | AR7: 106.35 | AS7: 109.54 | AT7: 89.88 | AU7: 62.01
A8: Unrealised foreign exchange gain/loss | B8: =-48.25+6.18 -> -42.07 | C8: =-13.28+0.22 -> -13.06 | D8: -5.44 | E8: -2.09 | F8: -2 | G8: 9 | I8: Net gain/loss on sale/write off/impairment of PPE | J8: 5.37 | K8: 1.67 | L8: 165.6 | M8: 22.71 | N8: 166.23 | O8: 1.78 | Q8: Depreciation and amortisation expense | R8: 99.0584 | S8: 118.9703 | T8: 166.6192 | U8: 325.9195 | V8: 398.25 | W8: 621.22 | Y8: Depreciation and amortisation expense | Z8: 1676.7 | AA8: 1228.8 | AB8: 1165.2 | AC8: 1250.2 | AD8: 1470 | AE8: 1703.7 | AG8: Allowance for credit loss | AH8: 2.64 | AI8: 14.42 | AJ8: =0.9+484.7 -> 485.6 | AK8: 2.27 | AL8: 7.08 | AM8: 1.77 | AO8: Unrealised foreign exchange | AP8: -31.9 | AQ8: -8.64 | AR8: 11.15 | AS8: -56.2 | AT8: -22.81 | AU8: -13.85
A9: Interest income from financial assets at amortised cost | B9: -6.66 | C9: -57.24 | D9: 2.33 | E9: 11.79 | F9: -301 | G9: -295 | I9: Finance costs | J9: 302.73 | K9: 141.3 | L9: 127.35 | M9: 172 | N9: 0 | O9: 295.3 | Q9: Net loss/gain on current investments | R9: -35.0586 | S9: -62.8649 | T9: -47.7721 | U9: -1.6219 | V9: -6.86 | W9: -139.06 | Y9: Impairment of non-current assets | Z9: 52.1 | AA9: 676.8 | AB9: 930.4 | AC9: 69.9 | AD9: 0.3 | AE9: 169.3 | AG9: Unrealised foreign exchange gain | AH9: -220.09 | AI9: -12.96 | AJ9: -36.4 | AK9: -49.15 | AL9: -88.38 | AM9: 0 | AO9: Share based payment | AP9: 23.45 | AQ9: 19.54 | AR9: 24.12 | AS9: 39.04 | AT9: 46.16 | AU9: 47.34
A10: Dividend income | B10: -37.37 | C10: 0 | D10: -68.96 | E10: -204.59 | F10: -5 | G10: -1 | I10: Interest income | J10: -354.62 | K10: -211.13 | L10: -553.37 | M10: -384.54 | N10: 0 | O10: 21.75 | Q10: Dividend income from financial assets | R10: -4.2821 | S10: -0.4243 | T10: -39.6611 | U10: -33.9758 | V10: -128.47 | W10: -21.78 | Y10: Allowance for credit losses (on trade receivables and other advances) | Z10: -56.1 | AA10: 23 | AB10: 7 | AC10: 20.5 | AD10: 27.5 | AE10: 16.1 | AG10: Loss on sale/discard/write off of PPE | AH10: 25.73 | AI10: 1.3 | AJ10: 0.82 | AK10: -21.62 | AL10: -57.09 | AM10: -14.7 | AO10: Allowances for credit loss | AP10: 180.27 | AQ10: 39.48 | AR10: -40.82 | AS10: -36.68 | AT10: 23.51 | AU10: 8.93
A11: Net gain on redemption | B11: -14.4 | C11: -2.65 | D11: 0 | E11: -5.04 | F11: 0 | G11: -4 | I11: Dividend income on investments | J11: -56.18 | K11: -256.04 | L11: -215.33 | M11: -146.45 | N11: 238.47 | O11: 231.36 | Q11: Dividend income from investments | R11: -0.0004 | S11: -0.0004 | T11: -0.0014 | U11: -0.0024 | V11: 0 | W11: 0 | Y11: (Profi t)/loss on sale/disposal of property, plant and equipment and other intangible assets | Z11: -92.9 | AA11: 4.2 | AB11: -111.9 | AC11: 20.8 | AD11: -90 | AE11: -151.2 | AG11: Net gain on sale of investments | AH11: -29.2 | AI11: -15.58 | AJ11: -10.14 | AK11: -19.51 | AL11: =0.02-17.99 -> -17.97 | AM11: =-1.34-16.73 -> -18.07 | AO11: Interest income on income tax refund | AP11: -9.28 | AQ11: -7.04 | AR11: -17.75 | AS11: -28.62 | AT11: -11.29 | AU11: -9.98
A12: Provision for doubtful debts | B12: 9.96 | C12: -0.11 | D12: -2.03 | E12: 0.33 | F12: 4 | G12: -2 | I12: Net gain arising on financial assets measured at fair value | J12: -57.19 | K12: -219.76 | L12: 361.95 | M12: 161.3 | N12: -1022.91 | O12: -1230.13 | Q12: Government grant | R12: -34.564 | S12: -44.7682 | T12: -0.0004 | U12: 0 | V12: 0 | W12: -163.96 | Y12: Share of profi t of equity accounted investees | Z12: -215.2 | AA12: -48 | AB12: -70.3 | AC12: -37 | AD12: -14.7 | AE12: -21.7 | AG12: Finance costs | AH12: 450.71 | AI12: 358.28 | AJ12: 255.06 | AK12: 333.44 | AL12: 353.56 | AM12: 252.31 | AO12: Interest income | AP12: -58.39 | AQ12: -40.22 | AR12: -61.87 | AS12: -133.62 | AT12: -208.3 | AU12: -254.42
A13: Finance costs | B13: 6.1 | C13: 0.87 | D13: 0.36 | E13: 0.33 | F13: 3 | G13: 2 | I13: Net gain on sale of financial assets measured at fair value | J13: -24.67 | K13: -13.82 | L13: -48.61 | M13: -184.71 | N13: -103.3 | O13: -66.9 | Q13: Unrealized foreign exchange (gain) / loss (net) | R13: 1.025 | S13: -0.5024 | T13: -38.4287 | U13: -36.8204 | V13: -73.95 | W13: -87.91 | Y13: Foreign exchange (gain)/loss, net | Z13: 6.8 | AA13: 185.3 | AB13: -75.8 | AC13: -92.3 | AD13: -53.3 | AE13: 21.1 | AG13: Interest income | AH13: -7.96 | AI13: -5.07 | AJ13: -7.15 | AK13: -14.78 | AL13: -11.48 | AM13: -20.19 | AO13: Dividend income | AP13: -0.06 | AQ13: -21.64 | AR13: -0.01 | AS13: 0 | AT13: 0 | AU13: 0
A14: Net gain on financial assets | B14: -44.99 | C14: 0 | D14: 0 | E14: 0 | F14: 0 | G14: 0 | I14: Net gain/loss on sale of financial assets measured at fair value | J14: -0.04 | K14: -26 | L14: -0.77 | M14: 24.03 | N14: 227.72 | O14: -133.78 | Q14: Exchange difference on translation of financial statements foreign operations | R14: -4.4223 | S14: 1.3555 | T14: -4.6932 | U14: 3.9584 | V14: -3.59 | W14: -2.38 | Y14: Interest income | Z14: -88.8 | AA14: -82.6 | AB14: -96.5 | AC14: -118 | AD14: -227.8 | AE14: -267.7 | AG14: Adjustments for | AO14: Sundry balances written off | AP14: -2.41 | AQ14: -0.06 | AR14: -6.37 | AS14: -9.08 | AT14: -18.83 | AU14: -10.94
A15: Loss on disposal/discard of assets | B15: 3.25 | C15: 5.96 | D15: 2.05 | E15: 1.13 | F15: 4 | G15: 4 | I15: Provision/write off/reversal for doubtful trade receivables | J15: 106.81 | K15: 4.31 | L15: 17.57 | M15: 207.05 | N15: -330.11 | O15: -395.81 | Q15: Loss/(gain) on disposal of property, plant and equipment (net) | R15: -1.9378 | S15: 3.0445 | T15: 0 | U15: -1.833 | V15: 1.82 | W15: 0 | Y15: Finance costs | Z15: 98.3 | AA15: 97 | AB15: 95.8 | AC15: 142.8 | AD15: 171.1 | AE15: 282.9 | AG15: Trade receivables, loans and other assets | AH15: -177.95 | AI15: 65.21 | AJ15: =-109.11-3.95 -> -113.06 | AK15: =-289.72-19.28 -> -309 | AL15: =78.32-6.78 -> 71.54 | AM15: =17.17-51.97 -> -34.8 | AO15: Net gain on sale of current investment | AP15: -125.92 | AQ15: -52.79 | AR15: -77.22 | AS15: -122.39 | AT15: -69.22 | AU15: -174.27
A16: Government grants | B16: -0.05 | C16: -0.07 | D16: -0.09 | E16: -0.1 | F16: 0 | G16: 0 | I16: Sundry balances written back | J16: -5.22 | K16: -12.28 | L16: -5.98 | M16: -15.07 | N16: 10.2 | O16: -17.14 | Q16: Loss/(gain) on sale of investment property (net) | R16: -9.0158 | S16: 0 | T16: 3.7434 | U16: -1.6649 | V16: -0.48 | W16: 5.37 | Y16: Equity settled share based payment expense | Z16: -0.5 | AA16: 58.4 | AB16: 59.2 | AC16: 39.7 | AD16: 40.7 | AE16: 42.4 | AG16: Inventories | AH16: -213.07 | AI16: -532.98 | AJ16: 218.88 | AK16: 255.71 | AL16: -49.43 | AM16: -262.18 | AO16: Loss on liquidation of subsidiaries | AP16: 4.66 | AQ16: 3.78 | AR16: 0 | AS16: -25.77 | AT16: -221.96 | AU16: -234.55
A17: Operating Profit before working capital changes | B17: =SUM(B5,B7:B16) -> 1879.47 | C17: =SUM(C5,C7:C16) -> 2855.33 | D17: =SUM(D5,D7:D16) -> 3923.23 | E17: =SUM(E5,E7:E16) -> 2513.57 | F17: =SUM(F5,F7:F16) -> 2244 | G17: =SUM(G5,G7:G16) -> 3031 | I17: Effect of exchange rate changes | J17: 22.77 | K17: 321.52 | L17: -17.2 | M17: 336.81 | N17: =90.59-29.21-249.92 -> -188.54 | O17: =180.83-5.62-336.67 -> -161.46 | Q17: Trade and other receivable balances written off | R17: 0.6122 | S17: 0.5535 | T17: 5.7629 | U17: 4.7077 | V17: 4.69 | W17: 4.35 | Y17: Dividend income | Z17: =15.4+3.6 -> 19 | AA17: 0 | AB17: 0 | AC17: 486.9 | AD17: 356.3 | AE17: 522 | AG17: Trade payables, liabilities and provisions | AH17: 5.19 | AI17: 129.52 | AJ17: =-392.37-65.3 -> -457.67 | AK17: =-58.02+93.11 -> 35.09 | AL17: =413.55-17.58 -> 395.97 | AM17: =-277.73+93.78 -> -183.95 | AO17: Net fair value gain/loss on financial instuments at fair value | AP17: 25.18 | AQ17: -12.08 | AR17: -2.02 | AS17: -20.68 | AT17: -3.49 | AU17: 5.06
A18: Adjustments for: | I18: Operating profit before working capital changes | J18: =SUM(J5,J7:J17) -> 7002.13 | K18: =SUM(K5,K7:K17) -> 4609.09 | L18: =SUM(L5,L7:L17) -> 6816.27 | M18: =SUM(M5,M7:M17) -> 12130.99 | N18: =SUM(N5,N7:N17) -> 12642.29 | O18: =SUM(O5,O7:O17) -> 14872.49 | Q18: Liabilities written back | R18: 0 | S18: -7.7124 | T18: -0.002 | U18: 0 | V18: 0 | W18: -2.76 | Y18: Operating profit before working capital changes | Z18: =SUM(Z5,Z7:Z17) -> 4448.2 | AA18: =SUM(AA5,AA7:AA17) -> 4970.7 | AB18: =SUM(AB5,AB7:AB17) -> 4936.8 | AC18: =SUM(AC5,AC7:AC17) -> 7744.4 | AD18: =SUM(AD5,AD7:AD17) -> 8566.2 | AE18: =SUM(AE5,AE7:AE17) -> 9641 | AG18: Cash generated from operations | AH18: =SUM(AH5,AH7:AH13,AH15:AH17) -> 1676.95 | AI18: =SUM(AI5,AI7:AI13,AI15:AI17) -> 2186.19 | AJ18: =SUM(AJ5,AJ7:AJ13,AJ15:AJ17) -> 2224.01 | AK18: =SUM(AK5,AK7:AK13,AK15:AK17) -> 2766.2 | AL18: =SUM(AL5,AL7:AL13,AL15:AL17) -> 3764.18 | AM18: =SUM(AM5,AM7:AM13,AM15:AM17) -> 3187.93 | AO18: Net gain on sale/disposal of PPE | AP18: -2.62 | AQ18: -3.01 | AR18: -8.68 | AS18: -1.58 | AT18: -0.93 | AU18: 0
A19: Increase/decrease in trade receivables | B19: -206.7 | C19: -265.4 | D19: -741.62 | E19: 650.41 | F19: -361 | G19: -582 | I19: Adjustments for | Q19: Allowance for expected credit loss | R19: 0.7426 | S19: 0.2006 | T19: 4.9157 | U19: 4.639 | V19: 5.95 | W19: 5 | Y19: Adjustments for | AG19: Income tax paid | AH19: -284.04 | AI19: -175.5 | AJ19: -421.02 | AK19: -398.07 | AL19: -498.1 | AM19: -602.82 | AO19: Rent income | AP19: -9.46 | AQ19: -14.77 | AR19: -11.36 | AS19: -7.88 | AT19: -12.97 | AU19: -14.54
