Workbook

Sheet Company Profile
A1: COMPANY PROFILE
A2: Logo | B2: #VALUE! | C2: #VALUE! | D2: #VALUE! | E2: #VALUE! | F2: #VALUE!
A3: Name | B3: Adani Power | C3: Reliance Power | D3: TATA Power | E3: JSW Energy | F3: NTPC
A4: Company Name | B4: #VALUE! | C4: #VALUE! | D4: #VALUE! | E4: #VALUE! | F4: #VALUE!
A5: Ticker Symbol | B5: {=_FV(B4,"Ticker symbol",TRUE)} -> 533096 | C5: {=_FV(C4,"Ticker symbol",TRUE)} -> 532939 | D5: {=_FV(D4,"Ticker symbol",TRUE)} -> 500400 | E5: {=_FV(E4,"Ticker symbol",TRUE)} -> 533148 | F5: {=_FV(F4,"Ticker symbol",TRUE)} -> NTPC
A6: Industry | B6: {=_FV(B4,"Industry")} -> Electrical Utilities & IPPs | C6: {=_FV(C4,"Industry")} -> Electrical Utilities & IPPs | D6: {=_FV(D4,"Industry")} -> Electrical Utilities & IPPs | E6: {=_FV(E4,"Industry")} -> Electrical Utilities & IPPs | F6: {=_FV(F4,"Industry")} -> Electrical Utilities & IPPs
A7: Listed Exchange | B7: {=_FV(B4,"Exchange")} -> Bombay Stock Exchange | C7: {=_FV(C4,"Exchange")} -> Bombay Stock Exchange | D7: {=_FV(D4,"Exchange")} -> Bombay Stock Exchange | E7: {=_FV(E4,"Exchange")} -> Bombay Stock Exchange | F7: {=_FV(F4,"Exchange")} -> National Stock Exchange of India
A8: Year of Corporation | B8: {=_FV(B4,"Year incorporated",TRUE)} -> 1996 | C8: {=_FV(C4,"Year incorporated",TRUE)} -> 1995 | D8: {=_FV(D4,"Year incorporated",TRUE)} -> 1919 | E8: {=_FV(E4,"Year incorporated",TRUE)} -> 1994 | F8: {=_FV(F4,"Year incorporated",TRUE)} -> 1975
A9: Market Capitalization | B9: {=_FV(B4,"Market cap",TRUE)} -> 2921246000000 | C9: {=_FV(C4,"Market cap",TRUE)} -> 162080900000 | D9: {=_FV(D4,"Market cap",TRUE)} -> 1256408000000 | E9: {=_FV(E4,"Market cap",TRUE)} -> 906696900000 | F9: {=_FV(F4,"Market cap",TRUE)} -> 3162083000000
A10: Exchange rate | B10: #VALUE! | C10: #VALUE! | D10: #VALUE! | E10: #VALUE! | F10: #VALUE!
B11: {=_FV(B10,"Price")} -> 0.01127 | C11: {=_FV(C10,"Price")} -> 0.01127 | D11: {=_FV(D10,"Price")} -> 0.01127 | E11: {=_FV(E10,"Price")} -> 0.01127 | F11: {=_FV(F10,"Price")} -> 0.01127
A12: Mcap in USD | B12: =B9*B11 -> 32922442420 | C12: =C9*C11 -> 1826651743 | D12: =D9*D11 -> 14159718160 | E12: =E9*E11 -> 10218474063 | F12: =F9*F11 -> 35636675410
A13: Market Price | B13: {=_FV(B4,"Price")} -> 150.05 | C13: {=_FV(C4,"Price")} -> 41.13 | D13: {=_FV(D4,"Price")} -> 395.95 | E13: {=_FV(E4,"Price")} -> 522.35 | F13: {=_FV(F4,"Price")} -> 325.45
A14: Shares Outstanding | B14: {=_FV(B4,"Shares outstanding",TRUE)} -> 19284700000 | C14: {=_FV(C4,"Shares outstanding",TRUE)} -> 4135771000 | D14: {=_FV(D4,"Shares outstanding",TRUE)} -> 3195340000 | E14: {=_FV(E4,"Shares outstanding",TRUE)} -> 1746503000 | F14: {=_FV(F4,"Shares outstanding",TRUE)} -> 9696666000
B15: =B14/10000000 -> 1928.47 | C15: =C14/10000000 -> 413.5771 | D15: =D14/10000000 -> 319.534 | E15: =E14/10000000 -> 174.6503 | F15: =F14/10000000 -> 969.6666
A16: Daily change | B16: {=_FV(B4,"Change (%)",TRUE)} -> -0.009571 | C16: {=_FV(C4,"Change (%)",TRUE)} -> 0.048165 | D16: {=_FV(D4,"Change (%)",TRUE)} -> 0.006482 | E16: {=_FV(E4,"Change (%)",TRUE)} -> 0.005002 | F16: {=_FV(F4,"Change (%)",TRUE)} -> -0.001993
A17: Beta | B17: {=_FV(B4,"Beta")} -> 1.1437 | C17: {=_FV(C4,"Beta")} -> 2.5566 | D17: {=_FV(D4,"Beta")} -> 1.4704 | E17: {=_FV(E4,"Beta")} -> 1.2627 | F17: {=_FV(F4,"Beta")} -> 1.101
A18: 52 Week Low | B18: {=_FV(B4,"52 week low",TRUE)} -> 86.17 | C18: {=_FV(C4,"52 week low",TRUE)} -> 31.3 | D18: {=_FV(D4,"52 week low",TRUE)} -> 326.25 | E18: {=_FV(E4,"52 week low",TRUE)} -> 419.1 | F18: {=_FV(F4,"52 week low",TRUE)} -> 292.8
A19: 52 Week High | B19: {=_FV(B4,"52 week high",TRUE)} -> 182.75 | C19: {=_FV(C4,"52 week high",TRUE)} -> 76.49 | D19: {=_FV(D4,"52 week high",TRUE)} -> 454.8 | E19: {=_FV(E4,"52 week high",TRUE)} -> 776.35 | F19: {=_FV(F4,"52 week high",TRUE)} -> 414.3

Sheet Balance Sheet
A1: Balance Sheet (ADANI POWER) | F1: #VALUE! | H1: Balance Sheet (Reliance Power) | M1: #VALUE! | O1: Balance Sheet (TATA Power) | T1: #VALUE! | V1: Balance Sheet (JSW Energy) | AA1: #VALUE! | AC1: Balance Sheet (NTPC) | AH1: #VALUE!
A2: Particulars | B2: Mar 20 | C2: Mar 21 | D2: Mar 22 | E2: Mar 23 | F2: Mar 24 | H2: Particulars | I2: Mar 20 | J2: Mar 21 | K2: Mar 22 | L2: Mar 23 | M2: Mar 24 | O2: Particulars | P2: Mar 20 | Q2: Mar 21 | R2: Mar 22 | S2: Mar 23 | T2: Mar 24 | V2: Particulars | W2: Mar 20 | X2: Mar 21 | Y2: Mar 22 | Z2: Mar 23 | AA2: Mar 24 | AC2: Particulars | AD2: Mar 20 | AE2: Mar 21 | AF2: Mar 22 | AG2: Mar 23 | AH2: Mar 24
A3: ASSETS | H3: ASSETS | O3: ASSETS | V3: Property, Plant and equipment | W3: 15217.11 | X3: 14166.26 | Y3: 13422.82 | Z3: 23065.01 | AA3: 26088.16 | AC3: ASSETS
A4: Non-Current Assets | H4: Non current assets | O4: Non current assets | V4: Capital work in progress | W4: 391.32 | X4: 472.77 | Y4: 2090.6 | Z4: 4779.5 | AA4: 10282.3 | AC4: Non-current assets
A5: Property, Plant and Equipment | B5: 55571.1 | C5: 52575.24 | D5: 53071.62 | E5: 50543.8 | F5: 62812.71 | H5: Property, plant and equipments | I5: 38526 | J5: 37144.68 | K5: 36263.94 | L5: 35733.76 | M5: 33543.18 | O5: Property, plant and equipment | P5: 44662.61 | Q5: 48748.86 | R5: 50502.96 | S5: 54524.96 | T5: 59624.06 | V5: Goodwill | W5: 639.82 | X5: 639.82 | Y5: 639.82 | Z5: 639.82 | AA5: 639.82 | AC5: Property, plant and equipment | AD5: 187176.46 | AE5: 202598.05 | AF5: 224343.75 | AG5: 239882.5 | AH5: 258423.86
A6: Capital work in progress | B6: 2346.77 | C6: 6439.42 | D6: 10269.74 | E6: 12879.54 | F6: 925.12 | H6: Capital work in progress | I6: 3614.79 | J6: 1911.68 | K6: 2019.95 | L6: 2319.59 | M6: 1293.41 | O6: Capital work in progress | P6: 1611.52 | Q6: 3599.8 | R6: 4635.1 | S6: 5376.36 | T6: 11561.31 | V6: Other intangible assets | W6: 855.82 | X6: 830.68 | Y6: 768 | Z6: 1315.66 | AA6: 2218.22 | AC6: Capital work in progress | AD6: 98210.94 | AE6: 97404.16 | AF6: 91025.21 | AG6: 89133.12 | AH6: 87592.8
A7: Investment Property | B7: 0 | C7: 0 | D7: 0 | E7: 704.94 | F7: 0 | H7: Goodwill on consolidation | I7: 14.11 | J7: 14.11 | K7: 14.11 | L7: 14.11 | M7: 14.11 | O7: Goodwill | P7: 1641.57 | Q7: 1794.57 | R7: 1858.31 | S7: 1858.31 | T7: 1757.46 | V7: Intangible assets under development | W7: 0 | X7: 0 | Y7: 0 | Z7: 8.69 | AA7: 2.79 | AC7: Intangible assets | AD7: 626.33 | AE7: 647.13 | AF7: 579.27 | AG7: 541.92 | AH7: 509.77
A8: Goodwill | B8: 190.61 | C8: 190.61 | D8: 190.61 | E8: 190.61 | F8: 190.61 | H8: Other intangible assets | I8: 33.49 | J8: 31.64 | K8: 29.8 | L8: 28.16 | M8: 26.33 | O8: Other intangible assets | P8: 1362.18 | Q8: 1345.85 | R8: =1366.18+3661.99 -> 5028.17 | S8: =3982.05+1381.34 -> 5363.39 | T8: =4368.75+1459.29 -> 5828.04 | V8: Investment in an associate and a joint venture | W8: 10.53 | X8: 27.68 | Y8: 36.22 | Z8: 55.51 | AA8: 72.02 | AC8: Intangible assets under development | AD8: 297.53 | AE8: 101.87 | AF8: 101.05 | AG8: 45.88 | AH8: 71.65
A9: Intangible Assets | B9: 84.1 | C9: 85.45 | D9: 11.98 | E9: 12.03 | F9: 12.53 | H9: Financial Assets | O9: Investments accounted for using equity method | P9: 13202.65 | Q9: 11920.63 | R9: 12580 | S9: 14218.88 | T9: 12983.51 | V9: Financial Assets | AC9: Investments accounted for using the equity method | AD9: 9256.31 | AE9: 9992.18 | AF9: 10522.14 | AG9: 13252.09 | AH9: 15130.96
A10: Financial Assets | H10: Investments | I10: 0.23 | J10: 4.29 | K10: 4.43 | L10: 4.43 | M10: 172.77 | O10: Financial assets | V10: Investments | W10: 1098.96 | X10: 3340.24 | Y10: 5194.6 | Z10: 4906.11 | AA10: 5873.76 | AC10: Financial assets
A11: Investments | B11: 0.01 | C11: 0.01 | D11: 0.01 | E11: 42.51 | F11: 0.01 | H11: Loans | I11: 407.86 | J11: 395.18 | K11: 400.88 | L11: 434.77 | M11: 0 | O11: Other investments | P11: 632.68 | Q11: 728.88 | R11: 1169.81 | S11: 1301.21 | T11: 1854.59 | V11: Trade receivables | W11: 0 | X11: 5.34 | Y11: 99.46 | Z11: 99.46 | AA11: 176.26 | AC11: Investments | AD11: 50.28 | AE11: 97.08 | AF11: 104.1 | AG11: 632.7 | AH11: 703.6
A12: Loans | B12: 0 | C12: 0 | D12: 0 | E12: 0 | F12: 0 | H12: Financial lease receivables | I12: 4240.85 | J12: 3944.79 | K12: 3648.26 | L12: 3381.53 | M12: 3307.93 | O12: Trade receivables | P12: 30.28 | Q12: 604.71 | R12: 685.78 | S12: 359.63 | T12: 273.29 | V12: Loans | W12: 664.96 | X12: 569.09 | Y12: 567.64 | Z12: 567.64 | AA12: 567.64 | AC12: Loans | AD12: 511.08 | AE12: 554.97 | AF12: 559.81 | AG12: 553.77 | AH12: 570.19
A13: Other Financial Assets | B13: 427.91 | C13: 245.44 | D13: 856.04 | E13: 779.71 | F13: 636.2 | H13: Other Financial assets | I13: 97.52 | J13: 81.3 | K13: 71.74 | L13: 46.96 | M13: 42.33 | O13: Loans | P13: 80.88 | Q13: 58.14 | R13: 3.45 | S13: 2.99 | T13: 2.48 | V13: Other Financial assets | W13: 1195.22 | X13: 1262.84 | Y13: 1312.97 | Z13: 2092.07 | AA13: 2139.16 | AC13: Trade receivables | AD13: 0 | AE13: 0 | AF13: 0 | AG13: 2638.68 | AH13: 1287.54
A14: Deferred tax assets (Net) | B14: 0 | C14: 0 | D14: 0 | E14: 0 | F14: 376.34 | H14: Non current tax assets | I14: 59.79 | J14: 51.83 | K14: 67.51 | L14: 78.46 | M14: 92.87 | O14: Financial lease receivables | P14: 588.92 | Q14: 598.61 | R14: 588.69 | S14: 567.22 | T14: 561.66 | V14: Income tax assets (net) | W14: 123.85 | X14: 112.27 | Y14: 130.26 | Z14: 192.55 | AA14: 216.49 | AC14: Other finance assets | AD14: 1206.32 | AE14: 1092.84 | AF14: 1017.98 | AG14: 900.7 | AH14: 710.8
A15: Other Non-current Assets | B15: 1811.32 | C15: 1627.39 | D15: 1352.95 | E15: 1115.13 | F15: 1784.67 | H15: Other non current assets | I15: 1493.85 | J15: 1480.06 | K15: 1481.29 | L15: 1469.8 | M15: 520.06 | O15: Other financial assets | P15: 578.79 | Q15: 1577.04 | R15: 1684.53 | S15: 1726.66 | T15: 2084.5 | V15: Deferred tax assets (net) | W15: 180.54 | X15: 229.76 | Y15: 418.2 | Z15: 324.44 | AA15: 502.25 | AC15: Deferred tax assets (net) | AD15: 1096.6 | AE15: 1075.89 | AF15: 995.7 | AG15: 937.85 | AH15: 1169.9
A16: Total Non-current Assets | B16: =SUM(B5:B9,B11:B15) -> 60431.82 | C16: =SUM(C5:C9,C11:C15) -> 61163.56 | D16: =SUM(D5:D9,D11:D15) -> 65752.95 | E16: =SUM(E5:E9,E11:E15) -> 66268.27 | F16: =SUM(F5:F9,F11:F15) -> 66738.19 | H16: Total non current assets | I16: =SUM(I5:I8,I10:I15) -> 48488.49 | J16: =SUM(J5:J8,J10:J15) -> 45059.56 | K16: =SUM(K5:K8,K10:K15) -> 44001.91 | L16: =SUM(L5:L8,L10:L15) -> 43511.57 | M16: =SUM(M5:M8,M10:M15) -> 39012.99 | O16: Non current tax assets (net) | P16: 342 | Q16: 328.35 | R16: 520.54 | S16: 739.07 | T16: 585.89 | V16: Other non-current assets | W16: 186.08 | X16: 315.5 | Y16: 1051.45 | Z16: 1071.13 | AA16: 825.45 | AC16: Other non-current assets | AD16: 14092.61 | AE16: 17031.51 | AF16: 15877.02 | AG16: 16333.91 | AH16: 16016.17
A17: Current Assets | H17: Current assets | O17: Deferred tax assets (net) | P17: 74.24 | Q17: 184.02 | R17: 334.6 | S17: 252.9 | T17: 499.09 | V17: Total non-current assets | W17: =SUM(W3:W8,W10:W16) -> 20564.21 | X17: =SUM(X3:X8,X10:X16) -> 21972.25 | Y17: =SUM(Y3:Y8,Y10:Y16) -> 25732.04 | Z17: =SUM(Z3:Z8,Z10:Z16) -> 39117.59 | AA17: =SUM(AA3:AA8,AA10:AA16) -> 49604.32 | AC17: Total non current assets | AD17: =SUM(AD5:AD9,AD11:AD16) -> 312524.46 | AE17: =SUM(AE5:AE9,AE11:AE16) -> 330595.68 | AF17: =SUM(AF5:AF9,AF11:AF16) -> 345126.03 | AG17: =SUM(AG5:AG9,AG11:AG16) -> 364853.12 | AH17: =SUM(AH5:AH9,AH11:AH16) -> 382187.24
A18: Inventories | B18: 2522.77 | C18: 2025.11 | D18: 2258.27 | E18: 3075.2 | F18: 4142.1 | H18: Inventories | I18: 1014.18 | J18: 874.12 | K18: 828.04 | L18: 925.32 | M18: 961.17 | O18: Other non current assets | P18: 1185.12 | Q18: 1465.06 | R18: 1849.82 | S18: 2532.46 | T18: 5173.57 | V18: Current Assets | AC18: Current assets
A19: Financial Assets | H19: Financial assets | O19: Total non current assets | P19: =SUM(P5:P9,P11:P18) -> 65993.44 | Q19: =SUM(Q5:Q9,Q11:Q18) -> 72954.52 | R19: =SUM(R5:R9,R11:R18) -> 81441.76 | S19: =SUM(S5:S9,S11:S18) -> 88824.04 | T19: =SUM(T5:T9,T11:T18) -> 102789.45 | V19: Inventories | W19: 639.58 | X19: 395.08 | Y19: 901.02 | Z19: 987.08 | AA19: 830.67 | AC19: Inventories | AD19: 11138.54 | AE19: 9809.6 | AF19: 10139.29 | AG19: 14240.37 | AH19: 18019.12
A20: Investments | B20: 2.79 | C20: 20.09 | D20: 183.24 | E20: 611.54 | F20: 373.5 | H20: Investments | I20: 30.21 | J20: 31.28 | K20: 32.32 | L20: 34.12 | M20: 36.58 | O20: Current Assets | V20: Financial Assets | AC20: Financial assets
A21: Trade Receivables | B21: 8366.47 | C21: 11839.28 | D21: 9560.92 | E21: 11529.36 | F21: 11677.48 | H21: Trade receivables | I21: 2364.52 | J21: 2409.88 | K21: 3213.5 | L21: 2679.9 | M21: 1650.41 | O21: Inventories | P21: 1752.35 | Q21: 1884.8 | R21: 4231.52 | S21: 3942.88 | T21: 4419.63 | V21: Investments | W21: 744.07 | X21: 684.23 | Y21: 1392.35 | Z21: 1071.15 | AA21: 1089.08 | AC21: Investments | AD21: 0 | AE21: 499.99 | AF21: 0 | AG21: 50 | AH21: 50
A22: Cash and Cash equivalents | B22: 941.1 | C22: 113.04 | D22: 782.37 | E22: 349.23 | F22: 1136.25 | H22: Cash and cash equivalents | I22: 124.94 | J22: 144.2 | K22: 164.88 | L22: 238.65 | M22: 486.15 | O22: Financial assets | V22: Trade receivables | W22: 1565.2 | X22: 964.46 | Y22: 670.22 | Z22: 1531.92 | AA22: 844.2 | AC22: Trade receivables | AD22: 20314.59 | AE22: 17718.07 | AF22: 27970.87 | AG22: 28825.22 | AH22: 33349.68
A23: Bank balance other than Cash equivalents | B23: 1038.21 | C23: 1494.28 | D23: 1582.31 | E23: 1524.42 | F23: 6075.51 | H23: Bank balances other than cash and cash equivalents | I23: 159.49 | J23: 171.01 | K23: 480.48 | L23: 412.51 | M23: 431.45 | O23: Investments | P23: 699.51 | Q23: 499.54 | R23: 410.52 | S23: 1149.6 | T23: 1477.89 | V23: Unbilled revenue | W23: 543.81 | X23: 336.78 | Y23: 544.43 | Z23: 776.03 | AA23: 859.34 | AC23: Cash and cash equivalents | AD23: 589.52 | AE23: 950.02 | AF23: 675.77 | AG23: 465.65 | AH23: 863.34
A24: Loans | B24: 3.05 | C24: 8.83 | D24: 7.62 | E24: 3.19 | F24: 3.49 | H24: Loans | I24: 139.1 | J24: 154.89 | K24: 191.59 | L24: 166.28 | M24: 483.26 | O24: Trade receivables | P24: 4425.9 | Q24: 5000.97 | R24: 5979.74 | S24: 6952.15 | T24: 7401.69 | V24: Cash and cash equivalents | W24: 151.69 | X24: 366.84 | Y24: 585.15 | Z24: 3422.29 | AA24: 3091.74 | AC24: Bank Balances other than cash | AD24: 2624.77 | AE24: 3437.78 | AF24: 3782.31 | AG24: 4482.88 | AH24: 5984
A25: Other Financial Assets | B25: 767.65 | C25: 325.12 | D25: 308.28 | E25: 557.5 | F25: 435.82 | H25: Finance lease receivables | I25: 298.76 | J25: 297.66 | K25: 296.53 | L25: 266.72 | M25: 169.16 | O25: Unbilled revenue | P25: 799.42 | Q25: 1573.64 | R25: 2285.57 | S25: 2456.71 | T25: 2552.23 | V25: Bank balances other than cash above | W25: 49.04 | X25: 112.34 | Y25: 548.95 | Z25: 591.59 | AA25: 1114.86 | AC25: Loans | AD25: 252.67 | AE25: 259.13 | AF25: 270.37 | AG25: 268.78 | AH25: 271.12
A26: Other Current assets | B26: 951.14 | C26: 1023.08 | D26: 1545.06 | E26: 1902.56 | F26: 1742.43 | H26: Other financial assets | I26: 665.39 | J26: 565.67 | K26: =419.76+1.02 -> 420.78 | L26: =112.57+1.05 -> 113.62 | M26: =90.06+1.36 -> 91.42 | O26: Cash and cash equivalents | P26: 1861.5 | Q26: 3782.51 | R26: 3077.24 | S26: 4189.76 | T26: 3324.34 | V26: Loans | W26: 250.84 | X26: 1130.84 | Y26: 150.9 | Z26: 180.9 | AA26: 110.9 | AC26: Other finance assets | AD26: =13081.12+8501.08 -> 21582.2 | AE26: =14991.26+9086.7 -> 24077.96 | AF26: =5826.14+9525.32 -> 15351.46 | AG26: =8912.07+11160.27 -> 20072.34 | AH26: =13212.71+11238.78 -> 24451.49
A27: Total Current Assets | B27: =SUM(B18,B20:B26) -> 14593.18 | C27: =SUM(C18,C20:C26) -> 16848.83 | D27: =SUM(D18,D20:D26) -> 16228.07 | E27: =SUM(E18,E20:E26) -> 19553 | F27: =SUM(F18,F20:F26) -> 25586.58 | H27: Other current assets | I27: 57.3 | J27: 218.56 | K27: 109.19 | L27: 114.29 | M27: 229.52 | O27: Bank balance other cash | P27: 232.68 | Q27: 2330.17 | R27: 3563.46 | S27: 7016.77 | T27: 5827.57 | V27: Other Financial assets | W27: =484.36+119.06 -> 603.42 | X27: =254.19+104.99 -> 359.18 | Y27: =252.78+154.61 -> 407.39 | Z27: =675.91+285.6 -> 961.51 | AA27: =194.52+529.47 -> 723.99 | AC27: Current tax assets (net) | AD27: 60.96 | AE27: 64.7 | AF27: 62.64 | AG27: 93.51 | AH27: 46.78
A28: Assets classified as held for sale | B28: 0 | C28: 793.52 | D28: 0 | E28: 0 | H28: Total current assets | I28: =SUM(I18,I20:I27) -> 4853.89 | J28: =SUM(J18,J20:J27) -> 4867.27 | K28: =SUM(K18,K20:K27) -> 5737.31 | L28: =SUM(L18,L20:L27) -> 4951.41 | M28: =SUM(M18,M20:M27) -> 4539.12 | O28: Loans | P28: 33 | Q28: 30.71 | R28: 9.34 | S28: 11.55 | T28: 11.14 | V28: Total Current assets | W28: =SUM(W19,W21:W27) -> 4547.65 | X28: =SUM(X19,X21:X27) -> 4349.75 | Y28: =SUM(Y19,Y21:Y27) -> 5200.41 | Z28: =SUM(Z19,Z21:Z27) -> 9522.47 | AA28: =SUM(AA19,AA21:AA27) -> 8664.78 | AC28: Total current assets | AD28: =SUM(AD19,AD21:AD27) -> 56563.25 | AE28: =SUM(AE19,AE21:AE27) -> 56817.25 | AF28: =SUM(AF19,AF21:AF27) -> 58252.71 | AG28: =SUM(AG19,AG21:AG27) -> 68498.75 | AH28: =SUM(AH19,AH21:AH27) -> 83035.53
A29: Total Assets | B29: =B16+B27 -> 75025 | C29: =C16+C27+C28 -> 78805.91 | D29: =D16+D27 -> 81981.02 | E29: =E16+E27 -> 85821.27 | F29: =F16+F27 -> 92324.77 | H29: Assets classified held for sale | I29: 0.52 | J29: 855 | K29: 72.44 | L29: 72.44 | M29: 208.15 | O29: Financial lease receivables | P29: 33.2 | Q29: 41.45 | R29: 46.91 | S29: 54.5 | T29: 65.92 | V29: Assets classified as held for sale | W29: 0 | X29: 114.33 | Y29: 0 | Z29: 101.64 | AA29: 0 | AC29: Assets held for sale | AD29: 0 | AE29: 0 | AF29: 18.5 | AG29: 120.92 | AH29: 117.77
A30: EQUITY AND LIABILITIES | H30: Total assets | I30: =I16+I28+I29 -> 53342.9 | J30: =J16+J28+J29 -> 50781.83 | K30: =K16+K28+K29 -> 49811.66 | L30: =L16+L28+L29 -> 48535.42 | M30: =M16+M28+M29 -> 43760.26 | O30: Other financial assets | P30: 1412.43 | Q30: 310.15 | R30: 501.45 | S30: 688.3 | T30: 471.48 | V30: Total assets | W30: =W17+W28+W29 -> 25111.86 | X30: =X17+X28+X29 -> 26436.33 | Y30: =Y17+Y28+Y29 -> 30932.45 | Z30: =Z17+Z28+Z29 -> 48741.7 | AA30: =AA17+AA28+AA29 -> 58269.1 | AC30: Regulatory deferral a/c debit balances | AD30: 9397.73 | AE30: 11553.28 | AF30: 13199.17 | AG30: 12548.66 | AH30: 14856.03
A31: EQUITY | H31: EQUITY AND LIABILITIES | O31: Current tax assets (net) | P31: 1.1 | Q31: 0.45 | R31: 0.01 | S31: 0.69 | T31: 8.2 | V31: EQUITY AND LIABILITIES | AC31: Total Assets | AD31: =AD17+AD28+AD29+AD30 -> 378485.44 | AE31: =AE17+AE28+AE29+AE30 -> 398966.21 | AF31: =AF17+AF28+AF29+AF30 -> 416596.41 | AG31: =AG17+AG28+AG29+AG30 -> 446021.45 | AH31: =AH17+AH28+AH29+AH30 -> 480196.57
A32: Equity share capital | B32: 3856.94 | C32: 3856.94 | D32: 3856.94 | E32: 3856.94 | F32: 3856.94 | H32: Equity | O32: Other current assets | P32: 770.39 | Q32: 916.69 | R32: 1479.67 | S32: 1328.72 | T32: 1704.3 | V32: Equity | AC32: EQUITY AND LIABILITIES
A33: Unsecured perpetual securities | B33: 8615 | C33: 12615 | D33: 13215 | E33: 13215 | F33: 7315 | H33: Equity share capital | I33: 2805.13 | J33: 2805.13 | K33: 3400.13 | L33: 3735.21 | M33: 4016.98 | O33: Total current assets | P33: =SUM(P21,P23:P32) -> 12021.48 | Q33: =SUM(Q21,Q23:Q32) -> 16371.08 | R33: =SUM(R21,R23:R32) -> 21585.43 | S33: =SUM(S21,S23:S32) -> 27791.63 | T33: =SUM(T21,T23:T32) -> 27264.39 | V33: Equity share capital | W33: 1641.9 | X33: 1642.33 | Y33: 1639.67 | Z33: 1640.54 | AA33: 1641.22 | AC33: Equity
A34: Other equity | B34: -5991.5 | C34: -3359.35 | D34: 1631.5 | E34: 12803.72 | F34: 31973.09 | H34: Other Equity | I34: 9063.74 | J34: 9440.71 | K34: =182.5+8879.9 -> 9062.4 | L34: =80+7780.17 -> 7860.17 | M34: 7596.88 | O34: Assets classified as held for sale | P34: 6253.06 | Q34: 3047.46 | R34: 3046.83 | S34: 3299.94 | T34: 1200.99 | V34: Other equity | W34: 10003.72 | X34: 12864.67 | Y34: 15775.23 | Z34: 16988.27 | AA34: 19190.52 | AC34: Equity share capital | AD34: 9894.56 | AE34: 9696.67 | AF34: 9696.67 | AG34: 9696.67 | AH34: 9696.67
A35: Equity attributed to equity holders of the parent | B35: =SUM(B32:B34) -> 6480.44 | C35: =SUM(C32:C34) -> 13112.59 | D35: =SUM(D32:D34) -> 18703.44 | E35: =SUM(E32:E34) -> 29875.66 | F35: =SUM(F32:F34) -> 43145.03 | H35: Equity attributable to the owners of the company | I35: =I33+I34 -> 11868.87 | J35: =J33+J34 -> 12245.84 | K35: =K33+K34 -> 12462.53 | L35: =L33+L34 -> 11595.38 | M35: =M33+M34 -> 11613.86 | O35: Total Assets before regulatory deferred a/c | P35: =P19+P33+P34 -> 84267.98 | Q35: =Q19+Q33+Q34 -> 92373.06 | R35: =R19+R33+R34 -> 106074.02 | S35: =S19+S33+S34 -> 119915.61 | T35: =T19+T33+T34 -> 131254.83 | V35: Equity attributable to owners of the parent | W35: =W33+W34 -> 11645.62 | X35: =X33+X34 -> 14507 | Y35: =Y33+Y34 -> 17414.9 | Z35: =Z33+Z34 -> 18628.81 | AA35: =AA33+AA34 -> 20831.74 | AC35: Other equity | AD35: 108944.6 | AE35: 116041.8 | AF35: 125677.07 | AG35: 137326.5 | AH35: 151012.6
A36: Non-Controlling interests | B36: 0.01 | C36: 0.01 | D36: 0 | E36: 0 | F36: 0 | H36: Non controlling interests | I36: 1352.79 | J36: 1568.01 | K36: 1621.57 | L36: 1691.75 | M36: 0 | O36: Regulatory deferred a/c- Assets | P36: 5480.17 | Q36: 6478.17 | R36: 6810.57 | S36: 8433.43 | T36: 8298.66 | V36: Non-controlling interests | W36: -23.84 | X36: -8.72 | Y36: 2.06 | Z36: 105.37 | AA36: 182.5 | AC36: Total equity attributable to owners of the company | AD36: =AD34+AD35 -> 118839.16 | AE36: =AE34+AE35 -> 125738.47 | AF36: =AF34+AF35 -> 135373.74 | AG36: =AG34+AG35 -> 147023.17 | AH36: =AH34+AH35 -> 160709.27
A37: Total Equity | B37: =B35+B36 -> 6480.45 | C37: =C35+C36 -> 13112.6 | D37: =D35+D36 -> 18703.44 | E37: =E35+E36 -> 29875.66 | F37: =F35+F36 -> 43145.03 | H37: Total equity | I37: =I35+I36 -> 13221.66 | J37: =J35+J36 -> 13813.85 | K37: =K35+K36 -> 14084.1 | L37: =L35+L36 -> 13287.13 | M37: =M35+M36 -> 11613.86 | O37: Total Assets | P37: =P35+P36 -> 89748.15 | Q37: =Q35+Q36 -> 98851.23 | R37: =R35+R36 -> 112884.59 | S37: =S35+S36 -> 128349.04 | T37: =T35+T36 -> 139553.49 | V37: Total equity | W37: =W35+W36 -> 11621.78 | X37: =X35+X36 -> 14498.28 | Y37: =Y35+Y36 -> 17416.96 | Z37: =Z35+Z36 -> 18734.18 | AA37: =AA35+AA36 -> 21014.24 | AC37: Non-controlling interests | AD37: 3317.19 | AE37: 3523.71 | AF37: 3760.41 | AG37: 3930.45 | AH37: 4413.01
A38: LIABILITIES | H38: Liabilities | O38: EQUITY AND LIABILITIES | V38: Liabilities | AC38: Total equity | AD38: =AD36+AD37 -> 122156.35 | AE38: =AE36+AE37 -> 129262.18 | AF38: =AF36+AF37 -> 139134.15 | AG38: =AG36+AG37 -> 150953.62 | AH38: =AH36+AH37 -> 165122.28
A39: Non current Liabilities | H39: Non current liabilities | O39: EQUITY | V39: Non Current liabilities | AC39: Liabilities
A40: Financial Liabilities | H40: Financial liabilities | O40: Equity share capital | P40: 270.5 | Q40: 319.56 | R40: 319.56 | S40: 319.56 | T40: 319.56 | V40: Financial liabilities | AC40: Non-current Liabilities
A41: Borrowings | B41: 44566.34 | C41: 39957 | D41: 37871.32 | E41: 33702.6 | F41: 26595.01 | H41: Borrowings | I41: 19860.56 | J41: 16831.49 | K41: 14205.21 | L41: 12240.36 | M41: 9409.48 | O41: Unsecured perpetual securities | P41: 1500 | Q41: 1500 | R41: 0 | S41: 0 | T41: 0 | V41: Long term borrowings | W41: 8280.74 | X41: 6972.41 | Y41: 6876.37 | Z41: 19207.9 | AA41: 27731.2 | AC41: Financial liabilities
A42: Lease Liabilities | B42: 0 | C42: 99.57 | D42: 94.36 | E42: 88.32 | F42: 143.11 | H42: Other financial liabilities | I42: 146.28 | J42: 180.17 | K42: 310.77 | L42: 670.15 | M42: 735.42 | O42: Other equity | P42: 17795.52 | Q42: 20502.7 | R42: 22122 | S42: 28467.87 | T42: 32035.73 | V42: Lease liabilities | W42: 0 | X42: 0 | Y42: 45.29 | Z42: 221.47 | AA42: 231.72 | AC42: Long term borrowings | AD42: 176020.02 | AE42: 181271.91 | AF42: 181871.19 | AG42: 187883.57 | AH42: 190214.97
A43: Other Financial liabilities | B43: 339.21 | C43: 703.08 | D43: 960.37 | E43: 0 | F43: 1.07 | H43: Long term provisions | I43: 51.16 | J43: 48.97 | K43: 54.12 | L43: 76.69 | M43: 83.56 | O43: Equity attributable to shareholders of the company | P43: =P40+P41+P42 -> 19566.02 | Q43: =Q40+Q41+Q42 -> 22322.26 | R43: =R40+R41+R42 -> 22441.56 | S43: =S40+S41+S42 -> 28787.43 | T43: =T40+T41+T42 -> 32355.29 | V43: Other financial liabilities | W43: 195.02 | X43: 453.43 | Y43: 73.45 | Z43: 101.82 | AA43: 62.25 | AC43: Lease liabilities | AD43: =10.35+57.75 -> 68.1 | AE43: =13.78+66.35 -> 80.13 | AF43: =962.69+13.45+71.19 -> 1047.33 | AG43: =1604.04+7.66+78.86 -> 1690.56 | AH43: 1837.83
A44: Provisions | B44: 88.43 | C44: 86.95 | D44: 220.87 | E44: 226.95 | F44: 237.45 | H44: Deferred tax liabilities (net) | I44: 2276.85 | J44: 2205.45 | K44: 2217.51 | L44: 2234.68 | M44: 2430.58 | O44: Non controlling interests | P44: 2332.04 | Q44: 2927.3 | R44: 3586.9 | S44: 5416.69 | T44: 5977.48 | V44: Long term provisions | W44: 82.39 | X44: 99.29 | Y44: 111.56 | Z44: 62.41 | AA44: 113.89 | AC44: Other financial liabilities | AD44: 1404.45 | AE44: 2089.14 | AF44: 1059.86 | AG44: 788.41 | AH44: 540.32
A45: Deferred Tax liabilities (Net) | B45: 266.07 | C45: 1328.08 | D45: 2499.78 | E45: 0 | F45: 315.8 | H45: Other non current liabilities | I45: 1832.78 | J45: 1773.7 | K45: 1714.66 | L45: 1652.6 | M45: 1593.17 | O45: Total equity | P45: =P43+P44 -> 21898.06 | Q45: =Q43+Q44 -> 25249.56 | R45: =R43+R44 -> 26028.46 | S45: =S43+S44 -> 34204.12 | T45: =T43+T44 -> 38332.77 | V45: Deferred tax liabilities (net) | W45: 370.48 | X45: 608.13 | Y45: 892.26 | Z45: 1078.41 | AA45: 1338.97 | AC45: Long term provisions | AD45: 1085.02 | AE45: 1042.39 | AF45: 1655.35 | AG45: 1917.89 | AH45: 2084.03
A46: Other Non-current liabilities | B46: 5095.35 | C46: 4791.28 | D46: 4487.21 | E46: 4183.15 | F46: 6098.63 | H46: Total non current liabilities | I46: =SUM(I41:I45) -> 24167.63 | J46: =SUM(J41:J45) -> 21039.78 | K46: =SUM(K41:K45) -> 18502.27 | L46: =SUM(L41:L45) -> 16874.48 | M46: =SUM(M41:M45) -> 14252.21 | O46: LIABILITIES | V46: Other non current liabilities | W46: 186.45 | X46: 235.52 | Y46: 423.81 | Z46: 329.89 | AA46: 507.39 | AC46: Deferred tax liabilities (net) | AD46: 8715.42 | AE46: 9887.82 | AF46: 10951.67 | AG46: 12690 | AH46: 15231.83
A47: Total Non-current liabilities | B47: =SUM(B41:B46) -> 50355.4 | C47: =SUM(C41:C46) -> 46965.96 | D47: =SUM(D41:D46) -> 46133.91 | E47: =SUM(E41:E46) -> 38201.02 | F47: =SUM(F41:F46) -> 33391.07 | H47: Current Liabilities | O47: Non current liabilities | V47: Total non current liabilities | W47: =SUM(W41:W46) -> 9115.08 | X47: =SUM(X41:X46) -> 8368.78 | Y47: =SUM(Y41:Y46) -> 8422.74 | Z47: =SUM(Z41:Z46) -> 21001.9 | AA47: =SUM(AA41:AA46) -> 29985.42 | AC47: Other non current liabilities | AD47: 1551.13 | AE47: 1996.47 | AF47: 1926.65 | AG47: 2611.95 | AH47: 2810.14
A48: Current Liabilities | H48: Financial liabilities | O48: Financial liabilities | V48: Current Liabilities | AC48: Total non current liabilities | AD48: =SUM(AD42:AD47) -> 188844.14 | AE48: =SUM(AE42:AE47) -> 196367.86 | AF48: =SUM(AF42:AF47) -> 198512.05 | AG48: =SUM(AG42:AG47) -> 207582.38 | AH48: =SUM(AH42:AH47) -> 212719.12
A49: Financial Liabilities | H49: Short term borrowings | I49: 4353.33 | J49: 3793.32 | K49: 8908.84 | L49: 8995.67 | M49: 9356.35 | O49: Long term borrowings | P49: 32695.14 | Q49: 30045.03 | R49: 32729.7 | S49: 30708.49 | T49: 37392.25 | V49: Financial liabilities | AC49: Current Liabilities
A50: Borrowings | B50: 7801.81 | C50: 12454.27 | D50: 10924.36 | E50: 8549.45 | F50: 7861.85 | H50: Trade payables | I50: =25.65+408.72 -> 434.37 | J50: =41.85+373.37 -> 415.22 | K50: =32.86+465.72 -> 498.58 | L50: =47.56+471.63 -> 519.19 | M50: =39.96+409.41 -> 449.37 | O50: Lease liabilities | P50: 3180.48 | Q50: 3142.48 | R50: 3207.79 | S50: 3510.7 | T50: 3742.48 | V50: Short term borrowings | W50: 0 | X50: 289.97 | Y50: 2016.17 | Z50: 5609.32 | AA50: 3595.41 | AC50: Financial liabilities
A51: Lease Liabilities | B51: 0 | C51: 7.84 | D51: 8.39 | E51: 9.16 | F51: 15.59 | H51: Other financial liabilities | I51: 10222.57 | J51: 10735.23 | K51: 6811.79 | L51: 7604.11 | M51: 6431.79 | O51: Trade payables | P51: 0 | Q51: 17.36 | R51: 0 | S51: 0 | T51: 0 | V51: Lease liabilities | Y51: 4.74 | Z51: 12.38 | AA51: 14.64 | AC51: Short term borrowings | AD51: 16556.23 | AE51: 15964.62 | AF51: 27684.07 | AG51: 31921.61 | AH51: 44825.33
A52: Trade Payables | B52: =28.21+5567.84 -> 5596.05 | C52: =41.48+3761.65 -> 3803.13 | D52: =57.59+3450.62 -> 3508.21 | E52: =95.76+2983.69 -> 3079.45 | F52: =141.93+3494.37 -> 3636.3 | H52: Other current liabilities | I52: 766.54 | J52: 944.84 | K52: 996.01 | L52: 1241.79 | M52: 1632.17 | O52: Other financial liabilities | P52: 721.52 | Q52: 1390.99 | R52: 1156.56 | S52: 1410.4 | T52: 1507.55 | V52: Trade payables | W52: 1602.87 | X52: 949.94 | Y52: 1075.93 | Z52: 1274.06 | AA52: 1343.65 | AC52: Lease liabilities | AD52: 0 | AE52: 0 | AF52: 188.61 | AG52: 216.75 | AH52: 252.85
A53: Other financial liabilities | B53: 4118.7 | C53: 1138.88 | D53: 1167.32 | E53: 2461.58 | F53: 2089.8 | H53: Short term provisions | I53: 5.85 | J53: 5.38 | K53: 6.41 | L53: 9.61 | M53: 10.3 | O53: Non current tax liabilities (net) | P53: 3.03 | Q53: 3.03 | R53: 3.03 | S53: 0 | T53: 0 | V53: Other financial liabilities | W53: 2674.39 | X53: 2226.51 | Y53: 1893.11 | Z53: 1917.48 | AA53: 2137.57 | AC53: Trade payables
A54: Other Current Liabilities | B54: 603.18 | C54: 1217.35 | D54: 861.36 | E54: 3622.82 | F54: 2159.44 | H54: Current tax liabilities | I54: 170.95 | J54: 34.21 | K54: 3.66 | L54: 3.44 | M54: 2.25 | O54: Deferred tax liabilities (net) | P54: 1174.04 | Q54: 976.15 | R54: 1033.3 | S54: 1919.37 | T54: 2772.33 | V54: Other current liabilities | W54: 48.99 | X54: 53.01 | Y54: 53.49 | Z54: 59.46 | AA54: 92.14 | AC54: Total outstanding dues of micro and small enterprises | AD54: 512.24 | AE54: 404.12 | AF54: 496.04 | AG54: 462.43 | AH54: 579.97
A55: Short Term Provisions | B55: 39.44 | C55: 60.17 | D55: 28.71 | E55: 21.64 | F55: 25.69 | H55: Total Current Liabilities | I55: =SUM(I49:I54) -> 15953.61 | J55: =SUM(J49:J54) -> 15928.2 | K55: =SUM(K49:K54) -> 17225.29 | L55: =SUM(L49:L54) -> 18373.81 | M55: =SUM(M49:M54) -> 17882.23 | O55: Long term provisions | P55: 407.4 | Q55: 839.58 | R55: 1218.18 | S55: 1420.02 | T55: 1865.08 | V55: Short term provisions | W55: 11.85 | X55: 13.05 | Y55: 12.53 | Z55: 20.19 | AA55: 25.57 | AC55: Total outstanding dues of creditors other than micro and small enterprises | AD55: 9596.34 | AE55: 8322.16 | AF55: 10781.28 | AG55: 13359.92 | AH55: 10757.98
A56: Current Tax Liabilities (Net) | B56: 29.97 | C56: 45.71 | D56: 645.32 | E56: 0.49 | F56: 0 | H56: Liabilities directly associated with assets classified as held for sale and discontinued operations | I56: 0 | J56: 0 | K56: 0 | L56: 0 | M56: 11.96 | O56: Other non current liabilities | P56: 2084.52 | Q56: 6217.95 | R56: 8139.29 | S56: 9847.82 | T56: 11973.08 | V56: Current tax liabilities (net) | W56: 36.89 | X56: 36.79 | Y56: 36.79 | Z56: 44.82 | AA56: 60.46 | AC56: Other financial liabilities | AD56: 28646.96 | AE56: 36301.39 | AF56: 27627.62 | AG56: 28181.98 | AH56: 32944.74
A57: Total Current Liabilties | B57: =SUM(B50:B56) -> 18189.15 | C57: =SUM(C50:C56) -> 18727.35 | D57: =SUM(D50:D56) -> 17143.67 | E57: =SUM(E50:E56) -> 17744.59 | F57: =SUM(F50:F56) -> 15788.67 | H57: Total Equity and Liabilities | I57: =I37+I46+I55+I56 -> 53342.9 | J57: =J37+J46+J55+J56 -> 50781.83 | K57: =K37+K46+K55+K56 -> 49811.66 | L57: =L37+L46+L55+L56 -> 48535.42 | M57: =M37+M46+M55+M56 -> 43760.26 | O57: Total non current liabilities | P57: =SUM(P49:P56) -> 40266.13 | Q57: =SUM(Q49:Q56) -> 42632.57 | R57: =SUM(R48:R56) -> 47487.85 | S57: =SUM(S48:S56) -> 48816.8 | T57: =SUM(T48:T56) -> 59252.77 | V57: Liabilities classified as held for sale | W57: 0 | X57: 0 | Y57: 0 | Z57: 67.91 | AA57: 0 | AC57: Other current liabilities | AD57: 1856.19 | AE57: 1949.5 | AF57: 1877.61 | AG57: 2088.55 | AH57: 1980.19
A58: Total Liabilities | B58: =B47+B57 -> 68544.55 | C58: =C47+C57 -> 65693.31 | D58: =D47+D57 -> 63277.58 | E58: =E47+E57 -> 55945.61 | F58: =F47+F57 -> 49179.74 | O58: Current liabilities | V58: Total current liabilities | W58: =SUM(W50:W57) -> 4374.99 | X58: =SUM(X50:X57) -> 3569.27 | Y58: =SUM(Y50:Y57) -> 5092.76 | Z58: =SUM(Z50:Z57) -> 9005.62 | AA58: =SUM(AA50:AA57) -> 7269.44 | AC58: Short term provisions | AD58: 7372.06 | AE58: 8113.6 | AF58: 7875.53 | AG58: 8217.26 | AH58: 7060.33
A59: Total Equity and Liabilities | B59: =B37+B58 -> 75025 | C59: =C37+C58 -> 78805.91 | D59: =D37+D58 -> 81981.02 | E59: =E37+E58 -> 85821.27 | F59: =F37+F58 -> 92324.77 | O59: Financial liabilities | V59: Total Liabilities | W59: =W47+W58 -> 13490.07 | X59: =X47+X58 -> 11938.05 | Y59: =Y47+Y58 -> 13515.5 | Z59: =Z47+Z58 -> 30007.52 | AA59: =AA47+AA58 -> 37254.86 | AC59: Current tax liabilities (net) | AD59: 1.71 | AE59: 17.5 | AF59: 141.13 | AG59: 86.47 | AH59: 2.95
O60: Short term borrowings | P60: 11844.36 | Q60: 8436.21 | R60: 14860.3 | S60: 18265.94 | T60: 12087.56 | V60: Total equity and liabilities | W60: =W37+W59 -> 25111.85 | X60: =X37+X59 -> 26436.33 | Y60: =Y37+Y59 -> 30932.46 | Z60: =Z37+Z59 -> 48741.7 | AA60: =AA37+AA59 -> 58269.1 | AC60: Total current liabilties | AD60: =SUM(AD51:AD52,AD54:AD59) -> 64541.73 | AE60: =SUM(AE51:AE52,AE54:AE59) -> 71072.89 | AF60: =SUM(AF51:AF52,AF54:AF59) -> 76671.89 | AG60: =SUM(AG51:AG52,AG54:AG59) -> 84534.97 | AH60: =SUM(AH51:AH52,AH54:AH59) -> 98404.34
O61: Lease liabilities | P61: 379.74 | Q61: 394.83 | R61: 397.33 | S61: 437.87 | T61: 467.16 | AC61: Deferred revenue | AD61: 2943.22 | AE61: 2263.28 | AF61: 2278.42 | AG61: 2950.48 | AH61: 2651
O62: Trade payables | P62: 5095.44 | Q62: 7120.08 | R62: 10459.6 | S62: 7407.2 | T62: =870+8451.37 -> 9321.37 | AC62: Regulatory deferral a/c credit balances | AD62: 0 | AE62: 0 | AF62: 0 | AG62: 0 | AH62: 1299.83
O63: Other financial liabilities | P63: 7502.9 | Q63: 12296.46 | R63: 9631.96 | S63: 13150.77 | T63: 14796.16 | AC63: Total Equity and Liabilities | AD63: =AD38+AD48+AD60+AD61+AD62 -> 378485.44 | AE63: =AE38+AE48+AE60+AE61+AE62 -> 398966.21 | AF63: =AF38+AF48+AF60+AF61+AF62 -> 416596.51 | AG63: =AG38+AG48+AG60+AG61+AG62 -> 446021.45 | AH63: =AH38+AH48+AH60+AH61+AH62 -> 480196.57
O64: Current tax liabilities (net) | P64: 129.49 | Q64: 198.38 | R64: 147 | S64: 217.96 | T64: 294.34
O65: Short term provisions | P65: 116.42 | Q65: 270.11 | R65: 344.82 | S65: 311.07 | T65: 291.54
O66: Other current liabilities | P66: 1453.08 | Q66: 2052.02 | R66: 2779.08 | S66: 4188.41 | T66: 3879.84
O67: Total current liabilities | P67: =SUM(P60:P66) -> 26521.43 | Q67: =SUM(Q60:Q66) -> 30768.09 | R67: =SUM(R60:R66) -> 38620.09 | S67: =SUM(S60:S66) -> 43979.22 | T67: =SUM(T60:T66) -> 41137.97
O68: Liabilities directly associated with assets classified as held for sale | P68: 1062.53 | Q68: 139.78 | R68: 113.56 | S68: 113.56 | T68: 113.56
O69: Total liabilities before regulatory deferred a/c | P69: =P57+P67+P68 -> 67850.09 | Q69: =Q57+Q67+Q68 -> 73540.44 | R69: =R57+R67+R68 -> 86221.5 | S69: =S57+S67+S68 -> 92909.58 | T69: =T57+T67+T68 -> 100504.3
O70: Regulatory deferred a/c- Liabilities | P70: 0 | Q70: 61.23 | R70: 634.63 | S70: 1235.34 | T70: 716.42
O71: Total EQUITY AND LIABILITIES | P71: =P69+P45+P70 -> 89748.15 | Q71: =Q69+Q45+Q70 -> 98851.23 | R71: =R69+R45+R70 -> 112884.59 | S71: =S69+S45+S70 -> 128349.04 | T71: =T69+T45+T70 -> 139553.49

Sheet Income Statement
A1: INCOME STATEMENT (ADANI POWER) | F1: #VALUE! | H1: INCOME STATEMENT (Reliance Power) | M1: #VALUE! | O1: INCOME STATEMENT (TATA Power) | T1: #VALUE! | V1: INCOME STATEMENT (JSW Energy) | AA1: #VALUE! | AC1: INCOME STATEMENT (NTPC) | AH1: #VALUE!
A2: Particulars | B2: Mar 20 | C2: Mar 21 | D2: Mar 22 | E2: Mar 23 | F2: Mar 24 | H2: Particulars | I2: Mar 20 | J2: Mar 21 | K2: Mar 22 | L2: Mar 23 | M2: Mar 24 | O2: Particulars | P2: Mar 20 | Q2: Mar 21 | R2: Mar 22 | S2: Mar 23 | T2: Mar 24 | V2: Particulars | W2: Mar 20 | X2: Mar 21 | Y2: Mar 22 | Z2: Mar 23 | AA2: Mar 24 | AC2: Particulars | AD2: Mar 20 | AE2: Mar 21 | AF2: Mar 22 | AG2: Mar 23 | AH2: Mar 24
A3: INCOME | H3: INCOME | O3: Revenue from operations | P3: 29136.37 | Q3: 32468.1 | R3: 42815.67 | S3: 55109.08 | T3: 61448.9 | V3: INCOME | AC3: INCOME
A4: Revenue from operations | B4: 26467.72 | C4: 26221.48 | D4: 27711.18 | E4: 38773.3 | F4: 50351.25 | H4: Revenue from Operations | I4: 7562.27 | J4: 7934.01 | K4: 7503.11 | L4: 7542.69 | M4: 7892.6 | O4: Other income | P4: 562.61 | Q4: 439.24 | R4: 919.96 | S4: 1438.02 | T4: 1823.42 | V4: Revenue from operations | W4: 8272.71 | X4: 6922.2 | Y4: 8167.15 | Z4: 10331.81 | AA4: 11486.91 | AC4: Revenue from operations | AD4: 109464.04 | AE4: 111531.15 | AF4: 132669.28 | AG4: 176206.93 | AH4: 178500.88
A5: Other income | B5: 1374.09 | C5: 1928.2 | D5: 3975.29 | E5: 4267.22 | F5: 9930.23 | H5: Other income | I5: 640.14 | J5: 454.59 | K5: 183.62 | L5: 340.05 | M5: 367.63 | O5: Total income | P5: =P3+P4 -> 29698.98 | Q5: =Q3+Q4 -> 32907.34 | R5: =R3+R4 -> 43735.63 | S5: =S3+S4 -> 56547.1 | T5: =T3+T4 -> 63272.32 | V5: Other income | W5: 286.98 | X5: 237.45 | Y5: 568.69 | Z5: 535.24 | AA5: 455.43 | AC5: Other income | AD5: 2908.54 | AE5: 4015.68 | AF5: 2325.03 | AG5: 1770.24 | AH5: 2664.98
A6: Total Income | B6: =B4+B5 -> 27841.81 | C6: =C4+C5 -> 28149.68 | D6: =D4+D5 -> 31686.47 | E6: =E4+E5 -> 43040.52 | F6: =F4+F5 -> 60281.48 | H6: Total Income | I6: =I4+I5 -> 8202.41 | J6: =J4+J5 -> 8388.6 | K6: =K4+K5 -> 7686.73 | L6: =L4+L5 -> 7882.74 | M6: =M4+M5 -> 8260.23 | O6: EXPENSES | V6: Total Income | W6: =W4+W5 -> 8559.69 | X6: =X4+X5 -> 7159.65 | Y6: =Y4+Y5 -> 8735.84 | Z6: =Z4+Z5 -> 10867.05 | AA6: =AA4+AA5 -> 11942.34 | AC6: Total Income | AD6: =AD4+AD5 -> 112372.58 | AE6: =AE4+AE5 -> 115546.83 | AF6: =AF4+AF5 -> 134994.31 | AG6: =AG4+AG5 -> 177977.17 | AH6: =AH4+AH5 -> 181165.86
A7: EXPENSES | H7: EXPENSES | O7: Cost of power purchased | P7: 6220.46 | Q7: 8334.41 | R7: 14640.62 | S7: 19062.67 | T7: 20014.46 | V7: EXPENSES | AC7: EXPENSES
A8: Fuel cost | B8: 17580.39 | C8: 14781.15 | D8: 14762.21 | E8: 25480.85 | F8: 28452.64 | H8: Cost of fuel consumed (including cost of coal excavation) | I8: 2896.6 | J8: 3116.69 | K8: 3025.8 | L8: 3654.76 | M8: 3831.35 | O8: Cost of fuel | P8: =9922.39+214 -> 10136.39 | Q8: =9074.96+504.6 -> 9579.56 | R8: =8290.92+1018.19 -> 9309.11 | S8: =13763.59+1194.95 -> 14958.54 | T8: =14130.47+1168.69 -> 15299.16 | V8: Fuel costs | W8: 4460.51 | X8: 3283.04 | Y8: 3493.95 | Z8: 5569.7 | AA8: 4581.6 | AC8: Fuel cost | AD8: 57185.69 | AE8: 56099.26 | AF8: 69752.97 | AG8: 100655.78 | AH8: 98311.96
A9: Purchase of stock in trade / Power for resale | B9: 467.1 | C9: 365.3 | D9: 545.56 | E9: 214.14 | F9: 222.26 | H9: Employee benefit expenses | I9: 209.33 | J9: 156.06 | K9: 173.74 | L9: 178.81 | M9: 184.24 | O9: Raw material consumed and construction cost (including project land and sub-contracting cost) | P9: 957.18 | Q9: 2628.19 | R9: 3832.83 | S9: 3882.3 | T9: 5439.86 | V9: Purchase of power | W9: 37.75 | X9: 0 | Y9: 80.21 | Z9: 367.6 | AA9: 124.79 | AC9: Electricity purchased for trading | AD9: 5185.95 | AE9: 5049.42 | AF9: 5584.69 | AG9: 5324.95 | AH9: 5682.79
A10: Transmission charges | B10: 621.82 | C10: 664.31 | D10: 642.77 | E10: 519.61 | F10: 503.99 | H10: Finance cost | I10: 3053.97 | J10: 2538.59 | K10: 2349.08 | L10: 2526.61 | M10: 2451.29 | O10: Purchase of finished goods and spares | P10: 111.74 | Q10: 28.89 | R10: 49.11 | S10: 56.15 | T10: 39.89 | V10: Employee benefit expenses | W10: 242.96 | X10: 236.63 | Y10: 264.15 | Z10: 307.6 | AA10: 364.47 | AC10: Employee benefit expenses | AD10: 5830.48 | AE10: 5953.93 | AF10: 6310.09 | AG10: 6528.34 | AH10: 6592.03
A11: Employee benefit expenses | B11: 426.82 | C11: 431.54 | D11: 470.31 | E11: 569.99 | F11: 643.7 | H11: Depreciation and ammortization | I11: 836.3 | J11: 1083.21 | K11: 1077.28 | L11: 1032.73 | M11: 1061.75 | O11: Decrease/Increase in stock-in-trade and work in progress | P11: -15.64 | Q11: 0.41 | R11: -199.22 | S11: 43.53 | T11: -51.78 | V11: Changes in inventories | W11: 0 | X11: 0 | Y11: 0 | Z11: 0 | AA11: 0.63 | AC11: Finance cost | AD11: 8116.85 | AE11: 9224.14 | AF11: 9315.98 | AG11: 11156.06 | AH11: 12048.21
A12: Finance costs | B12: 5314.82 | C12: 5106.33 | D12: 4094.78 | E12: 3333.5 | F12: 3388.09 | H12: Generation, Administration and other expenses | I12: 1433.71 | J12: 1086.3 | K12: 1582.23 | L12: 1824.14 | M12: 2719.7 | O12: Employee benefit expenses | P12: 1440.64 | Q12: 2156.48 | R12: 3611.63 | S12: 3624.26 | T12: 4036.09 | V12: Finance costs | W12: 1051.07 | X12: 895.65 | Y12: 776.91 | Z12: 844.3 | AA12: 2053.4 | AC12: Depreciation and ammortization expense | AD12: 10356.16 | AE12: 12450.31 | AF12: 13787.83 | AG12: 14792.27 | AH12: 16203.63
A13: Depreciation and ammortization expense | B13: 3006.5 | C13: 3201.65 | D13: 3117.54 | E13: 3303.68 | F13: 3931.33 | H13: Total Expenses | I13: =SUM(I8:I12) -> 8429.91 | J13: =SUM(J8:J12) -> 7980.85 | K13: =SUM(K8:K12) -> 8208.13 | L13: =SUM(L8:L12) -> 9217.05 | M13: =SUM(M8:M12) -> 10248.33 | O13: Finance cost | P13: 4493.73 | Q13: 4010.39 | R13: 3859.02 | S13: 4371.65 | T13: 4633.22 | V13: Depreciation and ammortization expense | W13: 1168.05 | X13: 1166.94 | Y13: 1131.05 | Z13: 1169.23 | AA13: 1633.41 | AC13: Other expenses | AD13: 9725.41 | AE13: 10454.71 | AF13: 10741.97 | AG13: 15968.95 | AH13: 16821.39
A14: Other expense | B14: 1686.29 | C14: 1310.66 | D14: 1476.17 | E14: 1944.05 | F14: 2347.96 | H14: Profit/Loss before exceptional items and tax | I14: =I6-I13 -> -227.5 | J14: =J6-J13 -> 407.75 | K14: =K6-K13 -> -521.4 | L14: =L6-L13 -> -1334.31 | M14: =M6-M13 -> -1988.1 | O14: Depreciation and ammortization | P14: 2633.56 | Q14: 2744.94 | R14: 3122.2 | S14: 3439.2 | T14: 3786.37 | V14: Other expense | W14: 574.63 | X14: 495.95 | Y14: 759.84 | Z14: 805.07 | AA14: 1032.64 | AC14: Total expenses | AD14: =SUM(AD8:AD13) -> 96400.54 | AE14: =SUM(AE8:AE13) -> 99231.77 | AF14: =SUM(AF8:AF13) -> 115493.53 | AG14: =SUM(AG8:AG13) -> 154426.35 | AH14: =SUM(AH8:AH13) -> 155660.01
A15: Total expenses | B15: =SUM(B8:B14) -> 29103.74 | C15: =SUM(C8:C14) -> 25860.94 | D15: =SUM(D8:D14) -> 25109.34 | E15: =SUM(E8:E14) -> 35365.82 | F15: =SUM(F8:F14) -> 39489.97 | H15: Exceptional items | O15: Other expenses | P15: 2342.78 | Q15: 2812.48 | R15: 4060.42 | S15: 5775.31 | T15: 5887.39 | V15: Total expenses | W15: =SUM(W8:W14) -> 7534.97 | X15: =SUM(X8:X14) -> 6078.21 | Y15: =SUM(Y8:Y14) -> 6506.11 | Z15: =SUM(Z8:Z14) -> 9063.5 | AA15: =SUM(AA8:AA14) -> 9790.94 | AC15: Profit before share of profits of joint ventures accounted for using equity method, tax and regulatory deferral a/c balances | AD15: =AD6-AD14 -> 15972.04 | AE15: =AE6-AE14 -> 16315.06 | AF15: =AF6-AF14 -> 19500.78 | AG15: =AG6-AG14 -> 23550.82 | AH15: =AH6-AH14 -> 25505.85
A16: Profit / Loss from operations before exceptional items, tax and deferred tax | B16: =B6-B15 -> -1261.93 | C16: =C6-C15 -> 2288.74 | D16: =D6-D15 -> 6577.13 | E16: =E6-E15 -> 7674.7 | F16: =F6-F15 -> 20791.51 | H16: Impairement of property, plant and equipments and capital work in progress | I16: -4004.21 | J16: 0 | K16: 0 | L16: 0 | M16: -1926.35 | O16: Total expenses | P16: =SUM(P7:P15) -> 28320.84 | Q16: =SUM(Q7:Q15) -> 32295.75 | R16: =SUM(R7:R15) -> 42285.72 | S16: =SUM(S7:S15) -> 55213.61 | T16: =SUM(T7:T15) -> 59084.66 | V16: Share of profit of joint venture and an associate | W16: 28.04 | X16: 17.15 | Y16: 8.54 | Z16: 19.29 | AA16: 16.51 | AC16: Add: Share of profits of joint ventures accounted for using equity method | AD16: 405.4 | AE16: 683.87 | AF16: 1020.13 | AG16: 779.77 | AH16: 1635.6
A17: Less: Exceptional items | B17: 1002.99 | C17: 0 | D17: 0 | E17: 0 | F17: 0 | H17: Liabilities written back | I17: 0 | J17: 4.42 | K17: 0 | L17: 1036.86 | M17: 1886.3 | O17: Profit/Loss before movement in regulatory deferral balances, exceptional items, tax and share of net profit of associates and Joint ventures accounted for using the equity method | P17: =P5-P16 -> 1378.14 | Q17: =Q5-Q16 -> 611.59 | R17: =R5-R16 -> 1449.91 | S17: =S5-S16 -> 1333.49 | T17: =T5-T16 -> 4187.66 | V17: Profit before exceptional items, tax and deferred tax adjustable in future tariff | W17: =W6-W15+W16 -> 1052.76 | X17: =X6-X15+X16 -> 1098.59 | Y17: =Y6-Y15+Y16 -> 2238.27 | Z17: =Z6-Z15+Z16 -> 1822.84 | AA17: =AA6-AA15+AA16 -> 2167.91 | AC17: Profit before exceptional items, tax and regulatory deferral a/c balances | AD17: =AD15+AD16 -> 16377.44 | AE17: =AE15+AE16 -> 16998.93 | AF17: =AF15+AF16 -> 20520.91 | AG17: =AG15+AG16 -> 24330.59 | AH17: =AH15+AH16 -> 27141.45
A18: Profit/Loss before tax and deferred tax recoverable from future tariff | B18: =B16-B17 -> -2264.92 | C18: =C16-C17 -> 2288.74 | D18: =D16-D17 -> 6577.13 | E18: =E16-E17 -> 7674.7 | F18: =F16-F17 -> 20791.51 | H18: Total exceptional items | I18: =SUM(I16:I17) -> -4004.21 | J18: =SUM(J16:J17) -> 4.42 | K18: 0 | L18: =SUM(L16:L17) -> 1036.86 | M18: =SUM(M16:M17) -> -40.05 | O18: Add/Less: Net movement in regulatory deferral balances | P18: -451.68 | Q18: 529.24 | R18: -380.42 | S18: 815.7 | T18: 56.24 | V18: Exceptional items (net) | W18: -61.46 | X18: 0 | Y18: 0 | Z18: 120 | AA18: 0 | AC18: Exceptional items | AD18: 0 | AE18: 1512.19 | AF18: 0 | AG18: 0 | AH18: 0
A19: Tax expense | H19: Profit/Loss before tax | I19: =I14+I18 -> -4231.71 | J19: =J14+J18 -> 412.17 | K19: =K14+K18 -> -521.4 | L19: =L14+L18 -> -297.45 | M19: =M14+M18 -> -2028.15 | O19: Add/Less: Net movement in regulatory deferral balances in respect of earlier years | P19: -21.32 | Q19: 0 | R19: 0 | S19: -8.53 | T19: 7.34 | V19: Profit before tax and deferred tax adjustable in future tariff | W19: =W17-W18 -> 1114.22 | X19: =X17-X18 -> 1098.59 | Y19: =Y17-Y18 -> 2238.27 | Z19: =Z17+Z18 -> 1942.84 | AA19: =AA17-AA18 -> 2167.91 | AC19: Profit before tax and regulatory deferral a/c balances | AD19: =AD17-AD18 -> 16377.44 | AE19: =AE17-AE18 -> 15486.74 | AF19: =AF17-AF18 -> 20520.91 | AG19: =AG17-AG18 -> 24330.59 | AH19: =AH17-AH18 -> 27141.45
A20: Current tax | B20: 24.68 | C20: 25.64 | D20: 768.34 | E20: 0.58 | F20: 0.09 | H20: Income tax expense | O20: Add/Less: Deferred tax recoverable/Payable | P20: 284.31 | Q20: 81.8 | R20: 140.95 | S20: 116.88 | T20: 29.85 | V20: Tax expense | AC20: Tax expenses
A21: Excess provision for earlier years written back | B21: -7.33 | C21: -4.27 | D21: -0.11 | E21: -768.18 | F21: 13.91 | H21: Current tax | I21: 45.18 | J21: 56.46 | K21: 23.13 | L21: 46.21 | M21: 18.13 | O21: Total movement in regulatory deferral balances (Net) | P21: =P18+P19+P20 -> -188.69 | Q21: =Q18+Q19+Q20 -> 611.04 | R21: =R18+R19+R20 -> -239.47 | S21: =S18+S19+S20 -> 924.05 | T21: =T18+T19+T20 -> 93.43 | V21: Current tax | W21: 111.91 | X21: 194.59 | Y21: 421.92 | Z21: 298.3 | AA21: 393.84 | AC21: Current Tax in current year | AD21: 2782.89 | AE21: 2958.8 | AF21: 3760.62 | AG21: 4659.84 | AH21: 4457.24
A22: Deferred tax | B22: 38.19 | C22: 1062.5 | D22: 976.57 | E22: -2499.77 | F22: -51.28 | H22: Deferred tax | I22: -21.28 | J22: -71.4 | K22: 12.06 | L22: 17.17 | M22: 195.9 | O22: Profit/Loss before exceptional items, tax and share of net profit of associates and Joint ventures | P22: =P17+P21 -> 1189.45 | Q22: =Q17+Q21 -> 1222.63 | R22: =R17+R21 -> 1210.44 | S22: =S17+S21 -> 2257.54 | T22: =T17+T21 -> 4281.09 | V22: Deferred tax | W22: -183.05 | X22: 31.67 | Y22: -83.29 | Z22: 178.31 | AA22: -104.24 | AC22: Earlier years | AD22: 2743.64 | AE22: -1867.74 | AF22: -2.69 | AG22: 196.27 | AH22: -161.14
A23: Total Tax expense | B23: =SUM(B20:B22) -> 55.54 | C23: =SUM(C20:C22) -> 1083.87 | D23: =SUM(D20:D22) -> 1744.8 | E23: =SUM(E20:E22) -> -3267.37 | F23: =SUM(F20:F22) -> -37.28 | H23: Income tax for previous years | I23: -0.24 | J23: 0.03 | K23: 8.54 | L23: 0.53 | M23: 0 | O23: Share of net profit of associates and Joint ventures accounted for using the equity method | P23: 952.55 | Q23: 873.39 | R23: 1942.83 | S23: 3199.46 | T23: 1177.57 | V23: Deferred tax adjustable in future tariff | W23: 104.18 | X23: 49.65 | Y23: 156.16 | Z23: -13.89 | AA23: 152.66 | AC23: Deferred tax | AD23: 3821.01 | AE23: 1329.47 | AF23: 1289.17 | AG23: 1940.01 | AH23: 2513.1
A24: Deferred tax recoverable from future tariff (net) | B24: -45.69 | C24: 65.11 | D24: 79.25 | E24: -215.43 | F24: 0 | H24: Total tax expenses | I24: =SUM(I21:I23) -> 23.66 | J24: =SUM(J21:J23) -> -14.91 | K24: =SUM(K21:K23) -> 43.73 | L24: =SUM(L21:L23) -> 63.91 | M24: =SUM(M21:M23) -> 214.03 | O24: Profit/Loss before exceptional items and tax | P24: =P22+P23 -> 2142 | Q24: =Q22+Q23 -> 2096.02 | R24: =R22+R23 -> 3153.27 | S24: =S22+S23 -> 5457 | T24: =T22+T23 -> 5458.66 | V24: Profit for the year | W24: =W19-W21-W22-W23 -> 1081.18 | X24: =X19-X21-X22-X23 -> 822.68 | Y24: =Y19-Y21-Y22-Y23 -> 1743.48 | Z24: =Z19-Z21-Z22-Z23 -> 1480.12 | AA24: =AA19-AA21-AA22-AA23 -> 1725.65 | AC24: Total tax expenses | AD24: =SUM(AD21:AD23) -> 9347.54 | AE24: =SUM(AE21:AE23) -> 2420.53 | AF24: =SUM(AF21:AF23) -> 5047.1 | AG24: =SUM(AG21:AG23) -> 6796.12 | AH24: =SUM(AH21:AH23) -> 6809.2
A25: Loss/Profit for the year | B25: =B18-B23-B24 -> -2274.77 | C25: =C18-C23+C24 -> 1269.98 | D25: =D18-D23+D24 -> 4911.58 | E25: =E18-E23+E24 -> 10726.64 | F25: =F18-F23+F24 -> 20828.79 | H25: Profit/Loss from continuing operations | I25: =I19-I24 -> -4255.37 | J25: =J19-J24 -> 427.08 | K25: =K19-K24 -> -565.13 | L25: =L19-L24 -> -361.36 | M25: =M19-M24 -> -2242.18 | O25: Add/Less: Exceptional Items: | AC25: Profit before regulatory deferral a/c balances | AD25: =AD19-AD24 -> 7029.9 | AE25: =AE19-AE24 -> 13066.21 | AF25: =AF19-AF24 -> 15473.81 | AG25: =AG19-AG24 -> 17534.47 | AH25: =AH19-AH24 -> 20332.25
A26: Other Comprehensive income/loss | H26: Discontinuing operations: | O26: Gain on dilution of interest in an associate | P26: 532.51 | Q26: 0 | R26: 0 | S26: 0 | T26: 234.68 | AC26: Net movement in regulatory deferral a/c balances (net of tax) | AD26: 4879.01 | AE26: 1903.19 | AF26: 1486.48 | AG26: -413.12 | AH26: 1000
A27: Items that will not be reclassified to profit/loss | H27: Profit/Loss before tax from discontinued operations | I27: -16.11 | J27: 26.86 | K27: 8.6 | L27: -41.53 | M27: 173.8 | O27: Impairement of Goodwill on acquisition | P27: -276.35 | Q27: -109.29 | R27: -150.27 | S27: 0 | T27: -100.85 | AC27: Profit for the year | AD27: =AD25+AD26 -> 11908.91 | AE27: =AE25+AE26 -> 14969.4 | AF27: =AF25+AF26 -> 16960.29 | AG27: =AG25+AG26 -> 17121.35 | AH27: =AH25+AH26 -> 21332.25
A28: Remeasurement gain/loss of defined benefit plans | B28: 1.26 | C28: -6.13 | D28: -10.73 | E28: -5.9 | F28: 9.29 | H28: Tax expense of discontinued operations | I28: 0 | J28: 0 | K28: 0 | L28: 0 | M28: 0 | O28: Profit on sale of subsidiaries and Join ventures | P28: =-265+235 -> -30 | Q28: 0 | R28: 0 | S28: 0 | T28: 139.53
A29: Gain on sale of investment | B29: 0 | C29: 0.49 | D29: 0.78 | E29: 0 | F29: -2.33 | H29: Profit/Loss from discontinuing operations | I29: =I27+I28 -> -16.11 | J29: =J27+J28 -> 26.86 | K29: =K27+K28 -> 8.6 | L29: =L27+L28 -> -41.53 | M29: =M27+M28 -> 173.8 | O29: Profit/Loss before tax for the year | P29: =P24+P26+P27+P28 -> 2368.16 | Q29: =Q24+Q26+Q27+Q28 -> 1986.73 | R29: =R24+R26+R27+R28 -> 3003 | S29: =S24+S26+S27+S28 -> 5457 | T29: =T24+T26+T27+T28 -> 5732.02
A30: Income tax impact | B30: -0.14 | C30: 3.76 | D30: 26.94 | E30: 0 | F30: 0 | H30: Profit/Loss for the year before non controlling interest | I30: =I25+I29 -> -4271.48 | J30: =J25+J29 -> 453.94 | K30: =K25+K29 -> -556.53 | L30: =L25+L29 -> -402.89 | M30: =M25+M29 -> -2068.38 | O30: Tax expense
A31: Other comprehensive gain/loss that will not be reclassified to profit or loss | B31: =SUM(B28:B30) -> 1.12 | C31: =SUM(C28:C30) -> -1.88 | D31: =SUM(D28:D30) -> 16.99 | E31: =SUM(E28:E30) -> -5.9 | F31: =SUM(F28:F30) -> 6.96 | H31: Non-Controlling interest | I31: -194.89 | J31: 225.31 | K31: 49.38 | L31: 67.88 | M31: 0 | O31: Current Tax | P31: 494.3 | Q31: 647.57 | R31: 580.3 | S31: 804.33 | T31: 871.47
A32: Items that will be reclassified to profit or loss | H32: Profit/Loss for the year | I32: =I30-I31 -> -4076.59 | J32: =J30-J31 -> 228.63 | K32: =K30-K31 -> -605.91 | L32: =L30-L31 -> -470.77 | M32: =M30-M31 -> -2068.38 | O32: Current tax in respect of earlier years | P32: 330.95 | Q32: 0 | R32: -105.11 | S32: -52.37 | T32: -62.68
A33: Net gain on effective portion of cash flow hedges | B33: 9.2 | C33: -28.52 | D33: 26.64 | E33: 39.64 | F33: -46.04 | H33: Other comprehensive income | O33: Deferred tax | P33: -24.51 | Q33: -145.69 | R33: 133.31 | S33: 1010.3 | T33: 725.85
A34: Income tax impact | B34: 0 | C34: 0 | F34: 11.59 | H34: Items that will be reclassified to profit or loss | O34: Deferred tax relating to earlier years | P34: -159.25 | Q34: 0 | R34: =-588.56+359.62 -> -228.94 | S34: -114.93 | T34: -82.72
A35: Other comprehensive gain/loss that will not be reclassified to profit or loss | B35: =B33+B34 -> 9.2 | C35: =C33+C34 -> -28.52 | D35: =D33+D34 -> 26.64 | E35: =E33+E34 -> 39.64 | F35: =F33+F34 -> -34.45 | H35: Remeasurements of post employment benefit obligation | I35: -2.81 | J35: 4.44 | K35: -0.99 | L35: -16.14 | M35: -1 | O35: Total Tax expense | P35: =P31+P33+P32+P34 -> 641.49 | Q35: =Q31+Q33+Q32+Q34 -> 501.88 | R35: =R31+R33+R32+R34 -> 379.56 | S35: =S31+S33+S32+S34 -> 1647.33 | T35: =T31+T33+T32+T34 -> 1451.92
A36: Other comprehensive gain/loss for the year, net of tax | B36: =B31+B35 -> 10.32 | C36: =C31+C35 -> -30.4 | D36: =D31+D35 -> 43.63 | E36: =E31+E35 -> 33.74 | F36: =F31+F35 -> -27.49 | H36: Currency translation gains/loss | I36: 29.13 | J36: -3.34 | K36: 1.97 | L36: -19.79 | M36: 4.16 | O36: Profit/Loss for the year from continuing operations | P36: =P29-P35 -> 1726.67 | Q36: =Q29-Q35 -> 1484.85 | R36: =R29-R35 -> 2623.44 | S36: =S29-S35 -> 3809.67 | T36: =T29-T35 -> 4280.1
A37: Total Comprehensive Profit/Loss for the year | B37: =B25+B36 -> -2264.45 | C37: =C25+C36 -> 1239.58 | D37: =D25+D36 -> 4955.21 | E37: =E25+E36 -> 10760.38 | F37: =F25+F36 -> 20801.3 | H37: Other comprehensive income/loss for the year | I37: =I35+I36 -> 26.32 | J37: =J35+J36 -> 1.1 | K37: =K35+K36 -> 0.98 | L37: =L35+L36 -> -35.93 | M37: =M35+M36 -> 3.16 | O37: Profit/Loss before tax from discontinued operations | P37: -81.64 | Q37: -59.85 | R37: 0 | S37: 0
H38: Total comprehensive income/loss for the year | I38: =I32+I37 -> -4050.27 | J38: =J32+J37 -> 229.73 | K38: =K32+K37 -> -604.93 | L38: =L32+L37 -> -506.7 | M38: =M32+M37 -> -2065.22 | O38: Impairement loss related to discontinued operations on remeasurement to fair value | P38: -361 | Q38: -160 | R38: -467.83 | S38: 0 | T38: 0
O39: Tax expense/Credit of discontinued operations
O40: Current tax | P40: 0 | Q40: -101.48 | R40: 0 | S40: 0 | T40: 0
O41: Deferred tax | P41: -32.41 | Q41: -72.17 | R41: 0 | S41: 0 | T41: 0
O42: Tax expense/Credit of discontinued operations | P42: =P40+P41 -> -32.41 | Q42: =Q40+Q41 -> -173.65 | R42: =R40+R41 -> 0 | S42: =S40+S41 -> 0 | T42: =T40+T41 -> 0
O43: Profit/Loss for the year from discontinued operations | P43: =P37+P38-P42 -> -410.23 | Q43: =Q37+Q38-Q42 -> -46.2 | R43: =R37+R38-R42 -> -467.83 | S43: =S37+S38-S42 -> 0 | T43: =T37+T38-T42 -> 0
O44: Profit /Loss for the year | P44: =P36+P43 -> 1316.44 | Q44: =Q36+Q43 -> 1438.65 | R44: =R36+R43 -> 2155.61 | S44: =S36+S43 -> 3809.67 | T44: =T36+T43 -> 4280.1

Sheet Cash Flow Statement
A1: CASH FLOW STATEMENT (ADANI POWER) | F1: #VALUE! | H1: CASH FLOW STATEMENT (Reliance Power) | M1: #VALUE! | O1: CASH FLOW STATEMENT (TATA Power) | T1: #VALUE! | V1: CASH FLOW STATEMENT (JSW Energy) | AA1: #VALUE! | AC1: CASH FLOW STATEMENT (NTPC) | AH1: #VALUE!
A2: Particulars | B2: Mar 20 | C2: Mar 21 | D2: Mar 22 | E2: Mar 23 | F2: Mar 24 | H2: Particulars | I2: Mar 20 | J2: Mar 21 | K2: Mar 22 | L2: Mar 23 | M2: Mar 24 | O2: Particulars | P2: Mar 20 | Q2: Mar 21 | R2: Mar 22 | S2: Mar 23 | T2: Mar 24 | V2: Particulars | W2: Mar 20 | X2: Mar 21 | Y2: Mar 22 | Z2: Mar 23 | AA2: Mar 24 | AC2: Particulars | AD2: Mar 20 | AE2: Mar 21 | AF2: Mar 22 | AG2: Mar 23 | AH2: Mar 24
A3: Cash flow from operating activities | H3: Cash flow from operating activities | O3: Cash flow Operating activities | V3: CASH FLOW FROM OPERATING ACTIVTIES | AC3: CASH FLOW FROM OPERATING ACTIVITIES
A4: Profit/Loss before tax | B4: -2264.92 | C4: 2288.74 | D4: 6577.13 | E4: 7674.7 | F4: 20791.51 | H4: Profit/Loss before tax | I4: -4231.54 | J4: 412.17 | K4: -879.49 | L4: -297.45 | M4: -2028.15 | O4: Profit/Loss before tax for the year | P4: =2368.16-442.64 -> 1925.52 | Q4: =1986.73-219.85 -> 1766.88 | R4: =3003-467.83 -> 2535.17 | S4: 5457 | T4: 5732.02 | V4: Profit before tax and deferred tax adjustable in future tariff | W4: 1114.22 | X4: 1098.59 | Y4: 2238.27 | Z4: 1942.84 | AA4: 2166.91 | AC4: Profit before tax and regulatory deferral ac balances | AD4: 16377.51 | AE4: 16998.93 | AF4: 20520.91 | AG4: 24330.59 | AH4: 27141.45
A5: Adjustments to reconcile profit before tax to net cash flows: | H5: Adjusted for: | O5: Adjustments: | V5: Adjusted for: | AC5: Add: Net movements in regulatory deferral a/c balances | AD5: 4872.01 | AE5: 1903.19 | AF5: 1486.48 | AG5: -413.12 | AH5: 1000.2
A6: Depreciation and ammortization expenses | B6: 3006.5 | C6: 3201.65 | D6: 3117.54 | E6: 3303.68 | F6: 3931.33 | H6: Gain arising on mutual fund investment | I6: -4.94 | J6: -1.08 | K6: -1.03 | L6: -1.79 | M6: -2.46 | O6: Depreciation and ammortization | P6: 2633.56 | Q6: 2744.94 | R6: 3122.2 | S6: 3439.2 | T6: 3786.37 | V6: Depreciation and ammortization | W6: 1168.05 | X6: 1166.94 | Y6: 1131.05 | Z6: 1169.23 | AA6: 1633.41 | AC6: Add: Tax on net movements in regulatory deferral a/c balances | AD6: 1032.07 | AE6: 387.5 | AF6: 303.99 | AG6: -92.68 | AH6: 214.19
A7: Unrealized foreign exchange fluctuation Gain/Loss (net) | B7: 84.1 | C7: -336.75 | D7: 61.55 | E7: 101.61 | F7: -2.49 | H7: Depreciation/Ammortization | I7: 984.06 | J7: 1293.07 | K7: 1275.05 | L7: 1243.79 | M7: 1256.75 | O7: Transfer to contingency reserve | P7: 17 | Q7: 11 | R7: 12.57 | S7: 13.68 | T7: 15.8 | V7: Finance cost | W7: 1051.07 | X7: 895.65 | Y7: 776.91 | Z7: 844.3 | AA7: 2053.4 | AC7: Profit before tax including movement in regulatory deferral a/c balances | AD7: =AD4+AD5+AD6 -> 22281.59 | AE7: =AE4+AE5+AE6 -> 19289.62 | AF7: =AF4+AF5+AF6 -> 22311.38 | AG7: =AG4+AG5+AG6 -> 23824.79 | AH7: =AH4+AH5+AH6 -> 28355.84
A8: Income from mutual funds | B8: -4.09 | C8: -0.02 | D8: -0.83 | E8: -13.1 | F8: -42.92 | H8: Finance cost including gain/loss on derivative | I8: 3053.97 | J8: 2538.59 | K8: 2707.17 | L8: 2526.61 | M8: 2451.29 | O8: Gain on dilution of interest in an associate | P8: -235 | Q8: -67.76 | R8: 467.83 | S8: 0 | T8: -234.68 | V8: Interest income earned on financial assets that are not designated | W8: -184.12 | X8: -105.56 | Y8: -351.22 | Z8: -144.98 | AA8: -223.12 | AC8: Adjustments:
A9: Loss on sale/retirement/provided for/write off of property, plant and equipment | B9: 48.34 | C9: 19.64 | D9: 67.25 | E9: 85.65 | F9: 78.35 | H9: Fair value of investment measured at FVTPL | I9: 3.98 | J9: 0 | K9: 0 | M9: -167.7 | O9: Finance cost | P9: 361 | Q9: 160 | R9: 41.09 | S9: 29.97 | T9: 0 | V9: Dividend income from investments designated as fair value | W9: -1.71 | X9: 0 | Y9: -45.52 | Z9: -121.52 | AA9: -23.81 | AC9: Depreciation, ammortization and impaired expense | AD9: 10356.16 | AE9: 12450.31 | AF9: 13787.83 | AG9: 14792.27 | AH9: 16203.63
A10: Ammortized government grant income | B10: -304.06 | C10: -304.06 | D10: -304.06 | E10: -304.06 | F10: -391.67 | H10: Interest income | I10: -92.29 | J10: -46.46 | K10: -53.36 | L10: -57.65 | M10: -53.81 | O10: Impairement of goodwill on acquisition | P10: 24.99 | Q10: -5.6 | R10: 3859.02 | S10: 4371.65 | T10: 4633.22 | V10: Share of profit of a joint venture | W10: -28.72 | X10: -14.01 | Y10: -8.54 | Z10: -19.29 | AA10: -16.51 | AC10: Provisions | AD10: 421.12 | AE10: 907.54 | AF10: 407.63 | AG10: 753.86 | AH10: 864.55
A11: Liabilitiy no longer required written back | B11: -42.44 | C11: -307.81 | D11: -21.82 | E11: -41.37 | F11: -92.2 | H11: Gain on foreign exchange fluctuations (net) | I11: 0 | J11: -289.54 | K11: 41.24 | L11: -8.81 | M11: -1.03 | O11: Profit on sale of subsidiaries and joint ventures | P11: 4529.88 | Q11: 4035.3 | R11: -292.51 | S11: -513.65 | T11: 100.85 | V11: Net gain arising on financial instruments designated | W11: -28.04 | X11: -17.15 | Y11: -4.99 | Z11: -1.72 | AA11: -0.71 | AC11: Share of net profit of joint ventures accounted for using equity method | AD11: -405.4 | AE11: =-683.87+15.88 -> -667.99 | AF11: -1020.13 | AG11: -779.77 | AH11: -1635.6
A12: Gain on sale of investment in subsidiaries | B12: 0 | C12: 0 | D12: 0 | E12: -694.45 | F12: -232.9 | H12: Liabilities written back | I12: 21.82 | J12: 68.95 | K12: -6.56 | L12: -1049.12 | M12: -1903.95 | O12: Gain/Loss on disposal of PPE (net) | P12: -135.55 | Q12: -175.65 | R12: 0 | S12: -3 | T12: -139.53 | V12: Writeback of liabilities no longer required | W12: -0.6 | X12: 1.27 | Y12: -43.52 | Z12: -41.59 | AA12: -43.1 | AC12: On account of govt grants | AD12: -91.54 | AE12: 477.38 | AF12: -109.5 | AG12: 668.76 | AH12: 214.33
A13: Finance cost | B13: 5314.82 | C13: 5106.33 | D13: 4094.78 | E13: 3333.5 | F13: 3388.09 | H13: Govt grant | I13: -53.07 | J13: -53.07 | K13: -53.07 | L13: -53.07 | M13: -53.07 | O13: Employee stock option expenses | P13: -85.87 | Q13: -6.78 | R13: -6.79 | S13: -524.14 | T13: -5.36 | V13: Share based payments | W13: -0.17 | X13: -31.08 | Y13: 15.38 | Z13: 24.73 | AA13: 24.55 | AC13: Deferred foreign currency fluctuation asset | AD13: -1072.34 | AE13: 527.46 | AF13: 416.75 | AG13: -84.69 | AH13: 78.84
A14: Interest income | B14: -959.63 | C14: -1045.45 | D14: -3558.27 | E14: -3607.19 | F14: -8921.11 | H14: Loss on sale of PPE | I14: -40.45 | J14: -35.89 | K14: 0.15 | L14: 21.22 | M14: 2.58 | O14: Interest income | P14: -53.39 | Q14: 25.82 | R14: -19.31 | S14: -92.22 | T14: 8.27 | V14: Gain/loss on disposal of PPE (net) | W14: 4.12 | X14: 1.92 | Y14: 2.63 | Z14: 0.15 | AA14: -0.05 | AC14: Deferred income from foreign currency fluctuation | AD14: =1340.04+0.03 -> 1340.07 | AE14: -412.13 | AF14: 224.94 | AG14: 948.27 | AH14: 14.72
A15: Stores and spares provided for | B15: 0 | C15: 0 | D15: 79.33 | E15: 12.13 | F15: -0.4 | H15: Provisions made during the year/impairement/amouts written off | I15: 4004.21 | J15: -0.1 | K15: 569.71 | L15: 824.75 | M15: 3620.36 | O15: Discount amortised/accrued on bonds (net) | P15: -532.51 | Q15: 0 | R15: 127.62 | S15: 383.81 | T15: -616.69 | V15: Allowance for slow moving inventory | W15: -2.85 | X15: 5.01 | Y15: 0 | Z15: 0.79 | AA15: 0 | AC15: Regulatory deferral account balances | AD15: -5904.08 | AE15: -2290.69 | AF15: -1790.47 | AG15: 505.8 | AH15: -1214.39
A16: Bad debts and sundry balance written off | B16: 216.84 | C16: 0 | D16: 0.42 | E16: 8.68 | F16: 7.53 | H16: Loss on revaluation of inventories | I16: 325.83 | J16: 16.25 | K16: 0 | L16: 5.63 | M16: 2.48 | O16: Dividend income | P16: 20.71 | Q16: 24.37 | R16: 11.94 | S16: 51.54 | T16: 0.02 | V16: Impairement loss on loans/trade receivables | W16: 0.29 | X16: 0.97 | Y16: 0.83 | Z16: 8.83 | AA16: 36.64 | AC16: Fly ash utilization reserve fund | AD16: -38.39 | AE16: 19.88 | AF16: -19.71 | AG16: 143.38 | AH16: 175.82
A17: Advances to suppliers/unrealized balances provided for | B17: 1002.99 | C17: 43.05 | D17: 39.44 | E17: 0 | F17: 164.53 | H17: Provision for leave encashment and gratuity | I17: 8.01 | J17: 5.91 | K17: 7.27 | L17: 13.67 | M17: 12.65 | O17: Gain on sale of current investment measured at fair value | P17: 0 | Q17: 69.87 | R17: 10.67 | S17: 26.07 | T17: -764.05 | V17: Unrealized foreign exchange loss (net) | W17: 0.41 | X17: =0.84-1.88 -> -1.04 | Y17: 0.22 | Z17: 13.38 | AA17: 3.22 | AC17: Finance cost | AD17: 8060.61 | AE17: 9162.74 | AF17: 9238.86 | AG17: 11092.08 | AH17: 11954.79
A18: Operating profit before working capital changes | B18: =SUM(B4,B6:B17) -> 6098.45 | C18: =SUM(C4,C6:C17) -> 8665.32 | D18: =SUM(D4,D6:D17) -> 10152.46 | E18: =SUM(E4,E6:E17) -> 9859.78 | F18: =SUM(F4,F6:F17) -> 18677.65 | H18: Operating profit before working capital changes | I18: =SUM(I4:I17) -> 3979.59 | J18: =SUM(J4:J17) -> 3908.8 | K18: =SUM(K4:K17) -> 3607.08 | L18: =SUM(L4:L17) -> 3167.78 | M18: =SUM(M4:M17) -> 3135.94 | O18: Allowances for doubtful debts and advances (net) | P18: 10.45 | Q18: 26.5 | R18: 150.27 | S18: 0 | T18: -80 | V18: Allowance for impairement of advances | W18: =-11.29+10.04+2.18 -> 0.93 | X18: =3.85+10.33+0.94 -> 15.12 | Y18: =70.27+10 -> 80.27 | Z18: =10 -> 10 | AA18: 0 | AC18: Unwinding of discount on vendor liabilities | AD18: 56.24 | AE18: 61.4 | AF18: 77.12 | AG18: 63.98 | AH18: 93.42
A19: Changes in working capital: | H19: Change in operating assets and liabilities | O19: Bad debts | P19: 0 | Q19: 109.29 | R19: -68.31 | S19: -94.77 | T19: 489.61 | V19: Exceptional items | W19: =0.53-177.48+116.02 -> -60.93 | X19: 0 | Y19: 36.56 | Z19: -120 | AA19: 0 | AC19: Interest income/late payment surcharge/income on investments | AD19: -1986.27 | AE19: -3390.34 | AF19: -1292.3 | AG19: -918.04 | AH19: -961.91
A20: Increase in inventories | B20: -1233.29 | C20: 385.47 | D20: -262.29 | E20: -829.06 | F20: -1066.5 | H20: Increase in inventories | I20: -2.46 | J20: 137.44 | K20: 46.08 | L20: -102.91 | M20: -38.32 | O20: Provision for warranties | P20: -49.46 | Q20: -66.27 | R20: -317.7 | S20: -356.67 | T20: 7.49 | AC20: Dividend income | AD20: -4.8 | AE20: -9 | AF20: -9 | AG20: -6.96 | AH20: -9.36
A21: Increase in trade receivables | B21: 1252.45 | C21: 188.86 | D21: 980.98 | E21: -2995.25 | F21: -1738.44 | H21: Increase/decrease in trade receivables | I21: -175.61 | J21: -61.67 | K21: -1052.64 | L21: 533.6 | M21: -41.02 | O21: Interest on overdue TR | P21: -3.15 | Q21: 0 | R21: -9.61 | S21: -11.15 | T21: 37.76 | V21: Operating profit before working capital changes | W21: =SUM(W4,W6:W19) -> 3031.95 | X21: =SUM(X4,X6:X20) -> 3016.63 | Y21: =SUM(Y4,Y6:Y20) -> 3828.33 | Z21: =SUM(Z4,Z6:Z20) -> 3565.15 | AA21: =SUM(AA4,AA6:AA20) -> 5610.83 | AC21: Provisions writtenback | AD21: -484.06 | AE21: -64.19 | AF21: -378.01 | AG21: -368.3 | AH21: -560.73
A22: Increase in other financial assets | B22: 0 | C22: -64.99 | D22: -215.37 | E22: -51.2 | F22: -122.33 | H22: Decrease in other financial assets | I22: 382.37 | J22: 479.24 | K22: 73.21 | L22: 346.05 | M22: 186.49 | O22: Ammortization of service line contributions and govt grant | P22: -89.18 | Q22: -152.19 | R22: -1942.83 | S22: -3199.46 | T22: -195.7 | V22: Adjustments for working capital changes | AC22: Profit on de recognition of PPE | AD22: -12.59 | AE22: -3.36 | AF22: -6.27 | AG22: -31.8 | AH22: -30.37
A23: Decrease/increase in other assets | B23: 818.47 | C23: -126.97 | D23: -358.75 | E23: -233.11 | F23: 1.43 | H23: Increase in other current assets | I23: 255.1 | J23: -161.36 | K23: 125.08 | L23: -16.39 | M23: -115.34 | O23: Guarantee commission from joint ventures | P23: -9.4 | Q23: -8.26 | R23: 55.41 | S23: 53.59 | T23: -385.56 | V23: Decrease/increase in trade receivables and unbilled revenue | W23: -676.92 | X23: 803.62 | Y23: -6.65 | Z23: -501.63 | AA23: 639.4 | AC23: Loss on de recognition of PPE | AD23: 64.19 | AE23: 137.27 | AF23: 108.06 | AG23: 168.55 | AH23: 220.67
A24: Increase/decrease in trade payables | B24: -1104.86 | C24: -1488.52 | D24: -368.06 | E24: -423.16 | F24: 615.62 | H24: Increase in other current liabilities | I24: 113.01 | J24: 153.43 | K24: 24.49 | L24: 108.71 | M24: 41.48 | O24: Share of net profit of associates and JV accounted for equity method | P24: -952.55 | Q24: -873.39 | R24: 1.44 | S24: 2.06 | T24: -12.12 | V24: Decrease/increase in inventories | W24: -185.14 | X24: 243.53 | Y24: -505.94 | Z24: -59.94 | AA24: 148.76 | AC24: Special rebate to beneficiaries - exceptional items | AD24: 0 | AE24: -1512.19 | AF24: 0 | AG24: 0
A25: Decrease/increase in Other financial liabilities | B25: 0 | C25: -479.32 | D25: 140.95 | E25: 414.57 | F25: -601.34 | H25: Decrease/increase in trade payables | I25: 15.77 | J25: -27.75 | K25: 74.47 | L25: 28.72 | M25: -57.93 | O25: Ammortization of deferred revenue | P25: 38.69 | Q25: 48.23 | R25: -199.64 | S25: 0 | T25: -1177.57 | V25: Decrease/increase in current and non current assets | W25: -72.77 | X25: 91.27 | Y25: -45.73 | Z25: -163.54 | AA25: 107.39 | AC25: Operating profit before working capital changes | AD25: =SUM(AD9:AD24) -> 10298.92 | AE25: =SUM(AE9:AE24) -> 15394.09 | AF25: =SUM(AF9:AF24) -> 19635.8 | AG25: =SUM(AG9:AG24) -> 26947.39 | AH25: =SUM(AH9:AH23) -> 25408.41
A26: Decrease/increase in other liabilities and provisions | B26: -175.85 | C26: -59.95 | D26: 387.15 | E26: 2766.61 | F26: -1538.52 | H26: Increase in other financial liabilities | I26: 94.07 | J26: -266.75 | K26: 850.73 | L26: 16.13 | M26: 77.82 | O26: Ammortization of deferred rent | P26: 0 | Q26: 1.12 | R26: 0 | S26: 18.52 | T26: 37.98 | V26: Increase/decrease in trade payables and other liabilities | W26: 163.53 | X26: -272.09 | Y26: 120.78 | Z26: -408.47 | AA26: 112.96 | AC26: Adjustments for;
A27: Cash flow from operating activities | B27: =SUM(B20:B26) -> -443.08 | C27: =SUM(C20:C26) -> -1645.42 | D27: =SUM(D20:D26) -> 304.61 | E27: =SUM(E20:E26) -> -1350.6 | F27: =SUM(F20:F26) -> -4450.08 | I27: =SUM(I20:I26) -> 682.25 | J27: =SUM(J20:J26) -> 252.58 | K27: =SUM(K20:K26) -> 141.42 | L27: =SUM(L20:L26) -> 913.91 | M27: =SUM(M20:M26) -> 53.18 | O27: Provision for future forseeable losses | P27: 0 | Q27: 0 | R27: 0 | S27: 0 | T27: 0.37 | AC27: Trade receivables | AD27: -7086.6 | AE27: 1805.87 | AF27: 199.73 | AG27: -3256.07 | AH27: -1296.73
A28: Less: Income tax paid/ tax deducted at sources (net of refund) | B28: -57.82 | C28: -5.55 | D28: -224.34 | E28: -78.65 | F28: -57.42 | H28: Taxes paid/refund (net) | I28: -118.9 | J28: -40.27 | K28: -49.07 | L28: -57.93 | M28: -34.04 | O28: Net foreign exchange differences | P28: -105.59 | Q28: -16.75 | R28: 37.56 | S28: -36.46 | T28: =1.42+18.18 -> 19.6 | V28: Cash flow from operations | W28: =SUM(W21,W23:W27) -> 2260.65 | X28: =SUM(X21,X23:X27) -> 3882.96 | Y28: =SUM(Y21,Y23:Y27) -> 3390.79 | Z28: =SUM(Z21,Z23:Z27) -> 2431.57 | AA28: =SUM(AA21,AA23:AA27) -> 6619.34 | AC28: Inventories | AD28: -2309.68 | AE28: 2032.27 | AF28: 538.68 | AG28: -3004.98 | AH28: -2586.73
A29: Net cash flows from Operating activities | B29: =B18+B27+B28 -> 5597.55 | C29: =C18+C27+C28 -> 7014.35 | D29: =D18+D27+D28 -> 10232.73 | E29: =E18+E27+E28 -> 8430.53 | F29: =F18+F27+F28 -> 14170.15 | H29: Net cash generated from operating activities-continuing operations | I29: =I27+I28+I18 -> 4542.94 | J29: =J27+J28+J18 -> 4121.11 | K29: =K27+K28+K18 -> 3699.43 | L29: =L27+L28+L18 -> 4023.76 | M29: =M27+M28+M18 -> 3155.08 | O29: Adjustments for increase/decrease in operating assets: | V29: Income tax paid | W29: -175.11 | X29: -183.1 | Y29: -438.76 | Z29: -347.3 | AA29: -385.71 | AC29: Trade payables, provisions, other financial liabilties and other liabilities | AD29: 1524.12 | AE29: -24.25 | AF29: 3697.41 | AG29: 3461.28 | AH29: -588.35
A30: Cash flow from investing activities | H30: Net cash generated from operating activities-discontinuing operations | I30: -0.12 | J30: 27.51 | K30: -86.33 | L30: 0.02 | M30: 18.77 | O30: Inventories | P30: -21.32 | Q30: -93.26 | R30: -2308.21 | S30: 309.91 | T30: -444.66 | V30: NET CASH GENERATED/USED IN OPERATING ACTIVITIES | W30: =W28+W29 -> 2085.54 | X30: =X28+X29 -> 3699.86 | Y30: =Y28+Y29 -> 2952.03 | Z30: =Z28+Z29 -> 2084.27 | AA30: =AA28+AA29 -> 6233.63 | AC30: Loans, othe financial assets and other assets | AD30: 2502.01 | AE30: -2985.25 | AF30: -2521.72 | AG30: -3845.21 | AH30: -4864.99
A31: Capital expenditure on payment towards PPE, including capital advances and capital WIP, and intangible assets | B31: -2226.56 | C31: -3617.61 | D31: -3434.55 | E31: -3243.68 | F31: -2602.45 | H31: Net cash generated from operating activities- continuing and discontinuing operations | I31: =I29+I30 -> 4542.82 | J31: =J29+J30 -> 4148.62 | K31: =K29+K30 -> 3613.1 | L31: =L29-L30 -> 4023.74 | M31: =M29+M30 -> 3173.85 | O31: Trade receivables | P31: -96.56 | Q31: -1103.76 | R31: -887.56 | S31: -1070.43 | T31: -859.28 | V31: CASH FLOW FROM INVESTING ACTIVITIES
A32: Proceeds from sale of PPE | B32: 6.72 | C32: 9.96 | D32: 1.24 | E32: 0.83 | F32: 0.56 | H32: Cash flow from investing activities | O32: Unbilled revenue | P32: 54.23 | Q32: -885.35 | R32: -694.43 | S32: -171.14 | T32: -95.52 | V32: Purchase of PPE | W32: -121.5 | X32: -435.44 | Y32: -2294.07 | Z32: -4236.31 | AA32: -8032.77 | AC32: Cash Generated from operations | AD32: =AD7+AD25+SUM(AD27:AD30) -> 27210.36 | AE32: =AE7+AE25+SUM(AE27:AE30) -> 35512.35 | AF32: =AF7+AF25+SUM(AF27:AF30) -> 43861.28 | AG32: =AG7+AG25+SUM(AG27:AG30) -> 44127.2 | AH32: =AH7+AH25+SUM(AH27:AH30) -> 44427.45
A33: Proceeds from sale of payment towards investments in optionally convertible cummulative debenture | B33: 0 | C33: =1415.23-412 -> 1003.23 | D33: 81.54 | E33: -42.5 | F33: 125.38 | H33: Payment for PPE's including capital advance and capital creditors (net) | I33: =-544.44+198.4 -> -346.04 | J33: =-133.96+0.23 -> -133.73 | K33: -196.16 | L33: -384.49 | M33: 51.46 | O33: Finance lease receivables | P33: -18.6 | Q33: -17.94 | R33: 4.46 | S33: 13.88 | T33: -5.86 | V33: Proceeds from sale of PPE | W33: 27.61 | X33: 93.8 | Y33: 0.49 | Z33: -0.27 | AA33: 0.72 | AC33: Income taxes paid/refunded | AD33: -3320.69 | AE33: -3068.29 | AF33: -2073.05 | AG33: -4075.65 | AH33: -3642.86
A34: Acquisition of subsidiaries | B34: -1 | C34: 0 | D34: -1 | E34: -727.16 | F34: 0 | H34: Interest income on bank and other deposits | I34: 87.84 | J34: 34.66 | K34: -71.92 | L34: 52.36 | M34: 45.05 | O34: Loans-Current | P34: -13.17 | Q34: 0.83 | R34: -1.93 | S34: -0.06 | T34: 0.77 | V34: Loans given | W34: -9 | X34: -1136 | Y34: -15.9 | Z34: -30 | AA34: 0 | AC34: NET CASH FROM/USED IN OPERATING ACTIVITIES | AD34: =AD32+AD33 -> 23889.67 | AE34: =AE32+AE33 -> 32444.06 | AF34: =AF32+AF33 -> 41788.23 | AG34: =AG32+AG33 -> 40051.55 | AH34: =AH32+AH33 -> 40784.59
A35: Advance for cost of acquisition of business | B35: 0 | C35: 733.86 | D35: 0 | E35: 0 | F35: -2.58 | H35: Inter corporate deposits/project/other advances given (net) | I35: -1565.95 | J35: -12.88 | K35: =34.25-63.06-0.15 -> -28.96 | L35: -58.44 | M35: -425.71 | O35: Other current assets | P35: 8.58 | Q35: 21.95 | R35: 1.15 | S35: 0.46 | T35: 0.51 | V35: Loans repaid | W35: 145.74 | X35: 351.87 | Y35: 997.29 | Z35: 120 | AA35: 70 | AC35: CASH FLOW FROM INVESTING ACTIVITIES
A36: Poceeds from sale of/Payment towards purchase of current investments | B36: 4.01 | C36: -17.28 | D36: -162.32 | E36: -415.2 | F36: 280.96 | H36: Investment/redemption in fixed deposits/margin money deposits having original maturity more than 3 months | I36: 1577.05 | J36: -10.83 | K36: -282.96 | L36: 36.39 | M36: -32.2 | O36: Other non current assets | P36: 387.45 | Q36: -270.14 | R36: -531.99 | S36: 154.35 | T36: -236.46 | V36: Advances given | W36: 0 | X36: -0.19 | Y36: 0.14 | Z36: -19.63 | AA36: 0 | AC36: Purchase of PPE and intangible assets | AD36: -18230.44 | AE36: -23312.34 | AF36: -24444.42 | AG36: -24818.52 | AH36: -30815.92
A37: Proceeds from disposal of subsidiaries | B37: 0 | C37: 0 | E37: 988.9 | F37: 536.22 | H37: Net cash used in investing activities- continuing operations | I37: =SUM(I33:I36) -> -247.1 | J37: =SUM(J33:J36) -> -122.78 | K37: =SUM(K33:K36) -> -580 | L37: =SUM(L33:L36) -> -354.18 | M37: =SUM(M33:M36) -> -361.4 | O37: Other financial assets - non current | P37: 214.01 | Q37: -156.71 | R37: -284.09 | S37: -289.41 | T37: -1130.6 | V37: Interest received | W37: 0.07 | X37: 0 | Y37: 316.62 | Z37: 234.21 | AA37: 189.35 | AC37: Disposal of PPE and intangible assets | AD37: 167.93 | AE37: 30.36 | AF37: 113.5 | AG37: 98.29 | AH37: 74.6
A38: Fixed/Margin money deposits/withdrawn (net) | B38: -151.93 | C38: -384.85 | D38: -214.85 | E38: 151.07 | F38: -4544.82 | H38: Net cash generated from investing activities- discontinuing operations | I38: 0 | J38: 608.38 | K38: 863.62 | M38: 169.25 | O38: Other financial assets- current | P38: 10.51 | Q38: 104.63 | R38: -115.86 | S38: 19.69 | T38: 149.14 | V38: Dividend received on investments | W38: 210.08 | X38: 170.71 | Y38: 45.52 | Z38: 121.52 | AA38: 23.81 | AC38: Redemption of non convertible debentures | AD38: 0 | AE38: -499.99 | AF38: 499.99 | AG38: 0 | AH38: 50
A39: Proceeds from loans given to related party | B39: -85.14 | C39: -5.82 | D39: 0.99 | E39: 4.83 | F39: 375.57 | H39: Net cash flow/used in investing activities | I39: =I37+I38 -> -247.1 | J39: =J37+J38 -> 485.6 | K39: =K37+K38 -> 283.62 | L39: =L37+L38 -> -354.18 | M39: =M37+M38 -> -192.15 | O39: Regulatory deferral account - assets | P39: -58.14 | Q39: 3.26 | R39: -15.63 | S39: -48.83 | T39: -77.79 | V39: Proceeds from sale of investments in subsidiaries | W39: 28.72 | X39: 14.01 | Y39: 0 | Z39: 76.09 | AA39: 82.69 | AC39: Investment in JV Companies (net) | AD39: =-11500-764.98 -> -12264.98 | AE39: -118.78 | AF39: 499.87 | AG39: -857.25 | AH39: -219.4
A40: Interest received | B40: 125.79 | C40: 90.94 | D40: 4301.06 | E40: 4827.34 | F40: 9316.19 | H40: Cash flow from financing activities | O40: Movement in operating assets | P40: =277.97-365.48+3.68+226.15 -> 142.32 | Q40: =-998-242.8+400.82 -> -839.98 | R40: -322.85 | S40: -1566.73 | T40: 310.41 | V40: Proceeds from redemption of preference shares | W40: -1.47 | X40: -1.42 | Y40: 166.98 | Z40: 0 | AA40: 0.46 | AC40: Interest income/late payment surcharge/income on investments received | AD40: 1045.63 | AE40: 126.69 | AF40: 1325.77 | AG40: 576.74 | AH40: 630.98
A41: Net cash flows from Investing activities | B41: =SUM(B31:B40) -> -2328.11 | C41: =SUM(C31:C40) -> -2187.57 | D41: =SUM(D31:D40) -> 572.11 | E41: =SUM(E31:E40) -> 1544.43 | F41: =SUM(F31:F40) -> 3485.03 | H41: Proceeds from long term borrowings | I41: 123.79 | J41: 0 | K41: 0 | L41: 863.5 | M41: 0 | O41: Adjustments for increase/decrease in operating liabilities: | V41: Purchase of investments designated as FVTPL | W41: 20.51 | X41: -89.9 | Y41: 0 | Z41: -61 | AA41: 0 | AC41: Dividend received from other investments | AD41: 4.8 | AE41: =4186.63+9 -> 4195.63 | AF41: 9 | AG41: 6.96 | AH41: 9.36
A42: Cash flow from financing activities | H42: Repayment of long term borrowings | I42: -1867 | J42: -1763.47 | K42: -1741.16 | L42: -2099.43 | M42: -1304.11 | O42: Trade payables | P42: -796.97 | Q42: 1709.92 | R42: 3221.69 | S42: -3018.39 | T42: 1895.95 | V42: Proceeds from sale of investments in earmarked MF and instruments | W42: 0 | X42: 0 | Y42: -143.81 | Z42: 116.32 | AA42: 23.32 | AC42: Income tax paid on income from investing activities | AD42: -326.97 | AE42: -637.37 | AF42: -545.86 | AG42: -434.92 | AH42: -414.55
A43: Payment towards principal portion of lease liabilities | B43: -4.36 | C43: -5 | D43: -5.95 | E43: -5.83 | F43: -0.47 | H43: Repayment of short term borrowings | I43: -240.61 | J43: -532.63 | K43: -79.33 | L43: -640.61 | M43: -66.17 | O43: Other current liabilities | P43: 448.63 | Q43: 729.58 | R43: 261.32 | S43: 1332.48 | T43: -324.15 | V43: Payments towards business acquisition | W43: 0 | X43: 0 | Y43: 0 | Z43: -2196.58 | AA43: 0 | AC43: Bank balances other than cash and cash equivalents | AD43: -24.09 | AE43: -818.65 | AF43: -348.77 | AG43: -678.5 | AH43: -1456.44
A44: Proceeds from non current borrowings | B44: 21319.44 | C44: 22558.44 | D44: 13332.16 | E44: 21205.41 | F44: 22671.61 | H44: Proceeds from short term borrowings | I44: 0 | J44: 119.2 | K44: 47.22 | L44: 10.86 | M44: 0 | O44: Other non current liabilities | P44: 141.53 | Q44: -6.91 | R44: 64.14 | S44: 7.17 | T44: 258.34 | V44: Payments towards asset acquisition | W44: 0 | X44: 0 | Z44: -1048.84 | AA44: 0 | AC44: NET CASH FROM/USED IN INVESTING ACTIVITIES | AD44: =SUM(AD36:AD43) -> -29628.12 | AE44: =SUM(AE36:AE43) -> -21034.45 | AF44: =SUM(AF36:AF43) -> -22890.92 | AG44: =SUM(AG36:AG43) -> -26107.2 | AH44: =SUM(AH36:AH43) -> -32141.37
A45: Repayment of non current borrowings | B45: -18306.79 | C45: -25132.54 | D45: -17896.16 | E45: -26948.43 | F45: -30597.95 | H45: Interest and finance charges paid | I45: -2113.99 | J45: -1834.18 | K45: -1583.34 | L45: -1837.46 | M45: -1449.88 | O45: Other financial liabilities-current | P45: 233.51 | Q45: 1081.05 | R45: 341 | S45: 2655.34 | T45: 2580.6 | V45: Bank deposits not considered as cash equivalents (net) | Y45: -465.49 | Z45: -84.99 | AA45: -675.31 | AC45: CASH FLOW FROM FINANCING ACTIVITIES
A46: Proceeds/repayments of current borrowings (net) | B46: -517.79 | C46: 704.5 | D46: -1831.58 | E46: -1200.05 | F46: 1896.53 | H46: Inter corporate deposits repaid | I46: -101.85 | J46: 109.14 | K46: 0 | L46: 0 | M46: -19.62 | O46: Other financial liab-non current | P46: 26.04 | Q46: 356.79 | R46: 79.54 | S46: 45.57 | T46: 221.15 | V46: NET CASH FROM/USED IN INVESTING ACTIVITIES | W46: =SUM(W32:W45) -> 300.76 | X46: =SUM(X32:X45) -> -1032.56 | Y46: =SUM(Y32:Y45) -> -1392.23 | Z46: =SUM(Z32:Z45) -> -7009.48 | AA46: =SUM(AA32:AA45) -> -8317.73 | AC46: Poceeds from non-current borrowings | AD46: 33653.14 | AE46: 35361.97 | AF46: 27237.43 | AG46: 28325.97 | AH46: 31631.65
A47: Proceeds from issue of unsecured perpetual securities | B47: 615 | C47: 400 | D47: 600 | E47: 566.49 | F47: 129.04 | H47: Proceeds from issue of equity share warrants/conversion | I47: 0 | J47: 0 | K47: 0 | L47: 80 | M47: 240 | O47: Regulatory deferral account - liabilities | P47: 0 | Q47: 61.23 | R47: 535.7 | S47: 600.71 | T47: -518.92 | V47: CASH FLOW FROM FINANCING ACTIVITIES | AC47: Repayment of non current borrowings | AD47: -9583.31 | AE47: -23912.83 | AF47: -19079.93 | AG47: -24523.66 | AH47: -22439.83
A48: Repayment towards redemption of unsecured perpetual securities | B48: 0 | C48: 0 | D48: 0 | E48: 0 | F48: -5900 | H48: Net cash used in financing activities - continuing operations | I48: =SUM(I41:I47) -> -4199.66 | J48: =SUM(J41:J47) -> -3901.94 | K48: =SUM(K41:K47) -> -3356.61 | L48: =SUM(L41:L47) -> -3623.14 | M48: =SUM(M41:M47) -> -2599.78 | O48: Current provisions | P48: -57.19 | Q48: 128.52 | R48: -85.98 | S48: -162.15 | T48: -241.21 | V48: Proceeds from fresh issue of equity shares under ESOP plan | W48: 6.96 | X48: 2.21 | Y48: 6.47 | Z48: 3.35 | AA48: 0 | AC48: Proceeds/repayments of current borrowings (net) | AD48: -812.62 | AE48: -591.61 | AF48: -7434.15 | AG48: 4343.48 | AH48: 5944.75
A49: Distribution to holders of unsecured perpetual securities | B49: -612.01 | C49: -380.36 | D49: -589.83 | E49: -661.17 | F49: -1631.93 | H49: Net cash used in financing activities - discontinuing operations | I49: 0 | J49: -713.02 | K49: -492.08 | M49: -134.42 | O49: Non current provisions | P49: 69.4 | Q49: 430.66 | R49: 550.91 | S49: 201.84 | T49: 445.06 | V49: Payment/Proceeds for treasury shares under ESOP Plan | W49: -1.57 | X49: -1.24 | Y49: -90.89 | Z49: 0.92 | AA49: -10.69 | AC49: Payment of lease liabilities | AD49: -78.71 | AE49: -57.03 | AF49: -55.1 | AG49: -230.1 | AH49: -130.89
A50: Finance cost paid | B50: -4870.67 | C50: -3799.88 | D50: -3946.5 | E50: -3364.88 | F50: -3430.86 | H50: Net cash flow/used in financing activities | I50: =I48+I49 -> -4199.66 | J50: =J48+J49 -> -4614.96 | K50: =K48+K49 -> -3848.69 | L50: =L48+L49 -> -3623.14 | M50: =M48+M49 -> -2734.2 | O50: Movement in operating liabilities | V50: Proceeds from non current borrowings | W50: 750 | X50: 400 | Y50: 5662.87 | Z50: 9354.38 | AA50: 11025.18 | AC50: Interest paid | AD50: -13399.15 | AE50: -13307.37 | AF50: -12732.88 | AG50: -14822.25 | AH50: -15831.78
A51: Net cash flow/used in financing activities | B51: =SUM(B43:B50) -> -2377.18 | C51: =SUM(C43:C50) -> -5654.84 | D51: =SUM(D43:D50) -> -10337.86 | E51: =SUM(E43:E50) -> -10408.46 | F51: =SUM(F43:F50) -> -16864.03 | H51: Net increase in cash and cash equivalents | I51: =I31+I39+I50 -> 96.06 | J51: =J31+J39+J50 -> 19.26 | K51: =K31+K39+K50 -> 48.03 | L51: =L31+L39+L50 -> 46.42 | M51: =M31+M39+M50 -> 247.5 | O51: Cash flow from/used in operations | P51: =SUM(P6:P28,P30:P40,P42:P49)+P50+P4 -> 7984.41 | Q51: =SUM(Q6:Q28,Q30:Q40,Q42:Q49)+Q50+Q4 -> 8905.04 | R51: =SUM(R6:R28,R30:R40,R42:R49)+R50+R4 -> 7387.47 | S51: =SUM(S6:S28,S30:S40,S42:S49)+S50+S4 -> 8029.83 | T51: =SUM(T6:T28,T30:T40,T42:T49)+T50+T4 -> 13185.58 | V51: Repayment of non current borrowings | W51: -1457.01 | X51: -2195.1 | Y51: -6036.3 | Z51: -970.08 | AA51: -6723.27 | AC51: Dividend paid | AD51: =-3133.37-641.72 -> -3775.09 | AE51: -5778.42 | AF51: -7106.93 | AG51: -7247.91 | AH51: -7419.43
A52: Net increase/decrease in cash and cash equivalents | B52: =B29+B41+B51 -> 892.26 | C52: =C29+C41+C51 -> -828.06 | D52: =D29+D41+D51 -> 466.98 | E52: =E29+E41+E51 -> -433.5 | F52: =F29+F41+F51 -> 791.15 | H52: Opening balance of cash and cash equivalents | I52: 28.88 | J52: 124.94 | K52: 144.2 | L52: 192.23 | M52: 238.65 | O52: Income tax paid | P52: -609.09 | Q52: -447.03 | R52: -694.74 | S52: -870.7 | T52: -589.47 | V52: Proceeds from current borrowings (net) | W52: 0 | X52: 289.97 | Y52: 765.82 | Z52: 353.44 | AA52: 68.31 | AC52: Buy back of equity share capital | AD52: 0 | AE52: -2763.82 | AF52: 0 | AG52: 0 | AH52: 0
A53: Reduction/Addition on disposal/acquisition of subsidiaries | B53: 24.27 | C53: 0 | D53: 202.35 | E53: 0.36 | F53: -2.71 | H53: Closing balance of cash and cash equivalents | I53: =I51+I52 -> 124.94 | J53: =J51+J52 -> 144.2 | K53: =K51+K52 -> 192.23 | L53: =L51+L52 -> 238.65 | M53: =M51+M52 -> 486.15 | O53: Net cash flow from/used in operating activities | P53: =P51+P52 -> 7375.32 | Q53: =Q51+Q52 -> 8458.01 | R53: =R51+R52 -> 6692.73 | S53: =S51+S52 -> 7159.13 | T53: =T51+T52 -> 12596.11 | V53: Payment of lease liabilities | W53: -2.97 | X53: -3.02 | Y53: -3.2 | Z53: -9.91 | AA53: -29.7 | AC53: Net cash from/used in financing activities | AD53: =SUM(AD46:AD52) -> 6004.26 | AE53: =SUM(AE46:AE52) -> -11049.11 | AF53: =SUM(AF46:AF52) -> -19171.56 | AG53: =SUM(AG46:AG52) -> -14154.47 | AH53: =SUM(AH46:AH52) -> -8245.53
A54: Net foreign exchange difference on cash and cash equivalents | B54: 0.03 | C54: 0 | D54: 0 | E54: 0 | F54: -1.42 | O54: Cash flow from Investing activities | V54: Interest paid | W54: -1062.14 | X54: -843.29 | Y54: -757.42 | Z54: -1075.81 | AA54: -2308.18 | AC54: Exchange differences on translation of foreign currency | AD54: -0.03 | AF54: 0 | AH54: 0
A55: Cash and cash equivalents at the beginning of the year | B55: 24.54 | C55: 941.1 | D55: 113.04 | E55: 782.37 | F55: 349.23 | O55: CapEx on PPE | P55: -2225.81 | Q55: -3335.79 | R55: -7267.86 | S55: -7656.01 | T55: -13332.75 | V55: Dividend paid | W55: -197.86 | X55: -164.28 | Y55: -328.66 | Z55: -328.81 | AA55: -346.82 | AC55: Net increase/decrease in cash and cash equivalents | AD55: =AD34+AD44+AD53+AD54 -> 265.78 | AE55: =AE34+AE44+AE53+AE54 -> 360.5 | AF55: =AF34+AF44+AF53+AF54 -> -274.25 | AG55: =AG34+AG44+AG53+AG54 -> -210.12 | AH55: =AH34+AH44+AH53+AH54 -> 397.69
A56: Cash and cash equivalents at the end of the year | B56: =SUM(B52:B55) -> 941.1 | C56: =SUM(C52:C55) -> 113.04 | D56: =SUM(D52:D55) -> 782.37 | E56: =SUM(E52:E55) -> 349.23 | F56: =SUM(F52:F55) -> 1136.25 | O56: Proceeds from sale of PPE | P56: 36.37 | Q56: 1549.09 | R56: 34.91 | S56: 50.29 | T56: 146.2 | V56: NET CASH GENERATED/USED IN FINANCING ACTIVITIES | W56: =SUM(W48:W55) -> -1964.59 | X56: =SUM(X48:X55) -> -2514.75 | Y56: =SUM(Y48:Y55) -> -781.31 | Z56: =SUM(Z48:Z55) -> 7327.48 | AA56: =SUM(AA48:AA55) -> 1674.83 | AC56: Cash and cash equivalents at the beginning of the year | AD56: 323.74 | AE56: 589.52 | AF56: 950.02 | AG56: 675.77 | AH56: 465.65
O57: Purchase/proceeds from sale of current investments (net) | P57: 0 | Q57: 420.85 | R57: 164 | S57: -638.42 | T57: -248.23 | V57: NET DECREASE/INCREASE IN CASH AND CASH EQUIVALENTS | W57: =W30+W46+W56 -> 421.71 | X57: =X30+X46+X56 -> 152.55 | Y57: =Y30+Y46+Y56 -> 778.49 | Z57: =Z30+Z46+Z56 -> 2402.27 | AA57: =AA30+AA46+AA56 -> -409.27 | AC57: Cash and cash equivalents at the end of the year | AD57: =AD55+AD56 -> 589.52 | AE57: =AE55+AE56 -> 950.02 | AF57: =AF55+AF56 -> 675.77 | AG57: =AG55+AG56 -> 465.65 | AH57: =AH55+AH56 -> 863.34
O58: Purchase of non-current investments | P58: -305.51 | Q58: 83.44 | R58: -585.06 | S58: -345.15 | T58: -96.08 | V58: CASH AND CASH EQUIVALENTS AT BEGINNING OF THE YEAR | W58: 474.43 | X58: 895.76 | Y58: 1051.07 | Z58: 1835.12 | AA58: 4468.74
O59: Buy back of non-current investments | P59: 0 | Q59: -720.75 | R59: 0 | S59: 10.45 | T59: 43.84 | V59: Add: Cash and cash equivalents pursuant to business combination | W59: 0 | X59: 0 | Y59: 0 | Z59: 224.94 | AA59: 121.22
O60: Proceeds from sale of non current investments | P60: -615.26 | Q60: -80.26 | R60: 195.8 | S60: 879.38 | T60: 341.8 | V60: Add: Fair value loss/gain on liquid investments | W60: 0.48 | X60: 1.48 | Y60: 4.5 | Z60: 7.17 | AA60: -2.95
O61: Inter corporate deposits given | P61: 577.88 | Q61: 844.32 | R61: 0 | S61: 0 | T61: -0.34 | V61: Add: Effect of exchange rate changes on cash and cash equivalents | W61: -0.86 | X61: 1.28 | Y61: 1.06 | Z61: -0.76 | AA61: 2.33
O62: Repayment of inter corporate deposits given | P62: 0 | Q62: 5.46 | R62: 0.22 | S62: -2.15 | T62: 16.51 | V62: CASH AND CASH EQUIVALENTS AT THE END OF THE YEAR | W62: =SUM(W57:W61) -> 895.76 | X62: =SUM(X57:X61) -> 1051.07 | Y62: =SUM(Y57:Y61) -> 1835.12 | Z62: =SUM(Z57:Z61) -> 4468.74 | AA62: =SUM(AA57:AA61) -> 4180.07
O63: Interests received | P63: 164.92 | Q63: 161.12 | R63: 151.24 | S63: 314.97 | T63: 660.68
O64: Interest on overdue trade receivables | P64: 49.61 | Q64: 66.27 | R64: 68.31 | S64: 143.1 | T64: 195.7
O65: Guarantee commission received | P65: 3.84 | Q65: 3.15 | R65: 9.61 | S65: 11.15 | T65: 12.12
O66: Dividend received | P66: 1894.53 | Q66: 1846.06 | R66: 1855.6 | S66: 3310.34 | T66: 2316.7
O67: Other non current bank deposits | P67: 0 | Q67: 0 | R67: 0 | T67: -280.05
O68: Bank balance not considered as cash and cash equivalents | P68: -123.5 | Q68: -175.36 | R68: -903.34 | S68: -3453.2 | T68: 1189.09
O69: Net cash flow from/used in investing activities | P69: =SUM(P55:P68) -> -542.93 | Q69: =SUM(Q55:Q68) -> 667.6 | R69: =SUM(R55:R68) -> -6276.57 | S69: =SUM(S55:S68) -> -7375.25 | T69: =SUM(T55:T68) -> -9034.81
O70: Cash flow from Financing activities
O71: Proceeds from issue of shares including shares issued to minority shareholders | P71: 20.07 | Q71: 2996.06 | R71: 11.33 | S71: 4008.41 | T71: 113.89
O72: Increase in capital/service line contributions and contribution from consumers | P72: 80.1 | Q72: 155.16 | R72: -1500 | S72: 0 | T72: 1003.94
O73: Proceeds from non current borrowings | P73: 7188.37 | Q73: 5602.19 | R73: 746.26 | S73: 1452.3 | T73: 17082.53
O74: Repayment of non current borrowings | P74: -5607.42 | Q74: -7453.61 | R74: 11473.88 | S74: 10730.41 | T74: -12438.65
O75: Proceeds from current borrowings | P75: -1687.99 | Q75: -4121.95 | R75: -5684.28 | S75: -11838.99 | T75: 51806.02
O76: Repayment from current borrowings | P76: -4002.5 | Q76: -3731.42 | R76: -1632.59 | S76: 2277.53 | T76: -55937.31
O77: Finance cost paid | P77: -330.03 | Q77: -351.78 | R77: -3555.18 | S77: -4108.41 | T77: -4776.53
O78: Payment of lease liability | P78: -500.57 | Q78: -526.29 | R78: -383.85 | S78: -393.59 | T78: -464.55
O79: Dividends paid to equity holders | P79: -98.6 | Q79: 0 | R79: -558.51 | S79: -786.89 | T79: -639.07
O80: Dividends paid to non controlling interests | P80: -171 | Q80: -171.24 | R80: -100.26 | S80: 0 | T80: -247.7
O81: Net cash flow from/used in Financing activities | P81: =SUM(P71:P80) -> -5109.57 | Q81: =SUM(Q71:Q80) -> -7602.88 | R81: =SUM(R71:R80) -> -1183.2 | S81: =SUM(S71:S80) -> 1340.77 | T81: =SUM(T71:T80) -> -4497.43
O82: Net increase in cash and cash equivalents | P82: =P53+P69+P81 -> 1722.82 | Q82: =Q53+Q69+Q81 -> 1522.73 | R82: =R53+R69+R81 -> -767.04 | S82: =S53+S69+S81 -> 1124.65 | T82: =T53+T69+T81 -> -936.13
O83: Cash and cash equivalents in the beginning of the year | P83: 61.52 | Q83: 1834.39 | R83: 3569.96 | S83: 2829.02 | T83: 4072.28
O84: Effect of exchange fluctuation on cash and cash equivalents | P84: 50.04 | Q84: -120.55 | R84: 89.53 | S84: 0 | T84: 7.7
O85: Cash and cash equivalents acquired on business combinations | P85: 0 | Q85: 446.29 | R85: -63.43 | S85: 118.61 | T85: 0
O86: Cash and cash equivalents in the end of the year | P86: =P82+P83+P84 -> 1834.38 | Q86: =Q82+Q83+Q84+Q85 -> 3682.86 | R86: =R82+R83+R84+R85 -> 2829.02 | S86: =S82+S83+S84+S85 -> 4072.28 | T86: =T82+T83+T84+T85 -> 3143.85

Sheet Financial Ratio
A1: FINANCIAL RATIOS (ADANI POWER) | F1: #VALUE! | H1: FINANCIAL RATIOS (Reliance Power) | M1: #VALUE! | O1: FINANCIAL RATIOS (TATA Power) | T1: #VALUE! | V1: FINANCIAL RATIOS (JSW Energy) | AA1: #VALUE! | AC1: FINANCIAL RATIOS (NTPC) | AH1: #VALUE!
A2: Particulars | B2: Mar 20 | C2: Mar 21 | D2: Mar 22 | E2: Mar 23 | F2: Mar 24 | H2: Particulars | I2: Mar 20 | J2: Mar 21 | K2: Mar 22 | L2: Mar 23 | M2: Mar 24 | O2: Particulars | P2: Mar 20 | Q2: Mar 21 | R2: Mar 22 | S2: Mar 23 | T2: Mar 24 | V2: Particulars | W2: Mar 20 | X2: Mar 21 | Y2: Mar 22 | Z2: Mar 23 | AA2: Mar 24 | AC2: Particulars | AD2: Mar 20 | AE2: Mar 21 | AF2: Mar 22 | AG2: Mar 23 | AH2: Mar 24
A3: Profitability ratios | H3: Profitability ratios | O3: Profitability ratios | V3: Profitability ratios | AC3: Profitability ratios
A4: Gross Profit margin | B4: =('Income Statement'!B6-('Income Statement'!B8+'Income Statement'!B9+'Income Statement'!B10))/'Income Statement'!B6 -> 0.32945056 | C4: =('Income Statement'!C6-('Income Statement'!C8+'Income Statement'!C9+'Income Statement'!C10))/'Income Statement'!C6 -> 0.43833251 | D4: =('Income Statement'!D6-('Income Statement'!D8+'Income Statement'!D9+'Income Statement'!D10))/'Income Statement'!D6 -> 0.49661354 | E4: =('Income Statement'!E6-('Income Statement'!E8+'Income Statement'!E9+'Income Statement'!E10))/'Income Statement'!E6 -> 0.39093208 | F4: =('Income Statement'!F6-('Income Statement'!F8+'Income Statement'!F9+'Income Statement'!F10))/'Income Statement'!F6 -> 0.51595598 | H4: Gross Profit margin | I4: =('Income Statement'!I6-('Income Statement'!I8+'Income Statement'!I9))/('Income Statement'!I6) -> 0.62133934 | J4: =('Income Statement'!J6-('Income Statement'!J8+'Income Statement'!J9))/('Income Statement'!J6) -> 0.60985743 | K4: =('Income Statement'!K6-('Income Statement'!K8+'Income Statement'!K9))/('Income Statement'!K6) -> 0.58375798 | L4: =('Income Statement'!L6-('Income Statement'!L8+'Income Statement'!L9))/('Income Statement'!L6) -> 0.51367545 | M4: =('Income Statement'!M6-('Income Statement'!M8+'Income Statement'!M9))/('Income Statement'!M6) -> 0.51386463 | O4: Gross Profit margin | P4: =('Income Statement'!P5-('Income Statement'!P7+'Income Statement'!P8+'Income Statement'!P9+'Income Statement'!P10+'Income Statement'!P11))/'Income Statement'!P5 -> 0.4137802 | Q4: =('Income Statement'!Q5-('Income Statement'!Q7+'Income Statement'!Q8+'Income Statement'!Q9+'Income Statement'!Q10+'Income Statement'!Q11))/'Income Statement'!Q5 -> 0.37486713 | R4: =('Income Statement'!R5-('Income Statement'!R7+'Income Statement'!R8+'Income Statement'!R9+'Income Statement'!R10+'Income Statement'!R11))/'Income Statement'!R5 -> 0.36819362 | S4: =('Income Statement'!S5-('Income Statement'!S7+'Income Statement'!S8+'Income Statement'!S9+'Income Statement'!S10+'Income Statement'!S11))/'Income Statement'!S5 -> 0.32793742 | T4: =('Income Statement'!T5-('Income Statement'!T7+'Income Statement'!T8+'Income Statement'!T9+'Income Statement'!T10+'Income Statement'!T11))/'Income Statement'!T5 -> 0.35609142 | V4: Gross Profit margin | W4: =('Income Statement'!W8+'Income Statement'!W9)/'Income Statement'!W6 -> 0.5255167 | X4: =('Income Statement'!X8+'Income Statement'!X9)/'Income Statement'!X6 -> 0.45854755 | Y4: =('Income Statement'!Y8+'Income Statement'!Y9)/'Income Statement'!Y6 -> 0.40913753 | Z4: =('Income Statement'!Z8+'Income Statement'!Z9)/'Income Statement'!Z6 -> 0.54635803 | AA4: =('Income Statement'!AA8+'Income Statement'!AA9)/'Income Statement'!AA6 -> 0.39409278 | AC4: Gross Profit margin | AD4: =('Income Statement'!AD6-('Income Statement'!AD8+'Income Statement'!AD9))/'Income Statement'!AD6 -> 0.44495677 | AE4: =('Income Statement'!AE6-('Income Statement'!AE8+'Income Statement'!AE9))/'Income Statement'!AE6 -> 0.47078877 | AF4: =('Income Statement'!AF6-('Income Statement'!AF8+'Income Statement'!AF9))/'Income Statement'!AF6 -> 0.44191974 | AG4: =('Income Statement'!AG6-('Income Statement'!AG8+'Income Statement'!AG9))/'Income Statement'!AG6 -> 0.40452627 | AH4: =('Income Statement'!AH6-('Income Statement'!AH8+'Income Statement'!AH9))/'Income Statement'!AH6 -> 0.42596939
A5: Operating profit margin | B5: ='Income Statement'!B16/'Income Statement'!B6 -> -0.045324999 | C5: ='Income Statement'!C16/'Income Statement'!C6 -> 0.081306075 | D5: ='Income Statement'!D16/'Income Statement'!D6 -> 0.20756903 | E5: ='Income Statement'!E16/'Income Statement'!E6 -> 0.17831337 | F5: ='Income Statement'!F16/'Income Statement'!F6 -> 0.34490709 | H5: Operating profit margin | I5: ='Income Statement'!I14/'Income Statement'!I6 -> -0.027735751 | J5: ='Income Statement'!J14/'Income Statement'!J6 -> 0.048607634 | K5: ='Income Statement'!K14/'Income Statement'!K6 -> -0.067831184 | L5: ='Income Statement'!L14/'Income Statement'!L6 -> -0.16926982 | M5: ='Income Statement'!M14/'Income Statement'!M6 -> -0.24068337 | O5: Operating profit margin | P5: ='Income Statement'!P17/'Income Statement'!P5 -> 0.046403614 | Q5: ='Income Statement'!Q17/'Income Statement'!Q5 -> 0.018585215 | R5: ='Income Statement'!R17/'Income Statement'!R5 -> 0.033151689 | S5: ='Income Statement'!S17/'Income Statement'!S5 -> 0.023581934 | T5: ='Income Statement'!T17/'Income Statement'!T5 -> 0.066184708 | V5: Operating profit margin | W5: ='Income Statement'!W17/'Income Statement'!W6 -> 0.12299044 | X5: ='Income Statement'!X17/'Income Statement'!X6 -> 0.15344186 | Y5: ='Income Statement'!Y17/'Income Statement'!Y6 -> 0.25621692 | Z5: ='Income Statement'!Z17/'Income Statement'!Z6 -> 0.1677401 | AA5: ='Income Statement'!AA17/'Income Statement'!AA6 -> 0.18153143 | AC5: Operating profit margin | AD5: ='Income Statement'!AD17/'Income Statement'!AD6 -> 0.14574232 | AE5: ='Income Statement'!AE17/'Income Statement'!AE6 -> 0.14711723 | AF5: ='Income Statement'!AF17/'Income Statement'!AF6 -> 0.15201315 | AG5: ='Income Statement'!AG17/'Income Statement'!AG6 -> 0.13670624 | AH5: ='Income Statement'!AH17/'Income Statement'!AH6 -> 0.14981548
A6: Net profit margin | B6: ='Income Statement'!B25/'Income Statement'!B6 -> -0.081703381 | C6: ='Income Statement'!C25/'Income Statement'!C6 -> 0.045115255 | D6: ='Income Statement'!D25/'Income Statement'!D6 -> 0.15500559 | E6: ='Income Statement'!E25/'Income Statement'!E6 -> 0.2492219 | F6: ='Income Statement'!F25/'Income Statement'!F6 -> 0.34552552 | H6: Net profit margin | I6: ='Income Statement'!I32/'Income Statement'!I6 -> -0.49699905 | J6: ='Income Statement'!J32/'Income Statement'!J6 -> 0.027254846 | K6: ='Income Statement'!K32/'Income Statement'!K6 -> -0.078825456 | L6: ='Income Statement'!L32/'Income Statement'!L6 -> -0.05972162 | M6: ='Income Statement'!M32/'Income Statement'!M6 -> -0.25040223 | O6: Net profit margin | P6: ='Income Statement'!P44/'Income Statement'!P5 -> 0.044326101 | Q6: ='Income Statement'!Q44/'Income Statement'!Q5 -> 0.04371821 | R6: ='Income Statement'!R44/'Income Statement'!R5 -> 0.049287274 | S6: ='Income Statement'!S44/'Income Statement'!S5 -> 0.067371625 | T6: ='Income Statement'!T44/'Income Statement'!T5 -> 0.067645694 | V6: Net profit margin | W6: ='Income Statement'!W24/'Income Statement'!W6 -> 0.12631065 | X6: ='Income Statement'!X24/'Income Statement'!X6 -> 0.11490506 | Y6: ='Income Statement'!Y24/'Income Statement'!Y6 -> 0.19957783 | Z6: ='Income Statement'!Z24/'Income Statement'!Z6 -> 0.13620256 | AA6: ='Income Statement'!AA24/'Income Statement'!AA6 -> 0.14449848 | AC6: Net profit margin | AD6: ='Income Statement'!AD27/'Income Statement'!AD6 -> 0.10597701 | AE6: ='Income Statement'!AE27/'Income Statement'!AE6 -> 0.12955267 | AF6: ='Income Statement'!AF27/'Income Statement'!AF6 -> 0.12563707 | AG6: ='Income Statement'!AG27/'Income Statement'!AG6 -> 0.096199698 | AH6: ='Income Statement'!AH27/'Income Statement'!AH6 -> 0.11774983
A7: Return on capital employed | B7: ='Income Statement'!B16/('Balance Sheet'!B29-'Balance Sheet'!B57) -> -0.022203064 | C7: ='Income Statement'!C16/('Balance Sheet'!C29-'Balance Sheet'!C57) -> 0.038095787 | D7: ='Income Statement'!D16/('Balance Sheet'!D29-'Balance Sheet'!D57) -> 0.10144045 | E7: ='Income Statement'!E16/('Balance Sheet'!E29-'Balance Sheet'!E57) -> 0.11273611 | F7: ='Income Statement'!F16/('Balance Sheet'!F29-'Balance Sheet'!F57) -> 0.27165625 | H7: Return on capital employed | I7: ='Income Statement'!I14/('Balance Sheet'!I30-'Balance Sheet'!I55) -> -0.0060846301 | J7: ='Income Statement'!J14/('Balance Sheet'!J30-'Balance Sheet'!J55) -> 0.011698925 | K7: ='Income Statement'!K14/('Balance Sheet'!K30-'Balance Sheet'!K55) -> -0.016000555 | L7: ='Income Statement'!L14/('Balance Sheet'!L30-'Balance Sheet'!L55) -> -0.044238686 | M7: ='Income Statement'!M14/('Balance Sheet'!M30-'Balance Sheet'!M55) -> -0.076825786 | O7: Return on capital employed | P7: ='Income Statement'!P17/('Balance Sheet'!I30-'Balance Sheet'!I55) -> 0.036859218 | Q7: ='Income Statement'!Q17/('Balance Sheet'!J30-'Balance Sheet'!J55) -> 0.017547383 | R7: ='Income Statement'!R17/('Balance Sheet'!K30-'Balance Sheet'!K55) -> 0.04449437 | S7: ='Income Statement'!S17/('Balance Sheet'!L30-'Balance Sheet'!L55) -> 0.044211499 | T7: ='Income Statement'!T17/('Balance Sheet'!M30-'Balance Sheet'!M55) -> 0.16182298 | V7: Return on capital employed | W7: ='Income Statement'!W17/('Balance Sheet'!W30-'Balance Sheet'!W58) -> 0.050767546 | X7: ='Income Statement'!X17/('Balance Sheet'!X30-'Balance Sheet'!X58) -> 0.048042468 | Y7: ='Income Statement'!Y17/('Balance Sheet'!Y30-'Balance Sheet'!Y58) -> 0.086621395 | Z7: ='Income Statement'!Z17/('Balance Sheet'!Z30-'Balance Sheet'!Z58) -> 0.045873675 | AA7: ='Income Statement'!AA17/('Balance Sheet'!AA30-'Balance Sheet'!AA58) -> 0.042508323 | AC7: Return on capital employed | AD7: ='Income Statement'!AD15/('Balance Sheet'!AD31-'Balance Sheet'!AD60) -> 0.05087549 | AE7: ='Income Statement'!AE15/('Balance Sheet'!AE31-'Balance Sheet'!AE60) -> 0.04975722 | AF7: ='Income Statement'!AF15/('Balance Sheet'!AF31-'Balance Sheet'!AF60) -> 0.057367971 | AG7: ='Income Statement'!AG15/('Balance Sheet'!AG31-'Balance Sheet'!AG60) -> 0.065149933 | AH7: ='Income Statement'!AH15/('Balance Sheet'!AH31-'Balance Sheet'!AH60) -> 0.066805576
A8: Return on Equity | B8: ='Income Statement'!B25/'Balance Sheet'!B37 -> -0.35102038 | C8: ='Income Statement'!C25/'Balance Sheet'!C37 -> 0.096851883 | D8: ='Income Statement'!D25/'Balance Sheet'!D37 -> 0.26260303 | E8: ='Income Statement'!E25/'Balance Sheet'!E37 -> 0.35904278 | F8: ='Income Statement'!F25/'Balance Sheet'!F37 -> 0.48276221 | H8: Return on Equity | I8: ='Income Statement'!I32/'Balance Sheet'!B37 -> -0.62905971 | J8: ='Income Statement'!J32/'Balance Sheet'!C37 -> 0.017435901 | K8: ='Income Statement'!K32/'Balance Sheet'!D37 -> -0.032395645 | L8: ='Income Statement'!L32/'Balance Sheet'!E37 -> -0.015757644 | M8: ='Income Statement'!M32/'Balance Sheet'!F37 -> -0.047940168 | O8: Return on Equity | P8: ='Income Statement'!P44/'Balance Sheet'!P45 -> 0.060116741 | Q8: ='Income Statement'!Q44/'Balance Sheet'!Q45 -> 0.05697723 | R8: ='Income Statement'!R44/'Balance Sheet'!R45 -> 0.082817424 | S8: ='Income Statement'!S44/'Balance Sheet'!S45 -> 0.11138044 | T8: ='Income Statement'!T44/'Balance Sheet'!T45 -> 0.11165642 | V8: Return on Equity | W8: ='Income Statement'!W24/'Balance Sheet'!W37 -> 0.0930305 | X8: ='Income Statement'!X24/'Balance Sheet'!X37 -> 0.056743283 | Y8: ='Income Statement'!Y24/'Balance Sheet'!Y37 -> 0.10010243 | Z8: ='Income Statement'!Z24/'Balance Sheet'!Z37 -> 0.079006394 | AA8: ='Income Statement'!AA24/'Balance Sheet'!AA37 -> 0.082118126 | AC8: Return on Equity | AD8: ='Income Statement'!AD27/'Balance Sheet'!AD38 -> 0.097489079 | AE8: ='Income Statement'!AE27/'Balance Sheet'!AE38 -> 0.11580649 | AF8: ='Income Statement'!AF27/'Balance Sheet'!AF38 -> 0.12189883 | AG8: ='Income Statement'!AG27/'Balance Sheet'!AG38 -> 0.11342126 | AH8: ='Income Statement'!AH27/'Balance Sheet'!AH38 -> 0.12919062
A9: Liquidity ratios | H9: Liquidity ratios | O9: Liquidity ratios | V9: Liquidity ratios | AC9: Liquidity ratios
A10: Current ratio | B10: ='Balance Sheet'!B27/'Balance Sheet'!B57 -> 0.80230137 | C10: ='Balance Sheet'!C27/'Balance Sheet'!C57 -> 0.89969109 | D10: ='Balance Sheet'!D27/'Balance Sheet'!D57 -> 0.94659253 | E10: ='Balance Sheet'!E27/'Balance Sheet'!E57 -> 1.1019133 | F10: ='Balance Sheet'!F27/'Balance Sheet'!F57 -> 1.6205659 | H10: Current ratio | I10: ='Balance Sheet'!I28/'Balance Sheet'!I55 -> 0.30425026 | J10: ='Balance Sheet'!J28/'Balance Sheet'!J55 -> 0.30557565 | K10: ='Balance Sheet'!K28/'Balance Sheet'!K55 -> 0.3330748 | L10: ='Balance Sheet'!L28/'Balance Sheet'!L55 -> 0.26948194 | M10: ='Balance Sheet'!M28/'Balance Sheet'!M55 -> 0.25383411 | O10: Current ratio | P10: ='Balance Sheet'!P33/'Balance Sheet'!P67 -> 0.4532742 | Q10: ='Balance Sheet'!Q33/'Balance Sheet'!Q67 -> 0.53207983 | R10: ='Balance Sheet'!R33/'Balance Sheet'!R67 -> 0.55891713 | S10: ='Balance Sheet'!S33/'Balance Sheet'!S67 -> 0.6319264 | T10: ='Balance Sheet'!T33/'Balance Sheet'!T67 -> 0.66275487 | V10: Current ratio | W10: ='Balance Sheet'!W28/'Balance Sheet'!W58 -> 1.0394652 | X10: ='Balance Sheet'!X28/'Balance Sheet'!X58 -> 1.2186666 | Y10: ='Balance Sheet'!Y28/'Balance Sheet'!Y58 -> 1.0211379 | Z10: ='Balance Sheet'!Z28/'Balance Sheet'!Z58 -> 1.0573919 | AA10: ='Balance Sheet'!AA28/'Balance Sheet'!AA58 -> 1.191946 | AC10: Current ratio | AD10: ='Balance Sheet'!AD28/'Balance Sheet'!AD60 -> 0.87638261 | AE10: ='Balance Sheet'!AE28/'Balance Sheet'!AE60 -> 0.79942226 | AF10: ='Balance Sheet'!AF28/'Balance Sheet'!AF60 -> 0.75976619 | AG10: ='Balance Sheet'!AG28/'Balance Sheet'!AG60 -> 0.81030075 | AH10: ='Balance Sheet'!AH28/'Balance Sheet'!AH60 -> 0.84381979
A11: Quick ratio | B11: =('Balance Sheet'!B27-'Balance Sheet'!B18)/'Balance Sheet'!B57 -> 0.66360495 | C11: =('Balance Sheet'!C27-'Balance Sheet'!C18)/'Balance Sheet'!C57 -> 0.7915546 | D11: =('Balance Sheet'!D27-'Balance Sheet'!D18)/'Balance Sheet'!D57 -> 0.81486636 | E11: =('Balance Sheet'!E27-'Balance Sheet'!E18)/'Balance Sheet'!E57 -> 0.92860979 | F11: =('Balance Sheet'!F27-'Balance Sheet'!F18)/'Balance Sheet'!F57 -> 1.3582195 | H11: Quick ratio | I11: =('Balance Sheet'!I28-'Balance Sheet'!I18)/'Balance Sheet'!I55 -> 0.2406797 | J11: =('Balance Sheet'!J28-'Balance Sheet'!J18)/'Balance Sheet'!J55 -> 0.25069688 | K11: =('Balance Sheet'!K28-'Balance Sheet'!K18)/'Balance Sheet'!K55 -> 0.28500362 | L11: =('Balance Sheet'!L28-'Balance Sheet'!L18)/'Balance Sheet'!L55 -> 0.21912113 | M11: =('Balance Sheet'!M28-'Balance Sheet'!M18)/'Balance Sheet'!M55 -> 0.20008411 | O11: Quick ratio | P11: =('Balance Sheet'!P33-'Balance Sheet'!P21)/'Balance Sheet'!P67 -> 0.38720122 | Q11: =('Balance Sheet'!Q33-'Balance Sheet'!Q21)/'Balance Sheet'!Q67 -> 0.47082156 | R11: =('Balance Sheet'!R33-'Balance Sheet'!R21)/'Balance Sheet'!R67 -> 0.44934929 | S11: =('Balance Sheet'!S33-'Balance Sheet'!S21)/'Balance Sheet'!S67 -> 0.54227315 | T11: =('Balance Sheet'!T33-'Balance Sheet'!T21)/'Balance Sheet'!T67 -> 0.55532055 | V11: Quick ratio | W11: =('Balance Sheet'!W28-'Balance Sheet'!W19)/'Balance Sheet'!W58 -> 0.89327518 | X11: =('Balance Sheet'!X28-'Balance Sheet'!X19)/'Balance Sheet'!X58 -> 1.1079773 | Y11: =('Balance Sheet'!Y28-'Balance Sheet'!Y19)/'Balance Sheet'!Y58 -> 0.8442161 | Z11: =('Balance Sheet'!Z28-'Balance Sheet'!Z19)/'Balance Sheet'!Z58 -> 0.94778483 | AA11: =('Balance Sheet'!AA28-'Balance Sheet'!AA19)/'Balance Sheet'!AA58 -> 1.0776772 | AC11: Quick ratio | AD11: =('Balance Sheet'!AD28-'Balance Sheet'!AD19)/'Balance Sheet'!AD60 -> 0.70380373 | AE11: =('Balance Sheet'!AE28-'Balance Sheet'!AE19)/'Balance Sheet'!AE60 -> 0.66140057 | AF11: =('Balance Sheet'!AF28-'Balance Sheet'!AF19)/'Balance Sheet'!AF60 -> 0.62752359 | AG11: =('Balance Sheet'!AG28-'Balance Sheet'!AG19)/'Balance Sheet'!AG60 -> 0.64184538 | AH11: =('Balance Sheet'!AH28-'Balance Sheet'!AH19)/'Balance Sheet'!AH60 -> 0.66070673
A12: Solvency ratio | H12: Solvency ratio | O12: Solvency ratio | V12: Solvency ratio | AC12: Solvency ratio
A13: Debt-to-Equity ratio | B13: =('Balance Sheet'!B41+'Balance Sheet'!B50)/'Balance Sheet'!B37 -> 8.0809435 | C13: =('Balance Sheet'!C41+'Balance Sheet'!C50)/'Balance Sheet'!C37 -> 3.9970158 | D13: =('Balance Sheet'!D41+'Balance Sheet'!D50)/'Balance Sheet'!D37 -> 2.6089147 | E13: =('Balance Sheet'!E41+'Balance Sheet'!E50)/'Balance Sheet'!E37 -> 1.4142633 | F13: =('Balance Sheet'!F41+'Balance Sheet'!F50)/'Balance Sheet'!F37 -> 0.79862872 | H13: Debt-to-Equity ratio | I13: =('Balance Sheet'!I41+'Balance Sheet'!I49)/'Balance Sheet'!I37 -> 1.8313805 | J13: =('Balance Sheet'!J41+'Balance Sheet'!J49)/'Balance Sheet'!J37 -> 1.493053 | K13: =('Balance Sheet'!K41+'Balance Sheet'!K49)/'Balance Sheet'!K37 -> 1.641145 | L13: =('Balance Sheet'!L41+'Balance Sheet'!L49)/'Balance Sheet'!L37 -> 1.5982406 | M13: =('Balance Sheet'!M41+'Balance Sheet'!M49)/'Balance Sheet'!M37 -> 1.6158133 | O13: Debt-to-Equity ratio | P13: =('Balance Sheet'!P49+'Balance Sheet'!P60)/'Balance Sheet'!P45 -> 2.0339473 | Q13: =('Balance Sheet'!Q49+'Balance Sheet'!Q60)/'Balance Sheet'!Q45 -> 1.5240361 | R13: =('Balance Sheet'!R49+'Balance Sheet'!R60)/'Balance Sheet'!R45 -> 1.8283832 | S13: =('Balance Sheet'!S49+'Balance Sheet'!S60)/'Balance Sheet'!S45 -> 1.4318284 | T13: =('Balance Sheet'!T49+'Balance Sheet'!T60)/'Balance Sheet'!T45 -> 1.2907966 | V13: Debt-to-Equity ratio | W13: =('Balance Sheet'!W41+'Balance Sheet'!W50)/'Balance Sheet'!W37 -> 0.71251908 | X13: =('Balance Sheet'!X41+'Balance Sheet'!X50)/'Balance Sheet'!X37 -> 0.50091321 | Y13: =('Balance Sheet'!Y41+'Balance Sheet'!Y50)/'Balance Sheet'!Y37 -> 0.51056786 | Z13: =('Balance Sheet'!Z41+'Balance Sheet'!Z50)/'Balance Sheet'!Z37 -> 1.3247028 | AA13: =('Balance Sheet'!AA41+'Balance Sheet'!AA50)/'Balance Sheet'!AA37 -> 1.4907325 | AC13: Debt-to-Equity ratio | AD13: =('Balance Sheet'!AD42+'Balance Sheet'!AD51)/'Balance Sheet'!AD38 -> 1.5764735 | AE13: =('Balance Sheet'!AE42+'Balance Sheet'!AE51)/'Balance Sheet'!AE38 -> 1.5258642 | AF13: =('Balance Sheet'!AF42+'Balance Sheet'!AF51)/'Balance Sheet'!AF38 -> 1.5061382 | AG13: =('Balance Sheet'!AG42+'Balance Sheet'!AG51)/'Balance Sheet'!AG38 -> 1.4561107 | AH13: =('Balance Sheet'!AH42+'Balance Sheet'!AH51)/'Balance Sheet'!AH38 -> 1.4234318
A14: Interest coverage ratio | B14: ='Income Statement'!B16/'Income Statement'!B12 -> -0.23743607 | C14: ='Income Statement'!C16/'Income Statement'!C12 -> 0.44821623 | D14: ='Income Statement'!D16/'Income Statement'!D12 -> 1.606223 | E14: ='Income Statement'!E16/'Income Statement'!E12 -> 2.3022949 | F14: ='Income Statement'!F16/'Income Statement'!F12 -> 6.1366463 | H14: Interest coverage ratio | I14: ='Income Statement'!I14/'Income Statement'!I10 -> -0.074493201 | J14: ='Income Statement'!J14/'Income Statement'!J10 -> 0.16062066 | K14: ='Income Statement'!K14/'Income Statement'!K10 -> -0.22195924 | L14: ='Income Statement'!L14/'Income Statement'!L10 -> -0.52810287 | M14: ='Income Statement'!M14/'Income Statement'!M10 -> -0.81104235 | O14: Interest coverage ratio | P14: ='Income Statement'!P17/'Income Statement'!P13 -> 0.30668064 | Q14: ='Income Statement'!Q17/'Income Statement'!Q13 -> 0.15250138 | R14: ='Income Statement'!R17/'Income Statement'!R13 -> 0.37571974 | S14: ='Income Statement'!S17/'Income Statement'!S13 -> 0.30503128 | T14: ='Income Statement'!T17/'Income Statement'!T13 -> 0.90383362 | V14: Interest coverage ratio | W14: ='Income Statement'!W17/'Income Statement'!W12 -> 1.0016079 | X14: ='Income Statement'!X17/'Income Statement'!X12 -> 1.226584 | Y14: ='Income Statement'!Y17/'Income Statement'!Y12 -> 2.8809901 | Z14: ='Income Statement'!Z17/'Income Statement'!Z12 -> 2.1589956 | AA14: ='Income Statement'!AA17/'Income Statement'!AA12 -> 1.055766 | AC14: Interest coverage ratio | AD14: ='Income Statement'!AD15/'Income Statement'!AD11 -> 1.9677634 | AE14: ='Income Statement'!AE15/'Income Statement'!AE11 -> 1.7687351 | AF14: ='Income Statement'!AF15/'Income Statement'!AF11 -> 2.0932613 | AG14: ='Income Statement'!AG15/'Income Statement'!AG11 -> 2.1110338 | AH14: ='Income Statement'!AH15/'Income Statement'!AH11 -> 2.1169825
A15: Efficiency ratio | H15: Efficiency ratio | O15: Efficiency ratio | V15: Efficiency ratio | AC15: Efficiency ratio
A16: Asset turnover ratio | B16: ='Income Statement'!B6/'Balance Sheet'!B29 -> 0.37110043 | C16: ='Income Statement'!C6/'Balance Sheet'!C29 -> 0.35720265 | D16: ='Income Statement'!D6/'Balance Sheet'!D29 -> 0.38650983 | E16: ='Income Statement'!E6/'Balance Sheet'!E29 -> 0.50151344 | F16: ='Income Statement'!F6/'Balance Sheet'!F29 -> 0.65292857 | H16: Asset turnover ratio | I16: ='Income Statement'!I6/'Balance Sheet'!I30 -> 0.15376761 | J16: ='Income Statement'!J6/'Balance Sheet'!J30 -> 0.16518901 | K16: ='Income Statement'!K6/'Balance Sheet'!K30 -> 0.15431588 | L16: ='Income Statement'!L6/'Balance Sheet'!L30 -> 0.16241211 | M16: ='Income Statement'!M6/'Balance Sheet'!M30 -> 0.18876099 | O16: Asset turnover ratio | P16: ='Income Statement'!P5/'Balance Sheet'!P37 -> 0.33091468 | Q16: ='Income Statement'!Q5/'Balance Sheet'!Q37 -> 0.33289763 | R16: ='Income Statement'!R5/'Balance Sheet'!R37 -> 0.38743667 | S16: ='Income Statement'!S5/'Balance Sheet'!S37 -> 0.44057283 | T16: ='Income Statement'!T5/'Balance Sheet'!T37 -> 0.45339117 | V16: Asset turnover ratio | W16: ='Income Statement'!W6/'Balance Sheet'!W30 -> 0.34086245 | X16: ='Income Statement'!X6/'Balance Sheet'!X30 -> 0.27082617 | Y16: ='Income Statement'!Y6/'Balance Sheet'!Y30 -> 0.28241669 | Z16: ='Income Statement'!Z6/'Balance Sheet'!Z30 -> 0.22295181 | AA16: ='Income Statement'!AA6/'Balance Sheet'!AA30 -> 0.20495151 | AC16: Asset turnover ratio | AD16: ='Income Statement'!AD6/'Balance Sheet'!AD31 -> 0.29690067 | AE16: ='Income Statement'!AE6/'Balance Sheet'!AE31 -> 0.28961558 | AF16: ='Income Statement'!AF6/'Balance Sheet'!AF31 -> 0.32404098 | AG16: ='Income Statement'!AG6/'Balance Sheet'!AG31 -> 0.39903276 | AH16: ='Income Statement'!AH6/'Balance Sheet'!AH31 -> 0.37727437
A17: Inventory turnover ratio | B17: =('Income Statement'!B8+'Income Statement'!B9+'Income Statement'!B10)/'Balance Sheet'!B18 -> 7.4003219 | C17: =('Income Statement'!C8+'Income Statement'!C9+'Income Statement'!C10)/'Balance Sheet'!C18 -> 7.8073586 | D17: =('Income Statement'!D8+'Income Statement'!D9+'Income Statement'!D10)/'Balance Sheet'!D18 -> 7.0631678 | E17: =('Income Statement'!E8+'Income Statement'!E9+'Income Statement'!E10)/'Balance Sheet'!E18 -> 8.5245187 | F17: =('Income Statement'!F8+'Income Statement'!F9+'Income Statement'!F10)/'Balance Sheet'!F18 -> 7.0444678 | H17: Inventory turnover ratio | I17: =('Income Statement'!I8+'Income Statement'!I9)/'Balance Sheet'!I18 -> 3.0625037 | J17: =('Income Statement'!J8+'Income Statement'!J9)/'Balance Sheet'!J18 -> 3.7440512 | K17: =('Income Statement'!K8+'Income Statement'!K9)/'Balance Sheet'!K18 -> 3.8639921 | L17: =('Income Statement'!L8+'Income Statement'!L9)/'Balance Sheet'!L18 -> 4.1429668 | M17: =('Income Statement'!M8+'Income Statement'!M9)/'Balance Sheet'!M18 -> 4.1778145 | O17: Inventory turnover ratio | P17: =('Income Statement'!P7+'Income Statement'!P8+'Income Statement'!P9+'Income Statement'!P10+'Income Statement'!P11)/'Balance Sheet'!P21 -> 9.935304 | Q17: =('Income Statement'!Q7+'Income Statement'!Q8+'Income Statement'!Q9+'Income Statement'!Q10+'Income Statement'!Q11)/'Balance Sheet'!Q21 -> 10.914399 | R17: =('Income Statement'!R7+'Income Statement'!R8+'Income Statement'!R9+'Income Statement'!R10+'Income Statement'!R11)/'Balance Sheet'!R21 -> 6.5301476 | S17: =('Income Statement'!S7+'Income Statement'!S8+'Income Statement'!S9+'Income Statement'!S10+'Income Statement'!S11)/'Balance Sheet'!S21 -> 9.6384343 | T17: =('Income Statement'!T7+'Income Statement'!T8+'Income Statement'!T9+'Income Statement'!T10+'Income Statement'!T11)/'Balance Sheet'!T21 -> 9.218326 | V17: Inventory turnover ratio | W17: =('Income Statement'!W8+'Income Statement'!W9)/'Balance Sheet'!W19 -> 7.0331468 | X17: =('Income Statement'!X8+'Income Statement'!X9)/'Balance Sheet'!X19 -> 8.3098107 | Y17: =('Income Statement'!Y8+'Income Statement'!Y9)/'Balance Sheet'!Y19 -> 3.9667932 | Z17: =('Income Statement'!Z8+'Income Statement'!Z9)/'Balance Sheet'!Z19 -> 6.015014 | AA17: =('Income Statement'!AA8+'Income Statement'!AA9)/'Balance Sheet'!AA19 -> 5.6657758 | AC17: Inventory turnover ratio | AD17: =('Income Statement'!AD8+'Income Statement'!AD9)/'Balance Sheet'!AD19 -> 5.5996244 | AE17: =('Income Statement'!AE8+'Income Statement'!AE9)/'Balance Sheet'!AE19 -> 6.2335549 | AF17: =('Income Statement'!AF8+'Income Statement'!AF9)/'Balance Sheet'!AF19 -> 7.4302698 | AG17: =('Income Statement'!AG8+'Income Statement'!AG9)/'Balance Sheet'!AG19 -> 7.4422736 | AH17: =('Income Statement'!AH8+'Income Statement'!AH9)/'Balance Sheet'!AH19 -> 5.7713556
A18: Day sales outstanding | B18: =('Balance Sheet'!B21/'Income Statement'!B6)*365 -> 109.68258 | C18: =('Balance Sheet'!C21/'Income Statement'!C6)*365 -> 153.51284 | D18: =('Balance Sheet'!D21/'Income Statement'!D6)*365 -> 110.13331 | E18: =('Balance Sheet'!E21/'Income Statement'!E6)*365 -> 97.773363 | F18: =('Balance Sheet'!F21/'Income Statement'!F6)*365 -> 70.706297 | H18: Day sales outstanding | I18: ='Balance Sheet'!I21/'Income Statement'!I6*365 -> 105.21905 | J18: ='Balance Sheet'!J21/'Income Statement'!J6*365 -> 104.85733 | K18: ='Balance Sheet'!K21/'Income Statement'!K6*365 -> 152.59122 | L18: ='Balance Sheet'!L21/'Income Statement'!L6*365 -> 124.08928 | M18: ='Balance Sheet'!M21/'Income Statement'!M6*365 -> 72.927709 | O18: Day sales outstanding | P18: =('Balance Sheet'!P24)/'Income Statement'!P5*365 -> 54.394242 | Q18: =('Balance Sheet'!Q24)/'Income Statement'!Q5*365 -> 55.469511 | R18: =('Balance Sheet'!R24)/'Income Statement'!R5*365 -> 49.904508 | S18: =('Balance Sheet'!S24)/'Income Statement'!S5*365 -> 44.874711 | T18: =('Balance Sheet'!T24)/'Income Statement'!T5*365 -> 42.698242 | V18: Day sales outstanding | W18: =('Balance Sheet'!W22/'Income Statement'!W6)*365 -> 66.742838 | X18: =('Balance Sheet'!X22/'Income Statement'!X6)*365 -> 49.168311 | Y18: =('Balance Sheet'!Y22/'Income Statement'!Y6)*365 -> 28.003066 | Z18: =('Balance Sheet'!Z22/'Income Statement'!Z6)*365 -> 51.45378 | AA18: =('Balance Sheet'!AA22/'Income Statement'!AA6)*365 -> 25.801727 | AC18: Day sales outstanding | AD18: ='Balance Sheet'!AD22/'Income Statement'!AD6*365 -> 65.984294 | AE18: ='Balance Sheet'!AE22/'Income Statement'!AE6*365 -> 55.969476 | AF18: ='Balance Sheet'!AF22/'Income Statement'!AF6*365 -> 75.628132 | AG18: ='Balance Sheet'!AG22/'Income Statement'!AG6*365 -> 59.115477 | AH18: ='Balance Sheet'!AH22/'Income Statement'!AH6*365 -> 67.190547
A19: Market value ratios | H19: Market value ratios | O19: Market value ratios | V19: Market value ratios | AC19: Market value ratios
A20: Price-to-earning ratio | B20: =B24/('Income Statement'!B25/'Financial Ratio'!B26) -> -6.1038435 | C20: =C24/('Income Statement'!C25/'Financial Ratio'!C26) -> 25.829489 | D20: =D24/('Income Statement'!D25/'Financial Ratio'!D26) -> 14.535286 | E20: =E24/('Income Statement'!E25/'Financial Ratio'!E26) -> 6.889222 | F20: =F24/('Income Statement'!F25/'Financial Ratio'!F26) -> 9.8844591 | H20: Price-to-earning ratio | I20: =I24/('Income Statement'!I32/'Financial Ratio'!I26) -> -0.43116244 | J20: =J24/('Income Statement'!J32/'Financial Ratio'!J26) -> 7.8687377 | K20: =K24/('Income Statement'!K32/'Financial Ratio'!K26) -> -9.2145616 | L20: =L24/('Income Statement'!L32/'Financial Ratio'!L26) -> -8.7410445 | M20: =M24/('Income Statement'!M32/'Financial Ratio'!M26) -> -5.6485522 | O20: Price-to-earning ratio | P20: =P24/('Income Statement'!P44/'Financial Ratio'!P26) -> 10.886117 | Q20: =Q24/('Income Statement'!Q44/'Financial Ratio'!Q26) -> 22.932244 | R20: =R24/('Income Statement'!R44/'Financial Ratio'!R26) -> 35.375525 | S20: =S24/('Income Statement'!S44/'Financial Ratio'!S26) -> 15.956916 | T20: =T24/('Income Statement'!T44/'Financial Ratio'!T26) -> 29.428921 | V20: Price-to-earning ratio | W20: =W24/('Income Statement'!W24/'Financial Ratio'!W26) -> 7.6107753 | X20: =X24/('Income Statement'!X24/'Financial Ratio'!X26) -> 18.636143 | Y20: =Y24/('Income Statement'!Y24/'Financial Ratio'!Y26) -> 30.249813 | Z20: =Z24/('Income Statement'!Z24/'Financial Ratio'!Z26) -> 28.398469 | AA20: =AA24/('Income Statement'!AA24/'Financial Ratio'!AA26) -> 53.489194 | AC20: Price-to-earning ratio | AD20: =AD24/('Income Statement'!AD27/'Financial Ratio'!AD26) -> 7.80033 | AE20: =AE24/('Income Statement'!AE27/'Financial Ratio'!AE26) -> 6.9018981 | AF20: =AF24/('Income Statement'!AF27/'Financial Ratio'!AF26) -> 7.7182701 | AG20: =AG24/('Income Statement'!AG27/'Financial Ratio'!AG26) -> 9.9167102 | AH20: =AH24/('Income Statement'!AH27/'Financial Ratio'!AH26) -> 15.26383
A21: Price-to-book ratio | B21: =B24/B25 -> 2.1425734 | C21: =C24/C25 -> 2.5016346 | D21: =D24/D25 -> 3.8170101 | E21: =E24/E25 -> 2.4735254 | F21: =F24/F25 -> 4.7718433 | H21: Price-to-book ratio | I21: =I24/I25 -> 0.13293887 | J21: =J24/J25 -> 0.13023375 | K21: =K24/K25 -> 0.3964183 | L21: =L24/L25 -> 0.3096998 | M21: =M24/M25 -> 1.0059836 | O21: Price-to-book ratio | P21: =P24/P25 -> 0.6544379 | Q21: =Q24/Q25 -> 1.3066157 | R21: =R24/R25 -> 2.9297098 | S21: =S24/S25 -> 1.7772883 | T21: =T24/T25 -> 3.2859281 | V21: Price-to-book ratio | W21: =W24/W25 -> 0.70803423 | X21: =X24/X25 -> 1.0574759 | Y21: =Y24/Y25 -> 3.0280798 | Z21: =Z24/Z25 -> 2.2436606 | AA21: =AA24/AA25 -> 4.3924324 | AC21: Price-to-book ratio | AD21: =AD24/AD25 -> 0.76044698 | AE21: =AE24/AE25 -> 0.79928462 | AF21: =AF24/AF25 -> 0.9408481 | AG21: =AG24/AG25 -> 1.1247658 | AH21: =AH24/AH25 -> 1.9719436
A22: Dividend yield | B22: 0 | C22: 0 | D22: 0 | E22: 0 | F22: 0 | H22: Dividend yield | I22: 0 | J22: 0 | K22: 0 | L22: 0 | M22: 0 | O22: Dividend yield | P22: =(-'Cash Flow Statement'!P79/'Financial Ratio'!P26)/'Financial Ratio'!P24 -> 0.006880228 | Q22: =(-'Cash Flow Statement'!Q79/'Financial Ratio'!Q26)/'Financial Ratio'!Q24 -> 0 | R22: =(-'Cash Flow Statement'!R79/'Financial Ratio'!R26)/'Financial Ratio'!R24 -> 0.0073241609 | S22: =(-'Cash Flow Statement'!S79/'Financial Ratio'!S26)/'Financial Ratio'!S24 -> 0.012944275 | T22: =(-'Cash Flow Statement'!T79/'Financial Ratio'!T26)/'Financial Ratio'!T24 -> 0.0050736461 | V22: Dividend yield | W22: =(-'Cash Flow Statement'!W55/'Financial Ratio'!W26)/'Financial Ratio'!W24 -> 0.02404535 | X22: =(-'Cash Flow Statement'!X55/'Financial Ratio'!X26)/'Financial Ratio'!X24 -> 0.010715137 | Y22: =(-'Cash Flow Statement'!Y55/'Financial Ratio'!Y26)/'Financial Ratio'!Y24 -> 0.0062317093 | Z22: =(-'Cash Flow Statement'!Z55/'Financial Ratio'!Z26)/'Financial Ratio'!Z24 -> 0.0078226367 | AA22: =(-'Cash Flow Statement'!AA55/'Financial Ratio'!AA26)/'Financial Ratio'!AA24 -> 0.0037573821 | AC22: Dividend yield | AD22: =(-'Cash Flow Statement'!AD51/'Financial Ratio'!AD26)/'Financial Ratio'!AD24 -> 0.040638935 | AE22: =(-'Cash Flow Statement'!AE51/'Financial Ratio'!AE26)/'Financial Ratio'!AE24 -> 0.055928886 | AF22: =(-'Cash Flow Statement'!AF51/'Financial Ratio'!AF26)/'Financial Ratio'!AF24 -> 0.054291118 | AG22: =(-'Cash Flow Statement'!AG51/'Financial Ratio'!AG26)/'Financial Ratio'!AG24 -> 0.042688133 | AH22: =(-'Cash Flow Statement'!AH51/'Financial Ratio'!AH26)/'Financial Ratio'!AH24 -> 0.022786119
A23: EV/EBITDA | B23: =((B24*B26)+'Balance Sheet'!B41+'Balance Sheet'!B50-'Balance Sheet'!B22)/'Income Statement'!B16 -> -51.755557 | C23: =((C24*C26)+'Balance Sheet'!C41+'Balance Sheet'!C50-'Balance Sheet'!C22)/'Income Statement'!C16 -> 37.182539 | D23: =((D24*D26)+'Balance Sheet'!D41+'Balance Sheet'!D50-'Balance Sheet'!D22)/'Income Statement'!D16 -> 18.154503 | E23: =((E24*E26)+'Balance Sheet'!E41+'Balance Sheet'!E50-'Balance Sheet'!E22)/'Income Statement'!E16 -> 15.088671 | F23: =((F24*F26)+'Balance Sheet'!F41+'Balance Sheet'!F50-'Balance Sheet'!F22)/'Income Statement'!F16 -> 11.504789 | H23: EV/EBITDA | I23: =((I24*I26)+'Balance Sheet'!I41+'Balance Sheet'!I49-'Balance Sheet'!I22)/'Income Statement'!I14 -> -113.61153 | J23: =((J24*J26)+'Balance Sheet'!J41+'Balance Sheet'!J49-'Balance Sheet'!J22)/'Income Statement'!J14 -> 54.64044 | K23: =((K24*K26)+'Balance Sheet'!K41+'Balance Sheet'!K49-'Balance Sheet'!K22)/'Income Statement'!K14 -> -54.722603 | L23: =((L24*L26)+'Balance Sheet'!L41+'Balance Sheet'!L49-'Balance Sheet'!L22)/'Income Statement'!L14 -> -18.820515 | M23: =((M24*M26)+'Balance Sheet'!M41+'Balance Sheet'!M49-'Balance Sheet'!M22)/'Income Statement'!M14 -> -15.07119 | O23: EV/EBITDA | P23: =((P24*P26)+'Balance Sheet'!P49+'Balance Sheet'!P60-'Balance Sheet'!P26)/'Income Statement'!P17 -> 41.366567 | Q23: =((Q24*Q26)+'Balance Sheet'!Q49+'Balance Sheet'!Q60-'Balance Sheet'!Q26)/'Income Statement'!Q17 -> 110.67905 | R23: =((R24*R26)+'Balance Sheet'!R49+'Balance Sheet'!R60-'Balance Sheet'!R26)/'Income Statement'!R17 -> 83.293856 | S23: =((S24*S26)+'Balance Sheet'!S49+'Balance Sheet'!S60-'Balance Sheet'!S26)/'Income Statement'!S17 -> 79.172137 | T23: =((T24*T26)+'Balance Sheet'!T49+'Balance Sheet'!T60-'Balance Sheet'!T26)/'Income Statement'!T17 -> 41.100327 | V23: EV/EBITDA | W23: =((W24*W26)+'Balance Sheet'!W41+'Balance Sheet'!W50-'Balance Sheet'!W24)/'Income Statement'!W17 -> 15.537889 | X23: =((X24*X26)+'Balance Sheet'!X41+'Balance Sheet'!X50-'Balance Sheet'!X24)/'Income Statement'!X17 -> 20.232409 | Y23: =((Y24*Y26)+'Balance Sheet'!Y41+'Balance Sheet'!Y50-'Balance Sheet'!Y24)/'Income Statement'!Y17 -> 27.274339 | Z23: =((Z24*Z26)+'Balance Sheet'!Z41+'Balance Sheet'!Z50-'Balance Sheet'!Z24)/'Income Statement'!Z17 -> 34.796292 | AA23: =((AA24*AA26)+'Balance Sheet'!AA41+'Balance Sheet'!AA50-'Balance Sheet'!AA24)/'Income Statement'!AA17 -> 55.601246 | AC23: EV/EBITDA | AD23: =((AD24*AD26)+'Balance Sheet'!AD42+'Balance Sheet'!AD51-'Balance Sheet'!AD23)/'Income Statement'!AD15 -> 17.836179 | AE23: =((AE24*AE26)+'Balance Sheet'!AE42+'Balance Sheet'!AE51-'Balance Sheet'!AE23)/'Income Statement'!AE15 -> 18.363634 | AF23: =((AF24*AF26)+'Balance Sheet'!AF42+'Balance Sheet'!AF51-'Balance Sheet'!AF23)/'Income Statement'!AF15 -> 17.424103 | AG23: =((AG24*AG26)+'Balance Sheet'!AG42+'Balance Sheet'!AG51-'Balance Sheet'!AG23)/'Income Statement'!AG15 -> 16.522864 | AH23: =((AH24*AH26)+'Balance Sheet'!AH42+'Balance Sheet'!AH51-'Balance Sheet'!AH23)/'Income Statement'!AH15 -> 21.947466
A24: Market price per share | B24: 36 | C24: 85.05 | D24: 185.1 | E24: 191.6 | F24: 533.8 | H24: Market price per share | I24: 4.25 | J24: 4.35 | K24: 13.5 | L24: 9.95 | M24: 28.25 | O24: Market price per share | P24: 44.85 | Q24: 103.25 | R24: 238.65 | S24: 190.25 | T24: 394.2 | V24: Market price per share | W24: 47.15 | X24: 87.85 | Y24: 302.2 | Z24: 240.85 | AA24: 528.9 | AC24: Market price per share | AD24: 95.8 | AE24: 106.55 | AF24: 135 | AG24: 175.1 | AH24: 335.8
A25: Book value per share | B25: ='Balance Sheet'!B37/'Financial Ratio'!B26 -> 16.802225 | C25: ='Balance Sheet'!C37/'Financial Ratio'!C26 -> 33.99777 | D25: ='Balance Sheet'!D37/'Financial Ratio'!D26 -> 48.493453 | E25: ='Balance Sheet'!E37/'Financial Ratio'!E26 -> 77.460292 | F25: ='Balance Sheet'!F37/'Financial Ratio'!F26 -> 111.86453 | H25: Book value per share | I25: ='Balance Sheet'!I37/'Financial Ratio'!I26 -> 31.969582 | J25: ='Balance Sheet'!J37/'Financial Ratio'!J26 -> 33.40148 | K25: ='Balance Sheet'!K37/'Financial Ratio'!K26 -> 34.054936 | L25: ='Balance Sheet'!L37/'Financial Ratio'!L26 -> 32.127886 | M25: ='Balance Sheet'!M37/'Financial Ratio'!M26 -> 28.081969 | O25: Book value per share | P25: ='Balance Sheet'!P45/'Financial Ratio'!P26 -> 68.532094 | Q25: ='Balance Sheet'!Q45/'Financial Ratio'!Q26 -> 79.020937 | R25: ='Balance Sheet'!R45/'Financial Ratio'!R26 -> 81.45858 | S25: ='Balance Sheet'!S45/'Financial Ratio'!S26 -> 107.0451 | T25: ='Balance Sheet'!T45/'Financial Ratio'!T26 -> 119.96611 | V25: Book value per share | W25: ='Balance Sheet'!W37/'Financial Ratio'!W26 -> 66.592826 | X25: ='Balance Sheet'!X37/'Financial Ratio'!X26 -> 83.075178 | Y25: ='Balance Sheet'!Y37/'Financial Ratio'!Y26 -> 99.799221 | Z25: ='Balance Sheet'!Z37/'Financial Ratio'!Z26 -> 107.34689 | AA25: ='Balance Sheet'!AA37/'Financial Ratio'!AA26 -> 120.41164 | AC25: Book value per share | AD25: ='Balance Sheet'!AD38/'Financial Ratio'!AD26 -> 125.97854 | AE25: ='Balance Sheet'!AE38/'Financial Ratio'!AE26 -> 133.30671 | AF25: ='Balance Sheet'!AF38/'Financial Ratio'!AF26 -> 143.48756 | AG25: ='Balance Sheet'!AG38/'Financial Ratio'!AG26 -> 155.67686 | AH25: ='Balance Sheet'!AH38/'Financial Ratio'!AH26 -> 170.28884
A26: Shares outstanding (total) | B26: 385.69 | C26: 385.69 | D26: 385.69 | E26: 385.69 | F26: 385.69 | H26: Shares outstanding (total) | I26: 413.57 | J26: 413.57 | K26: 413.57 | L26: 413.57 | M26: 413.57 | O26: Shares outstanding (total) | P26: 319.53 | Q26: 319.53 | R26: 319.53 | S26: 319.53 | T26: 319.53 | V26: Shares outstanding (total) | W26: 174.52 | X26: 174.52 | Y26: 174.52 | Z26: 174.52 | AA26: 174.52 | AC26: Shares outstanding (total in cr) | AD26: 969.66 | AE26: 969.66 | AF26: 969.66 | AG26: 969.66 | AH26: 969.66
A27: EPS | B27: ='Income Statement'!B25/'Company Profile'!$B$15 -> -1.1795724 | C27: ='Income Statement'!C25/'Company Profile'!$B$15 -> 0.65854278 | D27: ='Income Statement'!D25/'Company Profile'!$B$15 -> 2.5468791 | E27: ='Income Statement'!E25/'Company Profile'!$B$15 -> 5.562254 | F27: ='Income Statement'!F25/'Company Profile'!$B$15 -> 10.800681 | H27: EPS | I27: ='Income Statement'!I32/'Company Profile'!$C$15 -> -9.8569046 | J27: ='Income Statement'!J32/'Company Profile'!$C$15 -> 0.55281107 | K27: ='Income Statement'!K32/'Company Profile'!$C$15 -> -1.4650473 | L27: ='Income Statement'!L32/'Company Profile'!$C$15 -> -1.1382884 | M27: ='Income Statement'!M32/'Company Profile'!$C$15 -> -5.0011957 | O27: EPS | P27: ='Income Statement'!P44/'Company Profile'!$D$15 -> 4.1198746 | Q27: ='Income Statement'!Q44/'Company Profile'!$D$15 -> 4.5023378 | R27: ='Income Statement'!R44/'Company Profile'!$D$15 -> 6.7461053 | S27: ='Income Statement'!S44/'Company Profile'!$D$15 -> 11.922581 | T27: ='Income Statement'!T44/'Company Profile'!$D$15 -> 13.394819 | V27: EPS | W27: ='Income Statement'!W24/'Company Profile'!$E$15 -> 6.1905419 | X27: ='Income Statement'!X24/'Company Profile'!$E$15 -> 4.7104414 | Y27: ='Income Statement'!Y24/'Company Profile'!$E$15 -> 9.9826911 | Z27: ='Income Statement'!Z24/'Company Profile'!$E$15 -> 8.4747636 | AA27: ='Income Statement'!AA24/'Company Profile'!$E$15 -> 9.8806014 | AC27: EPS | AD27: ='Income Statement'!AD27/'Company Profile'!$F$15 -> 12.281448 | AE27: ='Income Statement'!AE27/'Company Profile'!$F$15 -> 15.437677 | AF27: ='Income Statement'!AF27/'Company Profile'!$F$15 -> 17.490847 | AG27: ='Income Statement'!AG27/'Company Profile'!$F$15 -> 17.656945 | AH27: ='Income Statement'!AH27/'Company Profile'!$F$15 -> 21.999572
A28: Market Cap | B28: =B24*B26 -> 13884.84 | C28: =C24*C26 -> 32802.934 | D28: =D24*D26 -> 71391.219 | E28: =E24*E26 -> 73898.204 | F28: =F24*F26 -> 205881.32 | H28: Market Cap | I28: =I24*I26 -> 1757.6725 | J28: =J24*J26 -> 1799.0295 | K28: =K24*K26 -> 5583.195 | L28: =L24*L26 -> 4115.0215 | M28: =M24*M26 -> 11683.352 | O28: Market Cap | P28: =P24*P26 -> 14330.92 | Q28: =Q24*Q26 -> 32991.472 | R28: =R24*R26 -> 76255.834 | S28: =S24*S26 -> 60790.582 | T28: =T24*T26 -> 125958.73 | V28: Market Cap | W28: =W24*W26 -> 8228.618 | X28: =X24*X26 -> 15331.582 | Y28: =Y24*Y26 -> 52739.944 | Z28: =Z24*Z26 -> 42033.142 | AA28: =AA24*AA26 -> 92303.628 | AC28: Market Cap | AD28: =AD24*AD26 -> 92893.428 | AE28: =AE24*AE26 -> 103317.27 | AF28: =AF24*AF26 -> 130904.1 | AG28: =AG24*AG26 -> 169787.47 | AH28: =AH24*AH26 -> 325611.83
A29: D/CE | B29: =('Balance Sheet'!B41+'Balance Sheet'!B50)/('Balance Sheet'!B29-'Balance Sheet'!B57) -> 0.92139292 | C29: =('Balance Sheet'!C41+'Balance Sheet'!C50)/('Balance Sheet'!C29-'Balance Sheet'!C57) -> 0.87237893 | D29: =('Balance Sheet'!D41+'Balance Sheet'!D50)/('Balance Sheet'!D29-'Balance Sheet'!D57) -> 0.75258597 | E29: =('Balance Sheet'!E41+'Balance Sheet'!E50)/('Balance Sheet'!E29-'Balance Sheet'!E57) -> 0.6206538 | F29: =('Balance Sheet'!F41+'Balance Sheet'!F50)/('Balance Sheet'!F29-'Balance Sheet'!F57) -> 0.45020402 | I29: =('Balance Sheet'!I41+'Balance Sheet'!I49)/('Balance Sheet'!I30-'Balance Sheet'!I55) -> 0.64761567 | J29: =('Balance Sheet'!J41+'Balance Sheet'!J49)/('Balance Sheet'!J30-'Balance Sheet'!J55) -> 0.59175501 | K29: =('Balance Sheet'!K41+'Balance Sheet'!K49)/('Balance Sheet'!K30-'Balance Sheet'!K55) -> 0.7093165 | L29: =('Balance Sheet'!L41+'Balance Sheet'!L49)/('Balance Sheet'!L30-'Balance Sheet'!L55) -> 0.70407482 | M29: =('Balance Sheet'!M41+'Balance Sheet'!M49)/('Balance Sheet'!M30-'Balance Sheet'!M55) -> 0.72516455 | P29: =('Balance Sheet'!P49+'Balance Sheet'!P60)/('Balance Sheet'!P37-'Balance Sheet'!P67) -> 0.7044411 | Q29: =('Balance Sheet'!Q49+'Balance Sheet'!Q60)/('Balance Sheet'!Q37-'Balance Sheet'!Q67) -> 0.56520954 | R29: =('Balance Sheet'!R49+'Balance Sheet'!R60)/('Balance Sheet'!R37-'Balance Sheet'!R67) -> 0.64081762 | S29: =('Balance Sheet'!S49+'Balance Sheet'!S60)/('Balance Sheet'!S37-'Balance Sheet'!S67) -> 0.58047333 | T29: =('Balance Sheet'!T49+'Balance Sheet'!T60)/('Balance Sheet'!T37-'Balance Sheet'!T67) -> 0.5027643 | W29: =('Balance Sheet'!W41+'Balance Sheet'!W50)/('Balance Sheet'!W30-'Balance Sheet'!W58) -> 0.39932449 | X29: =('Balance Sheet'!X41+'Balance Sheet'!X50)/('Balance Sheet'!X30-'Balance Sheet'!X58) -> 0.31759133 | Y29: =('Balance Sheet'!Y41+'Balance Sheet'!Y50)/('Balance Sheet'!Y30-'Balance Sheet'!Y58) -> 0.34414267 | Z29: =('Balance Sheet'!Z41+'Balance Sheet'!Z50)/('Balance Sheet'!Z30-'Balance Sheet'!Z58) -> 0.62455129 | AA29: =('Balance Sheet'!AA41+'Balance Sheet'!AA50)/('Balance Sheet'!AA30-'Balance Sheet'!AA58) -> 0.61425135 | AD29: =('Balance Sheet'!AD42+'Balance Sheet'!AD51)/('Balance Sheet'!AD31-'Balance Sheet'!AD60) -> 0.61341012 | AE29: =('Balance Sheet'!AE42+'Balance Sheet'!AE51)/('Balance Sheet'!AE31-'Balance Sheet'!AE60) -> 0.60152653 | AF29: =('Balance Sheet'!AF42+'Balance Sheet'!AF51)/('Balance Sheet'!AF31-'Balance Sheet'!AF60) -> 0.61647586 | AG29: =('Balance Sheet'!AG42+'Balance Sheet'!AG51)/('Balance Sheet'!AG31-'Balance Sheet'!AG60) -> 0.6080592 | AH29: =('Balance Sheet'!AH42+'Balance Sheet'!AH51)/('Balance Sheet'!AH31-'Balance Sheet'!AH60) -> 0.61562358

Sheet Key Assumptions
A1: KEY ASSUMPTIONS (ADANI POWER) | F1: #VALUE! | I1: KEY ASSUMPTIONS (Reliance Power) | N1: #VALUE! | Q1: FINANCIAL RATIOS (TATA Power) | V1: #VALUE! | Y1: FINANCIAL RATIOS (JSW Energy) | AD1: #VALUE! | AG1: FINANCIAL RATIOS (NTPC) | AL1: #VALUE!
A2: Particulars | B2: Mar 20 | C2: Mar 21 | D2: Mar 22 | E2: Mar 23 | F2: Mar 24 | I2: Particulars | J2: Mar 20 | K2: Mar 21 | L2: Mar 22 | M2: Mar 23 | N2: Mar 24 | Q2: Particulars | R2: Mar 20 | S2: Mar 21 | T2: Mar 22 | U2: Mar 23 | V2: Mar 24 | Y2: Particulars | Z2: Mar 20 | AA2: Mar 21 | AB2: Mar 22 | AC2: Mar 23 | AD2: Mar 24 | AG2: Particulars | AH2: Mar 20 | AI2: Mar 21 | AJ2: Mar 22 | AK2: Mar 23 | AL2: Mar 24
A3: Market Price as of Last year (Rs) | D3: ='Financial Ratio'!F24 -> 533.8 | I3: Market Price as of Last year (Rs) | L3: ='Financial Ratio'!M24 -> 28.25 | Q3: Market Price as of Last year (Rs) | T3: ='Financial Ratio'!T24 -> 394.2 | Y3: Market Price as of Last year (Rs) | AB3: ='Financial Ratio'!AA24 -> 528.9 | AG3: Market Price as of Last year (Rs) | AJ3: ='Financial Ratio'!AH24 -> 335.8
A4: Key Metrics & Assumptions | G4: Average | I4: Key Metrics & Assumptions | O4: Average | Q4: Key Metrics & Assumptions | W4: Average | Y4: Key Metrics & Assumptions | AE4: Average | AG4: Key Metrics & Assumptions | AM4: Average
A5: Revenue Y-o-Y growth | C5: =('Income Statement'!C6-'Income Statement'!B6)/'Income Statement'!B6 -> 0.01105783 | D5: =('Income Statement'!D6-'Income Statement'!C6)/'Income Statement'!C6 -> 0.12564228 | E5: =('Income Statement'!E6-'Income Statement'!D6)/'Income Statement'!D6 -> 0.35832486 | F5: =('Income Statement'!F6-'Income Statement'!E6)/'Income Statement'!E6 -> 0.40057509 | G5: =AVERAGE(C5:F5) -> 0.22390001 | I5: Revenue Y-o-Y growth | K5: =('Income Statement'!J6-'Income Statement'!I6)/'Income Statement'!I6 -> 0.022699426 | L5: =('Income Statement'!K6-'Income Statement'!J6)/'Income Statement'!J6 -> -0.083669504 | M5: =('Income Statement'!L6-'Income Statement'!K6)/'Income Statement'!K6 -> 0.02549979 | N5: =('Income Statement'!M6-'Income Statement'!L6)/'Income Statement'!L6 -> 0.047888171 | O5: =('Income Statement'!M6/'Income Statement'!K6)^(1/3)-1 -> 0.024275625 | Q5: Revenue Y-o-Y growth | S5: =('Income Statement'!Q5-'Income Statement'!P5)/'Income Statement'!P5 -> 0.1080293 | T5: =('Income Statement'!R5-'Income Statement'!Q5)/'Income Statement'!Q5 -> 0.32905394 | U5: =('Income Statement'!S5-'Income Statement'!R5)/'Income Statement'!R5 -> 0.29292981 | V5: =('Income Statement'!T5-'Income Statement'!S5)/'Income Statement'!S5 -> 0.1189313 | W5: =AVERAGE(R5:V5) -> 0.21223609 | Y5: Revenue Y-o-Y growth | AA5: =('Income Statement'!X4-'Income Statement'!W4)/'Income Statement'!W4 -> -0.1632488 | AB5: =('Income Statement'!Y4-'Income Statement'!X4)/'Income Statement'!X4 -> 0.17984889 | AC5: =('Income Statement'!Z4-'Income Statement'!Y4)/'Income Statement'!Y4 -> 0.26504472 | AD5: =('Income Statement'!AA4-'Income Statement'!Z4)/'Income Statement'!Z4 -> 0.11180035 | AE5: =AVERAGE(Z5:AD5) -> 0.098361291 | AG5: Revenue Y-o-Y growth | AI5: =('Income Statement'!AE6-'Income Statement'!AD6)/'Income Statement'!AD6 -> 0.028247549 | AJ5: =('Income Statement'!AF6-'Income Statement'!AE6)/'Income Statement'!AE6 -> 0.16830821 | AK5: =('Income Statement'!AG6-'Income Statement'!AF6)/'Income Statement'!AF6 -> 0.31840498 | AL5: =('Income Statement'!AH6-'Income Statement'!AG6)/'Income Statement'!AG6 -> 0.017916287 | AM5: =AVERAGE(AH5:AL5) -> 0.13321926
A6: EBIT Margin | B6: ='Financial Ratio'!B5 -> -0.045324999 | C6: ='Financial Ratio'!C5 -> 0.081306075 | D6: ='Financial Ratio'!D5 -> 0.20756903 | E6: ='Financial Ratio'!E5 -> 0.17831337 | F6: ='Financial Ratio'!F5 -> 0.34490709 | G6: =AVERAGE(B6:F6) -> 0.15335411 | I6: EBIT Margin | J6: ='Financial Ratio'!I5 -> -0.027735751 | K6: ='Financial Ratio'!J5 -> 0.048607634 | L6: ='Financial Ratio'!K5 -> -0.067831184 | M6: ='Financial Ratio'!L5 -> -0.16926982 | N6: ='Financial Ratio'!M5 -> -0.24068337 | O6: =AVERAGE(J6:N6) -> -0.091382499 | Q6: EBIT Margin | R6: ='Financial Ratio'!P5 -> 0.046403614 | S6: ='Financial Ratio'!Q5 -> 0.018585215 | T6: ='Financial Ratio'!R5 -> 0.033151689 | U6: ='Financial Ratio'!S5 -> 0.023581934 | V6: ='Financial Ratio'!T5 -> 0.066184708 | W6: =AVERAGE(R6:V6) -> 0.037581432 | Y6: EBIT Margin | Z6: ='Financial Ratio'!W5 -> 0.12299044 | AA6: ='Financial Ratio'!X5 -> 0.15344186 | AB6: ='Financial Ratio'!Y5 -> 0.25621692 | AC6: ='Financial Ratio'!Z5 -> 0.1677401 | AD6: ='Financial Ratio'!AA5 -> 0.18153143 | AE6: =AVERAGE(Z6:AD6) -> 0.17638415 | AG6: EBIT Margin | AH6: ='Financial Ratio'!AD5 -> 0.14574232 | AI6: ='Financial Ratio'!AE5 -> 0.14711723 | AJ6: ='Financial Ratio'!AF5 -> 0.15201315 | AK6: ='Financial Ratio'!AG5 -> 0.13670624 | AL6: ='Financial Ratio'!AH5 -> 0.14981548 | AM6: =AVERAGE(AH6:AL6) -> 0.14627888
A7: CapEX as % of revenue | B7: =(-'Cash Flow Statement'!B31/'Income Statement'!B6) -> 0.079971812 | C7: =(-'Cash Flow Statement'!C31/'Income Statement'!C6) -> 0.12851336 | D7: =(-'Cash Flow Statement'!D31/'Income Statement'!D6) -> 0.10839169 | E7: =(-'Cash Flow Statement'!E31/'Income Statement'!E6) -> 0.075363402 | F7: =(-'Cash Flow Statement'!F31/'Income Statement'!F6) -> 0.043171634 | G7: =AVERAGE(B7:F7) -> 0.08708238 | I7: CapEX as % of revenue | J7: =(-'Cash Flow Statement'!I33/'Income Statement'!I6) -> 0.042187601 | K7: =(-'Cash Flow Statement'!J33/'Income Statement'!J6) -> 0.015941873 | L7: =(-'Cash Flow Statement'!K33/'Income Statement'!K6) -> 0.025519304 | M7: =(-'Cash Flow Statement'!L33/'Income Statement'!L6) -> 0.048776187 | N7: =(-'Cash Flow Statement'!M33/'Income Statement'!M6) -> -0.0062298507 | O7: =AVERAGE(J7:N7) -> 0.025239023 | Q7: CapEX as % of revenue | R7: =(-'Cash Flow Statement'!P55/'Income Statement'!P5) -> 0.074945672 | S7: =(-'Cash Flow Statement'!Q55/'Income Statement'!Q5) -> 0.10136918 | T7: =(-'Cash Flow Statement'!R55/'Income Statement'!R5) -> 0.1661771 | U7: =(-'Cash Flow Statement'!S55/'Income Statement'!S5) -> 0.13539174 | V7: =(-'Cash Flow Statement'!T55/'Income Statement'!T5) -> 0.21072011 | W7: =AVERAGE(R7:V7) -> 0.13772076 | Y7: CapEX as % of revenue | Z7: =(-'Cash Flow Statement'!W32/'Income Statement'!W6) -> 0.014194439 | AA7: =(-'Cash Flow Statement'!X32/'Income Statement'!X6) -> 0.060818615 | AB7: =(-'Cash Flow Statement'!Y32/'Income Statement'!Y6) -> 0.2626044 | AC7: =(-'Cash Flow Statement'!Z32/'Income Statement'!Z6) -> 0.38983073 | AD7: =(-'Cash Flow Statement'!AA32/'Income Statement'!AA6) -> 0.67262948 | AE7: =AVERAGE(Z7:AD7) -> 0.28001553 | AG7: CapEX as % of revenue | AH7: =(-'Cash Flow Statement'!AD36/'Income Statement'!AD6) -> 0.1622321 | AI7: =(-'Cash Flow Statement'!AE36/'Income Statement'!AE6) -> 0.20175664 | AJ7: =(-'Cash Flow Statement'!AF36/'Income Statement'!AF6) -> 0.18107741 | AK7: =(-'Cash Flow Statement'!AG36/'Income Statement'!AG6) -> 0.13944777 | AL7: =(-'Cash Flow Statement'!AH36/'Income Statement'!AH6) -> 0.17009783 | AM7: =AVERAGE(AH7:AL7) -> 0.17092235
A8: Depreciation as % of revenue | B8: ='Income Statement'!B13/'Income Statement'!B6 -> 0.10798508 | C8: ='Income Statement'!C13/'Income Statement'!C6 -> 0.11373664 | D8: ='Income Statement'!D13/'Income Statement'!D6 -> 0.098387103 | E8: ='Income Statement'!E13/'Income Statement'!E6 -> 0.076757437 | F8: ='Income Statement'!F13/'Income Statement'!F6 -> 0.065216216 | G8: =AVERAGE(B8:F8) -> 0.092416494 | I8: Depreciation as % of revenue | J8: ='Income Statement'!I11/'Income Statement'!I6 -> 0.10195784 | K8: ='Income Statement'!J11/'Income Statement'!J6 -> 0.12912882 | L8: ='Income Statement'!K11/'Income Statement'!K6 -> 0.14014802 | M8: ='Income Statement'!L11/'Income Statement'!L6 -> 0.13101155 | N8: ='Income Statement'!M11/'Income Statement'!M6 -> 0.12853758 | O8: =AVERAGE(J8:N8) -> 0.12615676 | Q8: Depreciation as % of revenue | R8: ='Income Statement'!P14/'Income Statement'!P5 -> 0.088675099 | S8: ='Income Statement'!Q14/'Income Statement'!Q5 -> 0.083414217 | T8: ='Income Statement'!R14/'Income Statement'!R5 -> 0.071388019 | U8: ='Income Statement'!S14/'Income Statement'!S5 -> 0.060820095 | V8: ='Income Statement'!T14/'Income Statement'!T5 -> 0.05984244 | W8: =AVERAGE(R8:V8) -> 0.072827974 | Y8: Depreciation as % of revenue | Z8: ='Income Statement'!W13/'Income Statement'!W6 -> 0.13645938 | AA8: ='Income Statement'!X13/'Income Statement'!X6 -> 0.16298841 | AB8: ='Income Statement'!Y13/'Income Statement'!Y6 -> 0.12947238 | AC8: ='Income Statement'!Z13/'Income Statement'!Z6 -> 0.10759406 | AD8: ='Income Statement'!AA13/'Income Statement'!AA6 -> 0.1367747 | AE8: =AVERAGE(Z8:AD8) -> 0.13465779 | AG8: Depreciation as % of revenue | AH8: ='Income Statement'!AD12/'Income Statement'!AD6 -> 0.092159137 | AI8: ='Income Statement'!AE12/'Income Statement'!AE6 -> 0.1077512 | AJ8: ='Income Statement'!AF12/'Income Statement'!AF6 -> 0.10213638 | AK8: ='Income Statement'!AG12/'Income Statement'!AG6 -> 0.0831133 | AL8: ='Income Statement'!AH12/'Income Statement'!AH6 -> 0.089440858 | AM8: =AVERAGE(AH8:AL8) -> 0.094920176
A9: Working Capital | B9: ='Balance Sheet'!B27-'Balance Sheet'!B57 -> -3595.97 | C9: ='Balance Sheet'!C27-'Balance Sheet'!C57 -> -1878.52 | D9: ='Balance Sheet'!D27-'Balance Sheet'!D57 -> -915.6 | E9: ='Balance Sheet'!E27-'Balance Sheet'!E57 -> 1808.41 | F9: ='Balance Sheet'!F27-'Balance Sheet'!F57 -> 9797.91 | G9: Nil | I9: Working Capital | J9: ='Balance Sheet'!I28-'Balance Sheet'!I55 -> -11099.72 | K9: ='Balance Sheet'!J28-'Balance Sheet'!J55 -> -11060.93 | L9: ='Balance Sheet'!K28-'Balance Sheet'!K55 -> -11487.98 | M9: ='Balance Sheet'!L28-'Balance Sheet'!L55 -> -13422.4 | N9: ='Balance Sheet'!M28-'Balance Sheet'!M55 -> -13343.11 | O9: Nil | Q9: Working Capital | R9: ='Balance Sheet'!P33-'Balance Sheet'!P67 -> -14499.95 | S9: ='Balance Sheet'!Q33-'Balance Sheet'!Q67 -> -14397.01 | T9: ='Balance Sheet'!R33-'Balance Sheet'!R67 -> -17034.66 | U9: ='Balance Sheet'!S33-'Balance Sheet'!S67 -> -16187.59 | V9: ='Balance Sheet'!T33-'Balance Sheet'!T67 -> -13873.58 | Y9: Working Capital | Z9: ='Balance Sheet'!W28-'Balance Sheet'!W58 -> 172.66 | AA9: ='Balance Sheet'!X28-'Balance Sheet'!X58 -> 780.48 | AB9: ='Balance Sheet'!Y28-'Balance Sheet'!Y58 -> 107.65 | AC9: ='Balance Sheet'!Z28-'Balance Sheet'!Z58 -> 516.85 | AD9: ='Balance Sheet'!AA28-'Balance Sheet'!AA58 -> 1395.34 | AG9: Working Capital | AH9: ='Balance Sheet'!AD28-'Balance Sheet'!AD60 -> -7978.48 | AI9: ='Balance Sheet'!AE28-'Balance Sheet'!AE60 -> -14255.64 | AJ9: ='Balance Sheet'!AF28-'Balance Sheet'!AF60 -> -18419.18 | AK9: ='Balance Sheet'!AG28-'Balance Sheet'!AG60 -> -16036.22 | AL9: ='Balance Sheet'!AH28-'Balance Sheet'!AH60 -> -15368.81
A10: Change in Net WC as % of revenue | C10: =((C9-B9)/'Income Statement'!C6) -> 0.061011351 | D10: =((D9-C9)/'Income Statement'!D6) -> 0.030388996 | E10: =((E9-D9)/'Income Statement'!E6) -> 0.063289431 | F10: =((F9-E9)/'Income Statement'!F6) -> 0.13253656 | G10: =AVERAGE(B10:F10) -> 0.071806584 | I10: Change in Net WC as % of revenue | K10: =(K9-J9)/'Income Statement'!J6 -> 0.0046241328 | L10: =(L9-K9)/'Income Statement'!K6 -> -0.055556784 | M10: =(M9-L9)/'Income Statement'!L6 -> -0.24539944 | N10: =(N9-M9)/'Income Statement'!M6 -> 0.0095990063 | O10: =AVERAGE(J10:N10) -> -0.071683272 | Q10: Change in Net WC as % of revenue | S10: =(S9-R9)/'Income Statement'!Q5 -> 0.0031281775 | T10: =(T9-S9)/'Income Statement'!R5 -> -0.060308952 | U10: =(U9-T9)/'Income Statement'!S5 -> 0.014979902 | V10: =(V9-U9)/'Income Statement'!T5 -> 0.036572233 | W10: =AVERAGE(R10:V10) -> -0.00140716 | Y10: Change in Net WC as % of revenue | AA10: =(AA9-Z9)/'Income Statement'!X6 -> 0.084895211 | AB10: =(AB9-AA9)/'Income Statement'!Y6 -> -0.077019497 | AC10: =(AC9-AB9)/'Income Statement'!Z6 -> 0.037655113 | AD10: =(AD9-AC9)/'Income Statement'!AA6 -> 0.07356096 | AE10: =AVERAGE(Z10:AD10) -> 0.029772947 | AG10: Change in Net WC as % of revenue | AI10: =(AI9-AH9)/'Income Statement'!AE6 -> -0.054325679 | AJ10: =(AJ9-AI9)/'Income Statement'!AF6 -> -0.030842337 | AK10: =(AK9-AJ9)/'Income Statement'!AG6 -> 0.013389133 | AL10: =(AL9-AK9)/'Income Statement'!AH6 -> 0.0036839722 | AM10: =AVERAGE(AH10:AL10) -> -0.017023728
A12: Assumptions | I12: Assumptions | Q12: Assumptions | Y12: Assumptions | AG12: Assumptions
A13: Revenue growth rate | B13: =G5 -> 0.22390001 | I13: Revenue growth rate | J13: =O5 -> 0.024275625 | Q13: Revenue growth rate | R13: =W5 -> 0.21223609 | Y13: Revenue growth rate | Z13: =AE5 -> 0.098361291 | AG13: Revenue growth rate | AH13: =AM5 -> 0.13321926
A14: EBIT Margin | B14: =G6 -> 0.15335411 | I14: EBIT Margin | J14: =O6 -> -0.091382499 | Q14: EBIT Margin | R14: =W6 -> 0.037581432 | Y14: EBIT Margin | Z14: =AE6 -> 0.17638415 | AG14: EBIT Margin | AH14: =AM6 -> 0.14627888
A15: Depreciation as % of revenue | B15: =G8 -> 0.092416494 | I15: Depreciation as % of revenue | J15: =O8 -> 0.12615676 | Q15: Depreciation as % of revenue | R15: =W8 -> 0.072827974 | Y15: Depreciation as % of revenue | Z15: =AE8 -> 0.13465779 | AG15: Depreciation as % of revenue | AH15: =AM8 -> 0.094920176
A16: CapEx as % of revenue | B16: =G7 -> 0.08708238 | I16: CapEx as % of revenue | J16: =O7 -> 0.025239023 | Q16: CapEx as % of revenue | R16: =W7 -> 0.13772076 | Y16: CapEx as % of revenue | Z16: =AE7 -> 0.28001553 | AG16: CapEx as % of revenue | AH16: =AM7 -> 0.17092235
A17: Change in NWC as % of revenue | B17: =G10 -> 0.071806584 | I17: Change in NWC as % of revenue | J17: =O10 -> -0.071683272 | Q17: Change in NWC as % of revenue | R17: =W10 -> -0.00140716 | Y17: Change in NWC as % of revenue | Z17: =AE10 -> 0.029772947 | AG17: Change in NWC as % of revenue | AH17: =AM10 -> -0.017023728
A18: Tax Rate | B18: ='Income Statement'!D23/'Income Statement'!D18 -> 0.26528288 | I18: Tax Rate | J18: ='Income Statement'!M24/'Income Statement'!M19 -> -0.10552967 | Q18: Tax Rate | R18: ='Income Statement'!T35/'Income Statement'!T29 -> 0.25329988 | Y18: Tax Rate | Z18: =('Income Statement'!AA21+'Income Statement'!AA22+'Income Statement'!AA23)/'Income Statement'!AA19 -> 0.20400293 | AG18: Tax Rate | AH18: ='Income Statement'!AH24/'Income Statement'!AH19 -> 0.25087827
A19: Risk Free rate (Rf) | B19: 0.07 | I19: Risk Free rate (Rf) | J19: 0.07 | Q19: Risk Free rate (Rf) | R19: 0.07 | Y19: Risk Free rate (Rf) | Z19: 0.07 | AG19: Risk Free rate (Rf) | AH19: 0.07
A20: Market risk premium (Rm-Rf) | B20: =12%-B19 -> 0.05 | I20: Market risk premium (Rm-Rf) | J20: =12%-J19 -> 0.05 | Q20: Market risk premium (Rm-Rf) | R20: =0.12-R19 -> 0.05 | Y20: Market risk premium (Rm-Rf) | Z20: =0.12-Z19 -> 0.05 | AG20: Market risk premium (Rm-Rf) | AH20: =0.12-AH19 -> 0.05
A21: Beta | B21: ='Company Profile'!B17 -> 1.1437 | I21: Beta | J21: ='Company Profile'!C17 -> 2.5566 | Q21: Beta | R21: ='Company Profile'!D17 -> 1.4704 | Y21: Beta | Z21: ='Company Profile'!E17 -> 1.2627 | AG21: Beta | AH21: ='Company Profile'!F17 -> 1.101
A22: Perpetual growth rate (g) | B22: 0.035 | I22: Perpetual growth rate (g) | J22: 0.035 | Q22: Perpetual growth rate (g) | R22: 0.035 | Y22: Perpetual growth rate (g) | Z22: 0.035 | AG22: Perpetual growth rate (g) | AH22: 0.035
A23: Shares Outstanding in cr | B23: 385.69 | I23: Shares Outstanding | J23: ='Financial Ratio'!I26 -> 413.57 | Q23: Shares Outstanding | R23: ='Financial Ratio'!P26 -> 319.53 | Y23: Shares Outstanding | Z23: ='Financial Ratio'!W26 -> 174.52 | AG23: Shares Outstanding | AH23: ='Financial Ratio'!AD26 -> 969.66
A24: Current market price | B24: ='Company Profile'!B13 -> 150.05 | I24: CMP | J24: ='Company Profile'!C13 -> 41.13 | Q24: CMP | R24: ='Company Profile'!D13 -> 395.95 | Y24: CMP | Z24: ='Company Profile'!E13 -> 522.35 | AG24: CMP | AH24: ='Company Profile'!F13 -> 325.45
A25: Market Value of equity in cr | B25: =B23*B24 -> 57872.785 | I25: Market Value of equity | J25: =J23*J24 -> 17010.134 | Q25: Market Value of equity | R25: =R23*R24 -> 126517.9 | Y25: Market Value of equity | Z25: =Z23*Z24 -> 91160.522 | AG25: Market Value of equity | AH25: =AH23*AH24 -> 315575.85
A26: Market value of debt | B26: ='Balance Sheet'!F41+'Balance Sheet'!F50 -> 34456.86 | I26: Market value of debt | J26: ='Balance Sheet'!M41+'Balance Sheet'!M49 -> 18765.83 | Q26: Market value of debt | R26: ='Balance Sheet'!T49+'Balance Sheet'!T60 -> 49479.81 | Y26: Market value of debt | Z26: ='Balance Sheet'!AA41+'Balance Sheet'!AA50 -> 31326.61 | AG26: Market value of debt | AH26: ='Balance Sheet'!AH42+'Balance Sheet'!AH51 -> 235040.3

Sheet FCFF Projections (5y )
A1: FCFF(ADANI POWER) | G1: #VALUE! | K1: FCFF(Reliance Power) | Q1: #VALUE! | U1: FINANCIAL RATIOS (TATA Power) | AA1: #VALUE! | AE1: FINANCIAL RATIOS (JSW Energy) | AK1: #VALUE! | AO1: FINANCIAL RATIOS (NTPC) | AU1: #VALUE!
A2: Metrics | B2: 2024 | C2: Growth rate | D2: 2025 | E2: 2026 | F2: 2027 | G2: 2028 | H2: 2029 | I2: 2030 | K2: Metrics | L2: 2024 | M2: Growth rate | N2: 2025 | O2: 2026 | P2: 2027 | Q2: 2028 | R2: 2029 | S2: 2030 | U2: Particulars | V2: 2024 | W2: Growth rate | X2: 2025 | Y2: 2026 | Z2: 2027 | AA2: 2028 | AB2: 2029 | AC2: 2030 | AE2: Particulars | AF2: 2024 | AG2: Growth rate | AH2: 2025 | AI2: 2026 | AJ2: 2027 | AK2: 2028 | AL2: 2029 | AM2: 2030 | AO2: Particulars | AP2: 2024 | AQ2: Growth rate | AR2: 2025 | AS2: 2026 | AT2: 2027 | AU2: 2028 | AV2: 2029 | AW2: 2030
A3: Revenue | B3: ='Income Statement'!F6 -> 60281.48 | C3: ='Key Assumptions'!B13 -> 0.22390001 | D3: =B3*(1+C3) -> 73778.504 | E3: =D3*(1+C3) -> 90297.512 | F3: =E3*(1+C3) -> 110515.13 | G3: =F3*(1+C3) -> 135259.47 | H3: =G3*(1+$C$3) -> 165544.06 | I3: =H3*(1+$C$3) -> 202609.38 | K3: Revenue | L3: ='Income Statement'!M6 -> 8260.23 | M3: ='Key Assumptions'!J13 -> 0.024275625 | N3: =L3*(1+M3) -> 8460.7522 | O3: =N3*(1+M3) -> 8666.1423 | P3: =O3*(1+M3) -> 8876.5183 | Q3: =P3*(1+M3) -> 9092.0013 | R3: =Q3*(1+$M$3) -> 9312.7154 | S3: =R3*(1+$M$3) -> 9538.7874 | U3: Revenue | V3: ='Income Statement'!T5 -> 63272.32 | W3: ='Key Assumptions'!R13 -> 0.21223609 | X3: =V3*(1+W3) -> 76700.99 | Y3: =X3*(1+W3) -> 92979.708 | Z3: =Y3*(1+W3) -> 112713.36 | AA3: =Z3*(1+W3) -> 136635.2 | AB3: =AA3*(1+$W$3) -> 165634.12 | AC3: =AB3*(1+$W$3) -> 200787.66 | AE3: Revenue | AF3: ='Income Statement'!AA6 -> 11942.34 | AG3: ='Key Assumptions'!Z13 -> 0.098361291 | AH3: =AF3*(1+AG3) -> 13117.004 | AI3: =AH3*(1+AG3) -> 14407.209 | AJ3: =AI3*(1+AG3) -> 15824.321 | AK3: =AJ3*(1+AG3) -> 17380.822 | AL3: =AK3*(1+$AG$3) -> 19090.422 | AM3: =AL3*(1+$AG$3) -> 20968.18 | AO3: Revenue | AP3: ='Income Statement'!AH6 -> 181165.86 | AQ3: ='Key Assumptions'!AH13 -> 0.13321926 | AR3: =AP3*(1+AQ3) -> 205300.64 | AS3: =AR3*(1+AQ3) -> 232650.64 | AT3: =AS3*(1+AQ3) -> 263644.18 | AU3: =AT3*(1+AQ3) -> 298766.67 | AV3: =AU3*(1+$AQ$3) -> 338568.14 | AW3: =AV3*(1+$AQ$3) -> 383671.93
A4: EBIT | B4: ='Income Statement'!F16 -> 20791.51 | C4: ='Key Assumptions'!B14 -> 0.15335411 | D4: =B4*(1+C4) -> 23979.974 | E4: =D4*(1+C4) -> 27657.401 | F4: =E4*(1+C4) -> 31898.777 | G4: =F4*(1+C4) -> 36790.586 | H4: =G4*(1+$C$4) -> 42432.574 | I4: =H4*(1+$C$4) -> 48939.784 | K4: EBIT | L4: ='Income Statement'!M19 -> -2028.15 | M4: ='Key Assumptions'!J14 -> -0.091382499 | N4: =N3*$M$4 -> -773.16468 | O4: =O3*$M$4 -> -791.93374 | P4: =P3*$M$4 -> -811.15843 | Q4: =Q3*$M$4 -> -830.8498 | R4: =R3*$M$4 -> -851.0192 | S4: =S3*$M$4 -> -871.67822 | U4: EBIT | V4: ='Income Statement'!T29 -> 5732.02 | W4: ='Key Assumptions'!R14 -> 0.037581432 | X4: =V4*(1+$W$4) -> 5947.4375 | Y4: =X4*(1+W4) -> 6170.9507 | Z4: =Y4*(1+W4) -> 6402.8639 | AA4: =Z4*(1+W4) -> 6643.4927 | AB4: =AA4*(1+$W$4) -> 6893.1647 | AC4: =AB4*(1+$W$4) -> 7152.2197 | AE4: EBIT | AF4: ='Income Statement'!AA19 -> 2167.91 | AG4: ='Key Assumptions'!Z14 -> 0.17638415 | AH4: =AF4*(AG4+1) -> 2550.295 | AI4: =AH4*(1+AG4) -> 3000.1266 | AJ4: =AI4*(1+AG4) -> 3529.3013 | AK4: =AJ4*(1+AG4) -> 4151.8141 | AL4: =AK4*(1+$AG$4) -> 4884.1283 | AM4: =AL4*(1+$AG$4) -> 5745.6111 | AO4: EBIT | AP4: ='Income Statement'!AH19 -> 27141.45 | AQ4: ='Key Assumptions'!AH14 -> 0.14627888 | AR4: =AP4*(1+AQ4) -> 31111.671 | AS4: =AR4*(1+AQ4) -> 35662.651 | AT4: =AS4*(1+AQ4) -> 40879.344 | AU4: =AT4*(1+AQ4) -> 46859.129 | AV4: =AU4*(1+$AQ$4) -> 53713.63 | AW4: =AV4*(1+$AQ$4) -> 61570.8
A5: Taxes | B5: ='Income Statement'!F23 -> -37.28 | C5: ='Key Assumptions'!B18 -> 0.26528288 | D5: =D4*$C$5 -> 6361.4765 | E5: =E4*$C$5 -> 7337.0351 | F5: =F4*$C$5 -> 8462.1996 | G5: =G4*$C$5 -> 9759.9127 | H5: =H4*$C$5 -> 11256.636 | I5: =I4*$C$5 -> 12982.887 | K5: Taxes | L5: ='Income Statement'!M24 -> 214.03 | M5: ='Key Assumptions'!J18 -> -0.10552967 | U5: Taxes | V5: ='Income Statement'!T35 -> 1451.92 | W5: ='Key Assumptions'!R18 -> 0.25329988 | X5: =X4*$W$5 -> 1506.4852 | Y5: =Y4*$W$5 -> 1563.1011 | Z5: =Z4*$W$5 -> 1621.8447 | AA5: =AA4*$W$5 -> 1682.7959 | AB5: =AB4*$W$5 -> 1746.0378 | AC5: =AC4*$W$5 -> 1811.6564 | AE5: Taxes | AF5: ='Income Statement'!AA21+'Income Statement'!AA22+'Income Statement'!AA23 -> 442.26 | AG5: ='Key Assumptions'!Z18 -> 0.20400293 | AH5: =AH4*$AG$5 -> 520.26765 | AI5: =AI4*$AG$5 -> 612.03462 | AJ5: =AJ4*$AG$5 -> 719.98782 | AK5: =AK4*$AG$5 -> 846.98226 | AL5: =AL4*$AG$5 -> 996.3765 | AM5: =AM4*$AG$5 -> 1172.1215 | AO5: Taxes | AP5: ='Income Statement'!AH24 -> 6809.2 | AQ5: ='Key Assumptions'!AH18 -> 0.25087827 | AR5: =AR4*$AQ$5 -> 7805.2422 | AS5: =AS4*$AQ$5 -> 8946.9843 | AT5: =AT4*$AQ$5 -> 10255.739 | AU5: =AU4*$AQ$5 -> 11755.937 | AV5: =AV4*$AQ$5 -> 13475.583 | AW5: =AW4*$AQ$5 -> 15446.776
A6: NOPAT | B6: =B4-B5 -> 20828.79 | D6: =D4-D5 -> 17618.497 | E6: =E4-E5 -> 20320.366 | F6: =F4-F5 -> 23436.578 | G6: =G4-G5 -> 27030.673 | H6: =H4-H5 -> 31175.938 | I6: =I4-I5 -> 35956.897 | K6: NOPAT | L6: =L4-L5 -> -2242.18 | N6: =N4-N5 -> -773.16468 | O6: =O4-O5 -> -791.93374 | P6: =P4-P5 -> -811.15843 | Q6: =Q4-Q5 -> -830.8498 | R6: =R4-R5 -> -851.0192 | S6: =S4-S5 -> -871.67822 | U6: NOPAT | V6: ='Income Statement'!T36 -> 4280.1 | X6: =X4-X5 -> 4440.9523 | Y6: =Y4-Y5 -> 4607.8496 | Z6: =Z4-Z5 -> 4781.0192 | AA6: =AA4-AA5 -> 4960.6968 | AB6: =AB4-AB5 -> 5147.1269 | AC6: =AC4-AC5 -> 5340.5633 | AE6: NOPAT | AF6: =AF4-AF5 -> 1725.65 | AH6: =AH4-AH5 -> 2030.0273 | AI6: =AI4-AI5 -> 2388.0919 | AJ6: =AJ4-AJ5 -> 2809.3135 | AK6: =AK4-AK5 -> 3304.8319 | AL6: =AL4-AL5 -> 3887.7518 | AM6: =AM4-AM5 -> 4573.4896 | AO6: NOPAT | AP6: =AP4-AP5 -> 20332.25 | AR6: =AR4-AR5 -> 23306.429 | AS6: =AS4-AS5 -> 26715.667 | AT6: =AT4-AT5 -> 30623.605 | AU6: =AU4-AU5 -> 35103.192 | AV6: =AV4-AV5 -> 40238.048 | AW6: =AW4-AW5 -> 46124.024
A7: Plus: Depreciation & Ammortization | B7: ='Income Statement'!F13 -> 3931.33 | C7: ='Key Assumptions'!B15 -> 0.092416494 | D7: =D3*$C$7 -> 6818.3507 | E7: =E3*$C$7 -> 8344.9796 | F7: =F3*$C$7 -> 10213.421 | G7: =G3*$C$7 -> 12500.206 | H7: =H3*$C$7 -> 15299.002 | I7: =I3*$C$7 -> 18724.449 | K7: Plus: Depreciation & Ammortization | L7: ='Income Statement'!M11 -> 1061.75 | M7: ='Key Assumptions'!J15 -> 0.12615676 | N7: =N3*$M$7 -> 1067.3811 | O7: =O3*$M$7 -> 1093.2925 | P7: =P3*$M$7 -> 1119.8328 | Q7: =Q3*$M$7 -> 1147.0175 | R7: =R3*$M$7 -> 1174.862 | S7: =S3*$M$7 -> 1203.3825 | U7: Plus: Depreciation & Ammortization | V7: ='Income Statement'!T14 -> 3786.37 | W7: ='Key Assumptions'!R15 -> 0.072827974 | X7: =X3*$W$7 -> 5585.9777 | Y7: =Y3*$W$7 -> 6771.5238 | Z7: =Z3*$W$7 -> 8208.6855 | AA7: =AA3*$W$7 -> 9950.8648 | AB7: =AB3*$W$7 -> 12062.797 | AC7: =AC3*$W$7 -> 14622.958 | AE7: Plus: Depreciation & Ammortization | AF7: ='Income Statement'!AA13 -> 1633.41 | AG7: ='Key Assumptions'!Z15 -> 0.13465779 | AH7: =AH3*$AG$7 -> 1766.3067 | AI7: =AI3*$AG$7 -> 1940.0429 | AJ7: =AJ3*$AG$7 -> 2130.8681 | AK7: =AK3*$AG$7 -> 2340.463 | AL7: =AL3*$AG$7 -> 2570.674 | AM7: =AM3*$AG$7 -> 2823.5288 | AO7: Plus: Depreciation & Ammortization | AP7: ='Income Statement'!AH12 -> 16203.63 | AQ7: ='Key Assumptions'!AH15 -> 0.094920176 | AR7: =AR3*$AQ$7 -> 19487.173 | AS7: =AS3*$AQ$7 -> 22083.24 | AT7: =AT3*$AQ$7 -> 25025.152 | AU7: =AU3*$AQ$7 -> 28358.984 | AV7: =AV3*$AQ$7 -> 32136.947 | AW7: =AW3*$AQ$7 -> 36418.207
A8: Less: CapEx | B8: =-'Cash Flow Statement'!F31 -> 2602.45 | C8: ='Key Assumptions'!B16 -> 0.08708238 | D8: =D3*$C$8 -> 6424.8077 | E8: =E3*$C$8 -> 7863.3223 | F8: =F3*$C$8 -> 9623.9202 | G8: =G3*$C$8 -> 11778.716 | H8: =H3*$C$8 -> 14415.971 | I8: =I3*$C$8 -> 17643.707 | K8: Less: CapEx | L8: ='Cash Flow Statement'!M33 -> 51.46 | M8: ='Key Assumptions'!J16 -> 0.025239023 | N8: =N3*$M$8 -> 213.54112 | O8: =O3*$M$8 -> 218.72496 | P8: =P3*$M$8 -> 224.03465 | Q8: =Q3*$M$8 -> 229.47323 | R8: =R3*$M$8 -> 235.04384 | S8: =S3*$M$8 -> 240.74967 | U8: Less: CapEx | V8: =-'Cash Flow Statement'!T55 -> 13332.75 | W8: ='Key Assumptions'!R16 -> 0.13772076 | X8: =X3*$W$8 -> 10563.318 | Y8: =Y3*$W$8 -> 12805.236 | Z8: =Z3*$W$8 -> 15522.969 | AA8: =AA3*$W$8 -> 18817.503 | AB8: =AB3*$W$8 -> 22811.256 | AC8: =AC3*$W$8 -> 27652.628 | AE8: Less: CapEx | AF8: =-'Cash Flow Statement'!AA32 -> 8032.77 | AG8: ='Key Assumptions'!Z16 -> 0.28001553 | AH8: =AH3*$AG$8 -> 3672.9649 | AI8: =AI3*$AG$8 -> 4034.2424 | AJ8: =AJ3*$AG$8 -> 4431.0557 | AK8: =AK3*$AG$8 -> 4866.9001 | AL8: =AL3*$AG$8 -> 5345.6147 | AM8: =AM3*$AG$8 -> 5871.4162 | AO8: Less: CapEx | AP8: =-'Cash Flow Statement'!AH36 -> 30815.92 | AQ8: ='Key Assumptions'!AH16 -> 0.17092235 | AR8: =AR3*$AQ$8 -> 35090.468 | AS8: =AS3*$AQ$8 -> 39765.194 | AT8: =AT3*$AQ$8 -> 45062.684 | AU8: =AU3*$AQ$8 -> 51065.901 | AV8: =AV3*$AQ$8 -> 57868.862 | AW8: =AW3*$AQ$8 -> 65578.109
A9: Less: Change in NWC | B9: ='Key Assumptions'!F9-'Key Assumptions'!E9 -> 7989.5 | C9: ='Key Assumptions'!B17 -> 0.071806584 | D9: =D3*$C$9 -> 5297.7824 | E9: =E3*$C$9 -> 6483.9559 | F9: =F3*$C$9 -> 7935.7138 | G9: =G3*$C$9 -> 9712.5202 | H9: =H3*$C$9 -> 11887.154 | I9: =I3*$C$9 -> 14548.687 | K9: Less: Change in NWC | L9: ='Key Assumptions'!N9-'Key Assumptions'!M9 -> 79.29 | M9: ='Key Assumptions'!J17 -> -0.071683272 | N9: =N3*$M$9 -> -606.4944 | O9: =O3*$M$9 -> -621.21743 | P9: =P3*$M$9 -> -636.29788 | Q9: =Q3*$M$9 -> -651.7444 | R9: =R3*$M$9 -> -667.56591 | S9: =S3*$M$9 -> -683.77149 | U9: Less: Change in NWC | V9: ='Key Assumptions'!V9-'Key Assumptions'!U9 -> 2314.01 | W9: ='Key Assumptions'!R17 -> -0.00140716 | X9: =X3*$W$9 -> -107.93057 | Y9: =Y3*$W$9 -> -130.83733 | Z9: =Z3*$W$9 -> -158.60573 | AA9: =AA3*$W$9 -> -192.26759 | AB9: =AB3*$W$9 -> -233.07371 | AC9: =AC3*$W$9 -> -282.54036 | AE9: Less: Change in NWC | AF9: ='Key Assumptions'!AD9-'Key Assumptions'!AC9 -> 878.49 | AG9: ='Key Assumptions'!Z17 -> 0.029772947 | AH9: =AH3*$AG$9 -> 390.53187 | AI9: =AI3*$AG$9 -> 428.94508 | AJ9: =AJ3*$AG$9 -> 471.13668 | AK9: =AK3*$AG$9 -> 517.47829 | AL9: =AL3*$AG$9 -> 568.37812 | AM9: =AM3*$AG$9 -> 624.28453 | AO9: Less: Change in NWC | AP9: ='Key Assumptions'!AL9-'Key Assumptions'!AK9 -> 667.41 | AQ9: ='Key Assumptions'!AH17 -> -0.017023728 | AR9: =AR3*$AQ$9 -> -3494.9822 | AS9: =AS3*$AQ$9 -> -3960.5811 | AT9: =AT3*$AQ$9 -> -4488.2068 | AU9: =AU3*$AQ$9 -> -5086.1224 | AV9: =AV3*$AQ$9 -> -5763.6918 | AW9: =AW3*$AQ$9 -> -6531.5265
A10: FCFF | B10: =B6+B7-B8-B9 -> 14168.17 | D10: =D6+D7-D8-D9 -> 12714.258 | E10: =E6+E7-E8-E9 -> 14318.067 | F10: =F6+F7-F8-F9 -> 16090.364 | G10: =G6+G7-G8-G9 -> 18039.643 | H10: =H6+H7-H8-H9 -> 20171.816 | I10: =I6+I7-I8-I9 -> 22488.951 | K10: FCFF | L10: =L6+L7-L8-L9 -> -1311.18 | N10: =N6+N7-N8-N9 -> 687.16971 | O10: =O6+O7-O8-O9 -> 703.85119 | P10: =P6+P7-P8-P9 -> 720.93762 | Q10: =Q6+Q7-Q8-Q9 -> 738.43883 | R10: =R6+R7-R8-R9 -> 756.36489 | S10: =S6+S7-S8-S9 -> 774.72612 | U10: FCFF | V10: =V6+V7-V8-V9 -> -7580.29 | X10: =X6+X7-X8-X9 -> -428.45786 | Y10: =Y6+Y7-Y8-Y9 -> -1295.0251 | Z10: =Z6+Z7-Z8-Z9 -> -2374.6585 | AA10: =AA6+AA7-AA8-AA9 -> -3713.674 | AB10: =AB6+AB7-AB8-AB9 -> -5368.2585 | AC10: =AC6+AC7-AC8-AC9 -> -7406.5664 | AE10: FCFF | AF10: =AF6+AF7-AF8-AF9 -> -5552.2 | AH10: =AH6+AH7-AH8-AH9 -> -267.16269 | AI10: =AI6+AI7-AI8-AI9 -> -135.05263 | AJ10: =AJ6+AJ7-AJ8-AJ9 -> 37.989168 | AK10: =AK6+AK7-AK8-AK9 -> 260.91649 | AL10: =AL6+AL7-AL8-AL9 -> 544.43299 | AM10: =AM6+AM7-AM8-AM9 -> 901.31762 | AO10: FCFF | AP10: =AP6+AP7-AP8-AP9 -> 5052.55 | AR10: =AR6+AR7-AR8-AR9 -> 11198.116 | AS10: =AS6+AS7-AS8-AS9 -> 12994.294 | AT10: =AT6+AT7-AT8-AT9 -> 15074.28 | AU10: =AU6+AU7-AU8-AU9 -> 17482.398 | AV10: =AV6+AV7-AV8-AV9 -> 20269.824 | AW10: =AW6+AW7-AW8-AW9 -> 23495.649
A11: PV of Projected FCFF | D11: =D10/(1+'Weighted Avg Cost of Capital'!$B$7)^1 -> 11482.817 | E11: =E10/(1+'Weighted Avg Cost of Capital'!$B$7)^2 -> 11678.829 | F11: =F10/(1+'Weighted Avg Cost of Capital'!$B$7)^3 -> 11853.271 | G11: =G10/(1+'Weighted Avg Cost of Capital'!$B$7)^4 -> 12002.113 | H11: =H10/(1+'Weighted Avg Cost of Capital'!$B$7)^5 -> 12120.826 | I11: =I10/(1+'Weighted Avg Cost of Capital'!$B$7)^6 -> 12204.327 | K11: PV of Projected FCFF | N11: =N10/(1+'Weighted Avg Cost of Capital'!$C$7)^1 -> 599.91291 | O11: =O10/(1+'Weighted Avg Cost of Capital'!$C$7)^2 -> 536.45 | P11: =P10/(1+'Weighted Avg Cost of Capital'!$C$7)^3 -> 479.70062 | Q11: =Q10/(1+'Weighted Avg Cost of Capital'!$C$7)^4 -> 428.95459 | R11: =R10/(1+'Weighted Avg Cost of Capital'!$C$7)^5 -> 383.57682 | S11: =S10/(1+'Weighted Avg Cost of Capital'!$C$7)^6 -> 342.99943 | U11: PV of Projected FCFF | X11: =X10/(1+'Weighted Avg Cost of Capital'!$D$7)^1 -> -381.55858 | Y11: =Y10/(1+'Weighted Avg Cost of Capital'!$D$7)^2 -> -1027.033 | Z11: =Z10/(1+'Weighted Avg Cost of Capital'!$D$7)^3 -> -1677.1059 | AA11: =AA10/(1+'Weighted Avg Cost of Capital'!$D$7)^4 -> -2335.6954 | AB11: =AB10/(1+'Weighted Avg Cost of Capital'!$D$7)^5 -> -3006.7612 | AC11: =AC10/(1+'Weighted Avg Cost of Capital'!$D$7)^5 -> -4148.4173 | AE11: PV of Projected FCFF | AH11: =AH10/(1+'Weighted Avg Cost of Capital'!$E$7)^1 -> -240.32807 | AI11: =AI10/(1+'Weighted Avg Cost of Capital'!$E$7)^2 -> -109.28496 | AJ11: =AJ10/(1+'Weighted Avg Cost of Capital'!$E$7)^3 -> 27.653227 | AK11: =AK10/(1+'Weighted Avg Cost of Capital'!$E$7)^4 -> 170.8505 | AL11: =AL10/(1+'Weighted Avg Cost of Capital'!$E$7)^5 -> 320.69179 | AM11: =AM10/(1+'Weighted Avg Cost of Capital'!$E$7)^6 -> 477.5842 | AO11: PV of Projected FCFF | AR11: =AR10/(1+'Weighted Avg Cost of Capital'!$F$7)^1 -> 10291.618 | AS11: =AS10/(1+'Weighted Avg Cost of Capital'!$F$7)^2 -> 10975.646 | AT11: =AT10/(1+'Weighted Avg Cost of Capital'!$F$7)^3 -> 11701.801 | AU11: =AU10/(1+'Weighted Avg Cost of Capital'!$F$7)^4 -> 12472.566 | AV11: =AV10/(1+'Weighted Avg Cost of Capital'!$F$7)^5 -> 13290.567 | AW11: =AW10/(1+'Weighted Avg Cost of Capital'!$F$7)^5 -> 15405.683
A14: Revenue CAGR | B14: Adani | C14: =(I3/D3)^(1/6)-1 -> 0.18337289
A15: Revenue CAGR | B15: Reliance | C15: =(S3/N3)^(1/6)-1 -> 0.020189145
A16: Revenue CAGR | B16: Tata | C16: =(AC3/X3)^(1/6)-1 -> 0.17396732 | E16: GDP growth | F16: 2020 | G16: =AVERAGE(-5.8%,9.7%) -> 0.0195
A17: Revenue CAGR | B17: JSW | C17: =(AM3/AH3)^(1/6)-1 -> 0.081320282 | E17: GDP growth | F17: 2025 | G17: 0.078
A18: Revenue CAGR | B18: NTPC | C18: =(AW3/AR3)^(1/6)-1 -> 0.10984319 | E18: GDP growth | F18: Change | G18: =G17-G16 -> 0.0585
A19: Revenue CAGR | B19: Average | C19: =AVERAGE(C14:C18) -> 0.11373857 | E19: GDP growth | F19: Senstivity | G19: =C25/G18 -> 156.44249
A20: Earnings Growth | B20: =B14 -> Adani | C20: =('Income Statement'!F25-(AVERAGE('Income Statement'!B25:C25)))/ABS(AVERAGE('Income Statement'!B25:C25)) -> 42.458991
A21: Earnings Growth | B21: =B15 -> Reliance | C21: =('Income Statement'!M32-'Income Statement'!I32)/ABS('Income Statement'!I32) -> 0.49262006
A22: Earnings Growth | B22: =B16 -> Tata | C22: =('Income Statement'!T29-'Income Statement'!P29)/'Income Statement'!P29 -> 1.420453
A23: Earnings Growth | B23: =B17 -> JSW | C23: =('Income Statement'!AA24-'Income Statement'!W24)/'Income Statement'!W24 -> 0.59608021
A24: Earnings Growth | B24: =B18 -> NTPC | C24: =('Income Statement'!AH27-'Income Statement'!AD27)/'Income Statement'!AD27 -> 0.79128484
A25: Earnings Growth | B25: =B19 -> Average | C25: =AVERAGE(C20:C24) -> 9.1518859
A26: Capex intensity | B26: =B20 -> Adani | C26: =AVERAGE(D8:I8)/AVERAGE(D3:I3) -> 0.08708238
A27: Capex intensity | B27: =B21 -> Reliance | C27: =AVERAGE(N8:S8)/AVERAGE(N3:S3) -> 0.025239023
A28: Capex intensity | B28: =B22 -> Tata | C28: =AVERAGE(X8:AC8)/AVERAGE(X3:AC3) -> 0.13772076
A29: Capex intensity | B29: =B23 -> JSW | C29: =AVERAGE(AH8:AM8)/AVERAGE(AH3:AM3) -> 0.28001553
A30: Capex intensity | B30: =B24 -> NTPC | C30: =AVERAGE(AR8:AW8)/AVERAGE(AR3:AW3) -> 0.17092235
A31: Capex intensity | B31: =B25 -> Average | C31: =AVERAGE(C26:C30) -> 0.14019601

Sheet Weighted Avg Cost of Capital
A1: Weighted Average Cost of Capital | B1: #VALUE! | C1: #VALUE! | D1: #VALUE! | E1: #VALUE! | F1: #VALUE!
A2: Component | B2: Adani Power | C2: Reliance Power | D2: TATA Power | E2: JSW Energy | F2: NTPC
A3: Cost of Equity (Ke) | B3: ='Key Assumptions'!B19+'Key Assumptions'!B21*'Key Assumptions'!B20 -> 0.127185 | C3: ='Key Assumptions'!J19+'Key Assumptions'!J21*'Key Assumptions'!J20 -> 0.19783 | D3: ='Key Assumptions'!R19+'Key Assumptions'!R21*'Key Assumptions'!R20 -> 0.14352 | E3: ='Key Assumptions'!Z19+'Key Assumptions'!Z21*'Key Assumptions'!Z20 -> 0.133135 | F3: ='Key Assumptions'!AH19+'Key Assumptions'!AH21*'Key Assumptions'!AH20 -> 0.12505
A4: Cost of Debt (Kd) | B4: =('Income Statement'!F12/('Balance Sheet'!F41+'Balance Sheet'!F50))*(1-0.25) -> 0.073746345 | C4: =('Income Statement'!M10/('Balance Sheet'!M41+'Balance Sheet'!M49))*(1-0.25) -> 0.097968888 | D4: =('Income Statement'!T13/('Balance Sheet'!T49+'Balance Sheet'!T60))*(1-0.25) -> 0.070228948 | E4: =('Income Statement'!AA12/('Balance Sheet'!AA41+'Balance Sheet'!AA50))*(1-0.25) -> 0.049161081 | F4: =('Income Statement'!AH11/('Balance Sheet'!AH42+'Balance Sheet'!AH51))*(1-0.25) -> 0.038445141
A5: Weight of Equity | B5: ='Key Assumptions'!B25/('Key Assumptions'!B25+'Key Assumptions'!B26) -> 0.6268061 | C5: ='Key Assumptions'!J25/('Key Assumptions'!J25+'Key Assumptions'!J26) -> 0.47546263 | D5: ='Key Assumptions'!R25/('Key Assumptions'!R26+'Key Assumptions'!R25) -> 0.71886106 | E5: ='Key Assumptions'!Z25/('Key Assumptions'!Z25+'Key Assumptions'!Z26) -> 0.74424571 | F5: ='Key Assumptions'!AH25/('Key Assumptions'!AH25+'Key Assumptions'!AH26) -> 0.57313221
A6: Weight of Debt | B6: ='Key Assumptions'!B26/('Key Assumptions'!B25+'Key Assumptions'!B26) -> 0.3731939 | C6: ='Key Assumptions'!J26/('Key Assumptions'!J25+'Key Assumptions'!J26) -> 0.52453737 | D6: ='Key Assumptions'!R26/('Key Assumptions'!R25+'Key Assumptions'!R26) -> 0.28113894 | E6: ='Key Assumptions'!Z26/('Key Assumptions'!Z25+'Key Assumptions'!Z26) -> 0.25575429 | F6: ='Key Assumptions'!AH26/('Key Assumptions'!AH25+'Key Assumptions'!AH26) -> 0.42686779
A7: WACC | B7: =(B3*B5)+(B4*B6) -> 0.10724202 | C7: =(C3*C5)+(C4*C6) -> 0.14544912 | D7: =(D3*D5)+(D4*D6) -> 0.12291503 | E7: =(E3*E5)+(E4*E6) -> 0.11165831 | F7: =(F3*F5)+(F4*F6) -> 0.088081175
A8: Growth Rate | B8: 0.035 | C8: 0.035 | D8: 0.035 | E8: 0.035 | F8: 0.035

Sheet Intrinsic Value calculation
A1: Intrinsic Value Calculation
A2: Metric | B2: #VALUE! | C2: #VALUE! | D2: #VALUE! | E2: #VALUE! | F2: #VALUE!
A3: Terminal Value | B3: ='FCFF Projections (5y )'!I10/('Weighted Avg Cost of Capital'!B7-'Weighted Avg Cost of Capital'!B8) -> 311300.14 | C3: ='FCFF Projections (5y )'!S11/('Weighted Avg Cost of Capital'!B7-'Weighted Avg Cost of Capital'!B8) -> 4747.9213 | D3: ='FCFF Projections (5y )'!X10/('Weighted Avg Cost of Capital'!D7-'Weighted Avg Cost of Capital'!D8) -> -4873.545 | E3: ='FCFF Projections (5y )'!AM10/('Weighted Avg Cost of Capital'!E7-'Weighted Avg Cost of Capital'!E8) -> 11757.598 | F3: ='FCFF Projections (5y )'!AW10/('Weighted Avg Cost of Capital'!F7-'Weighted Avg Cost of Capital'!F8) -> 442636.19
A4: PV of Terminal Value | B4: =B3/(1+'Weighted Avg Cost of Capital'!B7)^6 -> 168936.68 | C4: =C3/(1+'Weighted Avg Cost of Capital'!C7)^6 -> 2102.0774 | D4: =D3/(1+'Weighted Avg Cost of Capital'!D7)^6 -> -2430.8805 | E4: =E3/(1+'Weighted Avg Cost of Capital'!E7)^6 -> 6230.0382 | F4: =F3/(1+'Weighted Avg Cost of Capital'!F7)^6 -> 266734.47
A5: PV of Projected FCFF | B5: =SUM('FCFF Projections (5y )'!D11:I11) -> 71342.182 | C5: =SUM('FCFF Projections (5y )'!N11:S11) -> 2771.5944 | D5: =SUM('FCFF Projections (5y )'!X11:AC11) -> -12576.571 | E5: =SUM('FCFF Projections (5y )'!AH11:AM11) -> 647.16669 | F5: =SUM('FCFF Projections (5y )'!AR11:AW11) -> 74137.88
A6: Equity Value | B6: =B4+B5 -> 240278.87 | C6: =C4+C5 -> 4873.6718 | D6: =D4+D5 -> -15007.452 | E6: =E4+E5 -> 6877.2049 | F6: =F4+F5 -> 340872.35
A7: Add: Total Debt | B7: ='Key Assumptions'!B26 -> 34456.86 | C7: ='Key Assumptions'!J26 -> 18765.83 | D7: ='Key Assumptions'!R26 -> 49479.81 | E7: ='Key Assumptions'!Z26 -> 31326.61 | F7: ='Key Assumptions'!AH26 -> 235040.3
A8: Less: Cash & Cash equivalents | B8: ='Balance Sheet'!F22 -> 1136.25 | C8: ='Balance Sheet'!M22 -> 486.15 | D8: ='Balance Sheet'!T26 -> 3324.34 | E8: ='Balance Sheet'!AA24 -> 3091.74 | F8: ='Balance Sheet'!AH23 -> 863.34
A9: Enterprise Value | B9: =B6+B7-B8 -> 273599.48 | C9: =C6+C7-C8 -> 23153.352 | D9: =D6+D7-D8 -> 31148.018 | E9: =E6+E7-E8 -> 35112.075 | F9: =F6+F7-F8 -> 575049.31
A10: Shares Outstanding | B10: ='Key Assumptions'!B23 -> 385.69 | C10: ='Key Assumptions'!J23 -> 413.57 | D10: ='Key Assumptions'!R23 -> 319.53 | E10: ='Key Assumptions'!Z23 -> 174.52 | F10: ='Key Assumptions'!AH23 -> 969.66
A11: Intrinsic Value per share | B11: =B9/B10 -> 709.37664 | C11: =C9/C10 -> 55.984118 | D11: =D9/D10 -> 97.480732 | E11: =E9/E10 -> 201.19227 | F11: =F9/F10 -> 593.04221
A12: Current Market Price | B12: ='Key Assumptions'!B24 -> 150.05 | C12: ='Key Assumptions'!J24 -> 41.13 | D12: ='Key Assumptions'!R24 -> 395.95 | E12: ='Key Assumptions'!Z24 -> 522.35 | F12: ='Key Assumptions'!AH24 -> 325.45
A13: Upside / Downside | B13: =(B11-B12)/B12 -> 3.7276017 | C13: =(C11-C12)/C12 -> 0.36115045 | D13: =(D11-D12)/D12 -> -0.75380545 | E13: =(E11-E12)/E12 -> -0.61483245 | F13: =(F11-F12)/F12 -> 0.82222219

Sheet Calc
A1: Year | B1: Metrics | C1: Company | D1: Amount | G1: Company | H1: Change in EBIT (Historical) | I1: Change in CE | J1: Incremental ROCE (Historical) | K1: Change in EBIT (Forecast) | L1: Capex | M1: Depreciation | N1: Effective Capital | O1: Raw ROCE (Forecast) | P1: Adjusted ROCE (Forecast)
A2: 2020-24 | B2: Avg Capex | C2: Adani Power | D2: =ABS(AVERAGE('Cash Flow Statement'!B31:F31)) -> 3024.97 | G2: =C2 -> Adani Power | H2: =(('Income Statement'!F16+'Income Statement'!F12)-('Income Statement'!B16+'Income Statement'!B12)) -> 20126.71 | I2: =(('Balance Sheet'!F29-'Balance Sheet'!F57)-('Balance Sheet'!B29-'Balance Sheet'!B57)) -> 19700.25 | J2: =H2/I2 -> 1.0216474 | K2: ='FCFF Projections (5y )'!I4-'FCFF Projections (5y )'!D4 -> 24959.81 | L2: =D8 -> 11291.741 | M2: =AVERAGE('FCFF Projections (5y )'!D7:I7) -> 11983.401 | N2: =IF(L2-M2<=0,L2,MAX(L2-M2,0.1*L2)) -> 11291.741 | O2: =K2/N2 -> 2.2104484 | P2: =MIN(MAX(O2,0.06),0.15) -> 0.15
A3: 2020-24 | B3: Avg Capex | C3: Reliance Power | D3: =ABS(AVERAGE('Cash Flow Statement'!I33:M33)) -> 201.792 | G3: =C3 -> Reliance Power | H3: =(('Income Statement'!M14+'Income Statement'!M10)-('Income Statement'!I14+'Income Statement'!I10)) -> -2363.28 | I3: =(('Balance Sheet'!M30-'Balance Sheet'!M55)-('Balance Sheet'!I30-'Balance Sheet'!I55)) -> -11511.26 | J3: =H3/I3 -> 0.20530159 | K3: ='FCFF Projections (5y )'!S4-'FCFF Projections (5y )'!N4 -> -98.513542 | L3: =D9 -> 226.92791 | M3: =AVERAGE('FCFF Projections (5y )'!N7:S7) -> 1134.2947 | N3: =IF(L3-M3<=0,L3,MAX(L3-M3,0.1*L3)) -> 226.92791 | O3: =K3/N3 -> -0.43411822 | P3: =MIN(MAX(O3,0.06),0.15) -> 0.06
A4: 2020-24 | B4: Avg Capex | C4: Tata Power | D4: =ABS(AVERAGE('Cash Flow Statement'!P55:T55)) -> 6763.644 | G4: =C4 -> Tata Power | H4: =(('Income Statement'!T17+'Income Statement'!T13)-('Income Statement'!P17+'Income Statement'!P13)) -> 2949.01 | I4: =(('Balance Sheet'!T37-'Balance Sheet'!T67)-('Balance Sheet'!P37-'Balance Sheet'!P67)) -> 35188.8 | J4: =H4/I4 -> 0.083805359 | K4: ='FCFF Projections (5y )'!AC4-'FCFF Projections (5y )'!X4 -> 1204.7821 | L4: =D10 -> 18028.819 | M4: =AVERAGE('FCFF Projections (5y )'!X7:AC7) -> 9533.8012 | N4: =IF(L4-M4<=0,L4,MAX(L4-M4,0.1*L4)) -> 8495.0173 | O4: =K4/N4 -> 0.14182221 | P4: =MIN(MAX(O4,0.06),0.15) -> 0.14182221
A5: 2020-24 | B5: Avg Capex | C5: JSW energy | D5: =ABS(AVERAGE('Cash Flow Statement'!W32:AA32)) -> 3024.018 | G5: =C5 -> JSW energy | H5: =(('Income Statement'!AA17+'Income Statement'!AA12)-('Income Statement'!W17+'Income Statement'!W12)) -> 2117.48 | I5: =(('Balance Sheet'!AA30-'Balance Sheet'!AA58)-('Balance Sheet'!W30-'Balance Sheet'!W58)) -> 30262.79 | J5: =H5/I5 -> 0.069969755 | K5: ='FCFF Projections (5y )'!AM4-'FCFF Projections (5y )'!AH4 -> 3195.3161 | L5: =D11 -> 4703.699 | M5: =AVERAGE('FCFF Projections (5y )'!AH7:AM7) -> 2261.9806 | N5: =IF(L5-M5<=0,L5,MAX(L5-M5,0.1*L5)) -> 2441.7184 | O5: =K5/N5 -> 1.3086342 | P5: =MIN(MAX(O5,0.06),0.15) -> 0.15
A6: 2020-24 | B6: Avg Capex | C6: NTPC | D6: =ABS(AVERAGE('Cash Flow Statement'!AD36:AH36)) -> 24324.328 | G6: =C6 -> NTPC | H6: =(('Income Statement'!AH15+'Income Statement'!AH11)-('Income Statement'!AD15+'Income Statement'!AD11)) -> 13465.17 | I6: =(('Balance Sheet'!AH31-'Balance Sheet'!AH60)-('Balance Sheet'!AD31-'Balance Sheet'!AD60)) -> 67848.52 | J6: =H6/I6 -> 0.1984593 | K6: ='FCFF Projections (5y )'!AW4-'FCFF Projections (5y )'!AR4 -> 30459.129 | L6: =D12 -> 49071.87 | M6: =AVERAGE('FCFF Projections (5y )'!AR7:AW7) -> 27251.617 | N6: =IF(L6-M6<=0,L6,MAX(L6-M6,0.1*L6)) -> 21820.253 | O6: =K6/N6 -> 1.3959109 | P6: =MIN(MAX(O6,0.06),0.15) -> 0.15
A7: 2020-24 | B7: Avg Capex | C7: Average | D7: =AVERAGE(D2:D6) -> 7467.7504 | G7: =C7 -> Average | J7: =AVERAGE(J2:J6) -> 0.31583669 | O7: =AVERAGE(O2:O6) -> 0.9245395 | P7: =AVERAGE(P2:P6) -> 0.13036444
A8: 2025-30 | B8: Avg Capex | C8: =C2 -> Adani Power | D8: =AVERAGE('FCFF Projections (5y )'!D8:I8) -> 11291.741
A9: 2025-30 | B9: Avg Capex | C9: =C3 -> Reliance Power | D9: =AVERAGE('FCFF Projections (5y )'!N8:S8) -> 226.92791
A10: 2025-30 | B10: Avg Capex | C10: =C4 -> Tata Power | D10: =AVERAGE('FCFF Projections (5y )'!X8:AC8) -> 18028.819
A11: 2025-30 | B11: Avg Capex | C11: =C5 -> JSW energy | D11: =AVERAGE('FCFF Projections (5y )'!AH8:AM8) -> 4703.699
A12: 2025-30 | B12: Avg Capex | C12: =C6 -> NTPC | D12: =AVERAGE('FCFF Projections (5y )'!AR8:AW8) -> 49071.87
A13: 2025-30 | B13: Avg Capex | C13: =C7 -> Average | D13: =AVERAGE(D8:D12) -> 16664.611
A14: =A8 -> 2025-30 | B14: Capex CAGR | C14: =C8 -> Adani Power | D14: =('FCFF Projections (5y )'!I8/'FCFF Projections (5y )'!D8)^(1/6)-1 -> 0.18337289
A15: =A9 -> 2025-30 | B15: Capex CAGR | C15: =C9 -> Reliance Power | D15: =('FCFF Projections (5y )'!S8/'FCFF Projections (5y )'!N8)^(1/6)-1 -> 0.020189145
A16: =A10 -> 2025-30 | B16: Capex CAGR | C16: =C10 -> Tata Power | D16: =('FCFF Projections (5y )'!AC8/'FCFF Projections (5y )'!X8)^(1/6)-1 -> 0.17396732
A17: =A11 -> 2025-30 | B17: Capex CAGR | C17: =C11 -> JSW energy | D17: =('FCFF Projections (5y )'!AM8/'FCFF Projections (5y )'!AH8)^(1/6)-1 -> 0.081320282
A18: =A12 -> 2025-30 | B18: Capex CAGR | C18: =C12 -> NTPC | D18: =('FCFF Projections (5y )'!AW8/'FCFF Projections (5y )'!AR8)^(1/6)-1 -> 0.10984319
A19: =A13 -> 2025-30 | B19: Capex CAGR | C19: =C13 -> Average | D19: =AVERAGE(D14:D18) -> 0.11373857
A20: =A14 -> 2025-30 | B20: Earnings CAGR | C20: =C14 -> Adani Power | D20: =('FCFF Projections (5y )'!I6/'FCFF Projections (5y )'!D6)^(1/6)-1 -> 0.12625195
A21: =A15 -> 2025-30 | B21: Earnings CAGR | C21: =C15 -> Reliance Power | D21: =('FCFF Projections (5y )'!S6/'FCFF Projections (5y )'!Q6)^(1/6)-1 -> 0.0080272656
A22: =A16 -> 2025-30 | B22: Earnings CAGR | C22: =C16 -> Tata Power | D22: =('FCFF Projections (5y )'!AC6/'FCFF Projections (5y )'!X6)^(1/6)-1 -> 0.031221184
A23: =A17 -> 2025-30 | B23: Earnings CAGR | C23: =C17 -> JSW energy | D23: =('FCFF Projections (5y )'!AM6/'FCFF Projections (5y )'!AH6)^(1/6)-1 -> 0.14496173
A24: =A18 -> 2025-30 | B24: Earnings CAGR | C24: =C18 -> NTPC | D24: =('FCFF Projections (5y )'!AW6/'FCFF Projections (5y )'!AR6)^(1/6)-1 -> 0.12049153
A25: =A19 -> 2025-30 | B25: Earnings CAGR | C25: =C19 -> Average | D25: =AVERAGE(D20:D24) -> 0.086190731
