Workbook

Sheet Company Profile
A1: COMPANY PROFILE
A3: Logo | B3: #VALUE! | C3: #VALUE! | D3: #VALUE! | E3: #VALUE! | F3: #VALUE! | G3: #VALUE!
A5: Trading Name | B5: #VALUE! | C5: #VALUE! | D5: #VALUE! | E5: #VALUE! | F5: #VALUE! | G5: #VALUE!
A6: Official Name | B6: {=_FV(B5,"Name")} -> BHARAT PETROLEUM CORPORATION LIMITED | C6: {=_FV(C5,"Name")} -> GAIL (INDIA) LIMITED | D6: {=_FV(D5,"Name")} -> HINDUSTAN PETROLEUM CORPORATION LIMITED | E6: {=_FV(E5,"Name")} -> INDIAN OIL CORPORATION LIMITED | F6: {=_FV(F5,"Name")} -> OIL AND NATURAL GAS CORPORATION LIMITED | G6: {=_FV(G5,"Name")} -> RELIANCE INDUSTRIES LIMITED
A7: Share Price | B7: {=_FV(B5,"Price")} -> 365.15 | C7: {=_FV(C5,"Price")} -> 181.52 | D7: {=_FV(D5,"Price")} -> 481.7 | E7: {=_FV(E5,"Price")} -> 169 | F7: {=_FV(F5,"Price")} -> 251.4 | G7: {=_FV(G5,"Price")} -> 1489.25
A8: Outstanding Shares | B8: {=_FV(B5,"Shares outstanding",TRUE)} -> 4338505000 | C8: {=_FV(C5,"Shares outstanding",TRUE)} -> 6575080000 | D8: {=_FV(D5,"Shares outstanding",TRUE)} -> 2127823000 | E8: {=_FV(E5,"Shares outstanding",TRUE)} -> 14121240000 | F8: {=_FV(F5,"Shares outstanding",TRUE)} -> 12580280000 | G8: {=_FV(G5,"Shares outstanding",TRUE)} -> 13532740000
A9: In crores | B9: =B8/10000000 -> 433.8505 | C9: =C8/10000000 -> 657.508 | D9: =D8/10000000 -> 212.7823 | E9: =E8/10000000 -> 1412.124 | F9: =F8/10000000 -> 1258.028 | G9: =G8/10000000 -> 1353.274
A10: Market Cap | B10: {=_FV(B5,"Market cap",TRUE)} -> 1592882000000 | C10: {=_FV(C5,"Market cap",TRUE)} -> 1186605000000 | D10: {=_FV(D5,"Market cap",TRUE)} -> 1020397000000 | E10: {=_FV(E5,"Market cap",TRUE)} -> 2388749000000 | F10: {=_FV(F5,"Market cap",TRUE)} -> 3172747000000 | G10: {=_FV(G5,"Market cap",TRUE)} -> 20000990000000
A11: Change | B11: {=_FV(B5,"Change (%)",TRUE)} -> -0.005447 | C11: {=_FV(C5,"Change (%)",TRUE)} -> 0.005818 | D11: {=_FV(D5,"Change (%)",TRUE)} -> 0.004483 | E11: {=_FV(E5,"Change (%)",TRUE)} -> -0.0002958 | F11: {=_FV(F5,"Change (%)",TRUE)} -> -0.003172 | G11: {=_FV(G5,"Change (%)",TRUE)} -> 0.007441
A12: Beta | B12: {=_FV(B5,"Beta")} -> 1.2921 | C12: {=_FV(C5,"Beta")} -> 1.5484 | D12: {=_FV(D5,"Beta")} -> 1.5872 | E12: {=_FV(E5,"Beta")} -> 1.3211 | F12: {=_FV(F5,"Beta")} -> 0.9935 | G12: {=_FV(G5,"Beta")} -> 1.1399

Sheet Balance Sheet
A1: BALANCE SHEET
A3: #VALUE! | I3: #VALUE! | Q3: #VALUE! | Y3: #VALUE! | AG3: #VALUE! | AO3: #VALUE!
A4: Particulars | B4: 2020 | C4: 2021 | D4: 2022 | E4: 2023 | F4: 2024 | G4: 2025 | I4: Particulars | J4: 2020 | K4: 2021 | L4: 2022 | M4: 2023 | N4: 2024 | O4: 2025 | Q4: Particulars | R4: 2020 | S4: 2021 | T4: 2022 | U4: 2023 | V4: 2024 | W4: 2025 | Y4: Particulars | Z4: 2020 | AA4: 2021 | AB4: 2022 | AC4: 2023 | AD4: 2024 | AE4: 2025 | AG4: Particulars | AH4: 2020 | AI4: 2021 | AJ4: 2022 | AK4: 2023 | AL4: 2024 | AM4: 2025 | AO4: Particulars | AP4: 2020 | AQ4: 2021 | AR4: 2022 | AS4: 2023 | AT4: 2024 | AU4: 2025
A5: ASSETS | I5: ASSETS | Q5: ASSETS | Y5: ASSETS | AG5: ASSETS | AO5: ASSETS
A6: Non-current assets | I6: Non current assets | Q6: Non Current assets | Y6: Non current assets | AG6: Non current assets | AO6: Non current Assets
A7: Property, plant and equipment | B7: 56687.98 | C7: 63588.84 | D7: 81507.26 | E7: 84464.8 | F7: 84718.04 | G7: 86593.79 | I7: Property, plant and equipment | J7: 35896.6 | K7: 37952.8 | L7: 40410.09 | M7: 44651.29 | N7: 47956.66 | O7: 49352.91 | Q7: Property, plant and equipment | R7: 48391.57 | S7: 49950.58 | T7: 56982.17 | U7: 67305.13 | V7: 78371.79 | W7: 84767.38 | Y7: PPE | Z7: 144076.3 | AA7: 153698.39 | AB7: 157194.98 | AC7: 176532.05 | AD7: 192159.52 | AE7: 197162.03 | AG7: Property, plant and equipment | AO7: PPE | AP7: 297854 | AQ7: 292092 | AR7: 223824 | AS7: 232238 | AT7: 258911 | AU7: 267096
A8: Capital work-in-progress | B8: 9108.09 | C8: 7537.18 | D8: 4979.89 | E8: 5645.05 | F8: 8679.72 | G8: 13240.29 | I8: Capital work in progress | J8: 11666.31 | K8: 13399.66 | L8: 15490.4 | M8: 16646.5 | N8: 23626.78 | O8: 27421.06 | Q8: Capital work in progress | R8: 17047.34 | S8: 25128.63 | T8: 28645.09 | U8: 25310.74 | V8: 20048.26 | W8: 17935.16 | Y8: Capital work in progress | Z8: 29628.86 | AA8: 32953.16 | AB8: 44049.82 | AC8: 47550.08 | AD8: 57316.86 | AE8: 73740.41 | AG8: Oil and gas assets | AH8: 140044.14 | AI8: 139280.85 | AJ8: 143352.36 | AK8: 130983.63 | AL8: =144996.692+362.896 -> 145359.59 | AM8: =157405.428+329.216 -> 157734.64 | AO8: Intangible assets | AP8: 15638 | AQ8: 20765 | AR8: 15802 | AS8: 12926 | AT8: 40719 | AU8: 43951
A9: Investment Property | B9: 0.21 | C9: 0 | D9: 1203.98 | E9: 0.01 | F9: 0.09 | G9: 0.09 | I9: Intangible assets | J9: 1880.36 | K9: 2300.68 | L9: 2536.61 | M9: 2856.29 | N9: 3135.35 | O9: 3324.56 | Q9: Intangible assets | R9: =16.69+543.52 -> 560.21 | S9: =321.62+639.71 -> 961.33 | T9: =321.62+822.31 -> 1143.93 | U9: =304.92+777.41 -> 1082.33 | V9: =304.92+1085.85 -> 1390.77 | W9: =304.92+1106.9 -> 1411.82 | Y9: Goodwill | Z9: 1.04 | AA9: 1.04 | AB9: 1.04 | AC9: 1.04 | AD9: 1.04 | AE9: 1.04 | AG9: Other property plant and equipment | AH9: 74127.397 | AI9: 74125.818 | AJ9: 83026.264 | AK9: 92631.504 | AL9: 126992.77 | AM9: 134067.95 | AO9: Capital work in progress | AP9: 8624 | AQ9: 14741 | AR9: 19267 | AS9: 30958 | AT9: 44294 | AU9: 76322
A10: Goodwill | B10: 0 | C10: 0.05 | D10: 0.03 | E10: 1203.98 | F10: 1203.98 | G10: 1203.98 | I10: Right of use assetss | J10: 452.66 | K10: 906.86 | L10: 1625.36 | M10: 2189.29 | N10: 4096.49 | O10: 6158.04 | Q10: Intangible assets under development | R10: 122.42 | S10: 207.4 | T10: 262.15 | U10: 296.62 | V10: 29.54 | W10: 31.99 | Y10: Intangible assets | Z10: 2944.79 | AA10: 3385.36 | AB10: 3318.33 | AC10: 3514.48 | AD10: 3837.23 | AE10: 3979.1 | AG10: Right of use assets | AH10: 14711.763 | AI10: 15906.384 | AJ10: 15782.603 | AK10: 14189.416 | AL10: 34407.325 | AM10: 34181.47 | AO10: Intangible assets under development | AP10: 12327 | AQ10: 12070 | AR10: 15395 | AS10: 17957 | AT10: 17338 | AU10: 6095
A11: Intangible assets | B11: 262.93 | C11: 509.42 | D11: 1190.19 | E11: 1006.33 | F11: 876.14 | G11: 830.37 | I11: Investments accounted as per equiy method | J11: 7331.43 | K11: 9042.74 | L11: 10978.18 | M11: 12163.97 | N11: 13120.76 | O11: 14638.56 | Q11: Investment in subsidiaries, Joint ventures and Associates | R11: 8820.82 | S11: 9333.88 | T11: 12840.27 | U11: 17809.73 | V11: 22654.1 | W11: 22136.45 | Y11: Intangible assets under development | Z11: 3215.98 | AA11: 3337.38 | AB11: 3419.45 | AC11: 3583.39 | AD11: 3715.56 | AE11: 4180.87 | AG11: Capital work in progress | AO11: Investments | AP11: 421793 | AQ11: 252620 | AR11: 330493 | AS11: 303558 | AT11: 301400 | AU11: 333258
A12: Intangible assets under development | B12: 396.62 | C12: 9500.11 | D12: 10453.06 | E12: 10603.88 | F12: 11524.24 | G12: 13146.5 | I12: Other investments | J12: 2561.52 | K12: 3546.52 | L12: 5429.97 | M12: 5084.35 | N12: 8789.28 | O12: 8126.05 | Q12: Other investments | R12: 229.93 | S12: 341.96 | T12: 655.56 | U12: 710.53 | V12: 1703.5 | W12: 1657.43 | Y12: Equity investment in joint ventures and associates | Z12: 13572.23 | AA12: 15010.12 | AB12: 16335 | AC12: 18038.31 | AD12: 18097 | AE12: 21392.04 | AG12: Oil and gas assets | AO12: Loans | AP12: 44348 | AQ12: 65698 | AR12: 41951 | AS12: 22448 | AT12: 10051 | AU12: 4941
A13: Investments accounted for using the equity method | B13: 10561.62 | C13: 19549.64 | D13: 18415.49 | E13: 21700.65 | F13: 20561.41 | G13: 21090.68 | I13: Trade receivables | J13: 1029.99 | K13: 1093.47 | L13: 1055.54 | M13: 1047.98 | N13: 1049.69 | O13: 1046.88 | Q13: Loans | R13: 1409.48 | S13: 979.21 | T13: 925.89 | U13: 977.81 | V13: 1201.41 | W13: 5148.97 | Y13: Investments | Z13: 13707.46 | AA13: 20424.09 | AB13: 28003.76 | AC13: 23715.61 | AD13: 37065.04 | AE13: 35457.55 | AG13: Development wells in progress | AH13: 5589.94 | AI13: 5900.707 | AJ13: 7612.84 | AK13: 9725.987 | AL13: 9010.132 | AM13: 4047.329 | AO13: Other financial assets | AP13: 0 | AQ13: 0 | AR13: 2247 | AS13: 2215 | AT13: 16902 | AU13: 15256
A14: Other investments | B14: 287.86 | C14: 423.82 | D14: 758.14 | E14: 800.49 | F14: 1778.51 | G14: 1776.77 | I14: Loans & Other receivables | J14: 556.12 | K14: 390.36 | L14: 285.37 | M14: 281.21 | N14: 305.85 | O14: 329.02 | Q14: Other financial assets | R14: =6.29+2702.07 -> 2708.36 | S14: =16.39+3073.25 -> 3089.64 | T14: =3337.66+145.55 -> 3483.21 | U14: =3677.97+192.63 -> 3870.6 | V14: =204.24+4329.47 -> 4533.71 | W14: =461.95+3488.65 -> 3950.6 | Y14: Loans | Z14: 3294.66 | AA14: 2615.24 | AB14: 2292.96 | AC14: 2285.11 | AD14: 2586.98 | AE14: 3223.44 | AG14: Oil and gas facilities in progress | AH14: 19750.109 | AI14: 27472.641 | AJ14: 32260.77 | AK14: 35301.822 | AL14: 37305.961 | AM14: 39269.055 | AO14: Other non current assets | AP14: 4461 | AQ14: 4968 | AR14: 7297 | AS14: 2333 | AT14: 7403 | AU14: 5919
A15: Loans | B15: 5442.94 | C15: 5175.31 | D15: 3956.62 | E15: 4336.01 | F15: 4452.74 | G15: 4939.75 | I15: Other financial assets | J15: 113.97 | K15: 356.12 | L15: 1144.03 | M15: 550.82 | N15: 329.36 | O15: 107.18 | Q15: Total non-current assets | R15: =SUM(R7:R14) -> 79290.13 | S15: =SUM(S7:S14) -> 89992.63 | T15: =SUM(T7:T14) -> 104938.27 | U15: =SUM(U7:U14) -> 117363.49 | V15: =SUM(V7:V14) -> 129933.08 | W15: =SUM(W7:W14) -> 137039.8 | Y15: Other financial assets | Z15: 1430.85 | AA15: 1952.5 | AB15: 2639.28 | AC15: 1748.36 | AD15: 2360.8 | AE15: 2336.86 | AG15: Others | AH15: 20495.577 | AI15: 29548.035 | AJ15: 31610.94 | AK15: 28947.362 | AL15: =21109.73+24229.713 -> 45339.443 | AM15: =21634.896+22085.543 -> 43720.439 | AO15: Total non current assets | AP15: =SUM(AP7:AP14) -> 805045 | AQ15: =SUM(AQ7:AQ14) -> 662954 | AR15: =SUM(AR7:AR14) -> 656276 | AS15: =SUM(AS7:AS14) -> 624633 | AT15: =SUM(AT7:AT14) -> 697018 | AU15: =SUM(AU7:AU14) -> 752838
A16: Other financial assets | B16: 8.3 | C16: 184.6 | D16: 706.98 | E16: 537.57 | F16: 653.89 | G16: 757.48 | I16: Non current tax assets | J16: 676.47 | K16: 413.57 | L16: 432.04 | M16: 744.13 | N16: 888.44 | O16: 3.11 | Q16: Current Assets | Y16: Income tax assets | Z16: 4236.2 | AA16: 2479.91 | AB16: 2819.51 | AC16: 1857.22 | AD16: 1827.98 | AE16: 1589.73 | AG16: Goodwill | AH16: 14236.65 | AI16: 13538.591 | AJ16: 7.869 | AK16: 7.868 | AL16: 7.867 | AM16: 7.866 | AO16: Current assets
A17: Income tax assets | B17: 1381.25 | C17: =1158.07+3.53 -> 1161.6 | D17: 349.8 | E17: 485.95 | F17: 477.44 | G17: 226.43 | I17: Other non current assets | J17: 1091.86 | K17: 1114.95 | L17: 864.66 | M17: 1034.23 | N17: 1146.76 | O17: 1139.66 | Q17: Inventories | R17: 19325.99 | S17: 28763.9 | T17: 35514.71 | U17: 29575 | V17: 34211.46 | W17: 38325.27 | Y17: Other non current assets | Z17: 2893.18 | AA17: 2850.04 | AB17: 3690.03 | AC17: 4070.95 | AD17: 4951.37 | AE17: 6160.83 | AG17: Investment property | AH17: 7.7872 | AI17: 7.871 | AJ17: 11205.649 | AK17: 12033.412 | AL17: 12136.444 | AM17: 12762.488 | AO17: Inventories | AP17: 38802 | AQ17: 37437 | AR17: 45923 | AS17: 48926 | AT17: 85100 | AU17: 89216
A18: Other non current assets | B18: 1267.95 | C18: 1276.13 | D18: 2007.83 | E18: 1311.12 | F18: 1797.44 | G18: 1743.87 | I18: Total Non current assets | J18: =SUM(J7:J17) -> 63257.29 | K18: =SUM(K7:K17) -> 70517.73 | L18: =SUM(L7:L17) -> 80252.25 | M18: =SUM(M7:M17) -> 87250.06 | N18: =SUM(N7:N17) -> 104445.42 | O18: =SUM(O7:O17) -> 111647.03 | Q18: Investments | R18: 5344.86 | S18: 5417.58 | T18: 5371.52 | U18: 5168.89 | V18: 5182.7 | W18: 3252.49 | Y18: Total non current assets | Z18: =SUM(Z7:Z17) -> 219001.55 | AA18: =SUM(AA7:AA17) -> 238707.23 | AB18: =SUM(AB7:AB17) -> 263764.16 | AC18: =SUM(AC7:AC17) -> 282896.6 | AD18: =SUM(AD7:AD17) -> 323919.38 | AE18: =SUM(AE7:AE17) -> 349223.9 | AG18: Other intangible assets | AH18: 764.141 | AI18: 886.849 | AJ18: 1027.428 | AK18: 973.607 | AL18: 1360.78 | AM18: 1420.744 | AO18: Investments | AP18: 70030 | AQ18: 94665 | AR18: 78304 | AS18: 86074 | AT18: 68663 | AU18: 57102
A19: Total non-current assets | B19: =SUM(B7:B18) -> 85405.75 | C19: =SUM(C7:C18) -> 108906.7 | D19: =SUM(D7:D18) -> 125529.27 | E19: =SUM(E7:E18) -> 132095.84 | F19: =SUM(F7:F18) -> 136723.64 | G19: =SUM(G7:G18) -> 145550 | I19: Current Assets | Q19: Trade receivables | R19: 3934.19 | S19: 6869.99 | T19: 6340.31 | U19: 6832.38 | V19: 9324.09 | W19: 11780.71 | Y19: Current Assets | AG19: Intangible assets under development | AO19: Trade receivables | AP19: 7483 | AQ19: 4159 | AR19: 14394 | AS19: 16898 | AT19: 14740 | AU19: 15591
A20: Current Assets | I20: Inventories | J20: 3183.01 | K20: 2989.73 | L20: 3576.61 | M20: 5917.92 | N20: 5970 | O20: 6249.92 | Q20: Cash and cash equivalents | R20: 204.76 | S20: 480.38 | T20: 233.85 | U20: 518.48 | V20: 279.85 | W20: 166.22 | Y20: Inventories | Z20: 67010.76 | AA20: 83427.46 | AB20: 111736.51 | AC20: 121107.58 | AD20: 121375.83 | AE20: 113878.49 | AG20: Exploratory wells in progress | AH20: 19402.48 | AI20: 18790.63 | AJ20: 15860.473 | AK20: 16392.494 | AL20: 18456.391 | AM20: 19585.93 | AO20: Cash and cash equivalents | AP20: 8485 | AQ20: 5573 | AR20: 161 | AS20: 595 | AT20: 69248 | AU20: 82471
A21: Inventories | B21: 20421.06 | C21: 26706.72 | D21: 42178.74 | E21: 38069.19 | F21: 42836.13 | G21: 45265.19 | I21: Investments | J21: 0 | K21: 468.48 | L21: 7446.53 | M21: 10679.61 | N21: 9580.27 | O21: 9436.44 | Q21: Bank Balances other than cash and cash equivalents | R21: 18.36 | S21: 94.54 | T21: 24.12 | U21: 153.92 | V21: 193.58 | W21: 87.58 | Y21: Investments | Z21: 8291.18 | AA21: 9282.61 | AB21: 8013.2 | AC21: 10436.54 | AD21: 10379.86 | AE21: 10368.91 | AG21: Acquisition cost | AH21: 18497.864 | AI21: 18439.733 | AJ21: 19165.642 | AK21: 23283.305 | AL21: 1265 | AM21: 0 | AO21: Other financial assets | AP21: =15028+16115 -> 31143 | AQ21: =993+59560 -> 60553 | AR21: 54901 | AS21: 49408 | AT21: 11747 | AU21: 15218
A22: Investments | B22: 5208.54 | C22: 6794.27 | D22: 4442.27 | E22: 4277.14 | F22: 4290.67 | G22: 3663.07 | I22: Trade receivables | J22: 4818.31 | K22: 3501.5 | L22: 1519.8 | M22: 243.77 | N22: 1146.03 | O22: 1317.18 | Q22: Loans | R22: 409.86 | S22: 126.33 | T22: 155.18 | U22: 171.46 | V22: 107.97 | W22: 118.52 | Y22: Trade receivables | Z22: 13259.48 | AA22: 13800.28 | AB22: 18700.42 | AC22: 16271.21 | AD22: 13831.45 | AE22: 18550.96 | AG22: Others | AH22: 96.758 | AI22: 180.251 | AJ22: 208.562 | AK22: 293.637 | AL22: =4219.238+51.998 -> 4271.236 | AM22: =5695.76+40.758 -> 5736.518 | AO22: Other current assets | AP22: 10711 | AQ22: 8332 | AR22: 7001 | AS22: 7220 | AT22: 13127 | AU22: 9965
A23: Trade receivables | B23: 5164.34 | C23: 7834.77 | D23: 9707.47 | E23: 6723.78 | F23: 8342.03 | G23: 9338.98 | I23: Cash and cash equivalents | J23: 624.13 | K23: 1506.59 | L23: 1284.23 | M23: 859.2 | N23: 566.1 | O23: 1403.34 | Q23: Other financial assets | R23: 7970.43 | S23: 1975.77 | T23: 1508 | U23: 1041.67 | V23: 2556.35 | W23: 2727.13 | Y23: Cash and cash equivalents | Z23: 1434.61 | AA23: 781.24 | AB23: 1176.59 | AC23: 996.35 | AD23: 1246.59 | AE23: 673.17 | AG23: Investments in | AO23: Total current assets | AP23: =SUM(AP17:AP22) -> 166654 | AQ23: =SUM(AQ17:AQ22) -> 210719 | AR23: =SUM(AR17:AR22) -> 200684 | AS23: =SUM(AS17:AS22) -> 209121 | AT23: =SUM(AT17:AT22) -> 262625 | AU23: =SUM(AU17:AU22) -> 269563
A24: Cash and cash equivalents | B24: 98.27 | C24: 7567.57 | D24: 2159.04 | E24: 2312.72 | F24: 2300.74 | G24: 557.93 | I24: Bank balances | J24: 626.04 | K24: 518.05 | L24: 99.54 | M24: 67.99 | N24: 72.62 | O24: 74.47 | Q24: Other current assets | R24: 401.24 | S24: 425.92 | T24: 482.39 | U24: 463.73 | V24: 914.09 | W24: 1237.15 | Y24: Bank balances other than above | Z24: 861.37 | AA24: 1693.49 | AB24: 643.55 | AC24: 1100.29 | AD24: 1910.46 | AE24: 2631.77 | AG24: Joint ventures and associates | AH24: 35352.174 | AI24: 35546.594 | AJ24: 36915.098 | AK24: 53671.154 | AL24: 54036.428 | AM24: 58647.459 | AO24: Total Assets | AP24: =AP15+AP23 -> 971699 | AQ24: =AQ15+AQ23 -> 873673 | AR24: =AR15+AR23 -> 856960 | AS24: =AS15+AS23 -> 833754 | AT24: =AT15+AT23 -> 959643 | AU24: =AU15+AU23 -> 1022401
A25: Bank balances | B25: 17.51 | C25: 542.54 | D25: 77.65 | E25: 261.66 | F25: 3985.62 | G25: 9917.66 | I25: Loans & Other receivables | J25: 720.32 | K25: 685.67 | L25: 1679.42 | M25: 1823.79 | N25: 1540.36 | O25: 1150.99 | Q25: Assets classified as held for sale | R25: 10.07 | S25: 12.67 | T25: 60.51 | U25: 50.49 | V25: 65.2 | W25: 9.77 | Y25: Loans | Z25: 1089.64 | AA25: 988.61 | AB25: 450.92 | AC25: 379.73 | AD25: 492.94 | AE25: 628.76 | AG25: Other investments | AH25: 16058.14 | AI25: 19057.991 | AJ25: 24355.513 | AK25: 20032.559 | AL25: 41444.934 | AM25: 33717.452 | AO25: EQUITY AND LIABILITIES
A26: Loans | B26: 590.58 | C26: 132.5 | D26: 136 | E26: 142.64 | F26: 136.92 | G26: 141.87 | I26: Other financial assets | J26: 766.26 | K26: 487.19 | L26: 0 | M26: 0 | N26: 0 | O26: 23.88 | Q26: Total current assets | R26: =SUM(R17:R25) -> 37619.76 | S26: =SUM(S17:S25) -> 44167.08 | T26: =SUM(T17:T25) -> 49690.59 | U26: =SUM(U17:U25) -> 43976.02 | V26: =SUM(V17:V25) -> 52835.29 | W26: =SUM(W17:W25) -> 57704.84 | Y26: Other financial assets | Z26: 14340.19 | AA26: 2256.04 | AB26: 1537.72 | AC26: 2660.79 | AD26: 2760.99 | AE26: 2259.46 | AG26: Trade receivables | AH26: 2374.097 | AI26: 2562.956 | AJ26: 2476.501 | AK26: 2622.486 | AL26: 2535.478 | AM26: 2379.229 | AO26: Equity
A27: Other financial assets | B27: 6811.24 | C27: 599.95 | D27: 559.66 | E27: 1101.66 | F27: 1257.95 | G27: 1771.88 | I27: Other current assets | J27: 918.82 | K27: 710.02 | L27: 701.02 | M27: 938.41 | N27: 1396.43 | O27: 1845.48 | Q27: Total assets | R27: =R15+R26 -> 116909.89 | S27: =S15+S26 -> 134159.71 | T27: =T15+T26 -> 154628.86 | U27: =U15+U26 -> 161339.51 | V27: =V15+V26 -> 182768.37 | W27: =W15+W26 -> 194744.64 | Y27: Current tax assets | Z27: 55.62 | AA27: 0 | AB27: 0 | AC27: 0 | AD27: 0.82 | AE27: 725.05 | AG27: Loans | AH27: 3214.581 | AI27: 2821.86 | AJ27: 2643.717 | AK27: 2965.559 | AL27: 3442.593 | AM27: 7584.73 | AO27: Equity share capital | AP27: 6339 | AQ27: 6445 | AR27: 6765 | AS27: 6766 | AT27: 6766 | AU27: 13532
A28: Current tax assets] | B28: 0.17 | C28: 535.21 | D28: 894.89 | E28: 969.11 | F28: 827.9 | G28: 164.66 | I28: Total current assets | J28: =SUM(J20:J27) -> 11656.89 | K28: =SUM(K20:K27) -> 10867.23 | L28: =SUM(L20:L27) -> 16307.15 | M28: =SUM(M20:M27) -> 20530.69 | N28: =SUM(N20:N27) -> 20271.81 | O28: =SUM(O20:O27) -> 21501.7 | Q28: EQUITY AND LIABILITIES | Y28: Other current assets | Z28: 4157.2 | AA28: 3786.06 | AB28: 3813.53 | AC28: 4929.57 | AD28: 5212.25 | AE28: 6414.73 | AG28: Deposit under site restoration fund | AH28: 22283.606 | AI28: 23511.47 | AJ28: 24872.18 | AK28: 26751.158 | AL28: 28571.04 | AM28: 30848.792 | AO28: Other equity | AP28: 384876 | AQ28: 468038 | AR28: 464762 | AS28: 472328 | AT28: 508330 | AU28: 529555
A29: Other current assets | B29: 1545.68 | C29: 1339.82 | D29: 1830.98 | E29: 2167.55 | F29: 1673.73 | G29: 1978.67 | I29: Total Assets | J29: =J18+J28 -> 74914.18 | K29: =K18+K28 -> 81384.96 | L29: =L18+L28 -> 96559.4 | M29: =M18+M28 -> 107780.75 | N29: =N18+N28 -> 124717.23 | O29: =O18+O28 -> 133148.73 | Q29: Equity | Y29: Assets held for sale | Z29: 235.23 | AA29: 192.9 | AB29: 788.25 | AC29: 983.43 | AD29: 1231.43 | AE29: 1511.85 | AG29: Finance lease receivables | AH29: 0 | AI29: 0 | AJ29: 0 | AK29: 0 | AL29: 0 | AM29: 0 | AO29: Total equity | AP29: =AP27+AP28 -> 391215 | AQ29: =AQ27+AQ28 -> 474483 | AR29: =AR27+AR28 -> 471527 | AS29: =AS27+AS28 -> 479094 | AT29: =AT27+AT28 -> 515096 | AU29: =AU27+AU28 -> 543087
A30: Assets held for sale | B30: 1205.84 | C30: 21.5 | D30: 12.66 | E30: 16.8 | F30: 42.42 | G30: 32.31 | I30: EQUITY AND LIABILITIES | Q30: Equity share capital | R30: 1524.21 | S30: 1452.41 | T30: 1418.94 | U30: 1418.94 | V30: 1418.94 | W30: 2128.21 | Y30: Total current assets | Z30: =SUM(Z20:Z29) -> 110735.28 | AA30: =SUM(AA20:AA29) -> 116208.69 | AB30: =SUM(AB20:AB29) -> 146860.69 | AC30: =SUM(AC20:AC29) -> 158865.49 | AD30: =SUM(AD20:AD29) -> 158442.62 | AE30: =SUM(AE20:AE29) -> 157643.15 | AG30: Others | AH30: 4136.896 | AI30: 3830.737 | AJ30: 7993.057 | AK30: 9421.588 | AL30: 10519.071 | AM30: 12098.23 | AO30: Liabilities
A31: Total current assets | B31: =SUM(B21:B30) -> 41063.23 | C31: =SUM(C21:C30) -> 52074.85 | D31: =SUM(D21:D30) -> 61999.36 | E31: =SUM(E21:E30) -> 56042.25 | F31: =SUM(F21:F30) -> 65694.11 | G31: =SUM(G21:G30) -> 72832.22 | I31: Equity | Q31: Other equity | R31: 29456.41 | S31: 36628.45 | T31: 39985.27 | U31: 30844.33 | V31: 45502.41 | W31: 49016.08 | Y31: Total assets | Z31: =Z18+Z30 -> 329736.83 | AA31: =AA18+AA30 -> 354915.92 | AB31: =AB18+AB30 -> 410624.85 | AC31: =AC18+AC30 -> 441762.09 | AD31: =AD18+AD30 -> 482362 | AE31: =AE18+AE30 -> 506867.05 | AG31: Deferred tax assets | AH31: 2667.495 | AI31: 2693.644 | AJ31: 3327.935 | AK31: 2414.586 | AL31: 6381.871 | AM31: 7077.557 | AO31: Non-current liabilities
A32: Total Assets | B32: =B19+B31 -> 126468.98 | C32: =C19+C31 -> 160981.55 | D32: =D19+D31 -> 187528.63 | E32: =E19+E31 -> 188138.09 | F32: =F19+F31 -> 202417.75 | G32: =G19+G31 -> 218382.22 | I32: Equity share capital | J32: 4510.14 | K32: 4440.39 | L32: 4440.39 | M32: 6575.1 | N32: 6575.1 | O32: 6575.1 | Q32: Total equity | R32: =R30+R31 -> 30980.62 | S32: =S30+S31 -> 38080.86 | T32: =T30+T31 -> 41404.21 | U32: =U30+U31 -> 32263.27 | V32: =V30+V31 -> 46921.35 | W32: =W30+W31 -> 51144.29 | Y32: EQUITY AND LIABILITIES | AG32: Non current tax assets | AH32: 10759.995 | AI32: 9588.479 | AJ32: 10518.589 | AK32: 14254.502 | AL32: 14873.245 | AM32: 14676.319 | AO32: Borrowings | AP32: 194402 | AQ32: 160598 | AR32: 167231 | AS32: 135561 | AT32: 161059 | AU32: 172025
A33: EQUITY AND LIABILITIES | I33: Other equity | J33: 44758.11 | K33: 48741.95 | L33: 59673.89 | M33: 58352.33 | N33: 70422.08 | O33: 78422.45 | Q33: Non current liabilities | Y33: Equity | AG33: Other non current assets | AH33: 4736.822 | AI33: 6388.355 | AJ33: 5176.63 | AK33: 3480.557 | AL33: 4060.286 | AM33: 4371.359 | AO33: Lease Liabilities | AP33: 0 | AQ33: 0 | AR33: 2790 | AS33: 2786 | AT33: 2692 | AU33: 2627
A34: Equity | I34: Non controlling interests | J34: 87.04 | K34: 97.49 | L34: 191.18 | M34: 179.55 | N34: 198.6 | O34: 242.93 | Q34: Borrowings | R34: 23109.63 | S34: 27764.42 | T34: 32115.28 | U34: 48171.47 | V34: 37943.04 | W34: 34650.77 | Y34: Equity share capital | Z34: 9181.04 | AA34: 9181.04 | AB34: 9181.04 | AC34: 13771.56 | AD34: 13771.56 | AE34: 13771.56 | AG34: Total non current assets | AH34: =SUM(AH8:AH10,AH13:AH18,AH20:AH22,AH24:AH33) -> 429308.41 | AI34: =SUM(AI8:AI10,AI13:AI18,AI20:AI22,AI24:AI33) -> 450080.45 | AJ34: =SUM(AJ8:AJ10,AJ13:AJ18,AJ20:AJ22,AJ24:AJ33) -> 479400.62 | AK34: =SUM(AK8:AK10,AK13:AK18,AK20:AK22,AK24:AK33) -> 500378.19 | AL34: =SUM(AL8:AL10,AL13:AL18,AL20:AL22,AL24:AL33) -> 601777.88 | AM34: =SUM(AM8:AM10,AM13:AM18,AM20:AM22,AM24:AM33) -> 623935.56 | AO34: Other financial liabilities | AP34: 2930 | AQ34: 4014 | AR34: 3210 | AS34: 584 | AT34: 0 | AU34: 4397
A35: Equity share capital | B35: 1966.88 | C35: 2092.91 | D35: 2129.45 | E35: 2129.45 | F35: 2136.29 | G35: 4272.58 | I35: Total equity | J35: =SUM(J32:J34) -> 49355.29 | K35: =SUM(K32:K34) -> 53279.83 | L35: =SUM(L32:L34) -> 64305.46 | M35: =SUM(M32:M34) -> 65106.98 | N35: =SUM(N32:N34) -> 77195.78 | O35: =SUM(O32:O34) -> 85240.48 | Q35: Lease Liabilities | R35: 0 | S35: 0 | T35: 3150.74 | U35: 3279.97 | V35: 3645.15 | W35: 3875.76 | Y35: Other equity | Z35: 86216.87 | AA35: 102657.01 | AB35: 124354.14 | AC35: 125948.68 | AD35: 169644.71 | AE35: 172715.76 | AG35: Current Assets | AO35: Provisions | AP35: 1410 | AQ35: 1499 | AR35: 1598 | AS35: 1296 | AT35: 1701 | AU35: 1767
A36: Other equity | B36: 31247.5 | C36: 51462.17 | D36: 49776.17 | E36: 51392.91 | F36: 73498.82 | G36: 77111.5 | I36: Non-current Liabilities | Q36: Other financial liabilities | R36: 0.7 | S36: 32.63 | T36: 0.73 | U36: 0.3 | V36: 0.32 | W36: 0.35 | Y36: Non controlling interest | Z36: 876.27 | AA36: 975.94 | AB36: 1591.47 | AC36: 3494.1 | AD36: 4746.71 | AE36: 4537.34 | AG36: Inventories | AH36: 33051.203 | AI36: 44573.326 | AJ36: 54163.099 | AK36: 44238.068 | AL36: 53792.779 | AM36: 58956.33 | AO36: Deferred tax liabilities | AP36: 50556 | AQ36: 30788 | AR36: 30832 | AS36: 33968 | AT36: 36259 | AU36: 37390
A37: Total Equity | B37: =B35+B36 -> 33214.38 | C37: =C35+C36 -> 53555.08 | D37: =D35+D36 -> 51905.62 | E37: =E35+E36 -> 53522.36 | F37: =F35+F36 -> 75635.11 | G37: =G35+G36 -> 81384.08 | I37: Borrowings | J37: 3773.4 | K37: 5237.4 | L37: 5468.06 | M37: 8879.69 | N37: 12806.02 | O37: 10781.04 | Q37: Provision | R37: 54.62 | S37: 56.78 | T37: 103.11 | U37: 112.93 | V37: 82.62 | W37: 203.34 | Y37: Total equity | Z37: =SUM(Z34:Z36) -> 96274.18 | AA37: =SUM(AA34:AA36) -> 112813.99 | AB37: =SUM(AB34:AB36) -> 135126.65 | AC37: =SUM(AC34:AC36) -> 143214.34 | AD37: =SUM(AD34:AD36) -> 188162.98 | AE37: =SUM(AE34:AE36) -> 191024.66 | AG37: Investments | AH37: 5344.862 | AI37: 5417.573 | AJ37: 5371.524 | AK37: 5168.897 | AL37: 5380.209 | AM37: 3252.502 | AO37: Other non current liabilities | AP37: 504 | AQ37: 504 | AR37: 504 | AS37: 0 | AT37: 2822 | AU37: 3173
A38: Non-current Liabilities | I38: Lease Liabilities | J38: 92.49 | K38: 453.34 | L38: 1001.9 | M38: 1117.72 | N38: 2331.35 | O38: 4237.97 | Q38: Deferred tax liabilities | R38: 5491.44 | S38: 5462.21 | T38: 5957.71 | U38: 2927.63 | V38: 6932.89 | W38: 7707.65 | Y38: LIABILITIES | AG38: Trade receivables | AH38: 9193.407 | AI38: 16015.834 | AJ38: 19187.283 | AK38: 18751.581 | AL38: 19704.13 | AM38: 21227.799 | AO38: Total non current liabilities | AP38: =SUM(AP32:AP37) -> 249802 | AQ38: =SUM(AQ32:AQ37) -> 197403 | AR38: =SUM(AR32:AR37) -> 206165 | AS38: =SUM(AS32:AS37) -> 174195 | AT38: =SUM(AT32:AT37) -> 204533 | AU38: =SUM(AU32:AU37) -> 221379
A39: Borrowings | B39: 26272.7 | C39: 35740.22 | D39: 36358.93 | E39: 41369.36 | F39: 26877.14 | G39: 26527.88 | I39: Deferred tax Liabilities | J39: 871.12 | K39: 689.72 | L39: 691.55 | M39: 732.8 | N39: 717.61 | O39: 809.44 | Q39: Other non current liabilities | R39: 224.83 | S39: 382.48 | T39: 456.84 | U39: 718.05 | V39: 817.49 | W39: 884.76 | Y39: Non current liabilities | AG39: Cash and cash equivalents | AH39: 4780.562 | AI39: 4019.369 | AJ39: 5034.667 | AK39: 2639.998 | AL39: 4141.571 | AM39: 4554.357 | AO39: Current Liabilities
A40: Lease liabilities | B40: 0 | C40: 7612.07 | D40: 8040.73 | E40: 8265.17 | F40: 8600.15 | G40: 8840.4 | I40: Other non current liabilities | J40: 538.51 | K40: 557.02 | L40: 676.08 | M40: 809.13 | N40: 942.05 | O40: 994.43 | Q40: Total non current liabilities | R40: =SUM(R34:R39) -> 28881.22 | S40: =SUM(S34:S39) -> 33698.52 | T40: =SUM(T34:T39) -> 41784.41 | U40: =SUM(U34:U39) -> 55210.35 | V40: =SUM(V34:V39) -> 49421.51 | W40: =SUM(W34:W39) -> 47322.63 | Y40: Borrowings | Z40: 56070.61 | AA40: 60934.9 | AB40: 55944.54 | AC40: 63312.94 | AD40: 46792.9 | AE40: 51755.75 | AG40: Other bank balances | AH40: 4859.674 | AI40: 3172.902 | AJ40: 1806.272 | AK40: 26500.329 | AL40: 37690.277 | AM40: 22623.402 | AO40: Borrowings | AP40: 59899 | AQ40: 33152 | AR40: 27332 | AS40: 80262 | AT40: 50731 | AU40: 26788
A41: Other financial liabilities | B41: 53.99 | C41: 58.08 | D41: 56.63 | E41: 68.89 | F41: 70.82 | G41: 58.74 | I41: Other financial liabilities | J41: 245.81 | K41: 345.16 | L41: 447.22 | M41: 486.13 | N41: 560.09 | O41: 692.3 | Q41: Current Liabilities | Y41: Other financial liabilities | Z41: 789.58 | AA41: 847.48 | AB41: 6363.62 | AC41: 6476.91 | AD41: 6331.9 | AE41: 6578.65 | AG41: Loans | AH41: 1182.117 | AI41: 752.06 | AJ41: 492.88 | AK41: 457.61 | AL41: 420.073 | AM41: 459.038 | AO41: Lease Liabilities | AP41: 0 | AQ41: 0 | AR41: 86 | AS41: 97 | AT41: 93 | AU41: 65
A42: Provisions | B42: 1574.12 | C42: 827.49 | D42: 234.29 | E42: 208.22 | F42: 305.35 | G42: 325.87 | I42: Provisions | J42: 4039.19 | K42: 4088.46 | L42: 4199.17 | M42: 4395.09 | N42: 4135.7 | O42: 4259.81 | Q42: Borrowings | R42: 16276.12 | S42: 14909.65 | T42: 12863.45 | U42: 18876.83 | V42: 24870.08 | W42: 31778.11 | Y42: Provisions | Z42: 1597.23 | AA42: 1596.83 | AB42: 1585.35 | AC42: 1396.44 | AD42: 1414.82 | AE42: 1406.63 | AG42: Others | AH42: 11570.754 | AI42: 6562.164 | AJ42: 5265.049 | AK42: 9246.876 | AL42: 12413.09 | AM42: 15445.431 | AO42: Micro and small enterprises | AP42: 116 | AQ42: 90 | AR42: 138 | AS42: 210 | AT42: 492 | AU42: 1301
A43: Deferred tax liability | B43: 5967.29 | C43: 4934.48 | D43: 6375.72 | E43: 7920.55 | F43: 7975.68 | G43: 8292.67 | I43: Contract liabilities | J43: 3522.22 | K43: 4181.7 | L43: 4676.63 | M43: 4542.19 | N43: 4388.09 | O43: 4233.75 | Q43: Lease Liabilities | R43: 0 | S43: 0 | T43: 368.28 | U43: 342.75 | V43: 225.55 | W43: 253.58 | Y43: Deferred tax liabilities | Z43: 11439.29 | AA43: 13964.47 | AB43: 15354.37 | AC43: 16800.42 | AD43: 18960.7 | AE43: 20664.96 | AG43: Current tax assets | AH43: 198.314 | AI43: 188.436 | AJ43: 120.994 | AK43: 134.016 | AL43: 0 | AM43: 0.779 | AO43: Other than above | AP43: 70932 | AQ43: 86909 | AR43: 133867 | AS43: 110512 | AT43: 129367 | AU43: 121078
A44: Other non current liabilities | B44: 381.72 | C44: 549.95 | D44: 1488.24 | E44: 1912.51 | F44: 2070.12 | G44: 2280.58 | I44: Total non current liabilities | J44: =SUM(J37:J43) -> 13082.74 | K44: =SUM(K37:K43) -> 15552.8 | L44: =SUM(L37:L43) -> 17160.61 | M44: =SUM(M37:M43) -> 20962.75 | N44: =SUM(N37:N43) -> 25880.91 | O44: =SUM(O37:O43) -> 26008.74 | Q44: Outstanding dues of micro and small enterprises | R44: 113.75 | S44: 131.99 | T44: 402.21 | U44: 465.15 | V44: 785.1 | W44: 901.64 | Y44: Other non current liabilities | Z44: 2048.1 | AA44: 2583.36 | AB44: =3180.59+205.11 -> 3385.7 | AC44: =194.81+3707.9 -> 3902.71 | AD44: =233.11+4061.57 -> 4294.68 | AE44: =199.43+4622.56 -> 4821.99 | AG44: Other current assets | AH44: 10534.424 | AI44: 12466.191 | AJ44: 14484.052 | AK44: 6959.33 | AL44: 6600.23 | AM44: 8263.799 | AO44: Total trade payables | AP44: =AP42+AP43 -> 71048 | AQ44: =AQ42+AQ43 -> 86999 | AR44: =AR42+AR43 -> 134005 | AS44: =AS42+AS43 -> 110722 | AT44: =AT42+AT43 -> 129859 | AU44: =AU42+AU43 -> 122379
A45: Total non-current liabilities | B45: =SUM(B39:B44) -> 34249.82 | C45: =SUM(C39:C44) -> 49722.29 | D45: =SUM(D39:D44) -> 52554.54 | E45: =SUM(E39:E44) -> 59744.7 | F45: =SUM(F39:F44) -> 45899.26 | G45: =SUM(G39:G44) -> 46326.14 | I45: Current Liabilities | Q45: Outstanding dues other than above | R45: 11358.8 | S45: 17666.66 | T45: 26075.12 | U45: 22448.08 | V45: 26514.91 | W45: 28899.16 | Y45: Total non current liabilities | Z45: =SUM(Z40:Z44) -> 71944.81 | AA45: =SUM(AA40:AA44) -> 79927.04 | AB45: =SUM(AB40:AB44) -> 82633.58 | AC45: =SUM(AC40:AC44) -> 91889.42 | AD45: =SUM(AD40:AD44) -> 77795 | AE45: =SUM(AE40:AE44) -> 85227.98 | AG45: Assets classified as held for sale | AH45: 14.134 | AI45: 16.309 | AJ45: 63.848 | AK45: 53.826 | AL45: 78.387 | AM45: 13.105 | AO45: Other financial liabilities | AP45: 132492 | AQ45: 61172 | AR45: 33225 | AS45: 25611 | AT45: 27493 | AU45: 35264
A46: Current Liabilities | I46: Borrowings | J46: 2564.2 | K46: 1522.9 | L46: 2362.26 | M46: 7395.21 | N46: 5801.98 | O46: 5526.33 | Q46: Total trade payables | R46: =R44+R45 -> 11472.55 | S46: =S44+S45 -> 17798.65 | T46: =T44+T45 -> 26477.33 | U46: =U44+U45 -> 22913.23 | V46: =V44+V45 -> 27300.01 | W46: =W44+W45 -> 29800.8 | Y46: Current Liabilities | AG46: Total current assets | AH46: =SUM(AH36,AH38:AH45) -> 75384.589 | AI46: =SUM(AI36,AI38:AI45) -> 87766.591 | AJ46: =SUM(AJ36,AJ38:AJ45) -> 100618.14 | AK46: =SUM(AK36,AK38:AK45) -> 108981.63 | AL46: =SUM(AL36,AL38:AL45) -> 134840.54 | AM46: =SUM(AM36,AM38:AM45) -> 131544.04 | AO46: Other current liabilities | AP46: 66170 | AQ46: 19563 | AR46: 5438 | AS46: 19659 | AT46: 30866 | AU46: 72283
A47: Borrowings | B47: 17721.37 | C47: 10935.99 | D47: 19573.75 | E47: 19085.25 | F47: 18607.79 | G47: 24533.03 | I47: Lease Liabilities | J47: 166.1 | K47: 213.91 | L47: 383.5 | M47: 423.56 | N47: 854.42 | O47: 1050.04 | Q47: Other financial liabilities | R47: 23385.91 | S47: 20778.02 | T47: 22539.11 | U47: 23460.4 | V47: 23635.24 | W47: 24427.18 | Y47: Borrowings | Z47: 69897.44 | AA47: 47580.01 | AB47: 67605.56 | AC47: 76801.88 | AD47: 76660.67 | AE47: 90804.15 | AG47: Total assets | AH47: =AH34+AH46 -> 504693 | AI47: =AI34+AI46 -> 537847.04 | AJ47: =AJ34+AJ46 -> 580018.76 | AK47: =AK34+AK46 -> 609359.83 | AL47: =AL34+AL46 -> 736618.42 | AM47: =AM34+AM46 -> 755479.6 | AO47: Provisions | AP47: 1073 | AQ47: 901 | AR47: 896 | AS47: 925 | AT47: 972 | AU47: 1156
A48: Lease liabilities | B48: 0 | C48: 243.58 | D48: 560.79 | E48: 656.25 | F48: 513.97 | G48: 1199.26 | I48: Total outstanding dues of micro and small enterprises | J48: 271.82 | K48: 241.26 | L48: 303.91 | M48: 344.29 | N48: 375.79 | O48: 376.55 | Q48: Other current liabilities | R48: 2915.94 | S48: 5715.2 | T48: 6437.49 | U48: 5572.76 | V48: 6817.58 | W48: 6412.1 | Y48: Lease Liabilities | Z48: 0 | AA48: 0 | AB48: 2105.87 | AC48: 2385.35 | AD48: 2842 | AE48: 3132.01 | AG48: EQUITY AND LIABILITIES | AO48: Total current liabilities | AP48: =SUM(AP40:AP41,AP44,AP45:AP47) -> 330682 | AQ48: =SUM(AQ40:AQ41,AQ44,AQ45:AQ47) -> 201787 | AR48: =SUM(AR40:AR41,AR44,AR45:AR47) -> 200982 | AS48: =SUM(AS40:AS41,AS44,AS45:AS47) -> 237276 | AT48: =SUM(AT40:AT41,AT44,AT45:AT47) -> 240014 | AU48: =SUM(AU40:AU41,AU44,AU45:AU47) -> 257935
A49: Outstanding dues of micro and small enterprises | B49: 67.17 | C49: 147.79 | D49: 245.26 | E49: 273.59 | F49: 276.89 | G49: 324.23 | I49: Total outstanding dues other than above | J49: 3650.36 | K49: 4211.92 | L49: 5057.35 | M49: 6799.27 | N49: 6263.88 | O49: 7383.3 | Q49: Provisions | R49: 2630.56 | S49: 2827.09 | T49: 2487.15 | U49: 2653.76 | V49: 3393.3 | W49: 3411.53 | Y49: Outstanding dues of micro and small enterprises | Z49: 205.56 | AA49: 324.28 | AB49: 806.63 | AC49: 1024.97 | AD49: 1423.7 | AE49: 1422.49 | AG49: EQUITY | AO49: Total equity and liabilities | AP49: =AP29+AP38+AP48 -> 971699 | AQ49: =AQ29+AQ38+AQ48 -> 873673 | AR49: =AR29+AR38+AR48 -> 878674 | AS49: =AS29+AS38+AS48 -> 890565 | AT49: =AT29+AT38+AT48 -> 959643 | AU49: =AU29+AU38+AU48 -> 1022401
A50: Outstanding dues other than above | B50: 12442.37 | C50: 16122.14 | D50: 30102.46 | E50: 23750.67 | F50: 28028.92 | G50: 30309.83 | I50: Total trade payables | J50: =J48+J49 -> 3922.18 | K50: =K48+K49 -> 4453.18 | L50: =L48+L49 -> 5361.26 | M50: =M48+M49 -> 7143.56 | N50: =N48+N49 -> 6639.67 | O50: =O48+O49 -> 7759.85 | Q50: Current tax liabilities | R50: 366.97 | S50: 351.72 | T50: 267.43 | U50: 46.16 | V50: 92.56 | W50: 194.42 | Y50: Outstanding dues other than above | Z50: 27370.7 | AA50: 36923.69 | AB50: 48255.22 | AC50: 53709.13 | AD50: 58030.4 | AE50: 59112.45 | AG50: Equity share capital | AH50: 6290.54 | AI50: 6290.139 | AJ50: 6290.139 | AK50: 6290.139 | AL50: 6290.139 | AM50: 6290.139 | AO50: Working capital | AP50: =AP23-AP48 -> -164028 | AQ50: =AQ23-AQ48 -> 8932 | AR50: =AR23-AR48 -> -298 | AS50: =AS23-AS48 -> -28155 | AT50: =AT23-AT48 -> 22611 | AU50: =AU23-AU48 -> 11628
A51: Total trade payables | B51: =B49+B50 -> 12509.54 | C51: =C49+C50 -> 16269.93 | D51: =D49+D50 -> 30347.72 | E51: =E49+E50 -> 24024.26 | F51: =F49+F50 -> 28305.81 | G51: =G49+G50 -> 30634.06 | I51: Other financial liabilities | J51: 3866.71 | K51: 4271.61 | L51: 4342.35 | M51: 4039.67 | N51: 5504.46 | O51: 4918.65 | Q51: Total current liabilities | R51: =SUM(R42:R43,R46,R47:R50) -> 57048.05 | S51: =SUM(S42:S43,S46,S47:S50) -> 62380.33 | T51: =SUM(T42:T43,T46,T47:T50) -> 71440.24 | U51: =SUM(U42:U43,U46,U47:U50) -> 73865.89 | V51: =SUM(V42:V43,V46,V47:V50) -> 86334.32 | W51: =SUM(W42:W43,W46,W47:W50) -> 96277.72 | Y51: Total trade payables | Z51: =Z49+Z50 -> 27576.26 | AA51: =AA49+AA50 -> 37247.97 | AB51: =AB49+AB50 -> 49061.85 | AC51: =AC49+AC50 -> 54734.1 | AD51: =AD49+AD50 -> 59454.1 | AE51: =AE49+AE50 -> 60534.94 | AG51: Other equity | AH51: 198814.45 | AI51: 214690.85 | AJ51: 253212.77 | AK51: 274357.16 | AL51: 332778.74 | AM51: 337150.34
A52: Other financial liabilities | B52: 22472.48 | C52: 19916.42 | D52: 20983.28 | E52: 21350.11 | F52: 22757.82 | G52: 25120.08 | I52: Other current liabilities | J52: 604.69 | K52: 764.54 | L52: 1183.04 | M52: 1169.19 | N52: 1052.08 | O52: 985.98 | Q52: Liabilities as held for sale | R52: 0 | S52: 0 | T52: 0 | U52: 0 | V52: 0 | W52: 91.19 | Y52: Other financial liabilities | Z52: 41939.63 | AA52: 50169.1 | AB52: 44730.46 | AC52: 45400.86 | AD52: 50604.91 | AE52: 51287.99 | AG52: Non controlling interests | AH52: 18405.739 | AI52: 21615.799 | AJ52: 23824.933 | AK52: 20607.739 | AL52: 20555.378 | AM52: 30794.641 | AO52: Particulars | AP52: 2026 | AQ52: 2027 | AR52: 2028 | AS52: 2029 | AT52: 2030
A53: Other current liabilities | B53: 3903.02 | C53: 6780.92 | D53: 7259.56 | E53: 7025 | F53: 7065.26 | G53: 6713.01 | I53: Provisions | J53: 577.11 | K53: 497.48 | L53: 587.72 | M53: 611.27 | N53: 711.87 | O53: 572.02 | Q53: Total equity and liabilities | R53: =R32+R40+R51+R52 -> 116909.89 | S53: =S32+S40+S51+S52 -> 134159.71 | T53: =T32+T40+T51+T52 -> 154628.86 | U53: =U32+U40+U51+U52 -> 161339.51 | V53: =V32+V40+V51+V52 -> 182677.18 | W53: =W32+W40+W51+W52 -> 194835.83 | Y53: Other current liabilities | Z53: 12468.24 | AA53: 17072.96 | AB53: 18966.68 | AC53: 17150.58 | AD53: 15240.85 | AE53: 14787.63 | AG53: Total equity | AH53: =SUM(AH50:AH52) -> 223510.73 | AI53: =SUM(AI50:AI52) -> 242596.79 | AJ53: =SUM(AJ50:AJ52) -> 283327.84 | AK53: =SUM(AK50:AK52) -> 301255.04 | AL53: =SUM(AL50:AL52) -> 359624.25 | AM53: =SUM(AM50:AM52) -> 374235.12 | AO53: Working Capital Forecast | AP53: =FCFF!AW5*FCFF!$AV$11 -> 2150.2785 | AQ53: =FCFF!AX5*FCFF!$AV$11 -> 2301.1389 | AR53: =FCFF!AY5*FCFF!$AV$11 -> 2462.5833 | AS53: =FCFF!AZ5*FCFF!$AV$11 -> 2635.3545 | AT53: =FCFF!BA5*FCFF!$AV$11 -> 2820.2471
A54: Provisions | B54: 1831 | C54: 2731.68 | D54: 2925.39 | E54: 2729.28 | F54: 3023.29 | G54: 2331.48 | I54: Current tax liabilities | J54: 0 | K54: 0 | L54: 0 | M54: 0 | N54: 0 | O54: 106.99 | Q54: Working capital | R54: =R26-R51 -> -19428.29 | S54: =S26-S51 -> -18213.25 | T54: =T26-T51 -> -21749.65 | U54: =U26-U51 -> -29889.87 | V54: =V26-V51 -> -33499.03 | W54: =W26-W51 -> -38572.88 | Y54: Provisions | Z54: 9636.27 | AA54: 9302.33 | AB54: 9749.83 | AC54: 10156.28 | AD54: 10628.26 | AE54: 10012.74 | AG54: Liabilities
A55: Current tax liabilities | B55: 32.8 | C55: 825.66 | D55: 1417.98 | E55: 0.98 | F55: 609.44 | G55: 141.08 | I55: Contract liabilities | J55: 775.16 | K55: 828.71 | L55: 873.2 | M55: 928.56 | N55: 1076.06 | O55: 979.65 | Y55: Current tax liabilities | Z55: 0 | AA55: 802.52 | AB55: 619.31 | AC55: 18.22 | AD55: 954.37 | AE55: 39.97 | AG55: Non current liabilities
A56: Total current liabilities | B56: =SUM(B47:B48,B51,B52:B55) -> 58470.21 | C56: =SUM(C47:C48,C51,C52:C55) -> 57704.18 | D56: =SUM(D47:D48,D51,D52:D55) -> 83068.47 | E56: =SUM(E47:E48,E51,E52:E55) -> 74871.13 | F56: =SUM(F47:F48,F51,F52:F55) -> 80883.38 | G56: =SUM(G47:G48,G51,G52:G55) -> 90672 | I56: Total current liabilities | J56: =SUM(J46:J47,J50,J51:J55) -> 12476.15 | K56: =SUM(K46:K47,K50,K51:K55) -> 12552.33 | L56: =SUM(L46:L47,L50,L51:L55) -> 15093.33 | M56: =SUM(M46:M47,M50,M51:M55) -> 21711.02 | N56: =SUM(N46:N47,N50,N51:N55) -> 21640.54 | O56: =SUM(O46:O47,O50,O51:O55) -> 21899.51 | Y56: Total current liabilities | Z56: =SUM(Z47:Z48,Z51,Z52:Z55) -> 161517.84 | AA56: =SUM(AA47:AA48,AA51,AA52:AA55) -> 162174.89 | AB56: =SUM(AB47:AB48,AB51,AB52:AB55) -> 192839.56 | AC56: =SUM(AC47:AC48,AC51,AC52:AC55) -> 206647.27 | AD56: =SUM(AD47:AD48,AD51,AD52:AD55) -> 216385.16 | AE56: =SUM(AE47:AE48,AE51,AE52:AE55) -> 230599.43 | AG56: Borrowings | AH56: 72931.577 | AI56: 79162.063 | AJ56: 88042.676 | AK56: 98359.545 | AL56: 96970.637 | AM56: 98474.125
A57: Liabilities held for sale | B57: 534.57 | C57: 0 | D57: 0 | E57: 0 | F57: 0 | G57: 0 | I57: Total Equity and Liabilities | J57: =J35+J44+J56 -> 74914.18 | K57: =K35+K44+K56 -> 81384.96 | L57: =L35+L44+L56 -> 96559.4 | M57: =M35+M44+M56 -> 107780.75 | N57: =N35+N44+N56 -> 124717.23 | O57: =O35+O44+O56 -> 133148.73 | Q57: Particulars | R57: 2026 | S57: 2027 | T57: 2028 | U57: 2029 | V57: 2030 | Y57: Liabilities as held for sale | Z57: 0 | AA57: 0 | AB57: 25.06 | AC57: 11.06 | AD57: 18.77 | AE57: 14.98 | AG57: Lease Liabilities | AH57: 8014.865 | AI57: 9646.202 | AJ57: 9216.721 | AK57: 8403.529 | AL57: 25576.195 | AM57: 24384.788
A58: Total Liabilities | B58: =B45+B56+B57 -> 93254.6 | C58: =C45+C56 -> 107426.47 | D58: =D45+D56 -> 135623.01 | E58: =E45+E56 -> 134615.83 | F58: =F45+F56 -> 126782.64 | G58: =G45+G56 -> 136998.14 | I58: Working capital | J58: =J28-J56 -> -819.26 | K58: =K28-K56 -> -1685.1 | L58: =L28-L56 -> 1213.82 | M58: =M28-M56 -> -1180.33 | N58: =N28-N56 -> -1368.73 | O58: =O28-O56 -> -397.81 | Q58: Working Capital Forecast | R58: =FCFF!$U$11*FCFF!V5 -> -44277.596 | S58: =FCFF!$U$11*FCFF!W5 -> -47983.811 | T58: =FCFF!$U$11*FCFF!X5 -> -52000.252 | U58: =FCFF!$U$11*FCFF!Y5 -> -56352.885 | V58: =FCFF!$U$11*FCFF!Z5 -> -61069.851 | Y58: Total equity and liabilities | Z58: =Z37+Z45+Z56+Z57 -> 329736.83 | AA58: =AA37+AA45+AA56+AA57 -> 354915.92 | AB58: =AB37+AB45+AB56+AB57 -> 410624.85 | AC58: =AC37+AC45+AC56+AC57 -> 441762.09 | AD58: =AD37+AD45+AD56+AD57 -> 482361.91 | AE58: =AE37+AE45+AE56+AE57 -> 506867.05 | AG58: Others | AH58: 701.914 | AI58: 6286.66 | AJ58: 1950.243 | AK58: 431.757 | AL58: 271.67 | AM58: 317.81
A59: Total Equity and Liabilities | B59: =B37+B58 -> 126468.98 | C59: =C37+C58 -> 160981.55 | D59: =D37+D58 -> 187528.63 | E59: =E37+E58 -> 188138.19 | F59: =F37+F58 -> 202417.75 | G59: =G37+G58 -> 218382.22 | Y59: Working capital | Z59: =Z30-Z56 -> -50782.56 | AA59: =AA30-AA56 -> -45966.2 | AB59: =AB30-AB56 -> -45978.87 | AC59: =AC30-AC56 -> -47781.78 | AD59: =AD30-AD56 -> -57942.54 | AE59: =AE30-AE56 -> -72956.28 | AG59: Provisions | AH59: 33100.604 | AI59: 36114.511 | AJ59: 36383.008 | AK59: 40423.068 | AL59: 50678.045 | AM59: 54308.149
A60: Working Capital | B60: =B31-B56 -> -17406.98 | C60: =C31-C56 -> -5629.33 | D60: =D31-D56 -> -21069.11 | E60: =E31-E56 -> -18828.88 | F60: =F31-F56 -> -15189.27 | G60: =G31-G56 -> -17839.78 | AG60: Deferred tax liabilities | AH60: 46042.014 | AI60: 45400.45 | AJ60: 38262.355 | AK60: 32135.79 | AL60: 38228.52 | AM60: 38761.834
Y61: Particulars | Z61: 2026 | AA61: 2027 | AB61: 2028 | AC61: 2029 | AD61: 2030 | AG61: Other non current liabilities | AH61: 643.722 | AI61: 793.194 | AJ61: 842.199 | AK61: 1249.821 | AL61: 1301.124 | AM61: 1399.273
A62: Particulars | B62: 2026 | C62: 2027 | D62: 2028 | E62: 2029 | F62: 2030 | I62: Particulars | J62: 2026 | K62: 2027 | L62: 2028 | M62: 2029 | N62: 2030 | Y62: Working Capital Forecast | Z62: =FCFF!AE5*FCFF!$AD$11 -> -65207.318 | AA62: =FCFF!AF5*FCFF!$AD$11 -> -69695.426 | AB62: =FCFF!AG5*FCFF!$AD$11 -> -74492.442 | AC62: =FCFF!AH5*FCFF!$AD$11 -> -79619.629 | AD62: =FCFF!AI5*FCFF!$AD$11 -> -85099.712 | AG62: Total non current liabilities | AH62: =SUM(AH56:AH61) -> 161434.7 | AI62: =SUM(AI56:AI61) -> 177403.08 | AJ62: =SUM(AJ56:AJ61) -> 174697.2 | AK62: =SUM(AK56:AK61) -> 181003.51 | AL62: =SUM(AL56:AL61) -> 213026.19 | AM62: =SUM(AM56:AM61) -> 217645.98
A63: Working Capital Forecast | B63: =FCFF!D5*FCFF!$C$11 -> -19845.969 | C63: =FCFF!E5*FCFF!$C$11 -> -21284.592 | D63: =FCFF!F5*FCFF!$C$11 -> -22827.5 | E63: =FCFF!G5*FCFF!$C$11 -> -24482.253 | F63: =FCFF!H5*FCFF!$C$11 -> -26256.957 | I63: Working Capital Forecast | J63: =FCFF!M5*FCFF!$L$11 -> -1041.7241 | K63: =FCFF!N5*FCFF!$L$11 -> -1163.0748 | L63: =FCFF!O5*FCFF!$L$11 -> -1298.5616 | M63: =FCFF!P5*FCFF!$L$11 -> -1449.8314 | N63: =FCFF!Q5*FCFF!$L$11 -> -1618.7226 | AG63: Current Liabilities
AG64: Borrowings | AH64: 31505.634 | AI64: 30657.61 | AJ64: 19733.13 | AK64: 30826.011 | AL64: 60714.95 | AM64: 55081.779
AG65: Outstanding dues of micro and small enterprises | AH65: 165.15 | AI65: 312.757 | AJ65: 794.849 | AK65: 749.094 | AL65: 1301.407 | AM65: 1380.386
AG66: Outstanding dues other than above | AH66: 22795.976 | AI66: 27136.388 | AJ66: 39391.165 | AK66: 32893.508 | AL66: 36845.855 | AM66: 37595.145
AG67: Total trade payables | AH67: =AH65+AH66 -> 22961.126 | AI67: =AI65+AI66 -> 27449.145 | AJ67: =AJ65+AJ66 -> 40186.014 | AK67: =AK65+AK66 -> 33642.602 | AL67: =AL65+AL66 -> 38147.262 | AM67: =AM65+AM66 -> 38975.531
AG68: Lease Liabilities | AH68: 5155.218 | AI68: 4479.569 | AJ68: 4993.331 | AK68: 4665.731 | AL68: 7933.445 | AM68: 9876.61
AG69: Others | AH69: 54304.651 | AI69: 46059.34 | AJ69: 43411.692 | AK69: 47722.264 | AL69: 43519.17 | AM69: 44562.952
AG70: Other current liabilities | AH70: 6333.519 | AI70: 8997.843 | AJ70: 11394.821 | AK70: 9759.084 | AL70: 11398.111 | AM70: 10631.687
AG71: Provisions | AH71: 4187.202 | AI71: 4878.686 | AJ71: 6663.468 | AK71: 5248.736 | AL71: 6963.753 | AM71: 7071.131
AG72: Current tax liabilities | AH72: 625.226 | AI72: 742.552 | AJ72: 982.787 | AK72: 405.753 | AL72: =579.601+91.186 -> 670.787 | AM72: 642.316
AG73: Total current liabilities | AH73: =SUM(AH64,AH67,AH68:AH72) -> 125072.58 | AI73: =SUM(AI64,AI67,AI68:AI72) -> 123264.75 | AJ73: =SUM(AJ64,AJ67,AJ68:AJ72) -> 127365.24 | AK73: =SUM(AK64,AK67,AK68:AK72) -> 132270.18 | AL73: =SUM(AL64,AL67,AL68:AL72) -> 169347.48 | AM73: =SUM(AM64,AM67,AM68:AM72) -> 166842.01
AG74: Total equity and liabilities | AH74: =AH53+AH62+AH73 -> 510018 | AI74: =AI53+AI62+AI73 -> 543264.61 | AJ74: =AJ53+AJ62+AJ73 -> 585390.29 | AK74: =AK53+AK62+AK73 -> 614528.73 | AL74: =AL53+AL62+AL73 -> 741997.92 | AM74: =AM53+AM62+AM73 -> 758723.1
AG75: Working capital | AH75: =AH46-AH73 -> -49687.987 | AI75: =AI46-AI73 -> -35498.154 | AJ75: =AJ46-AJ73 -> -26747.099 | AK75: =AK46-AK73 -> -23288.547 | AL75: =AL46-AL73 -> -34506.941 | AM75: =AM46-AM73 -> -35297.966
AG77: Particulars | AH77: 2026 | AI77: 2027 | AJ77: 2028 | AK77: 2029 | AL77: 2030
AG78: Working Capital Forecast | AH78: =FCFF!AN5*FCFF!$AM$11 -> -33294.908 | AI78: =FCFF!AO5*FCFF!$AM$11 -> -35843.53 | AJ78: =FCFF!AP5*FCFF!$AM$11 -> -38587.241 | AK78: =FCFF!AQ5*FCFF!$AM$11 -> -41540.974 | AL78: =FCFF!AR5*FCFF!$AM$11 -> -44720.806

Sheet Income Statement
A1: INCOME STATEMENT
A3: #VALUE! | I3: #VALUE! | Q3: #VALUE! | Y3: #VALUE! | AG3: #VALUE! | AO3: #VALUE!
A4: Particulars | B4: 2020 | C4: 2021 | D4: 2022 | E4: 2023 | F4: 2024 | G4: 2025 | I4: Particulars | J4: 2020 | K4: 2021 | L4: 2022 | M4: 2023 | N4: 2024 | O4: 2025 | Q4: Particulars | R4: 2020 | S4: 2021 | T4: 2022 | U4: 2023 | V4: 2024 | W4: 2025 | Y4: Particulars | Z4: 2020 | AA4: 2021 | AB4: 2022 | AC4: 2023 | AD4: 2024 | AE4: 2025 | AG4: Particulars | AH4: 2020 | AI4: 2021 | AJ4: 2022 | AK4: 2023 | AL4: 2024 | AM4: 2025 | AO4: Particulars | AP4: 2020 | AQ4: 2021 | AR4: 2022 | AS4: 2023 | AT4: 2024 | AU4: 2025
A5: INCOME | I5: INCOME | Q5: INCOME | Y5: INCOME | AG5: INCOME | AO5: INCOME
A6: Revenue from operations | B6: 327580.78 | C6: 301873.16 | D6: 432422.48 | E6: 533467.55 | F6: 506992.6 | G6: 500517.48 | I6: Revenue from operations | J6: 72576.98 | K6: 57428.26 | L6: 92873.82 | M6: 145875.03 | N6: 133499.54 | O6: 142291.42 | Q6: Gross sale of products | R6: 286574.27 | S6: 269493.69 | T6: 372867.94 | U6: 464989.7 | V6: 460147.32 | W6: 464626.25 | Y6: Revenue from operations | Z6: 575989.7 | AA6: 520236.84 | AB6: 736716.3 | AC6: 951409.94 | AD6: 881235.45 | AE6: 859362.73 | AG6: Revenue from operations | AH6: 424961.08 | AI6: 360572.31 | AJ6: 531792.54 | AK6: 684829.22 | AL6: 653170.77 | AM6: 663262.31 | AO6: Value of sales | AP6: 362869 | AQ6: 276181 | AR6: 463067 | AS6: 562234 | AT6: 533566 | AU6: 538564
A7: Other income | B7: 3081.31 | C7: 4336.27 | D7: 2629.36 | E7: 2183.99 | F7: 2234.73 | G7: 2684.72 | I7: Other income | J7: 1537.15 | K7: 1120.2 | L7: 1172.25 | M7: 1328.47 | N7: 1007.81 | O7: 1267.64 | Q7: Other operating income | R7: 1167.78 | S7: 1084.27 | T7: 1259.05 | U7: 1508.91 | V7: 1821.82 | W7: 2097.43 | Y7: Other income | Z7: 2773.62 | AA7: 3499.54 | AB7: 3096.76 | AC7: 4198.92 | AD7: 3838.56 | AE7: 3513.73 | AG7: Other income | AH7: 9077.022 | AI7: 9323.019 | AJ7: 7437.71 | AK7: 8074.08 | AL7: 12030.696 | AM7: 12393.574 | AO7: Income from services | AP7: 3308 | AQ7: 2759 | AR7: 1978 | AS7: 3113 | AT7: 41390 | AU7: 18599
A8: Total income | B8: =B6+B7 -> 330662.09 | C8: =C6+C7 -> 306209.43 | D8: =D6+D7 -> 435051.84 | E8: =E6+E7 -> 535651.54 | F8: =F6+F7 -> 509227.33 | G8: =G6+G7 -> 503202.2 | I8: Total income | J8: =J6+J7 -> 74114.13 | K8: =K6+K7 -> 58548.46 | L8: =L6+L7 -> 94046.07 | M8: =M6+M7 -> 147203.5 | N8: =N6+N7 -> 134507.35 | O8: =O6+O7 -> 143559.06 | Q8: Other income | R8: 1681.62 | S8: 2643.73 | T8: 2438.92 | U8: 1465.91 | V8: 1916.94 | W8: 2087.85 | Y8: Total income | Z8: =Z6+Z7 -> 578763.32 | AA8: =AA6+AA7 -> 523736.38 | AB8: =AB6+AB7 -> 739813.06 | AC8: =AC6+AC7 -> 955608.86 | AD8: =AD6+AD7 -> 885074.01 | AE8: =AE6+AE7 -> 862876.46 | AG8: Total income | AH8: =AH6+AH7 -> 434038.1 | AI8: =AI6+AI7 -> 369895.33 | AJ8: =AJ6+AJ7 -> 539230.25 | AK8: =AK6+AK7 -> 692903.3 | AL8: =AL6+AL7 -> 665201.46 | AM8: =AM6+AM7 -> 675655.88 | AO8: Less: GST | AP8: 14322 | AQ8: 13871 | AR8: 21050 | AS8: 23556 | AT8: 27014 | AU8: 24371
A9: EXPENSES | I9: EXPENSES | Q9: Total income | R9: =SUM(R6:R8) -> 289423.67 | S9: =SUM(S6:S8) -> 273221.69 | T9: =SUM(T6:T8) -> 376565.91 | U9: =SUM(U6:U8) -> 467964.52 | V9: =SUM(V6:V8) -> 463886.08 | W9: =SUM(W6:W8) -> 468811.53 | Y9: EXPENSES | AG9: EXPENSES | AO9: Other income | AP9: 13566 | AQ9: 14818 | AR9: 13843 | AS9: 11229 | AT9: 12128 | AU9: 16094
A10: Cost of materials consumed | B10: 113229.3 | C10: 71153.56 | D10: 163541.19 | E10: 234305.39 | F10: 212853 | G10: 225319.41 | I10: Cost of materials consumed | J10: 4411.97 | K10: 3905.88 | L10: 11103.28 | M10: 6860.15 | N10: 7325.46 | O10: 7273.36 | Q10: EXPENSES | Y10: Cost of material consumed | Z10: 281080.13 | AA10: 174196.22 | AB10: 330672.38 | AC10: 503757.28 | AD10: 446484.44 | AE10: 449812.63 | AG10: Purchase of stock in trade | AH10: 176006.43 | AI10: 144561.83 | AJ10: 225616.93 | AK10: 266120.04 | AL10: 234072.28 | AM10: 221401.89 | AO10: Total income | AP10: =AP6+AP7-AP8+AP9 -> 365421 | AQ10: =AQ6+AQ7-AQ8+AQ9 -> 279887 | AR10: =AR6+AR7-AR8+AR9 -> 457838 | AS10: =AS6+AS7-AS8+AS9 -> 553020 | AT10: =AT6+AT7-AT8+AT9 -> 560070 | AU10: =AU6+AU7-AU8+AU9 -> 548886
A11: Purchase of stock in trade | B11: 143164.25 | C11: 127800.87 | D11: 143901.7 | E11: 199884.14 | F11: 165232.84 | G11: 159646.45 | I11: Purchase of stock in trade | J11: 52878.13 | K11: 39379.13 | L11: 59266.68 | M11: 123964.11 | N11: 100670.08 | O11: 108757.13 | Q11: Cost of material consumed | R11: 59906.49 | S11: 41212.33 | T11: 68790.6 | U11: 123336.11 | V11: 126965.71 | W11: 146337.31 | Y11: Excise duty | Z11: 92226.67 | AA11: 156287.17 | AB11: 147395.1 | AC11: 109654.03 | AD11: 104883.6 | AE11: 101256.92 | AG11: Changes in inventories of finished goods | AH11: 1145.563 | AI11: -9916.659 | AJ11: -2303.069 | AK11: 2566.082 | AL11: -4394.95 | AM11: 689.546 | AO11: EXPENSES
A12: Changes in inventories of finished goods | B12: -456.62 | C12: -3633.57 | D12: -3988.8 | E12: -975.21 | F12: -1989.84 | G12: 331.05 | I12: Changes in inventories of finished goods | J12: -427.99 | K12: 440.2 | L12: -262.78 | M12: -1992.39 | N12: -41.02 | O12: -292.27 | Q12: Purchase of stock in trade | R12: 187234.13 | S12: 167861.2 | T12: 253966.25 | U12: 302443.32 | V12: 263318.4 | W12: 247545.55 | Y12: Purchase of stock in trade | Z12: 139463.72 | AA12: 107444.28 | AB12: 169991.5 | AC12: 250207.42 | AD12: 191018.86 | AE12: 207762.62 | AG12: Production, transportation, selling and distribution | AH12: 183947.98 | AI12: 168147.84 | AJ12: 221903.57 | AK12: 326689.01 | AL12: 311897.84 | AM12: 339329.62 | AO12: Cost of material consumed | AP12: 237342 | AQ12: 168262 | AR12: 320852 | AS12: 391508 | AT12: 376418 | AU12: 384021
A13: Excise duty expense | B13: 43197.83 | C13: 69319.86 | D13: 85778.54 | E13: 60342.88 | F13: 58909.57 | G13: 60245.62 | I13: Employee benefit expenses | J13: 1592.32 | K13: 1645.89 | L13: 1815.55 | M13: 1902.39 | N13: 2273.69 | O13: 2236.46 | Q13: Changes in inventories of finished goods | R13: -354.51 | S13: -8518.53 | T13: -625.88 | U13: 1429.83 | V13: -2732.49 | W13: 1016 | Y13: Changes in inventories of finished goods | Z13: -5414.35 | AA13: -6181.61 | AB13: -13710.98 | AC13: -6329.71 | AD13: 1290.52 | AE13: -789.75 | AG13: Survey costs | AH13: 1901.534 | AI13: 1967.724 | AJ13: 1988.529 | AK13: 3979.431 | AL13: 1942.949 | AM13: 2391.36 | AO13: Purchase of stock in trade | AP13: 7292 | AQ13: 7301 | AR13: 10691 | AS13: 9974 | AT13: 13453 | AU13: 15864
A14: Employee benefit expenses | B14: 3691.45 | C14: 4477.17 | D14: 3397.92 | E14: 2763.97 | F14: 3577.17 | G14: 3509.53 | I14: Finance costs | J14: 308.94 | K14: 179.27 | L14: 202.48 | M14: 366.58 | N14: 719.2 | O14: 747.99 | Q14: Excise duty | R14: 18650.52 | S14: 37329.51 | T14: 24213.81 | U14: 25789.36 | V14: 28112.63 | W14: 32617.51 | Y14: Employee benefit expenses | Z14: 9336.93 | AA14: 11308.78 | AB14: 11582.92 | AC14: 9359.14 | AD14: 11670.94 | AE14: 10879.86 | AG14: Exploration well costs | AH14: 7121.877 | AI14: 5167.817 | AJ14: 3904.613 | AK14: 6201.54 | AL14: 3867.626 | AM14: 7605.434 | AO14: Changes in inventories of finished goods | AP14: 77 | AQ14: 610 | AR14: -7962 | AS14: -6487 | AT14: 2700 | AU14: -10679
A15: Finance costs | B15: 2181.86 | C15: 1328.36 | D15: 2208.81 | E15: 3216.48 | F15: 4148.89 | G15: 3591.44 | I15: Depreciation and amortisation expense | J15: 2080.16 | K15: 2173.82 | L15: 2420.17 | M15: 2701.57 | N15: 3672 | O15: 3799.23 | Q15: Employee benefit expenses | R15: 3224.06 | S15: 3219.42 | T15: 3017.35 | U15: 3000.67 | V15: 3469.74 | W15: 3381.23 | Y15: Finance costs | Z15: 6578.74 | AA15: 3589.12 | AB15: 5423.26 | AC15: 7541.36 | AD15: 7825.65 | AE15: 9261.93 | AG15: Finance costs | AH15: 7489.339 | AI15: 5079.031 | AJ15: 5696.043 | AK15: 7889.356 | AL15: 13025.698 | AM15: 14534.947 | AO15: Excise duty | AP15: 14902 | AQ15: 19402 | AR15: 21672 | AS15: 13476 | AT15: 13408 | AU15: 15443
A16: Depreciation and amortisation expense | B16: 3786.89 | C16: 3978.05 | D16: 5417.9 | E16: 6347.48 | F16: 6771.26 | G16: 7256.69 | I16: Excise duty | J16: 59.28 | K16: 56.35 | L16: 103.99 | M16: 206.73 | N16: 271.08 | O16: 387.93 | Q16: Finance costs | R16: 1138.85 | S16: 963.28 | T16: 997.32 | U16: 2174.11 | V16: 2556 | W16: 3365.48 | Y16: Depreciation, amortisation and impairment | AG16: Depreciation, depletion, amortisation and impairment | AH16: 26634.881 | AI16: 25538.471 | AJ16: 26883.164 | AK16: 24557.055 | AL16: 30440.1 | AM16: 35205.965 | AO16: Employee benefit expenses | AP16: 6067 | AQ16: 5024 | AR16: 5419 | AS16: 5691 | AT16: 7807 | AU16: 8690
A17: Other expenses | B17: 18115.26 | C17: 15616.46 | D17: 20765.91 | E17: 26189.75 | F17: 24327.68 | G17: 26064.04 | I17: Other expenses | J17: 5028.98 | K17: 4757.05 | L17: 5695.52 | M17: 7446.58 | N17: 8703.93 | O17: 8496.99 | Q17: Depreciation and amortisation | R17: 3369.87 | S17: 3625.47 | T17: 4000.36 | U17: 4560.15 | V17: 5596.43 | W17: 6154.1 | Y17: PPE | Z17: 9586.7 | AA17: 10643.34 | AB17: 11986.15 | AC17: 12888.89 | AD17: 15603.44 | AE17: 16448.15 | AG17: Other impairment and write offs | AH17: 2732.717 | AI17: 1177.763 | AJ17: 808.38 | AK17: 3746.146 | AL17: 3401.989 | AM17: 2983.738 | AO17: Finance costs | AP17: 12105 | AQ17: 16211 | AR17: 9123 | AS17: 12626 | AT17: 13430 | AU17: 10054
A18: Total expenses | B18: =SUM(B10:B17) -> 326910.22 | C18: =SUM(C10:C17) -> 290040.76 | D18: =SUM(D10:D17) -> 421023.17 | E18: =SUM(E10:E17) -> 532074.88 | F18: =SUM(F10:F17) -> 473830.57 | G18: =SUM(G10:G17) -> 485964.23 | I18: Total expenses | J18: =SUM(J10:J17) -> 65931.79 | K18: =SUM(K10:K17) -> 52537.59 | L18: =SUM(L10:L17) -> 80344.89 | M18: =SUM(M10:M17) -> 141455.72 | N18: =SUM(N10:N17) -> 123594.42 | O18: =SUM(O10:O17) -> 131406.82 | Q18: Other expenses | R18: 13418.87 | S18: 13470.67 | T18: 14520.53 | U18: 17706.4 | V18: 17907.37 | W18: 19274.88 | Y18: Intangible assets | Z18: 686.69 | AA18: 298.11 | AB18: 361.43 | AC18: 292.16 | AD18: 262.67 | AE18: 329.19 | AG18: Total expenses | AH18: =SUM(AH10:AH17) -> 406980.32 | AI18: =SUM(AI10:AI17) -> 341723.81 | AJ18: =SUM(AJ10:AJ17) -> 484498.16 | AK18: =SUM(AK10:AK17) -> 641748.66 | AL18: =SUM(AL10:AL17) -> 594253.53 | AM18: =SUM(AM10:AM17) -> 624142.51 | AO18: Depreciation, amortisation and depletion | AP18: 9728 | AQ18: 9199 | AR18: 10264 | AS18: 10118 | AT18: 17690 | AU18: 17981
A19: Profit before exceptional items and tax | B19: =B8-B18 -> 3751.87 | C19: =C8-C18 -> 16168.67 | D19: =D8-D18 -> 14028.67 | E19: =E8-E18 -> 3576.66 | F19: =F8-F18 -> 35396.76 | G19: =G8-G18 -> 17237.97 | I19: Profit/loss before share of profit/loss of associate and JV | J19: =J8-J18 -> 8182.34 | K19: =K8-K18 -> 6010.87 | L19: =L8-L18 -> 13701.18 | M19: =M8-M18 -> 5747.78 | N19: =N8-N18 -> 10912.93 | O19: =O8-O18 -> 12152.24 | Q19: Total expenses | R19: =SUM(R11:R18) -> 286588.28 | S19: =SUM(S11:S18) -> 259163.35 | T19: =SUM(T11:T18) -> 368880.34 | U19: =SUM(U11:U18) -> 480439.95 | V19: =SUM(V11:V18) -> 445193.79 | W19: =SUM(W11:W18) -> 459692.06 | Y19: Impairment loss on financial assets | Z19: -613.94 | AA19: 1111.98 | AB19: -444.98 | AC19: 375.49 | AD19: 270.57 | AE19: 173.27 | AG19: Profit before exceptional items and tax | AH19: =AH8-AH18 -> 27057.779 | AI19: =AI8-AI18 -> 28171.517 | AJ19: =AJ8-AJ18 -> 54732.086 | AK19: =AK8-AK18 -> 51154.643 | AL19: =AL8-AL18 -> 70947.928 | AM19: =AM8-AM18 -> 51513.376 | AO19: Other expenses | AP19: 33347 | AQ19: 30970 | AR19: 42383 | AS19: 61981 | AT19: 59891 | AU19: 61384
A20: Exceptional items | B20: 1080.83 | C20: -6448.91 | D20: -1643.07 | E20: 1359.96 | F20: =1065.53-267.7 -> 797.83 | G20: =1322.74-378.41 -> 944.33 | I20: Share of profit/loss | J20: 2246.6 | K20: 1714.58 | L20: 1762.34 | M20: 1508.06 | N20: =1682.08+0 -> 1682.08 | O20: =1503.24+2440.03 -> 3943.27 | Q20: Profit/loss before share in profit of joint ventures | R20: =R9-R19 -> 2835.39 | S20: =S9-S19 -> 14058.34 | T20: =T9-T19 -> 7685.57 | U20: =U9-U19 -> -12475.43 | V20: =V9-V19 -> 18692.29 | W20: =W9-W19 -> 9119.47 | Y20: Net loss on de recognition of financial assets at amortised cost | Z20: 5.73 | AA20: 7.69 | AB20: 172.75 | AC20: 307.84 | AD20: 3.9 | AE20: 46.7 | AG20: Exceptional items | AH20: -9028.479 | AI20: 918.768 | AJ20: -2104.911 | AK20: -8137.942 | AL20: -1636.431 | AM20: -151.086 | AO20: Total expenses | AP20: =SUM(AP12:AP19) -> 320860 | AQ20: =SUM(AQ12:AQ19) -> 256979 | AR20: =SUM(AR12:AR19) -> 412442 | AS20: =SUM(AS12:AS19) -> 498887 | AT20: =SUM(AT12:AT19) -> 504797 | AU20: =SUM(AU12:AU19) -> 502758
A21: Profit before tax | B21: =B19-B20 -> 2671.04 | C21: =C19-C20 -> 22617.58 | D21: =D19-D20 -> 15671.74 | E21: =E19-E20 -> 2216.7 | F21: =F19-F20 -> 34598.93 | G21: =G19-G20 -> 16293.64 | I21: Profit/loss before tax | J21: =J19+J20 -> 10428.94 | K21: =K19+K20 -> 7725.45 | L21: =L19+L20 -> 15463.52 | M21: =M19+M20 -> 7255.84 | N21: =N19+N20 -> 12595.01 | O21: =O19+O20 -> 16095.51 | Q21: Share in profit/loss | R21: -458.17 | S21: 138.66 | T21: 1458.05 | U21: 2491.51 | V21: 1807.98 | W21: -119.59 | Y21: Other expenses | Z21: 43064.76 | AA21: 35477.3 | AB21: 43330.47 | AC21: 53379.46 | AD21: 50017.56 | AE21: 54229.94 | AG21: Share of profit of associates | AH21: 2355.957 | AI21: 1174.834 | AJ21: 809.519 | AK21: -319.234 | AL21: 3003.848 | AM21: 1081.166 | AO21: Profit before exceptional items and tax | AP21: =AP10-AP20 -> 44561 | AQ21: =AQ10-AQ20 -> 22908 | AR21: =AR10-AR20 -> 45396 | AS21: =AS10-AS20 -> 54133 | AT21: =AT10-AT20 -> 55273 | AU21: =AU10-AU20 -> 46128
A22: Tax expense | I22: Tax expense | Q22: Profit/loss before exceptional items and tax | R22: =R20+R21 -> 2377.22 | S22: =S20+S21 -> 14197 | T22: =T20+T21 -> 9143.62 | U22: =U20+U21 -> -9983.92 | V22: =V20+V21 -> 20500.27 | W22: =W20+W21 -> 8999.88 | Y22: Total expenses | Z22: =SUM(Z10:Z15,Z17:Z21) -> 576001.78 | AA22: =SUM(AA10:AA15,AA17:AA21) -> 494182.38 | AB22: =SUM(AB10:AB15,AB17:AB21) -> 706760 | AC22: =SUM(AC10:AC15,AC17:AC21) -> 941433.36 | AD22: =SUM(AD10:AD15,AD17:AD21) -> 829332.15 | AE22: =SUM(AE10:AE15,AE17:AE21) -> 849411.46 | AG22: Share of profit of Joint ventures | AH22: -1422.812 | AI22: -155.472 | AJ22: 654.408 | AK22: 353.285 | AL22: 1313.87 | AM22: -45.575 | AO22: Exceptional items | AP22: -4245 | AQ22: 4304 | AR22: 0 | AS22: 0 | AT22: 0 | AU22: 0
A23: Current tax | B23: 201 | C23: 5134.78 | D23: 2706.34 | E23: 352.18 | F23: 9419.98 | G23: 4470.93 | I23: Current tax | J23: 2116.2 | K23: 1591.88 | L23: 3333.25 | M23: 1355.89 | N23: 2683.02 | O23: 3464.8 | Q23: Exceptional items | R23: -1002.93 | S23: 0 | T23: 0 | U23: 0 | V23: 0 | W23: 0 | Y23: Profit/loss before share of profit | Z23: =Z8-Z22 -> 2761.54 | AA23: =AA8-AA22 -> 29554 | AB23: =AB8-AB22 -> 33053.06 | AC23: =AC8-AC22 -> 14175.5 | AD23: =AD8-AD22 -> 55741.86 | AE23: =AE8-AE22 -> 13465 | AG23: Profit before tax | AH23: =SUM(AH19:AH22) -> 18962.445 | AI23: =SUM(AI19:AI22) -> 30109.647 | AJ23: =SUM(AJ19:AJ22) -> 54091.102 | AK23: =SUM(AK19:AK22) -> 43050.752 | AL23: =SUM(AL19:AL22) -> 73629.215 | AM23: =SUM(AM19:AM22) -> 52397.881 | AO23: Profit before tax | AP23: =AP21+AP22 -> 40316 | AQ23: =AQ21+AQ22 -> 27212 | AR23: =AR21+AR22 -> 45396 | AS23: =AS21+AS22 -> 54133 | AT23: =AT21+AT22 -> 55273 | AU23: =AU21+AU22 -> 46128
A24: Deferred tax | B24: 400.68 | C24: -402.98 | D24: 643.99 | E24: 37.32 | F24: -84.39 | G24: 374.85 | I24: Earlier year | J24: 900.17 | K24: 6.32 | L24: -77.24 | M24: -52.01 | N24: -2.39 | O24: -4.53 | Q24: Profit/loss before tax | R24: =R22-R23 -> 3380.15 | S24: =S22-S23 -> 14197 | T24: =T22-T23 -> 9143.62 | U24: =U22-U23 -> -9983.92 | V24: =V22-V23 -> 20500.27 | W24: =W22-W23 -> 8999.88 | Y24: Share of profit/loss | Z24: 1366.09 | AA24: 1196.73 | AB24: 1235.56 | AC24: 862.19 | AD24: 1545.93 | AE24: 1760.43 | AG24: Tax expense | AO24: Tax expenses
A25: Tax provision for earlier years | B25: -613.83 | C25: -1155.89 | D25: 958.06 | E25: -42.9 | F25: 0.01 | G25: -0.03 | I25: Deferred tax | J25: -2102.07 | K25: -15.57 | L25: -96.12 | M25: 356.61 | N25: 11.57 | O25: 172.37 | Q25: Tax expense | Y25: Profit/loss before exceptional items and tax | Z25: =Z23+Z24 -> 4127.63 | AA25: =AA23+AA24 -> 30750.73 | AB25: =AB23+AB24 -> 34288.62 | AC25: =AC23+AC24 -> 15037.69 | AD25: =AD23+AD24 -> 57287.79 | AE25: =AE23+AE24 -> 15225.43 | AG25: Current tax | AH25: 9647.58 | AI25: 8081.523 | AJ25: 14017.279 | AK25: 14620.93 | AL25: 15230.188 | AM25: 15364.331 | AO25: Current tax | AP25: 7200 | AQ25: 0 | AR25: 544 | AS25: 6186 | AT25: 10922 | AU25: 9399
A26: Total tax expense | B26: =SUM(B23:B25) -> -12.15 | C26: =SUM(C23:C25) -> 3575.91 | D26: =SUM(D23:D25) -> 4308.39 | E26: =SUM(E23:E25) -> 346.6 | F26: =SUM(F23:F25) -> 9335.6 | G26: =SUM(G23:G25) -> 4845.75 | I26: Total tax expenses | J26: =J23+J24+J25 -> 914.3 | K26: =K23+K24+K25 -> 1582.63 | L26: =L23+L24+L25 -> 3159.89 | M26: =M23+M24+M25 -> 1660.49 | N26: =N23+N24+N25 -> 2692.2 | O26: =O23+O24+O25 -> 3632.64 | Q26: Current tax | R26: 166.95 | S26: 3569.56 | T26: 1510 | U26: 0 | V26: 814.36 | W26: 1770.92 | Y26: Exceptional items | Z26: -11304.64 | AA26: 0 | AB26: 0 | AC26: 0 | AD26: 0 | AE26: 1838.02 | AG26: Earlier year | AH26: -1805.422 | AI26: 982.03 | AJ26: -665.255 | AK26: -2891.432 | AL26: -391.723 | AM26: -124.899 | AO26: Deferred tax | AP26: 2213 | AQ26: -4732 | AR26: 6915 | AS26: 4930 | AT26: 2309 | AU26: 1467
A27: Profit for the period | B27: =B21-B26 -> 2683.19 | C27: =C21-C26 -> 19041.67 | D27: =D21-D26 -> 11363.35 | E27: =E21-E26 -> 1870.1 | F27: =F21-F26 -> 25263.33 | G27: =G21-G26 -> 11447.89 | I27: Profit for the year | J27: =J21-J26 -> 9514.64 | K27: =K21-K26 -> 6142.82 | L27: =L21-L26 -> 12303.63 | M27: =M21-M26 -> 5595.35 | N27: =N21-N26 -> 9902.81 | O27: =O21-O26 -> 12462.87 | Q27: Deferred tax | R27: 116.73 | S27: -52.08 | T27: 526.41 | U27: -2957.58 | V27: 3936.66 | W27: 597.42 | Y27: Profit/loss before tax | Z27: =Z25+Z26 -> -7177.01 | AA27: =AA25+AA26 -> 30750.73 | AB27: =AB25+AB26 -> 34288.62 | AC27: =AC25+AC26 -> 15037.69 | AD27: =AD25+AD26 -> 57287.79 | AE27: =AE25+AE26 -> 17063.45 | AG27: Deferred tax | AH27: -335.972 | AI27: -297.352 | AJ27: -8554.979 | AK27: -1456.351 | AL27: 3517.601 | AM27: -1170.161 | AO27: Total tax expense | AP27: =AP25+AP26 -> 9413 | AQ27: =AQ25+AQ26 -> -4732 | AR27: =AR25+AR26 -> 7459 | AS27: =AS25+AS26 -> 11116 | AT27: =AT25+AT26 -> 13231 | AU27: =AU25+AU26 -> 10866
Q28: Provision for earlier years | R28: -1548.12 | S28: 16.63 | T28: -187.02 | U28: -46.11 | V28: -265.36 | W28: -104.16 | Y28: Tax expense | AG28: Total tax expenses | AH28: =AH25+AH26+AH27 -> 7506.186 | AI28: =AI25+AI26+AI27 -> 8766.201 | AJ28: =AJ25+AJ26+AJ27 -> 4797.045 | AK28: =AK25+AK26+AK27 -> 10273.147 | AL28: =AL25+AL26+AL27 -> 18356.066 | AM28: =AM25+AM26+AM27 -> 14069.271 | AO28: Profit for the year | AP28: =AP23-AP27 -> 30903 | AQ28: =AQ23-AQ27 -> 31944 | AR28: =AR23-AR27 -> 37937 | AS28: =AS23-AS27 -> 43017 | AT28: =AT23-AT27 -> 42042 | AU28: =AU23-AU27 -> 35262
Q29: Total tax expenses | R29: =SUM(R26:R28) -> -1264.44 | S29: =SUM(S26:S28) -> 3534.11 | T29: =SUM(T26:T28) -> 1849.39 | U29: =SUM(U26:U28) -> -3003.69 | V29: =SUM(V26:V28) -> 4485.66 | W29: =SUM(W26:W28) -> 2264.18 | Y29: Current tax | Z29: 221.23 | AA29: 6868.47 | AB29: 7234.66 | AC29: 1922.46 | AD29: 12895.91 | AE29: 1700.08 | AG29: Profit for the year | AH29: =AH23-AH28 -> 11456.259 | AI29: =AI23-AI28 -> 21343.446 | AJ29: =AJ23-AJ28 -> 49294.057 | AK29: =AK23-AK28 -> 32777.605 | AL29: =AL23-AL28 -> 55273.149 | AM29: =AM23-AM28 -> 38328.61
Q30: Profit/Loss for the year | R30: =R24+R29 -> 2115.71 | S30: =S24-S29 -> 10662.89 | T30: =T24+T29 -> 10993.01 | U30: =U24-U29 -> -6980.23 | V30: =V24-V29 -> 16014.61 | W30: =W24-W29 -> 6735.7 | Y30: Deferred tax | Z30: -5521.92 | AA30: 2120.04 | AB30: 1327.36 | AC30: 1410.97 | AD30: 1230.73 | AE30: 1574.54
Y31: Total tax expense | Z31: =Z29+Z30 -> -5300.69 | AA31: =AA29+AA30 -> 8988.51 | AB31: =AB29+AB30 -> 8562.02 | AC31: =AC29+AC30 -> 3333.43 | AD31: =AD29+AD30 -> 14126.64 | AE31: =AE29+AE30 -> 3274.62
Y32: Profit/loss for the year | Z32: =Z27-Z31 -> -1876.32 | AA32: =AA27-AA31 -> 21762.22 | AB32: =AB27-AB31 -> 25726.6 | AC32: =AC27-AC31 -> 11704.26 | AD32: =AD27-AD31 -> 43161.15 | AE32: =AE27-AE31 -> 13788.83

Sheet Cash Flow Statement
A1: CASH FLOW STATEMENT
A3: #VALUE! | I3: #VALUE! | Q3: #VALUE! | Y3: #VALUE! | AG3: #VALUE! | AO3: #VALUE!
A4: Particulars | B4: 2020 | C4: 2021 | D4: 2022 | E4: 2023 | F4: 2024 | G4: 2025 | I4: Particulars | J4: 2020 | K4: 2021 | L4: 2022 | M4: 2023 | N4: 2024 | O4: 2025 | Q4: Particulars | R4: 2020 | S4: 2021 | T4: 2022 | U4: 2023 | V4: 2024 | W4: 2025 | Y4: Particulars | Z4: 2020 | AA4: 2021 | AB4: 2022 | AC4: 2023 | AD4: 2024 | AE4: 2025 | AG4: Particulars | AH4: 2020 | AI4: 2021 | AJ4: 2022 | AK4: 2023 | AL4: 2024 | AM4: 2025 | AO4: Particulars | AP4: 2020 | AQ4: 2021 | AR4: 2022 | AS4: 2023 | AT4: 2024 | AU4: 2025
A5: Net cash from/used in Operating Activities | B5: 6357.75 | C5: 20029.76 | D5: 20049.25 | E5: 10664.05 | F5: 35969.63 | G5: 23677.79 | I5: Net cash from/used in Operating Activities | J5: 8345.36 | K5: 8993.4 | L5: 9419.91 | M5: 3204.69 | N5: 12585.72 | O5: 15735.04 | Q5: Net cash from/used in Operating Activities | R5: 5469.24 | S5: 17829.26 | T5: 15810.23 | U5: -3466.31 | V5: 23851.87 | W5: 14227.74 | Y5: Net cash from/used in Operating Activities | Z5: 7146.25 | AA5: 49861.73 | AB5: 25746.67 | AC5: 29643.72 | AD5: 71146.41 | AE5: 34699.28 | AG5: Net cash from/used in Operating Activities | AH5: 70592.978 | AI5: 47201.393 | AJ5: 78248.246 | AK5: 84211.334 | AL5: 98846.605 | AM5: 90868.191 | AO5: Net cash from/used in Operating Activities | AP5: 77533 | AQ5: -512 | AR5: 67491 | AS5: 48050 | AT5: 73998 | AU5: 79392
A6: Capex | B6: -9460.25 | C6: -6063.48 | D6: -5355.16 | E6: -7376.83 | F6: -8838.62 | G6: -13342.56 | I6: Capex | J6: -9262.94 | K6: -5697.21 | L6: -6971.28 | M6: -8830.56 | N6: -12501.17 | O6: -7929.71 | Q6: Capex | R6: -13856.51 | S6: -11666 | T6: -12344.76 | U6: -9446.71 | V6: -10071.24 | W6: -9579.33 | Y6: Capex | Z6: -12337.43 | AA6: -6566.16 | AB6: -4944.71 | AC6: -5609.49 | AD6: -5005.85 | AE6: -5105.48 | AG6: Capex | AH6: -42258.429 | AI6: -32335.248 | AJ6: -33457.291 | AK6: -36792.453 | AL6: -38132.841 | AM6: -41030.802 | AO6: Capex | AP6: -21183 | AQ6: -21755 | AR6: -18154 | AS6: -28573 | AT6: -34258 | AU6: -37304
A7: Net cash from/used in Investing activities | B7: -9263.97 | C7: 2170.08 | D7: -7167.07 | E7: -6397.31 | F7: -10554.31 | G7: -19179.99 | I7: Net cash from/used in Investing activities | J7: -7444.64 | K7: -4693.04 | L7: -5436.04 | M7: -7640.12 | N7: -8273.42 | O7: -6737.79 | Q7: Net cash from/used in Investing activities | R7: -14167.89 | S7: -12278.59 | T7: -13744.84 | U7: -11383.55 | V7: -13019.23 | W7: -10556.61 | Y7: Net cash from/used in Investing activities | Z7: -29100.76 | AA7: -24244.89 | AB7: -21293.57 | AC7: -28029.56 | AD7: -31511.53 | AE7: -31848.19 | AG7: Net cash from/used in Investing activities | AH7: -53498.314 | AI7: -39089.771 | AJ7: -41329.623 | AK7: -73208.997 | AL7: -57485.019 | AM7: -43021.689 | AO7: Net cash from/used in Investing activities | AP7: -143625 | AQ7: 74257 | AR7: -45315 | AS7: -584 | AT7: -38292 | AU7: -28106
A8: Dividends Paid | B8: -4818.86 | C8: -4261.3 | D8: -14482.78 | E8: -1281.57 | F8: -5328.8 | G8: -6560.92 | I8: Dividends Paid | J8: -3960.56 | K8: -2238.06 | L8: -3995.37 | M8: -3069.25 | N8: -3620.53 | O8: -4275.44 | Q8: Dividends Paid | R8: -1725.11 | S8: -1484.41 | T8: -3222.89 | U8: -1985.71 | V8: -2130.51 | W8: -2336.26 | Y8: Dividends Paid | Z8: -5803.18 | AA8: -8383.19 | AB8: -10896.04 | AC8: -3305.68 | AD8: -10972.58 | AE8: -9545.1 | AG8: Dividends Paid | AH8: -8297.242 | AI8: -3096.294 | AJ8: -12923.827 | AK8: -17608.965 | AL8: -12894.901 | AM8: -16984.736 | AO8: Dividends Paid | AP8: -4584 | AQ8: -3921 | AR8: -4297 | AS8: -5083 | AT8: -6089 | AU8: -6766
A9: Net cash from/used in Financing activities | B9: 2940.22 | C9: -15622.27 | D9: -18697.08 | E9: -3665.87 | F9: -25247.3 | G9: -6240.61 | I9: Net cash from/used in Financing activities | J9: 281.22 | K9: -3470.62 | L9: -3916.71 | M9: 2972.06 | N9: -3457.39 | O9: -8940.85 | Q9: Net cash from/used in Financing activities | R9: 8451.96 | S9: -4709.19 | T9: -2066.24 | U9: 16025.17 | V9: -16155.04 | W9: -4138.24 | Y9: Net cash from/used in Financing activities | Z9: 22456.03 | AA9: -26270.21 | AB9: -4057.7 | AC9: -1794.4 | AD9: -39384.64 | AE9: -3424.51 | AG9: Net cash from/used in Financing activities | AH9: -16726.364 | AI9: -8257.811 | AJ9: -35790.015 | AK9: -12916.346 | AL9: -45009.25 | AM9: -47907.547 | AO9: Net cash from/used in Financing activities | AP9: 70767 | AQ9: -76657 | AR9: -6035 | AS9: -7369 | AT9: -27465 | AU9: -38063
A10: Net change in cash and cash equivalents | B10: 34 | C10: 6577.27 | D10: -5814.9 | E10: 600.87 | F10: -11.98 | G10: -1742.81 | I10: Net change in cash and cash equivalents | J10: 1181.94 | K10: 829.74 | L10: 67.16 | M10: -1463.37 | N10: 854.91 | O10: 56.4 | Q10: Net change in cash and cash equivalents | R10: -246.69 | S10: 841.48 | T10: -0.85 | U10: 1175.31 | V10: -5322.4 | W10: -467.11 | Y10: Net change in cash and cash equivalents | Z10: 501.52 | AA10: -653.37 | AB10: 395.4 | AC10: -180.24 | AD10: 250.24 | AE10: -573.42 | AG10: Net change in cash and cash equivalents | AH10: 368.3 | AI10: -146.189 | AJ10: 1128.608 | AK10: -1914.009 | AL10: -3647.664 | AM10: -61.045 | AO10: Net change in cash and cash equivalents | AP10: 4675 | AQ10: -2912 | AR10: 16141 | AS10: 40097 | AT10: 8241 | AU10: 13223

Sheet Financial Ratios
A1: FINANCIAL RATIOS
A3: #VALUE! | J3: #VALUE! | S3: #VALUE! | AB3: #VALUE! | AK3: #VALUE! | AT3: #VALUE!
A4: Category | B4: Ratio | C4: 2020 | D4: 2021 | E4: 2022 | F4: 2023 | G4: 2024 | H4: 2025 | J4: Category | K4: Ratio | L4: 2020 | M4: 2021 | N4: 2022 | O4: 2023 | P4: 2024 | Q4: 2025 | S4: Category | T4: Ratio | U4: 2020 | V4: 2021 | W4: 2022 | X4: 2023 | Y4: 2024 | Z4: 2025 | AB4: Category | AC4: Ratio | AD4: 2020 | AE4: 2021 | AF4: 2022 | AG4: 2023 | AH4: 2024 | AI4: 2025 | AK4: Category | AL4: Ratio | AM4: 2020 | AN4: 2021 | AO4: 2022 | AP4: 2023 | AQ4: 2024 | AR4: 2025 | AT4: Category | AU4: Ratio | AV4: 2020 | AW4: 2021 | AX4: 2022 | AY4: 2023 | AZ4: 2024 | BA4: 2025
A5: Liquidity | B5: Current Ratio | C5: ='Balance Sheet'!B31/'Balance Sheet'!B56 -> 0.70229318 | D5: ='Balance Sheet'!C31/'Balance Sheet'!C56 -> 0.90244502 | E5: ='Balance Sheet'!D31/'Balance Sheet'!D56 -> 0.74636454 | F5: ='Balance Sheet'!E31/'Balance Sheet'!E56 -> 0.74851615 | G5: ='Balance Sheet'!F31/'Balance Sheet'!F56 -> 0.81220777 | H5: ='Balance Sheet'!G31/'Balance Sheet'!G56 -> 0.80324929 | J5: Liquidity | K5: Current Ratio | L5: ='Balance Sheet'!J28/'Balance Sheet'!J56 -> 0.93433391 | M5: ='Balance Sheet'!K28/'Balance Sheet'!K56 -> 0.86575401 | N5: ='Balance Sheet'!L28/'Balance Sheet'!L56 -> 1.080421 | O5: ='Balance Sheet'!M28/'Balance Sheet'!M56 -> 0.94563452 | P5: ='Balance Sheet'!N28/'Balance Sheet'!N56 -> 0.93675158 | Q5: ='Balance Sheet'!O28/'Balance Sheet'!O56 -> 0.98183475 | S5: Liquidity | T5: Current Ratio | U5: ='Balance Sheet'!R26/'Balance Sheet'!R51 -> 0.65943989 | V5: ='Balance Sheet'!S26/'Balance Sheet'!S51 -> 0.70802896 | W5: ='Balance Sheet'!T26/'Balance Sheet'!T51 -> 0.69555463 | X5: ='Balance Sheet'!U26/'Balance Sheet'!U51 -> 0.59534949 | Y5: ='Balance Sheet'!V26/'Balance Sheet'!V51 -> 0.61198478 | Z5: ='Balance Sheet'!W26/'Balance Sheet'!W51 -> 0.59935819 | AB5: Liquidity | AC5: Current Ratio | AD5: ='Balance Sheet'!Z30/'Balance Sheet'!Z56 -> 0.68559163 | AE5: ='Balance Sheet'!AA30/'Balance Sheet'!AA56 -> 0.71656401 | AF5: ='Balance Sheet'!AB30/'Balance Sheet'!AB56 -> 0.76156931 | AG5: ='Balance Sheet'!AC30/'Balance Sheet'!AC56 -> 0.76877614 | AH5: ='Balance Sheet'!AD30/'Balance Sheet'!AD56 -> 0.73222498 | AI5: ='Balance Sheet'!AE30/'Balance Sheet'!AE56 -> 0.68362333 | AK5: Liquidity | AL5: Current Ratio | AM5: ='Balance Sheet'!AH46/'Balance Sheet'!AH73 -> 0.60272676 | AN5: ='Balance Sheet'!AI46/'Balance Sheet'!AI73 -> 0.71201698 | AO5: ='Balance Sheet'!AJ46/'Balance Sheet'!AJ73 -> 0.78999688 | AP5: ='Balance Sheet'!AK46/'Balance Sheet'!AK73 -> 0.82393199 | AQ5: ='Balance Sheet'!AL46/'Balance Sheet'!AL73 -> 0.79623587 | AR5: ='Balance Sheet'!AM46/'Balance Sheet'!AM73 -> 0.78843478 | AT5: Liquidity | AU5: Current Ratio | AV5: ='Balance Sheet'!AP23/'Balance Sheet'!AP48 -> 0.50397058 | AW5: ='Balance Sheet'!AQ23/'Balance Sheet'!AQ48 -> 1.0442645 | AX5: ='Balance Sheet'!AR23/'Balance Sheet'!AR48 -> 0.99851728 | AY5: ='Balance Sheet'!AS23/'Balance Sheet'!AS48 -> 0.88134072 | AZ5: ='Balance Sheet'!AT23/'Balance Sheet'!AT48 -> 1.094207 | BA5: ='Balance Sheet'!AU23/'Balance Sheet'!AU48 -> 1.0450811
A6: Liquidity | B6: Quick Ratio | C6: =('Balance Sheet'!B31-'Balance Sheet'!B21)/'Balance Sheet'!B56 -> 0.35303738 | D6: =('Balance Sheet'!C31-'Balance Sheet'!C21)/'Balance Sheet'!C56 -> 0.43962378 | E6: =('Balance Sheet'!D31-'Balance Sheet'!D21)/'Balance Sheet'!D56 -> 0.23860582 | F6: =('Balance Sheet'!E31-'Balance Sheet'!E21)/'Balance Sheet'!E56 -> 0.24005328 | G6: =('Balance Sheet'!F31-'Balance Sheet'!F21)/'Balance Sheet'!F56 -> 0.28260416 | H6: =('Balance Sheet'!G31-'Balance Sheet'!G21)/'Balance Sheet'!G56 -> 0.30403024 | J6: Liquidity | K6: Quick Ratio | L6: =('Balance Sheet'!J28-'Balance Sheet'!J20)/'Balance Sheet'!J56 -> 0.67920633 | M6: =('Balance Sheet'!K28-'Balance Sheet'!K20)/'Balance Sheet'!K56 -> 0.62757273 | N6: =('Balance Sheet'!L28-'Balance Sheet'!L20)/'Balance Sheet'!L56 -> 0.84345469 | O6: =('Balance Sheet'!M28-'Balance Sheet'!M20)/'Balance Sheet'!M56 -> 0.67305774 | P6: =('Balance Sheet'!N28-'Balance Sheet'!N20)/'Balance Sheet'!N56 -> 0.66088046 | Q6: =('Balance Sheet'!O28-'Balance Sheet'!O20)/'Balance Sheet'!O56 -> 0.69644389 | S6: Liquidity | T6: Quick Ratio | U6: =('Balance Sheet'!R26-'Balance Sheet'!R17)/'Balance Sheet'!R51 -> 0.32067301 | V6: =('Balance Sheet'!S26-'Balance Sheet'!S17)/'Balance Sheet'!S51 -> 0.24692367 | W6: =('Balance Sheet'!T26-'Balance Sheet'!T17)/'Balance Sheet'!T51 -> 0.1984299 | X6: =('Balance Sheet'!U26-'Balance Sheet'!U17)/'Balance Sheet'!U51 -> 0.19496171 | Y6: =('Balance Sheet'!V26-'Balance Sheet'!V17)/'Balance Sheet'!V51 -> 0.21571757 | Z6: =('Balance Sheet'!W26-'Balance Sheet'!W17)/'Balance Sheet'!W51 -> 0.20128821 | AB6: Liquidity | AC6: Quick Ratio | AD6: =('Balance Sheet'!Z30-'Balance Sheet'!Z20)/'Balance Sheet'!Z56 -> 0.27071016 | AE6: =('Balance Sheet'!AA30-'Balance Sheet'!AA20)/'Balance Sheet'!AA56 -> 0.20213505 | AF6: =('Balance Sheet'!AB30-'Balance Sheet'!AB20)/'Balance Sheet'!AB56 -> 0.18214198 | AG6: =('Balance Sheet'!AC30-'Balance Sheet'!AC20)/'Balance Sheet'!AC56 -> 0.18271671 | AH6: =('Balance Sheet'!AD30-'Balance Sheet'!AD20)/'Balance Sheet'!AD56 -> 0.17130006 | AI6: =('Balance Sheet'!AE30-'Balance Sheet'!AE20)/'Balance Sheet'!AE56 -> 0.18978651 | AK6: Liquidity | AL6: Quick Ratio | AM6: =('Balance Sheet'!AH46-'Balance Sheet'!AH36)/'Balance Sheet'!AH73 -> 0.33847057 | AN6: =('Balance Sheet'!AI46-'Balance Sheet'!AI36)/'Balance Sheet'!AI73 -> 0.35041053 | AO6: =('Balance Sheet'!AJ46-'Balance Sheet'!AJ36)/'Balance Sheet'!AJ73 -> 0.36473879 | AP6: =('Balance Sheet'!AK46-'Balance Sheet'!AK36)/'Balance Sheet'!AK73 -> 0.48947968 | AQ6: =('Balance Sheet'!AL46-'Balance Sheet'!AL36)/'Balance Sheet'!AL73 -> 0.47858851 | AR6: =('Balance Sheet'!AM46-'Balance Sheet'!AM36)/'Balance Sheet'!AM73 -> 0.43506855 | AT6: Liquidity | AU6: Quick Ratio | AV6: =('Balance Sheet'!AP23-'Balance Sheet'!AP17)/'Balance Sheet'!AP48 -> 0.38663127 | AW6: =('Balance Sheet'!AQ23-'Balance Sheet'!AQ17)/'Balance Sheet'!AQ48 -> 0.85873718 | AX6: =('Balance Sheet'!AR23-'Balance Sheet'!AR17)/'Balance Sheet'!AR48 -> 0.77002418 | AY6: =('Balance Sheet'!AS23-'Balance Sheet'!AS17)/'Balance Sheet'!AS48 -> 0.67514203 | AZ6: =('Balance Sheet'!AT23-'Balance Sheet'!AT17)/'Balance Sheet'!AT48 -> 0.73964435 | BA6: =('Balance Sheet'!AU23-'Balance Sheet'!AU17)/'Balance Sheet'!AU48 -> 0.69919553
A7: Capital Structure | B7: Debt to Equity | C7: =('Balance Sheet'!B39+'Balance Sheet'!B47)/'Balance Sheet'!B37 -> 1.3245489 | D7: =('Balance Sheet'!C39+'Balance Sheet'!C47)/'Balance Sheet'!C37 -> 0.87155523 | E7: =('Balance Sheet'!D39+'Balance Sheet'!D47)/'Balance Sheet'!D37 -> 1.0775843 | F7: =('Balance Sheet'!E39+'Balance Sheet'!E47)/'Balance Sheet'!E37 -> 1.1295206 | G7: =('Balance Sheet'!F39+'Balance Sheet'!F47)/'Balance Sheet'!F37 -> 0.60137322 | H7: =('Balance Sheet'!G39+'Balance Sheet'!G47)/'Balance Sheet'!G37 -> 0.62740661 | J7: Capital Structure | K7: Debt to Equity | L7: =('Balance Sheet'!J37+'Balance Sheet'!J46)/'Balance Sheet'!J35 -> 0.12840771 | M7: =('Balance Sheet'!K37+'Balance Sheet'!K46)/'Balance Sheet'!K35 -> 0.12688291 | N7: =('Balance Sheet'!L37+'Balance Sheet'!L46)/'Balance Sheet'!L35 -> 0.12176758 | O7: =('Balance Sheet'!M37+'Balance Sheet'!M46)/'Balance Sheet'!M35 -> 0.24997166 | P7: =('Balance Sheet'!N37+'Balance Sheet'!N46)/'Balance Sheet'!N35 -> 0.24104945 | Q7: =('Balance Sheet'!O37+'Balance Sheet'!O46)/'Balance Sheet'!O35 -> 0.19131016 | S7: Capital Structure | T7: Debt to Equity | U7: =('Balance Sheet'!R34+'Balance Sheet'!R42)/'Balance Sheet'!R32 -> 1.2713028 | V7: =('Balance Sheet'!S34+'Balance Sheet'!S42)/'Balance Sheet'!S32 -> 1.1206173 | W7: =('Balance Sheet'!T34+'Balance Sheet'!T42)/'Balance Sheet'!T32 -> 1.0863323 | X7: =('Balance Sheet'!U34+'Balance Sheet'!U42)/'Balance Sheet'!U32 -> 2.0781619 | Y7: =('Balance Sheet'!V34+'Balance Sheet'!V42)/'Balance Sheet'!V32 -> 1.3386895 | Z7: =('Balance Sheet'!W34+'Balance Sheet'!W42)/'Balance Sheet'!W32 -> 1.2988523 | AB7: Capital Structure | AC7: Debt to Equity | AD7: =('Balance Sheet'!Z40+'Balance Sheet'!Z47)/'Balance Sheet'!Z37 -> 1.3084303 | AE7: =('Balance Sheet'!AA40+'Balance Sheet'!AA47)/'Balance Sheet'!AA37 -> 0.96189231 | AF7: =('Balance Sheet'!AB40+'Balance Sheet'!AB47)/'Balance Sheet'!AB37 -> 0.91432815 | AG7: =('Balance Sheet'!AC40+'Balance Sheet'!AC47)/'Balance Sheet'!AC37 -> 0.97835747 | AH7: =('Balance Sheet'!AD40+'Balance Sheet'!AD47)/'Balance Sheet'!AD37 -> 0.65609914 | AI7: =('Balance Sheet'!AE40+'Balance Sheet'!AE47)/'Balance Sheet'!AE37 -> 0.74629056 | AK7: Capital Structure | AL7: Debt to Equity | AM7: =('Balance Sheet'!AH64+'Balance Sheet'!AH56)/'Balance Sheet'!AH53 -> 0.46725816 | AN7: =('Balance Sheet'!AI64+'Balance Sheet'!AI56)/'Balance Sheet'!AI53 -> 0.45268395 | AO7: =('Balance Sheet'!AJ64+'Balance Sheet'!AJ56)/'Balance Sheet'!AJ53 -> 0.38039257 | AP7: =('Balance Sheet'!AK64+'Balance Sheet'!AK56)/'Balance Sheet'!AK53 -> 0.42882455 | AQ7: =('Balance Sheet'!AL64+'Balance Sheet'!AL56)/'Balance Sheet'!AL53 -> 0.43847317 | AR7: =('Balance Sheet'!AM64+'Balance Sheet'!AM56)/'Balance Sheet'!AM53 -> 0.41031933 | AT7: Capital Structure | AU7: Debt to Equity | AV7: =('Balance Sheet'!AP40+'Balance Sheet'!AP32)/'Balance Sheet'!AP29 -> 0.65002876 | AW7: =('Balance Sheet'!AQ40+'Balance Sheet'!AQ32)/'Balance Sheet'!AQ29 -> 0.40833918 | AX7: =('Balance Sheet'!AR40+'Balance Sheet'!AR32)/'Balance Sheet'!AR29 -> 0.41262324 | AY7: =('Balance Sheet'!AS40+'Balance Sheet'!AS32)/'Balance Sheet'!AS29 -> 0.45048153 | AZ7: =('Balance Sheet'!AT40+'Balance Sheet'!AT32)/'Balance Sheet'!AT29 -> 0.41116607 | BA7: =('Balance Sheet'!AU40+'Balance Sheet'!AU32)/'Balance Sheet'!AU29 -> 0.36607947
A8: Capital Structure | B8: Debt to Capital | C8: =('Balance Sheet'!B39+'Balance Sheet'!B47)/('Balance Sheet'!B39+'Balance Sheet'!B47+'Balance Sheet'!B37) -> 0.569809 | D8: =('Balance Sheet'!C39+'Balance Sheet'!C47)/('Balance Sheet'!C39+'Balance Sheet'!C47+'Balance Sheet'!C37) -> 0.46568502 | E8: =('Balance Sheet'!D39+'Balance Sheet'!D47)/('Balance Sheet'!D39+'Balance Sheet'!D47+'Balance Sheet'!D37) -> 0.51867175 | F8: =('Balance Sheet'!E39+'Balance Sheet'!E47)/('Balance Sheet'!E39+'Balance Sheet'!E47+'Balance Sheet'!E37) -> 0.53041075 | G8: =('Balance Sheet'!F39+'Balance Sheet'!F47)/('Balance Sheet'!F39+'Balance Sheet'!F47+'Balance Sheet'!F37) -> 0.37553596 | H8: =('Balance Sheet'!G39+'Balance Sheet'!G47)/('Balance Sheet'!G39+'Balance Sheet'!G47+'Balance Sheet'!G37) -> 0.38552542 | J8: Capital Structure | K8: Debt to Capital | L8: =('Balance Sheet'!J37+'Balance Sheet'!J46)/('Balance Sheet'!J35+'Balance Sheet'!J37+'Balance Sheet'!J46) -> 0.1137955 | M8: =('Balance Sheet'!K37+'Balance Sheet'!K46)/('Balance Sheet'!K35+'Balance Sheet'!K37+'Balance Sheet'!K46) -> 0.11259636 | N8: =('Balance Sheet'!L37+'Balance Sheet'!L46)/('Balance Sheet'!L35+'Balance Sheet'!L37+'Balance Sheet'!L46) -> 0.10854974 | O8: =('Balance Sheet'!M37+'Balance Sheet'!M46)/('Balance Sheet'!M35+'Balance Sheet'!M37+'Balance Sheet'!M46) -> 0.19998186 | P8: =('Balance Sheet'!N37+'Balance Sheet'!N46)/('Balance Sheet'!N35+'Balance Sheet'!N37+'Balance Sheet'!N46) -> 0.19423033 | Q8: =('Balance Sheet'!O37+'Balance Sheet'!O46)/('Balance Sheet'!O35+'Balance Sheet'!O37+'Balance Sheet'!O46) -> 0.16058804 | S8: Capital Structure | T8: Debt to Capital | U8: =('Balance Sheet'!R34+'Balance Sheet'!R42)/('Balance Sheet'!R32+'Balance Sheet'!R34+'Balance Sheet'!R42) -> 0.55972406 | V8: =('Balance Sheet'!S34+'Balance Sheet'!S42)/('Balance Sheet'!S32+'Balance Sheet'!S34+'Balance Sheet'!S42) -> 0.52843919 | W8: =('Balance Sheet'!T34+'Balance Sheet'!T42)/('Balance Sheet'!T32+'Balance Sheet'!T34+'Balance Sheet'!T42) -> 0.52068996 | X8: =('Balance Sheet'!U34+'Balance Sheet'!U42)/('Balance Sheet'!U32+'Balance Sheet'!U34+'Balance Sheet'!U42) -> 0.6751308 | Y8: =('Balance Sheet'!V34+'Balance Sheet'!V42)/('Balance Sheet'!V32+'Balance Sheet'!V34+'Balance Sheet'!V42) -> 0.57241011 | Z8: =('Balance Sheet'!W34+'Balance Sheet'!W42)/('Balance Sheet'!W32+'Balance Sheet'!W34+'Balance Sheet'!W42) -> 0.56500033 | AB8: Capital Structure | AC8: Debt to Capital | AD8: =('Balance Sheet'!Z40+'Balance Sheet'!Z47)/('Balance Sheet'!Z40+'Balance Sheet'!Z47+'Balance Sheet'!Z37) -> 0.56680519 | AE8: =('Balance Sheet'!AA40+'Balance Sheet'!AA47)/('Balance Sheet'!AA40+'Balance Sheet'!AA47+'Balance Sheet'!AA37) -> 0.49028803 | AF8: =('Balance Sheet'!AB40+'Balance Sheet'!AB47)/('Balance Sheet'!AB40+'Balance Sheet'!AB47+'Balance Sheet'!AB37) -> 0.47762352 | AG8: =('Balance Sheet'!AC40+'Balance Sheet'!AC47)/('Balance Sheet'!AC40+'Balance Sheet'!AC47+'Balance Sheet'!AC37) -> 0.49453018 | AH8: =('Balance Sheet'!AD40+'Balance Sheet'!AD47)/('Balance Sheet'!AD40+'Balance Sheet'!AD47+'Balance Sheet'!AD37) -> 0.39617142 | AI8: =('Balance Sheet'!AE40+'Balance Sheet'!AE47)/('Balance Sheet'!AE40+'Balance Sheet'!AE47+'Balance Sheet'!AE37) -> 0.42735761 | AK8: Capital Structure | AL8: Debt to Capital | AM8: =('Balance Sheet'!AH56+'Balance Sheet'!AH64)/('Balance Sheet'!AH64+'Balance Sheet'!AH56+'Balance Sheet'!AH53) -> 0.31845668 | AN8: =('Balance Sheet'!AI56+'Balance Sheet'!AI64)/('Balance Sheet'!AI64+'Balance Sheet'!AI56+'Balance Sheet'!AI53) -> 0.31161902 | AO8: =('Balance Sheet'!AJ56+'Balance Sheet'!AJ64)/('Balance Sheet'!AJ64+'Balance Sheet'!AJ56+'Balance Sheet'!AJ53) -> 0.2755684 | AP8: =('Balance Sheet'!AK56+'Balance Sheet'!AK64)/('Balance Sheet'!AK64+'Balance Sheet'!AK56+'Balance Sheet'!AK53) -> 0.30012401 | AQ8: =('Balance Sheet'!AL56+'Balance Sheet'!AL64)/('Balance Sheet'!AL64+'Balance Sheet'!AL56+'Balance Sheet'!AL53) -> 0.30481846 | AR8: =('Balance Sheet'!AM56+'Balance Sheet'!AM64)/('Balance Sheet'!AM64+'Balance Sheet'!AM56+'Balance Sheet'!AM53) -> 0.29094073 | AT8: Capital Structure | AU8: Debt to Capital | AV8: =('Balance Sheet'!AP32+'Balance Sheet'!AP40)/('Balance Sheet'!AP40+'Balance Sheet'!AP32+'Balance Sheet'!AP29) -> 0.39394996 | AW8: =('Balance Sheet'!AQ32+'Balance Sheet'!AQ40)/('Balance Sheet'!AQ40+'Balance Sheet'!AQ32+'Balance Sheet'!AQ29) -> 0.28994378 | AX8: =('Balance Sheet'!AR32+'Balance Sheet'!AR40)/('Balance Sheet'!AR40+'Balance Sheet'!AR32+'Balance Sheet'!AR29) -> 0.29209716 | AY8: =('Balance Sheet'!AS32+'Balance Sheet'!AS40)/('Balance Sheet'!AS40+'Balance Sheet'!AS32+'Balance Sheet'!AS29) -> 0.31057378 | AZ8: =('Balance Sheet'!AT32+'Balance Sheet'!AT40)/('Balance Sheet'!AT40+'Balance Sheet'!AT32+'Balance Sheet'!AT29) -> 0.29136618 | BA8: =('Balance Sheet'!AU32+'Balance Sheet'!AU40)/('Balance Sheet'!AU40+'Balance Sheet'!AU32+'Balance Sheet'!AU29) -> 0.26797816
A9: Capital Structure | B9: Interest Coverage | C9: =('Income Statement'!B19+'Income Statement'!B15)/'Income Statement'!B15 -> 2.7195741 | D9: =('Income Statement'!C19+'Income Statement'!C15)/'Income Statement'!C15 -> 13.171904 | E9: =('Income Statement'!D19+'Income Statement'!D15)/'Income Statement'!D15 -> 7.3512344 | F9: =('Income Statement'!E19+'Income Statement'!E15)/'Income Statement'!E15 -> 2.1119796 | G9: =('Income Statement'!F19+'Income Statement'!F15)/'Income Statement'!F15 -> 9.5316217 | H9: =('Income Statement'!G19+'Income Statement'!G15)/'Income Statement'!G15 -> 5.7997377 | J9: Capital Structure | K9: Interest Coverage | L9: =('Income Statement'!J19+'Income Statement'!J14+'Income Statement'!J15)/'Income Statement'!J14 -> 34.218424 | M9: =('Income Statement'!K19+'Income Statement'!K14+'Income Statement'!K15)/'Income Statement'!K14 -> 46.655659 | N9: =('Income Statement'!L19+'Income Statement'!L14+'Income Statement'!L15)/'Income Statement'!L14 -> 80.619469 | O9: =('Income Statement'!M19+'Income Statement'!M14+'Income Statement'!M15)/'Income Statement'!M14 -> 24.04913 | P9: =('Income Statement'!N19+'Income Statement'!N14+'Income Statement'!N15)/'Income Statement'!N14 -> 21.27938 | Q9: =('Income Statement'!O19+'Income Statement'!O14+'Income Statement'!O15)/'Income Statement'!O14 -> 22.32578 | S9: Capital Structure | T9: Interest Coverage | U9: =('Income Statement'!R20+'Income Statement'!R16)/'Income Statement'!R16 -> 3.4896957 | V9: =('Income Statement'!S20+'Income Statement'!S16)/'Income Statement'!S16 -> 15.594241 | W9: =('Income Statement'!T20+'Income Statement'!T16)/'Income Statement'!T16 -> 8.7062227 | X9: =('Income Statement'!U20+'Income Statement'!U16)/'Income Statement'!U16 -> -4.7381779 | Y9: =('Income Statement'!V20+'Income Statement'!V16)/'Income Statement'!V16 -> 8.3131025 | Z9: =('Income Statement'!W20+'Income Statement'!W16)/'Income Statement'!W16 -> 3.7097086 | AB9: Capital Structure | AC9: Interest Coverage | AD9: =('Income Statement'!Z23+'Income Statement'!Z15)/'Income Statement'!Z15 -> 1.4197673 | AE9: =('Income Statement'!AA23+'Income Statement'!AA15)/'Income Statement'!AA15 -> 9.2343304 | AF9: =('Income Statement'!AB23+'Income Statement'!AB15)/'Income Statement'!AB15 -> 7.0946847 | AG9: =('Income Statement'!AC23+'Income Statement'!AC15)/'Income Statement'!AC15 -> 2.8797007 | AH9: =('Income Statement'!AD23+'Income Statement'!AD15)/'Income Statement'!AD15 -> 8.1229687 | AI9: =('Income Statement'!AE23+'Income Statement'!AE15)/'Income Statement'!AE15 -> 2.4538007 | AK9: Capital Structure | AL9: Interest Coverage | AM9: =('Income Statement'!AH19+'Income Statement'!AH15)/'Income Statement'!AH15 -> 4.6128394 | AN9: =('Income Statement'!AI19+'Income Statement'!AI15)/'Income Statement'!AI15 -> 6.5466322 | AO9: =('Income Statement'!AJ19+'Income Statement'!AJ15)/'Income Statement'!AJ15 -> 10.608791 | AP9: =('Income Statement'!AK19+'Income Statement'!AK15)/'Income Statement'!AK15 -> 7.4840074 | AQ9: =('Income Statement'!AL19+'Income Statement'!AL15)/'Income Statement'!AL15 -> 6.4467659 | AR9: =('Income Statement'!AM19+'Income Statement'!AM15)/'Income Statement'!AM15 -> 4.5441048 | AT9: Capital Structure | AU9: Interest Coverage | AV9: =('Income Statement'!AP21+'Income Statement'!AP17)/'Income Statement'!AP17 -> 4.6812061 | AW9: =('Income Statement'!AQ21+'Income Statement'!AQ17)/'Income Statement'!AQ17 -> 2.4131146 | AX9: =('Income Statement'!AR21+'Income Statement'!AR17)/'Income Statement'!AR17 -> 5.9759947 | AY9: =('Income Statement'!AS21+'Income Statement'!AS17)/'Income Statement'!AS17 -> 5.2874228 | AZ9: =('Income Statement'!AT21+'Income Statement'!AT17)/'Income Statement'!AT17 -> 5.1156366 | BA9: =('Income Statement'!AU21+'Income Statement'!AU17)/'Income Statement'!AU17 -> 5.5880247
A10: Profitability | B10: Gross Profit margin | C10: =('Income Statement'!B8-(Table7[[#This Row],[2020]]+'Income Statement'!B11+'Income Statement'!B12))/'Income Statement'!B8 -> 0.22598647 | D10: =('Income Statement'!C8-(Table7[[#This Row],[2021]]+'Income Statement'!C11+'Income Statement'!C12))/'Income Statement'!C8 -> 0.3621331 | E10: =('Income Statement'!D8-(Table7[[#This Row],[2022]]+'Income Statement'!D11+'Income Statement'!D12))/'Income Statement'!D8 -> 0.30248752 | F10: =('Income Statement'!E8-(Table7[[#This Row],[2023]]+'Income Statement'!E11+'Income Statement'!E12))/'Income Statement'!E8 -> 0.19123854 | G10: =('Income Statement'!F8-(Table7[[#This Row],[2024]]+'Income Statement'!F11+'Income Statement'!F12))/'Income Statement'!F8 -> 0.26143791 | H10: =('Income Statement'!G8-(Table7[[#This Row],[2025]]+'Income Statement'!G11+'Income Statement'!G12))/'Income Statement'!G8 -> 0.23430997 | J10: Profitability | K10: Gross Profit margin | L10: =('Income Statement'!J8-(Table8[[#This Row],[2020]]+'Income Statement'!J11+'Income Statement'!J12))/'Income Statement'!J8 -> 0.2327764 | M10: =('Income Statement'!K8-(Table8[[#This Row],[2021]]+'Income Statement'!K11+'Income Statement'!K12))/'Income Statement'!K8 -> 0.25317916 | N10: =('Income Statement'!L8-(Table8[[#This Row],[2022]]+'Income Statement'!L11+'Income Statement'!L12))/'Income Statement'!L8 -> 0.25454429 | O10: =('Income Statement'!M8-(Table8[[#This Row],[2023]]+'Income Statement'!M11+'Income Statement'!M12))/'Income Statement'!M8 -> 0.1248043 | P10: =('Income Statement'!N8-(Table8[[#This Row],[2024]]+'Income Statement'!N11+'Income Statement'!N12))/'Income Statement'!N8 -> 0.19740802 | Q10: =('Income Statement'!O8-(Table8[[#This Row],[2025]]+'Income Statement'!O11+'Income Statement'!O12))/'Income Statement'!O8 -> 0.19379369 | S10: Profitability | T10: Gross Profit margin | U10: =('Income Statement'!R9-('Income Statement'!R11+'Income Statement'!R12+'Income Statement'!R13))/'Income Statement'!R9 -> 0.14731884 | V10: =('Income Statement'!S9-('Income Statement'!S11+'Income Statement'!S12+'Income Statement'!S13))/'Income Statement'!S9 -> 0.26596238 | W10: =('Income Statement'!T9-('Income Statement'!T11+'Income Statement'!T12+'Income Statement'!T13))/'Income Statement'!T9 -> 0.14455621 | X10: =('Income Statement'!U9-('Income Statement'!U11+'Income Statement'!U12+'Income Statement'!U13))/'Income Statement'!U9 -> 0.087090491 | Y10: =('Income Statement'!V9-('Income Statement'!V11+'Income Statement'!V12+'Income Statement'!V13))/'Income Statement'!V9 -> 0.16455432 | Z10: =('Income Statement'!W9-('Income Statement'!W11+'Income Statement'!W12+'Income Statement'!W13))/'Income Statement'!W9 -> 0.15765967 | AB10: Profitability | AC10: Gross Profit margin | AD10: =('Income Statement'!Z8-(Table10[[#This Row],[2020]]+'Income Statement'!Z12+'Income Statement'!Z13))/'Income Statement'!Z8 -> 0.28273011 | AE10: =('Income Statement'!AA8-(Table10[[#This Row],[2021]]+'Income Statement'!AA12+'Income Statement'!AA13))/'Income Statement'!AA8 -> 0.47405049 | AF10: =('Income Statement'!AB8-(Table10[[#This Row],[2022]]+'Income Statement'!AB12+'Income Statement'!AB13))/'Income Statement'!AB8 -> 0.34178926 | AG10: =('Income Statement'!AC8-(Table10[[#This Row],[2023]]+'Income Statement'!AC12+'Income Statement'!AC13))/'Income Statement'!AC8 -> 0.21763493 | AH10: =('Income Statement'!AD8-(Table10[[#This Row],[2024]]+'Income Statement'!AD12+'Income Statement'!AD13))/'Income Statement'!AD8 -> 0.27825943 | AI10: =('Income Statement'!AE8-(Table10[[#This Row],[2025]]+'Income Statement'!AE12+'Income Statement'!AE13))/'Income Statement'!AE8 -> 0.23884179 | AK10: Profitability | AL10: Gross Profit margin | AM10: =('Income Statement'!AH8-(Table11[[#This Row],[2020]]+'Income Statement'!AH11))/'Income Statement'!AH8 -> 0.59185151 | AN10: =('Income Statement'!AI8-(Table11[[#This Row],[2021]]+'Income Statement'!AI11))/'Income Statement'!AI8 -> 0.63599116 | AO10: =('Income Statement'!AJ8-(Table11[[#This Row],[2022]]+'Income Statement'!AJ11))/'Income Statement'!AJ8 -> 0.58586548 | AP10: =('Income Statement'!AK8-(Table11[[#This Row],[2023]]+'Income Statement'!AK11))/'Income Statement'!AK8 -> 0.61223143 | AQ10: =('Income Statement'!AL8-(Table11[[#This Row],[2024]]+'Income Statement'!AL11))/'Income Statement'!AL8 -> 0.65472516 | AR10: =('Income Statement'!AM8-(Table11[[#This Row],[2025]]+'Income Statement'!AM11))/'Income Statement'!AM8 -> 0.67129504 | AT10: Profitability | AU10: Gross Profit margin | AV10: =(Table12[[#This Row],[2020]]-('Income Statement'!AP12+'Income Statement'!AP13+'Income Statement'!AP14))/Table12[[#This Row],[2020]] -> 0.33033132 | AW10: =(Table12[[#This Row],[2021]]-('Income Statement'!AQ12+'Income Statement'!AQ13+'Income Statement'!AQ14))/Table12[[#This Row],[2021]] -> 0.37055669 | AX10: =(Table12[[#This Row],[2022]]-('Income Statement'!AR12+'Income Statement'!AR13+'Income Statement'!AR14))/Table12[[#This Row],[2022]] -> 0.29324128 | AY10: =(Table12[[#This Row],[2023]]-('Income Statement'!AS12+'Income Statement'!AS13+'Income Statement'!AS14))/Table12[[#This Row],[2023]] -> 0.28574916 | AZ10: =(Table12[[#This Row],[2024]]-('Income Statement'!AT12+'Income Statement'!AT13+'Income Statement'!AT14))/Table12[[#This Row],[2024]] -> 0.29906797 | BA10: =(Table12[[#This Row],[2025]]-('Income Statement'!AU12+'Income Statement'!AU13+'Income Statement'!AU14))/Table12[[#This Row],[2025]] -> 0.29091651
A11: Profitability | B11: EBITDA Margin | C11: =('Income Statement'!B19+'Income Statement'!B15+'Income Statement'!B16)/'Income Statement'!B8 -> 0.029397443 | D11: =('Income Statement'!C19+'Income Statement'!C15+'Income Statement'!C16)/'Income Statement'!C8 -> 0.070132001 | E11: =('Income Statement'!D19+'Income Statement'!D15+'Income Statement'!D16)/'Income Statement'!D8 -> 0.049776551 | F11: =('Income Statement'!E19+'Income Statement'!E15+'Income Statement'!E16)/'Income Statement'!E8 -> 0.024532031 | G11: =('Income Statement'!F19+'Income Statement'!F15+'Income Statement'!F16)/'Income Statement'!F8 -> 0.090955271 | H11: =('Income Statement'!G19+'Income Statement'!G15+'Income Statement'!G16)/'Income Statement'!G8 -> 0.05581474 | J11: Profitability | K11: EBITDA Margin | L11: =('Income Statement'!J19+'Income Statement'!J14+'Income Statement'!J15)/'Income Statement'!J8 -> 0.14263731 | M11: =('Income Statement'!K19+'Income Statement'!K14+'Income Statement'!K15)/'Income Statement'!K8 -> 0.14285534 | N11: =('Income Statement'!L19+'Income Statement'!L14+'Income Statement'!L15)/'Income Statement'!L8 -> 0.1735727 | O11: =('Income Statement'!M19+'Income Statement'!M14+'Income Statement'!M15)/'Income Statement'!M8 -> 0.059889405 | P11: =('Income Statement'!N19+'Income Statement'!N14+'Income Statement'!N15)/'Income Statement'!N8 -> 0.11377914 | Q11: =('Income Statement'!O19+'Income Statement'!O14+'Income Statement'!O15)/'Income Statement'!O8 -> 0.11632467 | S11: Profitability | T11: EBITDA Margin | U11: =('Income Statement'!R20+'Income Statement'!R16+'Income Statement'!R17)/'Income Statement'!R9 -> 0.025374946 | V11: =('Income Statement'!S20+'Income Statement'!S16+'Income Statement'!S17)/'Income Statement'!S9 -> 0.068248937 | W11: =('Income Statement'!T20+'Income Statement'!T16+'Income Statement'!T17)/'Income Statement'!T9 -> 0.033681355 | X11: =('Income Statement'!U20+'Income Statement'!U16+'Income Statement'!U17)/'Income Statement'!U9 -> -0.012268387 | Y11: =('Income Statement'!V20+'Income Statement'!V16+'Income Statement'!V17)/'Income Statement'!V9 -> 0.057869208 | Z11: =('Income Statement'!W20+'Income Statement'!W16+'Income Statement'!W17)/'Income Statement'!W9 -> 0.039758088 | AB11: Profitability | AC11: EBITDA Margin | AD11: =('Income Statement'!Z23+'Income Statement'!Z15+'Income Statement'!Z17+'Income Statement'!Z18)/'Income Statement'!Z8 -> 0.033888931 | AE11: =('Income Statement'!AA23+'Income Statement'!AA15+'Income Statement'!AA17+'Income Statement'!AA18)/'Income Statement'!AA8 -> 0.084173206 | AF11: =('Income Statement'!AB23+'Income Statement'!AB15+'Income Statement'!AB17+'Income Statement'!AB18)/'Income Statement'!AB8 -> 0.068698301 | AG11: =('Income Statement'!AC23+'Income Statement'!AC15+'Income Statement'!AC17+'Income Statement'!AC18)/'Income Statement'!AC8 -> 0.036519031 | AH11: =('Income Statement'!AD23+'Income Statement'!AD15+'Income Statement'!AD17+'Income Statement'!AD18)/'Income Statement'!AD8 -> 0.089747997 | AI11: =('Income Statement'!AE23+'Income Statement'!AE15+'Income Statement'!AE17+'Income Statement'!AE18)/'Income Statement'!AE8 -> 0.045782069 | AK11: Profitability | AL11: EBITDA Margin | AM11: =('Income Statement'!AH19+'Income Statement'!AH15+'Income Statement'!AH16)/'Income Statement'!AH8 -> 0.14095997 | AN11: =('Income Statement'!AI19+'Income Statement'!AI15+'Income Statement'!AI16)/'Income Statement'!AI8 -> 0.1589342 | AO11: =('Income Statement'!AJ19+'Income Statement'!AJ15+'Income Statement'!AJ16)/'Income Statement'!AJ8 -> 0.16191839 | AP11: =('Income Statement'!AK19+'Income Statement'!AK15+'Income Statement'!AK16)/'Income Statement'!AK8 -> 0.12065328 | AQ11: =('Income Statement'!AL19+'Income Statement'!AL15+'Income Statement'!AL16)/'Income Statement'!AL8 -> 0.17199861 | AR11: =('Income Statement'!AM19+'Income Statement'!AM15+'Income Statement'!AM16)/'Income Statement'!AM8 -> 0.14986074 | AT11: Profitability | AU11: EBITDA Margin | AV11: =('Income Statement'!AP21+'Income Statement'!AP17+'Income Statement'!AP18)/'Income Statement'!AP10 -> 0.1816918 | AW11: =('Income Statement'!AQ21+'Income Statement'!AQ17+'Income Statement'!AQ18)/'Income Statement'!AQ10 -> 0.17263396 | AX11: =('Income Statement'!AR21+'Income Statement'!AR17+'Income Statement'!AR18)/'Income Statement'!AR10 -> 0.14149765 | AY11: =('Income Statement'!AS21+'Income Statement'!AS17+'Income Statement'!AS18)/'Income Statement'!AS10 -> 0.13901306 | AZ11: =('Income Statement'!AT21+'Income Statement'!AT17+'Income Statement'!AT18)/'Income Statement'!AT10 -> 0.15425393 | BA11: =('Income Statement'!AU21+'Income Statement'!AU17+'Income Statement'!AU18)/'Income Statement'!AU10 -> 0.13511549
A12: Profitability | B12: Net Profit margin | C12: ='Income Statement'!B27/'Income Statement'!B8 -> 0.0081145982 | D12: ='Income Statement'!C27/'Income Statement'!C8 -> 0.06218512 | E12: ='Income Statement'!D27/'Income Statement'!D8 -> 0.026119531 | F12: ='Income Statement'!E27/'Income Statement'!E8 -> 0.0034912622 | G12: ='Income Statement'!F27/'Income Statement'!F8 -> 0.049611104 | H12: ='Income Statement'!G27/'Income Statement'!G8 -> 0.022750079 | J12: Profitability | K12: Net Profit | L12: ='Income Statement'!J27/'Income Statement'!J8 -> 0.12837822 | M12: ='Income Statement'!K27/'Income Statement'!K8 -> 0.10491856 | N12: ='Income Statement'!L27/'Income Statement'!L8 -> 0.13082556 | O12: ='Income Statement'!M27/'Income Statement'!M8 -> 0.038010985 | P12: ='Income Statement'!N27/'Income Statement'!N8 -> 0.073622817 | Q12: ='Income Statement'!O27/'Income Statement'!O8 -> 0.086813539 | S12: Profitability | T12: Net Profit | U12: ='Income Statement'!R30/'Income Statement'!R9 -> 0.0073100794 | V12: ='Income Statement'!S30/'Income Statement'!S9 -> 0.039026514 | W12: ='Income Statement'!T30/'Income Statement'!T9 -> 0.029192791 | X12: ='Income Statement'!U30/'Income Statement'!U9 -> -0.014916152 | Y12: ='Income Statement'!V30/'Income Statement'!V9 -> 0.034522722 | Z12: ='Income Statement'!W30/'Income Statement'!W9 -> 0.014367607 | AB12: Profitability | AC12: Net Profit | AD12: ='Income Statement'!Z32/'Income Statement'!Z8 -> -0.003241947 | AE12: ='Income Statement'!AA32/'Income Statement'!AA8 -> 0.041551859 | AF12: ='Income Statement'!AB32/'Income Statement'!AB8 -> 0.03477446 | AG12: ='Income Statement'!AC32/'Income Statement'!AC8 -> 0.012247961 | AH12: ='Income Statement'!AD32/'Income Statement'!AD8 -> 0.048765583 | AI12: ='Income Statement'!AE32/'Income Statement'!AE8 -> 0.015980074 | AK12: Profitability | AL12: Net Profit | AM12: ='Income Statement'!AH29/'Income Statement'!AH8 -> 0.026394593 | AN12: ='Income Statement'!AI29/'Income Statement'!AI8 -> 0.057701313 | AO12: ='Income Statement'!AJ29/'Income Statement'!AJ8 -> 0.0914156 | AP12: ='Income Statement'!AK29/'Income Statement'!AK8 -> 0.047304732 | AQ12: ='Income Statement'!AL29/'Income Statement'!AL8 -> 0.083092344 | AR12: ='Income Statement'!AM29/'Income Statement'!AM8 -> 0.056728005 | AT12: Profitability | AU12: Net Profit | AV12: ='Income Statement'!AP28/'Income Statement'!AP10 -> 0.08456821 | AW12: ='Income Statement'!AQ28/'Income Statement'!AQ10 -> 0.11413177 | AX12: ='Income Statement'!AR28/'Income Statement'!AR10 -> 0.082861187 | AY12: ='Income Statement'!AS28/'Income Statement'!AS10 -> 0.077785614 | AZ12: ='Income Statement'!AT28/'Income Statement'!AT10 -> 0.075065617 | BA12: ='Income Statement'!AU28/'Income Statement'!AU10 -> 0.064242848
A13: Profitability | B13: Return on Assets | C13: ='Income Statement'!B27/'Balance Sheet'!B32 -> 0.021216191 | D13: ='Income Statement'!C27/'Balance Sheet'!C32 -> 0.1182848 | E13: ='Income Statement'!D27/'Balance Sheet'!D32 -> 0.060595281 | F13: ='Income Statement'!E27/'Balance Sheet'!E32 -> 0.0099400393 | G13: ='Income Statement'!F27/'Balance Sheet'!F32 -> 0.12480788 | H13: ='Income Statement'!G27/'Balance Sheet'!G32 -> 0.052421346 | J13: Profitability | K13: Return on Assets | L13: ='Income Statement'!J27/'Balance Sheet'!J29 -> 0.1270072 | M13: ='Income Statement'!K27/'Balance Sheet'!K29 -> 0.075478565 | N13: ='Income Statement'!L27/'Balance Sheet'!L29 -> 0.12742032 | O13: ='Income Statement'!M27/'Balance Sheet'!M29 -> 0.051914187 | P13: ='Income Statement'!N27/'Balance Sheet'!N29 -> 0.0794021 | Q13: ='Income Statement'!O27/'Balance Sheet'!O29 -> 0.093601118 | S13: Profitability | T13: Return on Assets | U13: ='Income Statement'!R30/'Balance Sheet'!R27 -> 0.018096929 | V13: ='Income Statement'!S30/'Balance Sheet'!S27 -> 0.079479078 | W13: ='Income Statement'!T30/'Balance Sheet'!T27 -> 0.071092874 | X13: ='Income Statement'!U30/'Balance Sheet'!U27 -> -0.043264232 | Y13: ='Income Statement'!V30/'Balance Sheet'!V27 -> 0.087622437 | Z13: ='Income Statement'!W30/'Balance Sheet'!W27 -> 0.034587345 | AB13: Profitability | AC13: Return on Assets | AD13: ='Income Statement'!Z32/'Balance Sheet'!Z31 -> -0.0056903562 | AE13: ='Income Statement'!AA32/'Balance Sheet'!AA31 -> 0.061316551 | AF13: ='Income Statement'!AB32/'Balance Sheet'!AB31 -> 0.062652321 | AG13: ='Income Statement'!AC32/'Balance Sheet'!AC31 -> 0.026494487 | AH13: ='Income Statement'!AD32/'Balance Sheet'!AD31 -> 0.089478752 | AI13: ='Income Statement'!AE32/'Balance Sheet'!AE31 -> 0.027204037 | AK13: Profitability | AL13: Return on Assets | AM13: ='Income Statement'!AH29/'Balance Sheet'!AH47 -> 0.022699461 | AN13: ='Income Statement'!AI29/'Balance Sheet'!AI47 -> 0.039683115 | AO13: ='Income Statement'!AJ29/'Balance Sheet'!AJ47 -> 0.084987004 | AP13: ='Income Statement'!AK29/'Balance Sheet'!AK47 -> 0.053790229 | AQ13: ='Income Statement'!AL29/'Balance Sheet'!AL47 -> 0.075036339 | AR13: ='Income Statement'!AM29/'Balance Sheet'!AM47 -> 0.050734143 | AT13: Profitability | AU13: Return on Assets | AV13: ='Income Statement'!AP28/'Balance Sheet'!AP24 -> 0.031803058 | AW13: ='Income Statement'!AQ28/'Balance Sheet'!AQ24 -> 0.036562879 | AX13: ='Income Statement'!AR28/'Balance Sheet'!AR24 -> 0.044269277 | AY13: ='Income Statement'!AS28/'Balance Sheet'!AS24 -> 0.051594355 | AZ13: ='Income Statement'!AT28/'Balance Sheet'!AT24 -> 0.043810042 | BA13: ='Income Statement'!AU28/'Balance Sheet'!AU24 -> 0.034489403
A14: Profitability | B14: Return on Equity | C14: ='Income Statement'!B27/'Balance Sheet'!B37 -> 0.080783986 | D14: ='Income Statement'!C27/'Balance Sheet'!C37 -> 0.35555301 | E14: ='Income Statement'!D27/'Balance Sheet'!D37 -> 0.21892331 | F14: ='Income Statement'!E27/'Balance Sheet'!E37 -> 0.034940537 | G14: ='Income Statement'!F27/'Balance Sheet'!F37 -> 0.33401591 | H14: ='Income Statement'!G27/'Balance Sheet'!G37 -> 0.14066498 | J14: Profitability | K14: Return on Equity | L14: ='Income Statement'!J27/'Balance Sheet'!J35 -> 0.19277852 | M14: ='Income Statement'!K27/'Balance Sheet'!K35 -> 0.11529354 | N14: ='Income Statement'!L27/'Balance Sheet'!L35 -> 0.19133103 | O14: ='Income Statement'!M27/'Balance Sheet'!M35 -> 0.085940862 | P14: ='Income Statement'!N27/'Balance Sheet'!N35 -> 0.12828175 | Q14: ='Income Statement'!O27/'Balance Sheet'!O35 -> 0.14620835 | S14: Profitability | T14: Return on Equity | U14: ='Income Statement'!R30/'Balance Sheet'!R32 -> 0.068291403 | V14: ='Income Statement'!S30/'Balance Sheet'!S32 -> 0.28000654 | W14: ='Income Statement'!T30/'Balance Sheet'!T32 -> 0.26550464 | X14: ='Income Statement'!U30/'Balance Sheet'!U32 -> -0.21635222 | Y14: ='Income Statement'!V30/'Balance Sheet'!V32 -> 0.34130753 | Z14: ='Income Statement'!W30/'Balance Sheet'!W32 -> 0.13169994 | AB14: Profitability | AC14: Return on Equity | AD14: ='Income Statement'!Z32/'Balance Sheet'!Z37 -> -0.019489338 | AE14: ='Income Statement'!AA32/'Balance Sheet'!AA37 -> 0.19290356 | AF14: ='Income Statement'!AB32/'Balance Sheet'!AB37 -> 0.19038879 | AG14: ='Income Statement'!AC32/'Balance Sheet'!AC37 -> 0.081725475 | AH14: ='Income Statement'!AD32/'Balance Sheet'!AD37 -> 0.22938173 | AI14: ='Income Statement'!AE32/'Balance Sheet'!AE37 -> 0.072183508 | AK14: Profitability | AL14: Return on Equity | AM14: ='Income Statement'!AH29/'Balance Sheet'!AH53 -> 0.051255969 | AN14: ='Income Statement'!AI29/'Balance Sheet'!AI53 -> 0.087979096 | AO14: ='Income Statement'!AJ29/'Balance Sheet'!AJ53 -> 0.1739824 | AP14: ='Income Statement'!AK29/'Balance Sheet'!AK53 -> 0.10880351 | AQ14: ='Income Statement'!AL29/'Balance Sheet'!AL53 -> 0.15369694 | AR14: ='Income Statement'!AM29/'Balance Sheet'!AM53 -> 0.10241853 | AT14: Profitability | AU14: Return on Equity | AV14: ='Income Statement'!AP28/'Balance Sheet'!AP29 -> 0.07899237 | AW14: ='Income Statement'!AQ28/'Balance Sheet'!AQ29 -> 0.067323803 | AX14: ='Income Statement'!AR28/'Balance Sheet'!AR29 -> 0.080455626 | AY14: ='Income Statement'!AS28/'Balance Sheet'!AS29 -> 0.089788225 | AZ14: ='Income Statement'!AT28/'Balance Sheet'!AT29 -> 0.081619737 | BA14: ='Income Statement'!AU28/'Balance Sheet'!AU29 -> 0.064928824
A15: Efficiency | B15: Asset Turnover | C15: ='Income Statement'!B8/'Balance Sheet'!B32 -> 2.6145707 | D15: ='Income Statement'!C8/'Balance Sheet'!C32 -> 1.9021399 | E15: ='Income Statement'!D8/'Balance Sheet'!D32 -> 2.3199222 | F15: ='Income Statement'!E8/'Balance Sheet'!E32 -> 2.847119 | G15: ='Income Statement'!F8/'Balance Sheet'!F32 -> 2.5157247 | H15: ='Income Statement'!G8/'Balance Sheet'!G32 -> 2.304227 | J15: Efficiency | K15: Asset Turnover | L15: ='Income Statement'!J8/'Balance Sheet'!J29 -> 0.98932045 | M15: ='Income Statement'!K8/'Balance Sheet'!K29 -> 0.71940147 | N15: ='Income Statement'!L8/'Balance Sheet'!L29 -> 0.97397115 | O15: ='Income Statement'!M8/'Balance Sheet'!M29 -> 1.365768 | P15: ='Income Statement'!N8/'Balance Sheet'!N29 -> 1.0784985 | Q15: ='Income Statement'!O8/'Balance Sheet'!O29 -> 1.0781857 | S15: Efficiency | T15: Asset Turnover | U15: ='Income Statement'!R9/'Balance Sheet'!R27 -> 2.4756132 | V15: ='Income Statement'!S9/'Balance Sheet'!S27 -> 2.0365406 | W15: ='Income Statement'!T9/'Balance Sheet'!T27 -> 2.4352887 | X15: ='Income Statement'!U9/'Balance Sheet'!U27 -> 2.9004955 | Y15: ='Income Statement'!V9/'Balance Sheet'!V27 -> 2.5381092 | Z15: ='Income Statement'!W9/'Balance Sheet'!W27 -> 2.4073142 | AB15: Efficiency | AC15: Asset Turnover | AD15: ='Income Statement'!Z8/'Balance Sheet'!Z31 -> 1.755228 | AE15: ='Income Statement'!AA8/'Balance Sheet'!AA31 -> 1.4756633 | AF15: ='Income Statement'!AB8/'Balance Sheet'!AB31 -> 1.8016763 | AG15: ='Income Statement'!AC8/'Balance Sheet'!AC31 -> 2.1631753 | AH15: ='Income Statement'!AD8/'Balance Sheet'!AD31 -> 1.8348751 | AI15: ='Income Statement'!AE8/'Balance Sheet'!AE31 -> 1.7023724 | AK15: Efficiency | AL15: Asset Turnover | AM15: ='Income Statement'!AH8/'Balance Sheet'!AH47 -> 0.8600042 | AN15: ='Income Statement'!AI8/'Balance Sheet'!AI47 -> 0.68773332 | AO15: ='Income Statement'!AJ8/'Balance Sheet'!AJ47 -> 0.92967725 | AP15: ='Income Statement'!AK8/'Balance Sheet'!AK47 -> 1.1371004 | AQ15: ='Income Statement'!AL8/'Balance Sheet'!AL47 -> 0.90304756 | AR15: ='Income Statement'!AM8/'Balance Sheet'!AM47 -> 0.89434034 | AT15: Efficiency | AU15: Asset Turnover | AV15: ='Income Statement'!AP10/'Balance Sheet'!AP24 -> 0.37606399 | AW15: ='Income Statement'!AQ10/'Balance Sheet'!AQ24 -> 0.3203567 | AX15: ='Income Statement'!AR10/'Balance Sheet'!AR24 -> 0.53425831 | AY15: ='Income Statement'!AS10/'Balance Sheet'!AS24 -> 0.66328917 | AZ15: ='Income Statement'!AT10/'Balance Sheet'!AT24 -> 0.58362328 | BA15: ='Income Statement'!AU10/'Balance Sheet'!AU24 -> 0.5368598
A16: Efficiency | B16: Inventory turnover | C16: =('Income Statement'!B10+'Income Statement'!B11+'Income Statement'!B12)/'Balance Sheet'!B21 -> 12.532989 | D16: =('Income Statement'!C10+'Income Statement'!C11+'Income Statement'!C12)/'Balance Sheet'!C21 -> 7.3135473 | E16: =('Income Statement'!D10+'Income Statement'!D11+'Income Statement'!D12)/'Balance Sheet'!D21 -> 7.1944797 | F16: =('Income Statement'!E10+'Income Statement'!E11+'Income Statement'!E12)/'Balance Sheet'!E21 -> 11.379657 | G16: =('Income Statement'!F10+'Income Statement'!F11+'Income Statement'!F12)/'Balance Sheet'!F21 -> 8.7798781 | H16: =('Income Statement'!G10+'Income Statement'!G11+'Income Statement'!G12)/'Balance Sheet'!G21 -> 8.5119914 | J16: Efficiency | K16: Inventory turnover | L16: =('Income Statement'!J10+'Income Statement'!J11+'Income Statement'!J12)/'Balance Sheet'!J20 -> 17.864257 | M16: =('Income Statement'!K10+'Income Statement'!K11+'Income Statement'!K12)/'Balance Sheet'!K20 -> 14.625137 | N16: =('Income Statement'!L10+'Income Statement'!L11+'Income Statement'!L12)/'Balance Sheet'!L20 -> 19.601572 | O16: =('Income Statement'!M10+'Income Statement'!M11+'Income Statement'!M12)/'Balance Sheet'!M20 -> 21.769789 | P16: =('Income Statement'!N10+'Income Statement'!N11+'Income Statement'!N12)/'Balance Sheet'!N20 -> 18.082834 | Q16: =('Income Statement'!O10+'Income Statement'!O11+'Income Statement'!O12)/'Balance Sheet'!O20 -> 18.518352 | S16: Efficiency | T16: Inventory turnover | U16: =('Income Statement'!R11+'Income Statement'!R12+'Income Statement'!R13)/'Balance Sheet'!R17 -> 12.769649 | V16: =('Income Statement'!S11+'Income Statement'!S12+'Income Statement'!S13)/'Balance Sheet'!S17 -> 6.9724551 | W16: =('Income Statement'!T11+'Income Statement'!T12+'Income Statement'!T13)/'Balance Sheet'!T17 -> 9.0703534 | X16: =('Income Statement'!U11+'Income Statement'!U12+'Income Statement'!U13)/'Balance Sheet'!U17 -> 14.444945 | Y16: =('Income Statement'!V11+'Income Statement'!V12+'Income Statement'!V13)/'Balance Sheet'!V17 -> 11.328123 | Z16: =('Income Statement'!W11+'Income Statement'!W12+'Income Statement'!W13)/'Balance Sheet'!W17 -> 10.303877 | AB16: Efficiency | AC16: Inventory turnover | AD16: =('Income Statement'!Z10+'Income Statement'!Z12+'Income Statement'!Z13)/'Balance Sheet'!Z20 -> 6.1949678 | AE16: =('Income Statement'!AA10+'Income Statement'!AA12+'Income Statement'!AA13)/'Balance Sheet'!AA20 -> 3.3017773 | AF16: =('Income Statement'!AB10+'Income Statement'!AB12+'Income Statement'!AB13)/'Balance Sheet'!AB20 -> 4.3580464 | AG16: =('Income Statement'!AC10+'Income Statement'!AC12+'Income Statement'!AC13)/'Balance Sheet'!AC20 -> 6.1733129 | AH16: =('Income Statement'!AD10+'Income Statement'!AD12+'Income Statement'!AD13)/'Balance Sheet'!AD20 -> 5.2629409 | AI16: =('Income Statement'!AE10+'Income Statement'!AE12+'Income Statement'!AE13)/'Balance Sheet'!AE20 -> 5.7674237 | AK16: Efficiency | AL16: Inventory turnover | AM16: =('Income Statement'!AH10+'Income Statement'!AH11)/'Balance Sheet'!AH36 -> 5.3599257 | AN16: =('Income Statement'!AI10+'Income Statement'!AI11)/'Balance Sheet'!AI36 -> 3.0207566 | AO16: =('Income Statement'!AJ10+'Income Statement'!AJ11)/'Balance Sheet'!AJ36 -> 4.122989 | AP16: =('Income Statement'!AK10+'Income Statement'!AK11)/'Balance Sheet'!AK36 -> 6.0736405 | AQ16: =('Income Statement'!AL10+'Income Statement'!AL11)/'Balance Sheet'!AL36 -> 4.2696684 | AR16: =('Income Statement'!AM10+'Income Statement'!AM11)/'Balance Sheet'!AM36 -> 3.76705 | AT16: Efficiency | AU16: Inventory turnover | AV16: =('Income Statement'!AP12+'Income Statement'!AP13+'Income Statement'!AP14)/'Balance Sheet'!AP17 -> 6.3066595 | AW16: =('Income Statement'!AQ12+'Income Statement'!AQ13+'Income Statement'!AQ14)/'Balance Sheet'!AQ17 -> 4.7058525 | AX16: =('Income Statement'!AR12+'Income Statement'!AR13+'Income Statement'!AR14)/'Balance Sheet'!AR17 -> 7.0461642 | AY16: =('Income Statement'!AS12+'Income Statement'!AS13+'Income Statement'!AS14)/'Balance Sheet'!AS17 -> 8.0733148 | AZ16: =('Income Statement'!AT12+'Income Statement'!AT13+'Income Statement'!AT14)/'Balance Sheet'!AT17 -> 4.6130552 | BA16: =('Income Statement'!AU12+'Income Statement'!AU13+'Income Statement'!AU14)/'Balance Sheet'!AU17 -> 4.3625135
A17: Efficiency | B17: Receivables turnover | C17: ='Income Statement'!B8/'Balance Sheet'!B23 -> 64.027947 | D17: ='Income Statement'!C8/'Balance Sheet'!C23 -> 39.083397 | E17: ='Income Statement'!D8/'Balance Sheet'!D23 -> 44.816192 | F17: ='Income Statement'!E8/'Balance Sheet'!E23 -> 79.665239 | G17: ='Income Statement'!F8/'Balance Sheet'!F23 -> 61.043575 | H17: ='Income Statement'!G8/'Balance Sheet'!G23 -> 53.881923 | J17: Efficiency | K17: Receivables turnover | L17: ='Income Statement'!J8/'Balance Sheet'!J22 -> 15.381769 | M17: ='Income Statement'!K8/'Balance Sheet'!K22 -> 16.720965 | N17: ='Income Statement'!L8/'Balance Sheet'!L22 -> 61.880557 | O17: ='Income Statement'!M8/'Balance Sheet'!M22 -> 603.86225 | P17: ='Income Statement'!N8/'Balance Sheet'!N22 -> 117.36809 | Q17: ='Income Statement'!O8/'Balance Sheet'!O22 -> 108.98971 | S17: Efficiency | T17: Receivables turnover | U17: ='Income Statement'!R9/'Balance Sheet'!R19 -> 73.566266 | V17: ='Income Statement'!S9/'Balance Sheet'!S19 -> 39.770318 | W17: ='Income Statement'!T9/'Balance Sheet'!T19 -> 59.39235 | X17: ='Income Statement'!U9/'Balance Sheet'!U19 -> 68.492168 | Y17: ='Income Statement'!V9/'Balance Sheet'!V19 -> 49.751352 | Z17: ='Income Statement'!W9/'Balance Sheet'!W19 -> 39.794845 | AB17: Efficiency | AC17: Receivables turnover | AD17: ='Income Statement'!Z8/'Balance Sheet'!Z22 -> 43.649021 | AE17: ='Income Statement'!AA8/'Balance Sheet'!AA22 -> 37.951142 | AF17: ='Income Statement'!AB8/'Balance Sheet'!AB22 -> 39.561307 | AG17: ='Income Statement'!AC8/'Balance Sheet'!AC22 -> 58.730043 | AH17: ='Income Statement'!AD8/'Balance Sheet'!AD22 -> 63.989966 | AI17: ='Income Statement'!AE8/'Balance Sheet'!AE22 -> 46.513844 | AK17: Efficiency | AL17: Receivables turnover | AM17: ='Income Statement'!AH8/'Balance Sheet'!AH26 -> 182.82239 | AN17: ='Income Statement'!AI8/'Balance Sheet'!AI26 -> 144.32371 | AO17: ='Income Statement'!AJ8/'Balance Sheet'!AJ26 -> 217.73876 | AP17: ='Income Statement'!AK8/'Balance Sheet'!AK26 -> 264.21621 | AQ17: ='Income Statement'!AL8/'Balance Sheet'!AL26 -> 262.35742 | AR17: ='Income Statement'!AM8/'Balance Sheet'!AM26 -> 283.98102 | AT17: Efficiency | AU17: Receivables turnover | AV17: ='Income Statement'!AP10/'Balance Sheet'!AP19 -> 48.833489 | AW17: ='Income Statement'!AQ10/'Balance Sheet'!AQ19 -> 67.296706 | AX17: ='Income Statement'!AR10/'Balance Sheet'!AR19 -> 31.807559 | AY17: ='Income Statement'!AS10/'Balance Sheet'!AS19 -> 32.72695 | AZ17: ='Income Statement'!AT10/'Balance Sheet'!AT19 -> 37.996608 | BA17: ='Income Statement'!AU10/'Balance Sheet'!AU19 -> 35.205311
A18: Efficiency | B18: Payable Turnover | C18: =('Income Statement'!B10+'Income Statement'!B11+'Income Statement'!B12)/'Balance Sheet'!B51 -> 20.45934 | D18: =('Income Statement'!C10+'Income Statement'!C11+'Income Statement'!C12)/'Balance Sheet'!C51 -> 12.005022 | E18: =('Income Statement'!D10+'Income Statement'!D11+'Income Statement'!D12)/'Balance Sheet'!D51 -> 9.9992385 | F18: =('Income Statement'!E10+'Income Statement'!E11+'Income Statement'!E12)/'Balance Sheet'!E51 -> 18.032369 | G18: =('Income Statement'!F10+'Income Statement'!F11+'Income Statement'!F12)/'Balance Sheet'!F51 -> 13.286884 | H18: =('Income Statement'!G10+'Income Statement'!G11+'Income Statement'!G12)/'Balance Sheet'!G51 -> 12.577403 | J18: Efficiency | K18: Payables Turnover | L18: =('Income Statement'!J10+'Income Statement'!J11+'Income Statement'!J12)/'Balance Sheet'!J50 -> 14.497578 | M18: =('Income Statement'!K10+'Income Statement'!K11+'Income Statement'!K12)/'Balance Sheet'!K50 -> 9.8188733 | N18: =('Income Statement'!L10+'Income Statement'!L11+'Income Statement'!L12)/'Balance Sheet'!L50 -> 13.076624 | O18: =('Income Statement'!M10+'Income Statement'!M11+'Income Statement'!M12)/'Balance Sheet'!M50 -> 18.034687 | P18: =('Income Statement'!N10+'Income Statement'!N11+'Income Statement'!N12)/'Balance Sheet'!N50 -> 16.259019 | Q18: =('Income Statement'!O10+'Income Statement'!O11+'Income Statement'!O12)/'Balance Sheet'!O50 -> 14.915007 | S18: Efficiency | T18: Payables Turnover | U18: =('Income Statement'!R11+'Income Statement'!R12+'Income Statement'!R13)/'Balance Sheet'!R46 -> 21.511008 | V18: =('Income Statement'!S11+'Income Statement'!S12+'Income Statement'!S13)/'Balance Sheet'!S46 -> 11.267989 | W18: =('Income Statement'!T11+'Income Statement'!T12+'Income Statement'!T13)/'Balance Sheet'!T46 -> 12.166294 | X18: =('Income Statement'!U11+'Income Statement'!U12+'Income Statement'!U13)/'Balance Sheet'!U46 -> 18.644655 | Y18: =('Income Statement'!V11+'Income Statement'!V12+'Income Statement'!V13)/'Balance Sheet'!V46 -> 14.196025 | Z18: =('Income Statement'!W11+'Income Statement'!W12+'Income Statement'!W13)/'Balance Sheet'!W46 -> 13.251284 | AC18: Payables Turnover | AD18: =('Income Statement'!Z10+'Income Statement'!Z12+'Income Statement'!Z13)/'Balance Sheet'!Z51 -> 15.053872 | AE18: =('Income Statement'!AA10+'Income Statement'!AA12+'Income Statement'!AA13)/'Balance Sheet'!AA51 -> 7.3952725 | AF18: =('Income Statement'!AB10+'Income Statement'!AB12+'Income Statement'!AB13)/'Balance Sheet'!AB51 -> 9.9252861 | AG18: =('Income Statement'!AC10+'Income Statement'!AC12+'Income Statement'!AC13)/'Balance Sheet'!AC51 -> 13.6594 | AH18: =('Income Statement'!AD10+'Income Statement'!AD12+'Income Statement'!AD13)/'Balance Sheet'!AD51 -> 10.744319 | AI18: =('Income Statement'!AE10+'Income Statement'!AE12+'Income Statement'!AE13)/'Balance Sheet'!AE51 -> 10.849693 | AL18: Payables Turnover | AM18: =('Income Statement'!AH10+'Income Statement'!AH11)/'Balance Sheet'!AH67 -> 7.7153007 | AN18: =('Income Statement'!AI10+'Income Statement'!AI11)/'Balance Sheet'!AI67 -> 4.9052592 | AO18: =('Income Statement'!AJ10+'Income Statement'!AJ11)/'Balance Sheet'!AJ67 -> 5.5570045 | AP18: =('Income Statement'!AK10+'Income Statement'!AK11)/'Balance Sheet'!AK67 -> 7.9864846 | AQ18: =('Income Statement'!AL10+'Income Statement'!AL11)/'Balance Sheet'!AL67 -> 6.0208077 | AR18: =('Income Statement'!AM10+'Income Statement'!AM11)/'Balance Sheet'!AM67 -> 5.6982275 | AU18: Payables Turnover | AV18: =('Income Statement'!AP12+'Income Statement'!AP13+'Income Statement'!AP14)/'Balance Sheet'!AP44 -> 3.4443053 | AW18: =('Income Statement'!AQ12+'Income Statement'!AQ13+'Income Statement'!AQ14)/'Balance Sheet'!AQ44 -> 2.0250003 | AX18: =('Income Statement'!AR12+'Income Statement'!AR13+'Income Statement'!AR14)/'Balance Sheet'!AR44 -> 2.4146935 | AY18: =('Income Statement'!AS12+'Income Statement'!AS13+'Income Statement'!AS14)/'Balance Sheet'!AS44 -> 3.5674482 | AZ18: =('Income Statement'!AT12+'Income Statement'!AT13+'Income Statement'!AT14)/'Balance Sheet'!AT44 -> 3.0230558 | BA18: =('Income Statement'!AU12+'Income Statement'!AU13+'Income Statement'!AU14)/'Balance Sheet'!AU44 -> 3.1803332
A19: Valuation | B19: EV/EBITDA | C19: =(('Company Profile'!B10/10000000)+'Balance Sheet'!B39+'Balance Sheet'!B47-'Balance Sheet'!B24)/(Table7[[#This Row],[2020]]+'Income Statement'!B15+'Income Statement'!B16) -> 20.90237 | D19: =(('Company Profile'!C10/10000000)+'Balance Sheet'!C39+'Balance Sheet'!C47-'Balance Sheet'!C24)/(Table7[[#This Row],[2021]]+'Income Statement'!C15+'Income Statement'!C16) -> 7.3466148 | E19: =(('Company Profile'!D10/10000000)+'Balance Sheet'!D39+'Balance Sheet'!D47-'Balance Sheet'!D24)/(Table7[[#This Row],[2022]]+'Income Statement'!D15+'Income Statement'!D16) -> 7.195133 | F19: =(('Company Profile'!E10/10000000)+'Balance Sheet'!E39+'Balance Sheet'!E47-'Balance Sheet'!E24)/(Table7[[#This Row],[2023]]+'Income Statement'!E15+'Income Statement'!E16) -> 22.602951 | G19: =(('Company Profile'!F10/10000000)+'Balance Sheet'!F39+'Balance Sheet'!F47-'Balance Sheet'!F24)/(Table7[[#This Row],[2024]]+'Income Statement'!F15+'Income Statement'!F16) -> 7.7824468 | H19: =(('Company Profile'!G10/10000000)+'Balance Sheet'!G39+'Balance Sheet'!G47-'Balance Sheet'!G24)/(Table7[[#This Row],[2025]]+'Income Statement'!G15+'Income Statement'!G16) -> 73.011275 | J19: Valuation | K19: EV/EBITDA | L19: =(('Company Profile'!C10/10000000)+'Balance Sheet'!J46+'Balance Sheet'!J37-'Balance Sheet'!J23)/(Table8[[#This Row],[2020]]+'Income Statement'!J14+'Income Statement'!J15) -> 11.765093 | M19: =(('Company Profile'!D10/10000000)+'Balance Sheet'!K46+'Balance Sheet'!K37-'Balance Sheet'!K23)/(Table8[[#This Row],[2021]]+'Income Statement'!K14+'Income Statement'!K15) -> 12.828064 | N19: =(('Company Profile'!E10/10000000)+'Balance Sheet'!L46+'Balance Sheet'!L37-'Balance Sheet'!L23)/(Table8[[#This Row],[2022]]+'Income Statement'!L14+'Income Statement'!L15) -> 15.034523 | O19: =(('Company Profile'!F10/10000000)+'Balance Sheet'!M46+'Balance Sheet'!M37-'Balance Sheet'!M23)/(Table8[[#This Row],[2023]]+'Income Statement'!M14+'Income Statement'!M15) -> 37.737414 | P19: =(('Company Profile'!G10/10000000)+'Balance Sheet'!N46+'Balance Sheet'!N37-'Balance Sheet'!N23)/(Table8[[#This Row],[2024]]+'Income Statement'!N14+'Income Statement'!N15) -> 131.86904 | Q19: =(Q25+'Balance Sheet'!O46+'Balance Sheet'!O37-'Balance Sheet'!O23)/(Table8[[#This Row],[2025]]+'Income Statement'!O14+'Income Statement'!O15) -> 8.0394745 | S19: Valuation | T19: EV/EBITDA | U19: =(('Company Profile'!$D$10/10000000)+'Balance Sheet'!R42+'Balance Sheet'!R34-'Balance Sheet'!R20)/('Income Statement'!R20+'Income Statement'!R16+'Income Statement'!R17) -> 19.229109 | V19: =(('Company Profile'!$D$10/10000000)+'Balance Sheet'!S42+'Balance Sheet'!S34-'Balance Sheet'!S20)/('Income Statement'!S20+'Income Statement'!S16+'Income Statement'!S17) -> 7.7349007 | W19: =(('Company Profile'!$D$10/10000000)+'Balance Sheet'!T42+'Balance Sheet'!T34-'Balance Sheet'!T20)/('Income Statement'!T20+'Income Statement'!T16+'Income Statement'!T17) -> 11.573105 | X19: =(('Company Profile'!$D$10/10000000)+'Balance Sheet'!U42+'Balance Sheet'!U34-'Balance Sheet'!U20)/('Income Statement'!U20+'Income Statement'!U16+'Income Statement'!U17) -> -29.361527 | Y19: =(('Company Profile'!$D$10/10000000)+'Balance Sheet'!V42+'Balance Sheet'!V34-'Balance Sheet'!V20)/('Income Statement'!V20+'Income Statement'!V16+'Income Statement'!V17) -> 6.1305527 | Z19: =(('Company Profile'!$D$10/10000000)+'Balance Sheet'!W42+'Balance Sheet'!W34-'Balance Sheet'!W20)/('Income Statement'!W20+'Income Statement'!W16+'Income Statement'!W17) -> 9.0295568 | AB19: Valuation | AC19: EV/EBITDA | AD19: =(('Company Profile'!$E$10/10000000)+'Balance Sheet'!Z40+'Balance Sheet'!Z47-'Balance Sheet'!Z23)/('Income Statement'!Z23+'Income Statement'!Z15+'Income Statement'!Z17+'Income Statement'!Z18) -> 18.528319 | AE19: =(('Company Profile'!$E$10/10000000)+'Balance Sheet'!AA40+'Balance Sheet'!AA47-'Balance Sheet'!AA23)/('Income Statement'!AA23+'Income Statement'!AA15+'Income Statement'!AA17+'Income Statement'!AA18) -> 7.8623557 | AF19: =(('Company Profile'!$E$10/10000000)+'Balance Sheet'!AB40+'Balance Sheet'!AB47-'Balance Sheet'!AB23)/('Income Statement'!AB23+'Income Statement'!AB15+'Income Statement'!AB17+'Income Statement'!AB18) -> 7.1078451 | AG19: =(('Company Profile'!$E$10/10000000)+'Balance Sheet'!AC40+'Balance Sheet'!AC47-'Balance Sheet'!AC23)/('Income Statement'!AC23+'Income Statement'!AC15+'Income Statement'!AC17+'Income Statement'!AC18) -> 10.831404 | AH19: =(('Company Profile'!$E$10/10000000)+'Balance Sheet'!AD40+'Balance Sheet'!AD47-'Balance Sheet'!AD23)/('Income Statement'!AD23+'Income Statement'!AD15+'Income Statement'!AD17+'Income Statement'!AD18) -> 4.545706 | AI19: =(('Company Profile'!$E$10/10000000)+'Balance Sheet'!AE40+'Balance Sheet'!AE47-'Balance Sheet'!AE23)/('Income Statement'!AE23+'Income Statement'!AE15+'Income Statement'!AE17+'Income Statement'!AE18) -> 9.638493 | AK19: Valuation | AL19: EV/EBITDA | AM19: =(('Company Profile'!$F$10/10000000)+'Balance Sheet'!AH56+'Balance Sheet'!AH64-'Balance Sheet'!AH39)/(Table11[[#This Row],[2020]]+'Income Statement'!AH15+'Income Statement'!AH16) -> 6.8146081 | AN19: =(('Company Profile'!$F$10/10000000)+'Balance Sheet'!AI56+'Balance Sheet'!AI64-'Balance Sheet'!AI39)/(Table11[[#This Row],[2021]]+'Income Statement'!AI15+'Income Statement'!AI16) -> 7.1964971 | AO19: =(('Company Profile'!$F$10/10000000)+'Balance Sheet'!AJ56+'Balance Sheet'!AJ64-'Balance Sheet'!AJ39)/(Table11[[#This Row],[2022]]+'Income Statement'!AJ15+'Income Statement'!AJ16) -> 4.8105557 | AP19: =(('Company Profile'!$F$10/10000000)+'Balance Sheet'!AK56+'Balance Sheet'!AK64-'Balance Sheet'!AK39)/(Table11[[#This Row],[2023]]+'Income Statement'!AK15+'Income Statement'!AK16) -> 5.3087878 | AQ19: =(('Company Profile'!$F$10/10000000)+'Balance Sheet'!AL56+'Balance Sheet'!AL64-'Balance Sheet'!AL39)/(Table11[[#This Row],[2024]]+'Income Statement'!AL15+'Income Statement'!AL16) -> 4.1150545 | AR19: =(('Company Profile'!$F$10/10000000)+'Balance Sheet'!AM56+'Balance Sheet'!AM64-'Balance Sheet'!AM39)/(Table11[[#This Row],[2025]]+'Income Statement'!AM15+'Income Statement'!AM16) -> 4.6050025 | AT19: Valuation | AU19: EV/EBITDA | AV19: =(('Company Profile'!$G$10/10000000)+'Balance Sheet'!AP32+'Balance Sheet'!AP40-'Balance Sheet'!AP20)/('Income Statement'!AP21+'Income Statement'!AP17+'Income Statement'!AP18) -> 33.827078 | AW19: =(('Company Profile'!$G$10/10000000)+'Balance Sheet'!AQ32+'Balance Sheet'!AQ40-'Balance Sheet'!AQ20)/('Income Statement'!AQ21+'Income Statement'!AQ17+'Income Statement'!AQ18) -> 45.289043 | AX19: =(('Company Profile'!$G$10/10000000)+'Balance Sheet'!AR32+'Balance Sheet'!AR40-'Balance Sheet'!AR20)/('Income Statement'!AR21+'Income Statement'!AR17+'Income Statement'!AR18) -> 33.874643 | AY19: =(('Company Profile'!$G$10/10000000)+'Balance Sheet'!AS32+'Balance Sheet'!AS40-'Balance Sheet'!AS20)/('Income Statement'!AS21+'Income Statement'!AS17+'Income Statement'!AS18) -> 28.816512 | AZ19: =(('Company Profile'!$G$10/10000000)+'Balance Sheet'!AT32+'Balance Sheet'!AT40-'Balance Sheet'!AT20)/('Income Statement'!AT21+'Income Statement'!AT17+'Income Statement'!AT18) -> 24.801095 | BA19: =(('Company Profile'!$G$10/10000000)+'Balance Sheet'!AU32+'Balance Sheet'!AU40-'Balance Sheet'!AU20)/('Income Statement'!AU21+'Income Statement'!AU17+'Income Statement'!AU18) -> 28.537694
A20: Valuation | B20: P/E | C20: =C23/('Income Statement'!B27/('Company Profile'!$B$8/10000000)) -> 25.639509 | D20: =D23/('Income Statement'!C27/('Company Profile'!$B$8/10000000)) -> 4.9829193 | E20: =E23/('Income Statement'!D27/('Company Profile'!$B$8/10000000)) -> 7.3412131 | F20: =F23/('Income Statement'!E27/('Company Profile'!$B$8/10000000)) -> 40.065227 | G20: =G23/('Income Statement'!F27/('Company Profile'!$B$8/10000000)) -> 5.1622435 | H20: =H23/('Income Statement'!G27/('Company Profile'!$B$8/10000000)) -> 13.838403 | J20: Valuation | K20: P/E | L20: =L23/('Income Statement'!J27/('Company Profile'!$C$8/10000000)) -> 3.7268259 | M20: =M23/('Income Statement'!K27/('Company Profile'!$C$8/10000000)) -> 9.9041182 | N20: =N23/('Income Statement'!L27/('Company Profile'!$C$8/10000000)) -> 5.7768817 | O20: =O23/('Income Statement'!M27/('Company Profile'!$C$8/10000000)) -> 12.3914 | P20: =P23/('Income Statement'!N27/('Company Profile'!$C$8/10000000)) -> 13.352256 | Q20: =Q23/('Income Statement'!O27/('Company Profile'!$C$8/10000000)) -> 9.5765143 | S20: Valuation | T20: P/E | U20: =U23/('Income Statement'!R30/('Company Profile'!$D$8/10000000)) -> 12.350306 | V20: =V23/('Income Statement'!S30/('Company Profile'!$D$8/10000000)) -> 3.1609363 | W20: =W23/('Income Statement'!T30/('Company Profile'!$D$8/10000000)) -> 3.8247743 | X20: =X23/('Income Statement'!U30/('Company Profile'!$D$8/10000000)) -> -4.5725349 | Y20: =Y23/('Income Statement'!V30/('Company Profile'!$D$8/10000000)) -> 4.2362181 | Z20: =Z23/('Income Statement'!W30/('Company Profile'!$D$8/10000000)) -> 15.217013 | AB20: Valuation | AC20: P/E | AD20: =AD23/('Income Statement'!Z32/('Company Profile'!$E$8/10000000)) -> -39.887957 | AE20: =AE23/('Income Statement'!AA32/('Company Profile'!$E$8/10000000)) -> 4.0354335 | AF20: =AF23/('Income Statement'!AB32/('Company Profile'!$E$8/10000000)) -> 4.6453109 | AG20: =AG23/('Income Statement'!AC32/('Company Profile'!$E$8/10000000)) -> 9.3745384 | AH20: =AH23/('Income Statement'!AD32/('Company Profile'!$E$8/10000000)) -> 5.566879 | AI20: =AI23/('Income Statement'!AE32/('Company Profile'!$E$8/10000000)) -> 17.307412 | AK20: Valuation | AL20: P/E | AM20: =AM23/('Income Statement'!AH29/('Company Profile'!$F$8/10000000)) -> 8.4884223 | AN20: =AN23/('Income Statement'!AI29/('Company Profile'!$F$8/10000000)) -> 6.5131045 | AO20: =AO23/('Income Statement'!AJ29/('Company Profile'!$F$8/10000000)) -> 4.3615194 | AP20: =AP23/('Income Statement'!AK29/('Company Profile'!$F$8/10000000)) -> 5.7801361 | AQ20: =AQ23/('Income Statement'!AL29/('Company Profile'!$F$8/10000000)) -> 6.0473855 | AR20: =AR23/('Income Statement'!AM29/('Company Profile'!$F$8/10000000)) -> 8.2514925 | AT20: Valuation | AU20: P/E | AV20: =AV23/('Income Statement'!AP28/('Company Profile'!$G$8/10000000)) -> 23.369956 | AW20: =AW23/('Income Statement'!AQ28/('Company Profile'!$G$8/10000000)) -> 42.826987 | AX20: =AX23/('Income Statement'!AR28/('Company Profile'!$G$8/10000000)) -> 46.652406 | AY20: =AY23/('Income Statement'!AS28/('Company Profile'!$G$8/10000000)) -> 36.82974 | AZ20: =AZ23/('Income Statement'!AT28/('Company Profile'!$G$8/10000000)) -> 47.238411 | BA20: =BA23/('Income Statement'!AU28/('Company Profile'!$G$8/10000000)) -> 57.15397
A21: Valuation | B21: P/B | C21: =C23/('Balance Sheet'!B37/('Company Profile'!$B$8/10000000)) -> 2.0712617 | D21: =D23/('Balance Sheet'!C37/('Company Profile'!$B$8/10000000)) -> 1.771692 | E21: =E23/('Balance Sheet'!D37/('Company Profile'!$B$8/10000000)) -> 1.6071627 | F21: =F23/('Balance Sheet'!E37/('Company Profile'!$B$8/10000000)) -> 1.3999006 | G21: =G23/('Balance Sheet'!F37/('Company Profile'!$B$8/10000000)) -> 1.7242714 | H21: =H23/('Balance Sheet'!G37/('Company Profile'!$B$8/10000000)) -> 1.9465786 | J21: Valuation | K21: P/B | L21: =L23/('Balance Sheet'!J35/('Company Profile'!$C$8/10000000)) -> 0.71845199 | M21: =M23/('Balance Sheet'!K35/('Company Profile'!$C$8/10000000)) -> 1.1418808 | N21: =N23/('Balance Sheet'!L35/('Company Profile'!$C$8/10000000)) -> 1.1052967 | O21: =O23/('Balance Sheet'!M35/('Company Profile'!$C$8/10000000)) -> 1.0649276 | P21: =P23/('Balance Sheet'!N35/('Company Profile'!$C$8/10000000)) -> 1.7128509 | Q21: =Q23/('Balance Sheet'!O35/('Company Profile'!$C$8/10000000)) -> 1.4001664 | S21: Valuation | T21: P/B | U21: =U23/('Balance Sheet'!R32/('Company Profile'!$D$8/10000000)) -> 0.84341974 | V21: =V23/('Balance Sheet'!S32/('Company Profile'!$D$8/10000000)) -> 0.88508286 | W21: =W23/('Balance Sheet'!T32/('Company Profile'!$D$8/10000000)) -> 1.0154953 | X21: =X23/('Balance Sheet'!U32/('Company Profile'!$D$8/10000000)) -> 0.98927806 | Y21: =Y23/('Balance Sheet'!V32/('Company Profile'!$D$8/10000000)) -> 1.4458531 | Z21: =Z23/('Balance Sheet'!W32/('Company Profile'!$D$8/10000000)) -> 2.0040797 | AB21: Valuation | AC21: P/B | AD21: =AD23/('Balance Sheet'!Z37/('Company Profile'!$E$8/10000000)) -> 0.77738987 | AE21: =AE23/('Balance Sheet'!AA37/('Company Profile'!$E$8/10000000)) -> 0.77844948 | AF21: =AF23/('Balance Sheet'!AB37/('Company Profile'!$E$8/10000000)) -> 0.88441513 | AG21: =AG23/('Balance Sheet'!AC37/('Company Profile'!$E$8/10000000)) -> 0.76613861 | AH21: =AH23/('Balance Sheet'!AD37/('Company Profile'!$E$8/10000000)) -> 1.2769403 | AI21: =AI23/('Balance Sheet'!AE37/('Company Profile'!$E$8/10000000)) -> 1.2493097 | AK21: Valuation | AL21: P/B | AM21: =AM23/('Balance Sheet'!AH53/('Company Profile'!$F$8/10000000)) -> 0.43508231 | AN21: =AN23/('Balance Sheet'!AI53/('Company Profile'!$F$8/10000000)) -> 0.57301704 | AO21: =AO23/('Balance Sheet'!AJ53/('Company Profile'!$F$8/10000000)) -> 0.75882759 | AP21: =AP23/('Balance Sheet'!AK53/('Company Profile'!$F$8/10000000)) -> 0.62889909 | AQ21: =AQ23/('Balance Sheet'!AL53/('Company Profile'!$F$8/10000000)) -> 0.92946467 | AR21: =AR23/('Balance Sheet'!AM53/('Company Profile'!$F$8/10000000)) -> 0.84510572 | AT21: Valuation | AU21: P/B | AV21: =AV23/('Balance Sheet'!AP29/('Company Profile'!$G$8/10000000)) -> 1.8460482 | AW21: =AW23/('Balance Sheet'!AQ29/('Company Profile'!$G$8/10000000)) -> 2.8832757 | AX21: =AX23/('Balance Sheet'!AR29/('Company Profile'!$G$8/10000000)) -> 3.7534486 | AY21: =AY23/('Balance Sheet'!AS29/('Company Profile'!$G$8/10000000)) -> 3.306877 | AZ21: =AZ23/('Balance Sheet'!AT29/('Company Profile'!$G$8/10000000)) -> 3.8555866 | BA21: =BA23/('Balance Sheet'!AU29/('Company Profile'!$G$8/10000000)) -> 3.7109401
A22: Valuation | B22: P/S | C22: =C23/('Income Statement'!B8/('Company Profile'!$B$8/10000000)) -> 0.20805431 | D22: =D23/('Income Statement'!C8/('Company Profile'!$B$8/10000000)) -> 0.30986343 | E22: =E23/('Income Statement'!D8/('Company Profile'!$B$8/10000000)) -> 0.19174904 | F22: =F23/('Income Statement'!E8/('Company Profile'!$B$8/10000000)) -> 0.13987822 | G22: =G23/('Income Statement'!F8/('Company Profile'!$B$8/10000000)) -> 0.2561046 | H22: =H23/('Income Statement'!G8/('Company Profile'!$B$8/10000000)) -> 0.31482476 | J22: Valuation | K22: P/S | L22: =L23/('Income Statement'!J8/('Company Profile'!$C$8/10000000)) -> 0.47844327 | M22: =M23/('Income Statement'!K8/('Company Profile'!$C$8/10000000)) -> 1.0391258 | N22: =N23/('Income Statement'!L8/('Company Profile'!$C$8/10000000)) -> 0.7557638 | O22: =O23/('Income Statement'!M8/('Company Profile'!$C$8/10000000)) -> 0.47100931 | P22: =P23/('Income Statement'!N8/('Company Profile'!$C$8/10000000)) -> 0.98303073 | Q22: =Q23/('Income Statement'!O8/('Company Profile'!$C$8/10000000)) -> 0.83137109 | S22: Valuation | T22: P/S | U22: =U23/('Income Statement'!R9/('Company Profile'!$D$8/10000000)) -> 0.090281719 | V22: =V23/('Income Statement'!S9/('Company Profile'!$D$8/10000000)) -> 0.12336032 | W22: =W23/('Income Statement'!T9/('Company Profile'!$D$8/10000000)) -> 0.11165584 | X22: =X23/('Income Statement'!U9/('Company Profile'!$D$8/10000000)) -> 0.068204626 | Y22: =Y23/('Income Statement'!V9/('Company Profile'!$D$8/10000000)) -> 0.14624578 | Z22: =Z23/('Income Statement'!W9/('Company Profile'!$D$8/10000000)) -> 0.21863207 | AB22: Valuation | AC22: P/S | AD22: =AD23/('Income Statement'!Z8/('Company Profile'!$E$8/10000000)) -> 0.12931464 | AE22: =AE23/('Income Statement'!AA8/('Company Profile'!$E$8/10000000)) -> 0.16767976 | AF22: =AF23/('Income Statement'!AB8/('Company Profile'!$E$8/10000000)) -> 0.16153818 | AG22: =AG23/('Income Statement'!AC8/('Company Profile'!$E$8/10000000)) -> 0.11481898 | AH22: =AH23/('Income Statement'!AD8/('Company Profile'!$E$8/10000000)) -> 0.2714721 | AI22: =AI23/('Income Statement'!AE8/('Company Profile'!$E$8/10000000)) -> 0.27657372 | AK22: Valuation | AL22: P/S | AM22: =AM23/('Income Statement'!AH8/('Company Profile'!$F$8/10000000)) -> 0.22404845 | AN22: =AN23/('Income Statement'!AI8/('Company Profile'!$F$8/10000000)) -> 0.37581468 | AO22: =AO23/('Income Statement'!AJ8/('Company Profile'!$F$8/10000000)) -> 0.39871091 | AP22: =AP23/('Income Statement'!AK8/('Company Profile'!$F$8/10000000)) -> 0.27342779 | AQ22: =AQ23/('Income Statement'!AL8/('Company Profile'!$F$8/10000000)) -> 0.50249144 | AR22: =AR23/('Income Statement'!AM8/('Company Profile'!$F$8/10000000)) -> 0.46809071 | AT22: Valuation | AU22: P/S | AV22: =AV23/('Income Statement'!AP10/('Company Profile'!$G$8/10000000)) -> 1.9763553 | AW22: =AW23/('Income Statement'!AQ10/('Company Profile'!$G$8/10000000)) -> 4.8879201 | AX22: =AX23/('Income Statement'!AR10/('Company Profile'!$G$8/10000000)) -> 3.8656737 | AY22: =AY23/('Income Statement'!AS10/('Company Profile'!$G$8/10000000)) -> 2.8648239 | AZ22: =AZ23/('Income Statement'!AT10/('Company Profile'!$G$8/10000000)) -> 3.5459804 | BA22: =BA23/('Income Statement'!AU10/('Company Profile'!$G$8/10000000)) -> 3.6717338
A23: Market Price | B23: CMP | C23: 158.57 | D23: 218.7 | E23: 192.28 | F23: 172.7 | G23: 300.6 | H23: ='Company Profile'!B7 -> 365.15 | J23: Market Price | K23: CMP | L23: 53.93 | M23: 92.53 | N23: 108.1 | O23: 105.45 | P23: 201.1 | Q23: ='Company Profile'!C7 -> 181.52 | S23: Market Price | T23: CMP | U23: 122.8 | V23: 158.4 | W23: 197.6 | X23: 150 | Y23: 318.83 | Z23: ='Company Profile'!D7 -> 481.7 | AB23: Market Price | AC23: CMP | AD23: 53 | AE23: 62.19 | AF23: 84.63 | AG23: 77.7 | AH23: 170.15 | AI23: ='Company Profile'!E7 -> 169 | AK23: Market Price | AL23: CMP | AM23: 77.3 | AN23: 110.5 | AO23: 170.9 | AP23: 150.6 | AQ23: 265.7 | AR23: ='Company Profile'!F7 -> 251.4 | AT23: Market Price | AU23: CMP | AV23: 533.67 | AW23: 1010.93 | AX23: 1307.83 | AY23: 1170.72 | AZ23: 1467.55 | BA23: ='Company Profile'!G7 -> 1489.25
A24: Valuation | B24: EPS | C24: ='Income Statement'!B27/('Company Profile'!$B$8/10000000) -> 6.1845958 | D24: ='Income Statement'!C27/('Company Profile'!$B$8/10000000) -> 43.889934 | E24: ='Income Statement'!D27/('Company Profile'!$B$8/10000000) -> 26.191856 | F24: ='Income Statement'!E27/('Company Profile'!$B$8/10000000) -> 4.310471 | G24: ='Income Statement'!F27/('Company Profile'!$B$8/10000000) -> 58.230496 | H24: ='Income Statement'!G27/('Company Profile'!$B$8/10000000) -> 26.386716 | J24: Valuation | K24: EPS | L24: {='Income Statement'!J27/'Company Profile'!$C$9} -> 14.470759 | M24: {='Income Statement'!K27/'Company Profile'!$C$9} -> 9.3425783 | N24: {='Income Statement'!L27/'Company Profile'!$C$9} -> 18.712518 | O24: {='Income Statement'!M27/'Company Profile'!$C$9} -> 8.5099345 | P24: {='Income Statement'!N27/'Company Profile'!$C$9} -> 15.061125 | Q24: {='Income Statement'!O27/'Company Profile'!$C$9} -> 18.954705 | S24: Valuation | T24: EPS | U24: ='Income Statement'!R30/'Company Profile'!$D$9 -> 9.9430733 | V24: ='Income Statement'!S30/'Company Profile'!$D$9 -> 50.111734 | W24: ='Income Statement'!T30/'Company Profile'!$D$9 -> 51.663179 | X24: ='Income Statement'!U30/'Company Profile'!$D$9 -> -32.804561 | Y24: ='Income Statement'!V30/'Company Profile'!$D$9 -> 75.262886 | Z24: ='Income Statement'!W30/'Company Profile'!$D$9 -> 31.655359 | AB24: Valuation | AC24: EPS | AD24: ='Income Statement'!Z32/'Company Profile'!$E$9 -> -1.3287218 | AE24: ='Income Statement'!AA32/'Company Profile'!$E$9 -> 15.410984 | AF24: ='Income Statement'!AB32/'Company Profile'!$E$9 -> 18.218372 | AG24: ='Income Statement'!AC32/'Company Profile'!$E$9 -> 8.2884081 | AH24: ='Income Statement'!AD32/'Company Profile'!$E$9 -> 30.564703 | AI24: ='Income Statement'!AE32/'Company Profile'!$E$9 -> 9.7646028 | AK24: Valuation | AL24: EPS | AM24: ='Income Statement'!AH29/'Company Profile'!$F$9 -> 9.1065215 | AN24: ='Income Statement'!AI29/'Company Profile'!$F$9 -> 16.965796 | AO24: ='Income Statement'!AJ29/'Company Profile'!$F$9 -> 39.183593 | AP24: ='Income Statement'!AK29/'Company Profile'!$F$9 -> 26.05475 | AQ24: ='Income Statement'!AL29/'Company Profile'!$F$9 -> 43.936342 | AR24: ='Income Statement'!AM29/'Company Profile'!$F$9 -> 30.467215 | AT24: Valuation | AU24: EPS | AV24: ='Income Statement'!AP28/'Company Profile'!$G$9 -> 22.83573 | AW24: ='Income Statement'!AQ28/'Company Profile'!$G$9 -> 23.604976 | AX24: ='Income Statement'!AR28/'Company Profile'!$G$9 -> 28.033495 | AY24: ='Income Statement'!AS28/'Company Profile'!$G$9 -> 31.787354 | AZ24: ='Income Statement'!AT28/'Company Profile'!$G$9 -> 31.066879 | BA24: ='Income Statement'!AU28/'Company Profile'!$G$9 -> 26.056807
A25: Valuation | B25: Market Cap | C25: =C23*'Company Profile'!$B$9 -> 68795.674 | D25: =D23*'Company Profile'!$B$9 -> 94883.104 | E25: =E23*'Company Profile'!$B$9 -> 83420.774 | F25: =F23*'Company Profile'!$B$9 -> 74925.981 | G25: =G23*'Company Profile'!$B$9 -> 130415.46 | H25: =H23*'Company Profile'!$B$9 -> 158420.51 | J25: Valuation | K25: Mcap | L25: =L23*'Company Profile'!$C$9 -> 35459.406 | M25: =M23*'Company Profile'!$C$9 -> 60839.215 | N25: =N23*'Company Profile'!$C$9 -> 71076.615 | O25: =O23*'Company Profile'!$C$9 -> 69334.219 | P25: =P23*'Company Profile'!$C$9 -> 132224.86 | Q25: =Q23*'Company Profile'!$C$9 -> 119350.85 | S25: Valuation | T25: Mcap | U25: =U23*'Company Profile'!$D$9 -> 26129.666 | V25: =V23*'Company Profile'!$D$9 -> 33704.716 | W25: =W23*'Company Profile'!$D$9 -> 42045.782 | X25: =X23*'Company Profile'!$D$9 -> 31917.345 | Y25: =Y23*'Company Profile'!$D$9 -> 67841.381 | Z25: =Z23*'Company Profile'!$D$9 -> 102497.23 | AB25: Valuation | AC25: Mcap | AD25: =AD23*'Company Profile'!$E$9 -> 74842.572 | AE25: =AE23*'Company Profile'!$E$9 -> 87819.992 | AF25: =AF23*'Company Profile'!$E$9 -> 119508.05 | AG25: =AG23*'Company Profile'!$E$9 -> 109722.03 | AH25: =AH23*'Company Profile'!$E$9 -> 240272.9 | AI25: =AI23*'Company Profile'!$E$9 -> 238648.96 | AK25: Valuation | AL25: Mcap | AM25: =AM23*'Company Profile'!$F$9 -> 97245.564 | AN25: =AN23*'Company Profile'!$F$9 -> 139012.09 | AO25: =AO23*'Company Profile'!$F$9 -> 214996.99 | AP25: =AP23*'Company Profile'!$F$9 -> 189459.02 | AQ25: =AQ23*'Company Profile'!$F$9 -> 334258.04 | AR25: =AR23*'Company Profile'!$F$9 -> 316268.24 | AT25: Valuation | AU25: Mcap | AV25: =AV23*'Company Profile'!$G$9 -> 722201.74 | AW25: =AW23*'Company Profile'!$G$9 -> 1368065.3 | AX25: =AX23*'Company Profile'!$G$9 -> 1769852.3 | AY25: =AY23*'Company Profile'!$G$9 -> 1584304.9 | AZ25: =AZ23*'Company Profile'!$G$9 -> 1985997.3 | BA25: =BA23*'Company Profile'!$G$9 -> 2015363.3

Sheet WACC
A1: WACC
A3: Particulars | B3: #VALUE! | C3: #VALUE! | D3: #VALUE! | E3: #VALUE! | F3: #VALUE! | G3: #VALUE!
A4: Risk-Free rate | B4: 0.072 | C4: 0.072 | D4: 0.072 | E4: 0.072 | F4: 0.072 | G4: 0.072
A5: Beta | B5: ='Company Profile'!B12 -> 1.2921 | C5: ='Company Profile'!C12 -> 1.5484 | D5: ='Company Profile'!D12 -> 1.5872 | E5: ='Company Profile'!E12 -> 1.3211 | F5: ='Company Profile'!F12 -> 0.9935 | G5: ='Company Profile'!G12 -> 1.1399
A6: Market risk premium | B6: 0.0726 | C6: 0.0726 | D6: 0.0726 | E6: 0.0726 | F6: 0.0726 | G6: 0.0726
A7: Cost of Equity | B7: =B4+(B5*B6) -> 0.16580646 | C7: =C4+(C5*C6) -> 0.18441384 | D7: =D4+(D5*D6) -> 0.18723072 | E7: =E4+(E5*E6) -> 0.16791186 | F7: =F4+(F5*F6) -> 0.1441281 | G7: =G4+(G5*G6) -> 0.15475674
A8: Interest expense | B8: =AVERAGE('Income Statement'!G15) -> 3591.44 | C8: =AVERAGE('Income Statement'!O14) -> 747.99 | D8: =AVERAGE('Income Statement'!W16) -> 3365.48 | E8: =AVERAGE('Income Statement'!AE15) -> 9261.93 | F8: =AVERAGE('Income Statement'!AM15) -> 14534.947 | G8: =AVERAGE('Income Statement'!AU17) -> 10054
A9: Total Debt | B9: =(AVERAGE('Balance Sheet'!G39)+AVERAGE('Balance Sheet'!G47)) -> 51060.91 | C9: =(AVERAGE('Balance Sheet'!O37)+AVERAGE('Balance Sheet'!O46)) -> 16307.37 | D9: =(AVERAGE('Balance Sheet'!W34)+AVERAGE('Balance Sheet'!W42)) -> 66428.88 | E9: =(AVERAGE('Balance Sheet'!AE40)+AVERAGE('Balance Sheet'!AE47)) -> 142559.9 | F9: =(AVERAGE('Balance Sheet'!AM56)+AVERAGE('Balance Sheet'!AM64)) -> 153555.9 | G9: =(AVERAGE('Balance Sheet'!AU32)+AVERAGE('Balance Sheet'!AU40)) -> 198813
A10: Pre tax cost of debt | B10: =B8/B9 -> 0.070336388 | C10: =C8/C9 -> 0.045868218 | D10: =D8/D9 -> 0.050662904 | E10: =E8/E9 -> 0.06496869 | F10: =F8/F9 -> 0.094655735 | G10: =G8/G9 -> 0.050570134
A11: Tax expense | B11: ='Income Statement'!G26/'Income Statement'!G21 -> 0.29740132 | C11: ='Income Statement'!O26/'Income Statement'!O21 -> 0.22569276 | D11: ='Income Statement'!W29/'Income Statement'!W24 -> 0.25157891 | E11: ='Income Statement'!AE31/'Income Statement'!AE27 -> 0.19190844 | F11: ='Income Statement'!AM28/'Income Statement'!AM23 -> 0.2685084 | G11: ='Income Statement'!AU27/'Income Statement'!AU23 -> 0.23556191
A12: After tax Cost of debt | B12: =B10*(1-B11) -> 0.049418254 | C12: =C10*(1-C11) -> 0.035516093 | D12: =D10*(1-D11) -> 0.037917186 | E12: =E10*(1-E11) -> 0.052500651 | F12: =F10*(1-F11) -> 0.069239876 | G12: =G10*(1-G11) -> 0.038657736
A13: Market value of Equity | B13: ='Company Profile'!B10/10000000 -> 159288.2 | C13: ='Company Profile'!C10/10000000 -> 118660.5 | D13: ='Company Profile'!D10/10000000 -> 102039.7 | E13: ='Company Profile'!E10/10000000 -> 238874.9 | F13: ='Company Profile'!F10/10000000 -> 317274.7 | G13: ='Company Profile'!G10/10000000 -> 2000099
A14: Total Debt | B14: =B9 -> 51060.91 | C14: =C9 -> 16307.37 | D14: =D9 -> 66428.88 | E14: =E9 -> 142559.9 | F14: =F9 -> 153555.9 | G14: =G9 -> 198813
A15: Weight of Equity | B15: =B13/(B13+B14) -> 0.75725635 | C15: =C13/(C13+C14) -> 0.87917591 | D15: =D13/(D13+D14) -> 0.6056898 | E15: =E13/(E13+E14) -> 0.62625356 | F15: =F13/(F13+F14) -> 0.67386168 | G15: =G13/(G13+G14) -> 0.90958574
A16: Weight of Debt | B16: =B14/(B14+B13) -> 0.24274365 | C16: =C14/(C14+C13) -> 0.12082409 | D16: =D14/(D14+D13) -> 0.3943102 | E16: =E14/(E14+E13) -> 0.37374644 | F16: =F14/(F14+F13) -> 0.32613832 | G16: =G14/(G14+G13) -> 0.090414259
A17: WACC | B17: =(B15*B7)+(B16*B12) -> 0.13755396 | C17: =(C15*C7)+(C16*C12) -> 0.16642341 | D17: =(D15*D7)+(D16*D12) -> 0.12835487 | E17: =(E15*E7)+(E16*E12) -> 0.12477733 | F17: =(F15*F7)+(F16*F12) -> 0.11970418 | G17: =(G15*G7)+(G16*G12) -> 0.14425973
A18: Cash and Cash Equivalents | B18: ='Balance Sheet'!G24 -> 557.93 | C18: ='Balance Sheet'!O23 -> 1403.34 | D18: ='Balance Sheet'!W20 -> 166.22 | E18: ='Balance Sheet'!AE23 -> 673.17 | F18: ='Balance Sheet'!AM39 -> 4554.357 | G18: ='Balance Sheet'!AU20 -> 82471
A19: Terminal Growth | B19: 0.04 | C19: 0.04 | D19: 0.04 | E19: 0.04 | F19: 0.04 | G19: 0.04

Sheet FCFF
A1: FCFF
A3: #VALUE! | J3: #VALUE! | S3: #VALUE! | AB3: #VALUE! | AK3: #VALUE! | AT3: #VALUE!
A4: Particulars | B4: 2025 | C4: Ratio | D4: 2026 | E4: 2027 | F4: 2028 | G4: 2029 | H4: 2030 | J4: Particulars | K4: 2025 | L4: Ratio | M4: 2026 | N4: 2027 | O4: 2028 | P4: 2029 | Q4: 2030 | S4: Particulars | T4: 2025 | U4: Ratio | V4: 2026 | W4: 2027 | X4: 2028 | Y4: 2029 | Z4: 2030 | AB4: Particulars | AC4: 2025 | AD4: Ratio | AE4: 2026 | AF4: 2027 | AG4: 2028 | AH4: 2029 | AI4: 2030 | AK4: Particulars | AL4: 2025 | AM4: Ratio | AN4: 2026 | AO4: 2027 | AP4: 2028 | AQ4: 2029 | AR4: 2030 | AT4: Particulars | AU4: 2025 | AV4: Ratio | AW4: 2026 | AX4: 2027 | AY4: 2028 | AZ4: 2029 | BA4: 2030
A5: Revenue | B5: ='Income Statement'!G8 -> 503202.2 | C5: =('Income Statement'!G8/'Income Statement'!B8)^(1/6)-1 -> 0.07248943 | D5: =Table34[[#This Row],[2025]]*(1+C5) -> 539679.04 | E5: =Table34[[#This Row],[2026]]*(1+$C$5) -> 578800.07 | F5: =Table34[[#This Row],[2027]]*(1+$C$5) -> 620756.95 | G5: =Table34[[#This Row],[2028]]*(1+$C$5) -> 665755.27 | H5: =Table34[[#This Row],[2029]]*(1+$C$5) -> 714015.49 | J5: Revenue | K5: ='Income Statement'!O8 -> 143559.06 | L5: =('Income Statement'!O8/'Income Statement'!J8)^(1/6)-1 -> 0.11649024 | M5: =Table14[[#This Row],[2025]]*(1+L5) -> 160282.29 | N5: =Table14[[#This Row],[2026]]*(1+$L$5) -> 178953.61 | O5: =Table14[[#This Row],[2027]]*(1+$L$5) -> 199799.96 | P5: =Table14[[#This Row],[2028]]*(1+$L$5) -> 223074.71 | Q5: =Table14[[#This Row],[2029]]*(1+$L$5) -> 249060.73 | S5: Revenue | T5: ='Income Statement'!W9 -> 468811.53 | U5: =('Income Statement'!W9/'Income Statement'!R9)^(1/6)-1 -> 0.083704075 | V5: =Table1422[[#This Row],[2025]]*(1+U5) -> 508052.97 | W5: =Table1422[[#This Row],[2026]]*(1+$U$5) -> 550579.07 | X5: =Table1422[[#This Row],[2027]]*(1+$U$5) -> 596664.78 | Y5: =Table1422[[#This Row],[2028]]*(1+$U$5) -> 646608.05 | Z5: =Table1422[[#This Row],[2029]]*(1+$U$5) -> 700731.78 | AB5: Revenue | AC5: ='Income Statement'!AE8 -> 862876.46 | AD5: =('Income Statement'!AE8/'Income Statement'!Z8)^(1/6)-1 -> 0.068828282 | AE5: =Table142236[[#This Row],[2025]]*(1+AD5) -> 922266.76 | AF5: =Table142236[[#This Row],[2026]]*(1+$AD$5) -> 985744.8 | AG5: =Table142236[[#This Row],[2027]]*(1+$AD$5) -> 1053591.9 | AH5: =Table142236[[#This Row],[2028]]*(1+$AD$5) -> 1126108.8 | AI5: =Table142236[[#This Row],[2029]]*(1+$AD$5) -> 1203617 | AK5: Revenue | AL5: ='Income Statement'!AM8 -> 675655.88 | AM5: =('Income Statement'!AM8/'Income Statement'!AH8)^(1/6)-1 -> 0.076546893 | AN5: =Table14223640[[#This Row],[2025]]*(1+AM5) -> 727375.24 | AO5: =Table14223640[[#This Row],[2026]]*(1+$AM$5) -> 783053.56 | AP5: =Table14223640[[#This Row],[2027]]*(1+$AM$5) -> 842993.87 | AQ5: =Table14223640[[#This Row],[2028]]*(1+$AM$5) -> 907522.44 | AR5: =Table14223640[[#This Row],[2029]]*(1+$AM$5) -> 976990.46 | AT5: Revenue | AU5: ='Income Statement'!AU10 -> 548886 | AV5: =('Income Statement'!AU10/'Income Statement'!AP10)^(1/6)-1 -> 0.070158508 | AW5: =Table14223644[[#This Row],[2025]]*(1+$AV$5) -> 587395.02 | AX5: =Table14223644[[#This Row],[2026]]*(1+$AV$5) -> 628605.78 | AY5: =Table14223644[[#This Row],[2027]]*(1+$AV$5) -> 672707.83 | AZ5: =Table14223644[[#This Row],[2028]]*(1+$AV$5) -> 719904 | BA5: =Table14223644[[#This Row],[2029]]*(1+$AV$5) -> 770411.39
A6: EBIT | B6: ='Income Statement'!G19+'Income Statement'!G15 -> 20829.41 | C6: =(AVERAGE('Income Statement'!B19:G19)+AVERAGE('Income Statement'!B15:G15))/AVERAGE('Income Statement'!B8:G8) -> 0.040777198 | D6: =D5*$C$6 -> 22006.599 | E6: =E5*$C$6 -> 23601.845 | F6: =F5*$C$6 -> 25312.729 | G6: =G5*$C$6 -> 27147.635 | H6: =H5*$C$6 -> 29115.551 | J6: EBIT | K6: ='Income Statement'!O19+'Income Statement'!O14 -> 12900.23 | L6: =(AVERAGE('Income Statement'!J19:O19)+AVERAGE('Income Statement'!J14:O14))/AVERAGE('Income Statement'!J8:O8) -> 0.090849305 | M6: =M5*$L$6 -> 14561.535 | N6: =N5*$L$6 -> 16257.811 | O6: =O5*$L$6 -> 18151.688 | P6: =P5*$L$6 -> 20266.182 | Q6: =Q5*$L$6 -> 22626.995 | S6: EBIT | T6: ='Income Statement'!W20+'Income Statement'!W16 -> 12484.95 | U6: =(AVERAGE('Income Statement'!R20:W20)+AVERAGE('Income Statement'!R16:W16))/AVERAGE('Income Statement'!R9:W9) -> 0.021843348 | V6: =V5*$U$6 -> 11097.578 | W6: =W5*$U$6 -> 12026.49 | X6: =X5*$U$6 -> 13033.157 | Y6: =Y5*$U$6 -> 14124.085 | Z6: =Z5*$U$6 -> 15306.328 | AB6: EBIT | AC6: ='Income Statement'!AE23+'Income Statement'!AE15 -> 22726.93 | AD6: =(AVERAGE('Income Statement'!Z23:AE23)+AVERAGE('Income Statement'!Z15:AE15))/AVERAGE('Income Statement'!Z8:AE8) -> 0.041569806 | AE6: =AE5*$AD$6 -> 38338.45 | AF6: =AF5*$AD$6 -> 40977.22 | AG6: =AG5*$AD$6 -> 43797.612 | AH6: =AH5*$AD$6 -> 46812.126 | AI6: =AI5*$AD$6 -> 50034.124 | AK6: EBIT | AL6: ='Income Statement'!AM19+'Income Statement'!AM15 -> 66048.323 | AM6: =(AVERAGE('Income Statement'!AH19:AM19)+AVERAGE('Income Statement'!AH15:AM15))/AVERAGE('Income Statement'!AH8:AM8) -> 0.099881345 | AN6: =AN5*$AM$6 -> 72651.217 | AO6: =AO5*$AM$6 -> 78212.442 | AP6: =AP5*$AM$6 -> 84199.362 | AQ6: =AQ5*$AM$6 -> 90644.561 | AR6: =AR5*$AM$6 -> 97583.121 | AT6: EBIT | AU6: ='Income Statement'!AU21+'Income Statement'!AU17 -> 56182 | AV6: =(AVERAGE('Income Statement'!AP21:AU21)+AVERAGE('Income Statement'!AP17:AU17))/AVERAGE('Income Statement'!AP10:AU10) -> 0.12366471 | AW6: =AW5*$AV$6 -> 72640.033 | AX6: =AX5*$AV$6 -> 77736.349 | AY6: =AY5*$AV$6 -> 83190.216 | AZ6: =AZ5*$AV$6 -> 89026.717 | BA6: =BA5*$AV$6 -> 95272.699
A7: Tax expense | B7: ='Income Statement'!G26 -> 4845.75 | C7: =WACC!B11 -> 0.29740132 | D7: =D6*$C$7 -> 6544.7916 | E7: =E6*$C$7 -> 7019.2198 | F7: =F6*$C$7 -> 7528.0391 | G7: =G6*$C$7 -> 8073.7423 | H7: =H6*$C$7 -> 8659.0033 | J7: Tax expense | K7: ='Income Statement'!O26 -> 3632.64 | L7: =WACC!C11 -> 0.22569276 | M7: =M6*$L$7 -> 3286.4329 | N7: =N6*$L$7 -> 3669.2702 | O7: =O6*$L$7 -> 4096.7044 | P7: =P6*$L$7 -> 4573.9305 | Q7: =Q6*$L$7 -> 5106.7488 | S7: Tax expense | T7: =T6*Table1422[[#This Row],[Ratio]] -> 3140.9501 | U7: =WACC!D11 -> 0.25157891 | V7: =V6*$U$7 -> 2791.9166 | W7: =W6*$U$7 -> 3025.6114 | X7: =X6*$U$7 -> 3278.8674 | Y7: =Y6*$U$7 -> 3553.3219 | Z7: =Z6*$U$7 -> 3850.7494 | AB7: Tax expense | AC7: =AC6*Table142236[[#This Row],[Ratio]] -> 4361.4896 | AD7: =WACC!E11 -> 0.19190844 | AE7: =AE6*$AD$7 -> 7357.472 | AF7: =AF6*$AD$7 -> 7863.8742 | AG7: =AG6*$AD$7 -> 8405.1311 | AH7: =AH6*$AD$7 -> 8983.6419 | AI7: =AI6*$AD$7 -> 9601.9705 | AK7: Tax expense | AL7: =Table14223640[[#This Row],[Ratio]]*AL6 -> 17734.529 | AM7: =WACC!F11 -> 0.2685084 | AN7: =AN6*$AM$7 -> 19507.462 | AO7: =AO6*$AM$7 -> 21000.697 | AP7: =AP6*$AM$7 -> 22608.236 | AQ7: =AQ6*$AM$7 -> 24338.826 | AR7: =AR6*$AM$7 -> 26201.887 | AT7: Tax expense | AU7: =AU6*Table14223644[[#This Row],[Ratio]] -> 13234.339 | AV7: =WACC!G11 -> 0.23556191 | AW7: =AW6*$AV$7 -> 17111.225 | AX7: =AX6*$AV$7 -> 18311.723 | AY7: =AY6*$AV$7 -> 19596.446 | AZ7: =AZ6*$AV$7 -> 20971.304 | BA7: =BA6*$AV$7 -> 22442.619
A8: NOPAT | B8: =B6-B7 -> 15983.66 | D8: =D6-D7 -> 15461.808 | E8: =E6-E7 -> 16582.625 | F8: =F6-F7 -> 17784.69 | G8: =G6-G7 -> 19073.892 | H8: =H6-H7 -> 20456.548 | J8: NOPAT | K8: =K6-K7 -> 9267.59 | M8: =M6-M7 -> 11275.102 | N8: =N6-N7 -> 12588.541 | O8: =O6-O7 -> 14054.983 | P8: =P6-P7 -> 15692.252 | Q8: =Q6-Q7 -> 17520.246 | S8: NOPAT | T8: =T6-T7 -> 9343.9999 | V8: =V6-V7 -> 8305.6614 | W8: =W6-W7 -> 9000.8791 | X8: =X6-X7 -> 9754.2893 | Y8: =Y6-Y7 -> 10570.763 | Z8: =Z6-Z7 -> 11455.579 | AB8: NOPAT | AC8: =AC6-AC7 -> 18365.44 | AE8: =AE6-AE7 -> 30980.978 | AF8: =AF6-AF7 -> 33113.346 | AG8: =AG6-AG7 -> 35392.48 | AH8: =AH6-AH7 -> 37828.484 | AI8: =AI6-AI7 -> 40432.154 | AK8: NOPAT | AL8: =AL6-AL7 -> 48313.794 | AN8: =AN6-AN7 -> 53143.755 | AO8: =AO6-AO7 -> 57211.745 | AP8: =AP6-AP7 -> 61591.126 | AQ8: =AQ6-AQ7 -> 66305.736 | AR8: =AR6-AR7 -> 71381.234 | AT8: NOPAT | AU8: =AU6-AU7 -> 42947.661 | AW8: =AW6-AW7 -> 55528.808 | AX8: =AX6-AX7 -> 59424.626 | AY8: =AY6-AY7 -> 63593.769 | AZ8: =AZ6-AZ7 -> 68055.413 | BA8: =BA6-BA7 -> 72830.079
A9: Depreciation | B9: ='Income Statement'!G16 -> 7256.69 | C9: =AVERAGE('Income Statement'!B16:G16)/AVERAGE('Income Statement'!B8:G8) -> 0.012808478 | D9: =D5*$C$9 -> 6912.4673 | E9: =E5*$C$9 -> 7413.5481 | F9: =F5*$C$9 -> 7950.952 | G9: =G5*$C$9 -> 8527.312 | H9: =H5*$C$9 -> 9145.452 | J9: Depreciation | K9: ='Income Statement'!O15 -> 3799.23 | L9: =AVERAGE('Income Statement'!J15:O15)/AVERAGE('Income Statement'!J8:O8) -> 0.02583973 | M9: =M5*$L$9 -> 4141.651 | N9: =N5*$L$9 -> 4624.113 | O9: =O5*$L$9 -> 5162.777 | P9: =P5*$L$9 -> 5764.1902 | Q9: =Q5*$L$9 -> 6435.6621 | S9: Depreciation | T9: ='Income Statement'!W17 -> 6154.1 | U9: =AVERAGE('Income Statement'!R17:W17)/AVERAGE(Table9[[#This Row],[2020]:[2025]]) -> 0.011670025 | V9: =V5*$U$9 -> 5928.9906 | W9: =W5*$U$9 -> 6425.2712 | X9: =X5*$U$9 -> 6963.0926 | Y9: =Y5*$U$9 -> 7545.9319 | Z9: =Z5*$U$9 -> 8177.5571 | AB9: Depreciation | AC9: ='Income Statement'!AE17+'Income Statement'!AE18 -> 16777.34 | AD9: =(AVERAGE('Income Statement'!Z17:AE17)+AVERAGE('Income Statement'!Z18:AE18))/AVERAGE('Income Statement'!Z8:AE8) -> 0.017463518 | AE9: =AE5*$AD$9 -> 16106.022 | AF9: =AF5*$AD$9 -> 17214.572 | AG9: =AG5*$AD$9 -> 18399.422 | AH9: =AH5*$AD$9 -> 19665.822 | AI9: =AI5*$AD$9 -> 21019.387 | AK9: Depreciation | AL9: ='Income Statement'!AM16 -> 35205.965 | AM9: =AVERAGE('Income Statement'!AH16:AM16)/AVERAGE('Income Statement'!AH8:AM8) -> 0.050122425 | AN9: =AN5*$AM$9 -> 36457.811 | AO9: =AO5*$AM$9 -> 39248.543 | AP9: =AP5*$AM$9 -> 42252.897 | AQ9: =AQ5*$AM$9 -> 45487.225 | AR9: =AR5*$AM$9 -> 48969.131 | AT9: Depreciation | AU9: =AU5*Table14223644[[#This Row],[Ratio]] -> 17655.626 | AV9: =AVERAGE('Income Statement'!AT18:AU18)/AVERAGE('Income Statement'!AT10:AU10) -> 0.03216629 | AW9: =AW5*$AV$9 -> 18894.318 | AX9: =AX5*$AV$9 -> 20219.916 | AY9: =AY5*$AV$9 -> 21638.515 | AZ9: =AZ5*$AV$9 -> 23156.641 | BA9: =BA5*$AV$9 -> 24781.276
A10: CapEx | B10: =ABS('Cash Flow Statement'!G6) -> 13342.56 | C10: =(ABS(AVERAGE('Cash Flow Statement'!B6:G6))/AVERAGE('Income Statement'!B8:G8)) -> 0.019250693 | D10: =D5*$C$10 -> 10389.195 | E10: =E5*$C$10 -> 11142.302 | F10: =F5*$C$10 -> 11950.001 | G10: =G5*$C$10 -> 12816.25 | H10: =H5*$C$10 -> 13745.293 | J10: CapEx | K10: =ABS('Cash Flow Statement'!O6) -> 7929.71 | L10: =ABS(AVERAGE('Cash Flow Statement'!O6)/AVERAGE('Income Statement'!J8:O8)) -> 0.07297519 | M10: =M5*$L$10 -> 11696.631 | N10: =N5*$L$10 -> 13059.174 | O10: =O5*$L$10 -> 14580.44 | P10: =P5*$L$10 -> 16278.919 | Q10: =Q5*$L$10 -> 18175.254 | S10: CapEx | T10: =ABS('Cash Flow Statement'!W6) -> 9579.33 | U10: =ABS(AVERAGE('Cash Flow Statement'!U6:W6))/AVERAGE('Income Statement'!U9:W9) -> 0.020773946 | V10: =V5*$U$10 -> 10554.265 | W10: =W5*$U$10 -> 11437.7 | X10: =X5*$U$10 -> 12395.082 | Y10: =Y5*$U$10 -> 13432.601 | Z10: =Z5*$U$10 -> 14556.964 | AB10: CapEx | AC10: =ABS('Cash Flow Statement'!AE6) -> 5105.48 | AD10: =ABS(AVERAGE('Cash Flow Statement'!AA6:AE6))/AVERAGE('Income Statement'!Z8:AE8) -> 0.0071885058 | AE10: =AE5*$AD$10 -> 6629.72 | AF10: =AF5*$AD$10 -> 7086.0322 | AG10: =AG5*$AD$10 -> 7573.7517 | AH10: =AH5*$AD$10 -> 8095.04 | AI10: =AI5*$AD$10 -> 8652.2077 | AK10: CapEx | AL10: =ABS('Cash Flow Statement'!AM6) -> 41030.802 | AM10: =ABS(AVERAGE('Cash Flow Statement'!AH6:AM6))/AVERAGE('Income Statement'!AH8:AM8) -> 0.066334641 | AN10: =AN5*$AM$10 -> 48250.176 | AO10: =AO5*$AM$10 -> 51943.577 | AP10: =AP5*$AM$10 -> 55919.696 | AQ10: =AQ5*$AM$10 -> 60200.175 | AR10: =AR5*$AM$10 -> 64808.312 | AT10: CapEx | AU10: =ABS('Cash Flow Statement'!AU6) -> 37304 | AV10: =ABS(AVERAGE('Cash Flow Statement'!AS6:AU6))/AVERAGE(Table12[[#This Row],[2023]:[2025]]) -> 0.060250569 | AW10: =AW5*$AV$10 -> 35390.884 | AX10: =AX5*$AV$10 -> 37873.856 | AY10: =AY5*$AV$10 -> 40531.029 | AZ10: =AZ5*$AV$10 -> 43374.626 | BA10: =BA5*$AV$10 -> 46417.725
A11: Δ in Working capital | B11: =(('Balance Sheet'!G31-'Balance Sheet'!G56)-('Balance Sheet'!F31-'Balance Sheet'!F56)) -> -2650.51 | C11: =AVERAGE('Balance Sheet'!D60:G60)/AVERAGE('Income Statement'!D8:G8) -> -0.036773652 | D11: {=Table36[2026]-'Balance Sheet'!G60} -> -2006.1894 | E11: {=Table36[2027]-Table36[2026]} -> -1438.623 | F11: {=Table36[2028]-Table36[2027]} -> -1542.908 | G11: {=Table36[2029]-Table36[2028]} -> -1654.7525 | H11: {=Table36[2030]-Table36[2029]} -> -1774.7046 | J11: Δ in Working capital | K11: ='Balance Sheet'!O58-'Balance Sheet'!N58 -> 970.92 | L11: =(AVERAGE('Balance Sheet'!J58:O58))/AVERAGE('Income Statement'!J8:O8) -> -0.0064993087 | M11: {=Table3618[2026]-'Balance Sheet'!O58} -> -643.91408 | N11: {=Table3618[2027]-Table3618[2026]} -> -121.35069 | O11: {=Table3618[2028]-Table3618[2027]} -> -135.48686 | P11: {=Table3618[2029]-Table3618[2028]} -> -151.26976 | Q11: {=Table3618[2030]-Table3618[2029]} -> -168.89121 | S11: Δ in Working capital | T11: ='Balance Sheet'!W54-'Balance Sheet'!V54 -> -5073.85 | U11: =AVERAGE('Balance Sheet'!U54:W54)/AVERAGE('Income Statement'!R9:W9) -> -0.087151536 | V11: {=Table361846[2026]-'Balance Sheet'!W54} -> -5704.7161 | W11: {=Table361846[2027]-Table361846[2026]} -> -3706.2152 | X11: {=Table361846[2028]-Table361846[2027]} -> -4016.4405 | Y11: {=Table361846[2029]-Table361846[2028]} -> -4352.633 | Z11: {=Table361846[2030]-Table361846[2029]} -> -4716.9661 | AB11: Δ in Working capital | AC11: ='Balance Sheet'!AE59-'Balance Sheet'!AD59 -> -15013.74 | AD11: =AVERAGE('Balance Sheet'!Z59:AE59)/AVERAGE('Income Statement'!Z8:AE8) -> -0.070703316 | AE11: {=Table36184648[2026]-'Balance Sheet'!AE59} -> 7748.9617 | AF11: {=Table36184648[2027]-Table36184648[2026]} -> -4488.1077 | AG11: {=Table36184648[2028]-Table36184648[2027]} -> -4797.0164 | AH11: {=Table36184648[2029]-Table36184648[2028]} -> -5127.1868 | AI11: {=Table36184648[2030]-Table36184648[2029]} -> -5480.0823 | AK11: Δ in Working capital | AL11: ='Balance Sheet'!AM75-'Balance Sheet'!AL75 -> -791.025 | AM11: =AVERAGE('Balance Sheet'!AK75:AM75)/AVERAGE('Income Statement'!AK8:AM8) -> -0.045774046 | AN11: {=Table3618464850[2026]-'Balance Sheet'!AM75} -> 2003.058 | AO11: {=Table3618464850[2027]-Table3618464850[2026]} -> -2548.6218 | AP11: {=Table3618464850[2028]-Table3618464850[2027]} -> -2743.7108 | AQ11: {=Table3618464850[2029]-Table3618464850[2028]} -> -2953.7334 | AR11: {=Table3618464850[2030]-Table3618464850[2029]} -> -3179.8325 | AT11: Δ in Working capital | AU11: ='Balance Sheet'!AU50-'Balance Sheet'!AT50 -> -10983 | AV11: =AVERAGE('Balance Sheet'!AS50:AU50)/AVERAGE('Income Statement'!AS10:AU10) -> 0.0036607027 | AW11: {=Table361846485052[2026]-'Balance Sheet'!AU50} -> -9477.7215 | AX11: {=Table361846485052[2027]-'Balance Sheet'!AV50} -> 2301.1389 | AY11: {=Table361846485052[2028]-'Balance Sheet'!AW50} -> 2462.5833 | AZ11: {=Table361846485052[2029]-'Balance Sheet'!AX50} -> 2635.3545 | BA11: {=Table361846485052[2030]-'Balance Sheet'!AY50} -> 2820.2471
A12: FCFF | B12: =B8+B9-B10-B11 -> 12548.3 | D12: =D8+D9-D10-D11 -> 13991.269 | E12: =E8+E9-E10-E11 -> 14292.494 | F12: =F8+F9-F10-F11 -> 15328.549 | G12: =G8+G9-G10-G11 -> 16439.707 | H12: =H8+H9-H10-H11 -> 17631.412 | J12: FCFF | K12: =K8+K9-K10-K11 -> 4166.19 | M12: =M8+M9-M10-M11 -> 4364.0363 | N12: =N8+N9-N10-N11 -> 4274.8309 | O12: =O8+O9-O10-O11 -> 4772.807 | P12: =P8+P9-P10-P11 -> 5328.7924 | Q12: =Q8+Q9-Q10-Q11 -> 5949.5447 | S12: FCFF | T12: =T8+T9-T10-T11 -> 10992.62 | V12: =V8+V9-V10-V11 -> 9385.103 | W12: =W8+W9-W10-W11 -> 7694.6655 | X12: =X8+X9-X10-X11 -> 8338.7403 | Y12: =Y8+Y9-Y10-Y11 -> 9036.7269 | Z12: =Z8+Z9-Z10-Z11 -> 9793.1378 | AB12: FCFF | AC12: =AC8+AC9-AC10-AC11 -> 45051.04 | AE12: =AE8+AE9-AE10-AE11 -> 32708.319 | AF12: =AF8+AF9-AF10-AF11 -> 47729.993 | AG12: =AG8+AG9-AG10-AG11 -> 51015.167 | AH12: =AH8+AH9-AH10-AH11 -> 54526.453 | AI12: =AI8+AI9-AI10-AI11 -> 58279.415 | AK12: FCFF | AL12: =AL8+AL9-AL10-AL11 -> 43279.982 | AN12: =AN8+AN9-AN10-AN11 -> 39348.333 | AO12: =AO8+AO9-AO10-AO11 -> 47065.333 | AP12: =AP8+AP9-AP10-AP11 -> 50668.038 | AQ12: =AQ8+AQ9-AQ10-AQ11 -> 54546.519 | AR12: =AR8+AR9-AR10-AR11 -> 58721.885 | AT12: FCFF | AU12: =AU8+AU9-AU10-AU11 -> 34282.287 | AV12: =AV8+AV9-AV10-AV11 -> -0.031744982 | AW12: =AW8+AW9-AW10-AW11 -> 48509.963 | AX12: =AX8+AX9-AX10-AX11 -> 39469.547 | AY12: =AY8+AY9-AY10-AY11 -> 42238.671 | AZ12: =AZ8+AZ9-AZ10-AZ11 -> 45202.073 | BA12: =BA8+BA9-BA10-BA11 -> 48373.383
A14: Parameters | B14: Value | J14: Parameters | K14: Value | S14: Parameters | T14: Value | AB14: Parameters | AC14: Value | AK14: Parameters | AL14: Value | AT14: Parameters | AU14: Value
A15: Terminal Value of FCFF | B15: =H12*(1+WACC!B19)/(WACC!B17-WACC!B19) -> 187964.36 | J15: Terminal Value of FCFF | K15: =Q12*(1+WACC!C19)/(WACC!C17-WACC!C19) -> 48942.888 | S15: Terminal Value of FCFF | T15: =Z12*(1+WACC!D19)/(WACC!D17-WACC!D19) -> 115272.23 | AB15: Terminal Value of FCFF | AC15: =AI12*(1+WACC!E19)/(WACC!E17-WACC!E19) -> 714938.67 | AK15: Terminal Value of FCFF | AL15: =AR12*(1+WACC!F19)/(WACC!F17-WACC!F19) -> 766217.79 | AT15: Terminal Value of FCFF | AU15: =BA12*(1+WACC!G19)/(WACC!G17-WACC!G19) -> 482528.74
A16: PV of Terminal Value | B16: =B15/(1+WACC!B17)^5 -> 98676.895 | J16: PV of Terminal Value | K16: =K15/(1+WACC!C17)^5 -> 22667.752 | S16: PV of Terminal Value | T16: =T15/(1+WACC!D17)^5 -> 63022.579 | AB16: PV of Terminal Value | AC16: =AC15/(1+WACC!E17)^5 -> 397133.03 | AK16: PV of Terminal Value | AL16: =AL15/(1+WACC!F17)^5 -> 435347.18 | AT16: PV of Terminal Value | AU16: =AU15/(1+WACC!G17)^5 -> 245980.18
A17: PV of FCFF | B17: =NPV(Table33[[#This Row],[Column2]],FCFF!D12:H12) -> 52831.304 | J17: PV of FCFF | K17: =NPV(Table33[[#This Row],[Column3]],FCFF!M12:Q12) -> 15525.145 | S17: PV of FCFF | T17: =NPV(Table33[[#This Row],[Column4]],FCFF!V12:Z12) -> 31094.599 | AB17: PV of FCFF | AC17: =NPV(Table33[[#This Row],[Column5]],FCFF!AE12:AI12) -> 169098.72 | AK17: PV of FCFF | AL17: =NPV(Table33[[#This Row],[Column6]],FCFF!AN12:AR12) -> 176841.21 | AT17: PV of FCFF | AU17: =NPV(Table33[[#This Row],[Column7]],FCFF!AW12:BA12) -> 151758.11
A18: Enterprise Value | B18: =B16+B17 -> 151508.2 | J18: Enterprise Value | K18: =K16+K17 -> 38192.898 | S18: Enterprise Value | T18: =T16+T17 -> 94117.178 | AB18: Enterprise Value | AC18: =AC16+AC17 -> 566231.76 | AK18: Enterprise Value | AL18: =AL16+AL17 -> 612188.38 | AT18: Enterprise Value | AU18: =AU16+AU17 -> 397738.28
A19: Net Debt | B19: =WACC!B9-WACC!B18 -> 50502.98 | J19: Net Debt | K19: =WACC!C14-WACC!C18 -> 14904.03 | S19: Net Debt | T19: =WACC!D14-WACC!D18 -> 66262.66 | AB19: Net Debt | AC19: =WACC!E14-WACC!E18 -> 141886.73 | AK19: Net Debt | AL19: =WACC!F14-WACC!F18 -> 149001.55 | AT19: Net Debt | AU19: =WACC!G14-WACC!G18 -> 116342
A20: Equity Value | B20: =B18-B19 -> 101005.22 | J20: Equity Value | K20: =K18-K19 -> 23288.868 | S20: Equity Value | T20: =T18-T19 -> 27854.518 | AB20: Equity Value | AC20: =AC18-AC19 -> 424345.03 | AK20: Equity Value | AL20: =AL18-AL19 -> 463186.84 | AT20: Equity Value | AU20: =AU18-AU19 -> 281396.28
A21: Shares Outstanding | B21: ='Company Profile'!B8/10000000 -> 433.8505 | J21: Shares Outstanding | K21: ='Company Profile'!C8/10000000 -> 657.508 | S21: Shares Outstanding | T21: ='Company Profile'!D8/10000000 -> 212.7823 | AB21: Shares Outstanding | AC21: ='Company Profile'!E8/10000000 -> 1412.124 | AK21: Shares Outstanding | AL21: ='Company Profile'!F8/10000000 -> 1258.028 | AT21: Shares Outstanding | AU21: ='Company Profile'!G8/10000000 -> 1353.274
A22: Intrinsic Value | B22: =B20/B21 -> 232.81112 | J22: Intrinsic Value | K22: =K20/K21 -> 35.4199 | S22: Intrinsic Value | T22: =T20/T21 -> 130.90618 | AB22: Intrinsic Value | AC22: =AC20/AC21 -> 300.50125 | AK22: Intrinsic Value | AL22: =AL20/AL21 -> 368.18484 | AT22: Intrinsic Value | AU22: =AU20/AU21 -> 207.9374
A23: Current Market price | B23: ='Company Profile'!B7 -> 365.15 | J23: Current Market price | K23: ='Company Profile'!C7 -> 181.52 | S23: Current Market price | T23: ='Company Profile'!D7 -> 481.7 | AB23: Current Market price | AC23: ='Company Profile'!E7 -> 169 | AK23: Current Market price | AL23: ='Company Profile'!F7 -> 251.4 | AT23: Current Market price | AU23: ='Company Profile'!G7 -> 1489.25
A24: #VALUE! | B24: =(B22-B23)/B23 -> -0.36242335 | J24: #VALUE! | K24: =(K22-K23)/K23 -> -0.80487054 | S24: #VALUE! | T24: =(T22-T23)/T23 -> -0.72824127 | AB24: #VALUE! | AC24: =(AC22-AC23)/AC23 -> 0.7781139 | AK24: #VALUE! | AL24: =(AL22-AL23)/AL23 -> 0.46453794 | AT24: #VALUE! | AU24: =(AU22-AU23)/AU23 -> -0.86037441

Sheet Relative
A1: RELATIVE VALUATION
A3: Company | B3: EV/EBITDA | C3: P/E | D3: P/B | E3: P/S | G3: Metrics | H3: BPCL | I3: HPCL | J3: GAIL | K3: ONGC | L3: RIL
A4: Bharat Petroleum Corporation | B4: ='Financial Ratios'!H19 -> 73.011275 | C4: ='Financial Ratios'!H20 -> 13.838403 | D4: ='Financial Ratios'!H21 -> 1.9465786 | E4: ='Financial Ratios'!H22 -> 0.31482476 | G4: EV/EBITDA | H4: =B20*B16 -> 207519.29 | I4: =B21*B16 -> 165417.5 | J4: =B16*B22 -> 293870.83 | K4: =B23*B16 -> 1781835 | L4: =B24*B16 -> 1305092.6
A5: GAIL (India) | B5: ='Financial Ratios'!Q19 -> 8.0394745 | C5: ='Financial Ratios'!Q20 -> 9.5765143 | D5: ='Financial Ratios'!Q21 -> 1.4001664 | E5: ='Financial Ratios'!Q22 -> 0.83137109 | G5: P/E | H5: =C16*C20 -> 150792.37 | I5: =C21*C16 -> 88723.092 | J5: =C22*C16 -> 164161.76 | K5: =C23*C16 -> 504867.02 | L5: =C24*C16 -> 464473.43
A6: Hindustan Petroleum Corporation | B6: ='Financial Ratios'!Z19 -> 9.0295568 | C6: ='Financial Ratios'!Z20 -> 15.217013 | D6: ='Financial Ratios'!Z21 -> 2.0040797 | E6: ='Financial Ratios'!Z22 -> 0.21863207 | G6: P/B | H6: =D16*D20 -> 137106.27 | I6: =D21*D16 -> 86161.848 | J6: =D22*D16 -> 143603.07 | K6: =D23*D16 -> 630467.05 | L6: =D24*D16 -> 914928.72
A7: Indian Oil Corporation | B7: ='Financial Ratios'!AI19 -> 9.638493 | C7: ='Financial Ratios'!AI20 -> 17.307412 | D7: ='Financial Ratios'!AI21 -> 1.2493097 | E7: ='Financial Ratios'!AI22 -> 0.27657372 | G7: P/S | H7: =E20*E16 -> 722146.58 | I7: =E21*E16 -> 672792.45 | J7: =E22*E16 -> 206021.92 | K7: =E23*E16 -> 969635.23 | L7: =E24*E16 -> 787707.5
A8: Oil and Natural Gas Corporation | B8: ='Financial Ratios'!AR19 -> 4.6050025 | C8: ='Financial Ratios'!AR20 -> 8.2514925 | D8: ='Financial Ratios'!AR21 -> 0.84510572 | E8: ='Financial Ratios'!AR22 -> 0.46809071 | G8: Market Cap | H8: ='Company Profile'!B10/10000000 -> 159288.2 | I8: ='Company Profile'!D10/10000000 -> 102039.7 | J8: ='Company Profile'!C10/10000000 -> 118660.5 | K8: ='Company Profile'!F10/10000000 -> 317274.7 | L8: ='Company Profile'!G10/10000000 -> 2000099
A9: Mangalore Refinery and Petrochemicals | B9: 17.36 | C9: 0 | D9: 1.71 | E9: 0.2 | G9: Average | H9: =AVERAGE(H4:H7) -> 304391.13 | I9: =AVERAGE(I4:I7) -> 253273.72 | J9: =AVERAGE(J4:J7) -> 201914.4 | K9: =AVERAGE(K4:K7) -> 971701.06 | L9: =AVERAGE(L4:L7) -> 868050.57
A10: Chennai Petroleum Corporation | B10: 24.35 | C10: 0 | D10: 1.27 | E10: 0.2
A11: Godavari Biorefineries | B11: 14.55 | C11: 0 | D11: 1.95 | E11: 0.81 | G11: Metrics | H11: BPCL | I11: HPCL | J11: GAIL | K11: ONGC | L11: RIL
A12: Oil India | B12: 6.89 | C12: 9.72 | D12: 1.28 | E12: 1.97 | G12: EV/EBITDA | H12: =H4/('Company Profile'!$B$8/10000000) -> 478.3198 | I12: =I4/('Company Profile'!$D$8/10000000) -> 777.40252 | J12: =J4/('Company Profile'!$C$8/10000000) -> 446.94639 | K12: =K4/('Company Profile'!$F$8/10000000) -> 1416.3715 | L12: =L4/('Company Profile'!$G$8/10000000) -> 964.39645
A13: Hind Oil Exploration | B13: 10.82 | C13: 19.59 | D13: 1.74 | E13: 6.32 | G13: P/E | H13: =H5/('Company Profile'!$B$8/10000000) -> 347.56759 | I13: =I5/('Company Profile'!$D$8/10000000) -> 416.9665 | J13: =J5/('Company Profile'!$C$8/10000000) -> 249.67264 | K13: =K5/('Company Profile'!$F$8/10000000) -> 401.3162 | L13: =L5/('Company Profile'!$G$8/10000000) -> 343.22201
A14: Jindal Drilling | B14: 4.34 | C14: 7.41 | D14: 1.11 | E14: 1.94 | G14: P/B | H14: =H6/('Company Profile'!$B$8/10000000) -> 316.02192 | I14: =I6/('Company Profile'!$D$8/10000000) -> 404.92958 | J14: =J6/('Company Profile'!$C$8/10000000) -> 218.40506 | K14: =K6/('Company Profile'!$F$8/10000000) -> 501.15502 | L14: =L6/('Company Profile'!$G$8/10000000) -> 676.08534
A15: Reliance Industries (O2C) | B15: ='Financial Ratios'!BA19 -> 28.537694 | C15: ='Financial Ratios'!BA20 -> 57.15397 | D15: ='Financial Ratios'!BA21 -> 3.7109401 | E15: ='Financial Ratios'!BA22 -> 3.6717338 | G15: P/S | H15: =H7/('Company Profile'!$B$8/10000000) -> 1664.5056 | I15: =I7/('Company Profile'!$D$8/10000000) -> 3161.8817 | J15: =J7/('Company Profile'!$C$8/10000000) -> 313.33751 | K15: =K7/('Company Profile'!$F$8/10000000) -> 770.75807 | L15: =L7/('Company Profile'!$G$8/10000000) -> 582.07539
A16: Average | B16: =AVERAGE(B4:B15) -> 17.597625 | C16: =AVERAGE(C4:C15) -> 13.172067 | D16: =AVERAGE(D4:D15) -> 1.6846817 | E16: =AVERAGE(E4:E15) -> 1.4351022 | G16: Market Price | H16: ='Company Profile'!B7 -> 365.15 | I16: ='Company Profile'!D7 -> 481.7 | J16: ='Company Profile'!C7 -> 181.52 | K16: ='Company Profile'!F7 -> 251.4 | L16: ='Company Profile'!G7 -> 1489.25
G17: Average | H17: =H9/('Company Profile'!$B$8/10000000) -> 701.60372 | I17: =I9/('Company Profile'!$D$8/10000000) -> 1190.2951 | J17: =J9/('Company Profile'!$C$8/10000000) -> 307.0904 | K17: =K9/('Company Profile'!$F$8/10000000) -> 772.40019 | L17: =L9/('Company Profile'!$G$8/10000000) -> 641.4448
A19: Particulars | B19: EBITDA | C19: Net Income | D19: Book Value | E19: Revenue | G19: Metrics | H19: BPCL | I19: HPCL | J19: GAIL | K19: ONGC | L19: RIL
A20: BPCL | B20: =Table7[[#This Row],[2025]]+'Income Statement'!G15+'Income Statement'!G16 -> 11792.46 | C20: ='Income Statement'!G27 -> 11447.89 | D20: ='Balance Sheet'!G37 -> 81384.08 | E20: ='Income Statement'!G8 -> 503202.2 | G20: EV/EBITDA | H20: =(H12-$H$16)/$H$16 -> 0.30992688 | I20: =(I12-$I$16)/$I$16 -> 0.61387278 | J20: =(J12-$J$16)/$J$16 -> 1.4622432 | K20: =(K12-$K$16)/$K$16 -> 4.6339358 | L20: =(L12-$L$16)/$L$16 -> -0.3524281
A21: HPCL | B21: =Table9[[#This Row],[2025]]+'Income Statement'!W16+'Income Statement'!W17 -> 9399.99 | C21: ='Income Statement'!W30 -> 6735.7 | D21: ='Balance Sheet'!W32 -> 51144.29 | E21: ='Income Statement'!W9 -> 468811.53 | G21: P/E | H21: =(H13-$H$16)/$H$16 -> -0.048151188 | I21: =(I13-$I$16)/$I$16 -> -0.1343855 | J21: =(J13-$J$16)/$J$16 -> 0.37545527 | K21: =(K13-$K$16)/$K$16 -> 0.59632539 | L21: =(L13-$L$16)/$L$16 -> -0.76953365
A22: GAIL | B22: ='Income Statement'!O19+'Income Statement'!O14+'Income Statement'!O15 -> 16699.46 | C22: ='Income Statement'!O27 -> 12462.87 | D22: ='Balance Sheet'!O35 -> 85240.48 | E22: ='Income Statement'!O8 -> 143559.06 | G22: P/B | H22: =(H14-$H$16)/$H$16 -> -0.13454218 | I22: =(I14-$I$16)/$I$16 -> -0.15937392 | J22: =(J14-$J$16)/$J$16 -> 0.20320109 | K22: =(K14-$K$16)/$K$16 -> 0.99345671 | L22: =(L14-$L$16)/$L$16 -> -0.54602293
A23: ONGC | B23: ='Income Statement'!AM19+'Income Statement'!AM15+'Income Statement'!AM16 -> 101254.29 | C23: ='Income Statement'!AM29 -> 38328.61 | D23: ='Balance Sheet'!AM53 -> 374235.12 | E23: ='Income Statement'!AM8 -> 675655.88 | G23: P/S | H23: =(H15-$H$16)/$H$16 -> 3.5584159 | I23: =(I15-$I$16)/$I$16 -> 5.5640059 | J23: =(J15-$J$16)/$J$16 -> 0.72618726 | K23: =(K15-$K$16)/$K$16 -> 2.0658634 | L23: =(L15-$L$16)/$L$16 -> -0.60914864
A24: RIL | B24: ='Income Statement'!AU21+'Income Statement'!AU17+'Income Statement'!AU18 -> 74163 | C24: ='Income Statement'!AU28 -> 35262 | D24: ='Balance Sheet'!AU29 -> 543087 | E24: ='Income Statement'!AU10 -> 548886 | G24: Average | H24: =(H17-H16)/H16 -> 0.92141236 | I24: =(I17-I16)/I16 -> 1.4710298 | J24: =(J17-J16)/J16 -> 0.69177172 | K24: =(K17-K16)/K16 -> 2.0723953 | L24: =(L17-L16)/L16 -> -0.56928333

Sheet Calc
A1: Revenue CAGR | B1: BPCL | C1: =(FCFF!H5/FCFF!D5)^(1/5)-1 -> 0.057582892 | I1: Company | J1: Change in EBIT (Historical) | K1: Change in CE | L1: Incremental ROCE (Historical) | M1: Change in EBIT (Forecast) | N1: Capex | O1: Depreciation | P1: Effective Capital | Q1: Raw ROCE (Forecast) | R1: Adjusted ROCE (Forecast)
A2: Revenue CAGR | B2: GAIL | C2: =(FCFF!Q5/FCFF!M5)^(1/5)-1 -> 0.092154163 | I2: BPCL | J2: =(('Income Statement'!G19+'Income Statement'!G15)-('Income Statement'!B19+'Income Statement'!B15)) -> 14895.68 | K2: =(('Balance Sheet'!G32-'Balance Sheet'!G56)-('Balance Sheet'!B32-'Balance Sheet'!B58)) -> 94495.84 | L2: =J2/K2 -> 0.15763318 | M2: =FCFF!H6-FCFF!D6 -> 7108.9521 | N2: =AVERAGE(FCFF!D10:H10) -> 12008.608 | O2: =AVERAGE(FCFF!D9:H9) -> 7989.9463 | P2: =IF(N2-O2<=0,N2,MAX(N2-O2,0.1*N2)) -> 4018.6621 | Q2: =M2/P2 -> 1.7689848 | R2: =MIN(MAX(Q2,0.06),0.12) -> 0.12
A3: Revenue CAGR | B3: HPCL | C3: =(FCFF!Z5/FCFF!V5)^(1/5)-1 -> 0.066420697 | I3: =B2 -> GAIL | J3: =(('Income Statement'!O19+'Income Statement'!O14)-('Income Statement'!J19+'Income Statement'!J14)) -> 4408.95 | K3: =(('Balance Sheet'!O29-'Balance Sheet'!O56)-('Balance Sheet'!J29-'Balance Sheet'!J56)) -> 48811.19 | L3: =J3/K3 -> 0.090326624 | M3: =FCFF!Q6-FCFF!M6 -> 8065.4601 | N3: =AVERAGE(FCFF!M10:Q10) -> 14758.084 | O3: =AVERAGE(FCFF!M9:Q9) -> 5225.6786 | P3: =IF(N3-O3<=0,N3,MAX(N3-O3,0.1*N3)) -> 9532.405 | Q3: =M3/P3 -> 0.84610967 | R3: =MIN(MAX(Q3,0.06),0.12) -> 0.12
A4: Revenue CAGR | B4: IOCL | C4: =(FCFF!AI5/FCFF!AE5)^(1/5)-1 -> 0.054693695 | I4: =B3 -> HPCL | J4: =(('Income Statement'!W20+'Income Statement'!W16)-('Income Statement'!R20+'Income Statement'!R16)) -> 8510.71 | K4: =('Balance Sheet'!W27-'Balance Sheet'!W51)-('Balance Sheet'!R27-'Balance Sheet'!R51) -> 38605.08 | L4: =J4/K4 -> 0.2204557 | M4: =FCFF!Z6-FCFF!V6 -> 4208.7505 | N4: =AVERAGE(FCFF!V10:Z10) -> 12475.323 | O4: =AVERAGE(FCFF!V9:Z9) -> 7008.1687 | P4: =IF(N4-O4<=0,N4,MAX(N4-O4,0.1*N4)) -> 5467.1539 | Q4: =M4/P4 -> 0.76982478 | R4: =MIN(MAX(Q4,0.06),0.12) -> 0.12
A5: Revenue CAGR | B5: ONGC | C5: =(Table14223640[[#This Row],[2030]]/Table14223640[[#This Row],[2026]])^(1/5)-1 -> 0.060782537 | I5: =B4 -> IOCL | J5: =(('Income Statement'!AE23+'Income Statement'!AE15)-('Income Statement'!Z23+'Income Statement'!Z15)) -> 13386.65 | K5: =('Balance Sheet'!AE31-'Balance Sheet'!AE56)-('Balance Sheet'!Z31-'Balance Sheet'!Z56) -> 108048.63 | L5: =J5/K5 -> 0.12389468 | M5: =FCFF!AI6-FCFF!AE6 -> 11695.674 | N5: =AVERAGE(FCFF!AE10:AI10) -> 7607.3503 | O5: =AVERAGE(FCFF!AE9:AI9) -> 18481.045 | P5: =IF(N5-O5<=0,N5,MAX(N5-O5,0.1*N5)) -> 7607.3503 | Q5: =M5/P5 -> 1.5374175 | R5: =MIN(MAX(Q5,0.06),0.12) -> 0.12
A6: Revenue CAGR | B6: RO2C | C6: =(FCFF!BA5/FCFF!AW5)^(1/5)-1 -> 0.055743672 | I6: =B5 -> ONGC | J6: =(('Income Statement'!AM19+'Income Statement'!AM15)-('Income Statement'!AH19+'Income Statement'!AH15)) -> 31501.205 | K6: =('Balance Sheet'!AM47-'Balance Sheet'!AM73)-('Balance Sheet'!AH47-'Balance Sheet'!AH73) -> 209017.17 | L6: =J6/K6 -> 0.15071109 | M6: =Table14223640[[#This Row],[2030]]-Table14223640[[#This Row],[2026]] -> 24931.904 | N6: =AVERAGE(FCFF!AN10:AR10) -> 56224.387 | O6: =AVERAGE(FCFF!AN9:AR9) -> 42483.121 | P6: =IF(N6-O6<=0,N6,MAX(N6-O6,0.1*N6)) -> 13741.266 | Q6: =M6/P6 -> 1.8143819 | R6: =MIN(MAX(Q6,0.06),0.12) -> 0.12
A7: Revenue CAGR | B7: Average | C7: =AVERAGE(C1:C6) -> 0.064562942 | E7: GDP g | F7: 2020 | G7: =AVERAGE(-5.8%,9.7%) -> 0.0195 | I7: =B6 -> RO2C | J7: =(('Income Statement'!AU21+'Income Statement'!AU17)-('Income Statement'!AP21+'Income Statement'!AP17)) -> -484 | K7: =('Balance Sheet'!AU24-'Balance Sheet'!AU48)-('Balance Sheet'!AP24-'Balance Sheet'!AP48) -> 123449 | L7: =J7/K7 -> -0.0039206474 | M7: =FCFF!BA6-FCFF!AW6 -> 22632.666 | N7: =AVERAGE(FCFF!AW10:BA10) -> 40717.624 | O7: =AVERAGE(FCFF!AW9:BA9) -> 21738.133 | P7: =IF(N7-O7<=0,N7,MAX(N7-O7,0.1*N7)) -> 18979.491 | Q7: =M7/P7 -> 1.1924801 | R7: =MIN(MAX(Q7,0.06),0.12) -> 0.12
A8: Capex Intensity | B8: BPCL | C8: =AVERAGE(FCFF!D10:H10)/AVERAGE(FCFF!D5:H5) -> 0.019250693 | E8: GDP g | F8: 2025 | G8: 0.078 | I8: Average | L8: =AVERAGE(L2:L7) -> 0.12318344 | Q8: =AVERAGE(Q2:Q7) -> 1.3215331 | R8: =AVERAGE(R2:R7) -> 0.12
A9: Capex Intensity | B9: GAIL | C9: =AVERAGE(FCFF!M10:Q10)/AVERAGE(FCFF!M5:Q5) -> 0.07297519 | E9: GDP g | F9: Change | G9: =G8-G7 -> 0.0585
A10: Capex Intensity | B10: HPCL | C10: =AVERAGE(Table1422[[#This Row],[2026]:[2030]])/AVERAGE(FCFF!V5:Z5) -> 0.020773946 | E10: GDP g | F10: Sensitivity | G10: =C21/G9 -> 19.5779
A11: Capex Intensity | B11: IOCL | C11: =AVERAGE(FCFF!AE10:AI10)/AVERAGE(FCFF!AE5:AI5) -> 0.0071885058
A12: Capex Intensity | B12: ONGC | C12: =AVERAGE(FCFF!AN10:AR10)/AVERAGE(FCFF!AN5:AR5) -> 0.066334641
A13: Capex Intensity | B13: RO2C | C13: =AVERAGE(FCFF!AW10:BA10)/AVERAGE(FCFF!AW5:BA5) -> 0.060250569
A14: Capex Intensity | B14: Average | C14: =AVERAGE(C8:C13) -> 0.041128924
A15: Earnings growth | B15: BPCL | C15: =('Income Statement'!G27-'Income Statement'!B27)/'Income Statement'!B27 -> 3.2665223
A16: Earnings growth | B16: GAIL | C16: =('Income Statement'!O27-'Income Statement'!J27)/'Income Statement'!J27 -> 0.30986249
A17: Earnings growth | B17: HPCL | C17: =('Income Statement'!W30-'Income Statement'!R30)/'Income Statement'!R30 -> 2.1836594
A18: Earnings growth | B18: IOCL | C18: =('Income Statement'!AE32-'Income Statement'!AA32)/'Income Statement'!AA32 -> -0.36638679
A19: Earnings growth | B19: ONGC | C19: =('Income Statement'!AM29-AVERAGE('Income Statement'!AH29:AI29))/AVERAGE('Income Statement'!AH29:AI29) -> 1.3371314
A20: Earnings growth | B20: RO2C | C20: =('Income Statement'!AU28-'Income Statement'!AP28)/'Income Statement'!AP28 -> 0.14105427
A21: Earnings growth | B21: Average | C21: =AVERAGE(C15:C20) -> 1.1453072
A22: Capex CAGR | B22: =B15 -> BPCL | C22: =(FCFF!H10/FCFF!D10)^(1/5)-1 -> 0.057582892
A23: Capex CAGR | B23: =B16 -> GAIL | C23: =(FCFF!Q10/FCFF!M10)^(1/5)-1 -> 0.092154163
A24: Capex CAGR | B24: =B17 -> HPCL | C24: =(FCFF!Z10/FCFF!V10)^(1/5)-1 -> 0.066420697
A25: Capex CAGR | B25: =B18 -> IOCL | C25: =(FCFF!AI10/FCFF!AE10)^(1/5)-1 -> 0.054693695
A26: Capex CAGR | B26: =B19 -> ONGC | C26: =(FCFF!AR10/FCFF!AN10)^(1/5)-1 -> 0.060782537
A27: Capex CAGR | B27: =B20 -> RO2C | C27: =(FCFF!BA10/FCFF!AW10)^(1/5)-1 -> 0.055743672
A28: Capex CAGR | B28: =B21 -> Average | C28: =AVERAGE(C22:C27) -> 0.064562942
A29: Earnings CAGR | B29: =B22 -> BPCL | C29: =(FCFF!H8/FCFF!D8)^(1/5)-1 -> 0.057582892
A30: Earnings CAGR | B30: =B23 -> GAIL | C30: =(FCFF!Q8/FCFF!M8)^(1/5)-1 -> 0.092154163
A31: Earnings CAGR | B31: =B24 -> HPCL | C31: =(FCFF!Z8/FCFF!V8)^(1/5)-1 -> 0.066420697
A32: Earnings CAGR | B32: =B25 -> IOCL | C32: =(FCFF!AI8/FCFF!AE8)^(1/5)-1 -> 0.054693695
A33: Earnings CAGR | B33: =B26 -> ONGC | C33: =(FCFF!AR8/FCFF!AN8)^(1/5)-1 -> 0.060782537
A34: Earnings CAGR | B34: =B27 -> RO2C | C34: =(FCFF!BA8/FCFF!AW8)^(1/5)-1 -> 0.055743672
A35: Earnings CAGR | B35: =B28 -> Average | C35: =AVERAGE(C29:C34) -> 0.064562942
