Workbook

Sheet Company Profile
A1: COMPANY PROFILE
A2: Particulars | B2: #VALUE! | C2: #VALUE! | D2: #VALUE! | E2: #VALUE! | F2: #VALUE! | G2: #VALUE!
A3: Company | B3: #VALUE! | C3: #VALUE! | D3: #VALUE! | E3: #VALUE! | F3: #VALUE! | G3: #VALUE!
A4: Official Name | B4: {=_FV(B3,"Official name",TRUE)} -> MARUTI SUZUKI INDIA LIMITED | C4: {=_FV(C3,"Official name",TRUE)} -> MAHINDRA AND MAHINDRA LIMITED | D4: {=_FV(D3,"Official name",TRUE)} -> TATA MOTORS PASSENGER VEHICLES LIMITED | E4: {=_FV(E3,"Official name",TRUE)} -> TVS MOTOR COMPANY LIMITED | F4: {=_FV(F3,"Official name",TRUE)} -> EXIDE INDUSTRIES LIMITED | G4: {=_FV(G3,"Official name",TRUE)} -> SAMVARDHANA MOTHERSON INTERNATIONAL LIMITED
A5: Ticker Symbol | B5: {=_FV(B3,"Ticker symbol",TRUE)} -> MARUTI | C5: {=_FV(C3,"Ticker symbol",TRUE)} -> M&M | D5: {=_FV(D3,"Ticker symbol",TRUE)} -> 500570 | E5: {=_FV(E3,"Ticker symbol",TRUE)} -> TVSMOTOR | F5: {=_FV(F3,"Ticker symbol",TRUE)} -> 500086 | G5: {=_FV(G3,"Ticker symbol",TRUE)} -> MOTHERSON
A6: Industry | B6: {=_FV(B3,"Industry")} -> Automobiles & Auto Parts | C6: {=_FV(C3,"Industry")} -> Automobiles & Auto Parts | D6: {=_FV(D3,"Industry")} -> Automobiles & Auto Parts | E6: {=_FV(E3,"Industry")} -> Automobiles & Auto Parts | F6: {=_FV(F3,"Industry")} -> Automobiles & Auto Parts | G6: {=_FV(G3,"Industry")} -> Automobiles & Auto Parts
A7: Headquarters | B7: {=_FV(B3,"Headquarters")} -> 1, Nelson Mandela Road,, Vasant Kunj,, NEW DELHI, DELHI, 110070 IN | C7: {=_FV(C3,"Headquarters")} -> Gateway Building, Apollo Bunder, MUMBAI, MAHARASHTRA, 400001 IN | D7: {=_FV(D3,"Headquarters")} -> A Block, Shivasagar Estate, Dr. Annie Besant Road, Worli, MUMBAI, MAHARASHTRA, 400018 IN | E7: {=_FV(E3,"Headquarters")} -> "Chaitanya", No.12, Khader Nawaz Khan Road, Nungambakkam, KRISHNAGIRI, TAMIL NADU, 600006 IN | F7: {=_FV(F3,"Headquarters")} -> Exide House, 59E, Chowringhee Road, KOLKATA, WEST BENGAL, 700020 IN | G7: {=_FV(G3,"Headquarters")} -> C-14 A & B, Sector 1,, Distt. Gautam Budh Nagar, NOIDA, UTTAR PRADESH, 201301 IN
A8: Established year | B8: {=_FV(B3,"Year incorporated",TRUE)} -> 1981 | C8: {=_FV(C3,"Year incorporated",TRUE)} -> 1945 | D8: {=_FV(D3,"Year incorporated",TRUE)} -> 1945 | E8: {=_FV(E3,"Year incorporated",TRUE)} -> 1992 | F8: {=_FV(F3,"Year incorporated",TRUE)} -> 1947 | G8: {=_FV(G3,"Year incorporated",TRUE)} -> 1986
A9: Employees | B9: {=_FV(B3,"Employees")} -> 20171 | C9: {=_FV(C3,"Employees")} -> 25222 | D9: {=_FV(D3,"Employees")} -> 86259 | E9: {=_FV(E3,"Employees")} -> 6522 | F9: {=_FV(F3,"Employees")} -> 5135 | G9: {=_FV(G3,"Employees")} -> 91481
B10: =B9/10000000 -> 0.0020171 | C10: =C9/10000000 -> 0.0025222 | D10: =D9/10000000 -> 0.0086259 | E10: =E9/10000000 -> 0.0006522 | F10: =F9/10000000 -> 0.0005135 | G10: =G9/10000000 -> 0.0091481
A11: Share Price | B11: {=_FV(B3,"Price")} -> 15583 | C11: {=_FV(C3,"Price")} -> 3663.9 | D11: {=_FV(D3,"Price")} -> 410.5 | E11: {=_FV(E3,"Price")} -> 3490.8 | F11: {=_FV(F3,"Price")} -> 379.55 | G11: {=_FV(G3,"Price")} -> 102.55
A12: Change (%) | B12: {=_FV(B3,"Change (%)",TRUE)} -> 0.006719 | C12: {=_FV(C3,"Change (%)",TRUE)} -> -0.007127 | D12: {=_FV(D3,"Change (%)",TRUE)} -> 0.011956 | E12: {=_FV(E3,"Change (%)",TRUE)} -> 0.009836 | F12: {=_FV(F3,"Change (%)",TRUE)} -> 0.00623 | G12: {=_FV(G3,"Change (%)",TRUE)} -> -0.012042
A13: Currency conversion | B13: #VALUE! | C13: #VALUE! | D13: #VALUE! | E13: #VALUE! | F13: #VALUE! | G13: #VALUE!
B14: {=_FV(B13,"Price")} -> 0.01127 | C14: {=_FV(C13,"Price")} -> 0.01127 | D14: {=_FV(D13,"Price")} -> 0.01127 | E14: {=_FV(E13,"Price")} -> 0.01127 | F14: {=_FV(F13,"Price")} -> 0.01127 | G14: {=_FV(G13,"Price")} -> 0.01127
A15: Share Outstanding | B15: {=_FV(B3,"Shares outstanding",TRUE)} -> 314402600 | C15: {=_FV(C3,"Shares outstanding",TRUE)} -> 1200046000 | D15: {=_FV(D3,"Shares outstanding",TRUE)} -> 3682331000 | E15: {=_FV(E3,"Shares outstanding",TRUE)} -> 474919100 | F15: {=_FV(F3,"Shares outstanding",TRUE)} -> 850000000 | G15: {=_FV(G3,"Shares outstanding",TRUE)} -> 10554440000
B16: =B15/10000000 -> 31.44026 | C16: =C15/10000000 -> 120.0046 | D16: =D15/10000000 -> 368.2331 | E16: =E15/10000000 -> 47.49191 | F16: =F15/10000000 -> 85 | G16: =G15/10000000 -> 1055.444
A17: Market Cap | B17: {=_FV(B3,"Market cap",TRUE)} -> 4866638000000 | C17: {=_FV(C3,"Market cap",TRUE)} -> 4428411000000 | D17: {=_FV(D3,"Market cap",TRUE)} -> 1493922000000 | E17: {=_FV(E3,"Market cap",TRUE)} -> 1641700000000 | F17: {=_FV(F3,"Market cap",TRUE)} -> 320747500000 | G17: {=_FV(G3,"Market cap",TRUE)} -> 1095551000000
B18: =B17/10000000 -> 486663.8 | C18: =C17/10000000 -> 442841.1 | D18: =D17/10000000 -> 149392.2 | E18: =E17/10000000 -> 164170 | F18: =F17/10000000 -> 32074.75 | G18: =G17/10000000 -> 109555.1
A19: Beta | B19: {=_FV(B3,"Beta")} -> 0.3464 | C19: {=_FV(C3,"Beta")} -> 0.7572 | D19: {=_FV(D3,"Beta")} -> 1.0253 | E19: {=_FV(E3,"Beta")} -> 0.1588 | F19: {=_FV(F3,"Beta")} -> 0.9844 | G19: {=_FV(G3,"Beta")} -> 1.5879

Sheet Balance Sheet
A1: Balance Sheet | F1: #VALUE! | I1: Balance Sheet | N1: #VALUE! | Q1: Balance Sheet | V1: #VALUE! | Y1: Balance Sheet | AD1: #VALUE! | AG1: Balance Sheet | AL1: #VALUE! | AO1: Balance Sheet | AT1: #VALUE!
A2: Particulars | B2: 2020 | C2: 2021 | D2: 2022 | E2: 2023 | F2: 2024 | G2: 2025 | I2: Particulars | J2: 2020 | K2: 2021 | L2: 2022 | M2: 2023 | N2: 2024 | O2: 2025 | Q2: Particulars | R2: 2020 | S2: 2021 | T2: 2022 | U2: 2023 | V2: 2024 | W2: 2025 | Y2: Particulars | Z2: 2020 | AA2: 2021 | AB2: 2022 | AC2: 2023 | AD2: 2024 | AE2: NA | AG2: Particulars | AH2: 2020 | AI2: 2021 | AJ2: 2022 | AK2: 2023 | AL2: 2024 | AM2: 2025 | AO2: Particulars | AP2: 2020 | AQ2: 2021 | AR2: 2022 | AS2: 2023 | AT2: 2024 | AU2: NA
A3: ASSETS | I3: ASSETS | Q3: ASSETS | Y3: ASSETS | AG3: ASSETS | AO3: ASSETS
A4: Non-Current Assets | I4: Non-Current Assets | Q4: Non-Current Assets | Y4: Non-Current Assets | AG4: Non-Current Assets | AO4: Non-Current Assets
A5: PPE | B5: 14790.5 | C5: 14178.5 | D5: 12826.1 | E5: 16692.1 | F5: 17431.4 | G5: 23638.2 | I5: PPE | J5: 24417.18 | K5: 17611.65 | L5: 21902.26 | M5: 20351.33 | N5: 21408.6 | O5: 25834.82 | Q5: PPE | R5: 77882.83 | S5: 79640.05 | T5: 80900.13 | U5: 76641.43 | V5: 73125 | W5: 72536 | Y5: PPE | Z5: 3066.54 | AA5: 3123.85 | AB5: 4377.8 | AC5: 4177.4 | AD5: 4294.12 | AG5: PPE | AH5: 2620 | AI5: 2970.19 | AJ5: 3240.18 | AK5: 3582.06 | AL5: 3760.47 | AM5: 3853.53 | AO5: PPE | AP5: 14713.8 | AQ5: 14373.8 | AR5: 14525.2 | AS5: 15644.5 | AT5: 18773
A6: Capital work-in-progress | B6: 1344.3 | C6: 1199.3 | D6: 2646.2 | E6: 2815.2 | F6: 6303.4 | G6: 5357.5 | I6: Capital work-in-progress | J6: 2551.75 | K6: 4477.64 | L6: 3036.1 | M6: 1222.66 | N6: 3461.33 | O6: 3652.56 | Q6: Capital work-in-progress | R6: 8599.56 | S6: 8377.14 | T6: 3529.04 | U6: 5219.87 | V6: 10937 | W6: 17624 | Y6: Capital work-in-progress | Z6: 847.14 | AA6: 873.89 | AB6: 320.18 | AC6: 315.81 | AD6: 338.01 | AG6: Capital work-in-progress | AH6: 360.72 | AI6: 379.47 | AJ6: 322.42 | AK6: 335.38 | AL6: 1164.54 | AM6: 3426.05 | AO6: Right-to-use assets | AP6: 1559.6 | AQ6: 1438.3 | AR6: 1603.1 | AS6: 1918.1 | AT6: 2880.6
A7: Intangible assets | B7: 335.8 | C7: 224.2 | D7: 349.9 | E7: 547.9 | F7: 451 | G7: 482.8 | I7: Intangible assets | J7: 1512.31 | K7: 1304.9 | L7: 2775.83 | M7: 4239.75 | N7: 4272.44 | O7: 6427.64 | Q7: Right of use assets | R7: 6275.34 | S7: 6490.66 | T7: 6686.02 | U7: 7801.04 | V7: 8059 | W7: 8476 | Y7: Investment properties | Z7: 137.7 | AA7: 137.7 | AB7: 137.7 | AC7: 137.7 | AD7: 137.7 | AG7: Goodwill | AH7: 581.9 | AI7: 581.9 | AJ7: 46.77 | AK7: 45.82 | AL7: 45.82 | AM7: 45.82 | AO7: Capital work-in-progress | AP7: 815.4 | AQ7: 838.3 | AR7: 1248.8 | AS7: 1422.2 | AT7: 2430.6
A8: Intangible assets under development | B8: 70.9 | C8: 297.5 | D8: 290.3 | E8: 88.9 | F8: 230.5 | G8: 401.8 | I8: Intangible assets under development | J8: 3759.78 | K8: 2463.13 | L8: 3666.71 | M8: 2745.92 | N8: 4577.97 | O8: 4645.08 | Q8: Goodwill | R8: 777.06 | S8: 803.72 | T8: 807.17 | U8: 840.6 | V8: 860 | W8: 895 | Y8: Goodwill | Z8: 2.2 | AA8: 2.2 | AB8: 0 | AC8: 0 | AD8: 0 | AG8: Other tangible assets | AH8: 46.6 | AI8: 46.66 | AJ8: 74.28 | AK8: 56.94 | AL8: 46.55 | AM8: 35.89 | AO8: Investment property | AP8: 119.7 | AQ8: 128.1 | AR8: 524.1 | AS8: 499.3 | AT8: 583.7
A9: Right-of-use assets | B9: 618.1 | C9: 586 | D9: 571.2 | E9: 590.4 | F9: 612.9 | G9: 585.8 | I9: Goodwill | J9: 4304.73 | K9: 3394.97 | L9: 1340.4 | M9: 2548.9 | N9: 2448.37 | O9: 2373.9 | Q9: Other intangible assets | R9: 42171.91 | S9: 51773.18 | T9: 50462.13 | U9: 46796.69 | V9: 39241 | W9: 33790 | Y9: Goodwill on consolidation | Z9: 186.11 | AA9: 186.11 | AB9: 569.47 | AC9: 597.05 | AD9: 597.05 | AG9: Intangible assets under development | AH9: 44.15 | AI9: 51.48 | AJ9: 18.52 | AK9: 189.67 | AL9: 187.44 | AM9: 217.36 | AO9: Goodwill | AP9: 2406 | AQ9: 2471.8 | AR9: 3374.3 | AS9: 3772.6 | AT9: 5750.1
A10: Financial assets | I10: Investments accounted using equity method | J10: 11229.4 | K10: 12256.22 | L10: 13149.7 | M10: 14380.57 | N10: 13800.71 | O10: 14176.68 | Q10: Intangible assets under development | R10: 27022.73 | S10: 12586.79 | T10: 6722.05 | U10: 9054.63 | V10: 24761 | W10: 48182 | Y10: Other tangible assets | Z10: 183 | AA10: 528.44 | AB10: 889.49 | AC10: 835.88 | AD10: 861.95 | AG10: Reinsurance asset | AH10: 138.96 | AI10: 271.2 | AJ10: 24.56 | AK10: 24.84 | AL10: 25.66 | AM10: 27.66 | AO10: Other Intangible assets | AP10: 1951 | AQ10: 1687.1 | AR10: 1384.5 | AS10: 1312.4 | AT10: 2134.1
A11: Investments | B11: 36269.2 | C11: 34529.1 | D11: 37934.6 | E11: 49184.3 | F11: 64601.5 | G11: 68945.9 | I11: Financial assets | Q11: Investment in equity accounted investees | R11: 4418.89 | S11: 4200.79 | T11: 4349.39 | U11: 4675.66 | V11: 5340 | W11: 5534 | Y11: Intangible assets under development | Z11: 158.87 | AA11: 166.88 | AB11: 231.35 | AC11: 427.64 | AD11: 694.94 | AG11: Financial assets | AO11: Intangible assets under development | AP11: 36.4 | AQ11: 38.6 | AR11: 60.9 | AS11: 55.7 | AT11: 67.2
A12: Loans | B12: 0.2 | C12: 0.2 | D12: 0.2 | E12: 0.2 | F12: 0.1 | G12: 0.1 | I12: Investments | J12: 1685.38 | K12: 6489.62 | L12: 6060.85 | M12: 6625.93 | N12: 7772.75 | O12: 5184.42 | Q12: Financial assets | Y12: Right of use assets | Z12: 235.14 | AA12: 242.75 | AB12: 0 | AC12: 0 | AD12: 0 | AG12: Investments | AO12: Investments accounted for using the equity method | AP12: 634.1 | AQ12: 716.6 | AR12: 6264.7 | AS12: 6105.9 | AT12: 6207.5
A13: Other Financial assets | B13: 36.5 | C13: 36.9 | D13: 37.5 | E13: 59.5 | F13: 82.2 | G13: 87.1 | I13: Loans | J13: 45945.23 | K13: 38525.68 | L13: 38849.4 | M13: 52772.75 | N13: 67783.65 | O13: 79607.31 | Q13: Other investments | R13: 1028.05 | S13: 1368.3 | T13: 2320.92 | U13: 2865.19 | V13: 3378 | W13: 2923 | Y13: Financial assets | AG13: Investments on life insurance business | AH13: 14736.78 | AI13: 17702.22 | AJ13: 4822.34 | AK13: 4477.82 | AL13: 5655.45 | AM13: 6122.03 | AO13: Financial assets
A14: Other non-current assets | B14: 1721.6 | C14: 1686.7 | D14: =544.6+141.1+2520.4 -> 3206.1 | E14: =574.9+279.4+2148.5 -> 3002.8 | F14: =543.9+112.4+2153.1 -> 2809.4 | G14: =474.3+2394.5 -> 2868.8 | I14: Other Financial assets | J14: 1187.72 | K14: 1497.38 | L14: 2206.65 | M14: 3353.97 | N14: 4297.97 | O14: 2282.79 | Q14: Financial receivables | R14: 16833.77 | S14: 16846.82 | T14: 11135.85 | U14: 7416.41 | V14: 6095 | W14: 0 | Y14: Investments | Z14: 195.71 | AA14: 180.39 | AB14: 109.51 | AC14: 364.1 | AD14: 482.75 | AG14: Other investments | AH14: 83.72 | AI14: 100.82 | AJ14: 25.59 | AK14: 23.19 | AL14: 40.39 | AM14: 43.44 | AO14: Investments | AP14: 161.4 | AQ14: 128.7 | AR14: 195.8 | AS14: 181.1 | AT14: 215.3
A15: Total non-current assets | B15: =SUM(B5:B9,B11:B14) -> 55187.1 | C15: =SUM(C5:C9,C11:C14) -> 52738.4 | D15: =SUM(D5:D9,D11:D14) -> 57862.1 | E15: =SUM(E5:E9,E11:E14) -> 72981.3 | F15: =SUM(F5:F9,F11:F14) -> 92522.4 | G15: =SUM(G5:G9,G11:G14) -> 102368 | I15: Trade receivables | J15: 556.19 | K15: 366.16 | L15: 309.43 | M15: 282.6 | N15: 270.66 | O15: 256.54 | Q15: Loans and advances | R15: 782.78 | S15: 1204.59 | T15: 843.35 | U15: 870.65 | V15: 442 | W15: 99 | Y15: Loans | Z15: 4148.49 | AA15: 5361.97 | AB15: 6716.45 | AC15: 10321.42 | AD15: 12054.55 | AG15: Trade receivables | AH15: 0.11 | AI15: 0.08 | AJ15: 0.05 | AK15: 0.32 | AL15: 0.6 | AM15: 0.59 | AO15: Loans | AP15: 17.7 | AQ15: 44.5 | AR15: 3.6 | AS15: 9 | AT15: 12.2
A16: Current Assets | I16: Deferred tax assets (net) | J16: 1290.53 | K16: 1717.32 | L16: 1724.31 | M16: 1615.46 | N16: 1578.99 | O16: 1573.11 | Q16: Other financial assets | R16: 4749.57 | S16: 5813.98 | T16: 5179.49 | U16: 7027.66 | V16: 9085 | W16: 12185 | Y16: Other financial assets | Z16: 36.64 | AA16: 14.92 | AB16: 124.14 | AC16: 192.93 | AD16: 195.52 | AG16: Loans | AH16: 38.08 | AI16: 51.17 | AJ16: 0.09 | AK16: 0.07 | AL16: 0.25 | AM16: 0.19 | AO16: Trade receivables | AP16: 1399.8 | AQ16: 1494.6 | AR16: 1451.6 | AS16: 1324.4 | AT16: 1557.2
A17: Inventories | B17: 3213.9 | C17: 3049 | D17: 3532.3 | E17: 4283.5 | F17: 4119.6 | G17: 5123 | I17: Income tax assets (net) | J17: 1897.98 | K17: 1887.47 | L17: 1604.24 | M17: 1802.88 | N17: 2129.91 | O17: 2270.77 | Q17: Deferred tax assets (net) | R17: 5457.9 | S17: 4520.35 | T17: 3870.85 | U17: 5184.67 | V17: 13099 | W17: 7176 | Y17: Investments accounted using equity method | Z17: 175.2 | AA17: 287.62 | AB17: 364.82 | AC17: 411.23 | AD17: 477.25 | AG17: Current tax assets (net) | AH17: 69.01 | AI17: 54.97 | AJ17: 37.9 | AK17: 41.2 | AL17: 39.54 | AM17: 26.69 | AO17: Other financial assets | AP17: 122.8 | AQ17: 106.9 | AR17: 241.3 | AS17: 115.5 | AT17: 155
A18: Financial assets | I18: Other non-current assets | J18: 2623.05 | K18: 2332.44 | L18: 2338.92 | M18: 2623.61 | N18: 4231.74 | O18: 2727.38 | Q18: Non-current tax assets (net) | R18: 1152.05 | S18: 1003.3 | T18: 1196.79 | U18: 1556.36 | V18: 2130 | W18: 2045 | Y18: Non-current tax assets (net) | Z18: 28.34 | AA18: 39.72 | AB18: 49.6 | AC18: 27.6 | AD18: 23.55 | AG18: Deferred tax assets (net) | AH18: 16.1 | AI18: 9.94 | AJ18: 65.38 | AK18: 115.98 | AL18: 23.04 | AM18: 6.65 | AO18: Deferred tax assets (net) | AP18: 503 | AQ18: 1022.4 | AR18: 1148.6 | AS18: 1364.4 | AT18: 2074.6
A19: Investments | B19: 1218.8 | C19: 8415.7 | D19: 4100.1 | E19: 0 | F19: 3912.2 | G19: 5560.4 | I19: Total non-current assets | J19: =SUM(J5:J10,J12:J18) -> 102961.23 | K19: =SUM(K5:K10,K12:K18) -> 94324.58 | L19: =SUM(L5:L10,L12:L18) -> 98964.8 | M19: =SUM(M5:M10,M12:M18) -> 114566.33 | N19: =SUM(N5:N10,N12:N18) -> 138035.09 | O19: =SUM(O5:O10,O12:O18) -> 151013 | Q19: Other non-current assets | R19: 5381.57 | S19: 1608.49 | T19: 5639.21 | U19: 8602.05 | V19: 5720 | W19: 6852 | Y19: Deferred tax assets | Z19: 86.65 | AA19: 127.62 | AB19: 217.88 | AC19: 305.73 | AD19: 394.28 | AG19: Other non-current assets | AH19: 221.51 | AI19: 211.08 | AJ19: 111.28 | AK19: 183.4 | AL19: 908.75 | AM19: 386.28 | AO19: Other non-current assets | AP19: 1216.5 | AQ19: 1383.5 | AR19: 1376.7 | AS19: 1226.5 | AT19: 1566.8
A20: Trade Receivables | B20: 1977.7 | C20: 1279.9 | D20: 2034.5 | E20: 3301.4 | F20: 4601.3 | G20: 6537.7 | I20: Current Assets | Q20: Total non-current assets | R20: =SUM(R5:R11,R13:R19) -> 202534.01 | S20: =SUM(S5:S11,S13:S19) -> 196238.16 | T20: =SUM(T5:T11,T13:T19) -> 183642.39 | U20: =SUM(U5:U11,U13:U19) -> 184552.91 | V20: =SUM(V5:V11,V13:V19) -> 202272 | W20: =SUM(W5:W11,W13:W19) -> 218317 | Y20: Other non-current assets | Z20: 132.09 | AA20: 181.79 | AB20: 115.43 | AC20: 94.14 | AD20: 148.78 | AG20: Total non-current assets | AH20: =SUM(AH5:AH10,AH13:AH19) -> 18957.64 | AI20: =SUM(AI5:AI10,AI13:AI19) -> 22431.18 | AJ20: =SUM(AJ5:AJ10,AJ13:AJ19) -> 8789.36 | AK20: =SUM(AK5:AK10,AK13:AK19) -> 9076.69 | AL20: =SUM(AL5:AL10,AL13:AL19) -> 11898.5 | AM20: =SUM(AM5:AM10,AM13:AM19) -> 14192.18 | AO20: Non-current tax assets (net) | AP20: 373.2 | AQ20: 184.3 | AR20: 250.7 | AS20: 120.9 | AT20: 341.6
A21: Cash and Cash Equivalents | B21: 20.8 | C21: 40.8 | D21: 35.1 | E21: 37.3 | F21: 455.7 | G21: 78 | I21: Inventories | J21: 11111.86 | K21: 9615.41 | L21: 11595.82 | M21: 16854.97 | N21: 18590.47 | O21: 20330.93 | Q21: Current Assets | Y21: Total Non-current assets | Z21: =SUM(Z5:Z12,Z14:Z20) -> 9619.82 | AA21: =SUM(AA5:AA12,AA14:AA20) -> 11455.85 | AB21: =SUM(AB5:AB12,AB14:AB20) -> 14223.82 | AC21: =SUM(AC5:AC12,AC14:AC20) -> 18208.63 | AD21: =SUM(AD5:AD12,AD14:AD20) -> 20700.45 | AE21: =SUM(AE5:AE12,AE14:AE20) -> 0 | AG21: Current Assets | AO21: Total Non-current assets | AP21: =SUM(AP5:AP12,AP14:AP20) -> 26030.4 | AQ21: =SUM(AQ5:AQ12,AQ14:AQ20) -> 26057.5 | AR21: =SUM(AR5:AR12,AR14:AR20) -> 33653.9 | AS21: =SUM(AS5:AS12,AS14:AS20) -> 35072.5 | AT21: =SUM(AT5:AT12,AT14:AT20) -> 44749.5 | AU21: =SUM(AU5:AU12,AU14:AU20) -> 0
A22: Other bank balances | B22: 8.2 | C22: 3006.3 | D22: 3007.1 | E22: 4.3 | F22: 4.3 | G22: 368.4 | I22: Financial assets | Q22: Inventories | R22: 37456.88 | S22: 36088.59 | T22: 35240.34 | U22: 40755.39 | V22: 47788 | W22: 47269 | Y22: Current Assets | AG22: Inventories | AH22: 2414.56 | AI22: 2636.86 | AJ22: 2855.29 | AK22: 3436.4 | AL22: 3868.53 | AM22: 4564.9 | AO22: Current Assets
A23: Loans | B23: 17 | C23: 23 | D23: 30.5 | E23: 29.7 | F23: 32.7 | G23: 43.2 | I23: Investments | J23: 6295.56 | K23: 10031.82 | L23: 10849.88 | M23: 14265.92 | N23: 13634.64 | O23: 21947.47 | Q23: Financial assets | Y23: Inventories | Z23: 1188.47 | AA23: 1367.43 | AB23: 1642.36 | AC23: 1921.51 | AD23: 2248.4 | AG23: Financial assets | AO23: Inventories | AP23: 5156.6 | AQ23: 4995.6 | AR23: 6441.7 | AS23: 7822.8 | AT23: 9138.6
A24: Other Financial assets | B24: 659.6 | C24: 642.7 | D24: 2593 | E24: 2193.4 | F24: 1980.1 | G24: 1731.2 | I24: Trade Receivables | J24: 6928.28 | K24: 6007.76 | L24: 6373.95 | M24: 7028.02 | N24: 7459.4 | O24: 8279.7 | Q24: Other investments | R24: 10861.54 | S24: 19051.19 | T24: 22709.22 | U24: 18838.31 | V24: 14253 | W24: 27199 | Y24: Financial assets | AG24: Investments | AO24: Financial assets
A25: Current tax assets (net) | B25: 527.2 | C25: 540.7 | D25: 0 | E25: 0 | F25: 0 | G25: 0 | I25: Cash and Cash Equivalents | J25: 4745.03 | K25: 3374.59 | L25: 3487.59 | M25: 3493.41 | N25: 4530.1 | O25: 4923.89 | Q25: Trade receivables | R25: 11172.69 | S25: 12679.08 | T25: 12442.12 | U25: 15737.97 | V25: 16952 | W25: 13248 | Y25: Trade receivables | Z25: 1454.36 | AA25: 1035.97 | AB25: 1155.24 | AC25: 1256.42 | AD25: 1839.42 | AG25: Investments of life insurance business | AH25: 918.21 | AI25: 633.58 | AJ25: 711.54 | AK25: 603.25 | AL25: 258.9 | AM25: 318.27 | AO25: Investments | AP25: 0.6 | AQ25: 1.2 | AR25: 1.2 | AS25: 2.9 | AT25: 98.6
A26: Other current assets | B26: 797.4 | C26: 1546.2 | D26: 1460.8 | E26: 1766 | F26: 2656.5 | G26: 3810.3 | I26: Other bank balances | J26: 3165.87 | K26: 9477.4 | L26: 7630.02 | M26: 7780.02 | N26: 7482.65 | O26: 15690.95 | Q26: Cash and cash equivalents | R26: 18467.8 | S26: 31700.01 | T26: 38159.01 | U26: 31886.95 | V26: 40015 | W26: 34349 | Y26: Loans | Z26: 5306.84 | AA26: 5794.23 | AB26: 7299.24 | AC26: 10225.16 | AD26: 13417.26 | AG26: Other investments | AH26: 76.79 | AI26: 903.04 | AJ26: 0 | AK26: 0 | AL26: 0 | AM26: 0 | AO26: Trade receivables | AP26: 5178.4 | AQ26: 5693.1 | AR26: 6573.1 | AS26: 8513.5 | AT26: 15637.1
A27: Total current Assets | B27: =SUM(B17,B19:B26) -> 8440.6 | C27: =SUM(C17,C19:C26) -> 18544.3 | D27: =SUM(D17,D19:D26) -> 16793.4 | E27: =SUM(E17,E19:E26) -> 11615.6 | F27: =SUM(F17,F19:F26) -> 17762.4 | G27: =SUM(G17,G19:G26) -> 23252.2 | I27: Loans | J27: 27963.68 | K27: 29119.55 | L27: 29242.26 | M27: 34684.81 | N27: 39060.13 | O27: 44644.77 | Q27: Bank Balances | R27: 15259.17 | S27: 15092.45 | T27: 2510.18 | U27: 5128.61 | V27: 5792 | W27: 6485 | Y27: Cash and cash equivalents | Z27: 1079.69 | AA27: 1573.76 | AB27: 1445.68 | AC27: 1851.19 | AD27: 2355.8 | AG27: Trade receivables | AH27: 1060.83 | AI27: 1076.2 | AJ27: 1097.85 | AK27: 1229.55 | AL27: 1382.27 | AM27: 1686.39 | AO27: Cash and cash equivalents | AP27: 4868.8 | AQ27: 5899.4 | AR27: 4877.5 | AS27: 4538.1 | AT27: 6743.2
A28: Total Assets | B28: =B15+B27 -> 63627.7 | C28: =C15+C27 -> 71282.7 | D28: =D15+D27 -> 74655.5 | E28: =E15+E27 -> 84596.9 | F28: =F15+F27 -> 110284.8 | G28: =G15+G27 -> 125620.2 | I28: Other Financial assets | J28: 1177.36 | K28: 1431.4 | L28: 1998.95 | M28: 1951.7 | N28: 2102.43 | O28: 3552.48 | Q28: Financial receivables | R28: 14245.3 | S28: 17868.09 | T28: 22095.35 | U28: 23417.31 | V28: 24070 | W28: 0 | Y28: Bank Balances | Z28: 27.88 | AA28: 83.09 | AB28: 89.93 | AC28: 27.92 | AD28: 69.93 | AG28: Cash and cash equivalents | AH28: 331.47 | AI28: 342.43 | AJ28: 189.11 | AK28: 131.78 | AL28: 322.99 | AM28: 180.82 | AO28: Bank Balances | AP28: 10.1 | AQ28: 6.8 | AR28: 121.9 | AS28: 160.6 | AT28: 242.5
A29: EQUITY AND LIABILITIES | I29: Current tax assets (net) | J29: 2561.29 | K29: 3079.98 | L29: 0 | M29: 56.6 | N29: 25.47 | O29: 0 | Q29: Loans and advances | R29: 935.25 | S29: 1749.4 | T29: 1671.93 | U29: 2302.84 | V29: 197 | W29: 72 | Y29: Other financial assets | Z29: 93.19 | AA29: 85.64 | AB29: 131.62 | AC29: 241.26 | AD29: 202.66 | AG29: Bank balances | AH29: 10.13 | AI29: 11.14 | AJ29: 9.88 | AK29: 8.53 | AL29: 7.52 | AM29: 7.2 | AO29: Loans | AP29: 31.3 | AQ29: 27.2 | AR29: 28.9 | AS29: 28.9 | AT29: 27.6
A30: Equity | I30: Other current assets | J30: 96.5 | K30: 0 | L30: 3969.53 | M30: 5209.99 | N30: 5380.35 | O30: 7203.08 | Q30: Other financial assets | R30: 4586.48 | S30: 5274.32 | T30: 3799.82 | U30: 2786.72 | V30: 8121 | W30: 18984 | Y30: Current tax assets (net) | Z30: 2.43 | AA30: 4.83 | AB30: 1.42 | AC30: 4.56 | AD30: 23.89 | AG30: Loans | AH30: 22.87 | AI30: 20.76 | AJ30: 0.28 | AK30: 0.26 | AL30: 0.36 | AM30: 0.34 | AO30: Other financial assets | AP30: 3088.2 | AQ30: 2420 | AR30: 3127.8 | AS30: 4021.3 | AT30: 5142.3
A31: Equity share capital | B31: 151 | C31: 151 | D31: 151 | E31: 151 | F31: 157.2 | G31: 157.2 | I31: Total current Assets | J31: =SUM(J21,J23:J30) -> 64045.43 | K31: =SUM(K21,K23:K30) -> 72137.91 | L31: =SUM(L21,L23:L30) -> 75148 | M31: =SUM(M21,M23:M30) -> 91325.44 | N31: =SUM(N21,N23:N30) -> 98265.64 | O31: =SUM(O21,O23:O30) -> 126573.27 | Q31: Current tax assets (net) | R31: 142.28 | S31: 865.31 | T31: 259.84 | U31: 259.26 | V31: 101 | W31: 411 | Y31: Other current assets | Z31: 586.14 | AA31: 591.89 | AB31: =952.35+130.23 -> 1082.58 | AC31: =1304.34+191.92 -> 1496.26 | AD31: =1199.46+163.19 -> 1362.65 | AG31: Other financial assets | AH31: 376.26 | AI31: 418.95 | AJ31: 53.14 | AK31: 58.07 | AL31: 46.46 | AM31: 76.72 | AO31: Other current assets | AP31: 1131.4 | AQ31: 1205.2 | AR31: 1444.1 | AS31: 1691.1 | AT31: 3242.3
A32: Other equity | B32: 49262 | C32: 52349.6 | D32: 55182.5 | E32: 61640.3 | F32: 83824.8 | G32: 93889.5 | I32: Total Assets | J32: =J19+J31 -> 167006.66 | K32: =K19+K31 -> 166462.49 | L32: =L19+L31 -> 174112.8 | M32: =M19+M31 -> 205891.77 | N32: =N19+N31 -> 236300.73 | O32: =O19+O31 -> 277586.27 | Q32: Assets classified as held-for-sale | R32: 194.43 | S32: 220.8 | T32: 523.85 | U32: 827.78 | V32: 674 | W32: 514 | Y32: Total current assets | Z32: =SUM(Z23,Z25:Z31) -> 9739 | AA32: =SUM(AA23,AA25:AA31) -> 10536.84 | AB32: =SUM(AB23,AB25:AB31) -> 12848.07 | AC32: =SUM(AC23,AC25:AC31) -> 17024.28 | AD32: =SUM(AD23,AD25:AD31) -> 21520.01 | AE32: =SUM(AE23,AE25:AE31) -> 0 | AG32: Other current assets | AH32: 198.83 | AI32: 212.97 | AJ32: 204.16 | AK32: 223.15 | AL32: =347.93+16.56 -> 364.49 | AM32: =352.29+17.12 -> 369.41 | AO32: Total current assets | AP32: =SUM(AP25:AP31,AP23) -> 19465.4 | AQ32: =SUM(AQ25:AQ31,AQ23) -> 20248.5 | AR32: =SUM(AR25:AR31,AR23) -> 22616.2 | AS32: =SUM(AS25:AS31,AS23) -> 26779.2 | AT32: =SUM(AT25:AT31,AT23) -> 40272.2 | AU32: =SUM(AU25:AU31,AU23) -> 0
A33: Equity attributable to owners of the company | B33: =SUM(B31:B32) -> 49413 | C33: =SUM(C31:C32) -> 52500.6 | D33: =SUM(D31:D32) -> 55333.5 | E33: =SUM(E31:E32) -> 61791.3 | F33: =SUM(F31:F32) -> 83982 | G33: =SUM(G31:G32) -> 94046.7 | I33: EQUITY AND LIABILITIES | Q33: Other assets | R33: 6264.91 | S33: 6298.4 | T33: 7565.88 | U33: 9587.33 | V33: 10429 | W33: 11794 | Y33: Total Assets | Z33: =Z21+Z32 -> 19358.82 | AA33: =AA21+AA32 -> 21992.69 | AB33: =AB21+AB32 -> 27071.89 | AC33: =AC21+AC32 -> 35232.91 | AD33: =AD21+AD32 -> 42220.46 | AE33: =AE21+AE32 -> 0 | AG33: Total current assets | AH33: =SUM(AH22,AH25:AH32) -> 5409.95 | AI33: =SUM(AI22,AI25:AI32) -> 6255.93 | AJ33: =SUM(AJ22,AJ25:AJ32) -> 5121.25 | AK33: =SUM(AK22,AK25:AK32) -> 5690.99 | AL33: =SUM(AL22,AL25:AL32) -> 6251.52 | AM33: =SUM(AM22,AM25:AM32) -> 7204.05 | AO33: Assets classified as held for distribution | AP33: 0 | AQ33: 1779 | AR33: 0 | AS33: 0
A34: Non-controlling interest | B34: 19.2 | C34: 0 | D34: 0 | E34: 0 | F34: 0 | G34: 0 | I34: Equity | Q34: Total Current assets | R34: =SUM(R22,R24:R33) -> 119586.73 | S34: =SUM(S22,S24:S33) -> 146887.64 | T34: =SUM(T22,T24:T33) -> 146977.54 | U34: =SUM(U22,U24:U33) -> 151528.47 | V34: =SUM(V22,V24:V33) -> 168392 | W34: =SUM(W22,W24:W33) -> 160325 | Y34: EQUITY AND LIABILITIES | AG34: Total Assets | AH34: =AH20+AH33 -> 24367.59 | AI34: =AI20+AI33 -> 28687.11 | AJ34: =AJ20+AJ33 -> 13910.61 | AK34: =AK20+AK33 -> 14767.68 | AL34: =AL20+AL33 -> 18150.02 | AM34: =AM20+AM33 -> 21396.23 | AO34: Total assets | AP34: =AP21+AP32+AP33 -> 45495.8 | AQ34: =AQ21+AQ32+AQ33 -> 48085 | AR34: =AR21+AR32+AR33 -> 56270.1 | AS34: =AS21+AS32+AS33 -> 61851.7 | AT34: =AT21+AT32+AT33 -> 85021.7 | AU34: =AU21+AU32+AU33 -> 0
A35: Total Equity | B35: =B33+B34 -> 49432.2 | C35: =C33+C34 -> 52500.6 | D35: =D33+D34 -> 55333.5 | E35: =E33+E34 -> 61791.3 | F35: =F33+F34 -> 83982 | G35: =G33+G34 -> 94046.7 | I35: Equity share capital | J35: 554.28 | K35: 555.15 | L35: 556.06 | M35: 556.82 | N35: 557.38 | O35: 558.15 | Q35: Total Assets | R35: =R20+R34 -> 322120.74 | S35: =S20+S34 -> 343125.8 | T35: =T20+T34 -> 330619.93 | U35: =U20+U34 -> 336081.38 | V35: =V20+V34 -> 370664 | W35: =W20+W34 -> 378642 | Y35: Equity | AG35: EQUITY AND LIABILITIES | AO35: EQUITY AND LIABILITIES
A36: Liabilities | I36: Other equity | J36: 39415.03 | K36: 41026.77 | L36: 46566.58 | M36: 55808.97 | N36: 65633.17 | O36: 76480.71 | Q36: EQUITY AND LIABILITIES | Y36: Equity share capital | Z36: 47.51 | AA36: 47.51 | AB36: 47.51 | AC36: 47.51 | AD36: 47.51 | AG36: Equity | AO36: Equity
A37: Non-current liabilities | I37: Equity attributable to owners of the company | J37: =SUM(J35:J36) -> 39969.31 | K37: =SUM(K35:K36) -> 41581.92 | L37: =SUM(L35:L36) -> 47122.64 | M37: =SUM(M35:M36) -> 56365.79 | N37: =SUM(N35:N36) -> 66190.55 | O37: =SUM(O35:O36) -> 77038.86 | Q37: Equity | Y37: Other equity | Z37: 3234.59 | AA37: 3779.1 | AB37: 4351.94 | AC37: 5457.49 | AD37: 6736 | AG37: Equity share capital | AH37: 85 | AI37: 85 | AJ37: 85 | AK37: 85 | AL37: 85 | AM37: 85 | AO37: Equity share capital | AP37: 315.8 | AQ37: 315.8 | AR37: 451.8 | AS37: 677.6 | AT37: 677.6
A38: Financial Liabilities | I38: Non-controlling interest | J38: 7691.74 | K38: 9070.31 | L38: 9702.62 | M38: 10716.32 | N38: 11318.79 | O38: 12059.14 | Q38: Equity share capital | R38: 719.54 | S38: 765.81 | T38: 765.88 | U38: 766.02 | V38: 767 | W38: 736 | Y38: Equity attributable to owners of the company | Z38: =SUM(Z36:Z37) -> 3282.1 | AA38: =SUM(AA36:AA37) -> 3826.61 | AB38: =SUM(AB36:AB37) -> 4399.45 | AC38: =SUM(AC36:AC37) -> 5505 | AD38: =SUM(AD36:AD37) -> 6783.51 | AE38: =SUM(AE36:AE37) -> 0 | AG38: Other equity | AH38: 6382.32 | AI38: 7187.27 | AJ38: 10498.74 | AK38: 11047.28 | AL38: 12801.34 | AM38: 13828.48 | AO38: Other equity
A39: Borrowings | B39: 5.4 | C39: 2.8 | D39: 0 | E39: 0 | F39: 0 | G39: 0 | I39: Total Equity | J39: =J37+J38 -> 47661.05 | K39: =K37+K38 -> 50652.23 | L39: =L37+L38 -> 56825.26 | M39: =M37+M38 -> 67082.11 | N39: =N37+N38 -> 77509.34 | O39: =O37+O38 -> 89098 | Q39: Other equity | R39: 62358.99 | S39: 54480.91 | T39: 43795.36 | U39: 44555.77 | V39: 84151 | W39: 115408 | Y39: Non-controlling interest | Z39: 320.94 | AA39: 387.9 | AB39: 653.56 | AC39: 404.85 | AD39: 727.6 | AG39: Equity attributable to owners of the company | AH39: =SUM(AH37:AH38) -> 6467.32 | AI39: =SUM(AI37:AI38) -> 7272.27 | AJ39: =SUM(AJ37:AJ38) -> 10583.74 | AK39: =SUM(AK37:AK38) -> 11132.28 | AL39: =SUM(AL37:AL38) -> 12886.34 | AM39: =SUM(AM37:AM38) -> 13913.48 | AO39: Reserves and Surplus | AP39: 10395.8 | AQ39: 11441.9 | AR39: 19451.1 | AS39: 20562.8 | AT39: 24778.8
A40: Lease Liabilities | B40: 59.8 | C40: 39.2 | D40: 32.9 | E40: 24.9 | F40: 67.7 | G40: 53.8 | I40: Liabilities | Q40: Equity attributable to owners of the company | R40: =SUM(R38:R39) -> 63078.53 | S40: =SUM(S38:S39) -> 55246.72 | T40: =SUM(T38:T39) -> 44561.24 | U40: =SUM(U38:U39) -> 45321.79 | V40: =SUM(V38:V39) -> 84918 | W40: =SUM(W38:W39) -> 116144 | Y40: Total Equity | Z40: =Z38+Z39 -> 3603.04 | AA40: =AA38+AA39 -> 4214.51 | AB40: =AB38+AB39 -> 5053.01 | AC40: =AC38+AC39 -> 5909.85 | AD40: =AD38+AD39 -> 7511.11 | AE40: =AE38+AE39 -> 0 | AG40: Non-controlling interest | AH40: 46.94 | AI40: 46.22 | AJ40: 40.21 | AK40: 9.02 | AL40: 15.16 | AM40: 20.64 | AO40: Other reserves | AP40: 549.3 | AQ40: 802.9 | AR40: 685.4 | AS40: 1211.1 | AT40: 698.5
A41: Provisions | B41: 51.6 | C41: 44.7 | D41: 84.4 | E41: 88.4 | F41: 144.8 | G41: 126 | I41: Non-current liabilities | Q41: Non-controlling interest | R41: 813.56 | S41: 1573.49 | T41: 4271.06 | U41: 7277.72 | V41: 8176 | W41: 6610 | Y41: Liabilities | AG41: Total Equity | AH41: =AH39+AH40 -> 6514.26 | AI41: =AI39+AI40 -> 7318.49 | AJ41: =AJ39+AJ40 -> 10623.95 | AK41: =AK39+AK40 -> 11141.3 | AL41: =AL39+AL40 -> 12901.5 | AM41: =AM39+AM40 -> 13934.12 | AO41: Equity attributable to owners of the company | AP41: =AP37+AP39+AP40 -> 11260.9 | AQ41: =AQ37+AQ39+AQ40 -> 12560.6 | AR41: =AR37+AR39+AR40 -> 20588.3 | AS41: =AS37+AS39+AS40 -> 22451.5 | AT41: =AT37+AT39+AT40 -> 26154.9 | AU41: =AU37+AU39+AU40 -> 0
A42: Deferred tax liabilities (net) | B42: 657.5 | C42: 445.4 | D42: 0 | E42: 0 | F42: 0 | G42: 1291.1 | I42: Financial Liabilities | Q42: Total Equity | R42: =R40+R41 -> 63892.09 | S42: =S40+S41 -> 56820.21 | T42: =T40+T41 -> 48832.3 | U42: =U40+U41 -> 52599.51 | V42: =V40+V41 -> 93094 | W42: =W40+W41 -> 122754 | Y42: Non-current liabilities | AG42: Liabilities | AO42: Non-controlling interests | AP42: 3565 | AQ42: 4023.3 | AR42: 1776.3 | AS42: 1925.4 | AT42: 2060.6
A43: Other non-current liabilities | B43: 2115.8 | C43: 2129.5 | D43: 2181.2 | E43: 2585 | F43: 3161.6 | G43: 3381.9 | I43: Borrowings | J43: 52298.05 | K43: 54906.56 | L43: 48625.06 | M43: 55027.39 | N43: 67719.69 | O43: 79707.19 | Q43: Liabilities | Y43: Financial Liabilities | AG43: Non-current liabilities | AO43: Total equity | AP43: =AP41+AP42 -> 14825.9 | AQ43: =AQ41+AQ42 -> 16583.9 | AR43: =AR41+AR42 -> 22364.6 | AS43: =AS41+AS42 -> 24376.9 | AT43: =AT41+AT42 -> 28215.5 | AU43: =AU41+AU42 -> 0
A44: Total non-current liabilities | B44: =SUM(B39:B43) -> 2890.1 | C44: =SUM(C39:C43) -> 2661.6 | D44: =SUM(D39:D43) -> 2298.5 | E44: =SUM(E39:E43) -> 2698.3 | F44: =SUM(F39:F43) -> 3374.1 | G44: =SUM(G39:G43) -> 4852.8 | I44: Other financial liabilities | J44: 1781.4 | K44: 1595.21 | L44: =2432.55+1406.04 -> 3838.59 | M44: =2882.5+1370.45 -> 4252.95 | N44: =2021.73+2813.92+1208.5 -> 6044.15 | O44: =4075.27+3170.14+1127.76 -> 8373.17 | Q44: Non-current liabilities | Y44: Borrowings | Z44: 5221.23 | AA44: 6280.26 | AB44: 7305.77 | AC44: 9064.08 | AD44: 12629.32 | AG44: Financial Liabilities | AO44: Liabilities
A45: Current Liabilities | I45: Trade payables | J45: 10.25 | K45: 1.44 | L45: 1.55 | M45: 0.04 | N45: 0 | O45: 0 | Q45: Financial Liabilities | Y45: Lease liabilities | Z45: 194.28 | AA45: 184.76 | AB45: 403.05 | AC45: 563.51 | AD45: 503.68 | AG45: Borrowings | AH45: 8.85 | AI45: 85.58 | AJ45: 82.36 | AK45: 141.29 | AL45: 221.54 | AM45: 943.07 | AO45: Non-current liabilities
A46: Financial Liabilities | I46: Provisions | J46: 4384.13 | K46: 1600.88 | L46: 1497.99 | M46: 1815.95 | N46: 1763.28 | O46: 1982.02 | Q46: Borrowings | R46: 83315.62 | S46: 93112.77 | T46: 97759.17 | U46: 88695.81 | V46: 62149 | W46: 40217 | Y46: Others | Z46: 9.84 | AA46: 26.11 | AB46: =9.85+44.88 -> 54.73 | AC46: 37.14 | AD46: 31.5 | AG46: Lease Liabilities | AH46: 101.56 | AI46: 341.19 | AJ46: 301.27 | AK46: 299.11 | AL46: 412.44 | AM46: 441.22 | AO46: Financial Liabilities
A47: Borrowings | B47: 106.3 | C47: 488.8 | D47: 381.9 | E47: 1215.8 | F47: 33.1 | G47: 0 | I47: Deferred tax liabilities (net) | J47: 1511.89 | K47: 1494.16 | L47: 1786.1 | M47: 1608.64 | N47: 1772.13 | O47: 1912.07 | Q47: Lease Liabilities | R47: 5162.94 | S47: 5412.06 | T47: 5962.44 | U47: 7568.49 | V47: 7670 | W47: 7642 | Y47: Provisions | Z47: 131.42 | AA47: 159.44 | AB47: 196.24 | AC47: 231.26 | AD47: 270.18 | AG47: Trade Payables | AO47: Borrowings | AP47: 8261.2 | AQ47: 7468.7 | AR47: 8500.7 | AS47: 6618.3 | AT47: 9980.6
A48: Trade Payables | I48: Other non-current liabilities | J48: 5350.37 | K48: 4766 | L48: 5249.92 | M48: 5525.28 | N48: 5946.49 | O48: 6191.81 | Q48: Provisions | R48: 14736.69 | S48: 13606.76 | T48: 12955.89 | U48: 13196.53 | V48: 16537 | W48: 20935 | Y48: Deferred tax liabilities (net) | Z48: 173.77 | AA48: 218.9 | AB48: 207.56 | AC48: 208.37 | AD48: 196.46 | AG48: Total outstanding dues of micro & small enterprises | AH48: 0 | AI48: 0 | AJ48: 0 | AK48: 0 | AL48: 0 | AM48: 0 | AO48: Lease liabilities | AP48: 1030 | AQ48: 942.2 | AR48: 1007 | AS48: 1205.6 | AT48: 1924.7
A49: Total outstanding dues of micro & small enterprises | B49: 48.1 | C49: 69.8 | D49: 108.7 | E49: 176.9 | F49: 0 | G49: 0 | I49: Total Non-current liabilities | J49: =SUM(J43:J48) -> 65336.09 | K49: =SUM(K43:K48) -> 64364.25 | L49: =SUM(L43:L48) -> 60999.21 | M49: =SUM(M43:M48) -> 68230.25 | N49: =SUM(N43:N48) -> 83245.74 | O49: =SUM(O43:O48) -> 98166.26 | Q49: Other financial liabilities | R49: 3858.48 | S49: 2556.35 | T49: 5333.66 | U49: 8322.47 | V49: =2548+1673 -> 4221 | W49: =2464+901 -> 3365 | Y49: Total non-current liabilities | Z49: =SUM(Z44:Z48) -> 5730.54 | AA49: =SUM(AA44:AA48) -> 6869.47 | AB49: =SUM(AB44:AB48) -> 8167.35 | AC49: =SUM(AC44:AC48) -> 10104.36 | AD49: =SUM(AD44:AD48) -> 13631.14 | AE49: =SUM(AE44:AE48) -> 0 | AG49: Total outstanding dues of creditors other than M&S | AH49: 5.74 | AI49: 7.83 | AJ49: 7.87 | AK49: 10.06 | AL49: 10.23 | AM49: 11.89 | AO49: Other financial liabilities | AP49: 379.4 | AQ49: 607.6 | AR49: 481.1 | AS49: 592.1 | AT49: 1059.9
A50: Total outstanding dues of creditors other than M&S | B50: 7450.7 | C50: 10098.3 | D50: 9656.5 | E50: 11608.6 | F50: 14582.4 | G50: 17421.1 | I50: Current Liabilities | Q50: Deferred tax liabilities (net) | R50: 1941.87 | S50: 1555.89 | T50: 1558.44 | U50: 1406.95 | V50: 1143 | W50: 1669 | Y50: Current Liabilities | AG50: Other financial liabilities | AH50: 7.34 | AI50: 8.61 | AJ50: 7.52 | AK50: 76.43 | AL50: 86.66 | AM50: 71.94 | AO50: Provisions | AP50: 83.5 | AQ50: 148.2 | AR50: 134.8 | AS50: 76.6 | AT50: 126
A51: Lease Liabilities | B51: 10.3 | C51: 7.4 | D51: 8 | E51: 6.6 | F51: 17.8 | G51: 22.6 | I51: Financial Liabilities | Q51: Other non-current liabilities | R51: 8759.52 | S51: 12312.56 | T51: 7535.22 | U51: 9264.29 | V51: 12234 | W51: 15376 | Y51: Financial Liabilities | AG51: Provisions | AH51: 72.54 | AI51: 63.96 | AJ51: 61.6 | AK51: 65.2 | AL51: 69.2 | AM51: 100.89 | AO51: Employee benefit obligations | AP51: 471.9 | AQ51: 491.4 | AR51: 546.6 | AS51: 515.6 | AT51: 746.9
A52: Other financial liabilities | B52: 904 | C52: 1272 | D52: 2027.2 | E52: 1853.7 | F52: 1942.6 | G52: 2443.4 | I52: Borrowings | J52: 10217.53 | K52: 4646.59 | L52: 26042.12 | M52: 33739.62 | N52: 35483.54 | O52: 41465.76 | Q52: Total non-current liabilities | R52: =SUM(R46:R51) -> 117775.12 | S52: =SUM(S46:S51) -> 128556.39 | T52: =SUM(T46:T51) -> 131104.82 | U52: =SUM(U46:U51) -> 128454.54 | V52: =SUM(V46:V51) -> 103954 | W52: =SUM(W46:W51) -> 89204 | Y52: Borrowings | Z52: 3780.7 | AA52: 3069.25 | AB52: 7991.51 | AC52: 12562.15 | AD52: 12657.3 | AG52: Insurance contract liabilities | AH52: 12907.87 | AI52: 14577.63 | AJ52: 0 | AK52: 0 | AL52: 0 | AM52: 0 | AO52: Government grants | AP52: 462.7 | AQ52: 336.3 | AR52: 544.5 | AS52: 521.7 | AT52: 843.9
A53: Provisions | B53: 680.7 | C53: 742.8 | D53: 861.3 | E53: 962.4 | F53: 1206.6 | G53: 1442.3 | I53: Trade Payables | Q53: Current Liabilities | Y53: Trade Payables | AG53: Investment contract liabilities | AH53: 885.45 | AI53: 837.75 | AJ53: 0 | AK53: 0 | AL53: 0 | AM53: 0 | AO53: Deferred tax liabilities (net) | AP53: 243.3 | AQ53: 214.2 | AR53: 239.2 | AS53: 227.5 | AT53: 200.7
A54: Current tax liabilities (net) | B54: 696.2 | C54: 854.7 | D54: 1111.3 | E54: 1158.4 | F54: 1203 | G54: 1273.7 | I54: Total outstanding dues of micro & small enterprises | J54: 147.45 | K54: 151.58 | L54: 195.51 | M54: 363.63 | N54: 459.7 | O54: 926.72 | Q54: Financial Liabilities | Y54: Total outstanding dues of micro & small enterprises | Z54: 121.49 | AA54: 45 | AB54: 69.78 | AC54: 75.83 | AD54: 62.38 | AG54: Deferred tax liabilities (net) | AH54: 107.82 | AI54: 83.1 | AJ54: 8.2 | AK54: 7.73 | AL54: 0.89 | AM54: 12.83 | AO54: Other non-current liabilities | AP54: 167.1 | AQ54: 162.9 | AR54: 166.3 | AS54: 202 | AT54: 203.1
A55: Other current liabilities | B55: 1409.1 | C55: 2586.7 | D55: 2868.6 | E55: 3124.9 | F55: 3943.2 | G55: 4117.6 | I55: Total outstanding dues of creditors other than M&S | J55: 14837.9 | K55: 15354.21 | L55: 18841.04 | M55: 23472.03 | N55: 25205.94 | O55: 29928.58 | Q55: Borrowings | R55: 16362.53 | S55: 21662.79 | T55: 41917.87 | U55: 36964.66 | V55: 36352 | W55: 22282 | Y55: Total outstanding dues of creditors other than M&S | Z55: 3065.35 | AA55: 4253.6 | AB55: 4555.21 | AC55: 5020.84 | AD55: 6575.84 | AG55: Other non-current liabilities | AO55: Total non-current liabilities | AP55: =SUM(AP47:AP54) -> 11099.1 | AQ55: =SUM(AQ47:AQ54) -> 10371.5 | AR55: =SUM(AR47:AR54) -> 11620.2 | AS55: =SUM(AS47:AS54) -> 9959.4 | AT55: =SUM(AT47:AT54) -> 15085.8 | AU55: =SUM(AU47:AU54) -> 0
A56: Total Current Liabilities | B56: =SUM(B47,B49:B55) -> 11305.4 | C56: =SUM(C47,C49:C55) -> 16120.5 | D56: =SUM(D47,D49:D55) -> 17023.5 | E56: =SUM(E47,E49:E55) -> 20107.3 | F56: =SUM(F47,F49:F55) -> 22928.7 | G56: =SUM(G47,G49:G55) -> 26720.7 | I56: Lease Liabilities | J56: 0 | K56: 0 | L56: 505.48 | M56: 597.34 | N56: 608.37 | O56: 606.22 | Q56: Trade Payables | Y56: Lease liabilities | Z56: 47.62 | AA56: 63.66 | AB56: 126.88 | AC56: 185.84 | AD56: 215.4 | AG56: Fund for discontinued policies | AH56: 163.52 | AI56: 164.22 | AJ56: 0 | AK56: 2.17 | AL56: 0 | AM56: 0 | AO56: Current Liabilities
A57: Total Liabilities | B57: =B44+B56 -> 14195.5 | C57: =C44+C56 -> 18782.1 | D57: =D44+D56 -> 19322 | E57: =E44+E56 -> 22805.6 | F57: =F44+F56 -> 26302.8 | G57: =G44+G56 -> 31573.5 | I57: Other financial liabilities | J57: 23852.06 | K57: 25913.4 | L57: 4422.25 | M57: 4424.94 | N57: 4480.96 | O57: 5542.63 | Q57: Total outstanding dues of micro & small enterprises | R57: 109.75 | S57: 186.21 | T57: 183.92 | U57: 316.01 | V57: 502 | W57: 452 | Y57: Other financial liabilities | Z57: 2538.37 | AA57: 2904.22 | AB57: 325.71 | AC57: 355.6 | AD57: 459.58 | AG57: Fund for future appropriation | AH57: 341.09 | AI57: 393.94 | AJ57: 0 | AK57: 0 | AL57: 0 | AM57: 0 | AO57: Financial Liabilities
A58: Total Equity and Liabilities | B58: =B35+B57 -> 63627.7 | C58: =C35+C57 -> 71282.7 | D58: =D35+D57 -> 74655.5 | E58: =E35+E57 -> 84596.9 | F58: =F35+F57 -> 110284.8 | G58: =G35+G57 -> 125620.2 | I58: Provisions | J58: 1751.54 | K58: 1074.34 | L58: 968.19 | M58: 1189.48 | N58: 1123 | O58: 1313.8 | Q58: Total outstanding dues of creditors other than M&S | R58: 63517.13 | S58: 67993.63 | T58: 59786.46 | U58: 71739.76 | V58: 87540 | W58: 93626 | Y58: Provisions | Z58: 90.57 | AA58: 85.34 | AB58: 107.42 | AC58: 115.74 | AD58: 166.64 | AG58: Total Non-current liabilities | AH58: =SUM(AH45:AH46,AH48:AH54,AH56:AH57) -> 14601.78 | AI58: =SUM(AI45:AI46,AI48:AI54,AI56:AI57) -> 16563.81 | AJ58: =SUM(AJ45:AJ46,AJ48:AJ54,AJ56:AJ57) -> 468.82 | AK58: =SUM(AK45:AK46,AK48:AK54,AK56:AK57) -> 601.99 | AL58: =SUM(AL45:AL46,AL48:AL54,AL56:AL57) -> 800.96 | AM58: =SUM(AM45:AM46,AM48:AM54,AM56:AM57) -> 1581.84 | AO58: Borrowings | AP58: 3407.9 | AQ58: 1357.5 | AR58: 4260.2 | AS58: 5547.4 | AT58: 7370.7
I59: Current tax liabilities (net) | J59: 300.99 | K59: 438.82 | L59: 392.02 | M59: 615.99 | N59: 542.52 | O59: 719.68 | Q59: Acceptances | R59: 2771.33 | S59: 7860.31 | T59: 9779.95 | U59: 7195.99 | V59: 5936 | W59: 3290 | Y59: Current tax liabilities (net) | Z59: 0 | AA59: 0 | AB59: 0 | AC59: 16.05 | AD59: 34.58 | AG59: Current Liabilities | AO59: Lease liabilities | AP59: 336.3 | AQ59: 324.2 | AR59: 361.8 | AS59: 421 | AT59: 645.9
B60: =B27-B56 -> -2864.8 | F60: =F27-F56 -> -5166.3 | G60: =G27-G56 -> -3468.5 | I60: Other current liabilities | J60: 2902.05 | K60: 3867.07 | L60: 4921.72 | M60: 6176.38 | N60: 7641.62 | O60: 9818.62 | Q60: Lease Liabilities | R60: 814.18 | S60: 814 | T60: 809.55 | U60: 884.48 | V60: 1093 | W60: 1399 | Y60: Other current liabilities | Z60: 381.14 | AA60: 487.64 | AB60: 675.21 | AC60: 886.65 | AD60: 906.49 | AG60: Financial Liabilities | AO60: Trade payables | AP60: 10309.1 | AQ60: 11140.6 | AR60: 11360.3 | AS60: 14136.3 | AT60: 22617.2
I61: Total Current Liabilities | J61: =SUM(J52,J54:J60) -> 54009.52 | K61: =SUM(K52,K54:K60) -> 51446.01 | L61: =SUM(L52,L54:L60) -> 56288.33 | M61: =SUM(M52,M54:M60) -> 70579.41 | N61: =SUM(N52,N54:N60) -> 75545.65 | O61: =SUM(O52,O54:O60) -> 90322.01 | Q61: Other financial liabilities | R61: 36544 | S61: 34854.59 | T61: 14420.24 | U61: 13828.58 | V61: 15385 | W61: 14318 | Y61: Total Current Liabilities | Z61: =SUM(Z52,Z54:Z60) -> 10025.24 | AA61: =SUM(AA52,AA54:AA60) -> 10908.71 | AB61: =SUM(AB52,AB54:AB60) -> 13851.72 | AC61: =SUM(AC52,AC54:AC60) -> 19218.7 | AD61: =SUM(AD52,AD54:AD60) -> 21078.21 | AE61: =SUM(AE52,AE54:AE60) -> 0 | AG61: Borrowings | AH61: 58.53 | AI61: 46.67 | AJ61: 126.87 | AK61: 138.09 | AL61: 475.42 | AM61: 618.1 | AO61: Other financial liabilities | AP61: 3308.2 | AQ61: 4919.6 | AR61: 3317.9 | AS61: 4258 | AT61: 5333.1
I62: Total Liabilities | J62: =J49+J61 -> 119345.61 | K62: =K49+K61 -> 115810.26 | L62: =L49+L61 -> 117287.54 | M62: =M49+M61 -> 138809.66 | N62: =N49+N61 -> 158791.39 | O62: =O49+O61 -> 188488.27 | Q62: Provisions | R62: 10329.04 | S62: 12848.03 | T62: 10766.31 | U62: 11810.66 | V62: 12291 | W62: 15831 | Y62: Total Liabilities | Z62: =Z49+Z61 -> 15755.78 | AA62: =AA49+AA61 -> 17778.18 | AB62: =AB49+AB61 -> 22019.07 | AC62: =AC49+AC61 -> 29323.06 | AD62: =AD49+AD61 -> 34709.35 | AE62: =AE49+AE61 -> 0 | AG62: Trade Payables | AO62: Provisions | AP62: 207.7 | AQ62: 496.8 | AR62: 481.5 | AS62: 470.4 | AT62: 1043
I63: Total Equity and Liabilities | J63: =J39+J62 -> 167006.66 | K63: =K39+K62 -> 166462.49 | L63: =L39+L62 -> 174112.8 | M63: =M39+M62 -> 205891.77 | N63: =N39+N62 -> 236300.73 | O63: =O39+O62 -> 277586.27 | Q63: Current tax liabilities (net) | R63: 1040.14 | S63: 1086.44 | T63: =1253.85+3.12 -> 1256.97 | U63: 1254.19 | V63: 1527 | W63: 2146 | Y63: Total Equity and Liabilities | Z63: =Z40+Z62 -> 19358.82 | AA63: =AA40+AA62 -> 21992.69 | AB63: =AB40+AB62 -> 27072.08 | AC63: =AC40+AC62 -> 35232.91 | AD63: =AD40+AD62 -> 42220.46 | AE63: =AE40+AE62 -> 0 | AG63: Total outstanding dues of micro & small enterprises | AH63: 132.78 | AI63: 287.46 | AJ63: 247.96 | AK63: 262.99 | AL63: 140.12 | AM63: 151.65 | AO63: Employee benefit obligations | AP63: 225.8 | AQ63: 201.4 | AR63: 228 | AS63: 257.3 | AT63: 414.2
Q64: Other current liabilities | R64: 8965.95 | S64: 10443.18 | T64: 11761.54 | U64: 11033 | V64: 12990 | W64: 13340 | AG64: Total outstanding dues of creditors other than M&S | AH64: 1472.79 | AI64: 2086.21 | AJ64: 1598.37 | AK64: 1592.62 | AL64: 2567.62 | AM64: 3193.31 | AO64: Government grants | AP64: 35.7 | AQ64: 45.5 | AR64: 47.5 | AS64: 51.1 | AT64: 31.5
J65: =J31-J61 -> 10035.91 | N65: =N31-N61 -> 22719.99 | O65: =O31-O61 -> 36251.26 | Q65: Total Current Liabilities | R65: =SUM(R55,R57:R64) -> 140454.05 | S65: =SUM(S55,S57:S64) -> 157749.18 | T65: =SUM(T55,T57:T64) -> 150682.81 | U65: =SUM(U55,U57:U64) -> 155027.33 | V65: =SUM(V55,V57:V64) -> 173616 | W65: =SUM(W55,W57:W64) -> 166684 | Z65: =Z32-Z61 -> -286.24 | AA65: =AA32-AA61 -> -371.87 | AB65: =AB32-AB61 -> -1003.65 | AC65: =AC32-AC61 -> -2194.42 | AD65: =AD32-AD61 -> 441.8 | AG65: Lease liabilities | AH65: 24.29 | AI65: 29.11 | AJ65: 9.01 | AK65: 9.9 | AL65: 13.47 | AM65: 14.32 | AO65: Current tax liabilities (net) | AP65: 362.3 | AQ65: 334.2 | AR65: 390.1 | AS65: 346.3 | AT65: 551.2
Q66: Total Liabilities | R66: =R52+R65 -> 258229.17 | S66: =S52+S65 -> 286305.57 | T66: =T52+T65 -> 281787.63 | U66: =U52+U65 -> 283481.87 | V66: =V52+V65 -> 277570 | W66: =W52+W65 -> 255888 | AG66: Other financial liabilities | AH66: 360.24 | AI66: 347.92 | AJ66: 303.53 | AK66: 395.57 | AL66: 654.87 | AM66: 993.68 | AO66: Other current liabilities | AP66: 1377.8 | AQ66: 1474.5 | AR66: 1838 | AS66: 2027.6 | AT66: 3713.6
Q67: Total Equity and Liabilities | R67: =R42+R66 -> 322121.26 | S67: =S42+S66 -> 343125.78 | T67: =T42+T66 -> 330619.93 | U67: =U42+U66 -> 336081.38 | V67: =V42+V66 -> 370664 | W67: =W42+W66 -> 378642 | AG67: Provisions | AH67: 306.77 | AI67: 280.6 | AJ67: 268.64 | AK67: 288.21 | AL67: 323.27 | AM67: 399 | AO67: Total current liabilities | AP67: =SUM(AP58:AP66) -> 19570.8 | AQ67: =SUM(AQ58:AQ66) -> 20294.3 | AR67: =SUM(AR58:AR66) -> 22285.3 | AS67: =SUM(AS58:AS66) -> 27515.4 | AT67: =SUM(AT58:AT66) -> 41720.4 | AU67: =SUM(AU58:AU66) -> 0
AG68: Current tax liabilities (net) | AH68: 0.63 | AI68: 1.1 | AJ68: 0 | AK68: 1.54 | AL68: 2.32 | AM68: 3.66 | AO68: Liabilities directly associated with the assets held for distribution | AP68: 0 | AQ68: 835.3 | AR68: 0 | AS68: 0
R69: =R34-R65 -> -20867.32 | V69: =V34-V65 -> -5224 | W69: =W34-W65 -> -6359 | AG69: Other current liabilities | AH69: 185.56 | AI69: 224.99 | AJ69: 263.46 | AK69: 335.47 | AL69: 270.47 | AM69: 506.65 | AO69: Total Liabilities | AP69: =AP55+AP67+AP68 -> 30669.9 | AQ69: =AQ55+AQ67+AQ68 -> 31501.1 | AR69: =AR55+AR67+AR68 -> 33905.5 | AS69: =AS55+AS67+AS68 -> 37474.8 | AT69: =AT55+AT67+AT68 -> 56806.2 | AU69: =AU55+AU67+AU68 -> 0
AG70: Insurance contract liabilities | AH70: 605.39 | AI70: 1361.08 | AJ70: 0 | AK70: 0 | AL70: 0 | AM70: 0 | AO70: Total Equity and Liabilities | AP70: =AP69+AP43 -> 45495.8 | AQ70: =AQ69+AQ43 -> 48085 | AR70: =AR69+AR43 -> 56270.1 | AS70: =AS69+AS43 -> 61851.7 | AT70: =AT69+AT43 -> 85021.7 | AU70: =AU69+AU43 -> 0
AG71: Investment contract liabilities | AH71: 104.57 | AI71: 139.67 | AJ71: 0 | AK71: 0 | AL71: 0 | AM71: 0
AG72: Total current liabilities | AH72: =SUM(AH61,AH63:AH71) -> 3251.55 | AI72: =SUM(AI61,AI63:AI71) -> 4804.81 | AJ72: =SUM(AJ61,AJ63:AJ71) -> 2817.84 | AK72: =SUM(AK61,AK63:AK71) -> 3024.39 | AL72: =SUM(AL61,AL63:AL71) -> 4447.56 | AM72: =SUM(AM61,AM63:AM71) -> 5880.37 | AO72: Working Capital | AP72: =AP32-AP67 -> -105.4 | AQ72: =AQ32-AQ67 -> -45.8 | AR72: =AR32-AR67 -> 330.9 | AS72: =AS32-AS67 -> -736.2 | AT72: =AT32-AT67 -> -1448.2
AG73: Total Liabilities | AH73: =AH58+AH72 -> 17853.33 | AI73: =AI58+AI72 -> 21368.62 | AJ73: =AJ58+AJ72 -> 3286.66 | AK73: =AK58+AK72 -> 3626.38 | AL73: =AL58+AL72 -> 5248.52 | AM73: =AM58+AM72 -> 7462.21
AG74: Total Equity and Liabilities | AH74: =AH73+AH41 -> 24367.59 | AI74: =AI73+AI41 -> 28687.11 | AJ74: =AJ73+AJ41 -> 13910.61 | AK74: =AK73+AK41 -> 14767.68 | AL74: =AL73+AL41 -> 18150.02 | AM74: =AM73+AM41 -> 21396.33
AG76: Working capital | AH76: =AH33-AH72 -> 2158.4 | AI76: =AI33-AI72 -> 1451.12 | AJ76: =AJ33-AJ72 -> 2303.41 | AK76: =AK33-AK72 -> 2666.6 | AL76: =AL33-AL72 -> 1803.96 | AM76: =AM33-AM72 -> 1323.68

Sheet Income Statement
A1: INCOME STATEMENT | F1: #VALUE! | I1: INCOME STATEMENT | N1: #VALUE! | Q1: INCOME STATEMENT | V1: #VALUE! | Y1: INCOME STATEMENT | AD1: #VALUE! | AG1: INCOME STATEMENT | AL1: #VALUE! | AO1: INCOME STATEMENT | AT1: #VALUE!
A2: Particulars | B2: 2020 | C2: 2021 | D2: 2022 | E2: 2023 | F2: 2024 | G2: 2025 | I2: Particulars | J2: 2020 | K2: 2021 | L2: 2022 | M2: 2023 | N2: 2024 | O2: 2025 | Q2: Particulars | R2: 2020 | S2: 2021 | T2: 2022 | U2: 2023 | V2: 2024 | W2: 2025 | Y2: Particulars | Z2: 2020 | AA2: 2021 | AB2: 2022 | AC2: 2023 | AD2: 2024 | AE2: NA | AG2: Particulars | AH2: 2020 | AI2: 2021 | AJ2: 2022 | AK2: 2023 | AL2: 2024 | AM2: 2025 | AO2: Particulars | AP2: 2020 | AQ2: 2021 | AR2: 2022 | AS2: 2023 | AT2: 2024 | AU2: NA
A3: INCOME | I3: INCOME | Q3: INCOME | Y3: INCOME | AG3: INCOME | AO3: INCOME
A4: Revenue from operations | B4: 75660 | C4: 70372 | D4: 88329.8 | E4: 117571.3 | F4: 134937.8 | G4: 145115.2 | I4: Revenue from operations | J4: 75381.93 | K4: 74277.78 | L4: 90170.57 | M4: 121268.55 | N4: 138279.3 | O4: 158749.75 | Q4: Revenue from operations | R4: 258594.36 | S4: 246972.17 | T4: 275235.23 | U4: 342874.59 | V4: 431212 | W4: 436821 | Y4: Revenue from operations | Z4: 18849.31 | AA4: 19420.82 | AB4: 24355.31 | AC4: 31973.99 | AD4: 39144.74 | AG4: Revenue from operations | AH4: 14471.01 | AI4: 15296.89 | AJ4: 12789.22 | AK4: 15078.16 | AL4: 16769.73 | AM4: 17237.85 | AO4: Revenue from operations | AP4: 60278.3 | AQ4: 56951.3 | AR4: 62936.7 | AS4: 77870.7 | AT4: 97779.4
A5: Other income | B5: 3334.4 | C5: 2936.3 | D5: 1744.7 | E5: 2140.7 | F5: =5994.8+3854.7 -> 9849.5 | G5: =6784.9+4750.4 -> 11535.3 | I5: Other income | J5: 1028.69 | K5: 1033.11 | L5: 934.51 | M5: 1206.49 | N5: =798.97+2176.42 -> 2975.39 | O5: =461.07+2181.05 -> 2642.12 | Q5: Other Operating revenues | R5: 2473.61 | S5: 2822.58 | T5: 3218.39 | U5: 3092.38 | V5: 2804 | W5: 2874 | Y5: Other income | Z5: 51.83 | AA5: 47.22 | AB5: 32.87 | AC5: 138 | AD5: 105.82 | AG5: Other income | AH5: 61.88 | AI5: 70.45 | AJ5: 62.07 | AK5: 124.74 | AL5: 89.95 | AM5: 112.8 | AO5: Other operating revenue | AP5: 450.6 | AQ5: 418.6 | AR5: 837.3 | AS5: 830 | AT5: 912.3
A6: Total income | B6: =B4+B5 -> 78994.4 | C6: =C4+C5 -> 73308.3 | D6: =D4+D5 -> 90074.5 | E6: =E4+E5 -> 119712 | F6: =F4+F5 -> 144787.3 | G6: =G4+G5 -> 156650.5 | I6: Total income | J6: =SUM(J4:J5) -> 76410.62 | K6: =SUM(K4:K5) -> 75310.89 | L6: =SUM(L4:L5) -> 91105.08 | M6: =SUM(M4:M5) -> 122475.04 | N6: =SUM(N4:N5) -> 141254.69 | O6: =SUM(O4:O5) -> 161391.87 | Q6: Total revenue from operations | R6: =SUM(R4:R5) -> 261067.97 | S6: =SUM(S4:S5) -> 249794.75 | T6: =SUM(T4:T5) -> 278453.62 | U6: =SUM(U4:U5) -> 345966.97 | V6: =SUM(V4:V5) -> 434016 | W6: =SUM(W4:W5) -> 439695 | Y6: Total income | Z6: =Z4+Z5 -> 18901.14 | AA6: =AA4+AA5 -> 19468.04 | AB6: =AB4+AB5 -> 24388.18 | AC6: =AC4+AC5 -> 32111.99 | AD6: =AD4+AD5 -> 39250.56 | AE6: =AE4+AE5 -> 0 | AG6: Total income | AH6: =SUM(AH4:AH5) -> 14532.89 | AI6: =SUM(AI4:AI5) -> 15367.34 | AJ6: =SUM(AJ4:AJ5) -> 12851.29 | AK6: =SUM(AK4:AK5) -> 15202.9 | AL6: =SUM(AL4:AL5) -> 16859.68 | AM6: =SUM(AM4:AM5) -> 17350.65 | AO6: Total revenue from operations | AP6: =SUM(AP4:AP5) -> 60728.9 | AQ6: =SUM(AQ4:AQ5) -> 57369.9 | AR6: =SUM(AR4:AR5) -> 63774 | AS6: =SUM(AS4:AS5) -> 78700.7 | AT6: =SUM(AT4:AT5) -> 98691.7 | AU6: =SUM(AU4:AU5) -> 0
A7: EXPENSES | I7: EXPENSES | Q7: Other income (includes government grants) | R7: 2973.15 | S7: 2643.19 | T7: 3053.63 | U7: 4633.18 | V7: 5692 | W7: 6244 | Y7: EXPENSES | AG7: EXPENSES | AO7: Other income | AP7: 224.6 | AQ7: 229.3 | AR7: 257.7 | AS7: 257 | AT7: 187.6
A8: Cost of material consumed | B8: 34634.8 | C8: 33296.4 | D8: 39739.6 | E8: 46669.6 | F8: 45939.7 | G8: 52927.1 | I8: Cost of materials consumed | J8: 32321.8 | K8: 32797.56 | L8: 46265.48 | M8: 68477.97 | N8: 77848.82 | O8: 88111.05 | Q8: Total income | R8: =R6+R7 -> 264041.12 | S8: =S6+S7 -> 252437.94 | T8: =T6+T7 -> 281507.25 | U8: =U6+U7 -> 350600.15 | V8: =V6+V7 -> 439708 | W8: =W6+W7 -> 445939 | Y8: Cost of materials consumed | Z8: 12050.84 | AA8: 12700.73 | AB8: 15938.65 | AC8: 20096.24 | AD8: 23717.91 | AG8: Cost of materials consumed | AH8: 6567.39 | AI8: 6645.5 | AJ8: 8882.49 | AK8: 10585.52 | AL8: 11481.61 | AM8: 11697.3 | AO8: Total income | AP8: =SUM(AP6:AP7) -> 60953.5 | AQ8: =SUM(AQ6:AQ7) -> 57599.2 | AR8: =SUM(AR6:AR7) -> 64031.7 | AS8: =SUM(AS6:AS7) -> 78957.7 | AT8: =SUM(AT6:AT7) -> 98879.3 | AU8: =SUM(AU6:AU7) -> 0
A9: Purchase of stock-in-trade | B9: 18767.2 | C9: 17254.1 | D9: 26397.5 | E9: 39985.1 | F9: 55109.9 | G9: 56434 | I9: Purchase of stock-in-trade | J9: 5273.5 | K9: 5473.64 | L9: 6399.37 | M9: 7541.9 | N9: 7221.25 | O9: 7643.85 | Q9: EXPENSES | Y9: Purchase of stock in trade | Z9: 259.2 | AA9: 224.92 | AB9: 579.04 | AC9: 890.95 | AD9: 1011.69 | AG9: Purchase of stock-in-trade | AH9: 54.25 | AI9: 41.77 | AJ9: 63.92 | AK9: 77.77 | AL9: 216.31 | AM9: 119.62 | AO9: EXPENSES
A10: Change in inventories of finished good, work-in-progress and SIT | B10: -238.7 | C10: 273.6 | D10: -93.1 | E10: -403.9 | F10: -442.9 | G10: -890.3 | I10: Changes in inventory of finished goods, stock in trade and work in progress | J10: 826.62 | K10: 135.59 | L10: -861.66 | M10: -2032.31 | N10: -1455.32 | O10: -12.18 | Q10: Cost of materials consumed | Y10: Changes in inventories of finished goods, stock-in-trade and work in progress | Z10: 6.73 | AA10: -0.19 | AB10: -260.4 | AC10: -140.93 | AD10: -324.35 | AG10: Changes in inventories of finished goods, work-in-progress and stock-in-trade | AH10: -219.14 | AI10: 0.13 | AJ10: -269.63 | AK10: -310 | AL10: -300.33 | AM10: -219.5 | AO10: Cost of materials consumed | AP10: 34285 | AQ10: 32675.8 | AR10: 36804.9 | AS10: 45175.5 | AT10: 53899.7
A11: Employee benefit expenses | B11: 3416.2 | C11: 3431.6 | D11: 4051.4 | E11: 4634.6 | F11: 5478.4 | G11: 6137 | I11: Employee benefit expense | J11: 8214.82 | K11: 7813.26 | L11: 8386.74 | M11: 9677.95 | N11: 10624.33 | O11: 11126.17 | Q11: Cost of materials consumed | R11: 152968.74 | S11: 141392.43 | T11: 159598.06 | U11: 208218.05 | V11: 249278 | W11: 241148 | Y11: Employee benefit expense | Z11: 1539.35 | AA11: 1689.37 | AB11: 2124.03 | AC11: 2890.25 | AD11: 3385.19 | AG11: Employee benefit expenses | AH11: 1118.93 | AI11: 1122.49 | AJ11: 906.36 | AK11: 1002.62 | AL11: 1166.63 | AM11: 1296.31 | AO11: Purchase of stock-in-trade | AP11: 710 | AQ11: 103.3 | AR11: 182.8 | AS11: 465.4 | AT11: 468.2
A12: Finance costs | B12: 134.2 | C12: 101.8 | D12: 126.6 | E12: 187 | F12: 193.2 | G12: 193.1 | I12: Finance cost | J12: 6021.15 | K12: 6102.22 | L12: 5018.05 | M12: 5829.7 | N12: 7488.21 | O12: 9083.39 | Q12: Basis adjustment on hedge accounted derivatives | R12: -297.27 | S12: -35.16 | T12: 1322.5 | U12: 726.26 | V12: 0 | W12: 0 | Y12: Finance costs | Z12: 854.54 | AA12: 881.49 | AB12: 940.22 | AC12: 1367.89 | AD12: 1927.72 | AG12: Other expenses | AH12: =1622.86+3880.66 -> 5503.52 | AI12: =2346.75+3559.83 -> 5906.58 | AJ12: 1806.15 | AK12: 2133.72 | AL12: 2388.42 | AM12: 2546.09 | AO12: Change in inventories of finished goods, WIP and SIT | AP12: -26.2 | AQ12: -181.2 | AR12: -251.4 | AS12: -323.5 | AT12: 46.8
A13: Depreciation and ammortisation expenses | B13: 3528.4 | C13: 3034.1 | D13: 2789 | E13: 2825.7 | F13: 3022.3 | G13: 3159.3 | I13: Depreciation and amortisation expense | J13: 3366.68 | K13: 3378.11 | L13: 3507.5 | M13: 4356.81 | N13: 4723.78 | O13: 6073.65 | Q13: Purchase of products for sale | R13: 12228.35 | S13: 12250.09 | T13: 18374.77 | U13: 22306.95 | V13: 25043 | W13: 27802 | Y13: Depreciation and ammortisation expense | Z13: 556 | AA13: 564.82 | AB13: 742.86 | AC13: 858.86 | AD13: 975.12 | AG13: Total expenses | AH13: =SUM(AH8:AH12) -> 13024.95 | AI13: =SUM(AI8:AI12) -> 13716.47 | AJ13: =SUM(AJ8:AJ12) -> 11389.29 | AK13: =SUM(AK8:AK12) -> 13489.63 | AL13: =SUM(AL8:AL12) -> 14952.64 | AM13: =SUM(AM8:AM12) -> 15439.82 | AO13: Employee benefit expense | AP13: 14372.6 | AQ13: 14099.6 | AR13: 15374.6 | AS13: 17931.4 | AT13: 23538.5
A14: Other expenses | B14: 11889.6 | C14: 10837.5 | D14: 12672.7 | E14: 15805.5 | F14: 18635.2 | G14: 19824 | I14: Other expenses | J14: 15871.2 | K14: 14541.92 | L14: 15297.79 | M14: 17317.75 | N14: =32.92+19914.34 -> 19947.26 | O14: =30.84+21792.9 -> 21823.74 | Q14: Changes in inventories of finished goods, WIP and products for sale | R14: 2231.19 | S14: 4684.16 | T14: 1590.49 | U14: -4781.62 | V14: -1566 | W14: 2836 | Y14: Other expenses | Z14: 2720.14 | AA14: 2568.16 | AB14: 3219.36 | AC14: 4170.1 | AD14: 5810.89 | AG14: EBITDA | AH14: =AH6-AH13 -> 1507.94 | AI14: =AI6-AI13 -> 1650.87 | AJ14: =AJ6-AJ13 -> 1462 | AK14: =AK6-AK13 -> 1713.27 | AL14: =AL6-AL13 -> 1907.04 | AM14: =AM6-AM13 -> 1910.83 | AO14: Depreciation and amortisation expense | AP14: 2721 | AQ14: 2926 | AR14: 2958.2 | AS14: 3135.8 | AT14: 3810.5
A15: Vehicle/dies for own use | B15: -121.7 | C15: -72.8 | D15: -144.5 | E15: -137.3 | F15: -188.8 | G15: -316.9 | I15: (-) Amounts capitalised | J15: 317.58 | K15: 160.74 | L15: 0 | M15: 0 | N15: 0 | O15: 0 | Q15: Employee benefit expense | R15: 30438.6 | S15: 27648.48 | T15: 30808.52 | U15: 33654.7 | V15: 41990 | W15: 47767 | Y15: Total expenses | Z15: =SUM(Z8:Z14) -> 17986.8 | AA15: =SUM(AA8:AA14) -> 18629.3 | AB15: =SUM(AB8:AB14) -> 23283.76 | AC15: =SUM(AC8:AC14) -> 30133.36 | AD15: =SUM(AD8:AD14) -> 36504.17 | AE15: =SUM(AE8:AE14) -> 0 | AG15: Finance costs | AH15: 96.59 | AI15: 142.19 | AJ15: 60.93 | AK15: 73.84 | AL15: 116 | AM15: 153.03 | AO15: Finance cost | AP15: 592.8 | AQ15: 511.5 | AR15: 542.6 | AS15: 780.9 | AT15: 1811.2
A16: Total expenses | B16: =SUM(B8:B15) -> 72010 | C16: =SUM(C8:C15) -> 68156.3 | D16: =SUM(D8:D15) -> 85539.2 | E16: =SUM(E8:E15) -> 109566.3 | F16: =SUM(F8:F15) -> 127747 | G16: =SUM(G8:G15) -> 137467.3 | I16: Total expenses | J16: =SUM(J8:J14)-J15 -> 71578.19 | K16: =SUM(K8:K14)-K15 -> 70081.56 | L16: =SUM(L8:L14)-L15 -> 84013.27 | M16: =SUM(M8:M14)-M15 -> 111169.77 | N16: =SUM(N8:N14)-N15 -> 126398.33 | O16: =SUM(O8:O14)-O15 -> 143849.67 | Q16: Finance cost | R16: 7243.33 | S16: 8097.17 | T16: 9311.86 | U16: 10225.48 | V16: 7594 | W16: 5083 | Y16: Profit before exceptional items, share of net profit/loss from associates and tax | Z16: =Z6-Z15 -> 914.34 | AA16: =AA6-AA15 -> 838.74 | AB16: =AB6-AB15 -> 1104.42 | AC16: =AC6-AC15 -> 1978.63 | AD16: =AD6-AD15 -> 2746.39 | AE16: =AE6-AE15 -> 0 | AG16: Depreciation and ammortisation expenses | AH16: 417.58 | AI16: 433.65 | AJ16: 439.52 | AK16: 502.12 | AL16: 560.42 | AM16: 582.34 | AO16: Other expenses | AP16: 6733.5 | AQ16: 6313.5 | AR16: 6963.7 | AS16: 9244.2 | AT16: 11451.9
A17: Share of profit of associates | B17: 117.5 | C17: 158.8 | D17: 146.4 | E17: 155.8 | F17: 0 | G17: 0 | I17: Profit before exceptional items, share of profit of associates and joint ventures and tax | J17: =J6-J16 -> 4832.43 | K17: =K6-K16 -> 5229.33 | L17: =L6-L16 -> 7091.81 | M17: =M6-M16 -> 11305.27 | N17: =N6-N16 -> 14856.36 | O17: =O6-O16 -> 17542.2 | Q17: Foreign exchange gain/loss (net) | R17: 1738.74 | S17: -1732.15 | T17: 78.68 | U17: -103.88 | V17: 15 | W17: -922 | Y17: Share of net profit/loss from associates using equity method | Z17: -8.59 | AA17: -7.75 | AB17: 2.49 | AC17: -40.73 | AD17: -43.47 | AG17: Interest, depreciation and ammortisation expenses | AH17: =SUM(AH15:AH16) -> 514.17 | AI17: =SUM(AI15:AI16) -> 575.84 | AJ17: =SUM(AJ15:AJ16) -> 500.45 | AK17: =SUM(AK15:AK16) -> 575.96 | AL17: =SUM(AL15:AL16) -> 676.42 | AM17: =SUM(AM15:AM16) -> 735.37 | AO17: Total expenses | AP17: =SUM(AP10:AP16) -> 59388.7 | AQ17: =SUM(AQ10:AQ16) -> 56448.5 | AR17: =SUM(AR10:AR16) -> 62575.4 | AS17: =SUM(AS10:AS16) -> 76409.7 | AT17: =SUM(AT10:AT16) -> 95026.8 | AU17: =SUM(AU10:AU16) -> 0
A18: Share of profit of joint ventures | B18: 0.9 | C18: 10.2 | D18: 15.5 | E18: 21.6 | F18: 0 | G18: 0 | I18: Exceptional items (net) | J18: -1171.28 | K18: -1158.26 | L18: 414.17 | M18: 1249.52 | N18: 0 | O18: 0 | Q18: Depreciation and ammortisation expense | R18: 21425.43 | S18: 23546.71 | T18: 24835.69 | U18: 24860.36 | V18: 27239 | W18: 23256 | Y18: Profit before exceptional items and tax | Z18: =Z16+Z17 -> 905.75 | AA18: =AA16+AA17 -> 830.99 | AB18: =AB16+AB17 -> 1106.91 | AC18: =AC16+AC17 -> 1937.9 | AD18: =AD16+AD17 -> 2702.92 | AE18: =AE16+AE17 -> 0 | AG18: Share of loss of equity accounted investees, net of tax | AH18: -0.19 | AI18: -0.64 | AJ18: -0.94 | AK18: 0.28 | AL18: 0.55 | AM18: 0.5 | AO18: Profit before exceptional items, share of profit of investments accounted for using equity method and tax | AP18: =AP8-AP17 -> 1564.8 | AQ18: =AQ8-AQ17 -> 1150.7 | AR18: =AR8-AR17 -> 1456.3 | AS18: =AS8-AS17 -> 2548 | AT18: =AT8-AT17 -> 3852.5 | AU18: =AU8-AU17 -> 0
A19: Profit/Loss before tax | B19: =(B6-B16)+B17+B18 -> 7102.8 | C19: =(C6-C16)+C17+C18 -> 5321 | D19: =(D6-D16)+D17+D18 -> 4697.2 | E19: =(E6-E16)+E17+E18 -> 10323.1 | F19: =(F6-F16)+F17+F18 -> 17040.3 | G19: =(G6-G16)+G17+G18 -> 19183.2 | I19: Share of profit associates and joint ventures, (net) | J19: 1027.28 | K19: 1276.66 | L19: 1855.79 | M19: 1505.44 | N19: 1121.43 | O19: 1537.42 | Q19: Product development/engineering expenses | R19: 4188.49 | S19: 5226.63 | T19: 9209.5 | U19: 10661.96 | V19: 10959 | W19: 10716 | Y19: Exceptional items | Z19: -40.33 | AA19: -9.36 | AB19: -40.12 | AC19: -1.87 | AD19: 0 | AG19: Profit before exceptional items and tax | AH19: =AH14-AH17+AH18 -> 993.58 | AI19: =AI14-AI17+AI18 -> 1074.39 | AJ19: =AJ14-AJ17+AJ18 -> 960.61 | AK19: =AK14-AK17+AK18 -> 1137.59 | AL19: =AL14-AL17+AL18 -> 1231.17 | AM19: =AM14-AM17+AM18 -> 1175.96 | AO19: Exceptional income/expenses | AP19: 0 | AQ19: -62.3 | AR19: 48.1 | AS19: 99.5 | AT19: -249.9
A20: Tax expense | I20: Profit before tax | J20: =SUM(J17:J19) -> 4688.43 | K20: =SUM(K17:K19) -> 5347.73 | L20: =SUM(L17:L19) -> 9361.77 | M20: =SUM(M17:M19) -> 14060.23 | N20: =SUM(N17:N19) -> 15977.79 | O20: =SUM(O17:O19) -> 19079.62 | Q20: Other expenses | R20: 57087.46 | S20: 40921.97 | T20: =47133.85+14.45 -> 47148.3 | U20: =61785.96+13.75 -> 61799.71 | V20: =77198+48 -> 77246 | W20: =85399-84 -> 85315 | Y20: Profit before tax | Z20: =SUM(Z18:Z19) -> 865.42 | AA20: =SUM(AA18:AA19) -> 821.63 | AB20: =SUM(AB18:AB19) -> 1066.79 | AC20: =SUM(AC18:AC19) -> 1936.03 | AD20: =SUM(AD18:AD19) -> 2702.92 | AE20: =SUM(AE18:AE19) -> 0 | AG20: Exceptional items | AH20: -21.7 | AI20: 0 | AJ20: 0 | AK20: 0 | AL20: 0 | AM20: 0 | AO20: Group's share in net profit/loss of associates and Joint ventures | AP20: 57.5 | AQ20: 84.9 | AR20: 16 | AS20: -43.7 | AT20: 237.6
A21: Current tax | B21: 1376.5 | C21: 1156.2 | D21: 1431 | E21: 2249.6 | F21: 3631.1 | G21: 3841.8 | I21: Tax expense | Q21: Amount transferred to capital and other account | R21: -17503.4 | S21: -12849.13 | T21: -14397.29 | U21: -18434.84 | V21: -26758 | W21: -31105 | Y21: Tax expense | AG21: Profit before tax | AH21: =AH19+AH20 -> 971.88 | AI21: =AI19+AI20 -> 1074.39 | AJ21: =AJ19+AJ20 -> 960.61 | AK21: =AK19+AK20 -> 1137.59 | AL21: =AL19+AL20 -> 1231.17 | AM21: =AM19+AM20 -> 1175.96 | AO21: Profit/Loss before tax from continuing operations | AP21: =AP18+AP19+AP20 -> 1622.3 | AQ21: =AQ18+AQ19+AQ20 -> 1173.3 | AR21: =AR18-AR19+AR20 -> 1424.2 | AS21: =AS18-AS19+AS20 -> 2404.8 | AT21: =AT18+AT19+AT20 -> 3840.2 | AU21: =AU18-AU19+AU20 -> 0
A22: Deferred tax | B22: 48.7 | C22: -224.3 | D22: -613.3 | E22: -137.5 | F22: 199.9 | G22: 1386.2 | I22: Current tax | J22: 2314.16 | K22: 2014.89 | L22: -1868.1 | M22: -2742.04 | N22: -3597.39 | O22: -4851.93 | Q22: Total expenses | R22: =SUM(R11:R21) -> 271749.66 | S22: =SUM(S11:S21) -> 249151.2 | T22: =SUM(T11:T21) -> 287881.08 | U22: =SUM(U11:U21) -> 349133.13 | V22: =SUM(V11:V21) -> 411040 | W22: =SUM(W11:W21) -> 411896 | Y22: Current tax | Z22: 294.65 | AA22: 249.76 | AB22: 364.55 | AC22: 703.46 | AD22: 1012.63 | AG22: Tax expense | AO22: Tax expenses
A23: Total tax expense | B23: =SUM(B21:B22) -> 1425.2 | C23: =SUM(C21:C22) -> 931.9 | D23: =SUM(D21:D22) -> 817.7 | E23: =SUM(E21:E22) -> 2112.1 | F23: =SUM(F21:F22) -> 3831 | G23: =SUM(G21:G22) -> 5228 | I23: Deferred tax | J23: -338.55 | K23: -369.08 | L23: -240.66 | M23: 56.29 | N23: -110.58 | O23: -154.52 | Q23: Profit/loss before exceptional items and tax | R23: =R8-R22 -> -7708.54 | S23: =S8-S22 -> 3286.74 | T23: =T8-T22 -> -6373.83 | U23: =U8-U22 -> 1467.02 | V23: =V8-V22 -> 28668 | W23: =W8-W22 -> 34043 | Y23: Deferred tax | Z23: -76.03 | AA23: -35.63 | AB23: -28.64 | AC23: -76.89 | AD23: -88.25 | AG23: Current tax | AH23: 288.02 | AI23: 291.24 | AJ23: 265.86 | AK23: 327.99 | AL23: 393.98 | AM23: 394.41 | AO23: Current tax | AP23: 775.5 | AQ23: 606.6 | AR23: 731.5 | AS23: 940.2 | AT23: 1262.7
A24: Profit/Loss for the year | B24: =B19-B23 -> 5677.6 | C24: =C19-C23 -> 4389.1 | D24: =D19-D23 -> 3879.5 | E24: =E19-E23 -> 8211 | F24: =F19-F23 -> 13209.3 | G24: =G19-G23 -> 13955.2 | I24: Total tax expense | J24: =SUM(J22:J23) -> 1975.61 | K24: =SUM(K22:K23) -> 1645.81 | L24: =SUM(L22:L23) -> -2108.76 | M24: =SUM(M22:M23) -> -2685.75 | N24: =SUM(N22:N23) -> -3707.97 | O24: =SUM(O22:O23) -> -5006.45 | Q24: Exceptional items | Y24: Total tax expense | Z24: =SUM(Z22:Z23) -> 218.62 | AA24: =SUM(AA22:AA23) -> 214.13 | AB24: =SUM(AB22:AB23) -> 335.91 | AC24: =SUM(AC22:AC23) -> 626.57 | AD24: =SUM(AD22:AD23) -> 924.38 | AE24: =SUM(AE22:AE23) -> 0 | AG24: Deferred tax | AH24: -78.62 | AI24: -19.95 | AJ24: 0.44 | AK24: -13.17 | AL24: -45.63 | AM24: -18.95 | AO24: Deferred tax expense | AP24: -87.4 | AQ24: -676 | AR24: -124.6 | AS24: -205 | AT24: -442.1
I25: Profit/loss for the year from continuing operations | J25: =J20-J24 -> 2712.82 | K25: =K20-K24 -> 3701.92 | L25: =L20+L24 -> 7253.01 | M25: =M20+M24 -> 11374.48 | N25: =N20+N24 -> 12269.82 | O25: =O20+O24 -> 14073.17 | Q25: Defined benefit pension plan amendment past service cost | R25: 0 | S25: 84.81 | T25: 0 | U25: -1495.07 | V25: -700 | W25: -287 | Y25: Profit for the year | Z25: =Z20-Z24 -> 646.8 | AA25: =AA20-AA24 -> 607.5 | AB25: =AB20-AB24 -> 730.88 | AC25: =AC20-AC24 -> 1309.46 | AD25: =AD20-AD24 -> 1778.54 | AE25: =AE20-AE24 -> 0 | AG25: Total tax expense | AH25: =SUM(AH23:AH24) -> 209.4 | AI25: =SUM(AI23:AI24) -> 271.29 | AJ25: =SUM(AJ23:AJ24) -> 266.3 | AK25: =SUM(AK23:AK24) -> 314.82 | AL25: =SUM(AL23:AL24) -> 348.35 | AM25: =SUM(AM23:AM24) -> 375.46 | AO25: Total tax expense | AP25: =SUM(AP23:AP24) -> 688.1 | AQ25: =SUM(AQ23:AQ24) -> -69.4 | AR25: =SUM(AR23:AR24) -> 606.9 | AS25: =SUM(AS23:AS24) -> 735.2 | AT25: =SUM(AT23:AT24) -> 820.6 | AU25: =SUM(AU23:AU24) -> 0
B26: =B19+B12 -> 7237 | G26: =G19+G12 -> 19376.3 | I26: Profit/loss before tax from discontinued operations | J26: -3033.82 | K26: -2189.53 | L26: 0 | M26: 0 | N26: 0 | O26: 0 | Q26: Employee seperation cost | R26: 436.14 | S26: 459.9 | T26: 9.83 | U26: 1.45 | V26: 0 | W26: 0 | Y26: Profit/Loss attributable to non-controlling interest | Z26: -22.18 | AA26: -13.24 | AB26: 25.94 | AC26: 19.21 | AD26: -92.17 | AG26: Profit after tax | AH26: =AH21-AH25 -> 762.48 | AI26: =AI21-AI25 -> 803.1 | AJ26: =AJ21-AJ25 -> 694.31 | AK26: =AK21-AK25 -> 822.77 | AL26: =AL21-AL25 -> 882.82 | AM26: =AM21-AM25 -> 800.5 | AO26: Profit for the year from continuing operations | AP26: =AP21-AP25 -> 934.2 | AQ26: =AQ21-AQ25 -> 1242.7 | AR26: =AR21-AR25 -> 817.3 | AS26: =AS21-AS25 -> 1669.6 | AT26: =AT21-AT25 -> 3019.6 | AU26: =AU21-AU25 -> 0
I27: Tax expense of discontinued operations | J27: 0 | K27: 0 | L27: 0 | M27: 0 | N27: 0 | O27: 0 | Q27: Charge associated with change in JLR strategy | R27: 0 | S27: 14994.3 | T27: 0 | U27: 0 | V27: 0 | W27: 0 | Y27: Profit for the year attributable to owners | Z27: =SUM(Z25:Z26) -> 624.62 | AA27: =SUM(AA25:AA26) -> 594.26 | AB27: =SUM(AB25:AB26) -> 756.82 | AC27: =SUM(AC25:AC26) -> 1328.67 | AD27: =SUM(AD25:AD26) -> 1686.37 | AE27: =SUM(AE25:AE26) -> 0 | AO27: Discontinued operations:
I28: Profit/Loss after tax from discontinued operations | J28: =SUM(J26:J27) -> -3033.82 | K28: =SUM(K26:K27) -> -2189.53 | L28: =SUM(L26:L27) -> 0 | M28: =SUM(M26:M27) -> 0 | N28: =SUM(N26:N27) -> 0 | O28: =SUM(O26:O27) -> 0 | Q28: Write off/provision (reversal) for tangible/intangible assets | R28: -73.04 | S28: 114 | T28: 0 | U28: 229.96 | V28: 0 | W28: 0 | AG28: COGS | AH28: =IF(AH10>=0,AH8+AH9-AH10,AH8+AH9+AH10) -> 6402.5 | AI28: =IF(AI10>=0,AI8+AI9-AI10,AI8+AI9+AI10) -> 6687.14 | AJ28: =IF(AJ10>=0,AJ8+AJ9-AJ10,AJ8+AJ9+AJ10) -> 8676.78 | AK28: =IF(AK10>=0,AK8+AK9-AK10,AK8+AK9+AK10) -> 10353.29 | AL28: =IF(AL10>=0,AL8+AL9-AL10,AL8+AL9+AL10) -> 11397.59 | AM28: =IF(AM10>=0,AM8+AM9-AM10,AM8+AM9+AM10) -> 11597.42 | AO28: Revenue from operations | AP28: 3943.9 | AQ28: 4138.2 | AR28: 3973.5 | AS28: 0 | AT28: 0
I29: Profit/loss after tax from continuing and discontinued operations | J29: =J25+J28 -> -321 | K29: =K25+K28 -> 1512.39 | L29: =L25+L28 -> 7253.01 | M29: =M25+M28 -> 11374.48 | N29: =N25+N28 -> 12269.82 | O29: =O25+O28 -> 14073.17 | Q29: Impairment losses/reversal in passenger vehicle business | R29: 1418.64 | S29: -1182.41 | T29: 0 | U29: 0 | V29: 939 | W29: 550 | Y29: COGS | Z29: =IF(Z10>=0,Z8+Z9-Z10,Z8+Z9+Z10) -> 12303.31 | AA29: =IF(AA10>=0,AA8+AA9-AA10,AA8+AA9+AA10) -> 12925.46 | AB29: =IF(AB10>=0,AB8+AB9-AB10,AB8+AB9+AB10) -> 16257.29 | AC29: =IF(AC10>=0,AC8+AC9-AC10,AC8+AC9+AC10) -> 20846.26 | AD29: =IF(AD10>=0,AD8+AD9-AD10,AD8+AD9+AD10) -> 24405.25 | AG29: EBIT | AH29: =AH14-AH16 -> 1090.36 | AI29: =AI14-AI16 -> 1217.22 | AJ29: =AJ14-AJ16 -> 1022.48 | AK29: =AK14-AK16 -> 1211.15 | AL29: =AL14-AL16 -> 1346.62 | AM29: =AM14-AM16 -> 1328.49 | AO29: Other income | AP29: 6.4 | AQ29: 27.5 | AR29: 20.7 | AS29: 0 | AT29: 0
Q30: Provision/reversal for onerous contracts and supplier claims | R30: 777 | S30: -663 | T30: 0 | U30: -61.03 | V30: 0 | W30: 0 | Y30: EBIT | Z30: =Z16+Z12 -> 1768.88 | AA30: =AA16+AA12 -> 1720.23 | AB30: =AB16+AB12 -> 2044.64 | AC30: =AC16+AC12 -> 3346.52 | AD30: =AD16+AD12 -> 4674.11 | AO30: Total expenses | AP30: 3459.7 | AQ30: 3726.1 | AR30: 3509.6 | AS30: 0 | AT30: 0
J31: =J17+J12 -> 10853.58 | O31: =O17+O12 -> 26625.59 | Q31: Reversal for cost of closure of operation of a subsidiary | R31: -65.62 | S31: -46.58 | T31: -21.47 | U31: 0 | V31: 0 | W31: 0 | AO31: Profit before tax from discontinued operations | AP31: =(AP28+AP29)-AP30 -> 490.6 | AQ31: =(AQ28+AQ29)-AQ30 -> 439.6 | AR31: =(AR28+AR29)-AR30 -> 484.6 | AS31: =(AS28+AS29)-AS30 -> 0 | AT31: =(AT28+AT29)-AT30 -> 0 | AU31: =(AU28+AU29)-AU30 -> 0
Q32: Impairment in subsidiaries | R32: 353.2 | S32: 0 | T32: -86.26 | U32: -214.39 | V32: 0 | W32: 0 | AO32: Tax expense/credit of discontinued operations | AP32: 130.3 | AQ32: 112.9 | AR32: 120.4 | AS32: 0
Q33: Provision for loan given to a joint venture | R33: 25.12 | S33: 0 | T33: =301.34+428.66-2.52 -> 727.48 | U33: =9-60.45 -> -51.45 | V33: 0 | W33: 0 | AO33: Profit/Loss for the year from discontinued operations | AP33: =AP31-AP32 -> 360.3 | AQ33: =AQ31-AQ32 -> 326.7 | AR33: =AR31-AR32 -> 364.2 | AS33: =AS31-AS32 -> 0 | AT33: =AT31-AT32 -> 0 | AU33: =AU31-AU32 -> 0
Q34: Total exceptional items | R34: =SUM(R25:R33) -> 2871.44 | S34: =SUM(S25:S33) -> 13761.02 | T34: =SUM(T25:T33) -> 629.58 | U34: =SUM(U25:U33) -> -1590.53 | V34: =SUM(V25:V33) -> 239 | W34: =SUM(W25:W33) -> 263 | AO34: Profit/Loss for the year from continuing and discontinued operations | AP34: =AP26+AP33 -> 1294.5 | AQ34: =AQ26+AQ33 -> 1569.4 | AR34: =AR26+AR33 -> 1181.5 | AS34: =AS26+AS33 -> 1669.6 | AT34: =AT26+AT33 -> 3019.6 | AU34: =AU26+AU33 -> 0
Q35: Profit/Loss before tax | R35: =R23-R34 -> -10579.98 | S35: =S23-S34 -> -10474.28 | T35: =T23-T34 -> -7003.41 | U35: =U23-U34 -> 3057.55 | V35: =V23-V34 -> 28429 | W35: =W23-W34 -> 33780
Q36: Tax expense | AO36: COGS | AP36: =IF(AP12>=0,AP10+AP11-AP12,AP10+AP11+AP12) -> 34968.8 | AQ36: =IF(AQ12>=0,AQ10+AQ11-AQ12,AQ10+AQ11+AQ12) -> 32597.9 | AR36: =IF(AR12>=0,AR10+AR11-AR12,AR10+AR11+AR12) -> 36736.3 | AS36: =IF(AS12>=0,AS10+AS11-AS12,AS10+AS11+AS12) -> 45317.4 | AT36: =IF(AT12>=0,AT10+AT11-AT12,AT10+AT11+AT12) -> 54321.1
Q37: Current tax (including minimum alternate tax) | R37: 0 | S37: 0 | T37: 2669.98 | U37: 3258.35 | V37: 4937 | W37: 5023 | AO37: EBIT | AP37: =AP18+AP15 -> 2157.6 | AQ37: =AQ18+AQ15 -> 1662.2 | AR37: =AR18+AR15 -> 1998.9 | AS37: =AS18+AS15 -> 3328.9 | AT37: =AT18+AT15 -> 5663.7
Q38: Deferred tax | R38: 0 | S38: 0 | T38: 1561.31 | U38: -2554.29 | V38: -8961 | W38: 5479
Q39: Total tax expense | R39: =SUM(R37:R38) -> 0 | S39: =SUM(S37:S38) -> 0 | T39: =SUM(T37:T38) -> 4231.29 | U39: =SUM(U37:U38) -> 704.06 | V39: =SUM(V37:V38) -> -4024 | W39: =SUM(W37:W38) -> 10502
Q40: Profit/Loss for the year from continuing operations | R40: =R35-R39 -> -10579.98 | S40: =S35-S39 -> -10474.28 | T40: =T35-T39 -> -11234.7 | U40: =U35-U39 -> 2353.49 | V40: =V35-V39 -> 32453 | W40: =W35-W39 -> 23278
Q41: Share of profit/loss of joint ventures and associates (net) | R41: 0 | S41: 0 | T41: -74.06 | U41: 336.38 | V41: -646 | W41: 4871
Q42: Profit/loss for the year | R42: =R40+R41 -> -10579.98 | S42: =S40+S41 -> -10474.28 | T42: =T40+T41 -> -11308.76 | U42: =U40+U41 -> 2689.87 | V42: =V40+V41 -> 31807 | W42: =W40+W41 -> 28149
Q44: COGS | R44: =IF(R14>=0,R11+R13-R14,R11+R13+R14) -> 162965.9 | S44: =IF(S14>=0,S11+S13-S14,S11+S13+S14) -> 148958.36 | T44: =IF(T14>=0,T11+T13-T14,T11+T13+T14) -> 176382.34 | U44: =IF(U14>=0,U11+U13-U14,U11+U13+U14) -> 225743.38 | V44: =IF(V14>=0,V11+V13-V14,V11+V13+V14) -> 272755 | W44: =IF(W14>=0,W11+W13-W14,W11+W13+W14) -> 266114
Q45: EBIT | R45: =R23+R16 -> -465.21 | S45: =S23+S16 -> 11383.91 | T45: =T23+T16 -> 2938.03 | U45: =U23+U16 -> 11692.5 | V45: =V23+V16 -> 36262 | W45: =W23+W16 -> 39126
Q46: Margin | R46: =R45/R4 -> -0.0017989952 | S46: =S45/S4 -> 0.046093898 | T46: =T45/T4 -> 0.010674615 | U46: =U45/U4 -> 0.03410139 | V46: =V45/V4 -> 0.084093207 | W46: =W45/W4 -> 0.08956987

Sheet Cash Flow Statement
A1: CASH FLOW STATEMENT | F1: #VALUE! | I1: CASH FLOW STATEMENT | N1: #VALUE! | Q1: CASH FLOW STATEMENT | V1: #VALUE! | Y1: CASH FLOW STATEMENT | AD1: #VALUE! | AG1: CASH FLOW STATEMENT | AL1: #VALUE! | AO1: CASH FLOW STATEMENT | AT1: #VALUE!
A2: Particulars | B2: 2020 | C2: 2021 | D2: 2022 | E2: 2023 | F2: 2024 | G2: 2025 | I2: Particulars | J2: 2020 | K2: 2021 | L2: 2022 | M2: 2023 | N2: 2024 | O2: 2025 | Q2: Particulars | R2: 2020 | S2: 2021 | T2: 2022 | U2: 2023 | V2: 2024 | W2: 2025 | Y2: Particulars | Z2: 2020 | AA2: 2021 | AB2: 2022 | AC2: 2023 | AD2: 2024 | AE2: NA | AG2: Particulars | AH2: 2020 | AI2: 2021 | AJ2: 2022 | AK2: 2023 | AL2: 2024 | AM2: 2025 | AO2: Particulars | AP2: 2020 | AQ2: 2021 | AR2: 2022 | AS2: 2023 | AT2: 2024 | AU2: NA
A3: Cash flow from Operating activities | I3: Cash flow from Operating activities | Q3: Cash flow from operating activities | Y3: Cash Flow from Operating actitivities | AG3: Cash flow from Operating activities | AO3: Cash flow from operating activities
A4: Profit before tax | B4: 7102.8 | C4: 5321 | D4: 4697.2 | E4: 10323.1 | F4: 17040.4 | G4: 19183.2 | I4: Profit/Loss before exceptional items and tax | J4: 4832.43 | K4: 5229.33 | L4: 7091.81 | M4: 11305.27 | N4: 14856.36 | O4: 17542.2 | Q4: Profit/Loss for the year | R4: -11975.23 | S4: -13395.1 | T4: -11308.76 | U4: 2689.87 | V4: 32453 | W4: 23278 | Y4: Net profit before tax | Z4: 865.42 | AA4: 821.63 | AB4: 1066.79 | AC4: 1936.03 | AD4: 2702.92 | AG4: Net profit before tax | AH4: 971.88 | AI4: 1074.39 | AJ4: 960.61 | AK4: 1137.59 | AL4: 1231.17 | AM4: 1175.96 | AO4: Profit before tax from continuing operation | AP4: 1622.3 | AQ4: 1173.3 | AR4: 1424.2 | AS4: 2404.8 | AT4: 3840.2
A5: Adjustments for: | I5: Profit/Loss before tax from discontinued operations | J5: -3033.82 | K5: -2189.53 | L5: 0 | M5: 0 | N5: 0 | O5: 0 | Q5: Adjustments for: | Y5: Add: Depreciation and amortisation for the year | Z5: 556 | AA5: 564.82 | AB5: 742.86 | AC5: 858.86 | AD5: 975.12 | AG5: Adjustments for: | AO5: Profit before tax from discontinued operation | AP5: 490.6 | AQ5: 439.6 | AR5: 484.6 | AS5: 0 | AT5: 0
A6: Share of profit of associates | B6: -117.5 | C6: -158.8 | D6: -146.4 | E6: -155.8 | F6: 0 | G6: 0 | I6: Profit/Loss | J6: =SUM(J4:J5) -> 1798.61 | K6: =SUM(K4:K5) -> 3039.8 | L6: =SUM(L4:L5) -> 7091.81 | M6: =SUM(M4:M5) -> 11305.27 | N6: =SUM(N4:N5) -> 14856.36 | O6: =SUM(O4:O5) -> 17542.2 | Q6: Depreciation and amortisation expense | R6: 21425.43 | S6: 23546.71 | T6: 24835.69 | U6: 24860.36 | V6: -646 | W6: 4871 | Y6: Gain on lease preclosure | Z6: -0.31 | AA6: 0 | AB6: 0 | AC6: -0.01 | AD6: -4.75 | AG6: Depreciation and amortisation | AH6: 417.58 | AI6: 433.65 | AJ6: 439.52 | AK6: 502.12 | AL6: 560.42 | AM6: 582.34 | AO6: Adjustments:
A7: Share of profit of joint ventures | B7: -0.9 | C7: -10.2 | D7: -15.5 | E7: -21.6 | F7: 0 | G7: 0 | I7: Adjustments for: | Q7: Allowances for finance receivables | R7: 660.21 | S7: 957.93 | T7: 1307.59 | U7: 2039.15 | V7: 27270 | W7: 23256 | Y7: Profit/Loss on sale of fixed assets | Z7: -2.28 | AA7: 1.96 | AB7: -2.47 | AC7: -2.65 | AD7: -3.38 | AG7: Gain on disposal of investment | AH7: -214.57 | AI7: -146.86 | AJ7: -23.61 | AK7: -38.2 | AL7: -46.8 | AM7: -27.8 | AO7: Share of profit/loss in associates and joint venture accounted for using the equity method | AP7: -57.5 | AQ7: -84.9 | AR7: -16 | AS7: 43.7 | AT7: -237.6
A8: Share of dividend from joint ventures and associates | B8: 86.7 | C8: 10.4 | D8: 49 | E8: 20.9 | F8: 0 | G8: 0 | I8: Depreciation, amortisation and impairment expense | J8: 4976.29 | K8: 4398.89 | L8: 3507.5 | M8: 4356.81 | N8: 4723.78 | O8: 6073.65 | Q8: Allowances for trade and other receivables | R8: 137.03 | S8: 50.01 | T8: 151.26 | U8: 80.63 | V8: 1153 | W8: 0 | Y8: Profit/Loss on sale of investments | Z8: -0.03 | AA8: -0.04 | AB8: -0.23 | AC8: =-61.84-45.56 -> -107.4 | AD8: =26.93-89.47 -> -62.54 | AG8: Profit/loss on PPE sold/discarded (net) | AH8: -7.32 | AI8: 0.18 | AJ8: 0.02 | AK8: -6.48 | AL8: 2.27 | AM8: -11.17 | AO8: Depreciation and amortisation expense | AP8: 2778 | AQ8: 2976.4 | AR8: 2996.3 | AS8: 3135.8 | AT8: 3810.5
A9: Depreciation and amortisation expense | B9: 3528.4 | C9: 3034.1 | D9: 2789 | E9: 2825.7 | F9: 3022.3 | G9: 3159.3 | I9: Loss/Gain on foreign exchange fluctuation (net) | J9: 202.94 | K9: 63.35 | L9: -65.31 | M9: 59.62 | N9: -74.33 | O9: 44.6 | Q9: Inventory write-down | R9: 351.14 | S9: 129.19 | T9: 125.34 | U9: 723.21 | V9: 197 | W9: 109 | Y9: Unrealised exchange gain/loss | Z9: -29.41 | AA9: 17.7 | AB9: -5.65 | AC9: 0.63 | AD9: 10.82 | AG9: Income from investments including dividend and interest | AH9: -1015.35 | AI9: -1188.95 | AJ9: -8.31 | AK9: -16.37 | AL9: -22.92 | AM9: -20.81 | AO9: Finance cost | AP9: 598.6 | AQ9: 520.2 | AR9: 551.9 | AS9: 780.9 | AT9: 1811.2
A10: Finance costs | B10: 134.2 | C10: 101.8 | D10: 126.6 | E10: 187 | F10: 193.2 | G10: 193.1 | I10: Gain due to change in lease arrangements | J10: 0 | K10: -44.21 | L10: -15.07 | M10: 0 | N10: 43.45 | O10: -18.18 | Q10: Reversal for costs of closure of operations of a subsidiary company | R10: -65.62 | S10: -51.99 | T10: -3.32 | U10: 0 | V10: 1334 | W10: 337 | Y10: Net profit/loss from associates using equity method | Z10: 8.59 | AA10: 7.75 | AB10: -2.49 | AC10: 40.73 | AD10: 43.47 | AG10: Gain on fair valuation of investment | AH10: 291.08 | AI10: -461.22 | AJ10: -7.68 | AK10: -10.47 | AL10: -5.43 | AM10: -21.77 | AO10: Interest income | AP10: -36.1 | AQ10: -65.8 | AR10: -117.3 | AS10: -70.3 | AT10: -148.3
A11: Interest income | B11: -96.9 | C11: -72.8 | D11: -174.7 | E11: -185.4 | F11: -98.4 | G11: -147.5 | I11: Dividend on investments and interest income | J11: -530.38 | K11: -465.79 | L11: -418.38 | M11: -528.01 | N11: -798.97 | O11: -461.07 | Q11: Write off/provision for tangible/intangible assets | R11: 0 | S11: 114 | T11: 0 | U11: 229.95 | V11: -107 | W11: 80 | Y11: Dividend income | Z11: -1.26 | AA11: -0.2 | AB11: -3.81 | AC11: -0.02 | AD11: -0.65 | AG11: Finance costs | AH11: 16.33 | AI11: 40.48 | AJ11: 60.93 | AK11: 73.84 | AL11: 116 | AM11: 153.03 | AO11: Dividend income | AP11: -0.6 | AQ11: 0 | AR11: -0.6 | AS11: 8.7 | AT11: -1.3
A12: Dividend income | B12: -3.7 | C12: -3.2 | D12: -2.9 | E12: -6 | F12: -65.8 | G12: -52.4 | I12: Interest, commitment and finance charges | J12: 715.33 | K12: 873.71 | L12: 625.45 | M12: 750.07 | N12: 32.92 | O12: 30.84 | Q12: Charge associated with change in JLR strategy | R12: 0 | S12: 14994.3 | T12: 0 | U12: 0 | V12: 58 | W12: 0 | Y12: Interest income | Z12: -26.64 | AA12: -32.88 | AB12: -8.16 | AC12: -10.99 | AD12: -22.1 | AG12: Unrealised foreign exchange loss | AH12: 27.98 | AI12: 0 | AJ12: -13.42 | AK12: -0.51 | AL12: 2.7 | AM12: 0.66 | AO12: Loss/gain on disposal of PPE | AP12: -4.1 | AQ12: 10.6 | AR12: 14.8 | AS12: -14.8 | AT12: =35.1-34.1 -> 1
A13: Net loss/gain on sale/discarding of PPE | B13: 42.4 | C13: 59 | D13: 45.8 | E13: 11.5 | F13: 48.1 | G13: 40.5 | I13: Equity-settled share based payment expenses | J13: 174.47 | K13: 132.84 | L13: 105.25 | M13: 139.75 | N13: -784.77 | O13: -1242.5 | Q13: Impairment in subsidiaries | R13: 353.2 | S13: 0 | T13: -104.42 | U13: -214.39 | V13: 977 | W13: 492 | Y13: Finance cost | Z13: 154.74 | AA13: 152.05 | AB13: 158.09 | AC13: 199.61 | AD13: 274.08 | AG13: Provision for expected credit loss on trade receivables | AH13: 17.03 | AI13: 2.82 | AJ13: 0 | AK13: -0.21 | AL13: -2.59 | AM13: 1.5 | AO13: Bad debts/advances written off | AP13: 6.7 | AQ13: 21.4 | AR13: =-1.2+9.7 -> 8.5 | AS13: 10.8 | AT13: 31.3
A14: Net gain/loss of sale of investments in debt mutual funds | B14: -150.3 | C14: -41.1 | D14: -204.6 | E14: -180.9 | F14: -90.1 | G14: -106 | I14: Net gain on financial instruments measured at fair value | J14: -296.49 | K14: -380.99 | L14: -355.65 | M14: -426.73 | N14: -1069.91 | O14: -388.15 | Q14: Impairment losses/reversal in passenger vehicle business | R14: 1418.64 | S14: -1182.41 | V14: 0 | W14: -4975 | Y14: Provisions | Z14: -28.21 | AA14: 26.56 | AB14: -25.49 | AC14: 15.74 | AD14: 61.4 | AG14: Share of profit of equity accounted investees, (net) | AH14: 0.19 | AI14: 0.64 | AJ14: 0.94 | AK14: -0.28 | AL14: -0.55 | AM14: -0.5 | AO14: Provision for doubtful debts/advances | AP14: 4.2 | AQ14: 38.7 | AR14: 11.2 | AS14: 34.8 | AT14: 145.9
A15: Fair valuation gain on investments in debt mutual funds | B15: -2941.3 | C15: -2771.3 | D15: -1362.5 | E15: -1727.9 | F15: -3600.5 | G15: -4374.8 | I15: Gain/Loss on PPE sold/scrapped/written off | J15: -53.96 | K15: -11.01 | L15: 39.11 | M15: -14.89 | N15: -60.21 | O15: -333.21 | Q15: Provision/reversal for onerous contracts and related supplier claims | R15: 777 | S15: -663 | T15: 0 | U15: -61.03 | V15: 43 | W15: 48 | Y15: Operating profit before working capital changes | Z15: =SUM(Z4:Z14) -> 1496.61 | AA15: =SUM(AA4:AA14) -> 1559.35 | AB15: =SUM(AB4:AB14) -> 1919.44 | AC15: =SUM(AC4:AC14) -> 2930.53 | AD15: =SUM(AD4:AD14) -> 3974.39 | AE15: =SUM(AE4:AE14) -> 0 | AG15: Change in valuation of liability against life policies | AH15: 1622.86 | AI15: 2346.75 | AJ15: 0 | AK15: 0 | AL15: 0 | AM15: 0 | AO15: Liability no longer required written back | AP15: -49.7 | AQ15: -34.7 | AR15: -36 | AS15: -82.8 | AT15: -19.8
A16: Liabilities no longer required written back | B16: -3.7 | C16: 0 | D16: 0 | E16: 0 | F16: 0 | G16: 0 | I16: Items related to discontinued operations and gain on loss of control | J16: 787.31 | K16: -18.87 | L16: 0 | M16: 0 | N16: =544.06+128.86 -> 672.92 | O16: =681.51+120.15 -> 801.66 | Q16: Defined benefit pension plan amendment past service cost | R16: 0 | S16: 84.81 | T16: 0 | U16: -1495.07 | V16: 0 | W16: 121 | Y16: Adjustments for: | AG16: Operating profit before working capital changes | AH16: =SUM(AH4,AH6:AH15) -> 2127.69 | AI16: =SUM(AI4,AI6:AI15) -> 2101.88 | AJ16: =SUM(AJ4,AJ6:AJ15) -> 1409 | AK16: =SUM(AK4,AK6:AK15) -> 1641.03 | AL16: =SUM(AL4,AL6:AL15) -> 1834.27 | AM16: =SUM(AM4,AM6:AM15) -> 1831.44 | AO16: Unrealised foreign currency loss/gain | AP16: 457.1 | AQ16: -26.7 | AR16: 52 | AS16: -70.6 | AT16: -160.8
A17: Unrealised foreign exchange gain/loss | B17: -76.8 | C17: 62.1 | D17: 30.9 | E17: 20.9 | F17: -4.2 | G17: 4 | I17: Operating profit before working capital changes | J17: =SUM(J6,J8:J16) -> 7774.12 | K17: =SUM(K6,K8:K16) -> 7587.72 | L17: =SUM(L6,L8:L16) -> 10514.71 | M17: =SUM(M6,M8:M16) -> 15641.89 | N17: =SUM(N6,N8:N16) -> 17541.24 | O17: =SUM(O6,O8:O16) -> 22049.84 | Q17: Employee seperation cost | R17: 409.78 | S17: 430.76 | T17: 0 | U17: 0 | V17: -24 | W17: -8 | Y17: Loans given by a financial enterprise | Z17: -1177.62 | AA17: -1700.87 | AB17: -2859.5 | AC17: -6530.88 | AD17: -4925.23 | AG17: Increase/decrease in trade receivables | AH17: 167.24 | AI17: -18.16 | AJ17: -159.18 | AK17: -131.46 | AL17: -150.06 | AM17: -303.85 | AO17: Operating profit before working capital changes | AP17: =SUM(AP4:AP5,AP7:AP16) -> 5809.5 | AQ17: =SUM(AQ4:AQ5,AQ7:AQ16) -> 4968.1 | AR17: =SUM(AR4:AR5,AR7:AR16) -> 5373.6 | AS17: =SUM(AS4:AS5,AS7:AS16) -> 6181 | AT17: =SUM(AT4:AT5,AT7:AT16) -> 9072.3
A18: Operating profit/loss before working capital changes | B18: =SUM(B4,B6:B17) -> 7503.4 | C18: =SUM(C4,C6:C17) -> 5531 | D18: =SUM(D4,D6:D17) -> 5831.9 | E18: =SUM(E4,E6:E17) -> 11111.5 | F18: =SUM(F4,F6:F17) -> 16445 | G18: =SUM(G4,G6:G17) -> 17899.4 | I18: Changes in: | Q18: Accrual for share based payments | R18: 4.7 | S18: 9.04 | T18: 18.05 | U18: 30.03 | V18: 303 | W18: 232 | Y18: Trade receivables | Z18: 130.37 | AA18: 398.92 | AB18: -120.61 | AC18: -95.16 | AD18: -590 | AG18: Increase/decrease in inventories | AH18: -349.25 | AI18: -222.3 | AJ18: -218.43 | AK18: -581.11 | AL18: -432.13 | AM18: -696.37 | AO18: Increase/decrease in trade and other payables | AP18: -151.1 | AQ18: 1918.4 | AR18: 551.8 | AS18: 3056.2 | AT18: 938.4
A19: Adjustments for changes in Working capital changes: | I19: Trade and other receivables | J19: 2409.01 | K19: -891.48 | L19: -2044.51 | M19: -2904.47 | N19: -1889.81 | O19: -3781.89 | Q19: Gain/loss on marked to market investments | R19: 389.05 | S19: -19.91 | T19: 0 | U19: -93.27 | V19: -263 | W19: -224 | Y19: Inventories | Z19: 103.1 | AA19: -178.96 | AB19: -274.93 | AC19: -313.99 | AD19: -326.89 | AG19: Increase/decrease in other financial assets and other assets | AH19: 26.68 | AI19: -179.77 | AJ19: -33.06 | AK19: -74.78 | AL19: -163.03 | AM19: -153.87 | AO19: Increase/decrease in other financial liabilities | AP19: 272.4 | AQ19: 272.5 | AR19: 33.8 | AS19: 279.9 | AT19: 814.2
A20: Increase/decrease in other financial assets | B20: -2.1 | C20: -0.4 | D20: -0.6 | E20: -22 | F20: 0.1 | G20: 0 | I20: Financial services receivable | J20: -3924.73 | K20: 5787.59 | L20: -461.61 | M20: -18797.21 | N20: -19887 | O20: -17170.29 | Q20: Profit/Loss on sale of assets | R20: 316.19 | S20: 265.59 | T20: 94.19 | U20: 354.96 | V20: -700 | W20: -287 | Y20: Other current assets | Z20: -29.12 | AA20: -5.75 | AB20: -360.46 | AC20: -334.61 | AD20: 104.88 | AG20: Increase in other financial liabilities, other liabilities and provisions | AH20: -92.2 | AI20: 858.24 | AJ20: 11.79 | AK20: 244.7 | AL20: 831.83 | AM20: 973.22 | AO20: Increase/decrease in trade receivables | AP20: 814.6 | AQ20: -1346.4 | AR20: -645.6 | AS20: -1729.6 | AT20: -452.1
A21: Increase/decrease in other non current assets | B21: -154.7 | C21: -13 | D21: -156.1 | E21: -136.8 | F21: -24.2 | G21: -4.9 | I21: Inventories | J21: 1316.36 | K21: 225.74 | L21: -2172.99 | M21: -5251.96 | N21: -1752.64 | O21: -1646.35 | Q21: Profit on sale of investments | R21: -187.34 | S21: -177.26 | T21: -266.56 | U21: -303.44 | V21: -3852 | W21: 10606 | Y21: Other financial assets | Z21: -11.81 | AA21: 48.78 | AB21: -90.78 | AC21: -155.08 | AD21: 15.54 | AG21: Cash generated from/used in operations | AH21: =SUM(AH16,AH17:AH20) -> 1880.16 | AI21: =SUM(AI16,AI17:AI20) -> 2539.89 | AJ21: =SUM(AJ16,AJ17:AJ20) -> 1010.12 | AK21: =SUM(AK16,AK17:AK20) -> 1098.38 | AL21: =SUM(AL16,AL17:AL20) -> 1920.88 | AM21: =SUM(AM16,AM17:AM20) -> 1650.57 | AO21: Increase/decrease in inventories | AP21: -436 | AQ21: -637.7 | AR21: -1354.2 | AS21: -1273.4 | AT21: 172.9
A22: Increase/decrease in inventories | B22: 108.7 | C22: 164.9 | D22: -483.3 | E22: -751.2 | F22: 233.2 | G22: -17.4 | I22: Trade and other payables and provisions | J22: -6775.09 | K22: 7049.34 | L22: 4972.37 | M22: 7012.6 | N22: 4354.36 | O22: 8485.19 | Q22: Provision for loan given to a joint ventures | R22: 25.12 | S22: 0 | T22: 0 | U22: =-61.99-140.76 -> -202.75 | V22: 9986 | W22: 5083 | Y22: Trade payables | Z22: 22.46 | AA22: 1113.53 | AB22: 327.52 | AC22: 517.35 | AD22: 1537.73 | AG22: Income tax | AH22: -260.97 | AI22: -276.76 | AJ22: -246.12 | AK22: -330.14 | AL22: -387.74 | AM22: -377.67 | AO22: Increase/decrease in other receivables | AP22: 30.7 | AQ22: -265.3 | AR22: -64.8 | AS22: -238.9 | AT22: -593.4
A23: Increase/decrease in trade receivables | B23: 340.5 | C23: 696.5 | D23: -764 | E23: -1258.1 | F23: 164.2 | G23: -1003.4 | I23: Cash generated from/used in operations | J23: =SUM(J17,J19:J22) -> 799.67 | K23: =SUM(K17,K19:K22) -> 19758.91 | L23: =SUM(L17,L19:L22) -> 10807.97 | M23: =SUM(M17,M19:M22) -> -4299.15 | N23: =SUM(N17,N19:N22) -> -1633.85 | O23: =SUM(O17,O19:O22) -> 7936.5 | Q23: Share of profits/loss of joint ventures and associates | R23: 1000 | S23: 378.96 | T23: 74.06 | U23: -336.38 | V23: 48 | W23: -84 | Y23: Other financial liabilities | Z23: -42 | AA23: 137.3 | AB23: 57.28 | AC23: -11.55 | AD23: 49 | AG23: Net cash from/used in operating activities | AH23: =AH21+AH22 -> 1619.19 | AI23: =AI21+AI22 -> 2263.13 | AJ23: =AJ21+AJ22 -> 764 | AK23: =AK21+AK22 -> 768.24 | AL23: =AL21+AL22 -> 1533.14 | AM23: =AM21+AM22 -> 1272.9 | AO23: Increase/decrease in other financial assets | AP23: 1089.5 | AQ23: 701.7 | AR23: -599.5 | AS23: -778.8 | AT23: -947.3
A24: Increase/decrease in loans (current) | B24: -0.9 | C24: -6 | D24: -7.5 | E24: 0.8 | F24: -1309.9 | G24: -1962.7 | I24: Income taxes paid | J24: -2256.6 | K24: -1850.08 | L24: -1560.42 | M24: -2774.87 | N24: -3996.1 | O24: -4760.69 | Q24: Tax expense | R24: 395.25 | S24: 2541.86 | T24: 4231.29 | U24: 704.06 | V24: -2608 | W24: -2473 | Y24: Other current liabilities | Z24: -0.94 | AA24: 106.5 | AB24: 174.57 | AC24: 161.07 | AD24: 36.88 | AG24: Cash flow from Investing activities | AO24: Cash generated/used in operating activities | AP24: =SUM(AP17:AP23) -> 7429.6 | AQ24: =SUM(AQ17:AQ23) -> 5611.3 | AR24: =SUM(AR17:AR23) -> 3295.1 | AS24: =SUM(AS17:AS23) -> 5496.4 | AT24: =SUM(AT17:AT23) -> 9005
A25: Increase/decrease in other financial assets (current) | B25: -71.3 | C25: 5.7 | D25: -1274.8 | E25: 380.2 | F25: -3 | G25: -10.5 | I25: Net cash from/used in operating activities | J25: =J23+J24 -> -1456.93 | K25: =K23+K24 -> 17908.83 | L25: =L23+L24 -> 9247.55 | M25: =M23+M24 -> -7074.02 | N25: =N23+N24 -> -5629.95 | O25: =O23+O24 -> 3175.81 | Q25: Finance cost | R25: 7243.33 | S25: 8097.17 | T25: 9326.31 | U25: 10239.23 | V25: -47 | W25: -64 | Y25: Other non-current assets | Z25: 124.2 | AA25: -76.78 | AB25: 33.46 | AC25: 35.38 | AD25: -169.55 | AG25: Purchase and construction of PPE | AH25: -608.09 | AI25: -501.62 | AJ25: -665.89 | AK25: -995.85 | AL25: -1876.05 | AM25: -1948.72 | AO25: Taxes | AP25: -1077.6 | AQ25: -560 | AR25: -832.4 | AS25: -853.5 | AT25: -1435.4
A26: Increase/decrease in other current assets | B26: -242.2 | C26: -748.8 | D26: -502.7 | E26: -305.2 | F26: 173.5 | G26: 270.1 | I26: Cash flow from Investing activities | Q26: Interest income | R26: -1170.12 | S26: -492.53 | T26: -625.22 | U26: -1251.18 | V26: 68 | W26: -77 | Y26: Cash generated from/used in operations | Z26: =SUM(Z17:Z25,Z15) -> 615.25 | AA26: =SUM(AA17:AA25,AA15) -> 1402.02 | AB26: =SUM(AB17:AB25,AB15) -> -1194.01 | AC26: =SUM(AC17:AC25,AC15) -> -3796.94 | AD26: =SUM(AD17:AD25,AD15) -> -293.25 | AE26: =SUM(AE17:AE25,AE15) -> 0 | AG26: Proceeds from sale of PPE | AH26: 12.97 | AI26: 2.06 | AJ26: 1.65 | AK26: 8.24 | AL26: 4.97 | AM26: 23.33 | AO26: Net cash generated/used in operating activities | AP26: =AP24+AP25 -> 6352 | AQ26: =AQ24+AQ25 -> 5051.3 | AR26: =AR24+AR25 -> 2462.7 | AS26: =AS24+AS25 -> 4642.9 | AT26: =AT24+AT25 -> 7569.6
A27: Increase/decrease in non-current provisions | B27: 12.1 | C27: -6.9 | D27: 39.7 | E27: 4 | F27: -889.5 | G27: -1153.8 | I27: Payment to acquire PPE and other intangible assets | J27: -6896.02 | K27: -5989.49 | L27: -6039.8 | M27: -6304.57 | N27: -9945.99 | O27: -10391.95 | Q27: Dividend income | R27: -21.13 | S27: -18.37 | T27: -34.22 | U27: -46.42 | V27: 0 | W27: -40 | Y27: Direct taxes paid | Z27: -241.82 | AA27: -250.73 | AB27: -366.15 | AC27: -607.87 | AD27: -959.42 | AG27: Acquisitions/disposal interest in associates (net) | AH27: -23.36 | AI27: 0 | AJ27: =-7.39+5.25 -> -2.14 | AK27: 0 | AL27: -0.27 | AM27: -1.5 | AO27: Cash flow investing activities
A28: Increase/decrease in other non-current liabilities | B28: 78.7 | C28: 13.7 | D28: 51.7 | E28: 403.8 | F28: 47.7 | G28: -17.2 | I28: Proceeds from sale of PPE and other intangible assets | J28: 101.9 | K28: 1364.15 | L28: 119.94 | M28: 137.78 | N28: 273.23 | O28: 582.96 | Q28: Foreign exchange gain/loss | R28: 1865.85 | S28: -4402.12 | T28: -878.51 | U28: 3746.61 | V28: -537 | W28: -1344 | Y28: Net cash from/used in operating activities | Z28: =Z26+Z27 -> 373.43 | AA28: =AA26+AA27 -> 1151.29 | AB28: =AB26+AB27 -> -1560.16 | AC28: =AC26+AC27 -> -4404.81 | AD28: =AD26+AD27 -> -1252.67 | AE28: =AE26+AE27 -> 0 | AG28: Net movement in bank deposits | AH28: 0 | AI28: -1.92 | AJ28: -0.09 | AK28: -0.1 | AL28: -0.12 | AM28: -0.29 | AO28: Payments for PPE and other intangible assets | AP28: -2274.1 | AQ28: -1970 | AR28: -2508.1 | AS28: -2221.1 | AT28: -4125.4
A29: Increase/decrease in trade payables | B29: -2155.1 | C29: 2680.1 | D29: -395.9 | E29: 2007.5 | F29: 576.7 | G29: 220.3 | I29: Payment to acquire investments | J29: -198567.8 | K29: -156289.44 | L29: -65421.47 | M29: -50164.56 | N29: -49926.64 | O29: -90594.98 | Q29: Operating profit before working capital changes | R29: =SUM(R4,R6:R28) -> 23352.48 | S29: =SUM(S4,S6:S28) -> 31197.64 | T29: =SUM(T4,T6:T28) -> 26942.77 | U29: =SUM(U4,U6:U28) -> 41694.13 | V29: =SUM(V4,V6:V28) -> 65106 | W29: =SUM(W4,W6:W28) -> 58937 | Y29: Cash flow from Investing activities | AG29: Purchase of investment | AH29: -8684.21 | AI29: -7647.89 | AJ29: -2038.34 | AK29: -2601 | AL29: -2381.78 | AM29: -1967.97 | AO29: Proceeds from sale of PPE and other intangibles | AP29: 79.9 | AQ29: 37.5 | AR29: 71.8 | AS29: 38.3 | AT29: 115.4
A30: Increase/decrease in other financial liabilities (current) | B30: -257.7 | C30: 311 | D30: 373.4 | E30: -307.7 | F30: 2811 | G30: 2834.9 | I30: Proceeds from sale of investments | J30: 198131.58 | K30: 147983.68 | L30: 65127.25 | M30: 46269.08 | N30: 50919.36 | O30: 85257.15 | Q30: Finance receivables | R30: 2020.77 | S30: -4386.94 | T30: -75.63 | U30: 617.45 | V30: -725 | W30: 0 | Y30: Purchase of PPE, intangible assets, capital WIP, intangibles under development, net of capital advances | Z30: -1021.09 | AA30: -927.98 | AB30: -984.46 | AC30: -1340.77 | AD30: -1145.17 | AG30: Proceeds from sale of investment | AH30: 7207.28 | AI30: 4902.35 | AJ30: 2268.72 | AK30: =2770.97+2.55 -> 2773.52 | AL30: 2776.13 | AM30: 1941.22 | AO30: Proceeds from sale/payment for purchase of investments | AP30: 3.3 | AQ30: -7.3 | AR30: 13.5 | AS30: -27.9 | AT30: -195.8
A31: Increase/decrease in current provisions | B31: -16.5 | C31: 62.1 | D31: 118.5 | E31: 101.1 | F31: -383.5 | G31: 537.7 | I31: Interest received | J31: 372.38 | K31: 431.11 | L31: 419.57 | M31: 463.67 | N31: 703.28 | O31: 883.9 | Q31: Trade receivables | R31: 7928.93 | S31: -1118.35 | T31: 261.08 | U31: -2830.1 | V31: -1151 | W31: 3573 | AG31: Investment income | AH31: 998.5 | AI31: 1166.73 | AJ31: 1.57 | AK31: 16.37 | AL31: 18.85 | AM31: 20.01 | AO31: Loan to/repaid by related parties (net) | AP31: -19.9 | AQ31: -34.9 | AR31: 49.8 | AS31: -2.8 | AT31: 12.1
A32: Increase/decrease in other current liabilities | B32: -209.6 | C32: 1177.6 | D32: 188.5 | E32: 256.3 | F32: =121.2+760.2 -> 881.4 | G32: =125.6+76.1 -> 201.7 | I32: Dividend received | J32: 695.76 | K32: 571.89 | L32: 1245.78 | M32: 1391.01 | N32: 1200.31 | O32: 1364.65 | Q32: Loans and advances and other financial assets | R32: 64.53 | S32: -1308.92 | T32: 129.26 | U32: -736.04 | V32: -3083 | W32: -3289 | Y32: Sale of fixed assets | Z32: 30.21 | AA32: 3.35 | AB32: 13.58 | AC32: 21.94 | AD32: 34.63 | AG32: Net cash from/used in investing activities | AH32: =SUM(AH24:AH31) -> -1096.91 | AI32: =SUM(AI24:AI31) -> -2080.29 | AJ32: =SUM(AJ24:AJ31) -> -434.52 | AK32: =SUM(AK24:AK31) -> -798.82 | AL32: =SUM(AL24:AL31) -> -1458.27 | AM32: =SUM(AM24:AM31) -> -1933.92 | AO32: Interest received | AP32: 38.7 | AQ32: 63.5 | AR32: 115.7 | AS32: 69 | AT32: 169.3
A33: Cash generated/used in Operating activities | B33: =SUM(B18,B20:B32) -> 4933.3 | C33: =SUM(C18,C20:C32) -> 9867.5 | D33: =SUM(D18,D20:D32) -> 3018.8 | E33: =SUM(E18,E20:E32) -> 11484.2 | F33: =SUM(F18,F20:F32) -> 18722.7 | G33: =SUM(G18,G20:G32) -> 17794.2 | I33: Proceeds from buy back of shares by associate | J33: 446.31 | K33: 0 | L33: 55.05 | M33: 70.93 | N33: 12.38 | O33: 9.55 | Q33: Other current and non-current assets | R33: -2830.89 | S33: 3853.53 | T33: -5312.17 | U33: -3182.09 | V33: 1666 | W33: -3183 | Y33: Purchase of investments | Z33: -94.01 | AA33: -5.51 | AB33: -146.8 | AC33: -265.58 | AD33: -223.25 | AG33: Cash flow from Financing activities | AO33: Dividend received | AP33: 0.6 | AQ33: 0 | AR33: 0.6 | AS33: 0 | AT33: 1.3
A34: Income taxes paid (net) | B34: -1437.5 | C34: -1011.3 | D34: -1178.3 | E34: -2232.8 | F34: -3555.7 | G34: -3781.8 | I34: Dividends received from others | J34: 26.28 | K34: 4.68 | L34: 1.25 | M34: 5.68 | N34: 27.27 | O34: 59.71 | Q34: Inventories | R34: 2325.5 | S34: 3814.5 | T34: 472.06 | U34: -5665.36 | V34: -7265 | W34: 2127 | Y34: Purchase of investments in associates | Z34: -38.97 | AA34: -52.56 | AB34: -75 | AC34: -87.17 | AD34: -387.59 | AG34: Proceeds from borrowings | AH34: 110.69 | AI34: 205.25 | AJ34: 134.08 | AK34: 175.61 | AL34: 526.7 | AM34: 1014.19 | AO34: Dividend received from associates and joint ventures entities | AP34: 55.9 | AQ34: 15 | AR34: 78.7 | AS34: 198.2 | AT34: 170.3
A35: Net cash from/used in Operating activities | B35: =B33+B34 -> 3495.8 | C35: =C33+C34 -> 8856.2 | D35: =D33+D34 -> 1840.5 | E35: =E33+E34 -> 9251.4 | F35: =F33+F34 -> 15167 | G35: =G33+G34 -> 14012.4 | I35: Bank deposits placed | J35: -3341.68 | K35: -10752.08 | L35: -7468.23 | M35: -12292.91 | N35: -12270.39 | O35: -15139.63 | Q35: Trade payables and acceptances | R35: -8084.81 | S35: 5748.15 | T35: -7011.86 | U35: 6944.85 | V35: 13706 | W35: 1303 | Y35: Redemption of preference shares | Z35: 0 | AA35: 16.44 | AB35: 87.44 | AC35: 317.01 | AD35: 168.59 | AG35: Repayment of borrowings | AH35: -128.44 | AI35: -134.19 | AJ35: -44.69 | AK35: -101.62 | AL35: -118.06 | AM35: -164.44 | AO35: Investment/proceeds from maturity of deposits with remaining maturity | AP35: -1.5 | AQ35: 2.7 | AR35: -25.8 | AS35: -39.3 | AT35: -85.7
A36: Cash flow from Investing activities | I36: Bank deposits matured | J36: 2583.41 | K36: 4533.02 | L36: 8813.19 | M36: 10755.17 | N36: 12199.41 | O36: 9034.06 | Q36: Other current and non current liabilities | R36: -6450.14 | S36: 2217.87 | T36: -3065.37 | U36: 537.16 | V36: 4699 | W36: 2364 | Y36: Sale of investments | Z36: 5.81 | AA36: 0.34 | AB36: -619.99 | AC36: -34.63 | AD36: 47.82 | AG36: Dividends paid | AH36: -502.11 | AI36: -170 | AJ36: -170 | AK36: 0 | AL36: -170 | AM36: -170 | AO36: Consideration paid on acquisition of subsidiaries | AP36: -122.8 | AQ36: 0 | AR36: -108.1 | AS36: -259.2 | AT36: -2723.2
A37: Payments for purchase of PPE and capital WIP | B37: -3194.7 | C37: -2132 | D37: -3206.33 | E37: -6116.6 | F37: -6726.9 | G37: -8348.6 | I37: Net change in earmarked and margin account | J37: -150.53 | K37: 0.87 | L37: 175.39 | M37: 70.89 | N37: 10.23 | O37: 20.83 | Q37: Other financial liabilities | R37: 272.74 | S37: -1168.39 | T37: -178.55 | U37: 706.43 | V37: 1845 | W37: -553 | Y37: Contribution from non-controlling interest | Z37: 0 | AA37: 54.51 | AB37: 228 | AC37: 68.8 | AD37: 480 | AG37: Payment towards lease liabilities | AH37: =-35.75+28.21 -> -7.54 | AI37: =-58.03 -> -58.03 | AJ37: -33.69 | AK37: =-34.83-21.57 -> -56.4 | AL37: -59.19 | AM37: -52.8 | AO37: Net cash from/used in investing activities | AP37: =SUM(AP28:AP36) -> -2239.9 | AQ37: =SUM(AQ28:AQ36) -> -1893.5 | AR37: =SUM(AR28:AR36) -> -2311.9 | AS37: =SUM(AS28:AS36) -> -2244.8 | AT37: =SUM(AT28:AT36) -> -6661.7
A38: Payments for purchase of intangible assets and IA under dev | B38: -242.3 | C38: -238.3 | D38: -253 | E38: -230.7 | F38: -280.8 | G38: -384.5 | I38: Inter corporate deposits placed | J38: -608 | K38: -569.4 | L38: -818.28 | M38: -987 | N38: -410.08 | O38: -471 | Q38: Provisions | R38: 9818.77 | S38: -7744.02 | T38: 4030.88 | U38: 480.57 | V38: -2367 | W38: 5814 | Y38: Interest received | Z38: 26.64 | AA38: 28.84 | AB38: 7.88 | AC38: 12.64 | AD38: 23.61 | AG38: Interest paid | AH38: -4.41 | AI38: -13.01 | AJ38: -35.32 | AK38: -47.69 | AL38: -71.35 | AM38: -112.33 | AO38: Cash flow from financing activities
A39: Proceeds from sale of PPE | B39: 37 | C39: 42 | D39: 136 | E39: 99.6 | F39: 44 | G39: 32.6 | I39: Inter corporate deposits refunded | J39: 614 | K39: 307.5 | L39: 266.5 | M39: 893.92 | N39: 895.55 | O39: 227 | Q39: Cash generated from/used in operations | R39: =SUM(R29,R30:R38) -> 28417.88 | S39: =SUM(S29,S30:S38) -> 31105.07 | T39: =SUM(T29,T30:T38) -> 16192.47 | U39: =SUM(U29,U30:U38) -> 38567 | V39: =SUM(V29,V30:V38) -> 72431 | W39: =SUM(W29,W30:W38) -> 67093 | Y39: Dividends received | Z39: 1.26 | AA39: 0.2 | AB39: 3.81 | AC39: 0 | AD39: 0 | AG39: Net cash generated from/used in Financing activitie | AH39: =SUM(AH34:AH38) -> -531.81 | AI39: =SUM(AI34:AI38) -> -169.98 | AJ39: =SUM(AJ34:AJ38) -> -149.62 | AK39: =SUM(AK34:AK38) -> -30.1 | AL39: =SUM(AL34:AL38) -> 108.1 | AM39: =SUM(AM34:AM38) -> 514.62 | AO39: Proceeds from minority shareholders | AP39: 0 | AQ39: 3.7 | AR39: 0 | AS39: -145.3 | AT39: 23.6
A40: Payments for purchase of investment in joint venture/associate | B40: -15 | C40: -65.3 | D40: -145.9 | E40: 0 | F40: -80 | G40: -18 | I40: Purchase of investment in join ventures and associates | J40: -418.27 | K40: -359.13 | L40: -222.38 | M40: -62.05 | N40: -248.84 | O40: -29.1 | Q40: Income tax paid (net) | R40: -1784.94 | S40: -2104.56 | T40: -1909.64 | U40: -3178.99 | V40: -4516 | W40: -3991 | Y40: Net cash from/used in Investing activities | Z40: =SUM(Z30:Z39) -> -1090.15 | AA40: =SUM(AA30:AA39) -> -882.37 | AB40: =SUM(AB30:AB39) -> -1485.54 | AC40: =SUM(AC30:AC39) -> -1307.76 | AD40: =SUM(AD30:AD39) -> -1001.36 | AG40: Net increase/decrease in cash and cash equivalents | AH40: =AH23+AH32+AH39 -> -9.53 | AI40: =AI23+AI32+AI39 -> 12.86 | AJ40: =AJ23+AJ32+AJ39 -> 179.86 | AK40: =AK23+AK32+AK39 -> -60.68 | AL40: =AL23+AL32+AL39 -> 182.97 | AM40: =AM23+AM32+AM39 -> -146.4 | AO40: Dividends paid | AP40: -945.7 | AQ40: -0.5 | AR40: -472.4 | AS40: -293.8 | AT40: -440.9
A41: Payment for purchase of Non-controlling interest | B41: 0 | C41: -21.8 | D41: =3003.7-30 -> 2973.7 | E41: =-102+3002.9 -> 2900.9 | F41: 61932.7 | G41: 59844.4 | I41: Purchase consideration paid on acquisition of subsidiaries net of cash | J41: -58.74 | K41: 0 | L41: -41.83 | M41: -586.58 | N41: -52.87 | O41: 0 | Q41: Net cash from/used in operating activities | R41: =R39+R40 -> 26632.94 | S41: =S39+S40 -> 29000.51 | T41: =T39+T40 -> 14282.83 | U41: =U39+U40 -> 35388.01 | V41: =V39+V40 -> 67915 | W41: =W39+W40 -> 63102 | Y41: Cash flow from Financing activities | AG41: Cash and cash equivalents at the beginning of the year | AH41: 340.94 | AI41: =AH43 -> 331.47 | AJ41: =AI43 -> 342.43 | AK41: =AJ43 -> 510.18 | AL41: =AK43 -> 452.85 | AM41: =AL43 -> 644.06 | AO41: Dividend distribution tax | AP41: -137 | AQ41: 0 | AR41: -173.3 | AS41: -37 | AT41: -234.2
A42: Proceeds from sale of debt mutual funds | B42: 46968.7 | C42: 42919.5 | D42: 63578.7 | E42: 61605.4 | F42: -65709.9 | G42: -61200 | I42: Consideration received on disposal of subsidiaries | J42: 174.59 | K42: 178.06 | L42: 5.72 | M42: 740.28 | N42: 20.24 | O42: 0 | Q42: Cash flow from Investing activities | Y42: Borrowings: | AG42: Effect of exchnage rates changes | AH42: 0.06 | AI42: -1.9 | AJ42: -12.11 | AK42: 3.35 | AL42: 8.24 | AM42: 4.23 | AO42: Dividend paid to minority share holders | AP42: -196.7 | AQ42: -160.7 | AR42: -552.8 | AS42: -808.3 | AT42: -1509.6
A43: Payments for purchase of debt mutual funds | B43: -44205 | C43: -44868.7 | D43: -60495.4 | E43: -66494.8 | F43: -26 | G43: -2 | I43: Consideration received on disposal of associate | J43: 0 | K43: 137.82 | L43: 556.53 | M43: 1052 | N43: 995.78 | O43: 560.74 | Q43: Payments for PPE | R43: -14319.17 | S43: -11775.65 | T43: -9039.4 | U43: -8492.63 | V43: -12975 | W43: -15189 | Y43: Non-current borrowings availed/repaid | Z43: 1458.99 | AA43: 1270.57 | AB43: 1012.31 | AC43: 5467.9 | AD43: 3844.07 | AG43: Cash and cash equivalents at the end of the year | AH43: =AH40+AH42+AH41 -> 331.47 | AI43: =AI40+AI42+AI41 -> 342.43 | AJ43: =AJ40+AJ42+AJ41 -> 510.18 | AK43: =AK40+AK42+AK41 -> 452.85 | AL43: =AL40+AL42+AL41 -> 644.06 | AM43: =AM40+AM42+AM41 -> 501.89 | AO43: Interest paid | AP43: -566.7 | AQ43: -414.1 | AR43: 1164.6 | AS43: 1154.4 | AT43: 10477.1
A44: Investment in fixed deposits with bank | B44: -5.3 | C44: -2996.9 | D44: -3004.4 | E44: 0 | F44: 0 | G44: -365 | I44: Net cash from/used in investing activities | J44: =SUM(J27:J43) -> -6894.83 | K44: =SUM(K27:K43) -> -18446.76 | L44: =SUM(L27:L43) -> -3225.82 | M44: =SUM(M27:M43) -> -8547.26 | N44: =SUM(N27:N43) -> -5597.77 | O44: =SUM(O27:O43) -> -18626.11 | Q44: Payments for other intangible assets | R44: -15382.86 | S44: -8429.75 | T44: -6129.02 | U44: -9603.05 | V44: -18439 | W44: -22853 | Y44: Current borrowings availed/repaid | Z44: 512.69 | AA44: -683.9 | AB44: 2341.03 | AC44: 1119.78 | AD44: -182.03 | AO44: Proceeds from long term borrowings | AP44: 35.5 | AQ44: 4111.6 | AR44: 4128.4 | AS44: 3707.8 | AT44: 1234.8
A45: Interest received | B45: 96.3 | C45: 67 | D45: 174.5 | E45: 194.1 | F45: 98.3 | G45: 147.2 | I45: Cash flow from Financing activities | Q45: Proceeds from sale of PPE | R45: 171.48 | S45: 350.58 | T45: 230.1 | U45: 285.03 | V45: 231 | W45: 974 | Y45: Other bank balances | Z45: 15.39 | AA45: -55.21 | AB45: -7.24 | AC45: 62.27 | AD45: -43.96 | AO45: Proceeds from short term borrowings | AP45: 3386.9 | AQ45: 2682.8 | AR45: -2008.9 | AS45: -1075.5 | AT45: -4977.1
A46: Dividend received | B46: 3.7 | C46: 3.2 | D46: 2.9 | E46: 6 | F46: 65.8 | G46: 52.4 | I46: Proceeds from sale of shares by M&M benefit trust | J46: 1242.51 | K46: 0 | L46: 0.92 | M46: 0.53 | N46: 0.51 | O46: 0.73 | Q46: Investments in mutual fund purchased/sold (net) | R46: -1339.29 | S46: -7432.85 | T46: 0 | U46: -836.29 | V46: -207 | W46: 0 | Y46: Finance cost paid | Z46: -124.33 | AA46: -126.75 | AB46: -155.74 | AC46: -112.08 | AD46: -283.67 | AO46: Proceeds from loans from other related parties | AP46: 418.2 | AQ46: 439.6 | AR46: -3038.5 | AS46: -4842.9 | AT46: -2697.1
A47: Net cash from/used in Investing actitivities | B47: =SUM(B37:B46) -> -556.6 | C47: =SUM(C37:C46) -> -7291.3 | D47: =SUM(D37:D46) -> -239.23 | E47: =SUM(E37:E46) -> -8036.1 | F47: =SUM(F37:F46) -> -10682.8 | G47: =SUM(G37:G46) -> -10241.5 | I47: Proceeds from issue of shares to employees by ESOP trust | J47: 0.53 | K47: 0.58 | L47: 53879.94 | M47: 55622.41 | N47: 61307.84 | O47: 82589.64 | Q47: Acquisition of subsidiary company | R47: -27.04 | S47: 0 | T47: -2968.54 | U47: 3963.25 | V47: 207 | W47: 0 | Y47: Lease liabilities paid | Z47: -43.11 | AA47: -52.24 | AB47: -81.94 | AC47: -127.98 | AD47: -195.7 | AO47: Payment of leased liability | AP47: -335.4 | AQ47: -393.4 | AR47: -264.5 | AS47: -393.6 | AT47: -595.9
A48: Cash flow from Financing activities | I48: Proceeds from borrowings | J48: 52617.59 | K48: 38100.37 | L48: -56937.78 | M48: -37572.29 | N48: -46443.19 | O48: -64227.06 | Q48: Investments in equity accounted investees | R48: -606.4 | S48: -9.9 | T48: -98.45 | U48: 19.37 | V48: 5143 | W48: -12603 | Y48: Dividend and dividend tax paid | Z48: -200.46 | AA48: -99.77 | AB48: -190.4 | AC48: -291.81 | AD48: -380.07 | AO48: Repayment of long term borrowings | AP48: -580.9 | AQ48: -2974.5 | AR48: 0 | AS48: 0 | AT48: 0
A49: Movement in long term/short term borrowings (net) | B49: -45.6 | C49: 380.3 | D49: 109.7 | E49: 831.2 | F49: -1182.7 | G49: -33.1 | I49: Repayment of borrowings | J49: -43415.94 | K49: -35772.09 | L49: -285.21 | M49: 516.71 | N49: -362.03 | O49: -462.16 | Q49: Investments-others | R49: -99.41 | S49: -97.3 | T49: -1228.21 | U49: -2839.87 | V49: -150 | W49: 0 | Y49: Net cash from/used in financing activities | Z49: =SUM(Z43:Z48) -> 1619.17 | AA49: =SUM(AA43:AA48) -> 252.7 | AB49: =SUM(AB43:AB48) -> 2918.02 | AC49: =SUM(AC43:AC48) -> 6118.08 | AD49: =SUM(AD43:AD48) -> 2758.64 | AO49: Repayment of short term borrowings | AP49: -3087.1 | AQ49: -4748.9 | AR49: 0 | AS49: 0 | AT49: 0
A50: Principal elements of lease payments | B50: -9.8 | C50: -11.1 | D50: -8.1 | E50: -46 | F50: -2718.7 | G50: -3930 | I50: Net change in loans repayable on demand and cash credit | J50: -628.14 | K50: -1733.29 | L50: 0 | M50: 400 | N50: 1600 | O50: 2050 | Q50: Proceeds from loans given to others | R50: 3.42 | S50: 0 | T50: -39.71 | U50: -50 | V50: 0 | W50: -688 | Y50: Net increase/decrease in cash and cash equivalents | Z50: =Z28+Z40+Z49 -> 902.45 | AA50: =AA28+AA40+AA49 -> 521.62 | AB50: =AB28+AB40+AB49 -> -127.68 | AC50: =AC28+AC40+AC49 -> 405.51 | AD50: =AD28+AD40+AD49 -> 504.61 | AO50: Repayment of loans to other related parties | AP50: -794 | AQ50: -643.1 | AR50: 0 | AS50: 0 | AT50: 0
A51: Finance cost paid | B51: -135.5 | C51: -101.6 | D51: -129.8 | E51: -185.8 | F51: -13.3 | G51: -19.8 | I51: Repayment of lease liabilities | J51: -557.73 | K51: -552.98 | L51: -583.23 | M51: -750.78 | N51: -785.5 | O51: -887.11 | Q51: Loans given to joint venture | R51: -1.7 | S51: 0 | T51: 103.55 | U51: 59.33 | V51: 107 | W51: 765 | Y51: Cash and cash equivalents at the beginning of the year | Z51: 138.89 | AA51: =Z52 -> 1041.34 | AB51: =AA52 -> 1562.96 | AC51: =AB52 -> 1435.28 | AD51: =AC52 -> 1840.79 | AO51: Net cash from/used in financing activites | AP51: =SUM(AP39:AP50) -> -2802.9 | AQ51: =SUM(AQ39:AQ50) -> -2097.5 | AR51: =SUM(AR39:AR50) -> -1217.4 | AS51: =SUM(AS39:AS50) -> -2734.2 | AT51: =SUM(AT39:AT50) -> 1280.7
A52: Payment of dividend on equity shares | B52: -2416.6 | C52: -1812.5 | D52: -1359.4 | E52: -1812.5 | F52: -5.2 | G52: -7.9 | I52: Dividends paid | J52: -1135.09 | K52: -264.33 | L52: -980.44 | M52: -1284.75 | N52: -1810.54 | O52: -2348.55 | Q52: Proceeds from sale of investments in other companies | R52: 21.45 | S52: 225.82 | T52: 0 | U52: 2872.88 | V52: -5492 | W52: 0 | Y52: Cash and cash equivalents at the end of the year | Z52: =Z50+Z51 -> 1041.34 | AA52: =AA50+AA51 -> 1562.96 | AB52: =AB50+AB51 -> 1435.28 | AC52: =AC50+AC51 -> 1840.79 | AD52: =AD50+AD51 -> 2345.4 | AO52: Net increase/decrease in cash and cash equivalents | AP52: =AP26+AP37+AP51 -> 1309.2 | AQ52: =AQ26+AQ37+AQ51 -> 1060.3 | AR52: =AR26+AR37+AR51 -> -1066.6 | AS52: =AS26+AS37+AS51 -> -336.1 | AT52: =AT26+AT37+AT51 -> 2188.6
A53: Related income tax | B53: -496.8 | C53: 0 | D53: 0 | E53: 0 | F53: -142 | G53: -157.8 | I53: Dividend paid to non-controlling interests | J53: -262.93 | K53: -6.71 | L53: -57.02 | M53: -237.38 | N53: -436.46 | O53: -457.88 | Q53: Interest received | R53: 1104.48 | S53: 427.51 | T53: 652.94 | U53: 973.44 | V53: 5400 | W53: 106 | AO53: Net foreign exchange difference on balance with banks in foreign currency | AP53: 19.7 | AQ53: 7.5 | AR53: 7.5 | AS53: -3.5 | AT53: 17.2
A54: Net cash from/used in financing activities | B54: =SUM(B49:B53) -> -3104.3 | C54: =SUM(C49:C53) -> -1544.9 | D54: =SUM(D49:D53) -> -1387.6 | E54: =SUM(E49:E53) -> -1213.1 | F54: =SUM(F49:F53) -> -4061.9 | G54: =SUM(G49:G53) -> -4148.6 | I54: Transactions with non-controlling interest | J54: -303.57 | K54: 1443.91 | L54: -240.28 | M54: -13.94 | N54: -192.35 | O54: 12.47 | Q54: Dividend received | R54: 21.14 | S54: 18.37 | T54: 32.01 | U54: 46.42 | V54: -74 | W54: -74 | AO54: Net cash and cash equivalents at the beginning of the year | AP54: 3539.9 | AQ54: 4868.8 | AR54: 5936.6 | AS54: 4877.5 | AT54: =AS55 -> 4537.9
A55: Net increase/decrease in cash and cash equivalents | B55: =B35+B47+B54 -> -165.1 | C55: =C35+C47+C54 -> 20 | D55: =D35+D47+D54 -> 213.67 | E55: =E35+E47+E54 -> 2.2 | F55: =F35+F47+F54 -> 422.3 | G55: =G35+G47+G54 -> -377.7 | I55: Interest, commitment and finance charges paid | J55: -624.48 | K55: -809.23 | L55: -679.5 | M55: -734.4 | N55: -596.87 | O55: -435.97 | Q55: Dividend received from equity accounted investees | R55: 622.44 | S55: 1.51 | T55: 0 | U55: 21.69 | V55: 278 | W55: 5 | AO55: Cash and cash equivalents at the end of the year | AP55: =AP52+AP53+AP54 -> 4868.8 | AQ55: =AQ52+AQ53+AQ54 -> 5936.6 | AR55: =AR52+AR53+AR54 -> 4877.5 | AS55: =AS52+AS53+AS54 -> 4537.9 | AT55: =AT52+AT53+AT54 -> 6743.7
A56: Cash and cash equivalents at the beginning of year | B56: 185.9 | C56: =B57 -> 20.8 | D56: =C57 -> 40.8 | E56: =D57 -> 254.47 | F56: =E57 -> 256.67 | G56: =F57 -> 678.97 | I56: Net cash from/used in Financing activities | J56: =SUM(J46:J55) -> 6932.75 | K56: =SUM(K46:K55) -> 406.23 | L56: =SUM(L46:L55) -> -5882.6 | M56: =SUM(M46:M55) -> 15946.11 | N56: =SUM(N46:N55) -> 12281.41 | O56: =SUM(O46:O55) -> 15834.11 | Q56: Deposits with financial institution | R56: -1000 | S56: -1000 | T56: -600 | U56: -2169.57 | V56: 2493 | W56: 2420
A57: Cash and cash equivalents at the end of the year | B57: =B55+B56 -> 20.8 | C57: =C55+C56 -> 40.8 | D57: =D55+D56 -> 254.47 | E57: =E55+E56 -> 256.67 | F57: =F55+F56 -> 678.97 | G57: =G55+G56 -> 301.27 | I57: Net increase/decrease in cash and cash equivalents | J57: =J25+J44+J56 -> -1419.01 | K57: =K25+K44+K56 -> -131.7 | L57: =L25+L44+L56 -> 139.13 | M57: =M25+M44+M56 -> 324.83 | N57: =N25+N44+N56 -> 1053.69 | O57: =O25+O44+O56 -> 383.81 | Q57: Realisation of deposit with financial institution | R57: 750 | S57: 750 | T57: 1300 | U57: 1469.59 | V57: 47 | W57: 64
I58: Cash and cash equivalents at the beginning of the year | J58: 6139 | K58: 4745.03 | L58: 3374.59 | M58: 3487.59 | N58: 3493.41 | O58: 4530.1 | Q58: Deposits/restricted deposits with banks | R58: -40676.65 | S58: -38243.27 | T58: -13203.08 | U58: -17723.34 | V58: 49 | W58: 111
I59: Cash and cash equivalents related to discontinued operations | J59: 0 | K59: -1252.79 | L59: -13.36 | M59: -352.87 | N59: -4.97 | O59: 0 | Q59: Realisation of deposits/restricted deposits with banks | R59: 36602.33 | S59: 39088.68 | T59: 25978.6 | U59: 15497.79 | V59: -25 | W59: -20
I60: Unrealised gain/loss on foreign currency cash and cash equivalents | J60: 25.04 | K60: 14.05 | L60: -12.77 | M60: 33.86 | N60: -12.03 | O60: 9.98 | Q60: Increase/decrease in short term inter-corporate deposits | R60: -14.44 | S60: 0 | T60: 234.09 | U60: -298.2 | V60: =-7326+7905 -> 579 | W60: =-8626+8014 -> -612
I61: Cash and cash equivalents at the end of the year | J61: =SUM(J57:J60) -> 4745.03 | K61: =SUM(K57:K60) -> 3374.59 | L61: =SUM(L57:L60) -> 3487.59 | M61: =SUM(M57:M60) -> 3493.41 | N61: =SUM(N57:N60) -> 4530.1 | O61: =SUM(O57:O60) -> 4923.89 | Q61: Net cash from/used in Investing activities | R61: =SUM(R43:R60) -> -34170.22 | S61: =SUM(S43:S60) -> -26126.25 | T61: =SUM(T43:T60) -> -4775.12 | U61: =SUM(U43:U60) -> -16804.16 | V61: =SUM(V43:V60) -> -22828 | W61: =SUM(W43:W60) -> -47594
Q62: Cash flow from Financing activities
Q63: Proceeds from issue of shares and warrants | R63: 3888.77 | S63: 2602.51 | T63: 18.59 | U63: 19.6 | V63: 82 | W63: 35
Q64: Proceeds from long-term borrowings | R64: 28741.21 | S64: 29642.36 | T64: 3750 | U64: 3750 | V64: 11629 | W64: 7386
Q65: Repayment of long term borrowings | R65: -16993.77 | S65: -18629.61 | T65: 0 | U65: -295.92 | V65: -31675 | W65: -19600
Q66: Proceeds from option settlement of long term borrowings | R66: 190.9 | S66: 35.01 | T66: 0 | U66: -99.5 | V66: -83 | W66: 186
Q67: Repayment of matured fixed deposits | R67: -6.75 | S67: -0.48 | T67: 31308.62 | U67: 16315.06 | V67: 0 | W67: 0
Q68: Proceeds from short term borrowings | R68: 10707.3 | S68: 20807.15 | T68: -23355.8 | U68: -31559.46 | V68: 10194 | W68: 846
Q69: Repayment of short term borrowings | R69: -12852.93 | S69: -11078.93 | T69: -97.77 | U69: -106.51 | V69: -15656 | W69: -1843
Q70: Net change in other short term borrowings | R70: -1587.12 | S70: -4544.27 | T70: 16866.24 | U70: 28125.45 | V70: -2994 | W70: 4966
Q71: Repayment of lease liability | R71: -1345.61 | S71: -1477.28 | T71: -19460.45 | U71: -30997.82 | V71: -1924 | W71: -2393
Q72: Dividend paid to non-controlling interest shareholders of subsidiaries | R72: -53.32 | S72: -28.75 | T72: -1975.59 | U72: -753.73 | V72: 3812 | W72: 0
Q73: Proceeds from issuance/payment for acquisition of shares from non-controlling | R73: -22.15 | S73: 0.24 | T73: -1558.95 | U73: -1516.61 | V73: 0 | W73: -63
Q74: Dividend paid | R74: -3.52 | S74: -1.56 | T74: -98.39 | U74: -140.88 | V74: -769 | W74: -2303
Q75: Proceeds from issuance of perpetual debt instrument classified | R75: 245 | S75: 700.75 | T75: =-1.53+476.28 -> 474.75 | U75: =353.38 -> 353.38 | V75: -290 | W75: -189
Q76: Interest paid | R76: -7518.4 | S76: -8122.94 | T76: -9251.42 | U76: -9335.96 | V76: -9332 | W76: -5814
Q77: Net cash from Financing activities | R77: =SUM(R63:R76) -> 3389.61 | S77: =SUM(S63:S76) -> 9904.2 | T77: =SUM(T63:T76) -> -3380.17 | U77: =SUM(U63:U76) -> -26242.9 | V77: =SUM(V63:V76) -> -37006 | W77: =SUM(W63:W76) -> -18786
Q78: Net increase/decrease in cash and cash equivalents | R78: =R41+R61+R77 -> -4147.67 | S78: =S41+S61+S77 -> 12778.46 | T78: =T41+T61+T77 -> 6127.54 | U78: =U41+U61+U77 -> -7659.05 | V78: =V41+V61+V77 -> 8081 | W78: =W41+W61+W77 -> -3278
Q79: Cash and cash equivalens at the beginning of the year | R79: 21559.8 | S79: 18467.8 | T79: =S81 -> 31700.01 | U79: =T81 -> 38159.01 | V79: =U81 -> 31886.95 | W79: =V81 -> 40014.95
Q80: Effect of foreign exchange on cash and cash equivalents | R80: 1055.67 | S80: 453.75 | T80: 331.46 | U80: 1386.99 | V80: 47 | W80: =-232-2999+843 -> -2388
Q81: Cash and cash equivalents at the end of the year | R81: =R78+R79+R80 -> 18467.8 | S81: =S78+S79+S80 -> 31700.01 | T81: =T78+T79+T80 -> 38159.01 | U81: =U78+U79+U80 -> 31886.95 | V81: =V78+V79+V80 -> 40014.95 | W81: =W78+W79+W80 -> 34348.95

Sheet Financial Ratios
A1: FINANCIAL RATIOS | G1: #VALUE! | J1: FINANCIAL RATIOS | P1: #VALUE! | S1: FINANCIAL RATIOS | Y1: #VALUE! | AB1: FINANCIAL RATIOS | AH1: #VALUE! | AK1: FINANCIAL RATIOS | AQ1: #VALUE! | AT1: FINANCIAL RATIOS | AZ1: #VALUE!
A2: Category | B2: Ratio | C2: 2020 | D2: 2021 | E2: 2022 | F2: 2023 | G2: 2024 | H2: 2025 | J2: Category | K2: Ratio | L2: 2020 | M2: 2021 | N2: 2022 | O2: 2023 | P2: 2024 | Q2: 2025 | S2: Category | T2: Ratio | U2: 2020 | V2: 2021 | W2: 2022 | X2: 2023 | Y2: 2024 | Z2: 2025 | AB2: Category | AC2: Ratio | AD2: 2020 | AE2: 2021 | AF2: 2022 | AG2: 2023 | AH2: 2024 | AI2: NA | AK2: Category | AL2: Ratio | AM2: 2020 | AN2: 2021 | AO2: 2022 | AP2: 2023 | AQ2: 2024 | AR2: 2025 | AT2: Category | AU2: Ratio | AV2: 2020 | AW2: 2021 | AX2: 2022 | AY2: 2023 | AZ2: 2024 | BA2: NA
A3: Liquidity | B3: Current Ratio | C3: ='Balance Sheet'!B27/'Balance Sheet'!B56 -> 0.74659897 | D3: ='Balance Sheet'!C27/'Balance Sheet'!C56 -> 1.1503551 | E3: ='Balance Sheet'!D27/'Balance Sheet'!D56 -> 0.98648339 | F3: ='Balance Sheet'!E27/'Balance Sheet'!E56 -> 0.57768074 | G3: ='Balance Sheet'!F27/'Balance Sheet'!F56 -> 0.77467977 | H3: ='Balance Sheet'!G27/'Balance Sheet'!G56 -> 0.87019427 | J3: Liquidity | K3: Current Ratio | L3: ='Balance Sheet'!J31/'Balance Sheet'!J61 -> 1.1858174 | M3: ='Balance Sheet'!K31/'Balance Sheet'!K61 -> 1.4022061 | N3: ='Balance Sheet'!L31/'Balance Sheet'!L61 -> 1.3350547 | O3: ='Balance Sheet'!M31/'Balance Sheet'!M61 -> 1.2939388 | P3: ='Balance Sheet'!N31/'Balance Sheet'!N61 -> 1.3007452 | Q3: ='Balance Sheet'!O31/'Balance Sheet'!O61 -> 1.4013558 | S3: Liquidity | T3: Current Ratio | U3: ='Balance Sheet'!R34/'Balance Sheet'!R65 -> 0.85142956 | V3: ='Balance Sheet'!S34/'Balance Sheet'!S65 -> 0.93114677 | W3: ='Balance Sheet'!T34/'Balance Sheet'!T65 -> 0.97541013 | X3: ='Balance Sheet'!U34/'Balance Sheet'!U65 -> 0.97743069 | Y3: ='Balance Sheet'!V34/'Balance Sheet'!V65 -> 0.96991061 | Z3: ='Balance Sheet'!W34/'Balance Sheet'!W65 -> 0.96184997 | AB3: Liquidity | AC3: Current Ratio | AD3: ='Balance Sheet'!Z32/'Balance Sheet'!Z61 -> 0.97144807 | AE3: ='Balance Sheet'!AA32/'Balance Sheet'!AA61 -> 0.96591073 | AF3: ='Balance Sheet'!AB32/'Balance Sheet'!AB61 -> 0.92754329 | AG3: ='Balance Sheet'!AC32/'Balance Sheet'!AC61 -> 0.8858185 | AH3: ='Balance Sheet'!AD32/'Balance Sheet'!AD61 -> 1.02096 | AK3: Liquidity | AL3: Current Ratio | AM3: ='Balance Sheet'!AH33/'Balance Sheet'!AH72 -> 1.6638065 | AN3: ='Balance Sheet'!AI33/'Balance Sheet'!AI72 -> 1.302014 | AO3: ='Balance Sheet'!AJ33/'Balance Sheet'!AJ72 -> 1.8174382 | AP3: ='Balance Sheet'!AK33/'Balance Sheet'!AK72 -> 1.8816985 | AQ3: ='Balance Sheet'!AL33/'Balance Sheet'!AL72 -> 1.4056067 | AR3: ='Balance Sheet'!AM33/'Balance Sheet'!AM72 -> 1.2251015 | AT3: Liquidity | AU3: Current Ratio | AV3: ='Balance Sheet'!AP32/'Balance Sheet'!AP67 -> 0.99461443 | AW3: ='Balance Sheet'!AQ32/'Balance Sheet'!AQ67 -> 0.99774321 | AX3: ='Balance Sheet'!AR32/'Balance Sheet'!AR67 -> 1.0148484 | AY3: ='Balance Sheet'!AS32/'Balance Sheet'!AS67 -> 0.97324407 | AZ3: ='Balance Sheet'!AT32/'Balance Sheet'!AT67 -> 0.96528796
B4: Quick ratio | C4: =('Balance Sheet'!B27-'Balance Sheet'!B17)/'Balance Sheet'!B56 -> 0.46231889 | D4: =('Balance Sheet'!C27-'Balance Sheet'!C17)/'Balance Sheet'!C56 -> 0.96121708 | E4: =('Balance Sheet'!D27-'Balance Sheet'!D17)/'Balance Sheet'!D56 -> 0.77898787 | F4: =('Balance Sheet'!E27-'Balance Sheet'!E17)/'Balance Sheet'!E56 -> 0.36464866 | G4: =('Balance Sheet'!F27-'Balance Sheet'!F17)/'Balance Sheet'!F56 -> 0.59500975 | H4: =('Balance Sheet'!G27-'Balance Sheet'!G17)/'Balance Sheet'!G56 -> 0.67847025 | K4: Quick ratio | L4: =('Balance Sheet'!J31-'Balance Sheet'!J21)/'Balance Sheet'!J61 -> 0.98007851 | M4: =('Balance Sheet'!K31-'Balance Sheet'!K21)/'Balance Sheet'!K61 -> 1.2153032 | N4: =('Balance Sheet'!L31-'Balance Sheet'!L21)/'Balance Sheet'!L61 -> 1.1290472 | O4: =('Balance Sheet'!M31-'Balance Sheet'!M21)/'Balance Sheet'!M61 -> 1.0551302 | P4: =('Balance Sheet'!N31-'Balance Sheet'!N21)/'Balance Sheet'!N61 -> 1.0546626 | Q4: =('Balance Sheet'!O31-'Balance Sheet'!O21)/'Balance Sheet'!O61 -> 1.1762619 | T4: Quick ratio | U4: =('Balance Sheet'!R34-'Balance Sheet'!R22)/'Balance Sheet'!R65 -> 0.58474533 | V4: =('Balance Sheet'!S34-'Balance Sheet'!S22)/'Balance Sheet'!S65 -> 0.70237481 | W4: =('Balance Sheet'!T34-'Balance Sheet'!T22)/'Balance Sheet'!T65 -> 0.74153913 | X4: =('Balance Sheet'!U34-'Balance Sheet'!U22)/'Balance Sheet'!U65 -> 0.71453904 | Y4: =('Balance Sheet'!V34-'Balance Sheet'!V22)/'Balance Sheet'!V65 -> 0.69465948 | Z4: =('Balance Sheet'!W34-'Balance Sheet'!W22)/'Balance Sheet'!W65 -> 0.67826546 | AC4: Quick ratio | AD4: =('Balance Sheet'!Z32-'Balance Sheet'!Z23)/'Balance Sheet'!Z61 -> 0.85290028 | AE4: =('Balance Sheet'!AA32-'Balance Sheet'!AA23)/'Balance Sheet'!AA61 -> 0.8405586 | AF4: =('Balance Sheet'!AB32-'Balance Sheet'!AB23)/'Balance Sheet'!AB61 -> 0.80897607 | AG4: =('Balance Sheet'!AC32-'Balance Sheet'!AC23)/'Balance Sheet'!AC61 -> 0.78583723 | AH4: =('Balance Sheet'!AD32-'Balance Sheet'!AD23)/'Balance Sheet'!AD61 -> 0.91429063 | AL4: Quick ratio | AM4: =('Balance Sheet'!AH33-'Balance Sheet'!AH22)/'Balance Sheet'!AH72 -> 0.92121911 | AN4: =('Balance Sheet'!AI33-'Balance Sheet'!AI22)/'Balance Sheet'!AI72 -> 0.75321813 | AO4: =('Balance Sheet'!AJ33-'Balance Sheet'!AJ22)/'Balance Sheet'!AJ72 -> 0.80414786 | AP4: =('Balance Sheet'!AK33-'Balance Sheet'!AK22)/'Balance Sheet'!AK72 -> 0.74546933 | AQ4: =('Balance Sheet'!AL33-'Balance Sheet'!AL22)/'Balance Sheet'!AL72 -> 0.53579716 | AR4: =('Balance Sheet'!AM33-'Balance Sheet'!AM22)/'Balance Sheet'!AM72 -> 0.44880679 | AU4: Quick ratio | AV4: =('Balance Sheet'!AP32-'Balance Sheet'!AP23)/'Balance Sheet'!AP67 -> 0.73113005 | AW4: =('Balance Sheet'!AQ32-'Balance Sheet'!AQ23)/'Balance Sheet'!AQ67 -> 0.75158542 | AX4: =('Balance Sheet'!AR32-'Balance Sheet'!AR23)/'Balance Sheet'!AR67 -> 0.72579234 | AY4: =('Balance Sheet'!AS32-'Balance Sheet'!AS23)/'Balance Sheet'!AS67 -> 0.68893783 | AZ4: =('Balance Sheet'!AT32-'Balance Sheet'!AT23)/'Balance Sheet'!AT67 -> 0.74624404
A5: Solvency | B5: Debt to Equity | C5: =('Balance Sheet'!B39+'Balance Sheet'!B47)/'Balance Sheet'!B35 -> 0.0022596607 | D5: =('Balance Sheet'!C39+'Balance Sheet'!C47)/'Balance Sheet'!C35 -> 0.0093637025 | E5: =('Balance Sheet'!D39+'Balance Sheet'!D47)/'Balance Sheet'!D35 -> 0.0069017864 | F5: =('Balance Sheet'!E39+'Balance Sheet'!E47)/'Balance Sheet'!E35 -> 0.019675909 | G5: =('Balance Sheet'!F39+'Balance Sheet'!F47)/'Balance Sheet'!F35 -> 0.00039413208 | H5: =('Balance Sheet'!G39+'Balance Sheet'!G47)/'Balance Sheet'!G35 -> 0 | J5: Solvency | K5: Debt to Equity | L5: =('Balance Sheet'!J43+'Balance Sheet'!J52)/'Balance Sheet'!J39 -> 1.3116702 | M5: =('Balance Sheet'!K43+'Balance Sheet'!K52)/'Balance Sheet'!K39 -> 1.1757261 | N5: =('Balance Sheet'!L43+'Balance Sheet'!L52)/'Balance Sheet'!L39 -> 1.3139787 | O5: =('Balance Sheet'!M43+'Balance Sheet'!M52)/'Balance Sheet'!M39 -> 1.3232591 | P5: =('Balance Sheet'!N43+'Balance Sheet'!N52)/'Balance Sheet'!N39 -> 1.3314941 | Q5: =('Balance Sheet'!O43+'Balance Sheet'!O52)/'Balance Sheet'!O39 -> 1.3599963 | S5: Solvency | T5: Debt to Equity | U5: =('Balance Sheet'!R46+'Balance Sheet'!R55)/'Balance Sheet'!R42 -> 1.5601016 | V5: =('Balance Sheet'!S46+'Balance Sheet'!S55)/'Balance Sheet'!S42 -> 2.0199778 | W5: =('Balance Sheet'!T46+'Balance Sheet'!T55)/'Balance Sheet'!T42 -> 2.8603412 | X5: =('Balance Sheet'!U46+'Balance Sheet'!U55)/'Balance Sheet'!U42 -> 2.3890046 | Y5: =('Balance Sheet'!V46+'Balance Sheet'!V55)/'Balance Sheet'!V42 -> 1.0580811 | Z5: =('Balance Sheet'!W46+'Balance Sheet'!W55)/'Balance Sheet'!W42 -> 0.50914023 | AB5: Solvency | AC5: Debt to Equity | AD5: =('Balance Sheet'!Z52+'Balance Sheet'!Z44)/'Balance Sheet'!Z40 -> 2.4984263 | AE5: =('Balance Sheet'!AA52+'Balance Sheet'!AA44)/'Balance Sheet'!AA40 -> 2.2184097 | AF5: =('Balance Sheet'!AB52+'Balance Sheet'!AB44)/'Balance Sheet'!AB40 -> 3.0273599 | AG5: =('Balance Sheet'!AC52+'Balance Sheet'!AC44)/'Balance Sheet'!AC40 -> 3.6593535 | AH5: =('Balance Sheet'!AD52+'Balance Sheet'!AD44)/'Balance Sheet'!AD40 -> 3.3665623 | AK5: Solvency | AL5: Debt to Equity | AM5: =('Balance Sheet'!AH45+'Balance Sheet'!AH61)/'Balance Sheet'!AH41 -> 0.010343462 | AN5: =('Balance Sheet'!AI45+'Balance Sheet'!AI61)/'Balance Sheet'!AI41 -> 0.018070668 | AO5: =('Balance Sheet'!AJ45+'Balance Sheet'!AJ61)/'Balance Sheet'!AJ41 -> 0.019694182 | AP5: =('Balance Sheet'!AK45+'Balance Sheet'!AK61)/'Balance Sheet'!AK41 -> 0.025076068 | AQ5: =('Balance Sheet'!AL45+'Balance Sheet'!AL61)/'Balance Sheet'!AL41 -> 0.054021625 | AR5: =('Balance Sheet'!AM45+'Balance Sheet'!AM61)/'Balance Sheet'!AM41 -> 0.11203937 | AT5: Solvency | AU5: Debt to Equity | AV5: =('Balance Sheet'!AP58+'Balance Sheet'!AP47)/'Balance Sheet'!AP43 -> 0.78707532 | AW5: =('Balance Sheet'!AQ58+'Balance Sheet'!AQ47)/'Balance Sheet'!AQ43 -> 0.53221498 | AX5: =('Balance Sheet'!AR58+'Balance Sheet'!AR47)/'Balance Sheet'!AR43 -> 0.57058476 | AY5: =('Balance Sheet'!AS58+'Balance Sheet'!AS47)/'Balance Sheet'!AS43 -> 0.49906674 | AZ5: =('Balance Sheet'!AT58+'Balance Sheet'!AT47)/'Balance Sheet'!AT43 -> 0.61495632
B6: Interest coverage | C6: =('Income Statement'!B19+'Income Statement'!B12)/'Income Statement'!B12 -> 53.926975 | D6: =('Income Statement'!C19+'Income Statement'!C12)/'Income Statement'!C12 -> 53.269155 | E6: =('Income Statement'!D19+'Income Statement'!D12)/'Income Statement'!D12 -> 38.102686 | F6: =('Income Statement'!E19+'Income Statement'!E12)/'Income Statement'!E12 -> 56.203743 | G6: =('Income Statement'!F19+'Income Statement'!F12)/'Income Statement'!F12 -> 89.200311 | H6: =('Income Statement'!G19+'Income Statement'!G12)/'Income Statement'!G12 -> 100.34335 | K6: Interest coverage | L6: =('Income Statement'!J17+'Income Statement'!J12+'Income Statement'!J13)/'Income Statement'!J12 -> 2.3617183 | M6: =('Income Statement'!K17+'Income Statement'!K12+'Income Statement'!K13)/'Income Statement'!K12 -> 2.4105424 | N6: =('Income Statement'!L17+'Income Statement'!L12+'Income Statement'!L13)/'Income Statement'!L12 -> 3.1122368 | O6: =('Income Statement'!M17+'Income Statement'!M12+'Income Statement'!M13)/'Income Statement'!M12 -> 3.6866014 | P6: =('Income Statement'!N17+'Income Statement'!N12+'Income Statement'!N13)/'Income Statement'!N12 -> 3.6147958 | Q6: =('Income Statement'!O17+'Income Statement'!O12+'Income Statement'!O13)/'Income Statement'!O12 -> 3.5998939 | T6: Interest coverage | U6: =('Income Statement'!R23+'Income Statement'!R16)/'Income Statement'!R16 -> -0.064225984 | V6: =('Income Statement'!S23+'Income Statement'!S16)/'Income Statement'!S16 -> 1.4059122 | W6: =('Income Statement'!T23+'Income Statement'!T16)/'Income Statement'!T16 -> 0.31551484 | X6: =('Income Statement'!U23+'Income Statement'!U16)/'Income Statement'!U16 -> 1.1434671 | Y6: =('Income Statement'!V23+'Income Statement'!V16)/'Income Statement'!V16 -> 4.7750856 | Z6: =('Income Statement'!W23+'Income Statement'!W16)/'Income Statement'!W16 -> 7.6974228 | AC6: Interest coverage | AD6: =('Income Statement'!Z16+'Income Statement'!Z12)/'Income Statement'!Z12 -> 2.0699792 | AE6: =('Income Statement'!AA16+'Income Statement'!AA12)/'Income Statement'!AA12 -> 1.9515026 | AF6: =('Income Statement'!AB16+'Income Statement'!AB12)/'Income Statement'!AB12 -> 2.17464 | AG6: =('Income Statement'!AC16+'Income Statement'!AC12)/'Income Statement'!AC12 -> 2.4464833 | AH6: =('Income Statement'!AD16+'Income Statement'!AD12)/'Income Statement'!AD12 -> 2.424683 | AL6: Interest coverage | AM6: =('Income Statement'!AH19+'Income Statement'!AH15)/'Income Statement'!AH15 -> 11.286572 | AN6: =('Income Statement'!AI19+'Income Statement'!AI15)/'Income Statement'!AI15 -> 8.5560166 | AO6: =('Income Statement'!AJ19+'Income Statement'!AJ15)/'Income Statement'!AJ15 -> 16.765797 | AP6: =('Income Statement'!AK19+'Income Statement'!AK15)/'Income Statement'!AK15 -> 16.406148 | AQ6: =('Income Statement'!AL19+'Income Statement'!AL15)/'Income Statement'!AL15 -> 11.613534 | AR6: =('Income Statement'!AM19+'Income Statement'!AM15)/'Income Statement'!AM15 -> 8.6845063 | AU6: Interest coverage | AV6: =('Income Statement'!AP18+'Income Statement'!AP15)/'Income Statement'!AP15 -> 3.6396761 | AW6: =('Income Statement'!AQ18+'Income Statement'!AQ15)/'Income Statement'!AQ15 -> 3.2496579 | AX6: =('Income Statement'!AR18+'Income Statement'!AR15)/'Income Statement'!AR15 -> 3.6839292 | AY6: =('Income Statement'!AS18+'Income Statement'!AS15)/'Income Statement'!AS15 -> 4.2629018 | AZ6: =('Income Statement'!AT18+'Income Statement'!AT15)/'Income Statement'!AT15 -> 3.1270428
B7: Debt ratio | C7: =('Balance Sheet'!B39+'Balance Sheet'!B47)/'Balance Sheet'!B28 -> 0.0017555247 | D7: =('Balance Sheet'!C39+'Balance Sheet'!C47)/'Balance Sheet'!C28 -> 0.006896484 | E7: =('Balance Sheet'!D39+'Balance Sheet'!D47)/'Balance Sheet'!D28 -> 0.0051154972 | F7: =('Balance Sheet'!E39+'Balance Sheet'!E47)/'Balance Sheet'!E28 -> 0.014371685 | G7: =('Balance Sheet'!F39+'Balance Sheet'!F47)/'Balance Sheet'!F28 -> 0.00030013202 | H7: =('Balance Sheet'!G39+'Balance Sheet'!G47)/'Balance Sheet'!G28 -> 0 | K7: Debt ratio | L7: =('Balance Sheet'!J43+'Balance Sheet'!J52)/'Balance Sheet'!J32 -> 0.37432986 | M7: =('Balance Sheet'!K43+'Balance Sheet'!K52)/'Balance Sheet'!K32 -> 0.35775717 | N7: =('Balance Sheet'!L43+'Balance Sheet'!L52)/'Balance Sheet'!L32 -> 0.42884372 | O7: =('Balance Sheet'!M43+'Balance Sheet'!M52)/'Balance Sheet'!M32 -> 0.43113433 | P7: =('Balance Sheet'!N43+'Balance Sheet'!N52)/'Balance Sheet'!N32 -> 0.43674529 | Q7: =('Balance Sheet'!O43+'Balance Sheet'!O52)/'Balance Sheet'!O32 -> 0.43652357 | T7: Debt ratio | U7: =('Balance Sheet'!R46+'Balance Sheet'!R55)/'Balance Sheet'!R35 -> 0.30944344 | V7: =('Balance Sheet'!S46+'Balance Sheet'!S55)/'Balance Sheet'!S35 -> 0.33449994 | W7: =('Balance Sheet'!T46+'Balance Sheet'!T55)/'Balance Sheet'!T35 -> 0.42247012 | X7: =('Balance Sheet'!U46+'Balance Sheet'!U55)/'Balance Sheet'!U35 -> 0.37389893 | Y7: =('Balance Sheet'!V46+'Balance Sheet'!V55)/'Balance Sheet'!V35 -> 0.26574202 | Z7: =('Balance Sheet'!W46+'Balance Sheet'!W55)/'Balance Sheet'!W35 -> 0.16506093 | AC7: Debt ratio | AD7: =('Balance Sheet'!Z44+'Balance Sheet'!Z52)/'Balance Sheet'!Z33 -> 0.46500407 | AE7: =('Balance Sheet'!AA44+'Balance Sheet'!AA52)/'Balance Sheet'!AA33 -> 0.42511898 | AF7: =('Balance Sheet'!AB44+'Balance Sheet'!AB52)/'Balance Sheet'!AB33 -> 0.5650614 | AG7: =('Balance Sheet'!AC44+'Balance Sheet'!AC52)/'Balance Sheet'!AC33 -> 0.61380766 | AH7: =('Balance Sheet'!AD44+'Balance Sheet'!AD52)/'Balance Sheet'!AD33 -> 0.59891863 | AL7: Debt ratio | AM7: =('Balance Sheet'!AH45+'Balance Sheet'!AH61)/'Balance Sheet'!AH34 -> 0.0027651483 | AN7: =('Balance Sheet'!AI45+'Balance Sheet'!AI61)/'Balance Sheet'!AI34 -> 0.0046100845 | AO7: =('Balance Sheet'!AJ45+'Balance Sheet'!AJ61)/'Balance Sheet'!AJ34 -> 0.015041037 | AP7: =('Balance Sheet'!AK45+'Balance Sheet'!AK61)/'Balance Sheet'!AK34 -> 0.018918341 | AQ7: =('Balance Sheet'!AL45+'Balance Sheet'!AL61)/'Balance Sheet'!AL34 -> 0.038399958 | AR7: =('Balance Sheet'!AM45+'Balance Sheet'!AM61)/'Balance Sheet'!AM34 -> 0.072964723 | AU7: Debt ratio | AV7: =('Balance Sheet'!AP47+'Balance Sheet'!AP58)/'Balance Sheet'!AP34 -> 0.25648741 | AW7: =('Balance Sheet'!AQ47+'Balance Sheet'!AQ58)/'Balance Sheet'!AQ34 -> 0.18355412 | AX7: =('Balance Sheet'!AR47+'Balance Sheet'!AR58)/'Balance Sheet'!AR34 -> 0.22677941 | AY7: =('Balance Sheet'!AS47+'Balance Sheet'!AS58)/'Balance Sheet'!AS34 -> 0.19669144 | AZ7: =('Balance Sheet'!AT47+'Balance Sheet'!AT58)/'Balance Sheet'!AT34 -> 0.20408084
A8: Profitability | B8: Net Profit margin | C8: =('Income Statement'!B24/'Income Statement'!B4) -> 0.075040973 | D8: =('Income Statement'!C24/'Income Statement'!C4) -> 0.062369977 | E8: =('Income Statement'!D24/'Income Statement'!D4) -> 0.043920625 | F8: =('Income Statement'!E24/'Income Statement'!E4) -> 0.069838472 | G8: =('Income Statement'!F24/'Income Statement'!F4) -> 0.097891769 | H8: =('Income Statement'!G24/'Income Statement'!G4) -> 0.096166356 | J8: Profitability | K8: Net Profit margin | L8: ='Income Statement'!J29/'Income Statement'!J4 -> -0.004258315 | M8: ='Income Statement'!K29/'Income Statement'!K4 -> 0.020361271 | N8: ='Income Statement'!L29/'Income Statement'!L4 -> 0.080436555 | O8: ='Income Statement'!M29/'Income Statement'!M4 -> 0.093795795 | P8: ='Income Statement'!N29/'Income Statement'!N4 -> 0.088732153 | Q8: ='Income Statement'!O29/'Income Statement'!O4 -> 0.088650029 | S8: Profitability | T8: Net Profit margin | U8: ='Income Statement'!R42/'Income Statement'!R4 -> -0.040913421 | V8: ='Income Statement'!S42/'Income Statement'!S4 -> -0.04241077 | W8: ='Income Statement'!T42/'Income Statement'!T4 -> -0.041087618 | X8: ='Income Statement'!U42/'Income Statement'!U4 -> 0.007845055 | Y8: ='Income Statement'!V42/'Income Statement'!V4 -> 0.073761862 | Z8: ='Income Statement'!W42/'Income Statement'!W4 -> 0.064440583 | AB8: Profitability | AC8: Net Profit margin | AD8: ='Income Statement'!Z27/'Income Statement'!Z4 -> 0.033137553 | AE8: ='Income Statement'!AA27/'Income Statement'!AA4 -> 0.03059912 | AF8: ='Income Statement'!AB27/'Income Statement'!AB4 -> 0.031074127 | AG8: ='Income Statement'!AC27/'Income Statement'!AC4 -> 0.041554714 | AH8: ='Income Statement'!AD27/'Income Statement'!AD4 -> 0.043080373 | AK8: Profitability | AL8: Net Profit margin | AM8: ='Income Statement'!AH26/'Income Statement'!AH4 -> 0.052690172 | AN8: ='Income Statement'!AI26/'Income Statement'!AI4 -> 0.052500868 | AO8: ='Income Statement'!AJ26/'Income Statement'!AJ4 -> 0.05428869 | AP8: ='Income Statement'!AK26/'Income Statement'!AK4 -> 0.054567003 | AQ8: ='Income Statement'!AL26/'Income Statement'!AL4 -> 0.052643662 | AR8: ='Income Statement'!AM26/'Income Statement'!AM4 -> 0.046438506 | AT8: Profitability | AU8: Net Profit margin | AV8: ='Income Statement'!AP34/'Income Statement'!AP4 -> 0.02147539 | AW8: ='Income Statement'!AQ34/'Income Statement'!AQ4 -> 0.027556878 | AX8: ='Income Statement'!AR34/'Income Statement'!AR4 -> 0.01877283 | AY8: ='Income Statement'!AS34/'Income Statement'!AS4 -> 0.02144067 | AZ8: ='Income Statement'!AT34/'Income Statement'!AT4 -> 0.03088176
B9: EBITDA Margin | C9: =('Income Statement'!B19+'Income Statement'!B12+'Income Statement'!B13)/'Income Statement'!B4 -> 0.14228655 | D9: =('Income Statement'!C19+'Income Statement'!C12+'Income Statement'!C13)/'Income Statement'!C4 -> 0.12017422 | E9: =('Income Statement'!D19+'Income Statement'!D12+'Income Statement'!D13)/'Income Statement'!D4 -> 0.086186089 | F9: =('Income Statement'!E19+'Income Statement'!E12+'Income Statement'!E13)/'Income Statement'!E4 -> 0.11342734 | G9: =('Income Statement'!F19+'Income Statement'!F12+'Income Statement'!F13)/'Income Statement'!F4 -> 0.15011213 | H9: =('Income Statement'!G19+'Income Statement'!G12+'Income Statement'!G13)/'Income Statement'!G4 -> 0.15529455 | K9: EBITDA Margin | L9: =('Income Statement'!J17+'Income Statement'!J12+'Income Statement'!J13)/'Income Statement'!J4 -> 0.18864282 | M9: =('Income Statement'!K17+'Income Statement'!K12+'Income Statement'!K13)/'Income Statement'!K4 -> 0.19803581 | N9: =('Income Statement'!L17+'Income Statement'!L12+'Income Statement'!L13)/'Income Statement'!L4 -> 0.17319797 | O9: =('Income Statement'!M17+'Income Statement'!M12+'Income Statement'!M13)/'Income Statement'!M4 -> 0.17722468 | P9: =('Income Statement'!N17+'Income Statement'!N12+'Income Statement'!N13)/'Income Statement'!N4 -> 0.19575128 | Q9: =('Income Statement'!O17+'Income Statement'!O12+'Income Statement'!O13)/'Income Statement'!O4 -> 0.20597979 | T9: EBITDA Margin | U9: =('Income Statement'!R23+'Income Statement'!R18+'Income Statement'!R16)/'Income Statement'!R4 -> 0.081054436 | V9: =('Income Statement'!S23+'Income Statement'!S18+'Income Statement'!S16)/'Income Statement'!S4 -> 0.14143545 | W9: =('Income Statement'!T23+'Income Statement'!T18+'Income Statement'!T16)/'Income Statement'!T4 -> 0.10090903 | X9: =('Income Statement'!U23+'Income Statement'!U18+'Income Statement'!U16)/'Income Statement'!U4 -> 0.10660708 | Y9: =('Income Statement'!V23+'Income Statement'!V18+'Income Statement'!V16)/'Income Statement'!V4 -> 0.14726167 | Z9: =('Income Statement'!W23+'Income Statement'!W18+'Income Statement'!W16)/'Income Statement'!W4 -> 0.14280907 | AC9: EBITDA Margin | AD9: =('Income Statement'!Z16+'Income Statement'!Z12+'Income Statement'!Z13)/'Income Statement'!Z4 -> 0.12334032 | AE9: =('Income Statement'!AA16+'Income Statement'!AA12+'Income Statement'!AA13)/'Income Statement'!AA4 -> 0.11765981 | AF9: =('Income Statement'!AB16+'Income Statement'!AB12+'Income Statement'!AB13)/'Income Statement'!AB4 -> 0.11445143 | AG9: =('Income Statement'!AC16+'Income Statement'!AC12+'Income Statement'!AC13)/'Income Statement'!AC4 -> 0.13152503 | AH9: =('Income Statement'!AD16+'Income Statement'!AD12+'Income Statement'!AD13)/'Income Statement'!AD4 -> 0.14431645 | AL9: EBITDA Margin | AM9: ='Income Statement'!AH14/'Income Statement'!AH4 -> 0.1042042 | AN9: ='Income Statement'!AI14/'Income Statement'!AI4 -> 0.10792194 | AO9: ='Income Statement'!AJ14/'Income Statement'!AJ4 -> 0.11431502 | AP9: ='Income Statement'!AK14/'Income Statement'!AK4 -> 0.11362593 | AQ9: ='Income Statement'!AL14/'Income Statement'!AL4 -> 0.11371918 | AR9: ='Income Statement'!AM14/'Income Statement'!AM4 -> 0.11085083 | AU9: EBITDA Margin | AV9: =('Income Statement'!AP18+'Income Statement'!AP15+'Income Statement'!AP14)/'Income Statement'!AP4 -> 0.080934598 | AW9: =('Income Statement'!AQ18+'Income Statement'!AQ15+'Income Statement'!AQ14)/'Income Statement'!AQ4 -> 0.080563569 | AX9: =('Income Statement'!AR18+'Income Statement'!AR15+'Income Statement'!AR14)/'Income Statement'!AR4 -> 0.078763265 | AY9: =('Income Statement'!AS18+'Income Statement'!AS15+'Income Statement'!AS14)/'Income Statement'!AS4 -> 0.083018388 | AZ9: =('Income Statement'!AT18+'Income Statement'!AT15+'Income Statement'!AT14)/'Income Statement'!AT4 -> 0.09689362
B10: Gross Profit margin | C10: =('Income Statement'!B4-('Income Statement'!B8+'Income Statement'!B9+'Income Statement'!B10))/'Income Statement'!B4 -> 0.29733941 | D10: =('Income Statement'!C4-('Income Statement'!C8+'Income Statement'!C9+'Income Statement'!C10))/'Income Statement'!C4 -> 0.27777951 | E10: =('Income Statement'!D4-('Income Statement'!D8+'Income Statement'!D9+'Income Statement'!D10))/'Income Statement'!D4 -> 0.25230217 | F10: =('Income Statement'!E4-('Income Statement'!E8+'Income Statement'!E9+'Income Statement'!E10))/'Income Statement'!E4 -> 0.2663958 | G10: =('Income Statement'!F4-('Income Statement'!F8+'Income Statement'!F9+'Income Statement'!F10))/'Income Statement'!F4 -> 0.25442167 | H10: =('Income Statement'!G4-('Income Statement'!G8+'Income Statement'!G9+'Income Statement'!G10))/'Income Statement'!G4 -> 0.25251938 | K10: Gross Profit margin | L10: =('Income Statement'!J4-(IF('Income Statement'!J10>=0,'Income Statement'!J8+'Income Statement'!J9-'Income Statement'!J10,'Income Statement'!J8+'Income Statement'!J9+'Income Statement'!J10)))/'Income Statement'!J4 -> 0.51223483 | M10: =('Income Statement'!K4-(IF('Income Statement'!K10>=0,'Income Statement'!K8+'Income Statement'!K9-'Income Statement'!K10,'Income Statement'!K8+'Income Statement'!K9+'Income Statement'!K10)))/'Income Statement'!K4 -> 0.48658118 | N10: =('Income Statement'!L4-(IF('Income Statement'!L10>=0,'Income Statement'!L8+'Income Statement'!L9-'Income Statement'!L10,'Income Statement'!L8+'Income Statement'!L9+'Income Statement'!L10)))/'Income Statement'!L4 -> 0.42549781 | O10: =('Income Statement'!M4-(IF('Income Statement'!M10>=0,'Income Statement'!M8+'Income Statement'!M9-'Income Statement'!M10,'Income Statement'!M8+'Income Statement'!M9+'Income Statement'!M10)))/'Income Statement'!M4 -> 0.38988666 | P10: =('Income Statement'!N4-(IF('Income Statement'!N10>=0,'Income Statement'!N8+'Income Statement'!N9-'Income Statement'!N10,'Income Statement'!N8+'Income Statement'!N9+'Income Statement'!N10)))/'Income Statement'!N4 -> 0.39531983 | Q10: =('Income Statement'!O4-(IF('Income Statement'!O10>=0,'Income Statement'!O8+'Income Statement'!O9-'Income Statement'!O10,'Income Statement'!O8+'Income Statement'!O9+'Income Statement'!O10)))/'Income Statement'!O4 -> 0.3968953 | T10: Gross Profit margin | U10: =('Income Statement'!R4-(IF('Income Statement'!R14>=0,'Income Statement'!R11+'Income Statement'!R13-'Income Statement'!R14,'Income Statement'!R11+'Income Statement'!R13+'Income Statement'!R14)))/'Income Statement'!R4 -> 0.36980103 | V10: =('Income Statement'!S4-(IF('Income Statement'!S14>=0,'Income Statement'!S11+'Income Statement'!S13-'Income Statement'!S14,'Income Statement'!S11+'Income Statement'!S13+'Income Statement'!S14)))/'Income Statement'!S4 -> 0.39686176 | W10: =('Income Statement'!T4-(IF('Income Statement'!T14>=0,'Income Statement'!T11+'Income Statement'!T13-'Income Statement'!T14,'Income Statement'!T11+'Income Statement'!T13+'Income Statement'!T14)))/'Income Statement'!T4 -> 0.35915784 | X10: =('Income Statement'!U4-(IF('Income Statement'!U14>=0,'Income Statement'!U11+'Income Statement'!U13-'Income Statement'!U14,'Income Statement'!U11+'Income Statement'!U13+'Income Statement'!U14)))/'Income Statement'!U4 -> 0.34161531 | Y10: =('Income Statement'!V4-(IF('Income Statement'!V14>=0,'Income Statement'!V11+'Income Statement'!V13-'Income Statement'!V14,'Income Statement'!V11+'Income Statement'!V13+'Income Statement'!V14)))/'Income Statement'!V4 -> 0.3674689 | Z10: =('Income Statement'!W4-(IF('Income Statement'!W14>=0,'Income Statement'!W11+'Income Statement'!W13-'Income Statement'!W14,'Income Statement'!W11+'Income Statement'!W13+'Income Statement'!W14)))/'Income Statement'!W4 -> 0.39079394 | AC10: Gross Profit margin | AD10: =('Income Statement'!Z4-'Income Statement'!Z29)/'Income Statement'!Z4 -> 0.34728062 | AE10: =('Income Statement'!AA4-'Income Statement'!AA29)/'Income Statement'!AA4 -> 0.33445344 | AF10: =('Income Statement'!AB4-'Income Statement'!AB29)/'Income Statement'!AB4 -> 0.33249505 | AG10: =('Income Statement'!AC4-'Income Statement'!AC29)/'Income Statement'!AC4 -> 0.34802444 | AH10: =('Income Statement'!AD4-'Income Statement'!AD29)/'Income Statement'!AD4 -> 0.3765382 | AL10: Gross Profit margin | AM10: =('Income Statement'!AH4-'Income Statement'!AH28)/'Income Statement'!AH4 -> 0.55756371 | AN10: =('Income Statement'!AI4-'Income Statement'!AI28)/'Income Statement'!AI4 -> 0.56284317 | AO10: =('Income Statement'!AJ4-'Income Statement'!AJ28)/'Income Statement'!AJ4 -> 0.32155518 | AP10: =('Income Statement'!AK4-'Income Statement'!AK28)/'Income Statement'!AK4 -> 0.31335853 | AQ10: =('Income Statement'!AL4-'Income Statement'!AL28)/'Income Statement'!AL4 -> 0.32034744 | AR10: =('Income Statement'!AM4-'Income Statement'!AM28)/'Income Statement'!AM4 -> 0.32721192 | AU10: Gross Profit margin | AV10: =('Income Statement'!AP4-'Income Statement'!AP36)/'Income Statement'!AP4 -> 0.41987747 | AW10: =('Income Statement'!AQ4-'Income Statement'!AQ36)/'Income Statement'!AQ4 -> 0.42761798 | AX10: =('Income Statement'!AR4-'Income Statement'!AR36)/'Income Statement'!AR4 -> 0.41629765 | AY10: =('Income Statement'!AS4-'Income Statement'!AS36)/'Income Statement'!AS4 -> 0.41804299 | AZ10: =('Income Statement'!AT4-'Income Statement'!AT36)/'Income Statement'!AT4 -> 0.44445251
B11: Return on Equity | C11: ='Income Statement'!B24/'Balance Sheet'!B35 -> 0.11485631 | D11: ='Income Statement'!C24/'Balance Sheet'!C35 -> 0.083600949 | E11: ='Income Statement'!D24/'Balance Sheet'!D35 -> 0.070111235 | F11: ='Income Statement'!E24/'Balance Sheet'!E35 -> 0.13288278 | G11: ='Income Statement'!F24/'Balance Sheet'!F35 -> 0.15728728 | H11: ='Income Statement'!G24/'Balance Sheet'!G35 -> 0.14838586 | K11: Return on Equity | L11: ='Income Statement'!J29/'Balance Sheet'!J39 -> -0.0067350593 | M11: ='Income Statement'!K29/(AVERAGE('Balance Sheet'!J39:K39)) -> 0.030766749 | N11: ='Income Statement'!L29/(AVERAGE('Balance Sheet'!K39:L39)) -> 0.13496798 | O11: ='Income Statement'!M29/(AVERAGE('Balance Sheet'!L39:M39)) -> 0.1835965 | P11: ='Income Statement'!N29/(AVERAGE('Balance Sheet'!M39:N39)) -> 0.16971709 | Q11: ='Income Statement'!O29/(AVERAGE('Balance Sheet'!N39:O39)) -> 0.16893818 | T11: Return on Equity | U11: ='Income Statement'!R42/'Balance Sheet'!R42 -> -0.16559139 | V11: ='Income Statement'!S42/'Balance Sheet'!S42 -> -0.18434075 | W11: ='Income Statement'!T42/'Balance Sheet'!T42 -> -0.2315836 | X11: ='Income Statement'!U42/'Balance Sheet'!U42 -> 0.051138689 | Y11: ='Income Statement'!V42/'Balance Sheet'!V42 -> 0.34166541 | Z11: ='Income Statement'!W42/'Balance Sheet'!W42 -> 0.22931228 | AC11: Return on Equity | AD11: ='Income Statement'!Z27/'Balance Sheet'!Z40 -> 0.17335916 | AE11: ='Income Statement'!AA27/'Balance Sheet'!AA40 -> 0.14100334 | AF11: ='Income Statement'!AB27/'Balance Sheet'!AB40 -> 0.14977607 | AG11: ='Income Statement'!AC27/'Balance Sheet'!AC40 -> 0.22482297 | AH11: ='Income Statement'!AD27/'Balance Sheet'!AD40 -> 0.22451675 | AL11: Return on Equity | AM11: ='Income Statement'!AH26/'Balance Sheet'!AH41 -> 0.11704783 | AN11: ='Income Statement'!AI26/'Balance Sheet'!AI41 -> 0.10973575 | AO11: ='Income Statement'!AJ26/'Balance Sheet'!AJ41 -> 0.065353282 | AP11: ='Income Statement'!AK26/'Balance Sheet'!AK41 -> 0.073848653 | AQ11: ='Income Statement'!AL26/'Balance Sheet'!AL41 -> 0.068427702 | AR11: ='Income Statement'!AM26/'Balance Sheet'!AM41 -> 0.05744891 | AU11: Return on Equity | AV11: ='Income Statement'!AP34/'Balance Sheet'!AP43 -> 0.087313418 | AW11: ='Income Statement'!AQ34/'Balance Sheet'!AQ43 -> 0.094633952 | AX11: ='Income Statement'!AR34/'Balance Sheet'!AR43 -> 0.052829024 | AY11: ='Income Statement'!AS34/'Balance Sheet'!AS43 -> 0.068491071 | AZ11: ='Income Statement'!AT34/'Balance Sheet'!AT43 -> 0.10701919
B12: Return on capital employed | C12: =('Income Statement'!B19+'Income Statement'!B12)/('Balance Sheet'!B28-'Balance Sheet'!B56) -> 0.13831579 | D12: =('Income Statement'!C19+'Income Statement'!C12)/('Balance Sheet'!C28-'Balance Sheet'!C56) -> 0.098306449 | E12: =('Income Statement'!D19+'Income Statement'!D12)/('Balance Sheet'!D28-'Balance Sheet'!D56) -> 0.083700028 | F12: =('Income Statement'!E19+'Income Statement'!E12)/('Balance Sheet'!E28-'Balance Sheet'!E56) -> 0.16297356 | G12: =('Income Statement'!F19+'Income Statement'!F12)/('Balance Sheet'!F28-'Balance Sheet'!F56) -> 0.19727872 | H12: =('Income Statement'!G19+'Income Statement'!G12)/('Balance Sheet'!G28-'Balance Sheet'!G56) -> 0.19591909 | K12: Return on capital employed | L12: =('Income Statement'!J20+'Income Statement'!J12)/('Balance Sheet'!J32-'Balance Sheet'!J61) -> 0.094777443 | M12: =('Income Statement'!K20+'Income Statement'!K12)/('Balance Sheet'!K32-'Balance Sheet'!K61) -> 0.099550517 | N12: =('Income Statement'!L20+'Income Statement'!L12)/('Balance Sheet'!L32-'Balance Sheet'!L61) -> 0.12204443 | O12: =('Income Statement'!M20+'Income Statement'!M12)/('Balance Sheet'!M32-'Balance Sheet'!M61) -> 0.14699271 | P12: =('Income Statement'!N20+'Income Statement'!N12)/('Balance Sheet'!N32-'Balance Sheet'!N61) -> 0.14597361 | Q12: =('Income Statement'!O20+'Income Statement'!O12)/('Balance Sheet'!O32-'Balance Sheet'!O61) -> 0.1503918 | T12: Return on capital employed | U12: =('Income Statement'!R23+'Income Statement'!R16)/('Balance Sheet'!R35-'Balance Sheet'!R65) -> -0.0025607887 | V12: =('Income Statement'!S23+'Income Statement'!S16)/('Balance Sheet'!S35-'Balance Sheet'!S65) -> 0.061409632 | W12: =('Income Statement'!T23+'Income Statement'!T16)/('Balance Sheet'!T35-'Balance Sheet'!T65) -> 0.016328093 | X12: =('Income Statement'!U23+'Income Statement'!U16)/('Balance Sheet'!U35-'Balance Sheet'!U65) -> 0.064580163 | Y12: =('Income Statement'!V23+'Income Statement'!V16)/('Balance Sheet'!V35-'Balance Sheet'!V65) -> 0.18402623 | Z12: =('Income Statement'!W23+'Income Statement'!W16)/('Balance Sheet'!W35-'Balance Sheet'!W65) -> 0.18459317 | AC12: Return on capital employed | AD12: =('Income Statement'!Z16+'Income Statement'!Z12)/('Balance Sheet'!Z33-'Balance Sheet'!Z61) -> 0.18951785 | AE12: =('Income Statement'!AA16+'Income Statement'!AA12)/('Balance Sheet'!AA33-'Balance Sheet'!AA61) -> 0.15519967 | AF12: =('Income Statement'!AB16+'Income Statement'!AB12)/('Balance Sheet'!AB33-'Balance Sheet'!AB61) -> 0.15466064 | AG12: =('Income Statement'!AC16+'Income Statement'!AC12)/('Balance Sheet'!AC33-'Balance Sheet'!AC61) -> 0.20897191 | AH12: =('Income Statement'!AD16+'Income Statement'!AD12)/('Balance Sheet'!AD33-'Balance Sheet'!AD61) -> 0.22107912 | AL12: Return on capital employed | AM12: =('Income Statement'!AH14+'Income Statement'!AH16)/('Balance Sheet'!AH34-'Balance Sheet'!AH72) -> 0.091187552 | AN12: =('Income Statement'!AI14+'Income Statement'!AI16)/('Balance Sheet'!AI34-'Balance Sheet'!AI72) -> 0.087283051 | AO12: =('Income Statement'!AJ14+'Income Statement'!AJ16)/('Balance Sheet'!AJ34-'Balance Sheet'!AJ72) -> 0.17141976 | AP12: =('Income Statement'!AK14+'Income Statement'!AK16)/('Balance Sheet'!AK34-'Balance Sheet'!AK72) -> 0.18865156 | AQ12: =('Income Statement'!AL14+'Income Statement'!AL16)/('Balance Sheet'!AL34-'Balance Sheet'!AL72) -> 0.18007423 | AR12: =('Income Statement'!AM14+'Income Statement'!AM16)/('Balance Sheet'!AM34-'Balance Sheet'!AM72) -> 0.16068526 | AU12: Return on capital employed | AV12: =('Income Statement'!AP18+'Income Statement'!AP15)/('Balance Sheet'!AP34-'Balance Sheet'!AP67) -> 0.083224687 | AW12: =('Income Statement'!AQ18+'Income Statement'!AQ15)/('Balance Sheet'!AQ34-'Balance Sheet'!AQ67) -> 0.059811376 | AX12: =('Income Statement'!AR18+'Income Statement'!AR15)/('Balance Sheet'!AR34-'Balance Sheet'!AR67) -> 0.058817471 | AY12: =('Income Statement'!AS18+'Income Statement'!AS15)/('Balance Sheet'!AS34-'Balance Sheet'!AS67) -> 0.096949875 | AZ12: =('Income Statement'!AT18+'Income Statement'!AT15)/('Balance Sheet'!AT34-'Balance Sheet'!AT67) -> 0.13079746
B13: Return on Assets | C13: ='Income Statement'!B24/'Balance Sheet'!B28 -> 0.089231577 | D13: ='Income Statement'!C24/'Balance Sheet'!C28 -> 0.061573145 | E13: ='Income Statement'!D24/'Balance Sheet'!D28 -> 0.051965361 | F13: ='Income Statement'!E24/'Balance Sheet'!E28 -> 0.097060294 | G13: ='Income Statement'!F24/'Balance Sheet'!F28 -> 0.11977444 | H13: ='Income Statement'!G24/'Balance Sheet'!G28 -> 0.11109041 | K13: Return on Assets | L13: ='Income Statement'!J29/'Balance Sheet'!J32 -> -0.001922079 | M13: ='Income Statement'!K29/'Balance Sheet'!K32 -> 0.0090854702 | N13: ='Income Statement'!L29/'Balance Sheet'!L32 -> 0.04165696 | O13: ='Income Statement'!M29/'Balance Sheet'!M32 -> 0.055244947 | P13: ='Income Statement'!N29/'Balance Sheet'!N32 -> 0.051924596 | Q13: ='Income Statement'!O29/'Balance Sheet'!O32 -> 0.050698365 | T13: Return on Assets | U13: ='Income Statement'!R42/'Balance Sheet'!R35 -> -0.032844765 | V13: ='Income Statement'!S42/'Balance Sheet'!S35 -> -0.030526064 | W13: ='Income Statement'!T42/'Balance Sheet'!T35 -> -0.034204714 | X13: ='Income Statement'!U42/'Balance Sheet'!U35 -> 0.008003627 | Y13: ='Income Statement'!V42/'Balance Sheet'!V35 -> 0.085810869 | Z13: ='Income Statement'!W42/'Balance Sheet'!W35 -> 0.074341991 | AC13: Return on Assets | AD13: ='Income Statement'!Z27/'Balance Sheet'!Z33 -> 0.032265396 | AE13: ='Income Statement'!AA27/'Balance Sheet'!AA33 -> 0.027020796 | AF13: ='Income Statement'!AB27/'Balance Sheet'!AB33 -> 0.027955935 | AG13: ='Income Statement'!AC27/'Balance Sheet'!AC33 -> 0.037711049 | AH13: ='Income Statement'!AD27/'Balance Sheet'!AD33 -> 0.039942009 | AL13: Return on Assets | AM13: ='Income Statement'!AH26/'Balance Sheet'!AH34 -> 0.031290743 | AN13: ='Income Statement'!AI26/'Balance Sheet'!AI34 -> 0.027995152 | AO13: ='Income Statement'!AJ26/'Balance Sheet'!AJ34 -> 0.049912261 | AP13: ='Income Statement'!AK26/'Balance Sheet'!AK34 -> 0.055714235 | AQ13: ='Income Statement'!AL26/'Balance Sheet'!AL34 -> 0.048640167 | AR13: ='Income Statement'!AM26/'Balance Sheet'!AM34 -> 0.037413133 | AU13: Return on Assets | AV13: ='Income Statement'!AP34/'Balance Sheet'!AP34 -> 0.028453176 | AW13: ='Income Statement'!AQ34/'Balance Sheet'!AQ34 -> 0.032638037 | AX13: ='Income Statement'!AR34/'Balance Sheet'!AR34 -> 0.020996942 | AY13: ='Income Statement'!AS34/'Balance Sheet'!AS34 -> 0.026993599 | AZ13: ='Income Statement'!AT34/'Balance Sheet'!AT34 -> 0.035515639
A14: Efficiency | B14: Inventory Turnover | C14: =('Income Statement'!B8+'Income Statement'!B9+'Income Statement'!B10)/'Balance Sheet'!B17 -> 16.541678 | D14: =(IF('Income Statement'!C10>=0,'Income Statement'!C8+'Income Statement'!C9+-'Income Statement'!C10,'Income Statement'!C8+'Income Statement'!C9+'Income Statement'!C10))/(AVERAGE('Balance Sheet'!B17:C17)) -> 16.05547 | E14: =(IF('Income Statement'!D10>=0,'Income Statement'!D8+'Income Statement'!D9+-'Income Statement'!D10,'Income Statement'!D8+'Income Statement'!D9+'Income Statement'!D10))/(AVERAGE('Balance Sheet'!C17:D17)) -> 20.070199 | F14: =(IF('Income Statement'!E10>=0,'Income Statement'!E8+'Income Statement'!E9+-'Income Statement'!E10,'Income Statement'!E8+'Income Statement'!E9+'Income Statement'!E10))/(AVERAGE('Balance Sheet'!D17:E17)) -> 22.070882 | G14: =(IF('Income Statement'!F10>=0,'Income Statement'!F8+'Income Statement'!F9+-'Income Statement'!F10,'Income Statement'!F8+'Income Statement'!F9+'Income Statement'!F10))/(AVERAGE('Balance Sheet'!E17:F17)) -> 23.945139 | H14: =(IF('Income Statement'!G10>=0,'Income Statement'!G8+'Income Statement'!G9+-'Income Statement'!G10,'Income Statement'!G8+'Income Statement'!G9+'Income Statement'!G10))/(AVERAGE('Balance Sheet'!F17:G17)) -> 23.471923 | J14: Efficiency | K14: Inventory Turnover | L14: =(IF('Income Statement'!J10>=0,'Income Statement'!J8+'Income Statement'!J9-'Income Statement'!J10,'Income Statement'!J8+'Income Statement'!J9+'Income Statement'!J10))/'Balance Sheet'!J21 -> 3.3089582 | M14: =IF('Income Statement'!K10>=0,'Income Statement'!K8+'Income Statement'!K9-'Income Statement'!K10,'Income Statement'!K8+'Income Statement'!K9+'Income Statement'!K10)/AVERAGE('Balance Sheet'!J21:K21) -> 3.6797523 | N14: =IF('Income Statement'!L10>=0,'Income Statement'!L8+'Income Statement'!L9-'Income Statement'!L10,'Income Statement'!L8+'Income Statement'!L9+'Income Statement'!L10)/AVERAGE('Balance Sheet'!K21:L21) -> 4.884506 | O14: =IF('Income Statement'!M10>=0,'Income Statement'!M8+'Income Statement'!M9-'Income Statement'!M10,'Income Statement'!M8+'Income Statement'!M9+'Income Statement'!M10)/AVERAGE('Balance Sheet'!L21:M21) -> 5.20109 | P14: =IF('Income Statement'!N10>=0,'Income Statement'!N8+'Income Statement'!N9-'Income Statement'!N10,'Income Statement'!N8+'Income Statement'!N9+'Income Statement'!N10)/AVERAGE('Balance Sheet'!M21:N21) -> 4.7179412 | Q14: =IF('Income Statement'!O10>=0,'Income Statement'!O8+'Income Statement'!O9-'Income Statement'!O10,'Income Statement'!O8+'Income Statement'!O9+'Income Statement'!O10)/AVERAGE('Balance Sheet'!N21:O21) -> 4.9197984 | S14: Efficiency | T14: Inventory Turnover | U14: ='Income Statement'!R44/'Balance Sheet'!R22 -> 4.3507601 | V14: ='Income Statement'!S44/(AVERAGE('Balance Sheet'!R22:S22)) -> 4.0507827 | W14: ='Income Statement'!T44/(AVERAGE('Balance Sheet'!S22:T22)) -> 4.9456045 | X14: ='Income Statement'!U44/(AVERAGE('Balance Sheet'!T22:U22)) -> 5.9409491 | Y14: ='Income Statement'!V44/(AVERAGE('Balance Sheet'!U22:V22)) -> 6.1609342 | Z14: ='Income Statement'!W44/(AVERAGE('Balance Sheet'!V22:W22)) -> 5.5990406 | AB14: Efficiency | AC14: Inventory Turnover | AD14: ='Income Statement'!Z29/'Balance Sheet'!Z23 -> 10.352226 | AE14: ='Income Statement'!AA29/(AVERAGE('Balance Sheet'!Z23:AA23)) -> 10.114214 | AF14: ='Income Statement'!AB29/(AVERAGE('Balance Sheet'!AA23:AB23)) -> 10.80294 | AG14: ='Income Statement'!AC29/(AVERAGE('Balance Sheet'!AB23:AC23)) -> 11.698665 | AH14: ='Income Statement'!AD29/(AVERAGE('Balance Sheet'!AC23:AD23)) -> 11.705409 | AK14: Efficiency | AL14: Inventory Turnover | AM14: ='Income Statement'!AH28/'Balance Sheet'!AH22 -> 2.6516218 | AN14: ='Income Statement'!AI28/AVERAGE('Balance Sheet'!AH22:AI22) -> 2.6476278 | AO14: ='Income Statement'!AJ28/AVERAGE('Balance Sheet'!AI22:AJ22) -> 3.1597025 | AP14: ='Income Statement'!AK28/AVERAGE('Balance Sheet'!AJ22:AK22) -> 3.2910998 | AQ14: ='Income Statement'!AL28/AVERAGE('Balance Sheet'!AK22:AL22) -> 3.12052 | AR14: ='Income Statement'!AM28/AVERAGE('Balance Sheet'!AL22:AM22) -> 2.7503448 | AT14: Efficiency | AU14: Inventory Turnover | AV14: ='Income Statement'!AP36/'Balance Sheet'!AP23 -> 6.7813676 | AW14: ='Income Statement'!AQ36/AVERAGE('Balance Sheet'!AP23:AQ23) -> 6.4218396 | AX14: ='Income Statement'!AR36/AVERAGE('Balance Sheet'!AQ23:AR23) -> 6.4239462 | AY14: ='Income Statement'!AS36/AVERAGE('Balance Sheet'!AR23:AS23) -> 6.3538715 | AZ14: ='Income Statement'!AT36/AVERAGE('Balance Sheet'!AS23:AT23) -> 6.4052614
B15: Receivables Turnover | C15: ='Income Statement'!B4/'Balance Sheet'!B20 -> 38.256561 | D15: ='Income Statement'!C4/AVERAGE('Balance Sheet'!B20:C20) -> 43.204813 | E15: ='Income Statement'!D4/AVERAGE('Balance Sheet'!C20:D20) -> 53.300628 | F15: ='Income Statement'!E4/AVERAGE('Balance Sheet'!D20:E20) -> 44.06803 | G15: ='Income Statement'!F4/AVERAGE('Balance Sheet'!E20:F20) -> 34.149797 | H15: ='Income Statement'!G4/AVERAGE('Balance Sheet'!F20:G20) -> 26.055337 | K15: Receivables Turnover | L15: ='Income Statement'!J4/('Balance Sheet'!J24+'Balance Sheet'!J15) -> 10.071779 | M15: ='Income Statement'!K4/(AVERAGE('Balance Sheet'!J24:K24)+AVERAGE('Balance Sheet'!J15:K15)) -> 10.71954 | N15: ='Income Statement'!L4/(AVERAGE('Balance Sheet'!K24:L24)+AVERAGE('Balance Sheet'!K15:L15)) -> 13.811518 | O15: ='Income Statement'!M4/(AVERAGE('Balance Sheet'!L24:M24)+AVERAGE('Balance Sheet'!L15:M15)) -> 17.331506 | P15: ='Income Statement'!N4/(AVERAGE('Balance Sheet'!M24:N24)+AVERAGE('Balance Sheet'!M15:N15)) -> 18.387373 | Q15: ='Income Statement'!O4/(AVERAGE('Balance Sheet'!N24:O24)+AVERAGE('Balance Sheet'!N15:O15)) -> 19.518852 | T15: Receivables Turnover | U15: ='Income Statement'!R4/'Balance Sheet'!R25 -> 23.145219 | V15: ='Income Statement'!S4/(AVERAGE('Balance Sheet'!R25:S25)) -> 20.708918 | W15: ='Income Statement'!T4/(AVERAGE('Balance Sheet'!S25:T25)) -> 21.912586 | X15: ='Income Statement'!U4/(AVERAGE('Balance Sheet'!T25:U25)) -> 24.334528 | Y15: ='Income Statement'!V4/(AVERAGE('Balance Sheet'!U25:V25)) -> 26.381915 | Z15: ='Income Statement'!W4/(AVERAGE('Balance Sheet'!V25:W25)) -> 28.928543 | AC15: Receivables Turnover | AD15: ='Income Statement'!Z4/'Balance Sheet'!Z25 -> 12.960553 | AE15: ='Income Statement'!AA4/AVERAGE('Balance Sheet'!Z25:AA25) -> 15.596985 | AF15: ='Income Statement'!AB4/AVERAGE('Balance Sheet'!AA25:AB25) -> 22.23001 | AG15: ='Income Statement'!AC4/AVERAGE('Balance Sheet'!AB25:AC25) -> 26.516167 | AH15: ='Income Statement'!AD4/AVERAGE('Balance Sheet'!AC25:AD25) -> 25.288607 | AL15: Receivables Turnover | AM15: ='Income Statement'!AH4/('Balance Sheet'!AH15+'Balance Sheet'!AH27) -> 13.639801 | AN15: ='Income Statement'!AI4/(AVERAGE('Balance Sheet'!AH15:AI15)+AVERAGE('Balance Sheet'!AH27:AI27)) -> 14.314755 | AO15: ='Income Statement'!AJ4/(AVERAGE('Balance Sheet'!AI15:AJ15)+AVERAGE('Balance Sheet'!AI27:AJ27)) -> 11.764638 | AP15: ='Income Statement'!AK4/(AVERAGE('Balance Sheet'!AJ15:AK15)+AVERAGE('Balance Sheet'!AJ27:AK27)) -> 12.955026 | AQ15: ='Income Statement'!AL4/(AVERAGE('Balance Sheet'!AK15:AL15)+AVERAGE('Balance Sheet'!AK27:AL27)) -> 12.836892 | AR15: ='Income Statement'!AM4/(AVERAGE('Balance Sheet'!AL15:AM15)+AVERAGE('Balance Sheet'!AL27:AM27)) -> 11.230418 | AU15: Receivables Turnover | AV15: ='Income Statement'!AP4/('Balance Sheet'!AP16+'Balance Sheet'!AQ16+'Balance Sheet'!AP26+'Balance Sheet'!AQ26) -> 4.3788129 | AW15: ='Income Statement'!AQ4/(AVERAGE('Balance Sheet'!AP16:AQ16)+AVERAGE('Balance Sheet'!AP26:AQ26)) -> 8.2742574 | AX15: ='Income Statement'!AR4/(AVERAGE('Balance Sheet'!AQ16:AR16)+AVERAGE('Balance Sheet'!AQ26:AR26)) -> 8.2743946 | AY15: ='Income Statement'!AS4/(AVERAGE('Balance Sheet'!AR16:AS16)+AVERAGE('Balance Sheet'!AR26:AS26)) -> 8.7188539 | AZ15: ='Income Statement'!AT4/(AVERAGE('Balance Sheet'!AS16:AT16)+AVERAGE('Balance Sheet'!AS26:AT26)) -> 7.234291
B16: Asset Turnover | C16: ='Income Statement'!B4/'Balance Sheet'!B28 -> 1.1891047 | D16: ='Income Statement'!C4/'Balance Sheet'!C28 -> 0.98722411 | E16: ='Income Statement'!D4/'Balance Sheet'!D28 -> 1.1831653 | F16: ='Income Statement'!E4/'Balance Sheet'!E28 -> 1.3897826 | G16: ='Income Statement'!F4/'Balance Sheet'!F28 -> 1.2235394 | H16: ='Income Statement'!G4/'Balance Sheet'!G28 -> 1.15519 | K16: Asset Turnover | L16: ='Income Statement'!J4/'Balance Sheet'!J32 -> 0.4513708 | M16: ='Income Statement'!K4/'Balance Sheet'!K32 -> 0.44621332 | N16: ='Income Statement'!L4/'Balance Sheet'!L32 -> 0.51788593 | O16: ='Income Statement'!M4/'Balance Sheet'!M32 -> 0.58899173 | P16: ='Income Statement'!N4/'Balance Sheet'!N32 -> 0.58518355 | Q16: ='Income Statement'!O4/'Balance Sheet'!O32 -> 0.57189338 | T16: Asset Turnover | U16: ='Income Statement'!R4/'Balance Sheet'!R35 -> 0.80278705 | V16: ='Income Statement'!S4/'Balance Sheet'!S35 -> 0.71977149 | W16: ='Income Statement'!T4/'Balance Sheet'!T35 -> 0.83248227 | X16: ='Income Statement'!U4/'Balance Sheet'!U35 -> 1.020213 | Y16: ='Income Statement'!V4/'Balance Sheet'!V35 -> 1.1633501 | Z16: ='Income Statement'!W4/'Balance Sheet'!W35 -> 1.1536517 | AC16: Asset Turnover | AD16: ='Income Statement'!Z4/'Balance Sheet'!Z33 -> 0.97368073 | AE16: ='Income Statement'!AA4/'Balance Sheet'!AA33 -> 0.88305796 | AF16: ='Income Statement'!AB4/'Balance Sheet'!AB33 -> 0.89965311 | AG16: ='Income Statement'!AC4/'Balance Sheet'!AC33 -> 0.90750352 | AH16: ='Income Statement'!AD4/'Balance Sheet'!AD33 -> 0.92715096 | AL16: Asset Turnover | AM16: ='Income Statement'!AH4/'Balance Sheet'!AH34 -> 0.593863 | AN16: ='Income Statement'!AI4/'Balance Sheet'!AI34 -> 0.53323217 | AO16: ='Income Statement'!AJ4/'Balance Sheet'!AJ34 -> 0.91938599 | AP16: ='Income Statement'!AK4/'Balance Sheet'!AK34 -> 1.0210243 | AQ16: ='Income Statement'!AL4/'Balance Sheet'!AL34 -> 0.92395105 | AR16: ='Income Statement'!AM4/'Balance Sheet'!AM34 -> 0.80564894 | AU16: Asset Turnover | AV16: ='Income Statement'!AP4/'Balance Sheet'!AP34 -> 1.3249201 | AW16: ='Income Statement'!AQ4/'Balance Sheet'!AQ34 -> 1.1843881 | AX16: ='Income Statement'!AR4/'Balance Sheet'!AR34 -> 1.118475 | AY16: ='Income Statement'!AS4/'Balance Sheet'!AS34 -> 1.2589905 | AZ16: ='Income Statement'!AT4/'Balance Sheet'!AT34 -> 1.1500523
B17: Working capital turnover | C17: ='Income Statement'!B4/('Balance Sheet'!B27-'Balance Sheet'!B56) -> -26.410221 | D17: ='Income Statement'!C4/('Balance Sheet'!C27-'Balance Sheet'!C56) -> 29.033749 | E17: ='Income Statement'!D4/('Balance Sheet'!D27-'Balance Sheet'!D56) -> -383.87571 | F17: ='Income Statement'!E4/('Balance Sheet'!E27-'Balance Sheet'!E56) -> -13.845437 | G17: ='Income Statement'!F4/('Balance Sheet'!F27-'Balance Sheet'!F56) -> -26.118847 | H17: ='Income Statement'!G4/('Balance Sheet'!G27-'Balance Sheet'!G56) -> -41.838028 | K17: Working capital turnover | L17: ='Income Statement'!J4/('Balance Sheet'!J31-'Balance Sheet'!J61) -> 7.5112202 | M17: ='Income Statement'!K4/('Balance Sheet'!K31-'Balance Sheet'!K61) -> 3.5897032 | N17: ='Income Statement'!L4/('Balance Sheet'!L31-'Balance Sheet'!L61) -> 4.7811319 | O17: ='Income Statement'!M4/('Balance Sheet'!M31-'Balance Sheet'!M61) -> 5.8453858 | P17: ='Income Statement'!N4/('Balance Sheet'!N31-'Balance Sheet'!N61) -> 6.0862395 | Q17: ='Income Statement'!O4/('Balance Sheet'!O31-'Balance Sheet'!O61) -> 4.3791512 | T17: Working capital turnover | U17: ='Income Statement'!R4/('Balance Sheet'!R34-'Balance Sheet'!R65) -> -12.392313 | V17: ='Income Statement'!S4/('Balance Sheet'!S34-'Balance Sheet'!S65) -> -22.738228 | W17: ='Income Statement'!T4/('Balance Sheet'!T34-'Balance Sheet'!T65) -> -74.282098 | X17: ='Income Statement'!U4/('Balance Sheet'!U34-'Balance Sheet'!U65) -> -97.996087 | Y17: ='Income Statement'!V4/('Balance Sheet'!V34-'Balance Sheet'!V65) -> -82.54441 | Z17: ='Income Statement'!W4/('Balance Sheet'!W34-'Balance Sheet'!W65) -> -68.693348 | AC17: Working capital turnover | AD17: ='Income Statement'!Z4/('Balance Sheet'!Z32-'Balance Sheet'!Z61) -> -65.851418 | AE17: ='Income Statement'!AA4/('Balance Sheet'!AA32-'Balance Sheet'!AA61) -> -52.224756 | AF17: ='Income Statement'!AB4/('Balance Sheet'!AB32-'Balance Sheet'!AB61) -> -24.266736 | AG17: ='Income Statement'!AC4/('Balance Sheet'!AC32-'Balance Sheet'!AC61) -> -14.570588 | AH17: ='Income Statement'!AD4/('Balance Sheet'!AD32-'Balance Sheet'!AD61) -> 88.602852 | AL17: Working capital turnover | AM17: ='Income Statement'!AH4/('Balance Sheet'!AH33-'Balance Sheet'!AH72) -> 6.704508 | AN17: ='Income Statement'!AI4/('Balance Sheet'!AI33-'Balance Sheet'!AI72) -> 10.541437 | AO17: ='Income Statement'!AJ4/('Balance Sheet'!AJ33-'Balance Sheet'!AJ72) -> 5.5522985 | AP17: ='Income Statement'!AK4/('Balance Sheet'!AK33-'Balance Sheet'!AK72) -> 5.6544514 | AQ17: ='Income Statement'!AL4/('Balance Sheet'!AL33-'Balance Sheet'!AL72) -> 9.2960653 | AR17: ='Income Statement'!AM4/('Balance Sheet'!AM33-'Balance Sheet'!AM72) -> 13.022672 | AU17: Working capital turnover | AV17: ='Income Statement'!AP4/('Balance Sheet'!AP32-'Balance Sheet'!AP67) -> -571.90038 | AW17: ='Income Statement'!AQ4/('Balance Sheet'!AQ32-'Balance Sheet'!AQ67) -> -1243.4782 | AX17: ='Income Statement'!AR4/('Balance Sheet'!AR32-'Balance Sheet'!AR67) -> 190.19855 | AY17: ='Income Statement'!AS4/('Balance Sheet'!AS32-'Balance Sheet'!AS67) -> -105.77384 | AZ17: ='Income Statement'!AT4/('Balance Sheet'!AT32-'Balance Sheet'!AT67) -> -67.517884
A18: Valuation | B18: EPS | C18: ='Income Statement'!B24/'Company Profile'!$B$16 -> 180.58375 | D18: ='Income Statement'!C24/'Company Profile'!$B$16 -> 139.60126 | E18: ='Income Statement'!D24/'Company Profile'!$B$16 -> 123.39275 | F18: ='Income Statement'!E24/'Company Profile'!$B$16 -> 261.16196 | G18: ='Income Statement'!F24/'Company Profile'!$B$16 -> 420.13966 | H18: ='Income Statement'!G24/'Company Profile'!$B$16 -> 443.86401 | J18: Valuation | K18: EPS | L18: ='Income Statement'!J29/'Company Profile'!$C$16 -> -2.6748975 | M18: ='Income Statement'!K29/'Company Profile'!$C$16 -> 12.602767 | N18: ='Income Statement'!L29/'Company Profile'!$C$16 -> 60.439433 | O18: ='Income Statement'!M29/'Company Profile'!$C$16 -> 94.7837 | P18: ='Income Statement'!N29/'Company Profile'!$C$16 -> 102.24458 | Q18: ='Income Statement'!O29/'Company Profile'!$C$16 -> 117.27192 | S18: Valuation | T18: EPS | U18: ='Income Statement'!R42/'Company Profile'!$D$16 -> -28.731746 | V18: ='Income Statement'!S42/'Company Profile'!$D$16 -> -28.4447 | W18: ='Income Statement'!T42/'Company Profile'!$D$16 -> -30.710873 | X18: ='Income Statement'!U42/'Company Profile'!$D$16 -> 7.3048023 | Y18: ='Income Statement'!V42/'Company Profile'!$D$16 -> 86.377352 | Z18: ='Income Statement'!W42/'Company Profile'!$D$16 -> 76.443427 | AB18: Valuation | AC18: EPS | AD18: ='Income Statement'!Z27/'Company Profile'!$E$16 -> 13.152135 | AE18: ='Income Statement'!AA27/'Company Profile'!$E$16 -> 12.512868 | AF18: ='Income Statement'!AB27/'Company Profile'!$E$16 -> 15.935767 | AG18: ='Income Statement'!AC27/'Company Profile'!$E$16 -> 27.976765 | AH18: ='Income Statement'!AD27/'Company Profile'!$E$16 -> 35.508574 | AK18: Valuation | AL18: EPS | AM18: ='Income Statement'!AH26/'Company Profile'!$F$16 -> 8.9703529 | AN18: ='Income Statement'!AI26/'Company Profile'!$F$16 -> 9.4482353 | AO18: ='Income Statement'!AJ26/'Company Profile'!$F$16 -> 8.1683529 | AP18: ='Income Statement'!AK26/'Company Profile'!$F$16 -> 9.6796471 | AQ18: ='Income Statement'!AL26/'Company Profile'!$F$16 -> 10.386118 | AR18: ='Income Statement'!AM26/'Company Profile'!$F$16 -> 9.4176471 | AT18: Valuation | AU18: EPS | AV18: ='Income Statement'!AP34/'Company Profile'!$G$16 -> 1.226498 | AW18: ='Income Statement'!AQ34/'Company Profile'!$G$16 -> 1.4869571 | AX18: ='Income Statement'!AR34/'Company Profile'!$G$16 -> 1.1194341 | AY18: ='Income Statement'!AS34/'Company Profile'!$G$16 -> 1.5818935 | AZ18: ='Income Statement'!AT34/'Company Profile'!$G$16 -> 2.860976
B19: Price to earnings (P/E) | C19: ='Company Profile'!$B$11/'Financial Ratios'!C18 -> 86.292372 | D19: ='Company Profile'!$B$11/'Financial Ratios'!D18 -> 111.62506 | E19: ='Company Profile'!$B$11/'Financial Ratios'!E18 -> 126.28781 | F19: ='Company Profile'!$B$11/'Financial Ratios'!F18 -> 59.667954 | G19: ='Company Profile'!$B$11/'Financial Ratios'!G18 -> 37.090048 | H19: ='Company Profile'!$B$11/'Financial Ratios'!H18 -> 35.107599 | K19: Price to earnings (P/E) | L19: ='Company Profile'!$C$11/'Financial Ratios'!L18 -> -1369.7347 | M19: ='Company Profile'!$C$11/'Financial Ratios'!M18 -> 290.72187 | N19: ='Company Profile'!$C$11/'Financial Ratios'!N18 -> 60.621019 | O19: ='Company Profile'!$C$11/'Financial Ratios'!O18 -> 38.655381 | P19: ='Company Profile'!$C$11/'Financial Ratios'!P18 -> 35.834662 | Q19: ='Company Profile'!$C$11/'Financial Ratios'!Q18 -> 31.242773 | T19: Price to earnings (P/E) | U19: ='Company Profile'!$D$11/'Financial Ratios'!U18 -> -14.287332 | V19: ='Company Profile'!$D$11/'Financial Ratios'!V18 -> -14.431511 | W19: ='Company Profile'!$D$11/'Financial Ratios'!W18 -> -13.366601 | X19: ='Company Profile'!$D$11/'Financial Ratios'!X18 -> 56.195908 | Y19: ='Company Profile'!$D$11/'Financial Ratios'!Y18 -> 4.7524032 | Z19: ='Company Profile'!$D$11/'Financial Ratios'!Z18 -> 5.3699843 | AC19: Price to earnings (P/E) | AD19: ='Company Profile'!$E$11/'Financial Ratios'!AD18 -> 265.41699 | AE19: ='Company Profile'!$E$11/'Financial Ratios'!AE18 -> 278.97681 | AF19: ='Company Profile'!$E$11/'Financial Ratios'!AF18 -> 219.05441 | AG19: ='Company Profile'!$E$11/'Financial Ratios'!AG18 -> 124.77497 | AH19: ='Company Profile'!$E$11/'Financial Ratios'!AH18 -> 98.308651 | AL19: Price to earnings (P/E) | AM19: ='Company Profile'!$F$11/'Financial Ratios'!AM18 -> 42.311602 | AN19: ='Company Profile'!$F$11/'Financial Ratios'!AN18 -> 40.171523 | AO19: ='Company Profile'!$F$11/'Financial Ratios'!AO18 -> 46.465916 | AP19: ='Company Profile'!$F$11/'Financial Ratios'!AP18 -> 39.21114 | AQ19: ='Company Profile'!$F$11/'Financial Ratios'!AQ18 -> 36.543973 | AR19: ='Company Profile'!$F$11/'Financial Ratios'!AR18 -> 40.301999 | AU19: Price to earnings (P/E) | AV19: ='Company Profile'!$G$11/'Financial Ratios'!AV18 -> 83.612037 | AW19: ='Company Profile'!$G$11/'Financial Ratios'!AW18 -> 68.966345 | AX19: ='Company Profile'!$G$11/'Financial Ratios'!AX18 -> 91.608787 | AY19: ='Company Profile'!$G$11/'Financial Ratios'!AY18 -> 64.827373 | AZ19: ='Company Profile'!$G$11/'Financial Ratios'!AZ18 -> 35.844411
B20: Price to book value | C20: ='Company Profile'!$B$11/('Balance Sheet'!B35/'Company Profile'!$B$16) -> 9.9112233 | D20: ='Company Profile'!$B$11/('Balance Sheet'!C35/'Company Profile'!$B$16) -> 9.3319614 | E20: ='Company Profile'!$B$11/('Balance Sheet'!D35/'Company Profile'!$B$16) -> 8.8541945 | F20: ='Company Profile'!$B$11/('Balance Sheet'!E35/'Company Profile'!$B$16) -> 7.9288439 | G20: ='Company Profile'!$B$11/('Balance Sheet'!F35/'Company Profile'!$B$16) -> 5.8337926 | H20: ='Company Profile'!$B$11/('Balance Sheet'!G35/'Company Profile'!$B$16) -> 5.2094712 | K20: Price to book value | L20: ='Company Profile'!$C$11/('Balance Sheet'!J39/'Company Profile'!$C$16) -> 9.2252448 | M20: ='Company Profile'!$C$11/('Balance Sheet'!K39/'Company Profile'!$C$16) -> 8.6804639 | N20: ='Company Profile'!$C$11/('Balance Sheet'!L39/'Company Profile'!$C$16) -> 7.7374895 | O20: ='Company Profile'!$C$11/('Balance Sheet'!M39/'Company Profile'!$C$16) -> 6.5544279 | P20: ='Company Profile'!$C$11/('Balance Sheet'!N39/'Company Profile'!$C$16) -> 5.6726693 | Q20: ='Company Profile'!$C$11/('Balance Sheet'!O39/'Company Profile'!$C$16) -> 4.9348454 | T20: Price to book value | U20: ='Company Profile'!$D$11/('Balance Sheet'!R42/'Company Profile'!$D$16) -> 2.3658592 | V20: ='Company Profile'!$D$11/('Balance Sheet'!S42/'Company Profile'!$D$16) -> 2.6603155 | W20: ='Company Profile'!$D$11/('Balance Sheet'!T42/'Company Profile'!$D$16) -> 3.0954857 | X20: ='Company Profile'!$D$11/('Balance Sheet'!U42/'Company Profile'!$D$16) -> 2.8737851 | Y20: ='Company Profile'!$D$11/('Balance Sheet'!V42/'Company Profile'!$D$16) -> 1.6237318 | Z20: ='Company Profile'!$D$11/('Balance Sheet'!W42/'Company Profile'!$D$16) -> 1.2314034 | AC20: Price to book value | AD20: ='Company Profile'!$E$11/('Balance Sheet'!Z40/'Company Profile'!$E$16) -> 46.012467 | AE20: ='Company Profile'!$E$11/('Balance Sheet'!AA40/'Company Profile'!$E$16) -> 39.336663 | AF20: ='Company Profile'!$E$11/('Balance Sheet'!AB40/'Company Profile'!$E$16) -> 32.80911 | AG20: ='Company Profile'!$E$11/('Balance Sheet'!AC40/'Company Profile'!$E$16) -> 28.052279 | AH20: ='Company Profile'!$E$11/('Balance Sheet'!AD40/'Company Profile'!$E$16) -> 22.071939 | AL20: Price to book value | AM20: ='Company Profile'!$F$11/('Balance Sheet'!AH41/'Company Profile'!$F$16) -> 4.9524812 | AN20: ='Company Profile'!$F$11/('Balance Sheet'!AI41/'Company Profile'!$F$16) -> 4.4082522 | AO20: ='Company Profile'!$F$11/('Balance Sheet'!AJ41/'Company Profile'!$F$16) -> 3.0367001 | AP20: ='Company Profile'!$F$11/('Balance Sheet'!AK41/'Company Profile'!$F$16) -> 2.8956899 | AQ20: ='Company Profile'!$F$11/('Balance Sheet'!AL41/'Company Profile'!$F$16) -> 2.5006201 | AR20: ='Company Profile'!$F$11/('Balance Sheet'!AM41/'Company Profile'!$F$16) -> 2.3153059 | AU20: Price to book value | AV20: ='Company Profile'!$G$11/('Balance Sheet'!AP43/'Company Profile'!$G$16) -> 7.3004527 | AW20: ='Company Profile'!$G$11/('Balance Sheet'!AQ43/'Company Profile'!$G$16) -> 6.5265578 | AX20: ='Company Profile'!$G$11/('Balance Sheet'!AR43/'Company Profile'!$G$16) -> 4.8396029 | AY20: ='Company Profile'!$G$11/('Balance Sheet'!AS43/'Company Profile'!$G$16) -> 4.4400962 | AZ20: ='Company Profile'!$G$11/('Balance Sheet'!AT43/'Company Profile'!$G$16) -> 3.8360398
B21: EV/EBITDA | C21: =('Company Profile'!$B$18+'Balance Sheet'!B39+'Balance Sheet'!B47-'Balance Sheet'!B21)/('Income Statement'!B19+'Income Statement'!B12+'Income Statement'!B13) -> 45.214734 | D21: =('Company Profile'!$B$18+'Balance Sheet'!C39+'Balance Sheet'!C47-'Balance Sheet'!C21)/('Income Statement'!C19+'Income Statement'!C12+'Income Statement'!C13) -> 57.599664 | E21: =('Company Profile'!$B$18+'Balance Sheet'!D39+'Balance Sheet'!D47-'Balance Sheet'!D21)/('Income Statement'!D19+'Income Statement'!D12+'Income Statement'!D13) -> 63.972599 | F21: =('Company Profile'!$B$18+'Balance Sheet'!E39+'Balance Sheet'!E47-'Balance Sheet'!E21)/('Income Statement'!E19+'Income Statement'!E12+'Income Statement'!E13) -> 36.581405 | G21: =('Company Profile'!$B$18+'Balance Sheet'!F39+'Balance Sheet'!F47-'Balance Sheet'!F21)/('Income Statement'!F19+'Income Statement'!F12+'Income Statement'!F13) -> 24.005036 | H21: =('Company Profile'!$B$18+'Balance Sheet'!G39+'Balance Sheet'!G47-'Balance Sheet'!G21)/('Income Statement'!G19+'Income Statement'!G12+'Income Statement'!G13) -> 21.591872 | K21: EV/EBITDA | L21: =('Company Profile'!$C$18+('Balance Sheet'!J43+'Balance Sheet'!J52-'Balance Sheet'!J25))/('Income Statement'!J20+'Income Statement'!J12+'Income Statement'!J13) -> 35.564251 | M21: =('Company Profile'!$C$18+('Balance Sheet'!K43+'Balance Sheet'!K52-'Balance Sheet'!K25))/('Income Statement'!K20+'Income Statement'!K12+'Income Statement'!K13) -> 33.653739 | N21: =('Company Profile'!$C$18+('Balance Sheet'!L43+'Balance Sheet'!L52-'Balance Sheet'!L25))/('Income Statement'!L20+'Income Statement'!L12+'Income Statement'!L13) -> 28.736596 | O21: =('Company Profile'!$C$18+('Balance Sheet'!M43+'Balance Sheet'!M52-'Balance Sheet'!M25))/('Income Statement'!M20+'Income Statement'!M12+'Income Statement'!M13) -> 21.780854 | P21: =('Company Profile'!$C$18+('Balance Sheet'!N43+'Balance Sheet'!N52-'Balance Sheet'!N25))/('Income Statement'!N20+'Income Statement'!N12+'Income Statement'!N13) -> 19.209594 | Q21: =('Company Profile'!$C$18+('Balance Sheet'!O43+'Balance Sheet'!O52-'Balance Sheet'!O25))/('Income Statement'!O20+'Income Statement'!O12+'Income Statement'!O13) -> 16.330161 | T21: EV/EBITDA | U21: =('Company Profile'!$D$18+('Balance Sheet'!R46+'Balance Sheet'!R55)-'Balance Sheet'!R26)/('Income Statement'!R23+'Income Statement'!R16+'Income Statement'!R18) -> 11.001915 | V21: =('Company Profile'!$D$18+('Balance Sheet'!S46+'Balance Sheet'!S55)-'Balance Sheet'!S26)/('Income Statement'!S23+'Income Statement'!S16+'Income Statement'!S18) -> 6.6551281 | W21: =('Company Profile'!$D$18+('Balance Sheet'!T46+'Balance Sheet'!T55)-'Balance Sheet'!T26)/('Income Statement'!T23+'Income Statement'!T16+'Income Statement'!T18) -> 9.034088 | X21: =('Company Profile'!$D$18+('Balance Sheet'!U46+'Balance Sheet'!U55)-'Balance Sheet'!U26)/('Income Statement'!U23+'Income Statement'!U16+'Income Statement'!U18) -> 6.6524403 | Y21: =('Company Profile'!$D$18+('Balance Sheet'!V46+'Balance Sheet'!V55)-'Balance Sheet'!V26)/('Income Statement'!V23+'Income Statement'!V16+'Income Statement'!V18) -> 3.2736209 | Z21: =('Company Profile'!$D$18+('Balance Sheet'!W46+'Balance Sheet'!W55)-'Balance Sheet'!W26)/('Income Statement'!W23+'Income Statement'!W16+'Income Statement'!W18) -> 2.8460485 | AC21: EV/EBITDA | AD21: =('Company Profile'!$E$18+('Balance Sheet'!Z44+'Balance Sheet'!Z52)-'Balance Sheet'!Z27)/('Income Statement'!Z16+'Income Statement'!Z12+'Income Statement'!Z13) -> 74.021988 | AE21: =('Company Profile'!$E$18+('Balance Sheet'!AA44+'Balance Sheet'!AA52)-'Balance Sheet'!AA27)/('Income Statement'!AA16+'Income Statement'!AA12+'Income Statement'!AA13) -> 75.248135 | AF21: =('Company Profile'!$E$18+('Balance Sheet'!AB44+'Balance Sheet'!AB52)-'Balance Sheet'!AB27)/('Income Statement'!AB16+'Income Statement'!AB12+'Income Statement'!AB13) -> 63.864251 | AG21: =('Company Profile'!$E$18+('Balance Sheet'!AC44+'Balance Sheet'!AC52)-'Balance Sheet'!AC27)/('Income Statement'!AC16+'Income Statement'!AC12+'Income Statement'!AC13) -> 43.740409 | AH21: =('Company Profile'!$E$18+('Balance Sheet'!AD44+'Balance Sheet'!AD52)-'Balance Sheet'!AD27)/('Income Statement'!AD16+'Income Statement'!AD12+'Income Statement'!AD13) -> 33.119703 | AL21: EV/EBITDA | AM21: =('Company Profile'!$F$18+('Balance Sheet'!AH45+'Balance Sheet'!AH61)-'Balance Sheet'!AH28)/'Income Statement'!AH14 -> 21.095441 | AN21: =('Company Profile'!$F$18+('Balance Sheet'!AI45+'Balance Sheet'!AI61)-'Balance Sheet'!AI28)/'Income Statement'!AI14 -> 19.301683 | AO21: =('Company Profile'!$F$18+('Balance Sheet'!AJ45+'Balance Sheet'!AJ61)-'Balance Sheet'!AJ28)/'Income Statement'!AJ14 -> 21.952715 | AP21: =('Company Profile'!$F$18+('Balance Sheet'!AK45+'Balance Sheet'!AK61)-'Balance Sheet'!AK28)/'Income Statement'!AK14 -> 18.807514 | AQ21: =('Company Profile'!$F$18+('Balance Sheet'!AL45+'Balance Sheet'!AL61)-'Balance Sheet'!AL28)/'Income Statement'!AL14 -> 17.015228 | AR21: =('Company Profile'!$F$18+('Balance Sheet'!AM45+'Balance Sheet'!AM61)-'Balance Sheet'!AM28)/'Income Statement'!AM14 -> 17.508151 | AU21: EV/EBITDA | AV21: =('Company Profile'!$G$18+('Balance Sheet'!AP47+'Balance Sheet'!AP58)-'Balance Sheet'!AP27)/('Income Statement'!AP18+'Income Statement'!AP15+'Income Statement'!AP14) -> 23.850162 | AW21: =('Company Profile'!$G$18+('Balance Sheet'!AQ47+'Balance Sheet'!AQ58)-'Balance Sheet'!AQ27)/('Income Statement'!AQ18+'Income Statement'!AQ15+'Income Statement'!AQ14) -> 24.515474 | AX21: =('Company Profile'!$G$18+('Balance Sheet'!AR47+'Balance Sheet'!AR58)-'Balance Sheet'!AR27)/('Income Statement'!AR18+'Income Statement'!AR15+'Income Statement'!AR14) -> 23.690969 | AY21: =('Company Profile'!$G$18+('Balance Sheet'!AS47+'Balance Sheet'!AS58)-'Balance Sheet'!AS27)/('Income Statement'!AS18+'Income Statement'!AS15+'Income Statement'!AS14) -> 18.126549 | AZ21: =('Company Profile'!$G$18+('Balance Sheet'!AT47+'Balance Sheet'!AT58)-'Balance Sheet'!AT27)/('Income Statement'!AT18+'Income Statement'!AT15+'Income Statement'!AT14) -> 12.683203
B22: PEG ratio | C22: =C19/C26 -> -300.85666 | D22: =D19/D26 -> -491.86067 | E22: =E19/E26 -> -1087.6959 | F22: =F19/F26 -> 53.441493 | G22: =G19/G26 -> 60.929993 | H22: =H19/H26 -> 621.72786 | K22: PEG ratio | L22: =L19/L26 -> 1312.0581 | M22: =M19/M26 -> 50.901184 | N22: =N19/N26 -> 15.970857 | O22: =O19/O26 -> 68.026181 | P22: =P19/P26 -> 455.24678 | Q22: =Q19/Q26 -> 212.57282 | T22: PEG ratio | U22: =U19/U26 -> -21.597032 | V22: =V19/V26 -> -1444.5137 | W22: =W19/W26 -> 167.77577 | X22: =X19/X26 -> 45.397731 | Y22: =Y19/Y26 -> 0.43903182 | Z22: =Z19/Z26 -> -46.693026 | AC22: PEG ratio | AD22: =AD19/AD27 -> -3909.7709 | AE22: =AE19/AE27 -> -5739.6079 | AF22: =AF19/AF27 -> 800.78294 | AG22: =AG19/AG27 -> 165.13455 | AH22: =AH19/AH27 -> 365.16566 | AL22: PEG ratio | AM22: =AM19/AM26 -> -429.74705 | AN22: =AN19/AN26 -> 754.06161 | AO22: =AO19/AO26 -> -343.01661 | AP22: =AP19/AP26 -> 211.93124 | AQ22: =AQ19/AQ26 -> 500.70415 | AR22: =AR19/AR26 -> -432.20858 | AU22: PEG ratio | AV22: =AV19/AV26 -> -181.88689 | AW22: =AW19/AW26 -> 324.76149 | AX22: =AX19/AX26 -> -370.6389 | AY22: =AY19/AY26 -> 156.92182 | AZ22: =AZ19/AZ26 -> 44.330243
A23: Cash Flow | B23: Operating cash flow | C23: ='Cash Flow Statement'!B35/'Balance Sheet'!B56 -> 0.30921507 | D23: ='Cash Flow Statement'!C35/'Balance Sheet'!C56 -> 0.54937502 | E23: ='Cash Flow Statement'!D35/'Balance Sheet'!D56 -> 0.10811525 | F23: ='Cash Flow Statement'!E35/'Balance Sheet'!E56 -> 0.46010156 | G23: ='Cash Flow Statement'!F35/'Balance Sheet'!F56 -> 0.66148539 | H23: ='Cash Flow Statement'!G35/'Balance Sheet'!G56 -> 0.52440243 | J23: Cash flow | K23: Operating cash flow | L23: ='Cash Flow Statement'!J25/'Balance Sheet'!J61 -> -0.02697543 | M23: ='Cash Flow Statement'!K25/'Balance Sheet'!K61 -> 0.34810921 | N23: ='Cash Flow Statement'!L25/'Balance Sheet'!L61 -> 0.16428894 | O23: ='Cash Flow Statement'!M25/'Balance Sheet'!M61 -> -0.10022781 | P23: ='Cash Flow Statement'!N25/'Balance Sheet'!N61 -> -0.074523814 | Q23: ='Cash Flow Statement'!O25/'Balance Sheet'!O61 -> 0.035160976 | T23: Operating cash flow | U23: =('Cash Flow Statement'!R41/'Balance Sheet'!R65) -> 0.18962031 | V23: =('Cash Flow Statement'!S41/'Balance Sheet'!S65) -> 0.18383937 | W23: =('Cash Flow Statement'!T41/'Balance Sheet'!T65) -> 0.094787388 | X23: =('Cash Flow Statement'!U41/'Balance Sheet'!U65) -> 0.22826949 | Y23: =('Cash Flow Statement'!V41/'Balance Sheet'!V65) -> 0.39117938 | Z23: =('Cash Flow Statement'!W41/'Balance Sheet'!W65) -> 0.37857263 | AC23: Operating cash flow | AD23: ='Cash Flow Statement'!Z28/'Balance Sheet'!Z61 -> 0.037248984 | AE23: ='Cash Flow Statement'!AA28/'Balance Sheet'!AA61 -> 0.1055386 | AF23: ='Cash Flow Statement'!AB28/'Balance Sheet'!AB61 -> -0.11263294 | AG23: ='Cash Flow Statement'!AC28/'Balance Sheet'!AC61 -> -0.22919396 | AH23: ='Cash Flow Statement'!AD28/'Balance Sheet'!AD61 -> -0.059429619 | AL23: Operating cash flow | AM23: ='Cash Flow Statement'!AH23/'Balance Sheet'!AH72 -> 0.49797481 | AN23: ='Cash Flow Statement'!AI23/'Balance Sheet'!AI72 -> 0.47101342 | AO23: ='Cash Flow Statement'!AJ23/'Balance Sheet'!AJ72 -> 0.27112966 | AP23: ='Cash Flow Statement'!AK23/'Balance Sheet'!AK72 -> 0.25401486 | AQ23: ='Cash Flow Statement'!AL23/'Balance Sheet'!AL72 -> 0.34471485 | AR23: ='Cash Flow Statement'!AM23/'Balance Sheet'!AM72 -> 0.21646597 | AT23: Cash Flow | AU23: Operating cash flow | AV23: ='Cash Flow Statement'!AP26/'Balance Sheet'!AP67 -> 0.32456517 | AW23: ='Cash Flow Statement'!AQ26/'Balance Sheet'!AQ67 -> 0.2489024 | AX23: ='Cash Flow Statement'!AR26/'Balance Sheet'!AR67 -> 0.11050782 | AY23: ='Cash Flow Statement'!AS26/'Balance Sheet'!AS67 -> 0.16873823 | AZ23: ='Cash Flow Statement'!AT26/'Balance Sheet'!AT67 -> 0.18143642
B24: CapEx to Operating CF | C24: =(-'Cash Flow Statement'!B37-'Cash Flow Statement'!B38)/'Cash Flow Statement'!B35 -> 0.98317982 | D24: =(-'Cash Flow Statement'!C37-'Cash Flow Statement'!C38)/'Cash Flow Statement'!C35 -> 0.26764301 | E24: =(-'Cash Flow Statement'!D37-'Cash Flow Statement'!D38)/'Cash Flow Statement'!D35 -> 1.8795599 | F24: =(-'Cash Flow Statement'!E37-'Cash Flow Statement'!E38)/'Cash Flow Statement'!E35 -> 0.68609075 | G24: =(-'Cash Flow Statement'!F37-'Cash Flow Statement'!F38)/'Cash Flow Statement'!F35 -> 0.462036 | H24: =(-'Cash Flow Statement'!G37-'Cash Flow Statement'!G38)/'Cash Flow Statement'!G35 -> 0.62324084 | K24: CapEx to Operating CF | L24: =-'Cash Flow Statement'!J27/'Cash Flow Statement'!J25 -> -4.7332542 | M24: =-'Cash Flow Statement'!K27/'Cash Flow Statement'!K25 -> 0.3344434 | N24: =-'Cash Flow Statement'!L27/'Cash Flow Statement'!L25 -> 0.65312434 | O24: =-'Cash Flow Statement'!M27/'Cash Flow Statement'!M25 -> -0.89122875 | P24: =-'Cash Flow Statement'!N27/'Cash Flow Statement'!N25 -> -1.7666214 | Q24: =-'Cash Flow Statement'!O27/'Cash Flow Statement'!O25 -> 3.2722203 | T24: CapEx to Operating CF | U24: =(-'Cash Flow Statement'!R43/'Cash Flow Statement'!R41) -> 0.53764887 | V24: =(-'Cash Flow Statement'!S43/'Cash Flow Statement'!S41) -> 0.40604976 | W24: =(-'Cash Flow Statement'!T43/'Cash Flow Statement'!T41) -> 0.63288578 | X24: =(-'Cash Flow Statement'!U43/'Cash Flow Statement'!U41) -> 0.23998609 | Y24: =(-'Cash Flow Statement'!V43/'Cash Flow Statement'!V41) -> 0.19104763 | Z24: =(-'Cash Flow Statement'!W43/'Cash Flow Statement'!W41) -> 0.24070552 | AC24: CapEx to Operating CF | AD24: {=(-'Cash Flow Statement'!Z30:Z31/'Cash Flow Statement'!Z28)} -> 2.7343545 | AE24: {=(-'Cash Flow Statement'!AA30:AA31/'Cash Flow Statement'!AA28)} -> 0.80603497 | AF24: {=(-'Cash Flow Statement'!AB30:AB31/'Cash Flow Statement'!AB28)} -> -0.63099938 | AG24: {=(-'Cash Flow Statement'!AC30:AC31/'Cash Flow Statement'!AC28)} -> -0.3043877 | AH24: {=(-'Cash Flow Statement'!AD30:AD31/'Cash Flow Statement'!AD28)} -> -0.9141833 | AL24: CapEx to Operating CF | AM24: =(-'Cash Flow Statement'!AH25/'Cash Flow Statement'!AH23) -> 0.37555197 | AN24: =(-'Cash Flow Statement'!AI25/'Cash Flow Statement'!AI23) -> 0.22164878 | AO24: =(-'Cash Flow Statement'!AJ25/'Cash Flow Statement'!AJ23) -> 0.87158377 | AP24: =(-'Cash Flow Statement'!AK25/'Cash Flow Statement'!AK23) -> 1.2962746 | AQ24: =(-'Cash Flow Statement'!AL25/'Cash Flow Statement'!AL23) -> 1.2236652 | AR24: =(-'Cash Flow Statement'!AM25/'Cash Flow Statement'!AM23) -> 1.5309294 | AU24: CapEx to Operating CF | AV24: =(-'Cash Flow Statement'!AP28/'Cash Flow Statement'!AP26) -> 0.35801322 | AW24: =(-'Cash Flow Statement'!AQ28/'Cash Flow Statement'!AQ26) -> 0.38999861 | AX24: =(-'Cash Flow Statement'!AR28/'Cash Flow Statement'!AR26) -> 1.0184351 | AY24: =(-'Cash Flow Statement'!AS28/'Cash Flow Statement'!AS26) -> 0.47838635 | AZ24: =(-'Cash Flow Statement'!AT28/'Cash Flow Statement'!AT26) -> 0.54499577
B25: FCF Margin | C25: =('Cash Flow Statement'!B35-(-'Cash Flow Statement'!B37-'Cash Flow Statement'!B38))/'Income Statement'!B4 -> 0.00077716098 | D25: =('Cash Flow Statement'!C35-(-'Cash Flow Statement'!C37-'Cash Flow Statement'!C38))/'Income Statement'!C4 -> 0.092165918 | E25: =('Cash Flow Statement'!D35-(-'Cash Flow Statement'!D37-'Cash Flow Statement'!D38))/'Income Statement'!D4 -> -0.01832711 | F25: =('Cash Flow Statement'!E35-(-'Cash Flow Statement'!E37-'Cash Flow Statement'!E38))/'Income Statement'!E4 -> 0.024700756 | G25: =('Cash Flow Statement'!F35-(-'Cash Flow Statement'!F37-'Cash Flow Statement'!F38))/'Income Statement'!F4 -> 0.060467119 | H25: =('Cash Flow Statement'!G35-(-'Cash Flow Statement'!G37-'Cash Flow Statement'!G38))/'Income Statement'!G4 -> 0.036380062 | K25: FCF Margin | L25: =('Cash Flow Statement'!J25-(-'Cash Flow Statement'!J27))/'Income Statement'!J4 -> -0.11080839 | M25: =('Cash Flow Statement'!K25-(-'Cash Flow Statement'!K27))/'Income Statement'!K4 -> 0.16046979 | N25: =('Cash Flow Statement'!L25-(-'Cash Flow Statement'!L27))/'Income Statement'!L4 -> 0.035574246 | O25: =('Cash Flow Statement'!M25-(-'Cash Flow Statement'!M27))/'Income Statement'!M4 -> -0.11032201 | P25: =('Cash Flow Statement'!N25-(-'Cash Flow Statement'!N27))/'Income Statement'!N4 -> -0.11264115 | Q25: =('Cash Flow Statement'!O25-(-'Cash Flow Statement'!O27))/'Income Statement'!O4 -> -0.045456072 | T25: FCF Margin | U25: =('Cash Flow Statement'!R41-(-'Cash Flow Statement'!R43))/'Income Statement'!R4 -> 0.047618092 | V25: =('Cash Flow Statement'!S41-(-'Cash Flow Statement'!S43))/'Income Statement'!S4 -> 0.069744134 | W25: =('Cash Flow Statement'!T41-(-'Cash Flow Statement'!T43))/'Income Statement'!T4 -> 0.019050723 | X25: =('Cash Flow Statement'!U41-(-'Cash Flow Statement'!U43))/'Income Statement'!U4 -> 0.078440867 | Y25: =('Cash Flow Statement'!V41-(-'Cash Flow Statement'!V43))/'Income Statement'!V4 -> 0.12740833 | Z25: =('Cash Flow Statement'!W41-(-'Cash Flow Statement'!W43))/'Income Statement'!W4 -> 0.10968566 | AD25: 0 | AE25: 0 | AF25: 0 | AG25: 0 | AH25: 0 | AL25: FCF Margin | AM25: =('Cash Flow Statement'!AH23-(-'Cash Flow Statement'!AH25))/'Income Statement'!AH4 -> 0.069870728 | AN25: =('Cash Flow Statement'!AI23-(-'Cash Flow Statement'!AI25))/'Income Statement'!AI4 -> 0.11515478 | AO25: =('Cash Flow Statement'!AJ23-(-'Cash Flow Statement'!AJ25))/'Income Statement'!AJ4 -> 0.0076713044 | AP25: =('Cash Flow Statement'!AK23-(-'Cash Flow Statement'!AK25))/'Income Statement'!AK4 -> -0.015095343 | AQ25: =('Cash Flow Statement'!AL23-(-'Cash Flow Statement'!AL25))/'Income Statement'!AL4 -> -0.020448153 | AR25: =('Cash Flow Statement'!AM23-(-'Cash Flow Statement'!AM25))/'Income Statement'!AM4 -> -0.039205585 | AU25: FCF Margin | AV25: =('Cash Flow Statement'!AP26-(-'Cash Flow Statement'!AP28))/'Income Statement'!AP4 -> 0.067651211 | AW25: =('Cash Flow Statement'!AQ26-(-'Cash Flow Statement'!AQ28))/'Income Statement'!AQ4 -> 0.054104121 | AX25: =('Cash Flow Statement'!AR26-(-'Cash Flow Statement'!AR28))/'Income Statement'!AR4 -> -0.00072135972 | AY25: =('Cash Flow Statement'!AS26-(-'Cash Flow Statement'!AS28))/'Income Statement'!AS4 -> 0.031100273 | AZ25: =('Cash Flow Statement'!AT26-(-'Cash Flow Statement'!AT28))/'Income Statement'!AT4 -> 0.035224188
B26: EPS Growth rate | C26: =(C18-253.21)/253.21 -> -0.28682221 | D26: =(D18-C18)/C18 -> -0.22694448 | E26: =(E18-D18)/D18 -> -0.11610581 | F26: =(F18-E18)/E18 -> 1.1165099 | G26: =(G18-F18)/F18 -> 0.60873219 | H26: =(H18-G18)/G18 -> 0.056467792 | K26: EPS Growth rate | L26: =(L18-60.85)/60.85 -> -1.0439589 | M26: =(M18-L18)/ABS(L18) -> 5.7114953 | N26: =(N18-M18)/ABS(M18) -> 3.7957273 | O26: =(O18-N18)/ABS(N18) -> 0.5682427 | P26: =(P18-O18)/ABS(O18) -> 0.078714807 | Q26: =(Q18-P18)/ABS(P18) -> 0.14697445 | T26: EPS Growth | U26: =(U18-(-84.89))/ABS(-84.89) -> 0.66154145 | V26: =(V18-U18)/ABS(U18) -> 0.0099905671 | W26: =(W18-V18)/ABS(V18) -> -0.079669438 | X26: =(X18-W18)/ABS(W18) -> 1.2378572 | Y26: =(Y18-X18)/(X18) -> 10.824735 | Z26: =(Z18-Y18)/ABS(Y18) -> -0.11500613 | AC26: FCF Margin | AD26: =('Cash Flow Statement'!Z28-(-'Cash Flow Statement'!Z31))/'Income Statement'!Z4 -> 0.019811335 | AE26: =('Cash Flow Statement'!AA28-(-'Cash Flow Statement'!AA31))/'Income Statement'!AA4 -> 0.059281225 | AF26: =('Cash Flow Statement'!AB28-(-'Cash Flow Statement'!AB31))/'Income Statement'!AB4 -> -0.06405831 | AG26: =('Cash Flow Statement'!AC28-(-'Cash Flow Statement'!AC31))/'Income Statement'!AC4 -> -0.13776229 | AH26: =('Cash Flow Statement'!AD28-(-'Cash Flow Statement'!AD31))/'Income Statement'!AD4 -> -0.032000979 | AL26: EPS Growth | AM26: =(AM18-9.95)/9.95 -> -0.098456991 | AN26: =(AN18-AM18)/AM18 -> 0.053273528 | AO26: =(AO18-AN18)/AN18 -> -0.13546258 | AP26: =(AP18-AO18)/AO18 -> 0.18501822 | AQ26: =(AQ18-AP18)/AP18 -> 0.07298516 | AR26: =(AR18-AQ18)/AQ18 -> -0.093246641 | AT26: EPS Growth rate | AV26: =(AV18-2.27)/2.27 -> -0.45969249 | AW26: =(AW18-AV18)/AV18 -> 0.21235998 | AX26: =(AX18-AW18)/AW18 -> -0.24716452 | AY26: =(AY18-AX18)/AX18 -> 0.41311892 | AZ26: =(AZ18-AY18)/AY18 -> 0.8085769
A27: Leverage | B27: Debt/CE | C27: =('Balance Sheet'!B39+'Balance Sheet'!B47)/('Balance Sheet'!B28-'Balance Sheet'!B56) -> 0.002134845 | D27: =('Balance Sheet'!C39+'Balance Sheet'!C47)/('Balance Sheet'!C28-'Balance Sheet'!C56) -> 0.0089118998 | E27: =('Balance Sheet'!D39+'Balance Sheet'!D47)/('Balance Sheet'!D28-'Balance Sheet'!D56) -> 0.0066265269 | F27: =('Balance Sheet'!E39+'Balance Sheet'!E47)/('Balance Sheet'!E28-'Balance Sheet'!E56) -> 0.018852652 | G27: =('Balance Sheet'!F39+'Balance Sheet'!F47)/('Balance Sheet'!F28-'Balance Sheet'!F56) -> 0.00037890886 | H27: =('Balance Sheet'!G39+'Balance Sheet'!G47)/('Balance Sheet'!G28-'Balance Sheet'!G56) -> 0 | J27: Leverage | K27: D/CE | L27: =('Balance Sheet'!J43+'Balance Sheet'!J52)/('Balance Sheet'!J32-'Balance Sheet'!J61) -> 0.55324922 | M27: =('Balance Sheet'!K43+'Balance Sheet'!K52)/('Balance Sheet'!K32-'Balance Sheet'!K61) -> 0.51777928 | N27: =('Balance Sheet'!L43+'Balance Sheet'!L52)/('Balance Sheet'!L32-'Balance Sheet'!L61) -> 0.63371539 | O27: =('Balance Sheet'!M43+'Balance Sheet'!M52)/('Balance Sheet'!M32-'Balance Sheet'!M61) -> 0.65601553 | P27: =('Balance Sheet'!N43+'Balance Sheet'!N52)/('Balance Sheet'!N32-'Balance Sheet'!N61) -> 0.64199047 | Q27: =('Balance Sheet'!O43+'Balance Sheet'!O52)/('Balance Sheet'!O32-'Balance Sheet'!O61) -> 0.64706928 | S27: Leverage | T27: D/CE | U27: =('Balance Sheet'!R46+'Balance Sheet'!R55)/('Balance Sheet'!R35-'Balance Sheet'!R65) -> 0.54868699 | V27: =('Balance Sheet'!S46+'Balance Sheet'!S55)/('Balance Sheet'!S35-'Balance Sheet'!S65) -> 0.61914798 | W27: =('Balance Sheet'!T46+'Balance Sheet'!T55)/('Balance Sheet'!T35-'Balance Sheet'!T65) -> 0.77625473 | X27: =('Balance Sheet'!U46+'Balance Sheet'!U55)/('Balance Sheet'!U35-'Balance Sheet'!U65) -> 0.69404948 | Y27: =('Balance Sheet'!V46+'Balance Sheet'!V55)/('Balance Sheet'!V35-'Balance Sheet'!V65) -> 0.49988328 | Z27: =('Balance Sheet'!W46+'Balance Sheet'!W55)/('Balance Sheet'!W35-'Balance Sheet'!W65) -> 0.29486502 | AC27: EPS Growth | AD27: =(AD18-14.11)/14.11 -> -0.06788556 | AE27: =(AE18-AD18)/AD18 -> -0.048605552 | AF27: =(AF18-AE18)/AE18 -> 0.2735503 | AG27: =(AG18-AF18)/AF18 -> 0.75559578 | AH27: =(AH18-AG18)/AG18 -> 0.26921659 | AK27: Leverage | AL27: D/CE | AM27: =('Balance Sheet'!AH45+'Balance Sheet'!AH61)/('Balance Sheet'!AH34-'Balance Sheet'!AH72) -> 0.0031909392 | AN27: =('Balance Sheet'!AI45+'Balance Sheet'!AI61)/('Balance Sheet'!AI34-'Balance Sheet'!AI72) -> 0.0055375739 | AO27: =('Balance Sheet'!AJ45+'Balance Sheet'!AJ61)/('Balance Sheet'!AJ34-'Balance Sheet'!AJ72) -> 0.018861835 | AP27: =('Balance Sheet'!AK45+'Balance Sheet'!AK61)/('Balance Sheet'!AK34-'Balance Sheet'!AK72) -> 0.023790607 | AQ27: =('Balance Sheet'!AL45+'Balance Sheet'!AL61)/('Balance Sheet'!AL34-'Balance Sheet'!AL72) -> 0.050863859 | AR27: =('Balance Sheet'!AM45+'Balance Sheet'!AM61)/('Balance Sheet'!AM34-'Balance Sheet'!AM72) -> 0.10061769 | AT27: Leverage | AU27: D/CE | AV27: =('Balance Sheet'!AP47+'Balance Sheet'!AP58)/('Balance Sheet'!AP34-'Balance Sheet'!AP67) -> 0.45010993 | AW27: =('Balance Sheet'!AQ47+'Balance Sheet'!AQ58)/('Balance Sheet'!AQ34-'Balance Sheet'!AQ67) -> 0.31759545 | AX27: =('Balance Sheet'!AR47+'Balance Sheet'!AR58)/('Balance Sheet'!AR34-'Balance Sheet'!AR67) -> 0.37548845 | AY27: =('Balance Sheet'!AS47+'Balance Sheet'!AS58)/('Balance Sheet'!AS34-'Balance Sheet'!AS67) -> 0.35431016 | AZ27: =('Balance Sheet'!AT47+'Balance Sheet'!AT58)/('Balance Sheet'!AT34-'Balance Sheet'!AT67) -> 0.40071083
B28: Debt/EBITDA | AB28: Leverage | AC28: D/CE | AD28: =('Balance Sheet'!Z44+'Balance Sheet'!Z52)/('Balance Sheet'!Z33-'Balance Sheet'!Z61) -> 0.96446701 | AE28: =('Balance Sheet'!AA44+'Balance Sheet'!AA52)/('Balance Sheet'!AA33-'Balance Sheet'!AA61) -> 0.8435156 | AF28: =('Balance Sheet'!AB44+'Balance Sheet'!AB52)/('Balance Sheet'!AB33-'Balance Sheet'!AB61) -> 1.1571167 | AG28: =('Balance Sheet'!AC44+'Balance Sheet'!AC52)/('Balance Sheet'!AC33-'Balance Sheet'!AC61) -> 1.35044 | AH28: =('Balance Sheet'!AD44+'Balance Sheet'!AD52)/('Balance Sheet'!AD33-'Balance Sheet'!AD61) -> 1.1960231
B29: Market Price | C29: =6837 -> 6837 | D29: =6885 -> 6885 | E29: 7566 | F29: 8405 | G29: =12512.65 -> 12512.65 | H29: 11476 | K29: Market Price | L29: 610 | M29: 801.5 | N29: 811 | O29: =1161.3 -> 1161.3 | P29: =1938 -> 1938 | Q29: =2652.8 -> 2652.8 | T29: Market Price | U29: =143.4 -> 143.4 | V29: 306.75 | W29: 434 | X29: 423 | Y29: =1000 -> 1000 | Z29: 670.55 | AL29: Market Price | AM29: 164 | AN29: 184.9 | AO29: 152 | AP29: 179 | AQ29: 305 | AR29: =359 -> 359 | AU29: Market Price | AV29: 30.15 | AW29: 55.46 | AX29: 62.2 | AY29: 45.23 | AZ29: =78.1 -> 78.1
